.bytecode 50.0
.class synchronized com/nd/android/u/ui/widge/ChatListItemView_Erp$1
.super java/lang/Object
.implements android/view/View$OnClickListener
.enclosing method com/nd/android/u/ui/widge/ChatListItemView_Erp
.inner class inner com/nd/android/u/ui/widge/ChatListItemView_Erp$1

.field final synthetic 'this$0' Lcom/nd/android/u/ui/widge/ChatListItemView_Erp;

.method <init>(Lcom/nd/android/u/ui/widge/ChatListItemView_Erp;)V
aload 0
aload 1
putfield com/nd/android/u/ui/widge/ChatListItemView_Erp$1/this$0 Lcom/nd/android/u/ui/widge/ChatListItemView_Erp;
aload 0
invokespecial java/lang/Object/<init>()V
return
.limit locals 2
.limit stack 2
.end method

.method public onClick(Landroid/view/View;)V
aload 1
invokevirtual android/view/View/getId()I
istore 2
iload 2
getstatic com/nd/android/u/chat/R$id/tvConfirm I
if_icmpne L0
aload 0
getfield com/nd/android/u/ui/widge/ChatListItemView_Erp$1/this$0 Lcom/nd/android/u/ui/widge/ChatListItemView_Erp;
invokestatic com/nd/android/u/ui/widge/ChatListItemView_Erp/access$000(Lcom/nd/android/u/ui/widge/ChatListItemView_Erp;)Lcom/nd/android/u/bean4xy/DisplayMessage_Person;
getfield com/nd/android/u/bean4xy/DisplayMessage_Person/erpInfo Lcom/product/android/commonInterface/chat/ErpInfo;
getfield com/product/android/commonInterface/chat/ErpInfo/type I
iconst_1
if_icmpne L1
aload 0
getfield com/nd/android/u/ui/widge/ChatListItemView_Erp$1/this$0 Lcom/nd/android/u/ui/widge/ChatListItemView_Erp;
invokestatic com/nd/android/u/ui/widge/ChatListItemView_Erp/access$000(Lcom/nd/android/u/ui/widge/ChatListItemView_Erp;)Lcom/nd/android/u/bean4xy/DisplayMessage_Person;
getfield com/nd/android/u/bean4xy/DisplayMessage_Person/erpInfo Lcom/product/android/commonInterface/chat/ErpInfo;
getfield com/product/android/commonInterface/chat/ErpInfo/status I
ifne L2
aload 0
getfield com/nd/android/u/ui/widge/ChatListItemView_Erp$1/this$0 Lcom/nd/android/u/ui/widge/ChatListItemView_Erp;
invokestatic com/nd/android/u/ui/widge/ChatListItemView_Erp/access$000(Lcom/nd/android/u/ui/widge/ChatListItemView_Erp;)Lcom/nd/android/u/bean4xy/DisplayMessage_Person;
getfield com/nd/android/u/bean4xy/DisplayMessage_Person/erpInfo Lcom/product/android/commonInterface/chat/ErpInfo;
iconst_0
putfield com/product/android/commonInterface/chat/ErpInfo/clickable Z
getstatic com/nd/android/u/ChatEntry/INSTANCE Lcom/nd/android/u/ChatEntry;
getfield com/nd/android/u/ChatEntry/chatCallOtherModel_UI Lcom/nd/android/u/ui/chatInterfaceImpl/IChatCallOtherModel_UI;
aload 0
getfield com/nd/android/u/ui/widge/ChatListItemView_Erp$1/this$0 Lcom/nd/android/u/ui/widge/ChatListItemView_Erp;
invokestatic com/nd/android/u/ui/widge/ChatListItemView_Erp/access$100(Lcom/nd/android/u/ui/widge/ChatListItemView_Erp;)Landroid/content/Context;
aload 0
getfield com/nd/android/u/ui/widge/ChatListItemView_Erp$1/this$0 Lcom/nd/android/u/ui/widge/ChatListItemView_Erp;
invokestatic com/nd/android/u/ui/widge/ChatListItemView_Erp/access$000(Lcom/nd/android/u/ui/widge/ChatListItemView_Erp;)Lcom/nd/android/u/bean4xy/DisplayMessage_Person;
getfield com/nd/android/u/bean4xy/DisplayMessage_Person/erpInfo Lcom/product/android/commonInterface/chat/ErpInfo;
invokeinterface com/nd/android/u/ui/chatInterfaceImpl/IChatCallOtherModel_UI/acceptTask(Landroid/content/Context;Lcom/product/android/commonInterface/chat/ErpInfo;)V 2
aload 0
getfield com/nd/android/u/ui/widge/ChatListItemView_Erp$1/this$0 Lcom/nd/android/u/ui/widge/ChatListItemView_Erp;
invokestatic com/nd/android/u/ui/widge/ChatListItemView_Erp/access$200(Lcom/nd/android/u/ui/widge/ChatListItemView_Erp;)Landroid/widget/TextView;
ldc_w -7829368
invokevirtual android/widget/TextView/setTextColor(I)V
aload 0
getfield com/nd/android/u/ui/widge/ChatListItemView_Erp$1/this$0 Lcom/nd/android/u/ui/widge/ChatListItemView_Erp;
invokestatic com/nd/android/u/ui/widge/ChatListItemView_Erp/access$200(Lcom/nd/android/u/ui/widge/ChatListItemView_Erp;)Landroid/widget/TextView;
iconst_0
invokevirtual android/widget/TextView/setEnabled(Z)V
L2:
return
L1:
aload 0
getfield com/nd/android/u/ui/widge/ChatListItemView_Erp$1/this$0 Lcom/nd/android/u/ui/widge/ChatListItemView_Erp;
invokestatic com/nd/android/u/ui/widge/ChatListItemView_Erp/access$000(Lcom/nd/android/u/ui/widge/ChatListItemView_Erp;)Lcom/nd/android/u/bean4xy/DisplayMessage_Person;
getfield com/nd/android/u/bean4xy/DisplayMessage_Person/erpInfo Lcom/product/android/commonInterface/chat/ErpInfo;
getfield com/product/android/commonInterface/chat/ErpInfo/status I
ifne L3
aload 0
getfield com/nd/android/u/ui/widge/ChatListItemView_Erp$1/this$0 Lcom/nd/android/u/ui/widge/ChatListItemView_Erp;
invokestatic com/nd/android/u/ui/widge/ChatListItemView_Erp/access$000(Lcom/nd/android/u/ui/widge/ChatListItemView_Erp;)Lcom/nd/android/u/bean4xy/DisplayMessage_Person;
getfield com/nd/android/u/bean4xy/DisplayMessage_Person/erpInfo Lcom/product/android/commonInterface/chat/ErpInfo;
iconst_0
putfield com/product/android/commonInterface/chat/ErpInfo/clickable Z
getstatic com/nd/android/u/ChatEntry/INSTANCE Lcom/nd/android/u/ChatEntry;
getfield com/nd/android/u/ChatEntry/chatCallOtherModel_UI Lcom/nd/android/u/ui/chatInterfaceImpl/IChatCallOtherModel_UI;
aload 0
getfield com/nd/android/u/ui/widge/ChatListItemView_Erp$1/this$0 Lcom/nd/android/u/ui/widge/ChatListItemView_Erp;
invokestatic com/nd/android/u/ui/widge/ChatListItemView_Erp/access$100(Lcom/nd/android/u/ui/widge/ChatListItemView_Erp;)Landroid/content/Context;
aload 0
getfield com/nd/android/u/ui/widge/ChatListItemView_Erp$1/this$0 Lcom/nd/android/u/ui/widge/ChatListItemView_Erp;
invokestatic com/nd/android/u/ui/widge/ChatListItemView_Erp/access$000(Lcom/nd/android/u/ui/widge/ChatListItemView_Erp;)Lcom/nd/android/u/bean4xy/DisplayMessage_Person;
getfield com/nd/android/u/bean4xy/DisplayMessage_Person/erpInfo Lcom/product/android/commonInterface/chat/ErpInfo;
invokeinterface com/nd/android/u/ui/chatInterfaceImpl/IChatCallOtherModel_UI/finishTask(Landroid/content/Context;Lcom/product/android/commonInterface/chat/ErpInfo;)V 2
aload 0
getfield com/nd/android/u/ui/widge/ChatListItemView_Erp$1/this$0 Lcom/nd/android/u/ui/widge/ChatListItemView_Erp;
invokestatic com/nd/android/u/ui/widge/ChatListItemView_Erp/access$200(Lcom/nd/android/u/ui/widge/ChatListItemView_Erp;)Landroid/widget/TextView;
ldc_w -7829368
invokevirtual android/widget/TextView/setTextColor(I)V
aload 0
getfield com/nd/android/u/ui/widge/ChatListItemView_Erp$1/this$0 Lcom/nd/android/u/ui/widge/ChatListItemView_Erp;
invokestatic com/nd/android/u/ui/widge/ChatListItemView_Erp/access$200(Lcom/nd/android/u/ui/widge/ChatListItemView_Erp;)Landroid/widget/TextView;
iconst_0
invokevirtual android/widget/TextView/setEnabled(Z)V
getstatic com/nd/android/u/chat/R$string/chat_finishing I
invokestatic com/common/android/utils/ToastUtils/display(I)V
return
L3:
aload 0
getfield com/nd/android/u/ui/widge/ChatListItemView_Erp$1/this$0 Lcom/nd/android/u/ui/widge/ChatListItemView_Erp;
invokestatic com/nd/android/u/ui/widge/ChatListItemView_Erp/access$000(Lcom/nd/android/u/ui/widge/ChatListItemView_Erp;)Lcom/nd/android/u/bean4xy/DisplayMessage_Person;
getfield com/nd/android/u/bean4xy/DisplayMessage_Person/erpInfo Lcom/product/android/commonInterface/chat/ErpInfo;
getfield com/product/android/commonInterface/chat/ErpInfo/status I
iconst_4
if_icmpne L2
aload 0
getfield com/nd/android/u/ui/widge/ChatListItemView_Erp$1/this$0 Lcom/nd/android/u/ui/widge/ChatListItemView_Erp;
invokestatic com/nd/android/u/ui/widge/ChatListItemView_Erp/access$000(Lcom/nd/android/u/ui/widge/ChatListItemView_Erp;)Lcom/nd/android/u/bean4xy/DisplayMessage_Person;
getfield com/nd/android/u/bean4xy/DisplayMessage_Person/erpInfo Lcom/product/android/commonInterface/chat/ErpInfo;
iconst_0
putfield com/product/android/commonInterface/chat/ErpInfo/clickable Z
getstatic com/nd/android/u/ChatEntry/INSTANCE Lcom/nd/android/u/ChatEntry;
getfield com/nd/android/u/ChatEntry/chatCallOtherModel_UI Lcom/nd/android/u/ui/chatInterfaceImpl/IChatCallOtherModel_UI;
aload 0
getfield com/nd/android/u/ui/widge/ChatListItemView_Erp$1/this$0 Lcom/nd/android/u/ui/widge/ChatListItemView_Erp;
invokestatic com/nd/android/u/ui/widge/ChatListItemView_Erp/access$100(Lcom/nd/android/u/ui/widge/ChatListItemView_Erp;)Landroid/content/Context;
aload 0
getfield com/nd/android/u/ui/widge/ChatListItemView_Erp$1/this$0 Lcom/nd/android/u/ui/widge/ChatListItemView_Erp;
invokestatic com/nd/android/u/ui/widge/ChatListItemView_Erp/access$000(Lcom/nd/android/u/ui/widge/ChatListItemView_Erp;)Lcom/nd/android/u/bean4xy/DisplayMessage_Person;
getfield com/nd/android/u/bean4xy/DisplayMessage_Person/erpInfo Lcom/product/android/commonInterface/chat/ErpInfo;
invokeinterface com/nd/android/u/ui/chatInterfaceImpl/IChatCallOtherModel_UI/acceptDelay(Landroid/content/Context;Lcom/product/android/commonInterface/chat/ErpInfo;)V 2
aload 0
getfield com/nd/android/u/ui/widge/ChatListItemView_Erp$1/this$0 Lcom/nd/android/u/ui/widge/ChatListItemView_Erp;
invokestatic com/nd/android/u/ui/widge/ChatListItemView_Erp/access$200(Lcom/nd/android/u/ui/widge/ChatListItemView_Erp;)Landroid/widget/TextView;
ldc_w -7829368
invokevirtual android/widget/TextView/setTextColor(I)V
aload 0
getfield com/nd/android/u/ui/widge/ChatListItemView_Erp$1/this$0 Lcom/nd/android/u/ui/widge/ChatListItemView_Erp;
invokestatic com/nd/android/u/ui/widge/ChatListItemView_Erp/access$200(Lcom/nd/android/u/ui/widge/ChatListItemView_Erp;)Landroid/widget/TextView;
iconst_0
invokevirtual android/widget/TextView/setEnabled(Z)V
getstatic com/nd/android/u/chat/R$string/chat_delay_task_proccessing I
invokestatic com/common/android/utils/ToastUtils/display(I)V
return
L0:
iload 2
getstatic com/nd/android/u/chat/R$id/tvDetail I
if_icmpne L2
getstatic com/nd/android/u/ChatEntry/INSTANCE Lcom/nd/android/u/ChatEntry;
getfield com/nd/android/u/ChatEntry/chatCallOtherModel_UI Lcom/nd/android/u/ui/chatInterfaceImpl/IChatCallOtherModel_UI;
aload 0
getfield com/nd/android/u/ui/widge/ChatListItemView_Erp$1/this$0 Lcom/nd/android/u/ui/widge/ChatListItemView_Erp;
invokestatic com/nd/android/u/ui/widge/ChatListItemView_Erp/access$100(Lcom/nd/android/u/ui/widge/ChatListItemView_Erp;)Landroid/content/Context;
aload 0
getfield com/nd/android/u/ui/widge/ChatListItemView_Erp$1/this$0 Lcom/nd/android/u/ui/widge/ChatListItemView_Erp;
invokestatic com/nd/android/u/ui/widge/ChatListItemView_Erp/access$000(Lcom/nd/android/u/ui/widge/ChatListItemView_Erp;)Lcom/nd/android/u/bean4xy/DisplayMessage_Person;
getfield com/nd/android/u/bean4xy/DisplayMessage_Person/erpInfo Lcom/product/android/commonInterface/chat/ErpInfo;
invokeinterface com/nd/android/u/ui/chatInterfaceImpl/IChatCallOtherModel_UI/viewDetail(Landroid/content/Context;Lcom/product/android/commonInterface/chat/ErpInfo;)V 2
return
.limit locals 3
.limit stack 3
.end method
