.bytecode 50.0
.class synchronized com/android/u/weibo/weibo/ui/activity4xiaoyou/XYTweetProfileBaseActivity$1
.super android/content/BroadcastReceiver
.enclosing method com/android/u/weibo/weibo/ui/activity4xiaoyou/XYTweetProfileBaseActivity
.inner class inner com/android/u/weibo/weibo/ui/activity4xiaoyou/XYTweetProfileBaseActivity$1

.field final synthetic 'this$0' Lcom/android/u/weibo/weibo/ui/activity4xiaoyou/XYTweetProfileBaseActivity;

.method <init>(Lcom/android/u/weibo/weibo/ui/activity4xiaoyou/XYTweetProfileBaseActivity;)V
aload 0
aload 1
putfield com/android/u/weibo/weibo/ui/activity4xiaoyou/XYTweetProfileBaseActivity$1/this$0 Lcom/android/u/weibo/weibo/ui/activity4xiaoyou/XYTweetProfileBaseActivity;
aload 0
invokespecial android/content/BroadcastReceiver/<init>()V
return
.limit locals 2
.limit stack 2
.end method

.method public onReceive(Landroid/content/Context;Landroid/content/Intent;)V
aload 2
ldc "afterDelete2Refresh"
iconst_0
invokevirtual android/content/Intent/getBooleanExtra(Ljava/lang/String;Z)Z
ifeq L0
aload 2
ldc "deleteTweetId"
lconst_0
invokevirtual android/content/Intent/getLongExtra(Ljava/lang/String;J)J
lstore 4
aload 0
getfield com/android/u/weibo/weibo/ui/activity4xiaoyou/XYTweetProfileBaseActivity$1/this$0 Lcom/android/u/weibo/weibo/ui/activity4xiaoyou/XYTweetProfileBaseActivity;
getfield com/android/u/weibo/weibo/ui/activity4xiaoyou/XYTweetProfileBaseActivity/mAdapter Lcom/android/u/weibo/weibo/ui/adapter/TweetListAdapter;
invokevirtual com/android/u/weibo/weibo/ui/adapter/TweetListAdapter/getData()Lcom/android/u/weibo/weibo/business/bean/TopicInfoList;
astore 1
aload 1
ifnull L1
aload 1
invokevirtual com/android/u/weibo/weibo/business/bean/TopicInfoList/isEmpty()Z
ifeq L2
L1:
return
L2:
lload 4
lconst_0
lcmp
ifle L3
aload 1
lload 4
invokevirtual com/android/u/weibo/weibo/business/bean/TopicInfoList/removeItemByID(J)V
L4:
aload 0
getfield com/android/u/weibo/weibo/ui/activity4xiaoyou/XYTweetProfileBaseActivity$1/this$0 Lcom/android/u/weibo/weibo/ui/activity4xiaoyou/XYTweetProfileBaseActivity;
getfield com/android/u/weibo/weibo/ui/activity4xiaoyou/XYTweetProfileBaseActivity/mAdapter Lcom/android/u/weibo/weibo/ui/adapter/TweetListAdapter;
invokevirtual com/android/u/weibo/weibo/ui/adapter/TweetListAdapter/notifyDataSetChanged()V
L5:
aload 0
getfield com/android/u/weibo/weibo/ui/activity4xiaoyou/XYTweetProfileBaseActivity$1/this$0 Lcom/android/u/weibo/weibo/ui/activity4xiaoyou/XYTweetProfileBaseActivity;
getfield com/android/u/weibo/weibo/ui/activity4xiaoyou/XYTweetProfileBaseActivity/mAdapter Lcom/android/u/weibo/weibo/ui/adapter/TweetListAdapter;
invokevirtual com/android/u/weibo/weibo/ui/adapter/TweetListAdapter/getData()Lcom/android/u/weibo/weibo/business/bean/TopicInfoList;
ifnull L6
aload 0
getfield com/android/u/weibo/weibo/ui/activity4xiaoyou/XYTweetProfileBaseActivity$1/this$0 Lcom/android/u/weibo/weibo/ui/activity4xiaoyou/XYTweetProfileBaseActivity;
getfield com/android/u/weibo/weibo/ui/activity4xiaoyou/XYTweetProfileBaseActivity/mAdapter Lcom/android/u/weibo/weibo/ui/adapter/TweetListAdapter;
invokevirtual com/android/u/weibo/weibo/ui/adapter/TweetListAdapter/getData()Lcom/android/u/weibo/weibo/business/bean/TopicInfoList;
invokevirtual com/android/u/weibo/weibo/business/bean/TopicInfoList/isEmpty()Z
ifeq L7
L6:
aload 0
getfield com/android/u/weibo/weibo/ui/activity4xiaoyou/XYTweetProfileBaseActivity$1/this$0 Lcom/android/u/weibo/weibo/ui/activity4xiaoyou/XYTweetProfileBaseActivity;
iconst_1
invokevirtual com/android/u/weibo/weibo/ui/activity4xiaoyou/XYTweetProfileBaseActivity/showEmptyView(Z)V
return
L3:
aload 2
ldc "localCreateAt"
lconst_0
invokevirtual android/content/Intent/getLongExtra(Ljava/lang/String;J)J
lstore 4
lload 4
lconst_0
lcmp
ifle L8
iconst_0
istore 3
L9:
iload 3
aload 1
invokevirtual com/android/u/weibo/weibo/business/bean/TopicInfoList/size()I
if_icmpge L10
aload 1
iload 3
invokevirtual com/android/u/weibo/weibo/business/bean/TopicInfoList/get(I)Ljava/lang/Object;
checkcast com/android/u/weibo/weibo/business/bean/TopicInfo
astore 2
lconst_0
aload 2
getfield com/android/u/weibo/weibo/business/bean/TopicInfo/post_time J
lcmp
ifne L11
aload 2
getfield com/android/u/weibo/weibo/business/bean/TopicInfo/localCreateAt J
lload 4
lcmp
ifne L11
aload 1
iload 3
invokevirtual com/android/u/weibo/weibo/business/bean/TopicInfoList/remove(I)Ljava/lang/Object;
pop
aload 0
getfield com/android/u/weibo/weibo/ui/activity4xiaoyou/XYTweetProfileBaseActivity$1/this$0 Lcom/android/u/weibo/weibo/ui/activity4xiaoyou/XYTweetProfileBaseActivity;
getfield com/android/u/weibo/weibo/ui/activity4xiaoyou/XYTweetProfileBaseActivity/mAdapter Lcom/android/u/weibo/weibo/ui/adapter/TweetListAdapter;
aload 1
invokevirtual com/android/u/weibo/weibo/ui/adapter/TweetListAdapter/setData(Lcom/android/u/weibo/weibo/business/bean/TopicInfoList;)V
aload 0
getfield com/android/u/weibo/weibo/ui/activity4xiaoyou/XYTweetProfileBaseActivity$1/this$0 Lcom/android/u/weibo/weibo/ui/activity4xiaoyou/XYTweetProfileBaseActivity;
getfield com/android/u/weibo/weibo/ui/activity4xiaoyou/XYTweetProfileBaseActivity/mAdapter Lcom/android/u/weibo/weibo/ui/adapter/TweetListAdapter;
invokevirtual com/android/u/weibo/weibo/ui/adapter/TweetListAdapter/notifyDataSetChanged()V
L10:
iconst_0
istore 3
L12:
iload 3
aload 0
getfield com/android/u/weibo/weibo/ui/activity4xiaoyou/XYTweetProfileBaseActivity$1/this$0 Lcom/android/u/weibo/weibo/ui/activity4xiaoyou/XYTweetProfileBaseActivity;
getfield com/android/u/weibo/weibo/ui/activity4xiaoyou/XYTweetProfileBaseActivity/mLocalTweetListCache Lcom/android/u/weibo/weibo/business/bean/TopicInfoList;
invokevirtual com/android/u/weibo/weibo/business/bean/TopicInfoList/size()I
if_icmpge L8
aload 0
getfield com/android/u/weibo/weibo/ui/activity4xiaoyou/XYTweetProfileBaseActivity$1/this$0 Lcom/android/u/weibo/weibo/ui/activity4xiaoyou/XYTweetProfileBaseActivity;
getfield com/android/u/weibo/weibo/ui/activity4xiaoyou/XYTweetProfileBaseActivity/mLocalTweetListCache Lcom/android/u/weibo/weibo/business/bean/TopicInfoList;
iload 3
invokevirtual com/android/u/weibo/weibo/business/bean/TopicInfoList/get(I)Ljava/lang/Object;
checkcast com/android/u/weibo/weibo/business/bean/TopicInfo
getfield com/android/u/weibo/weibo/business/bean/TopicInfo/localCreateAt J
lload 4
lcmp
ifne L13
aload 0
getfield com/android/u/weibo/weibo/ui/activity4xiaoyou/XYTweetProfileBaseActivity$1/this$0 Lcom/android/u/weibo/weibo/ui/activity4xiaoyou/XYTweetProfileBaseActivity;
getfield com/android/u/weibo/weibo/ui/activity4xiaoyou/XYTweetProfileBaseActivity/mLocalTweetListCache Lcom/android/u/weibo/weibo/business/bean/TopicInfoList;
iload 3
invokevirtual com/android/u/weibo/weibo/business/bean/TopicInfoList/remove(I)Ljava/lang/Object;
pop
L13:
iload 3
iconst_1
iadd
istore 3
goto L12
L11:
iload 3
iconst_1
iadd
istore 3
goto L9
L8:
aload 1
invokevirtual com/android/u/weibo/weibo/business/bean/TopicInfoList/isEmpty()Z
ifeq L14
aload 0
getfield com/android/u/weibo/weibo/ui/activity4xiaoyou/XYTweetProfileBaseActivity$1/this$0 Lcom/android/u/weibo/weibo/ui/activity4xiaoyou/XYTweetProfileBaseActivity;
iconst_1
invokevirtual com/android/u/weibo/weibo/ui/activity4xiaoyou/XYTweetProfileBaseActivity/showEmptyView(Z)V
goto L4
L14:
aload 0
getfield com/android/u/weibo/weibo/ui/activity4xiaoyou/XYTweetProfileBaseActivity$1/this$0 Lcom/android/u/weibo/weibo/ui/activity4xiaoyou/XYTweetProfileBaseActivity;
iconst_0
invokevirtual com/android/u/weibo/weibo/ui/activity4xiaoyou/XYTweetProfileBaseActivity/showEmptyView(Z)V
goto L4
L0:
aload 2
ldc "id"
lconst_0
invokevirtual android/content/Intent/getLongExtra(Ljava/lang/String;J)J
lstore 4
aload 2
ldc "like"
iconst_0
invokevirtual android/content/Intent/getBooleanExtra(Ljava/lang/String;Z)Z
istore 6
aload 0
getfield com/android/u/weibo/weibo/ui/activity4xiaoyou/XYTweetProfileBaseActivity$1/this$0 Lcom/android/u/weibo/weibo/ui/activity4xiaoyou/XYTweetProfileBaseActivity;
getfield com/android/u/weibo/weibo/ui/activity4xiaoyou/XYTweetProfileBaseActivity/mAdapter Lcom/android/u/weibo/weibo/ui/adapter/TweetListAdapter;
lload 4
iload 6
invokevirtual com/android/u/weibo/weibo/ui/adapter/TweetListAdapter/setLike(JZ)V
aload 0
getfield com/android/u/weibo/weibo/ui/activity4xiaoyou/XYTweetProfileBaseActivity$1/this$0 Lcom/android/u/weibo/weibo/ui/activity4xiaoyou/XYTweetProfileBaseActivity;
getfield com/android/u/weibo/weibo/ui/activity4xiaoyou/XYTweetProfileBaseActivity/mAdapter Lcom/android/u/weibo/weibo/ui/adapter/TweetListAdapter;
invokevirtual com/android/u/weibo/weibo/ui/adapter/TweetListAdapter/notifyDataSetChanged()V
goto L5
L7:
aload 0
getfield com/android/u/weibo/weibo/ui/activity4xiaoyou/XYTweetProfileBaseActivity$1/this$0 Lcom/android/u/weibo/weibo/ui/activity4xiaoyou/XYTweetProfileBaseActivity;
iconst_0
invokevirtual com/android/u/weibo/weibo/ui/activity4xiaoyou/XYTweetProfileBaseActivity/showEmptyView(Z)V
return
.limit locals 7
.limit stack 4
.end method
