.bytecode 50.0
.class synchronized com/android/u/weibo/weibo/ui/activity4xiaoyou/XYTweetProfileMyActivity$4
.super android/content/BroadcastReceiver
.enclosing method com/android/u/weibo/weibo/ui/activity4xiaoyou/XYTweetProfileMyActivity
.inner class inner com/android/u/weibo/weibo/ui/activity4xiaoyou/XYTweetProfileMyActivity$4

.field final synthetic 'this$0' Lcom/android/u/weibo/weibo/ui/activity4xiaoyou/XYTweetProfileMyActivity;

.method <init>(Lcom/android/u/weibo/weibo/ui/activity4xiaoyou/XYTweetProfileMyActivity;)V
aload 0
aload 1
putfield com/android/u/weibo/weibo/ui/activity4xiaoyou/XYTweetProfileMyActivity$4/this$0 Lcom/android/u/weibo/weibo/ui/activity4xiaoyou/XYTweetProfileMyActivity;
aload 0
invokespecial android/content/BroadcastReceiver/<init>()V
return
.limit locals 2
.limit stack 2
.end method

.method public onReceive(Landroid/content/Context;Landroid/content/Intent;)V
aload 2
ldc "content"
invokevirtual android/content/Intent/getStringExtra(Ljava/lang/String;)Ljava/lang/String;
astore 1
aload 2
ldc "img_paths"
invokevirtual android/content/Intent/getStringArrayListExtra(Ljava/lang/String;)Ljava/util/ArrayList;
astore 6
aload 2
ldc "localCreateAt"
lconst_0
invokevirtual android/content/Intent/getLongExtra(Ljava/lang/String;J)J
lstore 3
new com/android/u/weibo/weibo/business/bean/TopicInfo
dup
invokespecial com/android/u/weibo/weibo/business/bean/TopicInfo/<init>()V
astore 5
aload 6
ifnull L0
aload 6
invokevirtual java/util/ArrayList/isEmpty()Z
ifne L0
aload 5
new com/android/u/weibo/weibo/business/bean/WbImageList
dup
invokespecial com/android/u/weibo/weibo/business/bean/WbImageList/<init>()V
putfield com/android/u/weibo/weibo/business/bean/TopicInfo/image Lcom/android/u/weibo/weibo/business/bean/WbImageList;
aload 6
invokevirtual java/util/ArrayList/iterator()Ljava/util/Iterator;
astore 2
L1:
aload 2
invokeinterface java/util/Iterator/hasNext()Z 0
ifeq L0
aload 2
invokeinterface java/util/Iterator/next()Ljava/lang/Object; 0
checkcast java/lang/String
astore 6
new com/android/u/weibo/weibo/business/bean/WbImage
dup
invokespecial com/android/u/weibo/weibo/business/bean/WbImage/<init>()V
astore 7
aload 7
aload 6
putfield com/android/u/weibo/weibo/business/bean/WbImage/image_original Ljava/lang/String;
aload 5
getfield com/android/u/weibo/weibo/business/bean/TopicInfo/image Lcom/android/u/weibo/weibo/business/bean/WbImageList;
aload 7
invokevirtual com/android/u/weibo/weibo/business/bean/WbImageList/add(Ljava/lang/Object;)Z
pop
goto L1
L0:
aload 5
lconst_0
putfield com/android/u/weibo/weibo/business/bean/TopicInfo/tid J
aload 5
aload 1
invokestatic com/android/u/weibo/weibo/utils/WeiboUtil/processLongTweet(Ljava/lang/String;)Ljava/lang/String;
putfield com/android/u/weibo/weibo/business/bean/TopicInfo/content Ljava/lang/String;
aload 5
aload 1
putfield com/android/u/weibo/weibo/business/bean/TopicInfo/article Ljava/lang/String;
aload 5
lload 3
putfield com/android/u/weibo/weibo/business/bean/TopicInfo/localCreateAt J
aload 5
new com/product/android/commonInterface/weibo/WbUserInfo
dup
invokespecial com/product/android/commonInterface/weibo/WbUserInfo/<init>()V
putfield com/android/u/weibo/weibo/business/bean/TopicInfo/user Lcom/product/android/commonInterface/weibo/WbUserInfo;
aload 0
getfield com/android/u/weibo/weibo/ui/activity4xiaoyou/XYTweetProfileMyActivity$4/this$0 Lcom/android/u/weibo/weibo/ui/activity4xiaoyou/XYTweetProfileMyActivity;
getfield com/android/u/weibo/weibo/ui/activity4xiaoyou/XYTweetProfileMyActivity/mLocalTweetListCache Lcom/android/u/weibo/weibo/business/bean/TopicInfoList;
ifnonnull L2
aload 0
getfield com/android/u/weibo/weibo/ui/activity4xiaoyou/XYTweetProfileMyActivity$4/this$0 Lcom/android/u/weibo/weibo/ui/activity4xiaoyou/XYTweetProfileMyActivity;
new com/android/u/weibo/weibo/business/bean/TopicInfoList
dup
invokespecial com/android/u/weibo/weibo/business/bean/TopicInfoList/<init>()V
putfield com/android/u/weibo/weibo/ui/activity4xiaoyou/XYTweetProfileMyActivity/mLocalTweetListCache Lcom/android/u/weibo/weibo/business/bean/TopicInfoList;
L2:
aload 5
iconst_1
invokestatic com/android/u/weibo/weibo/utils/ConvertTweetListUtils/convertTopic(Lcom/android/u/weibo/weibo/business/bean/TopicInfo;Z)V
aload 0
getfield com/android/u/weibo/weibo/ui/activity4xiaoyou/XYTweetProfileMyActivity$4/this$0 Lcom/android/u/weibo/weibo/ui/activity4xiaoyou/XYTweetProfileMyActivity;
getfield com/android/u/weibo/weibo/ui/activity4xiaoyou/XYTweetProfileMyActivity/mLocalTweetListCache Lcom/android/u/weibo/weibo/business/bean/TopicInfoList;
iconst_0
aload 5
invokevirtual com/android/u/weibo/weibo/business/bean/TopicInfoList/add(ILjava/lang/Object;)V
aload 0
getfield com/android/u/weibo/weibo/ui/activity4xiaoyou/XYTweetProfileMyActivity$4/this$0 Lcom/android/u/weibo/weibo/ui/activity4xiaoyou/XYTweetProfileMyActivity;
getfield com/android/u/weibo/weibo/ui/activity4xiaoyou/XYTweetProfileMyActivity/mAdapter Lcom/android/u/weibo/weibo/ui/adapter/TweetListAdapter;
invokevirtual com/android/u/weibo/weibo/ui/adapter/TweetListAdapter/getData()Lcom/android/u/weibo/weibo/business/bean/TopicInfoList;
astore 2
aload 2
astore 1
aload 2
ifnonnull L3
new com/android/u/weibo/weibo/business/bean/TopicInfoList
dup
invokespecial com/android/u/weibo/weibo/business/bean/TopicInfoList/<init>()V
astore 1
L3:
aload 1
iconst_0
aload 5
invokevirtual com/android/u/weibo/weibo/business/bean/TopicInfoList/add(ILjava/lang/Object;)V
aload 0
getfield com/android/u/weibo/weibo/ui/activity4xiaoyou/XYTweetProfileMyActivity$4/this$0 Lcom/android/u/weibo/weibo/ui/activity4xiaoyou/XYTweetProfileMyActivity;
getfield com/android/u/weibo/weibo/ui/activity4xiaoyou/XYTweetProfileMyActivity/mAdapter Lcom/android/u/weibo/weibo/ui/adapter/TweetListAdapter;
aload 1
invokevirtual com/android/u/weibo/weibo/ui/adapter/TweetListAdapter/setData(Lcom/android/u/weibo/weibo/business/bean/TopicInfoList;)V
aload 0
getfield com/android/u/weibo/weibo/ui/activity4xiaoyou/XYTweetProfileMyActivity$4/this$0 Lcom/android/u/weibo/weibo/ui/activity4xiaoyou/XYTweetProfileMyActivity;
getfield com/android/u/weibo/weibo/ui/activity4xiaoyou/XYTweetProfileMyActivity/mAdapter Lcom/android/u/weibo/weibo/ui/adapter/TweetListAdapter;
invokevirtual com/android/u/weibo/weibo/ui/adapter/TweetListAdapter/notifyDataSetChanged()V
aload 0
getfield com/android/u/weibo/weibo/ui/activity4xiaoyou/XYTweetProfileMyActivity$4/this$0 Lcom/android/u/weibo/weibo/ui/activity4xiaoyou/XYTweetProfileMyActivity;
getfield com/android/u/weibo/weibo/ui/activity4xiaoyou/XYTweetProfileMyActivity/mAdapter Lcom/android/u/weibo/weibo/ui/adapter/TweetListAdapter;
invokevirtual com/android/u/weibo/weibo/ui/adapter/TweetListAdapter/getData()Lcom/android/u/weibo/weibo/business/bean/TopicInfoList;
ifnull L4
aload 0
getfield com/android/u/weibo/weibo/ui/activity4xiaoyou/XYTweetProfileMyActivity$4/this$0 Lcom/android/u/weibo/weibo/ui/activity4xiaoyou/XYTweetProfileMyActivity;
getfield com/android/u/weibo/weibo/ui/activity4xiaoyou/XYTweetProfileMyActivity/mAdapter Lcom/android/u/weibo/weibo/ui/adapter/TweetListAdapter;
invokevirtual com/android/u/weibo/weibo/ui/adapter/TweetListAdapter/getData()Lcom/android/u/weibo/weibo/business/bean/TopicInfoList;
invokevirtual com/android/u/weibo/weibo/business/bean/TopicInfoList/isEmpty()Z
ifeq L5
L4:
aload 0
getfield com/android/u/weibo/weibo/ui/activity4xiaoyou/XYTweetProfileMyActivity$4/this$0 Lcom/android/u/weibo/weibo/ui/activity4xiaoyou/XYTweetProfileMyActivity;
iconst_1
invokevirtual com/android/u/weibo/weibo/ui/activity4xiaoyou/XYTweetProfileMyActivity/showEmptyView(Z)V
return
L5:
aload 0
getfield com/android/u/weibo/weibo/ui/activity4xiaoyou/XYTweetProfileMyActivity$4/this$0 Lcom/android/u/weibo/weibo/ui/activity4xiaoyou/XYTweetProfileMyActivity;
iconst_0
invokevirtual com/android/u/weibo/weibo/ui/activity4xiaoyou/XYTweetProfileMyActivity/showEmptyView(Z)V
return
.limit locals 8
.limit stack 4
.end method
