.bytecode 50.0
.class synchronized com/android/u/weibo/weibo/ui/activity4xiaoyou/XYTweetProfileBaseActivity$4
.super java/lang/Object
.implements android/view/View$OnClickListener
.enclosing method com/android/u/weibo/weibo/ui/activity4xiaoyou/XYTweetProfileBaseActivity/initBirthdayBanner(II)V
.inner class inner com/android/u/weibo/weibo/ui/activity4xiaoyou/XYTweetProfileBaseActivity$4

.field final synthetic 'this$0' Lcom/android/u/weibo/weibo/ui/activity4xiaoyou/XYTweetProfileBaseActivity;

.method <init>(Lcom/android/u/weibo/weibo/ui/activity4xiaoyou/XYTweetProfileBaseActivity;)V
aload 0
aload 1
putfield com/android/u/weibo/weibo/ui/activity4xiaoyou/XYTweetProfileBaseActivity$4/this$0 Lcom/android/u/weibo/weibo/ui/activity4xiaoyou/XYTweetProfileBaseActivity;
aload 0
invokespecial java/lang/Object/<init>()V
return
.limit locals 2
.limit stack 2
.end method

.method public onClick(Landroid/view/View;)V
aload 0
getfield com/android/u/weibo/weibo/ui/activity4xiaoyou/XYTweetProfileBaseActivity$4/this$0 Lcom/android/u/weibo/weibo/ui/activity4xiaoyou/XYTweetProfileBaseActivity;
invokestatic com/android/u/weibo/weibo/ui/activity4xiaoyou/XYTweetProfileBaseActivity/access$300(Lcom/android/u/weibo/weibo/ui/activity4xiaoyou/XYTweetProfileBaseActivity;)Lcom/android/u/weibo/weibo/ui/activity4xiaoyou/XYTweetProfileBaseActivity$PostblessTask;
ifnull L0
aload 0
getfield com/android/u/weibo/weibo/ui/activity4xiaoyou/XYTweetProfileBaseActivity$4/this$0 Lcom/android/u/weibo/weibo/ui/activity4xiaoyou/XYTweetProfileBaseActivity;
invokestatic com/android/u/weibo/weibo/ui/activity4xiaoyou/XYTweetProfileBaseActivity/access$300(Lcom/android/u/weibo/weibo/ui/activity4xiaoyou/XYTweetProfileBaseActivity;)Lcom/android/u/weibo/weibo/ui/activity4xiaoyou/XYTweetProfileBaseActivity$PostblessTask;
invokevirtual com/android/u/weibo/weibo/ui/activity4xiaoyou/XYTweetProfileBaseActivity$PostblessTask/getStatus()Lcom/common/android/utils/concurrent/NdTinyHttpAsyncTask$Status;
getstatic com/common/android/utils/concurrent/NdTinyHttpAsyncTask$Status/RUNNING Lcom/common/android/utils/concurrent/NdTinyHttpAsyncTask$Status;
if_acmpne L0
aload 0
getfield com/android/u/weibo/weibo/ui/activity4xiaoyou/XYTweetProfileBaseActivity$4/this$0 Lcom/android/u/weibo/weibo/ui/activity4xiaoyou/XYTweetProfileBaseActivity;
invokestatic com/android/u/weibo/weibo/ui/activity4xiaoyou/XYTweetProfileBaseActivity/access$300(Lcom/android/u/weibo/weibo/ui/activity4xiaoyou/XYTweetProfileBaseActivity;)Lcom/android/u/weibo/weibo/ui/activity4xiaoyou/XYTweetProfileBaseActivity$PostblessTask;
iconst_1
invokevirtual com/android/u/weibo/weibo/ui/activity4xiaoyou/XYTweetProfileBaseActivity$PostblessTask/cancel(Z)Z
pop
L0:
aload 0
getfield com/android/u/weibo/weibo/ui/activity4xiaoyou/XYTweetProfileBaseActivity$4/this$0 Lcom/android/u/weibo/weibo/ui/activity4xiaoyou/XYTweetProfileBaseActivity;
new com/android/u/weibo/weibo/ui/activity4xiaoyou/XYTweetProfileBaseActivity$PostblessTask
dup
aload 0
getfield com/android/u/weibo/weibo/ui/activity4xiaoyou/XYTweetProfileBaseActivity$4/this$0 Lcom/android/u/weibo/weibo/ui/activity4xiaoyou/XYTweetProfileBaseActivity;
aconst_null
invokespecial com/android/u/weibo/weibo/ui/activity4xiaoyou/XYTweetProfileBaseActivity$PostblessTask/<init>(Lcom/android/u/weibo/weibo/ui/activity4xiaoyou/XYTweetProfileBaseActivity;Lcom/android/u/weibo/weibo/ui/activity4xiaoyou/XYTweetProfileBaseActivity$1;)V
invokestatic com/android/u/weibo/weibo/ui/activity4xiaoyou/XYTweetProfileBaseActivity/access$302(Lcom/android/u/weibo/weibo/ui/activity4xiaoyou/XYTweetProfileBaseActivity;Lcom/android/u/weibo/weibo/ui/activity4xiaoyou/XYTweetProfileBaseActivity$PostblessTask;)Lcom/android/u/weibo/weibo/ui/activity4xiaoyou/XYTweetProfileBaseActivity$PostblessTask;
pop
aload 0
getfield com/android/u/weibo/weibo/ui/activity4xiaoyou/XYTweetProfileBaseActivity$4/this$0 Lcom/android/u/weibo/weibo/ui/activity4xiaoyou/XYTweetProfileBaseActivity;
invokestatic com/android/u/weibo/weibo/ui/activity4xiaoyou/XYTweetProfileBaseActivity/access$300(Lcom/android/u/weibo/weibo/ui/activity4xiaoyou/XYTweetProfileBaseActivity;)Lcom/android/u/weibo/weibo/ui/activity4xiaoyou/XYTweetProfileBaseActivity$PostblessTask;
iconst_0
anewarray java/lang/Void
invokevirtual com/android/u/weibo/weibo/ui/activity4xiaoyou/XYTweetProfileBaseActivity$PostblessTask/execute([Ljava/lang/Object;)Lcom/common/android/utils/concurrent/NdTinyHttpAsyncTask;
pop
return
.limit locals 2
.limit stack 5
.end method
