.bytecode 50.0
.class synchronized com/android/u/weibo/weibo/ui/activity4xiaoyou/XYTweetProfileBaseActivity$PostblessTask
.super com/common/android/utils/concurrent/NdTinyHttpAsyncTask
.signature "Lcom/common/android/utils/concurrent/NdTinyHttpAsyncTask<Ljava/lang/Void;Ljava/lang/Void;Lcom/product/android/commonInterface/task/BirthBlessResult;>;"
.inner class private PostblessTask inner com/android/u/weibo/weibo/ui/activity4xiaoyou/XYTweetProfileBaseActivity$PostblessTask outer com/android/u/weibo/weibo/ui/activity4xiaoyou/XYTweetProfileBaseActivity

.field final synthetic 'this$0' Lcom/android/u/weibo/weibo/ui/activity4xiaoyou/XYTweetProfileBaseActivity;

.method private <init>(Lcom/android/u/weibo/weibo/ui/activity4xiaoyou/XYTweetProfileBaseActivity;)V
aload 0
aload 1
putfield com/android/u/weibo/weibo/ui/activity4xiaoyou/XYTweetProfileBaseActivity$PostblessTask/this$0 Lcom/android/u/weibo/weibo/ui/activity4xiaoyou/XYTweetProfileBaseActivity;
aload 0
invokespecial com/common/android/utils/concurrent/NdTinyHttpAsyncTask/<init>()V
return
.limit locals 2
.limit stack 2
.end method

.method synthetic <init>(Lcom/android/u/weibo/weibo/ui/activity4xiaoyou/XYTweetProfileBaseActivity;Lcom/android/u/weibo/weibo/ui/activity4xiaoyou/XYTweetProfileBaseActivity$1;)V
aload 0
aload 1
invokespecial com/android/u/weibo/weibo/ui/activity4xiaoyou/XYTweetProfileBaseActivity$PostblessTask/<init>(Lcom/android/u/weibo/weibo/ui/activity4xiaoyou/XYTweetProfileBaseActivity;)V
return
.limit locals 3
.limit stack 2
.end method

.method protected transient doInBackground([Ljava/lang/Void;)Lcom/product/android/commonInterface/task/BirthBlessResult;
aload 0
getfield com/android/u/weibo/weibo/ui/activity4xiaoyou/XYTweetProfileBaseActivity$PostblessTask/this$0 Lcom/android/u/weibo/weibo/ui/activity4xiaoyou/XYTweetProfileBaseActivity;
getfield com/android/u/weibo/weibo/ui/activity4xiaoyou/XYTweetProfileBaseActivity/mUid J
invokestatic com/android/u/weibo/weiboInterfaceImpl/WeiboCallOtherModel/postBless(J)Lcom/product/android/commonInterface/task/BirthBlessResult;
areturn
.limit locals 2
.limit stack 2
.end method

.method protected volatile synthetic doInBackground([Ljava/lang/Object;)Ljava/lang/Object;
aload 0
aload 1
checkcast [Ljava/lang/Void;
invokevirtual com/android/u/weibo/weibo/ui/activity4xiaoyou/XYTweetProfileBaseActivity$PostblessTask/doInBackground([Ljava/lang/Void;)Lcom/product/android/commonInterface/task/BirthBlessResult;
areturn
.limit locals 2
.limit stack 2
.end method

.method protected onPostExecute(Lcom/product/android/commonInterface/task/BirthBlessResult;)V
aload 0
aload 1
invokespecial com/common/android/utils/concurrent/NdTinyHttpAsyncTask/onPostExecute(Ljava/lang/Object;)V
aload 1
ifnull L0
aload 1
getfield com/product/android/commonInterface/task/BirthBlessResult/iCode I
tableswitch 200
L1
L2
default : L3
L3:
aload 0
getfield com/android/u/weibo/weibo/ui/activity4xiaoyou/XYTweetProfileBaseActivity$PostblessTask/this$0 Lcom/android/u/weibo/weibo/ui/activity4xiaoyou/XYTweetProfileBaseActivity;
getstatic com/android/u/weibo/R$string/blessing_fail I
invokestatic com/common/android/utils/ToastUtils/display(Landroid/content/Context;I)V
L4:
return
L1:
aload 1
getfield com/product/android/commonInterface/task/BirthBlessResult/iBlessCount I
istore 2
iload 2
ifle L5
aload 0
getfield com/android/u/weibo/weibo/ui/activity4xiaoyou/XYTweetProfileBaseActivity$PostblessTask/this$0 Lcom/android/u/weibo/weibo/ui/activity4xiaoyou/XYTweetProfileBaseActivity;
iload 2
putfield com/android/u/weibo/weibo/ui/activity4xiaoyou/XYTweetProfileBaseActivity/mBlessCnt I
L5:
aload 1
getfield com/product/android/commonInterface/task/BirthBlessResult/iExp I
ifle L6
aload 0
getfield com/android/u/weibo/weibo/ui/activity4xiaoyou/XYTweetProfileBaseActivity$PostblessTask/this$0 Lcom/android/u/weibo/weibo/ui/activity4xiaoyou/XYTweetProfileBaseActivity;
invokestatic com/android/u/weibo/weibo/ui/activity4xiaoyou/XYTweetProfileBaseActivity/access$500(Lcom/android/u/weibo/weibo/ui/activity4xiaoyou/XYTweetProfileBaseActivity;)V
L6:
aload 0
getfield com/android/u/weibo/weibo/ui/activity4xiaoyou/XYTweetProfileBaseActivity$PostblessTask/this$0 Lcom/android/u/weibo/weibo/ui/activity4xiaoyou/XYTweetProfileBaseActivity;
getfield com/android/u/weibo/weibo/ui/activity4xiaoyou/XYTweetProfileBaseActivity/isInitBirthdayBanner Z
ifeq L4
aload 0
getfield com/android/u/weibo/weibo/ui/activity4xiaoyou/XYTweetProfileBaseActivity$PostblessTask/this$0 Lcom/android/u/weibo/weibo/ui/activity4xiaoyou/XYTweetProfileBaseActivity;
getfield com/android/u/weibo/weibo/ui/activity4xiaoyou/XYTweetProfileBaseActivity/mTxtHeartNum Landroid/widget/TextView;
new java/lang/StringBuilder
dup
invokespecial java/lang/StringBuilder/<init>()V
ldc ""
invokevirtual java/lang/StringBuilder/append(Ljava/lang/String;)Ljava/lang/StringBuilder;
iload 2
invokevirtual java/lang/StringBuilder/append(I)Ljava/lang/StringBuilder;
invokevirtual java/lang/StringBuilder/toString()Ljava/lang/String;
invokevirtual android/widget/TextView/setText(Ljava/lang/CharSequence;)V
aload 0
getfield com/android/u/weibo/weibo/ui/activity4xiaoyou/XYTweetProfileBaseActivity$PostblessTask/this$0 Lcom/android/u/weibo/weibo/ui/activity4xiaoyou/XYTweetProfileBaseActivity;
getfield com/android/u/weibo/weibo/ui/activity4xiaoyou/XYTweetProfileBaseActivity/mTextSendGift Landroid/widget/TextView;
iconst_0
invokevirtual android/widget/TextView/setVisibility(I)V
aload 0
getfield com/android/u/weibo/weibo/ui/activity4xiaoyou/XYTweetProfileBaseActivity$PostblessTask/this$0 Lcom/android/u/weibo/weibo/ui/activity4xiaoyou/XYTweetProfileBaseActivity;
getfield com/android/u/weibo/weibo/ui/activity4xiaoyou/XYTweetProfileBaseActivity/mblessingBtn Landroid/widget/Button;
bipush 8
invokevirtual android/widget/Button/setVisibility(I)V
aload 0
getfield com/android/u/weibo/weibo/ui/activity4xiaoyou/XYTweetProfileBaseActivity$PostblessTask/this$0 Lcom/android/u/weibo/weibo/ui/activity4xiaoyou/XYTweetProfileBaseActivity;
getfield com/android/u/weibo/weibo/ui/activity4xiaoyou/XYTweetProfileBaseActivity/mAddOneImg Landroid/widget/ImageView;
iconst_0
invokevirtual android/widget/ImageView/setVisibility(I)V
return
L2:
aload 0
getfield com/android/u/weibo/weibo/ui/activity4xiaoyou/XYTweetProfileBaseActivity$PostblessTask/this$0 Lcom/android/u/weibo/weibo/ui/activity4xiaoyou/XYTweetProfileBaseActivity;
getstatic com/android/u/weibo/R$string/blessing_fail_double I
invokestatic com/common/android/utils/ToastUtils/display(Landroid/content/Context;I)V
return
L0:
aload 0
getfield com/android/u/weibo/weibo/ui/activity4xiaoyou/XYTweetProfileBaseActivity$PostblessTask/this$0 Lcom/android/u/weibo/weibo/ui/activity4xiaoyou/XYTweetProfileBaseActivity;
getstatic com/android/u/weibo/R$string/blessing_fail I
invokestatic com/common/android/utils/ToastUtils/display(Landroid/content/Context;I)V
return
.limit locals 3
.limit stack 3
.end method

.method protected volatile synthetic onPostExecute(Ljava/lang/Object;)V
aload 0
aload 1
checkcast com/product/android/commonInterface/task/BirthBlessResult
invokevirtual com/android/u/weibo/weibo/ui/activity4xiaoyou/XYTweetProfileBaseActivity$PostblessTask/onPostExecute(Lcom/product/android/commonInterface/task/BirthBlessResult;)V
return
.limit locals 2
.limit stack 2
.end method
