.bytecode 50.0
.class synchronized cmb/pb/util/c
.super java/lang/Object
.implements cmb/pb/ui/g

.field final synthetic 'a' Lcmb/pb/util/b;

.method <init>(Lcmb/pb/util/b;)V
aload 0
aload 1
putfield cmb/pb/util/c/a Lcmb/pb/util/b;
aload 0
invokespecial java/lang/Object/<init>()V
return
.limit locals 2
.limit stack 2
.end method

.method public a(I)V
aload 0
getfield cmb/pb/util/c/a Lcmb/pb/util/b;
invokestatic cmb/pb/util/b/a(Lcmb/pb/util/b;)Lcmb/pb/util/CMBKeyboardFunc;
aload 0
getfield cmb/pb/util/c/a Lcmb/pb/util/b;
invokestatic cmb/pb/util/b/a(Lcmb/pb/util/b;)Lcmb/pb/util/CMBKeyboardFunc;
invokestatic cmb/pb/util/CMBKeyboardFunc/a(Lcmb/pb/util/CMBKeyboardFunc;)Landroid/webkit/WebView;
invokevirtual android/webkit/WebView/getHeight()I
invokestatic cmb/pb/util/CMBKeyboardFunc/a(Lcmb/pb/util/CMBKeyboardFunc;I)V
aload 0
getfield cmb/pb/util/c/a Lcmb/pb/util/b;
invokestatic cmb/pb/util/b/a(Lcmb/pb/util/b;)Lcmb/pb/util/CMBKeyboardFunc;
invokestatic cmb/pb/util/CMBKeyboardFunc/b(Lcmb/pb/util/CMBKeyboardFunc;)I
istore 2
aload 0
getfield cmb/pb/util/c/a Lcmb/pb/util/b;
invokestatic cmb/pb/util/b/a(Lcmb/pb/util/b;)Lcmb/pb/util/CMBKeyboardFunc;
invokestatic cmb/pb/util/CMBKeyboardFunc/a(Lcmb/pb/util/CMBKeyboardFunc;)Landroid/webkit/WebView;
new android/widget/LinearLayout$LayoutParams
dup
iconst_m1
iload 2
iload 1
isub
invokespecial android/widget/LinearLayout$LayoutParams/<init>(II)V
invokevirtual android/webkit/WebView/setLayoutParams(Landroid/view/ViewGroup$LayoutParams;)V
aload 0
getfield cmb/pb/util/c/a Lcmb/pb/util/b;
invokestatic cmb/pb/util/b/a(Lcmb/pb/util/b;)Lcmb/pb/util/CMBKeyboardFunc;
iload 1
aload 0
getfield cmb/pb/util/c/a Lcmb/pb/util/b;
invokestatic cmb/pb/util/b/a(Lcmb/pb/util/b;)Lcmb/pb/util/CMBKeyboardFunc;
invokestatic cmb/pb/util/CMBKeyboardFunc/b(Lcmb/pb/util/CMBKeyboardFunc;)I
aload 0
getfield cmb/pb/util/c/a Lcmb/pb/util/b;
invokestatic cmb/pb/util/b/a(Lcmb/pb/util/b;)Lcmb/pb/util/CMBKeyboardFunc;
invokestatic cmb/pb/util/CMBKeyboardFunc/c(Lcmb/pb/util/CMBKeyboardFunc;)I
aload 0
getfield cmb/pb/util/c/a Lcmb/pb/util/b;
invokestatic cmb/pb/util/b/a(Lcmb/pb/util/b;)Lcmb/pb/util/CMBKeyboardFunc;
invokestatic cmb/pb/util/CMBKeyboardFunc/a(Lcmb/pb/util/CMBKeyboardFunc;)Landroid/webkit/WebView;
invokevirtual android/webkit/WebView/getScrollY()I
isub
isub
isub
invokestatic cmb/pb/util/CMBKeyboardFunc/b(Lcmb/pb/util/CMBKeyboardFunc;I)V
aload 0
getfield cmb/pb/util/c/a Lcmb/pb/util/b;
invokestatic cmb/pb/util/b/a(Lcmb/pb/util/b;)Lcmb/pb/util/CMBKeyboardFunc;
invokestatic cmb/pb/util/CMBKeyboardFunc/d(Lcmb/pb/util/CMBKeyboardFunc;)I
ifle L0
aload 0
getfield cmb/pb/util/c/a Lcmb/pb/util/b;
invokestatic cmb/pb/util/b/a(Lcmb/pb/util/b;)Lcmb/pb/util/CMBKeyboardFunc;
astore 3
aload 3
aload 3
invokestatic cmb/pb/util/CMBKeyboardFunc/d(Lcmb/pb/util/CMBKeyboardFunc;)I
aload 0
getfield cmb/pb/util/c/a Lcmb/pb/util/b;
invokestatic cmb/pb/util/b/a(Lcmb/pb/util/b;)Lcmb/pb/util/CMBKeyboardFunc;
invokestatic cmb/pb/util/CMBKeyboardFunc/a(Lcmb/pb/util/CMBKeyboardFunc;)Landroid/webkit/WebView;
invokevirtual android/webkit/WebView/getScrollY()I
iadd
invokestatic cmb/pb/util/CMBKeyboardFunc/b(Lcmb/pb/util/CMBKeyboardFunc;I)V
aload 0
getfield cmb/pb/util/c/a Lcmb/pb/util/b;
invokestatic cmb/pb/util/b/a(Lcmb/pb/util/b;)Lcmb/pb/util/CMBKeyboardFunc;
invokestatic cmb/pb/util/CMBKeyboardFunc/e(Lcmb/pb/util/CMBKeyboardFunc;)Landroid/os/Handler;
aload 0
getfield cmb/pb/util/c/a Lcmb/pb/util/b;
invokestatic cmb/pb/util/b/a(Lcmb/pb/util/b;)Lcmb/pb/util/CMBKeyboardFunc;
invokestatic cmb/pb/util/CMBKeyboardFunc/f(Lcmb/pb/util/CMBKeyboardFunc;)Ljava/lang/Runnable;
invokevirtual android/os/Handler/post(Ljava/lang/Runnable;)Z
pop
L0:
aload 0
getfield cmb/pb/util/c/a Lcmb/pb/util/b;
invokestatic cmb/pb/util/b/a(Lcmb/pb/util/b;)Lcmb/pb/util/CMBKeyboardFunc;
invokestatic cmb/pb/util/CMBKeyboardFunc/g(Lcmb/pb/util/CMBKeyboardFunc;)Landroid/app/Activity;
invokevirtual android/app/Activity/getApplicationContext()Landroid/content/Context;
invokestatic cmb/pb/util/i/a(Landroid/content/Context;)V
return
.limit locals 4
.limit stack 6
.end method
