.bytecode 50.0
.class public synchronized cmb/pb/util/h
.super java/lang/Object

.field static 'a' [B

.field static 'b' Ljava/lang/String;

.field static 'c' Ljava/security/PublicKey;

.field private static 'd' [C

.method static <clinit>()V
sipush 128
newarray byte
dup
iconst_0
ldc_w -78
bastore
dup
iconst_1
ldc_w -70
bastore
dup
iconst_2
ldc_w 1
bastore
dup
iconst_3
ldc_w -46
bastore
dup
iconst_4
ldc_w -82
bastore
dup
iconst_5
ldc_w 78
bastore
dup
bipush 6
ldc_w -3
bastore
dup
bipush 7
ldc_w -95
bastore
dup
bipush 8
ldc_w 7
bastore
dup
bipush 9
ldc_w 10
bastore
dup
bipush 10
ldc_w 57
bastore
dup
bipush 11
ldc_w -23
bastore
dup
bipush 12
ldc_w -61
bastore
dup
bipush 13
ldc_w 75
bastore
dup
bipush 14
ldc_w -50
bastore
dup
bipush 15
ldc_w 18
bastore
dup
bipush 16
ldc_w 36
bastore
dup
bipush 17
ldc_w 9
bastore
dup
bipush 18
ldc_w -35
bastore
dup
bipush 19
ldc_w -43
bastore
dup
bipush 20
ldc_w -114
bastore
dup
bipush 21
ldc_w 6
bastore
dup
bipush 22
ldc_w -117
bastore
dup
bipush 23
ldc_w 27
bastore
dup
bipush 24
ldc_w -91
bastore
dup
bipush 25
ldc_w 28
bastore
dup
bipush 26
ldc_w 80
bastore
dup
bipush 27
ldc_w 73
bastore
dup
bipush 28
ldc_w 100
bastore
dup
bipush 29
ldc_w -2
bastore
dup
bipush 30
ldc_w 75
bastore
dup
bipush 31
ldc_w 14
bastore
dup
bipush 32
ldc_w 106
bastore
dup
bipush 33
ldc_w 96
bastore
dup
bipush 34
ldc_w 97
bastore
dup
bipush 35
ldc_w 74
bastore
dup
bipush 36
ldc_w 97
bastore
dup
bipush 37
ldc_w 1
bastore
dup
bipush 38
ldc_w -18
bastore
dup
bipush 39
ldc_w -78
bastore
dup
bipush 40
ldc_w 50
bastore
dup
bipush 41
ldc_w -104
bastore
dup
bipush 42
ldc_w 74
bastore
dup
bipush 43
ldc_w 42
bastore
dup
bipush 44
ldc_w 71
bastore
dup
bipush 45
ldc_w -2
bastore
dup
bipush 46
ldc_w -45
bastore
dup
bipush 47
ldc_w -99
bastore
dup
bipush 48
ldc_w -87
bastore
dup
bipush 49
ldc_w 125
bastore
dup
bipush 50
ldc_w 42
bastore
dup
bipush 51
ldc_w -108
bastore
dup
bipush 52
ldc_w 99
bastore
dup
bipush 53
ldc_w 117
bastore
dup
bipush 54
ldc_w 48
bastore
dup
bipush 55
ldc_w 106
bastore
dup
bipush 56
ldc_w 13
bastore
dup
bipush 57
ldc_w -76
bastore
dup
bipush 58
ldc_w 14
bastore
dup
bipush 59
ldc_w 108
bastore
dup
bipush 60
ldc_w 124
bastore
dup
bipush 61
ldc_w 32
bastore
dup
bipush 62
ldc_w -27
bastore
dup
bipush 63
ldc_w 63
bastore
dup
bipush 64
ldc_w -43
bastore
dup
bipush 65
ldc_w 68
bastore
dup
bipush 66
ldc_w -102
bastore
dup
bipush 67
ldc_w 77
bastore
dup
bipush 68
ldc_w 54
bastore
dup
bipush 69
ldc_w -89
bastore
dup
bipush 70
ldc_w -85
bastore
dup
bipush 71
ldc_w 92
bastore
dup
bipush 72
ldc_w -62
bastore
dup
bipush 73
ldc_w 83
bastore
dup
bipush 74
ldc_w 69
bastore
dup
bipush 75
ldc_w 40
bastore
dup
bipush 76
ldc_w -49
bastore
dup
bipush 77
ldc_w -53
bastore
dup
bipush 78
ldc_w 72
bastore
dup
bipush 79
ldc_w -118
bastore
dup
bipush 80
ldc_w -12
bastore
dup
bipush 81
ldc_w -123
bastore
dup
bipush 82
ldc_w -121
bastore
dup
bipush 83
ldc_w -59
bastore
dup
bipush 84
ldc_w 9
bastore
dup
bipush 85
ldc_w -105
bastore
dup
bipush 86
ldc_w 61
bastore
dup
bipush 87
ldc_w 78
bastore
dup
bipush 88
ldc_w 112
bastore
dup
bipush 89
ldc_w -52
bastore
dup
bipush 90
ldc_w 69
bastore
dup
bipush 91
ldc_w 58
bastore
dup
bipush 92
ldc_w -94
bastore
dup
bipush 93
ldc_w 111
bastore
dup
bipush 94
ldc_w 7
bastore
dup
bipush 95
ldc_w -110
bastore
dup
bipush 96
ldc_w -18
bastore
dup
bipush 97
ldc_w -5
bastore
dup
bipush 98
ldc_w -60
bastore
dup
bipush 99
ldc_w 23
bastore
dup
bipush 100
ldc_w 103
bastore
dup
bipush 101
ldc_w 79
bastore
dup
bipush 102
ldc_w -113
bastore
dup
bipush 103
ldc_w 22
bastore
dup
bipush 104
ldc_w 101
bastore
dup
bipush 105
ldc_w -94
bastore
dup
bipush 106
ldc_w -35
bastore
dup
bipush 107
ldc_w -38
bastore
dup
bipush 108
ldc_w 89
bastore
dup
bipush 109
ldc_w -37
bastore
dup
bipush 110
ldc_w 94
bastore
dup
bipush 111
ldc_w -72
bastore
dup
bipush 112
ldc_w -105
bastore
dup
bipush 113
ldc_w -89
bastore
dup
bipush 114
ldc_w 35
bastore
dup
bipush 115
ldc_w -88
bastore
dup
bipush 116
ldc_w 127
bastore
dup
bipush 117
ldc_w -101
bastore
dup
bipush 118
ldc_w -33
bastore
dup
bipush 119
ldc_w 120
bastore
dup
bipush 120
ldc_w 96
bastore
dup
bipush 121
ldc_w -90
bastore
dup
bipush 122
ldc_w -20
bastore
dup
bipush 123
ldc_w 16
bastore
dup
bipush 124
ldc_w 42
bastore
dup
bipush 125
ldc_w -38
bastore
dup
bipush 126
ldc_w 23
bastore
dup
bipush 127
ldc_w -97
bastore
putstatic cmb/pb/util/h/a [B
ldc "MIIBIjANBgkqhkiG9w0BAQEFAAOCAQ8AMIIBCgKCAQEAk+PFDSFypJvT2VZOvh7L3fUf52aAgtSjxZT4ifKEyj1PIDaj8FCC3880xD0chYEXg+CpkVnj9WYCfBDqeDpNYdRBSKIf2LP/26CObifDxd9VK+4VY/vsiW0qtqjuxVtLHficIjeB34FhdTve7mzXOaecepdwaRSMbzPsonIdeb3ysiSC20XYuzYmfolNVDQIgMVq8tRvacKhc65nLHRovBUTmeUa7tu+1rftsXW8/WbfsHp1YftnqFnb1V/MCtCUcmp3q3fYzxMjukS0lvIodw3zDyuC2vC9ne3ICAg60OHRbEWSKjxlvqrKNdnAYbaKgPbDwBLo2wBCC5qfFpMppQIDAQAB"
putstatic cmb/pb/util/h/b Ljava/lang/String;
aconst_null
putstatic cmb/pb/util/h/c Ljava/security/PublicKey;
bipush 16
newarray char
dup
iconst_0
ldc_w 48
castore
dup
iconst_1
ldc_w 49
castore
dup
iconst_2
ldc_w 50
castore
dup
iconst_3
ldc_w 51
castore
dup
iconst_4
ldc_w 52
castore
dup
iconst_5
ldc_w 53
castore
dup
bipush 6
ldc_w 54
castore
dup
bipush 7
ldc_w 55
castore
dup
bipush 8
ldc_w 56
castore
dup
bipush 9
ldc_w 57
castore
dup
bipush 10
ldc_w 97
castore
dup
bipush 11
ldc_w 98
castore
dup
bipush 12
ldc_w 99
castore
dup
bipush 13
ldc_w 100
castore
dup
bipush 14
ldc_w 101
castore
dup
bipush 15
ldc_w 102
castore
putstatic cmb/pb/util/h/d [C
return
.limit locals 0
.limit stack 4
.end method

.method public static a(Ljava/lang/String;Ljava/lang/String;)Ljava/lang/String;
.catch java/security/InvalidKeyException from L0 to L1 using L2
.catch java/security/NoSuchAlgorithmException from L0 to L1 using L3
.catch java/security/spec/InvalidKeySpecException from L0 to L1 using L4
.catch javax/crypto/NoSuchPaddingException from L0 to L1 using L5
.catch javax/crypto/IllegalBlockSizeException from L0 to L1 using L6
.catch javax/crypto/BadPaddingException from L0 to L1 using L7
aload 0
ifnonnull L8
aconst_null
areturn
L8:
aload 1
ifnull L9
aload 1
astore 2
aload 1
invokevirtual java/lang/String/length()I
iconst_5
if_icmpge L10
L9:
invokestatic java/lang/System/currentTimeMillis()J
invokestatic java/lang/Long/toString(J)Ljava/lang/String;
astore 1
aload 1
aload 1
invokevirtual java/lang/String/length()I
bipush 12
isub
invokevirtual java/lang/String/substring(I)Ljava/lang/String;
astore 2
L10:
new java/lang/StringBuilder
dup
ldc "AAA"
invokespecial java/lang/StringBuilder/<init>(Ljava/lang/String;)V
aload 2
aload 2
invokevirtual java/lang/String/length()I
iconst_5
isub
invokevirtual java/lang/String/substring(I)Ljava/lang/String;
invokevirtual java/lang/StringBuilder/append(Ljava/lang/String;)Ljava/lang/StringBuilder;
aload 0
invokevirtual java/lang/StringBuilder/append(Ljava/lang/String;)Ljava/lang/StringBuilder;
invokevirtual java/lang/StringBuilder/toString()Ljava/lang/String;
invokevirtual java/lang/String/getBytes()[B
astore 0
L0:
aload 0
invokestatic cmb/pb/util/h/a([B)[B
invokestatic cmb/pb/util/a/b([B)Ljava/lang/String;
astore 0
L1:
aload 0
areturn
L2:
astore 0
aload 0
invokevirtual java/security/InvalidKeyException/printStackTrace()V
aconst_null
areturn
L3:
astore 0
aload 0
invokevirtual java/security/NoSuchAlgorithmException/printStackTrace()V
aconst_null
areturn
L4:
astore 0
aload 0
invokevirtual java/security/spec/InvalidKeySpecException/printStackTrace()V
aconst_null
areturn
L5:
astore 0
aload 0
invokevirtual javax/crypto/NoSuchPaddingException/printStackTrace()V
aconst_null
areturn
L6:
astore 0
aload 0
invokevirtual javax/crypto/IllegalBlockSizeException/printStackTrace()V
aconst_null
areturn
L7:
astore 0
aload 0
invokevirtual javax/crypto/BadPaddingException/printStackTrace()V
aconst_null
areturn
.limit locals 3
.limit stack 4
.end method

.method public static a(Ljava/lang/String;)V
getstatic cmb/pb/util/h/b Ljava/lang/String;
invokestatic cmb/pb/util/a/a(Ljava/lang/String;)[B
invokestatic cmb/pb/util/h/b([B)Ljava/security/PublicKey;
astore 1
aload 0
invokestatic cmb/pb/util/a/a(Ljava/lang/String;)[B
aload 1
invokestatic cmb/pb/util/h/a([BLjava/security/Key;)[B
invokestatic cmb/pb/util/h/b([B)Ljava/security/PublicKey;
putstatic cmb/pb/util/h/c Ljava/security/PublicKey;
return
.limit locals 2
.limit stack 2
.end method

.method public static a([B)[B
aload 0
ifnull L0
getstatic cmb/pb/util/h/c Ljava/security/PublicKey;
ifnonnull L1
L0:
aconst_null
areturn
L1:
ldc "RSA/ECB/PKCS1Padding"
invokestatic javax/crypto/Cipher/getInstance(Ljava/lang/String;)Ljavax/crypto/Cipher;
astore 1
aload 1
iconst_1
getstatic cmb/pb/util/h/c Ljava/security/PublicKey;
invokevirtual javax/crypto/Cipher/init(ILjava/security/Key;)V
aload 1
aload 0
invokevirtual javax/crypto/Cipher/doFinal([B)[B
areturn
.limit locals 2
.limit stack 3
.end method

.method public static a([BLjava/security/Key;)[B
ldc "RSA/ECB/PKCS1Padding"
invokestatic javax/crypto/Cipher/getInstance(Ljava/lang/String;)Ljavax/crypto/Cipher;
astore 2
aload 2
iconst_2
aload 1
invokevirtual javax/crypto/Cipher/init(ILjava/security/Key;)V
aload 2
aload 0
invokevirtual javax/crypto/Cipher/doFinal([B)[B
areturn
.limit locals 3
.limit stack 3
.end method

.method public static b(Ljava/lang/String;)Ljava/lang/String;
.catch java/security/InvalidKeyException from L0 to L1 using L2
.catch java/security/NoSuchAlgorithmException from L0 to L1 using L3
.catch java/security/spec/InvalidKeySpecException from L0 to L1 using L4
.catch javax/crypto/NoSuchPaddingException from L0 to L1 using L5
.catch javax/crypto/IllegalBlockSizeException from L0 to L1 using L6
.catch javax/crypto/BadPaddingException from L0 to L1 using L7
aload 0
ifnonnull L8
L9:
aconst_null
areturn
L8:
ldc "1234567890"
ifnull L9
ldc "1234567890"
invokevirtual java/lang/String/length()I
iconst_5
if_icmplt L9
new java/lang/StringBuilder
dup
ldc "AAA"
invokespecial java/lang/StringBuilder/<init>(Ljava/lang/String;)V
ldc "1234567890"
ldc "1234567890"
invokevirtual java/lang/String/length()I
iconst_5
isub
invokevirtual java/lang/String/substring(I)Ljava/lang/String;
invokevirtual java/lang/StringBuilder/append(Ljava/lang/String;)Ljava/lang/StringBuilder;
aload 0
invokevirtual java/lang/StringBuilder/append(Ljava/lang/String;)Ljava/lang/StringBuilder;
invokevirtual java/lang/StringBuilder/toString()Ljava/lang/String;
invokevirtual java/lang/String/getBytes()[B
astore 0
L0:
aload 0
invokestatic cmb/pb/util/h/a([B)[B
invokestatic cmb/pb/util/a/b([B)Ljava/lang/String;
astore 0
L1:
aload 0
areturn
L2:
astore 0
aload 0
invokevirtual java/security/InvalidKeyException/printStackTrace()V
aconst_null
areturn
L3:
astore 0
aload 0
invokevirtual java/security/NoSuchAlgorithmException/printStackTrace()V
aconst_null
areturn
L4:
astore 0
aload 0
invokevirtual java/security/spec/InvalidKeySpecException/printStackTrace()V
aconst_null
areturn
L5:
astore 0
aload 0
invokevirtual javax/crypto/NoSuchPaddingException/printStackTrace()V
aconst_null
areturn
L6:
astore 0
aload 0
invokevirtual javax/crypto/IllegalBlockSizeException/printStackTrace()V
aconst_null
areturn
L7:
astore 0
aload 0
invokevirtual javax/crypto/BadPaddingException/printStackTrace()V
aconst_null
areturn
.limit locals 1
.limit stack 4
.end method

.method public static b([B)Ljava/security/PublicKey;
new java/security/spec/X509EncodedKeySpec
dup
aload 0
invokespecial java/security/spec/X509EncodedKeySpec/<init>([B)V
astore 0
ldc "RSA"
invokestatic java/security/KeyFactory/getInstance(Ljava/lang/String;)Ljava/security/KeyFactory;
aload 0
invokevirtual java/security/KeyFactory/generatePublic(Ljava/security/spec/KeySpec;)Ljava/security/PublicKey;
areturn
.limit locals 1
.limit stack 3
.end method
