.bytecode 50.0
.class public final synchronized com/nd/android/u/contact/business/ContactOapComFactory
.super java/lang/Object

.field private static 'instance' Lcom/nd/android/u/contact/business/ContactOapComFactory;

.method static <clinit>()V
new com/nd/android/u/contact/business/ContactOapComFactory
dup
invokespecial com/nd/android/u/contact/business/ContactOapComFactory/<init>()V
putstatic com/nd/android/u/contact/business/ContactOapComFactory/instance Lcom/nd/android/u/contact/business/ContactOapComFactory;
return
.limit locals 0
.limit stack 2
.end method

.method private <init>()V
aload 0
invokespecial java/lang/Object/<init>()V
return
.limit locals 1
.limit stack 1
.end method

.method public static getInstance()Lcom/nd/android/u/contact/business/ContactOapComFactory;
getstatic com/nd/android/u/contact/business/ContactOapComFactory/instance Lcom/nd/android/u/contact/business/ContactOapComFactory;
areturn
.limit locals 0
.limit stack 1
.end method

.method public getOapAppCom()Lcom/nd/android/u/contact/com/OapAppCom;
new com/nd/android/u/contact/com/OapAppCom
dup
invokespecial com/nd/android/u/contact/com/OapAppCom/<init>()V
areturn
.limit locals 1
.limit stack 2
.end method

.method public getOapBlackListCom()Lcom/nd/android/u/contact/com/OapBlackListCom;
new com/nd/android/u/contact/com/OapBlackListCom
dup
invokespecial com/nd/android/u/contact/com/OapBlackListCom/<init>()V
areturn
.limit locals 1
.limit stack 2
.end method

.method public getOapClassCom()Lcom/nd/android/u/contact/com/OapClassCom;
new com/nd/android/u/contact/com/OapClassCom
dup
invokespecial com/nd/android/u/contact/com/OapClassCom/<init>()V
areturn
.limit locals 1
.limit stack 2
.end method

.method public getOapDepartCom()Lcom/nd/android/u/contact/com/OapDepartCom;
new com/nd/android/u/contact/com/OapDepartCom
dup
invokespecial com/nd/android/u/contact/com/OapDepartCom/<init>()V
areturn
.limit locals 1
.limit stack 2
.end method

.method public getOapDiscussionCom()Lcom/nd/android/u/contact/com/OapDiscussionCom;
new com/nd/android/u/contact/com/OapDiscussionCom
dup
invokespecial com/nd/android/u/contact/com/OapDiscussionCom/<init>()V
areturn
.limit locals 1
.limit stack 2
.end method

.method public getOapFriendGroupcom()Lcom/nd/android/u/contact/com/OapFriendGroupCom;
new com/nd/android/u/contact/com/OapFriendGroupCom
dup
invokespecial com/nd/android/u/contact/com/OapFriendGroupCom/<init>()V
areturn
.limit locals 1
.limit stack 2
.end method

.method public getOapGroupCom()Lcom/nd/android/u/contact/com/OapGroupCom;
new com/nd/android/u/contact/com/OapGroupCom
dup
invokespecial com/nd/android/u/contact/com/OapGroupCom/<init>()V
areturn
.limit locals 1
.limit stack 2
.end method

.method public getOapJMClassCom()Lcom/nd/android/u/contact/com/OapJMClassCom;
new com/nd/android/u/contact/com/OapJMClassCom
dup
invokespecial com/nd/android/u/contact/com/OapJMClassCom/<init>()V
areturn
.limit locals 1
.limit stack 2
.end method

.method public getOapSecretLoveCom()Lcom/nd/android/u/contact/com/OapSecretLoveCom;
new com/nd/android/u/contact/com/OapSecretLoveCom
dup
invokespecial com/nd/android/u/contact/com/OapSecretLoveCom/<init>()V
areturn
.limit locals 1
.limit stack 2
.end method

.method public getOapTagCom()Lcom/nd/android/u/contact/com/OapTagCom;
new com/nd/android/u/contact/com/OapTagCom
dup
invokespecial com/nd/android/u/contact/com/OapTagCom/<init>()V
areturn
.limit locals 1
.limit stack 2
.end method

.method public getOapUnitCom()Lcom/nd/android/u/contact/com/OapUnitCom;
new com/nd/android/u/contact/com/OapUnitCom
dup
invokespecial com/nd/android/u/contact/com/OapUnitCom/<init>()V
areturn
.limit locals 1
.limit stack 2
.end method

.method public getOapUserCom()Lcom/nd/android/u/contact/com/OapUserCom;
new com/nd/android/u/contact/com/OapUserCom
dup
invokespecial com/nd/android/u/contact/com/OapUserCom/<init>()V
areturn
.limit locals 1
.limit stack 2
.end method

.method public getSeniorSystemCom()Lcom/nd/android/u/contact/com/OapSeniorSystemCom;
new com/nd/android/u/contact/com/OapSeniorSystemCom
dup
invokespecial com/nd/android/u/contact/com/OapSeniorSystemCom/<init>()V
areturn
.limit locals 1
.limit stack 2
.end method
