.bytecode 50.0
.class synchronized com/android/u/weibo/flower/ui/activity/SendFlowerManagerActivity$1
.super android/os/Handler
.enclosing method com/android/u/weibo/flower/ui/activity/SendFlowerManagerActivity
.inner class inner com/android/u/weibo/flower/ui/activity/SendFlowerManagerActivity$1

.field final synthetic 'this$0' Lcom/android/u/weibo/flower/ui/activity/SendFlowerManagerActivity;

.method <init>(Lcom/android/u/weibo/flower/ui/activity/SendFlowerManagerActivity;)V
aload 0
aload 1
putfield com/android/u/weibo/flower/ui/activity/SendFlowerManagerActivity$1/this$0 Lcom/android/u/weibo/flower/ui/activity/SendFlowerManagerActivity;
aload 0
invokespecial android/os/Handler/<init>()V
return
.limit locals 2
.limit stack 2
.end method

.method public handleMessage(Landroid/os/Message;)V
aload 1
getfield android/os/Message/what I
lookupswitch
0 : L0
1 : L1
2 : L2
99 : L3
200 : L4
300 : L5
default : L6
L6:
return
L0:
aload 0
getfield com/android/u/weibo/flower/ui/activity/SendFlowerManagerActivity$1/this$0 Lcom/android/u/weibo/flower/ui/activity/SendFlowerManagerActivity;
invokestatic com/android/u/weibo/flower/ui/activity/SendFlowerManagerActivity/access$000(Lcom/android/u/weibo/flower/ui/activity/SendFlowerManagerActivity;)Lcom/android/u/weibo/flower/ui/widget/SendFlowerToMeView;
ifnull L7
aload 0
getfield com/android/u/weibo/flower/ui/activity/SendFlowerManagerActivity$1/this$0 Lcom/android/u/weibo/flower/ui/activity/SendFlowerManagerActivity;
invokestatic com/android/u/weibo/flower/ui/activity/SendFlowerManagerActivity/access$000(Lcom/android/u/weibo/flower/ui/activity/SendFlowerManagerActivity;)Lcom/android/u/weibo/flower/ui/widget/SendFlowerToMeView;
invokevirtual com/android/u/weibo/flower/ui/widget/SendFlowerToMeView/requestFocus()Z
pop
L7:
aload 0
getfield com/android/u/weibo/flower/ui/activity/SendFlowerManagerActivity$1/this$0 Lcom/android/u/weibo/flower/ui/activity/SendFlowerManagerActivity;
iconst_0
invokestatic com/android/u/weibo/flower/ui/activity/SendFlowerManagerActivity/access$100(Lcom/android/u/weibo/flower/ui/activity/SendFlowerManagerActivity;I)V
return
L1:
aload 0
getfield com/android/u/weibo/flower/ui/activity/SendFlowerManagerActivity$1/this$0 Lcom/android/u/weibo/flower/ui/activity/SendFlowerManagerActivity;
invokestatic com/android/u/weibo/flower/ui/activity/SendFlowerManagerActivity/access$200(Lcom/android/u/weibo/flower/ui/activity/SendFlowerManagerActivity;)Lcom/android/u/weibo/flower/ui/widget/TopRankListByTimeView;
ifnull L8
aload 0
getfield com/android/u/weibo/flower/ui/activity/SendFlowerManagerActivity$1/this$0 Lcom/android/u/weibo/flower/ui/activity/SendFlowerManagerActivity;
invokestatic com/android/u/weibo/flower/ui/activity/SendFlowerManagerActivity/access$200(Lcom/android/u/weibo/flower/ui/activity/SendFlowerManagerActivity;)Lcom/android/u/weibo/flower/ui/widget/TopRankListByTimeView;
invokevirtual com/android/u/weibo/flower/ui/widget/TopRankListByTimeView/requestFocus()Z
pop
L8:
aload 0
getfield com/android/u/weibo/flower/ui/activity/SendFlowerManagerActivity$1/this$0 Lcom/android/u/weibo/flower/ui/activity/SendFlowerManagerActivity;
bipush 8
invokestatic com/android/u/weibo/flower/ui/activity/SendFlowerManagerActivity/access$300(Lcom/android/u/weibo/flower/ui/activity/SendFlowerManagerActivity;I)V
return
L2:
aload 0
getfield com/android/u/weibo/flower/ui/activity/SendFlowerManagerActivity$1/this$0 Lcom/android/u/weibo/flower/ui/activity/SendFlowerManagerActivity;
bipush 8
invokestatic com/android/u/weibo/flower/ui/activity/SendFlowerManagerActivity/access$400(Lcom/android/u/weibo/flower/ui/activity/SendFlowerManagerActivity;I)V
return
L3:
aload 0
getfield com/android/u/weibo/flower/ui/activity/SendFlowerManagerActivity$1/this$0 Lcom/android/u/weibo/flower/ui/activity/SendFlowerManagerActivity;
invokestatic com/android/u/weibo/flower/ui/activity/SendFlowerManagerActivity/access$500(Lcom/android/u/weibo/flower/ui/activity/SendFlowerManagerActivity;)Lcom/common/android/ui/viewPagerIndicator/TitlePageIndicatorExl;
invokevirtual com/common/android/ui/viewPagerIndicator/TitlePageIndicatorExl/postInvalidate()V
return
L4:
aload 0
getfield com/android/u/weibo/flower/ui/activity/SendFlowerManagerActivity$1/this$0 Lcom/android/u/weibo/flower/ui/activity/SendFlowerManagerActivity;
getfield com/android/u/weibo/flower/ui/activity/SendFlowerManagerActivity/waterfallAdapter Lcom/android/u/weibo/flower/ui/adapter/SendFlowerPagerAdapter;
iconst_0
aload 1
getfield android/os/Message/arg1 I
invokevirtual com/android/u/weibo/flower/ui/adapter/SendFlowerPagerAdapter/setCount(II)V
aload 0
getfield com/android/u/weibo/flower/ui/activity/SendFlowerManagerActivity$1/this$0 Lcom/android/u/weibo/flower/ui/activity/SendFlowerManagerActivity;
invokestatic com/android/u/weibo/flower/ui/activity/SendFlowerManagerActivity/access$500(Lcom/android/u/weibo/flower/ui/activity/SendFlowerManagerActivity;)Lcom/common/android/ui/viewPagerIndicator/TitlePageIndicatorExl;
invokevirtual com/common/android/ui/viewPagerIndicator/TitlePageIndicatorExl/postInvalidate()V
return
L5:
aload 0
getfield com/android/u/weibo/flower/ui/activity/SendFlowerManagerActivity$1/this$0 Lcom/android/u/weibo/flower/ui/activity/SendFlowerManagerActivity;
getfield com/android/u/weibo/flower/ui/activity/SendFlowerManagerActivity/waterfallAdapter Lcom/android/u/weibo/flower/ui/adapter/SendFlowerPagerAdapter;
iconst_1
aload 1
getfield android/os/Message/arg1 I
invokevirtual com/android/u/weibo/flower/ui/adapter/SendFlowerPagerAdapter/setCount(II)V
aload 0
getfield com/android/u/weibo/flower/ui/activity/SendFlowerManagerActivity$1/this$0 Lcom/android/u/weibo/flower/ui/activity/SendFlowerManagerActivity;
invokestatic com/android/u/weibo/flower/ui/activity/SendFlowerManagerActivity/access$500(Lcom/android/u/weibo/flower/ui/activity/SendFlowerManagerActivity;)Lcom/common/android/ui/viewPagerIndicator/TitlePageIndicatorExl;
invokevirtual com/common/android/ui/viewPagerIndicator/TitlePageIndicatorExl/postInvalidate()V
return
.limit locals 2
.limit stack 3
.end method
