.bytecode 50.0
.class synchronized com/android/u/weibo/weibo/controller/Manager$9$1
.super com/android/u/weibo/weibo/controller/NdPostOrReTweetListener
.enclosing method com/android/u/weibo/weibo/controller/Manager$9/run()V
.inner class inner com/android/u/weibo/weibo/controller/Manager$9
.inner class inner com/android/u/weibo/weibo/controller/Manager$9$1

.field final synthetic 'this$1' Lcom/android/u/weibo/weibo/controller/Manager$9;

.method <init>(Lcom/android/u/weibo/weibo/controller/Manager$9;)V
aload 0
aload 1
putfield com/android/u/weibo/weibo/controller/Manager$9$1/this$1 Lcom/android/u/weibo/weibo/controller/Manager$9;
aload 0
invokespecial com/android/u/weibo/weibo/controller/NdPostOrReTweetListener/<init>()V
return
.limit locals 2
.limit stack 2
.end method

.method public onComplete(ILjava/lang/Object;Ljava/lang/String;J)V
.catch com/android/u/weibo/weibo/controller/WeiBoException from L0 to L1 using L2
invokestatic java/lang/Thread/interrupted()Z
ifeq L3
aload 0
getfield com/android/u/weibo/weibo/controller/Manager$9$1/this$1 Lcom/android/u/weibo/weibo/controller/Manager$9;
getfield com/android/u/weibo/weibo/controller/Manager$9/val$listener Lcom/android/u/weibo/weibo/controller/NdPostOrReTweetListener;
ifnull L4
aload 0
getfield com/android/u/weibo/weibo/controller/Manager$9$1/this$1 Lcom/android/u/weibo/weibo/controller/Manager$9;
getfield com/android/u/weibo/weibo/controller/Manager$9/val$listener Lcom/android/u/weibo/weibo/controller/NdPostOrReTweetListener;
sipush 1004
new com/android/u/weibo/weibo/controller/NdWeiboException
dup
aload 0
getfield com/android/u/weibo/weibo/controller/Manager$9$1/this$1 Lcom/android/u/weibo/weibo/controller/Manager$9;
getfield com/android/u/weibo/weibo/controller/Manager$9/this$0 Lcom/android/u/weibo/weibo/controller/Manager;
invokestatic com/android/u/weibo/weibo/controller/Manager/access$300(Lcom/android/u/weibo/weibo/controller/Manager;)Landroid/content/Context;
getstatic com/android/u/weibo/R$string/thread_interrupted_toast I
invokevirtual android/content/Context/getString(I)Ljava/lang/String;
invokespecial com/android/u/weibo/weibo/controller/NdWeiboException/<init>(Ljava/lang/String;)V
lload 4
invokevirtual com/android/u/weibo/weibo/controller/NdPostOrReTweetListener/onError(ILcom/android/u/weibo/weibo/controller/NdWeiboException;J)V
L4:
return
L3:
aload 2
checkcast com/android/u/weibo/weibo/business/bean/TopicInfo
astore 2
L0:
aload 0
getfield com/android/u/weibo/weibo/controller/Manager$9$1/this$1 Lcom/android/u/weibo/weibo/controller/Manager$9;
getfield com/android/u/weibo/weibo/controller/Manager$9/this$0 Lcom/android/u/weibo/weibo/controller/Manager;
invokestatic com/android/u/weibo/weibo/controller/Manager/access$300(Lcom/android/u/weibo/weibo/controller/Manager;)Landroid/content/Context;
invokestatic com/android/u/weibo/weibo/controller/NdWeiboManager/getInstance(Landroid/content/Context;)Lcom/android/u/weibo/weibo/controller/NdWeiboManager;
aload 0
getfield com/android/u/weibo/weibo/controller/Manager$9$1/this$1 Lcom/android/u/weibo/weibo/controller/Manager$9;
getfield com/android/u/weibo/weibo/controller/Manager$9/val$category Ljava/lang/String;
aload 0
getfield com/android/u/weibo/weibo/controller/Manager$9$1/this$1 Lcom/android/u/weibo/weibo/controller/Manager$9;
getfield com/android/u/weibo/weibo/controller/Manager$9/val$content Ljava/lang/String;
fconst_0
fconst_0
aload 0
getfield com/android/u/weibo/weibo/controller/Manager$9$1/this$1 Lcom/android/u/weibo/weibo/controller/Manager$9;
getfield com/android/u/weibo/weibo/controller/Manager$9/val$files Ljava/util/ArrayList;
aload 0
getfield com/android/u/weibo/weibo/controller/Manager$9$1/this$1 Lcom/android/u/weibo/weibo/controller/Manager$9;
getfield com/android/u/weibo/weibo/controller/Manager$9/val$is360Pic Z
aload 2
getfield com/android/u/weibo/weibo/business/bean/TopicInfo/tid J
invokevirtual com/android/u/weibo/weibo/controller/NdWeiboManager/postTopicInfo(Ljava/lang/String;Ljava/lang/String;FFLjava/util/ArrayList;ZJ)Lcom/android/u/weibo/weibo/business/bean/TopicInfo;
astore 2
L1:
invokestatic java/lang/Thread/interrupted()Z
ifeq L5
aload 0
getfield com/android/u/weibo/weibo/controller/Manager$9$1/this$1 Lcom/android/u/weibo/weibo/controller/Manager$9;
getfield com/android/u/weibo/weibo/controller/Manager$9/val$listener Lcom/android/u/weibo/weibo/controller/NdPostOrReTweetListener;
ifnull L4
aload 0
getfield com/android/u/weibo/weibo/controller/Manager$9$1/this$1 Lcom/android/u/weibo/weibo/controller/Manager$9;
getfield com/android/u/weibo/weibo/controller/Manager$9/val$listener Lcom/android/u/weibo/weibo/controller/NdPostOrReTweetListener;
sipush 1004
new com/android/u/weibo/weibo/controller/NdWeiboException
dup
aload 0
getfield com/android/u/weibo/weibo/controller/Manager$9$1/this$1 Lcom/android/u/weibo/weibo/controller/Manager$9;
getfield com/android/u/weibo/weibo/controller/Manager$9/this$0 Lcom/android/u/weibo/weibo/controller/Manager;
invokestatic com/android/u/weibo/weibo/controller/Manager/access$300(Lcom/android/u/weibo/weibo/controller/Manager;)Landroid/content/Context;
getstatic com/android/u/weibo/R$string/thread_interrupted_toast I
invokevirtual android/content/Context/getString(I)Ljava/lang/String;
invokespecial com/android/u/weibo/weibo/controller/NdWeiboException/<init>(Ljava/lang/String;)V
lload 4
invokevirtual com/android/u/weibo/weibo/controller/NdPostOrReTweetListener/onError(ILcom/android/u/weibo/weibo/controller/NdWeiboException;J)V
return
L2:
astore 2
aload 2
invokevirtual com/android/u/weibo/weibo/controller/WeiBoException/printStackTrace()V
aload 0
getfield com/android/u/weibo/weibo/controller/Manager$9$1/this$1 Lcom/android/u/weibo/weibo/controller/Manager$9;
getfield com/android/u/weibo/weibo/controller/Manager$9/val$listener Lcom/android/u/weibo/weibo/controller/NdPostOrReTweetListener;
sipush 1004
new com/android/u/weibo/weibo/controller/NdWeiboException
dup
aload 2
invokevirtual com/android/u/weibo/weibo/controller/WeiBoException/getMessage()Ljava/lang/String;
invokespecial com/android/u/weibo/weibo/controller/NdWeiboException/<init>(Ljava/lang/String;)V
lload 4
invokevirtual com/android/u/weibo/weibo/controller/NdPostOrReTweetListener/onError(ILcom/android/u/weibo/weibo/controller/NdWeiboException;J)V
return
L5:
aload 2
ifnull L6
aload 0
getfield com/android/u/weibo/weibo/controller/Manager$9$1/this$1 Lcom/android/u/weibo/weibo/controller/Manager$9;
getfield com/android/u/weibo/weibo/controller/Manager$9/val$listener Lcom/android/u/weibo/weibo/controller/NdPostOrReTweetListener;
sipush 1004
aload 2
aconst_null
lload 4
invokevirtual com/android/u/weibo/weibo/controller/NdPostOrReTweetListener/onComplete(ILjava/lang/Object;Ljava/lang/String;J)V
return
L6:
aload 0
getfield com/android/u/weibo/weibo/controller/Manager$9$1/this$1 Lcom/android/u/weibo/weibo/controller/Manager$9;
getfield com/android/u/weibo/weibo/controller/Manager$9/val$listener Lcom/android/u/weibo/weibo/controller/NdPostOrReTweetListener;
sipush 1004
new com/android/u/weibo/weibo/controller/NdWeiboException
dup
invokespecial com/android/u/weibo/weibo/controller/NdWeiboException/<init>()V
lload 4
invokevirtual com/android/u/weibo/weibo/controller/NdPostOrReTweetListener/onError(ILcom/android/u/weibo/weibo/controller/NdWeiboException;J)V
return
.limit locals 6
.limit stack 9
.end method

.method public onError(ILcom/android/u/weibo/weibo/controller/NdWeiboException;J)V
.catch com/android/u/weibo/weibo/controller/WeiBoException from L0 to L1 using L2
.catch org/json/JSONException from L3 to L4 using L5
L0:
aload 0
getfield com/android/u/weibo/weibo/controller/Manager$9$1/this$1 Lcom/android/u/weibo/weibo/controller/Manager$9;
getfield com/android/u/weibo/weibo/controller/Manager$9/this$0 Lcom/android/u/weibo/weibo/controller/Manager;
invokestatic com/android/u/weibo/weibo/controller/Manager/access$300(Lcom/android/u/weibo/weibo/controller/Manager;)Landroid/content/Context;
invokestatic com/android/u/weibo/weibo/controller/NdWeiboManager/getInstance(Landroid/content/Context;)Lcom/android/u/weibo/weibo/controller/NdWeiboManager;
aload 0
getfield com/android/u/weibo/weibo/controller/Manager$9$1/this$1 Lcom/android/u/weibo/weibo/controller/Manager$9;
getfield com/android/u/weibo/weibo/controller/Manager$9/val$category Ljava/lang/String;
aload 0
getfield com/android/u/weibo/weibo/controller/Manager$9$1/this$1 Lcom/android/u/weibo/weibo/controller/Manager$9;
getfield com/android/u/weibo/weibo/controller/Manager$9/val$content Ljava/lang/String;
fconst_0
fconst_0
aload 0
getfield com/android/u/weibo/weibo/controller/Manager$9$1/this$1 Lcom/android/u/weibo/weibo/controller/Manager$9;
getfield com/android/u/weibo/weibo/controller/Manager$9/val$files Ljava/util/ArrayList;
aload 0
getfield com/android/u/weibo/weibo/controller/Manager$9$1/this$1 Lcom/android/u/weibo/weibo/controller/Manager$9;
getfield com/android/u/weibo/weibo/controller/Manager$9/val$is360Pic Z
lconst_0
invokevirtual com/android/u/weibo/weibo/controller/NdWeiboManager/postTopicInfo(Ljava/lang/String;Ljava/lang/String;FFLjava/util/ArrayList;ZJ)Lcom/android/u/weibo/weibo/business/bean/TopicInfo;
astore 5
L1:
invokestatic java/lang/Thread/interrupted()Z
ifeq L6
aload 0
getfield com/android/u/weibo/weibo/controller/Manager$9$1/this$1 Lcom/android/u/weibo/weibo/controller/Manager$9;
getfield com/android/u/weibo/weibo/controller/Manager$9/val$listener Lcom/android/u/weibo/weibo/controller/NdPostOrReTweetListener;
ifnull L7
aload 0
getfield com/android/u/weibo/weibo/controller/Manager$9$1/this$1 Lcom/android/u/weibo/weibo/controller/Manager$9;
getfield com/android/u/weibo/weibo/controller/Manager$9/val$listener Lcom/android/u/weibo/weibo/controller/NdPostOrReTweetListener;
sipush 1004
new com/android/u/weibo/weibo/controller/NdWeiboException
dup
aload 0
getfield com/android/u/weibo/weibo/controller/Manager$9$1/this$1 Lcom/android/u/weibo/weibo/controller/Manager$9;
getfield com/android/u/weibo/weibo/controller/Manager$9/this$0 Lcom/android/u/weibo/weibo/controller/Manager;
invokestatic com/android/u/weibo/weibo/controller/Manager/access$300(Lcom/android/u/weibo/weibo/controller/Manager;)Landroid/content/Context;
getstatic com/android/u/weibo/R$string/thread_interrupted_toast I
invokevirtual android/content/Context/getString(I)Ljava/lang/String;
invokespecial com/android/u/weibo/weibo/controller/NdWeiboException/<init>(Ljava/lang/String;)V
lload 3
invokevirtual com/android/u/weibo/weibo/controller/NdPostOrReTweetListener/onError(ILcom/android/u/weibo/weibo/controller/NdWeiboException;J)V
L7:
return
L2:
astore 5
aload 5
invokevirtual com/android/u/weibo/weibo/controller/WeiBoException/printStackTrace()V
aconst_null
astore 5
goto L1
L6:
aload 2
invokevirtual com/android/u/weibo/weibo/controller/NdWeiboException/getMessage()Ljava/lang/String;
astore 2
aload 2
invokestatic android/text/TextUtils/isEmpty(Ljava/lang/CharSequence;)Z
ifeq L3
new com/android/u/weibo/weibo/controller/NdWeiboException
dup
new java/lang/StringBuilder
dup
invokespecial java/lang/StringBuilder/<init>()V
aload 0
getfield com/android/u/weibo/weibo/controller/Manager$9$1/this$1 Lcom/android/u/weibo/weibo/controller/Manager$9;
getfield com/android/u/weibo/weibo/controller/Manager$9/this$0 Lcom/android/u/weibo/weibo/controller/Manager;
invokestatic com/android/u/weibo/weibo/controller/Manager/access$300(Lcom/android/u/weibo/weibo/controller/Manager;)Landroid/content/Context;
getstatic com/android/u/weibo/R$string/post_sina_weibo_fail_msg I
invokevirtual android/content/Context/getString(I)Ljava/lang/String;
invokevirtual java/lang/StringBuilder/append(Ljava/lang/String;)Ljava/lang/StringBuilder;
ldc "!"
invokevirtual java/lang/StringBuilder/append(Ljava/lang/String;)Ljava/lang/StringBuilder;
invokevirtual java/lang/StringBuilder/toString()Ljava/lang/String;
invokespecial com/android/u/weibo/weibo/controller/NdWeiboException/<init>(Ljava/lang/String;)V
astore 2
L8:
aload 5
ifnull L9
new java/lang/StringBuilder
dup
invokespecial java/lang/StringBuilder/<init>()V
aload 2
invokevirtual com/android/u/weibo/weibo/controller/NdWeiboException/getMessage()Ljava/lang/String;
invokevirtual java/lang/StringBuilder/append(Ljava/lang/String;)Ljava/lang/StringBuilder;
aload 0
getfield com/android/u/weibo/weibo/controller/Manager$9$1/this$1 Lcom/android/u/weibo/weibo/controller/Manager$9;
getfield com/android/u/weibo/weibo/controller/Manager$9/this$0 Lcom/android/u/weibo/weibo/controller/Manager;
invokestatic com/android/u/weibo/weibo/controller/Manager/access$300(Lcom/android/u/weibo/weibo/controller/Manager;)Landroid/content/Context;
invokevirtual android/content/Context/getResources()Landroid/content/res/Resources;
getstatic com/android/u/weibo/R$string/send_public_weibo_success I
invokevirtual android/content/res/Resources/getString(I)Ljava/lang/String;
invokevirtual java/lang/StringBuilder/append(Ljava/lang/String;)Ljava/lang/StringBuilder;
invokevirtual java/lang/StringBuilder/toString()Ljava/lang/String;
astore 2
aload 0
getfield com/android/u/weibo/weibo/controller/Manager$9$1/this$1 Lcom/android/u/weibo/weibo/controller/Manager$9;
getfield com/android/u/weibo/weibo/controller/Manager$9/val$listener Lcom/android/u/weibo/weibo/controller/NdPostOrReTweetListener;
sipush 1004
aload 5
aload 2
lload 3
invokevirtual com/android/u/weibo/weibo/controller/NdPostOrReTweetListener/onComplete(ILjava/lang/Object;Ljava/lang/String;J)V
return
L3:
new org/json/JSONObject
dup
aload 2
invokespecial org/json/JSONObject/<init>(Ljava/lang/String;)V
ldc "error"
invokevirtual org/json/JSONObject/optString(Ljava/lang/String;)Ljava/lang/String;
astore 6
L4:
aload 6
astore 2
L10:
aload 2
invokestatic android/text/TextUtils/isEmpty(Ljava/lang/CharSequence;)Z
ifeq L11
new com/android/u/weibo/weibo/controller/NdWeiboException
dup
new java/lang/StringBuilder
dup
invokespecial java/lang/StringBuilder/<init>()V
aload 0
getfield com/android/u/weibo/weibo/controller/Manager$9$1/this$1 Lcom/android/u/weibo/weibo/controller/Manager$9;
getfield com/android/u/weibo/weibo/controller/Manager$9/this$0 Lcom/android/u/weibo/weibo/controller/Manager;
invokestatic com/android/u/weibo/weibo/controller/Manager/access$300(Lcom/android/u/weibo/weibo/controller/Manager;)Landroid/content/Context;
getstatic com/android/u/weibo/R$string/post_sina_weibo_fail_msg I
invokevirtual android/content/Context/getString(I)Ljava/lang/String;
invokevirtual java/lang/StringBuilder/append(Ljava/lang/String;)Ljava/lang/StringBuilder;
ldc "!"
invokevirtual java/lang/StringBuilder/append(Ljava/lang/String;)Ljava/lang/StringBuilder;
invokevirtual java/lang/StringBuilder/toString()Ljava/lang/String;
invokespecial com/android/u/weibo/weibo/controller/NdWeiboException/<init>(Ljava/lang/String;)V
astore 2
goto L8
L5:
astore 6
aload 6
invokevirtual org/json/JSONException/printStackTrace()V
goto L10
L11:
new com/android/u/weibo/weibo/controller/NdWeiboException
dup
new java/lang/StringBuilder
dup
invokespecial java/lang/StringBuilder/<init>()V
aload 0
getfield com/android/u/weibo/weibo/controller/Manager$9$1/this$1 Lcom/android/u/weibo/weibo/controller/Manager$9;
getfield com/android/u/weibo/weibo/controller/Manager$9/this$0 Lcom/android/u/weibo/weibo/controller/Manager;
invokestatic com/android/u/weibo/weibo/controller/Manager/access$300(Lcom/android/u/weibo/weibo/controller/Manager;)Landroid/content/Context;
getstatic com/android/u/weibo/R$string/post_sina_weibo_fail_msg I
invokevirtual android/content/Context/getString(I)Ljava/lang/String;
invokevirtual java/lang/StringBuilder/append(Ljava/lang/String;)Ljava/lang/StringBuilder;
ldc ":"
invokevirtual java/lang/StringBuilder/append(Ljava/lang/String;)Ljava/lang/StringBuilder;
aload 2
invokevirtual java/lang/StringBuilder/append(Ljava/lang/String;)Ljava/lang/StringBuilder;
invokevirtual java/lang/StringBuilder/toString()Ljava/lang/String;
invokespecial com/android/u/weibo/weibo/controller/NdWeiboException/<init>(Ljava/lang/String;)V
astore 2
goto L8
L9:
aload 0
getfield com/android/u/weibo/weibo/controller/Manager$9$1/this$1 Lcom/android/u/weibo/weibo/controller/Manager$9;
getfield com/android/u/weibo/weibo/controller/Manager$9/val$listener Lcom/android/u/weibo/weibo/controller/NdPostOrReTweetListener;
sipush 1004
aload 2
lload 3
invokevirtual com/android/u/weibo/weibo/controller/NdPostOrReTweetListener/onError(ILcom/android/u/weibo/weibo/controller/NdWeiboException;J)V
return
.limit locals 7
.limit stack 9
.end method
