.bytecode 50.0
.class synchronized com/android/u/weibo/weibo/controller/Manager$21
.super com/common/android/utils/concurrent/NdAbstractTask
.enclosing method com/android/u/weibo/weibo/controller/Manager/replyComment(JJZLjava/lang/String;IIIJLcom/android/u/weibo/weibo/controller/NdPostOrReTweetListener;)V
.inner class inner com/android/u/weibo/weibo/controller/Manager$21

.field final synthetic 'this$0' Lcom/android/u/weibo/weibo/controller/Manager;

.field final synthetic 'val$cid' J

.field final synthetic 'val$comment' Ljava/lang/String;

.field final synthetic 'val$listener' Lcom/android/u/weibo/weibo/controller/NdPostOrReTweetListener;

.field final synthetic 'val$localCreateAt' J

.field final synthetic 'val$reflag' I

.field final synthetic 'val$relay' I

.field final synthetic 'val$tid' J

.field final synthetic 'val$without_mention' I

.method <init>(Lcom/android/u/weibo/weibo/controller/Manager;JJLjava/lang/String;IIILcom/android/u/weibo/weibo/controller/NdPostOrReTweetListener;J)V
aload 0
aload 1
putfield com/android/u/weibo/weibo/controller/Manager$21/this$0 Lcom/android/u/weibo/weibo/controller/Manager;
aload 0
lload 2
putfield com/android/u/weibo/weibo/controller/Manager$21/val$tid J
aload 0
lload 4
putfield com/android/u/weibo/weibo/controller/Manager$21/val$cid J
aload 0
aload 6
putfield com/android/u/weibo/weibo/controller/Manager$21/val$comment Ljava/lang/String;
aload 0
iload 7
putfield com/android/u/weibo/weibo/controller/Manager$21/val$relay I
aload 0
iload 8
putfield com/android/u/weibo/weibo/controller/Manager$21/val$reflag I
aload 0
iload 9
putfield com/android/u/weibo/weibo/controller/Manager$21/val$without_mention I
aload 0
aload 10
putfield com/android/u/weibo/weibo/controller/Manager$21/val$listener Lcom/android/u/weibo/weibo/controller/NdPostOrReTweetListener;
aload 0
lload 11
putfield com/android/u/weibo/weibo/controller/Manager$21/val$localCreateAt J
aload 0
invokespecial com/common/android/utils/concurrent/NdAbstractTask/<init>()V
return
.limit locals 13
.limit stack 3
.end method

.method public run()V
.catch com/android/u/weibo/weibo/controller/WeiBoException from L0 to L1 using L2
L0:
aload 0
getfield com/android/u/weibo/weibo/controller/Manager$21/this$0 Lcom/android/u/weibo/weibo/controller/Manager;
invokestatic com/android/u/weibo/weibo/controller/Manager/access$300(Lcom/android/u/weibo/weibo/controller/Manager;)Landroid/content/Context;
invokestatic com/android/u/weibo/weibo/controller/NdWeiboManager/getInstance(Landroid/content/Context;)Lcom/android/u/weibo/weibo/controller/NdWeiboManager;
aload 0
getfield com/android/u/weibo/weibo/controller/Manager$21/val$tid J
aload 0
getfield com/android/u/weibo/weibo/controller/Manager$21/val$cid J
aload 0
getfield com/android/u/weibo/weibo/controller/Manager$21/val$comment Ljava/lang/String;
aload 0
getfield com/android/u/weibo/weibo/controller/Manager$21/val$relay I
aload 0
getfield com/android/u/weibo/weibo/controller/Manager$21/val$reflag I
aload 0
getfield com/android/u/weibo/weibo/controller/Manager$21/val$without_mention I
invokevirtual com/android/u/weibo/weibo/controller/NdWeiboManager/replyComment(JJLjava/lang/String;III)Lcom/android/u/weibo/weibo/business/bean/ReplyInfo;
astore 1
L1:
invokestatic java/lang/Thread/interrupted()Z
ifeq L3
aload 0
getfield com/android/u/weibo/weibo/controller/Manager$21/val$listener Lcom/android/u/weibo/weibo/controller/NdPostOrReTweetListener;
ifnull L4
aload 0
getfield com/android/u/weibo/weibo/controller/Manager$21/val$listener Lcom/android/u/weibo/weibo/controller/NdPostOrReTweetListener;
sipush 2004
new com/android/u/weibo/weibo/controller/NdWeiboException
dup
aload 0
getfield com/android/u/weibo/weibo/controller/Manager$21/this$0 Lcom/android/u/weibo/weibo/controller/Manager;
invokestatic com/android/u/weibo/weibo/controller/Manager/access$300(Lcom/android/u/weibo/weibo/controller/Manager;)Landroid/content/Context;
getstatic com/android/u/weibo/R$string/thread_interrupted_toast I
invokevirtual android/content/Context/getString(I)Ljava/lang/String;
invokespecial com/android/u/weibo/weibo/controller/NdWeiboException/<init>(Ljava/lang/String;)V
invokevirtual com/android/u/weibo/weibo/controller/NdPostOrReTweetListener/onError(ILcom/android/u/weibo/weibo/controller/NdWeiboException;)V
L4:
return
L2:
astore 1
aload 1
invokevirtual com/android/u/weibo/weibo/controller/WeiBoException/printStackTrace()V
aconst_null
astore 1
goto L1
L3:
aload 1
ifnull L5
aload 0
getfield com/android/u/weibo/weibo/controller/Manager$21/val$listener Lcom/android/u/weibo/weibo/controller/NdPostOrReTweetListener;
sipush 2004
aload 1
aconst_null
aload 0
getfield com/android/u/weibo/weibo/controller/Manager$21/val$localCreateAt J
invokevirtual com/android/u/weibo/weibo/controller/NdPostOrReTweetListener/onComplete(ILjava/lang/Object;Ljava/lang/String;J)V
return
L5:
aload 0
getfield com/android/u/weibo/weibo/controller/Manager$21/val$listener Lcom/android/u/weibo/weibo/controller/NdPostOrReTweetListener;
sipush 2004
new com/android/u/weibo/weibo/controller/NdWeiboException
dup
invokespecial com/android/u/weibo/weibo/controller/NdWeiboException/<init>()V
aload 0
getfield com/android/u/weibo/weibo/controller/Manager$21/val$localCreateAt J
invokevirtual com/android/u/weibo/weibo/controller/NdPostOrReTweetListener/onError(ILcom/android/u/weibo/weibo/controller/NdWeiboException;J)V
return
.limit locals 2
.limit stack 9
.end method
