.bytecode 50.0
.class synchronized cmb/pb/ui/b
.super java/lang/Object
.implements android/view/View$OnClickListener

.field final synthetic 'a' Lcmb/pb/ui/PBKeyboardActivity;

.method <init>(Lcmb/pb/ui/PBKeyboardActivity;)V
aload 0
aload 1
putfield cmb/pb/ui/b/a Lcmb/pb/ui/PBKeyboardActivity;
aload 0
invokespecial java/lang/Object/<init>()V
return
.limit locals 2
.limit stack 2
.end method

.method public onClick(Landroid/view/View;)V
.catch java/lang/Exception from L0 to L1 using L2
aload 0
getfield cmb/pb/ui/b/a Lcmb/pb/ui/PBKeyboardActivity;
invokestatic cmb/pb/ui/PBKeyboardActivity/b(Lcmb/pb/ui/PBKeyboardActivity;)Landroid/widget/TextView;
ifnull L3
L0:
aload 0
getfield cmb/pb/ui/b/a Lcmb/pb/ui/PBKeyboardActivity;
invokestatic cmb/pb/ui/PBKeyboardActivity/c(Lcmb/pb/ui/PBKeyboardActivity;)Landroid/app/Activity;
ldc "string"
ldc "cmbkb_finish_id"
invokestatic cmb/pb/util/i/a(Landroid/content/Context;Ljava/lang/String;Ljava/lang/String;)I
istore 2
aload 0
getfield cmb/pb/ui/b/a Lcmb/pb/ui/PBKeyboardActivity;
invokevirtual cmb/pb/ui/PBKeyboardActivity/getResources()Landroid/content/res/Resources;
iload 2
invokevirtual android/content/res/Resources/getString(I)Ljava/lang/String;
astore 1
aload 0
getfield cmb/pb/ui/b/a Lcmb/pb/ui/PBKeyboardActivity;
invokestatic cmb/pb/ui/PBKeyboardActivity/b(Lcmb/pb/ui/PBKeyboardActivity;)Landroid/widget/TextView;
aload 1
invokevirtual android/widget/TextView/setText(Ljava/lang/CharSequence;)V
L1:
aload 0
getfield cmb/pb/ui/b/a Lcmb/pb/ui/PBKeyboardActivity;
invokestatic cmb/pb/ui/PBKeyboardActivity/b(Lcmb/pb/ui/PBKeyboardActivity;)Landroid/widget/TextView;
aload 0
getfield cmb/pb/ui/b/a Lcmb/pb/ui/PBKeyboardActivity;
invokestatic cmb/pb/ui/PBKeyboardActivity/d(Lcmb/pb/ui/PBKeyboardActivity;)Landroid/view/View$OnClickListener;
invokevirtual android/widget/TextView/setOnClickListener(Landroid/view/View$OnClickListener;)V
aload 0
getfield cmb/pb/ui/b/a Lcmb/pb/ui/PBKeyboardActivity;
invokestatic cmb/pb/ui/PBKeyboardActivity/e(Lcmb/pb/ui/PBKeyboardActivity;)Landroid/inputmethodservice/KeyboardView;
aload 0
getfield cmb/pb/ui/b/a Lcmb/pb/ui/PBKeyboardActivity;
invokestatic cmb/pb/ui/PBKeyboardActivity/f(Lcmb/pb/ui/PBKeyboardActivity;)Landroid/inputmethodservice/Keyboard;
invokevirtual android/inputmethodservice/KeyboardView/setKeyboard(Landroid/inputmethodservice/Keyboard;)V
aload 0
getfield cmb/pb/ui/b/a Lcmb/pb/ui/PBKeyboardActivity;
getstatic cmb/pb/ui/f/f Lcmb/pb/ui/f;
invokestatic cmb/pb/ui/PBKeyboardActivity/a(Lcmb/pb/ui/PBKeyboardActivity;Lcmb/pb/ui/f;)V
L3:
return
L2:
astore 1
goto L1
.limit locals 3
.limit stack 3
.end method
