.bytecode 50.0
.class public synchronized com/product/android/business/service/BaseMsgBroadCastReceiver
.super android/content/BroadcastReceiver

.field private 'bundle' Landroid/os/Bundle;

.field private 'mCallBack' Lcom/product/android/business/service/ReceiveCallback;

.field private 'mContext' Landroid/content/Context;

.method public <init>(Lcom/product/android/business/service/ReceiveCallback;Landroid/content/Context;)V
aload 0
invokespecial android/content/BroadcastReceiver/<init>()V
aload 0
aload 2
putfield com/product/android/business/service/BaseMsgBroadCastReceiver/mContext Landroid/content/Context;
aload 0
aload 1
putfield com/product/android/business/service/BaseMsgBroadCastReceiver/mCallBack Lcom/product/android/business/service/ReceiveCallback;
return
.limit locals 3
.limit stack 2
.end method

.method public onReceive(Landroid/content/Context;Landroid/content/Intent;)V
aload 0
aload 2
invokevirtual android/content/Intent/getExtras()Landroid/os/Bundle;
putfield com/product/android/business/service/BaseMsgBroadCastReceiver/bundle Landroid/os/Bundle;
iconst_0
istore 3
aload 0
getfield com/product/android/business/service/BaseMsgBroadCastReceiver/bundle Landroid/os/Bundle;
ldc "cmd"
invokevirtual android/os/Bundle/containsKey(Ljava/lang/String;)Z
ifeq L0
aload 2
ldc "cmd"
iconst_0
invokevirtual android/content/Intent/getIntExtra(Ljava/lang/String;I)I
istore 3
L0:
iload 3
lookupswitch
16 : L1
31 : L2
33 : L3
39 : L4
51 : L5
53 : L6
89 : L7
119 : L8
635 : L9
2000 : L10
3011 : L11
5502 : L12
10003 : L13
11009 : L14
11011 : L15
12000 : L16
12200 : L17
12201 : L18
30010 : L19
30011 : L20
36864 : L21
49156 : L22
85674 : L23
131072 : L24
131074 : L25
131075 : L26
131076 : L27
131077 : L28
default : L29
L29:
return
L7:
aload 0
getfield com/product/android/business/service/BaseMsgBroadCastReceiver/mCallBack Lcom/product/android/business/service/ReceiveCallback;
ifnull L29
aload 0
getfield com/product/android/business/service/BaseMsgBroadCastReceiver/mCallBack Lcom/product/android/business/service/ReceiveCallback;
invokeinterface com/product/android/business/service/ReceiveCallback/handler_CMD_89()V 0
return
L17:
aload 0
getfield com/product/android/business/service/BaseMsgBroadCastReceiver/mCallBack Lcom/product/android/business/service/ReceiveCallback;
ifnull L29
aload 0
getfield com/product/android/business/service/BaseMsgBroadCastReceiver/mCallBack Lcom/product/android/business/service/ReceiveCallback;
invokeinterface com/product/android/business/service/ReceiveCallback/handler_CMD_SHOWLEFT()V 0
return
L18:
aload 0
getfield com/product/android/business/service/BaseMsgBroadCastReceiver/mCallBack Lcom/product/android/business/service/ReceiveCallback;
ifnull L29
aload 0
getfield com/product/android/business/service/BaseMsgBroadCastReceiver/mCallBack Lcom/product/android/business/service/ReceiveCallback;
invokeinterface com/product/android/business/service/ReceiveCallback/handler_CMD_SHOWRIGHT()V 0
return
L3:
aload 0
getfield com/product/android/business/service/BaseMsgBroadCastReceiver/mCallBack Lcom/product/android/business/service/ReceiveCallback;
ifnull L29
aload 0
getfield com/product/android/business/service/BaseMsgBroadCastReceiver/mCallBack Lcom/product/android/business/service/ReceiveCallback;
invokeinterface com/product/android/business/service/ReceiveCallback/handler_CMD_33()V 0
return
L21:
aload 0
getfield com/product/android/business/service/BaseMsgBroadCastReceiver/mCallBack Lcom/product/android/business/service/ReceiveCallback;
ifnull L29
aload 0
getfield com/product/android/business/service/BaseMsgBroadCastReceiver/mCallBack Lcom/product/android/business/service/ReceiveCallback;
invokeinterface com/product/android/business/service/ReceiveCallback/handler_CMD_36864()V 0
return
L8:
aload 0
getfield com/product/android/business/service/BaseMsgBroadCastReceiver/mCallBack Lcom/product/android/business/service/ReceiveCallback;
ifnull L29
aload 0
getfield com/product/android/business/service/BaseMsgBroadCastReceiver/mCallBack Lcom/product/android/business/service/ReceiveCallback;
invokeinterface com/product/android/business/service/ReceiveCallback/handler_CMD_119()V 0
return
L5:
aload 0
getfield com/product/android/business/service/BaseMsgBroadCastReceiver/mCallBack Lcom/product/android/business/service/ReceiveCallback;
ifnull L29
aload 0
getfield com/product/android/business/service/BaseMsgBroadCastReceiver/mCallBack Lcom/product/android/business/service/ReceiveCallback;
invokeinterface com/product/android/business/service/ReceiveCallback/handler_CMD_51()V 0
return
L6:
aload 0
getfield com/product/android/business/service/BaseMsgBroadCastReceiver/mCallBack Lcom/product/android/business/service/ReceiveCallback;
ifnull L29
aload 0
getfield com/product/android/business/service/BaseMsgBroadCastReceiver/mCallBack Lcom/product/android/business/service/ReceiveCallback;
invokeinterface com/product/android/business/service/ReceiveCallback/handler_CMD_53()V 0
return
L12:
aload 0
getfield com/product/android/business/service/BaseMsgBroadCastReceiver/mCallBack Lcom/product/android/business/service/ReceiveCallback;
ifnull L29
aload 0
getfield com/product/android/business/service/BaseMsgBroadCastReceiver/mCallBack Lcom/product/android/business/service/ReceiveCallback;
invokeinterface com/product/android/business/service/ReceiveCallback/handler_CMD_5502()V 0
return
L4:
aload 0
getfield com/product/android/business/service/BaseMsgBroadCastReceiver/mCallBack Lcom/product/android/business/service/ReceiveCallback;
ifnull L29
aload 0
getfield com/product/android/business/service/BaseMsgBroadCastReceiver/mCallBack Lcom/product/android/business/service/ReceiveCallback;
invokeinterface com/product/android/business/service/ReceiveCallback/handler_CMD_39()V 0
return
L1:
aload 0
getfield com/product/android/business/service/BaseMsgBroadCastReceiver/mCallBack Lcom/product/android/business/service/ReceiveCallback;
ifnull L29
aload 0
getfield com/product/android/business/service/BaseMsgBroadCastReceiver/mCallBack Lcom/product/android/business/service/ReceiveCallback;
invokeinterface com/product/android/business/service/ReceiveCallback/handler_CMD_16()V 0
return
L16:
aload 0
getfield com/product/android/business/service/BaseMsgBroadCastReceiver/mCallBack Lcom/product/android/business/service/ReceiveCallback;
ifnull L29
aload 2
ldc "url"
invokevirtual android/content/Intent/hasExtra(Ljava/lang/String;)Z
ifeq L30
aload 0
getfield com/product/android/business/service/BaseMsgBroadCastReceiver/mCallBack Lcom/product/android/business/service/ReceiveCallback;
aload 2
ldc "url"
invokevirtual android/content/Intent/getStringExtra(Ljava/lang/String;)Ljava/lang/String;
invokeinterface com/product/android/business/service/ReceiveCallback/handler_CMD_12000(Ljava/lang/String;)V 1
return
L30:
aload 0
getfield com/product/android/business/service/BaseMsgBroadCastReceiver/mCallBack Lcom/product/android/business/service/ReceiveCallback;
invokeinterface com/product/android/business/service/ReceiveCallback/handler_CMD_12000()V 0
return
L2:
aload 0
getfield com/product/android/business/service/BaseMsgBroadCastReceiver/mCallBack Lcom/product/android/business/service/ReceiveCallback;
ifnull L29
aload 0
getfield com/product/android/business/service/BaseMsgBroadCastReceiver/mCallBack Lcom/product/android/business/service/ReceiveCallback;
invokeinterface com/product/android/business/service/ReceiveCallback/handler_CMD_31()V 0
return
L19:
aload 0
getfield com/product/android/business/service/BaseMsgBroadCastReceiver/mCallBack Lcom/product/android/business/service/ReceiveCallback;
ifnull L29
aload 0
getfield com/product/android/business/service/BaseMsgBroadCastReceiver/mCallBack Lcom/product/android/business/service/ReceiveCallback;
invokeinterface com/product/android/business/service/ReceiveCallback/handler_CMD_30010()V 0
return
L20:
aload 0
getfield com/product/android/business/service/BaseMsgBroadCastReceiver/mCallBack Lcom/product/android/business/service/ReceiveCallback;
ifnull L29
aload 0
getfield com/product/android/business/service/BaseMsgBroadCastReceiver/mCallBack Lcom/product/android/business/service/ReceiveCallback;
invokeinterface com/product/android/business/service/ReceiveCallback/handler_CMD_30011()V 0
return
L14:
aload 0
getfield com/product/android/business/service/BaseMsgBroadCastReceiver/mCallBack Lcom/product/android/business/service/ReceiveCallback;
ifnull L29
aload 0
getfield com/product/android/business/service/BaseMsgBroadCastReceiver/mCallBack Lcom/product/android/business/service/ReceiveCallback;
aload 0
getfield com/product/android/business/service/BaseMsgBroadCastReceiver/bundle Landroid/os/Bundle;
invokeinterface com/product/android/business/service/ReceiveCallback/handler_CMD_RemoveGroup(Landroid/os/Bundle;)V 1
return
L22:
aload 0
getfield com/product/android/business/service/BaseMsgBroadCastReceiver/mCallBack Lcom/product/android/business/service/ReceiveCallback;
ifnull L29
aload 0
getfield com/product/android/business/service/BaseMsgBroadCastReceiver/mCallBack Lcom/product/android/business/service/ReceiveCallback;
aload 0
getfield com/product/android/business/service/BaseMsgBroadCastReceiver/bundle Landroid/os/Bundle;
invokeinterface com/product/android/business/service/ReceiveCallback/handler_CMD_49156(Landroid/os/Bundle;)V 1
return
L11:
aload 0
getfield com/product/android/business/service/BaseMsgBroadCastReceiver/mCallBack Lcom/product/android/business/service/ReceiveCallback;
ifnull L29
aload 0
getfield com/product/android/business/service/BaseMsgBroadCastReceiver/mCallBack Lcom/product/android/business/service/ReceiveCallback;
invokeinterface com/product/android/business/service/ReceiveCallback/handler_CMD_Suggest()V 0
return
L23:
aload 0
getfield com/product/android/business/service/BaseMsgBroadCastReceiver/mCallBack Lcom/product/android/business/service/ReceiveCallback;
ifnull L13
aload 0
getfield com/product/android/business/service/BaseMsgBroadCastReceiver/mCallBack Lcom/product/android/business/service/ReceiveCallback;
invokeinterface com/product/android/business/service/ReceiveCallback/handler_CMD_85674()V 0
L13:
aload 0
getfield com/product/android/business/service/BaseMsgBroadCastReceiver/mCallBack Lcom/product/android/business/service/ReceiveCallback;
ifnull L29
aload 0
getfield com/product/android/business/service/BaseMsgBroadCastReceiver/mCallBack Lcom/product/android/business/service/ReceiveCallback;
aload 0
getfield com/product/android/business/service/BaseMsgBroadCastReceiver/bundle Landroid/os/Bundle;
invokeinterface com/product/android/business/service/ReceiveCallback/handler_CMD_GROUP_SYSMSG_TYPE_GROUP_INFO_CHANGED(Landroid/os/Bundle;)V 1
return
L15:
aload 0
getfield com/product/android/business/service/BaseMsgBroadCastReceiver/mCallBack Lcom/product/android/business/service/ReceiveCallback;
ifnull L29
aload 0
getfield com/product/android/business/service/BaseMsgBroadCastReceiver/mCallBack Lcom/product/android/business/service/ReceiveCallback;
invokeinterface com/product/android/business/service/ReceiveCallback/handler_CMD_GETAPPINFO()V 0
return
L10:
aload 0
getfield com/product/android/business/service/BaseMsgBroadCastReceiver/bundle Landroid/os/Bundle;
ldc "msgData"
invokevirtual android/os/Bundle/containsKey(Ljava/lang/String;)Z
ifeq L29
aload 0
getfield com/product/android/business/service/BaseMsgBroadCastReceiver/mContext Landroid/content/Context;
aload 0
getfield com/product/android/business/service/BaseMsgBroadCastReceiver/bundle Landroid/os/Bundle;
ldc "msgData"
invokevirtual android/os/Bundle/getString(Ljava/lang/String;)Ljava/lang/String;
invokestatic com/common/android/utils/ToastUtils/display(Landroid/content/Context;Ljava/lang/String;)V
return
L9:
aload 0
getfield com/product/android/business/service/BaseMsgBroadCastReceiver/mCallBack Lcom/product/android/business/service/ReceiveCallback;
ifnull L29
aload 0
getfield com/product/android/business/service/BaseMsgBroadCastReceiver/mCallBack Lcom/product/android/business/service/ReceiveCallback;
invokeinterface com/product/android/business/service/ReceiveCallback/handler_CMD_635()V 0
return
L24:
aload 0
getfield com/product/android/business/service/BaseMsgBroadCastReceiver/mCallBack Lcom/product/android/business/service/ReceiveCallback;
ifnull L29
aload 0
getfield com/product/android/business/service/BaseMsgBroadCastReceiver/mCallBack Lcom/product/android/business/service/ReceiveCallback;
invokeinterface com/product/android/business/service/ReceiveCallback/handler_CMD_x20000()V 0
return
L25:
aload 0
getfield com/product/android/business/service/BaseMsgBroadCastReceiver/mCallBack Lcom/product/android/business/service/ReceiveCallback;
ifnull L29
aload 0
getfield com/product/android/business/service/BaseMsgBroadCastReceiver/mCallBack Lcom/product/android/business/service/ReceiveCallback;
invokeinterface com/product/android/business/service/ReceiveCallback/handler_CMD_x20002()V 0
return
L26:
aload 0
getfield com/product/android/business/service/BaseMsgBroadCastReceiver/mCallBack Lcom/product/android/business/service/ReceiveCallback;
ifnull L29
aload 0
getfield com/product/android/business/service/BaseMsgBroadCastReceiver/mCallBack Lcom/product/android/business/service/ReceiveCallback;
invokeinterface com/product/android/business/service/ReceiveCallback/handler_CMD_x20003()V 0
return
L27:
aload 0
getfield com/product/android/business/service/BaseMsgBroadCastReceiver/mCallBack Lcom/product/android/business/service/ReceiveCallback;
ifnull L29
aload 0
getfield com/product/android/business/service/BaseMsgBroadCastReceiver/mCallBack Lcom/product/android/business/service/ReceiveCallback;
invokeinterface com/product/android/business/service/ReceiveCallback/handler_CMD_x20004()V 0
return
L28:
aload 0
getfield com/product/android/business/service/BaseMsgBroadCastReceiver/mCallBack Lcom/product/android/business/service/ReceiveCallback;
ifnull L29
aload 0
getfield com/product/android/business/service/BaseMsgBroadCastReceiver/mCallBack Lcom/product/android/business/service/ReceiveCallback;
invokeinterface com/product/android/business/service/ReceiveCallback/handler_CMD_x20005()V 0
return
.limit locals 4
.limit stack 3
.end method
