.bytecode 50.0
.class public synchronized com/nd/android/u/cloud/com/WorkIdLoginCom
.super java/lang/Object

.field private static 'mLoginPro' Lcom/nd/android/u/cloud/com/WorkIdLoginCom;

.field private static 'oapPassportSupportCom' Lcom/nd/android/u/cloud/com/base/OapPassportSupportCom;

.field private static 'sidFromCheckcode' Ljava/lang/String;

.method static <clinit>()V
ldc ""
putstatic com/nd/android/u/cloud/com/WorkIdLoginCom/sidFromCheckcode Ljava/lang/String;
return
.limit locals 0
.limit stack 1
.end method

.method private <init>()V
aload 0
invokespecial java/lang/Object/<init>()V
return
.limit locals 1
.limit stack 1
.end method

.method private _getHttpAuthExceptionErrMsg(Lcom/common/android/utils/http/HttpAuthException;Ljava/lang/StringBuilder;)V
aload 1
invokevirtual com/common/android/utils/http/HttpAuthException/getMessage()Ljava/lang/String;
astore 3
aload 2
aload 3
aload 1
invokevirtual com/common/android/utils/http/HttpAuthException/getStatusCode()I
invokestatic com/common/android/utils/http/HttpBaseClient/getCause(I)Ljava/lang/String;
invokevirtual java/lang/String/length()I
aload 3
invokevirtual java/lang/String/length()I
invokevirtual java/lang/String/substring(II)Ljava/lang/String;
invokevirtual java/lang/StringBuilder/append(Ljava/lang/String;)Ljava/lang/StringBuilder;
pop
return
.limit locals 4
.limit stack 4
.end method

.method private _getHttpExceptionErrMsg(Lcom/common/android/utils/http/HttpException;Ljava/lang/StringBuilder;)V
aload 1
invokevirtual com/common/android/utils/http/HttpException/getMessage()Ljava/lang/String;
astore 3
aload 2
aload 3
aload 1
invokevirtual com/common/android/utils/http/HttpException/getStatusCode()I
invokestatic com/common/android/utils/http/HttpBaseClient/getCause(I)Ljava/lang/String;
invokevirtual java/lang/String/length()I
aload 3
invokevirtual java/lang/String/length()I
invokevirtual java/lang/String/substring(II)Ljava/lang/String;
invokevirtual java/lang/StringBuilder/append(Ljava/lang/String;)Ljava/lang/StringBuilder;
pop
return
.limit locals 4
.limit stack 4
.end method

.method private _getHttpServerExceptionErrMsg(Lcom/common/android/utils/http/HttpServerException;Ljava/lang/StringBuilder;)V
aload 1
invokevirtual com/common/android/utils/http/HttpServerException/getMessage()Ljava/lang/String;
astore 3
aload 2
aload 3
aload 1
invokevirtual com/common/android/utils/http/HttpServerException/getStatusCode()I
invokestatic com/common/android/utils/http/HttpBaseClient/getCause(I)Ljava/lang/String;
invokevirtual java/lang/String/length()I
aload 3
invokevirtual java/lang/String/length()I
invokevirtual java/lang/String/substring(II)Ljava/lang/String;
invokevirtual java/lang/StringBuilder/append(Ljava/lang/String;)Ljava/lang/StringBuilder;
pop
return
.limit locals 4
.limit stack 4
.end method

.method private _getResponseExceptionErrMsg(Lcom/common/android/utils/http/ResponseException;Ljava/lang/StringBuilder;)V
aload 1
invokevirtual com/common/android/utils/http/ResponseException/getMessage()Ljava/lang/String;
astore 3
aload 2
aload 3
aload 1
invokevirtual com/common/android/utils/http/ResponseException/getStatusCode()I
invokestatic com/common/android/utils/http/HttpBaseClient/getCause(I)Ljava/lang/String;
invokevirtual java/lang/String/length()I
aload 3
invokevirtual java/lang/String/length()I
invokevirtual java/lang/String/substring(II)Ljava/lang/String;
invokevirtual java/lang/StringBuilder/append(Ljava/lang/String;)Ljava/lang/StringBuilder;
pop
return
.limit locals 4
.limit stack 4
.end method

.method private getBlowfish()Ljava/lang/String;
getstatic com/product/android/business/ApplicationVariable/INSTANCE Lcom/product/android/business/ApplicationVariable;
getfield com/product/android/business/ApplicationVariable/applicationContext Landroid/content/Context;
ldc "phone"
invokevirtual android/content/Context/getSystemService(Ljava/lang/String;)Ljava/lang/Object;
checkcast android/telephony/TelephonyManager
invokevirtual android/telephony/TelephonyManager/getDeviceId()Ljava/lang/String;
astore 2
aload 2
astore 1
aload 2
invokestatic android/text/TextUtils/isEmpty(Ljava/lang/CharSequence;)Z
ifeq L0
invokestatic com/nd/android/u/cloud/helper/PubFunction/GetGUID()Ljava/lang/String;
astore 1
L0:
aload 1
invokestatic com/nd/android/u/cloud/helper/Utils/stringToMD5(Ljava/lang/String;)Ljava/lang/String;
areturn
.limit locals 3
.limit stack 2
.end method

.method public static getInstance()Lcom/nd/android/u/cloud/com/WorkIdLoginCom;
getstatic com/nd/android/u/cloud/com/WorkIdLoginCom/mLoginPro Lcom/nd/android/u/cloud/com/WorkIdLoginCom;
ifnonnull L0
new com/nd/android/u/cloud/com/WorkIdLoginCom
dup
invokespecial com/nd/android/u/cloud/com/WorkIdLoginCom/<init>()V
putstatic com/nd/android/u/cloud/com/WorkIdLoginCom/mLoginPro Lcom/nd/android/u/cloud/com/WorkIdLoginCom;
L0:
new com/nd/android/u/cloud/com/base/OapPassportSupportCom
dup
invokespecial com/nd/android/u/cloud/com/base/OapPassportSupportCom/<init>()V
putstatic com/nd/android/u/cloud/com/WorkIdLoginCom/oapPassportSupportCom Lcom/nd/android/u/cloud/com/base/OapPassportSupportCom;
getstatic com/nd/android/u/cloud/com/WorkIdLoginCom/mLoginPro Lcom/nd/android/u/cloud/com/WorkIdLoginCom;
areturn
.limit locals 0
.limit stack 2
.end method

.method public changePassword(Ljava/lang/String;Ljava/lang/String;Ljava/lang/StringBuilder;)Z
.catch com/common/android/utils/http/HttpAuthException from L0 to L1 using L2
.catch com/common/android/utils/http/ResponseException from L0 to L1 using L3
.catch com/common/android/utils/http/HttpServerException from L0 to L1 using L4
.catch com/common/android/utils/http/HttpException from L0 to L1 using L5
.catch org/json/JSONException from L0 to L1 using L6
.catch org/json/JSONException from L7 to L8 using L9
.catch org/json/JSONException from L8 to L10 using L9
iconst_0
istore 5
aload 3
astore 6
aload 3
ifnonnull L11
new java/lang/StringBuilder
dup
invokespecial java/lang/StringBuilder/<init>()V
astore 6
L11:
aload 6
iconst_0
aload 6
invokevirtual java/lang/StringBuilder/length()I
invokevirtual java/lang/StringBuilder/delete(II)Ljava/lang/StringBuilder;
pop
L0:
getstatic com/nd/android/u/cloud/com/WorkIdLoginCom/oapPassportSupportCom Lcom/nd/android/u/cloud/com/base/OapPassportSupportCom;
aload 1
aload 2
aload 6
invokevirtual com/nd/android/u/cloud/com/base/OapPassportSupportCom/doChangePassword(Ljava/lang/String;Ljava/lang/String;Ljava/lang/StringBuilder;)I
istore 4
L1:
iload 4
sipush 200
if_icmpne L12
iconst_1
istore 5
L12:
iload 5
ireturn
L2:
astore 1
L7:
new org/json/JSONObject
dup
aload 1
invokevirtual com/common/android/utils/http/HttpAuthException/getMessage()Ljava/lang/String;
invokespecial org/json/JSONObject/<init>(Ljava/lang/String;)V
ldc "msg"
invokevirtual org/json/JSONObject/optString(Ljava/lang/String;)Ljava/lang/String;
astore 1
L8:
aload 1
invokestatic android/text/TextUtils/isEmpty(Ljava/lang/CharSequence;)Z
ifne L12
aload 6
iconst_0
aload 6
invokevirtual java/lang/StringBuilder/length()I
invokevirtual java/lang/StringBuilder/delete(II)Ljava/lang/StringBuilder;
pop
aload 6
aload 1
invokevirtual java/lang/StringBuilder/append(Ljava/lang/String;)Ljava/lang/StringBuilder;
pop
L10:
iconst_0
ireturn
L9:
astore 1
aload 1
invokevirtual org/json/JSONException/printStackTrace()V
iconst_0
ireturn
L3:
astore 1
aload 0
aload 1
aload 6
invokespecial com/nd/android/u/cloud/com/WorkIdLoginCom/_getResponseExceptionErrMsg(Lcom/common/android/utils/http/ResponseException;Ljava/lang/StringBuilder;)V
iconst_0
ireturn
L4:
astore 1
aload 0
aload 1
aload 6
invokespecial com/nd/android/u/cloud/com/WorkIdLoginCom/_getHttpServerExceptionErrMsg(Lcom/common/android/utils/http/HttpServerException;Ljava/lang/StringBuilder;)V
iconst_0
ireturn
L5:
astore 1
aload 0
aload 1
aload 6
invokespecial com/nd/android/u/cloud/com/WorkIdLoginCom/_getHttpExceptionErrMsg(Lcom/common/android/utils/http/HttpException;Ljava/lang/StringBuilder;)V
iconst_0
ireturn
L6:
astore 1
aload 1
invokevirtual org/json/JSONException/printStackTrace()V
iconst_0
ireturn
.limit locals 7
.limit stack 4
.end method

.method public doAccountBind(Ljava/lang/String;Ljava/lang/String;Ljava/lang/String;Ljava/lang/StringBuilder;)I
.catch com/common/android/utils/http/HttpAuthException from L0 to L1 using L2
.catch com/common/android/utils/http/ResponseException from L0 to L1 using L3
.catch com/common/android/utils/http/HttpServerException from L0 to L1 using L4
.catch com/common/android/utils/http/HttpException from L0 to L1 using L5
.catch org/json/JSONException from L0 to L1 using L6
.catch com/common/android/utils/http/HttpAuthException from L7 to L8 using L2
.catch com/common/android/utils/http/ResponseException from L7 to L8 using L3
.catch com/common/android/utils/http/HttpServerException from L7 to L8 using L4
.catch com/common/android/utils/http/HttpException from L7 to L8 using L5
.catch org/json/JSONException from L7 to L8 using L6
.catch com/common/android/utils/http/HttpAuthException from L9 to L10 using L2
.catch com/common/android/utils/http/ResponseException from L9 to L10 using L3
.catch com/common/android/utils/http/HttpServerException from L9 to L10 using L4
.catch com/common/android/utils/http/HttpException from L9 to L10 using L5
.catch org/json/JSONException from L9 to L10 using L6
.catch com/common/android/utils/http/HttpAuthException from L11 to L12 using L2
.catch com/common/android/utils/http/ResponseException from L11 to L12 using L3
.catch com/common/android/utils/http/HttpServerException from L11 to L12 using L4
.catch com/common/android/utils/http/HttpException from L11 to L12 using L5
.catch org/json/JSONException from L11 to L12 using L6
.catch com/common/android/utils/http/HttpAuthException from L13 to L14 using L2
.catch com/common/android/utils/http/ResponseException from L13 to L14 using L3
.catch com/common/android/utils/http/HttpServerException from L13 to L14 using L4
.catch com/common/android/utils/http/HttpException from L13 to L14 using L5
.catch org/json/JSONException from L13 to L14 using L6
.catch com/common/android/utils/http/HttpAuthException from L15 to L16 using L2
.catch com/common/android/utils/http/ResponseException from L15 to L16 using L3
.catch com/common/android/utils/http/HttpServerException from L15 to L16 using L4
.catch com/common/android/utils/http/HttpException from L15 to L16 using L5
.catch org/json/JSONException from L15 to L16 using L6
.catch com/common/android/utils/http/HttpAuthException from L17 to L18 using L2
.catch com/common/android/utils/http/ResponseException from L17 to L18 using L3
.catch com/common/android/utils/http/HttpServerException from L17 to L18 using L4
.catch com/common/android/utils/http/HttpException from L17 to L18 using L5
.catch org/json/JSONException from L17 to L18 using L6
.catch com/common/android/utils/http/HttpAuthException from L19 to L20 using L2
.catch com/common/android/utils/http/ResponseException from L19 to L20 using L3
.catch com/common/android/utils/http/HttpServerException from L19 to L20 using L4
.catch com/common/android/utils/http/HttpException from L19 to L20 using L5
.catch org/json/JSONException from L19 to L20 using L6
.catch com/common/android/utils/http/HttpAuthException from L21 to L22 using L2
.catch com/common/android/utils/http/ResponseException from L21 to L22 using L3
.catch com/common/android/utils/http/HttpServerException from L21 to L22 using L4
.catch com/common/android/utils/http/HttpException from L21 to L22 using L5
.catch org/json/JSONException from L21 to L22 using L6
.catch com/common/android/utils/http/HttpAuthException from L23 to L24 using L2
.catch com/common/android/utils/http/ResponseException from L23 to L24 using L3
.catch com/common/android/utils/http/HttpServerException from L23 to L24 using L4
.catch com/common/android/utils/http/HttpException from L23 to L24 using L5
.catch org/json/JSONException from L23 to L24 using L6
.catch com/common/android/utils/http/HttpAuthException from L25 to L26 using L2
.catch com/common/android/utils/http/ResponseException from L25 to L26 using L3
.catch com/common/android/utils/http/HttpServerException from L25 to L26 using L4
.catch com/common/android/utils/http/HttpException from L25 to L26 using L5
.catch org/json/JSONException from L25 to L26 using L6
.catch com/common/android/utils/http/HttpAuthException from L27 to L28 using L2
.catch com/common/android/utils/http/ResponseException from L27 to L28 using L3
.catch com/common/android/utils/http/HttpServerException from L27 to L28 using L4
.catch com/common/android/utils/http/HttpException from L27 to L28 using L5
.catch org/json/JSONException from L27 to L28 using L6
.catch com/common/android/utils/http/HttpAuthException from L29 to L30 using L2
.catch com/common/android/utils/http/ResponseException from L29 to L30 using L3
.catch com/common/android/utils/http/HttpServerException from L29 to L30 using L4
.catch com/common/android/utils/http/HttpException from L29 to L30 using L5
.catch org/json/JSONException from L29 to L30 using L6
.catch com/common/android/utils/http/HttpAuthException from L31 to L32 using L2
.catch com/common/android/utils/http/ResponseException from L31 to L32 using L3
.catch com/common/android/utils/http/HttpServerException from L31 to L32 using L4
.catch com/common/android/utils/http/HttpException from L31 to L32 using L5
.catch org/json/JSONException from L31 to L32 using L6
.catch com/common/android/utils/http/HttpAuthException from L33 to L34 using L2
.catch com/common/android/utils/http/ResponseException from L33 to L34 using L3
.catch com/common/android/utils/http/HttpServerException from L33 to L34 using L4
.catch com/common/android/utils/http/HttpException from L33 to L34 using L5
.catch org/json/JSONException from L33 to L34 using L6
.catch com/common/android/utils/http/HttpAuthException from L35 to L36 using L2
.catch com/common/android/utils/http/ResponseException from L35 to L36 using L3
.catch com/common/android/utils/http/HttpServerException from L35 to L36 using L4
.catch com/common/android/utils/http/HttpException from L35 to L36 using L5
.catch org/json/JSONException from L35 to L36 using L6
.catch com/common/android/utils/http/HttpAuthException from L37 to L38 using L2
.catch com/common/android/utils/http/ResponseException from L37 to L38 using L3
.catch com/common/android/utils/http/HttpServerException from L37 to L38 using L4
.catch com/common/android/utils/http/HttpException from L37 to L38 using L5
.catch org/json/JSONException from L37 to L38 using L6
.catch com/common/android/utils/http/HttpAuthException from L39 to L40 using L2
.catch com/common/android/utils/http/ResponseException from L39 to L40 using L3
.catch com/common/android/utils/http/HttpServerException from L39 to L40 using L4
.catch com/common/android/utils/http/HttpException from L39 to L40 using L5
.catch org/json/JSONException from L39 to L40 using L6
.catch com/common/android/utils/http/HttpAuthException from L41 to L42 using L2
.catch com/common/android/utils/http/ResponseException from L41 to L42 using L3
.catch com/common/android/utils/http/HttpServerException from L41 to L42 using L4
.catch com/common/android/utils/http/HttpException from L41 to L42 using L5
.catch org/json/JSONException from L41 to L42 using L6
.catch com/common/android/utils/http/HttpAuthException from L43 to L44 using L2
.catch com/common/android/utils/http/ResponseException from L43 to L44 using L3
.catch com/common/android/utils/http/HttpServerException from L43 to L44 using L4
.catch com/common/android/utils/http/HttpException from L43 to L44 using L5
.catch org/json/JSONException from L43 to L44 using L6
.catch com/common/android/utils/http/HttpAuthException from L45 to L46 using L2
.catch com/common/android/utils/http/ResponseException from L45 to L46 using L3
.catch com/common/android/utils/http/HttpServerException from L45 to L46 using L4
.catch com/common/android/utils/http/HttpException from L45 to L46 using L5
.catch org/json/JSONException from L45 to L46 using L6
aload 4
astore 14
aload 4
ifnonnull L47
new java/lang/StringBuilder
dup
invokespecial java/lang/StringBuilder/<init>()V
astore 14
L47:
aload 14
iconst_0
aload 14
invokevirtual java/lang/StringBuilder/length()I
invokevirtual java/lang/StringBuilder/delete(II)Ljava/lang/StringBuilder;
pop
iconst_m1
istore 5
iload 5
istore 7
iload 5
istore 8
iload 5
istore 9
iload 5
istore 10
iload 5
istore 11
L0:
getstatic com/nd/android/u/cloud/com/WorkIdLoginCom/oapPassportSupportCom Lcom/nd/android/u/cloud/com/base/OapPassportSupportCom;
aload 2
aload 3
aload 14
invokevirtual com/nd/android/u/cloud/com/base/OapPassportSupportCom/doAccountBind(Ljava/lang/String;Ljava/lang/String;Ljava/lang/StringBuilder;)I
istore 5
L1:
iload 5
istore 6
iload 5
sipush 200
if_icmpne L48
iload 5
istore 7
iload 5
istore 8
iload 5
istore 9
iload 5
istore 10
iload 5
istore 11
L7:
new org/json/JSONObject
dup
aload 14
invokevirtual java/lang/StringBuilder/toString()Ljava/lang/String;
invokespecial org/json/JSONObject/<init>(Ljava/lang/String;)V
astore 2
L8:
iload 5
istore 6
aload 2
ifnull L48
iload 5
istore 7
iload 5
istore 8
iload 5
istore 9
iload 5
istore 10
iload 5
istore 11
L9:
getstatic com/product/android/business/ApplicationVariable/INSTANCE Lcom/product/android/business/ApplicationVariable;
invokevirtual com/product/android/business/ApplicationVariable/getOapUid()J
invokestatic com/nd/rj/common/login/entity/WorkerUserInfoTable/GetUserInfo(J)Lcom/product/android/business/login/JobNumberUserInfo;
astore 3
L10:
iload 5
istore 7
iload 5
istore 8
iload 5
istore 9
iload 5
istore 10
iload 5
istore 11
L11:
aload 2
ldc "uap_uid"
invokevirtual org/json/JSONObject/has(Ljava/lang/String;)Z
ifeq L49
L12:
iload 5
istore 7
iload 5
istore 8
iload 5
istore 9
iload 5
istore 10
iload 5
istore 11
L13:
aload 2
ldc "uap_uid"
invokevirtual org/json/JSONObject/getLong(Ljava/lang/String;)J
lstore 12
L14:
iload 5
istore 7
iload 5
istore 8
iload 5
istore 9
iload 5
istore 10
iload 5
istore 11
L15:
aload 3
lload 12
invokevirtual com/product/android/business/login/JobNumberUserInfo/setUap_uid(J)V
L16:
iload 5
istore 7
iload 5
istore 8
iload 5
istore 9
iload 5
istore 10
iload 5
istore 11
L17:
aload 3
aload 1
invokevirtual com/product/android/business/login/JobNumberUserInfo/setBindUapAccount(Ljava/lang/String;)V
L18:
iload 5
istore 7
iload 5
istore 8
iload 5
istore 9
iload 5
istore 10
iload 5
istore 11
L19:
aload 3
invokestatic com/nd/rj/common/login/entity/WorkerUserInfoTable/SetUserInfo(Lcom/product/android/business/login/JobNumberUserInfo;)I
pop
L20:
iload 5
istore 7
iload 5
istore 8
iload 5
istore 9
iload 5
istore 10
iload 5
istore 11
L21:
getstatic com/product/android/business/ApplicationVariable/INSTANCE Lcom/product/android/business/ApplicationVariable;
getfield com/product/android/business/ApplicationVariable/applicationContext Landroid/content/Context;
astore 2
L22:
iload 5
istore 7
iload 5
istore 8
iload 5
istore 9
iload 5
istore 10
iload 5
istore 11
L23:
aload 2
invokestatic com/nd/rj/common/login/LoginInterfaceManager/getOapLastLoginUser(Landroid/content/Context;)Lcom/nd/rj/common/login/entity/OapUser;
astore 3
L24:
aload 3
ifnull L32
iload 5
istore 7
iload 5
istore 8
iload 5
istore 9
iload 5
istore 10
iload 5
istore 11
L25:
aload 3
aload 1
putfield com/nd/rj/common/login/entity/OapUser/account Ljava/lang/String;
L26:
iload 5
istore 7
iload 5
istore 8
iload 5
istore 9
iload 5
istore 10
iload 5
istore 11
L27:
aload 3
lload 12
putfield com/nd/rj/common/login/entity/OapUser/uapUid J
L28:
iload 5
istore 7
iload 5
istore 8
iload 5
istore 9
iload 5
istore 10
iload 5
istore 11
L29:
aload 2
aload 3
invokestatic com/nd/rj/common/login/LoginInterfaceManager/saveOapUser(Landroid/content/Context;Lcom/nd/rj/common/login/entity/OapUser;)Z
pop
L30:
iload 5
istore 7
iload 5
istore 8
iload 5
istore 9
iload 5
istore 10
iload 5
istore 11
L31:
getstatic com/product/android/business/ApplicationVariable/INSTANCE Lcom/product/android/business/ApplicationVariable;
aload 2
invokestatic com/nd/rj/common/login/LoginInterfaceManager/getIUser(Landroid/content/Context;)Lcom/product/android/business/login/IGetUserInfo;
invokevirtual com/product/android/business/ApplicationVariable/setIUser(Lcom/product/android/business/login/IGetUserInfo;)V
L32:
iload 5
istore 7
iload 5
istore 8
iload 5
istore 9
iload 5
istore 10
iload 5
istore 11
L33:
new com/product/android/commonInterface/BaseCommonStruct
dup
invokespecial com/product/android/commonInterface/BaseCommonStruct/<init>()V
astore 1
L34:
iload 5
istore 7
iload 5
istore 8
iload 5
istore 9
iload 5
istore 10
iload 5
istore 11
L35:
aload 1
lload 12
l2i
putfield com/product/android/commonInterface/BaseCommonStruct/iPara I
L36:
iload 5
istore 7
iload 5
istore 8
iload 5
istore 9
iload 5
istore 10
iload 5
istore 11
L37:
getstatic com/product/android/commonInterface/CommonInterfaceManager/INSTANCE Lcom/product/android/commonInterface/CommonInterfaceManager;
iconst_1
sipush 10025
aload 1
invokevirtual com/product/android/commonInterface/CommonInterfaceManager/CommonInterfaceID(IILcom/product/android/commonInterface/BaseCommonStruct;)I
pop
L38:
iload 5
istore 6
goto L48
L49:
iload 5
istore 7
iload 5
istore 8
iload 5
istore 9
iload 5
istore 10
iload 5
istore 11
iload 5
istore 6
L39:
aload 2
ldc "msg"
invokevirtual org/json/JSONObject/has(Ljava/lang/String;)Z
ifeq L48
L40:
iload 5
istore 7
iload 5
istore 8
iload 5
istore 9
iload 5
istore 10
iload 5
istore 11
L41:
aload 14
iconst_0
aload 14
invokevirtual java/lang/StringBuilder/length()I
invokevirtual java/lang/StringBuilder/delete(II)Ljava/lang/StringBuilder;
pop
L42:
iload 5
istore 7
iload 5
istore 8
iload 5
istore 9
iload 5
istore 10
iload 5
istore 11
L43:
aload 14
aload 2
ldc "msg"
invokevirtual org/json/JSONObject/getString(Ljava/lang/String;)Ljava/lang/String;
invokevirtual java/lang/StringBuilder/append(Ljava/lang/String;)Ljava/lang/StringBuilder;
pop
L44:
iload 5
istore 7
iload 5
istore 8
iload 5
istore 9
iload 5
istore 10
iload 5
istore 11
L45:
aload 2
ldc "code"
invokevirtual org/json/JSONObject/getInt(Ljava/lang/String;)I
istore 5
L46:
iload 5
ireturn
L2:
astore 1
aload 0
aload 1
aload 14
invokespecial com/nd/android/u/cloud/com/WorkIdLoginCom/_getHttpAuthExceptionErrMsg(Lcom/common/android/utils/http/HttpAuthException;Ljava/lang/StringBuilder;)V
iload 7
istore 6
goto L48
L3:
astore 1
aload 0
aload 1
aload 14
invokespecial com/nd/android/u/cloud/com/WorkIdLoginCom/_getResponseExceptionErrMsg(Lcom/common/android/utils/http/ResponseException;Ljava/lang/StringBuilder;)V
iload 8
istore 6
goto L48
L4:
astore 1
aload 0
aload 1
aload 14
invokespecial com/nd/android/u/cloud/com/WorkIdLoginCom/_getHttpServerExceptionErrMsg(Lcom/common/android/utils/http/HttpServerException;Ljava/lang/StringBuilder;)V
iload 9
istore 6
goto L48
L5:
astore 1
aload 0
aload 1
aload 14
invokespecial com/nd/android/u/cloud/com/WorkIdLoginCom/_getHttpExceptionErrMsg(Lcom/common/android/utils/http/HttpException;Ljava/lang/StringBuilder;)V
iload 10
istore 6
goto L48
L6:
astore 1
aload 1
invokevirtual org/json/JSONException/printStackTrace()V
iload 11
istore 6
L48:
iload 6
ireturn
.limit locals 15
.limit stack 4
.end method

.method public doLogin(Lcom/nd/rj/common/login/entity/WorkerUserInfo;Ljava/lang/String;Lcom/nd/rj/common/login/entity/ClientInfo;Ljava/lang/StringBuilder;)I
.catch org/json/JSONException from L0 to L1 using L2
.catch com/common/android/utils/http/HttpAuthException from L0 to L1 using L3
.catch com/common/android/utils/http/ResponseException from L0 to L1 using L4
.catch com/common/android/utils/http/HttpServerException from L0 to L1 using L5
.catch com/common/android/utils/http/HttpException from L0 to L1 using L6
.catch org/json/JSONException from L7 to L8 using L2
.catch com/common/android/utils/http/HttpAuthException from L7 to L8 using L3
.catch com/common/android/utils/http/ResponseException from L7 to L8 using L4
.catch com/common/android/utils/http/HttpServerException from L7 to L8 using L5
.catch com/common/android/utils/http/HttpException from L7 to L8 using L6
.catch org/json/JSONException from L9 to L10 using L2
.catch com/common/android/utils/http/HttpAuthException from L9 to L10 using L3
.catch com/common/android/utils/http/ResponseException from L9 to L10 using L4
.catch com/common/android/utils/http/HttpServerException from L9 to L10 using L5
.catch com/common/android/utils/http/HttpException from L9 to L10 using L6
.catch org/json/JSONException from L11 to L12 using L2
.catch com/common/android/utils/http/HttpAuthException from L11 to L12 using L3
.catch com/common/android/utils/http/ResponseException from L11 to L12 using L4
.catch com/common/android/utils/http/HttpServerException from L11 to L12 using L5
.catch com/common/android/utils/http/HttpException from L11 to L12 using L6
.catch org/json/JSONException from L13 to L14 using L2
.catch com/common/android/utils/http/HttpAuthException from L13 to L14 using L3
.catch com/common/android/utils/http/ResponseException from L13 to L14 using L4
.catch com/common/android/utils/http/HttpServerException from L13 to L14 using L5
.catch com/common/android/utils/http/HttpException from L13 to L14 using L6
.catch org/json/JSONException from L15 to L16 using L2
.catch com/common/android/utils/http/HttpAuthException from L15 to L16 using L3
.catch com/common/android/utils/http/ResponseException from L15 to L16 using L4
.catch com/common/android/utils/http/HttpServerException from L15 to L16 using L5
.catch com/common/android/utils/http/HttpException from L15 to L16 using L6
.catch org/json/JSONException from L17 to L18 using L2
.catch com/common/android/utils/http/HttpAuthException from L17 to L18 using L3
.catch com/common/android/utils/http/ResponseException from L17 to L18 using L4
.catch com/common/android/utils/http/HttpServerException from L17 to L18 using L5
.catch com/common/android/utils/http/HttpException from L17 to L18 using L6
.catch org/json/JSONException from L19 to L20 using L2
.catch com/common/android/utils/http/HttpAuthException from L19 to L20 using L3
.catch com/common/android/utils/http/ResponseException from L19 to L20 using L4
.catch com/common/android/utils/http/HttpServerException from L19 to L20 using L5
.catch com/common/android/utils/http/HttpException from L19 to L20 using L6
.catch org/json/JSONException from L21 to L22 using L2
.catch com/common/android/utils/http/HttpAuthException from L21 to L22 using L3
.catch com/common/android/utils/http/ResponseException from L21 to L22 using L4
.catch com/common/android/utils/http/HttpServerException from L21 to L22 using L5
.catch com/common/android/utils/http/HttpException from L21 to L22 using L6
.catch org/json/JSONException from L23 to L24 using L2
.catch com/common/android/utils/http/HttpAuthException from L23 to L24 using L3
.catch com/common/android/utils/http/ResponseException from L23 to L24 using L4
.catch com/common/android/utils/http/HttpServerException from L23 to L24 using L5
.catch com/common/android/utils/http/HttpException from L23 to L24 using L6
.catch org/json/JSONException from L25 to L26 using L2
.catch com/common/android/utils/http/HttpAuthException from L25 to L26 using L3
.catch com/common/android/utils/http/ResponseException from L25 to L26 using L4
.catch com/common/android/utils/http/HttpServerException from L25 to L26 using L5
.catch com/common/android/utils/http/HttpException from L25 to L26 using L6
.catch org/json/JSONException from L27 to L28 using L2
.catch com/common/android/utils/http/HttpAuthException from L27 to L28 using L3
.catch com/common/android/utils/http/ResponseException from L27 to L28 using L4
.catch com/common/android/utils/http/HttpServerException from L27 to L28 using L5
.catch com/common/android/utils/http/HttpException from L27 to L28 using L6
.catch org/json/JSONException from L29 to L30 using L2
.catch com/common/android/utils/http/HttpAuthException from L29 to L30 using L3
.catch com/common/android/utils/http/ResponseException from L29 to L30 using L4
.catch com/common/android/utils/http/HttpServerException from L29 to L30 using L5
.catch com/common/android/utils/http/HttpException from L29 to L30 using L6
.catch org/json/JSONException from L31 to L32 using L2
.catch com/common/android/utils/http/HttpAuthException from L31 to L32 using L3
.catch com/common/android/utils/http/ResponseException from L31 to L32 using L4
.catch com/common/android/utils/http/HttpServerException from L31 to L32 using L5
.catch com/common/android/utils/http/HttpException from L31 to L32 using L6
.catch org/json/JSONException from L33 to L34 using L2
.catch com/common/android/utils/http/HttpAuthException from L33 to L34 using L3
.catch com/common/android/utils/http/ResponseException from L33 to L34 using L4
.catch com/common/android/utils/http/HttpServerException from L33 to L34 using L5
.catch com/common/android/utils/http/HttpException from L33 to L34 using L6
.catch org/json/JSONException from L35 to L36 using L2
.catch com/common/android/utils/http/HttpAuthException from L35 to L36 using L3
.catch com/common/android/utils/http/ResponseException from L35 to L36 using L4
.catch com/common/android/utils/http/HttpServerException from L35 to L36 using L5
.catch com/common/android/utils/http/HttpException from L35 to L36 using L6
.catch org/json/JSONException from L37 to L38 using L2
.catch com/common/android/utils/http/HttpAuthException from L37 to L38 using L3
.catch com/common/android/utils/http/ResponseException from L37 to L38 using L4
.catch com/common/android/utils/http/HttpServerException from L37 to L38 using L5
.catch com/common/android/utils/http/HttpException from L37 to L38 using L6
.catch org/json/JSONException from L39 to L40 using L2
.catch com/common/android/utils/http/HttpAuthException from L39 to L40 using L3
.catch com/common/android/utils/http/ResponseException from L39 to L40 using L4
.catch com/common/android/utils/http/HttpServerException from L39 to L40 using L5
.catch com/common/android/utils/http/HttpException from L39 to L40 using L6
.catch org/json/JSONException from L41 to L42 using L2
.catch com/common/android/utils/http/HttpAuthException from L41 to L42 using L3
.catch com/common/android/utils/http/ResponseException from L41 to L42 using L4
.catch com/common/android/utils/http/HttpServerException from L41 to L42 using L5
.catch com/common/android/utils/http/HttpException from L41 to L42 using L6
.catch org/json/JSONException from L43 to L44 using L2
.catch com/common/android/utils/http/HttpAuthException from L43 to L44 using L3
.catch com/common/android/utils/http/ResponseException from L43 to L44 using L4
.catch com/common/android/utils/http/HttpServerException from L43 to L44 using L5
.catch com/common/android/utils/http/HttpException from L43 to L44 using L6
.catch org/json/JSONException from L45 to L46 using L2
.catch com/common/android/utils/http/HttpAuthException from L45 to L46 using L3
.catch com/common/android/utils/http/ResponseException from L45 to L46 using L4
.catch com/common/android/utils/http/HttpServerException from L45 to L46 using L5
.catch com/common/android/utils/http/HttpException from L45 to L46 using L6
.catch org/json/JSONException from L47 to L48 using L2
.catch com/common/android/utils/http/HttpAuthException from L47 to L48 using L3
.catch com/common/android/utils/http/ResponseException from L47 to L48 using L4
.catch com/common/android/utils/http/HttpServerException from L47 to L48 using L5
.catch com/common/android/utils/http/HttpException from L47 to L48 using L6
.catch com/common/android/utils/http/HttpAuthException from L49 to L50 using L3
.catch com/common/android/utils/http/ResponseException from L49 to L50 using L4
.catch com/common/android/utils/http/HttpServerException from L49 to L50 using L5
.catch com/common/android/utils/http/HttpException from L49 to L50 using L6
.catch org/json/JSONException from L51 to L52 using L2
.catch com/common/android/utils/http/HttpAuthException from L51 to L52 using L3
.catch com/common/android/utils/http/ResponseException from L51 to L52 using L4
.catch com/common/android/utils/http/HttpServerException from L51 to L52 using L5
.catch com/common/android/utils/http/HttpException from L51 to L52 using L6
aload 4
astore 11
aload 4
ifnonnull L53
new java/lang/StringBuilder
dup
invokespecial java/lang/StringBuilder/<init>()V
astore 11
L53:
aload 11
iconst_0
aload 11
invokevirtual java/lang/StringBuilder/length()I
invokevirtual java/lang/StringBuilder/delete(II)Ljava/lang/StringBuilder;
pop
aload 1
invokevirtual com/nd/rj/common/login/entity/WorkerUserInfo/getBlowfish()Ljava/lang/String;
invokestatic android/text/TextUtils/isEmpty(Ljava/lang/CharSequence;)Z
ifeq L54
aload 1
aload 0
invokespecial com/nd/android/u/cloud/com/WorkIdLoginCom/getBlowfish()Ljava/lang/String;
invokevirtual com/nd/rj/common/login/entity/WorkerUserInfo/setBlowfish(Ljava/lang/String;)V
L54:
iconst_m1
istore 5
iload 5
istore 6
iload 5
istore 8
iload 5
istore 9
iload 5
istore 10
iload 5
istore 7
L0:
getstatic com/nd/android/u/cloud/com/WorkIdLoginCom/oapPassportSupportCom Lcom/nd/android/u/cloud/com/base/OapPassportSupportCom;
aload 1
invokevirtual com/nd/rj/common/login/entity/WorkerUserInfo/getUser_name()Ljava/lang/String;
aload 1
invokevirtual com/nd/rj/common/login/entity/WorkerUserInfo/getUser_pass()Ljava/lang/String;
aload 1
invokevirtual com/nd/rj/common/login/entity/WorkerUserInfo/getBlowfish()Ljava/lang/String;
iconst_m1
iconst_m1
ldc ""
ldc ""
aload 2
iconst_m1
aload 3
aload 11
invokevirtual com/nd/android/u/cloud/com/base/OapPassportSupportCom/doInnerLogin(Ljava/lang/String;Ljava/lang/String;Ljava/lang/String;IILjava/lang/String;Ljava/lang/String;Ljava/lang/String;ILcom/nd/rj/common/login/entity/ClientInfo;Ljava/lang/StringBuilder;)I
istore 5
L1:
iload 5
istore 6
iload 5
istore 8
iload 5
istore 9
iload 5
istore 10
iload 5
istore 7
L7:
new org/json/JSONObject
dup
aload 11
invokevirtual java/lang/StringBuilder/toString()Ljava/lang/String;
invokespecial org/json/JSONObject/<init>(Ljava/lang/String;)V
astore 2
L8:
iload 5
istore 7
iload 5
sipush 200
if_icmpne L55
iload 5
istore 7
aload 2
ifnull L55
iload 5
istore 6
iload 5
istore 8
iload 5
istore 9
iload 5
istore 10
iload 5
istore 7
L9:
aload 2
ldc "sid"
invokevirtual org/json/JSONObject/has(Ljava/lang/String;)Z
ifeq L12
L10:
iload 5
istore 6
iload 5
istore 8
iload 5
istore 9
iload 5
istore 10
iload 5
istore 7
L11:
aload 1
aload 2
ldc "sid"
invokevirtual org/json/JSONObject/getString(Ljava/lang/String;)Ljava/lang/String;
invokevirtual com/nd/rj/common/login/entity/WorkerUserInfo/setSid(Ljava/lang/String;)V
L12:
iload 5
istore 6
iload 5
istore 8
iload 5
istore 9
iload 5
istore 10
iload 5
istore 7
L13:
aload 2
ldc "uid"
invokevirtual org/json/JSONObject/has(Ljava/lang/String;)Z
ifeq L16
L14:
iload 5
istore 6
iload 5
istore 8
iload 5
istore 9
iload 5
istore 10
iload 5
istore 7
L15:
aload 1
aload 2
ldc "uid"
invokevirtual org/json/JSONObject/getLong(Ljava/lang/String;)J
invokevirtual com/nd/rj/common/login/entity/WorkerUserInfo/setOap_uid(J)V
L16:
iload 5
istore 6
iload 5
istore 8
iload 5
istore 9
iload 5
istore 10
iload 5
istore 7
L17:
aload 2
ldc "unitid"
invokevirtual org/json/JSONObject/has(Ljava/lang/String;)Z
ifeq L20
L18:
iload 5
istore 6
iload 5
istore 8
iload 5
istore 9
iload 5
istore 10
iload 5
istore 7
L19:
aload 1
aload 2
ldc "unitid"
invokevirtual org/json/JSONObject/getInt(Ljava/lang/String;)I
invokevirtual com/nd/rj/common/login/entity/WorkerUserInfo/setUnit_id(I)V
L20:
iload 5
istore 6
iload 5
istore 8
iload 5
istore 9
iload 5
istore 10
iload 5
istore 7
L21:
aload 2
ldc "ticket"
invokevirtual org/json/JSONObject/has(Ljava/lang/String;)Z
ifeq L24
L22:
iload 5
istore 6
iload 5
istore 8
iload 5
istore 9
iload 5
istore 10
iload 5
istore 7
L23:
aload 1
aload 2
ldc "ticket"
invokevirtual org/json/JSONObject/getString(Ljava/lang/String;)Ljava/lang/String;
invokevirtual com/nd/rj/common/login/entity/WorkerUserInfo/setTicket(Ljava/lang/String;)V
L24:
iload 5
istore 6
iload 5
istore 8
iload 5
istore 9
iload 5
istore 10
iload 5
istore 7
L25:
aload 2
ldc "pwdtime"
invokevirtual org/json/JSONObject/has(Ljava/lang/String;)Z
ifeq L34
L26:
iload 5
istore 6
iload 5
istore 8
iload 5
istore 9
iload 5
istore 10
iload 5
istore 7
L27:
aload 2
ldc "pwdtime"
invokevirtual org/json/JSONObject/getString(Ljava/lang/String;)Ljava/lang/String;
astore 3
L28:
iload 5
istore 6
iload 5
istore 8
iload 5
istore 9
iload 5
istore 10
iload 5
istore 7
L29:
ldc "null"
aload 3
invokevirtual java/lang/String/toLowerCase()Ljava/lang/String;
invokevirtual java/lang/String/equals(Ljava/lang/Object;)Z
ifne L32
L30:
iload 5
istore 6
iload 5
istore 8
iload 5
istore 9
iload 5
istore 10
iload 5
istore 7
L31:
aload 3
invokestatic android/text/TextUtils/isEmpty(Ljava/lang/CharSequence;)Z
ifeq L46
L32:
iload 5
istore 6
iload 5
istore 8
iload 5
istore 9
iload 5
istore 10
iload 5
istore 7
L33:
aload 1
ldc ""
invokevirtual com/nd/rj/common/login/entity/WorkerUserInfo/setPwdtime(Ljava/lang/String;)V
L34:
iload 5
istore 6
iload 5
istore 8
iload 5
istore 9
iload 5
istore 10
iload 5
istore 7
L35:
aload 2
ldc "bind_uap_account"
invokevirtual org/json/JSONObject/has(Ljava/lang/String;)Z
ifeq L44
L36:
iload 5
istore 6
iload 5
istore 8
iload 5
istore 9
iload 5
istore 10
iload 5
istore 7
L37:
aload 2
ldc "bind_uap_account"
invokevirtual org/json/JSONObject/getString(Ljava/lang/String;)Ljava/lang/String;
astore 2
L38:
iload 5
istore 6
iload 5
istore 8
iload 5
istore 9
iload 5
istore 10
iload 5
istore 7
L39:
ldc "null"
aload 2
invokevirtual java/lang/String/toLowerCase()Ljava/lang/String;
invokevirtual java/lang/String/equals(Ljava/lang/Object;)Z
ifne L42
L40:
iload 5
istore 6
iload 5
istore 8
iload 5
istore 9
iload 5
istore 10
iload 5
istore 7
L41:
aload 2
invokestatic android/text/TextUtils/isEmpty(Ljava/lang/CharSequence;)Z
ifeq L56
L42:
iload 5
istore 6
iload 5
istore 8
iload 5
istore 9
iload 5
istore 10
iload 5
istore 7
L43:
aload 1
ldc ""
invokevirtual com/nd/rj/common/login/entity/WorkerUserInfo/setBindUapAccount(Ljava/lang/String;)V
L44:
iload 5
istore 6
iload 5
istore 8
iload 5
istore 9
iload 5
istore 10
iload 5
istore 7
L45:
aload 1
invokevirtual com/nd/rj/common/login/entity/WorkerUserInfo/converToJobNumberUserInfo()Lcom/product/android/business/login/JobNumberUserInfo;
invokestatic com/nd/rj/common/login/entity/WorkerUserInfoTable/SetUserInfo(Lcom/product/android/business/login/JobNumberUserInfo;)I
ireturn
L46:
iload 5
istore 6
iload 5
istore 8
iload 5
istore 9
iload 5
istore 10
iload 5
istore 7
L47:
aload 1
aload 2
ldc "pwdtime"
invokevirtual org/json/JSONObject/getString(Ljava/lang/String;)Ljava/lang/String;
invokevirtual com/nd/rj/common/login/entity/WorkerUserInfo/setPwdtime(Ljava/lang/String;)V
L48:
goto L34
L2:
astore 1
iload 6
istore 8
iload 6
istore 9
iload 6
istore 10
iload 6
istore 7
L49:
aload 1
invokevirtual org/json/JSONException/printStackTrace()V
L50:
ldc_w 2131494389
ireturn
L56:
iload 5
istore 6
iload 5
istore 8
iload 5
istore 9
iload 5
istore 10
iload 5
istore 7
L51:
aload 1
aload 2
invokevirtual com/nd/rj/common/login/entity/WorkerUserInfo/setBindUapAccount(Ljava/lang/String;)V
L52:
goto L44
L3:
astore 1
aload 11
iconst_0
aload 11
invokevirtual java/lang/StringBuilder/length()I
invokevirtual java/lang/StringBuilder/delete(II)Ljava/lang/StringBuilder;
pop
aload 11
aload 1
invokevirtual com/common/android/utils/http/HttpAuthException/getMessage()Ljava/lang/String;
invokevirtual java/lang/StringBuilder/append(Ljava/lang/String;)Ljava/lang/StringBuilder;
pop
iload 8
ireturn
L4:
astore 1
aload 0
aload 1
aload 11
invokespecial com/nd/android/u/cloud/com/WorkIdLoginCom/_getResponseExceptionErrMsg(Lcom/common/android/utils/http/ResponseException;Ljava/lang/StringBuilder;)V
iload 9
ireturn
L5:
astore 1
aload 0
aload 1
aload 11
invokespecial com/nd/android/u/cloud/com/WorkIdLoginCom/_getHttpServerExceptionErrMsg(Lcom/common/android/utils/http/HttpServerException;Ljava/lang/StringBuilder;)V
iload 10
ireturn
L6:
astore 1
aload 11
iconst_0
aload 11
invokevirtual java/lang/StringBuilder/length()I
invokevirtual java/lang/StringBuilder/delete(II)Ljava/lang/StringBuilder;
pop
aload 11
aload 1
invokevirtual com/common/android/utils/http/HttpException/getMessage()Ljava/lang/String;
invokevirtual java/lang/StringBuilder/append(Ljava/lang/String;)Ljava/lang/StringBuilder;
pop
L55:
iload 7
ireturn
.limit locals 12
.limit stack 12
.end method

.method public fetchImage()Landroid/graphics/drawable/Drawable;
getstatic com/nd/android/u/cloud/com/WorkIdLoginCom/oapPassportSupportCom Lcom/nd/android/u/cloud/com/base/OapPassportSupportCom;
invokevirtual com/nd/android/u/cloud/com/base/OapPassportSupportCom/getCheckCode()Landroid/graphics/Bitmap;
astore 1
aload 1
ifnull L0
new android/graphics/drawable/BitmapDrawable
dup
aload 1
invokespecial android/graphics/drawable/BitmapDrawable/<init>(Landroid/graphics/Bitmap;)V
areturn
L0:
aconst_null
areturn
.limit locals 2
.limit stack 3
.end method

.method public getSidFromCheckcode()Ljava/lang/String;
getstatic com/nd/android/u/cloud/com/WorkIdLoginCom/sidFromCheckcode Ljava/lang/String;
areturn
.limit locals 1
.limit stack 1
.end method

.method public loginByTicket(Lcom/nd/rj/common/login/entity/WorkerUserInfo;Lcom/nd/rj/common/login/entity/ClientInfo;Ljava/lang/StringBuilder;)I
.catch com/common/android/utils/http/HttpAuthException from L0 to L1 using L2
.catch com/common/android/utils/http/ResponseException from L0 to L1 using L3
.catch com/common/android/utils/http/HttpServerException from L0 to L1 using L4
.catch com/common/android/utils/http/HttpException from L0 to L1 using L5
.catch org/json/JSONException from L0 to L1 using L6
.catch com/common/android/utils/http/HttpAuthException from L7 to L8 using L2
.catch com/common/android/utils/http/ResponseException from L7 to L8 using L3
.catch com/common/android/utils/http/HttpServerException from L7 to L8 using L4
.catch com/common/android/utils/http/HttpException from L7 to L8 using L5
.catch org/json/JSONException from L7 to L8 using L6
.catch com/common/android/utils/http/HttpAuthException from L9 to L10 using L2
.catch com/common/android/utils/http/ResponseException from L9 to L10 using L3
.catch com/common/android/utils/http/HttpServerException from L9 to L10 using L4
.catch com/common/android/utils/http/HttpException from L9 to L10 using L5
.catch org/json/JSONException from L9 to L10 using L6
.catch com/common/android/utils/http/HttpAuthException from L11 to L12 using L2
.catch com/common/android/utils/http/ResponseException from L11 to L12 using L3
.catch com/common/android/utils/http/HttpServerException from L11 to L12 using L4
.catch com/common/android/utils/http/HttpException from L11 to L12 using L5
.catch org/json/JSONException from L11 to L12 using L6
.catch com/common/android/utils/http/HttpAuthException from L13 to L14 using L2
.catch com/common/android/utils/http/ResponseException from L13 to L14 using L3
.catch com/common/android/utils/http/HttpServerException from L13 to L14 using L4
.catch com/common/android/utils/http/HttpException from L13 to L14 using L5
.catch org/json/JSONException from L13 to L14 using L6
.catch com/common/android/utils/http/HttpAuthException from L15 to L16 using L2
.catch com/common/android/utils/http/ResponseException from L15 to L16 using L3
.catch com/common/android/utils/http/HttpServerException from L15 to L16 using L4
.catch com/common/android/utils/http/HttpException from L15 to L16 using L5
.catch org/json/JSONException from L15 to L16 using L6
.catch com/common/android/utils/http/HttpAuthException from L17 to L18 using L2
.catch com/common/android/utils/http/ResponseException from L17 to L18 using L3
.catch com/common/android/utils/http/HttpServerException from L17 to L18 using L4
.catch com/common/android/utils/http/HttpException from L17 to L18 using L5
.catch org/json/JSONException from L17 to L18 using L6
.catch com/common/android/utils/http/HttpAuthException from L19 to L20 using L2
.catch com/common/android/utils/http/ResponseException from L19 to L20 using L3
.catch com/common/android/utils/http/HttpServerException from L19 to L20 using L4
.catch com/common/android/utils/http/HttpException from L19 to L20 using L5
.catch org/json/JSONException from L19 to L20 using L6
.catch com/common/android/utils/http/HttpAuthException from L21 to L22 using L2
.catch com/common/android/utils/http/ResponseException from L21 to L22 using L3
.catch com/common/android/utils/http/HttpServerException from L21 to L22 using L4
.catch com/common/android/utils/http/HttpException from L21 to L22 using L5
.catch org/json/JSONException from L21 to L22 using L6
.catch com/common/android/utils/http/HttpAuthException from L23 to L24 using L2
.catch com/common/android/utils/http/ResponseException from L23 to L24 using L3
.catch com/common/android/utils/http/HttpServerException from L23 to L24 using L4
.catch com/common/android/utils/http/HttpException from L23 to L24 using L5
.catch org/json/JSONException from L23 to L24 using L6
.catch com/common/android/utils/http/HttpAuthException from L25 to L26 using L2
.catch com/common/android/utils/http/ResponseException from L25 to L26 using L3
.catch com/common/android/utils/http/HttpServerException from L25 to L26 using L4
.catch com/common/android/utils/http/HttpException from L25 to L26 using L5
.catch org/json/JSONException from L25 to L26 using L6
.catch com/common/android/utils/http/HttpAuthException from L27 to L28 using L2
.catch com/common/android/utils/http/ResponseException from L27 to L28 using L3
.catch com/common/android/utils/http/HttpServerException from L27 to L28 using L4
.catch com/common/android/utils/http/HttpException from L27 to L28 using L5
.catch org/json/JSONException from L27 to L28 using L6
.catch com/common/android/utils/http/HttpAuthException from L29 to L30 using L2
.catch com/common/android/utils/http/ResponseException from L29 to L30 using L3
.catch com/common/android/utils/http/HttpServerException from L29 to L30 using L4
.catch com/common/android/utils/http/HttpException from L29 to L30 using L5
.catch org/json/JSONException from L29 to L30 using L6
.catch com/common/android/utils/http/HttpAuthException from L31 to L32 using L2
.catch com/common/android/utils/http/ResponseException from L31 to L32 using L3
.catch com/common/android/utils/http/HttpServerException from L31 to L32 using L4
.catch com/common/android/utils/http/HttpException from L31 to L32 using L5
.catch org/json/JSONException from L31 to L32 using L6
.catch com/common/android/utils/http/HttpAuthException from L33 to L34 using L2
.catch com/common/android/utils/http/ResponseException from L33 to L34 using L3
.catch com/common/android/utils/http/HttpServerException from L33 to L34 using L4
.catch com/common/android/utils/http/HttpException from L33 to L34 using L5
.catch org/json/JSONException from L33 to L34 using L6
.catch com/common/android/utils/http/HttpAuthException from L35 to L36 using L2
.catch com/common/android/utils/http/ResponseException from L35 to L36 using L3
.catch com/common/android/utils/http/HttpServerException from L35 to L36 using L4
.catch com/common/android/utils/http/HttpException from L35 to L36 using L5
.catch org/json/JSONException from L35 to L36 using L6
.catch com/common/android/utils/http/HttpAuthException from L37 to L38 using L2
.catch com/common/android/utils/http/ResponseException from L37 to L38 using L3
.catch com/common/android/utils/http/HttpServerException from L37 to L38 using L4
.catch com/common/android/utils/http/HttpException from L37 to L38 using L5
.catch org/json/JSONException from L37 to L38 using L6
.catch com/common/android/utils/http/HttpAuthException from L39 to L40 using L2
.catch com/common/android/utils/http/ResponseException from L39 to L40 using L3
.catch com/common/android/utils/http/HttpServerException from L39 to L40 using L4
.catch com/common/android/utils/http/HttpException from L39 to L40 using L5
.catch org/json/JSONException from L39 to L40 using L6
.catch com/common/android/utils/http/HttpAuthException from L41 to L42 using L2
.catch com/common/android/utils/http/ResponseException from L41 to L42 using L3
.catch com/common/android/utils/http/HttpServerException from L41 to L42 using L4
.catch com/common/android/utils/http/HttpException from L41 to L42 using L5
.catch org/json/JSONException from L41 to L42 using L6
.catch com/common/android/utils/http/HttpAuthException from L43 to L44 using L2
.catch com/common/android/utils/http/ResponseException from L43 to L44 using L3
.catch com/common/android/utils/http/HttpServerException from L43 to L44 using L4
.catch com/common/android/utils/http/HttpException from L43 to L44 using L5
.catch org/json/JSONException from L43 to L44 using L6
.catch com/common/android/utils/http/HttpAuthException from L45 to L46 using L2
.catch com/common/android/utils/http/ResponseException from L45 to L46 using L3
.catch com/common/android/utils/http/HttpServerException from L45 to L46 using L4
.catch com/common/android/utils/http/HttpException from L45 to L46 using L5
.catch org/json/JSONException from L45 to L46 using L6
.catch com/common/android/utils/http/HttpAuthException from L47 to L48 using L2
.catch com/common/android/utils/http/ResponseException from L47 to L48 using L3
.catch com/common/android/utils/http/HttpServerException from L47 to L48 using L4
.catch com/common/android/utils/http/HttpException from L47 to L48 using L5
.catch org/json/JSONException from L47 to L48 using L6
.catch com/common/android/utils/http/HttpAuthException from L49 to L50 using L2
.catch com/common/android/utils/http/ResponseException from L49 to L50 using L3
.catch com/common/android/utils/http/HttpServerException from L49 to L50 using L4
.catch com/common/android/utils/http/HttpException from L49 to L50 using L5
.catch org/json/JSONException from L49 to L50 using L6
.catch org/json/JSONException from L51 to L52 using L6
.catch com/common/android/utils/http/HttpAuthException from L53 to L54 using L2
.catch com/common/android/utils/http/ResponseException from L53 to L54 using L3
.catch com/common/android/utils/http/HttpServerException from L53 to L54 using L4
.catch com/common/android/utils/http/HttpException from L53 to L54 using L5
.catch org/json/JSONException from L53 to L54 using L6
.catch org/json/JSONException from L55 to L56 using L6
.catch org/json/JSONException from L57 to L58 using L6
.catch org/json/JSONException from L59 to L60 using L6
aload 3
astore 10
aload 3
ifnonnull L61
new java/lang/StringBuilder
dup
invokespecial java/lang/StringBuilder/<init>()V
astore 10
L61:
aload 10
iconst_0
aload 10
invokevirtual java/lang/StringBuilder/length()I
invokevirtual java/lang/StringBuilder/delete(II)Ljava/lang/StringBuilder;
pop
iconst_m1
istore 4
iload 4
istore 6
iload 4
istore 7
iload 4
istore 8
iload 4
istore 5
L0:
getstatic com/nd/android/u/cloud/com/WorkIdLoginCom/oapPassportSupportCom Lcom/nd/android/u/cloud/com/base/OapPassportSupportCom;
aload 1
invokevirtual com/nd/rj/common/login/entity/WorkerUserInfo/getBlowfish()Ljava/lang/String;
aload 1
invokevirtual com/nd/rj/common/login/entity/WorkerUserInfo/getTicket()Ljava/lang/String;
aload 2
aload 10
invokevirtual com/nd/android/u/cloud/com/base/OapPassportSupportCom/doLogin(Ljava/lang/String;Ljava/lang/String;Lcom/nd/rj/common/login/entity/ClientInfo;Ljava/lang/StringBuilder;)I
istore 4
L1:
iload 4
istore 6
iload 4
istore 7
iload 4
istore 8
iload 4
istore 5
L7:
new org/json/JSONObject
dup
aload 10
invokevirtual java/lang/StringBuilder/toString()Ljava/lang/String;
invokespecial org/json/JSONObject/<init>(Ljava/lang/String;)V
astore 2
L8:
iload 4
istore 9
iload 4
sipush 200
if_icmpne L62
iload 4
istore 9
aload 2
ifnull L62
iload 4
istore 6
iload 4
istore 7
iload 4
istore 8
iload 4
istore 5
L9:
aload 2
ldc "sid"
invokevirtual org/json/JSONObject/has(Ljava/lang/String;)Z
ifeq L12
L10:
iload 4
istore 6
iload 4
istore 7
iload 4
istore 8
iload 4
istore 5
L11:
aload 1
aload 2
ldc "sid"
invokevirtual org/json/JSONObject/getString(Ljava/lang/String;)Ljava/lang/String;
invokevirtual com/nd/rj/common/login/entity/WorkerUserInfo/setSid(Ljava/lang/String;)V
L12:
iload 4
istore 6
iload 4
istore 7
iload 4
istore 8
iload 4
istore 5
L13:
aload 2
ldc "uid"
invokevirtual org/json/JSONObject/has(Ljava/lang/String;)Z
ifeq L16
L14:
iload 4
istore 6
iload 4
istore 7
iload 4
istore 8
iload 4
istore 5
L15:
aload 1
aload 2
ldc "uid"
invokevirtual org/json/JSONObject/getLong(Ljava/lang/String;)J
invokevirtual com/nd/rj/common/login/entity/WorkerUserInfo/setOap_uid(J)V
L16:
iload 4
istore 6
iload 4
istore 7
iload 4
istore 8
iload 4
istore 5
L17:
aload 2
ldc "unitid"
invokevirtual org/json/JSONObject/has(Ljava/lang/String;)Z
ifeq L20
L18:
iload 4
istore 6
iload 4
istore 7
iload 4
istore 8
iload 4
istore 5
L19:
aload 1
aload 2
ldc "unitid"
invokevirtual org/json/JSONObject/getInt(Ljava/lang/String;)I
invokevirtual com/nd/rj/common/login/entity/WorkerUserInfo/setUnit_id(I)V
L20:
iload 4
istore 6
iload 4
istore 7
iload 4
istore 8
iload 4
istore 5
L21:
aload 2
ldc "ticket"
invokevirtual org/json/JSONObject/has(Ljava/lang/String;)Z
ifeq L24
L22:
iload 4
istore 6
iload 4
istore 7
iload 4
istore 8
iload 4
istore 5
L23:
aload 1
aload 2
ldc "ticket"
invokevirtual org/json/JSONObject/getString(Ljava/lang/String;)Ljava/lang/String;
invokevirtual com/nd/rj/common/login/entity/WorkerUserInfo/setTicket(Ljava/lang/String;)V
L24:
iload 4
istore 6
iload 4
istore 7
iload 4
istore 8
iload 4
istore 5
L25:
aload 2
ldc "pwdtime"
invokevirtual org/json/JSONObject/has(Ljava/lang/String;)Z
ifeq L34
L26:
iload 4
istore 6
iload 4
istore 7
iload 4
istore 8
iload 4
istore 5
L27:
aload 2
ldc "pwdtime"
invokevirtual org/json/JSONObject/getString(Ljava/lang/String;)Ljava/lang/String;
astore 3
L28:
iload 4
istore 6
iload 4
istore 7
iload 4
istore 8
iload 4
istore 5
L29:
ldc "null"
aload 3
invokevirtual java/lang/String/toLowerCase()Ljava/lang/String;
invokevirtual java/lang/String/equals(Ljava/lang/Object;)Z
ifne L32
L30:
iload 4
istore 6
iload 4
istore 7
iload 4
istore 8
iload 4
istore 5
L31:
aload 3
invokestatic android/text/TextUtils/isEmpty(Ljava/lang/CharSequence;)Z
ifeq L48
L32:
iload 4
istore 6
iload 4
istore 7
iload 4
istore 8
iload 4
istore 5
L33:
aload 1
ldc ""
invokevirtual com/nd/rj/common/login/entity/WorkerUserInfo/setPwdtime(Ljava/lang/String;)V
L34:
iload 4
istore 6
iload 4
istore 7
iload 4
istore 8
iload 4
istore 5
L35:
aload 2
ldc "bind_uap_account"
invokevirtual org/json/JSONObject/has(Ljava/lang/String;)Z
ifeq L44
L36:
iload 4
istore 6
iload 4
istore 7
iload 4
istore 8
iload 4
istore 5
L37:
aload 2
ldc "bind_uap_account"
invokevirtual org/json/JSONObject/getString(Ljava/lang/String;)Ljava/lang/String;
astore 2
L38:
iload 4
istore 6
iload 4
istore 7
iload 4
istore 8
iload 4
istore 5
L39:
ldc "null"
aload 2
invokevirtual java/lang/String/toLowerCase()Ljava/lang/String;
invokevirtual java/lang/String/equals(Ljava/lang/Object;)Z
ifne L42
L40:
iload 4
istore 6
iload 4
istore 7
iload 4
istore 8
iload 4
istore 5
L41:
aload 2
invokestatic android/text/TextUtils/isEmpty(Ljava/lang/CharSequence;)Z
ifeq L63
L42:
iload 4
istore 6
iload 4
istore 7
iload 4
istore 8
iload 4
istore 5
L43:
aload 1
ldc ""
invokevirtual com/nd/rj/common/login/entity/WorkerUserInfo/setBindUapAccount(Ljava/lang/String;)V
L44:
iload 4
istore 6
iload 4
istore 7
iload 4
istore 8
iload 4
istore 5
iload 4
istore 9
L45:
aload 1
invokevirtual com/nd/rj/common/login/entity/WorkerUserInfo/getOap_uid()J
lconst_0
lcmp
ifle L62
L46:
iload 4
istore 6
iload 4
istore 7
iload 4
istore 8
iload 4
istore 5
L47:
aload 1
invokevirtual com/nd/rj/common/login/entity/WorkerUserInfo/converToJobNumberUserInfo()Lcom/product/android/business/login/JobNumberUserInfo;
invokestatic com/nd/rj/common/login/entity/WorkerUserInfoTable/SetUserInfo(Lcom/product/android/business/login/JobNumberUserInfo;)I
ireturn
L48:
iload 4
istore 6
iload 4
istore 7
iload 4
istore 8
iload 4
istore 5
L49:
aload 1
aload 2
ldc "pwdtime"
invokevirtual org/json/JSONObject/getString(Ljava/lang/String;)Ljava/lang/String;
invokevirtual com/nd/rj/common/login/entity/WorkerUserInfo/setPwdtime(Ljava/lang/String;)V
L50:
goto L34
L2:
astore 1
L51:
aload 10
iconst_0
aload 10
invokevirtual java/lang/StringBuilder/length()I
invokevirtual java/lang/StringBuilder/delete(II)Ljava/lang/StringBuilder;
pop
aload 10
aload 1
invokevirtual com/common/android/utils/http/HttpAuthException/getMessage()Ljava/lang/String;
invokevirtual java/lang/StringBuilder/append(Ljava/lang/String;)Ljava/lang/StringBuilder;
pop
L52:
iload 6
ireturn
L6:
astore 1
aload 1
invokevirtual org/json/JSONException/printStackTrace()V
ldc_w 2131494389
ireturn
L63:
iload 4
istore 6
iload 4
istore 7
iload 4
istore 8
iload 4
istore 5
L53:
aload 1
aload 2
invokevirtual com/nd/rj/common/login/entity/WorkerUserInfo/setBindUapAccount(Ljava/lang/String;)V
L54:
goto L44
L3:
astore 1
L55:
aload 0
aload 1
aload 10
invokespecial com/nd/android/u/cloud/com/WorkIdLoginCom/_getResponseExceptionErrMsg(Lcom/common/android/utils/http/ResponseException;Ljava/lang/StringBuilder;)V
L56:
iload 7
ireturn
L4:
astore 1
L57:
aload 0
aload 1
aload 10
invokespecial com/nd/android/u/cloud/com/WorkIdLoginCom/_getHttpServerExceptionErrMsg(Lcom/common/android/utils/http/HttpServerException;Ljava/lang/StringBuilder;)V
L58:
iload 8
ireturn
L5:
astore 1
L59:
aload 0
aload 1
aload 10
invokespecial com/nd/android/u/cloud/com/WorkIdLoginCom/_getHttpExceptionErrMsg(Lcom/common/android/utils/http/HttpException;Ljava/lang/StringBuilder;)V
L60:
iload 5
istore 9
L62:
iload 9
ireturn
.limit locals 11
.limit stack 5
.end method

.method public setSidFromCheckcode(Ljava/lang/String;)V
aload 1
putstatic com/nd/android/u/cloud/com/WorkIdLoginCom/sidFromCheckcode Ljava/lang/String;
return
.limit locals 2
.limit stack 1
.end method
