.bytecode 50.0
.class synchronized com/nd/schoollife/ui/community/activity/AlterCommunitySignActivity$CommunitySignGridListener
.super java/lang/Object
.implements android/widget/AdapterView$OnItemClickListener
.inner class private CommunitySignGridListener inner com/nd/schoollife/ui/community/activity/AlterCommunitySignActivity$CommunitySignGridListener outer com/nd/schoollife/ui/community/activity/AlterCommunitySignActivity

.field final synthetic 'this$0' Lcom/nd/schoollife/ui/community/activity/AlterCommunitySignActivity;

.method private <init>(Lcom/nd/schoollife/ui/community/activity/AlterCommunitySignActivity;)V
aload 0
aload 1
putfield com/nd/schoollife/ui/community/activity/AlterCommunitySignActivity$CommunitySignGridListener/this$0 Lcom/nd/schoollife/ui/community/activity/AlterCommunitySignActivity;
aload 0
invokespecial java/lang/Object/<init>()V
return
.limit locals 2
.limit stack 2
.end method

.method synthetic <init>(Lcom/nd/schoollife/ui/community/activity/AlterCommunitySignActivity;Lcom/nd/schoollife/ui/community/activity/AlterCommunitySignActivity$1;)V
aload 0
aload 1
invokespecial com/nd/schoollife/ui/community/activity/AlterCommunitySignActivity$CommunitySignGridListener/<init>(Lcom/nd/schoollife/ui/community/activity/AlterCommunitySignActivity;)V
return
.limit locals 3
.limit stack 2
.end method

.method public onItemClick(Landroid/widget/AdapterView;Landroid/view/View;IJ)V
.signature "(Landroid/widget/AdapterView<*>;Landroid/view/View;IJ)V"
iconst_0
istore 6
aload 2
checkcast com/nd/schoollife/ui/team/view/ExtCheckButton
astore 1
aload 1
invokevirtual com/nd/schoollife/ui/team/view/ExtCheckButton/getCheck()Z
ifne L0
aload 0
getfield com/nd/schoollife/ui/community/activity/AlterCommunitySignActivity$CommunitySignGridListener/this$0 Lcom/nd/schoollife/ui/community/activity/AlterCommunitySignActivity;
invokestatic com/nd/schoollife/ui/community/activity/AlterCommunitySignActivity/access$500(Lcom/nd/schoollife/ui/community/activity/AlterCommunitySignActivity;)Lcom/nd/schoollife/ui/community/adapter/CommunityTagList;
invokevirtual com/nd/schoollife/ui/community/adapter/CommunityTagList/size()I
iconst_5
if_icmplt L0
aload 0
getfield com/nd/schoollife/ui/community/activity/AlterCommunitySignActivity$CommunitySignGridListener/this$0 Lcom/nd/schoollife/ui/community/activity/AlterCommunitySignActivity;
invokevirtual com/nd/schoollife/ui/community/activity/AlterCommunitySignActivity/getApplicationContext()Landroid/content/Context;
getstatic com/nd/schoollife/R$string/create_team_team_sign_must_less_5 I
iconst_0
invokestatic android/widget/Toast/makeText(Landroid/content/Context;II)Landroid/widget/Toast;
invokevirtual android/widget/Toast/show()V
return
L0:
aload 1
invokevirtual com/nd/schoollife/ui/team/view/ExtCheckButton/getCheck()Z
ifne L1
iconst_1
istore 6
L1:
aload 1
iload 6
invokevirtual com/nd/schoollife/ui/team/view/ExtCheckButton/setCheck(Z)V
aload 1
invokevirtual com/nd/schoollife/ui/team/view/ExtCheckButton/getCheck()Z
ifeq L2
aload 0
getfield com/nd/schoollife/ui/community/activity/AlterCommunitySignActivity$CommunitySignGridListener/this$0 Lcom/nd/schoollife/ui/community/activity/AlterCommunitySignActivity;
invokestatic com/nd/schoollife/ui/community/activity/AlterCommunitySignActivity/access$600(Lcom/nd/schoollife/ui/community/activity/AlterCommunitySignActivity;)Lcom/nd/schoollife/ui/community/adapter/CommunityTagList;
aload 1
invokevirtual com/nd/schoollife/ui/team/view/ExtCheckButton/getText()Ljava/lang/CharSequence;
invokeinterface java/lang/CharSequence/toString()Ljava/lang/String; 0
invokevirtual com/nd/schoollife/ui/community/adapter/CommunityTagList/getTagInfoByName(Ljava/lang/String;)Lcom/nd/schoollife/common/bean/structure/CommunityTagInfoBean;
astore 1
aload 0
getfield com/nd/schoollife/ui/community/activity/AlterCommunitySignActivity$CommunitySignGridListener/this$0 Lcom/nd/schoollife/ui/community/activity/AlterCommunitySignActivity;
invokestatic com/nd/schoollife/ui/community/activity/AlterCommunitySignActivity/access$500(Lcom/nd/schoollife/ui/community/activity/AlterCommunitySignActivity;)Lcom/nd/schoollife/ui/community/adapter/CommunityTagList;
aload 1
invokevirtual com/nd/schoollife/ui/community/adapter/CommunityTagList/addTagInfo(Lcom/nd/schoollife/common/bean/structure/CommunityTagInfoBean;)I
pop
L3:
aload 0
getfield com/nd/schoollife/ui/community/activity/AlterCommunitySignActivity$CommunitySignGridListener/this$0 Lcom/nd/schoollife/ui/community/activity/AlterCommunitySignActivity;
invokestatic com/nd/schoollife/ui/community/activity/AlterCommunitySignActivity/access$700(Lcom/nd/schoollife/ui/community/activity/AlterCommunitySignActivity;)V
return
L2:
aload 0
getfield com/nd/schoollife/ui/community/activity/AlterCommunitySignActivity$CommunitySignGridListener/this$0 Lcom/nd/schoollife/ui/community/activity/AlterCommunitySignActivity;
invokestatic com/nd/schoollife/ui/community/activity/AlterCommunitySignActivity/access$600(Lcom/nd/schoollife/ui/community/activity/AlterCommunitySignActivity;)Lcom/nd/schoollife/ui/community/adapter/CommunityTagList;
aload 1
invokevirtual com/nd/schoollife/ui/team/view/ExtCheckButton/getText()Ljava/lang/CharSequence;
invokeinterface java/lang/CharSequence/toString()Ljava/lang/String; 0
invokevirtual com/nd/schoollife/ui/community/adapter/CommunityTagList/getTagInfoByName(Ljava/lang/String;)Lcom/nd/schoollife/common/bean/structure/CommunityTagInfoBean;
astore 1
aload 0
getfield com/nd/schoollife/ui/community/activity/AlterCommunitySignActivity$CommunitySignGridListener/this$0 Lcom/nd/schoollife/ui/community/activity/AlterCommunitySignActivity;
invokestatic com/nd/schoollife/ui/community/activity/AlterCommunitySignActivity/access$500(Lcom/nd/schoollife/ui/community/activity/AlterCommunitySignActivity;)Lcom/nd/schoollife/ui/community/adapter/CommunityTagList;
aload 1
invokevirtual com/nd/schoollife/ui/community/adapter/CommunityTagList/remove(Lcom/nd/schoollife/common/bean/structure/CommunityTagInfoBean;)Z
pop
goto L3
.limit locals 7
.limit stack 3
.end method
