.bytecode 50.0
.class synchronized com/nd/schoollife/ui/community/activity/CommunityHomeActivity$9
.super java/lang/Object
.implements com/nd/schoollife/ui/community/task/CommunityTask$CommunityTaskCallback
.enclosing method com/nd/schoollife/ui/community/activity/CommunityHomeActivity/onDismissCommunity()V
.inner class inner com/nd/schoollife/ui/community/activity/CommunityHomeActivity$9
.inner class inner com/nd/schoollife/ui/community/activity/CommunityHomeActivity$9$1
.inner class inner com/nd/schoollife/ui/community/activity/CommunityHomeActivity$9$2

.field final synthetic 'this$0' Lcom/nd/schoollife/ui/community/activity/CommunityHomeActivity;

.method <init>(Lcom/nd/schoollife/ui/community/activity/CommunityHomeActivity;)V
aload 0
aload 1
putfield com/nd/schoollife/ui/community/activity/CommunityHomeActivity$9/this$0 Lcom/nd/schoollife/ui/community/activity/CommunityHomeActivity;
aload 0
invokespecial java/lang/Object/<init>()V
return
.limit locals 2
.limit stack 2
.end method

.method public onProcessPreExecute()V
aload 0
getfield com/nd/schoollife/ui/community/activity/CommunityHomeActivity$9/this$0 Lcom/nd/schoollife/ui/community/activity/CommunityHomeActivity;
ldc ""
ldc ""
invokevirtual com/nd/schoollife/ui/community/activity/CommunityHomeActivity/showSubmitingDialog(Ljava/lang/String;Ljava/lang/String;)V
return
.limit locals 1
.limit stack 3
.end method

.method public transient onProcessingExecute([Ljava/lang/Object;)V
return
.limit locals 2
.limit stack 0
.end method

.method public onProcessingPostExecute(Ljava/lang/Object;)V
aload 0
getfield com/nd/schoollife/ui/community/activity/CommunityHomeActivity$9/this$0 Lcom/nd/schoollife/ui/community/activity/CommunityHomeActivity;
invokevirtual com/nd/schoollife/ui/community/activity/CommunityHomeActivity/dismissSubmitingDialog()V
aload 1
ifnull L0
aload 1
instanceof com/nd/schoollife/common/bean/SchoolLifeResultBase
ifeq L0
aload 1
checkcast com/nd/schoollife/common/bean/SchoolLifeResultBase
invokevirtual com/nd/schoollife/common/bean/SchoolLifeResultBase/getResultCode()I
sipush 200
if_icmpne L0
aload 0
getfield com/nd/schoollife/ui/community/activity/CommunityHomeActivity$9/this$0 Lcom/nd/schoollife/ui/community/activity/CommunityHomeActivity;
aload 0
getfield com/nd/schoollife/ui/community/activity/CommunityHomeActivity$9/this$0 Lcom/nd/schoollife/ui/community/activity/CommunityHomeActivity;
invokestatic com/nd/schoollife/ui/community/activity/CommunityHomeActivity/access$1100(Lcom/nd/schoollife/ui/community/activity/CommunityHomeActivity;)Landroid/content/Context;
getstatic com/nd/schoollife/R$string/result I
invokevirtual android/content/Context/getString(I)Ljava/lang/String;
aload 0
getfield com/nd/schoollife/ui/community/activity/CommunityHomeActivity$9/this$0 Lcom/nd/schoollife/ui/community/activity/CommunityHomeActivity;
invokestatic com/nd/schoollife/ui/community/activity/CommunityHomeActivity/access$1200(Lcom/nd/schoollife/ui/community/activity/CommunityHomeActivity;)Landroid/content/Context;
getstatic com/nd/schoollife/R$string/commit_sucs I
invokevirtual android/content/Context/getString(I)Ljava/lang/String;
aload 0
getfield com/nd/schoollife/ui/community/activity/CommunityHomeActivity$9/this$0 Lcom/nd/schoollife/ui/community/activity/CommunityHomeActivity;
invokestatic com/nd/schoollife/ui/community/activity/CommunityHomeActivity/access$1300(Lcom/nd/schoollife/ui/community/activity/CommunityHomeActivity;)Landroid/content/Context;
getstatic com/nd/schoollife/R$string/confirm I
invokevirtual android/content/Context/getString(I)Ljava/lang/String;
ldc ""
new com/nd/schoollife/ui/community/activity/CommunityHomeActivity$9$1
dup
aload 0
invokespecial com/nd/schoollife/ui/community/activity/CommunityHomeActivity$9$1/<init>(Lcom/nd/schoollife/ui/community/activity/CommunityHomeActivity$9;)V
aconst_null
invokevirtual com/nd/schoollife/ui/community/activity/CommunityHomeActivity/showConfirmDialog(Ljava/lang/String;Ljava/lang/String;Ljava/lang/String;Ljava/lang/String;Landroid/view/View$OnClickListener;Landroid/view/View$OnClickListener;)V
return
L0:
aload 0
getfield com/nd/schoollife/ui/community/activity/CommunityHomeActivity$9/this$0 Lcom/nd/schoollife/ui/community/activity/CommunityHomeActivity;
aload 0
getfield com/nd/schoollife/ui/community/activity/CommunityHomeActivity$9/this$0 Lcom/nd/schoollife/ui/community/activity/CommunityHomeActivity;
invokestatic com/nd/schoollife/ui/community/activity/CommunityHomeActivity/access$1400(Lcom/nd/schoollife/ui/community/activity/CommunityHomeActivity;)Landroid/content/Context;
getstatic com/nd/schoollife/R$string/result I
invokevirtual android/content/Context/getString(I)Ljava/lang/String;
aload 0
getfield com/nd/schoollife/ui/community/activity/CommunityHomeActivity$9/this$0 Lcom/nd/schoollife/ui/community/activity/CommunityHomeActivity;
invokestatic com/nd/schoollife/ui/community/activity/CommunityHomeActivity/access$1500(Lcom/nd/schoollife/ui/community/activity/CommunityHomeActivity;)Landroid/content/Context;
getstatic com/nd/schoollife/R$string/commit_faild I
invokevirtual android/content/Context/getString(I)Ljava/lang/String;
aload 0
getfield com/nd/schoollife/ui/community/activity/CommunityHomeActivity$9/this$0 Lcom/nd/schoollife/ui/community/activity/CommunityHomeActivity;
invokestatic com/nd/schoollife/ui/community/activity/CommunityHomeActivity/access$1600(Lcom/nd/schoollife/ui/community/activity/CommunityHomeActivity;)Landroid/content/Context;
getstatic com/nd/schoollife/R$string/confirm I
invokevirtual android/content/Context/getString(I)Ljava/lang/String;
ldc ""
new com/nd/schoollife/ui/community/activity/CommunityHomeActivity$9$2
dup
aload 0
invokespecial com/nd/schoollife/ui/community/activity/CommunityHomeActivity$9$2/<init>(Lcom/nd/schoollife/ui/community/activity/CommunityHomeActivity$9;)V
aconst_null
invokevirtual com/nd/schoollife/ui/community/activity/CommunityHomeActivity/showConfirmDialog(Ljava/lang/String;Ljava/lang/String;Ljava/lang/String;Ljava/lang/String;Landroid/view/View$OnClickListener;Landroid/view/View$OnClickListener;)V
return
.limit locals 2
.limit stack 8
.end method
