.bytecode 50.0
.class synchronized com/nd/android/u/tast/birthday/view/HorizontalListView$3
.super android/view/GestureDetector$SimpleOnGestureListener
.enclosing method com/nd/android/u/tast/birthday/view/HorizontalListView
.inner class inner com/nd/android/u/tast/birthday/view/HorizontalListView$3

.field final synthetic 'this$0' Lcom/nd/android/u/tast/birthday/view/HorizontalListView;

.method <init>(Lcom/nd/android/u/tast/birthday/view/HorizontalListView;)V
aload 0
aload 1
putfield com/nd/android/u/tast/birthday/view/HorizontalListView$3/this$0 Lcom/nd/android/u/tast/birthday/view/HorizontalListView;
aload 0
invokespecial android/view/GestureDetector$SimpleOnGestureListener/<init>()V
return
.limit locals 2
.limit stack 2
.end method

.method public onDown(Landroid/view/MotionEvent;)Z
aload 0
getfield com/nd/android/u/tast/birthday/view/HorizontalListView$3/this$0 Lcom/nd/android/u/tast/birthday/view/HorizontalListView;
aload 1
invokevirtual com/nd/android/u/tast/birthday/view/HorizontalListView/onDown(Landroid/view/MotionEvent;)Z
ireturn
.limit locals 2
.limit stack 2
.end method

.method public onFling(Landroid/view/MotionEvent;Landroid/view/MotionEvent;FF)Z
aload 0
getfield com/nd/android/u/tast/birthday/view/HorizontalListView$3/this$0 Lcom/nd/android/u/tast/birthday/view/HorizontalListView;
aload 1
aload 2
fload 3
fload 4
invokevirtual com/nd/android/u/tast/birthday/view/HorizontalListView/onFling(Landroid/view/MotionEvent;Landroid/view/MotionEvent;FF)Z
ireturn
.limit locals 5
.limit stack 5
.end method

.method public onScroll(Landroid/view/MotionEvent;Landroid/view/MotionEvent;FF)Z
.catch all from L0 to L1 using L2
.catch all from L3 to L4 using L2
aload 0
getfield com/nd/android/u/tast/birthday/view/HorizontalListView$3/this$0 Lcom/nd/android/u/tast/birthday/view/HorizontalListView;
astore 1
aload 1
monitorenter
L0:
aload 0
getfield com/nd/android/u/tast/birthday/view/HorizontalListView$3/this$0 Lcom/nd/android/u/tast/birthday/view/HorizontalListView;
aload 0
getfield com/nd/android/u/tast/birthday/view/HorizontalListView$3/this$0 Lcom/nd/android/u/tast/birthday/view/HorizontalListView;
invokestatic com/nd/android/u/tast/birthday/view/HorizontalListView/access$200(Lcom/nd/android/u/tast/birthday/view/HorizontalListView;)I
fload 3
f2i
iadd
invokestatic com/nd/android/u/tast/birthday/view/HorizontalListView/access$202(Lcom/nd/android/u/tast/birthday/view/HorizontalListView;I)I
pop
aload 1
monitorexit
L1:
aload 0
getfield com/nd/android/u/tast/birthday/view/HorizontalListView$3/this$0 Lcom/nd/android/u/tast/birthday/view/HorizontalListView;
invokevirtual com/nd/android/u/tast/birthday/view/HorizontalListView/requestLayout()V
iconst_1
ireturn
L2:
astore 2
L3:
aload 1
monitorexit
L4:
aload 2
athrow
.limit locals 5
.limit stack 3
.end method

.method public onSingleTapConfirmed(Landroid/view/MotionEvent;)Z
new android/graphics/Rect
dup
invokespecial android/graphics/Rect/<init>()V
astore 5
iconst_0
istore 2
L0:
iload 2
aload 0
getfield com/nd/android/u/tast/birthday/view/HorizontalListView$3/this$0 Lcom/nd/android/u/tast/birthday/view/HorizontalListView;
invokevirtual com/nd/android/u/tast/birthday/view/HorizontalListView/getChildCount()I
if_icmpge L1
aload 0
getfield com/nd/android/u/tast/birthday/view/HorizontalListView$3/this$0 Lcom/nd/android/u/tast/birthday/view/HorizontalListView;
iload 2
invokevirtual com/nd/android/u/tast/birthday/view/HorizontalListView/getChildAt(I)Landroid/view/View;
astore 6
aload 6
invokevirtual android/view/View/getLeft()I
istore 3
aload 6
invokevirtual android/view/View/getRight()I
istore 4
aload 5
iload 3
aload 6
invokevirtual android/view/View/getTop()I
iload 4
aload 6
invokevirtual android/view/View/getBottom()I
invokevirtual android/graphics/Rect/set(IIII)V
aload 5
aload 1
invokevirtual android/view/MotionEvent/getX()F
f2i
aload 1
invokevirtual android/view/MotionEvent/getY()F
f2i
invokevirtual android/graphics/Rect/contains(II)Z
ifeq L2
aload 0
getfield com/nd/android/u/tast/birthday/view/HorizontalListView$3/this$0 Lcom/nd/android/u/tast/birthday/view/HorizontalListView;
invokestatic com/nd/android/u/tast/birthday/view/HorizontalListView/access$300(Lcom/nd/android/u/tast/birthday/view/HorizontalListView;)Landroid/widget/AdapterView$OnItemClickListener;
ifnull L3
aload 0
getfield com/nd/android/u/tast/birthday/view/HorizontalListView$3/this$0 Lcom/nd/android/u/tast/birthday/view/HorizontalListView;
invokestatic com/nd/android/u/tast/birthday/view/HorizontalListView/access$300(Lcom/nd/android/u/tast/birthday/view/HorizontalListView;)Landroid/widget/AdapterView$OnItemClickListener;
aload 0
getfield com/nd/android/u/tast/birthday/view/HorizontalListView$3/this$0 Lcom/nd/android/u/tast/birthday/view/HorizontalListView;
aload 6
aload 0
getfield com/nd/android/u/tast/birthday/view/HorizontalListView$3/this$0 Lcom/nd/android/u/tast/birthday/view/HorizontalListView;
invokestatic com/nd/android/u/tast/birthday/view/HorizontalListView/access$400(Lcom/nd/android/u/tast/birthday/view/HorizontalListView;)I
iconst_1
iadd
iload 2
iadd
aload 0
getfield com/nd/android/u/tast/birthday/view/HorizontalListView$3/this$0 Lcom/nd/android/u/tast/birthday/view/HorizontalListView;
invokestatic com/nd/android/u/tast/birthday/view/HorizontalListView/access$500(Lcom/nd/android/u/tast/birthday/view/HorizontalListView;)Landroid/widget/ListAdapter;
aload 0
getfield com/nd/android/u/tast/birthday/view/HorizontalListView$3/this$0 Lcom/nd/android/u/tast/birthday/view/HorizontalListView;
invokestatic com/nd/android/u/tast/birthday/view/HorizontalListView/access$400(Lcom/nd/android/u/tast/birthday/view/HorizontalListView;)I
iconst_1
iadd
iload 2
iadd
invokeinterface android/widget/ListAdapter/getItemId(I)J 1
invokeinterface android/widget/AdapterView$OnItemClickListener/onItemClick(Landroid/widget/AdapterView;Landroid/view/View;IJ)V 5
L3:
aload 0
getfield com/nd/android/u/tast/birthday/view/HorizontalListView$3/this$0 Lcom/nd/android/u/tast/birthday/view/HorizontalListView;
invokestatic com/nd/android/u/tast/birthday/view/HorizontalListView/access$600(Lcom/nd/android/u/tast/birthday/view/HorizontalListView;)Landroid/widget/AdapterView$OnItemSelectedListener;
ifnull L1
aload 0
getfield com/nd/android/u/tast/birthday/view/HorizontalListView$3/this$0 Lcom/nd/android/u/tast/birthday/view/HorizontalListView;
invokestatic com/nd/android/u/tast/birthday/view/HorizontalListView/access$600(Lcom/nd/android/u/tast/birthday/view/HorizontalListView;)Landroid/widget/AdapterView$OnItemSelectedListener;
aload 0
getfield com/nd/android/u/tast/birthday/view/HorizontalListView$3/this$0 Lcom/nd/android/u/tast/birthday/view/HorizontalListView;
aload 6
aload 0
getfield com/nd/android/u/tast/birthday/view/HorizontalListView$3/this$0 Lcom/nd/android/u/tast/birthday/view/HorizontalListView;
invokestatic com/nd/android/u/tast/birthday/view/HorizontalListView/access$400(Lcom/nd/android/u/tast/birthday/view/HorizontalListView;)I
iconst_1
iadd
iload 2
iadd
aload 0
getfield com/nd/android/u/tast/birthday/view/HorizontalListView$3/this$0 Lcom/nd/android/u/tast/birthday/view/HorizontalListView;
invokestatic com/nd/android/u/tast/birthday/view/HorizontalListView/access$500(Lcom/nd/android/u/tast/birthday/view/HorizontalListView;)Landroid/widget/ListAdapter;
aload 0
getfield com/nd/android/u/tast/birthday/view/HorizontalListView$3/this$0 Lcom/nd/android/u/tast/birthday/view/HorizontalListView;
invokestatic com/nd/android/u/tast/birthday/view/HorizontalListView/access$400(Lcom/nd/android/u/tast/birthday/view/HorizontalListView;)I
iconst_1
iadd
iload 2
iadd
invokeinterface android/widget/ListAdapter/getItemId(I)J 1
invokeinterface android/widget/AdapterView$OnItemSelectedListener/onItemSelected(Landroid/widget/AdapterView;Landroid/view/View;IJ)V 5
L1:
iconst_1
ireturn
L2:
iload 2
iconst_1
iadd
istore 2
goto L0
.limit locals 7
.limit stack 7
.end method
