.bytecode 50.0
.class synchronized com/nd/android/u/tast/birthday/view/WaterFallBirthdayLayout$2
.super com/common/android/utils/task/genericTask/TaskAdapter
.enclosing method com/nd/android/u/tast/birthday/view/WaterFallBirthdayLayout
.inner class inner com/nd/android/u/tast/birthday/view/WaterFallBirthdayLayout$2

.field final synthetic 'this$0' Lcom/nd/android/u/tast/birthday/view/WaterFallBirthdayLayout;

.method <init>(Lcom/nd/android/u/tast/birthday/view/WaterFallBirthdayLayout;)V
aload 0
aload 1
putfield com/nd/android/u/tast/birthday/view/WaterFallBirthdayLayout$2/this$0 Lcom/nd/android/u/tast/birthday/view/WaterFallBirthdayLayout;
aload 0
invokespecial com/common/android/utils/task/genericTask/TaskAdapter/<init>()V
return
.limit locals 2
.limit stack 2
.end method

.method public onPostExecute(Lcom/common/android/utils/task/genericTask/GenericTask;Lcom/common/android/utils/task/genericTask/TaskResult;)V
.catch all from L0 to L1 using L2
.catch all from L3 to L4 using L2
.catch all from L5 to L6 using L2
.catch all from L6 to L7 using L2
.catch all from L8 to L9 using L2
aload 0
getfield com/nd/android/u/tast/birthday/view/WaterFallBirthdayLayout$2/this$0 Lcom/nd/android/u/tast/birthday/view/WaterFallBirthdayLayout;
invokestatic com/nd/android/u/tast/birthday/view/WaterFallBirthdayLayout/access$1100(Lcom/nd/android/u/tast/birthday/view/WaterFallBirthdayLayout;)Landroid/widget/LinearLayout;
bipush 8
invokevirtual android/widget/LinearLayout/setVisibility(I)V
aload 0
getfield com/nd/android/u/tast/birthday/view/WaterFallBirthdayLayout$2/this$0 Lcom/nd/android/u/tast/birthday/view/WaterFallBirthdayLayout;
iconst_0
invokestatic com/nd/android/u/tast/birthday/view/WaterFallBirthdayLayout/access$602(Lcom/nd/android/u/tast/birthday/view/WaterFallBirthdayLayout;Z)Z
pop
aload 0
getfield com/nd/android/u/tast/birthday/view/WaterFallBirthdayLayout$2/this$0 Lcom/nd/android/u/tast/birthday/view/WaterFallBirthdayLayout;
invokestatic com/nd/android/u/tast/birthday/view/WaterFallBirthdayLayout/access$1200(Lcom/nd/android/u/tast/birthday/view/WaterFallBirthdayLayout;)Ljava/util/Vector;
ifnull L7
aload 0
getfield com/nd/android/u/tast/birthday/view/WaterFallBirthdayLayout$2/this$0 Lcom/nd/android/u/tast/birthday/view/WaterFallBirthdayLayout;
invokestatic com/nd/android/u/tast/birthday/view/WaterFallBirthdayLayout/access$1200(Lcom/nd/android/u/tast/birthday/view/WaterFallBirthdayLayout;)Ljava/util/Vector;
astore 1
aload 1
monitorenter
L0:
getstatic com/common/android/utils/task/genericTask/TaskResult/OK Lcom/common/android/utils/task/genericTask/TaskResult;
aload 2
if_acmpne L5
aload 0
getfield com/nd/android/u/tast/birthday/view/WaterFallBirthdayLayout$2/this$0 Lcom/nd/android/u/tast/birthday/view/WaterFallBirthdayLayout;
invokestatic com/nd/android/u/tast/birthday/view/WaterFallBirthdayLayout/access$1200(Lcom/nd/android/u/tast/birthday/view/WaterFallBirthdayLayout;)Ljava/util/Vector;
ifnull L5
aload 0
getfield com/nd/android/u/tast/birthday/view/WaterFallBirthdayLayout$2/this$0 Lcom/nd/android/u/tast/birthday/view/WaterFallBirthdayLayout;
invokestatic com/nd/android/u/tast/birthday/view/WaterFallBirthdayLayout/access$1200(Lcom/nd/android/u/tast/birthday/view/WaterFallBirthdayLayout;)Ljava/util/Vector;
invokevirtual java/util/Vector/size()I
ifle L5
L1:
iconst_0
istore 3
L3:
iload 3
aload 0
getfield com/nd/android/u/tast/birthday/view/WaterFallBirthdayLayout$2/this$0 Lcom/nd/android/u/tast/birthday/view/WaterFallBirthdayLayout;
invokestatic com/nd/android/u/tast/birthday/view/WaterFallBirthdayLayout/access$1200(Lcom/nd/android/u/tast/birthday/view/WaterFallBirthdayLayout;)Ljava/util/Vector;
invokevirtual java/util/Vector/size()I
if_icmpge L5
aload 0
getfield com/nd/android/u/tast/birthday/view/WaterFallBirthdayLayout$2/this$0 Lcom/nd/android/u/tast/birthday/view/WaterFallBirthdayLayout;
invokestatic com/nd/android/u/tast/birthday/view/WaterFallBirthdayLayout/access$1200(Lcom/nd/android/u/tast/birthday/view/WaterFallBirthdayLayout;)Ljava/util/Vector;
iload 3
invokevirtual java/util/Vector/get(I)Ljava/lang/Object;
checkcast com/nd/android/u/tast/birthday/view/FlowBirthdayView
astore 2
aload 0
getfield com/nd/android/u/tast/birthday/view/WaterFallBirthdayLayout$2/this$0 Lcom/nd/android/u/tast/birthday/view/WaterFallBirthdayLayout;
invokestatic com/nd/android/u/tast/birthday/view/WaterFallBirthdayLayout/access$1300(Lcom/nd/android/u/tast/birthday/view/WaterFallBirthdayLayout;)Z
ifne L10
aload 0
getfield com/nd/android/u/tast/birthday/view/WaterFallBirthdayLayout$2/this$0 Lcom/nd/android/u/tast/birthday/view/WaterFallBirthdayLayout;
aload 2
invokevirtual com/nd/android/u/tast/birthday/view/WaterFallBirthdayLayout/addFlowView(Lcom/nd/android/u/tast/birthday/view/FlowBirthdayView;)V
L4:
goto L10
L5:
aload 0
getfield com/nd/android/u/tast/birthday/view/WaterFallBirthdayLayout$2/this$0 Lcom/nd/android/u/tast/birthday/view/WaterFallBirthdayLayout;
invokestatic com/nd/android/u/tast/birthday/view/WaterFallBirthdayLayout/access$1200(Lcom/nd/android/u/tast/birthday/view/WaterFallBirthdayLayout;)Ljava/util/Vector;
ifnull L6
aload 0
getfield com/nd/android/u/tast/birthday/view/WaterFallBirthdayLayout$2/this$0 Lcom/nd/android/u/tast/birthday/view/WaterFallBirthdayLayout;
invokestatic com/nd/android/u/tast/birthday/view/WaterFallBirthdayLayout/access$1200(Lcom/nd/android/u/tast/birthday/view/WaterFallBirthdayLayout;)Ljava/util/Vector;
invokevirtual java/util/Vector/clear()V
L6:
aload 0
getfield com/nd/android/u/tast/birthday/view/WaterFallBirthdayLayout$2/this$0 Lcom/nd/android/u/tast/birthday/view/WaterFallBirthdayLayout;
iconst_1
invokestatic com/nd/android/u/tast/birthday/view/WaterFallBirthdayLayout/access$102(Lcom/nd/android/u/tast/birthday/view/WaterFallBirthdayLayout;Z)Z
pop
aload 1
monitorexit
L7:
aload 0
getfield com/nd/android/u/tast/birthday/view/WaterFallBirthdayLayout$2/this$0 Lcom/nd/android/u/tast/birthday/view/WaterFallBirthdayLayout;
invokestatic com/nd/android/u/tast/birthday/view/WaterFallBirthdayLayout/access$1400(Lcom/nd/android/u/tast/birthday/view/WaterFallBirthdayLayout;)Landroid/widget/LinearLayout;
invokevirtual android/widget/LinearLayout/getVisibility()I
ifne L11
aload 0
getfield com/nd/android/u/tast/birthday/view/WaterFallBirthdayLayout$2/this$0 Lcom/nd/android/u/tast/birthday/view/WaterFallBirthdayLayout;
invokestatic com/nd/android/u/tast/birthday/view/WaterFallBirthdayLayout/access$1400(Lcom/nd/android/u/tast/birthday/view/WaterFallBirthdayLayout;)Landroid/widget/LinearLayout;
bipush 8
invokevirtual android/widget/LinearLayout/setVisibility(I)V
L11:
aload 0
getfield com/nd/android/u/tast/birthday/view/WaterFallBirthdayLayout$2/this$0 Lcom/nd/android/u/tast/birthday/view/WaterFallBirthdayLayout;
invokestatic com/nd/android/u/tast/birthday/view/WaterFallBirthdayLayout/access$200(Lcom/nd/android/u/tast/birthday/view/WaterFallBirthdayLayout;)Ljava/util/ArrayList;
ifnull L12
aload 0
getfield com/nd/android/u/tast/birthday/view/WaterFallBirthdayLayout$2/this$0 Lcom/nd/android/u/tast/birthday/view/WaterFallBirthdayLayout;
invokestatic com/nd/android/u/tast/birthday/view/WaterFallBirthdayLayout/access$200(Lcom/nd/android/u/tast/birthday/view/WaterFallBirthdayLayout;)Ljava/util/ArrayList;
invokevirtual java/util/ArrayList/size()I
ifne L13
L12:
aload 0
getfield com/nd/android/u/tast/birthday/view/WaterFallBirthdayLayout$2/this$0 Lcom/nd/android/u/tast/birthday/view/WaterFallBirthdayLayout;
invokestatic com/nd/android/u/tast/birthday/view/WaterFallBirthdayLayout/access$1500(Lcom/nd/android/u/tast/birthday/view/WaterFallBirthdayLayout;)Landroid/widget/TextView;
getstatic com/nd/android/u/tasklib/R$string/no_data_now I
invokevirtual android/widget/TextView/setText(I)V
aload 0
getfield com/nd/android/u/tast/birthday/view/WaterFallBirthdayLayout$2/this$0 Lcom/nd/android/u/tast/birthday/view/WaterFallBirthdayLayout;
invokestatic com/nd/android/u/tast/birthday/view/WaterFallBirthdayLayout/access$1500(Lcom/nd/android/u/tast/birthday/view/WaterFallBirthdayLayout;)Landroid/widget/TextView;
iconst_0
invokevirtual android/widget/TextView/setVisibility(I)V
L14:
aload 0
getfield com/nd/android/u/tast/birthday/view/WaterFallBirthdayLayout$2/this$0 Lcom/nd/android/u/tast/birthday/view/WaterFallBirthdayLayout;
invokestatic com/nd/android/u/tast/birthday/view/WaterFallBirthdayLayout/access$1600(Lcom/nd/android/u/tast/birthday/view/WaterFallBirthdayLayout;)Landroid/os/Handler;
ifnull L15
aload 0
getfield com/nd/android/u/tast/birthday/view/WaterFallBirthdayLayout$2/this$0 Lcom/nd/android/u/tast/birthday/view/WaterFallBirthdayLayout;
invokestatic com/nd/android/u/tast/birthday/view/WaterFallBirthdayLayout/access$1600(Lcom/nd/android/u/tast/birthday/view/WaterFallBirthdayLayout;)Landroid/os/Handler;
bipush 24
invokevirtual android/os/Handler/sendEmptyMessage(I)Z
pop
L15:
return
L2:
astore 2
L8:
aload 1
monitorexit
L9:
aload 2
athrow
L13:
aload 0
getfield com/nd/android/u/tast/birthday/view/WaterFallBirthdayLayout$2/this$0 Lcom/nd/android/u/tast/birthday/view/WaterFallBirthdayLayout;
invokestatic com/nd/android/u/tast/birthday/view/WaterFallBirthdayLayout/access$1500(Lcom/nd/android/u/tast/birthday/view/WaterFallBirthdayLayout;)Landroid/widget/TextView;
bipush 8
invokevirtual android/widget/TextView/setVisibility(I)V
goto L14
L10:
iload 3
iconst_1
iadd
istore 3
goto L3
.limit locals 4
.limit stack 2
.end method
