.bytecode 50.0
.class synchronized com/nd/android/u/tast/birthday/view/WaterFallBirthdayLayout$3
.super com/common/android/utils/task/genericTask/TaskAdapter
.enclosing method com/nd/android/u/tast/birthday/view/WaterFallBirthdayLayout
.inner class inner com/nd/android/u/tast/birthday/view/WaterFallBirthdayLayout$3

.field final synthetic 'this$0' Lcom/nd/android/u/tast/birthday/view/WaterFallBirthdayLayout;

.method <init>(Lcom/nd/android/u/tast/birthday/view/WaterFallBirthdayLayout;)V
aload 0
aload 1
putfield com/nd/android/u/tast/birthday/view/WaterFallBirthdayLayout$3/this$0 Lcom/nd/android/u/tast/birthday/view/WaterFallBirthdayLayout;
aload 0
invokespecial com/common/android/utils/task/genericTask/TaskAdapter/<init>()V
return
.limit locals 2
.limit stack 2
.end method

.method public onPostExecute(Lcom/common/android/utils/task/genericTask/GenericTask;Lcom/common/android/utils/task/genericTask/TaskResult;)V
aload 0
getfield com/nd/android/u/tast/birthday/view/WaterFallBirthdayLayout$3/this$0 Lcom/nd/android/u/tast/birthday/view/WaterFallBirthdayLayout;
invokestatic com/nd/android/u/tast/birthday/view/WaterFallBirthdayLayout/access$200(Lcom/nd/android/u/tast/birthday/view/WaterFallBirthdayLayout;)Ljava/util/ArrayList;
ifnull L0
aload 0
getfield com/nd/android/u/tast/birthday/view/WaterFallBirthdayLayout$3/this$0 Lcom/nd/android/u/tast/birthday/view/WaterFallBirthdayLayout;
invokestatic com/nd/android/u/tast/birthday/view/WaterFallBirthdayLayout/access$200(Lcom/nd/android/u/tast/birthday/view/WaterFallBirthdayLayout;)Ljava/util/ArrayList;
invokevirtual java/util/ArrayList/size()I
ifne L1
L0:
aload 0
getfield com/nd/android/u/tast/birthday/view/WaterFallBirthdayLayout$3/this$0 Lcom/nd/android/u/tast/birthday/view/WaterFallBirthdayLayout;
invokestatic com/nd/android/u/tast/birthday/view/WaterFallBirthdayLayout/access$1500(Lcom/nd/android/u/tast/birthday/view/WaterFallBirthdayLayout;)Landroid/widget/TextView;
iconst_0
invokevirtual android/widget/TextView/setVisibility(I)V
aload 0
getfield com/nd/android/u/tast/birthday/view/WaterFallBirthdayLayout$3/this$0 Lcom/nd/android/u/tast/birthday/view/WaterFallBirthdayLayout;
invokestatic com/nd/android/u/tast/birthday/view/WaterFallBirthdayLayout/access$1400(Lcom/nd/android/u/tast/birthday/view/WaterFallBirthdayLayout;)Landroid/widget/LinearLayout;
bipush 8
invokevirtual android/widget/LinearLayout/setVisibility(I)V
return
L1:
aload 0
getfield com/nd/android/u/tast/birthday/view/WaterFallBirthdayLayout$3/this$0 Lcom/nd/android/u/tast/birthday/view/WaterFallBirthdayLayout;
iconst_0
invokestatic com/nd/android/u/tast/birthday/view/WaterFallBirthdayLayout/access$1302(Lcom/nd/android/u/tast/birthday/view/WaterFallBirthdayLayout;Z)Z
pop
aload 0
getfield com/nd/android/u/tast/birthday/view/WaterFallBirthdayLayout$3/this$0 Lcom/nd/android/u/tast/birthday/view/WaterFallBirthdayLayout;
invokevirtual com/nd/android/u/tast/birthday/view/WaterFallBirthdayLayout/refreshWaterFlow()V
return
.limit locals 3
.limit stack 2
.end method
