.bytecode 50.0
.class synchronized com/hisun/b2c/api/core/IPOSUtils$2
.super java/lang/Object
.implements java/lang/Runnable
.enclosing method com/hisun/b2c/api/core/IPOSUtils
.inner class inner com/hisun/b2c/api/core/IPOSUtils$2

.field final synthetic 'this$0' Lcom/hisun/b2c/api/core/IPOSUtils;

.method <init>(Lcom/hisun/b2c/api/core/IPOSUtils;)V
aload 0
aload 1
putfield com/hisun/b2c/api/core/IPOSUtils$2/this$0 Lcom/hisun/b2c/api/core/IPOSUtils;
aload 0
invokespecial java/lang/Object/<init>()V
return
.limit locals 2
.limit stack 2
.end method

.method public run()V
.catch java/lang/Exception from L0 to L1 using L2
.catch all from L0 to L1 using L3
.catch java/lang/Exception from L4 to L5 using L2
.catch all from L4 to L5 using L3
.catch java/lang/Exception from L6 to L7 using L2
.catch all from L6 to L7 using L3
.catch java/lang/Exception from L8 to L9 using L2
.catch all from L8 to L9 using L3
.catch all from L10 to L11 using L3
.catch java/lang/Exception from L12 to L13 using L2
.catch all from L12 to L13 using L3
.catch java/lang/Exception from L14 to L15 using L2
.catch all from L14 to L15 using L3
L0:
aload 0
getfield com/hisun/b2c/api/core/IPOSUtils$2/this$0 Lcom/hisun/b2c/api/core/IPOSUtils;
invokestatic com/hisun/b2c/api/core/IPOSUtils/access$6(Lcom/hisun/b2c/api/core/IPOSUtils;)V
aload 0
getfield com/hisun/b2c/api/core/IPOSUtils$2/this$0 Lcom/hisun/b2c/api/core/IPOSUtils;
invokestatic com/hisun/b2c/api/core/IPOSUtils/access$0(Lcom/hisun/b2c/api/core/IPOSUtils;)Z
istore 1
L1:
iload 1
ifeq L4
aload 0
getfield com/hisun/b2c/api/core/IPOSUtils$2/this$0 Lcom/hisun/b2c/api/core/IPOSUtils;
sipush 402
invokevirtual com/hisun/b2c/api/core/IPOSUtils/sendMessage(I)V
return
L4:
aload 0
getfield com/hisun/b2c/api/core/IPOSUtils$2/this$0 Lcom/hisun/b2c/api/core/IPOSUtils;
invokestatic com/hisun/b2c/api/core/IPOSUtils/access$7(Lcom/hisun/b2c/api/core/IPOSUtils;)Ljava/util/Map;
astore 2
L5:
aload 2
ifnull L14
L6:
ldc "000000"
aload 2
ldc "RSPCD"
invokeinterface java/util/Map/get(Ljava/lang/Object;)Ljava/lang/Object; 1
invokevirtual java/lang/String/equals(Ljava/lang/Object;)Z
ifeq L8
aload 2
ldc "SESSIONID"
invokeinterface java/util/Map/get(Ljava/lang/Object;)Ljava/lang/Object; 1
checkcast java/lang/String
astore 2
aload 0
getfield com/hisun/b2c/api/core/IPOSUtils$2/this$0 Lcom/hisun/b2c/api/core/IPOSUtils;
invokestatic com/hisun/b2c/api/core/IPOSUtils/access$8(Lcom/hisun/b2c/api/core/IPOSUtils;)Landroid/os/Handler;
ifnull L7
aload 0
getfield com/hisun/b2c/api/core/IPOSUtils$2/this$0 Lcom/hisun/b2c/api/core/IPOSUtils;
aload 0
getfield com/hisun/b2c/api/core/IPOSUtils$2/this$0 Lcom/hisun/b2c/api/core/IPOSUtils;
invokestatic com/hisun/b2c/api/core/IPOSUtils/access$9(Lcom/hisun/b2c/api/core/IPOSUtils;)I
aload 0
getfield com/hisun/b2c/api/core/IPOSUtils$2/this$0 Lcom/hisun/b2c/api/core/IPOSUtils;
aconst_null
aload 2
ldc "\u767b\u5f55\u6210\u529f"
invokestatic com/hisun/b2c/api/core/IPOSUtils/access$10(Lcom/hisun/b2c/api/core/IPOSUtils;Ljava/lang/String;Ljava/lang/String;Ljava/lang/String;)Ljava/lang/String;
aload 0
getfield com/hisun/b2c/api/core/IPOSUtils$2/this$0 Lcom/hisun/b2c/api/core/IPOSUtils;
invokestatic com/hisun/b2c/api/core/IPOSUtils/access$8(Lcom/hisun/b2c/api/core/IPOSUtils;)Landroid/os/Handler;
invokevirtual com/hisun/b2c/api/core/IPOSUtils/sendMessage(ILjava/lang/Object;Landroid/os/Handler;)V
L7:
aload 0
getfield com/hisun/b2c/api/core/IPOSUtils$2/this$0 Lcom/hisun/b2c/api/core/IPOSUtils;
sipush 402
invokevirtual com/hisun/b2c/api/core/IPOSUtils/sendMessage(I)V
return
L8:
ldc "CLI99980"
aload 2
ldc "RSPCD"
invokeinterface java/util/Map/get(Ljava/lang/Object;)Ljava/lang/Object; 1
invokevirtual java/lang/String/equals(Ljava/lang/Object;)Z
ifeq L12
aload 2
ldc "ERRORINFO"
invokeinterface java/util/Map/get(Ljava/lang/Object;)Ljava/lang/Object; 1
checkcast java/lang/String
astore 2
aload 0
getfield com/hisun/b2c/api/core/IPOSUtils$2/this$0 Lcom/hisun/b2c/api/core/IPOSUtils;
invokestatic com/hisun/b2c/api/core/IPOSUtils/access$8(Lcom/hisun/b2c/api/core/IPOSUtils;)Landroid/os/Handler;
ifnull L7
aload 0
getfield com/hisun/b2c/api/core/IPOSUtils$2/this$0 Lcom/hisun/b2c/api/core/IPOSUtils;
aload 0
getfield com/hisun/b2c/api/core/IPOSUtils$2/this$0 Lcom/hisun/b2c/api/core/IPOSUtils;
invokestatic com/hisun/b2c/api/core/IPOSUtils/access$9(Lcom/hisun/b2c/api/core/IPOSUtils;)I
aload 0
getfield com/hisun/b2c/api/core/IPOSUtils$2/this$0 Lcom/hisun/b2c/api/core/IPOSUtils;
ldc "8002"
aconst_null
aload 2
invokestatic com/hisun/b2c/api/core/IPOSUtils/access$10(Lcom/hisun/b2c/api/core/IPOSUtils;Ljava/lang/String;Ljava/lang/String;Ljava/lang/String;)Ljava/lang/String;
aload 0
getfield com/hisun/b2c/api/core/IPOSUtils$2/this$0 Lcom/hisun/b2c/api/core/IPOSUtils;
invokestatic com/hisun/b2c/api/core/IPOSUtils/access$8(Lcom/hisun/b2c/api/core/IPOSUtils;)Landroid/os/Handler;
invokevirtual com/hisun/b2c/api/core/IPOSUtils/sendMessage(ILjava/lang/Object;Landroid/os/Handler;)V
L9:
goto L7
L2:
astore 2
L10:
aload 2
invokevirtual java/lang/Exception/printStackTrace()V
L11:
aload 0
getfield com/hisun/b2c/api/core/IPOSUtils$2/this$0 Lcom/hisun/b2c/api/core/IPOSUtils;
sipush 402
invokevirtual com/hisun/b2c/api/core/IPOSUtils/sendMessage(I)V
return
L12:
aload 2
ldc "ERRORINFO"
invokeinterface java/util/Map/get(Ljava/lang/Object;)Ljava/lang/Object; 1
checkcast java/lang/String
astore 2
aload 0
getfield com/hisun/b2c/api/core/IPOSUtils$2/this$0 Lcom/hisun/b2c/api/core/IPOSUtils;
invokestatic com/hisun/b2c/api/core/IPOSUtils/access$8(Lcom/hisun/b2c/api/core/IPOSUtils;)Landroid/os/Handler;
ifnull L7
aload 0
getfield com/hisun/b2c/api/core/IPOSUtils$2/this$0 Lcom/hisun/b2c/api/core/IPOSUtils;
aload 0
getfield com/hisun/b2c/api/core/IPOSUtils$2/this$0 Lcom/hisun/b2c/api/core/IPOSUtils;
invokestatic com/hisun/b2c/api/core/IPOSUtils/access$9(Lcom/hisun/b2c/api/core/IPOSUtils;)I
aload 0
getfield com/hisun/b2c/api/core/IPOSUtils$2/this$0 Lcom/hisun/b2c/api/core/IPOSUtils;
aconst_null
aconst_null
aload 2
invokestatic com/hisun/b2c/api/core/IPOSUtils/access$10(Lcom/hisun/b2c/api/core/IPOSUtils;Ljava/lang/String;Ljava/lang/String;Ljava/lang/String;)Ljava/lang/String;
aload 0
getfield com/hisun/b2c/api/core/IPOSUtils$2/this$0 Lcom/hisun/b2c/api/core/IPOSUtils;
invokestatic com/hisun/b2c/api/core/IPOSUtils/access$8(Lcom/hisun/b2c/api/core/IPOSUtils;)Landroid/os/Handler;
invokevirtual com/hisun/b2c/api/core/IPOSUtils/sendMessage(ILjava/lang/Object;Landroid/os/Handler;)V
L13:
goto L7
L3:
astore 2
aload 0
getfield com/hisun/b2c/api/core/IPOSUtils$2/this$0 Lcom/hisun/b2c/api/core/IPOSUtils;
sipush 402
invokevirtual com/hisun/b2c/api/core/IPOSUtils/sendMessage(I)V
aload 2
athrow
L14:
aload 0
getfield com/hisun/b2c/api/core/IPOSUtils$2/this$0 Lcom/hisun/b2c/api/core/IPOSUtils;
invokestatic com/hisun/b2c/api/core/IPOSUtils/access$8(Lcom/hisun/b2c/api/core/IPOSUtils;)Landroid/os/Handler;
ifnull L7
aload 0
getfield com/hisun/b2c/api/core/IPOSUtils$2/this$0 Lcom/hisun/b2c/api/core/IPOSUtils;
aload 0
getfield com/hisun/b2c/api/core/IPOSUtils$2/this$0 Lcom/hisun/b2c/api/core/IPOSUtils;
invokestatic com/hisun/b2c/api/core/IPOSUtils/access$9(Lcom/hisun/b2c/api/core/IPOSUtils;)I
aload 0
getfield com/hisun/b2c/api/core/IPOSUtils$2/this$0 Lcom/hisun/b2c/api/core/IPOSUtils;
aconst_null
aconst_null
ldc "\u670d\u52a1\u5fd9\uff0c\u8bf7\u7a0d\u540e\u91cd\u8bd5"
invokestatic com/hisun/b2c/api/core/IPOSUtils/access$10(Lcom/hisun/b2c/api/core/IPOSUtils;Ljava/lang/String;Ljava/lang/String;Ljava/lang/String;)Ljava/lang/String;
aload 0
getfield com/hisun/b2c/api/core/IPOSUtils$2/this$0 Lcom/hisun/b2c/api/core/IPOSUtils;
invokestatic com/hisun/b2c/api/core/IPOSUtils/access$8(Lcom/hisun/b2c/api/core/IPOSUtils;)Landroid/os/Handler;
invokevirtual com/hisun/b2c/api/core/IPOSUtils/sendMessage(ILjava/lang/Object;Landroid/os/Handler;)V
L15:
goto L7
.limit locals 3
.limit stack 6
.end method
