.bytecode 50.0
.class synchronized com/nd/android/u/ui/activity/chat_relative_image/SelectorActivity$3
.super java/lang/Object
.implements android/view/View$OnClickListener
.enclosing method com/nd/android/u/ui/activity/chat_relative_image/SelectorActivity/initHeader()V
.inner class inner com/nd/android/u/ui/activity/chat_relative_image/SelectorActivity$3

.field final synthetic 'this$0' Lcom/nd/android/u/ui/activity/chat_relative_image/SelectorActivity;

.method <init>(Lcom/nd/android/u/ui/activity/chat_relative_image/SelectorActivity;)V
aload 0
aload 1
putfield com/nd/android/u/ui/activity/chat_relative_image/SelectorActivity$3/this$0 Lcom/nd/android/u/ui/activity/chat_relative_image/SelectorActivity;
aload 0
invokespecial java/lang/Object/<init>()V
return
.limit locals 2
.limit stack 2
.end method

.method public onClick(Landroid/view/View;)V
aload 0
getfield com/nd/android/u/ui/activity/chat_relative_image/SelectorActivity$3/this$0 Lcom/nd/android/u/ui/activity/chat_relative_image/SelectorActivity;
invokestatic com/nd/android/u/ui/activity/chat_relative_image/SelectorActivity/access$300(Lcom/nd/android/u/ui/activity/chat_relative_image/SelectorActivity;)Lcom/nd/android/u/ui/activity/chat_relative_image/adapter/PhotoAdapter;
invokevirtual com/nd/android/u/ui/activity/chat_relative_image/adapter/PhotoAdapter/getSelcted()Ljava/util/List;
astore 2
new java/util/ArrayList
dup
invokespecial java/util/ArrayList/<init>()V
astore 1
aload 2
invokeinterface java/util/List/iterator()Ljava/util/Iterator; 0
astore 2
L0:
aload 2
invokeinterface java/util/Iterator/hasNext()Z 0
ifeq L1
aload 1
aload 2
invokeinterface java/util/Iterator/next()Ljava/lang/Object; 0
checkcast com/nd/android/u/ui/activity/chat_relative_image/bean/Photo
getfield com/nd/android/u/ui/activity/chat_relative_image/bean/Photo/path Ljava/lang/String;
invokevirtual java/util/ArrayList/add(Ljava/lang/Object;)Z
pop
goto L0
L1:
new android/content/Intent
dup
invokespecial android/content/Intent/<init>()V
astore 2
aload 2
ldc "data"
aload 1
invokevirtual android/content/Intent/putStringArrayListExtra(Ljava/lang/String;Ljava/util/ArrayList;)Landroid/content/Intent;
pop
aload 0
getfield com/nd/android/u/ui/activity/chat_relative_image/SelectorActivity$3/this$0 Lcom/nd/android/u/ui/activity/chat_relative_image/SelectorActivity;
iconst_m1
aload 2
invokevirtual com/nd/android/u/ui/activity/chat_relative_image/SelectorActivity/setResult(ILandroid/content/Intent;)V
ldc "test"
new java/lang/StringBuilder
dup
invokespecial java/lang/StringBuilder/<init>()V
ldc "\u53d1\u9001\u56fe\u7247\u6210\u529f:"
invokevirtual java/lang/StringBuilder/append(Ljava/lang/String;)Ljava/lang/StringBuilder;
aload 1
invokevirtual java/lang/StringBuilder/append(Ljava/lang/Object;)Ljava/lang/StringBuilder;
invokevirtual java/lang/StringBuilder/toString()Ljava/lang/String;
invokestatic android/util/Log/i(Ljava/lang/String;Ljava/lang/String;)I
pop
aload 0
getfield com/nd/android/u/ui/activity/chat_relative_image/SelectorActivity$3/this$0 Lcom/nd/android/u/ui/activity/chat_relative_image/SelectorActivity;
invokevirtual com/nd/android/u/ui/activity/chat_relative_image/SelectorActivity/finish()V
return
.limit locals 3
.limit stack 3
.end method
