.bytecode 50.0
.class synchronized com/nd/android/u/ui/activity/chat_relative_image/SelectorActivity$2
.super java/lang/Object
.implements android/view/View$OnClickListener
.enclosing method com/nd/android/u/ui/activity/chat_relative_image/SelectorActivity/initHeader()V
.inner class inner com/nd/android/u/ui/activity/chat_relative_image/SelectorActivity$2

.field final synthetic 'this$0' Lcom/nd/android/u/ui/activity/chat_relative_image/SelectorActivity;

.field final synthetic 'val$rlHeader' Landroid/widget/RelativeLayout;

.method <init>(Lcom/nd/android/u/ui/activity/chat_relative_image/SelectorActivity;Landroid/widget/RelativeLayout;)V
aload 0
aload 1
putfield com/nd/android/u/ui/activity/chat_relative_image/SelectorActivity$2/this$0 Lcom/nd/android/u/ui/activity/chat_relative_image/SelectorActivity;
aload 0
aload 2
putfield com/nd/android/u/ui/activity/chat_relative_image/SelectorActivity$2/val$rlHeader Landroid/widget/RelativeLayout;
aload 0
invokespecial java/lang/Object/<init>()V
return
.limit locals 3
.limit stack 2
.end method

.method public onClick(Landroid/view/View;)V
aload 0
getfield com/nd/android/u/ui/activity/chat_relative_image/SelectorActivity$2/this$0 Lcom/nd/android/u/ui/activity/chat_relative_image/SelectorActivity;
invokestatic com/nd/android/u/ui/activity/chat_relative_image/SelectorActivity/access$100(Lcom/nd/android/u/ui/activity/chat_relative_image/SelectorActivity;)Ljava/util/List;
ifnull L0
aload 0
getfield com/nd/android/u/ui/activity/chat_relative_image/SelectorActivity$2/this$0 Lcom/nd/android/u/ui/activity/chat_relative_image/SelectorActivity;
invokestatic com/nd/android/u/ui/activity/chat_relative_image/SelectorActivity/access$100(Lcom/nd/android/u/ui/activity/chat_relative_image/SelectorActivity;)Ljava/util/List;
invokeinterface java/util/List/size()I 0
ifgt L1
L0:
return
L1:
aload 0
getfield com/nd/android/u/ui/activity/chat_relative_image/SelectorActivity$2/this$0 Lcom/nd/android/u/ui/activity/chat_relative_image/SelectorActivity;
invokestatic com/nd/android/u/ui/activity/chat_relative_image/SelectorActivity/access$000(Lcom/nd/android/u/ui/activity/chat_relative_image/SelectorActivity;)Landroid/widget/PopupWindow;
ifnull L0
aload 0
getfield com/nd/android/u/ui/activity/chat_relative_image/SelectorActivity$2/this$0 Lcom/nd/android/u/ui/activity/chat_relative_image/SelectorActivity;
invokestatic com/nd/android/u/ui/activity/chat_relative_image/SelectorActivity/access$000(Lcom/nd/android/u/ui/activity/chat_relative_image/SelectorActivity;)Landroid/widget/PopupWindow;
invokevirtual android/widget/PopupWindow/isShowing()Z
ifne L2
aload 0
getfield com/nd/android/u/ui/activity/chat_relative_image/SelectorActivity$2/this$0 Lcom/nd/android/u/ui/activity/chat_relative_image/SelectorActivity;
invokestatic com/nd/android/u/ui/activity/chat_relative_image/SelectorActivity/access$200(Lcom/nd/android/u/ui/activity/chat_relative_image/SelectorActivity;)Landroid/widget/TextView;
iconst_0
iconst_0
getstatic com/nd/android/u/chat/R$drawable/send_image_title_down_icon I
iconst_0
invokevirtual android/widget/TextView/setCompoundDrawablesWithIntrinsicBounds(IIII)V
aload 0
getfield com/nd/android/u/ui/activity/chat_relative_image/SelectorActivity$2/this$0 Lcom/nd/android/u/ui/activity/chat_relative_image/SelectorActivity;
invokestatic com/nd/android/u/ui/activity/chat_relative_image/SelectorActivity/access$000(Lcom/nd/android/u/ui/activity/chat_relative_image/SelectorActivity;)Landroid/widget/PopupWindow;
aload 0
getfield com/nd/android/u/ui/activity/chat_relative_image/SelectorActivity$2/val$rlHeader Landroid/widget/RelativeLayout;
invokevirtual android/widget/PopupWindow/showAsDropDown(Landroid/view/View;)V
return
L2:
aload 0
getfield com/nd/android/u/ui/activity/chat_relative_image/SelectorActivity$2/this$0 Lcom/nd/android/u/ui/activity/chat_relative_image/SelectorActivity;
invokestatic com/nd/android/u/ui/activity/chat_relative_image/SelectorActivity/access$000(Lcom/nd/android/u/ui/activity/chat_relative_image/SelectorActivity;)Landroid/widget/PopupWindow;
invokevirtual android/widget/PopupWindow/dismiss()V
return
.limit locals 2
.limit stack 5
.end method
