.bytecode 50.0
.class synchronized com/nd/android/u/ui/activity/chat_relative_image/SelectorActivity$8
.super android/os/Handler
.enclosing method com/nd/android/u/ui/activity/chat_relative_image/SelectorActivity
.inner class inner com/nd/android/u/ui/activity/chat_relative_image/SelectorActivity$8

.field final synthetic 'this$0' Lcom/nd/android/u/ui/activity/chat_relative_image/SelectorActivity;

.method <init>(Lcom/nd/android/u/ui/activity/chat_relative_image/SelectorActivity;)V
aload 0
aload 1
putfield com/nd/android/u/ui/activity/chat_relative_image/SelectorActivity$8/this$0 Lcom/nd/android/u/ui/activity/chat_relative_image/SelectorActivity;
aload 0
invokespecial android/os/Handler/<init>()V
return
.limit locals 2
.limit stack 2
.end method

.method public handleMessage(Landroid/os/Message;)V
.catch java/lang/Exception from L0 to L1 using L2
.catch java/lang/Exception from L1 to L3 using L2
.catch java/lang/Exception from L3 to L4 using L2
.catch java/lang/Exception from L5 to L6 using L2
aload 0
aload 1
invokespecial android/os/Handler/handleMessage(Landroid/os/Message;)V
L0:
aload 1
getfield android/os/Message/what I
tableswitch 1
L1
L5
default : L7
L1:
aload 0
getfield com/nd/android/u/ui/activity/chat_relative_image/SelectorActivity$8/this$0 Lcom/nd/android/u/ui/activity/chat_relative_image/SelectorActivity;
invokestatic com/nd/android/u/ui/activity/chat_relative_image/SelectorActivity/access$700(Lcom/nd/android/u/ui/activity/chat_relative_image/SelectorActivity;)V
aload 0
getfield com/nd/android/u/ui/activity/chat_relative_image/SelectorActivity$8/this$0 Lcom/nd/android/u/ui/activity/chat_relative_image/SelectorActivity;
invokestatic com/nd/android/u/ui/activity/chat_relative_image/SelectorActivity/access$100(Lcom/nd/android/u/ui/activity/chat_relative_image/SelectorActivity;)Ljava/util/List;
ifnull L3
aload 0
getfield com/nd/android/u/ui/activity/chat_relative_image/SelectorActivity$8/this$0 Lcom/nd/android/u/ui/activity/chat_relative_image/SelectorActivity;
invokestatic com/nd/android/u/ui/activity/chat_relative_image/SelectorActivity/access$100(Lcom/nd/android/u/ui/activity/chat_relative_image/SelectorActivity;)Ljava/util/List;
invokeinterface java/util/List/size()I 0
ifle L3
aload 0
getfield com/nd/android/u/ui/activity/chat_relative_image/SelectorActivity$8/this$0 Lcom/nd/android/u/ui/activity/chat_relative_image/SelectorActivity;
invokestatic com/nd/android/u/ui/activity/chat_relative_image/SelectorActivity/access$300(Lcom/nd/android/u/ui/activity/chat_relative_image/SelectorActivity;)Lcom/nd/android/u/ui/activity/chat_relative_image/adapter/PhotoAdapter;
aload 0
getfield com/nd/android/u/ui/activity/chat_relative_image/SelectorActivity$8/this$0 Lcom/nd/android/u/ui/activity/chat_relative_image/SelectorActivity;
invokestatic com/nd/android/u/ui/activity/chat_relative_image/SelectorActivity/access$100(Lcom/nd/android/u/ui/activity/chat_relative_image/SelectorActivity;)Ljava/util/List;
iconst_0
invokeinterface java/util/List/get(I)Ljava/lang/Object; 1
checkcast com/nd/android/u/ui/activity/chat_relative_image/bean/PhotoBucket
getfield com/nd/android/u/ui/activity/chat_relative_image/bean/PhotoBucket/photoList Ljava/util/List;
invokevirtual com/nd/android/u/ui/activity/chat_relative_image/adapter/PhotoAdapter/setList(Ljava/util/List;)V
aload 0
getfield com/nd/android/u/ui/activity/chat_relative_image/SelectorActivity$8/this$0 Lcom/nd/android/u/ui/activity/chat_relative_image/SelectorActivity;
invokestatic com/nd/android/u/ui/activity/chat_relative_image/SelectorActivity/access$300(Lcom/nd/android/u/ui/activity/chat_relative_image/SelectorActivity;)Lcom/nd/android/u/ui/activity/chat_relative_image/adapter/PhotoAdapter;
invokevirtual com/nd/android/u/ui/activity/chat_relative_image/adapter/PhotoAdapter/notifyDataSetChanged()V
L3:
aload 0
getfield com/nd/android/u/ui/activity/chat_relative_image/SelectorActivity$8/this$0 Lcom/nd/android/u/ui/activity/chat_relative_image/SelectorActivity;
invokestatic com/nd/android/u/ui/activity/chat_relative_image/SelectorActivity/access$600(Lcom/nd/android/u/ui/activity/chat_relative_image/SelectorActivity;)Landroid/app/ProgressDialog;
invokevirtual android/app/ProgressDialog/dismiss()V
L4:
return
L2:
astore 1
aload 1
invokevirtual java/lang/Exception/printStackTrace()V
return
L5:
aload 1
getfield android/os/Message/obj Ljava/lang/Object;
checkcast java/util/List
astore 1
aload 0
getfield com/nd/android/u/ui/activity/chat_relative_image/SelectorActivity$8/this$0 Lcom/nd/android/u/ui/activity/chat_relative_image/SelectorActivity;
invokestatic com/nd/android/u/ui/activity/chat_relative_image/SelectorActivity/access$300(Lcom/nd/android/u/ui/activity/chat_relative_image/SelectorActivity;)Lcom/nd/android/u/ui/activity/chat_relative_image/adapter/PhotoAdapter;
aload 1
invokevirtual com/nd/android/u/ui/activity/chat_relative_image/adapter/PhotoAdapter/setList(Ljava/util/List;)V
aload 0
getfield com/nd/android/u/ui/activity/chat_relative_image/SelectorActivity$8/this$0 Lcom/nd/android/u/ui/activity/chat_relative_image/SelectorActivity;
invokestatic com/nd/android/u/ui/activity/chat_relative_image/SelectorActivity/access$800(Lcom/nd/android/u/ui/activity/chat_relative_image/SelectorActivity;)Landroid/widget/GridView;
aload 0
getfield com/nd/android/u/ui/activity/chat_relative_image/SelectorActivity$8/this$0 Lcom/nd/android/u/ui/activity/chat_relative_image/SelectorActivity;
invokestatic com/nd/android/u/ui/activity/chat_relative_image/SelectorActivity/access$300(Lcom/nd/android/u/ui/activity/chat_relative_image/SelectorActivity;)Lcom/nd/android/u/ui/activity/chat_relative_image/adapter/PhotoAdapter;
invokevirtual android/widget/GridView/setAdapter(Landroid/widget/ListAdapter;)V
aload 0
getfield com/nd/android/u/ui/activity/chat_relative_image/SelectorActivity$8/this$0 Lcom/nd/android/u/ui/activity/chat_relative_image/SelectorActivity;
invokestatic com/nd/android/u/ui/activity/chat_relative_image/SelectorActivity/access$600(Lcom/nd/android/u/ui/activity/chat_relative_image/SelectorActivity;)Landroid/app/ProgressDialog;
invokevirtual android/app/ProgressDialog/dismiss()V
L6:
return
L7:
return
.limit locals 2
.limit stack 3
.end method
