.bytecode 50.0
.class synchronized com/nd/android/u/ui/activity/chat_relative_image/SendImageActivity$2
.super android/os/Handler
.enclosing method com/nd/android/u/ui/activity/chat_relative_image/SendImageActivity
.inner class inner com/nd/android/u/ui/activity/chat_relative_image/SendImageActivity$2

.field final synthetic 'this$0' Lcom/nd/android/u/ui/activity/chat_relative_image/SendImageActivity;

.method <init>(Lcom/nd/android/u/ui/activity/chat_relative_image/SendImageActivity;)V
aload 0
aload 1
putfield com/nd/android/u/ui/activity/chat_relative_image/SendImageActivity$2/this$0 Lcom/nd/android/u/ui/activity/chat_relative_image/SendImageActivity;
aload 0
invokespecial android/os/Handler/<init>()V
return
.limit locals 2
.limit stack 2
.end method

.method public handleMessage(Landroid/os/Message;)V
aload 0
aload 1
invokespecial android/os/Handler/handleMessage(Landroid/os/Message;)V
aload 0
getfield com/nd/android/u/ui/activity/chat_relative_image/SendImageActivity$2/this$0 Lcom/nd/android/u/ui/activity/chat_relative_image/SendImageActivity;
invokestatic com/nd/android/u/ui/activity/chat_relative_image/SendImageActivity/access$300(Lcom/nd/android/u/ui/activity/chat_relative_image/SendImageActivity;)Landroid/app/ProgressDialog;
ifnull L0
aload 0
getfield com/nd/android/u/ui/activity/chat_relative_image/SendImageActivity$2/this$0 Lcom/nd/android/u/ui/activity/chat_relative_image/SendImageActivity;
invokestatic com/nd/android/u/ui/activity/chat_relative_image/SendImageActivity/access$300(Lcom/nd/android/u/ui/activity/chat_relative_image/SendImageActivity;)Landroid/app/ProgressDialog;
invokevirtual android/app/ProgressDialog/dismiss()V
L0:
aload 1
getfield android/os/Message/what I
ifeq L1
aload 0
getfield com/nd/android/u/ui/activity/chat_relative_image/SendImageActivity$2/this$0 Lcom/nd/android/u/ui/activity/chat_relative_image/SendImageActivity;
aload 1
getfield android/os/Message/what I
invokestatic com/common/android/utils/ToastUtils/display(Landroid/content/Context;I)V
aload 0
getfield com/nd/android/u/ui/activity/chat_relative_image/SendImageActivity$2/this$0 Lcom/nd/android/u/ui/activity/chat_relative_image/SendImageActivity;
iconst_0
aload 0
getfield com/nd/android/u/ui/activity/chat_relative_image/SendImageActivity$2/this$0 Lcom/nd/android/u/ui/activity/chat_relative_image/SendImageActivity;
invokevirtual com/nd/android/u/ui/activity/chat_relative_image/SendImageActivity/getIntent()Landroid/content/Intent;
invokevirtual com/nd/android/u/ui/activity/chat_relative_image/SendImageActivity/setResult(ILandroid/content/Intent;)V
aload 0
getfield com/nd/android/u/ui/activity/chat_relative_image/SendImageActivity$2/this$0 Lcom/nd/android/u/ui/activity/chat_relative_image/SendImageActivity;
invokevirtual com/nd/android/u/ui/activity/chat_relative_image/SendImageActivity/finish()V
return
L1:
new android/content/Intent
dup
ldc "android.intent.action.SEND"
aload 1
getfield android/os/Message/obj Ljava/lang/Object;
checkcast android/net/Uri
invokespecial android/content/Intent/<init>(Ljava/lang/String;Landroid/net/Uri;)V
astore 1
aload 0
getfield com/nd/android/u/ui/activity/chat_relative_image/SendImageActivity$2/this$0 Lcom/nd/android/u/ui/activity/chat_relative_image/SendImageActivity;
iconst_m1
aload 1
invokevirtual com/nd/android/u/ui/activity/chat_relative_image/SendImageActivity/setResult(ILandroid/content/Intent;)V
aload 0
getfield com/nd/android/u/ui/activity/chat_relative_image/SendImageActivity$2/this$0 Lcom/nd/android/u/ui/activity/chat_relative_image/SendImageActivity;
invokevirtual com/nd/android/u/ui/activity/chat_relative_image/SendImageActivity/finish()V
return
.limit locals 2
.limit stack 4
.end method
