.bytecode 50.0
.class synchronized com/nd/android/u/ui/activity/chat_relative_quickreply/QuickReplyAcitivty$1
.super java/lang/Object
.implements com/nd/android/u/ui/widge/DragListViewController$onEventListener
.enclosing method com/nd/android/u/ui/activity/chat_relative_quickreply/QuickReplyAcitivty
.inner class inner com/nd/android/u/ui/activity/chat_relative_quickreply/QuickReplyAcitivty$1

.field final synthetic 'this$0' Lcom/nd/android/u/ui/activity/chat_relative_quickreply/QuickReplyAcitivty;

.method <init>(Lcom/nd/android/u/ui/activity/chat_relative_quickreply/QuickReplyAcitivty;)V
aload 0
aload 1
putfield com/nd/android/u/ui/activity/chat_relative_quickreply/QuickReplyAcitivty$1/this$0 Lcom/nd/android/u/ui/activity/chat_relative_quickreply/QuickReplyAcitivty;
aload 0
invokespecial java/lang/Object/<init>()V
return
.limit locals 2
.limit stack 2
.end method

.method public onClick(I)V
iload 1
iflt L0
iload 1
aload 0
getfield com/nd/android/u/ui/activity/chat_relative_quickreply/QuickReplyAcitivty$1/this$0 Lcom/nd/android/u/ui/activity/chat_relative_quickreply/QuickReplyAcitivty;
invokestatic com/nd/android/u/ui/activity/chat_relative_quickreply/QuickReplyAcitivty/access$100(Lcom/nd/android/u/ui/activity/chat_relative_quickreply/QuickReplyAcitivty;)Lcom/nd/android/u/controller/bean/QuickReplyList;
invokevirtual com/nd/android/u/controller/bean/QuickReplyList/size()I
if_icmpge L0
aload 0
getfield com/nd/android/u/ui/activity/chat_relative_quickreply/QuickReplyAcitivty$1/this$0 Lcom/nd/android/u/ui/activity/chat_relative_quickreply/QuickReplyAcitivty;
invokestatic com/nd/android/u/ui/activity/chat_relative_quickreply/QuickReplyAcitivty/access$400(Lcom/nd/android/u/ui/activity/chat_relative_quickreply/QuickReplyAcitivty;)Landroid/widget/EditText;
aload 0
getfield com/nd/android/u/ui/activity/chat_relative_quickreply/QuickReplyAcitivty$1/this$0 Lcom/nd/android/u/ui/activity/chat_relative_quickreply/QuickReplyAcitivty;
invokestatic com/nd/android/u/ui/activity/chat_relative_quickreply/QuickReplyAcitivty/access$100(Lcom/nd/android/u/ui/activity/chat_relative_quickreply/QuickReplyAcitivty;)Lcom/nd/android/u/controller/bean/QuickReplyList;
iload 1
invokevirtual com/nd/android/u/controller/bean/QuickReplyList/get(I)Ljava/lang/Object;
checkcast com/nd/android/u/controller/bean/QuickReply
invokevirtual com/nd/android/u/controller/bean/QuickReply/getText()Ljava/lang/String;
invokevirtual android/widget/EditText/setText(Ljava/lang/CharSequence;)V
aload 0
getfield com/nd/android/u/ui/activity/chat_relative_quickreply/QuickReplyAcitivty$1/this$0 Lcom/nd/android/u/ui/activity/chat_relative_quickreply/QuickReplyAcitivty;
iconst_1
invokestatic com/nd/android/u/ui/activity/chat_relative_quickreply/QuickReplyAcitivty/access$300(Lcom/nd/android/u/ui/activity/chat_relative_quickreply/QuickReplyAcitivty;I)V
aload 0
getfield com/nd/android/u/ui/activity/chat_relative_quickreply/QuickReplyAcitivty$1/this$0 Lcom/nd/android/u/ui/activity/chat_relative_quickreply/QuickReplyAcitivty;
invokestatic com/nd/android/u/ui/activity/chat_relative_quickreply/QuickReplyAcitivty/access$400(Lcom/nd/android/u/ui/activity/chat_relative_quickreply/QuickReplyAcitivty;)Landroid/widget/EditText;
invokevirtual android/widget/EditText/requestFocus()Z
pop
aload 0
getfield com/nd/android/u/ui/activity/chat_relative_quickreply/QuickReplyAcitivty$1/this$0 Lcom/nd/android/u/ui/activity/chat_relative_quickreply/QuickReplyAcitivty;
iload 1
invokestatic com/nd/android/u/ui/activity/chat_relative_quickreply/QuickReplyAcitivty/access$502(Lcom/nd/android/u/ui/activity/chat_relative_quickreply/QuickReplyAcitivty;I)I
pop
L0:
return
.limit locals 2
.limit stack 3
.end method

.method public onSwitch(II)V
iload 1
iload 2
if_icmpne L0
return
L0:
aload 0
getfield com/nd/android/u/ui/activity/chat_relative_quickreply/QuickReplyAcitivty$1/this$0 Lcom/nd/android/u/ui/activity/chat_relative_quickreply/QuickReplyAcitivty;
iconst_1
invokestatic com/nd/android/u/ui/activity/chat_relative_quickreply/QuickReplyAcitivty/access$002(Lcom/nd/android/u/ui/activity/chat_relative_quickreply/QuickReplyAcitivty;Z)Z
pop
aload 0
getfield com/nd/android/u/ui/activity/chat_relative_quickreply/QuickReplyAcitivty$1/this$0 Lcom/nd/android/u/ui/activity/chat_relative_quickreply/QuickReplyAcitivty;
invokestatic com/nd/android/u/ui/activity/chat_relative_quickreply/QuickReplyAcitivty/access$100(Lcom/nd/android/u/ui/activity/chat_relative_quickreply/QuickReplyAcitivty;)Lcom/nd/android/u/controller/bean/QuickReplyList;
iload 1
iload 2
invokevirtual com/nd/android/u/controller/bean/QuickReplyList/exchange(II)Z
pop
aload 0
getfield com/nd/android/u/ui/activity/chat_relative_quickreply/QuickReplyAcitivty$1/this$0 Lcom/nd/android/u/ui/activity/chat_relative_quickreply/QuickReplyAcitivty;
invokestatic com/nd/android/u/ui/activity/chat_relative_quickreply/QuickReplyAcitivty/access$200(Lcom/nd/android/u/ui/activity/chat_relative_quickreply/QuickReplyAcitivty;)Lcom/nd/android/u/ui/activity/chat_relative_quickreply/QuickReplyAdapter;
invokevirtual com/nd/android/u/ui/activity/chat_relative_quickreply/QuickReplyAdapter/notifyDataSetChanged()V
aload 0
getfield com/nd/android/u/ui/activity/chat_relative_quickreply/QuickReplyAcitivty$1/this$0 Lcom/nd/android/u/ui/activity/chat_relative_quickreply/QuickReplyAcitivty;
iconst_0
invokestatic com/nd/android/u/ui/activity/chat_relative_quickreply/QuickReplyAcitivty/access$300(Lcom/nd/android/u/ui/activity/chat_relative_quickreply/QuickReplyAcitivty;I)V
return
.limit locals 3
.limit stack 3
.end method
