.bytecode 50.0
.class public synchronized com/android/u/weibo/contact/ui/dialog/DlgSetBirthday
.super android/app/Dialog
.implements com/common/android/ui/wheel/OnWheelScrollListener
.inner class inner com/android/u/weibo/contact/ui/dialog/DlgSetBirthday$1
.inner class public static abstract interface OnDlgBirthDismissListener inner com/android/u/weibo/contact/ui/dialog/DlgSetBirthday$OnDlgBirthDismissListener outer com/android/u/weibo/contact/ui/dialog/DlgSetBirthday

.field private static final 'm_ciDefaultDay' I = 1


.field private static final 'm_ciDefaultMonth' I = 1


.field private static final 'm_ciDefaultYear' I = 1990


.field protected 'clickListener' Landroid/view/View$OnClickListener;

.field private 'mContext' Landroid/content/Context;

.field private 'm_DismissListener' Lcom/android/u/weibo/contact/ui/dialog/DlgSetBirthday$OnDlgBirthDismissListener;

.field private 'm_btnCancel' Landroid/widget/Button;

.field private 'm_btnReset' Landroid/widget/Button;

.field private 'm_btnSet' Landroid/widget/Button;

.field private 'm_curDateInfo' Lcom/common/android/ui/wheel/DateInfo;

.field private 'm_dateBirth' Ljava/util/Date;

.field private 'm_iDay' I

.field private 'm_iMonth' I

.field private 'm_iYear' I

.field private 'wheelDay' Lcom/common/android/ui/wheel/WheelView;

.field private 'wheelMonth' Lcom/common/android/ui/wheel/WheelView;

.field private 'wheelYear' Lcom/common/android/ui/wheel/WheelView;

.method public <init>(Landroid/content/Context;Ljava/lang/String;I)V
aload 0
aload 1
iload 3
invokespecial android/app/Dialog/<init>(Landroid/content/Context;I)V
aload 0
sipush 1990
putfield com/android/u/weibo/contact/ui/dialog/DlgSetBirthday/m_iYear I
aload 0
iconst_1
putfield com/android/u/weibo/contact/ui/dialog/DlgSetBirthday/m_iMonth I
aload 0
iconst_1
putfield com/android/u/weibo/contact/ui/dialog/DlgSetBirthday/m_iDay I
aload 0
new com/android/u/weibo/contact/ui/dialog/DlgSetBirthday$1
dup
aload 0
invokespecial com/android/u/weibo/contact/ui/dialog/DlgSetBirthday$1/<init>(Lcom/android/u/weibo/contact/ui/dialog/DlgSetBirthday;)V
putfield com/android/u/weibo/contact/ui/dialog/DlgSetBirthday/clickListener Landroid/view/View$OnClickListener;
aload 0
aload 1
putfield com/android/u/weibo/contact/ui/dialog/DlgSetBirthday/mContext Landroid/content/Context;
aload 0
aload 2
invokespecial com/android/u/weibo/contact/ui/dialog/DlgSetBirthday/getDateByString(Ljava/lang/String;)V
return
.limit locals 4
.limit stack 4
.end method

.method static synthetic access$000(Lcom/android/u/weibo/contact/ui/dialog/DlgSetBirthday;)V
aload 0
invokespecial com/android/u/weibo/contact/ui/dialog/DlgSetBirthday/initDefault()V
return
.limit locals 1
.limit stack 1
.end method

.method static synthetic access$100(Lcom/android/u/weibo/contact/ui/dialog/DlgSetBirthday;)Lcom/android/u/weibo/contact/ui/dialog/DlgSetBirthday$OnDlgBirthDismissListener;
aload 0
getfield com/android/u/weibo/contact/ui/dialog/DlgSetBirthday/m_DismissListener Lcom/android/u/weibo/contact/ui/dialog/DlgSetBirthday$OnDlgBirthDismissListener;
areturn
.limit locals 1
.limit stack 1
.end method

.method static synthetic access$200(Lcom/android/u/weibo/contact/ui/dialog/DlgSetBirthday;)I
aload 0
getfield com/android/u/weibo/contact/ui/dialog/DlgSetBirthday/m_iYear I
ireturn
.limit locals 1
.limit stack 1
.end method

.method static synthetic access$300(Lcom/android/u/weibo/contact/ui/dialog/DlgSetBirthday;)I
aload 0
getfield com/android/u/weibo/contact/ui/dialog/DlgSetBirthday/m_iMonth I
ireturn
.limit locals 1
.limit stack 1
.end method

.method static synthetic access$400(Lcom/android/u/weibo/contact/ui/dialog/DlgSetBirthday;)I
aload 0
getfield com/android/u/weibo/contact/ui/dialog/DlgSetBirthday/m_iDay I
ireturn
.limit locals 1
.limit stack 1
.end method

.method private getDateByString(Ljava/lang/String;)V
.catch java/lang/Exception from L0 to L1 using L2
aload 1
ifnull L1
aload 1
invokevirtual java/lang/String/length()I
ifeq L1
ldc "//^[\\d]{4}[-\\ ][\\d]{1,2}[-\\ ][\\d]{1,2}$//"
invokestatic java/util/regex/Pattern/compile(Ljava/lang/String;)Ljava/util/regex/Pattern;
aload 1
invokevirtual java/util/regex/Pattern/matcher(Ljava/lang/CharSequence;)Ljava/util/regex/Matcher;
invokevirtual java/util/regex/Matcher/matches()Z
ifne L1
L0:
aload 0
new java/util/Date
dup
aload 1
ldc "-"
ldc "/"
invokevirtual java/lang/String/replace(Ljava/lang/CharSequence;Ljava/lang/CharSequence;)Ljava/lang/String;
invokespecial java/util/Date/<init>(Ljava/lang/String;)V
putfield com/android/u/weibo/contact/ui/dialog/DlgSetBirthday/m_dateBirth Ljava/util/Date;
L1:
return
L2:
astore 1
aload 0
aconst_null
putfield com/android/u/weibo/contact/ui/dialog/DlgSetBirthday/m_dateBirth Ljava/util/Date;
aload 1
invokevirtual java/lang/Exception/printStackTrace()V
return
.limit locals 2
.limit stack 6
.end method

.method private getMonthData(II)I
iload 2
iconst_1
if_icmpeq L0
iload 2
iconst_3
if_icmpeq L0
iload 2
iconst_5
if_icmpeq L0
iload 2
bipush 7
if_icmpeq L0
iload 2
bipush 8
if_icmpeq L0
iload 2
bipush 10
if_icmpeq L0
iload 2
bipush 12
if_icmpne L1
L0:
bipush 31
ireturn
L1:
iload 2
iconst_4
if_icmpeq L2
iload 2
bipush 6
if_icmpeq L2
iload 2
bipush 9
if_icmpeq L2
iload 2
bipush 11
if_icmpne L3
L2:
bipush 30
ireturn
L3:
iload 1
iconst_4
irem
ifne L4
iload 1
bipush 100
irem
ifne L5
L4:
iload 1
sipush 400
irem
ifne L6
L5:
bipush 29
ireturn
L6:
bipush 28
ireturn
.limit locals 3
.limit stack 2
.end method

.method private initData()V
aload 0
getfield com/android/u/weibo/contact/ui/dialog/DlgSetBirthday/m_dateBirth Ljava/util/Date;
ifnull L0
aload 0
new com/common/android/ui/wheel/DateInfo
dup
iconst_0
invokespecial com/common/android/ui/wheel/DateInfo/<init>(Z)V
putfield com/android/u/weibo/contact/ui/dialog/DlgSetBirthday/m_curDateInfo Lcom/common/android/ui/wheel/DateInfo;
aload 0
getfield com/android/u/weibo/contact/ui/dialog/DlgSetBirthday/m_curDateInfo Lcom/common/android/ui/wheel/DateInfo;
aload 0
getfield com/android/u/weibo/contact/ui/dialog/DlgSetBirthday/m_dateBirth Ljava/util/Date;
invokevirtual java/util/Date/getYear()I
sipush 1900
iadd
putfield com/common/android/ui/wheel/DateInfo/year I
aload 0
getfield com/android/u/weibo/contact/ui/dialog/DlgSetBirthday/m_curDateInfo Lcom/common/android/ui/wheel/DateInfo;
aload 0
getfield com/android/u/weibo/contact/ui/dialog/DlgSetBirthday/m_dateBirth Ljava/util/Date;
invokevirtual java/util/Date/getMonth()I
iconst_1
iadd
putfield com/common/android/ui/wheel/DateInfo/month I
aload 0
getfield com/android/u/weibo/contact/ui/dialog/DlgSetBirthday/m_curDateInfo Lcom/common/android/ui/wheel/DateInfo;
aload 0
getfield com/android/u/weibo/contact/ui/dialog/DlgSetBirthday/m_dateBirth Ljava/util/Date;
invokevirtual java/util/Date/getDate()I
putfield com/common/android/ui/wheel/DateInfo/day I
L1:
aload 0
invokevirtual com/android/u/weibo/contact/ui/dialog/DlgSetBirthday/setDate()V
aload 0
invokespecial com/android/u/weibo/contact/ui/dialog/DlgSetBirthday/initYear()V
aload 0
invokespecial com/android/u/weibo/contact/ui/dialog/DlgSetBirthday/initMonth()V
aload 0
invokespecial com/android/u/weibo/contact/ui/dialog/DlgSetBirthday/initDay()V
aload 0
invokespecial com/android/u/weibo/contact/ui/dialog/DlgSetBirthday/initDefault()V
return
L0:
aload 0
new com/common/android/ui/wheel/DateInfo
dup
iconst_1
invokespecial com/common/android/ui/wheel/DateInfo/<init>(Z)V
putfield com/android/u/weibo/contact/ui/dialog/DlgSetBirthday/m_curDateInfo Lcom/common/android/ui/wheel/DateInfo;
goto L1
.limit locals 1
.limit stack 4
.end method

.method private initDay()V
aload 0
aload 0
getfield com/android/u/weibo/contact/ui/dialog/DlgSetBirthday/m_curDateInfo Lcom/common/android/ui/wheel/DateInfo;
getfield com/common/android/ui/wheel/DateInfo/year I
aload 0
getfield com/android/u/weibo/contact/ui/dialog/DlgSetBirthday/m_curDateInfo Lcom/common/android/ui/wheel/DateInfo;
getfield com/common/android/ui/wheel/DateInfo/month I
invokespecial com/android/u/weibo/contact/ui/dialog/DlgSetBirthday/getMonthData(II)I
istore 1
aload 0
aload 0
getfield com/android/u/weibo/contact/ui/dialog/DlgSetBirthday/wheelDay Lcom/common/android/ui/wheel/WheelView;
iconst_1
iload 1
iconst_1
invokespecial com/android/u/weibo/contact/ui/dialog/DlgSetBirthday/initWheel(Lcom/common/android/ui/wheel/WheelView;IIZ)Lcom/common/android/ui/wheel/NumericWheelAdapter;
pop
aload 0
getfield com/android/u/weibo/contact/ui/dialog/DlgSetBirthday/wheelDay Lcom/common/android/ui/wheel/WheelView;
invokevirtual com/common/android/ui/wheel/WheelView/getCurrentItem()I
iload 1
iconst_1
isub
if_icmple L0
aload 0
getfield com/android/u/weibo/contact/ui/dialog/DlgSetBirthday/wheelDay Lcom/common/android/ui/wheel/WheelView;
iload 1
iconst_1
isub
iconst_1
invokevirtual com/common/android/ui/wheel/WheelView/setCurrentItem(IZ)V
L0:
return
.limit locals 2
.limit stack 5
.end method

.method private initDefault()V
aload 0
getfield com/android/u/weibo/contact/ui/dialog/DlgSetBirthday/wheelYear Lcom/common/android/ui/wheel/WheelView;
ifnull L0
aload 0
getfield com/android/u/weibo/contact/ui/dialog/DlgSetBirthday/wheelYear Lcom/common/android/ui/wheel/WheelView;
aload 0
getfield com/android/u/weibo/contact/ui/dialog/DlgSetBirthday/m_iYear I
sipush 1900
isub
iconst_0
invokevirtual com/common/android/ui/wheel/WheelView/setCurrentItem(IZ)V
L0:
aload 0
getfield com/android/u/weibo/contact/ui/dialog/DlgSetBirthday/wheelMonth Lcom/common/android/ui/wheel/WheelView;
ifnull L1
aload 0
getfield com/android/u/weibo/contact/ui/dialog/DlgSetBirthday/wheelMonth Lcom/common/android/ui/wheel/WheelView;
aload 0
getfield com/android/u/weibo/contact/ui/dialog/DlgSetBirthday/m_iMonth I
iconst_1
isub
iconst_0
invokevirtual com/common/android/ui/wheel/WheelView/setCurrentItem(IZ)V
L1:
aload 0
getfield com/android/u/weibo/contact/ui/dialog/DlgSetBirthday/wheelDay Lcom/common/android/ui/wheel/WheelView;
ifnull L2
aload 0
invokespecial com/android/u/weibo/contact/ui/dialog/DlgSetBirthday/initDay()V
aload 0
getfield com/android/u/weibo/contact/ui/dialog/DlgSetBirthday/wheelDay Lcom/common/android/ui/wheel/WheelView;
aload 0
getfield com/android/u/weibo/contact/ui/dialog/DlgSetBirthday/m_iDay I
iconst_1
isub
iconst_0
invokevirtual com/common/android/ui/wheel/WheelView/setCurrentItem(IZ)V
L2:
return
.limit locals 1
.limit stack 3
.end method

.method private initMonth()V
aload 0
aload 0
getfield com/android/u/weibo/contact/ui/dialog/DlgSetBirthday/wheelMonth Lcom/common/android/ui/wheel/WheelView;
iconst_1
bipush 12
iconst_1
invokespecial com/android/u/weibo/contact/ui/dialog/DlgSetBirthday/initWheel(Lcom/common/android/ui/wheel/WheelView;IIZ)Lcom/common/android/ui/wheel/NumericWheelAdapter;
pop
return
.limit locals 1
.limit stack 5
.end method

.method private initWheel(Lcom/common/android/ui/wheel/WheelView;IIZ)Lcom/common/android/ui/wheel/NumericWheelAdapter;
new com/common/android/ui/wheel/NumericWheelAdapter
dup
aload 0
getfield com/android/u/weibo/contact/ui/dialog/DlgSetBirthday/mContext Landroid/content/Context;
iload 2
iload 3
ldc "%02d"
invokespecial com/common/android/ui/wheel/NumericWheelAdapter/<init>(Landroid/content/Context;IILjava/lang/String;)V
astore 5
aload 5
ldc_w -16777216
invokevirtual com/common/android/ui/wheel/NumericWheelAdapter/setTextColor(I)V
aload 1
aload 5
invokevirtual com/common/android/ui/wheel/WheelView/setViewAdapter(Lcom/common/android/ui/wheel/WheelViewAdapter;)V
aload 1
iload 4
invokevirtual com/common/android/ui/wheel/WheelView/setCyclic(Z)V
aload 1
iconst_3
invokevirtual com/common/android/ui/wheel/WheelView/setVisibleItems(I)V
aload 1
aload 0
invokevirtual com/common/android/ui/wheel/WheelView/addScrollingListener(Lcom/common/android/ui/wheel/OnWheelScrollListener;)V
aload 5
areturn
.limit locals 6
.limit stack 6
.end method

.method private initYear()V
aload 0
aload 0
getfield com/android/u/weibo/contact/ui/dialog/DlgSetBirthday/wheelYear Lcom/common/android/ui/wheel/WheelView;
sipush 1900
sipush 2049
iconst_0
invokespecial com/android/u/weibo/contact/ui/dialog/DlgSetBirthday/initWheel(Lcom/common/android/ui/wheel/WheelView;IIZ)Lcom/common/android/ui/wheel/NumericWheelAdapter;
pop
return
.limit locals 1
.limit stack 5
.end method

.method public onCreate(Landroid/os/Bundle;)V
aload 0
aload 1
invokespecial android/app/Dialog/onCreate(Landroid/os/Bundle;)V
aload 0
iconst_1
invokevirtual com/android/u/weibo/contact/ui/dialog/DlgSetBirthday/requestWindowFeature(I)Z
pop
aload 0
getstatic com/android/u/weibo/R$layout/birthday_set I
invokevirtual com/android/u/weibo/contact/ui/dialog/DlgSetBirthday/setContentView(I)V
aload 0
aload 0
getstatic com/android/u/weibo/R$id/button_cancel I
invokevirtual com/android/u/weibo/contact/ui/dialog/DlgSetBirthday/findViewById(I)Landroid/view/View;
checkcast android/widget/Button
putfield com/android/u/weibo/contact/ui/dialog/DlgSetBirthday/m_btnCancel Landroid/widget/Button;
aload 0
aload 0
getstatic com/android/u/weibo/R$id/button_reset I
invokevirtual com/android/u/weibo/contact/ui/dialog/DlgSetBirthday/findViewById(I)Landroid/view/View;
checkcast android/widget/Button
putfield com/android/u/weibo/contact/ui/dialog/DlgSetBirthday/m_btnReset Landroid/widget/Button;
aload 0
aload 0
getstatic com/android/u/weibo/R$id/button_set I
invokevirtual com/android/u/weibo/contact/ui/dialog/DlgSetBirthday/findViewById(I)Landroid/view/View;
checkcast android/widget/Button
putfield com/android/u/weibo/contact/ui/dialog/DlgSetBirthday/m_btnSet Landroid/widget/Button;
aload 0
aload 0
getstatic com/android/u/weibo/R$id/wheel_year I
invokevirtual com/android/u/weibo/contact/ui/dialog/DlgSetBirthday/findViewById(I)Landroid/view/View;
checkcast com/common/android/ui/wheel/WheelView
putfield com/android/u/weibo/contact/ui/dialog/DlgSetBirthday/wheelYear Lcom/common/android/ui/wheel/WheelView;
aload 0
aload 0
getstatic com/android/u/weibo/R$id/wheel_month I
invokevirtual com/android/u/weibo/contact/ui/dialog/DlgSetBirthday/findViewById(I)Landroid/view/View;
checkcast com/common/android/ui/wheel/WheelView
putfield com/android/u/weibo/contact/ui/dialog/DlgSetBirthday/wheelMonth Lcom/common/android/ui/wheel/WheelView;
aload 0
aload 0
getstatic com/android/u/weibo/R$id/wheel_day I
invokevirtual com/android/u/weibo/contact/ui/dialog/DlgSetBirthday/findViewById(I)Landroid/view/View;
checkcast com/common/android/ui/wheel/WheelView
putfield com/android/u/weibo/contact/ui/dialog/DlgSetBirthday/wheelDay Lcom/common/android/ui/wheel/WheelView;
aload 0
getfield com/android/u/weibo/contact/ui/dialog/DlgSetBirthday/m_btnCancel Landroid/widget/Button;
aload 0
getfield com/android/u/weibo/contact/ui/dialog/DlgSetBirthday/clickListener Landroid/view/View$OnClickListener;
invokevirtual android/widget/Button/setOnClickListener(Landroid/view/View$OnClickListener;)V
aload 0
getfield com/android/u/weibo/contact/ui/dialog/DlgSetBirthday/m_btnReset Landroid/widget/Button;
aload 0
getfield com/android/u/weibo/contact/ui/dialog/DlgSetBirthday/clickListener Landroid/view/View$OnClickListener;
invokevirtual android/widget/Button/setOnClickListener(Landroid/view/View$OnClickListener;)V
aload 0
getfield com/android/u/weibo/contact/ui/dialog/DlgSetBirthday/m_btnSet Landroid/widget/Button;
aload 0
getfield com/android/u/weibo/contact/ui/dialog/DlgSetBirthday/clickListener Landroid/view/View$OnClickListener;
invokevirtual android/widget/Button/setOnClickListener(Landroid/view/View$OnClickListener;)V
aload 0
invokespecial com/android/u/weibo/contact/ui/dialog/DlgSetBirthday/initData()V
return
.limit locals 2
.limit stack 3
.end method

.method public onScrollingFinished(Lcom/common/android/ui/wheel/WheelView;)V
aload 1
invokevirtual com/common/android/ui/wheel/WheelView/getId()I
istore 2
iload 2
getstatic com/android/u/weibo/R$id/wheel_year I
if_icmpne L0
aload 0
getfield com/android/u/weibo/contact/ui/dialog/DlgSetBirthday/m_curDateInfo Lcom/common/android/ui/wheel/DateInfo;
aload 1
invokevirtual com/common/android/ui/wheel/WheelView/getCurrentItem()I
sipush 1900
iadd
putfield com/common/android/ui/wheel/DateInfo/year I
aload 0
invokespecial com/android/u/weibo/contact/ui/dialog/DlgSetBirthday/initDay()V
L1:
return
L0:
iload 2
getstatic com/android/u/weibo/R$id/wheel_month I
if_icmpne L2
aload 0
getfield com/android/u/weibo/contact/ui/dialog/DlgSetBirthday/m_curDateInfo Lcom/common/android/ui/wheel/DateInfo;
aload 1
invokevirtual com/common/android/ui/wheel/WheelView/getCurrentItem()I
iconst_1
iadd
putfield com/common/android/ui/wheel/DateInfo/month I
aload 0
invokespecial com/android/u/weibo/contact/ui/dialog/DlgSetBirthday/initDay()V
return
L2:
iload 2
getstatic com/android/u/weibo/R$id/wheel_day I
if_icmpne L1
aload 0
getfield com/android/u/weibo/contact/ui/dialog/DlgSetBirthday/m_curDateInfo Lcom/common/android/ui/wheel/DateInfo;
aload 1
invokevirtual com/common/android/ui/wheel/WheelView/getCurrentItem()I
iconst_1
iadd
putfield com/common/android/ui/wheel/DateInfo/day I
return
.limit locals 3
.limit stack 3
.end method

.method public onScrollingStarted(Lcom/common/android/ui/wheel/WheelView;)V
return
.limit locals 2
.limit stack 0
.end method

.method public setDate()V
aload 0
aload 0
getfield com/android/u/weibo/contact/ui/dialog/DlgSetBirthday/m_curDateInfo Lcom/common/android/ui/wheel/DateInfo;
getfield com/common/android/ui/wheel/DateInfo/year I
putfield com/android/u/weibo/contact/ui/dialog/DlgSetBirthday/m_iYear I
aload 0
aload 0
getfield com/android/u/weibo/contact/ui/dialog/DlgSetBirthday/m_curDateInfo Lcom/common/android/ui/wheel/DateInfo;
getfield com/common/android/ui/wheel/DateInfo/month I
putfield com/android/u/weibo/contact/ui/dialog/DlgSetBirthday/m_iMonth I
aload 0
aload 0
getfield com/android/u/weibo/contact/ui/dialog/DlgSetBirthday/m_curDateInfo Lcom/common/android/ui/wheel/DateInfo;
getfield com/common/android/ui/wheel/DateInfo/day I
putfield com/android/u/weibo/contact/ui/dialog/DlgSetBirthday/m_iDay I
return
.limit locals 1
.limit stack 2
.end method

.method public setOnAfterDismissListener(Lcom/android/u/weibo/contact/ui/dialog/DlgSetBirthday$OnDlgBirthDismissListener;)V
aload 0
aload 1
putfield com/android/u/weibo/contact/ui/dialog/DlgSetBirthday/m_DismissListener Lcom/android/u/weibo/contact/ui/dialog/DlgSetBirthday$OnDlgBirthDismissListener;
return
.limit locals 2
.limit stack 2
.end method
