.bytecode 50.0
.class synchronized com/android/u/weibo/contact/ui/dialog/DlgSetBirthday$1
.super java/lang/Object
.implements android/view/View$OnClickListener
.enclosing method com/android/u/weibo/contact/ui/dialog/DlgSetBirthday
.inner class inner com/android/u/weibo/contact/ui/dialog/DlgSetBirthday$1

.field final synthetic 'this$0' Lcom/android/u/weibo/contact/ui/dialog/DlgSetBirthday;

.method <init>(Lcom/android/u/weibo/contact/ui/dialog/DlgSetBirthday;)V
aload 0
aload 1
putfield com/android/u/weibo/contact/ui/dialog/DlgSetBirthday$1/this$0 Lcom/android/u/weibo/contact/ui/dialog/DlgSetBirthday;
aload 0
invokespecial java/lang/Object/<init>()V
return
.limit locals 2
.limit stack 2
.end method

.method public onClick(Landroid/view/View;)V
aload 1
invokevirtual android/view/View/getId()I
istore 2
iload 2
getstatic com/android/u/weibo/R$id/button_cancel I
if_icmpne L0
aload 0
getfield com/android/u/weibo/contact/ui/dialog/DlgSetBirthday$1/this$0 Lcom/android/u/weibo/contact/ui/dialog/DlgSetBirthday;
invokevirtual com/android/u/weibo/contact/ui/dialog/DlgSetBirthday/dismiss()V
L1:
return
L0:
iload 2
getstatic com/android/u/weibo/R$id/button_reset I
if_icmpne L2
aload 0
getfield com/android/u/weibo/contact/ui/dialog/DlgSetBirthday$1/this$0 Lcom/android/u/weibo/contact/ui/dialog/DlgSetBirthday;
invokestatic com/android/u/weibo/contact/ui/dialog/DlgSetBirthday/access$000(Lcom/android/u/weibo/contact/ui/dialog/DlgSetBirthday;)V
return
L2:
iload 2
getstatic com/android/u/weibo/R$id/button_set I
if_icmpne L1
aload 0
getfield com/android/u/weibo/contact/ui/dialog/DlgSetBirthday$1/this$0 Lcom/android/u/weibo/contact/ui/dialog/DlgSetBirthday;
invokevirtual com/android/u/weibo/contact/ui/dialog/DlgSetBirthday/setDate()V
aload 0
getfield com/android/u/weibo/contact/ui/dialog/DlgSetBirthday$1/this$0 Lcom/android/u/weibo/contact/ui/dialog/DlgSetBirthday;
invokestatic com/android/u/weibo/contact/ui/dialog/DlgSetBirthday/access$100(Lcom/android/u/weibo/contact/ui/dialog/DlgSetBirthday;)Lcom/android/u/weibo/contact/ui/dialog/DlgSetBirthday$OnDlgBirthDismissListener;
ifnull L3
aload 0
getfield com/android/u/weibo/contact/ui/dialog/DlgSetBirthday$1/this$0 Lcom/android/u/weibo/contact/ui/dialog/DlgSetBirthday;
invokestatic com/android/u/weibo/contact/ui/dialog/DlgSetBirthday/access$100(Lcom/android/u/weibo/contact/ui/dialog/DlgSetBirthday;)Lcom/android/u/weibo/contact/ui/dialog/DlgSetBirthday$OnDlgBirthDismissListener;
aload 0
getfield com/android/u/weibo/contact/ui/dialog/DlgSetBirthday$1/this$0 Lcom/android/u/weibo/contact/ui/dialog/DlgSetBirthday;
invokestatic com/android/u/weibo/contact/ui/dialog/DlgSetBirthday/access$200(Lcom/android/u/weibo/contact/ui/dialog/DlgSetBirthday;)I
aload 0
getfield com/android/u/weibo/contact/ui/dialog/DlgSetBirthday$1/this$0 Lcom/android/u/weibo/contact/ui/dialog/DlgSetBirthday;
invokestatic com/android/u/weibo/contact/ui/dialog/DlgSetBirthday/access$300(Lcom/android/u/weibo/contact/ui/dialog/DlgSetBirthday;)I
aload 0
getfield com/android/u/weibo/contact/ui/dialog/DlgSetBirthday$1/this$0 Lcom/android/u/weibo/contact/ui/dialog/DlgSetBirthday;
invokestatic com/android/u/weibo/contact/ui/dialog/DlgSetBirthday/access$400(Lcom/android/u/weibo/contact/ui/dialog/DlgSetBirthday;)I
invokeinterface com/android/u/weibo/contact/ui/dialog/DlgSetBirthday$OnDlgBirthDismissListener/GetDate(III)V 3
L3:
aload 0
getfield com/android/u/weibo/contact/ui/dialog/DlgSetBirthday$1/this$0 Lcom/android/u/weibo/contact/ui/dialog/DlgSetBirthday;
invokevirtual com/android/u/weibo/contact/ui/dialog/DlgSetBirthday/dismiss()V
return
.limit locals 3
.limit stack 4
.end method
