.bytecode 50.0
.class public synchronized android/support/v4/view/accessibility/AccessibilityNodeInfoCompat
.super java/lang/Object
.inner class static AccessibilityNodeInfoIcsImpl inner android/support/v4/view/accessibility/AccessibilityNodeInfoCompat$AccessibilityNodeInfoIcsImpl outer android/support/v4/view/accessibility/AccessibilityNodeInfoCompat
.inner class static abstract interface AccessibilityNodeInfoImpl inner android/support/v4/view/accessibility/AccessibilityNodeInfoCompat$AccessibilityNodeInfoImpl outer android/support/v4/view/accessibility/AccessibilityNodeInfoCompat
.inner class static AccessibilityNodeInfoJellybeanImpl inner android/support/v4/view/accessibility/AccessibilityNodeInfoCompat$AccessibilityNodeInfoJellybeanImpl outer android/support/v4/view/accessibility/AccessibilityNodeInfoCompat
.inner class static AccessibilityNodeInfoStubImpl inner android/support/v4/view/accessibility/AccessibilityNodeInfoCompat$AccessibilityNodeInfoStubImpl outer android/support/v4/view/accessibility/AccessibilityNodeInfoCompat

.field public static final 'ACTION_ACCESSIBILITY_FOCUS' I = 64


.field public static final 'ACTION_ARGUMENT_HTML_ELEMENT_STRING' Ljava/lang/String; = "ACTION_ARGUMENT_HTML_ELEMENT_STRING"

.field public static final 'ACTION_ARGUMENT_MOVEMENT_GRANULARITY_INT' Ljava/lang/String; = "ACTION_ARGUMENT_MOVEMENT_GRANULARITY_INT"

.field public static final 'ACTION_CLEAR_ACCESSIBILITY_FOCUS' I = 128


.field public static final 'ACTION_CLEAR_FOCUS' I = 2


.field public static final 'ACTION_CLEAR_SELECTION' I = 8


.field public static final 'ACTION_CLICK' I = 16


.field public static final 'ACTION_FOCUS' I = 1


.field public static final 'ACTION_LONG_CLICK' I = 32


.field public static final 'ACTION_NEXT_AT_MOVEMENT_GRANULARITY' I = 256


.field public static final 'ACTION_NEXT_HTML_ELEMENT' I = 1024


.field public static final 'ACTION_PREVIOUS_AT_MOVEMENT_GRANULARITY' I = 512


.field public static final 'ACTION_PREVIOUS_HTML_ELEMENT' I = 2048


.field public static final 'ACTION_SCROLL_BACKWARD' I = 8192


.field public static final 'ACTION_SCROLL_FORWARD' I = 4096


.field public static final 'ACTION_SELECT' I = 4


.field public static final 'FOCUS_ACCESSIBILITY' I = 2


.field public static final 'FOCUS_INPUT' I = 1


.field private static final 'IMPL' Landroid/support/v4/view/accessibility/AccessibilityNodeInfoCompat$AccessibilityNodeInfoImpl;

.field public static final 'MOVEMENT_GRANULARITY_CHARACTER' I = 1


.field public static final 'MOVEMENT_GRANULARITY_LINE' I = 4


.field public static final 'MOVEMENT_GRANULARITY_PAGE' I = 16


.field public static final 'MOVEMENT_GRANULARITY_PARAGRAPH' I = 8


.field public static final 'MOVEMENT_GRANULARITY_WORD' I = 2


.field private final 'mInfo' Ljava/lang/Object;

.method static <clinit>()V
getstatic android/os/Build$VERSION/SDK_INT I
bipush 16
if_icmplt L0
new android/support/v4/view/accessibility/AccessibilityNodeInfoCompat$AccessibilityNodeInfoJellybeanImpl
dup
invokespecial android/support/v4/view/accessibility/AccessibilityNodeInfoCompat$AccessibilityNodeInfoJellybeanImpl/<init>()V
putstatic android/support/v4/view/accessibility/AccessibilityNodeInfoCompat/IMPL Landroid/support/v4/view/accessibility/AccessibilityNodeInfoCompat$AccessibilityNodeInfoImpl;
return
L0:
getstatic android/os/Build$VERSION/SDK_INT I
bipush 14
if_icmplt L1
new android/support/v4/view/accessibility/AccessibilityNodeInfoCompat$AccessibilityNodeInfoIcsImpl
dup
invokespecial android/support/v4/view/accessibility/AccessibilityNodeInfoCompat$AccessibilityNodeInfoIcsImpl/<init>()V
putstatic android/support/v4/view/accessibility/AccessibilityNodeInfoCompat/IMPL Landroid/support/v4/view/accessibility/AccessibilityNodeInfoCompat$AccessibilityNodeInfoImpl;
return
L1:
new android/support/v4/view/accessibility/AccessibilityNodeInfoCompat$AccessibilityNodeInfoStubImpl
dup
invokespecial android/support/v4/view/accessibility/AccessibilityNodeInfoCompat$AccessibilityNodeInfoStubImpl/<init>()V
putstatic android/support/v4/view/accessibility/AccessibilityNodeInfoCompat/IMPL Landroid/support/v4/view/accessibility/AccessibilityNodeInfoCompat$AccessibilityNodeInfoImpl;
return
.limit locals 0
.limit stack 2
.end method

.method public <init>(Ljava/lang/Object;)V
aload 0
invokespecial java/lang/Object/<init>()V
aload 0
aload 1
putfield android/support/v4/view/accessibility/AccessibilityNodeInfoCompat/mInfo Ljava/lang/Object;
return
.limit locals 2
.limit stack 2
.end method

.method public static obtain()Landroid/support/v4/view/accessibility/AccessibilityNodeInfoCompat;
getstatic android/support/v4/view/accessibility/AccessibilityNodeInfoCompat/IMPL Landroid/support/v4/view/accessibility/AccessibilityNodeInfoCompat$AccessibilityNodeInfoImpl;
invokeinterface android/support/v4/view/accessibility/AccessibilityNodeInfoCompat$AccessibilityNodeInfoImpl/obtain()Ljava/lang/Object; 0
invokestatic android/support/v4/view/accessibility/AccessibilityNodeInfoCompat/wrapNonNullInstance(Ljava/lang/Object;)Landroid/support/v4/view/accessibility/AccessibilityNodeInfoCompat;
areturn
.limit locals 0
.limit stack 1
.end method

.method public static obtain(Landroid/support/v4/view/accessibility/AccessibilityNodeInfoCompat;)Landroid/support/v4/view/accessibility/AccessibilityNodeInfoCompat;
getstatic android/support/v4/view/accessibility/AccessibilityNodeInfoCompat/IMPL Landroid/support/v4/view/accessibility/AccessibilityNodeInfoCompat$AccessibilityNodeInfoImpl;
aload 0
getfield android/support/v4/view/accessibility/AccessibilityNodeInfoCompat/mInfo Ljava/lang/Object;
invokeinterface android/support/v4/view/accessibility/AccessibilityNodeInfoCompat$AccessibilityNodeInfoImpl/obtain(Ljava/lang/Object;)Ljava/lang/Object; 1
invokestatic android/support/v4/view/accessibility/AccessibilityNodeInfoCompat/wrapNonNullInstance(Ljava/lang/Object;)Landroid/support/v4/view/accessibility/AccessibilityNodeInfoCompat;
areturn
.limit locals 1
.limit stack 2
.end method

.method public static obtain(Landroid/view/View;)Landroid/support/v4/view/accessibility/AccessibilityNodeInfoCompat;
getstatic android/support/v4/view/accessibility/AccessibilityNodeInfoCompat/IMPL Landroid/support/v4/view/accessibility/AccessibilityNodeInfoCompat$AccessibilityNodeInfoImpl;
aload 0
invokeinterface android/support/v4/view/accessibility/AccessibilityNodeInfoCompat$AccessibilityNodeInfoImpl/obtain(Landroid/view/View;)Ljava/lang/Object; 1
invokestatic android/support/v4/view/accessibility/AccessibilityNodeInfoCompat/wrapNonNullInstance(Ljava/lang/Object;)Landroid/support/v4/view/accessibility/AccessibilityNodeInfoCompat;
areturn
.limit locals 1
.limit stack 2
.end method

.method public static obtain(Landroid/view/View;I)Landroid/support/v4/view/accessibility/AccessibilityNodeInfoCompat;
getstatic android/support/v4/view/accessibility/AccessibilityNodeInfoCompat/IMPL Landroid/support/v4/view/accessibility/AccessibilityNodeInfoCompat$AccessibilityNodeInfoImpl;
aload 0
iload 1
invokeinterface android/support/v4/view/accessibility/AccessibilityNodeInfoCompat$AccessibilityNodeInfoImpl/obtain(Landroid/view/View;I)Ljava/lang/Object; 2
invokestatic android/support/v4/view/accessibility/AccessibilityNodeInfoCompat/wrapNonNullInstance(Ljava/lang/Object;)Landroid/support/v4/view/accessibility/AccessibilityNodeInfoCompat;
areturn
.limit locals 2
.limit stack 3
.end method

.method static wrapNonNullInstance(Ljava/lang/Object;)Landroid/support/v4/view/accessibility/AccessibilityNodeInfoCompat;
aload 0
ifnull L0
new android/support/v4/view/accessibility/AccessibilityNodeInfoCompat
dup
aload 0
invokespecial android/support/v4/view/accessibility/AccessibilityNodeInfoCompat/<init>(Ljava/lang/Object;)V
areturn
L0:
aconst_null
areturn
.limit locals 1
.limit stack 3
.end method

.method public addAction(I)V
getstatic android/support/v4/view/accessibility/AccessibilityNodeInfoCompat/IMPL Landroid/support/v4/view/accessibility/AccessibilityNodeInfoCompat$AccessibilityNodeInfoImpl;
aload 0
getfield android/support/v4/view/accessibility/AccessibilityNodeInfoCompat/mInfo Ljava/lang/Object;
iload 1
invokeinterface android/support/v4/view/accessibility/AccessibilityNodeInfoCompat$AccessibilityNodeInfoImpl/addAction(Ljava/lang/Object;I)V 2
return
.limit locals 2
.limit stack 3
.end method

.method public addChild(Landroid/view/View;)V
getstatic android/support/v4/view/accessibility/AccessibilityNodeInfoCompat/IMPL Landroid/support/v4/view/accessibility/AccessibilityNodeInfoCompat$AccessibilityNodeInfoImpl;
aload 0
getfield android/support/v4/view/accessibility/AccessibilityNodeInfoCompat/mInfo Ljava/lang/Object;
aload 1
invokeinterface android/support/v4/view/accessibility/AccessibilityNodeInfoCompat$AccessibilityNodeInfoImpl/addChild(Ljava/lang/Object;Landroid/view/View;)V 2
return
.limit locals 2
.limit stack 3
.end method

.method public addChild(Landroid/view/View;I)V
getstatic android/support/v4/view/accessibility/AccessibilityNodeInfoCompat/IMPL Landroid/support/v4/view/accessibility/AccessibilityNodeInfoCompat$AccessibilityNodeInfoImpl;
aload 0
getfield android/support/v4/view/accessibility/AccessibilityNodeInfoCompat/mInfo Ljava/lang/Object;
aload 1
iload 2
invokeinterface android/support/v4/view/accessibility/AccessibilityNodeInfoCompat$AccessibilityNodeInfoImpl/addChild(Ljava/lang/Object;Landroid/view/View;I)V 3
return
.limit locals 3
.limit stack 4
.end method

.method public equals(Ljava/lang/Object;)Z
aload 0
aload 1
if_acmpne L0
L1:
iconst_1
ireturn
L0:
aload 1
ifnonnull L2
iconst_0
ireturn
L2:
aload 0
invokevirtual java/lang/Object/getClass()Ljava/lang/Class;
aload 1
invokevirtual java/lang/Object/getClass()Ljava/lang/Class;
if_acmpeq L3
iconst_0
ireturn
L3:
aload 1
checkcast android/support/v4/view/accessibility/AccessibilityNodeInfoCompat
astore 1
aload 0
getfield android/support/v4/view/accessibility/AccessibilityNodeInfoCompat/mInfo Ljava/lang/Object;
ifnonnull L4
aload 1
getfield android/support/v4/view/accessibility/AccessibilityNodeInfoCompat/mInfo Ljava/lang/Object;
ifnull L1
iconst_0
ireturn
L4:
aload 0
getfield android/support/v4/view/accessibility/AccessibilityNodeInfoCompat/mInfo Ljava/lang/Object;
aload 1
getfield android/support/v4/view/accessibility/AccessibilityNodeInfoCompat/mInfo Ljava/lang/Object;
invokevirtual java/lang/Object/equals(Ljava/lang/Object;)Z
ifne L1
iconst_0
ireturn
.limit locals 2
.limit stack 2
.end method

.method public findAccessibilityNodeInfosByText(Ljava/lang/String;)Ljava/util/List;
.signature "(Ljava/lang/String;)Ljava/util/List<Landroid/support/v4/view/accessibility/AccessibilityNodeInfoCompat;>;"
new java/util/ArrayList
dup
invokespecial java/util/ArrayList/<init>()V
astore 4
getstatic android/support/v4/view/accessibility/AccessibilityNodeInfoCompat/IMPL Landroid/support/v4/view/accessibility/AccessibilityNodeInfoCompat$AccessibilityNodeInfoImpl;
aload 0
getfield android/support/v4/view/accessibility/AccessibilityNodeInfoCompat/mInfo Ljava/lang/Object;
aload 1
invokeinterface android/support/v4/view/accessibility/AccessibilityNodeInfoCompat$AccessibilityNodeInfoImpl/findAccessibilityNodeInfosByText(Ljava/lang/Object;Ljava/lang/String;)Ljava/util/List; 2
astore 1
aload 1
invokeinterface java/util/List/size()I 0
istore 3
iconst_0
istore 2
L0:
iload 2
iload 3
if_icmpge L1
aload 4
new android/support/v4/view/accessibility/AccessibilityNodeInfoCompat
dup
aload 1
iload 2
invokeinterface java/util/List/get(I)Ljava/lang/Object; 1
invokespecial android/support/v4/view/accessibility/AccessibilityNodeInfoCompat/<init>(Ljava/lang/Object;)V
invokeinterface java/util/List/add(Ljava/lang/Object;)Z 1
pop
iload 2
iconst_1
iadd
istore 2
goto L0
L1:
aload 4
areturn
.limit locals 5
.limit stack 5
.end method

.method public findFocus(I)Landroid/support/v4/view/accessibility/AccessibilityNodeInfoCompat;
getstatic android/support/v4/view/accessibility/AccessibilityNodeInfoCompat/IMPL Landroid/support/v4/view/accessibility/AccessibilityNodeInfoCompat$AccessibilityNodeInfoImpl;
aload 0
getfield android/support/v4/view/accessibility/AccessibilityNodeInfoCompat/mInfo Ljava/lang/Object;
iload 1
invokeinterface android/support/v4/view/accessibility/AccessibilityNodeInfoCompat$AccessibilityNodeInfoImpl/findFocus(Ljava/lang/Object;I)Ljava/lang/Object; 2
invokestatic android/support/v4/view/accessibility/AccessibilityNodeInfoCompat/wrapNonNullInstance(Ljava/lang/Object;)Landroid/support/v4/view/accessibility/AccessibilityNodeInfoCompat;
areturn
.limit locals 2
.limit stack 3
.end method

.method public focusSearch(I)Landroid/support/v4/view/accessibility/AccessibilityNodeInfoCompat;
getstatic android/support/v4/view/accessibility/AccessibilityNodeInfoCompat/IMPL Landroid/support/v4/view/accessibility/AccessibilityNodeInfoCompat$AccessibilityNodeInfoImpl;
aload 0
getfield android/support/v4/view/accessibility/AccessibilityNodeInfoCompat/mInfo Ljava/lang/Object;
iload 1
invokeinterface android/support/v4/view/accessibility/AccessibilityNodeInfoCompat$AccessibilityNodeInfoImpl/focusSearch(Ljava/lang/Object;I)Ljava/lang/Object; 2
invokestatic android/support/v4/view/accessibility/AccessibilityNodeInfoCompat/wrapNonNullInstance(Ljava/lang/Object;)Landroid/support/v4/view/accessibility/AccessibilityNodeInfoCompat;
areturn
.limit locals 2
.limit stack 3
.end method

.method public getActions()I
getstatic android/support/v4/view/accessibility/AccessibilityNodeInfoCompat/IMPL Landroid/support/v4/view/accessibility/AccessibilityNodeInfoCompat$AccessibilityNodeInfoImpl;
aload 0
getfield android/support/v4/view/accessibility/AccessibilityNodeInfoCompat/mInfo Ljava/lang/Object;
invokeinterface android/support/v4/view/accessibility/AccessibilityNodeInfoCompat$AccessibilityNodeInfoImpl/getActions(Ljava/lang/Object;)I 1
ireturn
.limit locals 1
.limit stack 2
.end method

.method public getBoundsInParent(Landroid/graphics/Rect;)V
getstatic android/support/v4/view/accessibility/AccessibilityNodeInfoCompat/IMPL Landroid/support/v4/view/accessibility/AccessibilityNodeInfoCompat$AccessibilityNodeInfoImpl;
aload 0
getfield android/support/v4/view/accessibility/AccessibilityNodeInfoCompat/mInfo Ljava/lang/Object;
aload 1
invokeinterface android/support/v4/view/accessibility/AccessibilityNodeInfoCompat$AccessibilityNodeInfoImpl/getBoundsInParent(Ljava/lang/Object;Landroid/graphics/Rect;)V 2
return
.limit locals 2
.limit stack 3
.end method

.method public getBoundsInScreen(Landroid/graphics/Rect;)V
getstatic android/support/v4/view/accessibility/AccessibilityNodeInfoCompat/IMPL Landroid/support/v4/view/accessibility/AccessibilityNodeInfoCompat$AccessibilityNodeInfoImpl;
aload 0
getfield android/support/v4/view/accessibility/AccessibilityNodeInfoCompat/mInfo Ljava/lang/Object;
aload 1
invokeinterface android/support/v4/view/accessibility/AccessibilityNodeInfoCompat$AccessibilityNodeInfoImpl/getBoundsInScreen(Ljava/lang/Object;Landroid/graphics/Rect;)V 2
return
.limit locals 2
.limit stack 3
.end method

.method public getChild(I)Landroid/support/v4/view/accessibility/AccessibilityNodeInfoCompat;
getstatic android/support/v4/view/accessibility/AccessibilityNodeInfoCompat/IMPL Landroid/support/v4/view/accessibility/AccessibilityNodeInfoCompat$AccessibilityNodeInfoImpl;
aload 0
getfield android/support/v4/view/accessibility/AccessibilityNodeInfoCompat/mInfo Ljava/lang/Object;
iload 1
invokeinterface android/support/v4/view/accessibility/AccessibilityNodeInfoCompat$AccessibilityNodeInfoImpl/getChild(Ljava/lang/Object;I)Ljava/lang/Object; 2
invokestatic android/support/v4/view/accessibility/AccessibilityNodeInfoCompat/wrapNonNullInstance(Ljava/lang/Object;)Landroid/support/v4/view/accessibility/AccessibilityNodeInfoCompat;
areturn
.limit locals 2
.limit stack 3
.end method

.method public getChildCount()I
getstatic android/support/v4/view/accessibility/AccessibilityNodeInfoCompat/IMPL Landroid/support/v4/view/accessibility/AccessibilityNodeInfoCompat$AccessibilityNodeInfoImpl;
aload 0
getfield android/support/v4/view/accessibility/AccessibilityNodeInfoCompat/mInfo Ljava/lang/Object;
invokeinterface android/support/v4/view/accessibility/AccessibilityNodeInfoCompat$AccessibilityNodeInfoImpl/getChildCount(Ljava/lang/Object;)I 1
ireturn
.limit locals 1
.limit stack 2
.end method

.method public getClassName()Ljava/lang/CharSequence;
getstatic android/support/v4/view/accessibility/AccessibilityNodeInfoCompat/IMPL Landroid/support/v4/view/accessibility/AccessibilityNodeInfoCompat$AccessibilityNodeInfoImpl;
aload 0
getfield android/support/v4/view/accessibility/AccessibilityNodeInfoCompat/mInfo Ljava/lang/Object;
invokeinterface android/support/v4/view/accessibility/AccessibilityNodeInfoCompat$AccessibilityNodeInfoImpl/getClassName(Ljava/lang/Object;)Ljava/lang/CharSequence; 1
areturn
.limit locals 1
.limit stack 2
.end method

.method public getContentDescription()Ljava/lang/CharSequence;
getstatic android/support/v4/view/accessibility/AccessibilityNodeInfoCompat/IMPL Landroid/support/v4/view/accessibility/AccessibilityNodeInfoCompat$AccessibilityNodeInfoImpl;
aload 0
getfield android/support/v4/view/accessibility/AccessibilityNodeInfoCompat/mInfo Ljava/lang/Object;
invokeinterface android/support/v4/view/accessibility/AccessibilityNodeInfoCompat$AccessibilityNodeInfoImpl/getContentDescription(Ljava/lang/Object;)Ljava/lang/CharSequence; 1
areturn
.limit locals 1
.limit stack 2
.end method

.method public getInfo()Ljava/lang/Object;
aload 0
getfield android/support/v4/view/accessibility/AccessibilityNodeInfoCompat/mInfo Ljava/lang/Object;
areturn
.limit locals 1
.limit stack 1
.end method

.method public getMovementGranularities()I
getstatic android/support/v4/view/accessibility/AccessibilityNodeInfoCompat/IMPL Landroid/support/v4/view/accessibility/AccessibilityNodeInfoCompat$AccessibilityNodeInfoImpl;
aload 0
getfield android/support/v4/view/accessibility/AccessibilityNodeInfoCompat/mInfo Ljava/lang/Object;
invokeinterface android/support/v4/view/accessibility/AccessibilityNodeInfoCompat$AccessibilityNodeInfoImpl/getMovementGranularities(Ljava/lang/Object;)I 1
ireturn
.limit locals 1
.limit stack 2
.end method

.method public getPackageName()Ljava/lang/CharSequence;
getstatic android/support/v4/view/accessibility/AccessibilityNodeInfoCompat/IMPL Landroid/support/v4/view/accessibility/AccessibilityNodeInfoCompat$AccessibilityNodeInfoImpl;
aload 0
getfield android/support/v4/view/accessibility/AccessibilityNodeInfoCompat/mInfo Ljava/lang/Object;
invokeinterface android/support/v4/view/accessibility/AccessibilityNodeInfoCompat$AccessibilityNodeInfoImpl/getPackageName(Ljava/lang/Object;)Ljava/lang/CharSequence; 1
areturn
.limit locals 1
.limit stack 2
.end method

.method public getParent()Landroid/support/v4/view/accessibility/AccessibilityNodeInfoCompat;
getstatic android/support/v4/view/accessibility/AccessibilityNodeInfoCompat/IMPL Landroid/support/v4/view/accessibility/AccessibilityNodeInfoCompat$AccessibilityNodeInfoImpl;
aload 0
getfield android/support/v4/view/accessibility/AccessibilityNodeInfoCompat/mInfo Ljava/lang/Object;
invokeinterface android/support/v4/view/accessibility/AccessibilityNodeInfoCompat$AccessibilityNodeInfoImpl/getParent(Ljava/lang/Object;)Ljava/lang/Object; 1
invokestatic android/support/v4/view/accessibility/AccessibilityNodeInfoCompat/wrapNonNullInstance(Ljava/lang/Object;)Landroid/support/v4/view/accessibility/AccessibilityNodeInfoCompat;
areturn
.limit locals 1
.limit stack 2
.end method

.method public getText()Ljava/lang/CharSequence;
getstatic android/support/v4/view/accessibility/AccessibilityNodeInfoCompat/IMPL Landroid/support/v4/view/accessibility/AccessibilityNodeInfoCompat$AccessibilityNodeInfoImpl;
aload 0
getfield android/support/v4/view/accessibility/AccessibilityNodeInfoCompat/mInfo Ljava/lang/Object;
invokeinterface android/support/v4/view/accessibility/AccessibilityNodeInfoCompat$AccessibilityNodeInfoImpl/getText(Ljava/lang/Object;)Ljava/lang/CharSequence; 1
areturn
.limit locals 1
.limit stack 2
.end method

.method public getWindowId()I
getstatic android/support/v4/view/accessibility/AccessibilityNodeInfoCompat/IMPL Landroid/support/v4/view/accessibility/AccessibilityNodeInfoCompat$AccessibilityNodeInfoImpl;
aload 0
getfield android/support/v4/view/accessibility/AccessibilityNodeInfoCompat/mInfo Ljava/lang/Object;
invokeinterface android/support/v4/view/accessibility/AccessibilityNodeInfoCompat$AccessibilityNodeInfoImpl/getWindowId(Ljava/lang/Object;)I 1
ireturn
.limit locals 1
.limit stack 2
.end method

.method public hashCode()I
aload 0
getfield android/support/v4/view/accessibility/AccessibilityNodeInfoCompat/mInfo Ljava/lang/Object;
ifnonnull L0
iconst_0
ireturn
L0:
aload 0
getfield android/support/v4/view/accessibility/AccessibilityNodeInfoCompat/mInfo Ljava/lang/Object;
invokevirtual java/lang/Object/hashCode()I
ireturn
.limit locals 1
.limit stack 1
.end method

.method public isAccessibilityFocused()Z
getstatic android/support/v4/view/accessibility/AccessibilityNodeInfoCompat/IMPL Landroid/support/v4/view/accessibility/AccessibilityNodeInfoCompat$AccessibilityNodeInfoImpl;
aload 0
getfield android/support/v4/view/accessibility/AccessibilityNodeInfoCompat/mInfo Ljava/lang/Object;
invokeinterface android/support/v4/view/accessibility/AccessibilityNodeInfoCompat$AccessibilityNodeInfoImpl/isAccessibilityFocused(Ljava/lang/Object;)Z 1
ireturn
.limit locals 1
.limit stack 2
.end method

.method public isCheckable()Z
getstatic android/support/v4/view/accessibility/AccessibilityNodeInfoCompat/IMPL Landroid/support/v4/view/accessibility/AccessibilityNodeInfoCompat$AccessibilityNodeInfoImpl;
aload 0
getfield android/support/v4/view/accessibility/AccessibilityNodeInfoCompat/mInfo Ljava/lang/Object;
invokeinterface android/support/v4/view/accessibility/AccessibilityNodeInfoCompat$AccessibilityNodeInfoImpl/isCheckable(Ljava/lang/Object;)Z 1
ireturn
.limit locals 1
.limit stack 2
.end method

.method public isChecked()Z
getstatic android/support/v4/view/accessibility/AccessibilityNodeInfoCompat/IMPL Landroid/support/v4/view/accessibility/AccessibilityNodeInfoCompat$AccessibilityNodeInfoImpl;
aload 0
getfield android/support/v4/view/accessibility/AccessibilityNodeInfoCompat/mInfo Ljava/lang/Object;
invokeinterface android/support/v4/view/accessibility/AccessibilityNodeInfoCompat$AccessibilityNodeInfoImpl/isChecked(Ljava/lang/Object;)Z 1
ireturn
.limit locals 1
.limit stack 2
.end method

.method public isClickable()Z
getstatic android/support/v4/view/accessibility/AccessibilityNodeInfoCompat/IMPL Landroid/support/v4/view/accessibility/AccessibilityNodeInfoCompat$AccessibilityNodeInfoImpl;
aload 0
getfield android/support/v4/view/accessibility/AccessibilityNodeInfoCompat/mInfo Ljava/lang/Object;
invokeinterface android/support/v4/view/accessibility/AccessibilityNodeInfoCompat$AccessibilityNodeInfoImpl/isClickable(Ljava/lang/Object;)Z 1
ireturn
.limit locals 1
.limit stack 2
.end method

.method public isEnabled()Z
getstatic android/support/v4/view/accessibility/AccessibilityNodeInfoCompat/IMPL Landroid/support/v4/view/accessibility/AccessibilityNodeInfoCompat$AccessibilityNodeInfoImpl;
aload 0
getfield android/support/v4/view/accessibility/AccessibilityNodeInfoCompat/mInfo Ljava/lang/Object;
invokeinterface android/support/v4/view/accessibility/AccessibilityNodeInfoCompat$AccessibilityNodeInfoImpl/isEnabled(Ljava/lang/Object;)Z 1
ireturn
.limit locals 1
.limit stack 2
.end method

.method public isFocusable()Z
getstatic android/support/v4/view/accessibility/AccessibilityNodeInfoCompat/IMPL Landroid/support/v4/view/accessibility/AccessibilityNodeInfoCompat$AccessibilityNodeInfoImpl;
aload 0
getfield android/support/v4/view/accessibility/AccessibilityNodeInfoCompat/mInfo Ljava/lang/Object;
invokeinterface android/support/v4/view/accessibility/AccessibilityNodeInfoCompat$AccessibilityNodeInfoImpl/isFocusable(Ljava/lang/Object;)Z 1
ireturn
.limit locals 1
.limit stack 2
.end method

.method public isFocused()Z
getstatic android/support/v4/view/accessibility/AccessibilityNodeInfoCompat/IMPL Landroid/support/v4/view/accessibility/AccessibilityNodeInfoCompat$AccessibilityNodeInfoImpl;
aload 0
getfield android/support/v4/view/accessibility/AccessibilityNodeInfoCompat/mInfo Ljava/lang/Object;
invokeinterface android/support/v4/view/accessibility/AccessibilityNodeInfoCompat$AccessibilityNodeInfoImpl/isFocused(Ljava/lang/Object;)Z 1
ireturn
.limit locals 1
.limit stack 2
.end method

.method public isLongClickable()Z
getstatic android/support/v4/view/accessibility/AccessibilityNodeInfoCompat/IMPL Landroid/support/v4/view/accessibility/AccessibilityNodeInfoCompat$AccessibilityNodeInfoImpl;
aload 0
getfield android/support/v4/view/accessibility/AccessibilityNodeInfoCompat/mInfo Ljava/lang/Object;
invokeinterface android/support/v4/view/accessibility/AccessibilityNodeInfoCompat$AccessibilityNodeInfoImpl/isLongClickable(Ljava/lang/Object;)Z 1
ireturn
.limit locals 1
.limit stack 2
.end method

.method public isPassword()Z
getstatic android/support/v4/view/accessibility/AccessibilityNodeInfoCompat/IMPL Landroid/support/v4/view/accessibility/AccessibilityNodeInfoCompat$AccessibilityNodeInfoImpl;
aload 0
getfield android/support/v4/view/accessibility/AccessibilityNodeInfoCompat/mInfo Ljava/lang/Object;
invokeinterface android/support/v4/view/accessibility/AccessibilityNodeInfoCompat$AccessibilityNodeInfoImpl/isPassword(Ljava/lang/Object;)Z 1
ireturn
.limit locals 1
.limit stack 2
.end method

.method public isScrollable()Z
getstatic android/support/v4/view/accessibility/AccessibilityNodeInfoCompat/IMPL Landroid/support/v4/view/accessibility/AccessibilityNodeInfoCompat$AccessibilityNodeInfoImpl;
aload 0
getfield android/support/v4/view/accessibility/AccessibilityNodeInfoCompat/mInfo Ljava/lang/Object;
invokeinterface android/support/v4/view/accessibility/AccessibilityNodeInfoCompat$AccessibilityNodeInfoImpl/isScrollable(Ljava/lang/Object;)Z 1
ireturn
.limit locals 1
.limit stack 2
.end method

.method public isSelected()Z
getstatic android/support/v4/view/accessibility/AccessibilityNodeInfoCompat/IMPL Landroid/support/v4/view/accessibility/AccessibilityNodeInfoCompat$AccessibilityNodeInfoImpl;
aload 0
getfield android/support/v4/view/accessibility/AccessibilityNodeInfoCompat/mInfo Ljava/lang/Object;
invokeinterface android/support/v4/view/accessibility/AccessibilityNodeInfoCompat$AccessibilityNodeInfoImpl/isSelected(Ljava/lang/Object;)Z 1
ireturn
.limit locals 1
.limit stack 2
.end method

.method public isVisibleToUser()Z
getstatic android/support/v4/view/accessibility/AccessibilityNodeInfoCompat/IMPL Landroid/support/v4/view/accessibility/AccessibilityNodeInfoCompat$AccessibilityNodeInfoImpl;
aload 0
getfield android/support/v4/view/accessibility/AccessibilityNodeInfoCompat/mInfo Ljava/lang/Object;
invokeinterface android/support/v4/view/accessibility/AccessibilityNodeInfoCompat$AccessibilityNodeInfoImpl/isVisibleToUser(Ljava/lang/Object;)Z 1
ireturn
.limit locals 1
.limit stack 2
.end method

.method public performAction(I)Z
getstatic android/support/v4/view/accessibility/AccessibilityNodeInfoCompat/IMPL Landroid/support/v4/view/accessibility/AccessibilityNodeInfoCompat$AccessibilityNodeInfoImpl;
aload 0
getfield android/support/v4/view/accessibility/AccessibilityNodeInfoCompat/mInfo Ljava/lang/Object;
iload 1
invokeinterface android/support/v4/view/accessibility/AccessibilityNodeInfoCompat$AccessibilityNodeInfoImpl/performAction(Ljava/lang/Object;I)Z 2
ireturn
.limit locals 2
.limit stack 3
.end method

.method public performAction(ILandroid/os/Bundle;)Z
getstatic android/support/v4/view/accessibility/AccessibilityNodeInfoCompat/IMPL Landroid/support/v4/view/accessibility/AccessibilityNodeInfoCompat$AccessibilityNodeInfoImpl;
aload 0
getfield android/support/v4/view/accessibility/AccessibilityNodeInfoCompat/mInfo Ljava/lang/Object;
iload 1
aload 2
invokeinterface android/support/v4/view/accessibility/AccessibilityNodeInfoCompat$AccessibilityNodeInfoImpl/performAction(Ljava/lang/Object;ILandroid/os/Bundle;)Z 3
ireturn
.limit locals 3
.limit stack 4
.end method

.method public recycle()V
getstatic android/support/v4/view/accessibility/AccessibilityNodeInfoCompat/IMPL Landroid/support/v4/view/accessibility/AccessibilityNodeInfoCompat$AccessibilityNodeInfoImpl;
aload 0
getfield android/support/v4/view/accessibility/AccessibilityNodeInfoCompat/mInfo Ljava/lang/Object;
invokeinterface android/support/v4/view/accessibility/AccessibilityNodeInfoCompat$AccessibilityNodeInfoImpl/recycle(Ljava/lang/Object;)V 1
return
.limit locals 1
.limit stack 2
.end method

.method public setAccessibilityFocused(Z)V
getstatic android/support/v4/view/accessibility/AccessibilityNodeInfoCompat/IMPL Landroid/support/v4/view/accessibility/AccessibilityNodeInfoCompat$AccessibilityNodeInfoImpl;
aload 0
getfield android/support/v4/view/accessibility/AccessibilityNodeInfoCompat/mInfo Ljava/lang/Object;
iload 1
invokeinterface android/support/v4/view/accessibility/AccessibilityNodeInfoCompat$AccessibilityNodeInfoImpl/setAccessibilityFocused(Ljava/lang/Object;Z)V 2
return
.limit locals 2
.limit stack 3
.end method

.method public setBoundsInParent(Landroid/graphics/Rect;)V
getstatic android/support/v4/view/accessibility/AccessibilityNodeInfoCompat/IMPL Landroid/support/v4/view/accessibility/AccessibilityNodeInfoCompat$AccessibilityNodeInfoImpl;
aload 0
getfield android/support/v4/view/accessibility/AccessibilityNodeInfoCompat/mInfo Ljava/lang/Object;
aload 1
invokeinterface android/support/v4/view/accessibility/AccessibilityNodeInfoCompat$AccessibilityNodeInfoImpl/setBoundsInParent(Ljava/lang/Object;Landroid/graphics/Rect;)V 2
return
.limit locals 2
.limit stack 3
.end method

.method public setBoundsInScreen(Landroid/graphics/Rect;)V
getstatic android/support/v4/view/accessibility/AccessibilityNodeInfoCompat/IMPL Landroid/support/v4/view/accessibility/AccessibilityNodeInfoCompat$AccessibilityNodeInfoImpl;
aload 0
getfield android/support/v4/view/accessibility/AccessibilityNodeInfoCompat/mInfo Ljava/lang/Object;
aload 1
invokeinterface android/support/v4/view/accessibility/AccessibilityNodeInfoCompat$AccessibilityNodeInfoImpl/setBoundsInScreen(Ljava/lang/Object;Landroid/graphics/Rect;)V 2
return
.limit locals 2
.limit stack 3
.end method

.method public setCheckable(Z)V
getstatic android/support/v4/view/accessibility/AccessibilityNodeInfoCompat/IMPL Landroid/support/v4/view/accessibility/AccessibilityNodeInfoCompat$AccessibilityNodeInfoImpl;
aload 0
getfield android/support/v4/view/accessibility/AccessibilityNodeInfoCompat/mInfo Ljava/lang/Object;
iload 1
invokeinterface android/support/v4/view/accessibility/AccessibilityNodeInfoCompat$AccessibilityNodeInfoImpl/setCheckable(Ljava/lang/Object;Z)V 2
return
.limit locals 2
.limit stack 3
.end method

.method public setChecked(Z)V
getstatic android/support/v4/view/accessibility/AccessibilityNodeInfoCompat/IMPL Landroid/support/v4/view/accessibility/AccessibilityNodeInfoCompat$AccessibilityNodeInfoImpl;
aload 0
getfield android/support/v4/view/accessibility/AccessibilityNodeInfoCompat/mInfo Ljava/lang/Object;
iload 1
invokeinterface android/support/v4/view/accessibility/AccessibilityNodeInfoCompat$AccessibilityNodeInfoImpl/setChecked(Ljava/lang/Object;Z)V 2
return
.limit locals 2
.limit stack 3
.end method

.method public setClassName(Ljava/lang/CharSequence;)V
getstatic android/support/v4/view/accessibility/AccessibilityNodeInfoCompat/IMPL Landroid/support/v4/view/accessibility/AccessibilityNodeInfoCompat$AccessibilityNodeInfoImpl;
aload 0
getfield android/support/v4/view/accessibility/AccessibilityNodeInfoCompat/mInfo Ljava/lang/Object;
aload 1
invokeinterface android/support/v4/view/accessibility/AccessibilityNodeInfoCompat$AccessibilityNodeInfoImpl/setClassName(Ljava/lang/Object;Ljava/lang/CharSequence;)V 2
return
.limit locals 2
.limit stack 3
.end method

.method public setClickable(Z)V
getstatic android/support/v4/view/accessibility/AccessibilityNodeInfoCompat/IMPL Landroid/support/v4/view/accessibility/AccessibilityNodeInfoCompat$AccessibilityNodeInfoImpl;
aload 0
getfield android/support/v4/view/accessibility/AccessibilityNodeInfoCompat/mInfo Ljava/lang/Object;
iload 1
invokeinterface android/support/v4/view/accessibility/AccessibilityNodeInfoCompat$AccessibilityNodeInfoImpl/setClickable(Ljava/lang/Object;Z)V 2
return
.limit locals 2
.limit stack 3
.end method

.method public setContentDescription(Ljava/lang/CharSequence;)V
getstatic android/support/v4/view/accessibility/AccessibilityNodeInfoCompat/IMPL Landroid/support/v4/view/accessibility/AccessibilityNodeInfoCompat$AccessibilityNodeInfoImpl;
aload 0
getfield android/support/v4/view/accessibility/AccessibilityNodeInfoCompat/mInfo Ljava/lang/Object;
aload 1
invokeinterface android/support/v4/view/accessibility/AccessibilityNodeInfoCompat$AccessibilityNodeInfoImpl/setContentDescription(Ljava/lang/Object;Ljava/lang/CharSequence;)V 2
return
.limit locals 2
.limit stack 3
.end method

.method public setEnabled(Z)V
getstatic android/support/v4/view/accessibility/AccessibilityNodeInfoCompat/IMPL Landroid/support/v4/view/accessibility/AccessibilityNodeInfoCompat$AccessibilityNodeInfoImpl;
aload 0
getfield android/support/v4/view/accessibility/AccessibilityNodeInfoCompat/mInfo Ljava/lang/Object;
iload 1
invokeinterface android/support/v4/view/accessibility/AccessibilityNodeInfoCompat$AccessibilityNodeInfoImpl/setEnabled(Ljava/lang/Object;Z)V 2
return
.limit locals 2
.limit stack 3
.end method

.method public setFocusable(Z)V
getstatic android/support/v4/view/accessibility/AccessibilityNodeInfoCompat/IMPL Landroid/support/v4/view/accessibility/AccessibilityNodeInfoCompat$AccessibilityNodeInfoImpl;
aload 0
getfield android/support/v4/view/accessibility/AccessibilityNodeInfoCompat/mInfo Ljava/lang/Object;
iload 1
invokeinterface android/support/v4/view/accessibility/AccessibilityNodeInfoCompat$AccessibilityNodeInfoImpl/setFocusable(Ljava/lang/Object;Z)V 2
return
.limit locals 2
.limit stack 3
.end method

.method public setFocused(Z)V
getstatic android/support/v4/view/accessibility/AccessibilityNodeInfoCompat/IMPL Landroid/support/v4/view/accessibility/AccessibilityNodeInfoCompat$AccessibilityNodeInfoImpl;
aload 0
getfield android/support/v4/view/accessibility/AccessibilityNodeInfoCompat/mInfo Ljava/lang/Object;
iload 1
invokeinterface android/support/v4/view/accessibility/AccessibilityNodeInfoCompat$AccessibilityNodeInfoImpl/setFocused(Ljava/lang/Object;Z)V 2
return
.limit locals 2
.limit stack 3
.end method

.method public setLongClickable(Z)V
getstatic android/support/v4/view/accessibility/AccessibilityNodeInfoCompat/IMPL Landroid/support/v4/view/accessibility/AccessibilityNodeInfoCompat$AccessibilityNodeInfoImpl;
aload 0
getfield android/support/v4/view/accessibility/AccessibilityNodeInfoCompat/mInfo Ljava/lang/Object;
iload 1
invokeinterface android/support/v4/view/accessibility/AccessibilityNodeInfoCompat$AccessibilityNodeInfoImpl/setLongClickable(Ljava/lang/Object;Z)V 2
return
.limit locals 2
.limit stack 3
.end method

.method public setMovementGranularities(I)V
getstatic android/support/v4/view/accessibility/AccessibilityNodeInfoCompat/IMPL Landroid/support/v4/view/accessibility/AccessibilityNodeInfoCompat$AccessibilityNodeInfoImpl;
aload 0
getfield android/support/v4/view/accessibility/AccessibilityNodeInfoCompat/mInfo Ljava/lang/Object;
iload 1
invokeinterface android/support/v4/view/accessibility/AccessibilityNodeInfoCompat$AccessibilityNodeInfoImpl/setMovementGranularities(Ljava/lang/Object;I)V 2
return
.limit locals 2
.limit stack 3
.end method

.method public setPackageName(Ljava/lang/CharSequence;)V
getstatic android/support/v4/view/accessibility/AccessibilityNodeInfoCompat/IMPL Landroid/support/v4/view/accessibility/AccessibilityNodeInfoCompat$AccessibilityNodeInfoImpl;
aload 0
getfield android/support/v4/view/accessibility/AccessibilityNodeInfoCompat/mInfo Ljava/lang/Object;
aload 1
invokeinterface android/support/v4/view/accessibility/AccessibilityNodeInfoCompat$AccessibilityNodeInfoImpl/setPackageName(Ljava/lang/Object;Ljava/lang/CharSequence;)V 2
return
.limit locals 2
.limit stack 3
.end method

.method public setParent(Landroid/view/View;)V
getstatic android/support/v4/view/accessibility/AccessibilityNodeInfoCompat/IMPL Landroid/support/v4/view/accessibility/AccessibilityNodeInfoCompat$AccessibilityNodeInfoImpl;
aload 0
getfield android/support/v4/view/accessibility/AccessibilityNodeInfoCompat/mInfo Ljava/lang/Object;
aload 1
invokeinterface android/support/v4/view/accessibility/AccessibilityNodeInfoCompat$AccessibilityNodeInfoImpl/setParent(Ljava/lang/Object;Landroid/view/View;)V 2
return
.limit locals 2
.limit stack 3
.end method

.method public setParent(Landroid/view/View;I)V
getstatic android/support/v4/view/accessibility/AccessibilityNodeInfoCompat/IMPL Landroid/support/v4/view/accessibility/AccessibilityNodeInfoCompat$AccessibilityNodeInfoImpl;
aload 0
getfield android/support/v4/view/accessibility/AccessibilityNodeInfoCompat/mInfo Ljava/lang/Object;
aload 1
iload 2
invokeinterface android/support/v4/view/accessibility/AccessibilityNodeInfoCompat$AccessibilityNodeInfoImpl/setParent(Ljava/lang/Object;Landroid/view/View;I)V 3
return
.limit locals 3
.limit stack 4
.end method

.method public setPassword(Z)V
getstatic android/support/v4/view/accessibility/AccessibilityNodeInfoCompat/IMPL Landroid/support/v4/view/accessibility/AccessibilityNodeInfoCompat$AccessibilityNodeInfoImpl;
aload 0
getfield android/support/v4/view/accessibility/AccessibilityNodeInfoCompat/mInfo Ljava/lang/Object;
iload 1
invokeinterface android/support/v4/view/accessibility/AccessibilityNodeInfoCompat$AccessibilityNodeInfoImpl/setPassword(Ljava/lang/Object;Z)V 2
return
.limit locals 2
.limit stack 3
.end method

.method public setScrollable(Z)V
getstatic android/support/v4/view/accessibility/AccessibilityNodeInfoCompat/IMPL Landroid/support/v4/view/accessibility/AccessibilityNodeInfoCompat$AccessibilityNodeInfoImpl;
aload 0
getfield android/support/v4/view/accessibility/AccessibilityNodeInfoCompat/mInfo Ljava/lang/Object;
iload 1
invokeinterface android/support/v4/view/accessibility/AccessibilityNodeInfoCompat$AccessibilityNodeInfoImpl/setScrollable(Ljava/lang/Object;Z)V 2
return
.limit locals 2
.limit stack 3
.end method

.method public setSelected(Z)V
getstatic android/support/v4/view/accessibility/AccessibilityNodeInfoCompat/IMPL Landroid/support/v4/view/accessibility/AccessibilityNodeInfoCompat$AccessibilityNodeInfoImpl;
aload 0
getfield android/support/v4/view/accessibility/AccessibilityNodeInfoCompat/mInfo Ljava/lang/Object;
iload 1
invokeinterface android/support/v4/view/accessibility/AccessibilityNodeInfoCompat$AccessibilityNodeInfoImpl/setSelected(Ljava/lang/Object;Z)V 2
return
.limit locals 2
.limit stack 3
.end method

.method public setSource(Landroid/view/View;)V
getstatic android/support/v4/view/accessibility/AccessibilityNodeInfoCompat/IMPL Landroid/support/v4/view/accessibility/AccessibilityNodeInfoCompat$AccessibilityNodeInfoImpl;
aload 0
getfield android/support/v4/view/accessibility/AccessibilityNodeInfoCompat/mInfo Ljava/lang/Object;
aload 1
invokeinterface android/support/v4/view/accessibility/AccessibilityNodeInfoCompat$AccessibilityNodeInfoImpl/setSource(Ljava/lang/Object;Landroid/view/View;)V 2
return
.limit locals 2
.limit stack 3
.end method

.method public setSource(Landroid/view/View;I)V
getstatic android/support/v4/view/accessibility/AccessibilityNodeInfoCompat/IMPL Landroid/support/v4/view/accessibility/AccessibilityNodeInfoCompat$AccessibilityNodeInfoImpl;
aload 0
getfield android/support/v4/view/accessibility/AccessibilityNodeInfoCompat/mInfo Ljava/lang/Object;
aload 1
iload 2
invokeinterface android/support/v4/view/accessibility/AccessibilityNodeInfoCompat$AccessibilityNodeInfoImpl/setSource(Ljava/lang/Object;Landroid/view/View;I)V 3
return
.limit locals 3
.limit stack 4
.end method

.method public setText(Ljava/lang/CharSequence;)V
getstatic android/support/v4/view/accessibility/AccessibilityNodeInfoCompat/IMPL Landroid/support/v4/view/accessibility/AccessibilityNodeInfoCompat$AccessibilityNodeInfoImpl;
aload 0
getfield android/support/v4/view/accessibility/AccessibilityNodeInfoCompat/mInfo Ljava/lang/Object;
aload 1
invokeinterface android/support/v4/view/accessibility/AccessibilityNodeInfoCompat$AccessibilityNodeInfoImpl/setText(Ljava/lang/Object;Ljava/lang/CharSequence;)V 2
return
.limit locals 2
.limit stack 3
.end method

.method public setVisibleToUser(Z)V
getstatic android/support/v4/view/accessibility/AccessibilityNodeInfoCompat/IMPL Landroid/support/v4/view/accessibility/AccessibilityNodeInfoCompat$AccessibilityNodeInfoImpl;
aload 0
getfield android/support/v4/view/accessibility/AccessibilityNodeInfoCompat/mInfo Ljava/lang/Object;
iload 1
invokeinterface android/support/v4/view/accessibility/AccessibilityNodeInfoCompat$AccessibilityNodeInfoImpl/setVisibleToUser(Ljava/lang/Object;Z)V 2
return
.limit locals 2
.limit stack 3
.end method
