.bytecode 50.0
.class synchronized android/support/v4/view/accessibility/AccessibilityNodeInfoCompatIcs
.super java/lang/Object

.method <init>()V
aload 0
invokespecial java/lang/Object/<init>()V
return
.limit locals 1
.limit stack 1
.end method

.method public static addAction(Ljava/lang/Object;I)V
aload 0
checkcast android/view/accessibility/AccessibilityNodeInfo
iload 1
invokevirtual android/view/accessibility/AccessibilityNodeInfo/addAction(I)V
return
.limit locals 2
.limit stack 2
.end method

.method public static addChild(Ljava/lang/Object;Landroid/view/View;)V
aload 0
checkcast android/view/accessibility/AccessibilityNodeInfo
aload 1
invokevirtual android/view/accessibility/AccessibilityNodeInfo/addChild(Landroid/view/View;)V
return
.limit locals 2
.limit stack 2
.end method

.method public static findAccessibilityNodeInfosByText(Ljava/lang/Object;Ljava/lang/String;)Ljava/util/List;
.signature "(Ljava/lang/Object;Ljava/lang/String;)Ljava/util/List<Ljava/lang/Object;>;"
aload 0
checkcast android/view/accessibility/AccessibilityNodeInfo
aload 1
invokevirtual android/view/accessibility/AccessibilityNodeInfo/findAccessibilityNodeInfosByText(Ljava/lang/String;)Ljava/util/List;
checkcast java/util/List
areturn
.limit locals 2
.limit stack 2
.end method

.method public static getActions(Ljava/lang/Object;)I
aload 0
checkcast android/view/accessibility/AccessibilityNodeInfo
invokevirtual android/view/accessibility/AccessibilityNodeInfo/getActions()I
ireturn
.limit locals 1
.limit stack 1
.end method

.method public static getBoundsInParent(Ljava/lang/Object;Landroid/graphics/Rect;)V
aload 0
checkcast android/view/accessibility/AccessibilityNodeInfo
aload 1
invokevirtual android/view/accessibility/AccessibilityNodeInfo/getBoundsInParent(Landroid/graphics/Rect;)V
return
.limit locals 2
.limit stack 2
.end method

.method public static getBoundsInScreen(Ljava/lang/Object;Landroid/graphics/Rect;)V
aload 0
checkcast android/view/accessibility/AccessibilityNodeInfo
aload 1
invokevirtual android/view/accessibility/AccessibilityNodeInfo/getBoundsInScreen(Landroid/graphics/Rect;)V
return
.limit locals 2
.limit stack 2
.end method

.method public static getChild(Ljava/lang/Object;I)Ljava/lang/Object;
aload 0
checkcast android/view/accessibility/AccessibilityNodeInfo
iload 1
invokevirtual android/view/accessibility/AccessibilityNodeInfo/getChild(I)Landroid/view/accessibility/AccessibilityNodeInfo;
areturn
.limit locals 2
.limit stack 2
.end method

.method public static getChildCount(Ljava/lang/Object;)I
aload 0
checkcast android/view/accessibility/AccessibilityNodeInfo
invokevirtual android/view/accessibility/AccessibilityNodeInfo/getChildCount()I
ireturn
.limit locals 1
.limit stack 1
.end method

.method public static getClassName(Ljava/lang/Object;)Ljava/lang/CharSequence;
aload 0
checkcast android/view/accessibility/AccessibilityNodeInfo
invokevirtual android/view/accessibility/AccessibilityNodeInfo/getClassName()Ljava/lang/CharSequence;
areturn
.limit locals 1
.limit stack 1
.end method

.method public static getContentDescription(Ljava/lang/Object;)Ljava/lang/CharSequence;
aload 0
checkcast android/view/accessibility/AccessibilityNodeInfo
invokevirtual android/view/accessibility/AccessibilityNodeInfo/getContentDescription()Ljava/lang/CharSequence;
areturn
.limit locals 1
.limit stack 1
.end method

.method public static getPackageName(Ljava/lang/Object;)Ljava/lang/CharSequence;
aload 0
checkcast android/view/accessibility/AccessibilityNodeInfo
invokevirtual android/view/accessibility/AccessibilityNodeInfo/getPackageName()Ljava/lang/CharSequence;
areturn
.limit locals 1
.limit stack 1
.end method

.method public static getParent(Ljava/lang/Object;)Ljava/lang/Object;
aload 0
checkcast android/view/accessibility/AccessibilityNodeInfo
invokevirtual android/view/accessibility/AccessibilityNodeInfo/getParent()Landroid/view/accessibility/AccessibilityNodeInfo;
areturn
.limit locals 1
.limit stack 1
.end method

.method public static getText(Ljava/lang/Object;)Ljava/lang/CharSequence;
aload 0
checkcast android/view/accessibility/AccessibilityNodeInfo
invokevirtual android/view/accessibility/AccessibilityNodeInfo/getText()Ljava/lang/CharSequence;
areturn
.limit locals 1
.limit stack 1
.end method

.method public static getWindowId(Ljava/lang/Object;)I
aload 0
checkcast android/view/accessibility/AccessibilityNodeInfo
invokevirtual android/view/accessibility/AccessibilityNodeInfo/getWindowId()I
ireturn
.limit locals 1
.limit stack 1
.end method

.method public static isCheckable(Ljava/lang/Object;)Z
aload 0
checkcast android/view/accessibility/AccessibilityNodeInfo
invokevirtual android/view/accessibility/AccessibilityNodeInfo/isCheckable()Z
ireturn
.limit locals 1
.limit stack 1
.end method

.method public static isChecked(Ljava/lang/Object;)Z
aload 0
checkcast android/view/accessibility/AccessibilityNodeInfo
invokevirtual android/view/accessibility/AccessibilityNodeInfo/isChecked()Z
ireturn
.limit locals 1
.limit stack 1
.end method

.method public static isClickable(Ljava/lang/Object;)Z
aload 0
checkcast android/view/accessibility/AccessibilityNodeInfo
invokevirtual android/view/accessibility/AccessibilityNodeInfo/isClickable()Z
ireturn
.limit locals 1
.limit stack 1
.end method

.method public static isEnabled(Ljava/lang/Object;)Z
aload 0
checkcast android/view/accessibility/AccessibilityNodeInfo
invokevirtual android/view/accessibility/AccessibilityNodeInfo/isEnabled()Z
ireturn
.limit locals 1
.limit stack 1
.end method

.method public static isFocusable(Ljava/lang/Object;)Z
aload 0
checkcast android/view/accessibility/AccessibilityNodeInfo
invokevirtual android/view/accessibility/AccessibilityNodeInfo/isFocusable()Z
ireturn
.limit locals 1
.limit stack 1
.end method

.method public static isFocused(Ljava/lang/Object;)Z
aload 0
checkcast android/view/accessibility/AccessibilityNodeInfo
invokevirtual android/view/accessibility/AccessibilityNodeInfo/isFocused()Z
ireturn
.limit locals 1
.limit stack 1
.end method

.method public static isLongClickable(Ljava/lang/Object;)Z
aload 0
checkcast android/view/accessibility/AccessibilityNodeInfo
invokevirtual android/view/accessibility/AccessibilityNodeInfo/isLongClickable()Z
ireturn
.limit locals 1
.limit stack 1
.end method

.method public static isPassword(Ljava/lang/Object;)Z
aload 0
checkcast android/view/accessibility/AccessibilityNodeInfo
invokevirtual android/view/accessibility/AccessibilityNodeInfo/isPassword()Z
ireturn
.limit locals 1
.limit stack 1
.end method

.method public static isScrollable(Ljava/lang/Object;)Z
aload 0
checkcast android/view/accessibility/AccessibilityNodeInfo
invokevirtual android/view/accessibility/AccessibilityNodeInfo/isScrollable()Z
ireturn
.limit locals 1
.limit stack 1
.end method

.method public static isSelected(Ljava/lang/Object;)Z
aload 0
checkcast android/view/accessibility/AccessibilityNodeInfo
invokevirtual android/view/accessibility/AccessibilityNodeInfo/isSelected()Z
ireturn
.limit locals 1
.limit stack 1
.end method

.method public static obtain()Ljava/lang/Object;
invokestatic android/view/accessibility/AccessibilityNodeInfo/obtain()Landroid/view/accessibility/AccessibilityNodeInfo;
areturn
.limit locals 0
.limit stack 1
.end method

.method public static obtain(Landroid/view/View;)Ljava/lang/Object;
aload 0
invokestatic android/view/accessibility/AccessibilityNodeInfo/obtain(Landroid/view/View;)Landroid/view/accessibility/AccessibilityNodeInfo;
areturn
.limit locals 1
.limit stack 1
.end method

.method public static obtain(Ljava/lang/Object;)Ljava/lang/Object;
aload 0
checkcast android/view/accessibility/AccessibilityNodeInfo
invokestatic android/view/accessibility/AccessibilityNodeInfo/obtain(Landroid/view/accessibility/AccessibilityNodeInfo;)Landroid/view/accessibility/AccessibilityNodeInfo;
areturn
.limit locals 1
.limit stack 1
.end method

.method public static performAction(Ljava/lang/Object;I)Z
aload 0
checkcast android/view/accessibility/AccessibilityNodeInfo
iload 1
invokevirtual android/view/accessibility/AccessibilityNodeInfo/performAction(I)Z
ireturn
.limit locals 2
.limit stack 2
.end method

.method public static recycle(Ljava/lang/Object;)V
aload 0
checkcast android/view/accessibility/AccessibilityNodeInfo
invokevirtual android/view/accessibility/AccessibilityNodeInfo/recycle()V
return
.limit locals 1
.limit stack 1
.end method

.method public static setBoundsInParent(Ljava/lang/Object;Landroid/graphics/Rect;)V
aload 0
checkcast android/view/accessibility/AccessibilityNodeInfo
aload 1
invokevirtual android/view/accessibility/AccessibilityNodeInfo/setBoundsInParent(Landroid/graphics/Rect;)V
return
.limit locals 2
.limit stack 2
.end method

.method public static setBoundsInScreen(Ljava/lang/Object;Landroid/graphics/Rect;)V
aload 0
checkcast android/view/accessibility/AccessibilityNodeInfo
aload 1
invokevirtual android/view/accessibility/AccessibilityNodeInfo/setBoundsInScreen(Landroid/graphics/Rect;)V
return
.limit locals 2
.limit stack 2
.end method

.method public static setCheckable(Ljava/lang/Object;Z)V
aload 0
checkcast android/view/accessibility/AccessibilityNodeInfo
iload 1
invokevirtual android/view/accessibility/AccessibilityNodeInfo/setCheckable(Z)V
return
.limit locals 2
.limit stack 2
.end method

.method public static setChecked(Ljava/lang/Object;Z)V
aload 0
checkcast android/view/accessibility/AccessibilityNodeInfo
iload 1
invokevirtual android/view/accessibility/AccessibilityNodeInfo/setChecked(Z)V
return
.limit locals 2
.limit stack 2
.end method

.method public static setClassName(Ljava/lang/Object;Ljava/lang/CharSequence;)V
aload 0
checkcast android/view/accessibility/AccessibilityNodeInfo
aload 1
invokevirtual android/view/accessibility/AccessibilityNodeInfo/setClassName(Ljava/lang/CharSequence;)V
return
.limit locals 2
.limit stack 2
.end method

.method public static setClickable(Ljava/lang/Object;Z)V
aload 0
checkcast android/view/accessibility/AccessibilityNodeInfo
iload 1
invokevirtual android/view/accessibility/AccessibilityNodeInfo/setClickable(Z)V
return
.limit locals 2
.limit stack 2
.end method

.method public static setContentDescription(Ljava/lang/Object;Ljava/lang/CharSequence;)V
aload 0
checkcast android/view/accessibility/AccessibilityNodeInfo
aload 1
invokevirtual android/view/accessibility/AccessibilityNodeInfo/setContentDescription(Ljava/lang/CharSequence;)V
return
.limit locals 2
.limit stack 2
.end method

.method public static setEnabled(Ljava/lang/Object;Z)V
aload 0
checkcast android/view/accessibility/AccessibilityNodeInfo
iload 1
invokevirtual android/view/accessibility/AccessibilityNodeInfo/setEnabled(Z)V
return
.limit locals 2
.limit stack 2
.end method

.method public static setFocusable(Ljava/lang/Object;Z)V
aload 0
checkcast android/view/accessibility/AccessibilityNodeInfo
iload 1
invokevirtual android/view/accessibility/AccessibilityNodeInfo/setFocusable(Z)V
return
.limit locals 2
.limit stack 2
.end method

.method public static setFocused(Ljava/lang/Object;Z)V
aload 0
checkcast android/view/accessibility/AccessibilityNodeInfo
iload 1
invokevirtual android/view/accessibility/AccessibilityNodeInfo/setFocused(Z)V
return
.limit locals 2
.limit stack 2
.end method

.method public static setLongClickable(Ljava/lang/Object;Z)V
aload 0
checkcast android/view/accessibility/AccessibilityNodeInfo
iload 1
invokevirtual android/view/accessibility/AccessibilityNodeInfo/setLongClickable(Z)V
return
.limit locals 2
.limit stack 2
.end method

.method public static setPackageName(Ljava/lang/Object;Ljava/lang/CharSequence;)V
aload 0
checkcast android/view/accessibility/AccessibilityNodeInfo
aload 1
invokevirtual android/view/accessibility/AccessibilityNodeInfo/setPackageName(Ljava/lang/CharSequence;)V
return
.limit locals 2
.limit stack 2
.end method

.method public static setParent(Ljava/lang/Object;Landroid/view/View;)V
aload 0
checkcast android/view/accessibility/AccessibilityNodeInfo
aload 1
invokevirtual android/view/accessibility/AccessibilityNodeInfo/setParent(Landroid/view/View;)V
return
.limit locals 2
.limit stack 2
.end method

.method public static setPassword(Ljava/lang/Object;Z)V
aload 0
checkcast android/view/accessibility/AccessibilityNodeInfo
iload 1
invokevirtual android/view/accessibility/AccessibilityNodeInfo/setPassword(Z)V
return
.limit locals 2
.limit stack 2
.end method

.method public static setScrollable(Ljava/lang/Object;Z)V
aload 0
checkcast android/view/accessibility/AccessibilityNodeInfo
iload 1
invokevirtual android/view/accessibility/AccessibilityNodeInfo/setScrollable(Z)V
return
.limit locals 2
.limit stack 2
.end method

.method public static setSelected(Ljava/lang/Object;Z)V
aload 0
checkcast android/view/accessibility/AccessibilityNodeInfo
iload 1
invokevirtual android/view/accessibility/AccessibilityNodeInfo/setSelected(Z)V
return
.limit locals 2
.limit stack 2
.end method

.method public static setSource(Ljava/lang/Object;Landroid/view/View;)V
aload 0
checkcast android/view/accessibility/AccessibilityNodeInfo
aload 1
invokevirtual android/view/accessibility/AccessibilityNodeInfo/setSource(Landroid/view/View;)V
return
.limit locals 2
.limit stack 2
.end method

.method public static setText(Ljava/lang/Object;Ljava/lang/CharSequence;)V
aload 0
checkcast android/view/accessibility/AccessibilityNodeInfo
aload 1
invokevirtual android/view/accessibility/AccessibilityNodeInfo/setText(Ljava/lang/CharSequence;)V
return
.limit locals 2
.limit stack 2
.end method
