.bytecode 50.0
.class synchronized android/support/v4/view/accessibility/AccessibilityRecordCompatIcs
.super java/lang/Object

.method <init>()V
aload 0
invokespecial java/lang/Object/<init>()V
return
.limit locals 1
.limit stack 1
.end method

.method public static getAddedCount(Ljava/lang/Object;)I
aload 0
checkcast android/view/accessibility/AccessibilityRecord
invokevirtual android/view/accessibility/AccessibilityRecord/getAddedCount()I
ireturn
.limit locals 1
.limit stack 1
.end method

.method public static getBeforeText(Ljava/lang/Object;)Ljava/lang/CharSequence;
aload 0
checkcast android/view/accessibility/AccessibilityRecord
invokevirtual android/view/accessibility/AccessibilityRecord/getBeforeText()Ljava/lang/CharSequence;
areturn
.limit locals 1
.limit stack 1
.end method

.method public static getClassName(Ljava/lang/Object;)Ljava/lang/CharSequence;
aload 0
checkcast android/view/accessibility/AccessibilityRecord
invokevirtual android/view/accessibility/AccessibilityRecord/getClassName()Ljava/lang/CharSequence;
areturn
.limit locals 1
.limit stack 1
.end method

.method public static getContentDescription(Ljava/lang/Object;)Ljava/lang/CharSequence;
aload 0
checkcast android/view/accessibility/AccessibilityRecord
invokevirtual android/view/accessibility/AccessibilityRecord/getContentDescription()Ljava/lang/CharSequence;
areturn
.limit locals 1
.limit stack 1
.end method

.method public static getCurrentItemIndex(Ljava/lang/Object;)I
aload 0
checkcast android/view/accessibility/AccessibilityRecord
invokevirtual android/view/accessibility/AccessibilityRecord/getCurrentItemIndex()I
ireturn
.limit locals 1
.limit stack 1
.end method

.method public static getFromIndex(Ljava/lang/Object;)I
aload 0
checkcast android/view/accessibility/AccessibilityRecord
invokevirtual android/view/accessibility/AccessibilityRecord/getFromIndex()I
ireturn
.limit locals 1
.limit stack 1
.end method

.method public static getItemCount(Ljava/lang/Object;)I
aload 0
checkcast android/view/accessibility/AccessibilityRecord
invokevirtual android/view/accessibility/AccessibilityRecord/getItemCount()I
ireturn
.limit locals 1
.limit stack 1
.end method

.method public static getParcelableData(Ljava/lang/Object;)Landroid/os/Parcelable;
aload 0
checkcast android/view/accessibility/AccessibilityRecord
invokevirtual android/view/accessibility/AccessibilityRecord/getParcelableData()Landroid/os/Parcelable;
areturn
.limit locals 1
.limit stack 1
.end method

.method public static getRemovedCount(Ljava/lang/Object;)I
aload 0
checkcast android/view/accessibility/AccessibilityRecord
invokevirtual android/view/accessibility/AccessibilityRecord/getRemovedCount()I
ireturn
.limit locals 1
.limit stack 1
.end method

.method public static getScrollX(Ljava/lang/Object;)I
aload 0
checkcast android/view/accessibility/AccessibilityRecord
invokevirtual android/view/accessibility/AccessibilityRecord/getScrollX()I
ireturn
.limit locals 1
.limit stack 1
.end method

.method public static getScrollY(Ljava/lang/Object;)I
aload 0
checkcast android/view/accessibility/AccessibilityRecord
invokevirtual android/view/accessibility/AccessibilityRecord/getScrollY()I
ireturn
.limit locals 1
.limit stack 1
.end method

.method public static getSource(Ljava/lang/Object;)Ljava/lang/Object;
aload 0
checkcast android/view/accessibility/AccessibilityRecord
invokevirtual android/view/accessibility/AccessibilityRecord/getSource()Landroid/view/accessibility/AccessibilityNodeInfo;
areturn
.limit locals 1
.limit stack 1
.end method

.method public static getText(Ljava/lang/Object;)Ljava/util/List;
.signature "(Ljava/lang/Object;)Ljava/util/List<Ljava/lang/CharSequence;>;"
aload 0
checkcast android/view/accessibility/AccessibilityRecord
invokevirtual android/view/accessibility/AccessibilityRecord/getText()Ljava/util/List;
areturn
.limit locals 1
.limit stack 1
.end method

.method public static getToIndex(Ljava/lang/Object;)I
aload 0
checkcast android/view/accessibility/AccessibilityRecord
invokevirtual android/view/accessibility/AccessibilityRecord/getToIndex()I
ireturn
.limit locals 1
.limit stack 1
.end method

.method public static getWindowId(Ljava/lang/Object;)I
aload 0
checkcast android/view/accessibility/AccessibilityRecord
invokevirtual android/view/accessibility/AccessibilityRecord/getWindowId()I
ireturn
.limit locals 1
.limit stack 1
.end method

.method public static isChecked(Ljava/lang/Object;)Z
aload 0
checkcast android/view/accessibility/AccessibilityRecord
invokevirtual android/view/accessibility/AccessibilityRecord/isChecked()Z
ireturn
.limit locals 1
.limit stack 1
.end method

.method public static isEnabled(Ljava/lang/Object;)Z
aload 0
checkcast android/view/accessibility/AccessibilityRecord
invokevirtual android/view/accessibility/AccessibilityRecord/isEnabled()Z
ireturn
.limit locals 1
.limit stack 1
.end method

.method public static isFullScreen(Ljava/lang/Object;)Z
aload 0
checkcast android/view/accessibility/AccessibilityRecord
invokevirtual android/view/accessibility/AccessibilityRecord/isFullScreen()Z
ireturn
.limit locals 1
.limit stack 1
.end method

.method public static isPassword(Ljava/lang/Object;)Z
aload 0
checkcast android/view/accessibility/AccessibilityRecord
invokevirtual android/view/accessibility/AccessibilityRecord/isPassword()Z
ireturn
.limit locals 1
.limit stack 1
.end method

.method public static isScrollable(Ljava/lang/Object;)Z
aload 0
checkcast android/view/accessibility/AccessibilityRecord
invokevirtual android/view/accessibility/AccessibilityRecord/isScrollable()Z
ireturn
.limit locals 1
.limit stack 1
.end method

.method public static obtain()Ljava/lang/Object;
invokestatic android/view/accessibility/AccessibilityRecord/obtain()Landroid/view/accessibility/AccessibilityRecord;
areturn
.limit locals 0
.limit stack 1
.end method

.method public static obtain(Ljava/lang/Object;)Ljava/lang/Object;
aload 0
checkcast android/view/accessibility/AccessibilityRecord
invokestatic android/view/accessibility/AccessibilityRecord/obtain(Landroid/view/accessibility/AccessibilityRecord;)Landroid/view/accessibility/AccessibilityRecord;
areturn
.limit locals 1
.limit stack 1
.end method

.method public static recycle(Ljava/lang/Object;)V
aload 0
checkcast android/view/accessibility/AccessibilityRecord
invokevirtual android/view/accessibility/AccessibilityRecord/recycle()V
return
.limit locals 1
.limit stack 1
.end method

.method public static setAddedCount(Ljava/lang/Object;I)V
aload 0
checkcast android/view/accessibility/AccessibilityRecord
iload 1
invokevirtual android/view/accessibility/AccessibilityRecord/setAddedCount(I)V
return
.limit locals 2
.limit stack 2
.end method

.method public static setBeforeText(Ljava/lang/Object;Ljava/lang/CharSequence;)V
aload 0
checkcast android/view/accessibility/AccessibilityRecord
aload 1
invokevirtual android/view/accessibility/AccessibilityRecord/setBeforeText(Ljava/lang/CharSequence;)V
return
.limit locals 2
.limit stack 2
.end method

.method public static setChecked(Ljava/lang/Object;Z)V
aload 0
checkcast android/view/accessibility/AccessibilityRecord
iload 1
invokevirtual android/view/accessibility/AccessibilityRecord/setChecked(Z)V
return
.limit locals 2
.limit stack 2
.end method

.method public static setClassName(Ljava/lang/Object;Ljava/lang/CharSequence;)V
aload 0
checkcast android/view/accessibility/AccessibilityRecord
aload 1
invokevirtual android/view/accessibility/AccessibilityRecord/setClassName(Ljava/lang/CharSequence;)V
return
.limit locals 2
.limit stack 2
.end method

.method public static setContentDescription(Ljava/lang/Object;Ljava/lang/CharSequence;)V
aload 0
checkcast android/view/accessibility/AccessibilityRecord
aload 1
invokevirtual android/view/accessibility/AccessibilityRecord/setContentDescription(Ljava/lang/CharSequence;)V
return
.limit locals 2
.limit stack 2
.end method

.method public static setCurrentItemIndex(Ljava/lang/Object;I)V
aload 0
checkcast android/view/accessibility/AccessibilityRecord
iload 1
invokevirtual android/view/accessibility/AccessibilityRecord/setCurrentItemIndex(I)V
return
.limit locals 2
.limit stack 2
.end method

.method public static setEnabled(Ljava/lang/Object;Z)V
aload 0
checkcast android/view/accessibility/AccessibilityRecord
iload 1
invokevirtual android/view/accessibility/AccessibilityRecord/setEnabled(Z)V
return
.limit locals 2
.limit stack 2
.end method

.method public static setFromIndex(Ljava/lang/Object;I)V
aload 0
checkcast android/view/accessibility/AccessibilityRecord
iload 1
invokevirtual android/view/accessibility/AccessibilityRecord/setFromIndex(I)V
return
.limit locals 2
.limit stack 2
.end method

.method public static setFullScreen(Ljava/lang/Object;Z)V
aload 0
checkcast android/view/accessibility/AccessibilityRecord
iload 1
invokevirtual android/view/accessibility/AccessibilityRecord/setFullScreen(Z)V
return
.limit locals 2
.limit stack 2
.end method

.method public static setItemCount(Ljava/lang/Object;I)V
aload 0
checkcast android/view/accessibility/AccessibilityRecord
iload 1
invokevirtual android/view/accessibility/AccessibilityRecord/setItemCount(I)V
return
.limit locals 2
.limit stack 2
.end method

.method public static setParcelableData(Ljava/lang/Object;Landroid/os/Parcelable;)V
aload 0
checkcast android/view/accessibility/AccessibilityRecord
aload 1
invokevirtual android/view/accessibility/AccessibilityRecord/setParcelableData(Landroid/os/Parcelable;)V
return
.limit locals 2
.limit stack 2
.end method

.method public static setPassword(Ljava/lang/Object;Z)V
aload 0
checkcast android/view/accessibility/AccessibilityRecord
iload 1
invokevirtual android/view/accessibility/AccessibilityRecord/setPassword(Z)V
return
.limit locals 2
.limit stack 2
.end method

.method public static setRemovedCount(Ljava/lang/Object;I)V
aload 0
checkcast android/view/accessibility/AccessibilityRecord
iload 1
invokevirtual android/view/accessibility/AccessibilityRecord/setRemovedCount(I)V
return
.limit locals 2
.limit stack 2
.end method

.method public static setScrollX(Ljava/lang/Object;I)V
aload 0
checkcast android/view/accessibility/AccessibilityRecord
iload 1
invokevirtual android/view/accessibility/AccessibilityRecord/setScrollX(I)V
return
.limit locals 2
.limit stack 2
.end method

.method public static setScrollY(Ljava/lang/Object;I)V
aload 0
checkcast android/view/accessibility/AccessibilityRecord
iload 1
invokevirtual android/view/accessibility/AccessibilityRecord/setScrollY(I)V
return
.limit locals 2
.limit stack 2
.end method

.method public static setScrollable(Ljava/lang/Object;Z)V
aload 0
checkcast android/view/accessibility/AccessibilityRecord
iload 1
invokevirtual android/view/accessibility/AccessibilityRecord/setScrollable(Z)V
return
.limit locals 2
.limit stack 2
.end method

.method public static setSource(Ljava/lang/Object;Landroid/view/View;)V
aload 0
checkcast android/view/accessibility/AccessibilityRecord
aload 1
invokevirtual android/view/accessibility/AccessibilityRecord/setSource(Landroid/view/View;)V
return
.limit locals 2
.limit stack 2
.end method

.method public static setToIndex(Ljava/lang/Object;I)V
aload 0
checkcast android/view/accessibility/AccessibilityRecord
iload 1
invokevirtual android/view/accessibility/AccessibilityRecord/setToIndex(I)V
return
.limit locals 2
.limit stack 2
.end method
