.bytecode 50.0
.class synchronized android/support/v4/view/accessibility/AccessibilityNodeInfoCompat$AccessibilityNodeInfoIcsImpl
.super android/support/v4/view/accessibility/AccessibilityNodeInfoCompat$AccessibilityNodeInfoStubImpl
.inner class static AccessibilityNodeInfoIcsImpl inner android/support/v4/view/accessibility/AccessibilityNodeInfoCompat$AccessibilityNodeInfoIcsImpl outer android/support/v4/view/accessibility/AccessibilityNodeInfoCompat

.method <init>()V
aload 0
invokespecial android/support/v4/view/accessibility/AccessibilityNodeInfoCompat$AccessibilityNodeInfoStubImpl/<init>()V
return
.limit locals 1
.limit stack 1
.end method

.method public addAction(Ljava/lang/Object;I)V
aload 1
iload 2
invokestatic android/support/v4/view/accessibility/AccessibilityNodeInfoCompatIcs/addAction(Ljava/lang/Object;I)V
return
.limit locals 3
.limit stack 2
.end method

.method public addChild(Ljava/lang/Object;Landroid/view/View;)V
aload 1
aload 2
invokestatic android/support/v4/view/accessibility/AccessibilityNodeInfoCompatIcs/addChild(Ljava/lang/Object;Landroid/view/View;)V
return
.limit locals 3
.limit stack 2
.end method

.method public findAccessibilityNodeInfosByText(Ljava/lang/Object;Ljava/lang/String;)Ljava/util/List;
.signature "(Ljava/lang/Object;Ljava/lang/String;)Ljava/util/List<Ljava/lang/Object;>;"
aload 1
aload 2
invokestatic android/support/v4/view/accessibility/AccessibilityNodeInfoCompatIcs/findAccessibilityNodeInfosByText(Ljava/lang/Object;Ljava/lang/String;)Ljava/util/List;
areturn
.limit locals 3
.limit stack 2
.end method

.method public getActions(Ljava/lang/Object;)I
aload 1
invokestatic android/support/v4/view/accessibility/AccessibilityNodeInfoCompatIcs/getActions(Ljava/lang/Object;)I
ireturn
.limit locals 2
.limit stack 1
.end method

.method public getBoundsInParent(Ljava/lang/Object;Landroid/graphics/Rect;)V
aload 1
aload 2
invokestatic android/support/v4/view/accessibility/AccessibilityNodeInfoCompatIcs/getBoundsInParent(Ljava/lang/Object;Landroid/graphics/Rect;)V
return
.limit locals 3
.limit stack 2
.end method

.method public getBoundsInScreen(Ljava/lang/Object;Landroid/graphics/Rect;)V
aload 1
aload 2
invokestatic android/support/v4/view/accessibility/AccessibilityNodeInfoCompatIcs/getBoundsInScreen(Ljava/lang/Object;Landroid/graphics/Rect;)V
return
.limit locals 3
.limit stack 2
.end method

.method public getChild(Ljava/lang/Object;I)Ljava/lang/Object;
aload 1
iload 2
invokestatic android/support/v4/view/accessibility/AccessibilityNodeInfoCompatIcs/getChild(Ljava/lang/Object;I)Ljava/lang/Object;
areturn
.limit locals 3
.limit stack 2
.end method

.method public getChildCount(Ljava/lang/Object;)I
aload 1
invokestatic android/support/v4/view/accessibility/AccessibilityNodeInfoCompatIcs/getChildCount(Ljava/lang/Object;)I
ireturn
.limit locals 2
.limit stack 1
.end method

.method public getClassName(Ljava/lang/Object;)Ljava/lang/CharSequence;
aload 1
invokestatic android/support/v4/view/accessibility/AccessibilityNodeInfoCompatIcs/getClassName(Ljava/lang/Object;)Ljava/lang/CharSequence;
areturn
.limit locals 2
.limit stack 1
.end method

.method public getContentDescription(Ljava/lang/Object;)Ljava/lang/CharSequence;
aload 1
invokestatic android/support/v4/view/accessibility/AccessibilityNodeInfoCompatIcs/getContentDescription(Ljava/lang/Object;)Ljava/lang/CharSequence;
areturn
.limit locals 2
.limit stack 1
.end method

.method public getPackageName(Ljava/lang/Object;)Ljava/lang/CharSequence;
aload 1
invokestatic android/support/v4/view/accessibility/AccessibilityNodeInfoCompatIcs/getPackageName(Ljava/lang/Object;)Ljava/lang/CharSequence;
areturn
.limit locals 2
.limit stack 1
.end method

.method public getParent(Ljava/lang/Object;)Ljava/lang/Object;
aload 1
invokestatic android/support/v4/view/accessibility/AccessibilityNodeInfoCompatIcs/getParent(Ljava/lang/Object;)Ljava/lang/Object;
areturn
.limit locals 2
.limit stack 1
.end method

.method public getText(Ljava/lang/Object;)Ljava/lang/CharSequence;
aload 1
invokestatic android/support/v4/view/accessibility/AccessibilityNodeInfoCompatIcs/getText(Ljava/lang/Object;)Ljava/lang/CharSequence;
areturn
.limit locals 2
.limit stack 1
.end method

.method public getWindowId(Ljava/lang/Object;)I
aload 1
invokestatic android/support/v4/view/accessibility/AccessibilityNodeInfoCompatIcs/getWindowId(Ljava/lang/Object;)I
ireturn
.limit locals 2
.limit stack 1
.end method

.method public isCheckable(Ljava/lang/Object;)Z
aload 1
invokestatic android/support/v4/view/accessibility/AccessibilityNodeInfoCompatIcs/isCheckable(Ljava/lang/Object;)Z
ireturn
.limit locals 2
.limit stack 1
.end method

.method public isChecked(Ljava/lang/Object;)Z
aload 1
invokestatic android/support/v4/view/accessibility/AccessibilityNodeInfoCompatIcs/isChecked(Ljava/lang/Object;)Z
ireturn
.limit locals 2
.limit stack 1
.end method

.method public isClickable(Ljava/lang/Object;)Z
aload 1
invokestatic android/support/v4/view/accessibility/AccessibilityNodeInfoCompatIcs/isClickable(Ljava/lang/Object;)Z
ireturn
.limit locals 2
.limit stack 1
.end method

.method public isEnabled(Ljava/lang/Object;)Z
aload 1
invokestatic android/support/v4/view/accessibility/AccessibilityNodeInfoCompatIcs/isEnabled(Ljava/lang/Object;)Z
ireturn
.limit locals 2
.limit stack 1
.end method

.method public isFocusable(Ljava/lang/Object;)Z
aload 1
invokestatic android/support/v4/view/accessibility/AccessibilityNodeInfoCompatIcs/isFocusable(Ljava/lang/Object;)Z
ireturn
.limit locals 2
.limit stack 1
.end method

.method public isFocused(Ljava/lang/Object;)Z
aload 1
invokestatic android/support/v4/view/accessibility/AccessibilityNodeInfoCompatIcs/isFocused(Ljava/lang/Object;)Z
ireturn
.limit locals 2
.limit stack 1
.end method

.method public isLongClickable(Ljava/lang/Object;)Z
aload 1
invokestatic android/support/v4/view/accessibility/AccessibilityNodeInfoCompatIcs/isLongClickable(Ljava/lang/Object;)Z
ireturn
.limit locals 2
.limit stack 1
.end method

.method public isPassword(Ljava/lang/Object;)Z
aload 1
invokestatic android/support/v4/view/accessibility/AccessibilityNodeInfoCompatIcs/isPassword(Ljava/lang/Object;)Z
ireturn
.limit locals 2
.limit stack 1
.end method

.method public isScrollable(Ljava/lang/Object;)Z
aload 1
invokestatic android/support/v4/view/accessibility/AccessibilityNodeInfoCompatIcs/isScrollable(Ljava/lang/Object;)Z
ireturn
.limit locals 2
.limit stack 1
.end method

.method public isSelected(Ljava/lang/Object;)Z
aload 1
invokestatic android/support/v4/view/accessibility/AccessibilityNodeInfoCompatIcs/isSelected(Ljava/lang/Object;)Z
ireturn
.limit locals 2
.limit stack 1
.end method

.method public obtain()Ljava/lang/Object;
invokestatic android/support/v4/view/accessibility/AccessibilityNodeInfoCompatIcs/obtain()Ljava/lang/Object;
areturn
.limit locals 1
.limit stack 1
.end method

.method public obtain(Landroid/view/View;)Ljava/lang/Object;
aload 1
invokestatic android/support/v4/view/accessibility/AccessibilityNodeInfoCompatIcs/obtain(Landroid/view/View;)Ljava/lang/Object;
areturn
.limit locals 2
.limit stack 1
.end method

.method public obtain(Ljava/lang/Object;)Ljava/lang/Object;
aload 1
invokestatic android/support/v4/view/accessibility/AccessibilityNodeInfoCompatIcs/obtain(Ljava/lang/Object;)Ljava/lang/Object;
areturn
.limit locals 2
.limit stack 1
.end method

.method public performAction(Ljava/lang/Object;I)Z
aload 1
iload 2
invokestatic android/support/v4/view/accessibility/AccessibilityNodeInfoCompatIcs/performAction(Ljava/lang/Object;I)Z
ireturn
.limit locals 3
.limit stack 2
.end method

.method public recycle(Ljava/lang/Object;)V
aload 1
invokestatic android/support/v4/view/accessibility/AccessibilityNodeInfoCompatIcs/recycle(Ljava/lang/Object;)V
return
.limit locals 2
.limit stack 1
.end method

.method public setBoundsInParent(Ljava/lang/Object;Landroid/graphics/Rect;)V
aload 1
aload 2
invokestatic android/support/v4/view/accessibility/AccessibilityNodeInfoCompatIcs/setBoundsInParent(Ljava/lang/Object;Landroid/graphics/Rect;)V
return
.limit locals 3
.limit stack 2
.end method

.method public setBoundsInScreen(Ljava/lang/Object;Landroid/graphics/Rect;)V
aload 1
aload 2
invokestatic android/support/v4/view/accessibility/AccessibilityNodeInfoCompatIcs/setBoundsInScreen(Ljava/lang/Object;Landroid/graphics/Rect;)V
return
.limit locals 3
.limit stack 2
.end method

.method public setCheckable(Ljava/lang/Object;Z)V
aload 1
iload 2
invokestatic android/support/v4/view/accessibility/AccessibilityNodeInfoCompatIcs/setCheckable(Ljava/lang/Object;Z)V
return
.limit locals 3
.limit stack 2
.end method

.method public setChecked(Ljava/lang/Object;Z)V
aload 1
iload 2
invokestatic android/support/v4/view/accessibility/AccessibilityNodeInfoCompatIcs/setChecked(Ljava/lang/Object;Z)V
return
.limit locals 3
.limit stack 2
.end method

.method public setClassName(Ljava/lang/Object;Ljava/lang/CharSequence;)V
aload 1
aload 2
invokestatic android/support/v4/view/accessibility/AccessibilityNodeInfoCompatIcs/setClassName(Ljava/lang/Object;Ljava/lang/CharSequence;)V
return
.limit locals 3
.limit stack 2
.end method

.method public setClickable(Ljava/lang/Object;Z)V
aload 1
iload 2
invokestatic android/support/v4/view/accessibility/AccessibilityNodeInfoCompatIcs/setClickable(Ljava/lang/Object;Z)V
return
.limit locals 3
.limit stack 2
.end method

.method public setContentDescription(Ljava/lang/Object;Ljava/lang/CharSequence;)V
aload 1
aload 2
invokestatic android/support/v4/view/accessibility/AccessibilityNodeInfoCompatIcs/setContentDescription(Ljava/lang/Object;Ljava/lang/CharSequence;)V
return
.limit locals 3
.limit stack 2
.end method

.method public setEnabled(Ljava/lang/Object;Z)V
aload 1
iload 2
invokestatic android/support/v4/view/accessibility/AccessibilityNodeInfoCompatIcs/setEnabled(Ljava/lang/Object;Z)V
return
.limit locals 3
.limit stack 2
.end method

.method public setFocusable(Ljava/lang/Object;Z)V
aload 1
iload 2
invokestatic android/support/v4/view/accessibility/AccessibilityNodeInfoCompatIcs/setFocusable(Ljava/lang/Object;Z)V
return
.limit locals 3
.limit stack 2
.end method

.method public setFocused(Ljava/lang/Object;Z)V
aload 1
iload 2
invokestatic android/support/v4/view/accessibility/AccessibilityNodeInfoCompatIcs/setFocused(Ljava/lang/Object;Z)V
return
.limit locals 3
.limit stack 2
.end method

.method public setLongClickable(Ljava/lang/Object;Z)V
aload 1
iload 2
invokestatic android/support/v4/view/accessibility/AccessibilityNodeInfoCompatIcs/setLongClickable(Ljava/lang/Object;Z)V
return
.limit locals 3
.limit stack 2
.end method

.method public setPackageName(Ljava/lang/Object;Ljava/lang/CharSequence;)V
aload 1
aload 2
invokestatic android/support/v4/view/accessibility/AccessibilityNodeInfoCompatIcs/setPackageName(Ljava/lang/Object;Ljava/lang/CharSequence;)V
return
.limit locals 3
.limit stack 2
.end method

.method public setParent(Ljava/lang/Object;Landroid/view/View;)V
aload 1
aload 2
invokestatic android/support/v4/view/accessibility/AccessibilityNodeInfoCompatIcs/setParent(Ljava/lang/Object;Landroid/view/View;)V
return
.limit locals 3
.limit stack 2
.end method

.method public setPassword(Ljava/lang/Object;Z)V
aload 1
iload 2
invokestatic android/support/v4/view/accessibility/AccessibilityNodeInfoCompatIcs/setPassword(Ljava/lang/Object;Z)V
return
.limit locals 3
.limit stack 2
.end method

.method public setScrollable(Ljava/lang/Object;Z)V
aload 1
iload 2
invokestatic android/support/v4/view/accessibility/AccessibilityNodeInfoCompatIcs/setScrollable(Ljava/lang/Object;Z)V
return
.limit locals 3
.limit stack 2
.end method

.method public setSelected(Ljava/lang/Object;Z)V
aload 1
iload 2
invokestatic android/support/v4/view/accessibility/AccessibilityNodeInfoCompatIcs/setSelected(Ljava/lang/Object;Z)V
return
.limit locals 3
.limit stack 2
.end method

.method public setSource(Ljava/lang/Object;Landroid/view/View;)V
aload 1
aload 2
invokestatic android/support/v4/view/accessibility/AccessibilityNodeInfoCompatIcs/setSource(Ljava/lang/Object;Landroid/view/View;)V
return
.limit locals 3
.limit stack 2
.end method

.method public setText(Ljava/lang/Object;Ljava/lang/CharSequence;)V
aload 1
aload 2
invokestatic android/support/v4/view/accessibility/AccessibilityNodeInfoCompatIcs/setText(Ljava/lang/Object;Ljava/lang/CharSequence;)V
return
.limit locals 3
.limit stack 2
.end method
