.bytecode 50.0
.class synchronized android/support/v4/view/accessibility/AccessibilityNodeInfoCompat$AccessibilityNodeInfoJellybeanImpl
.super android/support/v4/view/accessibility/AccessibilityNodeInfoCompat$AccessibilityNodeInfoIcsImpl
.inner class static AccessibilityNodeInfoJellybeanImpl inner android/support/v4/view/accessibility/AccessibilityNodeInfoCompat$AccessibilityNodeInfoJellybeanImpl outer android/support/v4/view/accessibility/AccessibilityNodeInfoCompat

.method <init>()V
aload 0
invokespecial android/support/v4/view/accessibility/AccessibilityNodeInfoCompat$AccessibilityNodeInfoIcsImpl/<init>()V
return
.limit locals 1
.limit stack 1
.end method

.method public addChild(Ljava/lang/Object;Landroid/view/View;I)V
aload 1
aload 2
iload 3
invokestatic android/support/v4/view/accessibility/AccessibilityNodeInfoCompatJellyBean/addChild(Ljava/lang/Object;Landroid/view/View;I)V
return
.limit locals 4
.limit stack 3
.end method

.method public findFocus(Ljava/lang/Object;I)Ljava/lang/Object;
aload 1
iload 2
invokestatic android/support/v4/view/accessibility/AccessibilityNodeInfoCompatJellyBean/findFocus(Ljava/lang/Object;I)Ljava/lang/Object;
areturn
.limit locals 3
.limit stack 2
.end method

.method public focusSearch(Ljava/lang/Object;I)Ljava/lang/Object;
aload 1
iload 2
invokestatic android/support/v4/view/accessibility/AccessibilityNodeInfoCompatJellyBean/focusSearch(Ljava/lang/Object;I)Ljava/lang/Object;
areturn
.limit locals 3
.limit stack 2
.end method

.method public getMovementGranularities(Ljava/lang/Object;)I
aload 1
invokestatic android/support/v4/view/accessibility/AccessibilityNodeInfoCompatJellyBean/getMovementGranularities(Ljava/lang/Object;)I
ireturn
.limit locals 2
.limit stack 1
.end method

.method public isAccessibilityFocused(Ljava/lang/Object;)Z
aload 1
invokestatic android/support/v4/view/accessibility/AccessibilityNodeInfoCompatJellyBean/isAccessibilityFocused(Ljava/lang/Object;)Z
ireturn
.limit locals 2
.limit stack 1
.end method

.method public isVisibleToUser(Ljava/lang/Object;)Z
aload 1
invokestatic android/support/v4/view/accessibility/AccessibilityNodeInfoCompatJellyBean/isVisibleToUser(Ljava/lang/Object;)Z
ireturn
.limit locals 2
.limit stack 1
.end method

.method public obtain(Landroid/view/View;I)Ljava/lang/Object;
aload 1
iload 2
invokestatic android/support/v4/view/accessibility/AccessibilityNodeInfoCompatJellyBean/obtain(Landroid/view/View;I)Ljava/lang/Object;
areturn
.limit locals 3
.limit stack 2
.end method

.method public performAction(Ljava/lang/Object;ILandroid/os/Bundle;)Z
aload 1
iload 2
aload 3
invokestatic android/support/v4/view/accessibility/AccessibilityNodeInfoCompatJellyBean/performAction(Ljava/lang/Object;ILandroid/os/Bundle;)Z
ireturn
.limit locals 4
.limit stack 3
.end method

.method public setAccessibilityFocused(Ljava/lang/Object;Z)V
aload 1
iload 2
invokestatic android/support/v4/view/accessibility/AccessibilityNodeInfoCompatJellyBean/setAccesibilityFocused(Ljava/lang/Object;Z)V
return
.limit locals 3
.limit stack 2
.end method

.method public setMovementGranularities(Ljava/lang/Object;I)V
aload 1
iload 2
invokestatic android/support/v4/view/accessibility/AccessibilityNodeInfoCompatJellyBean/setMovementGranularities(Ljava/lang/Object;I)V
return
.limit locals 3
.limit stack 2
.end method

.method public setParent(Ljava/lang/Object;Landroid/view/View;I)V
aload 1
aload 2
iload 3
invokestatic android/support/v4/view/accessibility/AccessibilityNodeInfoCompatJellyBean/setParent(Ljava/lang/Object;Landroid/view/View;I)V
return
.limit locals 4
.limit stack 3
.end method

.method public setSource(Ljava/lang/Object;Landroid/view/View;I)V
aload 1
aload 2
iload 3
invokestatic android/support/v4/view/accessibility/AccessibilityNodeInfoCompatJellyBean/setSource(Ljava/lang/Object;Landroid/view/View;I)V
return
.limit locals 4
.limit stack 3
.end method

.method public setVisibleToUser(Ljava/lang/Object;Z)V
aload 1
iload 2
invokestatic android/support/v4/view/accessibility/AccessibilityNodeInfoCompatJellyBean/setVisibleToUser(Ljava/lang/Object;Z)V
return
.limit locals 3
.limit stack 2
.end method
