.bytecode 50.0
.class public synchronized android/support/v4/view/accessibility/AccessibilityRecordCompat
.super java/lang/Object
.inner class static AccessibilityRecordIcsImpl inner android/support/v4/view/accessibility/AccessibilityRecordCompat$AccessibilityRecordIcsImpl outer android/support/v4/view/accessibility/AccessibilityRecordCompat
.inner class static AccessibilityRecordIcsMr1Impl inner android/support/v4/view/accessibility/AccessibilityRecordCompat$AccessibilityRecordIcsMr1Impl outer android/support/v4/view/accessibility/AccessibilityRecordCompat
.inner class static abstract interface AccessibilityRecordImpl inner android/support/v4/view/accessibility/AccessibilityRecordCompat$AccessibilityRecordImpl outer android/support/v4/view/accessibility/AccessibilityRecordCompat
.inner class static AccessibilityRecordJellyBeanImpl inner android/support/v4/view/accessibility/AccessibilityRecordCompat$AccessibilityRecordJellyBeanImpl outer android/support/v4/view/accessibility/AccessibilityRecordCompat
.inner class static AccessibilityRecordStubImpl inner android/support/v4/view/accessibility/AccessibilityRecordCompat$AccessibilityRecordStubImpl outer android/support/v4/view/accessibility/AccessibilityRecordCompat

.field private static final 'IMPL' Landroid/support/v4/view/accessibility/AccessibilityRecordCompat$AccessibilityRecordImpl;

.field private final 'mRecord' Ljava/lang/Object;

.method static <clinit>()V
getstatic android/os/Build$VERSION/SDK_INT I
bipush 16
if_icmplt L0
new android/support/v4/view/accessibility/AccessibilityRecordCompat$AccessibilityRecordJellyBeanImpl
dup
invokespecial android/support/v4/view/accessibility/AccessibilityRecordCompat$AccessibilityRecordJellyBeanImpl/<init>()V
putstatic android/support/v4/view/accessibility/AccessibilityRecordCompat/IMPL Landroid/support/v4/view/accessibility/AccessibilityRecordCompat$AccessibilityRecordImpl;
return
L0:
getstatic android/os/Build$VERSION/SDK_INT I
bipush 15
if_icmplt L1
new android/support/v4/view/accessibility/AccessibilityRecordCompat$AccessibilityRecordIcsMr1Impl
dup
invokespecial android/support/v4/view/accessibility/AccessibilityRecordCompat$AccessibilityRecordIcsMr1Impl/<init>()V
putstatic android/support/v4/view/accessibility/AccessibilityRecordCompat/IMPL Landroid/support/v4/view/accessibility/AccessibilityRecordCompat$AccessibilityRecordImpl;
return
L1:
getstatic android/os/Build$VERSION/SDK_INT I
bipush 14
if_icmplt L2
new android/support/v4/view/accessibility/AccessibilityRecordCompat$AccessibilityRecordIcsImpl
dup
invokespecial android/support/v4/view/accessibility/AccessibilityRecordCompat$AccessibilityRecordIcsImpl/<init>()V
putstatic android/support/v4/view/accessibility/AccessibilityRecordCompat/IMPL Landroid/support/v4/view/accessibility/AccessibilityRecordCompat$AccessibilityRecordImpl;
return
L2:
new android/support/v4/view/accessibility/AccessibilityRecordCompat$AccessibilityRecordStubImpl
dup
invokespecial android/support/v4/view/accessibility/AccessibilityRecordCompat$AccessibilityRecordStubImpl/<init>()V
putstatic android/support/v4/view/accessibility/AccessibilityRecordCompat/IMPL Landroid/support/v4/view/accessibility/AccessibilityRecordCompat$AccessibilityRecordImpl;
return
.limit locals 0
.limit stack 2
.end method

.method public <init>(Ljava/lang/Object;)V
aload 0
invokespecial java/lang/Object/<init>()V
aload 0
aload 1
putfield android/support/v4/view/accessibility/AccessibilityRecordCompat/mRecord Ljava/lang/Object;
return
.limit locals 2
.limit stack 2
.end method

.method public static obtain()Landroid/support/v4/view/accessibility/AccessibilityRecordCompat;
new android/support/v4/view/accessibility/AccessibilityRecordCompat
dup
getstatic android/support/v4/view/accessibility/AccessibilityRecordCompat/IMPL Landroid/support/v4/view/accessibility/AccessibilityRecordCompat$AccessibilityRecordImpl;
invokeinterface android/support/v4/view/accessibility/AccessibilityRecordCompat$AccessibilityRecordImpl/obtain()Ljava/lang/Object; 0
invokespecial android/support/v4/view/accessibility/AccessibilityRecordCompat/<init>(Ljava/lang/Object;)V
areturn
.limit locals 0
.limit stack 3
.end method

.method public static obtain(Landroid/support/v4/view/accessibility/AccessibilityRecordCompat;)Landroid/support/v4/view/accessibility/AccessibilityRecordCompat;
new android/support/v4/view/accessibility/AccessibilityRecordCompat
dup
getstatic android/support/v4/view/accessibility/AccessibilityRecordCompat/IMPL Landroid/support/v4/view/accessibility/AccessibilityRecordCompat$AccessibilityRecordImpl;
aload 0
getfield android/support/v4/view/accessibility/AccessibilityRecordCompat/mRecord Ljava/lang/Object;
invokeinterface android/support/v4/view/accessibility/AccessibilityRecordCompat$AccessibilityRecordImpl/obtain(Ljava/lang/Object;)Ljava/lang/Object; 1
invokespecial android/support/v4/view/accessibility/AccessibilityRecordCompat/<init>(Ljava/lang/Object;)V
areturn
.limit locals 1
.limit stack 4
.end method

.method public equals(Ljava/lang/Object;)Z
aload 0
aload 1
if_acmpne L0
L1:
iconst_1
ireturn
L0:
aload 1
ifnonnull L2
iconst_0
ireturn
L2:
aload 0
invokevirtual java/lang/Object/getClass()Ljava/lang/Class;
aload 1
invokevirtual java/lang/Object/getClass()Ljava/lang/Class;
if_acmpeq L3
iconst_0
ireturn
L3:
aload 1
checkcast android/support/v4/view/accessibility/AccessibilityRecordCompat
astore 1
aload 0
getfield android/support/v4/view/accessibility/AccessibilityRecordCompat/mRecord Ljava/lang/Object;
ifnonnull L4
aload 1
getfield android/support/v4/view/accessibility/AccessibilityRecordCompat/mRecord Ljava/lang/Object;
ifnull L1
iconst_0
ireturn
L4:
aload 0
getfield android/support/v4/view/accessibility/AccessibilityRecordCompat/mRecord Ljava/lang/Object;
aload 1
getfield android/support/v4/view/accessibility/AccessibilityRecordCompat/mRecord Ljava/lang/Object;
invokevirtual java/lang/Object/equals(Ljava/lang/Object;)Z
ifne L1
iconst_0
ireturn
.limit locals 2
.limit stack 2
.end method

.method public getAddedCount()I
getstatic android/support/v4/view/accessibility/AccessibilityRecordCompat/IMPL Landroid/support/v4/view/accessibility/AccessibilityRecordCompat$AccessibilityRecordImpl;
aload 0
getfield android/support/v4/view/accessibility/AccessibilityRecordCompat/mRecord Ljava/lang/Object;
invokeinterface android/support/v4/view/accessibility/AccessibilityRecordCompat$AccessibilityRecordImpl/getAddedCount(Ljava/lang/Object;)I 1
ireturn
.limit locals 1
.limit stack 2
.end method

.method public getBeforeText()Ljava/lang/CharSequence;
getstatic android/support/v4/view/accessibility/AccessibilityRecordCompat/IMPL Landroid/support/v4/view/accessibility/AccessibilityRecordCompat$AccessibilityRecordImpl;
aload 0
getfield android/support/v4/view/accessibility/AccessibilityRecordCompat/mRecord Ljava/lang/Object;
invokeinterface android/support/v4/view/accessibility/AccessibilityRecordCompat$AccessibilityRecordImpl/getBeforeText(Ljava/lang/Object;)Ljava/lang/CharSequence; 1
areturn
.limit locals 1
.limit stack 2
.end method

.method public getClassName()Ljava/lang/CharSequence;
getstatic android/support/v4/view/accessibility/AccessibilityRecordCompat/IMPL Landroid/support/v4/view/accessibility/AccessibilityRecordCompat$AccessibilityRecordImpl;
aload 0
getfield android/support/v4/view/accessibility/AccessibilityRecordCompat/mRecord Ljava/lang/Object;
invokeinterface android/support/v4/view/accessibility/AccessibilityRecordCompat$AccessibilityRecordImpl/getClassName(Ljava/lang/Object;)Ljava/lang/CharSequence; 1
areturn
.limit locals 1
.limit stack 2
.end method

.method public getContentDescription()Ljava/lang/CharSequence;
getstatic android/support/v4/view/accessibility/AccessibilityRecordCompat/IMPL Landroid/support/v4/view/accessibility/AccessibilityRecordCompat$AccessibilityRecordImpl;
aload 0
getfield android/support/v4/view/accessibility/AccessibilityRecordCompat/mRecord Ljava/lang/Object;
invokeinterface android/support/v4/view/accessibility/AccessibilityRecordCompat$AccessibilityRecordImpl/getContentDescription(Ljava/lang/Object;)Ljava/lang/CharSequence; 1
areturn
.limit locals 1
.limit stack 2
.end method

.method public getCurrentItemIndex()I
getstatic android/support/v4/view/accessibility/AccessibilityRecordCompat/IMPL Landroid/support/v4/view/accessibility/AccessibilityRecordCompat$AccessibilityRecordImpl;
aload 0
getfield android/support/v4/view/accessibility/AccessibilityRecordCompat/mRecord Ljava/lang/Object;
invokeinterface android/support/v4/view/accessibility/AccessibilityRecordCompat$AccessibilityRecordImpl/getCurrentItemIndex(Ljava/lang/Object;)I 1
ireturn
.limit locals 1
.limit stack 2
.end method

.method public getFromIndex()I
getstatic android/support/v4/view/accessibility/AccessibilityRecordCompat/IMPL Landroid/support/v4/view/accessibility/AccessibilityRecordCompat$AccessibilityRecordImpl;
aload 0
getfield android/support/v4/view/accessibility/AccessibilityRecordCompat/mRecord Ljava/lang/Object;
invokeinterface android/support/v4/view/accessibility/AccessibilityRecordCompat$AccessibilityRecordImpl/getFromIndex(Ljava/lang/Object;)I 1
ireturn
.limit locals 1
.limit stack 2
.end method

.method public getImpl()Ljava/lang/Object;
aload 0
getfield android/support/v4/view/accessibility/AccessibilityRecordCompat/mRecord Ljava/lang/Object;
areturn
.limit locals 1
.limit stack 1
.end method

.method public getItemCount()I
getstatic android/support/v4/view/accessibility/AccessibilityRecordCompat/IMPL Landroid/support/v4/view/accessibility/AccessibilityRecordCompat$AccessibilityRecordImpl;
aload 0
getfield android/support/v4/view/accessibility/AccessibilityRecordCompat/mRecord Ljava/lang/Object;
invokeinterface android/support/v4/view/accessibility/AccessibilityRecordCompat$AccessibilityRecordImpl/getItemCount(Ljava/lang/Object;)I 1
ireturn
.limit locals 1
.limit stack 2
.end method

.method public getMaxScrollX()I
getstatic android/support/v4/view/accessibility/AccessibilityRecordCompat/IMPL Landroid/support/v4/view/accessibility/AccessibilityRecordCompat$AccessibilityRecordImpl;
aload 0
getfield android/support/v4/view/accessibility/AccessibilityRecordCompat/mRecord Ljava/lang/Object;
invokeinterface android/support/v4/view/accessibility/AccessibilityRecordCompat$AccessibilityRecordImpl/getMaxScrollX(Ljava/lang/Object;)I 1
ireturn
.limit locals 1
.limit stack 2
.end method

.method public getMaxScrollY()I
getstatic android/support/v4/view/accessibility/AccessibilityRecordCompat/IMPL Landroid/support/v4/view/accessibility/AccessibilityRecordCompat$AccessibilityRecordImpl;
aload 0
getfield android/support/v4/view/accessibility/AccessibilityRecordCompat/mRecord Ljava/lang/Object;
invokeinterface android/support/v4/view/accessibility/AccessibilityRecordCompat$AccessibilityRecordImpl/getMaxScrollY(Ljava/lang/Object;)I 1
ireturn
.limit locals 1
.limit stack 2
.end method

.method public getParcelableData()Landroid/os/Parcelable;
getstatic android/support/v4/view/accessibility/AccessibilityRecordCompat/IMPL Landroid/support/v4/view/accessibility/AccessibilityRecordCompat$AccessibilityRecordImpl;
aload 0
getfield android/support/v4/view/accessibility/AccessibilityRecordCompat/mRecord Ljava/lang/Object;
invokeinterface android/support/v4/view/accessibility/AccessibilityRecordCompat$AccessibilityRecordImpl/getParcelableData(Ljava/lang/Object;)Landroid/os/Parcelable; 1
areturn
.limit locals 1
.limit stack 2
.end method

.method public getRemovedCount()I
getstatic android/support/v4/view/accessibility/AccessibilityRecordCompat/IMPL Landroid/support/v4/view/accessibility/AccessibilityRecordCompat$AccessibilityRecordImpl;
aload 0
getfield android/support/v4/view/accessibility/AccessibilityRecordCompat/mRecord Ljava/lang/Object;
invokeinterface android/support/v4/view/accessibility/AccessibilityRecordCompat$AccessibilityRecordImpl/getRemovedCount(Ljava/lang/Object;)I 1
ireturn
.limit locals 1
.limit stack 2
.end method

.method public getScrollX()I
getstatic android/support/v4/view/accessibility/AccessibilityRecordCompat/IMPL Landroid/support/v4/view/accessibility/AccessibilityRecordCompat$AccessibilityRecordImpl;
aload 0
getfield android/support/v4/view/accessibility/AccessibilityRecordCompat/mRecord Ljava/lang/Object;
invokeinterface android/support/v4/view/accessibility/AccessibilityRecordCompat$AccessibilityRecordImpl/getScrollX(Ljava/lang/Object;)I 1
ireturn
.limit locals 1
.limit stack 2
.end method

.method public getScrollY()I
getstatic android/support/v4/view/accessibility/AccessibilityRecordCompat/IMPL Landroid/support/v4/view/accessibility/AccessibilityRecordCompat$AccessibilityRecordImpl;
aload 0
getfield android/support/v4/view/accessibility/AccessibilityRecordCompat/mRecord Ljava/lang/Object;
invokeinterface android/support/v4/view/accessibility/AccessibilityRecordCompat$AccessibilityRecordImpl/getScrollY(Ljava/lang/Object;)I 1
ireturn
.limit locals 1
.limit stack 2
.end method

.method public getSource()Landroid/support/v4/view/accessibility/AccessibilityNodeInfoCompat;
getstatic android/support/v4/view/accessibility/AccessibilityRecordCompat/IMPL Landroid/support/v4/view/accessibility/AccessibilityRecordCompat$AccessibilityRecordImpl;
aload 0
getfield android/support/v4/view/accessibility/AccessibilityRecordCompat/mRecord Ljava/lang/Object;
invokeinterface android/support/v4/view/accessibility/AccessibilityRecordCompat$AccessibilityRecordImpl/getSource(Ljava/lang/Object;)Landroid/support/v4/view/accessibility/AccessibilityNodeInfoCompat; 1
areturn
.limit locals 1
.limit stack 2
.end method

.method public getText()Ljava/util/List;
.signature "()Ljava/util/List<Ljava/lang/CharSequence;>;"
getstatic android/support/v4/view/accessibility/AccessibilityRecordCompat/IMPL Landroid/support/v4/view/accessibility/AccessibilityRecordCompat$AccessibilityRecordImpl;
aload 0
getfield android/support/v4/view/accessibility/AccessibilityRecordCompat/mRecord Ljava/lang/Object;
invokeinterface android/support/v4/view/accessibility/AccessibilityRecordCompat$AccessibilityRecordImpl/getText(Ljava/lang/Object;)Ljava/util/List; 1
areturn
.limit locals 1
.limit stack 2
.end method

.method public getToIndex()I
getstatic android/support/v4/view/accessibility/AccessibilityRecordCompat/IMPL Landroid/support/v4/view/accessibility/AccessibilityRecordCompat$AccessibilityRecordImpl;
aload 0
getfield android/support/v4/view/accessibility/AccessibilityRecordCompat/mRecord Ljava/lang/Object;
invokeinterface android/support/v4/view/accessibility/AccessibilityRecordCompat$AccessibilityRecordImpl/getToIndex(Ljava/lang/Object;)I 1
ireturn
.limit locals 1
.limit stack 2
.end method

.method public getWindowId()I
getstatic android/support/v4/view/accessibility/AccessibilityRecordCompat/IMPL Landroid/support/v4/view/accessibility/AccessibilityRecordCompat$AccessibilityRecordImpl;
aload 0
getfield android/support/v4/view/accessibility/AccessibilityRecordCompat/mRecord Ljava/lang/Object;
invokeinterface android/support/v4/view/accessibility/AccessibilityRecordCompat$AccessibilityRecordImpl/getWindowId(Ljava/lang/Object;)I 1
ireturn
.limit locals 1
.limit stack 2
.end method

.method public hashCode()I
aload 0
getfield android/support/v4/view/accessibility/AccessibilityRecordCompat/mRecord Ljava/lang/Object;
ifnonnull L0
iconst_0
ireturn
L0:
aload 0
getfield android/support/v4/view/accessibility/AccessibilityRecordCompat/mRecord Ljava/lang/Object;
invokevirtual java/lang/Object/hashCode()I
ireturn
.limit locals 1
.limit stack 1
.end method

.method public isChecked()Z
getstatic android/support/v4/view/accessibility/AccessibilityRecordCompat/IMPL Landroid/support/v4/view/accessibility/AccessibilityRecordCompat$AccessibilityRecordImpl;
aload 0
getfield android/support/v4/view/accessibility/AccessibilityRecordCompat/mRecord Ljava/lang/Object;
invokeinterface android/support/v4/view/accessibility/AccessibilityRecordCompat$AccessibilityRecordImpl/isChecked(Ljava/lang/Object;)Z 1
ireturn
.limit locals 1
.limit stack 2
.end method

.method public isEnabled()Z
getstatic android/support/v4/view/accessibility/AccessibilityRecordCompat/IMPL Landroid/support/v4/view/accessibility/AccessibilityRecordCompat$AccessibilityRecordImpl;
aload 0
getfield android/support/v4/view/accessibility/AccessibilityRecordCompat/mRecord Ljava/lang/Object;
invokeinterface android/support/v4/view/accessibility/AccessibilityRecordCompat$AccessibilityRecordImpl/isEnabled(Ljava/lang/Object;)Z 1
ireturn
.limit locals 1
.limit stack 2
.end method

.method public isFullScreen()Z
getstatic android/support/v4/view/accessibility/AccessibilityRecordCompat/IMPL Landroid/support/v4/view/accessibility/AccessibilityRecordCompat$AccessibilityRecordImpl;
aload 0
getfield android/support/v4/view/accessibility/AccessibilityRecordCompat/mRecord Ljava/lang/Object;
invokeinterface android/support/v4/view/accessibility/AccessibilityRecordCompat$AccessibilityRecordImpl/isFullScreen(Ljava/lang/Object;)Z 1
ireturn
.limit locals 1
.limit stack 2
.end method

.method public isPassword()Z
getstatic android/support/v4/view/accessibility/AccessibilityRecordCompat/IMPL Landroid/support/v4/view/accessibility/AccessibilityRecordCompat$AccessibilityRecordImpl;
aload 0
getfield android/support/v4/view/accessibility/AccessibilityRecordCompat/mRecord Ljava/lang/Object;
invokeinterface android/support/v4/view/accessibility/AccessibilityRecordCompat$AccessibilityRecordImpl/isPassword(Ljava/lang/Object;)Z 1
ireturn
.limit locals 1
.limit stack 2
.end method

.method public isScrollable()Z
getstatic android/support/v4/view/accessibility/AccessibilityRecordCompat/IMPL Landroid/support/v4/view/accessibility/AccessibilityRecordCompat$AccessibilityRecordImpl;
aload 0
getfield android/support/v4/view/accessibility/AccessibilityRecordCompat/mRecord Ljava/lang/Object;
invokeinterface android/support/v4/view/accessibility/AccessibilityRecordCompat$AccessibilityRecordImpl/isScrollable(Ljava/lang/Object;)Z 1
ireturn
.limit locals 1
.limit stack 2
.end method

.method public recycle()V
getstatic android/support/v4/view/accessibility/AccessibilityRecordCompat/IMPL Landroid/support/v4/view/accessibility/AccessibilityRecordCompat$AccessibilityRecordImpl;
aload 0
getfield android/support/v4/view/accessibility/AccessibilityRecordCompat/mRecord Ljava/lang/Object;
invokeinterface android/support/v4/view/accessibility/AccessibilityRecordCompat$AccessibilityRecordImpl/recycle(Ljava/lang/Object;)V 1
return
.limit locals 1
.limit stack 2
.end method

.method public setAddedCount(I)V
getstatic android/support/v4/view/accessibility/AccessibilityRecordCompat/IMPL Landroid/support/v4/view/accessibility/AccessibilityRecordCompat$AccessibilityRecordImpl;
aload 0
getfield android/support/v4/view/accessibility/AccessibilityRecordCompat/mRecord Ljava/lang/Object;
iload 1
invokeinterface android/support/v4/view/accessibility/AccessibilityRecordCompat$AccessibilityRecordImpl/setAddedCount(Ljava/lang/Object;I)V 2
return
.limit locals 2
.limit stack 3
.end method

.method public setBeforeText(Ljava/lang/CharSequence;)V
getstatic android/support/v4/view/accessibility/AccessibilityRecordCompat/IMPL Landroid/support/v4/view/accessibility/AccessibilityRecordCompat$AccessibilityRecordImpl;
aload 0
getfield android/support/v4/view/accessibility/AccessibilityRecordCompat/mRecord Ljava/lang/Object;
aload 1
invokeinterface android/support/v4/view/accessibility/AccessibilityRecordCompat$AccessibilityRecordImpl/setBeforeText(Ljava/lang/Object;Ljava/lang/CharSequence;)V 2
return
.limit locals 2
.limit stack 3
.end method

.method public setChecked(Z)V
getstatic android/support/v4/view/accessibility/AccessibilityRecordCompat/IMPL Landroid/support/v4/view/accessibility/AccessibilityRecordCompat$AccessibilityRecordImpl;
aload 0
getfield android/support/v4/view/accessibility/AccessibilityRecordCompat/mRecord Ljava/lang/Object;
iload 1
invokeinterface android/support/v4/view/accessibility/AccessibilityRecordCompat$AccessibilityRecordImpl/setChecked(Ljava/lang/Object;Z)V 2
return
.limit locals 2
.limit stack 3
.end method

.method public setClassName(Ljava/lang/CharSequence;)V
getstatic android/support/v4/view/accessibility/AccessibilityRecordCompat/IMPL Landroid/support/v4/view/accessibility/AccessibilityRecordCompat$AccessibilityRecordImpl;
aload 0
getfield android/support/v4/view/accessibility/AccessibilityRecordCompat/mRecord Ljava/lang/Object;
aload 1
invokeinterface android/support/v4/view/accessibility/AccessibilityRecordCompat$AccessibilityRecordImpl/setClassName(Ljava/lang/Object;Ljava/lang/CharSequence;)V 2
return
.limit locals 2
.limit stack 3
.end method

.method public setContentDescription(Ljava/lang/CharSequence;)V
getstatic android/support/v4/view/accessibility/AccessibilityRecordCompat/IMPL Landroid/support/v4/view/accessibility/AccessibilityRecordCompat$AccessibilityRecordImpl;
aload 0
getfield android/support/v4/view/accessibility/AccessibilityRecordCompat/mRecord Ljava/lang/Object;
aload 1
invokeinterface android/support/v4/view/accessibility/AccessibilityRecordCompat$AccessibilityRecordImpl/setContentDescription(Ljava/lang/Object;Ljava/lang/CharSequence;)V 2
return
.limit locals 2
.limit stack 3
.end method

.method public setCurrentItemIndex(I)V
getstatic android/support/v4/view/accessibility/AccessibilityRecordCompat/IMPL Landroid/support/v4/view/accessibility/AccessibilityRecordCompat$AccessibilityRecordImpl;
aload 0
getfield android/support/v4/view/accessibility/AccessibilityRecordCompat/mRecord Ljava/lang/Object;
iload 1
invokeinterface android/support/v4/view/accessibility/AccessibilityRecordCompat$AccessibilityRecordImpl/setCurrentItemIndex(Ljava/lang/Object;I)V 2
return
.limit locals 2
.limit stack 3
.end method

.method public setEnabled(Z)V
getstatic android/support/v4/view/accessibility/AccessibilityRecordCompat/IMPL Landroid/support/v4/view/accessibility/AccessibilityRecordCompat$AccessibilityRecordImpl;
aload 0
getfield android/support/v4/view/accessibility/AccessibilityRecordCompat/mRecord Ljava/lang/Object;
iload 1
invokeinterface android/support/v4/view/accessibility/AccessibilityRecordCompat$AccessibilityRecordImpl/setEnabled(Ljava/lang/Object;Z)V 2
return
.limit locals 2
.limit stack 3
.end method

.method public setFromIndex(I)V
getstatic android/support/v4/view/accessibility/AccessibilityRecordCompat/IMPL Landroid/support/v4/view/accessibility/AccessibilityRecordCompat$AccessibilityRecordImpl;
aload 0
getfield android/support/v4/view/accessibility/AccessibilityRecordCompat/mRecord Ljava/lang/Object;
iload 1
invokeinterface android/support/v4/view/accessibility/AccessibilityRecordCompat$AccessibilityRecordImpl/setFromIndex(Ljava/lang/Object;I)V 2
return
.limit locals 2
.limit stack 3
.end method

.method public setFullScreen(Z)V
getstatic android/support/v4/view/accessibility/AccessibilityRecordCompat/IMPL Landroid/support/v4/view/accessibility/AccessibilityRecordCompat$AccessibilityRecordImpl;
aload 0
getfield android/support/v4/view/accessibility/AccessibilityRecordCompat/mRecord Ljava/lang/Object;
iload 1
invokeinterface android/support/v4/view/accessibility/AccessibilityRecordCompat$AccessibilityRecordImpl/setFullScreen(Ljava/lang/Object;Z)V 2
return
.limit locals 2
.limit stack 3
.end method

.method public setItemCount(I)V
getstatic android/support/v4/view/accessibility/AccessibilityRecordCompat/IMPL Landroid/support/v4/view/accessibility/AccessibilityRecordCompat$AccessibilityRecordImpl;
aload 0
getfield android/support/v4/view/accessibility/AccessibilityRecordCompat/mRecord Ljava/lang/Object;
iload 1
invokeinterface android/support/v4/view/accessibility/AccessibilityRecordCompat$AccessibilityRecordImpl/setItemCount(Ljava/lang/Object;I)V 2
return
.limit locals 2
.limit stack 3
.end method

.method public setMaxScrollX(I)V
getstatic android/support/v4/view/accessibility/AccessibilityRecordCompat/IMPL Landroid/support/v4/view/accessibility/AccessibilityRecordCompat$AccessibilityRecordImpl;
aload 0
getfield android/support/v4/view/accessibility/AccessibilityRecordCompat/mRecord Ljava/lang/Object;
iload 1
invokeinterface android/support/v4/view/accessibility/AccessibilityRecordCompat$AccessibilityRecordImpl/setMaxScrollX(Ljava/lang/Object;I)V 2
return
.limit locals 2
.limit stack 3
.end method

.method public setMaxScrollY(I)V
getstatic android/support/v4/view/accessibility/AccessibilityRecordCompat/IMPL Landroid/support/v4/view/accessibility/AccessibilityRecordCompat$AccessibilityRecordImpl;
aload 0
getfield android/support/v4/view/accessibility/AccessibilityRecordCompat/mRecord Ljava/lang/Object;
iload 1
invokeinterface android/support/v4/view/accessibility/AccessibilityRecordCompat$AccessibilityRecordImpl/setMaxScrollY(Ljava/lang/Object;I)V 2
return
.limit locals 2
.limit stack 3
.end method

.method public setParcelableData(Landroid/os/Parcelable;)V
getstatic android/support/v4/view/accessibility/AccessibilityRecordCompat/IMPL Landroid/support/v4/view/accessibility/AccessibilityRecordCompat$AccessibilityRecordImpl;
aload 0
getfield android/support/v4/view/accessibility/AccessibilityRecordCompat/mRecord Ljava/lang/Object;
aload 1
invokeinterface android/support/v4/view/accessibility/AccessibilityRecordCompat$AccessibilityRecordImpl/setParcelableData(Ljava/lang/Object;Landroid/os/Parcelable;)V 2
return
.limit locals 2
.limit stack 3
.end method

.method public setPassword(Z)V
getstatic android/support/v4/view/accessibility/AccessibilityRecordCompat/IMPL Landroid/support/v4/view/accessibility/AccessibilityRecordCompat$AccessibilityRecordImpl;
aload 0
getfield android/support/v4/view/accessibility/AccessibilityRecordCompat/mRecord Ljava/lang/Object;
iload 1
invokeinterface android/support/v4/view/accessibility/AccessibilityRecordCompat$AccessibilityRecordImpl/setPassword(Ljava/lang/Object;Z)V 2
return
.limit locals 2
.limit stack 3
.end method

.method public setRemovedCount(I)V
getstatic android/support/v4/view/accessibility/AccessibilityRecordCompat/IMPL Landroid/support/v4/view/accessibility/AccessibilityRecordCompat$AccessibilityRecordImpl;
aload 0
getfield android/support/v4/view/accessibility/AccessibilityRecordCompat/mRecord Ljava/lang/Object;
iload 1
invokeinterface android/support/v4/view/accessibility/AccessibilityRecordCompat$AccessibilityRecordImpl/setRemovedCount(Ljava/lang/Object;I)V 2
return
.limit locals 2
.limit stack 3
.end method

.method public setScrollX(I)V
getstatic android/support/v4/view/accessibility/AccessibilityRecordCompat/IMPL Landroid/support/v4/view/accessibility/AccessibilityRecordCompat$AccessibilityRecordImpl;
aload 0
getfield android/support/v4/view/accessibility/AccessibilityRecordCompat/mRecord Ljava/lang/Object;
iload 1
invokeinterface android/support/v4/view/accessibility/AccessibilityRecordCompat$AccessibilityRecordImpl/setScrollX(Ljava/lang/Object;I)V 2
return
.limit locals 2
.limit stack 3
.end method

.method public setScrollY(I)V
getstatic android/support/v4/view/accessibility/AccessibilityRecordCompat/IMPL Landroid/support/v4/view/accessibility/AccessibilityRecordCompat$AccessibilityRecordImpl;
aload 0
getfield android/support/v4/view/accessibility/AccessibilityRecordCompat/mRecord Ljava/lang/Object;
iload 1
invokeinterface android/support/v4/view/accessibility/AccessibilityRecordCompat$AccessibilityRecordImpl/setScrollY(Ljava/lang/Object;I)V 2
return
.limit locals 2
.limit stack 3
.end method

.method public setScrollable(Z)V
getstatic android/support/v4/view/accessibility/AccessibilityRecordCompat/IMPL Landroid/support/v4/view/accessibility/AccessibilityRecordCompat$AccessibilityRecordImpl;
aload 0
getfield android/support/v4/view/accessibility/AccessibilityRecordCompat/mRecord Ljava/lang/Object;
iload 1
invokeinterface android/support/v4/view/accessibility/AccessibilityRecordCompat$AccessibilityRecordImpl/setScrollable(Ljava/lang/Object;Z)V 2
return
.limit locals 2
.limit stack 3
.end method

.method public setSource(Landroid/view/View;)V
getstatic android/support/v4/view/accessibility/AccessibilityRecordCompat/IMPL Landroid/support/v4/view/accessibility/AccessibilityRecordCompat$AccessibilityRecordImpl;
aload 0
getfield android/support/v4/view/accessibility/AccessibilityRecordCompat/mRecord Ljava/lang/Object;
aload 1
invokeinterface android/support/v4/view/accessibility/AccessibilityRecordCompat$AccessibilityRecordImpl/setSource(Ljava/lang/Object;Landroid/view/View;)V 2
return
.limit locals 2
.limit stack 3
.end method

.method public setSource(Landroid/view/View;I)V
getstatic android/support/v4/view/accessibility/AccessibilityRecordCompat/IMPL Landroid/support/v4/view/accessibility/AccessibilityRecordCompat$AccessibilityRecordImpl;
aload 0
getfield android/support/v4/view/accessibility/AccessibilityRecordCompat/mRecord Ljava/lang/Object;
aload 1
iload 2
invokeinterface android/support/v4/view/accessibility/AccessibilityRecordCompat$AccessibilityRecordImpl/setSource(Ljava/lang/Object;Landroid/view/View;I)V 3
return
.limit locals 3
.limit stack 4
.end method

.method public setToIndex(I)V
getstatic android/support/v4/view/accessibility/AccessibilityRecordCompat/IMPL Landroid/support/v4/view/accessibility/AccessibilityRecordCompat$AccessibilityRecordImpl;
aload 0
getfield android/support/v4/view/accessibility/AccessibilityRecordCompat/mRecord Ljava/lang/Object;
iload 1
invokeinterface android/support/v4/view/accessibility/AccessibilityRecordCompat$AccessibilityRecordImpl/setToIndex(Ljava/lang/Object;I)V 2
return
.limit locals 2
.limit stack 3
.end method
