.bytecode 50.0
.class synchronized android/support/v4/view/accessibility/AccessibilityRecordCompat$AccessibilityRecordIcsImpl
.super android/support/v4/view/accessibility/AccessibilityRecordCompat$AccessibilityRecordStubImpl
.inner class static AccessibilityRecordIcsImpl inner android/support/v4/view/accessibility/AccessibilityRecordCompat$AccessibilityRecordIcsImpl outer android/support/v4/view/accessibility/AccessibilityRecordCompat

.method <init>()V
aload 0
invokespecial android/support/v4/view/accessibility/AccessibilityRecordCompat$AccessibilityRecordStubImpl/<init>()V
return
.limit locals 1
.limit stack 1
.end method

.method public getAddedCount(Ljava/lang/Object;)I
aload 1
invokestatic android/support/v4/view/accessibility/AccessibilityRecordCompatIcs/getAddedCount(Ljava/lang/Object;)I
ireturn
.limit locals 2
.limit stack 1
.end method

.method public getBeforeText(Ljava/lang/Object;)Ljava/lang/CharSequence;
aload 1
invokestatic android/support/v4/view/accessibility/AccessibilityRecordCompatIcs/getBeforeText(Ljava/lang/Object;)Ljava/lang/CharSequence;
areturn
.limit locals 2
.limit stack 1
.end method

.method public getClassName(Ljava/lang/Object;)Ljava/lang/CharSequence;
aload 1
invokestatic android/support/v4/view/accessibility/AccessibilityRecordCompatIcs/getClassName(Ljava/lang/Object;)Ljava/lang/CharSequence;
areturn
.limit locals 2
.limit stack 1
.end method

.method public getContentDescription(Ljava/lang/Object;)Ljava/lang/CharSequence;
aload 1
invokestatic android/support/v4/view/accessibility/AccessibilityRecordCompatIcs/getContentDescription(Ljava/lang/Object;)Ljava/lang/CharSequence;
areturn
.limit locals 2
.limit stack 1
.end method

.method public getCurrentItemIndex(Ljava/lang/Object;)I
aload 1
invokestatic android/support/v4/view/accessibility/AccessibilityRecordCompatIcs/getCurrentItemIndex(Ljava/lang/Object;)I
ireturn
.limit locals 2
.limit stack 1
.end method

.method public getFromIndex(Ljava/lang/Object;)I
aload 1
invokestatic android/support/v4/view/accessibility/AccessibilityRecordCompatIcs/getFromIndex(Ljava/lang/Object;)I
ireturn
.limit locals 2
.limit stack 1
.end method

.method public getItemCount(Ljava/lang/Object;)I
aload 1
invokestatic android/support/v4/view/accessibility/AccessibilityRecordCompatIcs/getItemCount(Ljava/lang/Object;)I
ireturn
.limit locals 2
.limit stack 1
.end method

.method public getParcelableData(Ljava/lang/Object;)Landroid/os/Parcelable;
aload 1
invokestatic android/support/v4/view/accessibility/AccessibilityRecordCompatIcs/getParcelableData(Ljava/lang/Object;)Landroid/os/Parcelable;
areturn
.limit locals 2
.limit stack 1
.end method

.method public getRemovedCount(Ljava/lang/Object;)I
aload 1
invokestatic android/support/v4/view/accessibility/AccessibilityRecordCompatIcs/getRemovedCount(Ljava/lang/Object;)I
ireturn
.limit locals 2
.limit stack 1
.end method

.method public getScrollX(Ljava/lang/Object;)I
aload 1
invokestatic android/support/v4/view/accessibility/AccessibilityRecordCompatIcs/getScrollX(Ljava/lang/Object;)I
ireturn
.limit locals 2
.limit stack 1
.end method

.method public getScrollY(Ljava/lang/Object;)I
aload 1
invokestatic android/support/v4/view/accessibility/AccessibilityRecordCompatIcs/getScrollY(Ljava/lang/Object;)I
ireturn
.limit locals 2
.limit stack 1
.end method

.method public getSource(Ljava/lang/Object;)Landroid/support/v4/view/accessibility/AccessibilityNodeInfoCompat;
aload 1
invokestatic android/support/v4/view/accessibility/AccessibilityRecordCompatIcs/getSource(Ljava/lang/Object;)Ljava/lang/Object;
invokestatic android/support/v4/view/accessibility/AccessibilityNodeInfoCompat/wrapNonNullInstance(Ljava/lang/Object;)Landroid/support/v4/view/accessibility/AccessibilityNodeInfoCompat;
areturn
.limit locals 2
.limit stack 1
.end method

.method public getText(Ljava/lang/Object;)Ljava/util/List;
.signature "(Ljava/lang/Object;)Ljava/util/List<Ljava/lang/CharSequence;>;"
aload 1
invokestatic android/support/v4/view/accessibility/AccessibilityRecordCompatIcs/getText(Ljava/lang/Object;)Ljava/util/List;
areturn
.limit locals 2
.limit stack 1
.end method

.method public getToIndex(Ljava/lang/Object;)I
aload 1
invokestatic android/support/v4/view/accessibility/AccessibilityRecordCompatIcs/getToIndex(Ljava/lang/Object;)I
ireturn
.limit locals 2
.limit stack 1
.end method

.method public getWindowId(Ljava/lang/Object;)I
aload 1
invokestatic android/support/v4/view/accessibility/AccessibilityRecordCompatIcs/getWindowId(Ljava/lang/Object;)I
ireturn
.limit locals 2
.limit stack 1
.end method

.method public isChecked(Ljava/lang/Object;)Z
aload 1
invokestatic android/support/v4/view/accessibility/AccessibilityRecordCompatIcs/isChecked(Ljava/lang/Object;)Z
ireturn
.limit locals 2
.limit stack 1
.end method

.method public isEnabled(Ljava/lang/Object;)Z
aload 1
invokestatic android/support/v4/view/accessibility/AccessibilityRecordCompatIcs/isEnabled(Ljava/lang/Object;)Z
ireturn
.limit locals 2
.limit stack 1
.end method

.method public isFullScreen(Ljava/lang/Object;)Z
aload 1
invokestatic android/support/v4/view/accessibility/AccessibilityRecordCompatIcs/isFullScreen(Ljava/lang/Object;)Z
ireturn
.limit locals 2
.limit stack 1
.end method

.method public isPassword(Ljava/lang/Object;)Z
aload 1
invokestatic android/support/v4/view/accessibility/AccessibilityRecordCompatIcs/isPassword(Ljava/lang/Object;)Z
ireturn
.limit locals 2
.limit stack 1
.end method

.method public isScrollable(Ljava/lang/Object;)Z
aload 1
invokestatic android/support/v4/view/accessibility/AccessibilityRecordCompatIcs/isScrollable(Ljava/lang/Object;)Z
ireturn
.limit locals 2
.limit stack 1
.end method

.method public obtain()Ljava/lang/Object;
invokestatic android/support/v4/view/accessibility/AccessibilityRecordCompatIcs/obtain()Ljava/lang/Object;
areturn
.limit locals 1
.limit stack 1
.end method

.method public obtain(Ljava/lang/Object;)Ljava/lang/Object;
aload 1
invokestatic android/support/v4/view/accessibility/AccessibilityRecordCompatIcs/obtain(Ljava/lang/Object;)Ljava/lang/Object;
areturn
.limit locals 2
.limit stack 1
.end method

.method public recycle(Ljava/lang/Object;)V
aload 1
invokestatic android/support/v4/view/accessibility/AccessibilityRecordCompatIcs/recycle(Ljava/lang/Object;)V
return
.limit locals 2
.limit stack 1
.end method

.method public setAddedCount(Ljava/lang/Object;I)V
aload 1
iload 2
invokestatic android/support/v4/view/accessibility/AccessibilityRecordCompatIcs/setAddedCount(Ljava/lang/Object;I)V
return
.limit locals 3
.limit stack 2
.end method

.method public setBeforeText(Ljava/lang/Object;Ljava/lang/CharSequence;)V
aload 1
aload 2
invokestatic android/support/v4/view/accessibility/AccessibilityRecordCompatIcs/setBeforeText(Ljava/lang/Object;Ljava/lang/CharSequence;)V
return
.limit locals 3
.limit stack 2
.end method

.method public setChecked(Ljava/lang/Object;Z)V
aload 1
iload 2
invokestatic android/support/v4/view/accessibility/AccessibilityRecordCompatIcs/setChecked(Ljava/lang/Object;Z)V
return
.limit locals 3
.limit stack 2
.end method

.method public setClassName(Ljava/lang/Object;Ljava/lang/CharSequence;)V
aload 1
aload 2
invokestatic android/support/v4/view/accessibility/AccessibilityRecordCompatIcs/setClassName(Ljava/lang/Object;Ljava/lang/CharSequence;)V
return
.limit locals 3
.limit stack 2
.end method

.method public setContentDescription(Ljava/lang/Object;Ljava/lang/CharSequence;)V
aload 1
aload 2
invokestatic android/support/v4/view/accessibility/AccessibilityRecordCompatIcs/setContentDescription(Ljava/lang/Object;Ljava/lang/CharSequence;)V
return
.limit locals 3
.limit stack 2
.end method

.method public setCurrentItemIndex(Ljava/lang/Object;I)V
aload 1
iload 2
invokestatic android/support/v4/view/accessibility/AccessibilityRecordCompatIcs/setCurrentItemIndex(Ljava/lang/Object;I)V
return
.limit locals 3
.limit stack 2
.end method

.method public setEnabled(Ljava/lang/Object;Z)V
aload 1
iload 2
invokestatic android/support/v4/view/accessibility/AccessibilityRecordCompatIcs/setEnabled(Ljava/lang/Object;Z)V
return
.limit locals 3
.limit stack 2
.end method

.method public setFromIndex(Ljava/lang/Object;I)V
aload 1
iload 2
invokestatic android/support/v4/view/accessibility/AccessibilityRecordCompatIcs/setFromIndex(Ljava/lang/Object;I)V
return
.limit locals 3
.limit stack 2
.end method

.method public setFullScreen(Ljava/lang/Object;Z)V
aload 1
iload 2
invokestatic android/support/v4/view/accessibility/AccessibilityRecordCompatIcs/setFullScreen(Ljava/lang/Object;Z)V
return
.limit locals 3
.limit stack 2
.end method

.method public setItemCount(Ljava/lang/Object;I)V
aload 1
iload 2
invokestatic android/support/v4/view/accessibility/AccessibilityRecordCompatIcs/setItemCount(Ljava/lang/Object;I)V
return
.limit locals 3
.limit stack 2
.end method

.method public setParcelableData(Ljava/lang/Object;Landroid/os/Parcelable;)V
aload 1
aload 2
invokestatic android/support/v4/view/accessibility/AccessibilityRecordCompatIcs/setParcelableData(Ljava/lang/Object;Landroid/os/Parcelable;)V
return
.limit locals 3
.limit stack 2
.end method

.method public setPassword(Ljava/lang/Object;Z)V
aload 1
iload 2
invokestatic android/support/v4/view/accessibility/AccessibilityRecordCompatIcs/setPassword(Ljava/lang/Object;Z)V
return
.limit locals 3
.limit stack 2
.end method

.method public setRemovedCount(Ljava/lang/Object;I)V
aload 1
iload 2
invokestatic android/support/v4/view/accessibility/AccessibilityRecordCompatIcs/setRemovedCount(Ljava/lang/Object;I)V
return
.limit locals 3
.limit stack 2
.end method

.method public setScrollX(Ljava/lang/Object;I)V
aload 1
iload 2
invokestatic android/support/v4/view/accessibility/AccessibilityRecordCompatIcs/setScrollX(Ljava/lang/Object;I)V
return
.limit locals 3
.limit stack 2
.end method

.method public setScrollY(Ljava/lang/Object;I)V
aload 1
iload 2
invokestatic android/support/v4/view/accessibility/AccessibilityRecordCompatIcs/setScrollY(Ljava/lang/Object;I)V
return
.limit locals 3
.limit stack 2
.end method

.method public setScrollable(Ljava/lang/Object;Z)V
aload 1
iload 2
invokestatic android/support/v4/view/accessibility/AccessibilityRecordCompatIcs/setScrollable(Ljava/lang/Object;Z)V
return
.limit locals 3
.limit stack 2
.end method

.method public setSource(Ljava/lang/Object;Landroid/view/View;)V
aload 1
aload 2
invokestatic android/support/v4/view/accessibility/AccessibilityRecordCompatIcs/setSource(Ljava/lang/Object;Landroid/view/View;)V
return
.limit locals 3
.limit stack 2
.end method

.method public setToIndex(Ljava/lang/Object;I)V
aload 1
iload 2
invokestatic android/support/v4/view/accessibility/AccessibilityRecordCompatIcs/setToIndex(Ljava/lang/Object;I)V
return
.limit locals 3
.limit stack 2
.end method
