.bytecode 50.0
.class public final synchronized enum com/android/u/weibo/sina/business/comm/WeiboAPI$STATUSES_TYPE
.super java/lang/Enum
.signature "Ljava/lang/Enum<Lcom/android/u/weibo/sina/business/comm/WeiboAPI$STATUSES_TYPE;>;"
.inner class public static final enum STATUSES_TYPE inner com/android/u/weibo/sina/business/comm/WeiboAPI$STATUSES_TYPE outer com/android/u/weibo/sina/business/comm/WeiboAPI

.field private static final synthetic '$VALUES' [Lcom/android/u/weibo/sina/business/comm/WeiboAPI$STATUSES_TYPE;

.field public static final enum 'BEAUTY' Lcom/android/u/weibo/sina/business/comm/WeiboAPI$STATUSES_TYPE;

.field public static final enum 'CARS' Lcom/android/u/weibo/sina/business/comm/WeiboAPI$STATUSES_TYPE;

.field public static final enum 'CATE' Lcom/android/u/weibo/sina/business/comm/WeiboAPI$STATUSES_TYPE;

.field public static final enum 'CONSTELLATION' Lcom/android/u/weibo/sina/business/comm/WeiboAPI$STATUSES_TYPE;

.field public static final enum 'ENTERTAINMENT' Lcom/android/u/weibo/sina/business/comm/WeiboAPI$STATUSES_TYPE;

.field public static final enum 'FASHION' Lcom/android/u/weibo/sina/business/comm/WeiboAPI$STATUSES_TYPE;

.field public static final enum 'FUNNY' Lcom/android/u/weibo/sina/business/comm/WeiboAPI$STATUSES_TYPE;

.field public static final enum 'LOVELY' Lcom/android/u/weibo/sina/business/comm/WeiboAPI$STATUSES_TYPE;

.field public static final enum 'MUSIC' Lcom/android/u/weibo/sina/business/comm/WeiboAPI$STATUSES_TYPE;

.field public static final enum 'VIDEO' Lcom/android/u/weibo/sina/business/comm/WeiboAPI$STATUSES_TYPE;

.method static <clinit>()V
new com/android/u/weibo/sina/business/comm/WeiboAPI$STATUSES_TYPE
dup
ldc "ENTERTAINMENT"
iconst_0
invokespecial com/android/u/weibo/sina/business/comm/WeiboAPI$STATUSES_TYPE/<init>(Ljava/lang/String;I)V
putstatic com/android/u/weibo/sina/business/comm/WeiboAPI$STATUSES_TYPE/ENTERTAINMENT Lcom/android/u/weibo/sina/business/comm/WeiboAPI$STATUSES_TYPE;
new com/android/u/weibo/sina/business/comm/WeiboAPI$STATUSES_TYPE
dup
ldc "FUNNY"
iconst_1
invokespecial com/android/u/weibo/sina/business/comm/WeiboAPI$STATUSES_TYPE/<init>(Ljava/lang/String;I)V
putstatic com/android/u/weibo/sina/business/comm/WeiboAPI$STATUSES_TYPE/FUNNY Lcom/android/u/weibo/sina/business/comm/WeiboAPI$STATUSES_TYPE;
new com/android/u/weibo/sina/business/comm/WeiboAPI$STATUSES_TYPE
dup
ldc "BEAUTY"
iconst_2
invokespecial com/android/u/weibo/sina/business/comm/WeiboAPI$STATUSES_TYPE/<init>(Ljava/lang/String;I)V
putstatic com/android/u/weibo/sina/business/comm/WeiboAPI$STATUSES_TYPE/BEAUTY Lcom/android/u/weibo/sina/business/comm/WeiboAPI$STATUSES_TYPE;
new com/android/u/weibo/sina/business/comm/WeiboAPI$STATUSES_TYPE
dup
ldc "VIDEO"
iconst_3
invokespecial com/android/u/weibo/sina/business/comm/WeiboAPI$STATUSES_TYPE/<init>(Ljava/lang/String;I)V
putstatic com/android/u/weibo/sina/business/comm/WeiboAPI$STATUSES_TYPE/VIDEO Lcom/android/u/weibo/sina/business/comm/WeiboAPI$STATUSES_TYPE;
new com/android/u/weibo/sina/business/comm/WeiboAPI$STATUSES_TYPE
dup
ldc "CONSTELLATION"
iconst_4
invokespecial com/android/u/weibo/sina/business/comm/WeiboAPI$STATUSES_TYPE/<init>(Ljava/lang/String;I)V
putstatic com/android/u/weibo/sina/business/comm/WeiboAPI$STATUSES_TYPE/CONSTELLATION Lcom/android/u/weibo/sina/business/comm/WeiboAPI$STATUSES_TYPE;
new com/android/u/weibo/sina/business/comm/WeiboAPI$STATUSES_TYPE
dup
ldc "LOVELY"
iconst_5
invokespecial com/android/u/weibo/sina/business/comm/WeiboAPI$STATUSES_TYPE/<init>(Ljava/lang/String;I)V
putstatic com/android/u/weibo/sina/business/comm/WeiboAPI$STATUSES_TYPE/LOVELY Lcom/android/u/weibo/sina/business/comm/WeiboAPI$STATUSES_TYPE;
new com/android/u/weibo/sina/business/comm/WeiboAPI$STATUSES_TYPE
dup
ldc "FASHION"
bipush 6
invokespecial com/android/u/weibo/sina/business/comm/WeiboAPI$STATUSES_TYPE/<init>(Ljava/lang/String;I)V
putstatic com/android/u/weibo/sina/business/comm/WeiboAPI$STATUSES_TYPE/FASHION Lcom/android/u/weibo/sina/business/comm/WeiboAPI$STATUSES_TYPE;
new com/android/u/weibo/sina/business/comm/WeiboAPI$STATUSES_TYPE
dup
ldc "CARS"
bipush 7
invokespecial com/android/u/weibo/sina/business/comm/WeiboAPI$STATUSES_TYPE/<init>(Ljava/lang/String;I)V
putstatic com/android/u/weibo/sina/business/comm/WeiboAPI$STATUSES_TYPE/CARS Lcom/android/u/weibo/sina/business/comm/WeiboAPI$STATUSES_TYPE;
new com/android/u/weibo/sina/business/comm/WeiboAPI$STATUSES_TYPE
dup
ldc "CATE"
bipush 8
invokespecial com/android/u/weibo/sina/business/comm/WeiboAPI$STATUSES_TYPE/<init>(Ljava/lang/String;I)V
putstatic com/android/u/weibo/sina/business/comm/WeiboAPI$STATUSES_TYPE/CATE Lcom/android/u/weibo/sina/business/comm/WeiboAPI$STATUSES_TYPE;
new com/android/u/weibo/sina/business/comm/WeiboAPI$STATUSES_TYPE
dup
ldc "MUSIC"
bipush 9
invokespecial com/android/u/weibo/sina/business/comm/WeiboAPI$STATUSES_TYPE/<init>(Ljava/lang/String;I)V
putstatic com/android/u/weibo/sina/business/comm/WeiboAPI$STATUSES_TYPE/MUSIC Lcom/android/u/weibo/sina/business/comm/WeiboAPI$STATUSES_TYPE;
bipush 10
anewarray com/android/u/weibo/sina/business/comm/WeiboAPI$STATUSES_TYPE
dup
iconst_0
getstatic com/android/u/weibo/sina/business/comm/WeiboAPI$STATUSES_TYPE/ENTERTAINMENT Lcom/android/u/weibo/sina/business/comm/WeiboAPI$STATUSES_TYPE;
aastore
dup
iconst_1
getstatic com/android/u/weibo/sina/business/comm/WeiboAPI$STATUSES_TYPE/FUNNY Lcom/android/u/weibo/sina/business/comm/WeiboAPI$STATUSES_TYPE;
aastore
dup
iconst_2
getstatic com/android/u/weibo/sina/business/comm/WeiboAPI$STATUSES_TYPE/BEAUTY Lcom/android/u/weibo/sina/business/comm/WeiboAPI$STATUSES_TYPE;
aastore
dup
iconst_3
getstatic com/android/u/weibo/sina/business/comm/WeiboAPI$STATUSES_TYPE/VIDEO Lcom/android/u/weibo/sina/business/comm/WeiboAPI$STATUSES_TYPE;
aastore
dup
iconst_4
getstatic com/android/u/weibo/sina/business/comm/WeiboAPI$STATUSES_TYPE/CONSTELLATION Lcom/android/u/weibo/sina/business/comm/WeiboAPI$STATUSES_TYPE;
aastore
dup
iconst_5
getstatic com/android/u/weibo/sina/business/comm/WeiboAPI$STATUSES_TYPE/LOVELY Lcom/android/u/weibo/sina/business/comm/WeiboAPI$STATUSES_TYPE;
aastore
dup
bipush 6
getstatic com/android/u/weibo/sina/business/comm/WeiboAPI$STATUSES_TYPE/FASHION Lcom/android/u/weibo/sina/business/comm/WeiboAPI$STATUSES_TYPE;
aastore
dup
bipush 7
getstatic com/android/u/weibo/sina/business/comm/WeiboAPI$STATUSES_TYPE/CARS Lcom/android/u/weibo/sina/business/comm/WeiboAPI$STATUSES_TYPE;
aastore
dup
bipush 8
getstatic com/android/u/weibo/sina/business/comm/WeiboAPI$STATUSES_TYPE/CATE Lcom/android/u/weibo/sina/business/comm/WeiboAPI$STATUSES_TYPE;
aastore
dup
bipush 9
getstatic com/android/u/weibo/sina/business/comm/WeiboAPI$STATUSES_TYPE/MUSIC Lcom/android/u/weibo/sina/business/comm/WeiboAPI$STATUSES_TYPE;
aastore
putstatic com/android/u/weibo/sina/business/comm/WeiboAPI$STATUSES_TYPE/$VALUES [Lcom/android/u/weibo/sina/business/comm/WeiboAPI$STATUSES_TYPE;
return
.limit locals 0
.limit stack 4
.end method

.method private <init>(Ljava/lang/String;I)V
.signature "()V"
aload 0
aload 1
iload 2
invokespecial java/lang/Enum/<init>(Ljava/lang/String;I)V
return
.limit locals 3
.limit stack 3
.end method

.method public static valueOf(Ljava/lang/String;)Lcom/android/u/weibo/sina/business/comm/WeiboAPI$STATUSES_TYPE;
ldc com/android/u/weibo/sina/business/comm/WeiboAPI$STATUSES_TYPE
aload 0
invokestatic java/lang/Enum/valueOf(Ljava/lang/Class;Ljava/lang/String;)Ljava/lang/Enum;
checkcast com/android/u/weibo/sina/business/comm/WeiboAPI$STATUSES_TYPE
areturn
.limit locals 1
.limit stack 2
.end method

.method public static values()[Lcom/android/u/weibo/sina/business/comm/WeiboAPI$STATUSES_TYPE;
getstatic com/android/u/weibo/sina/business/comm/WeiboAPI$STATUSES_TYPE/$VALUES [Lcom/android/u/weibo/sina/business/comm/WeiboAPI$STATUSES_TYPE;
invokevirtual [Lcom/android/u/weibo/sina/business/comm/WeiboAPI$STATUSES_TYPE;/clone()Ljava/lang/Object;
checkcast [Lcom/android/u/weibo/sina/business/comm/WeiboAPI$STATUSES_TYPE;
areturn
.limit locals 0
.limit stack 1
.end method
