.bytecode 50.0
.class public final synchronized enum com/android/u/weibo/sina/business/comm/WeiboAPI$CAPITAL
.super java/lang/Enum
.signature "Ljava/lang/Enum<Lcom/android/u/weibo/sina/business/comm/WeiboAPI$CAPITAL;>;"
.inner class public static final enum CAPITAL inner com/android/u/weibo/sina/business/comm/WeiboAPI$CAPITAL outer com/android/u/weibo/sina/business/comm/WeiboAPI

.field private static final synthetic '$VALUES' [Lcom/android/u/weibo/sina/business/comm/WeiboAPI$CAPITAL;

.field public static final enum 'A' Lcom/android/u/weibo/sina/business/comm/WeiboAPI$CAPITAL;

.field public static final enum 'B' Lcom/android/u/weibo/sina/business/comm/WeiboAPI$CAPITAL;

.field public static final enum 'C' Lcom/android/u/weibo/sina/business/comm/WeiboAPI$CAPITAL;

.field public static final enum 'D' Lcom/android/u/weibo/sina/business/comm/WeiboAPI$CAPITAL;

.field public static final enum 'E' Lcom/android/u/weibo/sina/business/comm/WeiboAPI$CAPITAL;

.field public static final enum 'F' Lcom/android/u/weibo/sina/business/comm/WeiboAPI$CAPITAL;

.field public static final enum 'G' Lcom/android/u/weibo/sina/business/comm/WeiboAPI$CAPITAL;

.field public static final enum 'H' Lcom/android/u/weibo/sina/business/comm/WeiboAPI$CAPITAL;

.field public static final enum 'I' Lcom/android/u/weibo/sina/business/comm/WeiboAPI$CAPITAL;

.field public static final enum 'J' Lcom/android/u/weibo/sina/business/comm/WeiboAPI$CAPITAL;

.field public static final enum 'K' Lcom/android/u/weibo/sina/business/comm/WeiboAPI$CAPITAL;

.field public static final enum 'L' Lcom/android/u/weibo/sina/business/comm/WeiboAPI$CAPITAL;

.field public static final enum 'M' Lcom/android/u/weibo/sina/business/comm/WeiboAPI$CAPITAL;

.field public static final enum 'N' Lcom/android/u/weibo/sina/business/comm/WeiboAPI$CAPITAL;

.field public static final enum 'O' Lcom/android/u/weibo/sina/business/comm/WeiboAPI$CAPITAL;

.field public static final enum 'P' Lcom/android/u/weibo/sina/business/comm/WeiboAPI$CAPITAL;

.field public static final enum 'Q' Lcom/android/u/weibo/sina/business/comm/WeiboAPI$CAPITAL;

.field public static final enum 'R' Lcom/android/u/weibo/sina/business/comm/WeiboAPI$CAPITAL;

.field public static final enum 'S' Lcom/android/u/weibo/sina/business/comm/WeiboAPI$CAPITAL;

.field public static final enum 'T' Lcom/android/u/weibo/sina/business/comm/WeiboAPI$CAPITAL;

.field public static final enum 'U' Lcom/android/u/weibo/sina/business/comm/WeiboAPI$CAPITAL;

.field public static final enum 'V' Lcom/android/u/weibo/sina/business/comm/WeiboAPI$CAPITAL;

.field public static final enum 'W' Lcom/android/u/weibo/sina/business/comm/WeiboAPI$CAPITAL;

.field public static final enum 'X' Lcom/android/u/weibo/sina/business/comm/WeiboAPI$CAPITAL;

.field public static final enum 'Y' Lcom/android/u/weibo/sina/business/comm/WeiboAPI$CAPITAL;

.field public static final enum 'Z' Lcom/android/u/weibo/sina/business/comm/WeiboAPI$CAPITAL;

.method static <clinit>()V
new com/android/u/weibo/sina/business/comm/WeiboAPI$CAPITAL
dup
ldc "A"
iconst_0
invokespecial com/android/u/weibo/sina/business/comm/WeiboAPI$CAPITAL/<init>(Ljava/lang/String;I)V
putstatic com/android/u/weibo/sina/business/comm/WeiboAPI$CAPITAL/A Lcom/android/u/weibo/sina/business/comm/WeiboAPI$CAPITAL;
new com/android/u/weibo/sina/business/comm/WeiboAPI$CAPITAL
dup
ldc "B"
iconst_1
invokespecial com/android/u/weibo/sina/business/comm/WeiboAPI$CAPITAL/<init>(Ljava/lang/String;I)V
putstatic com/android/u/weibo/sina/business/comm/WeiboAPI$CAPITAL/B Lcom/android/u/weibo/sina/business/comm/WeiboAPI$CAPITAL;
new com/android/u/weibo/sina/business/comm/WeiboAPI$CAPITAL
dup
ldc "C"
iconst_2
invokespecial com/android/u/weibo/sina/business/comm/WeiboAPI$CAPITAL/<init>(Ljava/lang/String;I)V
putstatic com/android/u/weibo/sina/business/comm/WeiboAPI$CAPITAL/C Lcom/android/u/weibo/sina/business/comm/WeiboAPI$CAPITAL;
new com/android/u/weibo/sina/business/comm/WeiboAPI$CAPITAL
dup
ldc "D"
iconst_3
invokespecial com/android/u/weibo/sina/business/comm/WeiboAPI$CAPITAL/<init>(Ljava/lang/String;I)V
putstatic com/android/u/weibo/sina/business/comm/WeiboAPI$CAPITAL/D Lcom/android/u/weibo/sina/business/comm/WeiboAPI$CAPITAL;
new com/android/u/weibo/sina/business/comm/WeiboAPI$CAPITAL
dup
ldc "E"
iconst_4
invokespecial com/android/u/weibo/sina/business/comm/WeiboAPI$CAPITAL/<init>(Ljava/lang/String;I)V
putstatic com/android/u/weibo/sina/business/comm/WeiboAPI$CAPITAL/E Lcom/android/u/weibo/sina/business/comm/WeiboAPI$CAPITAL;
new com/android/u/weibo/sina/business/comm/WeiboAPI$CAPITAL
dup
ldc "F"
iconst_5
invokespecial com/android/u/weibo/sina/business/comm/WeiboAPI$CAPITAL/<init>(Ljava/lang/String;I)V
putstatic com/android/u/weibo/sina/business/comm/WeiboAPI$CAPITAL/F Lcom/android/u/weibo/sina/business/comm/WeiboAPI$CAPITAL;
new com/android/u/weibo/sina/business/comm/WeiboAPI$CAPITAL
dup
ldc "G"
bipush 6
invokespecial com/android/u/weibo/sina/business/comm/WeiboAPI$CAPITAL/<init>(Ljava/lang/String;I)V
putstatic com/android/u/weibo/sina/business/comm/WeiboAPI$CAPITAL/G Lcom/android/u/weibo/sina/business/comm/WeiboAPI$CAPITAL;
new com/android/u/weibo/sina/business/comm/WeiboAPI$CAPITAL
dup
ldc "H"
bipush 7
invokespecial com/android/u/weibo/sina/business/comm/WeiboAPI$CAPITAL/<init>(Ljava/lang/String;I)V
putstatic com/android/u/weibo/sina/business/comm/WeiboAPI$CAPITAL/H Lcom/android/u/weibo/sina/business/comm/WeiboAPI$CAPITAL;
new com/android/u/weibo/sina/business/comm/WeiboAPI$CAPITAL
dup
ldc "I"
bipush 8
invokespecial com/android/u/weibo/sina/business/comm/WeiboAPI$CAPITAL/<init>(Ljava/lang/String;I)V
putstatic com/android/u/weibo/sina/business/comm/WeiboAPI$CAPITAL/I Lcom/android/u/weibo/sina/business/comm/WeiboAPI$CAPITAL;
new com/android/u/weibo/sina/business/comm/WeiboAPI$CAPITAL
dup
ldc "J"
bipush 9
invokespecial com/android/u/weibo/sina/business/comm/WeiboAPI$CAPITAL/<init>(Ljava/lang/String;I)V
putstatic com/android/u/weibo/sina/business/comm/WeiboAPI$CAPITAL/J Lcom/android/u/weibo/sina/business/comm/WeiboAPI$CAPITAL;
new com/android/u/weibo/sina/business/comm/WeiboAPI$CAPITAL
dup
ldc "K"
bipush 10
invokespecial com/android/u/weibo/sina/business/comm/WeiboAPI$CAPITAL/<init>(Ljava/lang/String;I)V
putstatic com/android/u/weibo/sina/business/comm/WeiboAPI$CAPITAL/K Lcom/android/u/weibo/sina/business/comm/WeiboAPI$CAPITAL;
new com/android/u/weibo/sina/business/comm/WeiboAPI$CAPITAL
dup
ldc "L"
bipush 11
invokespecial com/android/u/weibo/sina/business/comm/WeiboAPI$CAPITAL/<init>(Ljava/lang/String;I)V
putstatic com/android/u/weibo/sina/business/comm/WeiboAPI$CAPITAL/L Lcom/android/u/weibo/sina/business/comm/WeiboAPI$CAPITAL;
new com/android/u/weibo/sina/business/comm/WeiboAPI$CAPITAL
dup
ldc "M"
bipush 12
invokespecial com/android/u/weibo/sina/business/comm/WeiboAPI$CAPITAL/<init>(Ljava/lang/String;I)V
putstatic com/android/u/weibo/sina/business/comm/WeiboAPI$CAPITAL/M Lcom/android/u/weibo/sina/business/comm/WeiboAPI$CAPITAL;
new com/android/u/weibo/sina/business/comm/WeiboAPI$CAPITAL
dup
ldc "N"
bipush 13
invokespecial com/android/u/weibo/sina/business/comm/WeiboAPI$CAPITAL/<init>(Ljava/lang/String;I)V
putstatic com/android/u/weibo/sina/business/comm/WeiboAPI$CAPITAL/N Lcom/android/u/weibo/sina/business/comm/WeiboAPI$CAPITAL;
new com/android/u/weibo/sina/business/comm/WeiboAPI$CAPITAL
dup
ldc "O"
bipush 14
invokespecial com/android/u/weibo/sina/business/comm/WeiboAPI$CAPITAL/<init>(Ljava/lang/String;I)V
putstatic com/android/u/weibo/sina/business/comm/WeiboAPI$CAPITAL/O Lcom/android/u/weibo/sina/business/comm/WeiboAPI$CAPITAL;
new com/android/u/weibo/sina/business/comm/WeiboAPI$CAPITAL
dup
ldc "P"
bipush 15
invokespecial com/android/u/weibo/sina/business/comm/WeiboAPI$CAPITAL/<init>(Ljava/lang/String;I)V
putstatic com/android/u/weibo/sina/business/comm/WeiboAPI$CAPITAL/P Lcom/android/u/weibo/sina/business/comm/WeiboAPI$CAPITAL;
new com/android/u/weibo/sina/business/comm/WeiboAPI$CAPITAL
dup
ldc "Q"
bipush 16
invokespecial com/android/u/weibo/sina/business/comm/WeiboAPI$CAPITAL/<init>(Ljava/lang/String;I)V
putstatic com/android/u/weibo/sina/business/comm/WeiboAPI$CAPITAL/Q Lcom/android/u/weibo/sina/business/comm/WeiboAPI$CAPITAL;
new com/android/u/weibo/sina/business/comm/WeiboAPI$CAPITAL
dup
ldc "R"
bipush 17
invokespecial com/android/u/weibo/sina/business/comm/WeiboAPI$CAPITAL/<init>(Ljava/lang/String;I)V
putstatic com/android/u/weibo/sina/business/comm/WeiboAPI$CAPITAL/R Lcom/android/u/weibo/sina/business/comm/WeiboAPI$CAPITAL;
new com/android/u/weibo/sina/business/comm/WeiboAPI$CAPITAL
dup
ldc "S"
bipush 18
invokespecial com/android/u/weibo/sina/business/comm/WeiboAPI$CAPITAL/<init>(Ljava/lang/String;I)V
putstatic com/android/u/weibo/sina/business/comm/WeiboAPI$CAPITAL/S Lcom/android/u/weibo/sina/business/comm/WeiboAPI$CAPITAL;
new com/android/u/weibo/sina/business/comm/WeiboAPI$CAPITAL
dup
ldc "T"
bipush 19
invokespecial com/android/u/weibo/sina/business/comm/WeiboAPI$CAPITAL/<init>(Ljava/lang/String;I)V
putstatic com/android/u/weibo/sina/business/comm/WeiboAPI$CAPITAL/T Lcom/android/u/weibo/sina/business/comm/WeiboAPI$CAPITAL;
new com/android/u/weibo/sina/business/comm/WeiboAPI$CAPITAL
dup
ldc "U"
bipush 20
invokespecial com/android/u/weibo/sina/business/comm/WeiboAPI$CAPITAL/<init>(Ljava/lang/String;I)V
putstatic com/android/u/weibo/sina/business/comm/WeiboAPI$CAPITAL/U Lcom/android/u/weibo/sina/business/comm/WeiboAPI$CAPITAL;
new com/android/u/weibo/sina/business/comm/WeiboAPI$CAPITAL
dup
ldc "V"
bipush 21
invokespecial com/android/u/weibo/sina/business/comm/WeiboAPI$CAPITAL/<init>(Ljava/lang/String;I)V
putstatic com/android/u/weibo/sina/business/comm/WeiboAPI$CAPITAL/V Lcom/android/u/weibo/sina/business/comm/WeiboAPI$CAPITAL;
new com/android/u/weibo/sina/business/comm/WeiboAPI$CAPITAL
dup
ldc "W"
bipush 22
invokespecial com/android/u/weibo/sina/business/comm/WeiboAPI$CAPITAL/<init>(Ljava/lang/String;I)V
putstatic com/android/u/weibo/sina/business/comm/WeiboAPI$CAPITAL/W Lcom/android/u/weibo/sina/business/comm/WeiboAPI$CAPITAL;
new com/android/u/weibo/sina/business/comm/WeiboAPI$CAPITAL
dup
ldc "X"
bipush 23
invokespecial com/android/u/weibo/sina/business/comm/WeiboAPI$CAPITAL/<init>(Ljava/lang/String;I)V
putstatic com/android/u/weibo/sina/business/comm/WeiboAPI$CAPITAL/X Lcom/android/u/weibo/sina/business/comm/WeiboAPI$CAPITAL;
new com/android/u/weibo/sina/business/comm/WeiboAPI$CAPITAL
dup
ldc "Y"
bipush 24
invokespecial com/android/u/weibo/sina/business/comm/WeiboAPI$CAPITAL/<init>(Ljava/lang/String;I)V
putstatic com/android/u/weibo/sina/business/comm/WeiboAPI$CAPITAL/Y Lcom/android/u/weibo/sina/business/comm/WeiboAPI$CAPITAL;
new com/android/u/weibo/sina/business/comm/WeiboAPI$CAPITAL
dup
ldc "Z"
bipush 25
invokespecial com/android/u/weibo/sina/business/comm/WeiboAPI$CAPITAL/<init>(Ljava/lang/String;I)V
putstatic com/android/u/weibo/sina/business/comm/WeiboAPI$CAPITAL/Z Lcom/android/u/weibo/sina/business/comm/WeiboAPI$CAPITAL;
bipush 26
anewarray com/android/u/weibo/sina/business/comm/WeiboAPI$CAPITAL
dup
iconst_0
getstatic com/android/u/weibo/sina/business/comm/WeiboAPI$CAPITAL/A Lcom/android/u/weibo/sina/business/comm/WeiboAPI$CAPITAL;
aastore
dup
iconst_1
getstatic com/android/u/weibo/sina/business/comm/WeiboAPI$CAPITAL/B Lcom/android/u/weibo/sina/business/comm/WeiboAPI$CAPITAL;
aastore
dup
iconst_2
getstatic com/android/u/weibo/sina/business/comm/WeiboAPI$CAPITAL/C Lcom/android/u/weibo/sina/business/comm/WeiboAPI$CAPITAL;
aastore
dup
iconst_3
getstatic com/android/u/weibo/sina/business/comm/WeiboAPI$CAPITAL/D Lcom/android/u/weibo/sina/business/comm/WeiboAPI$CAPITAL;
aastore
dup
iconst_4
getstatic com/android/u/weibo/sina/business/comm/WeiboAPI$CAPITAL/E Lcom/android/u/weibo/sina/business/comm/WeiboAPI$CAPITAL;
aastore
dup
iconst_5
getstatic com/android/u/weibo/sina/business/comm/WeiboAPI$CAPITAL/F Lcom/android/u/weibo/sina/business/comm/WeiboAPI$CAPITAL;
aastore
dup
bipush 6
getstatic com/android/u/weibo/sina/business/comm/WeiboAPI$CAPITAL/G Lcom/android/u/weibo/sina/business/comm/WeiboAPI$CAPITAL;
aastore
dup
bipush 7
getstatic com/android/u/weibo/sina/business/comm/WeiboAPI$CAPITAL/H Lcom/android/u/weibo/sina/business/comm/WeiboAPI$CAPITAL;
aastore
dup
bipush 8
getstatic com/android/u/weibo/sina/business/comm/WeiboAPI$CAPITAL/I Lcom/android/u/weibo/sina/business/comm/WeiboAPI$CAPITAL;
aastore
dup
bipush 9
getstatic com/android/u/weibo/sina/business/comm/WeiboAPI$CAPITAL/J Lcom/android/u/weibo/sina/business/comm/WeiboAPI$CAPITAL;
aastore
dup
bipush 10
getstatic com/android/u/weibo/sina/business/comm/WeiboAPI$CAPITAL/K Lcom/android/u/weibo/sina/business/comm/WeiboAPI$CAPITAL;
aastore
dup
bipush 11
getstatic com/android/u/weibo/sina/business/comm/WeiboAPI$CAPITAL/L Lcom/android/u/weibo/sina/business/comm/WeiboAPI$CAPITAL;
aastore
dup
bipush 12
getstatic com/android/u/weibo/sina/business/comm/WeiboAPI$CAPITAL/M Lcom/android/u/weibo/sina/business/comm/WeiboAPI$CAPITAL;
aastore
dup
bipush 13
getstatic com/android/u/weibo/sina/business/comm/WeiboAPI$CAPITAL/N Lcom/android/u/weibo/sina/business/comm/WeiboAPI$CAPITAL;
aastore
dup
bipush 14
getstatic com/android/u/weibo/sina/business/comm/WeiboAPI$CAPITAL/O Lcom/android/u/weibo/sina/business/comm/WeiboAPI$CAPITAL;
aastore
dup
bipush 15
getstatic com/android/u/weibo/sina/business/comm/WeiboAPI$CAPITAL/P Lcom/android/u/weibo/sina/business/comm/WeiboAPI$CAPITAL;
aastore
dup
bipush 16
getstatic com/android/u/weibo/sina/business/comm/WeiboAPI$CAPITAL/Q Lcom/android/u/weibo/sina/business/comm/WeiboAPI$CAPITAL;
aastore
dup
bipush 17
getstatic com/android/u/weibo/sina/business/comm/WeiboAPI$CAPITAL/R Lcom/android/u/weibo/sina/business/comm/WeiboAPI$CAPITAL;
aastore
dup
bipush 18
getstatic com/android/u/weibo/sina/business/comm/WeiboAPI$CAPITAL/S Lcom/android/u/weibo/sina/business/comm/WeiboAPI$CAPITAL;
aastore
dup
bipush 19
getstatic com/android/u/weibo/sina/business/comm/WeiboAPI$CAPITAL/T Lcom/android/u/weibo/sina/business/comm/WeiboAPI$CAPITAL;
aastore
dup
bipush 20
getstatic com/android/u/weibo/sina/business/comm/WeiboAPI$CAPITAL/U Lcom/android/u/weibo/sina/business/comm/WeiboAPI$CAPITAL;
aastore
dup
bipush 21
getstatic com/android/u/weibo/sina/business/comm/WeiboAPI$CAPITAL/V Lcom/android/u/weibo/sina/business/comm/WeiboAPI$CAPITAL;
aastore
dup
bipush 22
getstatic com/android/u/weibo/sina/business/comm/WeiboAPI$CAPITAL/W Lcom/android/u/weibo/sina/business/comm/WeiboAPI$CAPITAL;
aastore
dup
bipush 23
getstatic com/android/u/weibo/sina/business/comm/WeiboAPI$CAPITAL/X Lcom/android/u/weibo/sina/business/comm/WeiboAPI$CAPITAL;
aastore
dup
bipush 24
getstatic com/android/u/weibo/sina/business/comm/WeiboAPI$CAPITAL/Y Lcom/android/u/weibo/sina/business/comm/WeiboAPI$CAPITAL;
aastore
dup
bipush 25
getstatic com/android/u/weibo/sina/business/comm/WeiboAPI$CAPITAL/Z Lcom/android/u/weibo/sina/business/comm/WeiboAPI$CAPITAL;
aastore
putstatic com/android/u/weibo/sina/business/comm/WeiboAPI$CAPITAL/$VALUES [Lcom/android/u/weibo/sina/business/comm/WeiboAPI$CAPITAL;
return
.limit locals 0
.limit stack 4
.end method

.method private <init>(Ljava/lang/String;I)V
.signature "()V"
aload 0
aload 1
iload 2
invokespecial java/lang/Enum/<init>(Ljava/lang/String;I)V
return
.limit locals 3
.limit stack 3
.end method

.method public static valueOf(Ljava/lang/String;)Lcom/android/u/weibo/sina/business/comm/WeiboAPI$CAPITAL;
ldc com/android/u/weibo/sina/business/comm/WeiboAPI$CAPITAL
aload 0
invokestatic java/lang/Enum/valueOf(Ljava/lang/Class;Ljava/lang/String;)Ljava/lang/Enum;
checkcast com/android/u/weibo/sina/business/comm/WeiboAPI$CAPITAL
areturn
.limit locals 1
.limit stack 2
.end method

.method public static values()[Lcom/android/u/weibo/sina/business/comm/WeiboAPI$CAPITAL;
getstatic com/android/u/weibo/sina/business/comm/WeiboAPI$CAPITAL/$VALUES [Lcom/android/u/weibo/sina/business/comm/WeiboAPI$CAPITAL;
invokevirtual [Lcom/android/u/weibo/sina/business/comm/WeiboAPI$CAPITAL;/clone()Ljava/lang/Object;
checkcast [Lcom/android/u/weibo/sina/business/comm/WeiboAPI$CAPITAL;
areturn
.limit locals 0
.limit stack 1
.end method
