.bytecode 50.0
.class public final synchronized enum com/android/u/weibo/sina/business/comm/WeiboAPI$USER_CATEGORY
.super java/lang/Enum
.signature "Ljava/lang/Enum<Lcom/android/u/weibo/sina/business/comm/WeiboAPI$USER_CATEGORY;>;"
.inner class public static final enum USER_CATEGORY inner com/android/u/weibo/sina/business/comm/WeiboAPI$USER_CATEGORY outer com/android/u/weibo/sina/business/comm/WeiboAPI

.field private static final synthetic '$VALUES' [Lcom/android/u/weibo/sina/business/comm/WeiboAPI$USER_CATEGORY;

.field public static final enum 'DEFAULT' Lcom/android/u/weibo/sina/business/comm/WeiboAPI$USER_CATEGORY;

.field public static final enum 'cooking' Lcom/android/u/weibo/sina/business/comm/WeiboAPI$USER_CATEGORY;

.field public static final enum 'ent' Lcom/android/u/weibo/sina/business/comm/WeiboAPI$USER_CATEGORY;

.field public static final enum 'finance' Lcom/android/u/weibo/sina/business/comm/WeiboAPI$USER_CATEGORY;

.field public static final enum 'hk_famous' Lcom/android/u/weibo/sina/business/comm/WeiboAPI$USER_CATEGORY;

.field public static final enum 'medium' Lcom/android/u/weibo/sina/business/comm/WeiboAPI$USER_CATEGORY;

.field public static final enum 'model' Lcom/android/u/weibo/sina/business/comm/WeiboAPI$USER_CATEGORY;

.field public static final enum 'moderator' Lcom/android/u/weibo/sina/business/comm/WeiboAPI$USER_CATEGORY;

.field public static final enum 'singer' Lcom/android/u/weibo/sina/business/comm/WeiboAPI$USER_CATEGORY;

.field public static final enum 'sports' Lcom/android/u/weibo/sina/business/comm/WeiboAPI$USER_CATEGORY;

.field public static final enum 'stockplayer' Lcom/android/u/weibo/sina/business/comm/WeiboAPI$USER_CATEGORY;

.field public static final enum 'tech' Lcom/android/u/weibo/sina/business/comm/WeiboAPI$USER_CATEGORY;

.field public static final enum 'writer' Lcom/android/u/weibo/sina/business/comm/WeiboAPI$USER_CATEGORY;

.method static <clinit>()V
new com/android/u/weibo/sina/business/comm/WeiboAPI$USER_CATEGORY
dup
ldc "DEFAULT"
iconst_0
invokespecial com/android/u/weibo/sina/business/comm/WeiboAPI$USER_CATEGORY/<init>(Ljava/lang/String;I)V
putstatic com/android/u/weibo/sina/business/comm/WeiboAPI$USER_CATEGORY/DEFAULT Lcom/android/u/weibo/sina/business/comm/WeiboAPI$USER_CATEGORY;
new com/android/u/weibo/sina/business/comm/WeiboAPI$USER_CATEGORY
dup
ldc "ent"
iconst_1
invokespecial com/android/u/weibo/sina/business/comm/WeiboAPI$USER_CATEGORY/<init>(Ljava/lang/String;I)V
putstatic com/android/u/weibo/sina/business/comm/WeiboAPI$USER_CATEGORY/ent Lcom/android/u/weibo/sina/business/comm/WeiboAPI$USER_CATEGORY;
new com/android/u/weibo/sina/business/comm/WeiboAPI$USER_CATEGORY
dup
ldc "hk_famous"
iconst_2
invokespecial com/android/u/weibo/sina/business/comm/WeiboAPI$USER_CATEGORY/<init>(Ljava/lang/String;I)V
putstatic com/android/u/weibo/sina/business/comm/WeiboAPI$USER_CATEGORY/hk_famous Lcom/android/u/weibo/sina/business/comm/WeiboAPI$USER_CATEGORY;
new com/android/u/weibo/sina/business/comm/WeiboAPI$USER_CATEGORY
dup
ldc "model"
iconst_3
invokespecial com/android/u/weibo/sina/business/comm/WeiboAPI$USER_CATEGORY/<init>(Ljava/lang/String;I)V
putstatic com/android/u/weibo/sina/business/comm/WeiboAPI$USER_CATEGORY/model Lcom/android/u/weibo/sina/business/comm/WeiboAPI$USER_CATEGORY;
new com/android/u/weibo/sina/business/comm/WeiboAPI$USER_CATEGORY
dup
ldc "cooking"
iconst_4
invokespecial com/android/u/weibo/sina/business/comm/WeiboAPI$USER_CATEGORY/<init>(Ljava/lang/String;I)V
putstatic com/android/u/weibo/sina/business/comm/WeiboAPI$USER_CATEGORY/cooking Lcom/android/u/weibo/sina/business/comm/WeiboAPI$USER_CATEGORY;
new com/android/u/weibo/sina/business/comm/WeiboAPI$USER_CATEGORY
dup
ldc "sports"
iconst_5
invokespecial com/android/u/weibo/sina/business/comm/WeiboAPI$USER_CATEGORY/<init>(Ljava/lang/String;I)V
putstatic com/android/u/weibo/sina/business/comm/WeiboAPI$USER_CATEGORY/sports Lcom/android/u/weibo/sina/business/comm/WeiboAPI$USER_CATEGORY;
new com/android/u/weibo/sina/business/comm/WeiboAPI$USER_CATEGORY
dup
ldc "finance"
bipush 6
invokespecial com/android/u/weibo/sina/business/comm/WeiboAPI$USER_CATEGORY/<init>(Ljava/lang/String;I)V
putstatic com/android/u/weibo/sina/business/comm/WeiboAPI$USER_CATEGORY/finance Lcom/android/u/weibo/sina/business/comm/WeiboAPI$USER_CATEGORY;
new com/android/u/weibo/sina/business/comm/WeiboAPI$USER_CATEGORY
dup
ldc "tech"
bipush 7
invokespecial com/android/u/weibo/sina/business/comm/WeiboAPI$USER_CATEGORY/<init>(Ljava/lang/String;I)V
putstatic com/android/u/weibo/sina/business/comm/WeiboAPI$USER_CATEGORY/tech Lcom/android/u/weibo/sina/business/comm/WeiboAPI$USER_CATEGORY;
new com/android/u/weibo/sina/business/comm/WeiboAPI$USER_CATEGORY
dup
ldc "singer"
bipush 8
invokespecial com/android/u/weibo/sina/business/comm/WeiboAPI$USER_CATEGORY/<init>(Ljava/lang/String;I)V
putstatic com/android/u/weibo/sina/business/comm/WeiboAPI$USER_CATEGORY/singer Lcom/android/u/weibo/sina/business/comm/WeiboAPI$USER_CATEGORY;
new com/android/u/weibo/sina/business/comm/WeiboAPI$USER_CATEGORY
dup
ldc "writer"
bipush 9
invokespecial com/android/u/weibo/sina/business/comm/WeiboAPI$USER_CATEGORY/<init>(Ljava/lang/String;I)V
putstatic com/android/u/weibo/sina/business/comm/WeiboAPI$USER_CATEGORY/writer Lcom/android/u/weibo/sina/business/comm/WeiboAPI$USER_CATEGORY;
new com/android/u/weibo/sina/business/comm/WeiboAPI$USER_CATEGORY
dup
ldc "moderator"
bipush 10
invokespecial com/android/u/weibo/sina/business/comm/WeiboAPI$USER_CATEGORY/<init>(Ljava/lang/String;I)V
putstatic com/android/u/weibo/sina/business/comm/WeiboAPI$USER_CATEGORY/moderator Lcom/android/u/weibo/sina/business/comm/WeiboAPI$USER_CATEGORY;
new com/android/u/weibo/sina/business/comm/WeiboAPI$USER_CATEGORY
dup
ldc "medium"
bipush 11
invokespecial com/android/u/weibo/sina/business/comm/WeiboAPI$USER_CATEGORY/<init>(Ljava/lang/String;I)V
putstatic com/android/u/weibo/sina/business/comm/WeiboAPI$USER_CATEGORY/medium Lcom/android/u/weibo/sina/business/comm/WeiboAPI$USER_CATEGORY;
new com/android/u/weibo/sina/business/comm/WeiboAPI$USER_CATEGORY
dup
ldc "stockplayer"
bipush 12
invokespecial com/android/u/weibo/sina/business/comm/WeiboAPI$USER_CATEGORY/<init>(Ljava/lang/String;I)V
putstatic com/android/u/weibo/sina/business/comm/WeiboAPI$USER_CATEGORY/stockplayer Lcom/android/u/weibo/sina/business/comm/WeiboAPI$USER_CATEGORY;
bipush 13
anewarray com/android/u/weibo/sina/business/comm/WeiboAPI$USER_CATEGORY
dup
iconst_0
getstatic com/android/u/weibo/sina/business/comm/WeiboAPI$USER_CATEGORY/DEFAULT Lcom/android/u/weibo/sina/business/comm/WeiboAPI$USER_CATEGORY;
aastore
dup
iconst_1
getstatic com/android/u/weibo/sina/business/comm/WeiboAPI$USER_CATEGORY/ent Lcom/android/u/weibo/sina/business/comm/WeiboAPI$USER_CATEGORY;
aastore
dup
iconst_2
getstatic com/android/u/weibo/sina/business/comm/WeiboAPI$USER_CATEGORY/hk_famous Lcom/android/u/weibo/sina/business/comm/WeiboAPI$USER_CATEGORY;
aastore
dup
iconst_3
getstatic com/android/u/weibo/sina/business/comm/WeiboAPI$USER_CATEGORY/model Lcom/android/u/weibo/sina/business/comm/WeiboAPI$USER_CATEGORY;
aastore
dup
iconst_4
getstatic com/android/u/weibo/sina/business/comm/WeiboAPI$USER_CATEGORY/cooking Lcom/android/u/weibo/sina/business/comm/WeiboAPI$USER_CATEGORY;
aastore
dup
iconst_5
getstatic com/android/u/weibo/sina/business/comm/WeiboAPI$USER_CATEGORY/sports Lcom/android/u/weibo/sina/business/comm/WeiboAPI$USER_CATEGORY;
aastore
dup
bipush 6
getstatic com/android/u/weibo/sina/business/comm/WeiboAPI$USER_CATEGORY/finance Lcom/android/u/weibo/sina/business/comm/WeiboAPI$USER_CATEGORY;
aastore
dup
bipush 7
getstatic com/android/u/weibo/sina/business/comm/WeiboAPI$USER_CATEGORY/tech Lcom/android/u/weibo/sina/business/comm/WeiboAPI$USER_CATEGORY;
aastore
dup
bipush 8
getstatic com/android/u/weibo/sina/business/comm/WeiboAPI$USER_CATEGORY/singer Lcom/android/u/weibo/sina/business/comm/WeiboAPI$USER_CATEGORY;
aastore
dup
bipush 9
getstatic com/android/u/weibo/sina/business/comm/WeiboAPI$USER_CATEGORY/writer Lcom/android/u/weibo/sina/business/comm/WeiboAPI$USER_CATEGORY;
aastore
dup
bipush 10
getstatic com/android/u/weibo/sina/business/comm/WeiboAPI$USER_CATEGORY/moderator Lcom/android/u/weibo/sina/business/comm/WeiboAPI$USER_CATEGORY;
aastore
dup
bipush 11
getstatic com/android/u/weibo/sina/business/comm/WeiboAPI$USER_CATEGORY/medium Lcom/android/u/weibo/sina/business/comm/WeiboAPI$USER_CATEGORY;
aastore
dup
bipush 12
getstatic com/android/u/weibo/sina/business/comm/WeiboAPI$USER_CATEGORY/stockplayer Lcom/android/u/weibo/sina/business/comm/WeiboAPI$USER_CATEGORY;
aastore
putstatic com/android/u/weibo/sina/business/comm/WeiboAPI$USER_CATEGORY/$VALUES [Lcom/android/u/weibo/sina/business/comm/WeiboAPI$USER_CATEGORY;
return
.limit locals 0
.limit stack 4
.end method

.method private <init>(Ljava/lang/String;I)V
.signature "()V"
aload 0
aload 1
iload 2
invokespecial java/lang/Enum/<init>(Ljava/lang/String;I)V
return
.limit locals 3
.limit stack 3
.end method

.method public static valueOf(Ljava/lang/String;)Lcom/android/u/weibo/sina/business/comm/WeiboAPI$USER_CATEGORY;
ldc com/android/u/weibo/sina/business/comm/WeiboAPI$USER_CATEGORY
aload 0
invokestatic java/lang/Enum/valueOf(Ljava/lang/Class;Ljava/lang/String;)Ljava/lang/Enum;
checkcast com/android/u/weibo/sina/business/comm/WeiboAPI$USER_CATEGORY
areturn
.limit locals 1
.limit stack 2
.end method

.method public static values()[Lcom/android/u/weibo/sina/business/comm/WeiboAPI$USER_CATEGORY;
getstatic com/android/u/weibo/sina/business/comm/WeiboAPI$USER_CATEGORY/$VALUES [Lcom/android/u/weibo/sina/business/comm/WeiboAPI$USER_CATEGORY;
invokevirtual [Lcom/android/u/weibo/sina/business/comm/WeiboAPI$USER_CATEGORY;/clone()Ljava/lang/Object;
checkcast [Lcom/android/u/weibo/sina/business/comm/WeiboAPI$USER_CATEGORY;
areturn
.limit locals 0
.limit stack 1
.end method
