.bytecode 50.0
.class public final synchronized enum com/nd/android/u/cloud/readschoolinfo/SchoolInfoHandle
.super java/lang/Enum
.signature "Ljava/lang/Enum<Lcom/nd/android/u/cloud/readschoolinfo/SchoolInfoHandle;>;"

.field private static final synthetic 'ENUM$VALUES' [Lcom/nd/android/u/cloud/readschoolinfo/SchoolInfoHandle;

.field public static final enum 'INSTANCE' Lcom/nd/android/u/cloud/readschoolinfo/SchoolInfoHandle;

.field private 'helper' Lcom/nd/android/u/cloud/readschoolinfo/SchoolInfoDBHelper;

.method static <clinit>()V
new com/nd/android/u/cloud/readschoolinfo/SchoolInfoHandle
dup
ldc "INSTANCE"
iconst_0
invokespecial com/nd/android/u/cloud/readschoolinfo/SchoolInfoHandle/<init>(Ljava/lang/String;I)V
putstatic com/nd/android/u/cloud/readschoolinfo/SchoolInfoHandle/INSTANCE Lcom/nd/android/u/cloud/readschoolinfo/SchoolInfoHandle;
iconst_1
anewarray com/nd/android/u/cloud/readschoolinfo/SchoolInfoHandle
dup
iconst_0
getstatic com/nd/android/u/cloud/readschoolinfo/SchoolInfoHandle/INSTANCE Lcom/nd/android/u/cloud/readschoolinfo/SchoolInfoHandle;
aastore
putstatic com/nd/android/u/cloud/readschoolinfo/SchoolInfoHandle/ENUM$VALUES [Lcom/nd/android/u/cloud/readschoolinfo/SchoolInfoHandle;
return
.limit locals 0
.limit stack 4
.end method

.method private <init>(Ljava/lang/String;I)V
aload 0
aload 1
iload 2
invokespecial java/lang/Enum/<init>(Ljava/lang/String;I)V
return
.limit locals 3
.limit stack 3
.end method

.method public static valueOf(Ljava/lang/String;)Lcom/nd/android/u/cloud/readschoolinfo/SchoolInfoHandle;
ldc com/nd/android/u/cloud/readschoolinfo/SchoolInfoHandle
aload 0
invokestatic java/lang/Enum/valueOf(Ljava/lang/Class;Ljava/lang/String;)Ljava/lang/Enum;
checkcast com/nd/android/u/cloud/readschoolinfo/SchoolInfoHandle
areturn
.limit locals 1
.limit stack 2
.end method

.method public static values()[Lcom/nd/android/u/cloud/readschoolinfo/SchoolInfoHandle;
getstatic com/nd/android/u/cloud/readschoolinfo/SchoolInfoHandle/ENUM$VALUES [Lcom/nd/android/u/cloud/readschoolinfo/SchoolInfoHandle;
astore 1
aload 1
arraylength
istore 0
iload 0
anewarray com/nd/android/u/cloud/readschoolinfo/SchoolInfoHandle
astore 2
aload 1
iconst_0
aload 2
iconst_0
iload 0
invokestatic java/lang/System/arraycopy(Ljava/lang/Object;ILjava/lang/Object;II)V
aload 2
areturn
.limit locals 3
.limit stack 5
.end method

.method public getCollegeInfoByName(Ljava/lang/String;)Lcom/nd/android/u/cloud/readschoolinfo/CollegeInfo;
aload 0
getfield com/nd/android/u/cloud/readschoolinfo/SchoolInfoHandle/helper Lcom/nd/android/u/cloud/readschoolinfo/SchoolInfoDBHelper;
ifnonnull L0
new com/nd/android/u/cloud/readschoolinfo/CollegeInfo
dup
invokespecial com/nd/android/u/cloud/readschoolinfo/CollegeInfo/<init>()V
areturn
L0:
aload 0
getfield com/nd/android/u/cloud/readschoolinfo/SchoolInfoHandle/helper Lcom/nd/android/u/cloud/readschoolinfo/SchoolInfoDBHelper;
aload 1
invokevirtual com/nd/android/u/cloud/readschoolinfo/SchoolInfoDBHelper/queryCollegeByName(Ljava/lang/String;)Lcom/nd/android/u/cloud/readschoolinfo/CollegeInfo;
areturn
.limit locals 2
.limit stack 2
.end method

.method public getCollegeInfos()Ljava/util/List;
.signature "()Ljava/util/List<Lcom/nd/android/u/cloud/readschoolinfo/CollegeInfo;>;"
aload 0
getfield com/nd/android/u/cloud/readschoolinfo/SchoolInfoHandle/helper Lcom/nd/android/u/cloud/readschoolinfo/SchoolInfoDBHelper;
ifnonnull L0
new java/util/ArrayList
dup
invokespecial java/util/ArrayList/<init>()V
areturn
L0:
aload 0
getfield com/nd/android/u/cloud/readschoolinfo/SchoolInfoHandle/helper Lcom/nd/android/u/cloud/readschoolinfo/SchoolInfoDBHelper;
invokevirtual com/nd/android/u/cloud/readschoolinfo/SchoolInfoDBHelper/queryCollege()Ljava/util/List;
areturn
.limit locals 1
.limit stack 2
.end method

.method public getCollegeNameByCode(Ljava/lang/String;)Ljava/lang/String;
aload 0
getfield com/nd/android/u/cloud/readschoolinfo/SchoolInfoHandle/helper Lcom/nd/android/u/cloud/readschoolinfo/SchoolInfoDBHelper;
ifnull L0
aload 0
getfield com/nd/android/u/cloud/readschoolinfo/SchoolInfoHandle/helper Lcom/nd/android/u/cloud/readschoolinfo/SchoolInfoDBHelper;
aload 1
invokevirtual com/nd/android/u/cloud/readschoolinfo/SchoolInfoDBHelper/queryCollegeByCode(Ljava/lang/String;)Lcom/nd/android/u/cloud/readschoolinfo/CollegeInfo;
astore 1
aload 1
invokevirtual com/nd/android/u/cloud/readschoolinfo/CollegeInfo/isObjectValid()Z
ifeq L0
aload 1
invokevirtual com/nd/android/u/cloud/readschoolinfo/CollegeInfo/getUnitName()Ljava/lang/String;
areturn
L0:
ldc ""
areturn
.limit locals 2
.limit stack 2
.end method

.method public getSchoolInfoByName(Ljava/lang/String;)Lcom/nd/android/u/cloud/readschoolinfo/HighSchoolInfo;
aload 0
getfield com/nd/android/u/cloud/readschoolinfo/SchoolInfoHandle/helper Lcom/nd/android/u/cloud/readschoolinfo/SchoolInfoDBHelper;
ifnonnull L0
new com/nd/android/u/cloud/readschoolinfo/HighSchoolInfo
dup
invokespecial com/nd/android/u/cloud/readschoolinfo/HighSchoolInfo/<init>()V
areturn
L0:
aload 0
getfield com/nd/android/u/cloud/readschoolinfo/SchoolInfoHandle/helper Lcom/nd/android/u/cloud/readschoolinfo/SchoolInfoDBHelper;
aload 1
invokevirtual com/nd/android/u/cloud/readschoolinfo/SchoolInfoDBHelper/querySchoolByName(Ljava/lang/String;)Lcom/nd/android/u/cloud/readschoolinfo/HighSchoolInfo;
areturn
.limit locals 2
.limit stack 2
.end method

.method public getSchoolInfoBySubName(Ljava/lang/String;)Ljava/util/List;
.signature "(Ljava/lang/String;)Ljava/util/List<Lcom/nd/android/u/cloud/readschoolinfo/HighSchoolInfo;>;"
aload 0
getfield com/nd/android/u/cloud/readschoolinfo/SchoolInfoHandle/helper Lcom/nd/android/u/cloud/readschoolinfo/SchoolInfoDBHelper;
ifnonnull L0
new java/util/ArrayList
dup
invokespecial java/util/ArrayList/<init>()V
areturn
L0:
aload 0
getfield com/nd/android/u/cloud/readschoolinfo/SchoolInfoHandle/helper Lcom/nd/android/u/cloud/readschoolinfo/SchoolInfoDBHelper;
aload 1
invokevirtual com/nd/android/u/cloud/readschoolinfo/SchoolInfoDBHelper/querySchoolBySubName(Ljava/lang/String;)Ljava/util/List;
areturn
.limit locals 2
.limit stack 2
.end method

.method public getSchoolNameByCode(Ljava/lang/String;)Ljava/lang/String;
aload 0
getfield com/nd/android/u/cloud/readschoolinfo/SchoolInfoHandle/helper Lcom/nd/android/u/cloud/readschoolinfo/SchoolInfoDBHelper;
ifnull L0
aload 0
getfield com/nd/android/u/cloud/readschoolinfo/SchoolInfoHandle/helper Lcom/nd/android/u/cloud/readschoolinfo/SchoolInfoDBHelper;
aload 1
invokevirtual com/nd/android/u/cloud/readschoolinfo/SchoolInfoDBHelper/querySchoolByCode(Ljava/lang/String;)Lcom/nd/android/u/cloud/readschoolinfo/HighSchoolInfo;
astore 1
aload 1
invokevirtual com/nd/android/u/cloud/readschoolinfo/HighSchoolInfo/isObjectValid()Z
ifeq L0
aload 1
invokevirtual com/nd/android/u/cloud/readschoolinfo/HighSchoolInfo/getSchoolName()Ljava/lang/String;
areturn
L0:
ldc ""
areturn
.limit locals 2
.limit stack 2
.end method

.method public openDatabase(Landroid/content/Context;)V
.catch all from L0 to L1 using L2
.catch all from L3 to L4 using L2
aload 0
getfield com/nd/android/u/cloud/readschoolinfo/SchoolInfoHandle/helper Lcom/nd/android/u/cloud/readschoolinfo/SchoolInfoDBHelper;
ifnonnull L5
ldc com/nd/android/u/cloud/readschoolinfo/SchoolInfoDBHelper
monitorenter
L0:
aload 0
new com/nd/android/u/cloud/readschoolinfo/SchoolInfoDBHelper
dup
aload 1
invokespecial com/nd/android/u/cloud/readschoolinfo/SchoolInfoDBHelper/<init>(Landroid/content/Context;)V
putfield com/nd/android/u/cloud/readschoolinfo/SchoolInfoHandle/helper Lcom/nd/android/u/cloud/readschoolinfo/SchoolInfoDBHelper;
ldc com/nd/android/u/cloud/readschoolinfo/SchoolInfoDBHelper
monitorexit
L1:
return
L2:
astore 1
L3:
ldc com/nd/android/u/cloud/readschoolinfo/SchoolInfoDBHelper
monitorexit
L4:
aload 1
athrow
L5:
return
.limit locals 2
.limit stack 4
.end method
