.bytecode 50.0
.class synchronized com/android/u/weibo/weibo/utils/SSOBindWeibo$AuthDialogListener$1
.super java/lang/Object
.implements com/weibo/sdk/android/net/RequestListener
.enclosing method com/android/u/weibo/weibo/utils/SSOBindWeibo$AuthDialogListener/onComplete(Landroid/os/Bundle;)V
.inner class AuthDialogListener inner com/android/u/weibo/weibo/utils/SSOBindWeibo$AuthDialogListener outer com/android/u/weibo/weibo/utils/SSOBindWeibo
.inner class inner com/android/u/weibo/weibo/utils/SSOBindWeibo$AuthDialogListener$1

.field final synthetic 'this$1' Lcom/android/u/weibo/weibo/utils/SSOBindWeibo$AuthDialogListener;

.method <init>(Lcom/android/u/weibo/weibo/utils/SSOBindWeibo$AuthDialogListener;)V
aload 0
aload 1
putfield com/android/u/weibo/weibo/utils/SSOBindWeibo$AuthDialogListener$1/this$1 Lcom/android/u/weibo/weibo/utils/SSOBindWeibo$AuthDialogListener;
aload 0
invokespecial java/lang/Object/<init>()V
return
.limit locals 2
.limit stack 2
.end method

.method public onComplete(Ljava/lang/String;)V
.catch org/json/JSONException from L0 to L1 using L2
L0:
new org/json/JSONObject
dup
aload 1
invokespecial org/json/JSONObject/<init>(Ljava/lang/String;)V
astore 1
aload 0
getfield com/android/u/weibo/weibo/utils/SSOBindWeibo$AuthDialogListener$1/this$1 Lcom/android/u/weibo/weibo/utils/SSOBindWeibo$AuthDialogListener;
getfield com/android/u/weibo/weibo/utils/SSOBindWeibo$AuthDialogListener/this$0 Lcom/android/u/weibo/weibo/utils/SSOBindWeibo;
aload 1
ldc "screen_name"
invokevirtual org/json/JSONObject/getString(Ljava/lang/String;)Ljava/lang/String;
invokestatic com/android/u/weibo/weibo/utils/SSOBindWeibo/access$702(Lcom/android/u/weibo/weibo/utils/SSOBindWeibo;Ljava/lang/String;)Ljava/lang/String;
pop
aload 0
getfield com/android/u/weibo/weibo/utils/SSOBindWeibo$AuthDialogListener$1/this$1 Lcom/android/u/weibo/weibo/utils/SSOBindWeibo$AuthDialogListener;
getfield com/android/u/weibo/weibo/utils/SSOBindWeibo$AuthDialogListener/this$0 Lcom/android/u/weibo/weibo/utils/SSOBindWeibo;
aload 1
ldc "profile_image_url"
invokevirtual org/json/JSONObject/getString(Ljava/lang/String;)Ljava/lang/String;
invokestatic com/android/u/weibo/weibo/utils/SSOBindWeibo/access$802(Lcom/android/u/weibo/weibo/utils/SSOBindWeibo;Ljava/lang/String;)Ljava/lang/String;
pop
aload 0
getfield com/android/u/weibo/weibo/utils/SSOBindWeibo$AuthDialogListener$1/this$1 Lcom/android/u/weibo/weibo/utils/SSOBindWeibo$AuthDialogListener;
getfield com/android/u/weibo/weibo/utils/SSOBindWeibo$AuthDialogListener/this$0 Lcom/android/u/weibo/weibo/utils/SSOBindWeibo;
invokestatic com/android/u/weibo/weibo/utils/SSOBindWeibo/access$500(Lcom/android/u/weibo/weibo/utils/SSOBindWeibo;)Landroid/os/Handler;
iconst_1
invokevirtual android/os/Handler/sendEmptyMessage(I)Z
pop
L1:
return
L2:
astore 1
ldc "FirstLoginOptionData"
ldc "\u89e3\u6790JSON\u51fa\u9519"
invokestatic android/util/Log/i(Ljava/lang/String;Ljava/lang/String;)I
pop
aload 0
getfield com/android/u/weibo/weibo/utils/SSOBindWeibo$AuthDialogListener$1/this$1 Lcom/android/u/weibo/weibo/utils/SSOBindWeibo$AuthDialogListener;
getfield com/android/u/weibo/weibo/utils/SSOBindWeibo$AuthDialogListener/this$0 Lcom/android/u/weibo/weibo/utils/SSOBindWeibo;
invokestatic com/android/u/weibo/weibo/utils/SSOBindWeibo/access$500(Lcom/android/u/weibo/weibo/utils/SSOBindWeibo;)Landroid/os/Handler;
iconst_m1
invokevirtual android/os/Handler/sendEmptyMessage(I)Z
pop
return
.limit locals 2
.limit stack 3
.end method

.method public onComplete4binary(Ljava/io/ByteArrayOutputStream;)V
return
.limit locals 2
.limit stack 0
.end method

.method public onError(Lcom/weibo/sdk/android/WeiboException;)V
aload 0
getfield com/android/u/weibo/weibo/utils/SSOBindWeibo$AuthDialogListener$1/this$1 Lcom/android/u/weibo/weibo/utils/SSOBindWeibo$AuthDialogListener;
getfield com/android/u/weibo/weibo/utils/SSOBindWeibo$AuthDialogListener/this$0 Lcom/android/u/weibo/weibo/utils/SSOBindWeibo;
invokestatic com/android/u/weibo/weibo/utils/SSOBindWeibo/access$500(Lcom/android/u/weibo/weibo/utils/SSOBindWeibo;)Landroid/os/Handler;
iconst_m1
invokevirtual android/os/Handler/sendEmptyMessage(I)Z
pop
return
.limit locals 2
.limit stack 2
.end method

.method public onIOException(Ljava/io/IOException;)V
aload 0
getfield com/android/u/weibo/weibo/utils/SSOBindWeibo$AuthDialogListener$1/this$1 Lcom/android/u/weibo/weibo/utils/SSOBindWeibo$AuthDialogListener;
getfield com/android/u/weibo/weibo/utils/SSOBindWeibo$AuthDialogListener/this$0 Lcom/android/u/weibo/weibo/utils/SSOBindWeibo;
invokestatic com/android/u/weibo/weibo/utils/SSOBindWeibo/access$500(Lcom/android/u/weibo/weibo/utils/SSOBindWeibo;)Landroid/os/Handler;
iconst_m1
invokevirtual android/os/Handler/sendEmptyMessage(I)Z
pop
return
.limit locals 2
.limit stack 2
.end method
