.bytecode 50.0
.class synchronized com/android/u/weibo/weibo/utils/SSOBindWeibo$AuthDialogListener
.super java/lang/Object
.implements com/weibo/sdk/android/WeiboAuthListener
.inner class AuthDialogListener inner com/android/u/weibo/weibo/utils/SSOBindWeibo$AuthDialogListener outer com/android/u/weibo/weibo/utils/SSOBindWeibo
.inner class inner com/android/u/weibo/weibo/utils/SSOBindWeibo$AuthDialogListener$1

.field final synthetic 'this$0' Lcom/android/u/weibo/weibo/utils/SSOBindWeibo;

.method <init>(Lcom/android/u/weibo/weibo/utils/SSOBindWeibo;)V
aload 0
aload 1
putfield com/android/u/weibo/weibo/utils/SSOBindWeibo$AuthDialogListener/this$0 Lcom/android/u/weibo/weibo/utils/SSOBindWeibo;
aload 0
invokespecial java/lang/Object/<init>()V
return
.limit locals 2
.limit stack 2
.end method

.method private getValuesByBundle(Landroid/os/Bundle;)V
aload 0
getfield com/android/u/weibo/weibo/utils/SSOBindWeibo$AuthDialogListener/this$0 Lcom/android/u/weibo/weibo/utils/SSOBindWeibo;
aload 1
ldc "access_token"
invokevirtual android/os/Bundle/getString(Ljava/lang/String;)Ljava/lang/String;
invokestatic com/android/u/weibo/weibo/utils/SSOBindWeibo/access$002(Lcom/android/u/weibo/weibo/utils/SSOBindWeibo;Ljava/lang/String;)Ljava/lang/String;
pop
aload 0
getfield com/android/u/weibo/weibo/utils/SSOBindWeibo$AuthDialogListener/this$0 Lcom/android/u/weibo/weibo/utils/SSOBindWeibo;
aload 1
ldc "expires_in"
invokevirtual android/os/Bundle/getString(Ljava/lang/String;)Ljava/lang/String;
invokestatic com/android/u/weibo/weibo/utils/SSOBindWeibo/access$102(Lcom/android/u/weibo/weibo/utils/SSOBindWeibo;Ljava/lang/String;)Ljava/lang/String;
pop
aload 0
getfield com/android/u/weibo/weibo/utils/SSOBindWeibo$AuthDialogListener/this$0 Lcom/android/u/weibo/weibo/utils/SSOBindWeibo;
aload 1
ldc "uid"
invokevirtual android/os/Bundle/getString(Ljava/lang/String;)Ljava/lang/String;
invokestatic com/android/u/weibo/weibo/utils/SSOBindWeibo/access$202(Lcom/android/u/weibo/weibo/utils/SSOBindWeibo;Ljava/lang/String;)Ljava/lang/String;
pop
aload 0
getfield com/android/u/weibo/weibo/utils/SSOBindWeibo$AuthDialogListener/this$0 Lcom/android/u/weibo/weibo/utils/SSOBindWeibo;
aload 1
ldc "refresh_token"
invokevirtual android/os/Bundle/getString(Ljava/lang/String;)Ljava/lang/String;
invokestatic com/android/u/weibo/weibo/utils/SSOBindWeibo/access$302(Lcom/android/u/weibo/weibo/utils/SSOBindWeibo;Ljava/lang/String;)Ljava/lang/String;
pop
return
.limit locals 2
.limit stack 3
.end method

.method public onCancel()V
aload 0
getfield com/android/u/weibo/weibo/utils/SSOBindWeibo$AuthDialogListener/this$0 Lcom/android/u/weibo/weibo/utils/SSOBindWeibo;
invokestatic com/android/u/weibo/weibo/utils/SSOBindWeibo/access$500(Lcom/android/u/weibo/weibo/utils/SSOBindWeibo;)Landroid/os/Handler;
bipush -2
invokevirtual android/os/Handler/sendEmptyMessage(I)Z
pop
return
.limit locals 1
.limit stack 2
.end method

.method public onComplete(Landroid/os/Bundle;)V
.catch org/json/JSONException from L0 to L1 using L2
.catch org/json/JSONException from L1 to L3 using L2
.catch org/json/JSONException from L4 to L5 using L2
aload 1
ldc "code"
invokevirtual android/os/Bundle/getString(Ljava/lang/String;)Ljava/lang/String;
astore 2
new java/lang/StringBuilder
dup
invokespecial java/lang/StringBuilder/<init>()V
astore 3
aload 2
invokestatic android/text/TextUtils/isEmpty(Ljava/lang/CharSequence;)Z
ifne L6
aload 0
getfield com/android/u/weibo/weibo/utils/SSOBindWeibo$AuthDialogListener/this$0 Lcom/android/u/weibo/weibo/utils/SSOBindWeibo;
invokestatic com/android/u/weibo/weibo/utils/SSOBindWeibo/access$400(Lcom/android/u/weibo/weibo/utils/SSOBindWeibo;)Landroid/content/Context;
aload 2
aload 3
invokestatic com/android/u/weibo/sina/business/comm/LocalSinaSDK/getTokenByCode(Landroid/content/Context;Ljava/lang/String;Ljava/lang/StringBuilder;)V
aload 3
invokevirtual java/lang/StringBuilder/length()I
ifne L0
aload 0
getfield com/android/u/weibo/weibo/utils/SSOBindWeibo$AuthDialogListener/this$0 Lcom/android/u/weibo/weibo/utils/SSOBindWeibo;
invokestatic com/android/u/weibo/weibo/utils/SSOBindWeibo/access$500(Lcom/android/u/weibo/weibo/utils/SSOBindWeibo;)Landroid/os/Handler;
iconst_m1
invokevirtual android/os/Handler/sendEmptyMessage(I)Z
pop
L7:
return
L0:
new org/json/JSONObject
dup
aload 3
invokevirtual java/lang/StringBuilder/toString()Ljava/lang/String;
invokespecial org/json/JSONObject/<init>(Ljava/lang/String;)V
astore 1
aload 1
ldc "access_token"
invokevirtual org/json/JSONObject/has(Ljava/lang/String;)Z
ifeq L1
aload 1
ldc "expires_in"
invokevirtual org/json/JSONObject/has(Ljava/lang/String;)Z
ifeq L1
aload 1
ldc "uid"
invokevirtual org/json/JSONObject/has(Ljava/lang/String;)Z
ifne L4
L1:
aload 0
getfield com/android/u/weibo/weibo/utils/SSOBindWeibo$AuthDialogListener/this$0 Lcom/android/u/weibo/weibo/utils/SSOBindWeibo;
invokestatic com/android/u/weibo/weibo/utils/SSOBindWeibo/access$500(Lcom/android/u/weibo/weibo/utils/SSOBindWeibo;)Landroid/os/Handler;
iconst_m1
invokevirtual android/os/Handler/sendEmptyMessage(I)Z
pop
L3:
return
L2:
astore 1
aload 1
invokevirtual org/json/JSONException/printStackTrace()V
aload 0
getfield com/android/u/weibo/weibo/utils/SSOBindWeibo$AuthDialogListener/this$0 Lcom/android/u/weibo/weibo/utils/SSOBindWeibo;
invokestatic com/android/u/weibo/weibo/utils/SSOBindWeibo/access$500(Lcom/android/u/weibo/weibo/utils/SSOBindWeibo;)Landroid/os/Handler;
iconst_m1
invokevirtual android/os/Handler/sendEmptyMessage(I)Z
pop
return
L4:
aload 0
getfield com/android/u/weibo/weibo/utils/SSOBindWeibo$AuthDialogListener/this$0 Lcom/android/u/weibo/weibo/utils/SSOBindWeibo;
aload 1
ldc "access_token"
invokevirtual org/json/JSONObject/getString(Ljava/lang/String;)Ljava/lang/String;
invokestatic com/android/u/weibo/weibo/utils/SSOBindWeibo/access$002(Lcom/android/u/weibo/weibo/utils/SSOBindWeibo;Ljava/lang/String;)Ljava/lang/String;
pop
aload 0
getfield com/android/u/weibo/weibo/utils/SSOBindWeibo$AuthDialogListener/this$0 Lcom/android/u/weibo/weibo/utils/SSOBindWeibo;
aload 1
ldc "uid"
invokevirtual org/json/JSONObject/getString(Ljava/lang/String;)Ljava/lang/String;
invokestatic com/android/u/weibo/weibo/utils/SSOBindWeibo/access$202(Lcom/android/u/weibo/weibo/utils/SSOBindWeibo;Ljava/lang/String;)Ljava/lang/String;
pop
aload 0
getfield com/android/u/weibo/weibo/utils/SSOBindWeibo$AuthDialogListener/this$0 Lcom/android/u/weibo/weibo/utils/SSOBindWeibo;
aload 1
ldc "expires_in"
invokevirtual org/json/JSONObject/getString(Ljava/lang/String;)Ljava/lang/String;
invokestatic com/android/u/weibo/weibo/utils/SSOBindWeibo/access$102(Lcom/android/u/weibo/weibo/utils/SSOBindWeibo;Ljava/lang/String;)Ljava/lang/String;
pop
L5:
aload 0
getfield com/android/u/weibo/weibo/utils/SSOBindWeibo$AuthDialogListener/this$0 Lcom/android/u/weibo/weibo/utils/SSOBindWeibo;
invokestatic com/android/u/weibo/weibo/utils/SSOBindWeibo/access$000(Lcom/android/u/weibo/weibo/utils/SSOBindWeibo;)Ljava/lang/String;
invokestatic android/text/TextUtils/isEmpty(Ljava/lang/CharSequence;)Z
ifne L8
aload 0
getfield com/android/u/weibo/weibo/utils/SSOBindWeibo$AuthDialogListener/this$0 Lcom/android/u/weibo/weibo/utils/SSOBindWeibo;
invokestatic com/android/u/weibo/weibo/utils/SSOBindWeibo/access$100(Lcom/android/u/weibo/weibo/utils/SSOBindWeibo;)Ljava/lang/String;
invokestatic android/text/TextUtils/isEmpty(Ljava/lang/CharSequence;)Z
ifne L8
aload 0
getfield com/android/u/weibo/weibo/utils/SSOBindWeibo$AuthDialogListener/this$0 Lcom/android/u/weibo/weibo/utils/SSOBindWeibo;
invokestatic com/android/u/weibo/weibo/utils/SSOBindWeibo/access$200(Lcom/android/u/weibo/weibo/utils/SSOBindWeibo;)Ljava/lang/String;
invokestatic android/text/TextUtils/isEmpty(Ljava/lang/CharSequence;)Z
ifeq L9
L8:
aload 0
getfield com/android/u/weibo/weibo/utils/SSOBindWeibo$AuthDialogListener/this$0 Lcom/android/u/weibo/weibo/utils/SSOBindWeibo;
invokestatic com/android/u/weibo/weibo/utils/SSOBindWeibo/access$500(Lcom/android/u/weibo/weibo/utils/SSOBindWeibo;)Landroid/os/Handler;
iconst_m1
invokevirtual android/os/Handler/sendEmptyMessage(I)Z
pop
return
L6:
aload 0
aload 1
invokespecial com/android/u/weibo/weibo/utils/SSOBindWeibo$AuthDialogListener/getValuesByBundle(Landroid/os/Bundle;)V
goto L5
L9:
aload 0
getfield com/android/u/weibo/weibo/utils/SSOBindWeibo$AuthDialogListener/this$0 Lcom/android/u/weibo/weibo/utils/SSOBindWeibo;
invokestatic com/android/u/weibo/weibo/utils/SSOBindWeibo/access$500(Lcom/android/u/weibo/weibo/utils/SSOBindWeibo;)Landroid/os/Handler;
iconst_0
invokevirtual android/os/Handler/sendEmptyMessage(I)Z
pop
new com/weibo/sdk/android/Oauth2AccessToken
dup
aload 0
getfield com/android/u/weibo/weibo/utils/SSOBindWeibo$AuthDialogListener/this$0 Lcom/android/u/weibo/weibo/utils/SSOBindWeibo;
invokestatic com/android/u/weibo/weibo/utils/SSOBindWeibo/access$000(Lcom/android/u/weibo/weibo/utils/SSOBindWeibo;)Ljava/lang/String;
aload 0
getfield com/android/u/weibo/weibo/utils/SSOBindWeibo$AuthDialogListener/this$0 Lcom/android/u/weibo/weibo/utils/SSOBindWeibo;
invokestatic com/android/u/weibo/weibo/utils/SSOBindWeibo/access$100(Lcom/android/u/weibo/weibo/utils/SSOBindWeibo;)Ljava/lang/String;
invokespecial com/weibo/sdk/android/Oauth2AccessToken/<init>(Ljava/lang/String;Ljava/lang/String;)V
putstatic com/android/u/weibo/weibo/utils/SSOBindWeibo/m_accessToken Lcom/weibo/sdk/android/Oauth2AccessToken;
getstatic com/android/u/weibo/weibo/utils/SSOBindWeibo/m_accessToken Lcom/weibo/sdk/android/Oauth2AccessToken;
invokevirtual com/weibo/sdk/android/Oauth2AccessToken/isSessionValid()Z
ifeq L7
aload 0
getfield com/android/u/weibo/weibo/utils/SSOBindWeibo$AuthDialogListener/this$0 Lcom/android/u/weibo/weibo/utils/SSOBindWeibo;
getstatic com/android/u/weibo/weibo/utils/SSOBindWeibo/m_accessToken Lcom/weibo/sdk/android/Oauth2AccessToken;
invokevirtual com/weibo/sdk/android/Oauth2AccessToken/getExpiresTime()J
invokestatic com/android/u/weibo/weibo/utils/SSOBindWeibo/access$602(Lcom/android/u/weibo/weibo/utils/SSOBindWeibo;J)J
pop2
new com/android/u/weibo/sina/business/comm/UsersAPI
dup
getstatic com/android/u/weibo/weibo/utils/SSOBindWeibo/m_accessToken Lcom/weibo/sdk/android/Oauth2AccessToken;
invokespecial com/android/u/weibo/sina/business/comm/UsersAPI/<init>(Lcom/weibo/sdk/android/Oauth2AccessToken;)V
aload 0
getfield com/android/u/weibo/weibo/utils/SSOBindWeibo$AuthDialogListener/this$0 Lcom/android/u/weibo/weibo/utils/SSOBindWeibo;
invokestatic com/android/u/weibo/weibo/utils/SSOBindWeibo/access$200(Lcom/android/u/weibo/weibo/utils/SSOBindWeibo;)Ljava/lang/String;
invokestatic java/lang/Long/parseLong(Ljava/lang/String;)J
new com/android/u/weibo/weibo/utils/SSOBindWeibo$AuthDialogListener$1
dup
aload 0
invokespecial com/android/u/weibo/weibo/utils/SSOBindWeibo$AuthDialogListener$1/<init>(Lcom/android/u/weibo/weibo/utils/SSOBindWeibo$AuthDialogListener;)V
invokevirtual com/android/u/weibo/sina/business/comm/UsersAPI/show(JLcom/weibo/sdk/android/net/RequestListener;)V
return
.limit locals 4
.limit stack 6
.end method

.method public onError(Lcom/weibo/sdk/android/WeiboDialogError;)V
aload 0
getfield com/android/u/weibo/weibo/utils/SSOBindWeibo$AuthDialogListener/this$0 Lcom/android/u/weibo/weibo/utils/SSOBindWeibo;
invokestatic com/android/u/weibo/weibo/utils/SSOBindWeibo/access$500(Lcom/android/u/weibo/weibo/utils/SSOBindWeibo;)Landroid/os/Handler;
iconst_m1
invokevirtual android/os/Handler/sendEmptyMessage(I)Z
pop
return
.limit locals 2
.limit stack 2
.end method

.method public onWeiboException(Lcom/weibo/sdk/android/WeiboException;)V
aload 0
getfield com/android/u/weibo/weibo/utils/SSOBindWeibo$AuthDialogListener/this$0 Lcom/android/u/weibo/weibo/utils/SSOBindWeibo;
invokestatic com/android/u/weibo/weibo/utils/SSOBindWeibo/access$500(Lcom/android/u/weibo/weibo/utils/SSOBindWeibo;)Landroid/os/Handler;
iconst_m1
invokevirtual android/os/Handler/sendEmptyMessage(I)Z
pop
return
.limit locals 2
.limit stack 2
.end method
