.bytecode 50.0
.class synchronized com/nd/android/u/ui/dialog/AddFriendConfirmDialog$1
.super java/lang/Object
.implements android/widget/CompoundButton$OnCheckedChangeListener
.enclosing method com/nd/android/u/ui/dialog/AddFriendConfirmDialog
.inner class inner com/nd/android/u/ui/dialog/AddFriendConfirmDialog$1

.field final synthetic 'this$0' Lcom/nd/android/u/ui/dialog/AddFriendConfirmDialog;

.method <init>(Lcom/nd/android/u/ui/dialog/AddFriendConfirmDialog;)V
aload 0
aload 1
putfield com/nd/android/u/ui/dialog/AddFriendConfirmDialog$1/this$0 Lcom/nd/android/u/ui/dialog/AddFriendConfirmDialog;
aload 0
invokespecial java/lang/Object/<init>()V
return
.limit locals 2
.limit stack 2
.end method

.method public onCheckedChanged(Landroid/widget/CompoundButton;Z)V
aload 1
invokevirtual android/widget/CompoundButton/getId()I
getstatic com/nd/android/u/chat/R$id/addfriend_confirm_dialog_radio_agress I
if_icmpne L0
iload 2
ifeq L1
aload 0
getfield com/nd/android/u/ui/dialog/AddFriendConfirmDialog$1/this$0 Lcom/nd/android/u/ui/dialog/AddFriendConfirmDialog;
invokestatic com/nd/android/u/ui/dialog/AddFriendConfirmDialog/access$000(Lcom/nd/android/u/ui/dialog/AddFriendConfirmDialog;)Landroid/widget/EditText;
iconst_0
invokevirtual android/widget/EditText/setEnabled(Z)V
aload 0
getfield com/nd/android/u/ui/dialog/AddFriendConfirmDialog$1/this$0 Lcom/nd/android/u/ui/dialog/AddFriendConfirmDialog;
invokestatic com/nd/android/u/ui/dialog/AddFriendConfirmDialog/access$000(Lcom/nd/android/u/ui/dialog/AddFriendConfirmDialog;)Landroid/widget/EditText;
invokevirtual android/widget/EditText/getContext()Landroid/content/Context;
ldc "input_method"
invokevirtual android/content/Context/getSystemService(Ljava/lang/String;)Ljava/lang/Object;
checkcast android/view/inputmethod/InputMethodManager
aload 0
getfield com/nd/android/u/ui/dialog/AddFriendConfirmDialog$1/this$0 Lcom/nd/android/u/ui/dialog/AddFriendConfirmDialog;
invokestatic com/nd/android/u/ui/dialog/AddFriendConfirmDialog/access$000(Lcom/nd/android/u/ui/dialog/AddFriendConfirmDialog;)Landroid/widget/EditText;
invokevirtual android/widget/EditText/getWindowToken()Landroid/os/IBinder;
iconst_0
invokevirtual android/view/inputmethod/InputMethodManager/hideSoftInputFromWindow(Landroid/os/IBinder;I)Z
pop
L1:
return
L0:
aload 1
invokevirtual android/widget/CompoundButton/getId()I
getstatic com/nd/android/u/chat/R$id/addfriend_confirm_dialog_radio_reject I
if_icmpne L1
iload 2
ifeq L1
aload 0
getfield com/nd/android/u/ui/dialog/AddFriendConfirmDialog$1/this$0 Lcom/nd/android/u/ui/dialog/AddFriendConfirmDialog;
invokestatic com/nd/android/u/ui/dialog/AddFriendConfirmDialog/access$000(Lcom/nd/android/u/ui/dialog/AddFriendConfirmDialog;)Landroid/widget/EditText;
iconst_1
invokevirtual android/widget/EditText/setEnabled(Z)V
aload 0
getfield com/nd/android/u/ui/dialog/AddFriendConfirmDialog$1/this$0 Lcom/nd/android/u/ui/dialog/AddFriendConfirmDialog;
invokestatic com/nd/android/u/ui/dialog/AddFriendConfirmDialog/access$100(Lcom/nd/android/u/ui/dialog/AddFriendConfirmDialog;)Landroid/widget/TextView;
invokevirtual android/widget/TextView/requestFocus()Z
pop
aload 0
getfield com/nd/android/u/ui/dialog/AddFriendConfirmDialog$1/this$0 Lcom/nd/android/u/ui/dialog/AddFriendConfirmDialog;
invokestatic com/nd/android/u/ui/dialog/AddFriendConfirmDialog/access$000(Lcom/nd/android/u/ui/dialog/AddFriendConfirmDialog;)Landroid/widget/EditText;
invokevirtual android/widget/EditText/getContext()Landroid/content/Context;
ldc "input_method"
invokevirtual android/content/Context/getSystemService(Ljava/lang/String;)Ljava/lang/Object;
checkcast android/view/inputmethod/InputMethodManager
aload 0
getfield com/nd/android/u/ui/dialog/AddFriendConfirmDialog$1/this$0 Lcom/nd/android/u/ui/dialog/AddFriendConfirmDialog;
invokestatic com/nd/android/u/ui/dialog/AddFriendConfirmDialog/access$000(Lcom/nd/android/u/ui/dialog/AddFriendConfirmDialog;)Landroid/widget/EditText;
iconst_1
invokevirtual android/view/inputmethod/InputMethodManager/showSoftInput(Landroid/view/View;I)Z
pop
return
.limit locals 3
.limit stack 3
.end method
