.bytecode 50.0
.class synchronized com/android/u/weibo/flower/ui/widget/SurplusFlowerView$1
.super com/common/android/utils/task/genericTask/TaskAdapter
.enclosing method com/android/u/weibo/flower/ui/widget/SurplusFlowerView
.inner class inner com/android/u/weibo/flower/ui/widget/SurplusFlowerView$1

.field final synthetic 'this$0' Lcom/android/u/weibo/flower/ui/widget/SurplusFlowerView;

.method <init>(Lcom/android/u/weibo/flower/ui/widget/SurplusFlowerView;)V
aload 0
aload 1
putfield com/android/u/weibo/flower/ui/widget/SurplusFlowerView$1/this$0 Lcom/android/u/weibo/flower/ui/widget/SurplusFlowerView;
aload 0
invokespecial com/common/android/utils/task/genericTask/TaskAdapter/<init>()V
return
.limit locals 2
.limit stack 2
.end method

.method public onPostExecute(Lcom/common/android/utils/task/genericTask/GenericTask;Lcom/common/android/utils/task/genericTask/TaskResult;)V
aload 2
getstatic com/common/android/utils/task/genericTask/TaskResult/OK Lcom/common/android/utils/task/genericTask/TaskResult;
if_acmpne L0
aload 0
getfield com/android/u/weibo/flower/ui/widget/SurplusFlowerView$1/this$0 Lcom/android/u/weibo/flower/ui/widget/SurplusFlowerView;
iconst_1
invokestatic com/android/u/weibo/flower/ui/widget/SurplusFlowerView/access$602(Lcom/android/u/weibo/flower/ui/widget/SurplusFlowerView;Z)Z
pop
aload 0
getfield com/android/u/weibo/flower/ui/widget/SurplusFlowerView$1/this$0 Lcom/android/u/weibo/flower/ui/widget/SurplusFlowerView;
invokestatic com/android/u/weibo/flower/ui/widget/SurplusFlowerView/access$000(Lcom/android/u/weibo/flower/ui/widget/SurplusFlowerView;)Landroid/widget/LinearLayout;
bipush 8
invokevirtual android/widget/LinearLayout/setVisibility(I)V
aload 0
getfield com/android/u/weibo/flower/ui/widget/SurplusFlowerView$1/this$0 Lcom/android/u/weibo/flower/ui/widget/SurplusFlowerView;
invokestatic com/android/u/weibo/flower/ui/widget/SurplusFlowerView/access$100(Lcom/android/u/weibo/flower/ui/widget/SurplusFlowerView;)Landroid/widget/LinearLayout;
iconst_0
invokevirtual android/widget/LinearLayout/setVisibility(I)V
aload 0
getfield com/android/u/weibo/flower/ui/widget/SurplusFlowerView$1/this$0 Lcom/android/u/weibo/flower/ui/widget/SurplusFlowerView;
invokestatic com/android/u/weibo/flower/ui/widget/SurplusFlowerView/access$700(Lcom/android/u/weibo/flower/ui/widget/SurplusFlowerView;)Lcom/android/u/weibo/flower/ui/widget/FlowerMsgSetView;
iconst_0
invokevirtual com/android/u/weibo/flower/ui/widget/FlowerMsgSetView/setVisibility(I)V
aload 0
getfield com/android/u/weibo/flower/ui/widget/SurplusFlowerView$1/this$0 Lcom/android/u/weibo/flower/ui/widget/SurplusFlowerView;
invokestatic com/android/u/weibo/flower/ui/widget/SurplusFlowerView/access$800(Lcom/android/u/weibo/flower/ui/widget/SurplusFlowerView;)Lcom/android/u/weibo/flower/ui/widget/FlowerMsgSetView;
iconst_0
invokevirtual com/android/u/weibo/flower/ui/widget/FlowerMsgSetView/setVisibility(I)V
aload 0
getfield com/android/u/weibo/flower/ui/widget/SurplusFlowerView$1/this$0 Lcom/android/u/weibo/flower/ui/widget/SurplusFlowerView;
invokestatic com/android/u/weibo/flower/ui/widget/SurplusFlowerView/access$200(Lcom/android/u/weibo/flower/ui/widget/SurplusFlowerView;)Lcom/product/android/commonInterface/weibo/FlowerMessageInfo;
ifnonnull L1
aload 0
getfield com/android/u/weibo/flower/ui/widget/SurplusFlowerView$1/this$0 Lcom/android/u/weibo/flower/ui/widget/SurplusFlowerView;
aload 0
getfield com/android/u/weibo/flower/ui/widget/SurplusFlowerView$1/this$0 Lcom/android/u/weibo/flower/ui/widget/SurplusFlowerView;
invokestatic com/android/u/weibo/flower/ui/widget/SurplusFlowerView/access$300(Lcom/android/u/weibo/flower/ui/widget/SurplusFlowerView;)Landroid/content/Context;
invokestatic com/android/u/weibo/weibo/business/db/NdWeiboDatabase/getInstance(Landroid/content/Context;)Lcom/android/u/weibo/weibo/business/db/NdWeiboDatabase;
getstatic com/product/android/business/ApplicationVariable/INSTANCE Lcom/product/android/business/ApplicationVariable;
invokevirtual com/product/android/business/ApplicationVariable/getIUser()Lcom/product/android/business/login/IGetUserInfo;
invokeinterface com/product/android/business/login/IGetUserInfo/getOapUid()J 0
iconst_1
invokevirtual com/android/u/weibo/weibo/business/db/NdWeiboDatabase/getFlowerMessageInfo(JI)Lcom/product/android/commonInterface/weibo/FlowerMessageInfo;
invokestatic com/android/u/weibo/flower/ui/widget/SurplusFlowerView/access$202(Lcom/android/u/weibo/flower/ui/widget/SurplusFlowerView;Lcom/product/android/commonInterface/weibo/FlowerMessageInfo;)Lcom/product/android/commonInterface/weibo/FlowerMessageInfo;
pop
aload 0
getfield com/android/u/weibo/flower/ui/widget/SurplusFlowerView$1/this$0 Lcom/android/u/weibo/flower/ui/widget/SurplusFlowerView;
invokestatic com/android/u/weibo/flower/ui/widget/SurplusFlowerView/access$200(Lcom/android/u/weibo/flower/ui/widget/SurplusFlowerView;)Lcom/product/android/commonInterface/weibo/FlowerMessageInfo;
ifnonnull L1
aload 0
getfield com/android/u/weibo/flower/ui/widget/SurplusFlowerView$1/this$0 Lcom/android/u/weibo/flower/ui/widget/SurplusFlowerView;
new com/product/android/commonInterface/weibo/FlowerMessageInfo
dup
invokespecial com/product/android/commonInterface/weibo/FlowerMessageInfo/<init>()V
invokestatic com/android/u/weibo/flower/ui/widget/SurplusFlowerView/access$202(Lcom/android/u/weibo/flower/ui/widget/SurplusFlowerView;Lcom/product/android/commonInterface/weibo/FlowerMessageInfo;)Lcom/product/android/commonInterface/weibo/FlowerMessageInfo;
pop
aload 0
getfield com/android/u/weibo/flower/ui/widget/SurplusFlowerView$1/this$0 Lcom/android/u/weibo/flower/ui/widget/SurplusFlowerView;
invokestatic com/android/u/weibo/flower/ui/widget/SurplusFlowerView/access$200(Lcom/android/u/weibo/flower/ui/widget/SurplusFlowerView;)Lcom/product/android/commonInterface/weibo/FlowerMessageInfo;
getstatic com/product/android/business/ApplicationVariable/INSTANCE Lcom/product/android/business/ApplicationVariable;
invokevirtual com/product/android/business/ApplicationVariable/getIUser()Lcom/product/android/business/login/IGetUserInfo;
invokeinterface com/product/android/business/login/IGetUserInfo/getOapUid()J 0
invokevirtual com/product/android/commonInterface/weibo/FlowerMessageInfo/setUid(J)V
aload 0
getfield com/android/u/weibo/flower/ui/widget/SurplusFlowerView$1/this$0 Lcom/android/u/weibo/flower/ui/widget/SurplusFlowerView;
invokestatic com/android/u/weibo/flower/ui/widget/SurplusFlowerView/access$200(Lcom/android/u/weibo/flower/ui/widget/SurplusFlowerView;)Lcom/product/android/commonInterface/weibo/FlowerMessageInfo;
iconst_1
invokevirtual com/product/android/commonInterface/weibo/FlowerMessageInfo/setType(I)V
L1:
aload 0
getfield com/android/u/weibo/flower/ui/widget/SurplusFlowerView$1/this$0 Lcom/android/u/weibo/flower/ui/widget/SurplusFlowerView;
invokestatic com/android/u/weibo/flower/ui/widget/SurplusFlowerView/access$700(Lcom/android/u/weibo/flower/ui/widget/SurplusFlowerView;)Lcom/android/u/weibo/flower/ui/widget/FlowerMsgSetView;
aload 0
getfield com/android/u/weibo/flower/ui/widget/SurplusFlowerView$1/this$0 Lcom/android/u/weibo/flower/ui/widget/SurplusFlowerView;
invokestatic com/android/u/weibo/flower/ui/widget/SurplusFlowerView/access$200(Lcom/android/u/weibo/flower/ui/widget/SurplusFlowerView;)Lcom/product/android/commonInterface/weibo/FlowerMessageInfo;
invokevirtual com/android/u/weibo/flower/ui/widget/FlowerMsgSetView/setData(Lcom/product/android/commonInterface/weibo/FlowerMessageInfo;)V
aload 0
getfield com/android/u/weibo/flower/ui/widget/SurplusFlowerView$1/this$0 Lcom/android/u/weibo/flower/ui/widget/SurplusFlowerView;
invokestatic com/android/u/weibo/flower/ui/widget/SurplusFlowerView/access$400(Lcom/android/u/weibo/flower/ui/widget/SurplusFlowerView;)Lcom/product/android/commonInterface/weibo/FlowerMessageInfo;
ifnonnull L2
aload 0
getfield com/android/u/weibo/flower/ui/widget/SurplusFlowerView$1/this$0 Lcom/android/u/weibo/flower/ui/widget/SurplusFlowerView;
aload 0
getfield com/android/u/weibo/flower/ui/widget/SurplusFlowerView$1/this$0 Lcom/android/u/weibo/flower/ui/widget/SurplusFlowerView;
invokestatic com/android/u/weibo/flower/ui/widget/SurplusFlowerView/access$300(Lcom/android/u/weibo/flower/ui/widget/SurplusFlowerView;)Landroid/content/Context;
invokestatic com/android/u/weibo/weibo/business/db/NdWeiboDatabase/getInstance(Landroid/content/Context;)Lcom/android/u/weibo/weibo/business/db/NdWeiboDatabase;
getstatic com/product/android/business/ApplicationVariable/INSTANCE Lcom/product/android/business/ApplicationVariable;
invokevirtual com/product/android/business/ApplicationVariable/getIUser()Lcom/product/android/business/login/IGetUserInfo;
invokeinterface com/product/android/business/login/IGetUserInfo/getOapUid()J 0
iconst_2
invokevirtual com/android/u/weibo/weibo/business/db/NdWeiboDatabase/getFlowerMessageInfo(JI)Lcom/product/android/commonInterface/weibo/FlowerMessageInfo;
invokestatic com/android/u/weibo/flower/ui/widget/SurplusFlowerView/access$402(Lcom/android/u/weibo/flower/ui/widget/SurplusFlowerView;Lcom/product/android/commonInterface/weibo/FlowerMessageInfo;)Lcom/product/android/commonInterface/weibo/FlowerMessageInfo;
pop
aload 0
getfield com/android/u/weibo/flower/ui/widget/SurplusFlowerView$1/this$0 Lcom/android/u/weibo/flower/ui/widget/SurplusFlowerView;
invokestatic com/android/u/weibo/flower/ui/widget/SurplusFlowerView/access$400(Lcom/android/u/weibo/flower/ui/widget/SurplusFlowerView;)Lcom/product/android/commonInterface/weibo/FlowerMessageInfo;
ifnonnull L2
aload 0
getfield com/android/u/weibo/flower/ui/widget/SurplusFlowerView$1/this$0 Lcom/android/u/weibo/flower/ui/widget/SurplusFlowerView;
new com/product/android/commonInterface/weibo/FlowerMessageInfo
dup
invokespecial com/product/android/commonInterface/weibo/FlowerMessageInfo/<init>()V
invokestatic com/android/u/weibo/flower/ui/widget/SurplusFlowerView/access$402(Lcom/android/u/weibo/flower/ui/widget/SurplusFlowerView;Lcom/product/android/commonInterface/weibo/FlowerMessageInfo;)Lcom/product/android/commonInterface/weibo/FlowerMessageInfo;
pop
aload 0
getfield com/android/u/weibo/flower/ui/widget/SurplusFlowerView$1/this$0 Lcom/android/u/weibo/flower/ui/widget/SurplusFlowerView;
invokestatic com/android/u/weibo/flower/ui/widget/SurplusFlowerView/access$400(Lcom/android/u/weibo/flower/ui/widget/SurplusFlowerView;)Lcom/product/android/commonInterface/weibo/FlowerMessageInfo;
getstatic com/product/android/business/ApplicationVariable/INSTANCE Lcom/product/android/business/ApplicationVariable;
invokevirtual com/product/android/business/ApplicationVariable/getIUser()Lcom/product/android/business/login/IGetUserInfo;
invokeinterface com/product/android/business/login/IGetUserInfo/getOapUid()J 0
invokevirtual com/product/android/commonInterface/weibo/FlowerMessageInfo/setUid(J)V
aload 0
getfield com/android/u/weibo/flower/ui/widget/SurplusFlowerView$1/this$0 Lcom/android/u/weibo/flower/ui/widget/SurplusFlowerView;
invokestatic com/android/u/weibo/flower/ui/widget/SurplusFlowerView/access$400(Lcom/android/u/weibo/flower/ui/widget/SurplusFlowerView;)Lcom/product/android/commonInterface/weibo/FlowerMessageInfo;
iconst_2
invokevirtual com/product/android/commonInterface/weibo/FlowerMessageInfo/setType(I)V
L2:
aload 0
getfield com/android/u/weibo/flower/ui/widget/SurplusFlowerView$1/this$0 Lcom/android/u/weibo/flower/ui/widget/SurplusFlowerView;
invokestatic com/android/u/weibo/flower/ui/widget/SurplusFlowerView/access$800(Lcom/android/u/weibo/flower/ui/widget/SurplusFlowerView;)Lcom/android/u/weibo/flower/ui/widget/FlowerMsgSetView;
aload 0
getfield com/android/u/weibo/flower/ui/widget/SurplusFlowerView$1/this$0 Lcom/android/u/weibo/flower/ui/widget/SurplusFlowerView;
invokestatic com/android/u/weibo/flower/ui/widget/SurplusFlowerView/access$400(Lcom/android/u/weibo/flower/ui/widget/SurplusFlowerView;)Lcom/product/android/commonInterface/weibo/FlowerMessageInfo;
invokevirtual com/android/u/weibo/flower/ui/widget/FlowerMsgSetView/setData(Lcom/product/android/commonInterface/weibo/FlowerMessageInfo;)V
aload 0
getfield com/android/u/weibo/flower/ui/widget/SurplusFlowerView$1/this$0 Lcom/android/u/weibo/flower/ui/widget/SurplusFlowerView;
invokevirtual com/android/u/weibo/flower/ui/widget/SurplusFlowerView/setMyInfo()V
return
L0:
aload 0
getfield com/android/u/weibo/flower/ui/widget/SurplusFlowerView$1/this$0 Lcom/android/u/weibo/flower/ui/widget/SurplusFlowerView;
invokestatic com/android/u/weibo/flower/ui/widget/SurplusFlowerView/access$000(Lcom/android/u/weibo/flower/ui/widget/SurplusFlowerView;)Landroid/widget/LinearLayout;
iconst_0
invokevirtual android/widget/LinearLayout/setVisibility(I)V
aload 0
getfield com/android/u/weibo/flower/ui/widget/SurplusFlowerView$1/this$0 Lcom/android/u/weibo/flower/ui/widget/SurplusFlowerView;
invokestatic com/android/u/weibo/flower/ui/widget/SurplusFlowerView/access$100(Lcom/android/u/weibo/flower/ui/widget/SurplusFlowerView;)Landroid/widget/LinearLayout;
bipush 8
invokevirtual android/widget/LinearLayout/setVisibility(I)V
aload 0
getfield com/android/u/weibo/flower/ui/widget/SurplusFlowerView$1/this$0 Lcom/android/u/weibo/flower/ui/widget/SurplusFlowerView;
invokestatic com/android/u/weibo/flower/ui/widget/SurplusFlowerView/access$900(Lcom/android/u/weibo/flower/ui/widget/SurplusFlowerView;)Landroid/widget/ProgressBar;
bipush 8
invokevirtual android/widget/ProgressBar/setVisibility(I)V
aload 0
getfield com/android/u/weibo/flower/ui/widget/SurplusFlowerView$1/this$0 Lcom/android/u/weibo/flower/ui/widget/SurplusFlowerView;
invokestatic com/android/u/weibo/flower/ui/widget/SurplusFlowerView/access$1000(Lcom/android/u/weibo/flower/ui/widget/SurplusFlowerView;)Landroid/widget/TextView;
aload 0
getfield com/android/u/weibo/flower/ui/widget/SurplusFlowerView$1/this$0 Lcom/android/u/weibo/flower/ui/widget/SurplusFlowerView;
invokestatic com/android/u/weibo/flower/ui/widget/SurplusFlowerView/access$300(Lcom/android/u/weibo/flower/ui/widget/SurplusFlowerView;)Landroid/content/Context;
getstatic com/android/u/weibo/R$string/get_fail I
invokevirtual android/content/Context/getString(I)Ljava/lang/String;
invokevirtual android/widget/TextView/setText(Ljava/lang/CharSequence;)V
return
.limit locals 3
.limit stack 5
.end method
