.bytecode 50.0
.class synchronized com/nd/android/u/publicNumber/ui/activity/PspInformationActivity$4
.super android/os/Handler
.enclosing method com/nd/android/u/publicNumber/ui/activity/PspInformationActivity
.inner class inner com/nd/android/u/publicNumber/ui/activity/PspInformationActivity$4

.field final synthetic 'this$0' Lcom/nd/android/u/publicNumber/ui/activity/PspInformationActivity;

.method <init>(Lcom/nd/android/u/publicNumber/ui/activity/PspInformationActivity;)V
aload 0
aload 1
putfield com/nd/android/u/publicNumber/ui/activity/PspInformationActivity$4/this$0 Lcom/nd/android/u/publicNumber/ui/activity/PspInformationActivity;
aload 0
invokespecial android/os/Handler/<init>()V
return
.limit locals 2
.limit stack 2
.end method

.method public handleMessage(Landroid/os/Message;)V
aload 0
aload 1
invokespecial android/os/Handler/handleMessage(Landroid/os/Message;)V
aload 0
getfield com/nd/android/u/publicNumber/ui/activity/PspInformationActivity$4/this$0 Lcom/nd/android/u/publicNumber/ui/activity/PspInformationActivity;
invokestatic com/nd/android/u/publicNumber/ui/activity/PspInformationActivity/access$900(Lcom/nd/android/u/publicNumber/ui/activity/PspInformationActivity;)Lcom/nd/android/u/publicNumber/ui/dialog/PublicNumberOpDailog;
ifnull L0
aload 0
getfield com/nd/android/u/publicNumber/ui/activity/PspInformationActivity$4/this$0 Lcom/nd/android/u/publicNumber/ui/activity/PspInformationActivity;
invokestatic com/nd/android/u/publicNumber/ui/activity/PspInformationActivity/access$900(Lcom/nd/android/u/publicNumber/ui/activity/PspInformationActivity;)Lcom/nd/android/u/publicNumber/ui/dialog/PublicNumberOpDailog;
invokevirtual com/nd/android/u/publicNumber/ui/dialog/PublicNumberOpDailog/removeMessage()V
aload 0
getfield com/nd/android/u/publicNumber/ui/activity/PspInformationActivity$4/this$0 Lcom/nd/android/u/publicNumber/ui/activity/PspInformationActivity;
invokestatic com/nd/android/u/publicNumber/ui/activity/PspInformationActivity/access$900(Lcom/nd/android/u/publicNumber/ui/activity/PspInformationActivity;)Lcom/nd/android/u/publicNumber/ui/dialog/PublicNumberOpDailog;
invokevirtual com/nd/android/u/publicNumber/ui/dialog/PublicNumberOpDailog/dismissDialog()V
L0:
aload 1
getfield android/os/Message/arg1 I
sipush 200
if_icmpne L1
iconst_1
istore 2
L2:
aload 1
getfield android/os/Message/what I
lookupswitch
17 : L3
18 : L4
3001 : L5
default : L6
L6:
return
L1:
iconst_0
istore 2
goto L2
L3:
aload 0
getfield com/nd/android/u/publicNumber/ui/activity/PspInformationActivity$4/this$0 Lcom/nd/android/u/publicNumber/ui/activity/PspInformationActivity;
iload 2
invokestatic com/nd/android/u/publicNumber/ui/activity/PspInformationActivity/access$1000(Lcom/nd/android/u/publicNumber/ui/activity/PspInformationActivity;Z)V
return
L4:
aload 0
getfield com/nd/android/u/publicNumber/ui/activity/PspInformationActivity$4/this$0 Lcom/nd/android/u/publicNumber/ui/activity/PspInformationActivity;
iload 2
invokestatic com/nd/android/u/publicNumber/ui/activity/PspInformationActivity/access$1100(Lcom/nd/android/u/publicNumber/ui/activity/PspInformationActivity;Z)V
return
L5:
aload 1
getfield android/os/Message/obj Ljava/lang/Object;
ifnull L6
aload 1
getfield android/os/Message/obj Ljava/lang/Object;
instanceof com/nd/android/u/publicNumber/controller/bean/PublicNumberInfo
ifeq L6
aload 0
getfield com/nd/android/u/publicNumber/ui/activity/PspInformationActivity$4/this$0 Lcom/nd/android/u/publicNumber/ui/activity/PspInformationActivity;
aload 1
getfield android/os/Message/obj Ljava/lang/Object;
checkcast com/nd/android/u/publicNumber/controller/bean/PublicNumberInfo
invokestatic com/nd/android/u/publicNumber/ui/activity/PspInformationActivity/access$202(Lcom/nd/android/u/publicNumber/ui/activity/PspInformationActivity;Lcom/nd/android/u/publicNumber/controller/bean/PublicNumberInfo;)Lcom/nd/android/u/publicNumber/controller/bean/PublicNumberInfo;
pop
aload 0
getfield com/nd/android/u/publicNumber/ui/activity/PspInformationActivity$4/this$0 Lcom/nd/android/u/publicNumber/ui/activity/PspInformationActivity;
aload 0
getfield com/nd/android/u/publicNumber/ui/activity/PspInformationActivity$4/this$0 Lcom/nd/android/u/publicNumber/ui/activity/PspInformationActivity;
invokestatic com/nd/android/u/publicNumber/ui/activity/PspInformationActivity/access$200(Lcom/nd/android/u/publicNumber/ui/activity/PspInformationActivity;)Lcom/nd/android/u/publicNumber/controller/bean/PublicNumberInfo;
invokestatic com/nd/android/u/publicNumber/ui/activity/PspInformationActivity/access$1200(Lcom/nd/android/u/publicNumber/ui/activity/PspInformationActivity;Lcom/nd/android/u/publicNumber/controller/bean/PublicNumberInfo;)V
return
.limit locals 3
.limit stack 2
.end method
