.bytecode 50.0
.class synchronized com/nd/android/u/publicNumber/ui/activity/PspListFragment$6
.super java/lang/Object
.implements android/view/View$OnClickListener
.enclosing method com/nd/android/u/publicNumber/ui/activity/PspListFragment
.inner class inner com/nd/android/u/publicNumber/ui/activity/PspListFragment$6

.field final synthetic 'this$0' Lcom/nd/android/u/publicNumber/ui/activity/PspListFragment;

.method <init>(Lcom/nd/android/u/publicNumber/ui/activity/PspListFragment;)V
aload 0
aload 1
putfield com/nd/android/u/publicNumber/ui/activity/PspListFragment$6/this$0 Lcom/nd/android/u/publicNumber/ui/activity/PspListFragment;
aload 0
invokespecial java/lang/Object/<init>()V
return
.limit locals 2
.limit stack 2
.end method

.method public onClick(Landroid/view/View;)V
aload 0
getfield com/nd/android/u/publicNumber/ui/activity/PspListFragment$6/this$0 Lcom/nd/android/u/publicNumber/ui/activity/PspListFragment;
invokestatic com/nd/android/u/publicNumber/ui/activity/PspListFragment/access$000(Lcom/nd/android/u/publicNumber/ui/activity/PspListFragment;)Lcom/nd/android/u/publicNumber/ui/dialog/PublicNumberOpDailog;
ifnull L0
aload 0
getfield com/nd/android/u/publicNumber/ui/activity/PspListFragment$6/this$0 Lcom/nd/android/u/publicNumber/ui/activity/PspListFragment;
invokestatic com/nd/android/u/publicNumber/ui/activity/PspListFragment/access$000(Lcom/nd/android/u/publicNumber/ui/activity/PspListFragment;)Lcom/nd/android/u/publicNumber/ui/dialog/PublicNumberOpDailog;
invokevirtual com/nd/android/u/publicNumber/ui/dialog/PublicNumberOpDailog/dismissDialog()V
L0:
aload 0
getfield com/nd/android/u/publicNumber/ui/activity/PspListFragment$6/this$0 Lcom/nd/android/u/publicNumber/ui/activity/PspListFragment;
invokestatic com/nd/android/u/publicNumber/ui/activity/PspListFragment/access$1900(Lcom/nd/android/u/publicNumber/ui/activity/PspListFragment;)Lcom/nd/android/u/publicNumber/controller/bean/PublicNumberInfo;
getfield com/nd/android/u/publicNumber/controller/bean/PublicNumberInfo/name Ljava/lang/String;
invokestatic android/text/TextUtils/isEmpty(Ljava/lang/CharSequence;)Z
ifne L1
aload 0
getfield com/nd/android/u/publicNumber/ui/activity/PspListFragment$6/this$0 Lcom/nd/android/u/publicNumber/ui/activity/PspListFragment;
new com/nd/android/u/publicNumber/ui/dialog/PublicNumberOpDailog
dup
aload 0
getfield com/nd/android/u/publicNumber/ui/activity/PspListFragment$6/this$0 Lcom/nd/android/u/publicNumber/ui/activity/PspListFragment;
invokevirtual com/nd/android/u/publicNumber/ui/activity/PspListFragment/getActivity()Landroid/support/v4/app/FragmentActivity;
aload 0
getfield com/nd/android/u/publicNumber/ui/activity/PspListFragment$6/this$0 Lcom/nd/android/u/publicNumber/ui/activity/PspListFragment;
invokestatic com/nd/android/u/publicNumber/ui/activity/PspListFragment/access$1900(Lcom/nd/android/u/publicNumber/ui/activity/PspListFragment;)Lcom/nd/android/u/publicNumber/controller/bean/PublicNumberInfo;
getfield com/nd/android/u/publicNumber/controller/bean/PublicNumberInfo/pspid Ljava/lang/String;
aload 0
getfield com/nd/android/u/publicNumber/ui/activity/PspListFragment$6/this$0 Lcom/nd/android/u/publicNumber/ui/activity/PspListFragment;
invokestatic com/nd/android/u/publicNumber/ui/activity/PspListFragment/access$1900(Lcom/nd/android/u/publicNumber/ui/activity/PspListFragment;)Lcom/nd/android/u/publicNumber/controller/bean/PublicNumberInfo;
getfield com/nd/android/u/publicNumber/controller/bean/PublicNumberInfo/name Ljava/lang/String;
iconst_0
invokespecial com/nd/android/u/publicNumber/ui/dialog/PublicNumberOpDailog/<init>(Landroid/content/Context;Ljava/lang/String;Ljava/lang/String;I)V
invokestatic com/nd/android/u/publicNumber/ui/activity/PspListFragment/access$002(Lcom/nd/android/u/publicNumber/ui/activity/PspListFragment;Lcom/nd/android/u/publicNumber/ui/dialog/PublicNumberOpDailog;)Lcom/nd/android/u/publicNumber/ui/dialog/PublicNumberOpDailog;
pop
L2:
aload 0
getfield com/nd/android/u/publicNumber/ui/activity/PspListFragment$6/this$0 Lcom/nd/android/u/publicNumber/ui/activity/PspListFragment;
invokestatic com/nd/android/u/publicNumber/ui/activity/PspListFragment/access$000(Lcom/nd/android/u/publicNumber/ui/activity/PspListFragment;)Lcom/nd/android/u/publicNumber/ui/dialog/PublicNumberOpDailog;
invokevirtual com/nd/android/u/publicNumber/ui/dialog/PublicNumberOpDailog/show()V
aload 0
getfield com/nd/android/u/publicNumber/ui/activity/PspListFragment$6/this$0 Lcom/nd/android/u/publicNumber/ui/activity/PspListFragment;
invokestatic com/nd/android/u/publicNumber/ui/activity/PspListFragment/access$2000(Lcom/nd/android/u/publicNumber/ui/activity/PspListFragment;)Lcom/nd/android/u/publicNumber/ui/widget/PspPopDel;
invokevirtual com/nd/android/u/publicNumber/ui/widget/PspPopDel/dismiss()V
return
L1:
aload 0
getfield com/nd/android/u/publicNumber/ui/activity/PspListFragment$6/this$0 Lcom/nd/android/u/publicNumber/ui/activity/PspListFragment;
new com/nd/android/u/publicNumber/ui/dialog/PublicNumberOpDailog
dup
aload 0
getfield com/nd/android/u/publicNumber/ui/activity/PspListFragment$6/this$0 Lcom/nd/android/u/publicNumber/ui/activity/PspListFragment;
invokevirtual com/nd/android/u/publicNumber/ui/activity/PspListFragment/getActivity()Landroid/support/v4/app/FragmentActivity;
aload 0
getfield com/nd/android/u/publicNumber/ui/activity/PspListFragment$6/this$0 Lcom/nd/android/u/publicNumber/ui/activity/PspListFragment;
invokestatic com/nd/android/u/publicNumber/ui/activity/PspListFragment/access$1900(Lcom/nd/android/u/publicNumber/ui/activity/PspListFragment;)Lcom/nd/android/u/publicNumber/controller/bean/PublicNumberInfo;
getfield com/nd/android/u/publicNumber/controller/bean/PublicNumberInfo/pspid Ljava/lang/String;
aload 0
getfield com/nd/android/u/publicNumber/ui/activity/PspListFragment$6/this$0 Lcom/nd/android/u/publicNumber/ui/activity/PspListFragment;
invokestatic com/nd/android/u/publicNumber/ui/activity/PspListFragment/access$1900(Lcom/nd/android/u/publicNumber/ui/activity/PspListFragment;)Lcom/nd/android/u/publicNumber/controller/bean/PublicNumberInfo;
getfield com/nd/android/u/publicNumber/controller/bean/PublicNumberInfo/pspid Ljava/lang/String;
iconst_0
invokespecial com/nd/android/u/publicNumber/ui/dialog/PublicNumberOpDailog/<init>(Landroid/content/Context;Ljava/lang/String;Ljava/lang/String;I)V
invokestatic com/nd/android/u/publicNumber/ui/activity/PspListFragment/access$002(Lcom/nd/android/u/publicNumber/ui/activity/PspListFragment;Lcom/nd/android/u/publicNumber/ui/dialog/PublicNumberOpDailog;)Lcom/nd/android/u/publicNumber/ui/dialog/PublicNumberOpDailog;
pop
goto L2
.limit locals 2
.limit stack 7
.end method
