.bytecode 50.0
.class final synchronized com/flurry/android/aa
.super java/lang/Object

.field private 'a' Landroid/content/Context;

.field private 'b' Lcom/flurry/android/v;

.field private 'c' Lcom/flurry/android/a;

.field private volatile 'd' J

.field private 'e' Lcom/flurry/android/ag;

.field private 'f' Lcom/flurry/android/ag;

.field private 'g' Ljava/util/Map;

.field private 'h' Ljava/util/Map;

.field private 'i' Ljava/util/Map;

.field private 'j' Ljava/util/Map;

.field private volatile 'k' Z

.method <init>()V
aload 0
invokespecial java/lang/Object/<init>()V
aload 0
new com/flurry/android/ag
dup
bipush 100
invokespecial com/flurry/android/ag/<init>(I)V
putfield com/flurry/android/aa/e Lcom/flurry/android/ag;
aload 0
new com/flurry/android/ag
dup
bipush 100
invokespecial com/flurry/android/ag/<init>(I)V
putfield com/flurry/android/aa/f Lcom/flurry/android/ag;
aload 0
new java/util/HashMap
dup
invokespecial java/util/HashMap/<init>()V
putfield com/flurry/android/aa/g Ljava/util/Map;
aload 0
new java/util/HashMap
dup
invokespecial java/util/HashMap/<init>()V
putfield com/flurry/android/aa/h Ljava/util/Map;
aload 0
new java/util/HashMap
dup
invokespecial java/util/HashMap/<init>()V
putfield com/flurry/android/aa/i Ljava/util/Map;
aload 0
new java/util/HashMap
dup
invokespecial java/util/HashMap/<init>()V
putfield com/flurry/android/aa/j Ljava/util/Map;
return
.limit locals 1
.limit stack 4
.end method

.method private a(B)Lcom/flurry/android/c;
.catch all from L0 to L1 using L2
aload 0
monitorenter
L0:
aload 0
getfield com/flurry/android/aa/i Ljava/util/Map;
iload 1
invokestatic java/lang/Byte/valueOf(B)Ljava/lang/Byte;
invokeinterface java/util/Map/get(Ljava/lang/Object;)Ljava/lang/Object; 1
checkcast com/flurry/android/c
astore 2
L1:
aload 0
monitorexit
aload 2
areturn
L2:
astore 2
aload 0
monitorexit
aload 2
athrow
.limit locals 3
.limit stack 2
.end method

.method private a(I)V
aload 0
getfield com/flurry/android/aa/g Ljava/util/Map;
invokeinterface java/util/Map/isEmpty()Z 0
ifne L0
iconst_1
istore 2
L1:
aload 0
iload 2
putfield com/flurry/android/aa/k Z
aload 0
getfield com/flurry/android/aa/k Z
ifeq L2
aload 0
getfield com/flurry/android/aa/b Lcom/flurry/android/v;
iload 1
invokevirtual com/flurry/android/v/a(I)V
L2:
return
L0:
iconst_0
istore 2
goto L1
.limit locals 3
.limit stack 2
.end method

.method private a(Ljava/io/DataInputStream;)V
iconst_0
istore 6
ldc "FlurryAgent"
ldc "Reading cache"
invokestatic com/flurry/android/ai/a(Ljava/lang/String;Ljava/lang/String;)I
pop
aload 1
invokevirtual java/io/DataInputStream/readUnsignedShort()I
iconst_2
if_icmpeq L0
return
L0:
aload 0
aload 1
invokevirtual java/io/DataInputStream/readLong()J
putfield com/flurry/android/aa/d J
aload 1
invokevirtual java/io/DataInputStream/readUnsignedShort()I
istore 5
aload 0
new com/flurry/android/ag
dup
bipush 100
invokespecial com/flurry/android/ag/<init>(I)V
putfield com/flurry/android/aa/e Lcom/flurry/android/ag;
iconst_0
istore 4
L1:
iload 4
iload 5
if_icmpge L2
aload 1
invokevirtual java/io/DataInputStream/readLong()J
lstore 9
new com/flurry/android/AdImage
dup
invokespecial com/flurry/android/AdImage/<init>()V
astore 11
aload 11
aload 1
invokevirtual com/flurry/android/AdImage/a(Ljava/io/DataInput;)V
aload 0
getfield com/flurry/android/aa/e Lcom/flurry/android/ag;
lload 9
invokestatic java/lang/Long/valueOf(J)Ljava/lang/Long;
aload 11
invokevirtual com/flurry/android/ag/a(Ljava/lang/Object;Ljava/lang/Object;)V
iload 4
iconst_1
iadd
istore 4
goto L1
L2:
aload 1
invokevirtual java/io/DataInputStream/readUnsignedShort()I
istore 5
aload 0
new com/flurry/android/ag
dup
bipush 100
invokespecial com/flurry/android/ag/<init>(I)V
putfield com/flurry/android/aa/f Lcom/flurry/android/ag;
iconst_0
istore 4
L3:
iload 4
iload 5
if_icmpge L4
aload 1
invokevirtual java/io/DataInputStream/readLong()J
lstore 9
new com/flurry/android/am
dup
invokespecial com/flurry/android/am/<init>()V
astore 11
aload 1
invokeinterface java/io/DataInput/readBoolean()Z 0
ifeq L5
aload 11
aload 1
invokeinterface java/io/DataInput/readUTF()Ljava/lang/String; 0
putfield com/flurry/android/am/a Ljava/lang/String;
L5:
aload 1
invokeinterface java/io/DataInput/readBoolean()Z 0
ifeq L6
aload 11
aload 1
invokeinterface java/io/DataInput/readUTF()Ljava/lang/String; 0
putfield com/flurry/android/am/b Ljava/lang/String;
L6:
aload 11
aload 1
invokeinterface java/io/DataInput/readInt()I 0
putfield com/flurry/android/am/c I
aload 0
getfield com/flurry/android/aa/f Lcom/flurry/android/ag;
lload 9
invokestatic java/lang/Long/valueOf(J)Ljava/lang/Long;
aload 11
invokevirtual com/flurry/android/ag/a(Ljava/lang/Object;Ljava/lang/Object;)V
iload 4
iconst_1
iadd
istore 4
goto L3
L4:
aload 1
invokevirtual java/io/DataInputStream/readUnsignedShort()I
istore 5
aload 0
new java/util/HashMap
dup
iload 5
invokespecial java/util/HashMap/<init>(I)V
putfield com/flurry/android/aa/h Ljava/util/Map;
iconst_0
istore 4
L7:
iload 4
iload 5
if_icmpge L8
aload 1
invokevirtual java/io/DataInputStream/readUTF()Ljava/lang/String;
astore 11
new com/flurry/android/e
dup
aload 1
invokespecial com/flurry/android/e/<init>(Ljava/io/DataInput;)V
astore 12
aload 0
getfield com/flurry/android/aa/h Ljava/util/Map;
aload 11
aload 12
invokeinterface java/util/Map/put(Ljava/lang/Object;Ljava/lang/Object;)Ljava/lang/Object; 2
pop
iload 4
iconst_1
iadd
istore 4
goto L7
L8:
aload 1
invokevirtual java/io/DataInputStream/readUnsignedShort()I
istore 7
aload 0
new java/util/HashMap
dup
iload 7
invokespecial java/util/HashMap/<init>(I)V
putfield com/flurry/android/aa/g Ljava/util/Map;
iconst_0
istore 4
L9:
iload 4
iload 7
if_icmpge L10
aload 1
invokevirtual java/io/DataInputStream/readUTF()Ljava/lang/String;
astore 11
aload 1
invokevirtual java/io/DataInputStream/readUnsignedShort()I
istore 8
iload 8
anewarray com/flurry/android/w
astore 12
iconst_0
istore 5
L11:
iload 5
iload 8
if_icmpge L12
new com/flurry/android/w
dup
invokespecial com/flurry/android/w/<init>()V
astore 13
aload 13
aload 1
invokevirtual com/flurry/android/w/a(Ljava/io/DataInput;)V
aload 12
iload 5
aload 13
aastore
iload 5
iconst_1
iadd
istore 5
goto L11
L12:
aload 0
getfield com/flurry/android/aa/g Ljava/util/Map;
aload 11
aload 12
invokeinterface java/util/Map/put(Ljava/lang/Object;Ljava/lang/Object;)Ljava/lang/Object; 2
pop
iload 4
iconst_1
iadd
istore 4
goto L9
L10:
aload 1
invokevirtual java/io/DataInputStream/readUnsignedShort()I
istore 5
aload 0
new java/util/HashMap
dup
invokespecial java/util/HashMap/<init>()V
putfield com/flurry/android/aa/i Ljava/util/Map;
iconst_0
istore 4
L13:
iload 4
iload 5
if_icmpge L14
aload 1
invokevirtual java/io/DataInputStream/readByte()B
istore 2
new com/flurry/android/c
dup
invokespecial com/flurry/android/c/<init>()V
astore 11
aload 11
aload 1
invokevirtual com/flurry/android/c/b(Ljava/io/DataInput;)V
aload 0
getfield com/flurry/android/aa/i Ljava/util/Map;
iload 2
invokestatic java/lang/Byte/valueOf(B)Ljava/lang/Byte;
aload 11
invokeinterface java/util/Map/put(Ljava/lang/Object;Ljava/lang/Object;)Ljava/lang/Object; 2
pop
iload 4
iconst_1
iadd
istore 4
goto L13
L14:
aload 1
invokevirtual java/io/DataInputStream/readUnsignedShort()I
istore 5
aload 0
new java/util/HashMap
dup
iload 5
invokespecial java/util/HashMap/<init>(I)V
putfield com/flurry/android/aa/j Ljava/util/Map;
iload 6
istore 4
L15:
iload 4
iload 5
if_icmpge L16
aload 1
invokevirtual java/io/DataInputStream/readShort()S
istore 3
aload 1
invokevirtual java/io/DataInputStream/readLong()J
lstore 9
aload 0
getfield com/flurry/android/aa/j Ljava/util/Map;
iload 3
invokestatic java/lang/Short/valueOf(S)Ljava/lang/Short;
lload 9
invokestatic java/lang/Long/valueOf(J)Ljava/lang/Long;
invokeinterface java/util/Map/put(Ljava/lang/Object;Ljava/lang/Object;)Ljava/lang/Object; 2
pop
iload 4
iconst_1
iadd
istore 4
goto L15
L16:
aload 0
invokespecial com/flurry/android/aa/f()V
ldc "FlurryAgent"
new java/lang/StringBuilder
dup
invokespecial java/lang/StringBuilder/<init>()V
ldc "Cache read, num images: "
invokevirtual java/lang/StringBuilder/append(Ljava/lang/String;)Ljava/lang/StringBuilder;
aload 0
getfield com/flurry/android/aa/e Lcom/flurry/android/ag;
invokevirtual com/flurry/android/ag/a()I
invokevirtual java/lang/StringBuilder/append(I)Ljava/lang/StringBuilder;
invokevirtual java/lang/StringBuilder/toString()Ljava/lang/String;
invokestatic com/flurry/android/ai/a(Ljava/lang/String;Ljava/lang/String;)I
pop
return
.limit locals 14
.limit stack 4
.end method

.method private a(Ljava/io/DataOutputStream;)V
aload 1
iconst_2
invokevirtual java/io/DataOutputStream/writeShort(I)V
aload 1
aload 0
getfield com/flurry/android/aa/d J
invokevirtual java/io/DataOutputStream/writeLong(J)V
aload 0
getfield com/flurry/android/aa/e Lcom/flurry/android/ag;
invokevirtual com/flurry/android/ag/b()Ljava/util/List;
astore 5
aload 1
aload 5
invokeinterface java/util/List/size()I 0
invokevirtual java/io/DataOutputStream/writeShort(I)V
aload 5
invokeinterface java/util/List/iterator()Ljava/util/Iterator; 0
astore 5
L0:
aload 5
invokeinterface java/util/Iterator/hasNext()Z 0
ifeq L1
aload 5
invokeinterface java/util/Iterator/next()Ljava/lang/Object; 0
checkcast java/util/Map$Entry
astore 6
aload 1
aload 6
invokeinterface java/util/Map$Entry/getKey()Ljava/lang/Object; 0
checkcast java/lang/Long
invokevirtual java/lang/Long/longValue()J
invokevirtual java/io/DataOutputStream/writeLong(J)V
aload 6
invokeinterface java/util/Map$Entry/getValue()Ljava/lang/Object; 0
checkcast com/flurry/android/AdImage
astore 6
aload 1
aload 6
getfield com/flurry/android/AdImage/a J
invokeinterface java/io/DataOutput/writeLong(J)V 2
aload 1
aload 6
getfield com/flurry/android/AdImage/b I
invokeinterface java/io/DataOutput/writeInt(I)V 1
aload 1
aload 6
getfield com/flurry/android/AdImage/c I
invokeinterface java/io/DataOutput/writeInt(I)V 1
aload 1
aload 6
getfield com/flurry/android/AdImage/d Ljava/lang/String;
invokeinterface java/io/DataOutput/writeUTF(Ljava/lang/String;)V 1
aload 1
aload 6
getfield com/flurry/android/AdImage/e [B
arraylength
invokeinterface java/io/DataOutput/writeInt(I)V 1
aload 1
aload 6
getfield com/flurry/android/AdImage/e [B
invokeinterface java/io/DataOutput/write([B)V 1
goto L0
L1:
aload 0
getfield com/flurry/android/aa/f Lcom/flurry/android/ag;
invokevirtual com/flurry/android/ag/b()Ljava/util/List;
astore 5
aload 1
aload 5
invokeinterface java/util/List/size()I 0
invokevirtual java/io/DataOutputStream/writeShort(I)V
aload 5
invokeinterface java/util/List/iterator()Ljava/util/Iterator; 0
astore 5
L2:
aload 5
invokeinterface java/util/Iterator/hasNext()Z 0
ifeq L3
aload 5
invokeinterface java/util/Iterator/next()Ljava/lang/Object; 0
checkcast java/util/Map$Entry
astore 6
aload 1
aload 6
invokeinterface java/util/Map$Entry/getKey()Ljava/lang/Object; 0
checkcast java/lang/Long
invokevirtual java/lang/Long/longValue()J
invokevirtual java/io/DataOutputStream/writeLong(J)V
aload 6
invokeinterface java/util/Map$Entry/getValue()Ljava/lang/Object; 0
checkcast com/flurry/android/am
astore 6
aload 6
getfield com/flurry/android/am/a Ljava/lang/String;
ifnull L4
iconst_1
istore 4
L5:
aload 1
iload 4
invokeinterface java/io/DataOutput/writeBoolean(Z)V 1
iload 4
ifeq L6
aload 1
aload 6
getfield com/flurry/android/am/a Ljava/lang/String;
invokeinterface java/io/DataOutput/writeUTF(Ljava/lang/String;)V 1
L6:
aload 6
getfield com/flurry/android/am/b Ljava/lang/String;
ifnull L7
iconst_1
istore 4
L8:
aload 1
iload 4
invokeinterface java/io/DataOutput/writeBoolean(Z)V 1
iload 4
ifeq L9
aload 1
aload 6
getfield com/flurry/android/am/b Ljava/lang/String;
invokeinterface java/io/DataOutput/writeUTF(Ljava/lang/String;)V 1
L9:
aload 1
aload 6
getfield com/flurry/android/am/c I
invokeinterface java/io/DataOutput/writeInt(I)V 1
goto L2
L4:
iconst_0
istore 4
goto L5
L7:
iconst_0
istore 4
goto L8
L3:
aload 1
aload 0
getfield com/flurry/android/aa/h Ljava/util/Map;
invokeinterface java/util/Map/size()I 0
invokevirtual java/io/DataOutputStream/writeShort(I)V
aload 0
getfield com/flurry/android/aa/h Ljava/util/Map;
invokeinterface java/util/Map/entrySet()Ljava/util/Set; 0
invokeinterface java/util/Set/iterator()Ljava/util/Iterator; 0
astore 5
L10:
aload 5
invokeinterface java/util/Iterator/hasNext()Z 0
ifeq L11
aload 5
invokeinterface java/util/Iterator/next()Ljava/lang/Object; 0
checkcast java/util/Map$Entry
astore 6
aload 1
aload 6
invokeinterface java/util/Map$Entry/getKey()Ljava/lang/Object; 0
checkcast java/lang/String
invokevirtual java/io/DataOutputStream/writeUTF(Ljava/lang/String;)V
aload 6
invokeinterface java/util/Map$Entry/getValue()Ljava/lang/Object; 0
checkcast com/flurry/android/e
astore 6
aload 1
aload 6
getfield com/flurry/android/e/a Ljava/lang/String;
invokeinterface java/io/DataOutput/writeUTF(Ljava/lang/String;)V 1
aload 1
aload 6
getfield com/flurry/android/e/b B
invokeinterface java/io/DataOutput/writeByte(I)V 1
aload 1
aload 6
getfield com/flurry/android/e/c B
invokeinterface java/io/DataOutput/writeByte(I)V 1
goto L10
L11:
aload 1
aload 0
getfield com/flurry/android/aa/g Ljava/util/Map;
invokeinterface java/util/Map/size()I 0
invokevirtual java/io/DataOutputStream/writeShort(I)V
aload 0
getfield com/flurry/android/aa/g Ljava/util/Map;
invokeinterface java/util/Map/entrySet()Ljava/util/Set; 0
invokeinterface java/util/Set/iterator()Ljava/util/Iterator; 0
astore 5
L12:
aload 5
invokeinterface java/util/Iterator/hasNext()Z 0
ifeq L13
aload 5
invokeinterface java/util/Iterator/next()Ljava/lang/Object; 0
checkcast java/util/Map$Entry
astore 6
aload 1
aload 6
invokeinterface java/util/Map$Entry/getKey()Ljava/lang/Object; 0
checkcast java/lang/String
invokevirtual java/io/DataOutputStream/writeUTF(Ljava/lang/String;)V
aload 6
invokeinterface java/util/Map$Entry/getValue()Ljava/lang/Object; 0
checkcast [Lcom/flurry/android/w;
astore 6
aload 6
ifnonnull L14
iconst_0
istore 2
L15:
aload 1
iload 2
invokevirtual java/io/DataOutputStream/writeShort(I)V
iconst_0
istore 3
L16:
iload 3
iload 2
if_icmpge L12
aload 6
iload 3
aaload
astore 7
aload 1
aload 7
getfield com/flurry/android/w/a J
invokeinterface java/io/DataOutput/writeLong(J)V 2
aload 1
aload 7
getfield com/flurry/android/w/b J
invokeinterface java/io/DataOutput/writeLong(J)V 2
aload 1
aload 7
getfield com/flurry/android/w/d Ljava/lang/String;
invokeinterface java/io/DataOutput/writeUTF(Ljava/lang/String;)V 1
aload 1
aload 7
getfield com/flurry/android/w/c Ljava/lang/String;
invokeinterface java/io/DataOutput/writeUTF(Ljava/lang/String;)V 1
aload 1
aload 7
getfield com/flurry/android/w/e J
invokeinterface java/io/DataOutput/writeLong(J)V 2
aload 1
aload 7
getfield com/flurry/android/w/f Ljava/lang/Long;
invokevirtual java/lang/Long/longValue()J
invokeinterface java/io/DataOutput/writeLong(J)V 2
aload 1
aload 7
getfield com/flurry/android/w/g [B
arraylength
invokeinterface java/io/DataOutput/writeByte(I)V 1
aload 1
aload 7
getfield com/flurry/android/w/g [B
invokeinterface java/io/DataOutput/write([B)V 1
iload 3
iconst_1
iadd
istore 3
goto L16
L14:
aload 6
arraylength
istore 2
goto L15
L13:
aload 1
aload 0
getfield com/flurry/android/aa/i Ljava/util/Map;
invokeinterface java/util/Map/size()I 0
invokevirtual java/io/DataOutputStream/writeShort(I)V
aload 0
getfield com/flurry/android/aa/i Ljava/util/Map;
invokeinterface java/util/Map/entrySet()Ljava/util/Set; 0
invokeinterface java/util/Set/iterator()Ljava/util/Iterator; 0
astore 5
L17:
aload 5
invokeinterface java/util/Iterator/hasNext()Z 0
ifeq L18
aload 5
invokeinterface java/util/Iterator/next()Ljava/lang/Object; 0
checkcast java/util/Map$Entry
astore 6
aload 1
aload 6
invokeinterface java/util/Map$Entry/getKey()Ljava/lang/Object; 0
checkcast java/lang/Byte
invokevirtual java/lang/Byte/byteValue()B
invokevirtual java/io/DataOutputStream/writeByte(I)V
aload 6
invokeinterface java/util/Map$Entry/getValue()Ljava/lang/Object; 0
checkcast com/flurry/android/c
aload 1
invokevirtual com/flurry/android/c/a(Ljava/io/DataOutput;)V
goto L17
L18:
aload 1
aload 0
getfield com/flurry/android/aa/j Ljava/util/Map;
invokeinterface java/util/Map/size()I 0
invokevirtual java/io/DataOutputStream/writeShort(I)V
aload 0
getfield com/flurry/android/aa/j Ljava/util/Map;
invokeinterface java/util/Map/entrySet()Ljava/util/Set; 0
invokeinterface java/util/Set/iterator()Ljava/util/Iterator; 0
astore 5
L19:
aload 5
invokeinterface java/util/Iterator/hasNext()Z 0
ifeq L20
aload 5
invokeinterface java/util/Iterator/next()Ljava/lang/Object; 0
checkcast java/util/Map$Entry
astore 6
aload 1
aload 6
invokeinterface java/util/Map$Entry/getKey()Ljava/lang/Object; 0
checkcast java/lang/Short
invokevirtual java/lang/Short/shortValue()S
invokevirtual java/io/DataOutputStream/writeShort(I)V
aload 1
aload 6
invokeinterface java/util/Map$Entry/getValue()Ljava/lang/Object; 0
checkcast java/lang/Long
invokevirtual java/lang/Long/longValue()J
invokevirtual java/io/DataOutputStream/writeLong(J)V
goto L19
L20:
return
.limit locals 8
.limit stack 3
.end method

.method private static a(Ljava/io/File;)V
aload 0
invokevirtual java/io/File/delete()Z
ifne L0
ldc "FlurryAgent"
ldc "Cannot delete cached ads"
invokestatic com/flurry/android/ai/b(Ljava/lang/String;Ljava/lang/String;)I
pop
L0:
return
.limit locals 1
.limit stack 2
.end method

.method private f()V
aload 0
getfield com/flurry/android/aa/i Ljava/util/Map;
invokeinterface java/util/Map/values()Ljava/util/Collection; 0
invokeinterface java/util/Collection/iterator()Ljava/util/Iterator; 0
astore 3
L0:
aload 3
invokeinterface java/util/Iterator/hasNext()Z 0
ifeq L1
aload 3
invokeinterface java/util/Iterator/next()Ljava/lang/Object; 0
pop
goto L0
L1:
aload 0
getfield com/flurry/android/aa/g Ljava/util/Map;
invokeinterface java/util/Map/values()Ljava/util/Collection; 0
invokeinterface java/util/Collection/iterator()Ljava/util/Iterator; 0
astore 3
L2:
aload 3
invokeinterface java/util/Iterator/hasNext()Z 0
ifeq L3
aload 3
invokeinterface java/util/Iterator/next()Ljava/lang/Object; 0
checkcast [Lcom/flurry/android/w;
astore 4
aload 4
ifnull L2
aload 4
arraylength
istore 2
iconst_0
istore 1
L4:
iload 1
iload 2
if_icmpge L2
aload 4
iload 1
aaload
astore 5
aload 5
aload 0
aload 5
getfield com/flurry/android/w/f Ljava/lang/Long;
invokevirtual java/lang/Long/longValue()J
invokevirtual com/flurry/android/aa/b(J)Lcom/flurry/android/AdImage;
putfield com/flurry/android/w/h Lcom/flurry/android/AdImage;
aload 5
getfield com/flurry/android/w/h Lcom/flurry/android/AdImage;
ifnonnull L5
ldc "FlurryAgent"
new java/lang/StringBuilder
dup
invokespecial java/lang/StringBuilder/<init>()V
ldc "Ad "
invokevirtual java/lang/StringBuilder/append(Ljava/lang/String;)Ljava/lang/StringBuilder;
aload 5
getfield com/flurry/android/w/d Ljava/lang/String;
invokevirtual java/lang/StringBuilder/append(Ljava/lang/String;)Ljava/lang/StringBuilder;
ldc " has no image"
invokevirtual java/lang/StringBuilder/append(Ljava/lang/String;)Ljava/lang/StringBuilder;
invokevirtual java/lang/StringBuilder/toString()Ljava/lang/String;
invokestatic com/flurry/android/ai/b(Ljava/lang/String;Ljava/lang/String;)I
pop
L5:
aload 0
aload 5
getfield com/flurry/android/w/a J
invokevirtual com/flurry/android/aa/a(J)Lcom/flurry/android/am;
ifnonnull L6
ldc "FlurryAgent"
new java/lang/StringBuilder
dup
invokespecial java/lang/StringBuilder/<init>()V
ldc "Ad "
invokevirtual java/lang/StringBuilder/append(Ljava/lang/String;)Ljava/lang/StringBuilder;
aload 5
getfield com/flurry/android/w/d Ljava/lang/String;
invokevirtual java/lang/StringBuilder/append(Ljava/lang/String;)Ljava/lang/StringBuilder;
ldc " has no pricing"
invokevirtual java/lang/StringBuilder/append(Ljava/lang/String;)Ljava/lang/StringBuilder;
invokevirtual java/lang/StringBuilder/toString()Ljava/lang/String;
invokestatic com/flurry/android/ai/b(Ljava/lang/String;Ljava/lang/String;)I
pop
L6:
iload 1
iconst_1
iadd
istore 1
goto L4
L3:
aload 0
getfield com/flurry/android/aa/h Ljava/util/Map;
invokeinterface java/util/Map/values()Ljava/util/Collection; 0
invokeinterface java/util/Collection/iterator()Ljava/util/Iterator; 0
astore 3
L7:
aload 3
invokeinterface java/util/Iterator/hasNext()Z 0
ifeq L8
aload 3
invokeinterface java/util/Iterator/next()Ljava/lang/Object; 0
checkcast com/flurry/android/e
astore 4
aload 4
aload 0
aload 4
getfield com/flurry/android/e/c B
invokespecial com/flurry/android/aa/a(B)Lcom/flurry/android/c;
putfield com/flurry/android/e/d Lcom/flurry/android/c;
aload 4
getfield com/flurry/android/e/d Lcom/flurry/android/c;
ifnonnull L7
ldc "FlurryAgent"
new java/lang/StringBuilder
dup
invokespecial java/lang/StringBuilder/<init>()V
ldc "No ad theme found for "
invokevirtual java/lang/StringBuilder/append(Ljava/lang/String;)Ljava/lang/StringBuilder;
aload 4
getfield com/flurry/android/e/c B
invokevirtual java/lang/StringBuilder/append(I)Ljava/lang/StringBuilder;
invokevirtual java/lang/StringBuilder/toString()Ljava/lang/String;
invokestatic com/flurry/android/ai/d(Ljava/lang/String;Ljava/lang/String;)I
pop
goto L7
L8:
return
.limit locals 6
.limit stack 4
.end method

.method private g()Ljava/lang/String;
new java/lang/StringBuilder
dup
invokespecial java/lang/StringBuilder/<init>()V
ldc ".flurryappcircle."
invokevirtual java/lang/StringBuilder/append(Ljava/lang/String;)Ljava/lang/StringBuilder;
aload 0
getfield com/flurry/android/aa/c Lcom/flurry/android/a;
getfield com/flurry/android/a/a Ljava/lang/String;
invokevirtual java/lang/String/hashCode()I
bipush 16
invokestatic java/lang/Integer/toString(II)Ljava/lang/String;
invokevirtual java/lang/StringBuilder/append(Ljava/lang/String;)Ljava/lang/StringBuilder;
invokevirtual java/lang/StringBuilder/toString()Ljava/lang/String;
areturn
.limit locals 1
.limit stack 3
.end method

.method final a(S)Lcom/flurry/android/AdImage;
.catch all from L0 to L1 using L2
.catch all from L3 to L4 using L2
aload 0
monitorenter
L0:
aload 0
getfield com/flurry/android/aa/j Ljava/util/Map;
iconst_1
invokestatic java/lang/Short/valueOf(S)Ljava/lang/Short;
invokeinterface java/util/Map/get(Ljava/lang/Object;)Ljava/lang/Object; 1
checkcast java/lang/Long
astore 2
L1:
aload 2
ifnonnull L3
aconst_null
astore 2
L5:
aload 0
monitorexit
aload 2
areturn
L3:
aload 0
aload 2
invokevirtual java/lang/Long/longValue()J
invokevirtual com/flurry/android/aa/b(J)Lcom/flurry/android/AdImage;
astore 2
L4:
goto L5
L2:
astore 2
aload 0
monitorexit
aload 2
athrow
.limit locals 3
.limit stack 3
.end method

.method final a(J)Lcom/flurry/android/am;
.catch all from L0 to L1 using L2
aload 0
monitorenter
L0:
aload 0
getfield com/flurry/android/aa/f Lcom/flurry/android/ag;
lload 1
invokestatic java/lang/Long/valueOf(J)Ljava/lang/Long;
invokevirtual com/flurry/android/ag/a(Ljava/lang/Object;)Ljava/lang/Object;
checkcast com/flurry/android/am
astore 3
L1:
aload 0
monitorexit
aload 3
areturn
L2:
astore 3
aload 0
monitorexit
aload 3
athrow
.limit locals 4
.limit stack 3
.end method

.method final a()Ljava/util/Set;
.catch all from L0 to L1 using L2
aload 0
monitorenter
L0:
aload 0
getfield com/flurry/android/aa/e Lcom/flurry/android/ag;
invokevirtual com/flurry/android/ag/c()Ljava/util/Set;
astore 1
L1:
aload 0
monitorexit
aload 1
areturn
L2:
astore 1
aload 0
monitorexit
aload 1
athrow
.limit locals 2
.limit stack 1
.end method

.method final a(Landroid/content/Context;Lcom/flurry/android/v;Lcom/flurry/android/a;)V
aload 0
aload 1
putfield com/flurry/android/aa/a Landroid/content/Context;
aload 0
aload 2
putfield com/flurry/android/aa/b Lcom/flurry/android/v;
aload 0
aload 3
putfield com/flurry/android/aa/c Lcom/flurry/android/a;
return
.limit locals 4
.limit stack 2
.end method

.method final a(Ljava/util/Map;Ljava/util/Map;Ljava/util/Map;Ljava/util/Map;Ljava/util/Map;Ljava/util/Map;)V
.catch all from L0 to L1 using L2
.catch all from L1 to L3 using L2
.catch all from L4 to L5 using L2
.catch all from L5 to L6 using L2
.catch all from L7 to L8 using L2
.catch all from L9 to L10 using L2
.catch all from L11 to L12 using L2
.catch all from L12 to L13 using L2
.catch all from L13 to L14 using L2
.catch all from L15 to L16 using L2
.catch all from L16 to L17 using L2
.catch all from L18 to L19 using L2
.catch all from L20 to L21 using L2
aload 0
monitorenter
L0:
aload 0
invokestatic java/lang/System/currentTimeMillis()J
putfield com/flurry/android/aa/d J
aload 4
invokeinterface java/util/Map/entrySet()Ljava/util/Set; 0
invokeinterface java/util/Set/iterator()Ljava/util/Iterator; 0
astore 4
L1:
aload 4
invokeinterface java/util/Iterator/hasNext()Z 0
ifeq L4
aload 4
invokeinterface java/util/Iterator/next()Ljava/lang/Object; 0
checkcast java/util/Map$Entry
astore 7
aload 7
invokeinterface java/util/Map$Entry/getValue()Ljava/lang/Object; 0
ifnull L1
aload 0
getfield com/flurry/android/aa/e Lcom/flurry/android/ag;
aload 7
invokeinterface java/util/Map$Entry/getKey()Ljava/lang/Object; 0
aload 7
invokeinterface java/util/Map$Entry/getValue()Ljava/lang/Object; 0
invokevirtual com/flurry/android/ag/a(Ljava/lang/Object;Ljava/lang/Object;)V
L3:
goto L1
L2:
astore 1
aload 0
monitorexit
aload 1
athrow
L4:
aload 5
invokeinterface java/util/Map/entrySet()Ljava/util/Set; 0
invokeinterface java/util/Set/iterator()Ljava/util/Iterator; 0
astore 4
L5:
aload 4
invokeinterface java/util/Iterator/hasNext()Z 0
ifeq L22
aload 4
invokeinterface java/util/Iterator/next()Ljava/lang/Object; 0
checkcast java/util/Map$Entry
astore 5
aload 5
invokeinterface java/util/Map$Entry/getValue()Ljava/lang/Object; 0
ifnull L5
aload 0
getfield com/flurry/android/aa/f Lcom/flurry/android/ag;
aload 5
invokeinterface java/util/Map$Entry/getKey()Ljava/lang/Object; 0
aload 5
invokeinterface java/util/Map$Entry/getValue()Ljava/lang/Object; 0
invokevirtual com/flurry/android/ag/a(Ljava/lang/Object;Ljava/lang/Object;)V
L6:
goto L5
L22:
aload 2
ifnull L8
L7:
aload 2
invokeinterface java/util/Map/isEmpty()Z 0
ifne L8
aload 0
aload 2
putfield com/flurry/android/aa/h Ljava/util/Map;
L8:
aload 3
ifnull L10
L9:
aload 3
invokeinterface java/util/Map/isEmpty()Z 0
ifne L10
aload 0
aload 3
putfield com/flurry/android/aa/i Ljava/util/Map;
L10:
aload 6
ifnull L12
L11:
aload 6
invokeinterface java/util/Map/isEmpty()Z 0
ifne L12
aload 0
aload 6
putfield com/flurry/android/aa/j Ljava/util/Map;
L12:
aload 0
new java/util/HashMap
dup
invokespecial java/util/HashMap/<init>()V
putfield com/flurry/android/aa/g Ljava/util/Map;
aload 2
invokeinterface java/util/Map/entrySet()Ljava/util/Set; 0
invokeinterface java/util/Set/iterator()Ljava/util/Iterator; 0
astore 2
L13:
aload 2
invokeinterface java/util/Iterator/hasNext()Z 0
ifeq L20
aload 2
invokeinterface java/util/Iterator/next()Ljava/lang/Object; 0
checkcast java/util/Map$Entry
astore 5
aload 5
invokeinterface java/util/Map$Entry/getValue()Ljava/lang/Object; 0
checkcast com/flurry/android/e
astore 4
aload 1
aload 4
getfield com/flurry/android/e/b B
invokestatic java/lang/Byte/valueOf(B)Ljava/lang/Byte;
invokeinterface java/util/Map/get(Ljava/lang/Object;)Ljava/lang/Object; 1
checkcast [Lcom/flurry/android/w;
astore 6
L14:
aload 6
ifnull L16
L15:
aload 0
getfield com/flurry/android/aa/g Ljava/util/Map;
aload 5
invokeinterface java/util/Map$Entry/getKey()Ljava/lang/Object; 0
aload 6
invokeinterface java/util/Map/put(Ljava/lang/Object;Ljava/lang/Object;)Ljava/lang/Object; 2
pop
L16:
aload 3
aload 4
getfield com/flurry/android/e/c B
invokestatic java/lang/Byte/valueOf(B)Ljava/lang/Byte;
invokeinterface java/util/Map/get(Ljava/lang/Object;)Ljava/lang/Object; 1
checkcast com/flurry/android/c
astore 5
L17:
aload 5
ifnull L13
L18:
aload 4
aload 5
putfield com/flurry/android/e/d Lcom/flurry/android/c;
L19:
goto L13
L20:
aload 0
invokespecial com/flurry/android/aa/f()V
aload 0
sipush 202
invokespecial com/flurry/android/aa/a(I)V
L21:
aload 0
monitorexit
return
.limit locals 8
.limit stack 3
.end method

.method final a(Ljava/lang/String;)[Lcom/flurry/android/w;
.catch all from L0 to L1 using L2
.catch all from L3 to L4 using L2
aload 0
monitorenter
L0:
aload 0
getfield com/flurry/android/aa/g Ljava/util/Map;
aload 1
invokeinterface java/util/Map/get(Ljava/lang/Object;)Ljava/lang/Object; 1
checkcast [Lcom/flurry/android/w;
astore 2
L1:
aload 2
astore 1
aload 2
ifnonnull L4
L3:
aload 0
getfield com/flurry/android/aa/g Ljava/util/Map;
ldc ""
invokeinterface java/util/Map/get(Ljava/lang/Object;)Ljava/lang/Object; 1
checkcast [Lcom/flurry/android/w;
astore 1
L4:
aload 0
monitorexit
aload 1
areturn
L2:
astore 1
aload 0
monitorexit
aload 1
athrow
.limit locals 3
.limit stack 2
.end method

.method final b(J)Lcom/flurry/android/AdImage;
.catch all from L0 to L1 using L2
aload 0
monitorenter
L0:
aload 0
getfield com/flurry/android/aa/e Lcom/flurry/android/ag;
lload 1
invokestatic java/lang/Long/valueOf(J)Ljava/lang/Long;
invokevirtual com/flurry/android/ag/a(Ljava/lang/Object;)Ljava/lang/Object;
checkcast com/flurry/android/AdImage
astore 3
L1:
aload 0
monitorexit
aload 3
areturn
L2:
astore 3
aload 0
monitorexit
aload 3
athrow
.limit locals 4
.limit stack 3
.end method

.method final b(Ljava/lang/String;)Lcom/flurry/android/e;
.catch all from L0 to L1 using L2
.catch all from L3 to L4 using L2
aload 0
monitorenter
L0:
aload 0
getfield com/flurry/android/aa/h Ljava/util/Map;
aload 1
invokeinterface java/util/Map/get(Ljava/lang/Object;)Ljava/lang/Object; 1
checkcast com/flurry/android/e
astore 2
L1:
aload 2
astore 1
aload 2
ifnonnull L4
L3:
aload 0
getfield com/flurry/android/aa/h Ljava/util/Map;
ldc ""
invokeinterface java/util/Map/get(Ljava/lang/Object;)Ljava/lang/Object; 1
checkcast com/flurry/android/e
astore 1
L4:
aload 0
monitorexit
aload 1
areturn
L2:
astore 1
aload 0
monitorexit
aload 1
athrow
.limit locals 3
.limit stack 2
.end method

.method final b()Z
aload 0
getfield com/flurry/android/aa/k Z
ireturn
.limit locals 1
.limit stack 1
.end method

.method final c()J
aload 0
getfield com/flurry/android/aa/d J
lreturn
.limit locals 1
.limit stack 2
.end method

.method final d()V
.catch all from L0 to L1 using L2
.catch java/lang/Throwable from L3 to L4 using L5
.catch all from L3 to L4 using L6
.catch java/lang/Throwable from L7 to L8 using L9
.catch all from L7 to L8 using L10
.catch java/lang/Throwable from L11 to L12 using L9
.catch all from L11 to L12 using L10
.catch java/lang/Throwable from L13 to L14 using L9
.catch all from L13 to L14 using L10
.catch all from L14 to L15 using L2
.catch java/lang/Throwable from L16 to L17 using L9
.catch all from L16 to L17 using L10
.catch all from L18 to L19 using L10
.catch all from L20 to L21 using L10
.catch all from L21 to L22 using L2
.catch all from L23 to L24 using L2
.catch all from L24 to L25 using L2
aload 0
monitorenter
L0:
aload 0
getfield com/flurry/android/aa/a Landroid/content/Context;
aload 0
invokespecial com/flurry/android/aa/g()Ljava/lang/String;
invokevirtual android/content/Context/getFileStreamPath(Ljava/lang/String;)Ljava/io/File;
astore 5
aload 5
invokevirtual java/io/File/exists()Z
istore 1
L1:
iload 1
ifeq L24
L3:
new java/io/DataInputStream
dup
new java/io/FileInputStream
dup
aload 5
invokespecial java/io/FileInputStream/<init>(Ljava/io/File;)V
invokespecial java/io/DataInputStream/<init>(Ljava/io/InputStream;)V
astore 3
L4:
aload 3
astore 2
L7:
aload 3
invokevirtual java/io/DataInputStream/readUnsignedShort()I
ldc_w 46587
if_icmpne L26
L8:
aload 3
astore 2
L11:
aload 0
aload 3
invokespecial com/flurry/android/aa/a(Ljava/io/DataInputStream;)V
L12:
aload 3
astore 2
L13:
aload 0
sipush 201
invokespecial com/flurry/android/aa/a(I)V
L14:
aload 3
invokestatic com/flurry/android/r/a(Ljava/io/Closeable;)V
L15:
aload 0
monitorexit
return
L26:
aload 3
astore 2
L16:
aload 5
invokestatic com/flurry/android/aa/a(Ljava/io/File;)V
L17:
goto L14
L9:
astore 4
L27:
aload 3
astore 2
L18:
ldc "FlurryAgent"
ldc "Discarding cache"
aload 4
invokestatic com/flurry/android/ai/a(Ljava/lang/String;Ljava/lang/String;Ljava/lang/Throwable;)I
pop
L19:
aload 3
astore 2
L20:
aload 5
invokestatic com/flurry/android/aa/a(Ljava/io/File;)V
L21:
aload 3
invokestatic com/flurry/android/r/a(Ljava/io/Closeable;)V
L22:
goto L15
L2:
astore 2
aload 0
monitorexit
aload 2
athrow
L6:
astore 3
aconst_null
astore 2
L23:
aload 2
invokestatic com/flurry/android/r/a(Ljava/io/Closeable;)V
aload 3
athrow
L24:
ldc "FlurryAgent"
new java/lang/StringBuilder
dup
invokespecial java/lang/StringBuilder/<init>()V
ldc "cache file does not exist, path="
invokevirtual java/lang/StringBuilder/append(Ljava/lang/String;)Ljava/lang/StringBuilder;
aload 5
invokevirtual java/io/File/getAbsolutePath()Ljava/lang/String;
invokevirtual java/lang/StringBuilder/append(Ljava/lang/String;)Ljava/lang/StringBuilder;
invokevirtual java/lang/StringBuilder/toString()Ljava/lang/String;
invokestatic com/flurry/android/ai/c(Ljava/lang/String;Ljava/lang/String;)I
pop
L25:
goto L15
L10:
astore 3
goto L23
L5:
astore 4
aconst_null
astore 3
goto L27
.limit locals 6
.limit stack 5
.end method

.method final e()V
.catch java/lang/Throwable from L0 to L1 using L2
.catch all from L0 to L1 using L3
.catch java/lang/Throwable from L4 to L5 using L2
.catch all from L4 to L5 using L3
.catch java/lang/Throwable from L6 to L7 using L2
.catch all from L6 to L7 using L3
.catch java/lang/Throwable from L8 to L9 using L2
.catch all from L8 to L9 using L3
.catch java/lang/Throwable from L10 to L11 using L2
.catch all from L10 to L11 using L3
.catch all from L11 to L12 using L13
.catch java/lang/Throwable from L14 to L15 using L2
.catch all from L14 to L15 using L3
.catch java/lang/Throwable from L15 to L16 using L17
.catch all from L15 to L16 using L18
.catch all from L16 to L19 using L13
.catch all from L20 to L21 using L3
.catch all from L21 to L22 using L13
.catch all from L23 to L18 using L13
aconst_null
astore 2
aconst_null
astore 3
aload 0
monitorenter
aload 2
astore 1
L0:
aload 0
getfield com/flurry/android/aa/a Landroid/content/Context;
aload 0
invokespecial com/flurry/android/aa/g()Ljava/lang/String;
invokevirtual android/content/Context/getFileStreamPath(Ljava/lang/String;)Ljava/io/File;
astore 4
L1:
aload 2
astore 1
L4:
aload 4
invokevirtual java/io/File/getParentFile()Ljava/io/File;
astore 5
L5:
aload 2
astore 1
L6:
aload 5
invokevirtual java/io/File/mkdirs()Z
ifne L24
L7:
aload 2
astore 1
L8:
aload 5
invokevirtual java/io/File/exists()Z
ifne L24
L9:
aload 2
astore 1
L10:
ldc "FlurryAgent"
new java/lang/StringBuilder
dup
invokespecial java/lang/StringBuilder/<init>()V
ldc "Unable to create persistent dir: "
invokevirtual java/lang/StringBuilder/append(Ljava/lang/String;)Ljava/lang/StringBuilder;
aload 5
invokevirtual java/lang/StringBuilder/append(Ljava/lang/Object;)Ljava/lang/StringBuilder;
invokevirtual java/lang/StringBuilder/toString()Ljava/lang/String;
invokestatic com/flurry/android/ai/b(Ljava/lang/String;Ljava/lang/String;)I
pop
L11:
aconst_null
invokestatic com/flurry/android/r/a(Ljava/io/Closeable;)V
L12:
aload 0
monitorexit
return
L24:
aload 2
astore 1
L14:
new java/io/DataOutputStream
dup
new java/io/FileOutputStream
dup
aload 4
invokespecial java/io/FileOutputStream/<init>(Ljava/io/File;)V
invokespecial java/io/DataOutputStream/<init>(Ljava/io/OutputStream;)V
astore 2
L15:
aload 2
ldc_w 46587
invokevirtual java/io/DataOutputStream/writeShort(I)V
aload 0
aload 2
invokespecial com/flurry/android/aa/a(Ljava/io/DataOutputStream;)V
L16:
aload 2
invokestatic com/flurry/android/r/a(Ljava/io/Closeable;)V
L19:
goto L12
L13:
astore 1
aload 0
monitorexit
aload 1
athrow
L2:
astore 1
aload 3
astore 2
aload 1
astore 3
L25:
aload 2
astore 1
L20:
ldc "FlurryAgent"
ldc ""
aload 3
invokestatic com/flurry/android/ai/b(Ljava/lang/String;Ljava/lang/String;Ljava/lang/Throwable;)I
pop
L21:
aload 2
invokestatic com/flurry/android/r/a(Ljava/io/Closeable;)V
L22:
goto L12
L23:
aload 1
invokestatic com/flurry/android/r/a(Ljava/io/Closeable;)V
aload 2
athrow
L18:
astore 3
aload 2
astore 1
aload 3
astore 2
goto L23
L17:
astore 3
goto L25
L3:
astore 2
goto L23
.limit locals 6
.limit stack 5
.end method

.method public final toString()Ljava/lang/String;
new java/lang/StringBuilder
dup
invokespecial java/lang/StringBuilder/<init>()V
astore 1
aload 1
ldc "{"
invokevirtual java/lang/StringBuilder/append(Ljava/lang/String;)Ljava/lang/StringBuilder;
pop
aload 1
new java/lang/StringBuilder
dup
invokespecial java/lang/StringBuilder/<init>()V
ldc "adImages ("
invokevirtual java/lang/StringBuilder/append(Ljava/lang/String;)Ljava/lang/StringBuilder;
aload 0
getfield com/flurry/android/aa/e Lcom/flurry/android/ag;
invokevirtual com/flurry/android/ag/b()Ljava/util/List;
invokeinterface java/util/List/size()I 0
invokevirtual java/lang/StringBuilder/append(I)Ljava/lang/StringBuilder;
ldc "),\n"
invokevirtual java/lang/StringBuilder/append(Ljava/lang/String;)Ljava/lang/StringBuilder;
invokevirtual java/lang/StringBuilder/toString()Ljava/lang/String;
invokevirtual java/lang/StringBuilder/append(Ljava/lang/String;)Ljava/lang/StringBuilder;
pop
aload 1
new java/lang/StringBuilder
dup
invokespecial java/lang/StringBuilder/<init>()V
ldc "adBlock ("
invokevirtual java/lang/StringBuilder/append(Ljava/lang/String;)Ljava/lang/StringBuilder;
aload 0
getfield com/flurry/android/aa/g Ljava/util/Map;
invokeinterface java/util/Map/size()I 0
invokevirtual java/lang/StringBuilder/append(I)Ljava/lang/StringBuilder;
ldc "):"
invokevirtual java/lang/StringBuilder/append(Ljava/lang/String;)Ljava/lang/StringBuilder;
invokevirtual java/lang/StringBuilder/toString()Ljava/lang/String;
invokevirtual java/lang/StringBuilder/append(Ljava/lang/String;)Ljava/lang/StringBuilder;
ldc ",\n"
invokevirtual java/lang/StringBuilder/append(Ljava/lang/String;)Ljava/lang/StringBuilder;
pop
aload 0
getfield com/flurry/android/aa/g Ljava/util/Map;
invokeinterface java/util/Map/entrySet()Ljava/util/Set; 0
invokeinterface java/util/Set/iterator()Ljava/util/Iterator; 0
astore 2
L0:
aload 2
invokeinterface java/util/Iterator/hasNext()Z 0
ifeq L1
aload 2
invokeinterface java/util/Iterator/next()Ljava/lang/Object; 0
checkcast java/util/Map$Entry
astore 3
aload 1
new java/lang/StringBuilder
dup
invokespecial java/lang/StringBuilder/<init>()V
ldc "\u0009"
invokevirtual java/lang/StringBuilder/append(Ljava/lang/String;)Ljava/lang/StringBuilder;
aload 3
invokeinterface java/util/Map$Entry/getKey()Ljava/lang/Object; 0
checkcast java/lang/String
invokevirtual java/lang/StringBuilder/append(Ljava/lang/String;)Ljava/lang/StringBuilder;
ldc ": "
invokevirtual java/lang/StringBuilder/append(Ljava/lang/String;)Ljava/lang/StringBuilder;
aload 3
invokeinterface java/util/Map$Entry/getValue()Ljava/lang/Object; 0
checkcast [Ljava/lang/Object;
invokestatic java/util/Arrays/toString([Ljava/lang/Object;)Ljava/lang/String;
invokevirtual java/lang/StringBuilder/append(Ljava/lang/String;)Ljava/lang/StringBuilder;
invokevirtual java/lang/StringBuilder/toString()Ljava/lang/String;
invokevirtual java/lang/StringBuilder/append(Ljava/lang/String;)Ljava/lang/StringBuilder;
pop
goto L0
L1:
aload 1
new java/lang/StringBuilder
dup
invokespecial java/lang/StringBuilder/<init>()V
ldc "adHooks ("
invokevirtual java/lang/StringBuilder/append(Ljava/lang/String;)Ljava/lang/StringBuilder;
aload 0
getfield com/flurry/android/aa/h Ljava/util/Map;
invokeinterface java/util/Map/size()I 0
invokevirtual java/lang/StringBuilder/append(I)Ljava/lang/StringBuilder;
ldc "):"
invokevirtual java/lang/StringBuilder/append(Ljava/lang/String;)Ljava/lang/StringBuilder;
aload 0
getfield com/flurry/android/aa/h Ljava/util/Map;
invokevirtual java/lang/StringBuilder/append(Ljava/lang/Object;)Ljava/lang/StringBuilder;
invokevirtual java/lang/StringBuilder/toString()Ljava/lang/String;
invokevirtual java/lang/StringBuilder/append(Ljava/lang/String;)Ljava/lang/StringBuilder;
ldc ",\n"
invokevirtual java/lang/StringBuilder/append(Ljava/lang/String;)Ljava/lang/StringBuilder;
pop
aload 1
new java/lang/StringBuilder
dup
invokespecial java/lang/StringBuilder/<init>()V
ldc "adThemes ("
invokevirtual java/lang/StringBuilder/append(Ljava/lang/String;)Ljava/lang/StringBuilder;
aload 0
getfield com/flurry/android/aa/i Ljava/util/Map;
invokeinterface java/util/Map/size()I 0
invokevirtual java/lang/StringBuilder/append(I)Ljava/lang/StringBuilder;
ldc "):"
invokevirtual java/lang/StringBuilder/append(Ljava/lang/String;)Ljava/lang/StringBuilder;
aload 0
getfield com/flurry/android/aa/i Ljava/util/Map;
invokevirtual java/lang/StringBuilder/append(Ljava/lang/Object;)Ljava/lang/StringBuilder;
invokevirtual java/lang/StringBuilder/toString()Ljava/lang/String;
invokevirtual java/lang/StringBuilder/append(Ljava/lang/String;)Ljava/lang/StringBuilder;
ldc ",\n"
invokevirtual java/lang/StringBuilder/append(Ljava/lang/String;)Ljava/lang/StringBuilder;
pop
aload 1
new java/lang/StringBuilder
dup
invokespecial java/lang/StringBuilder/<init>()V
ldc "auxMap ("
invokevirtual java/lang/StringBuilder/append(Ljava/lang/String;)Ljava/lang/StringBuilder;
aload 0
getfield com/flurry/android/aa/j Ljava/util/Map;
invokeinterface java/util/Map/size()I 0
invokevirtual java/lang/StringBuilder/append(I)Ljava/lang/StringBuilder;
ldc "):"
invokevirtual java/lang/StringBuilder/append(Ljava/lang/String;)Ljava/lang/StringBuilder;
aload 0
getfield com/flurry/android/aa/j Ljava/util/Map;
invokevirtual java/lang/StringBuilder/append(Ljava/lang/Object;)Ljava/lang/StringBuilder;
invokevirtual java/lang/StringBuilder/toString()Ljava/lang/String;
invokevirtual java/lang/StringBuilder/append(Ljava/lang/String;)Ljava/lang/StringBuilder;
ldc ",\n"
invokevirtual java/lang/StringBuilder/append(Ljava/lang/String;)Ljava/lang/StringBuilder;
pop
aload 1
ldc "}"
invokevirtual java/lang/StringBuilder/append(Ljava/lang/String;)Ljava/lang/StringBuilder;
pop
aload 1
invokevirtual java/lang/StringBuilder/toString()Ljava/lang/String;
areturn
.limit locals 4
.limit stack 3
.end method
