.bytecode 50.0
.class final synchronized com/flurry/android/c
.super com/flurry/android/ak

.field private 'A' I

.field private 'B' I

.field private 'C' I

.field private 'D' I

.field private 'E' I

.field private 'F' I

.field private 'G' I

.field private 'H' I

.field private 'I' I

.field private 'J' I

.field private 'K' I

.field private 'L' I

.field private 'M' I

.field private 'N' I

.field private 'O' I

.field private 'P' I

.field private 'Q' I

.field private 'R' I

.field private 'S' I

.field private 'T' I

.field private 'U' I

.field private 'V' I

.field private 'W' I

.field private 'X' I

.field private 'Y' I

.field private 'Z' I

.field 'a' B

.field private 'aa' I

.field private 'ab' I

.field private 'ac' I

.field private 'ad' I

.field private 'ae' I

.field private 'af' I

.field private 'ag' Z

.field 'b' Ljava/lang/String;

.field 'c' J

.field 'd' Ljava/lang/String;

.field 'e' I

.field 'f' I

.field 'g' Ljava/lang/String;

.field 'h' I

.field 'i' I

.field 'j' Ljava/lang/String;

.field 'k' I

.field 'l' I

.field 'm' I

.field 'n' I

.field 'o' I

.field 'p' I

.field 'q' I

.field private 'r' J

.field private 's' Ljava/lang/String;

.field private 't' I

.field private 'u' I

.field private 'v' Ljava/lang/String;

.field private 'w' I

.field private 'x' I

.field private 'y' Ljava/lang/String;

.field private 'z' I

.method <init>()V
aload 0
invokespecial com/flurry/android/ak/<init>()V
return
.limit locals 1
.limit stack 1
.end method

.method <init>(Ljava/io/DataInput;)V
aload 0
invokespecial com/flurry/android/ak/<init>()V
aload 0
aload 1
invokespecial com/flurry/android/c/c(Ljava/io/DataInput;)V
return
.limit locals 2
.limit stack 2
.end method

.method private c(Ljava/io/DataInput;)V
aload 0
aload 1
invokeinterface java/io/DataInput/readByte()B 0
putfield com/flurry/android/c/a B
aload 0
aload 1
invokeinterface java/io/DataInput/readUTF()Ljava/lang/String; 0
putfield com/flurry/android/c/b Ljava/lang/String;
aload 0
aload 1
invokeinterface java/io/DataInput/readLong()J 0
putfield com/flurry/android/c/c J
aload 0
aload 1
invokeinterface java/io/DataInput/readLong()J 0
putfield com/flurry/android/c/r J
aload 0
aload 1
invokeinterface java/io/DataInput/readUTF()Ljava/lang/String; 0
putfield com/flurry/android/c/d Ljava/lang/String;
aload 0
aload 1
invokeinterface java/io/DataInput/readUnsignedShort()I 0
putfield com/flurry/android/c/e I
aload 0
aload 1
invokeinterface java/io/DataInput/readInt()I 0
putfield com/flurry/android/c/f I
aload 0
aload 1
invokeinterface java/io/DataInput/readUTF()Ljava/lang/String; 0
putfield com/flurry/android/c/g Ljava/lang/String;
aload 0
aload 1
invokeinterface java/io/DataInput/readUnsignedShort()I 0
putfield com/flurry/android/c/h I
aload 0
aload 1
invokeinterface java/io/DataInput/readInt()I 0
putfield com/flurry/android/c/i I
aload 0
aload 1
invokeinterface java/io/DataInput/readUTF()Ljava/lang/String; 0
putfield com/flurry/android/c/j Ljava/lang/String;
aload 0
aload 1
invokeinterface java/io/DataInput/readUnsignedShort()I 0
putfield com/flurry/android/c/k I
aload 0
aload 1
invokeinterface java/io/DataInput/readInt()I 0
putfield com/flurry/android/c/l I
return
.limit locals 2
.limit stack 3
.end method

.method final a(Ljava/io/DataInput;)V
aload 0
aload 1
invokeinterface java/io/DataInput/readUTF()Ljava/lang/String; 0
putfield com/flurry/android/c/s Ljava/lang/String;
aload 0
aload 1
invokeinterface java/io/DataInput/readUnsignedShort()I 0
putfield com/flurry/android/c/t I
aload 0
aload 1
invokeinterface java/io/DataInput/readInt()I 0
putfield com/flurry/android/c/u I
aload 0
aload 1
invokeinterface java/io/DataInput/readUTF()Ljava/lang/String; 0
putfield com/flurry/android/c/v Ljava/lang/String;
aload 0
aload 1
invokeinterface java/io/DataInput/readUnsignedShort()I 0
putfield com/flurry/android/c/w I
aload 0
aload 1
invokeinterface java/io/DataInput/readInt()I 0
putfield com/flurry/android/c/x I
aload 0
aload 1
invokeinterface java/io/DataInput/readUTF()Ljava/lang/String; 0
putfield com/flurry/android/c/y Ljava/lang/String;
aload 0
aload 1
invokeinterface java/io/DataInput/readUnsignedShort()I 0
putfield com/flurry/android/c/z I
aload 0
aload 1
invokeinterface java/io/DataInput/readInt()I 0
putfield com/flurry/android/c/A I
aload 0
aload 1
invokeinterface java/io/DataInput/readInt()I 0
putfield com/flurry/android/c/B I
aload 0
aload 1
invokeinterface java/io/DataInput/readInt()I 0
putfield com/flurry/android/c/C I
aload 0
aload 1
invokeinterface java/io/DataInput/readInt()I 0
putfield com/flurry/android/c/m I
aload 0
aload 1
invokeinterface java/io/DataInput/readInt()I 0
putfield com/flurry/android/c/n I
aload 0
aload 1
invokeinterface java/io/DataInput/readInt()I 0
putfield com/flurry/android/c/o I
aload 0
aload 1
invokeinterface java/io/DataInput/readInt()I 0
putfield com/flurry/android/c/p I
aload 0
aload 1
invokeinterface java/io/DataInput/readInt()I 0
putfield com/flurry/android/c/D I
aload 0
aload 1
invokeinterface java/io/DataInput/readInt()I 0
putfield com/flurry/android/c/E I
aload 0
aload 1
invokeinterface java/io/DataInput/readInt()I 0
putfield com/flurry/android/c/F I
aload 0
aload 1
invokeinterface java/io/DataInput/readInt()I 0
putfield com/flurry/android/c/G I
aload 0
aload 1
invokeinterface java/io/DataInput/readInt()I 0
putfield com/flurry/android/c/H I
aload 0
aload 1
invokeinterface java/io/DataInput/readInt()I 0
putfield com/flurry/android/c/I I
aload 0
aload 1
invokeinterface java/io/DataInput/readInt()I 0
putfield com/flurry/android/c/J I
aload 0
aload 1
invokeinterface java/io/DataInput/readInt()I 0
putfield com/flurry/android/c/K I
aload 0
aload 1
invokeinterface java/io/DataInput/readInt()I 0
putfield com/flurry/android/c/q I
aload 0
aload 1
invokeinterface java/io/DataInput/readInt()I 0
putfield com/flurry/android/c/L I
aload 0
aload 1
invokeinterface java/io/DataInput/readInt()I 0
putfield com/flurry/android/c/M I
aload 0
aload 1
invokeinterface java/io/DataInput/readInt()I 0
putfield com/flurry/android/c/N I
aload 0
aload 1
invokeinterface java/io/DataInput/readInt()I 0
putfield com/flurry/android/c/O I
aload 0
aload 1
invokeinterface java/io/DataInput/readInt()I 0
putfield com/flurry/android/c/P I
aload 0
aload 1
invokeinterface java/io/DataInput/readInt()I 0
putfield com/flurry/android/c/Q I
aload 0
aload 1
invokeinterface java/io/DataInput/readInt()I 0
putfield com/flurry/android/c/R I
aload 0
aload 1
invokeinterface java/io/DataInput/readInt()I 0
putfield com/flurry/android/c/S I
aload 0
aload 1
invokeinterface java/io/DataInput/readInt()I 0
putfield com/flurry/android/c/T I
aload 0
aload 1
invokeinterface java/io/DataInput/readInt()I 0
putfield com/flurry/android/c/U I
aload 0
aload 1
invokeinterface java/io/DataInput/readInt()I 0
putfield com/flurry/android/c/V I
aload 0
aload 1
invokeinterface java/io/DataInput/readInt()I 0
putfield com/flurry/android/c/W I
aload 0
aload 1
invokeinterface java/io/DataInput/readInt()I 0
putfield com/flurry/android/c/X I
aload 0
aload 1
invokeinterface java/io/DataInput/readInt()I 0
putfield com/flurry/android/c/Y I
aload 0
aload 1
invokeinterface java/io/DataInput/readInt()I 0
putfield com/flurry/android/c/Z I
aload 0
aload 1
invokeinterface java/io/DataInput/readInt()I 0
putfield com/flurry/android/c/aa I
aload 0
aload 1
invokeinterface java/io/DataInput/readInt()I 0
putfield com/flurry/android/c/ab I
aload 0
aload 1
invokeinterface java/io/DataInput/readInt()I 0
putfield com/flurry/android/c/ac I
aload 0
aload 1
invokeinterface java/io/DataInput/readInt()I 0
putfield com/flurry/android/c/ad I
aload 0
aload 1
invokeinterface java/io/DataInput/readInt()I 0
putfield com/flurry/android/c/ae I
aload 0
aload 1
invokeinterface java/io/DataInput/readInt()I 0
putfield com/flurry/android/c/af I
aload 0
iconst_1
putfield com/flurry/android/c/ag Z
return
.limit locals 2
.limit stack 2
.end method

.method final a(Ljava/io/DataOutput;)V
aload 1
aload 0
getfield com/flurry/android/c/a B
invokeinterface java/io/DataOutput/writeByte(I)V 1
aload 1
aload 0
getfield com/flurry/android/c/b Ljava/lang/String;
invokeinterface java/io/DataOutput/writeUTF(Ljava/lang/String;)V 1
aload 1
aload 0
getfield com/flurry/android/c/c J
invokeinterface java/io/DataOutput/writeLong(J)V 2
aload 1
aload 0
getfield com/flurry/android/c/r J
invokeinterface java/io/DataOutput/writeLong(J)V 2
aload 1
aload 0
getfield com/flurry/android/c/d Ljava/lang/String;
invokeinterface java/io/DataOutput/writeUTF(Ljava/lang/String;)V 1
aload 1
aload 0
getfield com/flurry/android/c/e I
invokeinterface java/io/DataOutput/writeShort(I)V 1
aload 1
aload 0
getfield com/flurry/android/c/f I
invokeinterface java/io/DataOutput/writeInt(I)V 1
aload 1
aload 0
getfield com/flurry/android/c/g Ljava/lang/String;
invokeinterface java/io/DataOutput/writeUTF(Ljava/lang/String;)V 1
aload 1
aload 0
getfield com/flurry/android/c/h I
invokeinterface java/io/DataOutput/writeShort(I)V 1
aload 1
aload 0
getfield com/flurry/android/c/i I
invokeinterface java/io/DataOutput/writeInt(I)V 1
aload 1
aload 0
getfield com/flurry/android/c/j Ljava/lang/String;
invokeinterface java/io/DataOutput/writeUTF(Ljava/lang/String;)V 1
aload 1
aload 0
getfield com/flurry/android/c/k I
invokeinterface java/io/DataOutput/writeShort(I)V 1
aload 1
aload 0
getfield com/flurry/android/c/l I
invokeinterface java/io/DataOutput/writeInt(I)V 1
aload 1
aload 0
getfield com/flurry/android/c/ag Z
invokeinterface java/io/DataOutput/writeBoolean(Z)V 1
aload 0
getfield com/flurry/android/c/ag Z
ifeq L0
aload 1
aload 0
getfield com/flurry/android/c/s Ljava/lang/String;
invokeinterface java/io/DataOutput/writeUTF(Ljava/lang/String;)V 1
aload 1
aload 0
getfield com/flurry/android/c/t I
invokeinterface java/io/DataOutput/writeShort(I)V 1
aload 1
aload 0
getfield com/flurry/android/c/u I
invokeinterface java/io/DataOutput/writeInt(I)V 1
aload 1
aload 0
getfield com/flurry/android/c/v Ljava/lang/String;
invokeinterface java/io/DataOutput/writeUTF(Ljava/lang/String;)V 1
aload 1
aload 0
getfield com/flurry/android/c/w I
invokeinterface java/io/DataOutput/writeShort(I)V 1
aload 1
aload 0
getfield com/flurry/android/c/x I
invokeinterface java/io/DataOutput/writeInt(I)V 1
aload 1
aload 0
getfield com/flurry/android/c/y Ljava/lang/String;
invokeinterface java/io/DataOutput/writeUTF(Ljava/lang/String;)V 1
aload 1
aload 0
getfield com/flurry/android/c/z I
invokeinterface java/io/DataOutput/writeShort(I)V 1
aload 1
aload 0
getfield com/flurry/android/c/A I
invokeinterface java/io/DataOutput/writeInt(I)V 1
aload 1
aload 0
getfield com/flurry/android/c/B I
invokeinterface java/io/DataOutput/writeInt(I)V 1
aload 1
aload 0
getfield com/flurry/android/c/C I
invokeinterface java/io/DataOutput/writeInt(I)V 1
aload 1
aload 0
getfield com/flurry/android/c/m I
invokeinterface java/io/DataOutput/writeInt(I)V 1
aload 1
aload 0
getfield com/flurry/android/c/n I
invokeinterface java/io/DataOutput/writeInt(I)V 1
aload 1
aload 0
getfield com/flurry/android/c/o I
invokeinterface java/io/DataOutput/writeInt(I)V 1
aload 1
aload 0
getfield com/flurry/android/c/p I
invokeinterface java/io/DataOutput/writeInt(I)V 1
aload 1
aload 0
getfield com/flurry/android/c/D I
invokeinterface java/io/DataOutput/writeInt(I)V 1
aload 1
aload 0
getfield com/flurry/android/c/E I
invokeinterface java/io/DataOutput/writeInt(I)V 1
aload 1
aload 0
getfield com/flurry/android/c/F I
invokeinterface java/io/DataOutput/writeInt(I)V 1
aload 1
aload 0
getfield com/flurry/android/c/G I
invokeinterface java/io/DataOutput/writeInt(I)V 1
aload 1
aload 0
getfield com/flurry/android/c/H I
invokeinterface java/io/DataOutput/writeInt(I)V 1
aload 1
aload 0
getfield com/flurry/android/c/I I
invokeinterface java/io/DataOutput/writeInt(I)V 1
aload 1
aload 0
getfield com/flurry/android/c/J I
invokeinterface java/io/DataOutput/writeInt(I)V 1
aload 1
aload 0
getfield com/flurry/android/c/K I
invokeinterface java/io/DataOutput/writeInt(I)V 1
aload 1
aload 0
getfield com/flurry/android/c/q I
invokeinterface java/io/DataOutput/writeInt(I)V 1
aload 1
aload 0
getfield com/flurry/android/c/L I
invokeinterface java/io/DataOutput/writeInt(I)V 1
aload 1
aload 0
getfield com/flurry/android/c/M I
invokeinterface java/io/DataOutput/writeInt(I)V 1
aload 1
aload 0
getfield com/flurry/android/c/N I
invokeinterface java/io/DataOutput/writeInt(I)V 1
aload 1
aload 0
getfield com/flurry/android/c/O I
invokeinterface java/io/DataOutput/writeInt(I)V 1
aload 1
aload 0
getfield com/flurry/android/c/P I
invokeinterface java/io/DataOutput/writeInt(I)V 1
aload 1
aload 0
getfield com/flurry/android/c/Q I
invokeinterface java/io/DataOutput/writeInt(I)V 1
aload 1
aload 0
getfield com/flurry/android/c/R I
invokeinterface java/io/DataOutput/writeInt(I)V 1
aload 1
aload 0
getfield com/flurry/android/c/S I
invokeinterface java/io/DataOutput/writeInt(I)V 1
aload 1
aload 0
getfield com/flurry/android/c/T I
invokeinterface java/io/DataOutput/writeInt(I)V 1
aload 1
aload 0
getfield com/flurry/android/c/U I
invokeinterface java/io/DataOutput/writeInt(I)V 1
aload 1
aload 0
getfield com/flurry/android/c/V I
invokeinterface java/io/DataOutput/writeInt(I)V 1
aload 1
aload 0
getfield com/flurry/android/c/W I
invokeinterface java/io/DataOutput/writeInt(I)V 1
aload 1
aload 0
getfield com/flurry/android/c/X I
invokeinterface java/io/DataOutput/writeInt(I)V 1
aload 1
aload 0
getfield com/flurry/android/c/Y I
invokeinterface java/io/DataOutput/writeInt(I)V 1
aload 1
aload 0
getfield com/flurry/android/c/Z I
invokeinterface java/io/DataOutput/writeInt(I)V 1
aload 1
aload 0
getfield com/flurry/android/c/aa I
invokeinterface java/io/DataOutput/writeInt(I)V 1
aload 1
aload 0
getfield com/flurry/android/c/ab I
invokeinterface java/io/DataOutput/writeInt(I)V 1
aload 1
aload 0
getfield com/flurry/android/c/ac I
invokeinterface java/io/DataOutput/writeInt(I)V 1
aload 1
aload 0
getfield com/flurry/android/c/ad I
invokeinterface java/io/DataOutput/writeInt(I)V 1
aload 1
aload 0
getfield com/flurry/android/c/ae I
invokeinterface java/io/DataOutput/writeInt(I)V 1
aload 1
aload 0
getfield com/flurry/android/c/af I
invokeinterface java/io/DataOutput/writeInt(I)V 1
L0:
return
.limit locals 2
.limit stack 3
.end method

.method final b(Ljava/io/DataInput;)V
aload 0
aload 1
invokespecial com/flurry/android/c/c(Ljava/io/DataInput;)V
aload 0
aload 1
invokeinterface java/io/DataInput/readBoolean()Z 0
putfield com/flurry/android/c/ag Z
aload 0
getfield com/flurry/android/c/ag Z
ifeq L0
aload 0
aload 1
invokevirtual com/flurry/android/c/a(Ljava/io/DataInput;)V
L0:
return
.limit locals 2
.limit stack 2
.end method
