.bytecode 50.0
.class final synchronized com/flurry/android/e
.super com/flurry/android/ak

.field 'a' Ljava/lang/String;

.field 'b' B

.field 'c' B

.field 'd' Lcom/flurry/android/c;

.method <init>()V
aload 0
invokespecial com/flurry/android/ak/<init>()V
return
.limit locals 1
.limit stack 1
.end method

.method <init>(Ljava/io/DataInput;)V
aload 0
invokespecial com/flurry/android/ak/<init>()V
aload 0
aload 1
invokeinterface java/io/DataInput/readUTF()Ljava/lang/String; 0
putfield com/flurry/android/e/a Ljava/lang/String;
aload 0
aload 1
invokeinterface java/io/DataInput/readByte()B 0
putfield com/flurry/android/e/b B
aload 0
aload 1
invokeinterface java/io/DataInput/readByte()B 0
putfield com/flurry/android/e/c B
return
.limit locals 2
.limit stack 2
.end method

.method public final toString()Ljava/lang/String;
new java/lang/StringBuilder
dup
invokespecial java/lang/StringBuilder/<init>()V
ldc "{name: "
invokevirtual java/lang/StringBuilder/append(Ljava/lang/String;)Ljava/lang/StringBuilder;
aload 0
getfield com/flurry/android/e/a Ljava/lang/String;
invokevirtual java/lang/StringBuilder/append(Ljava/lang/String;)Ljava/lang/StringBuilder;
ldc ", blockId: "
invokevirtual java/lang/StringBuilder/append(Ljava/lang/String;)Ljava/lang/StringBuilder;
aload 0
getfield com/flurry/android/e/b B
invokevirtual java/lang/StringBuilder/append(I)Ljava/lang/StringBuilder;
ldc ", themeId: "
invokevirtual java/lang/StringBuilder/append(Ljava/lang/String;)Ljava/lang/StringBuilder;
aload 0
getfield com/flurry/android/e/c B
invokevirtual java/lang/StringBuilder/append(I)Ljava/lang/StringBuilder;
invokevirtual java/lang/StringBuilder/toString()Ljava/lang/String;
areturn
.limit locals 1
.limit stack 2
.end method
