.bytecode 50.0
.class public final synchronized com/flurry/android/FlurryAgent
.super java/lang/Object
.implements android/location/LocationListener

.field static 'a' Ljava/lang/String;

.field private static final 'b' [Ljava/lang/String;

.field private static volatile 'c' Ljava/lang/String;

.field private static volatile 'd' Ljava/lang/String;

.field private static volatile 'e' Ljava/lang/String;

.field private static volatile 'f' Ljava/lang/String;

.field private static volatile 'g' Ljava/lang/String;

.field private static final 'h' Lcom/flurry/android/FlurryAgent;

.field private static 'i' J

.field private static 'j' Z

.field private static 'k' Z

.field private static volatile 'kInsecureReportUrl' Ljava/lang/String;

.field private static volatile 'kSecureReportUrl' Ljava/lang/String;

.field private static 'l' Z

.field private static 'm' Z

.field private static 'n' Landroid/location/Criteria;

.field private static 'o' Z

.field private static 'p' Lcom/flurry/android/AppCircle;

.field private static 'q' Ljava/util/concurrent/atomic/AtomicInteger;

.field private static 'r' Ljava/util/concurrent/atomic/AtomicInteger;

.field private 'A' Ljava/lang/String;

.field private 'B' Ljava/lang/String;

.field private 'C' Z

.field private 'D' Ljava/util/List;

.field private 'E' Landroid/location/LocationManager;

.field private 'F' Ljava/lang/String;

.field private 'G' Z

.field private 'H' J

.field private 'I' [B

.field private 'J' Ljava/util/List;

.field private 'K' J

.field private 'L' J

.field private 'M' J

.field private 'N' Ljava/lang/String;

.field private 'O' Ljava/lang/String;

.field private 'P' B

.field private 'Q' Ljava/lang/String;

.field private 'R' B

.field private 'S' Ljava/lang/Long;

.field private 'T' I

.field private 'U' Landroid/location/Location;

.field private 'V' Ljava/util/Map;

.field private 'W' Ljava/util/List;

.field private 'X' Z

.field private 'Y' I

.field private 'Z' Ljava/util/List;

.field private 'aa' I

.field private 'ab' Lcom/flurry/android/v;

.field private final 's' Landroid/os/Handler;

.field private 't' Ljava/io/File;

.field private 'u' Ljava/io/File;

.field private volatile 'v' Z

.field private volatile 'w' Z

.field private 'x' J

.field private 'y' Ljava/util/Map;

.field private 'z' Ljava/lang/String;

.method static <clinit>()V
iconst_2
anewarray java/lang/String
dup
iconst_0
ldc "9774d56d682e549c"
aastore
dup
iconst_1
ldc "dead00beef"
aastore
putstatic com/flurry/android/FlurryAgent/b [Ljava/lang/String;
aconst_null
putstatic com/flurry/android/FlurryAgent/c Ljava/lang/String;
ldc "http://data.flurry.com/aap.do"
putstatic com/flurry/android/FlurryAgent/kInsecureReportUrl Ljava/lang/String;
ldc "https://data.flurry.com/aap.do"
putstatic com/flurry/android/FlurryAgent/kSecureReportUrl Ljava/lang/String;
aconst_null
putstatic com/flurry/android/FlurryAgent/d Ljava/lang/String;
ldc "http://ad.flurry.com/getCanvas.do"
putstatic com/flurry/android/FlurryAgent/e Ljava/lang/String;
aconst_null
putstatic com/flurry/android/FlurryAgent/f Ljava/lang/String;
ldc "http://ad.flurry.com/getAndroidApp.do"
putstatic com/flurry/android/FlurryAgent/g Ljava/lang/String;
new com/flurry/android/FlurryAgent
dup
invokespecial com/flurry/android/FlurryAgent/<init>()V
putstatic com/flurry/android/FlurryAgent/h Lcom/flurry/android/FlurryAgent;
ldc2_w 10000L
putstatic com/flurry/android/FlurryAgent/i J
iconst_1
putstatic com/flurry/android/FlurryAgent/j Z
iconst_0
putstatic com/flurry/android/FlurryAgent/k Z
iconst_0
putstatic com/flurry/android/FlurryAgent/l Z
iconst_1
putstatic com/flurry/android/FlurryAgent/m Z
aconst_null
putstatic com/flurry/android/FlurryAgent/n Landroid/location/Criteria;
iconst_0
putstatic com/flurry/android/FlurryAgent/o Z
new com/flurry/android/AppCircle
dup
invokespecial com/flurry/android/AppCircle/<init>()V
putstatic com/flurry/android/FlurryAgent/p Lcom/flurry/android/AppCircle;
new java/util/concurrent/atomic/AtomicInteger
dup
iconst_0
invokespecial java/util/concurrent/atomic/AtomicInteger/<init>(I)V
putstatic com/flurry/android/FlurryAgent/q Ljava/util/concurrent/atomic/AtomicInteger;
new java/util/concurrent/atomic/AtomicInteger
dup
iconst_0
invokespecial java/util/concurrent/atomic/AtomicInteger/<init>(I)V
putstatic com/flurry/android/FlurryAgent/r Ljava/util/concurrent/atomic/AtomicInteger;
return
.limit locals 0
.limit stack 4
.end method

.method private <init>()V
aload 0
invokespecial java/lang/Object/<init>()V
aload 0
aconst_null
putfield com/flurry/android/FlurryAgent/u Ljava/io/File;
aload 0
iconst_0
putfield com/flurry/android/FlurryAgent/v Z
aload 0
iconst_0
putfield com/flurry/android/FlurryAgent/w Z
aload 0
new java/util/WeakHashMap
dup
invokespecial java/util/WeakHashMap/<init>()V
putfield com/flurry/android/FlurryAgent/y Ljava/util/Map;
aload 0
iconst_1
putfield com/flurry/android/FlurryAgent/C Z
aload 0
new java/util/ArrayList
dup
invokespecial java/util/ArrayList/<init>()V
putfield com/flurry/android/FlurryAgent/J Ljava/util/List;
aload 0
ldc ""
putfield com/flurry/android/FlurryAgent/N Ljava/lang/String;
aload 0
ldc ""
putfield com/flurry/android/FlurryAgent/O Ljava/lang/String;
aload 0
iconst_m1
putfield com/flurry/android/FlurryAgent/P B
aload 0
ldc ""
putfield com/flurry/android/FlurryAgent/Q Ljava/lang/String;
aload 0
iconst_m1
putfield com/flurry/android/FlurryAgent/R B
aload 0
new java/util/HashMap
dup
invokespecial java/util/HashMap/<init>()V
putfield com/flurry/android/FlurryAgent/V Ljava/util/Map;
aload 0
new java/util/ArrayList
dup
invokespecial java/util/ArrayList/<init>()V
putfield com/flurry/android/FlurryAgent/W Ljava/util/List;
aload 0
new java/util/ArrayList
dup
invokespecial java/util/ArrayList/<init>()V
putfield com/flurry/android/FlurryAgent/Z Ljava/util/List;
aload 0
new com/flurry/android/v
dup
invokespecial com/flurry/android/v/<init>()V
putfield com/flurry/android/FlurryAgent/ab Lcom/flurry/android/v;
new android/os/HandlerThread
dup
ldc "FlurryAgent"
invokespecial android/os/HandlerThread/<init>(Ljava/lang/String;)V
astore 1
aload 1
invokevirtual android/os/HandlerThread/start()V
aload 0
new android/os/Handler
dup
aload 1
invokevirtual android/os/HandlerThread/getLooper()Landroid/os/Looper;
invokespecial android/os/Handler/<init>(Landroid/os/Looper;)V
putfield com/flurry/android/FlurryAgent/s Landroid/os/Handler;
return
.limit locals 2
.limit stack 4
.end method

.method private static a(D)D
dload 0
ldc2_w 1000.0D
dmul
invokestatic java/lang/Math/round(D)J
l2d
ldc2_w 1000.0D
ddiv
dreturn
.limit locals 2
.limit stack 4
.end method

.method static a(Landroid/content/Context;Ljava/lang/String;I)Landroid/view/View;
.catch java/lang/Throwable from L0 to L1 using L2
getstatic com/flurry/android/FlurryAgent/o Z
ifne L0
aconst_null
areturn
L0:
getstatic com/flurry/android/FlurryAgent/h Lcom/flurry/android/FlurryAgent;
getfield com/flurry/android/FlurryAgent/ab Lcom/flurry/android/v;
aload 0
aload 1
iload 2
invokevirtual com/flurry/android/v/a(Landroid/content/Context;Ljava/lang/String;I)Landroid/view/View;
astore 0
L1:
aload 0
areturn
L2:
astore 0
ldc "FlurryAgent"
ldc ""
aload 0
invokestatic com/flurry/android/ai/b(Ljava/lang/String;Ljava/lang/String;Ljava/lang/Throwable;)I
pop
aconst_null
areturn
.limit locals 3
.limit stack 4
.end method

.method static a(Ljava/lang/String;)Lcom/flurry/android/Offer;
getstatic com/flurry/android/FlurryAgent/o Z
ifne L0
aconst_null
areturn
L0:
getstatic com/flurry/android/FlurryAgent/h Lcom/flurry/android/FlurryAgent;
getfield com/flurry/android/FlurryAgent/ab Lcom/flurry/android/v;
aload 0
invokevirtual com/flurry/android/v/b(Ljava/lang/String;)Lcom/flurry/android/Offer;
areturn
.limit locals 1
.limit stack 2
.end method

.method private a(Lorg/apache/http/params/HttpParams;)Lorg/apache/http/client/HttpClient;
.catch java/lang/Exception from L0 to L1 using L2
L0:
invokestatic java/security/KeyStore/getDefaultType()Ljava/lang/String;
invokestatic java/security/KeyStore/getInstance(Ljava/lang/String;)Ljava/security/KeyStore;
astore 2
aload 2
aconst_null
aconst_null
invokevirtual java/security/KeyStore/load(Ljava/io/InputStream;[C)V
new com/flurry/android/aj
dup
aload 0
aload 2
invokespecial com/flurry/android/aj/<init>(Lcom/flurry/android/FlurryAgent;Ljava/security/KeyStore;)V
astore 2
new org/apache/http/conn/scheme/SchemeRegistry
dup
invokespecial org/apache/http/conn/scheme/SchemeRegistry/<init>()V
astore 3
aload 3
new org/apache/http/conn/scheme/Scheme
dup
ldc "http"
invokestatic org/apache/http/conn/scheme/PlainSocketFactory/getSocketFactory()Lorg/apache/http/conn/scheme/PlainSocketFactory;
bipush 80
invokespecial org/apache/http/conn/scheme/Scheme/<init>(Ljava/lang/String;Lorg/apache/http/conn/scheme/SocketFactory;I)V
invokevirtual org/apache/http/conn/scheme/SchemeRegistry/register(Lorg/apache/http/conn/scheme/Scheme;)Lorg/apache/http/conn/scheme/Scheme;
pop
aload 3
new org/apache/http/conn/scheme/Scheme
dup
ldc "https"
aload 2
sipush 443
invokespecial org/apache/http/conn/scheme/Scheme/<init>(Ljava/lang/String;Lorg/apache/http/conn/scheme/SocketFactory;I)V
invokevirtual org/apache/http/conn/scheme/SchemeRegistry/register(Lorg/apache/http/conn/scheme/Scheme;)Lorg/apache/http/conn/scheme/Scheme;
pop
new org/apache/http/impl/client/DefaultHttpClient
dup
new org/apache/http/impl/conn/tsccm/ThreadSafeClientConnManager
dup
aload 1
aload 3
invokespecial org/apache/http/impl/conn/tsccm/ThreadSafeClientConnManager/<init>(Lorg/apache/http/params/HttpParams;Lorg/apache/http/conn/scheme/SchemeRegistry;)V
aload 1
invokespecial org/apache/http/impl/client/DefaultHttpClient/<init>(Lorg/apache/http/conn/ClientConnectionManager;Lorg/apache/http/params/HttpParams;)V
astore 2
L1:
aload 2
areturn
L2:
astore 2
new org/apache/http/impl/client/DefaultHttpClient
dup
aload 1
invokespecial org/apache/http/impl/client/DefaultHttpClient/<init>(Lorg/apache/http/params/HttpParams;)V
areturn
.limit locals 4
.limit stack 6
.end method

.method private a(Landroid/content/Context;)V
.catch all from L0 to L1 using L2
.catch java/lang/Throwable from L1 to L3 using L4
.catch all from L1 to L3 using L5
.catch java/lang/Throwable from L6 to L7 using L8
.catch all from L6 to L7 using L9
.catch java/lang/Throwable from L10 to L11 using L8
.catch all from L10 to L11 using L9
.catch all from L11 to L12 using L2
.catch java/lang/Throwable from L12 to L13 using L14
.catch all from L12 to L13 using L2
.catch all from L13 to L15 using L2
.catch all from L15 to L16 using L2
.catch all from L16 to L17 using L2
.catch java/lang/Throwable from L18 to L19 using L8
.catch all from L18 to L19 using L9
.catch all from L20 to L21 using L9
.catch all from L21 to L22 using L2
.catch all from L23 to L24 using L2
.catch java/lang/Throwable from L24 to L25 using L14
.catch all from L24 to L25 using L2
.catch all from L26 to L27 using L2
.catch all from L28 to L29 using L2
aload 0
monitorenter
L0:
aload 0
aload 0
aload 1
invokespecial com/flurry/android/FlurryAgent/b(Landroid/content/Context;)Ljava/lang/String;
putfield com/flurry/android/FlurryAgent/F Ljava/lang/String;
aload 0
getfield com/flurry/android/FlurryAgent/u Ljava/io/File;
invokevirtual java/io/File/exists()Z
ifeq L28
ldc "FlurryAgent"
new java/lang/StringBuilder
dup
invokespecial java/lang/StringBuilder/<init>()V
ldc "loading persistent data: "
invokevirtual java/lang/StringBuilder/append(Ljava/lang/String;)Ljava/lang/StringBuilder;
aload 0
getfield com/flurry/android/FlurryAgent/u Ljava/io/File;
invokevirtual java/io/File/getAbsolutePath()Ljava/lang/String;
invokevirtual java/lang/StringBuilder/append(Ljava/lang/String;)Ljava/lang/StringBuilder;
invokevirtual java/lang/StringBuilder/toString()Ljava/lang/String;
invokestatic com/flurry/android/ai/c(Ljava/lang/String;Ljava/lang/String;)I
pop
L1:
new java/io/DataInputStream
dup
new java/io/FileInputStream
dup
aload 0
getfield com/flurry/android/FlurryAgent/u Ljava/io/File;
invokespecial java/io/FileInputStream/<init>(Ljava/io/File;)V
invokespecial java/io/DataInputStream/<init>(Ljava/io/InputStream;)V
astore 9
L3:
aload 9
astore 8
L6:
aload 9
invokevirtual java/io/DataInputStream/readUnsignedShort()I
ldc_w 46586
if_icmpne L30
L7:
aload 9
astore 8
L10:
aload 0
aload 9
invokespecial com/flurry/android/FlurryAgent/b(Ljava/io/DataInputStream;)V
L11:
aload 9
invokestatic com/flurry/android/r/a(Ljava/io/Closeable;)V
L12:
aload 0
getfield com/flurry/android/FlurryAgent/w Z
ifne L13
aload 0
getfield com/flurry/android/FlurryAgent/u Ljava/io/File;
invokevirtual java/io/File/delete()Z
ifeq L24
ldc "FlurryAgent"
ldc "Deleted persistence file"
invokestatic com/flurry/android/ai/a(Ljava/lang/String;Ljava/lang/String;)I
pop
L13:
aload 0
getfield com/flurry/android/FlurryAgent/w Z
ifne L15
aload 0
iconst_0
putfield com/flurry/android/FlurryAgent/G Z
aload 0
aload 0
getfield com/flurry/android/FlurryAgent/K J
putfield com/flurry/android/FlurryAgent/H J
aload 0
iconst_1
putfield com/flurry/android/FlurryAgent/w Z
L15:
aload 0
getfield com/flurry/android/FlurryAgent/F Ljava/lang/String;
ifnonnull L16
invokestatic java/lang/Math/random()D
invokestatic java/lang/Double/doubleToLongBits(D)J
lstore 2
invokestatic java/lang/System/nanoTime()J
lstore 4
aload 0
getfield com/flurry/android/FlurryAgent/z Ljava/lang/String;
invokevirtual java/lang/String/hashCode()I
bipush 37
imul
i2l
lstore 6
aload 0
new java/lang/StringBuilder
dup
invokespecial java/lang/StringBuilder/<init>()V
ldc "ID"
invokevirtual java/lang/StringBuilder/append(Ljava/lang/String;)Ljava/lang/StringBuilder;
lload 2
ldc2_w 37L
lload 4
lload 6
ladd
lmul
ladd
bipush 16
invokestatic java/lang/Long/toString(JI)Ljava/lang/String;
invokevirtual java/lang/StringBuilder/append(Ljava/lang/String;)Ljava/lang/StringBuilder;
invokevirtual java/lang/StringBuilder/toString()Ljava/lang/String;
putfield com/flurry/android/FlurryAgent/F Ljava/lang/String;
ldc "FlurryAgent"
ldc "Generated id"
invokestatic com/flurry/android/ai/c(Ljava/lang/String;Ljava/lang/String;)I
pop
L16:
aload 0
getfield com/flurry/android/FlurryAgent/ab Lcom/flurry/android/v;
aload 0
getfield com/flurry/android/FlurryAgent/F Ljava/lang/String;
invokevirtual com/flurry/android/v/a(Ljava/lang/String;)V
aload 0
getfield com/flurry/android/FlurryAgent/F Ljava/lang/String;
ldc "AND"
invokevirtual java/lang/String/startsWith(Ljava/lang/String;)Z
ifne L17
aload 0
getfield com/flurry/android/FlurryAgent/t Ljava/io/File;
invokevirtual java/io/File/exists()Z
ifne L17
aload 0
aload 1
aload 0
getfield com/flurry/android/FlurryAgent/F Ljava/lang/String;
invokespecial com/flurry/android/FlurryAgent/c(Landroid/content/Context;Ljava/lang/String;)V
L17:
aload 0
monitorexit
return
L30:
aload 9
astore 8
L18:
ldc "FlurryAgent"
ldc "Unexpected file type"
invokestatic com/flurry/android/ai/a(Ljava/lang/String;Ljava/lang/String;)I
pop
L19:
goto L11
L8:
astore 10
L31:
aload 9
astore 8
L20:
ldc "FlurryAgent"
ldc "Error when loading persistent file"
aload 10
invokestatic com/flurry/android/ai/b(Ljava/lang/String;Ljava/lang/String;Ljava/lang/Throwable;)I
pop
L21:
aload 9
invokestatic com/flurry/android/r/a(Ljava/io/Closeable;)V
L22:
goto L12
L2:
astore 1
aload 0
monitorexit
aload 1
athrow
L5:
astore 1
aconst_null
astore 8
L23:
aload 8
invokestatic com/flurry/android/r/a(Ljava/io/Closeable;)V
aload 1
athrow
L24:
ldc "FlurryAgent"
ldc "Cannot delete persistence file"
invokestatic com/flurry/android/ai/b(Ljava/lang/String;Ljava/lang/String;)I
pop
L25:
goto L13
L14:
astore 8
L26:
ldc "FlurryAgent"
ldc ""
aload 8
invokestatic com/flurry/android/ai/b(Ljava/lang/String;Ljava/lang/String;Ljava/lang/Throwable;)I
pop
L27:
goto L13
L28:
ldc "FlurryAgent"
ldc "Agent cache file doesn't exist."
invokestatic com/flurry/android/ai/c(Ljava/lang/String;Ljava/lang/String;)I
pop
L29:
goto L13
L9:
astore 1
goto L23
L4:
astore 10
aconst_null
astore 9
goto L31
.limit locals 11
.limit stack 10
.end method

.method static a(Landroid/content/Context;J)V
getstatic com/flurry/android/FlurryAgent/o Z
ifne L0
ldc "FlurryAgent"
ldc "Cannot accept Offer. AppCircle is not enabled"
invokestatic com/flurry/android/ai/d(Ljava/lang/String;Ljava/lang/String;)I
pop
L0:
getstatic com/flurry/android/FlurryAgent/h Lcom/flurry/android/FlurryAgent;
getfield com/flurry/android/FlurryAgent/ab Lcom/flurry/android/v;
aload 0
lload 1
invokevirtual com/flurry/android/v/a(Landroid/content/Context;J)V
return
.limit locals 3
.limit stack 4
.end method

.method static a(Landroid/content/Context;Ljava/lang/String;)V
getstatic com/flurry/android/FlurryAgent/o Z
ifne L0
return
L0:
getstatic com/flurry/android/FlurryAgent/h Lcom/flurry/android/FlurryAgent;
getfield com/flurry/android/FlurryAgent/ab Lcom/flurry/android/v;
aload 0
aload 1
invokevirtual com/flurry/android/v/a(Landroid/content/Context;Ljava/lang/String;)V
return
.limit locals 2
.limit stack 3
.end method

.method private a(Landroid/content/Context;Z)V
.catch all from L0 to L1 using L2
.catch all from L1 to L3 using L2
.catch all from L4 to L5 using L2
.catch all from L5 to L6 using L2
.catch all from L6 to L7 using L2
.catch all from L8 to L9 using L2
aload 0
monitorenter
aload 1
ifnull L1
L0:
aload 0
getfield com/flurry/android/FlurryAgent/y Ljava/util/Map;
aload 1
invokeinterface java/util/Map/remove(Ljava/lang/Object;)Ljava/lang/Object; 1
checkcast android/content/Context
ifnonnull L1
ldc "FlurryAgent"
ldc "onEndSession called without context from corresponding onStartSession"
invokestatic com/flurry/android/ai/d(Ljava/lang/String;Ljava/lang/String;)I
pop
L1:
aload 0
getfield com/flurry/android/FlurryAgent/v Z
ifeq L7
aload 0
getfield com/flurry/android/FlurryAgent/y Ljava/util/Map;
invokeinterface java/util/Map/isEmpty()Z 0
ifeq L7
ldc "FlurryAgent"
ldc "Ending session"
invokestatic com/flurry/android/ai/a(Ljava/lang/String;Ljava/lang/String;)I
pop
aload 0
invokespecial com/flurry/android/FlurryAgent/o()V
L3:
aload 1
ifnonnull L8
aconst_null
astore 5
L10:
aload 1
ifnull L5
L4:
aload 5
invokevirtual android/content/Context/getPackageName()Ljava/lang/String;
astore 1
aload 0
getfield com/flurry/android/FlurryAgent/A Ljava/lang/String;
aload 1
invokevirtual java/lang/String/equals(Ljava/lang/Object;)Z
ifne L5
ldc "FlurryAgent"
new java/lang/StringBuilder
dup
invokespecial java/lang/StringBuilder/<init>()V
ldc "onEndSession called from different application package, expected: "
invokevirtual java/lang/StringBuilder/append(Ljava/lang/String;)Ljava/lang/StringBuilder;
aload 0
getfield com/flurry/android/FlurryAgent/A Ljava/lang/String;
invokevirtual java/lang/StringBuilder/append(Ljava/lang/String;)Ljava/lang/StringBuilder;
ldc " actual: "
invokevirtual java/lang/StringBuilder/append(Ljava/lang/String;)Ljava/lang/StringBuilder;
aload 1
invokevirtual java/lang/StringBuilder/append(Ljava/lang/String;)Ljava/lang/StringBuilder;
invokevirtual java/lang/StringBuilder/toString()Ljava/lang/String;
invokestatic com/flurry/android/ai/b(Ljava/lang/String;Ljava/lang/String;)I
pop
L5:
invokestatic android/os/SystemClock/elapsedRealtime()J
lstore 3
aload 0
lload 3
putfield com/flurry/android/FlurryAgent/x J
aload 0
lload 3
aload 0
getfield com/flurry/android/FlurryAgent/L J
lsub
putfield com/flurry/android/FlurryAgent/M J
aload 0
getfield com/flurry/android/FlurryAgent/F Ljava/lang/String;
ifnonnull L6
ldc "FlurryAgent"
ldc "Not creating report because of bad Android ID or generated ID is null"
invokestatic com/flurry/android/ai/b(Ljava/lang/String;Ljava/lang/String;)I
pop
L6:
aload 0
new com/flurry/android/b
dup
aload 0
iload 2
aload 5
invokespecial com/flurry/android/b/<init>(Lcom/flurry/android/FlurryAgent;ZLandroid/content/Context;)V
invokespecial com/flurry/android/FlurryAgent/a(Ljava/lang/Runnable;)V
aload 0
iconst_0
putfield com/flurry/android/FlurryAgent/v Z
L7:
aload 0
monitorexit
return
L8:
aload 1
invokevirtual android/content/Context/getApplicationContext()Landroid/content/Context;
astore 5
L9:
goto L10
L2:
astore 1
aload 0
monitorexit
aload 1
athrow
.limit locals 6
.limit stack 6
.end method

.method static a(Lcom/flurry/android/AppCircleCallback;)V
getstatic com/flurry/android/FlurryAgent/h Lcom/flurry/android/FlurryAgent;
getfield com/flurry/android/FlurryAgent/ab Lcom/flurry/android/v;
aload 0
invokevirtual com/flurry/android/v/a(Lcom/flurry/android/AppCircleCallback;)V
return
.limit locals 1
.limit stack 2
.end method

.method static synthetic a(Lcom/flurry/android/FlurryAgent;Landroid/content/Context;)V
aload 0
aload 1
invokespecial com/flurry/android/FlurryAgent/a(Landroid/content/Context;)V
return
.limit locals 2
.limit stack 2
.end method

.method static synthetic a(Lcom/flurry/android/FlurryAgent;Landroid/content/Context;Z)V
.catch java/lang/Throwable from L0 to L1 using L2
.catch java/lang/Throwable from L1 to L3 using L2
.catch all from L3 to L4 using L5
.catch java/lang/Throwable from L4 to L6 using L2
.catch java/lang/Throwable from L6 to L7 using L2
.catch all from L8 to L9 using L5
.catch java/lang/Throwable from L9 to L2 using L2
aconst_null
astore 3
iload 2
ifeq L1
L0:
aload 0
aload 1
invokespecial com/flurry/android/FlurryAgent/d(Landroid/content/Context;)Landroid/location/Location;
astore 3
L1:
aload 0
monitorenter
L3:
aload 0
aload 3
putfield com/flurry/android/FlurryAgent/U Landroid/location/Location;
aload 0
monitorexit
L4:
getstatic com/flurry/android/FlurryAgent/o Z
ifeq L6
aload 0
getfield com/flurry/android/FlurryAgent/ab Lcom/flurry/android/v;
invokevirtual com/flurry/android/v/b()V
L6:
aload 0
aload 1
invokestatic com/flurry/android/FlurryAgent/e(Landroid/content/Context;)[B
putfield com/flurry/android/FlurryAgent/I [B
ldc "FlurryAgent"
new java/lang/StringBuilder
dup
invokespecial java/lang/StringBuilder/<init>()V
ldc "Fetching IMEI: "
invokevirtual java/lang/StringBuilder/append(Ljava/lang/String;)Ljava/lang/StringBuilder;
aload 0
getfield com/flurry/android/FlurryAgent/I [B
invokevirtual java/lang/StringBuilder/append(Ljava/lang/Object;)Ljava/lang/StringBuilder;
invokevirtual java/lang/StringBuilder/toString()Ljava/lang/String;
invokestatic com/flurry/android/ai/c(Ljava/lang/String;Ljava/lang/String;)I
pop
aload 0
iconst_1
invokespecial com/flurry/android/FlurryAgent/c(Z)V
L7:
return
L5:
astore 1
L8:
aload 0
monitorexit
L9:
aload 1
athrow
L2:
astore 0
ldc "FlurryAgent"
ldc ""
aload 0
invokestatic com/flurry/android/ai/b(Ljava/lang/String;Ljava/lang/String;Ljava/lang/Throwable;)I
pop
return
.limit locals 4
.limit stack 3
.end method

.method private a(Ljava/io/DataInputStream;)V
new java/util/HashMap
dup
invokespecial java/util/HashMap/<init>()V
astore 10
new java/util/HashMap
dup
invokespecial java/util/HashMap/<init>()V
astore 11
new java/util/HashMap
dup
invokespecial java/util/HashMap/<init>()V
astore 12
new java/util/HashMap
dup
invokespecial java/util/HashMap/<init>()V
astore 13
new java/util/HashMap
dup
invokespecial java/util/HashMap/<init>()V
astore 14
new java/util/HashMap
dup
invokespecial java/util/HashMap/<init>()V
astore 15
L0:
aload 1
invokevirtual java/io/DataInputStream/readUnsignedShort()I
istore 4
aload 1
invokevirtual java/io/DataInputStream/readInt()I
istore 3
iload 4
tableswitch 258
L1
L2
L3
L3
L4
L5
L6
L3
L7
L3
L8
L9
L10
L11
L12
L13
default : L3
L3:
ldc "FlurryAgent"
new java/lang/StringBuilder
dup
invokespecial java/lang/StringBuilder/<init>()V
ldc "Unknown chunkType: "
invokevirtual java/lang/StringBuilder/append(Ljava/lang/String;)Ljava/lang/StringBuilder;
iload 4
invokevirtual java/lang/StringBuilder/append(I)Ljava/lang/StringBuilder;
invokevirtual java/lang/StringBuilder/toString()Ljava/lang/String;
invokestatic com/flurry/android/ai/a(Ljava/lang/String;Ljava/lang/String;)I
pop
aload 1
iload 3
invokevirtual java/io/DataInputStream/skipBytes(I)I
pop
L6:
iload 4
sipush 264
if_icmpne L0
getstatic com/flurry/android/FlurryAgent/o Z
ifeq L14
aload 10
invokeinterface java/util/Map/isEmpty()Z 0
ifeq L15
ldc "FlurryAgent"
ldc "No ads from server"
invokestatic com/flurry/android/ai/a(Ljava/lang/String;Ljava/lang/String;)I
pop
L15:
aload 0
getfield com/flurry/android/FlurryAgent/ab Lcom/flurry/android/v;
aload 10
aload 13
aload 14
aload 11
aload 12
aload 15
invokevirtual com/flurry/android/v/a(Ljava/util/Map;Ljava/util/Map;Ljava/util/Map;Ljava/util/Map;Ljava/util/Map;Ljava/util/Map;)V
L14:
return
L1:
aload 1
invokevirtual java/io/DataInputStream/readInt()I
pop
goto L6
L2:
aload 1
invokevirtual java/io/DataInputStream/readByte()B
istore 2
aload 1
invokevirtual java/io/DataInputStream/readUnsignedShort()I
istore 5
iload 5
anewarray com/flurry/android/w
astore 8
iconst_0
istore 3
L16:
iload 3
iload 5
if_icmpge L17
aload 8
iload 3
new com/flurry/android/w
dup
aload 1
invokespecial com/flurry/android/w/<init>(Ljava/io/DataInput;)V
aastore
iload 3
iconst_1
iadd
istore 3
goto L16
L17:
aload 10
iload 2
invokestatic java/lang/Byte/valueOf(B)Ljava/lang/Byte;
aload 8
invokeinterface java/util/Map/put(Ljava/lang/Object;Ljava/lang/Object;)Ljava/lang/Object; 2
pop
goto L6
L4:
aload 1
invokevirtual java/io/DataInputStream/readUnsignedShort()I
istore 5
iconst_0
istore 3
L18:
iload 3
iload 5
if_icmpge L6
new com/flurry/android/AdImage
dup
aload 1
invokespecial com/flurry/android/AdImage/<init>(Ljava/io/DataInput;)V
astore 8
aload 11
aload 8
getfield com/flurry/android/AdImage/a J
invokestatic java/lang/Long/valueOf(J)Ljava/lang/Long;
aload 8
invokeinterface java/util/Map/put(Ljava/lang/Object;Ljava/lang/Object;)Ljava/lang/Object; 2
pop
iload 3
iconst_1
iadd
istore 3
goto L18
L5:
aload 1
invokevirtual java/io/DataInputStream/readInt()I
istore 5
iconst_0
istore 3
L19:
iload 3
iload 5
if_icmpge L6
new com/flurry/android/e
dup
aload 1
invokespecial com/flurry/android/e/<init>(Ljava/io/DataInput;)V
astore 8
aload 13
aload 8
getfield com/flurry/android/e/a Ljava/lang/String;
aload 8
invokeinterface java/util/Map/put(Ljava/lang/Object;Ljava/lang/Object;)Ljava/lang/Object; 2
pop
ldc "FlurryAgent"
new java/lang/StringBuilder
dup
invokespecial java/lang/StringBuilder/<init>()V
ldc "Parsed hook: "
invokevirtual java/lang/StringBuilder/append(Ljava/lang/String;)Ljava/lang/StringBuilder;
aload 8
invokevirtual java/lang/StringBuilder/append(Ljava/lang/Object;)Ljava/lang/StringBuilder;
invokevirtual java/lang/StringBuilder/toString()Ljava/lang/String;
invokestatic com/flurry/android/ai/a(Ljava/lang/String;Ljava/lang/String;)I
pop
iload 3
iconst_1
iadd
istore 3
goto L19
L10:
aload 1
iload 3
invokevirtual java/io/DataInputStream/skipBytes(I)I
pop
goto L6
L7:
aload 1
invokevirtual java/io/DataInputStream/readByte()B
istore 5
iconst_0
istore 3
L20:
iload 3
iload 5
if_icmpge L6
new com/flurry/android/c
dup
aload 1
invokespecial com/flurry/android/c/<init>(Ljava/io/DataInput;)V
astore 8
aload 14
aload 8
getfield com/flurry/android/c/a B
invokestatic java/lang/Byte/valueOf(B)Ljava/lang/Byte;
aload 8
invokeinterface java/util/Map/put(Ljava/lang/Object;Ljava/lang/Object;)Ljava/lang/Object; 2
pop
iload 3
iconst_1
iadd
istore 3
goto L20
L11:
aload 1
invokevirtual java/io/DataInputStream/readByte()B
istore 5
iconst_0
istore 3
L21:
iload 3
iload 5
if_icmpge L6
aload 14
aload 1
invokevirtual java/io/DataInputStream/readByte()B
invokestatic java/lang/Byte/valueOf(B)Ljava/lang/Byte;
invokeinterface java/util/Map/get(Ljava/lang/Object;)Ljava/lang/Object; 1
checkcast com/flurry/android/c
astore 8
aload 8
ifnull L22
aload 8
aload 1
invokevirtual com/flurry/android/c/a(Ljava/io/DataInput;)V
L22:
iload 3
iconst_1
iadd
istore 3
goto L21
L8:
aload 1
invokevirtual java/io/DataInputStream/readInt()I
istore 5
iconst_0
istore 3
L23:
iload 3
iload 5
if_icmpge L6
aload 1
invokevirtual java/io/DataInputStream/readLong()J
lstore 6
aload 15
aload 1
invokevirtual java/io/DataInputStream/readShort()S
invokestatic java/lang/Short/valueOf(S)Ljava/lang/Short;
lload 6
invokestatic java/lang/Long/valueOf(J)Ljava/lang/Long;
invokeinterface java/util/Map/put(Ljava/lang/Object;Ljava/lang/Object;)Ljava/lang/Object; 2
pop
iload 3
iconst_1
iadd
istore 3
goto L23
L12:
aload 1
invokevirtual java/io/DataInputStream/readLong()J
lstore 6
aload 12
lload 6
invokestatic java/lang/Long/valueOf(J)Ljava/lang/Long;
invokeinterface java/util/Map/get(Ljava/lang/Object;)Ljava/lang/Object; 1
checkcast com/flurry/android/am
astore 9
aload 9
astore 8
aload 9
ifnonnull L24
new com/flurry/android/am
dup
invokespecial com/flurry/android/am/<init>()V
astore 8
L24:
aload 8
aload 1
invokevirtual java/io/DataInputStream/readUTF()Ljava/lang/String;
putfield com/flurry/android/am/a Ljava/lang/String;
aload 8
aload 1
invokevirtual java/io/DataInputStream/readInt()I
putfield com/flurry/android/am/c I
aload 12
lload 6
invokestatic java/lang/Long/valueOf(J)Ljava/lang/Long;
aload 8
invokeinterface java/util/Map/put(Ljava/lang/Object;Ljava/lang/Object;)Ljava/lang/Object; 2
pop
goto L6
L9:
aload 1
iload 3
invokevirtual java/io/DataInputStream/skipBytes(I)I
pop
goto L6
L13:
aload 1
iload 3
invokevirtual java/io/DataInputStream/skipBytes(I)I
pop
goto L6
.limit locals 16
.limit stack 7
.end method

.method private a(Ljava/lang/Runnable;)V
aload 0
getfield com/flurry/android/FlurryAgent/s Landroid/os/Handler;
aload 1
invokevirtual android/os/Handler/post(Ljava/lang/Runnable;)Z
pop
return
.limit locals 2
.limit stack 2
.end method

.method private a(Ljava/lang/String;Ljava/lang/String;Ljava/lang/String;)V
.catch all from L0 to L1 using L2
.catch all from L3 to L4 using L2
.catch all from L5 to L6 using L2
aload 0
monitorenter
L0:
aload 0
getfield com/flurry/android/FlurryAgent/Z Ljava/util/List;
ifnonnull L3
ldc "FlurryAgent"
new java/lang/StringBuilder
dup
invokespecial java/lang/StringBuilder/<init>()V
ldc "onError called before onStartSession.  Error: "
invokevirtual java/lang/StringBuilder/append(Ljava/lang/String;)Ljava/lang/StringBuilder;
aload 1
invokevirtual java/lang/StringBuilder/append(Ljava/lang/String;)Ljava/lang/StringBuilder;
invokevirtual java/lang/StringBuilder/toString()Ljava/lang/String;
invokestatic com/flurry/android/ai/b(Ljava/lang/String;Ljava/lang/String;)I
pop
L1:
aload 0
monitorexit
return
L3:
aload 0
aload 0
getfield com/flurry/android/FlurryAgent/T I
iconst_1
iadd
putfield com/flurry/android/FlurryAgent/T I
aload 0
getfield com/flurry/android/FlurryAgent/Z Ljava/util/List;
invokeinterface java/util/List/size()I 0
bipush 10
if_icmpge L5
new com/flurry/android/ab
dup
invokespecial com/flurry/android/ab/<init>()V
astore 4
aload 4
invokestatic java/lang/System/currentTimeMillis()J
putfield com/flurry/android/ab/b J
aload 4
aload 1
sipush 255
invokestatic com/flurry/android/r/a(Ljava/lang/String;I)Ljava/lang/String;
putfield com/flurry/android/ab/c Ljava/lang/String;
aload 4
aload 2
sipush 512
invokestatic com/flurry/android/r/a(Ljava/lang/String;I)Ljava/lang/String;
putfield com/flurry/android/ab/d Ljava/lang/String;
aload 4
aload 3
sipush 255
invokestatic com/flurry/android/r/a(Ljava/lang/String;I)Ljava/lang/String;
putfield com/flurry/android/ab/e Ljava/lang/String;
aload 0
getfield com/flurry/android/FlurryAgent/Z Ljava/util/List;
aload 4
invokeinterface java/util/List/add(Ljava/lang/Object;)Z 1
pop
ldc "FlurryAgent"
new java/lang/StringBuilder
dup
invokespecial java/lang/StringBuilder/<init>()V
ldc "Error logged: "
invokevirtual java/lang/StringBuilder/append(Ljava/lang/String;)Ljava/lang/StringBuilder;
aload 4
getfield com/flurry/android/ab/c Ljava/lang/String;
invokevirtual java/lang/StringBuilder/append(Ljava/lang/String;)Ljava/lang/StringBuilder;
invokevirtual java/lang/StringBuilder/toString()Ljava/lang/String;
invokestatic com/flurry/android/ai/a(Ljava/lang/String;Ljava/lang/String;)I
pop
L4:
goto L1
L2:
astore 1
aload 0
monitorexit
aload 1
athrow
L5:
ldc "FlurryAgent"
ldc "Max errors logged. No more errors logged."
invokestatic com/flurry/android/ai/a(Ljava/lang/String;Ljava/lang/String;)I
pop
L6:
goto L1
.limit locals 5
.limit stack 3
.end method

.method private a(Ljava/lang/String;Ljava/util/Map;Z)V
.catch all from L0 to L1 using L2
.catch all from L3 to L4 using L2
.catch all from L5 to L6 using L2
.catch all from L6 to L7 using L2
.catch all from L8 to L9 using L2
.catch all from L9 to L10 using L2
.catch all from L11 to L12 using L2
.catch all from L13 to L14 using L2
.catch all from L15 to L16 using L2
.catch all from L17 to L18 using L2
.catch all from L19 to L20 using L2
aload 0
monitorenter
L0:
aload 0
getfield com/flurry/android/FlurryAgent/W Ljava/util/List;
ifnonnull L3
ldc "FlurryAgent"
new java/lang/StringBuilder
dup
invokespecial java/lang/StringBuilder/<init>()V
ldc "onEvent called before onStartSession.  Event: "
invokevirtual java/lang/StringBuilder/append(Ljava/lang/String;)Ljava/lang/StringBuilder;
aload 1
invokevirtual java/lang/StringBuilder/append(Ljava/lang/String;)Ljava/lang/StringBuilder;
invokevirtual java/lang/StringBuilder/toString()Ljava/lang/String;
invokestatic com/flurry/android/ai/b(Ljava/lang/String;Ljava/lang/String;)I
pop
L1:
aload 0
monitorexit
return
L3:
invokestatic android/os/SystemClock/elapsedRealtime()J
lstore 4
aload 0
getfield com/flurry/android/FlurryAgent/L J
lstore 6
aload 1
sipush 255
invokestatic com/flurry/android/r/a(Ljava/lang/String;I)Ljava/lang/String;
astore 8
aload 8
invokevirtual java/lang/String/length()I
ifeq L1
aload 0
getfield com/flurry/android/FlurryAgent/V Ljava/util/Map;
aload 8
invokeinterface java/util/Map/get(Ljava/lang/Object;)Ljava/lang/Object; 1
checkcast com/flurry/android/g
astore 1
L4:
aload 1
ifnonnull L13
L5:
aload 0
getfield com/flurry/android/FlurryAgent/V Ljava/util/Map;
invokeinterface java/util/Map/size()I 0
bipush 100
if_icmpge L11
new com/flurry/android/g
dup
invokespecial com/flurry/android/g/<init>()V
astore 1
aload 1
iconst_1
putfield com/flurry/android/g/a I
aload 0
getfield com/flurry/android/FlurryAgent/V Ljava/util/Map;
aload 8
aload 1
invokeinterface java/util/Map/put(Ljava/lang/Object;Ljava/lang/Object;)Ljava/lang/Object; 2
pop
ldc "FlurryAgent"
new java/lang/StringBuilder
dup
invokespecial java/lang/StringBuilder/<init>()V
ldc "Event count incremented: "
invokevirtual java/lang/StringBuilder/append(Ljava/lang/String;)Ljava/lang/StringBuilder;
aload 8
invokevirtual java/lang/StringBuilder/append(Ljava/lang/String;)Ljava/lang/StringBuilder;
invokevirtual java/lang/StringBuilder/toString()Ljava/lang/String;
invokestatic com/flurry/android/ai/a(Ljava/lang/String;Ljava/lang/String;)I
pop
L6:
getstatic com/flurry/android/FlurryAgent/j Z
ifeq L19
aload 0
getfield com/flurry/android/FlurryAgent/W Ljava/util/List;
invokeinterface java/util/List/size()I 0
sipush 200
if_icmpge L19
aload 0
getfield com/flurry/android/FlurryAgent/Y I
sipush 16000
if_icmpge L19
L7:
aload 2
ifnonnull L21
L8:
invokestatic java/util/Collections/emptyMap()Ljava/util/Map;
astore 1
L9:
aload 1
invokeinterface java/util/Map/size()I 0
bipush 10
if_icmple L15
ldc "FlurryAgent"
invokestatic com/flurry/android/ai/a(Ljava/lang/String;)Z
ifeq L1
ldc "FlurryAgent"
new java/lang/StringBuilder
dup
invokespecial java/lang/StringBuilder/<init>()V
ldc "MaxEventParams exceeded: "
invokevirtual java/lang/StringBuilder/append(Ljava/lang/String;)Ljava/lang/StringBuilder;
aload 1
invokeinterface java/util/Map/size()I 0
invokevirtual java/lang/StringBuilder/append(I)Ljava/lang/StringBuilder;
invokevirtual java/lang/StringBuilder/toString()Ljava/lang/String;
invokestatic com/flurry/android/ai/a(Ljava/lang/String;Ljava/lang/String;)I
pop
L10:
goto L1
L2:
astore 1
aload 0
monitorexit
aload 1
athrow
L11:
ldc "FlurryAgent"
invokestatic com/flurry/android/ai/a(Ljava/lang/String;)Z
ifeq L6
ldc "FlurryAgent"
new java/lang/StringBuilder
dup
invokespecial java/lang/StringBuilder/<init>()V
ldc "Too many different events. Event not counted: "
invokevirtual java/lang/StringBuilder/append(Ljava/lang/String;)Ljava/lang/StringBuilder;
aload 8
invokevirtual java/lang/StringBuilder/append(Ljava/lang/String;)Ljava/lang/StringBuilder;
invokevirtual java/lang/StringBuilder/toString()Ljava/lang/String;
invokestatic com/flurry/android/ai/a(Ljava/lang/String;Ljava/lang/String;)I
pop
L12:
goto L6
L13:
aload 1
aload 1
getfield com/flurry/android/g/a I
iconst_1
iadd
putfield com/flurry/android/g/a I
ldc "FlurryAgent"
new java/lang/StringBuilder
dup
invokespecial java/lang/StringBuilder/<init>()V
ldc "Event count incremented: "
invokevirtual java/lang/StringBuilder/append(Ljava/lang/String;)Ljava/lang/StringBuilder;
aload 8
invokevirtual java/lang/StringBuilder/append(Ljava/lang/String;)Ljava/lang/StringBuilder;
invokevirtual java/lang/StringBuilder/toString()Ljava/lang/String;
invokestatic com/flurry/android/ai/a(Ljava/lang/String;Ljava/lang/String;)I
pop
L14:
goto L6
L15:
new com/flurry/android/i
dup
aload 8
aload 1
lload 4
lload 6
lsub
iload 3
invokespecial com/flurry/android/i/<init>(Ljava/lang/String;Ljava/util/Map;JZ)V
astore 1
aload 1
invokevirtual com/flurry/android/i/a()[B
arraylength
aload 0
getfield com/flurry/android/FlurryAgent/Y I
iadd
sipush 16000
if_icmpgt L17
aload 0
getfield com/flurry/android/FlurryAgent/W Ljava/util/List;
aload 1
invokeinterface java/util/List/add(Ljava/lang/Object;)Z 1
pop
aload 0
aload 0
getfield com/flurry/android/FlurryAgent/Y I
aload 1
invokevirtual com/flurry/android/i/a()[B
arraylength
iadd
putfield com/flurry/android/FlurryAgent/Y I
ldc "FlurryAgent"
new java/lang/StringBuilder
dup
invokespecial java/lang/StringBuilder/<init>()V
ldc "Logged event: "
invokevirtual java/lang/StringBuilder/append(Ljava/lang/String;)Ljava/lang/StringBuilder;
aload 8
invokevirtual java/lang/StringBuilder/append(Ljava/lang/String;)Ljava/lang/StringBuilder;
invokevirtual java/lang/StringBuilder/toString()Ljava/lang/String;
invokestatic com/flurry/android/ai/a(Ljava/lang/String;Ljava/lang/String;)I
pop
L16:
goto L1
L17:
aload 0
sipush 16000
putfield com/flurry/android/FlurryAgent/Y I
aload 0
iconst_0
putfield com/flurry/android/FlurryAgent/X Z
ldc "FlurryAgent"
ldc "Event Log size exceeded. No more event details logged."
invokestatic com/flurry/android/ai/a(Ljava/lang/String;Ljava/lang/String;)I
pop
L18:
goto L1
L19:
aload 0
iconst_0
putfield com/flurry/android/FlurryAgent/X Z
L20:
goto L1
L21:
aload 2
astore 1
goto L9
.limit locals 9
.limit stack 8
.end method

.method static a(Ljava/util/List;)V
getstatic com/flurry/android/FlurryAgent/o Z
ifne L0
return
L0:
getstatic com/flurry/android/FlurryAgent/h Lcom/flurry/android/FlurryAgent;
getfield com/flurry/android/FlurryAgent/ab Lcom/flurry/android/v;
aload 0
invokevirtual com/flurry/android/v/a(Ljava/util/List;)V
return
.limit locals 1
.limit stack 2
.end method

.method static a(Z)V
getstatic com/flurry/android/FlurryAgent/o Z
ifne L0
return
L0:
getstatic com/flurry/android/FlurryAgent/h Lcom/flurry/android/FlurryAgent;
getfield com/flurry/android/FlurryAgent/ab Lcom/flurry/android/v;
iload 0
invokevirtual com/flurry/android/v/a(Z)V
return
.limit locals 1
.limit stack 2
.end method

.method static a()Z
getstatic com/flurry/android/FlurryAgent/h Lcom/flurry/android/FlurryAgent;
getfield com/flurry/android/FlurryAgent/ab Lcom/flurry/android/v;
invokevirtual com/flurry/android/v/h()Z
ireturn
.limit locals 0
.limit stack 1
.end method

.method static synthetic a(Lcom/flurry/android/FlurryAgent;)Z
aload 0
getfield com/flurry/android/FlurryAgent/w Z
ireturn
.limit locals 1
.limit stack 1
.end method

.method private static a(Ljava/io/File;)Z
aload 0
invokevirtual java/io/File/getParentFile()Ljava/io/File;
astore 0
aload 0
invokevirtual java/io/File/mkdirs()Z
ifne L0
aload 0
invokevirtual java/io/File/exists()Z
ifne L0
ldc "FlurryAgent"
new java/lang/StringBuilder
dup
invokespecial java/lang/StringBuilder/<init>()V
ldc "Unable to create persistent dir: "
invokevirtual java/lang/StringBuilder/append(Ljava/lang/String;)Ljava/lang/StringBuilder;
aload 0
invokevirtual java/lang/StringBuilder/append(Ljava/lang/Object;)Ljava/lang/StringBuilder;
invokevirtual java/lang/StringBuilder/toString()Ljava/lang/String;
invokestatic com/flurry/android/ai/b(Ljava/lang/String;Ljava/lang/String;)I
pop
iconst_0
ireturn
L0:
iconst_1
ireturn
.limit locals 1
.limit stack 3
.end method

.method private a([B)Z
.catch java/lang/Exception from L0 to L1 using L2
.catch all from L3 to L4 using L5
.catch all from L6 to L7 using L5
.catch all from L8 to L9 using L5
.catch java/lang/Exception from L9 to L10 using L11
.catch all from L12 to L13 using L5
invokestatic com/flurry/android/FlurryAgent/m()Ljava/lang/String;
astore 4
aload 4
ifnonnull L0
iconst_0
istore 3
L14:
iload 3
ireturn
L0:
aload 0
aload 1
aload 4
invokespecial com/flurry/android/FlurryAgent/a([BLjava/lang/String;)Z
istore 2
L1:
iload 2
istore 3
iload 2
ifne L14
iload 2
istore 3
getstatic com/flurry/android/FlurryAgent/c Ljava/lang/String;
ifnonnull L14
iload 2
istore 3
getstatic com/flurry/android/FlurryAgent/k Z
ifeq L14
iload 2
istore 3
getstatic com/flurry/android/FlurryAgent/l Z
ifne L14
getstatic com/flurry/android/FlurryAgent/h Lcom/flurry/android/FlurryAgent;
astore 4
aload 4
monitorenter
L3:
iconst_1
putstatic com/flurry/android/FlurryAgent/l Z
invokestatic com/flurry/android/FlurryAgent/m()Ljava/lang/String;
astore 5
L4:
aload 5
ifnonnull L8
L6:
aload 4
monitorexit
L7:
iconst_0
ireturn
L2:
astore 4
ldc "FlurryAgent"
new java/lang/StringBuilder
dup
invokespecial java/lang/StringBuilder/<init>()V
ldc "Sending report exception: "
invokevirtual java/lang/StringBuilder/append(Ljava/lang/String;)Ljava/lang/StringBuilder;
aload 4
invokevirtual java/lang/Exception/getMessage()Ljava/lang/String;
invokevirtual java/lang/StringBuilder/append(Ljava/lang/String;)Ljava/lang/StringBuilder;
invokevirtual java/lang/StringBuilder/toString()Ljava/lang/String;
invokestatic com/flurry/android/ai/a(Ljava/lang/String;Ljava/lang/String;)I
pop
iconst_0
istore 2
goto L1
L8:
aload 4
monitorexit
L9:
aload 0
aload 1
aload 5
invokespecial com/flurry/android/FlurryAgent/a([BLjava/lang/String;)Z
istore 3
L10:
iload 3
ireturn
L5:
astore 1
L12:
aload 4
monitorexit
L13:
aload 1
athrow
L11:
astore 1
iload 2
ireturn
.limit locals 6
.limit stack 3
.end method

.method private a([BLjava/lang/String;)Z
.catch all from L0 to L1 using L2
.catch all from L3 to L4 using L2
.catch all from L5 to L6 using L7
.catch all from L6 to L8 using L2
.catch all from L9 to L10 using L2
.catch all from L11 to L12 using L2
.catch all from L13 to L14 using L2
.catch all from L14 to L15 using L2
iconst_1
istore 5
ldc "local"
aload 2
invokevirtual java/lang/String/equals(Ljava/lang/Object;)Z
ifeq L16
iconst_1
ireturn
L16:
ldc "FlurryAgent"
new java/lang/StringBuilder
dup
invokespecial java/lang/StringBuilder/<init>()V
ldc "Sending report to: "
invokevirtual java/lang/StringBuilder/append(Ljava/lang/String;)Ljava/lang/StringBuilder;
aload 2
invokevirtual java/lang/StringBuilder/append(Ljava/lang/String;)Ljava/lang/StringBuilder;
invokevirtual java/lang/StringBuilder/toString()Ljava/lang/String;
invokestatic com/flurry/android/ai/a(Ljava/lang/String;Ljava/lang/String;)I
pop
new org/apache/http/entity/ByteArrayEntity
dup
aload 1
invokespecial org/apache/http/entity/ByteArrayEntity/<init>([B)V
astore 1
aload 1
ldc "application/octet-stream"
invokevirtual org/apache/http/entity/ByteArrayEntity/setContentType(Ljava/lang/String;)V
new org/apache/http/client/methods/HttpPost
dup
aload 2
invokespecial org/apache/http/client/methods/HttpPost/<init>(Ljava/lang/String;)V
astore 2
aload 2
aload 1
invokevirtual org/apache/http/client/methods/HttpPost/setEntity(Lorg/apache/http/HttpEntity;)V
new org/apache/http/params/BasicHttpParams
dup
invokespecial org/apache/http/params/BasicHttpParams/<init>()V
astore 1
aload 1
sipush 10000
invokestatic org/apache/http/params/HttpConnectionParams/setConnectionTimeout(Lorg/apache/http/params/HttpParams;I)V
aload 1
sipush 15000
invokestatic org/apache/http/params/HttpConnectionParams/setSoTimeout(Lorg/apache/http/params/HttpParams;I)V
aload 2
invokevirtual org/apache/http/client/methods/HttpPost/getParams()Lorg/apache/http/params/HttpParams;
ldc "http.protocol.expect-continue"
iconst_0
invokeinterface org/apache/http/params/HttpParams/setBooleanParameter(Ljava/lang/String;Z)Lorg/apache/http/params/HttpParams; 2
pop
aload 0
aload 1
invokespecial com/flurry/android/FlurryAgent/a(Lorg/apache/http/params/HttpParams;)Lorg/apache/http/client/HttpClient;
aload 2
invokeinterface org/apache/http/client/HttpClient/execute(Lorg/apache/http/client/methods/HttpUriRequest;)Lorg/apache/http/HttpResponse; 1
astore 1
aload 1
invokeinterface org/apache/http/HttpResponse/getStatusLine()Lorg/apache/http/StatusLine; 0
invokeinterface org/apache/http/StatusLine/getStatusCode()I 0
istore 3
aload 0
monitorenter
iload 3
sipush 200
if_icmpne L14
L0:
ldc "FlurryAgent"
ldc "Report successful"
invokestatic com/flurry/android/ai/a(Ljava/lang/String;Ljava/lang/String;)I
pop
aload 0
iconst_1
putfield com/flurry/android/FlurryAgent/G Z
aload 0
getfield com/flurry/android/FlurryAgent/J Ljava/util/List;
aload 0
getfield com/flurry/android/FlurryAgent/D Ljava/util/List;
invokeinterface java/util/List/removeAll(Ljava/util/Collection;)Z 1
pop
aload 1
invokeinterface org/apache/http/HttpResponse/getEntity()Lorg/apache/http/HttpEntity; 0
astore 1
ldc "FlurryAgent"
ldc "Processing report response"
invokestatic com/flurry/android/ai/a(Ljava/lang/String;Ljava/lang/String;)I
pop
L1:
iload 5
istore 4
aload 1
ifnull L9
L3:
aload 1
invokeinterface org/apache/http/HttpEntity/getContentLength()J 0
lstore 6
L4:
iload 5
istore 4
lload 6
lconst_0
lcmp
ifeq L9
L5:
aload 0
new java/io/DataInputStream
dup
aload 1
invokeinterface org/apache/http/HttpEntity/getContent()Ljava/io/InputStream; 0
invokespecial java/io/DataInputStream/<init>(Ljava/io/InputStream;)V
invokespecial com/flurry/android/FlurryAgent/a(Ljava/io/DataInputStream;)V
L6:
aload 1
invokeinterface org/apache/http/HttpEntity/consumeContent()V 0
L8:
iload 5
istore 4
L9:
aload 0
aconst_null
putfield com/flurry/android/FlurryAgent/D Ljava/util/List;
aload 0
monitorexit
L10:
iload 4
ireturn
L2:
astore 1
L11:
aload 0
monitorexit
L12:
aload 1
athrow
L7:
astore 2
L13:
aload 1
invokeinterface org/apache/http/HttpEntity/consumeContent()V 0
aload 2
athrow
L14:
ldc "FlurryAgent"
new java/lang/StringBuilder
dup
invokespecial java/lang/StringBuilder/<init>()V
ldc "Report failed. HTTP response: "
invokevirtual java/lang/StringBuilder/append(Ljava/lang/String;)Ljava/lang/StringBuilder;
iload 3
invokevirtual java/lang/StringBuilder/append(I)Ljava/lang/StringBuilder;
invokevirtual java/lang/StringBuilder/toString()Ljava/lang/String;
invokestatic com/flurry/android/ai/a(Ljava/lang/String;Ljava/lang/String;)I
pop
L15:
iconst_0
istore 4
goto L9
.limit locals 8
.limit stack 4
.end method

.method public static addUserCookie(Ljava/lang/String;Ljava/lang/String;)V
getstatic com/flurry/android/FlurryAgent/o Z
ifne L0
return
L0:
getstatic com/flurry/android/FlurryAgent/h Lcom/flurry/android/FlurryAgent;
getfield com/flurry/android/FlurryAgent/ab Lcom/flurry/android/v;
aload 0
aload 1
invokevirtual com/flurry/android/v/a(Ljava/lang/String;Ljava/lang/String;)V
return
.limit locals 2
.limit stack 3
.end method

.method static b()Lcom/flurry/android/v;
getstatic com/flurry/android/FlurryAgent/h Lcom/flurry/android/FlurryAgent;
getfield com/flurry/android/FlurryAgent/ab Lcom/flurry/android/v;
areturn
.limit locals 0
.limit stack 1
.end method

.method private b(Landroid/content/Context;)Ljava/lang/String;
.catch java/lang/Throwable from L0 to L1 using L2
.catch all from L0 to L1 using L3
.catch java/lang/Throwable from L4 to L5 using L6
.catch all from L4 to L5 using L7
.catch java/lang/Throwable from L8 to L9 using L6
.catch all from L8 to L9 using L7
.catch all from L10 to L11 using L7
aconst_null
astore 6
iconst_0
istore 4
aload 0
getfield com/flurry/android/FlurryAgent/F Ljava/lang/String;
ifnull L12
aload 0
getfield com/flurry/android/FlurryAgent/F Ljava/lang/String;
astore 1
L13:
aload 1
areturn
L12:
aload 1
invokevirtual android/content/Context/getContentResolver()Landroid/content/ContentResolver;
ldc "android_id"
invokestatic android/provider/Settings$System/getString(Landroid/content/ContentResolver;Ljava/lang/String;)Ljava/lang/String;
astore 7
iload 4
istore 2
aload 7
ifnull L14
iload 4
istore 2
aload 7
invokevirtual java/lang/String/length()I
ifle L14
aload 7
ldc "null"
invokevirtual java/lang/String/equals(Ljava/lang/Object;)Z
ifeq L15
iload 4
istore 2
L14:
iload 2
ifeq L16
new java/lang/StringBuilder
dup
invokespecial java/lang/StringBuilder/<init>()V
ldc "AND"
invokevirtual java/lang/StringBuilder/append(Ljava/lang/String;)Ljava/lang/StringBuilder;
aload 7
invokevirtual java/lang/StringBuilder/append(Ljava/lang/String;)Ljava/lang/StringBuilder;
invokevirtual java/lang/StringBuilder/toString()Ljava/lang/String;
areturn
L15:
getstatic com/flurry/android/FlurryAgent/b [Ljava/lang/String;
astore 8
aload 8
arraylength
istore 5
iconst_0
istore 3
L17:
iload 3
iload 5
if_icmpge L18
iload 4
istore 2
aload 7
aload 8
iload 3
aaload
invokevirtual java/lang/String/equals(Ljava/lang/Object;)Z
ifne L14
iload 3
iconst_1
iadd
istore 3
goto L17
L18:
iconst_1
istore 2
goto L14
L16:
aload 1
ldc ".flurryb."
invokevirtual android/content/Context/getFileStreamPath(Ljava/lang/String;)Ljava/io/File;
astore 7
aload 6
astore 1
aload 7
invokevirtual java/io/File/exists()Z
ifeq L13
L0:
new java/io/DataInputStream
dup
new java/io/FileInputStream
dup
aload 7
invokespecial java/io/FileInputStream/<init>(Ljava/io/File;)V
invokespecial java/io/DataInputStream/<init>(Ljava/io/InputStream;)V
astore 6
L1:
aload 6
astore 1
L4:
aload 6
invokevirtual java/io/DataInputStream/readInt()I
pop
L5:
aload 6
astore 1
L8:
aload 6
invokevirtual java/io/DataInputStream/readUTF()Ljava/lang/String;
astore 7
L9:
aload 6
invokestatic com/flurry/android/r/a(Ljava/io/Closeable;)V
aload 7
areturn
L2:
astore 7
aconst_null
astore 6
L19:
aload 6
astore 1
L10:
ldc "FlurryAgent"
ldc "Error when loading b file"
aload 7
invokestatic com/flurry/android/ai/b(Ljava/lang/String;Ljava/lang/String;Ljava/lang/Throwable;)I
pop
L11:
aload 6
invokestatic com/flurry/android/r/a(Ljava/io/Closeable;)V
aconst_null
areturn
L3:
astore 1
aconst_null
astore 7
aload 1
astore 6
L20:
aload 7
invokestatic com/flurry/android/r/a(Ljava/io/Closeable;)V
aload 6
athrow
L7:
astore 6
aload 1
astore 7
goto L20
L6:
astore 7
goto L19
.limit locals 9
.limit stack 5
.end method

.method static b(Ljava/lang/String;)Ljava/util/List;
getstatic com/flurry/android/FlurryAgent/o Z
ifne L0
aconst_null
areturn
L0:
getstatic com/flurry/android/FlurryAgent/h Lcom/flurry/android/FlurryAgent;
getfield com/flurry/android/FlurryAgent/ab Lcom/flurry/android/v;
aload 0
invokevirtual com/flurry/android/v/c(Ljava/lang/String;)Ljava/util/List;
areturn
.limit locals 1
.limit stack 2
.end method

.method private b(Landroid/content/Context;Ljava/lang/String;)V
.catch all from L0 to L1 using L2
.catch all from L1 to L3 using L2
.catch all from L3 to L4 using L2
.catch all from L4 to L5 using L2
.catch all from L5 to L6 using L2
.catch all from L6 to L7 using L2
.catch all from L7 to L8 using L2
.catch all from L8 to L9 using L2
.catch all from L9 to L10 using L2
.catch all from L10 to L11 using L2
.catch all from L12 to L13 using L2
.catch all from L14 to L15 using L2
aload 0
monitorenter
L0:
aload 0
getfield com/flurry/android/FlurryAgent/z Ljava/lang/String;
ifnull L1
aload 0
getfield com/flurry/android/FlurryAgent/z Ljava/lang/String;
aload 2
invokevirtual java/lang/String/equals(Ljava/lang/Object;)Z
ifne L1
ldc "FlurryAgent"
new java/lang/StringBuilder
dup
invokespecial java/lang/StringBuilder/<init>()V
ldc "onStartSession called with different api keys: "
invokevirtual java/lang/StringBuilder/append(Ljava/lang/String;)Ljava/lang/StringBuilder;
aload 0
getfield com/flurry/android/FlurryAgent/z Ljava/lang/String;
invokevirtual java/lang/StringBuilder/append(Ljava/lang/String;)Ljava/lang/StringBuilder;
ldc " and "
invokevirtual java/lang/StringBuilder/append(Ljava/lang/String;)Ljava/lang/StringBuilder;
aload 2
invokevirtual java/lang/StringBuilder/append(Ljava/lang/String;)Ljava/lang/StringBuilder;
invokevirtual java/lang/StringBuilder/toString()Ljava/lang/String;
invokestatic com/flurry/android/ai/b(Ljava/lang/String;Ljava/lang/String;)I
pop
L1:
aload 0
getfield com/flurry/android/FlurryAgent/y Ljava/util/Map;
aload 1
aload 1
invokeinterface java/util/Map/put(Ljava/lang/Object;Ljava/lang/Object;)Ljava/lang/Object; 2
checkcast android/content/Context
ifnull L3
ldc "FlurryAgent"
ldc "onStartSession called with duplicate context, use a specific Activity or Service as context instead of using a global context"
invokestatic com/flurry/android/ai/d(Ljava/lang/String;Ljava/lang/String;)I
pop
L3:
aload 0
getfield com/flurry/android/FlurryAgent/v Z
ifne L11
ldc "FlurryAgent"
ldc "Initializing Flurry session"
invokestatic com/flurry/android/ai/a(Ljava/lang/String;Ljava/lang/String;)I
pop
getstatic com/flurry/android/FlurryAgent/q Ljava/util/concurrent/atomic/AtomicInteger;
iconst_0
invokevirtual java/util/concurrent/atomic/AtomicInteger/set(I)V
getstatic com/flurry/android/FlurryAgent/r Ljava/util/concurrent/atomic/AtomicInteger;
iconst_0
invokevirtual java/util/concurrent/atomic/AtomicInteger/set(I)V
aload 0
aload 2
putfield com/flurry/android/FlurryAgent/z Ljava/lang/String;
aload 0
aload 1
new java/lang/StringBuilder
dup
invokespecial java/lang/StringBuilder/<init>()V
ldc ".flurryagent."
invokevirtual java/lang/StringBuilder/append(Ljava/lang/String;)Ljava/lang/StringBuilder;
aload 0
getfield com/flurry/android/FlurryAgent/z Ljava/lang/String;
invokevirtual java/lang/String/hashCode()I
bipush 16
invokestatic java/lang/Integer/toString(II)Ljava/lang/String;
invokevirtual java/lang/StringBuilder/append(Ljava/lang/String;)Ljava/lang/StringBuilder;
invokevirtual java/lang/StringBuilder/toString()Ljava/lang/String;
invokevirtual android/content/Context/getFileStreamPath(Ljava/lang/String;)Ljava/io/File;
putfield com/flurry/android/FlurryAgent/u Ljava/io/File;
aload 0
aload 1
ldc ".flurryb."
invokevirtual android/content/Context/getFileStreamPath(Ljava/lang/String;)Ljava/io/File;
putfield com/flurry/android/FlurryAgent/t Ljava/io/File;
getstatic com/flurry/android/FlurryAgent/m Z
ifeq L4
new com/flurry/android/FlurryAgent$FlurryDefaultExceptionHandler
dup
invokespecial com/flurry/android/FlurryAgent$FlurryDefaultExceptionHandler/<init>()V
invokestatic java/lang/Thread/setDefaultUncaughtExceptionHandler(Ljava/lang/Thread$UncaughtExceptionHandler;)V
L4:
aload 1
invokevirtual android/content/Context/getApplicationContext()Landroid/content/Context;
astore 5
aload 0
getfield com/flurry/android/FlurryAgent/B Ljava/lang/String;
ifnonnull L5
aload 0
aload 5
invokestatic com/flurry/android/FlurryAgent/c(Landroid/content/Context;)Ljava/lang/String;
putfield com/flurry/android/FlurryAgent/B Ljava/lang/String;
L5:
aload 5
invokevirtual android/content/Context/getPackageName()Ljava/lang/String;
astore 2
aload 0
getfield com/flurry/android/FlurryAgent/A Ljava/lang/String;
ifnull L6
aload 0
getfield com/flurry/android/FlurryAgent/A Ljava/lang/String;
aload 2
invokevirtual java/lang/String/equals(Ljava/lang/Object;)Z
ifne L6
ldc "FlurryAgent"
new java/lang/StringBuilder
dup
invokespecial java/lang/StringBuilder/<init>()V
ldc "onStartSession called from different application packages: "
invokevirtual java/lang/StringBuilder/append(Ljava/lang/String;)Ljava/lang/StringBuilder;
aload 0
getfield com/flurry/android/FlurryAgent/A Ljava/lang/String;
invokevirtual java/lang/StringBuilder/append(Ljava/lang/String;)Ljava/lang/StringBuilder;
ldc " and "
invokevirtual java/lang/StringBuilder/append(Ljava/lang/String;)Ljava/lang/StringBuilder;
aload 2
invokevirtual java/lang/StringBuilder/append(Ljava/lang/String;)Ljava/lang/StringBuilder;
invokevirtual java/lang/StringBuilder/toString()Ljava/lang/String;
invokestatic com/flurry/android/ai/b(Ljava/lang/String;Ljava/lang/String;)I
pop
L6:
aload 0
aload 2
putfield com/flurry/android/FlurryAgent/A Ljava/lang/String;
invokestatic android/os/SystemClock/elapsedRealtime()J
lstore 3
lload 3
aload 0
getfield com/flurry/android/FlurryAgent/x J
lsub
getstatic com/flurry/android/FlurryAgent/i J
lcmp
ifle L14
ldc "FlurryAgent"
ldc "New session"
invokestatic com/flurry/android/ai/a(Ljava/lang/String;Ljava/lang/String;)I
pop
aload 0
invokestatic java/lang/System/currentTimeMillis()J
putfield com/flurry/android/FlurryAgent/K J
aload 0
lload 3
putfield com/flurry/android/FlurryAgent/L J
aload 0
ldc2_w -1L
putfield com/flurry/android/FlurryAgent/M J
aload 0
ldc ""
putfield com/flurry/android/FlurryAgent/Q Ljava/lang/String;
aload 0
iconst_0
putfield com/flurry/android/FlurryAgent/T I
aload 0
aconst_null
putfield com/flurry/android/FlurryAgent/U Landroid/location/Location;
aload 0
invokestatic java/util/TimeZone/getDefault()Ljava/util/TimeZone;
invokevirtual java/util/TimeZone/getID()Ljava/lang/String;
putfield com/flurry/android/FlurryAgent/O Ljava/lang/String;
aload 0
new java/lang/StringBuilder
dup
invokespecial java/lang/StringBuilder/<init>()V
invokestatic java/util/Locale/getDefault()Ljava/util/Locale;
invokevirtual java/util/Locale/getLanguage()Ljava/lang/String;
invokevirtual java/lang/StringBuilder/append(Ljava/lang/String;)Ljava/lang/StringBuilder;
ldc "_"
invokevirtual java/lang/StringBuilder/append(Ljava/lang/String;)Ljava/lang/StringBuilder;
invokestatic java/util/Locale/getDefault()Ljava/util/Locale;
invokevirtual java/util/Locale/getCountry()Ljava/lang/String;
invokevirtual java/lang/StringBuilder/append(Ljava/lang/String;)Ljava/lang/StringBuilder;
invokevirtual java/lang/StringBuilder/toString()Ljava/lang/String;
putfield com/flurry/android/FlurryAgent/N Ljava/lang/String;
aload 0
new java/util/HashMap
dup
invokespecial java/util/HashMap/<init>()V
putfield com/flurry/android/FlurryAgent/V Ljava/util/Map;
aload 0
new java/util/ArrayList
dup
invokespecial java/util/ArrayList/<init>()V
putfield com/flurry/android/FlurryAgent/W Ljava/util/List;
aload 0
iconst_1
putfield com/flurry/android/FlurryAgent/X Z
aload 0
new java/util/ArrayList
dup
invokespecial java/util/ArrayList/<init>()V
putfield com/flurry/android/FlurryAgent/Z Ljava/util/List;
aload 0
iconst_0
putfield com/flurry/android/FlurryAgent/Y I
aload 0
iconst_0
putfield com/flurry/android/FlurryAgent/aa I
getstatic com/flurry/android/FlurryAgent/o Z
ifeq L9
aload 0
getfield com/flurry/android/FlurryAgent/ab Lcom/flurry/android/v;
invokevirtual com/flurry/android/v/a()Z
ifne L8
ldc "FlurryAgent"
ldc "Initializing AppCircle"
invokestatic com/flurry/android/ai/a(Ljava/lang/String;Ljava/lang/String;)I
pop
new com/flurry/android/a
dup
invokespecial com/flurry/android/a/<init>()V
astore 6
aload 6
aload 0
getfield com/flurry/android/FlurryAgent/z Ljava/lang/String;
putfield com/flurry/android/a/a Ljava/lang/String;
aload 6
aload 0
getfield com/flurry/android/FlurryAgent/H J
putfield com/flurry/android/a/b J
getstatic com/flurry/android/FlurryAgent/d Ljava/lang/String;
ifnull L12
getstatic com/flurry/android/FlurryAgent/d Ljava/lang/String;
astore 2
L7:
aload 6
aload 2
putfield com/flurry/android/a/c Ljava/lang/String;
aload 6
invokestatic com/flurry/android/FlurryAgent/c()Ljava/lang/String;
putfield com/flurry/android/a/d Ljava/lang/String;
aload 6
aload 0
getfield com/flurry/android/FlurryAgent/s Landroid/os/Handler;
putfield com/flurry/android/a/e Landroid/os/Handler;
aload 0
getfield com/flurry/android/FlurryAgent/ab Lcom/flurry/android/v;
aload 1
aload 6
invokevirtual com/flurry/android/v/a(Landroid/content/Context;Lcom/flurry/android/a;)V
ldc "FlurryAgent"
ldc "AppCircle initialized"
invokestatic com/flurry/android/ai/a(Ljava/lang/String;Ljava/lang/String;)I
pop
L8:
aload 0
getfield com/flurry/android/FlurryAgent/ab Lcom/flurry/android/v;
aload 0
getfield com/flurry/android/FlurryAgent/K J
aload 0
getfield com/flurry/android/FlurryAgent/L J
invokevirtual com/flurry/android/v/a(JJ)V
L9:
aload 0
new com/flurry/android/d
dup
aload 0
aload 5
aload 0
getfield com/flurry/android/FlurryAgent/C Z
invokespecial com/flurry/android/d/<init>(Lcom/flurry/android/FlurryAgent;Landroid/content/Context;Z)V
invokespecial com/flurry/android/FlurryAgent/a(Ljava/lang/Runnable;)V
L10:
aload 0
iconst_1
putfield com/flurry/android/FlurryAgent/v Z
L11:
aload 0
monitorexit
return
L12:
getstatic com/flurry/android/FlurryAgent/e Ljava/lang/String;
astore 2
L13:
goto L7
L14:
ldc "FlurryAgent"
ldc "Continuing previous session"
invokestatic com/flurry/android/ai/a(Ljava/lang/String;Ljava/lang/String;)I
pop
aload 0
getfield com/flurry/android/FlurryAgent/J Ljava/util/List;
invokeinterface java/util/List/isEmpty()Z 0
ifne L10
aload 0
getfield com/flurry/android/FlurryAgent/J Ljava/util/List;
aload 0
getfield com/flurry/android/FlurryAgent/J Ljava/util/List;
invokeinterface java/util/List/size()I 0
iconst_1
isub
invokeinterface java/util/List/remove(I)Ljava/lang/Object; 1
pop
L15:
goto L10
L2:
astore 1
aload 0
monitorexit
aload 1
athrow
.limit locals 7
.limit stack 6
.end method

.method static synthetic b(Lcom/flurry/android/FlurryAgent;)V
aload 0
invokespecial com/flurry/android/FlurryAgent/k()V
return
.limit locals 1
.limit stack 1
.end method

.method static synthetic b(Lcom/flurry/android/FlurryAgent;Landroid/content/Context;)V
.catch java/lang/Throwable from L0 to L1 using L2
.catch all from L1 to L3 using L4
.catch all from L5 to L6 using L4
.catch all from L7 to L8 using L4
.catch all from L9 to L10 using L4
.catch all from L11 to L12 using L4
.catch java/lang/Throwable from L13 to L14 using L2
.catch all from L15 to L16 using L4
.catch java/lang/Throwable from L16 to L2 using L2
iconst_0
istore 3
L0:
aload 0
monitorenter
L1:
invokestatic android/os/SystemClock/elapsedRealtime()J
lstore 4
aload 0
getfield com/flurry/android/FlurryAgent/x J
lstore 6
L3:
iload 3
istore 2
L5:
aload 0
getfield com/flurry/android/FlurryAgent/v Z
ifne L11
L6:
iload 3
istore 2
L7:
lload 4
lload 6
lsub
getstatic com/flurry/android/FlurryAgent/i J
lcmp
ifle L11
L8:
iload 3
istore 2
L9:
aload 0
getfield com/flurry/android/FlurryAgent/J Ljava/util/List;
invokeinterface java/util/List/size()I 0
ifle L11
L10:
iconst_1
istore 2
L11:
aload 0
monitorexit
L12:
iload 2
ifeq L14
L13:
aload 0
iconst_0
invokespecial com/flurry/android/FlurryAgent/c(Z)V
L14:
return
L4:
astore 1
L15:
aload 0
monitorexit
L16:
aload 1
athrow
L2:
astore 0
ldc "FlurryAgent"
ldc ""
aload 0
invokestatic com/flurry/android/ai/b(Ljava/lang/String;Ljava/lang/String;Ljava/lang/Throwable;)I
pop
return
.limit locals 8
.limit stack 4
.end method

.method private b(Ljava/io/DataInputStream;)V
.catch all from L0 to L1 using L2
.catch all from L3 to L2 using L2
.catch all from L4 to L5 using L2
.catch all from L5 to L6 using L2
.catch all from L6 to L7 using L2
.catch all from L8 to L9 using L2
.catch all from L10 to L11 using L2
.catch all from L12 to L13 using L2
.catch all from L14 to L15 using L2
.catch all from L16 to L17 using L2
iconst_0
istore 2
aload 0
monitorenter
L0:
aload 1
invokevirtual java/io/DataInputStream/readUnsignedShort()I
istore 3
L1:
iload 3
iconst_2
if_icmple L18
L3:
ldc "FlurryAgent"
new java/lang/StringBuilder
dup
invokespecial java/lang/StringBuilder/<init>()V
ldc "Unknown agent file version: "
invokevirtual java/lang/StringBuilder/append(Ljava/lang/String;)Ljava/lang/StringBuilder;
iload 3
invokevirtual java/lang/StringBuilder/append(I)Ljava/lang/StringBuilder;
invokevirtual java/lang/StringBuilder/toString()Ljava/lang/String;
invokestatic com/flurry/android/ai/b(Ljava/lang/String;Ljava/lang/String;)I
pop
new java/io/IOException
dup
new java/lang/StringBuilder
dup
invokespecial java/lang/StringBuilder/<init>()V
ldc "Unknown agent file version: "
invokevirtual java/lang/StringBuilder/append(Ljava/lang/String;)Ljava/lang/StringBuilder;
iload 3
invokevirtual java/lang/StringBuilder/append(I)Ljava/lang/StringBuilder;
invokevirtual java/lang/StringBuilder/toString()Ljava/lang/String;
invokespecial java/io/IOException/<init>(Ljava/lang/String;)V
athrow
L2:
astore 1
aload 0
monitorexit
aload 1
athrow
L18:
iload 3
iconst_2
if_icmplt L16
L4:
aload 1
invokevirtual java/io/DataInputStream/readUTF()Ljava/lang/String;
astore 4
ldc "FlurryAgent"
new java/lang/StringBuilder
dup
invokespecial java/lang/StringBuilder/<init>()V
ldc "Loading API key: "
invokevirtual java/lang/StringBuilder/append(Ljava/lang/String;)Ljava/lang/StringBuilder;
aload 0
getfield com/flurry/android/FlurryAgent/z Ljava/lang/String;
invokestatic com/flurry/android/FlurryAgent/d(Ljava/lang/String;)Ljava/lang/String;
invokevirtual java/lang/StringBuilder/append(Ljava/lang/String;)Ljava/lang/StringBuilder;
invokevirtual java/lang/StringBuilder/toString()Ljava/lang/String;
invokestatic com/flurry/android/ai/a(Ljava/lang/String;Ljava/lang/String;)I
pop
aload 4
aload 0
getfield com/flurry/android/FlurryAgent/z Ljava/lang/String;
invokevirtual java/lang/String/equals(Ljava/lang/Object;)Z
ifeq L14
aload 1
invokevirtual java/io/DataInputStream/readUTF()Ljava/lang/String;
astore 4
aload 0
getfield com/flurry/android/FlurryAgent/F Ljava/lang/String;
ifnonnull L5
ldc "FlurryAgent"
new java/lang/StringBuilder
dup
invokespecial java/lang/StringBuilder/<init>()V
ldc "Loading phoneId: "
invokevirtual java/lang/StringBuilder/append(Ljava/lang/String;)Ljava/lang/StringBuilder;
aload 4
invokevirtual java/lang/StringBuilder/append(Ljava/lang/String;)Ljava/lang/StringBuilder;
invokevirtual java/lang/StringBuilder/toString()Ljava/lang/String;
invokestatic com/flurry/android/ai/a(Ljava/lang/String;Ljava/lang/String;)I
pop
L5:
aload 0
aload 4
putfield com/flurry/android/FlurryAgent/F Ljava/lang/String;
aload 0
aload 1
invokevirtual java/io/DataInputStream/readBoolean()Z
putfield com/flurry/android/FlurryAgent/G Z
aload 0
aload 1
invokevirtual java/io/DataInputStream/readLong()J
putfield com/flurry/android/FlurryAgent/H J
ldc "FlurryAgent"
ldc "Loading session reports"
invokestatic com/flurry/android/ai/a(Ljava/lang/String;Ljava/lang/String;)I
pop
L6:
aload 1
invokevirtual java/io/DataInputStream/readUnsignedShort()I
istore 3
L7:
iload 3
ifeq L12
L8:
iload 3
newarray byte
astore 4
aload 1
aload 4
invokevirtual java/io/DataInputStream/readFully([B)V
aload 0
getfield com/flurry/android/FlurryAgent/J Ljava/util/List;
iconst_0
aload 4
invokeinterface java/util/List/add(ILjava/lang/Object;)V 2
new java/lang/StringBuilder
dup
invokespecial java/lang/StringBuilder/<init>()V
ldc "Session report added: "
invokevirtual java/lang/StringBuilder/append(Ljava/lang/String;)Ljava/lang/StringBuilder;
astore 4
L9:
iload 2
iconst_1
iadd
istore 2
L10:
ldc "FlurryAgent"
aload 4
iload 2
invokevirtual java/lang/StringBuilder/append(I)Ljava/lang/StringBuilder;
invokevirtual java/lang/StringBuilder/toString()Ljava/lang/String;
invokestatic com/flurry/android/ai/a(Ljava/lang/String;Ljava/lang/String;)I
pop
L11:
goto L6
L12:
ldc "FlurryAgent"
ldc "Persistent file loaded"
invokestatic com/flurry/android/ai/a(Ljava/lang/String;Ljava/lang/String;)I
pop
aload 0
iconst_1
putfield com/flurry/android/FlurryAgent/w Z
L13:
aload 0
monitorexit
return
L14:
ldc "FlurryAgent"
new java/lang/StringBuilder
dup
invokespecial java/lang/StringBuilder/<init>()V
ldc "Api keys do not match, old: "
invokevirtual java/lang/StringBuilder/append(Ljava/lang/String;)Ljava/lang/StringBuilder;
aload 4
invokestatic com/flurry/android/FlurryAgent/d(Ljava/lang/String;)Ljava/lang/String;
invokevirtual java/lang/StringBuilder/append(Ljava/lang/String;)Ljava/lang/StringBuilder;
ldc ", new: "
invokevirtual java/lang/StringBuilder/append(Ljava/lang/String;)Ljava/lang/StringBuilder;
aload 0
getfield com/flurry/android/FlurryAgent/z Ljava/lang/String;
invokestatic com/flurry/android/FlurryAgent/d(Ljava/lang/String;)Ljava/lang/String;
invokevirtual java/lang/StringBuilder/append(Ljava/lang/String;)Ljava/lang/StringBuilder;
invokevirtual java/lang/StringBuilder/toString()Ljava/lang/String;
invokestatic com/flurry/android/ai/a(Ljava/lang/String;Ljava/lang/String;)I
pop
L15:
goto L13
L16:
ldc "FlurryAgent"
new java/lang/StringBuilder
dup
invokespecial java/lang/StringBuilder/<init>()V
ldc "Deleting old file version: "
invokevirtual java/lang/StringBuilder/append(Ljava/lang/String;)Ljava/lang/StringBuilder;
iload 3
invokevirtual java/lang/StringBuilder/append(I)Ljava/lang/StringBuilder;
invokevirtual java/lang/StringBuilder/toString()Ljava/lang/String;
invokestatic com/flurry/android/ai/d(Ljava/lang/String;Ljava/lang/String;)I
pop
L17:
goto L13
.limit locals 5
.limit stack 4
.end method

.method private b(Z)[B
.catch java/lang/Throwable from L0 to L1 using L2
.catch all from L0 to L1 using L3
.catch java/lang/Throwable from L4 to L5 using L6
.catch all from L4 to L5 using L7
.catch java/lang/Throwable from L8 to L9 using L6
.catch all from L8 to L9 using L7
.catch java/lang/Throwable from L10 to L11 using L6
.catch all from L10 to L11 using L7
.catch java/lang/Throwable from L12 to L13 using L6
.catch all from L12 to L13 using L7
.catch java/lang/Throwable from L14 to L15 using L6
.catch all from L14 to L15 using L7
.catch java/lang/Throwable from L16 to L17 using L6
.catch all from L16 to L17 using L7
.catch java/lang/Throwable from L18 to L19 using L6
.catch all from L18 to L19 using L7
.catch java/lang/Throwable from L20 to L21 using L6
.catch all from L20 to L21 using L7
.catch java/lang/Throwable from L22 to L23 using L6
.catch all from L22 to L23 using L7
.catch java/lang/Throwable from L24 to L25 using L6
.catch all from L24 to L25 using L7
.catch java/lang/Throwable from L26 to L27 using L6
.catch all from L26 to L27 using L7
.catch java/lang/Throwable from L28 to L29 using L6
.catch all from L28 to L29 using L7
.catch all from L30 to L31 using L7
.catch all from L31 to L32 using L33
.catch java/lang/Throwable from L34 to L35 using L6
.catch all from L34 to L35 using L7
.catch all from L36 to L33 using L33
.catch java/lang/Throwable from L37 to L38 using L6
.catch all from L37 to L38 using L7
.catch java/lang/Throwable from L39 to L40 using L6
.catch all from L39 to L40 using L7
.catch java/lang/Throwable from L41 to L42 using L6
.catch all from L41 to L42 using L7
.catch java/lang/Throwable from L43 to L44 using L6
.catch all from L43 to L44 using L7
.catch java/lang/Throwable from L45 to L46 using L6
.catch all from L45 to L46 using L7
.catch java/lang/Throwable from L47 to L48 using L6
.catch all from L47 to L48 using L7
.catch java/lang/Throwable from L49 to L50 using L6
.catch all from L49 to L50 using L7
.catch java/lang/Throwable from L51 to L52 using L6
.catch all from L51 to L52 using L7
.catch java/lang/Throwable from L53 to L54 using L6
.catch all from L53 to L54 using L7
.catch java/lang/Throwable from L55 to L56 using L6
.catch all from L55 to L56 using L7
.catch java/lang/Throwable from L57 to L58 using L6
.catch all from L57 to L58 using L7
.catch java/lang/Throwable from L59 to L60 using L6
.catch all from L59 to L60 using L7
.catch java/lang/Throwable from L61 to L62 using L6
.catch all from L61 to L62 using L7
.catch java/lang/Throwable from L63 to L64 using L6
.catch all from L63 to L64 using L7
.catch java/lang/Throwable from L65 to L66 using L6
.catch all from L65 to L66 using L7
.catch java/lang/Throwable from L67 to L68 using L6
.catch all from L67 to L68 using L7
.catch java/lang/Throwable from L69 to L70 using L6
.catch all from L69 to L70 using L7
.catch java/lang/Throwable from L71 to L72 using L6
.catch all from L71 to L72 using L7
.catch java/lang/Throwable from L73 to L74 using L6
.catch all from L73 to L74 using L7
.catch java/lang/Throwable from L75 to L76 using L6
.catch all from L75 to L76 using L7
.catch java/lang/Throwable from L77 to L78 using L6
.catch all from L77 to L78 using L7
.catch java/lang/Throwable from L79 to L80 using L6
.catch all from L79 to L80 using L7
.catch java/lang/Throwable from L81 to L82 using L6
.catch all from L81 to L82 using L7
.catch java/lang/Throwable from L83 to L84 using L6
.catch all from L83 to L84 using L7
.catch java/lang/Throwable from L85 to L86 using L6
.catch all from L85 to L86 using L7
.catch java/lang/Throwable from L87 to L88 using L6
.catch all from L87 to L88 using L7
.catch java/lang/Throwable from L89 to L90 using L6
.catch all from L89 to L90 using L7
.catch java/lang/Throwable from L91 to L92 using L6
.catch all from L91 to L92 using L7
.catch java/lang/Throwable from L93 to L94 using L6
.catch all from L93 to L94 using L7
.catch java/lang/Throwable from L95 to L96 using L6
.catch all from L95 to L96 using L7
.catch java/lang/Throwable from L97 to L98 using L6
.catch all from L97 to L98 using L7
.catch java/lang/Throwable from L99 to L100 using L6
.catch all from L99 to L100 using L7
.catch java/lang/Throwable from L101 to L102 using L6
.catch all from L101 to L102 using L7
.catch java/lang/Throwable from L103 to L104 using L6
.catch all from L103 to L104 using L7
.catch java/lang/Throwable from L105 to L106 using L6
.catch all from L105 to L106 using L7
.catch java/lang/Throwable from L107 to L108 using L6
.catch all from L107 to L108 using L7
.catch java/lang/Throwable from L109 to L110 using L6
.catch all from L109 to L110 using L7
.catch java/lang/Throwable from L111 to L112 using L6
.catch all from L111 to L112 using L7
.catch java/lang/Throwable from L113 to L114 using L6
.catch all from L113 to L114 using L7
.catch all from L115 to L116 using L33
iconst_0
istore 3
aload 0
monitorenter
L0:
new com/flurry/android/CrcMessageDigest
dup
invokespecial com/flurry/android/CrcMessageDigest/<init>()V
astore 9
new java/io/ByteArrayOutputStream
dup
invokespecial java/io/ByteArrayOutputStream/<init>()V
astore 10
new java/security/DigestOutputStream
dup
aload 10
aload 9
invokespecial java/security/DigestOutputStream/<init>(Ljava/io/OutputStream;Ljava/security/MessageDigest;)V
astore 11
new java/io/DataOutputStream
dup
aload 11
invokespecial java/io/DataOutputStream/<init>(Ljava/io/OutputStream;)V
astore 8
L1:
aload 8
astore 7
L4:
aload 8
bipush 22
invokevirtual java/io/DataOutputStream/writeShort(I)V
L5:
aload 8
astore 7
L8:
getstatic com/flurry/android/FlurryAgent/o Z
ifeq L117
L9:
iload 1
ifeq L117
aload 8
astore 7
L10:
aload 8
iconst_1
invokevirtual java/io/DataOutputStream/writeShort(I)V
L11:
aload 8
astore 7
L12:
getstatic com/flurry/android/FlurryAgent/o Z
ifeq L118
L13:
aload 8
astore 7
L14:
aload 8
aload 0
getfield com/flurry/android/FlurryAgent/ab Lcom/flurry/android/v;
invokevirtual com/flurry/android/v/d()J
invokevirtual java/io/DataOutputStream/writeLong(J)V
L15:
aload 8
astore 7
L16:
aload 0
getfield com/flurry/android/FlurryAgent/ab Lcom/flurry/android/v;
invokevirtual com/flurry/android/v/e()Ljava/util/Set;
astore 12
L17:
aload 8
astore 7
L18:
aload 8
aload 12
invokeinterface java/util/Set/size()I 0
invokevirtual java/io/DataOutputStream/writeShort(I)V
L19:
aload 8
astore 7
L20:
aload 12
invokeinterface java/util/Set/iterator()Ljava/util/Iterator; 0
astore 12
L21:
aload 8
astore 7
L22:
aload 12
invokeinterface java/util/Iterator/hasNext()Z 0
ifeq L40
L23:
aload 8
astore 7
L24:
aload 12
invokeinterface java/util/Iterator/next()Ljava/lang/Object; 0
checkcast java/lang/Long
invokevirtual java/lang/Long/longValue()J
lstore 5
L25:
aload 8
astore 7
L26:
aload 8
iconst_1
invokevirtual java/io/DataOutputStream/writeByte(I)V
L27:
aload 8
astore 7
L28:
aload 8
lload 5
invokevirtual java/io/DataOutputStream/writeLong(J)V
L29:
goto L21
L6:
astore 9
L119:
aload 8
astore 7
L30:
ldc "FlurryAgent"
ldc "Error when generating report"
aload 9
invokestatic com/flurry/android/ai/b(Ljava/lang/String;Ljava/lang/String;Ljava/lang/Throwable;)I
pop
L31:
aload 8
invokestatic com/flurry/android/r/a(Ljava/io/Closeable;)V
L32:
aconst_null
astore 7
L120:
aload 0
monitorexit
aload 7
areturn
L117:
aload 8
astore 7
L34:
aload 8
iconst_0
invokevirtual java/io/DataOutputStream/writeShort(I)V
L35:
goto L11
L7:
astore 9
aload 7
astore 8
aload 9
astore 7
L36:
aload 8
invokestatic com/flurry/android/r/a(Ljava/io/Closeable;)V
aload 7
athrow
L33:
astore 7
aload 0
monitorexit
aload 7
athrow
L118:
aload 8
astore 7
L37:
aload 8
lconst_0
invokevirtual java/io/DataOutputStream/writeLong(J)V
L38:
aload 8
astore 7
L39:
aload 8
iconst_0
invokevirtual java/io/DataOutputStream/writeShort(I)V
L40:
aload 8
astore 7
L41:
aload 8
iconst_3
invokevirtual java/io/DataOutputStream/writeShort(I)V
L42:
aload 8
astore 7
L43:
aload 8
bipush 122
invokevirtual java/io/DataOutputStream/writeShort(I)V
L44:
aload 8
astore 7
L45:
aload 8
invokestatic java/lang/System/currentTimeMillis()J
invokevirtual java/io/DataOutputStream/writeLong(J)V
L46:
aload 8
astore 7
L47:
aload 8
aload 0
getfield com/flurry/android/FlurryAgent/z Ljava/lang/String;
invokevirtual java/io/DataOutputStream/writeUTF(Ljava/lang/String;)V
L48:
aload 8
astore 7
L49:
aload 8
aload 0
getfield com/flurry/android/FlurryAgent/B Ljava/lang/String;
invokevirtual java/io/DataOutputStream/writeUTF(Ljava/lang/String;)V
L50:
aload 8
astore 7
L51:
aload 0
getfield com/flurry/android/FlurryAgent/I [B
ifnonnull L121
L52:
iconst_1
istore 2
L122:
aload 8
astore 7
L53:
aload 8
iload 2
invokevirtual java/io/DataOutputStream/writeShort(I)V
L54:
aload 8
astore 7
L55:
aload 8
iconst_0
invokevirtual java/io/DataOutputStream/writeShort(I)V
L56:
aload 8
astore 7
L57:
aload 8
aload 0
getfield com/flurry/android/FlurryAgent/F Ljava/lang/String;
invokevirtual java/io/DataOutputStream/writeUTF(Ljava/lang/String;)V
L58:
iload 2
iconst_1
if_icmple L66
aload 8
astore 7
L59:
aload 8
iconst_5
invokevirtual java/io/DataOutputStream/writeShort(I)V
L60:
aload 8
astore 7
L61:
aload 8
aload 0
getfield com/flurry/android/FlurryAgent/I [B
arraylength
invokevirtual java/io/DataOutputStream/writeShort(I)V
L62:
aload 8
astore 7
L63:
aload 8
aload 0
getfield com/flurry/android/FlurryAgent/I [B
invokevirtual java/io/DataOutputStream/write([B)V
L64:
aload 8
astore 7
L65:
ldc "FlurryAgent"
new java/lang/StringBuilder
dup
invokespecial java/lang/StringBuilder/<init>()V
ldc "Sent IMEI: "
invokevirtual java/lang/StringBuilder/append(Ljava/lang/String;)Ljava/lang/StringBuilder;
aload 0
getfield com/flurry/android/FlurryAgent/I [B
invokestatic java/util/Arrays/toString([B)Ljava/lang/String;
invokevirtual java/lang/StringBuilder/append(Ljava/lang/String;)Ljava/lang/StringBuilder;
invokevirtual java/lang/StringBuilder/toString()Ljava/lang/String;
invokestatic com/flurry/android/ai/c(Ljava/lang/String;Ljava/lang/String;)I
pop
L66:
aload 8
astore 7
L67:
aload 8
iconst_0
invokevirtual java/io/DataOutputStream/write(I)V
L68:
aload 8
astore 7
L69:
aload 8
aload 0
getfield com/flurry/android/FlurryAgent/H J
invokevirtual java/io/DataOutputStream/writeLong(J)V
L70:
aload 8
astore 7
L71:
aload 8
aload 0
getfield com/flurry/android/FlurryAgent/K J
invokevirtual java/io/DataOutputStream/writeLong(J)V
L72:
aload 8
astore 7
L73:
aload 8
bipush 6
invokevirtual java/io/DataOutputStream/writeShort(I)V
L74:
aload 8
astore 7
L75:
aload 8
ldc "device.model"
invokevirtual java/io/DataOutputStream/writeUTF(Ljava/lang/String;)V
L76:
aload 8
astore 7
L77:
aload 8
getstatic android/os/Build/MODEL Ljava/lang/String;
invokevirtual java/io/DataOutputStream/writeUTF(Ljava/lang/String;)V
L78:
aload 8
astore 7
L79:
aload 8
ldc "build.brand"
invokevirtual java/io/DataOutputStream/writeUTF(Ljava/lang/String;)V
L80:
aload 8
astore 7
L81:
aload 8
getstatic android/os/Build/BRAND Ljava/lang/String;
invokevirtual java/io/DataOutputStream/writeUTF(Ljava/lang/String;)V
L82:
aload 8
astore 7
L83:
aload 8
ldc "build.id"
invokevirtual java/io/DataOutputStream/writeUTF(Ljava/lang/String;)V
L84:
aload 8
astore 7
L85:
aload 8
getstatic android/os/Build/ID Ljava/lang/String;
invokevirtual java/io/DataOutputStream/writeUTF(Ljava/lang/String;)V
L86:
aload 8
astore 7
L87:
aload 8
ldc "version.release"
invokevirtual java/io/DataOutputStream/writeUTF(Ljava/lang/String;)V
L88:
aload 8
astore 7
L89:
aload 8
getstatic android/os/Build$VERSION/RELEASE Ljava/lang/String;
invokevirtual java/io/DataOutputStream/writeUTF(Ljava/lang/String;)V
L90:
aload 8
astore 7
L91:
aload 8
ldc "build.device"
invokevirtual java/io/DataOutputStream/writeUTF(Ljava/lang/String;)V
L92:
aload 8
astore 7
L93:
aload 8
getstatic android/os/Build/DEVICE Ljava/lang/String;
invokevirtual java/io/DataOutputStream/writeUTF(Ljava/lang/String;)V
L94:
aload 8
astore 7
L95:
aload 8
ldc "build.product"
invokevirtual java/io/DataOutputStream/writeUTF(Ljava/lang/String;)V
L96:
aload 8
astore 7
L97:
aload 8
getstatic android/os/Build/PRODUCT Ljava/lang/String;
invokevirtual java/io/DataOutputStream/writeUTF(Ljava/lang/String;)V
L98:
aload 8
astore 7
L99:
aload 0
getfield com/flurry/android/FlurryAgent/J Ljava/util/List;
invokeinterface java/util/List/size()I 0
istore 4
L100:
aload 8
astore 7
L101:
aload 8
iload 4
invokevirtual java/io/DataOutputStream/writeShort(I)V
L102:
iload 3
istore 2
L123:
iload 2
iload 4
if_icmpge L124
aload 8
astore 7
L103:
aload 8
aload 0
getfield com/flurry/android/FlurryAgent/J Ljava/util/List;
iload 2
invokeinterface java/util/List/get(I)Ljava/lang/Object; 1
checkcast [B
invokevirtual java/io/DataOutputStream/write([B)V
L104:
iload 2
iconst_1
iadd
istore 2
goto L123
L124:
aload 8
astore 7
L105:
aload 0
new java/util/ArrayList
dup
aload 0
getfield com/flurry/android/FlurryAgent/J Ljava/util/List;
invokespecial java/util/ArrayList/<init>(Ljava/util/Collection;)V
putfield com/flurry/android/FlurryAgent/D Ljava/util/List;
L106:
aload 8
astore 7
L107:
aload 11
iconst_0
invokevirtual java/security/DigestOutputStream/on(Z)V
L108:
aload 8
astore 7
L109:
aload 8
aload 9
invokevirtual com/flurry/android/CrcMessageDigest/getDigest()[B
invokevirtual java/io/DataOutputStream/write([B)V
L110:
aload 8
astore 7
L111:
aload 8
invokevirtual java/io/DataOutputStream/close()V
L112:
aload 8
astore 7
L113:
aload 10
invokevirtual java/io/ByteArrayOutputStream/toByteArray()[B
astore 9
L114:
aload 9
astore 7
L115:
aload 8
invokestatic com/flurry/android/r/a(Ljava/io/Closeable;)V
L116:
goto L120
L3:
astore 7
aconst_null
astore 8
goto L36
L2:
astore 9
aconst_null
astore 8
goto L119
L121:
iconst_2
istore 2
goto L122
.limit locals 13
.limit stack 4
.end method

.method static c()Ljava/lang/String;
getstatic com/flurry/android/FlurryAgent/f Ljava/lang/String;
ifnull L0
getstatic com/flurry/android/FlurryAgent/f Ljava/lang/String;
areturn
L0:
getstatic com/flurry/android/FlurryAgent/g Ljava/lang/String;
areturn
.limit locals 0
.limit stack 1
.end method

.method private static c(Landroid/content/Context;)Ljava/lang/String;
.catch java/lang/Throwable from L0 to L1 using L2
.catch java/lang/Throwable from L1 to L3 using L2
L0:
aload 0
invokevirtual android/content/Context/getPackageManager()Landroid/content/pm/PackageManager;
aload 0
invokevirtual android/content/Context/getPackageName()Ljava/lang/String;
iconst_0
invokevirtual android/content/pm/PackageManager/getPackageInfo(Ljava/lang/String;I)Landroid/content/pm/PackageInfo;
astore 0
aload 0
getfield android/content/pm/PackageInfo/versionName Ljava/lang/String;
ifnull L1
aload 0
getfield android/content/pm/PackageInfo/versionName Ljava/lang/String;
areturn
L1:
aload 0
getfield android/content/pm/PackageInfo/versionCode I
ifeq L4
aload 0
getfield android/content/pm/PackageInfo/versionCode I
invokestatic java/lang/Integer/toString(I)Ljava/lang/String;
astore 0
L3:
aload 0
areturn
L2:
astore 0
ldc "FlurryAgent"
ldc ""
aload 0
invokestatic com/flurry/android/ai/b(Ljava/lang/String;Ljava/lang/String;Ljava/lang/Throwable;)I
pop
L4:
ldc "Unknown"
areturn
.limit locals 1
.limit stack 3
.end method

.method private c(Landroid/content/Context;Ljava/lang/String;)V
.catch all from L0 to L1 using L2
.catch java/lang/Throwable from L3 to L4 using L5
.catch all from L3 to L4 using L6
.catch java/lang/Throwable from L7 to L8 using L9
.catch all from L7 to L8 using L10
.catch java/lang/Throwable from L11 to L12 using L9
.catch all from L11 to L12 using L10
.catch all from L12 to L13 using L2
.catch all from L14 to L15 using L10
.catch all from L15 to L16 using L2
.catch all from L17 to L10 using L2
aload 0
monitorenter
L0:
aload 0
aload 1
ldc ".flurryb."
invokevirtual android/content/Context/getFileStreamPath(Ljava/lang/String;)Ljava/io/File;
putfield com/flurry/android/FlurryAgent/t Ljava/io/File;
aload 0
getfield com/flurry/android/FlurryAgent/t Ljava/io/File;
invokestatic com/flurry/android/FlurryAgent/a(Ljava/io/File;)Z
istore 3
L1:
iload 3
ifne L3
L18:
aload 0
monitorexit
return
L3:
new java/io/DataOutputStream
dup
new java/io/FileOutputStream
dup
aload 0
getfield com/flurry/android/FlurryAgent/t Ljava/io/File;
invokespecial java/io/FileOutputStream/<init>(Ljava/io/File;)V
invokespecial java/io/DataOutputStream/<init>(Ljava/io/OutputStream;)V
astore 4
L4:
aload 4
astore 1
L7:
aload 4
iconst_1
invokevirtual java/io/DataOutputStream/writeInt(I)V
L8:
aload 4
astore 1
L11:
aload 4
aload 2
invokevirtual java/io/DataOutputStream/writeUTF(Ljava/lang/String;)V
L12:
aload 4
invokestatic com/flurry/android/r/a(Ljava/io/Closeable;)V
L13:
goto L18
L2:
astore 1
aload 0
monitorexit
aload 1
athrow
L5:
astore 5
aconst_null
astore 2
L19:
aload 2
astore 1
L14:
ldc "FlurryAgent"
ldc "Error when saving b file"
aload 5
invokestatic com/flurry/android/ai/b(Ljava/lang/String;Ljava/lang/String;Ljava/lang/Throwable;)I
pop
L15:
aload 2
invokestatic com/flurry/android/r/a(Ljava/io/Closeable;)V
L16:
goto L18
L17:
aload 1
invokestatic com/flurry/android/r/a(Ljava/io/Closeable;)V
aload 2
athrow
L10:
astore 2
goto L17
L9:
astore 5
aload 4
astore 2
goto L19
L6:
astore 2
aconst_null
astore 1
goto L17
.limit locals 6
.limit stack 5
.end method

.method static synthetic c(Lcom/flurry/android/FlurryAgent;)V
aload 0
invokespecial com/flurry/android/FlurryAgent/n()V
return
.limit locals 1
.limit stack 1
.end method

.method private c(Ljava/lang/String;)V
.catch all from L0 to L1 using L2
.catch all from L1 to L3 using L2
aload 0
monitorenter
L0:
aload 0
getfield com/flurry/android/FlurryAgent/W Ljava/util/List;
invokeinterface java/util/List/iterator()Ljava/util/Iterator; 0
astore 2
L1:
aload 2
invokeinterface java/util/Iterator/hasNext()Z 0
ifeq L3
aload 2
invokeinterface java/util/Iterator/next()Ljava/lang/Object; 0
checkcast com/flurry/android/i
astore 3
aload 3
aload 1
invokevirtual com/flurry/android/i/a(Ljava/lang/String;)Z
ifeq L1
aload 3
invokestatic android/os/SystemClock/elapsedRealtime()J
aload 0
getfield com/flurry/android/FlurryAgent/L J
lsub
invokevirtual com/flurry/android/i/a(J)V
L3:
aload 0
monitorexit
return
L2:
astore 1
aload 0
monitorexit
aload 1
athrow
.limit locals 4
.limit stack 5
.end method

.method private c(Z)V
.catch java/io/IOException from L0 to L1 using L2
.catch java/lang/Throwable from L0 to L1 using L3
.catch java/io/IOException from L4 to L5 using L2
.catch java/lang/Throwable from L4 to L5 using L3
.catch java/io/IOException from L6 to L7 using L2
.catch java/lang/Throwable from L6 to L7 using L3
.catch java/io/IOException from L8 to L9 using L2
.catch java/lang/Throwable from L8 to L9 using L3
L0:
ldc "FlurryAgent"
ldc "generating report"
invokestatic com/flurry/android/ai/a(Ljava/lang/String;Ljava/lang/String;)I
pop
aload 0
iload 1
invokespecial com/flurry/android/FlurryAgent/b(Z)[B
astore 2
L1:
aload 2
ifnull L8
L4:
aload 0
aload 2
invokespecial com/flurry/android/FlurryAgent/a([B)Z
ifeq L10
new java/lang/StringBuilder
dup
invokespecial java/lang/StringBuilder/<init>()V
ldc "Done sending "
invokevirtual java/lang/StringBuilder/append(Ljava/lang/String;)Ljava/lang/StringBuilder;
astore 3
aload 0
getfield com/flurry/android/FlurryAgent/v Z
ifeq L11
L5:
ldc "initial "
astore 2
L6:
ldc "FlurryAgent"
aload 3
aload 2
invokevirtual java/lang/StringBuilder/append(Ljava/lang/String;)Ljava/lang/StringBuilder;
ldc "agent report"
invokevirtual java/lang/StringBuilder/append(Ljava/lang/String;)Ljava/lang/StringBuilder;
invokevirtual java/lang/StringBuilder/toString()Ljava/lang/String;
invokestatic com/flurry/android/ai/a(Ljava/lang/String;Ljava/lang/String;)I
pop
aload 0
invokespecial com/flurry/android/FlurryAgent/n()V
L7:
return
L8:
ldc "FlurryAgent"
ldc "Error generating report"
invokestatic com/flurry/android/ai/a(Ljava/lang/String;Ljava/lang/String;)I
pop
L9:
return
L2:
astore 2
ldc "FlurryAgent"
ldc ""
aload 2
invokestatic com/flurry/android/ai/a(Ljava/lang/String;Ljava/lang/String;Ljava/lang/Throwable;)I
pop
return
L3:
astore 2
ldc "FlurryAgent"
ldc ""
aload 2
invokestatic com/flurry/android/ai/b(Ljava/lang/String;Ljava/lang/String;Ljava/lang/Throwable;)I
pop
L10:
return
L11:
ldc ""
astore 2
goto L6
.limit locals 4
.limit stack 3
.end method

.method public static clearUserCookies()V
getstatic com/flurry/android/FlurryAgent/o Z
ifne L0
return
L0:
getstatic com/flurry/android/FlurryAgent/h Lcom/flurry/android/FlurryAgent;
getfield com/flurry/android/FlurryAgent/ab Lcom/flurry/android/v;
invokevirtual com/flurry/android/v/k()V
return
.limit locals 0
.limit stack 1
.end method

.method private d(Landroid/content/Context;)Landroid/location/Location;
.catch all from L0 to L1 using L2
.catch all from L1 to L3 using L2
.catch all from L4 to L5 using L2
.catch all from L6 to L7 using L2
aload 1
ldc "android.permission.ACCESS_FINE_LOCATION"
invokevirtual android/content/Context/checkCallingOrSelfPermission(Ljava/lang/String;)I
ifeq L8
aload 1
ldc "android.permission.ACCESS_COARSE_LOCATION"
invokevirtual android/content/Context/checkCallingOrSelfPermission(Ljava/lang/String;)I
ifne L9
L8:
aload 1
ldc "location"
invokevirtual android/content/Context/getSystemService(Ljava/lang/String;)Ljava/lang/Object;
checkcast android/location/LocationManager
astore 1
aload 0
monitorenter
L0:
aload 0
getfield com/flurry/android/FlurryAgent/E Landroid/location/LocationManager;
ifnonnull L4
aload 0
aload 1
putfield com/flurry/android/FlurryAgent/E Landroid/location/LocationManager;
L1:
aload 0
monitorexit
L3:
getstatic com/flurry/android/FlurryAgent/n Landroid/location/Criteria;
astore 3
aload 3
astore 2
aload 3
ifnonnull L10
new android/location/Criteria
dup
invokespecial android/location/Criteria/<init>()V
astore 2
L10:
aload 1
aload 2
iconst_1
invokevirtual android/location/LocationManager/getBestProvider(Landroid/location/Criteria;Z)Ljava/lang/String;
astore 2
aload 2
ifnull L9
aload 1
aload 2
lconst_0
fconst_0
aload 0
invokestatic android/os/Looper/getMainLooper()Landroid/os/Looper;
invokevirtual android/location/LocationManager/requestLocationUpdates(Ljava/lang/String;JFLandroid/location/LocationListener;Landroid/os/Looper;)V
aload 1
aload 2
invokevirtual android/location/LocationManager/getLastKnownLocation(Ljava/lang/String;)Landroid/location/Location;
areturn
L4:
aload 0
getfield com/flurry/android/FlurryAgent/E Landroid/location/LocationManager;
astore 1
L5:
goto L1
L2:
astore 1
L6:
aload 0
monitorexit
L7:
aload 1
athrow
L9:
aconst_null
areturn
.limit locals 4
.limit stack 7
.end method

.method static synthetic d(Lcom/flurry/android/FlurryAgent;)Landroid/os/Handler;
aload 0
getfield com/flurry/android/FlurryAgent/s Landroid/os/Handler;
areturn
.limit locals 1
.limit stack 1
.end method

.method private static d(Ljava/lang/String;)Ljava/lang/String;
aload 0
astore 2
aload 0
ifnull L0
aload 0
astore 2
aload 0
invokevirtual java/lang/String/length()I
iconst_4
if_icmple L0
new java/lang/StringBuilder
dup
invokespecial java/lang/StringBuilder/<init>()V
astore 2
iconst_0
istore 1
L1:
iload 1
aload 0
invokevirtual java/lang/String/length()I
iconst_4
isub
if_icmpge L2
aload 2
bipush 42
invokevirtual java/lang/StringBuilder/append(C)Ljava/lang/StringBuilder;
pop
iload 1
iconst_1
iadd
istore 1
goto L1
L2:
aload 2
aload 0
aload 0
invokevirtual java/lang/String/length()I
iconst_4
isub
invokevirtual java/lang/String/substring(I)Ljava/lang/String;
invokevirtual java/lang/StringBuilder/append(Ljava/lang/String;)Ljava/lang/StringBuilder;
pop
aload 2
invokevirtual java/lang/StringBuilder/toString()Ljava/lang/String;
astore 2
L0:
aload 2
areturn
.limit locals 3
.limit stack 4
.end method

.method static d()Z
getstatic com/flurry/android/FlurryAgent/o Z
ifne L0
iconst_0
ireturn
L0:
getstatic com/flurry/android/FlurryAgent/h Lcom/flurry/android/FlurryAgent;
getfield com/flurry/android/FlurryAgent/ab Lcom/flurry/android/v;
invokevirtual com/flurry/android/v/m()Z
ireturn
.limit locals 0
.limit stack 1
.end method

.method static synthetic e(Lcom/flurry/android/FlurryAgent;)Lcom/flurry/android/v;
aload 0
getfield com/flurry/android/FlurryAgent/ab Lcom/flurry/android/v;
areturn
.limit locals 1
.limit stack 1
.end method

.method static e()Ljava/lang/String;
getstatic com/flurry/android/FlurryAgent/h Lcom/flurry/android/FlurryAgent;
getfield com/flurry/android/FlurryAgent/z Ljava/lang/String;
areturn
.limit locals 0
.limit stack 1
.end method

.method private static e(Landroid/content/Context;)[B
.catch java/lang/Exception from L0 to L1 using L2
.catch java/lang/Exception from L3 to L4 using L2
.catch java/lang/Exception from L5 to L6 using L2
aload 0
ldc "android.permission.READ_PHONE_STATE"
invokevirtual android/content/Context/checkCallingOrSelfPermission(Ljava/lang/String;)I
ifne L6
aload 0
ldc "phone"
invokevirtual android/content/Context/getSystemService(Ljava/lang/String;)Ljava/lang/Object;
checkcast android/telephony/TelephonyManager
astore 0
aload 0
ifnull L6
aload 0
invokevirtual android/telephony/TelephonyManager/getDeviceId()Ljava/lang/String;
astore 0
aload 0
ifnull L6
L0:
aload 0
invokestatic com/flurry/android/r/b(Ljava/lang/String;)[B
astore 0
L1:
aload 0
ifnull L5
L3:
aload 0
arraylength
bipush 20
if_icmpne L5
L4:
aload 0
areturn
L5:
ldc "FlurryAgent"
new java/lang/StringBuilder
dup
invokespecial java/lang/StringBuilder/<init>()V
ldc "sha1 is not 20 bytes long: "
invokevirtual java/lang/StringBuilder/append(Ljava/lang/String;)Ljava/lang/StringBuilder;
aload 0
invokestatic java/util/Arrays/toString([B)Ljava/lang/String;
invokevirtual java/lang/StringBuilder/append(Ljava/lang/String;)Ljava/lang/StringBuilder;
invokevirtual java/lang/StringBuilder/toString()Ljava/lang/String;
invokestatic com/flurry/android/ai/b(Ljava/lang/String;Ljava/lang/String;)I
pop
L6:
aconst_null
areturn
L2:
astore 0
goto L6
.limit locals 1
.limit stack 3
.end method

.method public static enableAppCircle()V
iconst_1
putstatic com/flurry/android/FlurryAgent/o Z
return
.limit locals 0
.limit stack 1
.end method

.method public static endTimedEvent(Ljava/lang/String;)V
.catch java/lang/Throwable from L0 to L1 using L2
L0:
getstatic com/flurry/android/FlurryAgent/h Lcom/flurry/android/FlurryAgent;
aload 0
invokespecial com/flurry/android/FlurryAgent/c(Ljava/lang/String;)V
L1:
return
L2:
astore 1
ldc "FlurryAgent"
new java/lang/StringBuilder
dup
invokespecial java/lang/StringBuilder/<init>()V
ldc "Failed to signify the end of event: "
invokevirtual java/lang/StringBuilder/append(Ljava/lang/String;)Ljava/lang/StringBuilder;
aload 0
invokevirtual java/lang/StringBuilder/append(Ljava/lang/String;)Ljava/lang/StringBuilder;
invokevirtual java/lang/StringBuilder/toString()Ljava/lang/String;
aload 1
invokestatic com/flurry/android/ai/b(Ljava/lang/String;Ljava/lang/String;Ljava/lang/Throwable;)I
pop
return
.limit locals 2
.limit stack 3
.end method

.method static f()I
getstatic com/flurry/android/FlurryAgent/q Ljava/util/concurrent/atomic/AtomicInteger;
invokevirtual java/util/concurrent/atomic/AtomicInteger/incrementAndGet()I
ireturn
.limit locals 0
.limit stack 1
.end method

.method static g()I
getstatic com/flurry/android/FlurryAgent/r Ljava/util/concurrent/atomic/AtomicInteger;
invokevirtual java/util/concurrent/atomic/AtomicInteger/incrementAndGet()I
ireturn
.limit locals 0
.limit stack 1
.end method

.method public static getAgentVersion()I
bipush 122
ireturn
.limit locals 0
.limit stack 1
.end method

.method public static getAppCircle()Lcom/flurry/android/AppCircle;
getstatic com/flurry/android/FlurryAgent/p Lcom/flurry/android/AppCircle;
areturn
.limit locals 0
.limit stack 1
.end method

.method public static getForbidPlaintextFallback()Z
iconst_0
ireturn
.limit locals 0
.limit stack 1
.end method

.method public static getPhoneId()Ljava/lang/String;
getstatic com/flurry/android/FlurryAgent/h Lcom/flurry/android/FlurryAgent;
invokespecial com/flurry/android/FlurryAgent/p()Ljava/lang/String;
areturn
.limit locals 0
.limit stack 1
.end method

.method static synthetic h()Lcom/flurry/android/FlurryAgent;
getstatic com/flurry/android/FlurryAgent/h Lcom/flurry/android/FlurryAgent;
areturn
.limit locals 0
.limit stack 1
.end method

.method static synthetic i()J
getstatic com/flurry/android/FlurryAgent/i J
lreturn
.limit locals 0
.limit stack 2
.end method

.method protected static isCaptureUncaughtExceptions()Z
getstatic com/flurry/android/FlurryAgent/m Z
ireturn
.limit locals 0
.limit stack 1
.end method

.method static synthetic j()Z
getstatic com/flurry/android/FlurryAgent/o Z
ireturn
.limit locals 0
.limit stack 1
.end method

.method private k()V
.catch java/io/IOException from L0 to L1 using L2
.catch all from L0 to L1 using L3
.catch java/io/IOException from L1 to L4 using L5
.catch all from L1 to L4 using L6
.catch java/io/IOException from L7 to L8 using L5
.catch all from L7 to L8 using L6
.catch java/io/IOException from L8 to L9 using L5
.catch all from L8 to L9 using L6
.catch java/io/IOException from L9 to L10 using L5
.catch all from L9 to L10 using L6
.catch java/io/IOException from L10 to L11 using L5
.catch all from L10 to L11 using L6
.catch all from L12 to L13 using L14
.catch all from L13 to L15 using L16
.catch java/io/IOException from L17 to L18 using L5
.catch all from L17 to L18 using L6
.catch java/io/IOException from L19 to L20 using L5
.catch all from L19 to L20 using L6
.catch all from L21 to L16 using L16
.catch java/io/IOException from L22 to L23 using L5
.catch all from L22 to L23 using L6
.catch java/io/IOException from L24 to L25 using L5
.catch all from L24 to L25 using L6
.catch java/io/IOException from L25 to L26 using L5
.catch all from L25 to L26 using L6
.catch java/io/IOException from L27 to L28 using L5
.catch all from L27 to L28 using L6
.catch java/io/IOException from L28 to L29 using L5
.catch all from L28 to L29 using L6
.catch java/io/IOException from L30 to L31 using L5
.catch all from L30 to L31 using L6
.catch java/io/IOException from L31 to L32 using L5
.catch all from L31 to L32 using L6
.catch java/io/IOException from L33 to L34 using L5
.catch all from L33 to L34 using L6
.catch java/io/IOException from L34 to L35 using L5
.catch all from L34 to L35 using L6
.catch all from L35 to L36 using L16
aload 0
monitorenter
aconst_null
astore 1
L0:
new java/io/ByteArrayOutputStream
dup
invokespecial java/io/ByteArrayOutputStream/<init>()V
astore 3
new java/io/DataOutputStream
dup
aload 3
invokespecial java/io/DataOutputStream/<init>(Ljava/io/OutputStream;)V
astore 2
L1:
aload 2
iconst_1
invokevirtual java/io/DataOutputStream/writeShort(I)V
aload 2
aload 0
getfield com/flurry/android/FlurryAgent/B Ljava/lang/String;
invokevirtual java/io/DataOutputStream/writeUTF(Ljava/lang/String;)V
aload 2
aload 0
getfield com/flurry/android/FlurryAgent/K J
invokevirtual java/io/DataOutputStream/writeLong(J)V
aload 2
aload 0
getfield com/flurry/android/FlurryAgent/M J
invokevirtual java/io/DataOutputStream/writeLong(J)V
aload 2
lconst_0
invokevirtual java/io/DataOutputStream/writeLong(J)V
aload 2
aload 0
getfield com/flurry/android/FlurryAgent/N Ljava/lang/String;
invokevirtual java/io/DataOutputStream/writeUTF(Ljava/lang/String;)V
aload 2
aload 0
getfield com/flurry/android/FlurryAgent/O Ljava/lang/String;
invokevirtual java/io/DataOutputStream/writeUTF(Ljava/lang/String;)V
aload 2
aload 0
getfield com/flurry/android/FlurryAgent/P B
invokevirtual java/io/DataOutputStream/writeByte(I)V
aload 0
getfield com/flurry/android/FlurryAgent/Q Ljava/lang/String;
ifnonnull L17
L4:
ldc ""
astore 1
L7:
aload 2
aload 1
invokevirtual java/io/DataOutputStream/writeUTF(Ljava/lang/String;)V
aload 0
getfield com/flurry/android/FlurryAgent/U Landroid/location/Location;
ifnonnull L19
aload 2
iconst_0
invokevirtual java/io/DataOutputStream/writeBoolean(Z)V
L8:
aload 2
aload 0
getfield com/flurry/android/FlurryAgent/aa I
invokevirtual java/io/DataOutputStream/writeInt(I)V
aload 2
iconst_m1
invokevirtual java/io/DataOutputStream/writeByte(I)V
aload 2
iconst_m1
invokevirtual java/io/DataOutputStream/writeByte(I)V
aload 2
aload 0
getfield com/flurry/android/FlurryAgent/R B
invokevirtual java/io/DataOutputStream/writeByte(I)V
aload 0
getfield com/flurry/android/FlurryAgent/S Ljava/lang/Long;
ifnonnull L22
aload 2
iconst_0
invokevirtual java/io/DataOutputStream/writeBoolean(Z)V
L9:
aload 2
aload 0
getfield com/flurry/android/FlurryAgent/V Ljava/util/Map;
invokeinterface java/util/Map/size()I 0
invokevirtual java/io/DataOutputStream/writeShort(I)V
aload 0
getfield com/flurry/android/FlurryAgent/V Ljava/util/Map;
invokeinterface java/util/Map/entrySet()Ljava/util/Set; 0
invokeinterface java/util/Set/iterator()Ljava/util/Iterator; 0
astore 1
L10:
aload 1
invokeinterface java/util/Iterator/hasNext()Z 0
ifeq L24
aload 1
invokeinterface java/util/Iterator/next()Ljava/lang/Object; 0
checkcast java/util/Map$Entry
astore 4
aload 2
aload 4
invokeinterface java/util/Map$Entry/getKey()Ljava/lang/Object; 0
checkcast java/lang/String
invokevirtual java/io/DataOutputStream/writeUTF(Ljava/lang/String;)V
aload 2
aload 4
invokeinterface java/util/Map$Entry/getValue()Ljava/lang/Object; 0
checkcast com/flurry/android/g
getfield com/flurry/android/g/a I
invokevirtual java/io/DataOutputStream/writeInt(I)V
L11:
goto L10
L5:
astore 3
aload 2
astore 1
aload 3
astore 2
L12:
ldc "FlurryAgent"
ldc ""
aload 2
invokestatic com/flurry/android/ai/b(Ljava/lang/String;Ljava/lang/String;Ljava/lang/Throwable;)I
pop
L13:
aload 1
invokestatic com/flurry/android/r/a(Ljava/io/Closeable;)V
L15:
aload 0
monitorexit
return
L17:
aload 0
getfield com/flurry/android/FlurryAgent/Q Ljava/lang/String;
astore 1
L18:
goto L7
L19:
aload 2
iconst_1
invokevirtual java/io/DataOutputStream/writeBoolean(Z)V
aload 2
aload 0
getfield com/flurry/android/FlurryAgent/U Landroid/location/Location;
invokevirtual android/location/Location/getLatitude()D
invokestatic com/flurry/android/FlurryAgent/a(D)D
invokevirtual java/io/DataOutputStream/writeDouble(D)V
aload 2
aload 0
getfield com/flurry/android/FlurryAgent/U Landroid/location/Location;
invokevirtual android/location/Location/getLongitude()D
invokestatic com/flurry/android/FlurryAgent/a(D)D
invokevirtual java/io/DataOutputStream/writeDouble(D)V
aload 2
aload 0
getfield com/flurry/android/FlurryAgent/U Landroid/location/Location;
invokevirtual android/location/Location/getAccuracy()F
invokevirtual java/io/DataOutputStream/writeFloat(F)V
L20:
goto L8
L6:
astore 1
L21:
aload 2
invokestatic com/flurry/android/r/a(Ljava/io/Closeable;)V
aload 1
athrow
L16:
astore 1
aload 0
monitorexit
aload 1
athrow
L22:
aload 2
iconst_1
invokevirtual java/io/DataOutputStream/writeBoolean(Z)V
aload 2
aload 0
getfield com/flurry/android/FlurryAgent/S Ljava/lang/Long;
invokevirtual java/lang/Long/longValue()J
invokevirtual java/io/DataOutputStream/writeLong(J)V
L23:
goto L9
L24:
aload 2
aload 0
getfield com/flurry/android/FlurryAgent/W Ljava/util/List;
invokeinterface java/util/List/size()I 0
invokevirtual java/io/DataOutputStream/writeShort(I)V
aload 0
getfield com/flurry/android/FlurryAgent/W Ljava/util/List;
invokeinterface java/util/List/iterator()Ljava/util/Iterator; 0
astore 1
L25:
aload 1
invokeinterface java/util/Iterator/hasNext()Z 0
ifeq L27
aload 2
aload 1
invokeinterface java/util/Iterator/next()Ljava/lang/Object; 0
checkcast com/flurry/android/i
invokevirtual com/flurry/android/i/a()[B
invokevirtual java/io/DataOutputStream/write([B)V
L26:
goto L25
L27:
aload 2
aload 0
getfield com/flurry/android/FlurryAgent/X Z
invokevirtual java/io/DataOutputStream/writeBoolean(Z)V
aload 2
aload 0
getfield com/flurry/android/FlurryAgent/T I
invokevirtual java/io/DataOutputStream/writeInt(I)V
aload 2
aload 0
getfield com/flurry/android/FlurryAgent/Z Ljava/util/List;
invokeinterface java/util/List/size()I 0
invokevirtual java/io/DataOutputStream/writeShort(I)V
aload 0
getfield com/flurry/android/FlurryAgent/Z Ljava/util/List;
invokeinterface java/util/List/iterator()Ljava/util/Iterator; 0
astore 1
L28:
aload 1
invokeinterface java/util/Iterator/hasNext()Z 0
ifeq L30
aload 1
invokeinterface java/util/Iterator/next()Ljava/lang/Object; 0
checkcast com/flurry/android/ab
astore 4
aload 2
aload 4
getfield com/flurry/android/ab/a I
invokevirtual java/io/DataOutputStream/writeShort(I)V
aload 2
aload 4
getfield com/flurry/android/ab/b J
invokevirtual java/io/DataOutputStream/writeLong(J)V
aload 2
aload 4
getfield com/flurry/android/ab/c Ljava/lang/String;
invokevirtual java/io/DataOutputStream/writeUTF(Ljava/lang/String;)V
aload 2
aload 4
getfield com/flurry/android/ab/d Ljava/lang/String;
invokevirtual java/io/DataOutputStream/writeUTF(Ljava/lang/String;)V
aload 2
aload 4
getfield com/flurry/android/ab/e Ljava/lang/String;
invokevirtual java/io/DataOutputStream/writeUTF(Ljava/lang/String;)V
L29:
goto L28
L30:
getstatic com/flurry/android/FlurryAgent/o Z
ifeq L33
aload 0
getfield com/flurry/android/FlurryAgent/ab Lcom/flurry/android/v;
invokevirtual com/flurry/android/v/f()Ljava/util/List;
astore 1
aload 2
aload 1
invokeinterface java/util/List/size()I 0
invokevirtual java/io/DataOutputStream/writeShort(I)V
aload 1
invokeinterface java/util/List/iterator()Ljava/util/Iterator; 0
astore 1
L31:
aload 1
invokeinterface java/util/Iterator/hasNext()Z 0
ifeq L34
aload 1
invokeinterface java/util/Iterator/next()Ljava/lang/Object; 0
checkcast com/flurry/android/p
aload 2
invokevirtual com/flurry/android/p/a(Ljava/io/DataOutput;)V
L32:
goto L31
L33:
aload 2
iconst_0
invokevirtual java/io/DataOutputStream/writeShort(I)V
L34:
aload 2
iconst_0
invokevirtual java/io/DataOutputStream/writeShort(I)V
aload 0
getfield com/flurry/android/FlurryAgent/J Ljava/util/List;
aload 3
invokevirtual java/io/ByteArrayOutputStream/toByteArray()[B
invokeinterface java/util/List/add(Ljava/lang/Object;)Z 1
pop
L35:
aload 2
invokestatic com/flurry/android/r/a(Ljava/io/Closeable;)V
L36:
goto L15
L3:
astore 1
aconst_null
astore 2
goto L21
L14:
astore 3
aload 1
astore 2
aload 3
astore 1
goto L21
L2:
astore 2
goto L12
.limit locals 5
.limit stack 3
.end method

.method private l()V
.catch all from L0 to L1 using L2
aload 0
monitorenter
L0:
aload 0
aload 0
getfield com/flurry/android/FlurryAgent/aa I
iconst_1
iadd
putfield com/flurry/android/FlurryAgent/aa I
L1:
aload 0
monitorexit
return
L2:
astore 1
aload 0
monitorexit
aload 1
athrow
.limit locals 2
.limit stack 3
.end method

.method public static logEvent(Ljava/lang/String;)V
.catch java/lang/Throwable from L0 to L1 using L2
L0:
getstatic com/flurry/android/FlurryAgent/h Lcom/flurry/android/FlurryAgent;
aload 0
aconst_null
iconst_0
invokespecial com/flurry/android/FlurryAgent/a(Ljava/lang/String;Ljava/util/Map;Z)V
L1:
return
L2:
astore 1
ldc "FlurryAgent"
new java/lang/StringBuilder
dup
invokespecial java/lang/StringBuilder/<init>()V
ldc "Failed to log event: "
invokevirtual java/lang/StringBuilder/append(Ljava/lang/String;)Ljava/lang/StringBuilder;
aload 0
invokevirtual java/lang/StringBuilder/append(Ljava/lang/String;)Ljava/lang/StringBuilder;
invokevirtual java/lang/StringBuilder/toString()Ljava/lang/String;
aload 1
invokestatic com/flurry/android/ai/b(Ljava/lang/String;Ljava/lang/String;Ljava/lang/Throwable;)I
pop
return
.limit locals 2
.limit stack 4
.end method

.method public static logEvent(Ljava/lang/String;Ljava/util/Map;)V
.catch java/lang/Throwable from L0 to L1 using L2
L0:
getstatic com/flurry/android/FlurryAgent/h Lcom/flurry/android/FlurryAgent;
aload 0
aload 1
iconst_0
invokespecial com/flurry/android/FlurryAgent/a(Ljava/lang/String;Ljava/util/Map;Z)V
L1:
return
L2:
astore 1
ldc "FlurryAgent"
new java/lang/StringBuilder
dup
invokespecial java/lang/StringBuilder/<init>()V
ldc "Failed to log event: "
invokevirtual java/lang/StringBuilder/append(Ljava/lang/String;)Ljava/lang/StringBuilder;
aload 0
invokevirtual java/lang/StringBuilder/append(Ljava/lang/String;)Ljava/lang/StringBuilder;
invokevirtual java/lang/StringBuilder/toString()Ljava/lang/String;
aload 1
invokestatic com/flurry/android/ai/b(Ljava/lang/String;Ljava/lang/String;Ljava/lang/Throwable;)I
pop
return
.limit locals 2
.limit stack 4
.end method

.method public static logEvent(Ljava/lang/String;Ljava/util/Map;Z)V
.catch java/lang/Throwable from L0 to L1 using L2
L0:
getstatic com/flurry/android/FlurryAgent/h Lcom/flurry/android/FlurryAgent;
aload 0
aload 1
iload 2
invokespecial com/flurry/android/FlurryAgent/a(Ljava/lang/String;Ljava/util/Map;Z)V
L1:
return
L2:
astore 1
ldc "FlurryAgent"
new java/lang/StringBuilder
dup
invokespecial java/lang/StringBuilder/<init>()V
ldc "Failed to log event: "
invokevirtual java/lang/StringBuilder/append(Ljava/lang/String;)Ljava/lang/StringBuilder;
aload 0
invokevirtual java/lang/StringBuilder/append(Ljava/lang/String;)Ljava/lang/StringBuilder;
invokevirtual java/lang/StringBuilder/toString()Ljava/lang/String;
aload 1
invokestatic com/flurry/android/ai/b(Ljava/lang/String;Ljava/lang/String;Ljava/lang/Throwable;)I
pop
return
.limit locals 3
.limit stack 4
.end method

.method public static logEvent(Ljava/lang/String;Z)V
.catch java/lang/Throwable from L0 to L1 using L2
L0:
getstatic com/flurry/android/FlurryAgent/h Lcom/flurry/android/FlurryAgent;
aload 0
aconst_null
iload 1
invokespecial com/flurry/android/FlurryAgent/a(Ljava/lang/String;Ljava/util/Map;Z)V
L1:
return
L2:
astore 2
ldc "FlurryAgent"
new java/lang/StringBuilder
dup
invokespecial java/lang/StringBuilder/<init>()V
ldc "Failed to log event: "
invokevirtual java/lang/StringBuilder/append(Ljava/lang/String;)Ljava/lang/StringBuilder;
aload 0
invokevirtual java/lang/StringBuilder/append(Ljava/lang/String;)Ljava/lang/StringBuilder;
invokevirtual java/lang/StringBuilder/toString()Ljava/lang/String;
aload 2
invokestatic com/flurry/android/ai/b(Ljava/lang/String;Ljava/lang/String;Ljava/lang/Throwable;)I
pop
return
.limit locals 3
.limit stack 4
.end method

.method private static m()Ljava/lang/String;
getstatic com/flurry/android/FlurryAgent/c Ljava/lang/String;
ifnull L0
getstatic com/flurry/android/FlurryAgent/c Ljava/lang/String;
areturn
L0:
getstatic com/flurry/android/FlurryAgent/l Z
ifeq L1
getstatic com/flurry/android/FlurryAgent/kInsecureReportUrl Ljava/lang/String;
areturn
L1:
getstatic com/flurry/android/FlurryAgent/k Z
ifeq L2
getstatic com/flurry/android/FlurryAgent/kSecureReportUrl Ljava/lang/String;
areturn
L2:
getstatic com/flurry/android/FlurryAgent/kInsecureReportUrl Ljava/lang/String;
areturn
.limit locals 0
.limit stack 1
.end method

.method private n()V
.catch java/lang/Throwable from L0 to L1 using L2
.catch all from L0 to L1 using L3
.catch all from L4 to L5 using L6
.catch java/lang/Throwable from L7 to L8 using L2
.catch all from L7 to L8 using L3
.catch java/lang/Throwable from L9 to L10 using L11
.catch all from L9 to L10 using L12
.catch java/lang/Throwable from L13 to L14 using L11
.catch all from L13 to L14 using L12
.catch java/lang/Throwable from L15 to L16 using L11
.catch all from L15 to L16 using L12
.catch java/lang/Throwable from L17 to L18 using L11
.catch all from L17 to L18 using L12
.catch java/lang/Throwable from L19 to L20 using L11
.catch all from L19 to L20 using L12
.catch java/lang/Throwable from L21 to L22 using L11
.catch all from L21 to L22 using L12
.catch java/lang/Throwable from L23 to L24 using L11
.catch all from L23 to L24 using L12
.catch java/lang/Throwable from L25 to L26 using L11
.catch all from L25 to L26 using L12
.catch java/lang/Throwable from L27 to L28 using L11
.catch all from L27 to L28 using L12
.catch java/lang/Throwable from L29 to L30 using L11
.catch all from L29 to L30 using L12
.catch java/lang/Throwable from L31 to L32 using L11
.catch all from L31 to L32 using L12
.catch java/lang/Throwable from L33 to L34 using L11
.catch all from L33 to L34 using L12
.catch all from L34 to L35 using L6
.catch java/lang/Throwable from L36 to L37 using L11
.catch all from L36 to L37 using L12
.catch java/lang/Throwable from L38 to L39 using L11
.catch all from L38 to L39 using L12
.catch all from L40 to L41 using L12
.catch all from L41 to L42 using L6
.catch all from L43 to L12 using L6
aload 0
monitorenter
L0:
aload 0
getfield com/flurry/android/FlurryAgent/u Ljava/io/File;
invokestatic com/flurry/android/FlurryAgent/a(Ljava/io/File;)Z
istore 3
L1:
iload 3
ifne L7
L4:
aconst_null
invokestatic com/flurry/android/r/a(Ljava/io/Closeable;)V
L5:
aload 0
monitorexit
return
L7:
new java/io/DataOutputStream
dup
new java/io/FileOutputStream
dup
aload 0
getfield com/flurry/android/FlurryAgent/u Ljava/io/File;
invokespecial java/io/FileOutputStream/<init>(Ljava/io/File;)V
invokespecial java/io/DataOutputStream/<init>(Ljava/io/OutputStream;)V
astore 5
L8:
aload 5
astore 4
L9:
aload 5
ldc_w 46586
invokevirtual java/io/DataOutputStream/writeShort(I)V
L10:
aload 5
astore 4
L13:
aload 5
iconst_2
invokevirtual java/io/DataOutputStream/writeShort(I)V
L14:
aload 5
astore 4
L15:
aload 5
aload 0
getfield com/flurry/android/FlurryAgent/z Ljava/lang/String;
invokevirtual java/io/DataOutputStream/writeUTF(Ljava/lang/String;)V
L16:
aload 5
astore 4
L17:
aload 5
aload 0
getfield com/flurry/android/FlurryAgent/F Ljava/lang/String;
invokevirtual java/io/DataOutputStream/writeUTF(Ljava/lang/String;)V
L18:
aload 5
astore 4
L19:
aload 5
aload 0
getfield com/flurry/android/FlurryAgent/G Z
invokevirtual java/io/DataOutputStream/writeBoolean(Z)V
L20:
aload 5
astore 4
L21:
aload 5
aload 0
getfield com/flurry/android/FlurryAgent/H J
invokevirtual java/io/DataOutputStream/writeLong(J)V
L22:
aload 5
astore 4
L23:
aload 0
getfield com/flurry/android/FlurryAgent/J Ljava/util/List;
invokeinterface java/util/List/size()I 0
iconst_1
isub
istore 1
L24:
iload 1
iflt L32
aload 5
astore 4
L25:
aload 0
getfield com/flurry/android/FlurryAgent/J Ljava/util/List;
iload 1
invokeinterface java/util/List/get(I)Ljava/lang/Object; 1
checkcast [B
astore 6
L26:
aload 5
astore 4
L27:
aload 6
arraylength
istore 2
L28:
aload 5
astore 4
L29:
iload 2
iconst_2
iadd
aload 5
invokevirtual java/io/DataOutputStream/size()I
iadd
ldc_w 50000
if_icmple L44
L30:
aload 5
astore 4
L31:
ldc "FlurryAgent"
new java/lang/StringBuilder
dup
invokespecial java/lang/StringBuilder/<init>()V
ldc "discarded sessions: "
invokevirtual java/lang/StringBuilder/append(Ljava/lang/String;)Ljava/lang/StringBuilder;
iload 1
invokevirtual java/lang/StringBuilder/append(I)Ljava/lang/StringBuilder;
invokevirtual java/lang/StringBuilder/toString()Ljava/lang/String;
invokestatic com/flurry/android/ai/a(Ljava/lang/String;Ljava/lang/String;)I
pop
L32:
aload 5
astore 4
L33:
aload 5
iconst_0
invokevirtual java/io/DataOutputStream/writeShort(I)V
L34:
aload 5
invokestatic com/flurry/android/r/a(Ljava/io/Closeable;)V
L35:
goto L5
L6:
astore 4
aload 0
monitorexit
aload 4
athrow
L44:
aload 5
astore 4
L36:
aload 5
iload 2
invokevirtual java/io/DataOutputStream/writeShort(I)V
L37:
aload 5
astore 4
L38:
aload 5
aload 6
invokevirtual java/io/DataOutputStream/write([B)V
L39:
iload 1
iconst_1
isub
istore 1
goto L24
L2:
astore 6
aconst_null
astore 5
L45:
aload 5
astore 4
L40:
ldc "FlurryAgent"
ldc ""
aload 6
invokestatic com/flurry/android/ai/b(Ljava/lang/String;Ljava/lang/String;Ljava/lang/Throwable;)I
pop
L41:
aload 5
invokestatic com/flurry/android/r/a(Ljava/io/Closeable;)V
L42:
goto L5
L43:
aload 4
invokestatic com/flurry/android/r/a(Ljava/io/Closeable;)V
aload 5
athrow
L12:
astore 5
goto L43
L11:
astore 6
goto L45
L3:
astore 5
aconst_null
astore 4
goto L43
.limit locals 7
.limit stack 5
.end method

.method private o()V
.catch all from L0 to L1 using L2
aload 0
monitorenter
L0:
aload 0
getfield com/flurry/android/FlurryAgent/E Landroid/location/LocationManager;
ifnull L1
aload 0
getfield com/flurry/android/FlurryAgent/E Landroid/location/LocationManager;
aload 0
invokevirtual android/location/LocationManager/removeUpdates(Landroid/location/LocationListener;)V
L1:
aload 0
monitorexit
return
L2:
astore 1
aload 0
monitorexit
aload 1
athrow
.limit locals 2
.limit stack 2
.end method

.method public static onEndSession(Landroid/content/Context;)V
.catch java/lang/Throwable from L0 to L1 using L2
aload 0
ifnonnull L0
new java/lang/NullPointerException
dup
ldc "Null context"
invokespecial java/lang/NullPointerException/<init>(Ljava/lang/String;)V
athrow
L0:
getstatic com/flurry/android/FlurryAgent/h Lcom/flurry/android/FlurryAgent;
aload 0
iconst_0
invokespecial com/flurry/android/FlurryAgent/a(Landroid/content/Context;Z)V
L1:
return
L2:
astore 0
ldc "FlurryAgent"
ldc ""
aload 0
invokestatic com/flurry/android/ai/b(Ljava/lang/String;Ljava/lang/String;Ljava/lang/Throwable;)I
pop
return
.limit locals 1
.limit stack 3
.end method

.method public static onError(Ljava/lang/String;Ljava/lang/String;Ljava/lang/String;)V
.catch java/lang/Throwable from L0 to L1 using L2
L0:
getstatic com/flurry/android/FlurryAgent/h Lcom/flurry/android/FlurryAgent;
aload 0
aload 1
aload 2
invokespecial com/flurry/android/FlurryAgent/a(Ljava/lang/String;Ljava/lang/String;Ljava/lang/String;)V
L1:
return
L2:
astore 0
ldc "FlurryAgent"
ldc ""
aload 0
invokestatic com/flurry/android/ai/b(Ljava/lang/String;Ljava/lang/String;Ljava/lang/Throwable;)I
pop
return
.limit locals 3
.limit stack 4
.end method

.method public static onEvent(Ljava/lang/String;)V
.catch java/lang/Throwable from L0 to L1 using L2
L0:
getstatic com/flurry/android/FlurryAgent/h Lcom/flurry/android/FlurryAgent;
aload 0
aconst_null
iconst_0
invokespecial com/flurry/android/FlurryAgent/a(Ljava/lang/String;Ljava/util/Map;Z)V
L1:
return
L2:
astore 0
ldc "FlurryAgent"
ldc ""
aload 0
invokestatic com/flurry/android/ai/b(Ljava/lang/String;Ljava/lang/String;Ljava/lang/Throwable;)I
pop
return
.limit locals 1
.limit stack 4
.end method

.method public static onEvent(Ljava/lang/String;Ljava/util/Map;)V
.catch java/lang/Throwable from L0 to L1 using L2
L0:
getstatic com/flurry/android/FlurryAgent/h Lcom/flurry/android/FlurryAgent;
aload 0
aload 1
iconst_0
invokespecial com/flurry/android/FlurryAgent/a(Ljava/lang/String;Ljava/util/Map;Z)V
L1:
return
L2:
astore 0
ldc "FlurryAgent"
ldc ""
aload 0
invokestatic com/flurry/android/ai/b(Ljava/lang/String;Ljava/lang/String;Ljava/lang/Throwable;)I
pop
return
.limit locals 2
.limit stack 4
.end method

.method public static onPageView()V
.catch java/lang/Throwable from L0 to L1 using L2
L0:
getstatic com/flurry/android/FlurryAgent/h Lcom/flurry/android/FlurryAgent;
invokespecial com/flurry/android/FlurryAgent/l()V
L1:
return
L2:
astore 0
ldc "FlurryAgent"
ldc ""
aload 0
invokestatic com/flurry/android/ai/b(Ljava/lang/String;Ljava/lang/String;Ljava/lang/Throwable;)I
pop
return
.limit locals 1
.limit stack 3
.end method

.method public static onStartSession(Landroid/content/Context;Ljava/lang/String;)V
.catch java/lang/Throwable from L0 to L1 using L2
aload 0
ifnonnull L3
new java/lang/NullPointerException
dup
ldc "Null context"
invokespecial java/lang/NullPointerException/<init>(Ljava/lang/String;)V
athrow
L3:
aload 1
ifnull L4
aload 1
invokevirtual java/lang/String/length()I
ifne L0
L4:
new java/lang/IllegalArgumentException
dup
ldc "Api key not specified"
invokespecial java/lang/IllegalArgumentException/<init>(Ljava/lang/String;)V
athrow
L0:
getstatic com/flurry/android/FlurryAgent/h Lcom/flurry/android/FlurryAgent;
aload 0
aload 1
invokespecial com/flurry/android/FlurryAgent/b(Landroid/content/Context;Ljava/lang/String;)V
L1:
return
L2:
astore 0
ldc "FlurryAgent"
ldc ""
aload 0
invokestatic com/flurry/android/ai/b(Ljava/lang/String;Ljava/lang/String;Ljava/lang/Throwable;)I
pop
return
.limit locals 2
.limit stack 3
.end method

.method private p()Ljava/lang/String;
.catch all from L0 to L1 using L2
aload 0
monitorenter
L0:
aload 0
getfield com/flurry/android/FlurryAgent/F Ljava/lang/String;
astore 1
L1:
aload 0
monitorexit
aload 1
areturn
L2:
astore 1
aload 0
monitorexit
aload 1
athrow
.limit locals 2
.limit stack 1
.end method

.method public static setAge(I)V
iload 0
ifle L0
iload 0
bipush 110
if_icmpge L0
new java/util/Date
dup
new java/util/Date
dup
invokestatic java/lang/System/currentTimeMillis()J
iload 0
i2l
ldc2_w 31449600000L
lmul
lsub
invokespecial java/util/Date/<init>(J)V
invokevirtual java/util/Date/getYear()I
iconst_1
iconst_1
invokespecial java/util/Date/<init>(III)V
astore 1
getstatic com/flurry/android/FlurryAgent/h Lcom/flurry/android/FlurryAgent;
aload 1
invokevirtual java/util/Date/getTime()J
invokestatic java/lang/Long/valueOf(J)Ljava/lang/Long;
putfield com/flurry/android/FlurryAgent/S Ljava/lang/Long;
L0:
return
.limit locals 2
.limit stack 10
.end method

.method public static setCanvasUrl(Ljava/lang/String;)V
aload 0
putstatic com/flurry/android/FlurryAgent/d Ljava/lang/String;
return
.limit locals 1
.limit stack 1
.end method

.method public static setCaptureUncaughtExceptions(Z)V
.catch all from L0 to L1 using L2
.catch all from L3 to L4 using L2
.catch all from L5 to L6 using L2
getstatic com/flurry/android/FlurryAgent/h Lcom/flurry/android/FlurryAgent;
astore 1
aload 1
monitorenter
L0:
getstatic com/flurry/android/FlurryAgent/h Lcom/flurry/android/FlurryAgent;
getfield com/flurry/android/FlurryAgent/v Z
ifeq L3
ldc "FlurryAgent"
ldc "Cannot setCaptureUncaughtExceptions after onSessionStart"
invokestatic com/flurry/android/ai/b(Ljava/lang/String;Ljava/lang/String;)I
pop
aload 1
monitorexit
L1:
return
L3:
iload 0
putstatic com/flurry/android/FlurryAgent/m Z
aload 1
monitorexit
L4:
return
L2:
astore 2
L5:
aload 1
monitorexit
L6:
aload 2
athrow
.limit locals 3
.limit stack 2
.end method

.method public static setCatalogIntentName(Ljava/lang/String;)V
aload 0
putstatic com/flurry/android/FlurryAgent/a Ljava/lang/String;
return
.limit locals 1
.limit stack 1
.end method

.method public static setContinueSessionMillis(J)V
.catch all from L0 to L1 using L2
.catch all from L3 to L4 using L2
lload 0
ldc2_w 5000L
lcmp
ifge L5
ldc "FlurryAgent"
new java/lang/StringBuilder
dup
invokespecial java/lang/StringBuilder/<init>()V
ldc "Invalid time set for session resumption: "
invokevirtual java/lang/StringBuilder/append(Ljava/lang/String;)Ljava/lang/StringBuilder;
lload 0
invokevirtual java/lang/StringBuilder/append(J)Ljava/lang/StringBuilder;
invokevirtual java/lang/StringBuilder/toString()Ljava/lang/String;
invokestatic com/flurry/android/ai/b(Ljava/lang/String;Ljava/lang/String;)I
pop
return
L5:
getstatic com/flurry/android/FlurryAgent/h Lcom/flurry/android/FlurryAgent;
astore 2
aload 2
monitorenter
L0:
lload 0
putstatic com/flurry/android/FlurryAgent/i J
aload 2
monitorexit
L1:
return
L2:
astore 3
L3:
aload 2
monitorexit
L4:
aload 3
athrow
.limit locals 4
.limit stack 4
.end method

.method public static setDefaultNoAdsMessage(Ljava/lang/String;)V
getstatic com/flurry/android/FlurryAgent/o Z
ifne L0
return
L0:
aload 0
astore 1
aload 0
ifnonnull L1
ldc ""
astore 1
L1:
aload 1
putstatic com/flurry/android/v/b Ljava/lang/String;
return
.limit locals 2
.limit stack 1
.end method

.method public static setGender(B)V
iload 0
tableswitch 0
L0
L0
default : L1
L1:
getstatic com/flurry/android/FlurryAgent/h Lcom/flurry/android/FlurryAgent;
iconst_m1
putfield com/flurry/android/FlurryAgent/R B
return
L0:
getstatic com/flurry/android/FlurryAgent/h Lcom/flurry/android/FlurryAgent;
iload 0
putfield com/flurry/android/FlurryAgent/R B
return
.limit locals 1
.limit stack 2
.end method

.method public static setGetAppUrl(Ljava/lang/String;)V
aload 0
putstatic com/flurry/android/FlurryAgent/f Ljava/lang/String;
return
.limit locals 1
.limit stack 1
.end method

.method public static setLocationCriteria(Landroid/location/Criteria;)V
.catch all from L0 to L1 using L2
.catch all from L3 to L4 using L2
getstatic com/flurry/android/FlurryAgent/h Lcom/flurry/android/FlurryAgent;
astore 1
aload 1
monitorenter
L0:
aload 0
putstatic com/flurry/android/FlurryAgent/n Landroid/location/Criteria;
aload 1
monitorexit
L1:
return
L2:
astore 0
L3:
aload 1
monitorexit
L4:
aload 0
athrow
.limit locals 2
.limit stack 1
.end method

.method public static setLogEnabled(Z)V
.catch all from L0 to L1 using L2
.catch all from L1 to L3 using L2
.catch all from L4 to L5 using L2
.catch all from L6 to L7 using L2
getstatic com/flurry/android/FlurryAgent/h Lcom/flurry/android/FlurryAgent;
astore 1
aload 1
monitorenter
iload 0
ifeq L4
L0:
invokestatic com/flurry/android/ai/b()V
L1:
aload 1
monitorexit
L3:
return
L4:
invokestatic com/flurry/android/ai/a()V
L5:
goto L1
L2:
astore 2
L6:
aload 1
monitorexit
L7:
aload 2
athrow
.limit locals 3
.limit stack 1
.end method

.method public static setLogEvents(Z)V
.catch all from L0 to L1 using L2
.catch all from L3 to L4 using L2
getstatic com/flurry/android/FlurryAgent/h Lcom/flurry/android/FlurryAgent;
astore 1
aload 1
monitorenter
L0:
iload 0
putstatic com/flurry/android/FlurryAgent/j Z
aload 1
monitorexit
L1:
return
L2:
astore 2
L3:
aload 1
monitorexit
L4:
aload 2
athrow
.limit locals 3
.limit stack 1
.end method

.method public static setLogLevel(I)V
.catch all from L0 to L1 using L2
.catch all from L3 to L4 using L2
getstatic com/flurry/android/FlurryAgent/h Lcom/flurry/android/FlurryAgent;
astore 1
aload 1
monitorenter
L0:
iload 0
invokestatic com/flurry/android/ai/a(I)V
aload 1
monitorexit
L1:
return
L2:
astore 2
L3:
aload 1
monitorexit
L4:
aload 2
athrow
.limit locals 3
.limit stack 1
.end method

.method public static setReportLocation(Z)V
.catch all from L0 to L1 using L2
.catch all from L3 to L4 using L2
getstatic com/flurry/android/FlurryAgent/h Lcom/flurry/android/FlurryAgent;
astore 1
aload 1
monitorenter
L0:
getstatic com/flurry/android/FlurryAgent/h Lcom/flurry/android/FlurryAgent;
iload 0
putfield com/flurry/android/FlurryAgent/C Z
aload 1
monitorexit
L1:
return
L2:
astore 2
L3:
aload 1
monitorexit
L4:
aload 2
athrow
.limit locals 3
.limit stack 2
.end method

.method public static setReportUrl(Ljava/lang/String;)V
aload 0
putstatic com/flurry/android/FlurryAgent/c Ljava/lang/String;
return
.limit locals 1
.limit stack 1
.end method

.method public static setUseHttps(Z)V
iload 0
putstatic com/flurry/android/FlurryAgent/k Z
return
.limit locals 1
.limit stack 1
.end method

.method public static setUserId(Ljava/lang/String;)V
.catch all from L0 to L1 using L2
.catch all from L3 to L4 using L2
getstatic com/flurry/android/FlurryAgent/h Lcom/flurry/android/FlurryAgent;
astore 1
aload 1
monitorenter
L0:
getstatic com/flurry/android/FlurryAgent/h Lcom/flurry/android/FlurryAgent;
aload 0
sipush 255
invokestatic com/flurry/android/r/a(Ljava/lang/String;I)Ljava/lang/String;
putfield com/flurry/android/FlurryAgent/Q Ljava/lang/String;
aload 1
monitorexit
L1:
return
L2:
astore 0
L3:
aload 1
monitorexit
L4:
aload 0
athrow
.limit locals 2
.limit stack 3
.end method

.method public static setVersionName(Ljava/lang/String;)V
.catch all from L0 to L1 using L2
.catch all from L3 to L4 using L2
getstatic com/flurry/android/FlurryAgent/h Lcom/flurry/android/FlurryAgent;
astore 1
aload 1
monitorenter
L0:
getstatic com/flurry/android/FlurryAgent/h Lcom/flurry/android/FlurryAgent;
aload 0
putfield com/flurry/android/FlurryAgent/B Ljava/lang/String;
aload 1
monitorexit
L1:
return
L2:
astore 0
L3:
aload 1
monitorexit
L4:
aload 0
athrow
.limit locals 2
.limit stack 2
.end method

.method final a(Ljava/lang/Throwable;)V
aload 1
invokevirtual java/lang/Throwable/printStackTrace()V
ldc ""
astore 2
aload 1
invokevirtual java/lang/Throwable/getStackTrace()[Ljava/lang/StackTraceElement;
astore 3
aload 3
ifnull L0
aload 3
arraylength
ifle L0
aload 3
iconst_0
aaload
astore 2
new java/lang/StringBuilder
dup
invokespecial java/lang/StringBuilder/<init>()V
astore 3
aload 3
aload 2
invokevirtual java/lang/StackTraceElement/getClassName()Ljava/lang/String;
invokevirtual java/lang/StringBuilder/append(Ljava/lang/String;)Ljava/lang/StringBuilder;
ldc "."
invokevirtual java/lang/StringBuilder/append(Ljava/lang/String;)Ljava/lang/StringBuilder;
aload 2
invokevirtual java/lang/StackTraceElement/getMethodName()Ljava/lang/String;
invokevirtual java/lang/StringBuilder/append(Ljava/lang/String;)Ljava/lang/StringBuilder;
ldc ":"
invokevirtual java/lang/StringBuilder/append(Ljava/lang/String;)Ljava/lang/StringBuilder;
aload 2
invokevirtual java/lang/StackTraceElement/getLineNumber()I
invokevirtual java/lang/StringBuilder/append(I)Ljava/lang/StringBuilder;
pop
aload 1
invokevirtual java/lang/Throwable/getMessage()Ljava/lang/String;
ifnull L1
aload 3
new java/lang/StringBuilder
dup
invokespecial java/lang/StringBuilder/<init>()V
ldc " ("
invokevirtual java/lang/StringBuilder/append(Ljava/lang/String;)Ljava/lang/StringBuilder;
aload 1
invokevirtual java/lang/Throwable/getMessage()Ljava/lang/String;
invokevirtual java/lang/StringBuilder/append(Ljava/lang/String;)Ljava/lang/StringBuilder;
ldc ")"
invokevirtual java/lang/StringBuilder/append(Ljava/lang/String;)Ljava/lang/StringBuilder;
invokevirtual java/lang/StringBuilder/toString()Ljava/lang/String;
invokevirtual java/lang/StringBuilder/append(Ljava/lang/String;)Ljava/lang/StringBuilder;
pop
L1:
aload 3
invokevirtual java/lang/StringBuilder/toString()Ljava/lang/String;
astore 2
L2:
ldc "uncaught"
aload 2
aload 1
invokevirtual java/lang/Object/getClass()Ljava/lang/Class;
invokevirtual java/lang/Class/toString()Ljava/lang/String;
invokestatic com/flurry/android/FlurryAgent/onError(Ljava/lang/String;Ljava/lang/String;Ljava/lang/String;)V
aload 0
getfield com/flurry/android/FlurryAgent/y Ljava/util/Map;
invokeinterface java/util/Map/clear()V 0
aload 0
aconst_null
iconst_1
invokespecial com/flurry/android/FlurryAgent/a(Landroid/content/Context;Z)V
return
L0:
aload 1
invokevirtual java/lang/Throwable/getMessage()Ljava/lang/String;
ifnull L2
aload 1
invokevirtual java/lang/Throwable/getMessage()Ljava/lang/String;
astore 2
goto L2
.limit locals 4
.limit stack 3
.end method

.method public final onLocationChanged(Landroid/location/Location;)V
.catch java/lang/Throwable from L0 to L1 using L2
.catch all from L0 to L1 using L3
.catch all from L4 to L5 using L3
aload 0
monitorenter
L0:
aload 0
aload 1
putfield com/flurry/android/FlurryAgent/U Landroid/location/Location;
aload 0
invokespecial com/flurry/android/FlurryAgent/o()V
L1:
aload 0
monitorexit
return
L2:
astore 1
L4:
ldc "FlurryAgent"
ldc ""
aload 1
invokestatic com/flurry/android/ai/b(Ljava/lang/String;Ljava/lang/String;Ljava/lang/Throwable;)I
pop
L5:
goto L1
L3:
astore 1
aload 0
monitorexit
aload 1
athrow
.limit locals 2
.limit stack 3
.end method

.method public final onProviderDisabled(Ljava/lang/String;)V
return
.limit locals 2
.limit stack 0
.end method

.method public final onProviderEnabled(Ljava/lang/String;)V
return
.limit locals 2
.limit stack 0
.end method

.method public final onStatusChanged(Ljava/lang/String;ILandroid/os/Bundle;)V
return
.limit locals 4
.limit stack 0
.end method
