.bytecode 50.0
.class final synchronized com/flurry/android/t
.super java/lang/Object
.implements java/lang/Runnable

.field private synthetic 'a' Ljava/util/Map;

.field private synthetic 'b' Lcom/flurry/android/InstallReceiver;

.method <init>(Lcom/flurry/android/InstallReceiver;Ljava/util/Map;)V
aload 0
aload 1
putfield com/flurry/android/t/b Lcom/flurry/android/InstallReceiver;
aload 0
aload 2
putfield com/flurry/android/t/a Ljava/util/Map;
aload 0
invokespecial java/lang/Object/<init>()V
return
.limit locals 3
.limit stack 2
.end method

.method public final run()V
.catch java/lang/Throwable from L0 to L1 using L2
.catch all from L0 to L1 using L3
.catch java/lang/Throwable from L4 to L5 using L2
.catch all from L4 to L5 using L3
.catch java/lang/Throwable from L6 to L7 using L2
.catch all from L6 to L7 using L3
.catch java/lang/Throwable from L8 to L9 using L2
.catch all from L8 to L9 using L3
.catch java/lang/Throwable from L10 to L11 using L2
.catch all from L10 to L11 using L3
.catch java/lang/Throwable from L11 to L12 using L13
.catch all from L11 to L12 using L14
.catch java/lang/Throwable from L15 to L16 using L13
.catch all from L15 to L16 using L14
.catch java/lang/Throwable from L17 to L18 using L13
.catch all from L17 to L18 using L14
.catch all from L19 to L20 using L3
.catch java/lang/Throwable from L21 to L22 using L13
.catch all from L21 to L22 using L14
.catch java/lang/Throwable from L23 to L24 using L13
.catch all from L23 to L24 using L14
aconst_null
astore 3
aconst_null
astore 5
aload 3
astore 2
L0:
aload 0
getfield com/flurry/android/t/b Lcom/flurry/android/InstallReceiver;
invokestatic com/flurry/android/InstallReceiver/a(Lcom/flurry/android/InstallReceiver;)Ljava/io/File;
invokevirtual java/io/File/getParentFile()Ljava/io/File;
astore 4
L1:
aload 3
astore 2
L4:
aload 4
invokevirtual java/io/File/mkdirs()Z
ifne L25
L5:
aload 3
astore 2
L6:
aload 4
invokevirtual java/io/File/exists()Z
ifne L25
L7:
aload 3
astore 2
L8:
ldc "InstallReceiver"
new java/lang/StringBuilder
dup
invokespecial java/lang/StringBuilder/<init>()V
ldc "Unable to create persistent dir: "
invokevirtual java/lang/StringBuilder/append(Ljava/lang/String;)Ljava/lang/StringBuilder;
aload 4
invokevirtual java/lang/StringBuilder/append(Ljava/lang/Object;)Ljava/lang/StringBuilder;
invokevirtual java/lang/StringBuilder/toString()Ljava/lang/String;
invokestatic com/flurry/android/ai/b(Ljava/lang/String;Ljava/lang/String;)I
pop
L9:
aconst_null
invokestatic com/flurry/android/r/a(Ljava/io/Closeable;)V
return
L25:
aload 3
astore 2
L10:
new java/io/DataOutputStream
dup
new java/io/FileOutputStream
dup
aload 0
getfield com/flurry/android/t/b Lcom/flurry/android/InstallReceiver;
invokestatic com/flurry/android/InstallReceiver/a(Lcom/flurry/android/InstallReceiver;)Ljava/io/File;
invokespecial java/io/FileOutputStream/<init>(Ljava/io/File;)V
invokespecial java/io/DataOutputStream/<init>(Ljava/io/OutputStream;)V
astore 3
L11:
aload 0
getfield com/flurry/android/t/a Ljava/util/Map;
invokeinterface java/util/Map/entrySet()Ljava/util/Set; 0
invokeinterface java/util/Set/iterator()Ljava/util/Iterator; 0
astore 2
L12:
iconst_1
istore 1
L15:
aload 2
invokeinterface java/util/Iterator/hasNext()Z 0
ifeq L23
aload 2
invokeinterface java/util/Iterator/next()Ljava/lang/Object; 0
checkcast java/util/Map$Entry
astore 4
L16:
iload 1
iconst_1
if_icmpne L21
iconst_0
istore 1
L17:
aload 3
aload 4
invokeinterface java/util/Map$Entry/getKey()Ljava/lang/Object; 0
checkcast java/lang/String
invokevirtual java/io/DataOutputStream/writeUTF(Ljava/lang/String;)V
aload 3
ldc "="
invokevirtual java/io/DataOutputStream/writeUTF(Ljava/lang/String;)V
aload 3
aload 4
invokeinterface java/util/Map$Entry/getValue()Ljava/lang/Object; 0
checkcast java/lang/String
invokevirtual java/io/DataOutputStream/writeUTF(Ljava/lang/String;)V
L18:
goto L15
L13:
astore 4
L26:
aload 3
astore 2
L19:
ldc "InstallReceiver"
ldc ""
aload 4
invokestatic com/flurry/android/ai/b(Ljava/lang/String;Ljava/lang/String;Ljava/lang/Throwable;)I
pop
L20:
aload 3
invokestatic com/flurry/android/r/a(Ljava/io/Closeable;)V
return
L21:
aload 3
ldc "&"
invokevirtual java/io/DataOutputStream/writeUTF(Ljava/lang/String;)V
L22:
goto L17
L14:
astore 4
aload 3
astore 2
aload 4
astore 3
L27:
aload 2
invokestatic com/flurry/android/r/a(Ljava/io/Closeable;)V
aload 3
athrow
L23:
aload 3
iconst_0
invokevirtual java/io/DataOutputStream/writeShort(I)V
L24:
aload 3
invokestatic com/flurry/android/r/a(Ljava/io/Closeable;)V
return
L3:
astore 3
goto L27
L2:
astore 4
aload 5
astore 3
goto L26
.limit locals 6
.limit stack 5
.end method
