.bytecode 50.0
.class final synchronized com/flurry/android/v
.super java/lang/Object
.implements android/view/View$OnClickListener

.field private static volatile 'A' J

.field static 'a' Ljava/lang/String;

.field static 'b' Ljava/lang/String;

.field private static volatile 'c' Ljava/lang/String;

.field private static volatile 'd' Ljava/lang/String;

.field private static volatile 'e' Ljava/lang/String;

.field private static 'f' Ljava/lang/String;

.field private static 'g' I

.field private 'h' Ljava/lang/String;

.field private 'i' Ljava/lang/String;

.field private 'j' Ljava/lang/String;

.field private 'k' J

.field private 'l' J

.field private 'm' J

.field private 'n' J

.field private 'o' Lcom/flurry/android/aa;

.field private 'p' Z

.field private volatile 'q' Z

.field private 'r' Ljava/lang/String;

.field private 's' Ljava/util/Map;

.field private 't' Landroid/os/Handler;

.field private 'u' Z

.field private transient 'v' Ljava/util/Map;

.field private 'w' Lcom/flurry/android/ah;

.field private 'x' Ljava/util/List;

.field private 'y' Ljava/util/Map;

.field private 'z' Lcom/flurry/android/AppCircleCallback;

.method static <clinit>()V
ldc "market://"
putstatic com/flurry/android/v/c Ljava/lang/String;
ldc "market://details?id="
putstatic com/flurry/android/v/d Ljava/lang/String;
ldc "https://market.android.com/details?id="
putstatic com/flurry/android/v/e Ljava/lang/String;
ldc "com.flurry.android.ACTION_CATALOG"
putstatic com/flurry/android/v/f Ljava/lang/String;
ldc "FlurryAgent"
putstatic com/flurry/android/v/a Ljava/lang/String;
new java/util/Random
dup
invokestatic java/lang/System/currentTimeMillis()J
invokespecial java/util/Random/<init>(J)V
pop
sipush 5000
putstatic com/flurry/android/v/g I
ldc ""
putstatic com/flurry/android/v/b Ljava/lang/String;
lconst_0
putstatic com/flurry/android/v/A J
return
.limit locals 0
.limit stack 4
.end method

.method public <init>()V
aload 0
invokespecial java/lang/Object/<init>()V
aload 0
iconst_1
putfield com/flurry/android/v/p Z
aload 0
new java/util/HashMap
dup
invokespecial java/util/HashMap/<init>()V
putfield com/flurry/android/v/s Ljava/util/Map;
aload 0
new java/util/HashMap
dup
invokespecial java/util/HashMap/<init>()V
putfield com/flurry/android/v/v Ljava/util/Map;
aload 0
new java/util/ArrayList
dup
invokespecial java/util/ArrayList/<init>()V
putfield com/flurry/android/v/x Ljava/util/List;
aload 0
new java/util/HashMap
dup
invokespecial java/util/HashMap/<init>()V
putfield com/flurry/android/v/y Ljava/util/Map;
aload 0
new com/flurry/android/aa
dup
invokespecial com/flurry/android/aa/<init>()V
putfield com/flurry/android/v/o Lcom/flurry/android/aa;
return
.limit locals 1
.limit stack 3
.end method

.method static synthetic a(Lcom/flurry/android/v;)Lcom/flurry/android/AppCircleCallback;
aload 0
getfield com/flurry/android/v/z Lcom/flurry/android/AppCircleCallback;
areturn
.limit locals 1
.limit stack 1
.end method

.method private a(Ljava/lang/String;Lcom/flurry/android/w;)Lcom/flurry/android/Offer;
new com/flurry/android/p
dup
aload 1
iconst_3
aload 0
invokevirtual com/flurry/android/v/j()J
invokespecial com/flurry/android/p/<init>(Ljava/lang/String;BJ)V
astore 6
aload 0
aload 6
invokespecial com/flurry/android/v/c(Lcom/flurry/android/p;)V
aload 6
new com/flurry/android/f
dup
iconst_2
aload 0
invokevirtual com/flurry/android/v/j()J
invokespecial com/flurry/android/f/<init>(BJ)V
invokevirtual com/flurry/android/p/a(Lcom/flurry/android/f;)V
aload 6
aload 2
putfield com/flurry/android/p/c Lcom/flurry/android/w;
aload 0
getfield com/flurry/android/v/o Lcom/flurry/android/aa;
aload 2
getfield com/flurry/android/w/a J
invokevirtual com/flurry/android/aa/a(J)Lcom/flurry/android/am;
astore 7
aload 7
ifnonnull L0
ldc ""
astore 1
L1:
aload 7
ifnonnull L2
iconst_0
istore 3
L3:
getstatic com/flurry/android/v/A J
lconst_1
ladd
lstore 4
lload 4
putstatic com/flurry/android/v/A J
new com/flurry/android/u
dup
lload 4
aload 6
aload 2
getfield com/flurry/android/w/h Lcom/flurry/android/AdImage;
aload 2
getfield com/flurry/android/w/d Ljava/lang/String;
aload 1
iload 3
invokespecial com/flurry/android/u/<init>(JLcom/flurry/android/p;Lcom/flurry/android/AdImage;Ljava/lang/String;Ljava/lang/String;I)V
astore 1
aload 0
getfield com/flurry/android/v/y Ljava/util/Map;
aload 1
getfield com/flurry/android/u/a J
invokestatic java/lang/Long/valueOf(J)Ljava/lang/Long;
aload 1
invokeinterface java/util/Map/put(Ljava/lang/Object;Ljava/lang/Object;)Ljava/lang/Object; 2
pop
new com/flurry/android/Offer
dup
aload 1
getfield com/flurry/android/u/a J
aload 1
getfield com/flurry/android/u/f Lcom/flurry/android/AdImage;
aload 1
getfield com/flurry/android/u/c Ljava/lang/String;
aload 1
getfield com/flurry/android/u/d Ljava/lang/String;
aload 1
getfield com/flurry/android/u/e I
invokespecial com/flurry/android/Offer/<init>(JLcom/flurry/android/AdImage;Ljava/lang/String;Ljava/lang/String;I)V
areturn
L0:
aload 7
getfield com/flurry/android/am/a Ljava/lang/String;
astore 1
goto L1
L2:
aload 7
getfield com/flurry/android/am/c I
istore 3
goto L3
.limit locals 8
.limit stack 9
.end method

.method static synthetic a(Lcom/flurry/android/v;Ljava/lang/String;)Ljava/lang/String;
aload 0
aload 1
invokespecial com/flurry/android/v/d(Ljava/lang/String;)Ljava/lang/String;
areturn
.limit locals 2
.limit stack 2
.end method

.method private static a([B)Ljava/lang/String;
new java/lang/StringBuilder
dup
invokespecial java/lang/StringBuilder/<init>()V
astore 3
iconst_0
istore 1
L0:
iload 1
aload 0
arraylength
if_icmpge L1
aload 0
iload 1
baload
iconst_4
ishr
bipush 15
iand
istore 2
iload 2
bipush 10
if_icmpge L2
aload 3
iload 2
bipush 48
iadd
i2c
invokevirtual java/lang/StringBuilder/append(C)Ljava/lang/StringBuilder;
pop
L3:
aload 0
iload 1
baload
bipush 15
iand
istore 2
iload 2
bipush 10
if_icmpge L4
aload 3
iload 2
bipush 48
iadd
i2c
invokevirtual java/lang/StringBuilder/append(C)Ljava/lang/StringBuilder;
pop
L5:
iload 1
iconst_1
iadd
istore 1
goto L0
L2:
aload 3
iload 2
bipush 65
iadd
bipush 10
isub
i2c
invokevirtual java/lang/StringBuilder/append(C)Ljava/lang/StringBuilder;
pop
goto L3
L4:
aload 3
iload 2
bipush 65
iadd
bipush 10
isub
i2c
invokevirtual java/lang/StringBuilder/append(C)Ljava/lang/StringBuilder;
pop
goto L5
L1:
aload 3
invokevirtual java/lang/StringBuilder/toString()Ljava/lang/String;
areturn
.limit locals 4
.limit stack 3
.end method

.method private a(Ljava/util/List;Ljava/lang/Long;)Ljava/util/List;
aload 1
ifnull L0
aload 1
invokeinterface java/util/List/isEmpty()Z 0
ifne L0
aload 0
getfield com/flurry/android/v/o Lcom/flurry/android/aa;
invokevirtual com/flurry/android/aa/b()Z
ifne L1
L0:
invokestatic java/util/Collections/emptyList()Ljava/util/List;
areturn
L1:
aload 0
getfield com/flurry/android/v/o Lcom/flurry/android/aa;
aload 1
iconst_0
invokeinterface java/util/List/get(I)Ljava/lang/Object; 1
checkcast java/lang/String
invokevirtual com/flurry/android/aa/a(Ljava/lang/String;)[Lcom/flurry/android/w;
astore 3
aload 3
ifnull L2
aload 3
arraylength
ifle L2
new java/util/ArrayList
dup
aload 3
invokestatic java/util/Arrays/asList([Ljava/lang/Object;)Ljava/util/List;
invokespecial java/util/ArrayList/<init>(Ljava/util/Collection;)V
astore 3
aload 3
invokestatic java/util/Collections/shuffle(Ljava/util/List;)V
aload 2
ifnull L3
aload 3
invokeinterface java/util/List/iterator()Ljava/util/Iterator; 0
astore 4
L4:
aload 4
invokeinterface java/util/Iterator/hasNext()Z 0
ifeq L3
aload 4
invokeinterface java/util/Iterator/next()Ljava/lang/Object; 0
checkcast com/flurry/android/w
getfield com/flurry/android/w/a J
aload 2
invokevirtual java/lang/Long/longValue()J
lcmp
ifne L4
aload 4
invokeinterface java/util/Iterator/remove()V 0
L3:
aload 3
iconst_0
aload 3
invokeinterface java/util/List/size()I 0
aload 1
invokeinterface java/util/List/size()I 0
invokestatic java/lang/Math/min(II)I
invokeinterface java/util/List/subList(II)Ljava/util/List; 2
areturn
L2:
invokestatic java/util/Collections/emptyList()Ljava/util/List;
areturn
.limit locals 5
.limit stack 4
.end method

.method static synthetic a(Lcom/flurry/android/v;Landroid/content/Context;Ljava/lang/String;)V
.catch java/lang/Exception from L0 to L1 using L2
aload 2
getstatic com/flurry/android/v/d Ljava/lang/String;
invokevirtual java/lang/String/startsWith(Ljava/lang/String;)Z
ifeq L3
aload 2
getstatic com/flurry/android/v/d Ljava/lang/String;
invokevirtual java/lang/String/length()I
invokevirtual java/lang/String/substring(I)Ljava/lang/String;
astore 3
aload 0
getfield com/flurry/android/v/p Z
ifeq L4
L0:
getstatic com/flurry/android/v/a Ljava/lang/String;
new java/lang/StringBuilder
dup
invokespecial java/lang/StringBuilder/<init>()V
ldc "Launching Android Market for app "
invokevirtual java/lang/StringBuilder/append(Ljava/lang/String;)Ljava/lang/StringBuilder;
aload 3
invokevirtual java/lang/StringBuilder/append(Ljava/lang/String;)Ljava/lang/StringBuilder;
invokevirtual java/lang/StringBuilder/toString()Ljava/lang/String;
invokestatic com/flurry/android/ai/a(Ljava/lang/String;Ljava/lang/String;)I
pop
aload 1
new android/content/Intent
dup
ldc "android.intent.action.VIEW"
invokespecial android/content/Intent/<init>(Ljava/lang/String;)V
aload 2
invokestatic android/net/Uri/parse(Ljava/lang/String;)Landroid/net/Uri;
invokevirtual android/content/Intent/setData(Landroid/net/Uri;)Landroid/content/Intent;
invokevirtual android/content/Context/startActivity(Landroid/content/Intent;)V
L1:
return
L2:
astore 0
getstatic com/flurry/android/v/a Ljava/lang/String;
new java/lang/StringBuilder
dup
invokespecial java/lang/StringBuilder/<init>()V
ldc "Cannot launch Marketplace url "
invokevirtual java/lang/StringBuilder/append(Ljava/lang/String;)Ljava/lang/StringBuilder;
aload 2
invokevirtual java/lang/StringBuilder/append(Ljava/lang/String;)Ljava/lang/StringBuilder;
invokevirtual java/lang/StringBuilder/toString()Ljava/lang/String;
aload 0
invokestatic com/flurry/android/ai/c(Ljava/lang/String;Ljava/lang/String;Ljava/lang/Throwable;)I
pop
return
L4:
getstatic com/flurry/android/v/a Ljava/lang/String;
new java/lang/StringBuilder
dup
invokespecial java/lang/StringBuilder/<init>()V
ldc "Launching Android Market website for app "
invokevirtual java/lang/StringBuilder/append(Ljava/lang/String;)Ljava/lang/StringBuilder;
aload 3
invokevirtual java/lang/StringBuilder/append(Ljava/lang/String;)Ljava/lang/StringBuilder;
invokevirtual java/lang/StringBuilder/toString()Ljava/lang/String;
invokestatic com/flurry/android/ai/a(Ljava/lang/String;Ljava/lang/String;)I
pop
new java/lang/StringBuilder
dup
invokespecial java/lang/StringBuilder/<init>()V
getstatic com/flurry/android/v/e Ljava/lang/String;
invokevirtual java/lang/StringBuilder/append(Ljava/lang/String;)Ljava/lang/StringBuilder;
aload 3
invokevirtual java/lang/StringBuilder/append(Ljava/lang/String;)Ljava/lang/StringBuilder;
invokevirtual java/lang/StringBuilder/toString()Ljava/lang/String;
astore 0
aload 1
new android/content/Intent
dup
ldc "android.intent.action.VIEW"
invokespecial android/content/Intent/<init>(Ljava/lang/String;)V
aload 0
invokestatic android/net/Uri/parse(Ljava/lang/String;)Landroid/net/Uri;
invokevirtual android/content/Intent/setData(Landroid/net/Uri;)Landroid/content/Intent;
invokevirtual android/content/Context/startActivity(Landroid/content/Intent;)V
return
L3:
getstatic com/flurry/android/v/a Ljava/lang/String;
new java/lang/StringBuilder
dup
invokespecial java/lang/StringBuilder/<init>()V
ldc "Unexpected android market url scheme: "
invokevirtual java/lang/StringBuilder/append(Ljava/lang/String;)Ljava/lang/StringBuilder;
aload 2
invokevirtual java/lang/StringBuilder/append(Ljava/lang/String;)Ljava/lang/StringBuilder;
invokevirtual java/lang/StringBuilder/toString()Ljava/lang/String;
invokestatic com/flurry/android/ai/d(Ljava/lang/String;Ljava/lang/String;)I
pop
return
.limit locals 4
.limit stack 4
.end method

.method private static a(Ljava/lang/Runnable;)V
new android/os/Handler
dup
invokespecial android/os/Handler/<init>()V
aload 0
invokevirtual android/os/Handler/post(Ljava/lang/Runnable;)Z
pop
return
.limit locals 1
.limit stack 2
.end method

.method private b(Landroid/content/Context;Lcom/flurry/android/p;Ljava/lang/String;)V
new android/content/Intent
dup
invokestatic com/flurry/android/v/o()Ljava/lang/String;
invokespecial android/content/Intent/<init>(Ljava/lang/String;)V
astore 4
aload 4
ldc "android.intent.category.DEFAULT"
invokevirtual android/content/Intent/addCategory(Ljava/lang/String;)Landroid/content/Intent;
pop
aload 4
ldc "u"
aload 3
invokevirtual android/content/Intent/putExtra(Ljava/lang/String;Ljava/lang/String;)Landroid/content/Intent;
pop
aload 2
ifnull L0
aload 4
ldc "o"
aload 2
invokevirtual com/flurry/android/p/a()J
invokevirtual android/content/Intent/putExtra(Ljava/lang/String;J)Landroid/content/Intent;
pop
L0:
aload 1
aload 4
invokevirtual android/content/Context/startActivity(Landroid/content/Intent;)V
return
.limit locals 5
.limit stack 4
.end method

.method static synthetic b(Lcom/flurry/android/v;Ljava/lang/String;)V
aload 0
aload 1
invokespecial com/flurry/android/v/e(Ljava/lang/String;)V
return
.limit locals 2
.limit stack 2
.end method

.method private c(Lcom/flurry/android/p;)V
aload 0
getfield com/flurry/android/v/x Ljava/util/List;
invokeinterface java/util/List/size()I 0
sipush 32767
if_icmpge L0
aload 0
getfield com/flurry/android/v/x Ljava/util/List;
aload 1
invokeinterface java/util/List/add(Ljava/lang/Object;)Z 1
pop
aload 0
getfield com/flurry/android/v/v Ljava/util/Map;
aload 1
invokevirtual com/flurry/android/p/a()J
invokestatic java/lang/Long/valueOf(J)Ljava/lang/Long;
aload 1
invokeinterface java/util/Map/put(Ljava/lang/Object;Ljava/lang/Object;)Ljava/lang/Object; 2
pop
L0:
return
.limit locals 2
.limit stack 3
.end method

.method private d(Ljava/lang/String;)Ljava/lang/String;
.catch java/net/UnknownHostException from L0 to L1 using L2
.catch java/lang/Exception from L0 to L1 using L3
.catch java/net/UnknownHostException from L4 to L5 using L2
.catch java/lang/Exception from L4 to L5 using L3
.catch java/net/UnknownHostException from L6 to L7 using L2
.catch java/lang/Exception from L6 to L7 using L3
.catch java/net/UnknownHostException from L8 to L9 using L2
.catch java/lang/Exception from L8 to L9 using L3
.catch java/net/UnknownHostException from L10 to L11 using L2
.catch java/lang/Exception from L10 to L11 using L3
.catch java/net/UnknownHostException from L12 to L13 using L2
.catch java/lang/Exception from L12 to L13 using L3
.catch java/net/UnknownHostException from L14 to L15 using L2
.catch java/lang/Exception from L14 to L15 using L3
.catch java/net/UnknownHostException from L16 to L17 using L2
.catch java/lang/Exception from L16 to L17 using L3
.catch java/net/UnknownHostException from L18 to L19 using L2
.catch java/lang/Exception from L18 to L19 using L3
aload 1
astore 4
aload 1
astore 3
L0:
aload 1
getstatic com/flurry/android/v/c Ljava/lang/String;
invokevirtual java/lang/String/startsWith(Ljava/lang/String;)Z
ifne L20
L1:
aload 1
astore 4
L4:
new org/apache/http/client/methods/HttpGet
dup
aload 1
invokespecial org/apache/http/client/methods/HttpGet/<init>(Ljava/lang/String;)V
astore 3
L5:
aload 1
astore 4
L6:
new org/apache/http/impl/client/DefaultHttpClient
dup
invokespecial org/apache/http/impl/client/DefaultHttpClient/<init>()V
aload 3
invokeinterface org/apache/http/client/HttpClient/execute(Lorg/apache/http/client/methods/HttpUriRequest;)Lorg/apache/http/HttpResponse; 1
astore 3
L7:
aload 1
astore 4
L8:
aload 3
invokeinterface org/apache/http/HttpResponse/getStatusLine()Lorg/apache/http/StatusLine; 0
invokeinterface org/apache/http/StatusLine/getStatusCode()I 0
istore 2
L9:
iload 2
sipush 200
if_icmpne L15
aload 1
astore 4
L10:
aload 3
invokeinterface org/apache/http/HttpResponse/getEntity()Lorg/apache/http/HttpEntity; 0
invokestatic org/apache/http/util/EntityUtils/toString(Lorg/apache/http/HttpEntity;)Ljava/lang/String;
astore 1
L11:
aload 1
astore 4
aload 1
astore 3
L12:
aload 1
getstatic com/flurry/android/v/c Ljava/lang/String;
invokevirtual java/lang/String/startsWith(Ljava/lang/String;)Z
ifne L20
L13:
aload 1
astore 4
L14:
aload 0
aload 1
invokespecial com/flurry/android/v/d(Ljava/lang/String;)Ljava/lang/String;
areturn
L15:
aload 1
astore 4
L16:
getstatic com/flurry/android/v/a Ljava/lang/String;
new java/lang/StringBuilder
dup
invokespecial java/lang/StringBuilder/<init>()V
ldc "Cannot process with responseCode "
invokevirtual java/lang/StringBuilder/append(Ljava/lang/String;)Ljava/lang/StringBuilder;
iload 2
invokevirtual java/lang/StringBuilder/append(I)Ljava/lang/StringBuilder;
invokevirtual java/lang/StringBuilder/toString()Ljava/lang/String;
invokestatic com/flurry/android/ai/c(Ljava/lang/String;Ljava/lang/String;)I
pop
L17:
aload 1
astore 4
L18:
aload 0
new java/lang/StringBuilder
dup
invokespecial java/lang/StringBuilder/<init>()V
ldc "Error when fetching application's android market ID, responseCode "
invokevirtual java/lang/StringBuilder/append(Ljava/lang/String;)Ljava/lang/StringBuilder;
iload 2
invokevirtual java/lang/StringBuilder/append(I)Ljava/lang/StringBuilder;
invokevirtual java/lang/StringBuilder/toString()Ljava/lang/String;
invokespecial com/flurry/android/v/e(Ljava/lang/String;)V
L19:
aload 1
areturn
L2:
astore 1
getstatic com/flurry/android/v/a Ljava/lang/String;
new java/lang/StringBuilder
dup
invokespecial java/lang/StringBuilder/<init>()V
ldc "Unknown host: "
invokevirtual java/lang/StringBuilder/append(Ljava/lang/String;)Ljava/lang/StringBuilder;
aload 1
invokevirtual java/net/UnknownHostException/getMessage()Ljava/lang/String;
invokevirtual java/lang/StringBuilder/append(Ljava/lang/String;)Ljava/lang/StringBuilder;
invokevirtual java/lang/StringBuilder/toString()Ljava/lang/String;
invokestatic com/flurry/android/ai/c(Ljava/lang/String;Ljava/lang/String;)I
pop
aload 0
getfield com/flurry/android/v/z Lcom/flurry/android/AppCircleCallback;
ifnull L21
aload 0
new java/lang/StringBuilder
dup
invokespecial java/lang/StringBuilder/<init>()V
ldc "Unknown host: "
invokevirtual java/lang/StringBuilder/append(Ljava/lang/String;)Ljava/lang/StringBuilder;
aload 1
invokevirtual java/net/UnknownHostException/getMessage()Ljava/lang/String;
invokevirtual java/lang/StringBuilder/append(Ljava/lang/String;)Ljava/lang/StringBuilder;
invokevirtual java/lang/StringBuilder/toString()Ljava/lang/String;
invokespecial com/flurry/android/v/e(Ljava/lang/String;)V
L21:
aconst_null
areturn
L3:
astore 1
getstatic com/flurry/android/v/a Ljava/lang/String;
new java/lang/StringBuilder
dup
invokespecial java/lang/StringBuilder/<init>()V
ldc "Failed on url: "
invokevirtual java/lang/StringBuilder/append(Ljava/lang/String;)Ljava/lang/StringBuilder;
aload 4
invokevirtual java/lang/StringBuilder/append(Ljava/lang/String;)Ljava/lang/StringBuilder;
invokevirtual java/lang/StringBuilder/toString()Ljava/lang/String;
aload 1
invokestatic com/flurry/android/ai/c(Ljava/lang/String;Ljava/lang/String;Ljava/lang/Throwable;)I
pop
aconst_null
astore 3
L20:
aload 3
areturn
.limit locals 5
.limit stack 3
.end method

.method private e(Ljava/lang/String;)V
new com/flurry/android/af
dup
aload 0
aload 1
invokespecial com/flurry/android/af/<init>(Lcom/flurry/android/v;Ljava/lang/String;)V
invokestatic com/flurry/android/v/a(Ljava/lang/Runnable;)V
return
.limit locals 2
.limit stack 4
.end method

.method private n()Lcom/flurry/android/AdImage;
.catch all from L0 to L1 using L2
.catch all from L3 to L4 using L2
aload 0
monitorenter
L0:
aload 0
invokespecial com/flurry/android/v/p()Z
istore 1
L1:
iload 1
ifne L3
aconst_null
astore 2
L5:
aload 0
monitorexit
aload 2
areturn
L3:
aload 0
getfield com/flurry/android/v/o Lcom/flurry/android/aa;
iconst_1
invokevirtual com/flurry/android/aa/a(S)Lcom/flurry/android/AdImage;
astore 2
L4:
goto L5
L2:
astore 2
aload 0
monitorexit
aload 2
athrow
.limit locals 3
.limit stack 2
.end method

.method private static o()Ljava/lang/String;
getstatic com/flurry/android/FlurryAgent/a Ljava/lang/String;
ifnull L0
getstatic com/flurry/android/FlurryAgent/a Ljava/lang/String;
areturn
L0:
getstatic com/flurry/android/v/f Ljava/lang/String;
areturn
.limit locals 0
.limit stack 1
.end method

.method private p()Z
aload 0
getfield com/flurry/android/v/q Z
ifne L0
getstatic com/flurry/android/v/a Ljava/lang/String;
ldc "AppCircle is not initialized"
invokestatic com/flurry/android/ai/d(Ljava/lang/String;Ljava/lang/String;)I
pop
L0:
aload 0
getfield com/flurry/android/v/r Ljava/lang/String;
ifnonnull L1
getstatic com/flurry/android/v/a Ljava/lang/String;
ldc "Cannot identify UDID."
invokestatic com/flurry/android/ai/d(Ljava/lang/String;Ljava/lang/String;)I
pop
L1:
aload 0
getfield com/flurry/android/v/q Z
ireturn
.limit locals 1
.limit stack 2
.end method

.method final a(Landroid/content/Context;Ljava/lang/String;I)Landroid/view/View;
.catch all from L0 to L1 using L2
.catch all from L3 to L4 using L2
aload 0
monitorenter
L0:
aload 0
invokespecial com/flurry/android/v/p()Z
istore 4
L1:
iload 4
ifne L3
aconst_null
astore 1
L5:
aload 0
monitorexit
aload 1
areturn
L3:
new com/flurry/android/o
dup
aload 0
aload 1
aload 2
iload 3
invokespecial com/flurry/android/o/<init>(Lcom/flurry/android/v;Landroid/content/Context;Ljava/lang/String;I)V
astore 1
aload 0
getfield com/flurry/android/v/w Lcom/flurry/android/ah;
aload 1
invokevirtual com/flurry/android/ah/a(Lcom/flurry/android/o;)V
L4:
goto L5
L2:
astore 1
aload 0
monitorexit
aload 1
athrow
.limit locals 5
.limit stack 6
.end method

.method final a(J)Lcom/flurry/android/AdImage;
.catch all from L0 to L1 using L2
.catch all from L3 to L4 using L2
aload 0
monitorenter
L0:
aload 0
invokespecial com/flurry/android/v/p()Z
istore 3
L1:
iload 3
ifne L3
aconst_null
astore 4
L5:
aload 0
monitorexit
aload 4
areturn
L3:
aload 0
getfield com/flurry/android/v/o Lcom/flurry/android/aa;
lload 1
invokevirtual com/flurry/android/aa/b(J)Lcom/flurry/android/AdImage;
astore 4
L4:
goto L5
L2:
astore 4
aload 0
monitorexit
aload 4
athrow
.limit locals 5
.limit stack 3
.end method

.method final a(Lcom/flurry/android/p;)Ljava/lang/String;
.catch all from L0 to L1 using L2
.catch all from L1 to L3 using L2
.catch all from L4 to L5 using L2
aload 0
monitorenter
L0:
aload 1
getfield com/flurry/android/p/c Lcom/flurry/android/w;
astore 2
new java/lang/StringBuilder
dup
invokespecial java/lang/StringBuilder/<init>()V
ldc "?apik="
invokevirtual java/lang/StringBuilder/append(Ljava/lang/String;)Ljava/lang/StringBuilder;
aload 0
getfield com/flurry/android/v/j Ljava/lang/String;
invokevirtual java/lang/StringBuilder/append(Ljava/lang/String;)Ljava/lang/StringBuilder;
ldc "&cid="
invokevirtual java/lang/StringBuilder/append(Ljava/lang/String;)Ljava/lang/StringBuilder;
aload 2
getfield com/flurry/android/w/e J
invokevirtual java/lang/StringBuilder/append(J)Ljava/lang/StringBuilder;
ldc "&adid="
invokevirtual java/lang/StringBuilder/append(Ljava/lang/String;)Ljava/lang/StringBuilder;
aload 2
getfield com/flurry/android/w/a J
invokevirtual java/lang/StringBuilder/append(J)Ljava/lang/StringBuilder;
ldc "&pid="
invokevirtual java/lang/StringBuilder/append(Ljava/lang/String;)Ljava/lang/StringBuilder;
aload 0
getfield com/flurry/android/v/r Ljava/lang/String;
invokevirtual java/lang/StringBuilder/append(Ljava/lang/String;)Ljava/lang/StringBuilder;
ldc "&iid="
invokevirtual java/lang/StringBuilder/append(Ljava/lang/String;)Ljava/lang/StringBuilder;
aload 0
getfield com/flurry/android/v/k J
invokevirtual java/lang/StringBuilder/append(J)Ljava/lang/StringBuilder;
ldc "&sid="
invokevirtual java/lang/StringBuilder/append(Ljava/lang/String;)Ljava/lang/StringBuilder;
aload 0
getfield com/flurry/android/v/l J
invokevirtual java/lang/StringBuilder/append(J)Ljava/lang/StringBuilder;
ldc "&lid="
invokevirtual java/lang/StringBuilder/append(Ljava/lang/String;)Ljava/lang/StringBuilder;
aload 1
getfield com/flurry/android/p/b I
invokevirtual java/lang/StringBuilder/append(I)Ljava/lang/StringBuilder;
ldc "&aso="
invokevirtual java/lang/StringBuilder/append(Ljava/lang/String;)Ljava/lang/StringBuilder;
aload 1
getfield com/flurry/android/p/e Ljava/util/List;
aload 1
getfield com/flurry/android/p/e Ljava/util/List;
invokeinterface java/util/List/size()I 0
iconst_1
isub
invokeinterface java/util/List/get(I)Ljava/lang/Object; 1
checkcast com/flurry/android/f
getfield com/flurry/android/f/b J
invokevirtual java/lang/StringBuilder/append(J)Ljava/lang/StringBuilder;
ldc "&hid="
invokevirtual java/lang/StringBuilder/append(Ljava/lang/String;)Ljava/lang/StringBuilder;
aload 1
getfield com/flurry/android/p/a Ljava/lang/String;
invokestatic com/flurry/android/r/a(Ljava/lang/String;)Ljava/lang/String;
invokevirtual java/lang/StringBuilder/append(Ljava/lang/String;)Ljava/lang/StringBuilder;
ldc "&ac="
invokevirtual java/lang/StringBuilder/append(Ljava/lang/String;)Ljava/lang/StringBuilder;
aload 2
getfield com/flurry/android/w/g [B
invokestatic com/flurry/android/v/a([B)Ljava/lang/String;
invokevirtual java/lang/StringBuilder/append(Ljava/lang/String;)Ljava/lang/StringBuilder;
astore 1
aload 0
getfield com/flurry/android/v/s Ljava/util/Map;
ifnull L4
aload 0
getfield com/flurry/android/v/s Ljava/util/Map;
invokeinterface java/util/Map/isEmpty()Z 0
ifne L4
aload 0
getfield com/flurry/android/v/s Ljava/util/Map;
invokeinterface java/util/Map/entrySet()Ljava/util/Set; 0
invokeinterface java/util/Set/iterator()Ljava/util/Iterator; 0
astore 2
L1:
aload 2
invokeinterface java/util/Iterator/hasNext()Z 0
ifeq L4
aload 2
invokeinterface java/util/Iterator/next()Ljava/lang/Object; 0
checkcast java/util/Map$Entry
astore 4
new java/lang/StringBuilder
dup
invokespecial java/lang/StringBuilder/<init>()V
ldc "c_"
invokevirtual java/lang/StringBuilder/append(Ljava/lang/String;)Ljava/lang/StringBuilder;
aload 4
invokeinterface java/util/Map$Entry/getKey()Ljava/lang/Object; 0
checkcast java/lang/String
invokestatic com/flurry/android/r/a(Ljava/lang/String;)Ljava/lang/String;
invokevirtual java/lang/StringBuilder/append(Ljava/lang/String;)Ljava/lang/StringBuilder;
invokevirtual java/lang/StringBuilder/toString()Ljava/lang/String;
astore 3
aload 4
invokeinterface java/util/Map$Entry/getValue()Ljava/lang/Object; 0
checkcast java/lang/String
invokestatic com/flurry/android/r/a(Ljava/lang/String;)Ljava/lang/String;
astore 4
aload 1
ldc "&"
invokevirtual java/lang/StringBuilder/append(Ljava/lang/String;)Ljava/lang/StringBuilder;
aload 3
invokevirtual java/lang/StringBuilder/append(Ljava/lang/String;)Ljava/lang/StringBuilder;
ldc "="
invokevirtual java/lang/StringBuilder/append(Ljava/lang/String;)Ljava/lang/StringBuilder;
aload 4
invokevirtual java/lang/StringBuilder/append(Ljava/lang/String;)Ljava/lang/StringBuilder;
pop
L3:
goto L1
L2:
astore 1
aload 0
monitorexit
aload 1
athrow
L4:
aload 1
ldc "&ats="
invokevirtual java/lang/StringBuilder/append(Ljava/lang/String;)Ljava/lang/StringBuilder;
invokestatic java/lang/System/currentTimeMillis()J
invokevirtual java/lang/StringBuilder/append(J)Ljava/lang/StringBuilder;
pop
aload 1
invokevirtual java/lang/StringBuilder/toString()Ljava/lang/String;
astore 1
L5:
aload 0
monitorexit
aload 1
areturn
.limit locals 5
.limit stack 4
.end method

.method final a(Landroid/content/Context;Ljava/util/List;Ljava/lang/Long;IZ)Ljava/util/List;
.catch all from L0 to L1 using L2
.catch all from L3 to L4 using L2
.catch all from L5 to L6 using L2
.catch all from L7 to L8 using L2
.catch all from L9 to L10 using L2
.catch all from L11 to L12 using L2
.catch all from L13 to L14 using L2
aload 0
monitorenter
L0:
aload 0
invokespecial com/flurry/android/v/p()Z
ifne L3
invokestatic java/util/Collections/emptyList()Ljava/util/List;
astore 1
L1:
aload 0
monitorexit
aload 1
areturn
L3:
aload 0
getfield com/flurry/android/v/o Lcom/flurry/android/aa;
invokevirtual com/flurry/android/aa/b()Z
ifeq L13
L4:
aload 2
ifnull L13
L5:
aload 0
aload 2
aload 3
invokespecial com/flurry/android/v/a(Ljava/util/List;Ljava/lang/Long;)Ljava/util/List;
astore 8
aload 2
invokeinterface java/util/List/size()I 0
aload 8
invokeinterface java/util/List/size()I 0
invokestatic java/lang/Math/min(II)I
istore 7
new java/util/ArrayList
dup
invokespecial java/util/ArrayList/<init>()V
astore 3
L6:
iconst_0
istore 6
L15:
iload 6
iload 7
if_icmpge L16
L7:
aload 2
iload 6
invokeinterface java/util/List/get(I)Ljava/lang/Object; 1
checkcast java/lang/String
astore 10
aload 0
getfield com/flurry/android/v/o Lcom/flurry/android/aa;
aload 10
invokevirtual com/flurry/android/aa/b(Ljava/lang/String;)Lcom/flurry/android/e;
astore 9
L8:
aload 9
ifnull L11
L9:
new com/flurry/android/p
dup
aload 2
iload 6
invokeinterface java/util/List/get(I)Ljava/lang/Object; 1
checkcast java/lang/String
iconst_1
aload 0
invokevirtual com/flurry/android/v/j()J
invokespecial com/flurry/android/p/<init>(Ljava/lang/String;BJ)V
astore 10
aload 0
aload 10
invokespecial com/flurry/android/v/c(Lcom/flurry/android/p;)V
iload 6
aload 8
invokeinterface java/util/List/size()I 0
if_icmpge L17
aload 10
aload 8
iload 6
invokeinterface java/util/List/get(I)Ljava/lang/Object; 1
checkcast com/flurry/android/w
putfield com/flurry/android/p/c Lcom/flurry/android/w;
aload 10
new com/flurry/android/f
dup
iconst_2
aload 0
invokevirtual com/flurry/android/v/j()J
invokespecial com/flurry/android/f/<init>(BJ)V
invokevirtual com/flurry/android/p/a(Lcom/flurry/android/f;)V
aload 3
new com/flurry/android/z
dup
aload 1
aload 0
aload 10
aload 9
iload 4
iload 5
invokespecial com/flurry/android/z/<init>(Landroid/content/Context;Lcom/flurry/android/v;Lcom/flurry/android/p;Lcom/flurry/android/e;IZ)V
invokeinterface java/util/List/add(Ljava/lang/Object;)Z 1
pop
L10:
goto L17
L11:
getstatic com/flurry/android/v/a Ljava/lang/String;
new java/lang/StringBuilder
dup
invokespecial java/lang/StringBuilder/<init>()V
ldc "Cannot find hook: "
invokevirtual java/lang/StringBuilder/append(Ljava/lang/String;)Ljava/lang/StringBuilder;
aload 10
invokevirtual java/lang/StringBuilder/append(Ljava/lang/String;)Ljava/lang/StringBuilder;
invokevirtual java/lang/StringBuilder/toString()Ljava/lang/String;
invokestatic com/flurry/android/ai/d(Ljava/lang/String;Ljava/lang/String;)I
pop
L12:
goto L17
L2:
astore 1
aload 0
monitorexit
aload 1
athrow
L16:
aload 3
astore 1
goto L1
L13:
invokestatic java/util/Collections/emptyList()Ljava/util/List;
astore 1
L14:
goto L1
L17:
iload 6
iconst_1
iadd
istore 6
goto L15
.limit locals 11
.limit stack 9
.end method

.method final a(I)V
.catch all from L0 to L1 using L2
aload 0
monitorenter
L0:
aload 0
getfield com/flurry/android/v/z Lcom/flurry/android/AppCircleCallback;
ifnull L1
new com/flurry/android/ae
dup
aload 0
iload 1
invokespecial com/flurry/android/ae/<init>(Lcom/flurry/android/v;I)V
invokestatic com/flurry/android/v/a(Ljava/lang/Runnable;)V
L1:
aload 0
monitorexit
return
L2:
astore 2
aload 0
monitorexit
aload 2
athrow
.limit locals 3
.limit stack 4
.end method

.method final a(JJ)V
.catch all from L0 to L1 using L2
aload 0
monitorenter
L0:
aload 0
lload 1
putfield com/flurry/android/v/l J
aload 0
lload 3
putfield com/flurry/android/v/m J
aload 0
lconst_0
putfield com/flurry/android/v/n J
aload 0
getfield com/flurry/android/v/x Ljava/util/List;
invokeinterface java/util/List/clear()V 0
L1:
aload 0
monitorexit
return
L2:
astore 5
aload 0
monitorexit
aload 5
athrow
.limit locals 6
.limit stack 3
.end method

.method final a(Landroid/content/Context;J)V
.catch all from L0 to L1 using L2
.catch all from L3 to L4 using L2
.catch all from L5 to L6 using L2
.catch all from L7 to L8 using L2
aload 0
monitorenter
L0:
aload 0
invokespecial com/flurry/android/v/p()Z
istore 4
L1:
iload 4
ifne L3
L9:
aload 0
monitorexit
return
L3:
aload 0
getfield com/flurry/android/v/y Ljava/util/Map;
lload 2
invokestatic java/lang/Long/valueOf(J)Ljava/lang/Long;
invokeinterface java/util/Map/get(Ljava/lang/Object;)Ljava/lang/Object; 1
checkcast com/flurry/android/u
astore 5
L4:
aload 5
ifnonnull L7
L5:
getstatic com/flurry/android/v/a Ljava/lang/String;
new java/lang/StringBuilder
dup
invokespecial java/lang/StringBuilder/<init>()V
ldc "Cannot find offer "
invokevirtual java/lang/StringBuilder/append(Ljava/lang/String;)Ljava/lang/StringBuilder;
lload 2
invokevirtual java/lang/StringBuilder/append(J)Ljava/lang/StringBuilder;
invokevirtual java/lang/StringBuilder/toString()Ljava/lang/String;
invokestatic com/flurry/android/ai/b(Ljava/lang/String;Ljava/lang/String;)I
pop
L6:
goto L9
L2:
astore 1
aload 0
monitorexit
aload 1
athrow
L7:
aload 0
aload 5
getfield com/flurry/android/u/b Lcom/flurry/android/p;
invokevirtual com/flurry/android/v/b(Lcom/flurry/android/p;)Lcom/flurry/android/p;
astore 6
aload 5
aload 6
putfield com/flurry/android/u/b Lcom/flurry/android/p;
new java/lang/StringBuilder
dup
invokespecial java/lang/StringBuilder/<init>()V
invokestatic com/flurry/android/FlurryAgent/c()Ljava/lang/String;
invokevirtual java/lang/StringBuilder/append(Ljava/lang/String;)Ljava/lang/StringBuilder;
aload 0
aload 6
invokevirtual com/flurry/android/v/a(Lcom/flurry/android/p;)Ljava/lang/String;
invokevirtual java/lang/StringBuilder/append(Ljava/lang/String;)Ljava/lang/StringBuilder;
invokevirtual java/lang/StringBuilder/toString()Ljava/lang/String;
astore 7
getstatic com/flurry/android/v/a Ljava/lang/String;
new java/lang/StringBuilder
dup
invokespecial java/lang/StringBuilder/<init>()V
ldc "Offer "
invokevirtual java/lang/StringBuilder/append(Ljava/lang/String;)Ljava/lang/StringBuilder;
aload 5
getfield com/flurry/android/u/a J
invokevirtual java/lang/StringBuilder/append(J)Ljava/lang/StringBuilder;
ldc " accepted. Sent with cookies: "
invokevirtual java/lang/StringBuilder/append(Ljava/lang/String;)Ljava/lang/StringBuilder;
aload 0
getfield com/flurry/android/v/s Ljava/util/Map;
invokevirtual java/lang/StringBuilder/append(Ljava/lang/Object;)Ljava/lang/StringBuilder;
invokevirtual java/lang/StringBuilder/toString()Ljava/lang/String;
invokestatic com/flurry/android/ai/a(Ljava/lang/String;Ljava/lang/String;)I
pop
aload 0
aload 1
aload 6
aload 7
invokevirtual com/flurry/android/v/a(Landroid/content/Context;Lcom/flurry/android/p;Ljava/lang/String;)V
L8:
goto L9
.limit locals 8
.limit stack 4
.end method

.method final a(Landroid/content/Context;Lcom/flurry/android/a;)V
.catch all from L0 to L1 using L2
.catch all from L1 to L3 using L2
iconst_1
istore 3
aload 0
monitorenter
L0:
aload 0
getfield com/flurry/android/v/q Z
ifne L3
aload 0
aload 2
getfield com/flurry/android/a/c Ljava/lang/String;
putfield com/flurry/android/v/h Ljava/lang/String;
aload 0
aload 2
getfield com/flurry/android/a/d Ljava/lang/String;
putfield com/flurry/android/v/i Ljava/lang/String;
aload 0
aload 2
getfield com/flurry/android/a/a Ljava/lang/String;
putfield com/flurry/android/v/j Ljava/lang/String;
aload 0
aload 2
getfield com/flurry/android/a/b J
putfield com/flurry/android/v/k J
aload 0
aload 2
getfield com/flurry/android/a/e Landroid/os/Handler;
putfield com/flurry/android/v/t Landroid/os/Handler;
aload 0
new com/flurry/android/ah
dup
aload 0
getfield com/flurry/android/v/t Landroid/os/Handler;
getstatic com/flurry/android/v/g I
invokespecial com/flurry/android/ah/<init>(Landroid/os/Handler;I)V
putfield com/flurry/android/v/w Lcom/flurry/android/ah;
aload 1
invokevirtual android/content/Context/getResources()Landroid/content/res/Resources;
invokevirtual android/content/res/Resources/getDisplayMetrics()Landroid/util/DisplayMetrics;
pop
aload 0
getfield com/flurry/android/v/y Ljava/util/Map;
invokeinterface java/util/Map/clear()V 0
aload 0
getfield com/flurry/android/v/v Ljava/util/Map;
invokeinterface java/util/Map/clear()V 0
aload 0
getfield com/flurry/android/v/o Lcom/flurry/android/aa;
aload 1
aload 0
aload 2
invokevirtual com/flurry/android/aa/a(Landroid/content/Context;Lcom/flurry/android/v;Lcom/flurry/android/a;)V
aload 0
getfield com/flurry/android/v/s Ljava/util/Map;
invokeinterface java/util/Map/clear()V 0
aload 1
invokevirtual android/content/Context/getPackageManager()Landroid/content/pm/PackageManager;
astore 2
aload 1
invokevirtual android/content/Context/getPackageName()Ljava/lang/String;
astore 1
new java/lang/StringBuilder
dup
invokespecial java/lang/StringBuilder/<init>()V
getstatic com/flurry/android/v/d Ljava/lang/String;
invokevirtual java/lang/StringBuilder/append(Ljava/lang/String;)Ljava/lang/StringBuilder;
aload 1
invokevirtual java/lang/StringBuilder/append(Ljava/lang/String;)Ljava/lang/StringBuilder;
invokevirtual java/lang/StringBuilder/toString()Ljava/lang/String;
astore 1
new android/content/Intent
dup
ldc "android.intent.action.VIEW"
invokespecial android/content/Intent/<init>(Ljava/lang/String;)V
astore 4
aload 4
aload 1
invokestatic android/net/Uri/parse(Ljava/lang/String;)Landroid/net/Uri;
invokevirtual android/content/Intent/setData(Landroid/net/Uri;)Landroid/content/Intent;
pop
aload 2
aload 4
ldc_w 65536
invokevirtual android/content/pm/PackageManager/queryIntentActivities(Landroid/content/Intent;I)Ljava/util/List;
invokeinterface java/util/List/size()I 0
ifle L4
L1:
aload 0
iload 3
putfield com/flurry/android/v/p Z
aload 0
iconst_1
putfield com/flurry/android/v/q Z
L3:
aload 0
monitorexit
return
L4:
iconst_0
istore 3
goto L1
L2:
astore 1
aload 0
monitorexit
aload 1
athrow
.limit locals 5
.limit stack 5
.end method

.method final a(Landroid/content/Context;Lcom/flurry/android/p;Ljava/lang/String;)V
.catch all from L0 to L1 using L2
.catch all from L3 to L4 using L2
aload 0
monitorenter
L0:
aload 0
invokespecial com/flurry/android/v/p()Z
istore 4
L1:
iload 4
ifne L3
L5:
aload 0
monitorexit
return
L3:
aload 0
getfield com/flurry/android/v/t Landroid/os/Handler;
new com/flurry/android/al
dup
aload 0
aload 3
aload 1
aload 2
invokespecial com/flurry/android/al/<init>(Lcom/flurry/android/v;Ljava/lang/String;Landroid/content/Context;Lcom/flurry/android/p;)V
invokevirtual android/os/Handler/post(Ljava/lang/Runnable;)Z
pop
L4:
goto L5
L2:
astore 1
aload 0
monitorexit
aload 1
athrow
.limit locals 5
.limit stack 7
.end method

.method final a(Landroid/content/Context;Ljava/lang/String;)V
.catch all from L0 to L1 using L2
.catch java/lang/Exception from L3 to L4 using L5
.catch all from L3 to L4 using L2
.catch java/lang/Exception from L6 to L7 using L5
.catch all from L6 to L7 using L2
.catch all from L8 to L9 using L2
.catch java/lang/Exception from L10 to L11 using L5
.catch all from L10 to L11 using L2
aload 0
monitorenter
L0:
aload 0
invokespecial com/flurry/android/v/p()Z
istore 3
L1:
iload 3
ifne L3
L12:
aload 0
monitorexit
return
L3:
aload 0
iconst_1
anewarray java/lang/String
dup
iconst_0
aload 2
aastore
invokestatic java/util/Arrays/asList([Ljava/lang/Object;)Ljava/util/List;
aconst_null
invokespecial com/flurry/android/v/a(Ljava/util/List;Ljava/lang/Long;)Ljava/util/List;
astore 4
L4:
aload 4
ifnull L10
L6:
aload 4
invokeinterface java/util/List/isEmpty()Z 0
ifne L10
new com/flurry/android/p
dup
aload 2
iconst_2
aload 0
invokevirtual com/flurry/android/v/j()J
invokespecial com/flurry/android/p/<init>(Ljava/lang/String;BJ)V
astore 5
aload 5
aload 4
iconst_0
invokeinterface java/util/List/get(I)Ljava/lang/Object; 1
checkcast com/flurry/android/w
putfield com/flurry/android/p/c Lcom/flurry/android/w;
aload 0
aload 5
invokespecial com/flurry/android/v/c(Lcom/flurry/android/p;)V
aload 0
aload 1
aload 5
new java/lang/StringBuilder
dup
invokespecial java/lang/StringBuilder/<init>()V
aload 0
getfield com/flurry/android/v/h Ljava/lang/String;
invokevirtual java/lang/StringBuilder/append(Ljava/lang/String;)Ljava/lang/StringBuilder;
aload 0
aload 5
invokevirtual com/flurry/android/v/a(Lcom/flurry/android/p;)Ljava/lang/String;
invokevirtual java/lang/StringBuilder/append(Ljava/lang/String;)Ljava/lang/StringBuilder;
invokevirtual java/lang/StringBuilder/toString()Ljava/lang/String;
invokespecial com/flurry/android/v/b(Landroid/content/Context;Lcom/flurry/android/p;Ljava/lang/String;)V
L7:
goto L12
L5:
astore 1
L8:
getstatic com/flurry/android/v/a Ljava/lang/String;
new java/lang/StringBuilder
dup
invokespecial java/lang/StringBuilder/<init>()V
ldc "Failed to launch promotional canvas for hook: "
invokevirtual java/lang/StringBuilder/append(Ljava/lang/String;)Ljava/lang/StringBuilder;
aload 2
invokevirtual java/lang/StringBuilder/append(Ljava/lang/String;)Ljava/lang/StringBuilder;
invokevirtual java/lang/StringBuilder/toString()Ljava/lang/String;
aload 1
invokestatic com/flurry/android/ai/d(Ljava/lang/String;Ljava/lang/String;Ljava/lang/Throwable;)I
pop
L9:
goto L12
L2:
astore 1
aload 0
monitorexit
aload 1
athrow
L10:
new android/content/Intent
dup
invokestatic com/flurry/android/v/o()Ljava/lang/String;
invokespecial android/content/Intent/<init>(Ljava/lang/String;)V
astore 4
aload 4
ldc "android.intent.category.DEFAULT"
invokevirtual android/content/Intent/addCategory(Ljava/lang/String;)Landroid/content/Intent;
pop
aload 1
aload 4
invokevirtual android/content/Context/startActivity(Landroid/content/Intent;)V
L11:
goto L12
.limit locals 6
.limit stack 6
.end method

.method final a(Lcom/flurry/android/AppCircleCallback;)V
aload 0
aload 1
putfield com/flurry/android/v/z Lcom/flurry/android/AppCircleCallback;
return
.limit locals 2
.limit stack 2
.end method

.method final a(Ljava/lang/String;)V
aload 0
aload 1
putfield com/flurry/android/v/r Ljava/lang/String;
return
.limit locals 2
.limit stack 2
.end method

.method final a(Ljava/lang/String;Ljava/lang/String;)V
.catch all from L0 to L1 using L2
aload 0
monitorenter
L0:
aload 0
getfield com/flurry/android/v/s Ljava/util/Map;
aload 1
aload 2
invokeinterface java/util/Map/put(Ljava/lang/Object;Ljava/lang/Object;)Ljava/lang/Object; 2
pop
L1:
aload 0
monitorexit
return
L2:
astore 1
aload 0
monitorexit
aload 1
athrow
.limit locals 3
.limit stack 3
.end method

.method final a(Ljava/util/List;)V
.catch all from L0 to L1 using L2
.catch all from L3 to L4 using L2
.catch all from L4 to L5 using L2
aload 0
monitorenter
L0:
aload 0
invokespecial com/flurry/android/v/p()Z
istore 2
L1:
iload 2
ifne L3
L6:
aload 0
monitorexit
return
L3:
aload 1
invokeinterface java/util/List/iterator()Ljava/util/Iterator; 0
astore 1
L4:
aload 1
invokeinterface java/util/Iterator/hasNext()Z 0
ifeq L6
aload 1
invokeinterface java/util/Iterator/next()Ljava/lang/Object; 0
checkcast java/lang/Long
astore 3
aload 0
getfield com/flurry/android/v/y Ljava/util/Map;
aload 3
invokeinterface java/util/Map/remove(Ljava/lang/Object;)Ljava/lang/Object; 1
pop
L5:
goto L4
L2:
astore 1
aload 0
monitorexit
aload 1
athrow
.limit locals 4
.limit stack 2
.end method

.method final a(Ljava/util/Map;Ljava/util/Map;Ljava/util/Map;Ljava/util/Map;Ljava/util/Map;Ljava/util/Map;)V
.catch all from L0 to L1 using L2
.catch all from L3 to L4 using L2
aload 0
monitorenter
L0:
aload 0
invokespecial com/flurry/android/v/p()Z
istore 7
L1:
iload 7
ifne L3
L5:
aload 0
monitorexit
return
L3:
aload 0
getfield com/flurry/android/v/o Lcom/flurry/android/aa;
aload 1
aload 2
aload 3
aload 4
aload 5
aload 6
invokevirtual com/flurry/android/aa/a(Ljava/util/Map;Ljava/util/Map;Ljava/util/Map;Ljava/util/Map;Ljava/util/Map;Ljava/util/Map;)V
ldc "FlurryAgent"
aload 0
getfield com/flurry/android/v/o Lcom/flurry/android/aa;
invokevirtual com/flurry/android/aa/toString()Ljava/lang/String;
invokestatic android/util/Log/i(Ljava/lang/String;Ljava/lang/String;)I
pop
L4:
goto L5
L2:
astore 1
aload 0
monitorexit
aload 1
athrow
.limit locals 8
.limit stack 7
.end method

.method final a(Z)V
aload 0
iload 1
putfield com/flurry/android/v/u Z
return
.limit locals 2
.limit stack 2
.end method

.method final a()Z
aload 0
getfield com/flurry/android/v/q Z
ireturn
.limit locals 1
.limit stack 1
.end method

.method final b(Ljava/lang/String;)Lcom/flurry/android/Offer;
.catch all from L0 to L1 using L2
.catch all from L3 to L4 using L2
.catch all from L5 to L6 using L2
aconst_null
astore 4
aload 0
monitorenter
L0:
aload 0
invokespecial com/flurry/android/v/p()Z
istore 2
L1:
iload 2
ifne L3
aload 4
astore 3
L7:
aload 0
monitorexit
aload 3
areturn
L3:
aload 0
iconst_1
anewarray java/lang/String
dup
iconst_0
aload 1
aastore
invokestatic java/util/Arrays/asList([Ljava/lang/Object;)Ljava/util/List;
aconst_null
invokespecial com/flurry/android/v/a(Ljava/util/List;Ljava/lang/Long;)Ljava/util/List;
astore 5
L4:
aload 4
astore 3
aload 5
ifnull L7
aload 4
astore 3
L5:
aload 5
invokeinterface java/util/List/isEmpty()Z 0
ifne L7
aload 0
aload 1
aload 5
iconst_0
invokeinterface java/util/List/get(I)Ljava/lang/Object; 1
checkcast com/flurry/android/w
invokespecial com/flurry/android/v/a(Ljava/lang/String;Lcom/flurry/android/w;)Lcom/flurry/android/Offer;
astore 3
getstatic com/flurry/android/v/a Ljava/lang/String;
new java/lang/StringBuilder
dup
invokespecial java/lang/StringBuilder/<init>()V
ldc "Impression for offer with ID "
invokevirtual java/lang/StringBuilder/append(Ljava/lang/String;)Ljava/lang/StringBuilder;
aload 3
invokevirtual com/flurry/android/Offer/getId()J
invokevirtual java/lang/StringBuilder/append(J)Ljava/lang/StringBuilder;
invokevirtual java/lang/StringBuilder/toString()Ljava/lang/String;
invokestatic com/flurry/android/ai/a(Ljava/lang/String;Ljava/lang/String;)I
pop
L6:
goto L7
L2:
astore 1
aload 0
monitorexit
aload 1
athrow
.limit locals 6
.limit stack 5
.end method

.method final b(J)Lcom/flurry/android/p;
.catch all from L0 to L1 using L2
aload 0
monitorenter
L0:
aload 0
getfield com/flurry/android/v/v Ljava/util/Map;
lload 1
invokestatic java/lang/Long/valueOf(J)Ljava/lang/Long;
invokeinterface java/util/Map/get(Ljava/lang/Object;)Ljava/lang/Object; 1
checkcast com/flurry/android/p
astore 3
L1:
aload 0
monitorexit
aload 3
areturn
L2:
astore 3
aload 0
monitorexit
aload 3
athrow
.limit locals 4
.limit stack 3
.end method

.method final b(Lcom/flurry/android/p;)Lcom/flurry/android/p;
.catch all from L0 to L1 using L2
.catch all from L1 to L3 using L2
aload 0
monitorenter
aload 1
astore 2
L0:
aload 0
getfield com/flurry/android/v/x Ljava/util/List;
aload 1
invokeinterface java/util/List/contains(Ljava/lang/Object;)Z 1
ifne L1
new com/flurry/android/p
dup
aload 1
aload 0
invokevirtual com/flurry/android/v/j()J
invokespecial com/flurry/android/p/<init>(Lcom/flurry/android/p;J)V
astore 2
aload 0
getfield com/flurry/android/v/x Ljava/util/List;
aload 2
invokeinterface java/util/List/add(Ljava/lang/Object;)Z 1
pop
L1:
aload 2
new com/flurry/android/f
dup
iconst_4
aload 0
invokevirtual com/flurry/android/v/j()J
invokespecial com/flurry/android/f/<init>(BJ)V
invokevirtual com/flurry/android/p/a(Lcom/flurry/android/f;)V
L3:
aload 0
monitorexit
aload 2
areturn
L2:
astore 1
aload 0
monitorexit
aload 1
athrow
.limit locals 3
.limit stack 6
.end method

.method final b()V
.catch all from L0 to L1 using L2
.catch all from L3 to L4 using L2
aload 0
monitorenter
L0:
aload 0
invokespecial com/flurry/android/v/p()Z
istore 1
L1:
iload 1
ifne L3
L5:
aload 0
monitorexit
return
L3:
aload 0
getfield com/flurry/android/v/o Lcom/flurry/android/aa;
invokevirtual com/flurry/android/aa/d()V
L4:
goto L5
L2:
astore 2
aload 0
monitorexit
aload 2
athrow
.limit locals 3
.limit stack 1
.end method

.method final c(Ljava/lang/String;)Ljava/util/List;
.catch all from L0 to L1 using L2
.catch all from L3 to L4 using L2
.catch all from L5 to L6 using L2
.catch all from L7 to L8 using L2
.catch all from L9 to L10 using L2
.catch all from L11 to L12 using L2
aload 0
monitorenter
L0:
aload 0
invokespecial com/flurry/android/v/p()Z
ifne L3
invokestatic java/util/Collections/emptyList()Ljava/util/List;
astore 1
L1:
aload 0
monitorexit
aload 1
areturn
L3:
aload 0
getfield com/flurry/android/v/o Lcom/flurry/android/aa;
invokevirtual com/flurry/android/aa/b()Z
ifne L5
invokestatic java/util/Collections/emptyList()Ljava/util/List;
astore 1
L4:
goto L1
L5:
aload 0
getfield com/flurry/android/v/o Lcom/flurry/android/aa;
aload 1
invokevirtual com/flurry/android/aa/a(Ljava/lang/String;)[Lcom/flurry/android/w;
astore 5
new java/util/ArrayList
dup
invokespecial java/util/ArrayList/<init>()V
astore 4
L6:
aload 5
ifnull L11
L7:
aload 5
arraylength
ifle L11
aload 5
arraylength
istore 3
L8:
iconst_0
istore 2
L13:
iload 2
iload 3
if_icmpge L11
L9:
aload 4
aload 0
aload 1
aload 5
iload 2
aaload
invokespecial com/flurry/android/v/a(Ljava/lang/String;Lcom/flurry/android/w;)Lcom/flurry/android/Offer;
invokeinterface java/util/List/add(Ljava/lang/Object;)Z 1
pop
L10:
iload 2
iconst_1
iadd
istore 2
goto L13
L11:
getstatic com/flurry/android/v/a Ljava/lang/String;
new java/lang/StringBuilder
dup
invokespecial java/lang/StringBuilder/<init>()V
ldc "Impressions for "
invokevirtual java/lang/StringBuilder/append(Ljava/lang/String;)Ljava/lang/StringBuilder;
aload 4
invokeinterface java/util/List/size()I 0
invokevirtual java/lang/StringBuilder/append(I)Ljava/lang/StringBuilder;
ldc " offers."
invokevirtual java/lang/StringBuilder/append(Ljava/lang/String;)Ljava/lang/StringBuilder;
invokevirtual java/lang/StringBuilder/toString()Ljava/lang/String;
invokestatic com/flurry/android/ai/a(Ljava/lang/String;Ljava/lang/String;)I
pop
L12:
aload 4
astore 1
goto L1
L2:
astore 1
aload 0
monitorexit
aload 1
athrow
.limit locals 6
.limit stack 5
.end method

.method final c()V
.catch all from L0 to L1 using L2
.catch all from L3 to L4 using L2
aload 0
monitorenter
L0:
aload 0
invokespecial com/flurry/android/v/p()Z
istore 1
L1:
iload 1
ifne L3
L5:
aload 0
monitorexit
return
L3:
aload 0
getfield com/flurry/android/v/o Lcom/flurry/android/aa;
invokevirtual com/flurry/android/aa/e()V
L4:
goto L5
L2:
astore 2
aload 0
monitorexit
aload 2
athrow
.limit locals 3
.limit stack 1
.end method

.method final d()J
.catch all from L0 to L1 using L2
.catch all from L3 to L4 using L2
aload 0
monitorenter
L0:
aload 0
invokespecial com/flurry/android/v/p()Z
istore 1
L1:
iload 1
ifne L3
lconst_0
lstore 2
L5:
aload 0
monitorexit
lload 2
lreturn
L3:
aload 0
getfield com/flurry/android/v/o Lcom/flurry/android/aa;
invokevirtual com/flurry/android/aa/c()J
lstore 2
L4:
goto L5
L2:
astore 4
aload 0
monitorexit
aload 4
athrow
.limit locals 5
.limit stack 2
.end method

.method final e()Ljava/util/Set;
.catch all from L0 to L1 using L2
.catch all from L3 to L4 using L2
aload 0
monitorenter
L0:
aload 0
invokespecial com/flurry/android/v/p()Z
ifne L3
invokestatic java/util/Collections/emptySet()Ljava/util/Set;
astore 1
L1:
aload 0
monitorexit
aload 1
areturn
L3:
aload 0
getfield com/flurry/android/v/o Lcom/flurry/android/aa;
invokevirtual com/flurry/android/aa/a()Ljava/util/Set;
astore 1
L4:
goto L1
L2:
astore 1
aload 0
monitorexit
aload 1
athrow
.limit locals 2
.limit stack 1
.end method

.method final f()Ljava/util/List;
.catch all from L0 to L1 using L2
aload 0
monitorenter
L0:
aload 0
getfield com/flurry/android/v/x Ljava/util/List;
astore 1
L1:
aload 0
monitorexit
aload 1
areturn
L2:
astore 1
aload 0
monitorexit
aload 1
athrow
.limit locals 2
.limit stack 1
.end method

.method final g()V
.catch all from L0 to L1 using L2
aload 0
monitorenter
L0:
aload 0
getfield com/flurry/android/v/v Ljava/util/Map;
invokeinterface java/util/Map/clear()V 0
L1:
aload 0
monitorexit
return
L2:
astore 1
aload 0
monitorexit
aload 1
athrow
.limit locals 2
.limit stack 1
.end method

.method final h()Z
aload 0
getfield com/flurry/android/v/u Z
ireturn
.limit locals 1
.limit stack 1
.end method

.method final i()Ljava/lang/String;
aload 0
getfield com/flurry/android/v/h Ljava/lang/String;
areturn
.limit locals 1
.limit stack 1
.end method

.method final j()J
.catch all from L0 to L1 using L2
.catch all from L1 to L3 using L2
.catch all from L4 to L5 using L2
aload 0
monitorenter
L0:
invokestatic android/os/SystemClock/elapsedRealtime()J
aload 0
getfield com/flurry/android/v/m J
lsub
lstore 1
lload 1
aload 0
getfield com/flurry/android/v/n J
lcmp
ifle L4
L1:
aload 0
lload 1
putfield com/flurry/android/v/n J
aload 0
getfield com/flurry/android/v/n J
lstore 1
L3:
aload 0
monitorexit
lload 1
lreturn
L4:
aload 0
getfield com/flurry/android/v/n J
lconst_1
ladd
lstore 1
aload 0
lload 1
putfield com/flurry/android/v/n J
L5:
goto L1
L2:
astore 3
aload 0
monitorexit
aload 3
athrow
.limit locals 4
.limit stack 4
.end method

.method final k()V
.catch all from L0 to L1 using L2
aload 0
monitorenter
L0:
aload 0
getfield com/flurry/android/v/s Ljava/util/Map;
invokeinterface java/util/Map/clear()V 0
L1:
aload 0
monitorexit
return
L2:
astore 1
aload 0
monitorexit
aload 1
athrow
.limit locals 2
.limit stack 1
.end method

.method final l()Lcom/flurry/android/AdImage;
.catch all from L0 to L1 using L2
.catch all from L3 to L4 using L2
aload 0
monitorenter
L0:
aload 0
invokespecial com/flurry/android/v/p()Z
istore 1
L1:
iload 1
ifne L3
aconst_null
astore 2
L5:
aload 0
monitorexit
aload 2
areturn
L3:
aload 0
invokespecial com/flurry/android/v/n()Lcom/flurry/android/AdImage;
astore 2
L4:
goto L5
L2:
astore 2
aload 0
monitorexit
aload 2
athrow
.limit locals 3
.limit stack 1
.end method

.method final m()Z
.catch all from L0 to L1 using L2
.catch all from L3 to L4 using L2
aload 0
monitorenter
L0:
aload 0
invokespecial com/flurry/android/v/p()Z
istore 1
L1:
iload 1
ifne L3
iconst_0
istore 1
L5:
aload 0
monitorexit
iload 1
ireturn
L3:
aload 0
getfield com/flurry/android/v/o Lcom/flurry/android/aa;
invokevirtual com/flurry/android/aa/b()Z
istore 1
L4:
goto L5
L2:
astore 2
aload 0
monitorexit
aload 2
athrow
.limit locals 3
.limit stack 1
.end method

.method public final onClick(Landroid/view/View;)V
.catch all from L0 to L1 using L2
.catch all from L3 to L4 using L2
aload 0
monitorenter
L0:
aload 1
checkcast com/flurry/android/z
astore 3
aload 0
aload 3
invokevirtual com/flurry/android/z/a()Lcom/flurry/android/p;
invokevirtual com/flurry/android/v/b(Lcom/flurry/android/p;)Lcom/flurry/android/p;
astore 2
aload 3
aload 2
invokevirtual com/flurry/android/z/a(Lcom/flurry/android/p;)V
aload 0
aload 2
invokevirtual com/flurry/android/v/a(Lcom/flurry/android/p;)Ljava/lang/String;
astore 3
aload 0
getfield com/flurry/android/v/u Z
ifeq L3
aload 0
aload 1
invokevirtual android/view/View/getContext()Landroid/content/Context;
aload 2
new java/lang/StringBuilder
dup
invokespecial java/lang/StringBuilder/<init>()V
aload 0
getfield com/flurry/android/v/h Ljava/lang/String;
invokevirtual java/lang/StringBuilder/append(Ljava/lang/String;)Ljava/lang/StringBuilder;
aload 3
invokevirtual java/lang/StringBuilder/append(Ljava/lang/String;)Ljava/lang/StringBuilder;
invokevirtual java/lang/StringBuilder/toString()Ljava/lang/String;
invokespecial com/flurry/android/v/b(Landroid/content/Context;Lcom/flurry/android/p;Ljava/lang/String;)V
L1:
aload 0
monitorexit
return
L3:
aload 0
aload 1
invokevirtual android/view/View/getContext()Landroid/content/Context;
aload 2
new java/lang/StringBuilder
dup
invokespecial java/lang/StringBuilder/<init>()V
aload 0
getfield com/flurry/android/v/i Ljava/lang/String;
invokevirtual java/lang/StringBuilder/append(Ljava/lang/String;)Ljava/lang/StringBuilder;
aload 3
invokevirtual java/lang/StringBuilder/append(Ljava/lang/String;)Ljava/lang/StringBuilder;
invokevirtual java/lang/StringBuilder/toString()Ljava/lang/String;
invokevirtual com/flurry/android/v/a(Landroid/content/Context;Lcom/flurry/android/p;Ljava/lang/String;)V
L4:
goto L1
L2:
astore 1
aload 0
monitorexit
aload 1
athrow
.limit locals 4
.limit stack 5
.end method

.method public final toString()Ljava/lang/String;
new java/lang/StringBuilder
dup
invokespecial java/lang/StringBuilder/<init>()V
astore 1
aload 1
ldc "[adLogs="
invokevirtual java/lang/StringBuilder/append(Ljava/lang/String;)Ljava/lang/StringBuilder;
aload 0
getfield com/flurry/android/v/x Ljava/util/List;
invokevirtual java/lang/StringBuilder/append(Ljava/lang/Object;)Ljava/lang/StringBuilder;
ldc "]"
invokevirtual java/lang/StringBuilder/append(Ljava/lang/String;)Ljava/lang/StringBuilder;
pop
aload 1
invokevirtual java/lang/StringBuilder/toString()Ljava/lang/String;
areturn
.limit locals 2
.limit stack 2
.end method
