.bytecode 50.0
.class final synchronized com/flurry/android/w
.super com/flurry/android/ak

.field 'a' J

.field 'b' J

.field 'c' Ljava/lang/String;

.field 'd' Ljava/lang/String;

.field 'e' J

.field 'f' Ljava/lang/Long;

.field 'g' [B

.field 'h' Lcom/flurry/android/AdImage;

.method <init>()V
aload 0
invokespecial com/flurry/android/ak/<init>()V
return
.limit locals 1
.limit stack 1
.end method

.method <init>(Ljava/io/DataInput;)V
aload 0
invokespecial com/flurry/android/ak/<init>()V
aload 0
aload 1
invokespecial com/flurry/android/w/b(Ljava/io/DataInput;)V
return
.limit locals 2
.limit stack 2
.end method

.method private static a([B)Ljava/lang/String;
new java/lang/StringBuilder
dup
invokespecial java/lang/StringBuilder/<init>()V
astore 3
iconst_0
istore 1
L0:
iload 1
aload 0
arraylength
if_icmpge L1
aload 0
iload 1
baload
iconst_4
ishr
bipush 15
iand
istore 2
iload 2
bipush 10
if_icmpge L2
aload 3
iload 2
bipush 48
iadd
i2c
invokevirtual java/lang/StringBuilder/append(C)Ljava/lang/StringBuilder;
pop
L3:
aload 0
iload 1
baload
bipush 15
iand
istore 2
iload 2
bipush 10
if_icmpge L4
aload 3
iload 2
bipush 48
iadd
i2c
invokevirtual java/lang/StringBuilder/append(C)Ljava/lang/StringBuilder;
pop
L5:
iload 1
iconst_1
iadd
istore 1
goto L0
L2:
aload 3
iload 2
bipush 65
iadd
bipush 10
isub
i2c
invokevirtual java/lang/StringBuilder/append(C)Ljava/lang/StringBuilder;
pop
goto L3
L4:
aload 3
iload 2
bipush 65
iadd
bipush 10
isub
i2c
invokevirtual java/lang/StringBuilder/append(C)Ljava/lang/StringBuilder;
pop
goto L5
L1:
aload 3
invokevirtual java/lang/StringBuilder/toString()Ljava/lang/String;
areturn
.limit locals 4
.limit stack 3
.end method

.method private b(Ljava/io/DataInput;)V
aload 0
aload 1
invokeinterface java/io/DataInput/readLong()J 0
putfield com/flurry/android/w/a J
aload 0
aload 1
invokeinterface java/io/DataInput/readLong()J 0
putfield com/flurry/android/w/b J
aload 0
aload 1
invokeinterface java/io/DataInput/readUTF()Ljava/lang/String; 0
putfield com/flurry/android/w/d Ljava/lang/String;
aload 0
aload 1
invokeinterface java/io/DataInput/readUTF()Ljava/lang/String; 0
putfield com/flurry/android/w/c Ljava/lang/String;
aload 0
aload 1
invokeinterface java/io/DataInput/readLong()J 0
putfield com/flurry/android/w/e J
aload 0
aload 1
invokeinterface java/io/DataInput/readLong()J 0
invokestatic java/lang/Long/valueOf(J)Ljava/lang/Long;
putfield com/flurry/android/w/f Ljava/lang/Long;
aload 0
aload 1
invokeinterface java/io/DataInput/readUnsignedByte()I 0
newarray byte
putfield com/flurry/android/w/g [B
aload 1
aload 0
getfield com/flurry/android/w/g [B
invokeinterface java/io/DataInput/readFully([B)V 1
return
.limit locals 2
.limit stack 3
.end method

.method final a(Ljava/io/DataInput;)V
aload 0
aload 1
invokespecial com/flurry/android/w/b(Ljava/io/DataInput;)V
return
.limit locals 2
.limit stack 2
.end method

.method public final toString()Ljava/lang/String;
new java/lang/StringBuilder
dup
invokespecial java/lang/StringBuilder/<init>()V
ldc "ad {id="
invokevirtual java/lang/StringBuilder/append(Ljava/lang/String;)Ljava/lang/StringBuilder;
aload 0
getfield com/flurry/android/w/a J
invokevirtual java/lang/StringBuilder/append(J)Ljava/lang/StringBuilder;
ldc ", name='"
invokevirtual java/lang/StringBuilder/append(Ljava/lang/String;)Ljava/lang/StringBuilder;
aload 0
getfield com/flurry/android/w/d Ljava/lang/String;
invokevirtual java/lang/StringBuilder/append(Ljava/lang/String;)Ljava/lang/StringBuilder;
ldc "', cookie: '"
invokevirtual java/lang/StringBuilder/append(Ljava/lang/String;)Ljava/lang/StringBuilder;
aload 0
getfield com/flurry/android/w/g [B
invokestatic com/flurry/android/w/a([B)Ljava/lang/String;
invokevirtual java/lang/StringBuilder/append(Ljava/lang/String;)Ljava/lang/StringBuilder;
ldc "'}"
invokevirtual java/lang/StringBuilder/append(Ljava/lang/String;)Ljava/lang/StringBuilder;
invokevirtual java/lang/StringBuilder/toString()Ljava/lang/String;
areturn
.limit locals 1
.limit stack 3
.end method
