.bytecode 50.0
.class public final synchronized com/alipay/apmobilesecuritysdk/c/d
.super java/lang/Object

.method public static a(Landroid/content/Context;)Ljava/util/Map;
.signature "(Landroid/content/Context;)Ljava/util/Map<Ljava/lang/String;Ljava/lang/String;>;"
.catch all from L0 to L1 using L2
.catch all from L3 to L4 using L2
.catch all from L5 to L6 using L2
ldc com/alipay/apmobilesecuritysdk/c/d
monitorenter
L0:
invokestatic com/alipay/security/mobile/module/deviceinfo/d/a()Lcom/alipay/security/mobile/module/deviceinfo/d;
pop
new java/util/HashMap
dup
invokespecial java/util/HashMap/<init>()V
astore 2
aload 2
ldc "AE1"
invokestatic com/alipay/security/mobile/module/deviceinfo/d/b()Ljava/lang/String;
invokeinterface java/util/Map/put(Ljava/lang/Object;Ljava/lang/Object;)Ljava/lang/Object; 2
pop
new java/lang/StringBuilder
dup
invokespecial java/lang/StringBuilder/<init>()V
astore 3
invokestatic com/alipay/security/mobile/module/deviceinfo/d/c()Z
ifeq L7
L1:
ldc "1"
astore 1
L3:
aload 2
ldc "AE2"
aload 3
aload 1
invokevirtual java/lang/StringBuilder/append(Ljava/lang/String;)Ljava/lang/StringBuilder;
invokevirtual java/lang/StringBuilder/toString()Ljava/lang/String;
invokeinterface java/util/Map/put(Ljava/lang/Object;Ljava/lang/Object;)Ljava/lang/Object; 2
pop
new java/lang/StringBuilder
dup
invokespecial java/lang/StringBuilder/<init>()V
astore 1
aload 0
invokestatic com/alipay/security/mobile/module/deviceinfo/d/a(Landroid/content/Context;)Z
ifeq L8
L4:
ldc "1"
astore 0
L5:
aload 2
ldc "AE3"
aload 1
aload 0
invokevirtual java/lang/StringBuilder/append(Ljava/lang/String;)Ljava/lang/StringBuilder;
invokevirtual java/lang/StringBuilder/toString()Ljava/lang/String;
invokeinterface java/util/Map/put(Ljava/lang/Object;Ljava/lang/Object;)Ljava/lang/Object; 2
pop
aload 2
ldc "AE4"
invokestatic com/alipay/security/mobile/module/deviceinfo/d/d()Ljava/lang/String;
invokeinterface java/util/Map/put(Ljava/lang/Object;Ljava/lang/Object;)Ljava/lang/Object; 2
pop
aload 2
ldc "AE5"
invokestatic com/alipay/security/mobile/module/deviceinfo/d/e()Ljava/lang/String;
invokeinterface java/util/Map/put(Ljava/lang/Object;Ljava/lang/Object;)Ljava/lang/Object; 2
pop
aload 2
ldc "AE6"
invokestatic com/alipay/security/mobile/module/deviceinfo/d/f()Ljava/lang/String;
invokeinterface java/util/Map/put(Ljava/lang/Object;Ljava/lang/Object;)Ljava/lang/Object; 2
pop
aload 2
ldc "AE7"
invokestatic com/alipay/security/mobile/module/deviceinfo/d/g()Ljava/lang/String;
invokeinterface java/util/Map/put(Ljava/lang/Object;Ljava/lang/Object;)Ljava/lang/Object; 2
pop
aload 2
ldc "AE8"
invokestatic com/alipay/security/mobile/module/deviceinfo/d/h()Ljava/lang/String;
invokeinterface java/util/Map/put(Ljava/lang/Object;Ljava/lang/Object;)Ljava/lang/Object; 2
pop
aload 2
ldc "AE9"
invokestatic com/alipay/security/mobile/module/deviceinfo/d/i()Ljava/lang/String;
invokeinterface java/util/Map/put(Ljava/lang/Object;Ljava/lang/Object;)Ljava/lang/Object; 2
pop
aload 2
ldc "AE10"
invokestatic com/alipay/security/mobile/module/deviceinfo/d/j()Ljava/lang/String;
invokeinterface java/util/Map/put(Ljava/lang/Object;Ljava/lang/Object;)Ljava/lang/Object; 2
pop
aload 2
ldc "AE11"
invokestatic com/alipay/security/mobile/module/deviceinfo/d/k()Ljava/lang/String;
invokeinterface java/util/Map/put(Ljava/lang/Object;Ljava/lang/Object;)Ljava/lang/Object; 2
pop
aload 2
ldc "AE12"
invokestatic com/alipay/security/mobile/module/deviceinfo/d/l()Ljava/lang/String;
invokeinterface java/util/Map/put(Ljava/lang/Object;Ljava/lang/Object;)Ljava/lang/Object; 2
pop
aload 2
ldc "AE13"
invokestatic com/alipay/security/mobile/module/deviceinfo/d/m()Ljava/lang/String;
invokeinterface java/util/Map/put(Ljava/lang/Object;Ljava/lang/Object;)Ljava/lang/Object; 2
pop
aload 2
ldc "AE14"
invokestatic com/alipay/security/mobile/module/deviceinfo/d/n()Ljava/lang/String;
invokeinterface java/util/Map/put(Ljava/lang/Object;Ljava/lang/Object;)Ljava/lang/Object; 2
pop
aload 2
ldc "AE15"
invokestatic com/alipay/security/mobile/module/deviceinfo/d/o()Ljava/lang/String;
invokeinterface java/util/Map/put(Ljava/lang/Object;Ljava/lang/Object;)Ljava/lang/Object; 2
pop
L6:
ldc com/alipay/apmobilesecuritysdk/c/d
monitorexit
aload 2
areturn
L7:
ldc "0"
astore 1
goto L3
L8:
ldc "0"
astore 0
goto L5
L2:
astore 0
ldc com/alipay/apmobilesecuritysdk/c/d
monitorexit
aload 0
athrow
.limit locals 4
.limit stack 4
.end method
