.bytecode 50.0
.class synchronized com/nd/android/u/tast/birthday/activity/BirthdayGiftGiverActivity$mTask
.super com/common/android/utils/task/genericTask/GenericTask
.inner class private mTask inner com/nd/android/u/tast/birthday/activity/BirthdayGiftGiverActivity$mTask outer com/nd/android/u/tast/birthday/activity/BirthdayGiftGiverActivity

.field final synthetic 'this$0' Lcom/nd/android/u/tast/birthday/activity/BirthdayGiftGiverActivity;

.method private <init>(Lcom/nd/android/u/tast/birthday/activity/BirthdayGiftGiverActivity;)V
aload 0
aload 1
putfield com/nd/android/u/tast/birthday/activity/BirthdayGiftGiverActivity$mTask/this$0 Lcom/nd/android/u/tast/birthday/activity/BirthdayGiftGiverActivity;
aload 0
invokespecial com/common/android/utils/task/genericTask/GenericTask/<init>()V
return
.limit locals 2
.limit stack 2
.end method

.method synthetic <init>(Lcom/nd/android/u/tast/birthday/activity/BirthdayGiftGiverActivity;Lcom/nd/android/u/tast/birthday/activity/BirthdayGiftGiverActivity$1;)V
aload 0
aload 1
invokespecial com/nd/android/u/tast/birthday/activity/BirthdayGiftGiverActivity$mTask/<init>(Lcom/nd/android/u/tast/birthday/activity/BirthdayGiftGiverActivity;)V
return
.limit locals 3
.limit stack 2
.end method

.method protected transient _doInBackground([Lcom/common/android/utils/task/genericTask/TaskParams;)Lcom/common/android/utils/task/genericTask/TaskResult;
.catch com/common/android/utils/http/HttpException from L0 to L1 using L2
.catch com/common/android/utils/http/HttpException from L3 to L4 using L2
.catch com/common/android/utils/http/HttpException from L4 to L5 using L2
.catch com/common/android/utils/http/HttpException from L6 to L7 using L2
.catch com/common/android/utils/http/HttpException from L8 to L9 using L2
.catch com/common/android/utils/http/HttpException from L10 to L11 using L2
new com/nd/android/u/tast/com/OapBirthdayCom
dup
invokespecial com/nd/android/u/tast/com/OapBirthdayCom/<init>()V
astore 1
new java/lang/StringBuilder
dup
invokespecial java/lang/StringBuilder/<init>()V
astore 4
L0:
aload 1
iconst_1
bipush 20
invokevirtual com/nd/android/u/tast/com/OapBirthdayCom/getmyblesslistlist(II)Ljava/util/List;
astore 5
L1:
aload 5
ifnull L11
L3:
aload 5
invokeinterface java/util/List/size()I 0
ifeq L11
aload 0
getfield com/nd/android/u/tast/birthday/activity/BirthdayGiftGiverActivity$mTask/this$0 Lcom/nd/android/u/tast/birthday/activity/BirthdayGiftGiverActivity;
aload 5
iconst_0
invokeinterface java/util/List/get(I)Ljava/lang/Object; 1
checkcast com/nd/android/u/tast/birthday/dataStructure/Myblesslist
invokevirtual com/nd/android/u/tast/birthday/dataStructure/Myblesslist/getTotal()J
invokestatic com/nd/android/u/tast/birthday/activity/BirthdayGiftGiverActivity/access$802(Lcom/nd/android/u/tast/birthday/activity/BirthdayGiftGiverActivity;J)J
pop2
aload 0
getfield com/nd/android/u/tast/birthday/activity/BirthdayGiftGiverActivity$mTask/this$0 Lcom/nd/android/u/tast/birthday/activity/BirthdayGiftGiverActivity;
invokestatic com/nd/android/u/tast/birthday/activity/BirthdayGiftGiverActivity/access$700(Lcom/nd/android/u/tast/birthday/activity/BirthdayGiftGiverActivity;)Ljava/util/List;
invokeinterface java/util/List/size()I 0
istore 2
aload 0
getfield com/nd/android/u/tast/birthday/activity/BirthdayGiftGiverActivity$mTask/this$0 Lcom/nd/android/u/tast/birthday/activity/BirthdayGiftGiverActivity;
invokestatic com/nd/android/u/tast/birthday/activity/BirthdayGiftGiverActivity/access$700(Lcom/nd/android/u/tast/birthday/activity/BirthdayGiftGiverActivity;)Ljava/util/List;
aload 5
invokeinterface java/util/List/addAll(Ljava/util/Collection;)Z 1
pop
aload 4
invokevirtual java/lang/StringBuilder/length()I
ifeq L4
aload 4
ldc "\u3001"
invokevirtual java/lang/StringBuilder/append(Ljava/lang/String;)Ljava/lang/StringBuilder;
pop
L4:
aload 4
aload 0
getfield com/nd/android/u/tast/birthday/activity/BirthdayGiftGiverActivity$mTask/this$0 Lcom/nd/android/u/tast/birthday/activity/BirthdayGiftGiverActivity;
invokestatic com/nd/android/u/tast/birthday/activity/BirthdayGiftGiverActivity/access$700(Lcom/nd/android/u/tast/birthday/activity/BirthdayGiftGiverActivity;)Ljava/util/List;
iload 2
invokeinterface java/util/List/get(I)Ljava/lang/Object; 1
checkcast com/nd/android/u/tast/birthday/dataStructure/Myblesslist
invokevirtual com/nd/android/u/tast/birthday/dataStructure/Myblesslist/getUsername()Ljava/lang/String;
invokevirtual java/lang/StringBuilder/append(Ljava/lang/String;)Ljava/lang/StringBuilder;
pop
L5:
iload 2
iconst_1
iadd
istore 2
L6:
aload 0
getfield com/nd/android/u/tast/birthday/activity/BirthdayGiftGiverActivity$mTask/this$0 Lcom/nd/android/u/tast/birthday/activity/BirthdayGiftGiverActivity;
invokestatic com/nd/android/u/tast/birthday/activity/BirthdayGiftGiverActivity/access$700(Lcom/nd/android/u/tast/birthday/activity/BirthdayGiftGiverActivity;)Ljava/util/List;
invokeinterface java/util/List/size()I 0
istore 3
L7:
iload 2
iload 3
if_icmpge L10
L8:
aload 4
ldc "\u3001"
invokevirtual java/lang/StringBuilder/append(Ljava/lang/String;)Ljava/lang/StringBuilder;
aload 0
getfield com/nd/android/u/tast/birthday/activity/BirthdayGiftGiverActivity$mTask/this$0 Lcom/nd/android/u/tast/birthday/activity/BirthdayGiftGiverActivity;
invokestatic com/nd/android/u/tast/birthday/activity/BirthdayGiftGiverActivity/access$700(Lcom/nd/android/u/tast/birthday/activity/BirthdayGiftGiverActivity;)Ljava/util/List;
iload 2
invokeinterface java/util/List/get(I)Ljava/lang/Object; 1
checkcast com/nd/android/u/tast/birthday/dataStructure/Myblesslist
invokevirtual com/nd/android/u/tast/birthday/dataStructure/Myblesslist/getUsername()Ljava/lang/String;
invokevirtual java/lang/StringBuilder/append(Ljava/lang/String;)Ljava/lang/StringBuilder;
pop
L9:
iload 2
iconst_1
iadd
istore 2
goto L7
L10:
aload 0
getfield com/nd/android/u/tast/birthday/activity/BirthdayGiftGiverActivity$mTask/this$0 Lcom/nd/android/u/tast/birthday/activity/BirthdayGiftGiverActivity;
aload 0
getfield com/nd/android/u/tast/birthday/activity/BirthdayGiftGiverActivity$mTask/this$0 Lcom/nd/android/u/tast/birthday/activity/BirthdayGiftGiverActivity;
aload 0
getfield com/nd/android/u/tast/birthday/activity/BirthdayGiftGiverActivity$mTask/this$0 Lcom/nd/android/u/tast/birthday/activity/BirthdayGiftGiverActivity;
invokestatic com/nd/android/u/tast/birthday/activity/BirthdayGiftGiverActivity/access$100(Lcom/nd/android/u/tast/birthday/activity/BirthdayGiftGiverActivity;)Landroid/widget/TextView;
aload 0
getfield com/nd/android/u/tast/birthday/activity/BirthdayGiftGiverActivity$mTask/this$0 Lcom/nd/android/u/tast/birthday/activity/BirthdayGiftGiverActivity;
invokestatic com/nd/android/u/tast/birthday/activity/BirthdayGiftGiverActivity/access$000(Lcom/nd/android/u/tast/birthday/activity/BirthdayGiftGiverActivity;)I
aload 0
getfield com/nd/android/u/tast/birthday/activity/BirthdayGiftGiverActivity$mTask/this$0 Lcom/nd/android/u/tast/birthday/activity/BirthdayGiftGiverActivity;
invokestatic com/nd/android/u/tast/birthday/activity/BirthdayGiftGiverActivity/access$200(Lcom/nd/android/u/tast/birthday/activity/BirthdayGiftGiverActivity;)I
aload 4
invokevirtual java/lang/StringBuilder/toString()Ljava/lang/String;
invokevirtual com/nd/android/u/tast/birthday/activity/BirthdayGiftGiverActivity/changeGivers(Landroid/widget/TextView;IILjava/lang/String;)Ljava/lang/String;
invokestatic com/nd/android/u/tast/birthday/activity/BirthdayGiftGiverActivity/access$902(Lcom/nd/android/u/tast/birthday/activity/BirthdayGiftGiverActivity;Ljava/lang/String;)Ljava/lang/String;
pop
L11:
aload 0
getfield com/nd/android/u/tast/birthday/activity/BirthdayGiftGiverActivity$mTask/this$0 Lcom/nd/android/u/tast/birthday/activity/BirthdayGiftGiverActivity;
invokestatic com/nd/android/u/tast/birthday/activity/BirthdayGiftGiverActivity/access$1400(Lcom/nd/android/u/tast/birthday/activity/BirthdayGiftGiverActivity;)I
aload 0
getfield com/nd/android/u/tast/birthday/activity/BirthdayGiftGiverActivity$mTask/this$0 Lcom/nd/android/u/tast/birthday/activity/BirthdayGiftGiverActivity;
invokestatic com/nd/android/u/tast/birthday/activity/BirthdayGiftGiverActivity/access$1500(Lcom/nd/android/u/tast/birthday/activity/BirthdayGiftGiverActivity;)I
if_icmpgt L12
aload 0
getfield com/nd/android/u/tast/birthday/activity/BirthdayGiftGiverActivity$mTask/this$0 Lcom/nd/android/u/tast/birthday/activity/BirthdayGiftGiverActivity;
invokestatic com/nd/android/u/tast/birthday/activity/BirthdayGiftGiverActivity/access$700(Lcom/nd/android/u/tast/birthday/activity/BirthdayGiftGiverActivity;)Ljava/util/List;
invokeinterface java/util/List/size()I 0
i2l
aload 0
getfield com/nd/android/u/tast/birthday/activity/BirthdayGiftGiverActivity$mTask/this$0 Lcom/nd/android/u/tast/birthday/activity/BirthdayGiftGiverActivity;
invokestatic com/nd/android/u/tast/birthday/activity/BirthdayGiftGiverActivity/access$800(Lcom/nd/android/u/tast/birthday/activity/BirthdayGiftGiverActivity;)J
lcmp
iflt L0
L12:
getstatic com/common/android/utils/task/genericTask/TaskResult/OK Lcom/common/android/utils/task/genericTask/TaskResult;
areturn
L2:
astore 1
aload 1
invokevirtual com/common/android/utils/http/HttpException/printStackTrace()V
getstatic com/common/android/utils/task/genericTask/TaskResult/FAILED Lcom/common/android/utils/task/genericTask/TaskResult;
areturn
.limit locals 6
.limit stack 6
.end method
