.bytecode 50.0
.class synchronized com/nd/android/u/tast/birthday/activity/BirthdayGiftGiverActivity$2
.super java/lang/Object
.implements android/view/ViewTreeObserver$OnGlobalLayoutListener
.enclosing method com/nd/android/u/tast/birthday/activity/BirthdayGiftGiverActivity/findView()V
.inner class inner com/nd/android/u/tast/birthday/activity/BirthdayGiftGiverActivity$2

.field final synthetic 'this$0' Lcom/nd/android/u/tast/birthday/activity/BirthdayGiftGiverActivity;

.method <init>(Lcom/nd/android/u/tast/birthday/activity/BirthdayGiftGiverActivity;)V
aload 0
aload 1
putfield com/nd/android/u/tast/birthday/activity/BirthdayGiftGiverActivity$2/this$0 Lcom/nd/android/u/tast/birthday/activity/BirthdayGiftGiverActivity;
aload 0
invokespecial java/lang/Object/<init>()V
return
.limit locals 2
.limit stack 2
.end method

.method public onGlobalLayout()V
aload 0
getfield com/nd/android/u/tast/birthday/activity/BirthdayGiftGiverActivity$2/this$0 Lcom/nd/android/u/tast/birthday/activity/BirthdayGiftGiverActivity;
aload 0
getfield com/nd/android/u/tast/birthday/activity/BirthdayGiftGiverActivity$2/this$0 Lcom/nd/android/u/tast/birthday/activity/BirthdayGiftGiverActivity;
invokestatic com/nd/android/u/tast/birthday/activity/BirthdayGiftGiverActivity/access$300(Lcom/nd/android/u/tast/birthday/activity/BirthdayGiftGiverActivity;)Landroid/widget/Button;
invokevirtual android/widget/Button/getWidth()I
invokestatic com/nd/android/u/tast/birthday/activity/BirthdayGiftGiverActivity/access$202(Lcom/nd/android/u/tast/birthday/activity/BirthdayGiftGiverActivity;I)I
pop
aload 0
getfield com/nd/android/u/tast/birthday/activity/BirthdayGiftGiverActivity$2/this$0 Lcom/nd/android/u/tast/birthday/activity/BirthdayGiftGiverActivity;
invokestatic com/nd/android/u/tast/birthday/activity/BirthdayGiftGiverActivity/access$200(Lcom/nd/android/u/tast/birthday/activity/BirthdayGiftGiverActivity;)I
ifle L0
aload 0
getfield com/nd/android/u/tast/birthday/activity/BirthdayGiftGiverActivity$2/this$0 Lcom/nd/android/u/tast/birthday/activity/BirthdayGiftGiverActivity;
invokestatic com/nd/android/u/tast/birthday/activity/BirthdayGiftGiverActivity/access$100(Lcom/nd/android/u/tast/birthday/activity/BirthdayGiftGiverActivity;)Landroid/widget/TextView;
invokevirtual android/widget/TextView/getWidth()I
ifle L0
aload 0
getfield com/nd/android/u/tast/birthday/activity/BirthdayGiftGiverActivity$2/this$0 Lcom/nd/android/u/tast/birthday/activity/BirthdayGiftGiverActivity;
invokestatic com/nd/android/u/tast/birthday/activity/BirthdayGiftGiverActivity/access$400(Lcom/nd/android/u/tast/birthday/activity/BirthdayGiftGiverActivity;)Z
ifne L0
aload 0
getfield com/nd/android/u/tast/birthday/activity/BirthdayGiftGiverActivity$2/this$0 Lcom/nd/android/u/tast/birthday/activity/BirthdayGiftGiverActivity;
invokestatic com/nd/android/u/tast/birthday/activity/BirthdayGiftGiverActivity/access$300(Lcom/nd/android/u/tast/birthday/activity/BirthdayGiftGiverActivity;)Landroid/widget/Button;
bipush 8
invokevirtual android/widget/Button/setVisibility(I)V
aload 0
getfield com/nd/android/u/tast/birthday/activity/BirthdayGiftGiverActivity$2/this$0 Lcom/nd/android/u/tast/birthday/activity/BirthdayGiftGiverActivity;
invokestatic com/nd/android/u/tast/birthday/activity/BirthdayGiftGiverActivity/access$500(Lcom/nd/android/u/tast/birthday/activity/BirthdayGiftGiverActivity;)Landroid/widget/LinearLayout;
bipush 8
invokevirtual android/widget/LinearLayout/setVisibility(I)V
aload 0
getfield com/nd/android/u/tast/birthday/activity/BirthdayGiftGiverActivity$2/this$0 Lcom/nd/android/u/tast/birthday/activity/BirthdayGiftGiverActivity;
invokestatic com/nd/android/u/tast/birthday/activity/BirthdayGiftGiverActivity/access$600(Lcom/nd/android/u/tast/birthday/activity/BirthdayGiftGiverActivity;)V
aload 0
getfield com/nd/android/u/tast/birthday/activity/BirthdayGiftGiverActivity$2/this$0 Lcom/nd/android/u/tast/birthday/activity/BirthdayGiftGiverActivity;
iconst_1
invokestatic com/nd/android/u/tast/birthday/activity/BirthdayGiftGiverActivity/access$402(Lcom/nd/android/u/tast/birthday/activity/BirthdayGiftGiverActivity;Z)Z
pop
L0:
return
.limit locals 1
.limit stack 2
.end method
