.bytecode 50.0
.class synchronized com/nd/android/u/tast/birthday/activity/BirthdayActivity$2
.super com/common/android/utils/task/genericTask/TaskAdapter
.enclosing method com/nd/android/u/tast/birthday/activity/BirthdayActivity
.inner class inner com/nd/android/u/tast/birthday/activity/BirthdayActivity$2

.field final synthetic 'this$0' Lcom/nd/android/u/tast/birthday/activity/BirthdayActivity;

.method <init>(Lcom/nd/android/u/tast/birthday/activity/BirthdayActivity;)V
aload 0
aload 1
putfield com/nd/android/u/tast/birthday/activity/BirthdayActivity$2/this$0 Lcom/nd/android/u/tast/birthday/activity/BirthdayActivity;
aload 0
invokespecial com/common/android/utils/task/genericTask/TaskAdapter/<init>()V
return
.limit locals 2
.limit stack 2
.end method

.method public onPostExecute(Lcom/common/android/utils/task/genericTask/GenericTask;Lcom/common/android/utils/task/genericTask/TaskResult;)V
.catch java/lang/Exception from L0 to L1 using L2
aload 2
getstatic com/common/android/utils/task/genericTask/TaskResult/OK Lcom/common/android/utils/task/genericTask/TaskResult;
if_acmpne L3
aconst_null
astore 2
aload 1
instanceof com/nd/android/u/tast/birthday/activity/BirthdayActivity$GetBirthdayUserUserTask
ifeq L4
aload 1
checkcast com/nd/android/u/tast/birthday/activity/BirthdayActivity$GetBirthdayUserUserTask
invokestatic com/nd/android/u/tast/birthday/activity/BirthdayActivity$GetBirthdayUserUserTask/access$500(Lcom/nd/android/u/tast/birthday/activity/BirthdayActivity$GetBirthdayUserUserTask;)Lorg/json/JSONObject;
astore 2
L4:
aload 2
ldc "code"
invokestatic com/common/android/utils/JSONUtils/getInt(Lorg/json/JSONObject;Ljava/lang/String;)I
sipush 200
if_icmpeq L5
aload 0
getfield com/nd/android/u/tast/birthday/activity/BirthdayActivity$2/this$0 Lcom/nd/android/u/tast/birthday/activity/BirthdayActivity;
invokestatic com/nd/android/u/tast/birthday/activity/BirthdayActivity/access$600(Lcom/nd/android/u/tast/birthday/activity/BirthdayActivity;)Landroid/widget/TextView;
new java/lang/StringBuilder
dup
invokespecial java/lang/StringBuilder/<init>()V
ldc "get Birthday code error:"
invokevirtual java/lang/StringBuilder/append(Ljava/lang/String;)Ljava/lang/StringBuilder;
aload 2
ldc "code"
invokestatic com/common/android/utils/JSONUtils/getInt(Lorg/json/JSONObject;Ljava/lang/String;)I
invokevirtual java/lang/StringBuilder/append(I)Ljava/lang/StringBuilder;
invokevirtual java/lang/StringBuilder/toString()Ljava/lang/String;
invokevirtual android/widget/TextView/setText(Ljava/lang/CharSequence;)V
L5:
aload 2
ifnull L6
aload 2
ldc "tip"
invokestatic com/common/android/utils/JSONUtils/getString(Lorg/json/JSONObject;Ljava/lang/String;)Ljava/lang/String;
astore 1
aload 1
ifnull L0
aload 0
getfield com/nd/android/u/tast/birthday/activity/BirthdayActivity$2/this$0 Lcom/nd/android/u/tast/birthday/activity/BirthdayActivity;
invokestatic com/nd/android/u/tast/birthday/activity/BirthdayActivity/access$600(Lcom/nd/android/u/tast/birthday/activity/BirthdayActivity;)Landroid/widget/TextView;
aload 1
invokevirtual android/widget/TextView/setText(Ljava/lang/CharSequence;)V
L0:
aload 0
getfield com/nd/android/u/tast/birthday/activity/BirthdayActivity$2/this$0 Lcom/nd/android/u/tast/birthday/activity/BirthdayActivity;
invokestatic com/nd/android/u/tast/birthday/activity/BirthdayActivity/access$700(Lcom/nd/android/u/tast/birthday/activity/BirthdayActivity;)V
L1:
aload 0
getfield com/nd/android/u/tast/birthday/activity/BirthdayActivity$2/this$0 Lcom/nd/android/u/tast/birthday/activity/BirthdayActivity;
invokestatic com/nd/android/u/tast/birthday/activity/BirthdayActivity/access$800(Lcom/nd/android/u/tast/birthday/activity/BirthdayActivity;)V
return
L6:
aload 0
getfield com/nd/android/u/tast/birthday/activity/BirthdayActivity$2/this$0 Lcom/nd/android/u/tast/birthday/activity/BirthdayActivity;
invokestatic com/nd/android/u/tast/birthday/activity/BirthdayActivity/access$600(Lcom/nd/android/u/tast/birthday/activity/BirthdayActivity;)Landroid/widget/TextView;
getstatic com/nd/android/u/tasklib/R$string/get_bless_data_error I
invokevirtual android/widget/TextView/setText(I)V
goto L0
L2:
astore 1
aload 0
getfield com/nd/android/u/tast/birthday/activity/BirthdayActivity$2/this$0 Lcom/nd/android/u/tast/birthday/activity/BirthdayActivity;
ldc "get Birthday User parseDate error"
invokestatic com/common/android/utils/ToastUtils/display(Landroid/content/Context;Ljava/lang/String;)V
goto L1
L3:
aload 2
getstatic com/common/android/utils/task/genericTask/TaskResult/No_RESULT Lcom/common/android/utils/task/genericTask/TaskResult;
if_acmpne L7
aload 0
getfield com/nd/android/u/tast/birthday/activity/BirthdayActivity$2/this$0 Lcom/nd/android/u/tast/birthday/activity/BirthdayActivity;
invokestatic com/nd/android/u/tast/birthday/activity/BirthdayActivity/access$200(Lcom/nd/android/u/tast/birthday/activity/BirthdayActivity;)Landroid/widget/TextView;
getstatic com/nd/android/u/tasklib/R$string/no_data_now I
invokevirtual android/widget/TextView/setText(I)V
aload 0
getfield com/nd/android/u/tast/birthday/activity/BirthdayActivity$2/this$0 Lcom/nd/android/u/tast/birthday/activity/BirthdayActivity;
invokestatic com/nd/android/u/tast/birthday/activity/BirthdayActivity/access$200(Lcom/nd/android/u/tast/birthday/activity/BirthdayActivity;)Landroid/widget/TextView;
iconst_0
invokevirtual android/widget/TextView/setVisibility(I)V
aload 0
getfield com/nd/android/u/tast/birthday/activity/BirthdayActivity$2/this$0 Lcom/nd/android/u/tast/birthday/activity/BirthdayActivity;
invokestatic com/nd/android/u/tast/birthday/activity/BirthdayActivity/access$100(Lcom/nd/android/u/tast/birthday/activity/BirthdayActivity;)Landroid/widget/LinearLayout;
bipush 8
invokevirtual android/widget/LinearLayout/setVisibility(I)V
return
L7:
aload 0
getfield com/nd/android/u/tast/birthday/activity/BirthdayActivity$2/this$0 Lcom/nd/android/u/tast/birthday/activity/BirthdayActivity;
invokestatic com/nd/android/u/tast/birthday/activity/BirthdayActivity/access$600(Lcom/nd/android/u/tast/birthday/activity/BirthdayActivity;)Landroid/widget/TextView;
getstatic com/nd/android/u/tasklib/R$string/get_bless_data_error I
invokevirtual android/widget/TextView/setText(I)V
aload 0
getfield com/nd/android/u/tast/birthday/activity/BirthdayActivity$2/this$0 Lcom/nd/android/u/tast/birthday/activity/BirthdayActivity;
invokestatic com/nd/android/u/tast/birthday/activity/BirthdayActivity/access$200(Lcom/nd/android/u/tast/birthday/activity/BirthdayActivity;)Landroid/widget/TextView;
iconst_0
invokevirtual android/widget/TextView/setVisibility(I)V
aload 0
getfield com/nd/android/u/tast/birthday/activity/BirthdayActivity$2/this$0 Lcom/nd/android/u/tast/birthday/activity/BirthdayActivity;
invokestatic com/nd/android/u/tast/birthday/activity/BirthdayActivity/access$100(Lcom/nd/android/u/tast/birthday/activity/BirthdayActivity;)Landroid/widget/LinearLayout;
bipush 8
invokevirtual android/widget/LinearLayout/setVisibility(I)V
return
.limit locals 3
.limit stack 4
.end method
