.bytecode 50.0
.class synchronized com/nd/android/u/tast/birthday/activity/BirthdayGiftGiverActivity$4
.super java/lang/Object
.implements android/view/View$OnClickListener
.enclosing method com/nd/android/u/tast/birthday/activity/BirthdayGiftGiverActivity/setClick()V
.inner class inner com/nd/android/u/tast/birthday/activity/BirthdayGiftGiverActivity$4

.field final synthetic 'this$0' Lcom/nd/android/u/tast/birthday/activity/BirthdayGiftGiverActivity;

.method <init>(Lcom/nd/android/u/tast/birthday/activity/BirthdayGiftGiverActivity;)V
aload 0
aload 1
putfield com/nd/android/u/tast/birthday/activity/BirthdayGiftGiverActivity$4/this$0 Lcom/nd/android/u/tast/birthday/activity/BirthdayGiftGiverActivity;
aload 0
invokespecial java/lang/Object/<init>()V
return
.limit locals 2
.limit stack 2
.end method

.method public onClick(Landroid/view/View;)V
aload 0
getfield com/nd/android/u/tast/birthday/activity/BirthdayGiftGiverActivity$4/this$0 Lcom/nd/android/u/tast/birthday/activity/BirthdayGiftGiverActivity;
invokestatic com/nd/android/u/tast/birthday/activity/BirthdayGiftGiverActivity/access$700(Lcom/nd/android/u/tast/birthday/activity/BirthdayGiftGiverActivity;)Ljava/util/List;
invokeinterface java/util/List/size()I 0
i2l
aload 0
getfield com/nd/android/u/tast/birthday/activity/BirthdayGiftGiverActivity$4/this$0 Lcom/nd/android/u/tast/birthday/activity/BirthdayGiftGiverActivity;
invokestatic com/nd/android/u/tast/birthday/activity/BirthdayGiftGiverActivity/access$800(Lcom/nd/android/u/tast/birthday/activity/BirthdayGiftGiverActivity;)J
lcmp
ifne L0
aload 0
getfield com/nd/android/u/tast/birthday/activity/BirthdayGiftGiverActivity$4/this$0 Lcom/nd/android/u/tast/birthday/activity/BirthdayGiftGiverActivity;
invokestatic com/nd/android/u/tast/birthday/activity/BirthdayGiftGiverActivity/access$100(Lcom/nd/android/u/tast/birthday/activity/BirthdayGiftGiverActivity;)Landroid/widget/TextView;
aload 0
getfield com/nd/android/u/tast/birthday/activity/BirthdayGiftGiverActivity$4/this$0 Lcom/nd/android/u/tast/birthday/activity/BirthdayGiftGiverActivity;
invokestatic com/nd/android/u/tast/birthday/activity/BirthdayGiftGiverActivity/access$900(Lcom/nd/android/u/tast/birthday/activity/BirthdayGiftGiverActivity;)Ljava/lang/String;
invokevirtual android/widget/TextView/setText(Ljava/lang/CharSequence;)V
L1:
aload 0
getfield com/nd/android/u/tast/birthday/activity/BirthdayGiftGiverActivity$4/this$0 Lcom/nd/android/u/tast/birthday/activity/BirthdayGiftGiverActivity;
invokestatic com/nd/android/u/tast/birthday/activity/BirthdayGiftGiverActivity/access$1200(Lcom/nd/android/u/tast/birthday/activity/BirthdayGiftGiverActivity;)Landroid/widget/LinearLayout;
bipush 8
invokevirtual android/widget/LinearLayout/setVisibility(I)V
aload 0
getfield com/nd/android/u/tast/birthday/activity/BirthdayGiftGiverActivity$4/this$0 Lcom/nd/android/u/tast/birthday/activity/BirthdayGiftGiverActivity;
invokestatic com/nd/android/u/tast/birthday/activity/BirthdayGiftGiverActivity/access$500(Lcom/nd/android/u/tast/birthday/activity/BirthdayGiftGiverActivity;)Landroid/widget/LinearLayout;
iconst_0
invokevirtual android/widget/LinearLayout/setVisibility(I)V
aload 0
getfield com/nd/android/u/tast/birthday/activity/BirthdayGiftGiverActivity$4/this$0 Lcom/nd/android/u/tast/birthday/activity/BirthdayGiftGiverActivity;
invokestatic com/nd/android/u/tast/birthday/activity/BirthdayGiftGiverActivity/access$300(Lcom/nd/android/u/tast/birthday/activity/BirthdayGiftGiverActivity;)Landroid/widget/Button;
bipush 8
invokevirtual android/widget/Button/setVisibility(I)V
return
L0:
aload 0
getfield com/nd/android/u/tast/birthday/activity/BirthdayGiftGiverActivity$4/this$0 Lcom/nd/android/u/tast/birthday/activity/BirthdayGiftGiverActivity;
new com/nd/android/u/tast/birthday/activity/BirthdayGiftGiverActivity$GetOnePageGiversTask
dup
aload 0
getfield com/nd/android/u/tast/birthday/activity/BirthdayGiftGiverActivity$4/this$0 Lcom/nd/android/u/tast/birthday/activity/BirthdayGiftGiverActivity;
aconst_null
invokespecial com/nd/android/u/tast/birthday/activity/BirthdayGiftGiverActivity$GetOnePageGiversTask/<init>(Lcom/nd/android/u/tast/birthday/activity/BirthdayGiftGiverActivity;Lcom/nd/android/u/tast/birthday/activity/BirthdayGiftGiverActivity$1;)V
invokestatic com/nd/android/u/tast/birthday/activity/BirthdayGiftGiverActivity/access$1002(Lcom/nd/android/u/tast/birthday/activity/BirthdayGiftGiverActivity;Lcom/nd/android/u/tast/birthday/activity/BirthdayGiftGiverActivity$GetOnePageGiversTask;)Lcom/nd/android/u/tast/birthday/activity/BirthdayGiftGiverActivity$GetOnePageGiversTask;
pop
aload 0
getfield com/nd/android/u/tast/birthday/activity/BirthdayGiftGiverActivity$4/this$0 Lcom/nd/android/u/tast/birthday/activity/BirthdayGiftGiverActivity;
invokestatic com/nd/android/u/tast/birthday/activity/BirthdayGiftGiverActivity/access$1000(Lcom/nd/android/u/tast/birthday/activity/BirthdayGiftGiverActivity;)Lcom/nd/android/u/tast/birthday/activity/BirthdayGiftGiverActivity$GetOnePageGiversTask;
iconst_0
anewarray java/lang/Void
invokevirtual com/nd/android/u/tast/birthday/activity/BirthdayGiftGiverActivity$GetOnePageGiversTask/execute([Ljava/lang/Object;)Landroid/os/AsyncTask;
pop
goto L1
.limit locals 2
.limit stack 5
.end method
