.bytecode 50.0
.class synchronized com/nd/schoollife/ui/post/activity/ImageBrowserActivity$2
.super java/lang/Object
.implements com/nd/schoollife/ui/common/process/PraiseListener
.enclosing method com/nd/schoollife/ui/post/activity/ImageBrowserActivity/initEvent()V
.inner class inner com/nd/schoollife/ui/post/activity/ImageBrowserActivity$2

.field final synthetic 'this$0' Lcom/nd/schoollife/ui/post/activity/ImageBrowserActivity;

.method <init>(Lcom/nd/schoollife/ui/post/activity/ImageBrowserActivity;)V
aload 0
aload 1
putfield com/nd/schoollife/ui/post/activity/ImageBrowserActivity$2/this$0 Lcom/nd/schoollife/ui/post/activity/ImageBrowserActivity;
aload 0
invokespecial java/lang/Object/<init>()V
return
.limit locals 2
.limit stack 2
.end method

.method public onCancelPraise(JZLcom/nd/schoollife/ui/common/process/PraiseListener$PRAISE_TYPE;)V
lload 1
aload 0
getfield com/nd/schoollife/ui/post/activity/ImageBrowserActivity$2/this$0 Lcom/nd/schoollife/ui/post/activity/ImageBrowserActivity;
invokestatic com/nd/schoollife/ui/post/activity/ImageBrowserActivity/access$400(Lcom/nd/schoollife/ui/post/activity/ImageBrowserActivity;)J
lcmp
ifne L0
lload 1
ldc2_w -1L
lcmp
ifne L1
L0:
return
L1:
aload 4
getstatic com/nd/schoollife/ui/common/process/PraiseListener$PRAISE_TYPE/BROWSER Lcom/nd/schoollife/ui/common/process/PraiseListener$PRAISE_TYPE;
if_acmpeq L2
iload 3
ifeq L3
aload 0
getfield com/nd/schoollife/ui/post/activity/ImageBrowserActivity$2/this$0 Lcom/nd/schoollife/ui/post/activity/ImageBrowserActivity;
invokestatic com/nd/schoollife/ui/post/activity/ImageBrowserActivity/access$500(Lcom/nd/schoollife/ui/post/activity/ImageBrowserActivity;)I
iconst_1
if_icmpne L0
aload 0
getfield com/nd/schoollife/ui/post/activity/ImageBrowserActivity$2/this$0 Lcom/nd/schoollife/ui/post/activity/ImageBrowserActivity;
invokestatic com/nd/schoollife/ui/post/activity/ImageBrowserActivity/access$600(Lcom/nd/schoollife/ui/post/activity/ImageBrowserActivity;)I
ifle L4
aload 0
getfield com/nd/schoollife/ui/post/activity/ImageBrowserActivity$2/this$0 Lcom/nd/schoollife/ui/post/activity/ImageBrowserActivity;
aload 0
getfield com/nd/schoollife/ui/post/activity/ImageBrowserActivity$2/this$0 Lcom/nd/schoollife/ui/post/activity/ImageBrowserActivity;
invokestatic com/nd/schoollife/ui/post/activity/ImageBrowserActivity/access$600(Lcom/nd/schoollife/ui/post/activity/ImageBrowserActivity;)I
iconst_1
isub
invokestatic com/nd/schoollife/ui/post/activity/ImageBrowserActivity/access$602(Lcom/nd/schoollife/ui/post/activity/ImageBrowserActivity;I)I
pop
L4:
aload 0
getfield com/nd/schoollife/ui/post/activity/ImageBrowserActivity$2/this$0 Lcom/nd/schoollife/ui/post/activity/ImageBrowserActivity;
iconst_0
invokestatic com/nd/schoollife/ui/post/activity/ImageBrowserActivity/access$502(Lcom/nd/schoollife/ui/post/activity/ImageBrowserActivity;I)I
pop
aload 0
getfield com/nd/schoollife/ui/post/activity/ImageBrowserActivity$2/this$0 Lcom/nd/schoollife/ui/post/activity/ImageBrowserActivity;
invokestatic com/nd/schoollife/ui/post/activity/ImageBrowserActivity/access$700(Lcom/nd/schoollife/ui/post/activity/ImageBrowserActivity;)V
return
L3:
aload 0
getfield com/nd/schoollife/ui/post/activity/ImageBrowserActivity$2/this$0 Lcom/nd/schoollife/ui/post/activity/ImageBrowserActivity;
invokestatic com/nd/schoollife/ui/post/activity/ImageBrowserActivity/access$500(Lcom/nd/schoollife/ui/post/activity/ImageBrowserActivity;)I
ifne L0
aload 0
getfield com/nd/schoollife/ui/post/activity/ImageBrowserActivity$2/this$0 Lcom/nd/schoollife/ui/post/activity/ImageBrowserActivity;
aload 0
getfield com/nd/schoollife/ui/post/activity/ImageBrowserActivity$2/this$0 Lcom/nd/schoollife/ui/post/activity/ImageBrowserActivity;
invokestatic com/nd/schoollife/ui/post/activity/ImageBrowserActivity/access$600(Lcom/nd/schoollife/ui/post/activity/ImageBrowserActivity;)I
iconst_1
iadd
invokestatic com/nd/schoollife/ui/post/activity/ImageBrowserActivity/access$602(Lcom/nd/schoollife/ui/post/activity/ImageBrowserActivity;I)I
pop
aload 0
getfield com/nd/schoollife/ui/post/activity/ImageBrowserActivity$2/this$0 Lcom/nd/schoollife/ui/post/activity/ImageBrowserActivity;
iconst_1
invokestatic com/nd/schoollife/ui/post/activity/ImageBrowserActivity/access$502(Lcom/nd/schoollife/ui/post/activity/ImageBrowserActivity;I)I
pop
aload 0
getfield com/nd/schoollife/ui/post/activity/ImageBrowserActivity$2/this$0 Lcom/nd/schoollife/ui/post/activity/ImageBrowserActivity;
invokestatic com/nd/schoollife/ui/post/activity/ImageBrowserActivity/access$700(Lcom/nd/schoollife/ui/post/activity/ImageBrowserActivity;)V
return
L2:
iload 3
ifne L0
aload 0
getfield com/nd/schoollife/ui/post/activity/ImageBrowserActivity$2/this$0 Lcom/nd/schoollife/ui/post/activity/ImageBrowserActivity;
aload 0
getfield com/nd/schoollife/ui/post/activity/ImageBrowserActivity$2/this$0 Lcom/nd/schoollife/ui/post/activity/ImageBrowserActivity;
invokestatic com/nd/schoollife/ui/post/activity/ImageBrowserActivity/access$600(Lcom/nd/schoollife/ui/post/activity/ImageBrowserActivity;)I
iconst_1
iadd
invokestatic com/nd/schoollife/ui/post/activity/ImageBrowserActivity/access$602(Lcom/nd/schoollife/ui/post/activity/ImageBrowserActivity;I)I
pop
aload 0
getfield com/nd/schoollife/ui/post/activity/ImageBrowserActivity$2/this$0 Lcom/nd/schoollife/ui/post/activity/ImageBrowserActivity;
iconst_1
invokestatic com/nd/schoollife/ui/post/activity/ImageBrowserActivity/access$502(Lcom/nd/schoollife/ui/post/activity/ImageBrowserActivity;I)I
pop
aload 0
getfield com/nd/schoollife/ui/post/activity/ImageBrowserActivity$2/this$0 Lcom/nd/schoollife/ui/post/activity/ImageBrowserActivity;
invokestatic com/nd/schoollife/ui/post/activity/ImageBrowserActivity/access$700(Lcom/nd/schoollife/ui/post/activity/ImageBrowserActivity;)V
return
.limit locals 5
.limit stack 4
.end method

.method public onPraise(JZLcom/nd/schoollife/ui/common/process/PraiseListener$PRAISE_TYPE;)V
lload 1
aload 0
getfield com/nd/schoollife/ui/post/activity/ImageBrowserActivity$2/this$0 Lcom/nd/schoollife/ui/post/activity/ImageBrowserActivity;
invokestatic com/nd/schoollife/ui/post/activity/ImageBrowserActivity/access$400(Lcom/nd/schoollife/ui/post/activity/ImageBrowserActivity;)J
lcmp
ifne L0
lload 1
ldc2_w -1L
lcmp
ifne L1
L0:
return
L1:
aload 4
getstatic com/nd/schoollife/ui/common/process/PraiseListener$PRAISE_TYPE/BROWSER Lcom/nd/schoollife/ui/common/process/PraiseListener$PRAISE_TYPE;
if_acmpeq L2
iload 3
ifeq L3
aload 0
getfield com/nd/schoollife/ui/post/activity/ImageBrowserActivity$2/this$0 Lcom/nd/schoollife/ui/post/activity/ImageBrowserActivity;
invokestatic com/nd/schoollife/ui/post/activity/ImageBrowserActivity/access$500(Lcom/nd/schoollife/ui/post/activity/ImageBrowserActivity;)I
ifne L0
aload 0
getfield com/nd/schoollife/ui/post/activity/ImageBrowserActivity$2/this$0 Lcom/nd/schoollife/ui/post/activity/ImageBrowserActivity;
aload 0
getfield com/nd/schoollife/ui/post/activity/ImageBrowserActivity$2/this$0 Lcom/nd/schoollife/ui/post/activity/ImageBrowserActivity;
invokestatic com/nd/schoollife/ui/post/activity/ImageBrowserActivity/access$600(Lcom/nd/schoollife/ui/post/activity/ImageBrowserActivity;)I
iconst_1
iadd
invokestatic com/nd/schoollife/ui/post/activity/ImageBrowserActivity/access$602(Lcom/nd/schoollife/ui/post/activity/ImageBrowserActivity;I)I
pop
aload 0
getfield com/nd/schoollife/ui/post/activity/ImageBrowserActivity$2/this$0 Lcom/nd/schoollife/ui/post/activity/ImageBrowserActivity;
iconst_1
invokestatic com/nd/schoollife/ui/post/activity/ImageBrowserActivity/access$502(Lcom/nd/schoollife/ui/post/activity/ImageBrowserActivity;I)I
pop
aload 0
getfield com/nd/schoollife/ui/post/activity/ImageBrowserActivity$2/this$0 Lcom/nd/schoollife/ui/post/activity/ImageBrowserActivity;
invokestatic com/nd/schoollife/ui/post/activity/ImageBrowserActivity/access$700(Lcom/nd/schoollife/ui/post/activity/ImageBrowserActivity;)V
return
L3:
aload 0
getfield com/nd/schoollife/ui/post/activity/ImageBrowserActivity$2/this$0 Lcom/nd/schoollife/ui/post/activity/ImageBrowserActivity;
invokestatic com/nd/schoollife/ui/post/activity/ImageBrowserActivity/access$500(Lcom/nd/schoollife/ui/post/activity/ImageBrowserActivity;)I
iconst_1
if_icmpne L0
aload 0
getfield com/nd/schoollife/ui/post/activity/ImageBrowserActivity$2/this$0 Lcom/nd/schoollife/ui/post/activity/ImageBrowserActivity;
invokestatic com/nd/schoollife/ui/post/activity/ImageBrowserActivity/access$600(Lcom/nd/schoollife/ui/post/activity/ImageBrowserActivity;)I
ifle L4
aload 0
getfield com/nd/schoollife/ui/post/activity/ImageBrowserActivity$2/this$0 Lcom/nd/schoollife/ui/post/activity/ImageBrowserActivity;
aload 0
getfield com/nd/schoollife/ui/post/activity/ImageBrowserActivity$2/this$0 Lcom/nd/schoollife/ui/post/activity/ImageBrowserActivity;
invokestatic com/nd/schoollife/ui/post/activity/ImageBrowserActivity/access$600(Lcom/nd/schoollife/ui/post/activity/ImageBrowserActivity;)I
iconst_1
isub
invokestatic com/nd/schoollife/ui/post/activity/ImageBrowserActivity/access$602(Lcom/nd/schoollife/ui/post/activity/ImageBrowserActivity;I)I
pop
L4:
aload 0
getfield com/nd/schoollife/ui/post/activity/ImageBrowserActivity$2/this$0 Lcom/nd/schoollife/ui/post/activity/ImageBrowserActivity;
iconst_0
invokestatic com/nd/schoollife/ui/post/activity/ImageBrowserActivity/access$502(Lcom/nd/schoollife/ui/post/activity/ImageBrowserActivity;I)I
pop
aload 0
getfield com/nd/schoollife/ui/post/activity/ImageBrowserActivity$2/this$0 Lcom/nd/schoollife/ui/post/activity/ImageBrowserActivity;
invokestatic com/nd/schoollife/ui/post/activity/ImageBrowserActivity/access$700(Lcom/nd/schoollife/ui/post/activity/ImageBrowserActivity;)V
return
L2:
iload 3
ifne L0
aload 0
getfield com/nd/schoollife/ui/post/activity/ImageBrowserActivity$2/this$0 Lcom/nd/schoollife/ui/post/activity/ImageBrowserActivity;
invokestatic com/nd/schoollife/ui/post/activity/ImageBrowserActivity/access$600(Lcom/nd/schoollife/ui/post/activity/ImageBrowserActivity;)I
ifle L5
aload 0
getfield com/nd/schoollife/ui/post/activity/ImageBrowserActivity$2/this$0 Lcom/nd/schoollife/ui/post/activity/ImageBrowserActivity;
aload 0
getfield com/nd/schoollife/ui/post/activity/ImageBrowserActivity$2/this$0 Lcom/nd/schoollife/ui/post/activity/ImageBrowserActivity;
invokestatic com/nd/schoollife/ui/post/activity/ImageBrowserActivity/access$600(Lcom/nd/schoollife/ui/post/activity/ImageBrowserActivity;)I
iconst_1
isub
invokestatic com/nd/schoollife/ui/post/activity/ImageBrowserActivity/access$602(Lcom/nd/schoollife/ui/post/activity/ImageBrowserActivity;I)I
pop
L5:
aload 0
getfield com/nd/schoollife/ui/post/activity/ImageBrowserActivity$2/this$0 Lcom/nd/schoollife/ui/post/activity/ImageBrowserActivity;
iconst_0
invokestatic com/nd/schoollife/ui/post/activity/ImageBrowserActivity/access$502(Lcom/nd/schoollife/ui/post/activity/ImageBrowserActivity;I)I
pop
aload 0
getfield com/nd/schoollife/ui/post/activity/ImageBrowserActivity$2/this$0 Lcom/nd/schoollife/ui/post/activity/ImageBrowserActivity;
invokestatic com/nd/schoollife/ui/post/activity/ImageBrowserActivity/access$700(Lcom/nd/schoollife/ui/post/activity/ImageBrowserActivity;)V
return
.limit locals 5
.limit stack 4
.end method
