.bytecode 50.0
.class synchronized com/nd/schoollife/ui/post/activity/PostDetailActivity$6
.super java/lang/Object
.implements com/nd/schoollife/ui/common/process/PraiseListener
.enclosing method com/nd/schoollife/ui/post/activity/PostDetailActivity/initEvent()V
.inner class inner com/nd/schoollife/ui/post/activity/PostDetailActivity$6

.field final synthetic 'this$0' Lcom/nd/schoollife/ui/post/activity/PostDetailActivity;

.method <init>(Lcom/nd/schoollife/ui/post/activity/PostDetailActivity;)V
aload 0
aload 1
putfield com/nd/schoollife/ui/post/activity/PostDetailActivity$6/this$0 Lcom/nd/schoollife/ui/post/activity/PostDetailActivity;
aload 0
invokespecial java/lang/Object/<init>()V
return
.limit locals 2
.limit stack 2
.end method

.method public onCancelPraise(JZLcom/nd/schoollife/ui/common/process/PraiseListener$PRAISE_TYPE;)V
lload 1
aload 0
getfield com/nd/schoollife/ui/post/activity/PostDetailActivity$6/this$0 Lcom/nd/schoollife/ui/post/activity/PostDetailActivity;
invokestatic com/nd/schoollife/ui/post/activity/PostDetailActivity/access$1500(Lcom/nd/schoollife/ui/post/activity/PostDetailActivity;)J
lcmp
ifne L0
lload 1
ldc2_w -1L
lcmp
ifne L1
L0:
return
L1:
aload 4
getstatic com/nd/schoollife/ui/common/process/PraiseListener$PRAISE_TYPE/DETAIL Lcom/nd/schoollife/ui/common/process/PraiseListener$PRAISE_TYPE;
if_acmpeq L2
iload 3
ifeq L3
aload 0
getfield com/nd/schoollife/ui/post/activity/PostDetailActivity$6/this$0 Lcom/nd/schoollife/ui/post/activity/PostDetailActivity;
invokestatic com/nd/schoollife/ui/post/activity/PostDetailActivity/access$700(Lcom/nd/schoollife/ui/post/activity/PostDetailActivity;)Z
ifeq L0
aload 0
getfield com/nd/schoollife/ui/post/activity/PostDetailActivity$6/this$0 Lcom/nd/schoollife/ui/post/activity/PostDetailActivity;
invokevirtual com/nd/schoollife/ui/post/activity/PostDetailActivity/showPraiseIvAnim()V
aload 0
getfield com/nd/schoollife/ui/post/activity/PostDetailActivity$6/this$0 Lcom/nd/schoollife/ui/post/activity/PostDetailActivity;
invokestatic com/nd/schoollife/ui/post/activity/PostDetailActivity/access$1400(Lcom/nd/schoollife/ui/post/activity/PostDetailActivity;)Lcom/nd/android/forumsdk/business/bean/result/PostInfoBean;
invokevirtual com/nd/android/forumsdk/business/bean/result/PostInfoBean/getPraises()J
lconst_1
lsub
lstore 1
lload 1
lconst_0
lcmp
iflt L4
aload 0
getfield com/nd/schoollife/ui/post/activity/PostDetailActivity$6/this$0 Lcom/nd/schoollife/ui/post/activity/PostDetailActivity;
invokestatic com/nd/schoollife/ui/post/activity/PostDetailActivity/access$1400(Lcom/nd/schoollife/ui/post/activity/PostDetailActivity;)Lcom/nd/android/forumsdk/business/bean/result/PostInfoBean;
lload 1
invokevirtual com/nd/android/forumsdk/business/bean/result/PostInfoBean/setPraises(J)V
L4:
aload 0
getfield com/nd/schoollife/ui/post/activity/PostDetailActivity$6/this$0 Lcom/nd/schoollife/ui/post/activity/PostDetailActivity;
invokestatic com/nd/schoollife/ui/post/activity/PostDetailActivity/access$1400(Lcom/nd/schoollife/ui/post/activity/PostDetailActivity;)Lcom/nd/android/forumsdk/business/bean/result/PostInfoBean;
iconst_0
invokevirtual com/nd/android/forumsdk/business/bean/result/PostInfoBean/setPraised(I)V
return
L3:
aload 0
getfield com/nd/schoollife/ui/post/activity/PostDetailActivity$6/this$0 Lcom/nd/schoollife/ui/post/activity/PostDetailActivity;
invokestatic com/nd/schoollife/ui/post/activity/PostDetailActivity/access$700(Lcom/nd/schoollife/ui/post/activity/PostDetailActivity;)Z
ifne L0
aload 0
getfield com/nd/schoollife/ui/post/activity/PostDetailActivity$6/this$0 Lcom/nd/schoollife/ui/post/activity/PostDetailActivity;
invokevirtual com/nd/schoollife/ui/post/activity/PostDetailActivity/showPraiseIvAnim()V
aload 0
getfield com/nd/schoollife/ui/post/activity/PostDetailActivity$6/this$0 Lcom/nd/schoollife/ui/post/activity/PostDetailActivity;
invokestatic com/nd/schoollife/ui/post/activity/PostDetailActivity/access$1400(Lcom/nd/schoollife/ui/post/activity/PostDetailActivity;)Lcom/nd/android/forumsdk/business/bean/result/PostInfoBean;
aload 0
getfield com/nd/schoollife/ui/post/activity/PostDetailActivity$6/this$0 Lcom/nd/schoollife/ui/post/activity/PostDetailActivity;
invokestatic com/nd/schoollife/ui/post/activity/PostDetailActivity/access$1400(Lcom/nd/schoollife/ui/post/activity/PostDetailActivity;)Lcom/nd/android/forumsdk/business/bean/result/PostInfoBean;
invokevirtual com/nd/android/forumsdk/business/bean/result/PostInfoBean/getPraises()J
lconst_1
ladd
invokevirtual com/nd/android/forumsdk/business/bean/result/PostInfoBean/setPraises(J)V
aload 0
getfield com/nd/schoollife/ui/post/activity/PostDetailActivity$6/this$0 Lcom/nd/schoollife/ui/post/activity/PostDetailActivity;
invokestatic com/nd/schoollife/ui/post/activity/PostDetailActivity/access$1400(Lcom/nd/schoollife/ui/post/activity/PostDetailActivity;)Lcom/nd/android/forumsdk/business/bean/result/PostInfoBean;
iconst_1
invokevirtual com/nd/android/forumsdk/business/bean/result/PostInfoBean/setPraised(I)V
return
L2:
iload 3
ifne L5
aload 0
getfield com/nd/schoollife/ui/post/activity/PostDetailActivity$6/this$0 Lcom/nd/schoollife/ui/post/activity/PostDetailActivity;
invokestatic com/nd/schoollife/ui/post/activity/PostDetailActivity/access$1400(Lcom/nd/schoollife/ui/post/activity/PostDetailActivity;)Lcom/nd/android/forumsdk/business/bean/result/PostInfoBean;
aload 0
getfield com/nd/schoollife/ui/post/activity/PostDetailActivity$6/this$0 Lcom/nd/schoollife/ui/post/activity/PostDetailActivity;
invokestatic com/nd/schoollife/ui/post/activity/PostDetailActivity/access$1400(Lcom/nd/schoollife/ui/post/activity/PostDetailActivity;)Lcom/nd/android/forumsdk/business/bean/result/PostInfoBean;
invokevirtual com/nd/android/forumsdk/business/bean/result/PostInfoBean/getPraises()J
lconst_1
ladd
invokevirtual com/nd/android/forumsdk/business/bean/result/PostInfoBean/setPraises(J)V
aload 0
getfield com/nd/schoollife/ui/post/activity/PostDetailActivity$6/this$0 Lcom/nd/schoollife/ui/post/activity/PostDetailActivity;
invokestatic com/nd/schoollife/ui/post/activity/PostDetailActivity/access$1400(Lcom/nd/schoollife/ui/post/activity/PostDetailActivity;)Lcom/nd/android/forumsdk/business/bean/result/PostInfoBean;
iconst_1
invokevirtual com/nd/android/forumsdk/business/bean/result/PostInfoBean/setPraised(I)V
aload 0
getfield com/nd/schoollife/ui/post/activity/PostDetailActivity$6/this$0 Lcom/nd/schoollife/ui/post/activity/PostDetailActivity;
invokevirtual com/nd/schoollife/ui/post/activity/PostDetailActivity/showPraiseIvAnim()V
return
L5:
aload 0
getfield com/nd/schoollife/ui/post/activity/PostDetailActivity$6/this$0 Lcom/nd/schoollife/ui/post/activity/PostDetailActivity;
invokestatic com/nd/schoollife/ui/post/activity/PostDetailActivity/access$1700(Lcom/nd/schoollife/ui/post/activity/PostDetailActivity;)Landroid/content/Context;
aload 0
getfield com/nd/schoollife/ui/post/activity/PostDetailActivity$6/this$0 Lcom/nd/schoollife/ui/post/activity/PostDetailActivity;
getstatic com/nd/schoollife/R$string/str_cancel_praise_success I
invokevirtual com/nd/schoollife/ui/post/activity/PostDetailActivity/getString(I)Ljava/lang/String;
invokestatic com/nd/schoollife/common/utils/ui/ToastUtil/showShortToast(Landroid/content/Context;Ljava/lang/String;)V
return
.limit locals 5
.limit stack 5
.end method

.method public onPraise(JZLcom/nd/schoollife/ui/common/process/PraiseListener$PRAISE_TYPE;)V
lload 1
aload 0
getfield com/nd/schoollife/ui/post/activity/PostDetailActivity$6/this$0 Lcom/nd/schoollife/ui/post/activity/PostDetailActivity;
invokestatic com/nd/schoollife/ui/post/activity/PostDetailActivity/access$1500(Lcom/nd/schoollife/ui/post/activity/PostDetailActivity;)J
lcmp
ifne L0
lload 1
ldc2_w -1L
lcmp
ifne L1
L0:
return
L1:
aload 4
getstatic com/nd/schoollife/ui/common/process/PraiseListener$PRAISE_TYPE/DETAIL Lcom/nd/schoollife/ui/common/process/PraiseListener$PRAISE_TYPE;
if_acmpeq L2
iload 3
ifeq L3
aload 0
getfield com/nd/schoollife/ui/post/activity/PostDetailActivity$6/this$0 Lcom/nd/schoollife/ui/post/activity/PostDetailActivity;
invokestatic com/nd/schoollife/ui/post/activity/PostDetailActivity/access$700(Lcom/nd/schoollife/ui/post/activity/PostDetailActivity;)Z
ifne L0
aload 0
getfield com/nd/schoollife/ui/post/activity/PostDetailActivity$6/this$0 Lcom/nd/schoollife/ui/post/activity/PostDetailActivity;
invokevirtual com/nd/schoollife/ui/post/activity/PostDetailActivity/showPraiseIvAnim()V
aload 0
getfield com/nd/schoollife/ui/post/activity/PostDetailActivity$6/this$0 Lcom/nd/schoollife/ui/post/activity/PostDetailActivity;
invokestatic com/nd/schoollife/ui/post/activity/PostDetailActivity/access$1400(Lcom/nd/schoollife/ui/post/activity/PostDetailActivity;)Lcom/nd/android/forumsdk/business/bean/result/PostInfoBean;
aload 0
getfield com/nd/schoollife/ui/post/activity/PostDetailActivity$6/this$0 Lcom/nd/schoollife/ui/post/activity/PostDetailActivity;
invokestatic com/nd/schoollife/ui/post/activity/PostDetailActivity/access$1400(Lcom/nd/schoollife/ui/post/activity/PostDetailActivity;)Lcom/nd/android/forumsdk/business/bean/result/PostInfoBean;
invokevirtual com/nd/android/forumsdk/business/bean/result/PostInfoBean/getPraises()J
lconst_1
ladd
invokevirtual com/nd/android/forumsdk/business/bean/result/PostInfoBean/setPraises(J)V
aload 0
getfield com/nd/schoollife/ui/post/activity/PostDetailActivity$6/this$0 Lcom/nd/schoollife/ui/post/activity/PostDetailActivity;
invokestatic com/nd/schoollife/ui/post/activity/PostDetailActivity/access$1400(Lcom/nd/schoollife/ui/post/activity/PostDetailActivity;)Lcom/nd/android/forumsdk/business/bean/result/PostInfoBean;
iconst_1
invokevirtual com/nd/android/forumsdk/business/bean/result/PostInfoBean/setPraised(I)V
return
L3:
aload 0
getfield com/nd/schoollife/ui/post/activity/PostDetailActivity$6/this$0 Lcom/nd/schoollife/ui/post/activity/PostDetailActivity;
invokestatic com/nd/schoollife/ui/post/activity/PostDetailActivity/access$700(Lcom/nd/schoollife/ui/post/activity/PostDetailActivity;)Z
ifeq L0
aload 0
getfield com/nd/schoollife/ui/post/activity/PostDetailActivity$6/this$0 Lcom/nd/schoollife/ui/post/activity/PostDetailActivity;
invokevirtual com/nd/schoollife/ui/post/activity/PostDetailActivity/showPraiseIvAnim()V
aload 0
getfield com/nd/schoollife/ui/post/activity/PostDetailActivity$6/this$0 Lcom/nd/schoollife/ui/post/activity/PostDetailActivity;
invokestatic com/nd/schoollife/ui/post/activity/PostDetailActivity/access$1400(Lcom/nd/schoollife/ui/post/activity/PostDetailActivity;)Lcom/nd/android/forumsdk/business/bean/result/PostInfoBean;
invokevirtual com/nd/android/forumsdk/business/bean/result/PostInfoBean/getPraises()J
lconst_1
lsub
lstore 1
lload 1
lconst_0
lcmp
iflt L4
aload 0
getfield com/nd/schoollife/ui/post/activity/PostDetailActivity$6/this$0 Lcom/nd/schoollife/ui/post/activity/PostDetailActivity;
invokestatic com/nd/schoollife/ui/post/activity/PostDetailActivity/access$1400(Lcom/nd/schoollife/ui/post/activity/PostDetailActivity;)Lcom/nd/android/forumsdk/business/bean/result/PostInfoBean;
lload 1
invokevirtual com/nd/android/forumsdk/business/bean/result/PostInfoBean/setPraises(J)V
L4:
aload 0
getfield com/nd/schoollife/ui/post/activity/PostDetailActivity$6/this$0 Lcom/nd/schoollife/ui/post/activity/PostDetailActivity;
invokestatic com/nd/schoollife/ui/post/activity/PostDetailActivity/access$1400(Lcom/nd/schoollife/ui/post/activity/PostDetailActivity;)Lcom/nd/android/forumsdk/business/bean/result/PostInfoBean;
iconst_0
invokevirtual com/nd/android/forumsdk/business/bean/result/PostInfoBean/setPraised(I)V
return
L2:
iload 3
ifne L5
aload 0
getfield com/nd/schoollife/ui/post/activity/PostDetailActivity$6/this$0 Lcom/nd/schoollife/ui/post/activity/PostDetailActivity;
invokestatic com/nd/schoollife/ui/post/activity/PostDetailActivity/access$1400(Lcom/nd/schoollife/ui/post/activity/PostDetailActivity;)Lcom/nd/android/forumsdk/business/bean/result/PostInfoBean;
invokevirtual com/nd/android/forumsdk/business/bean/result/PostInfoBean/getPraises()J
lconst_1
lsub
lstore 1
lload 1
lconst_0
lcmp
iflt L6
aload 0
getfield com/nd/schoollife/ui/post/activity/PostDetailActivity$6/this$0 Lcom/nd/schoollife/ui/post/activity/PostDetailActivity;
invokestatic com/nd/schoollife/ui/post/activity/PostDetailActivity/access$1400(Lcom/nd/schoollife/ui/post/activity/PostDetailActivity;)Lcom/nd/android/forumsdk/business/bean/result/PostInfoBean;
lload 1
invokevirtual com/nd/android/forumsdk/business/bean/result/PostInfoBean/setPraises(J)V
L6:
aload 0
getfield com/nd/schoollife/ui/post/activity/PostDetailActivity$6/this$0 Lcom/nd/schoollife/ui/post/activity/PostDetailActivity;
invokestatic com/nd/schoollife/ui/post/activity/PostDetailActivity/access$1400(Lcom/nd/schoollife/ui/post/activity/PostDetailActivity;)Lcom/nd/android/forumsdk/business/bean/result/PostInfoBean;
iconst_0
invokevirtual com/nd/android/forumsdk/business/bean/result/PostInfoBean/setPraised(I)V
aload 0
getfield com/nd/schoollife/ui/post/activity/PostDetailActivity$6/this$0 Lcom/nd/schoollife/ui/post/activity/PostDetailActivity;
invokevirtual com/nd/schoollife/ui/post/activity/PostDetailActivity/showPraiseIvAnim()V
return
L5:
aload 0
getfield com/nd/schoollife/ui/post/activity/PostDetailActivity$6/this$0 Lcom/nd/schoollife/ui/post/activity/PostDetailActivity;
invokestatic com/nd/schoollife/ui/post/activity/PostDetailActivity/access$1600(Lcom/nd/schoollife/ui/post/activity/PostDetailActivity;)Landroid/content/Context;
aload 0
getfield com/nd/schoollife/ui/post/activity/PostDetailActivity$6/this$0 Lcom/nd/schoollife/ui/post/activity/PostDetailActivity;
getstatic com/nd/schoollife/R$string/str_do_praise_success I
invokevirtual com/nd/schoollife/ui/post/activity/PostDetailActivity/getString(I)Ljava/lang/String;
invokestatic com/nd/schoollife/common/utils/ui/ToastUtil/showLongToast(Landroid/content/Context;Ljava/lang/String;)V
return
.limit locals 5
.limit stack 5
.end method
