.bytecode 50.0
.class synchronized com/nd/schoollife/ui/post/activity/PostDetailActivity$7
.super java/lang/Object
.implements android/view/View$OnClickListener
.enclosing method com/nd/schoollife/ui/post/activity/PostDetailActivity/deletePost()V
.inner class inner com/nd/schoollife/ui/post/activity/PostDetailActivity$7

.field final synthetic 'this$0' Lcom/nd/schoollife/ui/post/activity/PostDetailActivity;

.method <init>(Lcom/nd/schoollife/ui/post/activity/PostDetailActivity;)V
aload 0
aload 1
putfield com/nd/schoollife/ui/post/activity/PostDetailActivity$7/this$0 Lcom/nd/schoollife/ui/post/activity/PostDetailActivity;
aload 0
invokespecial java/lang/Object/<init>()V
return
.limit locals 2
.limit stack 2
.end method

.method public onClick(Landroid/view/View;)V
aload 0
getfield com/nd/schoollife/ui/post/activity/PostDetailActivity$7/this$0 Lcom/nd/schoollife/ui/post/activity/PostDetailActivity;
invokestatic com/nd/schoollife/ui/post/activity/PostDetailActivity/access$1800(Lcom/nd/schoollife/ui/post/activity/PostDetailActivity;)Landroid/content/Context;
ifnull L0
aload 0
getfield com/nd/schoollife/ui/post/activity/PostDetailActivity$7/this$0 Lcom/nd/schoollife/ui/post/activity/PostDetailActivity;
invokestatic com/nd/schoollife/ui/post/activity/PostDetailActivity/access$1900(Lcom/nd/schoollife/ui/post/activity/PostDetailActivity;)Landroid/content/Context;
checkcast com/nd/schoollife/ui/common/activity/BaseSchoollifeActivity
invokevirtual com/nd/schoollife/ui/common/activity/BaseSchoollifeActivity/dismissConfirmDialog()V
L0:
aload 0
getfield com/nd/schoollife/ui/post/activity/PostDetailActivity$7/this$0 Lcom/nd/schoollife/ui/post/activity/PostDetailActivity;
invokevirtual com/nd/schoollife/ui/post/activity/PostDetailActivity/showLoading()V
new com/nd/schoollife/ui/post/task/PostProcessTask
dup
aload 0
getfield com/nd/schoollife/ui/post/activity/PostDetailActivity$7/this$0 Lcom/nd/schoollife/ui/post/activity/PostDetailActivity;
invokestatic com/nd/schoollife/ui/post/activity/PostDetailActivity/access$2000(Lcom/nd/schoollife/ui/post/activity/PostDetailActivity;)Landroid/content/Context;
bipush 8
getstatic com/nd/schoollife/ui/common/task/CallStyle/CALL_STYLE_SUBMIT Lcom/nd/schoollife/ui/common/task/CallStyle;
aload 0
getfield com/nd/schoollife/ui/post/activity/PostDetailActivity$7/this$0 Lcom/nd/schoollife/ui/post/activity/PostDetailActivity;
invokespecial com/nd/schoollife/ui/post/task/PostProcessTask/<init>(Landroid/content/Context;ILcom/nd/schoollife/ui/common/task/CallStyle;Lcom/nd/schoollife/ui/common/base/interfaces/AsyncTaskCallback;)V
iconst_1
anewarray java/lang/String
dup
iconst_0
new java/lang/StringBuilder
dup
invokespecial java/lang/StringBuilder/<init>()V
aload 0
getfield com/nd/schoollife/ui/post/activity/PostDetailActivity$7/this$0 Lcom/nd/schoollife/ui/post/activity/PostDetailActivity;
invokestatic com/nd/schoollife/ui/post/activity/PostDetailActivity/access$1500(Lcom/nd/schoollife/ui/post/activity/PostDetailActivity;)J
invokevirtual java/lang/StringBuilder/append(J)Ljava/lang/StringBuilder;
ldc ""
invokevirtual java/lang/StringBuilder/append(Ljava/lang/String;)Ljava/lang/StringBuilder;
invokevirtual java/lang/StringBuilder/toString()Ljava/lang/String;
aastore
invokevirtual com/nd/schoollife/ui/post/task/PostProcessTask/execute([Ljava/lang/Object;)Lcom/common/android/utils/concurrent/NdTinyHttpAsyncTask;
pop
return
.limit locals 2
.limit stack 7
.end method
