.bytecode 50.0
.class public synchronized com/nd/android/u/tast/birthday/adapter/BirthdayAdapter
.super com/product/android/ui/adapter/BaseListViewAdapter
.inner class static synthetic inner com/nd/android/u/tast/birthday/adapter/BirthdayAdapter$1
.inner class private MyClickListener inner com/nd/android/u/tast/birthday/adapter/BirthdayAdapter$MyClickListener outer com/nd/android/u/tast/birthday/adapter/BirthdayAdapter
.inner class private Task inner com/nd/android/u/tast/birthday/adapter/BirthdayAdapter$Task outer com/nd/android/u/tast/birthday/adapter/BirthdayAdapter
.inner class inner com/nd/android/u/tast/birthday/adapter/BirthdayAdapter$Task$1
.inner class private ViewHolder inner com/nd/android/u/tast/birthday/adapter/BirthdayAdapter$ViewHolder outer com/nd/android/u/tast/birthday/adapter/BirthdayAdapter

.field private 'Spacing' I

.field private 'ad' Landroid/graphics/drawable/AnimationDrawable;

.field 'display' Landroid/view/Display;

.field 'hegiht' I

.field 'iMax' I

.field 'itemWidth' I

.field private 'mContext' Landroid/content/Context;

.field private 'task' Lcom/nd/android/u/tast/birthday/adapter/BirthdayAdapter$Task;

.field 'width' I

.method public <init>(Landroid/content/Context;)V
aload 0
aload 1
aconst_null
invokespecial com/product/android/ui/adapter/BaseListViewAdapter/<init>(Landroid/content/Context;Ljava/util/ArrayList;)V
aload 0
bipush 10
putfield com/nd/android/u/tast/birthday/adapter/BirthdayAdapter/Spacing I
aload 0
aload 1
putfield com/nd/android/u/tast/birthday/adapter/BirthdayAdapter/mContext Landroid/content/Context;
aload 0
aload 0
getfield com/nd/android/u/tast/birthday/adapter/BirthdayAdapter/mContext Landroid/content/Context;
checkcast android/app/Activity
invokevirtual android/app/Activity/getWindowManager()Landroid/view/WindowManager;
invokeinterface android/view/WindowManager/getDefaultDisplay()Landroid/view/Display; 0
putfield com/nd/android/u/tast/birthday/adapter/BirthdayAdapter/display Landroid/view/Display;
aload 0
aload 0
getfield com/nd/android/u/tast/birthday/adapter/BirthdayAdapter/display Landroid/view/Display;
invokevirtual android/view/Display/getWidth()I
putfield com/nd/android/u/tast/birthday/adapter/BirthdayAdapter/width I
aload 0
aload 0
getfield com/nd/android/u/tast/birthday/adapter/BirthdayAdapter/display Landroid/view/Display;
invokevirtual android/view/Display/getHeight()I
putfield com/nd/android/u/tast/birthday/adapter/BirthdayAdapter/hegiht I
aload 0
getfield com/nd/android/u/tast/birthday/adapter/BirthdayAdapter/width I
aload 0
getfield com/nd/android/u/tast/birthday/adapter/BirthdayAdapter/hegiht I
if_icmple L0
aload 0
aload 0
getfield com/nd/android/u/tast/birthday/adapter/BirthdayAdapter/hegiht I
putfield com/nd/android/u/tast/birthday/adapter/BirthdayAdapter/iMax I
L1:
aload 0
aload 0
getfield com/nd/android/u/tast/birthday/adapter/BirthdayAdapter/iMax I
iconst_3
idiv
aload 0
getfield com/nd/android/u/tast/birthday/adapter/BirthdayAdapter/Spacing I
isub
putfield com/nd/android/u/tast/birthday/adapter/BirthdayAdapter/itemWidth I
return
L0:
aload 0
aload 0
getfield com/nd/android/u/tast/birthday/adapter/BirthdayAdapter/width I
putfield com/nd/android/u/tast/birthday/adapter/BirthdayAdapter/iMax I
goto L1
.limit locals 2
.limit stack 3
.end method

.method static synthetic access$100(Lcom/nd/android/u/tast/birthday/adapter/BirthdayAdapter;)Landroid/content/Context;
aload 0
getfield com/nd/android/u/tast/birthday/adapter/BirthdayAdapter/mContext Landroid/content/Context;
areturn
.limit locals 1
.limit stack 1
.end method

.method static synthetic access$200(Lcom/nd/android/u/tast/birthday/adapter/BirthdayAdapter;)Landroid/graphics/drawable/AnimationDrawable;
aload 0
getfield com/nd/android/u/tast/birthday/adapter/BirthdayAdapter/ad Landroid/graphics/drawable/AnimationDrawable;
areturn
.limit locals 1
.limit stack 1
.end method

.method static synthetic access$202(Lcom/nd/android/u/tast/birthday/adapter/BirthdayAdapter;Landroid/graphics/drawable/AnimationDrawable;)Landroid/graphics/drawable/AnimationDrawable;
aload 0
aload 1
putfield com/nd/android/u/tast/birthday/adapter/BirthdayAdapter/ad Landroid/graphics/drawable/AnimationDrawable;
aload 1
areturn
.limit locals 2
.limit stack 2
.end method

.method static synthetic access$300(Lcom/nd/android/u/tast/birthday/adapter/BirthdayAdapter;)Lcom/nd/android/u/tast/birthday/adapter/BirthdayAdapter$Task;
aload 0
getfield com/nd/android/u/tast/birthday/adapter/BirthdayAdapter/task Lcom/nd/android/u/tast/birthday/adapter/BirthdayAdapter$Task;
areturn
.limit locals 1
.limit stack 1
.end method

.method static synthetic access$302(Lcom/nd/android/u/tast/birthday/adapter/BirthdayAdapter;Lcom/nd/android/u/tast/birthday/adapter/BirthdayAdapter$Task;)Lcom/nd/android/u/tast/birthday/adapter/BirthdayAdapter$Task;
aload 0
aload 1
putfield com/nd/android/u/tast/birthday/adapter/BirthdayAdapter/task Lcom/nd/android/u/tast/birthday/adapter/BirthdayAdapter$Task;
aload 1
areturn
.limit locals 2
.limit stack 2
.end method

.method static synthetic access$500(Lcom/nd/android/u/tast/birthday/adapter/BirthdayAdapter;)Ljava/util/ArrayList;
aload 0
getfield com/nd/android/u/tast/birthday/adapter/BirthdayAdapter/mDataList Ljava/util/ArrayList;
areturn
.limit locals 1
.limit stack 1
.end method

.method static synthetic access$700(Lcom/nd/android/u/tast/birthday/adapter/BirthdayAdapter;)V
aload 0
invokespecial com/nd/android/u/tast/birthday/adapter/BirthdayAdapter/broadcastBlessTaskOver()V
return
.limit locals 1
.limit stack 1
.end method

.method private broadcastBlessTaskOver()V
new android/content/Intent
dup
ldc "com.nd.android.u.chat.flowertaskover"
invokespecial android/content/Intent/<init>(Ljava/lang/String;)V
astore 1
aload 1
ldc "activity_context"
aload 0
getfield com/nd/android/u/tast/birthday/adapter/BirthdayAdapter/mContext Landroid/content/Context;
invokevirtual java/lang/Object/toString()Ljava/lang/String;
invokevirtual android/content/Intent/putExtra(Ljava/lang/String;Ljava/lang/String;)Landroid/content/Intent;
pop
aload 1
ldc "task_over_type"
iconst_0
invokevirtual android/content/Intent/putExtra(Ljava/lang/String;I)Landroid/content/Intent;
pop
aload 0
getfield com/nd/android/u/tast/birthday/adapter/BirthdayAdapter/mContext Landroid/content/Context;
invokestatic android/support/v4/content/LocalBroadcastManager/getInstance(Landroid/content/Context;)Landroid/support/v4/content/LocalBroadcastManager;
aload 1
invokevirtual android/support/v4/content/LocalBroadcastManager/sendBroadcast(Landroid/content/Intent;)Z
pop
return
.limit locals 2
.limit stack 3
.end method

.method private setEvent(Lcom/nd/android/u/tast/birthday/adapter/BirthdayAdapter$ViewHolder;I)V
new com/nd/android/u/tast/birthday/adapter/BirthdayAdapter$MyClickListener
dup
aload 0
iload 2
aload 1
invokespecial com/nd/android/u/tast/birthday/adapter/BirthdayAdapter$MyClickListener/<init>(Lcom/nd/android/u/tast/birthday/adapter/BirthdayAdapter;ILcom/nd/android/u/tast/birthday/adapter/BirthdayAdapter$ViewHolder;)V
astore 3
aload 1
getfield com/nd/android/u/tast/birthday/adapter/BirthdayAdapter$ViewHolder/mImageView Landroid/widget/ImageView;
aload 3
invokevirtual android/widget/ImageView/setOnClickListener(Landroid/view/View$OnClickListener;)V
aload 1
getfield com/nd/android/u/tast/birthday/adapter/BirthdayAdapter$ViewHolder/mbtnSendFlowers Landroid/widget/Button;
aload 3
invokevirtual android/widget/Button/setOnClickListener(Landroid/view/View$OnClickListener;)V
aload 1
getfield com/nd/android/u/tast/birthday/adapter/BirthdayAdapter$ViewHolder/mtvUserNameText Landroid/widget/TextView;
aload 3
invokevirtual android/widget/TextView/setOnClickListener(Landroid/view/View$OnClickListener;)V
aload 1
getfield com/nd/android/u/tast/birthday/adapter/BirthdayAdapter$ViewHolder/mtvDepartNameText Landroid/widget/TextView;
aload 3
invokevirtual android/widget/TextView/setOnClickListener(Landroid/view/View$OnClickListener;)V
aload 1
getfield com/nd/android/u/tast/birthday/adapter/BirthdayAdapter$ViewHolder/mrlBottom Landroid/widget/RelativeLayout;
aload 3
invokevirtual android/widget/RelativeLayout/setOnClickListener(Landroid/view/View$OnClickListener;)V
aload 1
getfield com/nd/android/u/tast/birthday/adapter/BirthdayAdapter$ViewHolder/mbtnBless Landroid/widget/Button;
aload 3
invokevirtual android/widget/Button/setOnClickListener(Landroid/view/View$OnClickListener;)V
return
.limit locals 4
.limit stack 5
.end method

.method private setValue(Lcom/nd/android/u/tast/birthday/adapter/BirthdayAdapter$ViewHolder;Lcom/nd/android/u/tast/birthday/dataStructure/Birthuserlist;)V
aload 1
aload 2
invokevirtual com/nd/android/u/tast/birthday/dataStructure/Birthuserlist/getUid()J
putfield com/nd/android/u/tast/birthday/adapter/BirthdayAdapter$ViewHolder/uid J
aload 2
invokevirtual com/nd/android/u/tast/birthday/dataStructure/Birthuserlist/getUid()J
aload 2
invokevirtual com/nd/android/u/tast/birthday/dataStructure/Birthuserlist/getSysAvatarId()I
aload 1
getfield com/nd/android/u/tast/birthday/adapter/BirthdayAdapter$ViewHolder/mImageView Landroid/widget/ImageView;
invokestatic com/product/android/business/headImage/HeadImageLoader/displayImage(JILandroid/widget/ImageView;)V
aload 1
getfield com/nd/android/u/tast/birthday/adapter/BirthdayAdapter$ViewHolder/mImageView Landroid/widget/ImageView;
invokevirtual android/widget/ImageView/getLayoutParams()Landroid/view/ViewGroup$LayoutParams;
checkcast android/widget/RelativeLayout$LayoutParams
astore 3
aload 3
ifnull L0
aload 1
getfield com/nd/android/u/tast/birthday/adapter/BirthdayAdapter$ViewHolder/mImageView Landroid/widget/ImageView;
invokevirtual android/widget/ImageView/getLayoutParams()Landroid/view/ViewGroup$LayoutParams;
aload 0
getfield com/nd/android/u/tast/birthday/adapter/BirthdayAdapter/itemWidth I
bipush 10
isub
putfield android/view/ViewGroup$LayoutParams/width I
aload 1
getfield com/nd/android/u/tast/birthday/adapter/BirthdayAdapter$ViewHolder/mImageView Landroid/widget/ImageView;
invokevirtual android/widget/ImageView/getLayoutParams()Landroid/view/ViewGroup$LayoutParams;
aload 1
getfield com/nd/android/u/tast/birthday/adapter/BirthdayAdapter$ViewHolder/mImageView Landroid/widget/ImageView;
invokevirtual android/widget/ImageView/getLayoutParams()Landroid/view/ViewGroup$LayoutParams;
getfield android/view/ViewGroup$LayoutParams/width I
putfield android/view/ViewGroup$LayoutParams/height I
aload 3
iconst_5
putfield android/widget/RelativeLayout$LayoutParams/topMargin I
aload 1
getfield com/nd/android/u/tast/birthday/adapter/BirthdayAdapter$ViewHolder/mImageView Landroid/widget/ImageView;
aload 3
invokevirtual android/widget/ImageView/setLayoutParams(Landroid/view/ViewGroup$LayoutParams;)V
L0:
aload 1
getfield com/nd/android/u/tast/birthday/adapter/BirthdayAdapter$ViewHolder/mtvUserNameText Landroid/widget/TextView;
aload 2
invokevirtual com/nd/android/u/tast/birthday/dataStructure/Birthuserlist/getUsername()Ljava/lang/String;
invokevirtual android/widget/TextView/setText(Ljava/lang/CharSequence;)V
aload 2
invokevirtual com/nd/android/u/tast/birthday/dataStructure/Birthuserlist/getDeptname()Ljava/lang/String;
ifnull L1
aload 2
invokevirtual com/nd/android/u/tast/birthday/dataStructure/Birthuserlist/getDeptname()Ljava/lang/String;
ldc ""
invokevirtual java/lang/String/equals(Ljava/lang/Object;)Z
ifeq L2
L1:
aload 1
getfield com/nd/android/u/tast/birthday/adapter/BirthdayAdapter$ViewHolder/mtvDepartNameText Landroid/widget/TextView;
bipush 8
invokevirtual android/widget/TextView/setVisibility(I)V
L3:
aload 1
getfield com/nd/android/u/tast/birthday/adapter/BirthdayAdapter$ViewHolder/mtvBlessedCount Landroid/widget/TextView;
new java/lang/StringBuilder
dup
invokespecial java/lang/StringBuilder/<init>()V
ldc ""
invokevirtual java/lang/StringBuilder/append(Ljava/lang/String;)Ljava/lang/StringBuilder;
aload 2
invokevirtual com/nd/android/u/tast/birthday/dataStructure/Birthuserlist/getBlesscount()J
invokevirtual java/lang/StringBuilder/append(J)Ljava/lang/StringBuilder;
invokevirtual java/lang/StringBuilder/toString()Ljava/lang/String;
invokevirtual android/widget/TextView/setText(Ljava/lang/CharSequence;)V
aload 2
invokevirtual com/nd/android/u/tast/birthday/dataStructure/Birthuserlist/getIsblessed()J
lconst_1
lcmp
ifne L4
aload 1
getfield com/nd/android/u/tast/birthday/adapter/BirthdayAdapter$ViewHolder/mbtnBless Landroid/widget/Button;
bipush 8
invokevirtual android/widget/Button/setVisibility(I)V
aload 1
getfield com/nd/android/u/tast/birthday/adapter/BirthdayAdapter$ViewHolder/mbtnSendFlowers Landroid/widget/Button;
iconst_0
invokevirtual android/widget/Button/setVisibility(I)V
aload 1
getfield com/nd/android/u/tast/birthday/adapter/BirthdayAdapter$ViewHolder/mivHeart Landroid/widget/ImageView;
iconst_0
invokevirtual android/widget/ImageView/setVisibility(I)V
aload 1
getfield com/nd/android/u/tast/birthday/adapter/BirthdayAdapter$ViewHolder/mivHeart Landroid/widget/ImageView;
getstatic com/nd/android/u/tasklib/R$drawable/bless_heart_4 I
invokevirtual android/widget/ImageView/setBackgroundResource(I)V
L5:
aload 2
invokevirtual com/nd/android/u/tast/birthday/dataStructure/Birthuserlist/getBlesscount()J
lconst_1
lcmp
ifge L6
aload 1
getfield com/nd/android/u/tast/birthday/adapter/BirthdayAdapter$ViewHolder/mrlBlessCount Landroid/widget/RelativeLayout;
bipush 8
invokevirtual android/widget/RelativeLayout/setVisibility(I)V
L7:
aload 2
invokevirtual com/nd/android/u/tast/birthday/dataStructure/Birthuserlist/getUid()J
getstatic com/product/android/business/ApplicationVariable/INSTANCE Lcom/product/android/business/ApplicationVariable;
invokevirtual com/product/android/business/ApplicationVariable/getIUser()Lcom/product/android/business/login/IGetUserInfo;
invokeinterface com/product/android/business/login/IGetUserInfo/getOapUid()J 0
lcmp
ifne L8
aload 1
getfield com/nd/android/u/tast/birthday/adapter/BirthdayAdapter$ViewHolder/mbtnBless Landroid/widget/Button;
bipush 8
invokevirtual android/widget/Button/setVisibility(I)V
aload 1
getfield com/nd/android/u/tast/birthday/adapter/BirthdayAdapter$ViewHolder/mbtnSendFlowers Landroid/widget/Button;
bipush 8
invokevirtual android/widget/Button/setVisibility(I)V
aload 1
getfield com/nd/android/u/tast/birthday/adapter/BirthdayAdapter$ViewHolder/tvHappyBirthday Landroid/widget/TextView;
iconst_0
invokevirtual android/widget/TextView/setVisibility(I)V
return
L2:
aload 1
getfield com/nd/android/u/tast/birthday/adapter/BirthdayAdapter$ViewHolder/mtvDepartNameText Landroid/widget/TextView;
aload 2
invokevirtual com/nd/android/u/tast/birthday/dataStructure/Birthuserlist/getDeptname()Ljava/lang/String;
invokevirtual android/widget/TextView/setText(Ljava/lang/CharSequence;)V
goto L3
L4:
aload 1
getfield com/nd/android/u/tast/birthday/adapter/BirthdayAdapter$ViewHolder/mivHeart Landroid/widget/ImageView;
bipush 8
invokevirtual android/widget/ImageView/setVisibility(I)V
aload 1
getfield com/nd/android/u/tast/birthday/adapter/BirthdayAdapter$ViewHolder/mbtnBless Landroid/widget/Button;
iconst_0
invokevirtual android/widget/Button/setVisibility(I)V
aload 1
getfield com/nd/android/u/tast/birthday/adapter/BirthdayAdapter$ViewHolder/mbtnSendFlowers Landroid/widget/Button;
bipush 8
invokevirtual android/widget/Button/setVisibility(I)V
goto L5
L6:
aload 1
getfield com/nd/android/u/tast/birthday/adapter/BirthdayAdapter$ViewHolder/mrlBlessCount Landroid/widget/RelativeLayout;
iconst_0
invokevirtual android/widget/RelativeLayout/setVisibility(I)V
goto L7
L8:
aload 1
getfield com/nd/android/u/tast/birthday/adapter/BirthdayAdapter$ViewHolder/tvHappyBirthday Landroid/widget/TextView;
bipush 8
invokevirtual android/widget/TextView/setVisibility(I)V
return
.limit locals 4
.limit stack 4
.end method

.method public blessFail(Lcom/nd/android/u/tast/birthday/adapter/BirthdayAdapter$ViewHolder;IJI)V
aload 1
getfield com/nd/android/u/tast/birthday/adapter/BirthdayAdapter$ViewHolder/mtvBlessedCount Landroid/widget/TextView;
invokevirtual android/widget/TextView/getText()Ljava/lang/CharSequence;
invokeinterface java/lang/CharSequence/toString()Ljava/lang/String; 0
astore 8
iconst_0
istore 6
aload 8
invokestatic com/common/android/utils/StringUtils/isNumeric(Ljava/lang/String;)Z
ifeq L0
aload 8
invokestatic java/lang/Integer/parseInt(Ljava/lang/String;)I
iconst_1
isub
istore 6
L0:
iload 6
istore 7
iload 6
ifge L1
iconst_0
istore 7
L1:
aload 0
iload 5
invokevirtual com/nd/android/u/tast/birthday/adapter/BirthdayAdapter/getItem(I)Lcom/nd/android/u/tast/birthday/dataStructure/Birthuserlist;
iload 7
i2l
invokevirtual com/nd/android/u/tast/birthday/dataStructure/Birthuserlist/setBlesscount(J)V
aload 0
iload 5
invokevirtual com/nd/android/u/tast/birthday/adapter/BirthdayAdapter/getItem(I)Lcom/nd/android/u/tast/birthday/dataStructure/Birthuserlist;
lconst_0
invokevirtual com/nd/android/u/tast/birthday/dataStructure/Birthuserlist/setIsblessed(J)V
aload 1
getfield com/nd/android/u/tast/birthday/adapter/BirthdayAdapter$ViewHolder/uid J
lload 3
lcmp
ifeq L2
L3:
return
L2:
aload 1
getfield com/nd/android/u/tast/birthday/adapter/BirthdayAdapter$ViewHolder/mtvBlessedCount Landroid/widget/TextView;
new java/lang/StringBuilder
dup
invokespecial java/lang/StringBuilder/<init>()V
ldc ""
invokevirtual java/lang/StringBuilder/append(Ljava/lang/String;)Ljava/lang/StringBuilder;
iload 7
invokevirtual java/lang/StringBuilder/append(I)Ljava/lang/StringBuilder;
invokevirtual java/lang/StringBuilder/toString()Ljava/lang/String;
invokevirtual android/widget/TextView/setText(Ljava/lang/CharSequence;)V
iload 2
iconst_1
if_icmpne L4
aload 0
getfield com/nd/android/u/tast/birthday/adapter/BirthdayAdapter/mContext Landroid/content/Context;
getstatic com/nd/android/u/tasklib/R$string/blessing_fail_double I
invokestatic com/common/android/utils/ToastUtils/display(Landroid/content/Context;I)V
aload 1
getfield com/nd/android/u/tast/birthday/adapter/BirthdayAdapter$ViewHolder/mbtnBless Landroid/widget/Button;
bipush 8
invokevirtual android/widget/Button/setVisibility(I)V
aload 1
getfield com/nd/android/u/tast/birthday/adapter/BirthdayAdapter$ViewHolder/mbtnSendFlowers Landroid/widget/Button;
iconst_0
invokevirtual android/widget/Button/setVisibility(I)V
aload 1
getfield com/nd/android/u/tast/birthday/adapter/BirthdayAdapter$ViewHolder/mivHeart Landroid/widget/ImageView;
iconst_0
invokevirtual android/widget/ImageView/setVisibility(I)V
return
L4:
iload 2
iconst_2
if_icmpne L3
aload 0
getfield com/nd/android/u/tast/birthday/adapter/BirthdayAdapter/mContext Landroid/content/Context;
getstatic com/nd/android/u/tasklib/R$string/blessing_fail I
invokestatic com/common/android/utils/ToastUtils/display(Landroid/content/Context;I)V
aload 1
getfield com/nd/android/u/tast/birthday/adapter/BirthdayAdapter$ViewHolder/mbtnBless Landroid/widget/Button;
iconst_0
invokevirtual android/widget/Button/setVisibility(I)V
aload 1
getfield com/nd/android/u/tast/birthday/adapter/BirthdayAdapter$ViewHolder/mbtnSendFlowers Landroid/widget/Button;
bipush 8
invokevirtual android/widget/Button/setVisibility(I)V
iload 7
iconst_1
if_icmpge L5
aload 1
getfield com/nd/android/u/tast/birthday/adapter/BirthdayAdapter$ViewHolder/mrlBlessCount Landroid/widget/RelativeLayout;
bipush 8
invokevirtual android/widget/RelativeLayout/setVisibility(I)V
L5:
aload 1
getfield com/nd/android/u/tast/birthday/adapter/BirthdayAdapter$ViewHolder/mivHeart Landroid/widget/ImageView;
bipush 8
invokevirtual android/widget/ImageView/setVisibility(I)V
aload 1
getfield com/nd/android/u/tast/birthday/adapter/BirthdayAdapter$ViewHolder/mbtnBless Landroid/widget/Button;
iconst_1
invokevirtual android/widget/Button/setClickable(Z)V
return
.limit locals 9
.limit stack 4
.end method

.method public getCount()I
aload 0
getfield com/nd/android/u/tast/birthday/adapter/BirthdayAdapter/mDataList Ljava/util/ArrayList;
invokevirtual java/util/ArrayList/size()I
ireturn
.limit locals 1
.limit stack 1
.end method

.method public getItem(I)Lcom/nd/android/u/tast/birthday/dataStructure/Birthuserlist;
aload 0
getfield com/nd/android/u/tast/birthday/adapter/BirthdayAdapter/mDataList Ljava/util/ArrayList;
iload 1
invokevirtual java/util/ArrayList/get(I)Ljava/lang/Object;
checkcast com/nd/android/u/tast/birthday/dataStructure/Birthuserlist
areturn
.limit locals 2
.limit stack 2
.end method

.method public volatile synthetic getItem(I)Ljava/lang/Object;
aload 0
iload 1
invokevirtual com/nd/android/u/tast/birthday/adapter/BirthdayAdapter/getItem(I)Lcom/nd/android/u/tast/birthday/dataStructure/Birthuserlist;
areturn
.limit locals 2
.limit stack 2
.end method

.method public getItemId(I)J
iload 1
i2l
lreturn
.limit locals 2
.limit stack 2
.end method

.method public getView(ILandroid/view/View;Landroid/view/ViewGroup;)Landroid/view/View;
aload 2
ifnonnull L0
new com/nd/android/u/tast/birthday/adapter/BirthdayAdapter$ViewHolder
dup
aload 0
aconst_null
invokespecial com/nd/android/u/tast/birthday/adapter/BirthdayAdapter$ViewHolder/<init>(Lcom/nd/android/u/tast/birthday/adapter/BirthdayAdapter;Lcom/nd/android/u/tast/birthday/adapter/BirthdayAdapter$1;)V
astore 3
aload 0
getfield com/nd/android/u/tast/birthday/adapter/BirthdayAdapter/mContext Landroid/content/Context;
invokestatic android/view/LayoutInflater/from(Landroid/content/Context;)Landroid/view/LayoutInflater;
getstatic com/nd/android/u/tasklib/R$layout/flowviewbirthday_item I
aconst_null
invokevirtual android/view/LayoutInflater/inflate(ILandroid/view/ViewGroup;)Landroid/view/View;
astore 2
aload 3
aload 2
getstatic com/nd/android/u/tasklib/R$id/rl_bless_count I
invokevirtual android/view/View/findViewById(I)Landroid/view/View;
checkcast android/widget/RelativeLayout
putfield com/nd/android/u/tast/birthday/adapter/BirthdayAdapter$ViewHolder/mrlBlessCount Landroid/widget/RelativeLayout;
aload 3
aload 2
getstatic com/nd/android/u/tasklib/R$id/flowview_bottom_layout I
invokevirtual android/view/View/findViewById(I)Landroid/view/View;
checkcast android/widget/RelativeLayout
putfield com/nd/android/u/tast/birthday/adapter/BirthdayAdapter$ViewHolder/mrlBottom Landroid/widget/RelativeLayout;
aload 3
aload 2
getstatic com/nd/android/u/tasklib/R$id/iv_heart I
invokevirtual android/view/View/findViewById(I)Landroid/view/View;
checkcast android/widget/ImageView
putfield com/nd/android/u/tast/birthday/adapter/BirthdayAdapter$ViewHolder/mivHeart Landroid/widget/ImageView;
aload 3
aload 2
getstatic com/nd/android/u/tasklib/R$id/tv_bless_count I
invokevirtual android/view/View/findViewById(I)Landroid/view/View;
checkcast android/widget/TextView
putfield com/nd/android/u/tast/birthday/adapter/BirthdayAdapter$ViewHolder/mtvBlessedCount Landroid/widget/TextView;
aload 3
aload 2
getstatic com/nd/android/u/tasklib/R$id/flowview_item_text_name I
invokevirtual android/view/View/findViewById(I)Landroid/view/View;
checkcast android/widget/TextView
putfield com/nd/android/u/tast/birthday/adapter/BirthdayAdapter$ViewHolder/mtvUserNameText Landroid/widget/TextView;
aload 3
aload 2
getstatic com/nd/android/u/tasklib/R$id/flowview_item_image I
invokevirtual android/view/View/findViewById(I)Landroid/view/View;
checkcast android/widget/ImageView
putfield com/nd/android/u/tast/birthday/adapter/BirthdayAdapter$ViewHolder/mImageView Landroid/widget/ImageView;
aload 3
aload 2
getstatic com/nd/android/u/tasklib/R$id/flowview_item_text_departname I
invokevirtual android/view/View/findViewById(I)Landroid/view/View;
checkcast android/widget/TextView
putfield com/nd/android/u/tast/birthday/adapter/BirthdayAdapter$ViewHolder/mtvDepartNameText Landroid/widget/TextView;
aload 3
aload 2
getstatic com/nd/android/u/tasklib/R$id/btn_bless I
invokevirtual android/view/View/findViewById(I)Landroid/view/View;
checkcast android/widget/Button
putfield com/nd/android/u/tast/birthday/adapter/BirthdayAdapter$ViewHolder/mbtnBless Landroid/widget/Button;
aload 3
aload 2
getstatic com/nd/android/u/tasklib/R$id/btn_send_flowers I
invokevirtual android/view/View/findViewById(I)Landroid/view/View;
checkcast android/widget/Button
putfield com/nd/android/u/tast/birthday/adapter/BirthdayAdapter$ViewHolder/mbtnSendFlowers Landroid/widget/Button;
aload 3
aload 2
getstatic com/nd/android/u/tasklib/R$id/tv_happy_birthday I
invokevirtual android/view/View/findViewById(I)Landroid/view/View;
checkcast android/widget/TextView
putfield com/nd/android/u/tast/birthday/adapter/BirthdayAdapter$ViewHolder/tvHappyBirthday Landroid/widget/TextView;
aload 2
aload 3
invokevirtual android/view/View/setTag(Ljava/lang/Object;)V
L1:
aload 0
aload 3
iload 1
invokespecial com/nd/android/u/tast/birthday/adapter/BirthdayAdapter/setEvent(Lcom/nd/android/u/tast/birthday/adapter/BirthdayAdapter$ViewHolder;I)V
aload 0
aload 3
aload 0
iload 1
invokevirtual com/nd/android/u/tast/birthday/adapter/BirthdayAdapter/getItem(I)Lcom/nd/android/u/tast/birthday/dataStructure/Birthuserlist;
invokespecial com/nd/android/u/tast/birthday/adapter/BirthdayAdapter/setValue(Lcom/nd/android/u/tast/birthday/adapter/BirthdayAdapter$ViewHolder;Lcom/nd/android/u/tast/birthday/dataStructure/Birthuserlist;)V
aload 2
areturn
L0:
aload 2
invokevirtual android/view/View/getTag()Ljava/lang/Object;
checkcast com/nd/android/u/tast/birthday/adapter/BirthdayAdapter$ViewHolder
astore 3
goto L1
.limit locals 4
.limit stack 4
.end method

.method public refreshItem(JI)V
iconst_0
istore 4
L0:
iload 4
aload 0
getfield com/nd/android/u/tast/birthday/adapter/BirthdayAdapter/mDataList Ljava/util/ArrayList;
invokevirtual java/util/ArrayList/size()I
if_icmpge L1
aload 0
getfield com/nd/android/u/tast/birthday/adapter/BirthdayAdapter/mDataList Ljava/util/ArrayList;
iload 4
invokevirtual java/util/ArrayList/get(I)Ljava/lang/Object;
checkcast com/nd/android/u/tast/birthday/dataStructure/Birthuserlist
invokevirtual com/nd/android/u/tast/birthday/dataStructure/Birthuserlist/getUid()J
lload 1
lcmp
ifne L2
aload 0
getfield com/nd/android/u/tast/birthday/adapter/BirthdayAdapter/mDataList Ljava/util/ArrayList;
iload 4
invokevirtual java/util/ArrayList/get(I)Ljava/lang/Object;
checkcast com/nd/android/u/tast/birthday/dataStructure/Birthuserlist
invokevirtual com/nd/android/u/tast/birthday/dataStructure/Birthuserlist/getBlesscount()J
iload 3
i2l
lcmp
ifge L2
aload 0
getfield com/nd/android/u/tast/birthday/adapter/BirthdayAdapter/mDataList Ljava/util/ArrayList;
iload 4
invokevirtual java/util/ArrayList/get(I)Ljava/lang/Object;
checkcast com/nd/android/u/tast/birthday/dataStructure/Birthuserlist
iload 3
i2l
invokevirtual com/nd/android/u/tast/birthday/dataStructure/Birthuserlist/setBlesscount(J)V
aload 0
getfield com/nd/android/u/tast/birthday/adapter/BirthdayAdapter/mDataList Ljava/util/ArrayList;
iload 4
invokevirtual java/util/ArrayList/get(I)Ljava/lang/Object;
checkcast com/nd/android/u/tast/birthday/dataStructure/Birthuserlist
lconst_1
invokevirtual com/nd/android/u/tast/birthday/dataStructure/Birthuserlist/setIsblessed(J)V
aload 0
invokevirtual com/nd/android/u/tast/birthday/adapter/BirthdayAdapter/notifyDataSetChanged()V
L2:
iload 4
iconst_1
iadd
istore 4
goto L0
L1:
return
.limit locals 5
.limit stack 4
.end method
