.bytecode 50.0
.class synchronized com/nd/android/u/tast/birthday/adapter/BirthdayAdapter$MyClickListener
.super java/lang/Object
.implements android/view/View$OnClickListener
.inner class private MyClickListener inner com/nd/android/u/tast/birthday/adapter/BirthdayAdapter$MyClickListener outer com/nd/android/u/tast/birthday/adapter/BirthdayAdapter

.field private 'mHolder' Lcom/nd/android/u/tast/birthday/adapter/BirthdayAdapter$ViewHolder;

.field private 'mPosition' I

.field final synthetic 'this$0' Lcom/nd/android/u/tast/birthday/adapter/BirthdayAdapter;

.method public <init>(Lcom/nd/android/u/tast/birthday/adapter/BirthdayAdapter;ILcom/nd/android/u/tast/birthday/adapter/BirthdayAdapter$ViewHolder;)V
aload 0
aload 1
putfield com/nd/android/u/tast/birthday/adapter/BirthdayAdapter$MyClickListener/this$0 Lcom/nd/android/u/tast/birthday/adapter/BirthdayAdapter;
aload 0
invokespecial java/lang/Object/<init>()V
aload 0
iload 2
putfield com/nd/android/u/tast/birthday/adapter/BirthdayAdapter$MyClickListener/mPosition I
aload 0
aload 3
putfield com/nd/android/u/tast/birthday/adapter/BirthdayAdapter$MyClickListener/mHolder Lcom/nd/android/u/tast/birthday/adapter/BirthdayAdapter$ViewHolder;
return
.limit locals 4
.limit stack 2
.end method

.method private clickHotArea()V
aload 0
getfield com/nd/android/u/tast/birthday/adapter/BirthdayAdapter$MyClickListener/mHolder Lcom/nd/android/u/tast/birthday/adapter/BirthdayAdapter$ViewHolder;
getfield com/nd/android/u/tast/birthday/adapter/BirthdayAdapter$ViewHolder/mbtnBless Landroid/widget/Button;
invokevirtual android/widget/Button/getVisibility()I
ifne L0
aload 0
invokespecial com/nd/android/u/tast/birthday/adapter/BirthdayAdapter$MyClickListener/doBelss()V
L1:
return
L0:
aload 0
getfield com/nd/android/u/tast/birthday/adapter/BirthdayAdapter$MyClickListener/mHolder Lcom/nd/android/u/tast/birthday/adapter/BirthdayAdapter$ViewHolder;
getfield com/nd/android/u/tast/birthday/adapter/BirthdayAdapter$ViewHolder/mbtnSendFlowers Landroid/widget/Button;
invokevirtual android/widget/Button/getVisibility()I
ifne L1
aload 0
getfield com/nd/android/u/tast/birthday/adapter/BirthdayAdapter$MyClickListener/this$0 Lcom/nd/android/u/tast/birthday/adapter/BirthdayAdapter;
invokestatic com/nd/android/u/tast/birthday/adapter/BirthdayAdapter/access$100(Lcom/nd/android/u/tast/birthday/adapter/BirthdayAdapter;)Landroid/content/Context;
aload 0
getfield com/nd/android/u/tast/birthday/adapter/BirthdayAdapter$MyClickListener/this$0 Lcom/nd/android/u/tast/birthday/adapter/BirthdayAdapter;
aload 0
getfield com/nd/android/u/tast/birthday/adapter/BirthdayAdapter$MyClickListener/mPosition I
invokevirtual com/nd/android/u/tast/birthday/adapter/BirthdayAdapter/getItem(I)Lcom/nd/android/u/tast/birthday/dataStructure/Birthuserlist;
invokevirtual com/nd/android/u/tast/birthday/dataStructure/Birthuserlist/getUid()J
invokestatic com/nd/android/u/tast/taskInterfaceImpl/TaskCallOtherModel/sendFlowers(Landroid/content/Context;J)V
return
.limit locals 1
.limit stack 3
.end method

.method private doBelss()V
aload 0
getfield com/nd/android/u/tast/birthday/adapter/BirthdayAdapter$MyClickListener/mHolder Lcom/nd/android/u/tast/birthday/adapter/BirthdayAdapter$ViewHolder;
getfield com/nd/android/u/tast/birthday/adapter/BirthdayAdapter$ViewHolder/mrlBlessCount Landroid/widget/RelativeLayout;
invokevirtual android/widget/RelativeLayout/getVisibility()I
bipush 8
if_icmpeq L0
aload 0
getfield com/nd/android/u/tast/birthday/adapter/BirthdayAdapter$MyClickListener/mHolder Lcom/nd/android/u/tast/birthday/adapter/BirthdayAdapter$ViewHolder;
getfield com/nd/android/u/tast/birthday/adapter/BirthdayAdapter$ViewHolder/mrlBlessCount Landroid/widget/RelativeLayout;
invokevirtual android/widget/RelativeLayout/getVisibility()I
iconst_4
if_icmpne L1
L0:
aload 0
getfield com/nd/android/u/tast/birthday/adapter/BirthdayAdapter$MyClickListener/mHolder Lcom/nd/android/u/tast/birthday/adapter/BirthdayAdapter$ViewHolder;
getfield com/nd/android/u/tast/birthday/adapter/BirthdayAdapter$ViewHolder/mrlBlessCount Landroid/widget/RelativeLayout;
iconst_0
invokevirtual android/widget/RelativeLayout/setVisibility(I)V
L1:
aload 0
getfield com/nd/android/u/tast/birthday/adapter/BirthdayAdapter$MyClickListener/mHolder Lcom/nd/android/u/tast/birthday/adapter/BirthdayAdapter$ViewHolder;
getfield com/nd/android/u/tast/birthday/adapter/BirthdayAdapter$ViewHolder/mbtnBless Landroid/widget/Button;
bipush 8
invokevirtual android/widget/Button/setVisibility(I)V
aload 0
getfield com/nd/android/u/tast/birthday/adapter/BirthdayAdapter$MyClickListener/mHolder Lcom/nd/android/u/tast/birthday/adapter/BirthdayAdapter$ViewHolder;
getfield com/nd/android/u/tast/birthday/adapter/BirthdayAdapter$ViewHolder/mbtnSendFlowers Landroid/widget/Button;
iconst_0
invokevirtual android/widget/Button/setVisibility(I)V
aload 0
getfield com/nd/android/u/tast/birthday/adapter/BirthdayAdapter$MyClickListener/mHolder Lcom/nd/android/u/tast/birthday/adapter/BirthdayAdapter$ViewHolder;
getfield com/nd/android/u/tast/birthday/adapter/BirthdayAdapter$ViewHolder/mivHeart Landroid/widget/ImageView;
iconst_0
invokevirtual android/widget/ImageView/setVisibility(I)V
aload 0
getfield com/nd/android/u/tast/birthday/adapter/BirthdayAdapter$MyClickListener/mHolder Lcom/nd/android/u/tast/birthday/adapter/BirthdayAdapter$ViewHolder;
getfield com/nd/android/u/tast/birthday/adapter/BirthdayAdapter$ViewHolder/mtvBlessedCount Landroid/widget/TextView;
invokevirtual android/widget/TextView/getText()Ljava/lang/CharSequence;
invokeinterface java/lang/CharSequence/toString()Ljava/lang/String; 0
astore 2
iconst_0
istore 1
aload 2
invokestatic com/common/android/utils/StringUtils/isNumeric(Ljava/lang/String;)Z
ifeq L2
aload 2
invokestatic java/lang/Integer/parseInt(Ljava/lang/String;)I
iconst_1
iadd
istore 1
L2:
aload 0
getfield com/nd/android/u/tast/birthday/adapter/BirthdayAdapter$MyClickListener/mHolder Lcom/nd/android/u/tast/birthday/adapter/BirthdayAdapter$ViewHolder;
getfield com/nd/android/u/tast/birthday/adapter/BirthdayAdapter$ViewHolder/mtvBlessedCount Landroid/widget/TextView;
new java/lang/StringBuilder
dup
invokespecial java/lang/StringBuilder/<init>()V
ldc ""
invokevirtual java/lang/StringBuilder/append(Ljava/lang/String;)Ljava/lang/StringBuilder;
iload 1
invokevirtual java/lang/StringBuilder/append(I)Ljava/lang/StringBuilder;
invokevirtual java/lang/StringBuilder/toString()Ljava/lang/String;
invokevirtual android/widget/TextView/setText(Ljava/lang/CharSequence;)V
aload 0
getfield com/nd/android/u/tast/birthday/adapter/BirthdayAdapter$MyClickListener/this$0 Lcom/nd/android/u/tast/birthday/adapter/BirthdayAdapter;
aload 0
getfield com/nd/android/u/tast/birthday/adapter/BirthdayAdapter$MyClickListener/mPosition I
invokevirtual com/nd/android/u/tast/birthday/adapter/BirthdayAdapter/getItem(I)Lcom/nd/android/u/tast/birthday/dataStructure/Birthuserlist;
iload 1
i2l
invokevirtual com/nd/android/u/tast/birthday/dataStructure/Birthuserlist/setBlesscount(J)V
aload 0
getfield com/nd/android/u/tast/birthday/adapter/BirthdayAdapter$MyClickListener/this$0 Lcom/nd/android/u/tast/birthday/adapter/BirthdayAdapter;
aload 0
getfield com/nd/android/u/tast/birthday/adapter/BirthdayAdapter$MyClickListener/mPosition I
invokevirtual com/nd/android/u/tast/birthday/adapter/BirthdayAdapter/getItem(I)Lcom/nd/android/u/tast/birthday/dataStructure/Birthuserlist;
lconst_1
invokevirtual com/nd/android/u/tast/birthday/dataStructure/Birthuserlist/setIsblessed(J)V
aload 0
getfield com/nd/android/u/tast/birthday/adapter/BirthdayAdapter$MyClickListener/mHolder Lcom/nd/android/u/tast/birthday/adapter/BirthdayAdapter$ViewHolder;
getfield com/nd/android/u/tast/birthday/adapter/BirthdayAdapter$ViewHolder/mivHeart Landroid/widget/ImageView;
getstatic com/nd/android/u/tasklib/R$anim/bless I
invokevirtual android/widget/ImageView/setBackgroundResource(I)V
aload 0
getfield com/nd/android/u/tast/birthday/adapter/BirthdayAdapter$MyClickListener/this$0 Lcom/nd/android/u/tast/birthday/adapter/BirthdayAdapter;
aload 0
getfield com/nd/android/u/tast/birthday/adapter/BirthdayAdapter$MyClickListener/mHolder Lcom/nd/android/u/tast/birthday/adapter/BirthdayAdapter$ViewHolder;
getfield com/nd/android/u/tast/birthday/adapter/BirthdayAdapter$ViewHolder/mivHeart Landroid/widget/ImageView;
invokevirtual android/widget/ImageView/getBackground()Landroid/graphics/drawable/Drawable;
checkcast android/graphics/drawable/AnimationDrawable
invokestatic com/nd/android/u/tast/birthday/adapter/BirthdayAdapter/access$202(Lcom/nd/android/u/tast/birthday/adapter/BirthdayAdapter;Landroid/graphics/drawable/AnimationDrawable;)Landroid/graphics/drawable/AnimationDrawable;
pop
aload 0
getfield com/nd/android/u/tast/birthday/adapter/BirthdayAdapter$MyClickListener/this$0 Lcom/nd/android/u/tast/birthday/adapter/BirthdayAdapter;
invokestatic com/nd/android/u/tast/birthday/adapter/BirthdayAdapter/access$200(Lcom/nd/android/u/tast/birthday/adapter/BirthdayAdapter;)Landroid/graphics/drawable/AnimationDrawable;
invokevirtual android/graphics/drawable/AnimationDrawable/start()V
aload 0
getfield com/nd/android/u/tast/birthday/adapter/BirthdayAdapter$MyClickListener/this$0 Lcom/nd/android/u/tast/birthday/adapter/BirthdayAdapter;
new com/nd/android/u/tast/birthday/adapter/BirthdayAdapter$Task
dup
aload 0
getfield com/nd/android/u/tast/birthday/adapter/BirthdayAdapter$MyClickListener/this$0 Lcom/nd/android/u/tast/birthday/adapter/BirthdayAdapter;
aconst_null
invokespecial com/nd/android/u/tast/birthday/adapter/BirthdayAdapter$Task/<init>(Lcom/nd/android/u/tast/birthday/adapter/BirthdayAdapter;Lcom/nd/android/u/tast/birthday/adapter/BirthdayAdapter$1;)V
invokestatic com/nd/android/u/tast/birthday/adapter/BirthdayAdapter/access$302(Lcom/nd/android/u/tast/birthday/adapter/BirthdayAdapter;Lcom/nd/android/u/tast/birthday/adapter/BirthdayAdapter$Task;)Lcom/nd/android/u/tast/birthday/adapter/BirthdayAdapter$Task;
pop
aload 0
getfield com/nd/android/u/tast/birthday/adapter/BirthdayAdapter$MyClickListener/this$0 Lcom/nd/android/u/tast/birthday/adapter/BirthdayAdapter;
invokestatic com/nd/android/u/tast/birthday/adapter/BirthdayAdapter/access$300(Lcom/nd/android/u/tast/birthday/adapter/BirthdayAdapter;)Lcom/nd/android/u/tast/birthday/adapter/BirthdayAdapter$Task;
iconst_2
anewarray java/lang/Object
dup
iconst_0
aload 0
getfield com/nd/android/u/tast/birthday/adapter/BirthdayAdapter$MyClickListener/mHolder Lcom/nd/android/u/tast/birthday/adapter/BirthdayAdapter$ViewHolder;
aastore
dup
iconst_1
aload 0
getfield com/nd/android/u/tast/birthday/adapter/BirthdayAdapter$MyClickListener/mPosition I
invokestatic java/lang/Integer/valueOf(I)Ljava/lang/Integer;
aastore
invokevirtual com/nd/android/u/tast/birthday/adapter/BirthdayAdapter$Task/execute([Ljava/lang/Object;)Landroid/os/AsyncTask;
pop
return
.limit locals 3
.limit stack 5
.end method

.method public onClick(Landroid/view/View;)V
aload 1
invokevirtual android/view/View/getId()I
istore 2
iload 2
getstatic com/nd/android/u/tasklib/R$id/btn_bless I
if_icmpne L0
aload 0
getfield com/nd/android/u/tast/birthday/adapter/BirthdayAdapter$MyClickListener/mHolder Lcom/nd/android/u/tast/birthday/adapter/BirthdayAdapter$ViewHolder;
ifnull L0
aload 0
invokespecial com/nd/android/u/tast/birthday/adapter/BirthdayAdapter$MyClickListener/doBelss()V
L1:
return
L0:
iload 2
getstatic com/nd/android/u/tasklib/R$id/btn_send_flowers I
if_icmpne L2
aload 0
getfield com/nd/android/u/tast/birthday/adapter/BirthdayAdapter$MyClickListener/this$0 Lcom/nd/android/u/tast/birthday/adapter/BirthdayAdapter;
invokestatic com/nd/android/u/tast/birthday/adapter/BirthdayAdapter/access$100(Lcom/nd/android/u/tast/birthday/adapter/BirthdayAdapter;)Landroid/content/Context;
aload 0
getfield com/nd/android/u/tast/birthday/adapter/BirthdayAdapter$MyClickListener/this$0 Lcom/nd/android/u/tast/birthday/adapter/BirthdayAdapter;
aload 0
getfield com/nd/android/u/tast/birthday/adapter/BirthdayAdapter$MyClickListener/mPosition I
invokevirtual com/nd/android/u/tast/birthday/adapter/BirthdayAdapter/getItem(I)Lcom/nd/android/u/tast/birthday/dataStructure/Birthuserlist;
invokevirtual com/nd/android/u/tast/birthday/dataStructure/Birthuserlist/getUid()J
invokestatic com/nd/android/u/tast/taskInterfaceImpl/TaskCallOtherModel/sendFlowers(Landroid/content/Context;J)V
return
L2:
aload 0
getfield com/nd/android/u/tast/birthday/adapter/BirthdayAdapter$MyClickListener/mHolder Lcom/nd/android/u/tast/birthday/adapter/BirthdayAdapter$ViewHolder;
ifnull L3
iload 2
getstatic com/nd/android/u/tasklib/R$id/flowview_item_text_name I
if_icmpeq L4
iload 2
getstatic com/nd/android/u/tasklib/R$id/flowview_item_text_departname I
if_icmpeq L4
iload 2
getstatic com/nd/android/u/tasklib/R$id/flowview_bottom_layout I
if_icmpne L3
L4:
aload 0
invokespecial com/nd/android/u/tast/birthday/adapter/BirthdayAdapter$MyClickListener/clickHotArea()V
return
L3:
iload 2
getstatic com/nd/android/u/tasklib/R$id/flowview_item_image I
if_icmpne L1
aload 0
getfield com/nd/android/u/tast/birthday/adapter/BirthdayAdapter$MyClickListener/this$0 Lcom/nd/android/u/tast/birthday/adapter/BirthdayAdapter;
invokestatic com/nd/android/u/tast/birthday/adapter/BirthdayAdapter/access$100(Lcom/nd/android/u/tast/birthday/adapter/BirthdayAdapter;)Landroid/content/Context;
aload 0
getfield com/nd/android/u/tast/birthday/adapter/BirthdayAdapter$MyClickListener/this$0 Lcom/nd/android/u/tast/birthday/adapter/BirthdayAdapter;
aload 0
getfield com/nd/android/u/tast/birthday/adapter/BirthdayAdapter$MyClickListener/mPosition I
invokevirtual com/nd/android/u/tast/birthday/adapter/BirthdayAdapter/getItem(I)Lcom/nd/android/u/tast/birthday/dataStructure/Birthuserlist;
invokevirtual com/nd/android/u/tast/birthday/dataStructure/Birthuserlist/getUid()J
sipush 2424
invokestatic com/nd/android/u/tast/taskInterfaceImpl/TaskCallOtherModel/toTweetProfileActivity(Landroid/content/Context;JI)V
return
.limit locals 3
.limit stack 4
.end method
