.bytecode 50.0
.class synchronized com/nd/android/u/tast/birthday/adapter/BirthdayAdapter$Task
.super android/os/AsyncTask
.signature "Landroid/os/AsyncTask<Ljava/lang/Object;Ljava/lang/Void;Lcom/common/android/utils/task/genericTask/TaskResult;>;"
.inner class private Task inner com/nd/android/u/tast/birthday/adapter/BirthdayAdapter$Task outer com/nd/android/u/tast/birthday/adapter/BirthdayAdapter
.inner class inner com/nd/android/u/tast/birthday/adapter/BirthdayAdapter$Task$1

.field private 'holder' Lcom/nd/android/u/tast/birthday/adapter/BirthdayAdapter$ViewHolder;

.field private 'position' I

.field private 'retJson' Lorg/json/JSONObject;

.field final synthetic 'this$0' Lcom/nd/android/u/tast/birthday/adapter/BirthdayAdapter;

.field private 'uid' J

.method private <init>(Lcom/nd/android/u/tast/birthday/adapter/BirthdayAdapter;)V
aload 0
aload 1
putfield com/nd/android/u/tast/birthday/adapter/BirthdayAdapter$Task/this$0 Lcom/nd/android/u/tast/birthday/adapter/BirthdayAdapter;
aload 0
invokespecial android/os/AsyncTask/<init>()V
aload 0
aconst_null
putfield com/nd/android/u/tast/birthday/adapter/BirthdayAdapter$Task/retJson Lorg/json/JSONObject;
aload 0
aconst_null
putfield com/nd/android/u/tast/birthday/adapter/BirthdayAdapter$Task/holder Lcom/nd/android/u/tast/birthday/adapter/BirthdayAdapter$ViewHolder;
return
.limit locals 2
.limit stack 2
.end method

.method synthetic <init>(Lcom/nd/android/u/tast/birthday/adapter/BirthdayAdapter;Lcom/nd/android/u/tast/birthday/adapter/BirthdayAdapter$1;)V
aload 0
aload 1
invokespecial com/nd/android/u/tast/birthday/adapter/BirthdayAdapter$Task/<init>(Lcom/nd/android/u/tast/birthday/adapter/BirthdayAdapter;)V
return
.limit locals 3
.limit stack 2
.end method

.method static synthetic access$600(Lcom/nd/android/u/tast/birthday/adapter/BirthdayAdapter$Task;)Lcom/nd/android/u/tast/birthday/adapter/BirthdayAdapter$ViewHolder;
aload 0
getfield com/nd/android/u/tast/birthday/adapter/BirthdayAdapter$Task/holder Lcom/nd/android/u/tast/birthday/adapter/BirthdayAdapter$ViewHolder;
areturn
.limit locals 1
.limit stack 1
.end method

.method protected transient doInBackground([Ljava/lang/Object;)Lcom/common/android/utils/task/genericTask/TaskResult;
.catch com/common/android/utils/http/HttpException from L0 to L1 using L2
.catch java/lang/Exception from L0 to L1 using L3
aload 0
aload 1
iconst_1
aaload
checkcast java/lang/Integer
invokevirtual java/lang/Integer/intValue()I
putfield com/nd/android/u/tast/birthday/adapter/BirthdayAdapter$Task/position I
new com/nd/android/u/tast/com/OapBirthdayCom
dup
invokespecial com/nd/android/u/tast/com/OapBirthdayCom/<init>()V
astore 2
L0:
aload 0
aload 0
getfield com/nd/android/u/tast/birthday/adapter/BirthdayAdapter$Task/this$0 Lcom/nd/android/u/tast/birthday/adapter/BirthdayAdapter;
invokestatic com/nd/android/u/tast/birthday/adapter/BirthdayAdapter/access$500(Lcom/nd/android/u/tast/birthday/adapter/BirthdayAdapter;)Ljava/util/ArrayList;
aload 0
getfield com/nd/android/u/tast/birthday/adapter/BirthdayAdapter$Task/position I
invokevirtual java/util/ArrayList/get(I)Ljava/lang/Object;
checkcast com/nd/android/u/tast/birthday/dataStructure/Birthuserlist
invokevirtual com/nd/android/u/tast/birthday/dataStructure/Birthuserlist/getUid()J
putfield com/nd/android/u/tast/birthday/adapter/BirthdayAdapter$Task/uid J
aload 0
aload 2
aload 0
getfield com/nd/android/u/tast/birthday/adapter/BirthdayAdapter$Task/uid J
invokevirtual com/nd/android/u/tast/com/OapBirthdayCom/postBlessGetJson(J)Lorg/json/JSONObject;
putfield com/nd/android/u/tast/birthday/adapter/BirthdayAdapter$Task/retJson Lorg/json/JSONObject;
L1:
aload 0
aload 1
iconst_0
aaload
checkcast com/nd/android/u/tast/birthday/adapter/BirthdayAdapter$ViewHolder
putfield com/nd/android/u/tast/birthday/adapter/BirthdayAdapter$Task/holder Lcom/nd/android/u/tast/birthday/adapter/BirthdayAdapter$ViewHolder;
aload 0
getfield com/nd/android/u/tast/birthday/adapter/BirthdayAdapter$Task/retJson Lorg/json/JSONObject;
ifnull L4
getstatic com/common/android/utils/task/genericTask/TaskResult/OK Lcom/common/android/utils/task/genericTask/TaskResult;
areturn
L2:
astore 2
aload 2
invokevirtual com/common/android/utils/http/HttpException/printStackTrace()V
goto L1
L3:
astore 2
aload 2
invokevirtual java/lang/Exception/printStackTrace()V
goto L1
L4:
getstatic com/common/android/utils/task/genericTask/TaskResult/FAILED Lcom/common/android/utils/task/genericTask/TaskResult;
areturn
.limit locals 3
.limit stack 4
.end method

.method protected volatile synthetic doInBackground([Ljava/lang/Object;)Ljava/lang/Object;
aload 0
aload 1
invokevirtual com/nd/android/u/tast/birthday/adapter/BirthdayAdapter$Task/doInBackground([Ljava/lang/Object;)Lcom/common/android/utils/task/genericTask/TaskResult;
areturn
.limit locals 2
.limit stack 2
.end method

.method protected onPostExecute(Lcom/common/android/utils/task/genericTask/TaskResult;)V
aload 1
getstatic com/common/android/utils/task/genericTask/TaskResult/OK Lcom/common/android/utils/task/genericTask/TaskResult;
if_acmpne L0
aload 0
getfield com/nd/android/u/tast/birthday/adapter/BirthdayAdapter$Task/retJson Lorg/json/JSONObject;
ldc "code"
invokestatic com/common/android/utils/JSONUtils/getInt(Lorg/json/JSONObject;Ljava/lang/String;)I
istore 2
iload 2
sipush 200
if_icmpne L1
aload 0
getfield com/nd/android/u/tast/birthday/adapter/BirthdayAdapter$Task/retJson Lorg/json/JSONObject;
ldc "exp"
invokestatic com/common/android/utils/JSONUtils/getInt(Lorg/json/JSONObject;Ljava/lang/String;)I
istore 4
aload 0
getfield com/nd/android/u/tast/birthday/adapter/BirthdayAdapter$Task/this$0 Lcom/nd/android/u/tast/birthday/adapter/BirthdayAdapter;
invokestatic com/nd/android/u/tast/birthday/adapter/BirthdayAdapter/access$200(Lcom/nd/android/u/tast/birthday/adapter/BirthdayAdapter;)Landroid/graphics/drawable/AnimationDrawable;
ifnull L2
iconst_0
istore 3
iconst_0
istore 2
L3:
iload 2
aload 0
getfield com/nd/android/u/tast/birthday/adapter/BirthdayAdapter$Task/this$0 Lcom/nd/android/u/tast/birthday/adapter/BirthdayAdapter;
invokestatic com/nd/android/u/tast/birthday/adapter/BirthdayAdapter/access$200(Lcom/nd/android/u/tast/birthday/adapter/BirthdayAdapter;)Landroid/graphics/drawable/AnimationDrawable;
invokevirtual android/graphics/drawable/AnimationDrawable/getNumberOfFrames()I
if_icmpge L4
iload 3
aload 0
getfield com/nd/android/u/tast/birthday/adapter/BirthdayAdapter$Task/this$0 Lcom/nd/android/u/tast/birthday/adapter/BirthdayAdapter;
invokestatic com/nd/android/u/tast/birthday/adapter/BirthdayAdapter/access$200(Lcom/nd/android/u/tast/birthday/adapter/BirthdayAdapter;)Landroid/graphics/drawable/AnimationDrawable;
iload 2
invokevirtual android/graphics/drawable/AnimationDrawable/getDuration(I)I
iadd
istore 3
iload 2
iconst_1
iadd
istore 2
goto L3
L4:
new android/os/Handler
dup
invokespecial android/os/Handler/<init>()V
new com/nd/android/u/tast/birthday/adapter/BirthdayAdapter$Task$1
dup
aload 0
iload 4
invokespecial com/nd/android/u/tast/birthday/adapter/BirthdayAdapter$Task$1/<init>(Lcom/nd/android/u/tast/birthday/adapter/BirthdayAdapter$Task;I)V
iload 3
i2l
invokevirtual android/os/Handler/postDelayed(Ljava/lang/Runnable;J)Z
pop
L2:
return
L1:
iload 2
sipush 201
if_icmpne L5
aload 0
getfield com/nd/android/u/tast/birthday/adapter/BirthdayAdapter$Task/this$0 Lcom/nd/android/u/tast/birthday/adapter/BirthdayAdapter;
aload 0
getfield com/nd/android/u/tast/birthday/adapter/BirthdayAdapter$Task/holder Lcom/nd/android/u/tast/birthday/adapter/BirthdayAdapter$ViewHolder;
iconst_1
aload 0
getfield com/nd/android/u/tast/birthday/adapter/BirthdayAdapter$Task/uid J
aload 0
getfield com/nd/android/u/tast/birthday/adapter/BirthdayAdapter$Task/position I
invokevirtual com/nd/android/u/tast/birthday/adapter/BirthdayAdapter/blessFail(Lcom/nd/android/u/tast/birthday/adapter/BirthdayAdapter$ViewHolder;IJI)V
return
L5:
aload 0
getfield com/nd/android/u/tast/birthday/adapter/BirthdayAdapter$Task/this$0 Lcom/nd/android/u/tast/birthday/adapter/BirthdayAdapter;
aload 0
getfield com/nd/android/u/tast/birthday/adapter/BirthdayAdapter$Task/holder Lcom/nd/android/u/tast/birthday/adapter/BirthdayAdapter$ViewHolder;
iconst_2
aload 0
getfield com/nd/android/u/tast/birthday/adapter/BirthdayAdapter$Task/uid J
aload 0
getfield com/nd/android/u/tast/birthday/adapter/BirthdayAdapter$Task/position I
invokevirtual com/nd/android/u/tast/birthday/adapter/BirthdayAdapter/blessFail(Lcom/nd/android/u/tast/birthday/adapter/BirthdayAdapter$ViewHolder;IJI)V
return
L0:
aload 0
getfield com/nd/android/u/tast/birthday/adapter/BirthdayAdapter$Task/this$0 Lcom/nd/android/u/tast/birthday/adapter/BirthdayAdapter;
aload 0
getfield com/nd/android/u/tast/birthday/adapter/BirthdayAdapter$Task/holder Lcom/nd/android/u/tast/birthday/adapter/BirthdayAdapter$ViewHolder;
iconst_2
aload 0
getfield com/nd/android/u/tast/birthday/adapter/BirthdayAdapter$Task/uid J
aload 0
getfield com/nd/android/u/tast/birthday/adapter/BirthdayAdapter$Task/position I
invokevirtual com/nd/android/u/tast/birthday/adapter/BirthdayAdapter/blessFail(Lcom/nd/android/u/tast/birthday/adapter/BirthdayAdapter$ViewHolder;IJI)V
return
.limit locals 5
.limit stack 6
.end method

.method protected volatile synthetic onPostExecute(Ljava/lang/Object;)V
aload 0
aload 1
checkcast com/common/android/utils/task/genericTask/TaskResult
invokevirtual com/nd/android/u/tast/birthday/adapter/BirthdayAdapter$Task/onPostExecute(Lcom/common/android/utils/task/genericTask/TaskResult;)V
return
.limit locals 2
.limit stack 2
.end method
