.bytecode 50.0
.class public synchronized com/android/u/weibo/contact/utils/ContactConstellation
.super java/lang/Object

.field private static final 'DAY' I = 21


.method public <init>()V
aload 0
invokespecial java/lang/Object/<init>()V
return
.limit locals 1
.limit stack 1
.end method

.method public static getConstellation(Ljava/util/Date;)Ljava/lang/String;
aload 0
ifnonnull L0
ldc ""
areturn
L0:
getstatic com/product/android/business/ApplicationVariable/INSTANCE Lcom/product/android/business/ApplicationVariable;
getfield com/product/android/business/ApplicationVariable/applicationContext Landroid/content/Context;
astore 3
aload 0
invokevirtual java/util/Date/getMonth()I
istore 1
aload 0
invokevirtual java/util/Date/getDate()I
istore 2
iload 1
tableswitch 0
L1
L2
L3
L4
L5
L6
L7
L8
L9
L10
L11
L12
default : L13
L13:
ldc ""
areturn
L1:
iload 2
bipush 21
if_icmplt L14
aload 3
invokevirtual android/content/Context/getResources()Landroid/content/res/Resources;
getstatic com/android/u/weibo/R$string/xz_sp I
invokevirtual android/content/res/Resources/getString(I)Ljava/lang/String;
areturn
L14:
aload 3
invokevirtual android/content/Context/getResources()Landroid/content/res/Resources;
getstatic com/android/u/weibo/R$string/xz_mj I
invokevirtual android/content/res/Resources/getString(I)Ljava/lang/String;
areturn
L2:
iload 2
bipush 21
if_icmplt L15
aload 3
invokevirtual android/content/Context/getResources()Landroid/content/res/Resources;
getstatic com/android/u/weibo/R$string/xz_sy I
invokevirtual android/content/res/Resources/getString(I)Ljava/lang/String;
areturn
L15:
aload 3
invokevirtual android/content/Context/getResources()Landroid/content/res/Resources;
getstatic com/android/u/weibo/R$string/xz_sp I
invokevirtual android/content/res/Resources/getString(I)Ljava/lang/String;
areturn
L3:
iload 2
bipush 21
if_icmplt L16
aload 3
invokevirtual android/content/Context/getResources()Landroid/content/res/Resources;
getstatic com/android/u/weibo/R$string/xz_by I
invokevirtual android/content/res/Resources/getString(I)Ljava/lang/String;
areturn
L16:
aload 3
invokevirtual android/content/Context/getResources()Landroid/content/res/Resources;
getstatic com/android/u/weibo/R$string/xz_sy I
invokevirtual android/content/res/Resources/getString(I)Ljava/lang/String;
areturn
L4:
iload 2
bipush 21
if_icmplt L17
aload 3
invokevirtual android/content/Context/getResources()Landroid/content/res/Resources;
getstatic com/android/u/weibo/R$string/xz_jn I
invokevirtual android/content/res/Resources/getString(I)Ljava/lang/String;
areturn
L17:
aload 3
invokevirtual android/content/Context/getResources()Landroid/content/res/Resources;
getstatic com/android/u/weibo/R$string/xz_by I
invokevirtual android/content/res/Resources/getString(I)Ljava/lang/String;
areturn
L5:
iload 2
bipush 21
if_icmplt L18
aload 3
invokevirtual android/content/Context/getResources()Landroid/content/res/Resources;
getstatic com/android/u/weibo/R$string/xz_sz I
invokevirtual android/content/res/Resources/getString(I)Ljava/lang/String;
areturn
L18:
aload 3
invokevirtual android/content/Context/getResources()Landroid/content/res/Resources;
getstatic com/android/u/weibo/R$string/xz_jn I
invokevirtual android/content/res/Resources/getString(I)Ljava/lang/String;
areturn
L6:
iload 2
bipush 21
if_icmplt L19
aload 3
invokevirtual android/content/Context/getResources()Landroid/content/res/Resources;
getstatic com/android/u/weibo/R$string/xz_jx I
invokevirtual android/content/res/Resources/getString(I)Ljava/lang/String;
areturn
L19:
aload 3
invokevirtual android/content/Context/getResources()Landroid/content/res/Resources;
getstatic com/android/u/weibo/R$string/xz_sz I
invokevirtual android/content/res/Resources/getString(I)Ljava/lang/String;
areturn
L7:
iload 2
bipush 21
if_icmplt L20
aload 3
invokevirtual android/content/Context/getResources()Landroid/content/res/Resources;
getstatic com/android/u/weibo/R$string/xz_szh I
invokevirtual android/content/res/Resources/getString(I)Ljava/lang/String;
areturn
L20:
aload 3
invokevirtual android/content/Context/getResources()Landroid/content/res/Resources;
getstatic com/android/u/weibo/R$string/xz_jx I
invokevirtual android/content/res/Resources/getString(I)Ljava/lang/String;
areturn
L8:
iload 2
bipush 21
if_icmplt L21
aload 3
invokevirtual android/content/Context/getResources()Landroid/content/res/Resources;
getstatic com/android/u/weibo/R$string/xz_cn I
invokevirtual android/content/res/Resources/getString(I)Ljava/lang/String;
areturn
L21:
aload 3
invokevirtual android/content/Context/getResources()Landroid/content/res/Resources;
getstatic com/android/u/weibo/R$string/xz_szh I
invokevirtual android/content/res/Resources/getString(I)Ljava/lang/String;
areturn
L9:
iload 2
bipush 21
if_icmplt L22
aload 3
invokevirtual android/content/Context/getResources()Landroid/content/res/Resources;
getstatic com/android/u/weibo/R$string/xz_tc I
invokevirtual android/content/res/Resources/getString(I)Ljava/lang/String;
areturn
L22:
aload 3
invokevirtual android/content/Context/getResources()Landroid/content/res/Resources;
getstatic com/android/u/weibo/R$string/xz_cn I
invokevirtual android/content/res/Resources/getString(I)Ljava/lang/String;
areturn
L10:
iload 2
bipush 21
if_icmplt L23
aload 3
invokevirtual android/content/Context/getResources()Landroid/content/res/Resources;
getstatic com/android/u/weibo/R$string/xz_tx I
invokevirtual android/content/res/Resources/getString(I)Ljava/lang/String;
areturn
L23:
aload 3
invokevirtual android/content/Context/getResources()Landroid/content/res/Resources;
getstatic com/android/u/weibo/R$string/xz_tc I
invokevirtual android/content/res/Resources/getString(I)Ljava/lang/String;
areturn
L11:
iload 2
bipush 21
if_icmplt L24
aload 3
invokevirtual android/content/Context/getResources()Landroid/content/res/Resources;
getstatic com/android/u/weibo/R$string/xz_ss I
invokevirtual android/content/res/Resources/getString(I)Ljava/lang/String;
areturn
L24:
aload 3
invokevirtual android/content/Context/getResources()Landroid/content/res/Resources;
getstatic com/android/u/weibo/R$string/xz_tx I
invokevirtual android/content/res/Resources/getString(I)Ljava/lang/String;
areturn
L12:
iload 2
bipush 21
if_icmplt L25
aload 3
invokevirtual android/content/Context/getResources()Landroid/content/res/Resources;
getstatic com/android/u/weibo/R$string/xz_mj I
invokevirtual android/content/res/Resources/getString(I)Ljava/lang/String;
areturn
L25:
aload 3
invokevirtual android/content/Context/getResources()Landroid/content/res/Resources;
getstatic com/android/u/weibo/R$string/xz_ss I
invokevirtual android/content/res/Resources/getString(I)Ljava/lang/String;
areturn
.limit locals 4
.limit stack 2
.end method
