.bytecode 50.0
.class final synchronized com/nd/android/u/contact/db/ContactDaoFactory$1
.super java/util/HashMap
.signature "Ljava/util/HashMap<Ljava/lang/Class;Ljava/lang/String;>;"
.enclosing method com/nd/android/u/contact/db/ContactDaoFactory
.inner class static final inner com/nd/android/u/contact/db/ContactDaoFactory$1

.method <init>()V
aload 0
invokespecial java/util/HashMap/<init>()V
aload 0
ldc com/nd/android/u/contact/dao/BirthdayRemindDao
ldc "com.nd.android.u.contact.dao.impl.BirthdayRemindDaoImpl"
invokevirtual com/nd/android/u/contact/db/ContactDaoFactory$1/put(Ljava/lang/Object;Ljava/lang/Object;)Ljava/lang/Object;
pop
aload 0
ldc com/nd/android/u/contact/dao/BirthdayRemindHistoryDao
ldc "com.nd.android.u.contact.dao.impl.BirthdayRemindHistoryDaoImpl"
invokevirtual com/nd/android/u/contact/db/ContactDaoFactory$1/put(Ljava/lang/Object;Ljava/lang/Object;)Ljava/lang/Object;
pop
aload 0
ldc com/nd/android/u/contact/dao/FriendRelationDao
ldc "com.nd.android.u.contact.dao.impl.FriendRelationDaoImpl"
invokevirtual com/nd/android/u/contact/db/ContactDaoFactory$1/put(Ljava/lang/Object;Ljava/lang/Object;)Ljava/lang/Object;
pop
aload 0
ldc com/nd/android/u/contact/dao/HeadImageDao
ldc "com.nd.android.u.contact.dao.impl.HeadImageDaoImpl"
invokevirtual com/nd/android/u/contact/db/ContactDaoFactory$1/put(Ljava/lang/Object;Ljava/lang/Object;)Ljava/lang/Object;
pop
aload 0
ldc com/nd/android/u/contact/dao/MessageInfoDAO
ldc "com.nd.android.u.contact.dao.impl.MessageInfoDAOImpl"
invokevirtual com/nd/android/u/contact/db/ContactDaoFactory$1/put(Ljava/lang/Object;Ljava/lang/Object;)Ljava/lang/Object;
pop
aload 0
ldc com/nd/android/u/contact/dao/OapAppDao
ldc "com.nd.android.u.contact.dao.impl.OapAppDaoImpl"
invokevirtual com/nd/android/u/contact/db/ContactDaoFactory$1/put(Ljava/lang/Object;Ljava/lang/Object;)Ljava/lang/Object;
pop
aload 0
ldc com/nd/android/u/contact/dao/OapAppTypeDao
ldc "com.nd.android.u.contact.dao.impl.OapAppTypeDaoImpl"
invokevirtual com/nd/android/u/contact/db/ContactDaoFactory$1/put(Ljava/lang/Object;Ljava/lang/Object;)Ljava/lang/Object;
pop
aload 0
ldc com/nd/android/u/contact/dao/OapAppUpdateTimeDao
ldc "com.nd.android.u.contact.dao.impl.OapAppUpdateTimeDaoImpl"
invokevirtual com/nd/android/u/contact/db/ContactDaoFactory$1/put(Ljava/lang/Object;Ljava/lang/Object;)Ljava/lang/Object;
pop
aload 0
ldc com/nd/android/u/contact/dao/OapBlackListDao
ldc "com.nd.android.u.contact.dao.impl.OapBlackListDaoImpl"
invokevirtual com/nd/android/u/contact/db/ContactDaoFactory$1/put(Ljava/lang/Object;Ljava/lang/Object;)Ljava/lang/Object;
pop
aload 0
ldc com/nd/android/u/contact/dao/OapClassDao
ldc "com.nd.android.u.contact.dao.impl.OapClassDaoImpl"
invokevirtual com/nd/android/u/contact/db/ContactDaoFactory$1/put(Ljava/lang/Object;Ljava/lang/Object;)Ljava/lang/Object;
pop
aload 0
ldc com/nd/android/u/contact/dao/OapClassRelationDao
ldc "com.nd.android.u.contact.dao.impl.OapClassRelationDaoImpl"
invokevirtual com/nd/android/u/contact/db/ContactDaoFactory$1/put(Ljava/lang/Object;Ljava/lang/Object;)Ljava/lang/Object;
pop
aload 0
ldc com/nd/android/u/contact/dao/OapDepartDao
ldc "com.nd.android.u.contact.dao.impl.OapDepartDaoImpl"
invokevirtual com/nd/android/u/contact/db/ContactDaoFactory$1/put(Ljava/lang/Object;Ljava/lang/Object;)Ljava/lang/Object;
pop
aload 0
ldc com/nd/android/u/contact/dao/OapFriendGroupDao
ldc "com.nd.android.u.contact.dao.impl.OapFriendGroupDaoImpl"
invokevirtual com/nd/android/u/contact/db/ContactDaoFactory$1/put(Ljava/lang/Object;Ljava/lang/Object;)Ljava/lang/Object;
pop
aload 0
ldc com/nd/android/u/contact/dao/OapGroupDao
ldc "com.nd.android.u.contact.dao.impl.OapGroupDaoImpl"
invokevirtual com/nd/android/u/contact/db/ContactDaoFactory$1/put(Ljava/lang/Object;Ljava/lang/Object;)Ljava/lang/Object;
pop
aload 0
ldc com/nd/android/u/contact/dao/OapGroupRelationDao
ldc "com.nd.android.u.contact.dao.impl.OapGroupRelationDaoImpl"
invokevirtual com/nd/android/u/contact/db/ContactDaoFactory$1/put(Ljava/lang/Object;Ljava/lang/Object;)Ljava/lang/Object;
pop
aload 0
ldc com/nd/android/u/contact/dao/OapUnitDao
ldc "com.nd.android.u.contact.dao.impl.UserInfoAndOapUnitDaoImpl"
invokevirtual com/nd/android/u/contact/db/ContactDaoFactory$1/put(Ljava/lang/Object;Ljava/lang/Object;)Ljava/lang/Object;
pop
aload 0
ldc com/nd/android/u/contact/dao/OapUnitRelationDao
ldc "com.nd.android.u.contact.dao.impl.OapUnitRelationDaoImpl"
invokevirtual com/nd/android/u/contact/db/ContactDaoFactory$1/put(Ljava/lang/Object;Ljava/lang/Object;)Ljava/lang/Object;
pop
aload 0
ldc com/nd/android/u/contact/dao/OapUserDao
ldc "com.nd.android.u.contact.dao.impl.OapUserDaoImpl"
invokevirtual com/nd/android/u/contact/db/ContactDaoFactory$1/put(Ljava/lang/Object;Ljava/lang/Object;)Ljava/lang/Object;
pop
aload 0
ldc com/nd/android/u/contact/dao/PhoneInfoDAO
ldc "com.nd.android.u.contact.dao.impl.PhoneInfoDAOImpl"
invokevirtual com/nd/android/u/contact/db/ContactDaoFactory$1/put(Ljava/lang/Object;Ljava/lang/Object;)Ljava/lang/Object;
pop
aload 0
ldc com/nd/android/u/contact/dao/SmsQueryDetailDAO
ldc "com.nd.android.u.contact.dao.impl.SmsQueryDetailDAOImpl"
invokevirtual com/nd/android/u/contact/db/ContactDaoFactory$1/put(Ljava/lang/Object;Ljava/lang/Object;)Ljava/lang/Object;
pop
aload 0
ldc com/nd/android/u/contact/dao/TagDao
ldc "com.nd.android.u.contact.dao.impl.TagDAOImpl"
invokevirtual com/nd/android/u/contact/db/ContactDaoFactory$1/put(Ljava/lang/Object;Ljava/lang/Object;)Ljava/lang/Object;
pop
aload 0
ldc com/nd/android/u/contact/dao/UserInfoDao
ldc "com.nd.android.u.contact.dao.impl.UserInfoAndOapUnitDaoImpl"
invokevirtual com/nd/android/u/contact/db/ContactDaoFactory$1/put(Ljava/lang/Object;Ljava/lang/Object;)Ljava/lang/Object;
pop
aload 0
ldc com/nd/android/u/contact/dao/VisitorDao
ldc "com.nd.android.u.contact.dao.impl.VisitorDAOImpl"
invokevirtual com/nd/android/u/contact/db/ContactDaoFactory$1/put(Ljava/lang/Object;Ljava/lang/Object;)Ljava/lang/Object;
pop
aload 0
ldc com/nd/android/u/contact/dao/OapJMClassDao
ldc "com.nd.android.u.contact.dao.impl.OapJMClassDaoImpl"
invokevirtual com/nd/android/u/contact/db/ContactDaoFactory$1/put(Ljava/lang/Object;Ljava/lang/Object;)Ljava/lang/Object;
pop
aload 0
ldc com/nd/android/u/contact/dao/OapJMClassRelationDao
ldc "com.nd.android.u.contact.dao.impl.OapJMClassRelationDaoImpl"
invokevirtual com/nd/android/u/contact/db/ContactDaoFactory$1/put(Ljava/lang/Object;Ljava/lang/Object;)Ljava/lang/Object;
pop
aload 0
ldc com/nd/android/u/contact/dao/VersionDao
ldc "com.nd.android.u.contact.dao.impl.VersionDAOImpl"
invokevirtual com/nd/android/u/contact/db/ContactDaoFactory$1/put(Ljava/lang/Object;Ljava/lang/Object;)Ljava/lang/Object;
pop
aload 0
ldc com/nd/android/u/contact/dao/PassportPhotoDao
ldc "com.nd.android.u.contact.dao.impl.PassportPhotoDaoImpl"
invokevirtual com/nd/android/u/contact/db/ContactDaoFactory$1/put(Ljava/lang/Object;Ljava/lang/Object;)Ljava/lang/Object;
pop
aload 0
ldc com/nd/android/u/contact/dao/NewFansDao
ldc "com.nd.android.u.contact.dao.impl.NewFansDaoImpl"
invokevirtual com/nd/android/u/contact/db/ContactDaoFactory$1/put(Ljava/lang/Object;Ljava/lang/Object;)Ljava/lang/Object;
pop
aload 0
ldc com/nd/android/u/contact/dao/MySeniorDao
ldc "com.nd.android.u.contact.dao.impl.MySeniorDaoImpl"
invokevirtual com/nd/android/u/contact/db/ContactDaoFactory$1/put(Ljava/lang/Object;Ljava/lang/Object;)Ljava/lang/Object;
pop
return
.limit locals 1
.limit stack 3
.end method
