.bytecode 50.0
.class synchronized com/nd/android/u/cloud/ui/dialog/AddOrgRequestDialog$1
.super java/lang/Object
.implements android/content/DialogInterface$OnClickListener
.enclosing method com/nd/android/u/cloud/ui/dialog/AddOrgRequestDialog/setListener()V
.inner class inner com/nd/android/u/cloud/ui/dialog/AddOrgRequestDialog$1

.field final synthetic 'this$0' Lcom/nd/android/u/cloud/ui/dialog/AddOrgRequestDialog;

.method <init>(Lcom/nd/android/u/cloud/ui/dialog/AddOrgRequestDialog;)V
aload 0
aload 1
putfield com/nd/android/u/cloud/ui/dialog/AddOrgRequestDialog$1/this$0 Lcom/nd/android/u/cloud/ui/dialog/AddOrgRequestDialog;
aload 0
invokespecial java/lang/Object/<init>()V
return
.limit locals 2
.limit stack 2
.end method

.method public onClick(Landroid/content/DialogInterface;I)V
.catch java/lang/Exception from L0 to L1 using L2
.catch java/lang/Exception from L1 to L3 using L2
.catch java/lang/Exception from L3 to L4 using L2
.catch java/lang/Exception from L5 to L6 using L2
.catch java/lang/Exception from L6 to L7 using L2
.catch java/lang/Exception from L8 to L9 using L2
.catch java/lang/Exception from L10 to L11 using L2
aload 0
getfield com/nd/android/u/cloud/ui/dialog/AddOrgRequestDialog$1/this$0 Lcom/nd/android/u/cloud/ui/dialog/AddOrgRequestDialog;
aload 0
getfield com/nd/android/u/cloud/ui/dialog/AddOrgRequestDialog$1/this$0 Lcom/nd/android/u/cloud/ui/dialog/AddOrgRequestDialog;
invokestatic com/nd/android/u/cloud/ui/dialog/AddOrgRequestDialog/access$100(Lcom/nd/android/u/cloud/ui/dialog/AddOrgRequestDialog;)Landroid/widget/EditText;
invokevirtual android/widget/EditText/getText()Landroid/text/Editable;
invokevirtual java/lang/Object/toString()Ljava/lang/String;
invokestatic com/nd/android/u/cloud/ui/dialog/AddOrgRequestDialog/access$002(Lcom/nd/android/u/cloud/ui/dialog/AddOrgRequestDialog;Ljava/lang/String;)Ljava/lang/String;
pop
aload 0
getfield com/nd/android/u/cloud/ui/dialog/AddOrgRequestDialog$1/this$0 Lcom/nd/android/u/cloud/ui/dialog/AddOrgRequestDialog;
aload 0
getfield com/nd/android/u/cloud/ui/dialog/AddOrgRequestDialog$1/this$0 Lcom/nd/android/u/cloud/ui/dialog/AddOrgRequestDialog;
invokestatic com/nd/android/u/cloud/ui/dialog/AddOrgRequestDialog/access$300(Lcom/nd/android/u/cloud/ui/dialog/AddOrgRequestDialog;)Landroid/widget/EditText;
invokevirtual android/widget/EditText/getText()Landroid/text/Editable;
invokevirtual java/lang/Object/toString()Ljava/lang/String;
invokestatic com/nd/android/u/cloud/ui/dialog/AddOrgRequestDialog/access$202(Lcom/nd/android/u/cloud/ui/dialog/AddOrgRequestDialog;Ljava/lang/String;)Ljava/lang/String;
pop
L0:
aload 1
invokevirtual java/lang/Object/getClass()Ljava/lang/Class;
invokevirtual java/lang/Class/getSuperclass()Ljava/lang/Class;
ldc "mShowing"
invokevirtual java/lang/Class/getDeclaredField(Ljava/lang/String;)Ljava/lang/reflect/Field;
astore 3
aload 3
iconst_1
invokevirtual java/lang/reflect/Field/setAccessible(Z)V
aload 0
getfield com/nd/android/u/cloud/ui/dialog/AddOrgRequestDialog$1/this$0 Lcom/nd/android/u/cloud/ui/dialog/AddOrgRequestDialog;
invokestatic com/nd/android/u/cloud/ui/dialog/AddOrgRequestDialog/access$000(Lcom/nd/android/u/cloud/ui/dialog/AddOrgRequestDialog;)Ljava/lang/String;
ifnull L1
ldc ""
aload 0
getfield com/nd/android/u/cloud/ui/dialog/AddOrgRequestDialog$1/this$0 Lcom/nd/android/u/cloud/ui/dialog/AddOrgRequestDialog;
invokestatic com/nd/android/u/cloud/ui/dialog/AddOrgRequestDialog/access$000(Lcom/nd/android/u/cloud/ui/dialog/AddOrgRequestDialog;)Ljava/lang/String;
invokevirtual java/lang/String/endsWith(Ljava/lang/String;)Z
ifeq L5
L1:
aload 0
getfield com/nd/android/u/cloud/ui/dialog/AddOrgRequestDialog$1/this$0 Lcom/nd/android/u/cloud/ui/dialog/AddOrgRequestDialog;
invokestatic com/nd/android/u/cloud/ui/dialog/AddOrgRequestDialog/access$400(Lcom/nd/android/u/cloud/ui/dialog/AddOrgRequestDialog;)Landroid/content/Context;
ldc_w 2131495526
invokestatic com/common/android/utils/ToastUtils/display(Landroid/content/Context;I)V
aload 3
aload 1
iconst_0
invokestatic java/lang/Boolean/valueOf(Z)Ljava/lang/Boolean;
invokevirtual java/lang/reflect/Field/set(Ljava/lang/Object;Ljava/lang/Object;)V
L3:
aload 1
invokeinterface android/content/DialogInterface/dismiss()V 0
L4:
return
L5:
aload 0
getfield com/nd/android/u/cloud/ui/dialog/AddOrgRequestDialog$1/this$0 Lcom/nd/android/u/cloud/ui/dialog/AddOrgRequestDialog;
invokestatic com/nd/android/u/cloud/ui/dialog/AddOrgRequestDialog/access$200(Lcom/nd/android/u/cloud/ui/dialog/AddOrgRequestDialog;)Ljava/lang/String;
ifnull L6
ldc ""
aload 0
getfield com/nd/android/u/cloud/ui/dialog/AddOrgRequestDialog$1/this$0 Lcom/nd/android/u/cloud/ui/dialog/AddOrgRequestDialog;
invokestatic com/nd/android/u/cloud/ui/dialog/AddOrgRequestDialog/access$200(Lcom/nd/android/u/cloud/ui/dialog/AddOrgRequestDialog;)Ljava/lang/String;
invokevirtual java/lang/String/endsWith(Ljava/lang/String;)Z
ifeq L8
L6:
aload 0
getfield com/nd/android/u/cloud/ui/dialog/AddOrgRequestDialog$1/this$0 Lcom/nd/android/u/cloud/ui/dialog/AddOrgRequestDialog;
invokestatic com/nd/android/u/cloud/ui/dialog/AddOrgRequestDialog/access$400(Lcom/nd/android/u/cloud/ui/dialog/AddOrgRequestDialog;)Landroid/content/Context;
ldc_w 2131494656
invokestatic com/common/android/utils/ToastUtils/display(Landroid/content/Context;I)V
aload 3
aload 1
iconst_0
invokestatic java/lang/Boolean/valueOf(Z)Ljava/lang/Boolean;
invokevirtual java/lang/reflect/Field/set(Ljava/lang/Object;Ljava/lang/Object;)V
L7:
goto L3
L8:
aload 0
getfield com/nd/android/u/cloud/ui/dialog/AddOrgRequestDialog$1/this$0 Lcom/nd/android/u/cloud/ui/dialog/AddOrgRequestDialog;
invokestatic com/nd/android/u/cloud/ui/dialog/AddOrgRequestDialog/access$200(Lcom/nd/android/u/cloud/ui/dialog/AddOrgRequestDialog;)Ljava/lang/String;
invokestatic ims/utils/CommUtil/isMobile(Ljava/lang/String;)Z
ifne L10
aload 0
getfield com/nd/android/u/cloud/ui/dialog/AddOrgRequestDialog$1/this$0 Lcom/nd/android/u/cloud/ui/dialog/AddOrgRequestDialog;
invokestatic com/nd/android/u/cloud/ui/dialog/AddOrgRequestDialog/access$400(Lcom/nd/android/u/cloud/ui/dialog/AddOrgRequestDialog;)Landroid/content/Context;
ldc_w 2131494078
invokestatic com/common/android/utils/ToastUtils/display(Landroid/content/Context;I)V
aload 3
aload 1
iconst_0
invokestatic java/lang/Boolean/valueOf(Z)Ljava/lang/Boolean;
invokevirtual java/lang/reflect/Field/set(Ljava/lang/Object;Ljava/lang/Object;)V
L9:
goto L3
L10:
aload 3
aload 1
iconst_1
invokestatic java/lang/Boolean/valueOf(Z)Ljava/lang/Boolean;
invokevirtual java/lang/reflect/Field/set(Ljava/lang/Object;Ljava/lang/Object;)V
aload 0
getfield com/nd/android/u/cloud/ui/dialog/AddOrgRequestDialog$1/this$0 Lcom/nd/android/u/cloud/ui/dialog/AddOrgRequestDialog;
aload 0
getfield com/nd/android/u/cloud/ui/dialog/AddOrgRequestDialog$1/this$0 Lcom/nd/android/u/cloud/ui/dialog/AddOrgRequestDialog;
invokestatic com/nd/android/u/cloud/ui/dialog/AddOrgRequestDialog/access$600(Lcom/nd/android/u/cloud/ui/dialog/AddOrgRequestDialog;)Landroid/widget/EditText;
invokevirtual android/widget/EditText/getText()Landroid/text/Editable;
invokevirtual java/lang/Object/toString()Ljava/lang/String;
invokestatic com/nd/android/u/cloud/ui/dialog/AddOrgRequestDialog/access$502(Lcom/nd/android/u/cloud/ui/dialog/AddOrgRequestDialog;Ljava/lang/String;)Ljava/lang/String;
pop
aload 0
getfield com/nd/android/u/cloud/ui/dialog/AddOrgRequestDialog$1/this$0 Lcom/nd/android/u/cloud/ui/dialog/AddOrgRequestDialog;
invokevirtual com/nd/android/u/cloud/ui/dialog/AddOrgRequestDialog/sendRequestApplication()V
L11:
goto L3
L2:
astore 1
return
.limit locals 4
.limit stack 3
.end method
