.bytecode 50.0
.class synchronized com/nd/android/u/cloud/activity/mbless/BirthdayRemActivity$3
.super com/common/android/utils/task/genericTask/TaskAdapter
.enclosing method com/nd/android/u/cloud/activity/mbless/BirthdayRemActivity
.inner class inner com/nd/android/u/cloud/activity/mbless/BirthdayRemActivity$3

.field final synthetic 'this$0' Lcom/nd/android/u/cloud/activity/mbless/BirthdayRemActivity;

.method <init>(Lcom/nd/android/u/cloud/activity/mbless/BirthdayRemActivity;)V
aload 0
aload 1
putfield com/nd/android/u/cloud/activity/mbless/BirthdayRemActivity$3/this$0 Lcom/nd/android/u/cloud/activity/mbless/BirthdayRemActivity;
aload 0
invokespecial com/common/android/utils/task/genericTask/TaskAdapter/<init>()V
return
.limit locals 2
.limit stack 2
.end method

.method public onPostExecute(Lcom/common/android/utils/task/genericTask/GenericTask;Lcom/common/android/utils/task/genericTask/TaskResult;)V
aload 0
getfield com/nd/android/u/cloud/activity/mbless/BirthdayRemActivity$3/this$0 Lcom/nd/android/u/cloud/activity/mbless/BirthdayRemActivity;
invokestatic com/nd/android/u/cloud/activity/mbless/BirthdayRemActivity/access$100(Lcom/nd/android/u/cloud/activity/mbless/BirthdayRemActivity;)Ljava/util/List;
ifnull L0
aload 0
getfield com/nd/android/u/cloud/activity/mbless/BirthdayRemActivity$3/this$0 Lcom/nd/android/u/cloud/activity/mbless/BirthdayRemActivity;
invokestatic com/nd/android/u/cloud/activity/mbless/BirthdayRemActivity/access$000(Lcom/nd/android/u/cloud/activity/mbless/BirthdayRemActivity;)Ljava/util/List;
iconst_0
aload 0
getfield com/nd/android/u/cloud/activity/mbless/BirthdayRemActivity$3/this$0 Lcom/nd/android/u/cloud/activity/mbless/BirthdayRemActivity;
invokestatic com/nd/android/u/cloud/activity/mbless/BirthdayRemActivity/access$100(Lcom/nd/android/u/cloud/activity/mbless/BirthdayRemActivity;)Ljava/util/List;
invokeinterface java/util/List/addAll(ILjava/util/Collection;)Z 2
pop
aload 0
getfield com/nd/android/u/cloud/activity/mbless/BirthdayRemActivity$3/this$0 Lcom/nd/android/u/cloud/activity/mbless/BirthdayRemActivity;
invokestatic com/nd/android/u/cloud/activity/mbless/BirthdayRemActivity/access$100(Lcom/nd/android/u/cloud/activity/mbless/BirthdayRemActivity;)Ljava/util/List;
invokeinterface java/util/List/size()I 0
bipush 10
if_icmpge L1
aload 0
getfield com/nd/android/u/cloud/activity/mbless/BirthdayRemActivity$3/this$0 Lcom/nd/android/u/cloud/activity/mbless/BirthdayRemActivity;
iconst_0
invokestatic com/nd/android/u/cloud/activity/mbless/BirthdayRemActivity/access$202(Lcom/nd/android/u/cloud/activity/mbless/BirthdayRemActivity;Z)Z
pop
L1:
aload 0
getfield com/nd/android/u/cloud/activity/mbless/BirthdayRemActivity$3/this$0 Lcom/nd/android/u/cloud/activity/mbless/BirthdayRemActivity;
invokestatic com/nd/android/u/cloud/activity/mbless/BirthdayRemActivity/access$300(Lcom/nd/android/u/cloud/activity/mbless/BirthdayRemActivity;)Lcom/nd/android/u/cloud/ui/adapter/mbless/BirthdayRemAdapter;
aload 0
getfield com/nd/android/u/cloud/activity/mbless/BirthdayRemActivity$3/this$0 Lcom/nd/android/u/cloud/activity/mbless/BirthdayRemActivity;
invokestatic com/nd/android/u/cloud/activity/mbless/BirthdayRemActivity/access$000(Lcom/nd/android/u/cloud/activity/mbless/BirthdayRemActivity;)Ljava/util/List;
invokevirtual com/nd/android/u/cloud/ui/adapter/mbless/BirthdayRemAdapter/setUserList(Ljava/util/List;)V
aload 0
getfield com/nd/android/u/cloud/activity/mbless/BirthdayRemActivity$3/this$0 Lcom/nd/android/u/cloud/activity/mbless/BirthdayRemActivity;
invokestatic com/nd/android/u/cloud/activity/mbless/BirthdayRemActivity/access$300(Lcom/nd/android/u/cloud/activity/mbless/BirthdayRemActivity;)Lcom/nd/android/u/cloud/ui/adapter/mbless/BirthdayRemAdapter;
invokevirtual com/nd/android/u/cloud/ui/adapter/mbless/BirthdayRemAdapter/notifyDataSetChanged()V
aload 0
getfield com/nd/android/u/cloud/activity/mbless/BirthdayRemActivity$3/this$0 Lcom/nd/android/u/cloud/activity/mbless/BirthdayRemActivity;
getfield com/nd/android/u/cloud/activity/mbless/BirthdayRemActivity/mlistView Lcom/nd/android/u/ui/widge/ScrollListView;
aload 0
getfield com/nd/android/u/cloud/activity/mbless/BirthdayRemActivity$3/this$0 Lcom/nd/android/u/cloud/activity/mbless/BirthdayRemActivity;
invokestatic com/nd/android/u/cloud/activity/mbless/BirthdayRemActivity/access$100(Lcom/nd/android/u/cloud/activity/mbless/BirthdayRemActivity;)Ljava/util/List;
invokeinterface java/util/List/size()I 0
invokevirtual com/nd/android/u/ui/widge/ScrollListView/setSelection(I)V
L0:
aload 0
getfield com/nd/android/u/cloud/activity/mbless/BirthdayRemActivity$3/this$0 Lcom/nd/android/u/cloud/activity/mbless/BirthdayRemActivity;
getfield com/nd/android/u/cloud/activity/mbless/BirthdayRemActivity/mlistView Lcom/nd/android/u/ui/widge/ScrollListView;
invokevirtual com/nd/android/u/ui/widge/ScrollListView/onRefreshComplete()V
return
.limit locals 3
.limit stack 3
.end method
