.bytecode 50.0
.class synchronized com/common/android/utils/smiley/SmileyView$3
.super android/support/v4/view/PagerAdapter
.enclosing method com/common/android/utils/smiley/SmileyView
.inner class inner com/common/android/utils/smiley/SmileyView$3

.field final synthetic 'this$0' Lcom/common/android/utils/smiley/SmileyView;

.method <init>(Lcom/common/android/utils/smiley/SmileyView;)V
aload 0
aload 1
putfield com/common/android/utils/smiley/SmileyView$3/this$0 Lcom/common/android/utils/smiley/SmileyView;
aload 0
invokespecial android/support/v4/view/PagerAdapter/<init>()V
return
.limit locals 2
.limit stack 2
.end method

.method public destroyItem(Landroid/view/ViewGroup;ILjava/lang/Object;)V
aload 1
aload 3
checkcast android/view/View
invokevirtual android/view/ViewGroup/removeView(Landroid/view/View;)V
return
.limit locals 4
.limit stack 2
.end method

.method public getCount()I
aload 0
getfield com/common/android/utils/smiley/SmileyView$3/this$0 Lcom/common/android/utils/smiley/SmileyView;
invokestatic com/common/android/utils/smiley/SmileyView/access$500(Lcom/common/android/utils/smiley/SmileyView;)[I
aload 0
getfield com/common/android/utils/smiley/SmileyView$3/this$0 Lcom/common/android/utils/smiley/SmileyView;
invokestatic com/common/android/utils/smiley/SmileyView/access$300(Lcom/common/android/utils/smiley/SmileyView;)I
iaload
ireturn
.limit locals 1
.limit stack 2
.end method

.method public getItemPosition(Ljava/lang/Object;)I
bipush -2
ireturn
.limit locals 2
.limit stack 1
.end method

.method public instantiateItem(Landroid/view/ViewGroup;I)Ljava/lang/Object;
aload 0
getfield com/common/android/utils/smiley/SmileyView$3/this$0 Lcom/common/android/utils/smiley/SmileyView;
invokestatic com/common/android/utils/smiley/SmileyView/access$600(Lcom/common/android/utils/smiley/SmileyView;)Landroid/view/LayoutInflater;
getstatic com/nd/android/u/allcommon/R$layout/smiley_grid I
aconst_null
invokevirtual android/view/LayoutInflater/inflate(ILandroid/view/ViewGroup;)Landroid/view/View;
checkcast android/widget/LinearLayout
astore 3
aload 3
getstatic com/nd/android/u/allcommon/R$id/gridview I
invokevirtual android/widget/LinearLayout/findViewById(I)Landroid/view/View;
checkcast android/widget/GridView
astore 4
aload 4
aload 0
getfield com/common/android/utils/smiley/SmileyView$3/this$0 Lcom/common/android/utils/smiley/SmileyView;
invokestatic com/common/android/utils/smiley/SmileyView/access$700(Lcom/common/android/utils/smiley/SmileyView;)[I
aload 0
getfield com/common/android/utils/smiley/SmileyView$3/this$0 Lcom/common/android/utils/smiley/SmileyView;
invokestatic com/common/android/utils/smiley/SmileyView/access$300(Lcom/common/android/utils/smiley/SmileyView;)I
iaload
invokevirtual android/widget/GridView/setNumColumns(I)V
new com/common/android/utils/smiley/SmileyAdapter
dup
aload 0
getfield com/common/android/utils/smiley/SmileyView$3/this$0 Lcom/common/android/utils/smiley/SmileyView;
invokestatic com/common/android/utils/smiley/SmileyView/access$800(Lcom/common/android/utils/smiley/SmileyView;)Landroid/content/Context;
aload 0
getfield com/common/android/utils/smiley/SmileyView$3/this$0 Lcom/common/android/utils/smiley/SmileyView;
invokestatic com/common/android/utils/smiley/SmileyView/access$300(Lcom/common/android/utils/smiley/SmileyView;)I
invokespecial com/common/android/utils/smiley/SmileyAdapter/<init>(Landroid/content/Context;I)V
astore 5
aload 5
iload 2
invokevirtual com/common/android/utils/smiley/SmileyAdapter/setPageNo(I)V
aload 4
aload 5
invokevirtual android/widget/GridView/setAdapter(Landroid/widget/ListAdapter;)V
aload 4
aload 0
getfield com/common/android/utils/smiley/SmileyView$3/this$0 Lcom/common/android/utils/smiley/SmileyView;
invokestatic com/common/android/utils/smiley/SmileyView/access$900(Lcom/common/android/utils/smiley/SmileyView;)Landroid/widget/AdapterView$OnItemClickListener;
invokevirtual android/widget/GridView/setOnItemClickListener(Landroid/widget/AdapterView$OnItemClickListener;)V
aload 4
aload 0
getfield com/common/android/utils/smiley/SmileyView$3/this$0 Lcom/common/android/utils/smiley/SmileyView;
invokestatic com/common/android/utils/smiley/SmileyView/access$1000(Lcom/common/android/utils/smiley/SmileyView;)Lcom/common/android/utils/smiley/SmileyView$OnSmileyDelTouchListener;
invokevirtual android/widget/GridView/setOnTouchListener(Landroid/view/View$OnTouchListener;)V
aload 1
aload 3
invokevirtual android/view/ViewGroup/addView(Landroid/view/View;)V
aload 3
areturn
.limit locals 6
.limit stack 4
.end method

.method public isViewFromObject(Landroid/view/View;Ljava/lang/Object;)Z
aload 1
aload 2
if_acmpne L0
iconst_1
ireturn
L0:
iconst_0
ireturn
.limit locals 3
.limit stack 2
.end method

.method public saveState()Landroid/os/Parcelable;
aconst_null
areturn
.limit locals 1
.limit stack 1
.end method
