.bytecode 50.0
.class synchronized com/common/android/utils/smiley/SmileyView$OnSmileyDelTouchListener
.super java/lang/Object
.implements android/view/View$OnTouchListener
.inner class OnSmileyDelTouchListener inner com/common/android/utils/smiley/SmileyView$OnSmileyDelTouchListener outer com/common/android/utils/smiley/SmileyView
.inner class inner com/common/android/utils/smiley/SmileyView$OnSmileyDelTouchListener$1

.field 'TIME' I

.field final synthetic 'this$0' Lcom/common/android/utils/smiley/SmileyView;

.method <init>(Lcom/common/android/utils/smiley/SmileyView;)V
aload 0
aload 1
putfield com/common/android/utils/smiley/SmileyView$OnSmileyDelTouchListener/this$0 Lcom/common/android/utils/smiley/SmileyView;
aload 0
invokespecial java/lang/Object/<init>()V
aload 0
sipush 150
putfield com/common/android/utils/smiley/SmileyView$OnSmileyDelTouchListener/TIME I
return
.limit locals 2
.limit stack 2
.end method

.method public onTouch(Landroid/view/View;Landroid/view/MotionEvent;)Z
aload 2
invokevirtual android/view/MotionEvent/getAction()I
ifne L0
aload 1
checkcast android/widget/GridView
astore 1
aload 1
aload 2
invokevirtual android/view/MotionEvent/getX()F
f2i
aload 2
invokevirtual android/view/MotionEvent/getY()F
f2i
invokevirtual android/widget/GridView/pointToPosition(II)I
istore 3
aload 1
invokevirtual android/widget/GridView/getAdapter()Landroid/widget/ListAdapter;
checkcast com/common/android/utils/smiley/SmileyAdapter
astore 1
iload 3
ifge L1
L2:
iconst_0
ireturn
L1:
aload 1
iload 3
invokevirtual com/common/android/utils/smiley/SmileyAdapter/getItem(I)Ljava/lang/Object;
checkcast com/common/android/utils/smiley/Smiley
astore 1
aload 1
ifnull L2
aload 1
getfield com/common/android/utils/smiley/Smiley/id I
sipush 993
if_icmpne L2
aload 0
getfield com/common/android/utils/smiley/SmileyView$OnSmileyDelTouchListener/this$0 Lcom/common/android/utils/smiley/SmileyView;
iconst_1
putfield com/common/android/utils/smiley/SmileyView/mIsTouchDel Z
new com/common/android/utils/smiley/SmileyView$OnSmileyDelTouchListener$1
dup
aload 0
invokespecial com/common/android/utils/smiley/SmileyView$OnSmileyDelTouchListener$1/<init>(Lcom/common/android/utils/smiley/SmileyView$OnSmileyDelTouchListener;)V
invokevirtual java/lang/Thread/start()V
iconst_0
ireturn
L0:
aload 2
invokevirtual android/view/MotionEvent/getAction()I
iconst_1
if_icmpne L2
aload 0
getfield com/common/android/utils/smiley/SmileyView$OnSmileyDelTouchListener/this$0 Lcom/common/android/utils/smiley/SmileyView;
iconst_0
putfield com/common/android/utils/smiley/SmileyView/mIsTouchDel Z
iconst_0
ireturn
.limit locals 4
.limit stack 3
.end method
