.bytecode 50.0
.class synchronized com/common/android/utils/smiley/SmileyView$5
.super java/lang/Object
.implements android/widget/AdapterView$OnItemClickListener
.enclosing method com/common/android/utils/smiley/SmileyView
.inner class inner com/common/android/utils/smiley/SmileyView$5
.inner class inner com/common/android/utils/smiley/SmileyView$5$1

.field final synthetic 'this$0' Lcom/common/android/utils/smiley/SmileyView;

.method <init>(Lcom/common/android/utils/smiley/SmileyView;)V
aload 0
aload 1
putfield com/common/android/utils/smiley/SmileyView$5/this$0 Lcom/common/android/utils/smiley/SmileyView;
aload 0
invokespecial java/lang/Object/<init>()V
return
.limit locals 2
.limit stack 2
.end method

.method public onItemClick(Landroid/widget/AdapterView;Landroid/view/View;IJ)V
.signature "(Landroid/widget/AdapterView<*>;Landroid/view/View;IJ)V"
aload 1
invokevirtual android/widget/AdapterView/getAdapter()Landroid/widget/Adapter;
checkcast com/common/android/utils/smiley/SmileyAdapter
iload 3
invokevirtual com/common/android/utils/smiley/SmileyAdapter/getItem(I)Ljava/lang/Object;
checkcast com/common/android/utils/smiley/Smiley
astore 1
aload 0
getfield com/common/android/utils/smiley/SmileyView$5/this$0 Lcom/common/android/utils/smiley/SmileyView;
aload 1
invokestatic com/common/android/utils/smiley/SmileyView/access$1200(Lcom/common/android/utils/smiley/SmileyView;Lcom/common/android/utils/smiley/Smiley;)Z
ifeq L0
L1:
return
L0:
aload 1
getfield com/common/android/utils/smiley/Smiley/id I
istore 3
invokestatic com/common/android/utils/smiley/Smileyhelper/getInstance()Lcom/common/android/utils/smiley/Smileyhelper;
aload 0
getfield com/common/android/utils/smiley/SmileyView$5/this$0 Lcom/common/android/utils/smiley/SmileyView;
invokestatic com/common/android/utils/smiley/SmileyView/access$800(Lcom/common/android/utils/smiley/SmileyView;)Landroid/content/Context;
iload 3
invokevirtual com/common/android/utils/smiley/Smileyhelper/getSmileyById(Landroid/content/Context;I)Landroid/graphics/drawable/Drawable;
astore 2
aload 2
ifnull L1
invokestatic com/common/android/utils/smiley/Smileyhelper/getInstance()Lcom/common/android/utils/smiley/Smileyhelper;
iload 3
invokevirtual com/common/android/utils/smiley/Smileyhelper/isCatID(I)Z
ifne L2
invokestatic com/common/android/utils/smiley/Smileyhelper/getInstance()Lcom/common/android/utils/smiley/Smileyhelper;
iload 3
invokevirtual com/common/android/utils/smiley/Smileyhelper/isCosID(I)Z
ifeq L3
L2:
aload 0
getfield com/common/android/utils/smiley/SmileyView$5/this$0 Lcom/common/android/utils/smiley/SmileyView;
invokestatic com/common/android/utils/smiley/SmileyView/access$1300(Lcom/common/android/utils/smiley/SmileyView;)Lcom/common/android/utils/smiley/SmileyView$OnSelectGifListener;
ifnull L4
aload 0
getfield com/common/android/utils/smiley/SmileyView$5/this$0 Lcom/common/android/utils/smiley/SmileyView;
invokestatic com/common/android/utils/smiley/SmileyView/access$1300(Lcom/common/android/utils/smiley/SmileyView;)Lcom/common/android/utils/smiley/SmileyView$OnSelectGifListener;
aload 1
invokeinterface com/common/android/utils/smiley/SmileyView$OnSelectGifListener/onSelectGifSmiley(Lcom/common/android/utils/smiley/Smiley;)V 1
L4:
iload 3
sipush 993
if_icmpeq L1
invokestatic com/common/android/utils/concurrent/NdExecutors/getCachedThreadPool()Ljava/util/concurrent/ExecutorService;
new com/common/android/utils/smiley/SmileyView$5$1
dup
aload 0
aload 1
invokespecial com/common/android/utils/smiley/SmileyView$5$1/<init>(Lcom/common/android/utils/smiley/SmileyView$5;Lcom/common/android/utils/smiley/Smiley;)V
invokeinterface java/util/concurrent/ExecutorService/submit(Ljava/lang/Runnable;)Ljava/util/concurrent/Future; 1
pop
return
L3:
invokestatic com/common/android/utils/smiley/Smileyhelper/getInstance()Lcom/common/android/utils/smiley/Smileyhelper;
iload 3
aload 2
aload 0
getfield com/common/android/utils/smiley/SmileyView$5/this$0 Lcom/common/android/utils/smiley/SmileyView;
invokestatic com/common/android/utils/smiley/SmileyView/access$1100(Lcom/common/android/utils/smiley/SmileyView;)Landroid/widget/EditText;
aload 0
getfield com/common/android/utils/smiley/SmileyView$5/this$0 Lcom/common/android/utils/smiley/SmileyView;
invokestatic com/common/android/utils/smiley/SmileyView/access$1400(Lcom/common/android/utils/smiley/SmileyView;)I
aload 0
getfield com/common/android/utils/smiley/SmileyView$5/this$0 Lcom/common/android/utils/smiley/SmileyView;
invokestatic com/common/android/utils/smiley/SmileyView/access$1500(Lcom/common/android/utils/smiley/SmileyView;)I
aload 0
getfield com/common/android/utils/smiley/SmileyView$5/this$0 Lcom/common/android/utils/smiley/SmileyView;
invokestatic com/common/android/utils/smiley/SmileyView/access$1600(Lcom/common/android/utils/smiley/SmileyView;)I
aload 0
getfield com/common/android/utils/smiley/SmileyView$5/this$0 Lcom/common/android/utils/smiley/SmileyView;
invokestatic com/common/android/utils/smiley/SmileyView/access$1700(Lcom/common/android/utils/smiley/SmileyView;)Lcom/common/android/utils/smiley/SmileyView$GetWordLengthConfig;
aload 0
getfield com/common/android/utils/smiley/SmileyView$5/this$0 Lcom/common/android/utils/smiley/SmileyView;
invokestatic com/common/android/utils/smiley/SmileyView/access$1800(Lcom/common/android/utils/smiley/SmileyView;)Lcom/common/android/utils/smiley/SmileyView$OnSmileyCutListener;
invokevirtual com/common/android/utils/smiley/Smileyhelper/setSpannableToEditText(ILandroid/graphics/drawable/Drawable;Landroid/widget/EditText;IIILcom/common/android/utils/smiley/SmileyView$GetWordLengthConfig;Lcom/common/android/utils/smiley/SmileyView$OnSmileyCutListener;)V
goto L4
.limit locals 6
.limit stack 9
.end method
