.bytecode 50.0
.class synchronized com/product/android/ui/widget/ScrollDoubleLayout$2
.super android/os/Handler
.enclosing method com/product/android/ui/widget/ScrollDoubleLayout
.inner class inner com/product/android/ui/widget/ScrollDoubleLayout$2

.field final synthetic 'this$0' Lcom/product/android/ui/widget/ScrollDoubleLayout;

.method <init>(Lcom/product/android/ui/widget/ScrollDoubleLayout;)V
aload 0
aload 1
putfield com/product/android/ui/widget/ScrollDoubleLayout$2/this$0 Lcom/product/android/ui/widget/ScrollDoubleLayout;
aload 0
invokespecial android/os/Handler/<init>()V
return
.limit locals 2
.limit stack 2
.end method

.method public handleMessage(Landroid/os/Message;)V
.catch java/lang/Exception from L0 to L1 using L2
.catch java/lang/Exception from L3 to L4 using L5
.catch java/lang/Exception from L6 to L7 using L8
.catch java/lang/Exception from L9 to L10 using L11
.catch java/lang/Exception from L12 to L13 using L14
.catch java/lang/Exception from L15 to L16 using L17
aload 0
aload 1
invokespecial android/os/Handler/handleMessage(Landroid/os/Message;)V
ldc ""
astore 10
ldc ""
astore 6
ldc ""
astore 7
ldc ""
astore 8
ldc ""
astore 9
ldc ""
astore 15
ldc ""
astore 11
ldc ""
astore 12
ldc ""
astore 13
ldc ""
astore 14
aload 0
getfield com/product/android/ui/widget/ScrollDoubleLayout$2/this$0 Lcom/product/android/ui/widget/ScrollDoubleLayout;
invokestatic com/product/android/ui/widget/ScrollDoubleLayout/access$000(Lcom/product/android/ui/widget/ScrollDoubleLayout;)I
iconst_m1
if_icmpeq L18
getstatic com/product/android/ui/widget/ScrollDoubleLayout/mdata12 Ljava/util/List;
invokeinterface java/util/List/size()I 0
aload 0
getfield com/product/android/ui/widget/ScrollDoubleLayout$2/this$0 Lcom/product/android/ui/widget/ScrollDoubleLayout;
invokestatic com/product/android/ui/widget/ScrollDoubleLayout/access$000(Lcom/product/android/ui/widget/ScrollDoubleLayout;)I
if_icmpgt L19
ldc "ScrollDoubleLayout"
new java/lang/StringBuilder
dup
invokespecial java/lang/StringBuilder/<init>()V
ldc "handler:"
invokevirtual java/lang/StringBuilder/append(Ljava/lang/String;)Ljava/lang/StringBuilder;
getstatic com/product/android/ui/widget/ScrollDoubleLayout/mdata12 Ljava/util/List;
invokeinterface java/util/List/size()I 0
invokevirtual java/lang/StringBuilder/append(I)Ljava/lang/StringBuilder;
ldc "-"
invokevirtual java/lang/StringBuilder/append(Ljava/lang/String;)Ljava/lang/StringBuilder;
aload 0
getfield com/product/android/ui/widget/ScrollDoubleLayout$2/this$0 Lcom/product/android/ui/widget/ScrollDoubleLayout;
invokestatic com/product/android/ui/widget/ScrollDoubleLayout/access$000(Lcom/product/android/ui/widget/ScrollDoubleLayout;)I
invokevirtual java/lang/StringBuilder/append(I)Ljava/lang/StringBuilder;
invokevirtual java/lang/StringBuilder/toString()Ljava/lang/String;
invokestatic com/product/android/utils/LogUtils/e(Ljava/lang/String;Ljava/lang/String;)V
return
L19:
getstatic com/product/android/ui/widget/ScrollDoubleLayout/mdata12 Ljava/util/List;
aload 0
getfield com/product/android/ui/widget/ScrollDoubleLayout$2/this$0 Lcom/product/android/ui/widget/ScrollDoubleLayout;
invokestatic com/product/android/ui/widget/ScrollDoubleLayout/access$000(Lcom/product/android/ui/widget/ScrollDoubleLayout;)I
invokeinterface java/util/List/get(I)Ljava/lang/Object; 1
checkcast [Ljava/lang/String;
arraylength
iconst_4
if_icmpgt L20
ldc "ScrollDoubleLayout"
new java/lang/StringBuilder
dup
invokespecial java/lang/StringBuilder/<init>()V
ldc "handler:"
invokevirtual java/lang/StringBuilder/append(Ljava/lang/String;)Ljava/lang/StringBuilder;
getstatic com/product/android/ui/widget/ScrollDoubleLayout/mdata12 Ljava/util/List;
aload 0
getfield com/product/android/ui/widget/ScrollDoubleLayout$2/this$0 Lcom/product/android/ui/widget/ScrollDoubleLayout;
invokestatic com/product/android/ui/widget/ScrollDoubleLayout/access$000(Lcom/product/android/ui/widget/ScrollDoubleLayout;)I
invokeinterface java/util/List/get(I)Ljava/lang/Object; 1
checkcast [Ljava/lang/String;
arraylength
invokevirtual java/lang/StringBuilder/append(I)Ljava/lang/StringBuilder;
invokevirtual java/lang/StringBuilder/toString()Ljava/lang/String;
invokestatic com/product/android/utils/LogUtils/e(Ljava/lang/String;Ljava/lang/String;)V
return
L20:
getstatic com/product/android/ui/widget/ScrollDoubleLayout/mdata12 Ljava/util/List;
aload 0
getfield com/product/android/ui/widget/ScrollDoubleLayout$2/this$0 Lcom/product/android/ui/widget/ScrollDoubleLayout;
invokestatic com/product/android/ui/widget/ScrollDoubleLayout/access$000(Lcom/product/android/ui/widget/ScrollDoubleLayout;)I
invokeinterface java/util/List/get(I)Ljava/lang/Object; 1
checkcast [Ljava/lang/String;
iconst_0
aaload
astore 10
getstatic com/product/android/ui/widget/ScrollDoubleLayout/mdata12 Ljava/util/List;
aload 0
getfield com/product/android/ui/widget/ScrollDoubleLayout$2/this$0 Lcom/product/android/ui/widget/ScrollDoubleLayout;
invokestatic com/product/android/ui/widget/ScrollDoubleLayout/access$000(Lcom/product/android/ui/widget/ScrollDoubleLayout;)I
invokeinterface java/util/List/get(I)Ljava/lang/Object; 1
checkcast [Ljava/lang/String;
iconst_1
aaload
astore 6
getstatic com/product/android/ui/widget/ScrollDoubleLayout/mdata12 Ljava/util/List;
aload 0
getfield com/product/android/ui/widget/ScrollDoubleLayout$2/this$0 Lcom/product/android/ui/widget/ScrollDoubleLayout;
invokestatic com/product/android/ui/widget/ScrollDoubleLayout/access$000(Lcom/product/android/ui/widget/ScrollDoubleLayout;)I
invokeinterface java/util/List/get(I)Ljava/lang/Object; 1
checkcast [Ljava/lang/String;
iconst_2
aaload
astore 7
getstatic com/product/android/ui/widget/ScrollDoubleLayout/mdata12 Ljava/util/List;
aload 0
getfield com/product/android/ui/widget/ScrollDoubleLayout$2/this$0 Lcom/product/android/ui/widget/ScrollDoubleLayout;
invokestatic com/product/android/ui/widget/ScrollDoubleLayout/access$000(Lcom/product/android/ui/widget/ScrollDoubleLayout;)I
invokeinterface java/util/List/get(I)Ljava/lang/Object; 1
checkcast [Ljava/lang/String;
iconst_3
aaload
astore 8
getstatic com/product/android/ui/widget/ScrollDoubleLayout/mdata12 Ljava/util/List;
aload 0
getfield com/product/android/ui/widget/ScrollDoubleLayout$2/this$0 Lcom/product/android/ui/widget/ScrollDoubleLayout;
invokestatic com/product/android/ui/widget/ScrollDoubleLayout/access$000(Lcom/product/android/ui/widget/ScrollDoubleLayout;)I
invokeinterface java/util/List/get(I)Ljava/lang/Object; 1
checkcast [Ljava/lang/String;
iconst_4
aaload
astore 9
aload 0
getfield com/product/android/ui/widget/ScrollDoubleLayout$2/this$0 Lcom/product/android/ui/widget/ScrollDoubleLayout;
invokestatic com/product/android/ui/widget/ScrollDoubleLayout/access$008(Lcom/product/android/ui/widget/ScrollDoubleLayout;)I
pop
L18:
aload 0
getfield com/product/android/ui/widget/ScrollDoubleLayout$2/this$0 Lcom/product/android/ui/widget/ScrollDoubleLayout;
invokestatic com/product/android/ui/widget/ScrollDoubleLayout/access$100(Lcom/product/android/ui/widget/ScrollDoubleLayout;)I
iconst_m1
if_icmpeq L21
getstatic com/product/android/ui/widget/ScrollDoubleLayout/mdata34 Ljava/util/List;
invokeinterface java/util/List/size()I 0
aload 0
getfield com/product/android/ui/widget/ScrollDoubleLayout$2/this$0 Lcom/product/android/ui/widget/ScrollDoubleLayout;
invokestatic com/product/android/ui/widget/ScrollDoubleLayout/access$100(Lcom/product/android/ui/widget/ScrollDoubleLayout;)I
if_icmpgt L22
ldc "ScrollDoubleLayout"
new java/lang/StringBuilder
dup
invokespecial java/lang/StringBuilder/<init>()V
ldc "handler:"
invokevirtual java/lang/StringBuilder/append(Ljava/lang/String;)Ljava/lang/StringBuilder;
getstatic com/product/android/ui/widget/ScrollDoubleLayout/mdata34 Ljava/util/List;
invokeinterface java/util/List/size()I 0
invokevirtual java/lang/StringBuilder/append(I)Ljava/lang/StringBuilder;
ldc "-"
invokevirtual java/lang/StringBuilder/append(Ljava/lang/String;)Ljava/lang/StringBuilder;
aload 0
getfield com/product/android/ui/widget/ScrollDoubleLayout$2/this$0 Lcom/product/android/ui/widget/ScrollDoubleLayout;
invokestatic com/product/android/ui/widget/ScrollDoubleLayout/access$100(Lcom/product/android/ui/widget/ScrollDoubleLayout;)I
invokevirtual java/lang/StringBuilder/append(I)Ljava/lang/StringBuilder;
invokevirtual java/lang/StringBuilder/toString()Ljava/lang/String;
invokestatic com/product/android/utils/LogUtils/e(Ljava/lang/String;Ljava/lang/String;)V
return
L22:
getstatic com/product/android/ui/widget/ScrollDoubleLayout/mdata34 Ljava/util/List;
aload 0
getfield com/product/android/ui/widget/ScrollDoubleLayout$2/this$0 Lcom/product/android/ui/widget/ScrollDoubleLayout;
invokestatic com/product/android/ui/widget/ScrollDoubleLayout/access$100(Lcom/product/android/ui/widget/ScrollDoubleLayout;)I
invokeinterface java/util/List/get(I)Ljava/lang/Object; 1
checkcast [Ljava/lang/String;
arraylength
iconst_4
if_icmpgt L23
ldc "ScrollDoubleLayout"
new java/lang/StringBuilder
dup
invokespecial java/lang/StringBuilder/<init>()V
ldc "handler:"
invokevirtual java/lang/StringBuilder/append(Ljava/lang/String;)Ljava/lang/StringBuilder;
getstatic com/product/android/ui/widget/ScrollDoubleLayout/mdata34 Ljava/util/List;
aload 0
getfield com/product/android/ui/widget/ScrollDoubleLayout$2/this$0 Lcom/product/android/ui/widget/ScrollDoubleLayout;
invokestatic com/product/android/ui/widget/ScrollDoubleLayout/access$100(Lcom/product/android/ui/widget/ScrollDoubleLayout;)I
invokeinterface java/util/List/get(I)Ljava/lang/Object; 1
checkcast [Ljava/lang/String;
arraylength
invokevirtual java/lang/StringBuilder/append(I)Ljava/lang/StringBuilder;
invokevirtual java/lang/StringBuilder/toString()Ljava/lang/String;
invokestatic com/product/android/utils/LogUtils/e(Ljava/lang/String;Ljava/lang/String;)V
return
L23:
getstatic com/product/android/ui/widget/ScrollDoubleLayout/mdata34 Ljava/util/List;
aload 0
getfield com/product/android/ui/widget/ScrollDoubleLayout$2/this$0 Lcom/product/android/ui/widget/ScrollDoubleLayout;
invokestatic com/product/android/ui/widget/ScrollDoubleLayout/access$100(Lcom/product/android/ui/widget/ScrollDoubleLayout;)I
invokeinterface java/util/List/get(I)Ljava/lang/Object; 1
checkcast [Ljava/lang/String;
iconst_0
aaload
astore 15
getstatic com/product/android/ui/widget/ScrollDoubleLayout/mdata34 Ljava/util/List;
aload 0
getfield com/product/android/ui/widget/ScrollDoubleLayout$2/this$0 Lcom/product/android/ui/widget/ScrollDoubleLayout;
invokestatic com/product/android/ui/widget/ScrollDoubleLayout/access$100(Lcom/product/android/ui/widget/ScrollDoubleLayout;)I
invokeinterface java/util/List/get(I)Ljava/lang/Object; 1
checkcast [Ljava/lang/String;
iconst_1
aaload
astore 11
getstatic com/product/android/ui/widget/ScrollDoubleLayout/mdata34 Ljava/util/List;
aload 0
getfield com/product/android/ui/widget/ScrollDoubleLayout$2/this$0 Lcom/product/android/ui/widget/ScrollDoubleLayout;
invokestatic com/product/android/ui/widget/ScrollDoubleLayout/access$100(Lcom/product/android/ui/widget/ScrollDoubleLayout;)I
invokeinterface java/util/List/get(I)Ljava/lang/Object; 1
checkcast [Ljava/lang/String;
iconst_2
aaload
astore 12
getstatic com/product/android/ui/widget/ScrollDoubleLayout/mdata34 Ljava/util/List;
aload 0
getfield com/product/android/ui/widget/ScrollDoubleLayout$2/this$0 Lcom/product/android/ui/widget/ScrollDoubleLayout;
invokestatic com/product/android/ui/widget/ScrollDoubleLayout/access$100(Lcom/product/android/ui/widget/ScrollDoubleLayout;)I
invokeinterface java/util/List/get(I)Ljava/lang/Object; 1
checkcast [Ljava/lang/String;
iconst_3
aaload
astore 13
getstatic com/product/android/ui/widget/ScrollDoubleLayout/mdata34 Ljava/util/List;
aload 0
getfield com/product/android/ui/widget/ScrollDoubleLayout$2/this$0 Lcom/product/android/ui/widget/ScrollDoubleLayout;
invokestatic com/product/android/ui/widget/ScrollDoubleLayout/access$100(Lcom/product/android/ui/widget/ScrollDoubleLayout;)I
invokeinterface java/util/List/get(I)Ljava/lang/Object; 1
checkcast [Ljava/lang/String;
iconst_4
aaload
astore 14
aload 0
getfield com/product/android/ui/widget/ScrollDoubleLayout$2/this$0 Lcom/product/android/ui/widget/ScrollDoubleLayout;
invokestatic com/product/android/ui/widget/ScrollDoubleLayout/access$108(Lcom/product/android/ui/widget/ScrollDoubleLayout;)I
pop
L21:
aload 1
getfield android/os/Message/what I
tableswitch 0
L24
L25
L26
L27
default : L28
L28:
return
L24:
aload 0
getfield com/product/android/ui/widget/ScrollDoubleLayout$2/this$0 Lcom/product/android/ui/widget/ScrollDoubleLayout;
invokestatic com/product/android/ui/widget/ScrollDoubleLayout/access$000(Lcom/product/android/ui/widget/ScrollDoubleLayout;)I
iconst_m1
if_icmpeq L29
lconst_0
lstore 2
L0:
aload 10
invokestatic java/lang/Long/parseLong(Ljava/lang/String;)J
lstore 4
L1:
lload 4
lstore 2
L30:
aload 0
getfield com/product/android/ui/widget/ScrollDoubleLayout$2/this$0 Lcom/product/android/ui/widget/ScrollDoubleLayout;
lload 2
aload 0
getfield com/product/android/ui/widget/ScrollDoubleLayout$2/this$0 Lcom/product/android/ui/widget/ScrollDoubleLayout;
getfield com/product/android/ui/widget/ScrollDoubleLayout/lot_user1_head Landroid/widget/ImageView;
invokestatic com/product/android/ui/widget/ScrollDoubleLayout/access$300(Lcom/product/android/ui/widget/ScrollDoubleLayout;JLandroid/widget/ImageView;)V
aload 0
getfield com/product/android/ui/widget/ScrollDoubleLayout$2/this$0 Lcom/product/android/ui/widget/ScrollDoubleLayout;
aload 0
getfield com/product/android/ui/widget/ScrollDoubleLayout$2/this$0 Lcom/product/android/ui/widget/ScrollDoubleLayout;
getfield com/product/android/ui/widget/ScrollDoubleLayout/lot_user1_depart Landroid/widget/TextView;
aload 6
invokevirtual com/product/android/ui/widget/ScrollDoubleLayout/setDepartment(Landroid/widget/TextView;Ljava/lang/String;)V
aload 0
getfield com/product/android/ui/widget/ScrollDoubleLayout$2/this$0 Lcom/product/android/ui/widget/ScrollDoubleLayout;
getfield com/product/android/ui/widget/ScrollDoubleLayout/lot_user1_name Landroid/widget/TextView;
aload 7
invokevirtual android/widget/TextView/setText(Ljava/lang/CharSequence;)V
aload 0
getfield com/product/android/ui/widget/ScrollDoubleLayout$2/this$0 Lcom/product/android/ui/widget/ScrollDoubleLayout;
getfield com/product/android/ui/widget/ScrollDoubleLayout/lot_user1_prise Landroid/widget/TextView;
aload 8
invokevirtual android/widget/TextView/setText(Ljava/lang/CharSequence;)V
aload 0
getfield com/product/android/ui/widget/ScrollDoubleLayout$2/this$0 Lcom/product/android/ui/widget/ScrollDoubleLayout;
getfield com/product/android/ui/widget/ScrollDoubleLayout/lot_user1_time Landroid/widget/TextView;
aload 9
invokevirtual android/widget/TextView/setText(Ljava/lang/CharSequence;)V
aload 0
getfield com/product/android/ui/widget/ScrollDoubleLayout$2/this$0 Lcom/product/android/ui/widget/ScrollDoubleLayout;
getfield com/product/android/ui/widget/ScrollDoubleLayout/lot_user1 Landroid/widget/RelativeLayout;
iconst_0
invokevirtual android/widget/RelativeLayout/setVisibility(I)V
aload 0
getfield com/product/android/ui/widget/ScrollDoubleLayout$2/this$0 Lcom/product/android/ui/widget/ScrollDoubleLayout;
getfield com/product/android/ui/widget/ScrollDoubleLayout/lot_user2 Landroid/widget/RelativeLayout;
iconst_0
invokevirtual android/widget/RelativeLayout/setVisibility(I)V
L29:
aload 0
getfield com/product/android/ui/widget/ScrollDoubleLayout$2/this$0 Lcom/product/android/ui/widget/ScrollDoubleLayout;
invokestatic com/product/android/ui/widget/ScrollDoubleLayout/access$100(Lcom/product/android/ui/widget/ScrollDoubleLayout;)I
iconst_m1
if_icmpeq L31
lconst_0
lstore 2
L3:
aload 15
invokestatic java/lang/Long/parseLong(Ljava/lang/String;)J
lstore 4
L4:
lload 4
lstore 2
L32:
aload 0
getfield com/product/android/ui/widget/ScrollDoubleLayout$2/this$0 Lcom/product/android/ui/widget/ScrollDoubleLayout;
lload 2
aload 0
getfield com/product/android/ui/widget/ScrollDoubleLayout$2/this$0 Lcom/product/android/ui/widget/ScrollDoubleLayout;
getfield com/product/android/ui/widget/ScrollDoubleLayout/lot_user3_head Landroid/widget/ImageView;
invokestatic com/product/android/ui/widget/ScrollDoubleLayout/access$300(Lcom/product/android/ui/widget/ScrollDoubleLayout;JLandroid/widget/ImageView;)V
aload 0
getfield com/product/android/ui/widget/ScrollDoubleLayout$2/this$0 Lcom/product/android/ui/widget/ScrollDoubleLayout;
aload 0
getfield com/product/android/ui/widget/ScrollDoubleLayout$2/this$0 Lcom/product/android/ui/widget/ScrollDoubleLayout;
getfield com/product/android/ui/widget/ScrollDoubleLayout/lot_user3_depart Landroid/widget/TextView;
aload 11
invokevirtual com/product/android/ui/widget/ScrollDoubleLayout/setDepartment(Landroid/widget/TextView;Ljava/lang/String;)V
aload 0
getfield com/product/android/ui/widget/ScrollDoubleLayout$2/this$0 Lcom/product/android/ui/widget/ScrollDoubleLayout;
getfield com/product/android/ui/widget/ScrollDoubleLayout/lot_user3_name Landroid/widget/TextView;
aload 12
invokevirtual android/widget/TextView/setText(Ljava/lang/CharSequence;)V
aload 0
getfield com/product/android/ui/widget/ScrollDoubleLayout$2/this$0 Lcom/product/android/ui/widget/ScrollDoubleLayout;
getfield com/product/android/ui/widget/ScrollDoubleLayout/lot_user3_prise Landroid/widget/TextView;
aload 13
invokevirtual android/widget/TextView/setText(Ljava/lang/CharSequence;)V
aload 0
getfield com/product/android/ui/widget/ScrollDoubleLayout$2/this$0 Lcom/product/android/ui/widget/ScrollDoubleLayout;
getfield com/product/android/ui/widget/ScrollDoubleLayout/lot_user3_time Landroid/widget/TextView;
aload 14
invokevirtual android/widget/TextView/setText(Ljava/lang/CharSequence;)V
aload 0
getfield com/product/android/ui/widget/ScrollDoubleLayout$2/this$0 Lcom/product/android/ui/widget/ScrollDoubleLayout;
getfield com/product/android/ui/widget/ScrollDoubleLayout/lot_user3 Landroid/widget/RelativeLayout;
iconst_0
invokevirtual android/widget/RelativeLayout/setVisibility(I)V
aload 0
getfield com/product/android/ui/widget/ScrollDoubleLayout$2/this$0 Lcom/product/android/ui/widget/ScrollDoubleLayout;
getfield com/product/android/ui/widget/ScrollDoubleLayout/lot_user4 Landroid/widget/RelativeLayout;
iconst_0
invokevirtual android/widget/RelativeLayout/setVisibility(I)V
L31:
aload 0
getfield com/product/android/ui/widget/ScrollDoubleLayout$2/this$0 Lcom/product/android/ui/widget/ScrollDoubleLayout;
getfield com/product/android/ui/widget/ScrollDoubleLayout/layout13 Landroid/widget/LinearLayout;
iconst_0
invokevirtual android/widget/LinearLayout/setVisibility(I)V
aload 0
getfield com/product/android/ui/widget/ScrollDoubleLayout$2/this$0 Lcom/product/android/ui/widget/ScrollDoubleLayout;
getfield com/product/android/ui/widget/ScrollDoubleLayout/layout24 Landroid/widget/LinearLayout;
bipush 8
invokevirtual android/widget/LinearLayout/setVisibility(I)V
return
L2:
astore 1
aload 1
invokevirtual java/lang/Exception/printStackTrace()V
goto L30
L5:
astore 1
aload 1
invokevirtual java/lang/Exception/printStackTrace()V
goto L32
L25:
aload 0
getfield com/product/android/ui/widget/ScrollDoubleLayout$2/this$0 Lcom/product/android/ui/widget/ScrollDoubleLayout;
invokestatic com/product/android/ui/widget/ScrollDoubleLayout/access$000(Lcom/product/android/ui/widget/ScrollDoubleLayout;)I
iconst_m1
if_icmpeq L33
lconst_0
lstore 2
L6:
aload 10
invokestatic java/lang/Long/parseLong(Ljava/lang/String;)J
lstore 4
L7:
lload 4
lstore 2
L34:
aload 0
getfield com/product/android/ui/widget/ScrollDoubleLayout$2/this$0 Lcom/product/android/ui/widget/ScrollDoubleLayout;
lload 2
aload 0
getfield com/product/android/ui/widget/ScrollDoubleLayout$2/this$0 Lcom/product/android/ui/widget/ScrollDoubleLayout;
getfield com/product/android/ui/widget/ScrollDoubleLayout/lot_user2_head Landroid/widget/ImageView;
invokestatic com/product/android/ui/widget/ScrollDoubleLayout/access$300(Lcom/product/android/ui/widget/ScrollDoubleLayout;JLandroid/widget/ImageView;)V
aload 0
getfield com/product/android/ui/widget/ScrollDoubleLayout$2/this$0 Lcom/product/android/ui/widget/ScrollDoubleLayout;
aload 0
getfield com/product/android/ui/widget/ScrollDoubleLayout$2/this$0 Lcom/product/android/ui/widget/ScrollDoubleLayout;
getfield com/product/android/ui/widget/ScrollDoubleLayout/lot_user2_depart Landroid/widget/TextView;
aload 6
invokevirtual com/product/android/ui/widget/ScrollDoubleLayout/setDepartment(Landroid/widget/TextView;Ljava/lang/String;)V
aload 0
getfield com/product/android/ui/widget/ScrollDoubleLayout$2/this$0 Lcom/product/android/ui/widget/ScrollDoubleLayout;
getfield com/product/android/ui/widget/ScrollDoubleLayout/lot_user2_name Landroid/widget/TextView;
aload 7
invokevirtual android/widget/TextView/setText(Ljava/lang/CharSequence;)V
aload 0
getfield com/product/android/ui/widget/ScrollDoubleLayout$2/this$0 Lcom/product/android/ui/widget/ScrollDoubleLayout;
getfield com/product/android/ui/widget/ScrollDoubleLayout/lot_user2_prise Landroid/widget/TextView;
aload 8
invokevirtual android/widget/TextView/setText(Ljava/lang/CharSequence;)V
aload 0
getfield com/product/android/ui/widget/ScrollDoubleLayout$2/this$0 Lcom/product/android/ui/widget/ScrollDoubleLayout;
getfield com/product/android/ui/widget/ScrollDoubleLayout/lot_user2_time Landroid/widget/TextView;
aload 9
invokevirtual android/widget/TextView/setText(Ljava/lang/CharSequence;)V
L33:
aload 0
getfield com/product/android/ui/widget/ScrollDoubleLayout$2/this$0 Lcom/product/android/ui/widget/ScrollDoubleLayout;
invokestatic com/product/android/ui/widget/ScrollDoubleLayout/access$100(Lcom/product/android/ui/widget/ScrollDoubleLayout;)I
iconst_m1
if_icmpeq L35
lconst_0
lstore 2
L9:
aload 15
invokestatic java/lang/Long/parseLong(Ljava/lang/String;)J
lstore 4
L10:
lload 4
lstore 2
L36:
aload 0
getfield com/product/android/ui/widget/ScrollDoubleLayout$2/this$0 Lcom/product/android/ui/widget/ScrollDoubleLayout;
lload 2
aload 0
getfield com/product/android/ui/widget/ScrollDoubleLayout$2/this$0 Lcom/product/android/ui/widget/ScrollDoubleLayout;
getfield com/product/android/ui/widget/ScrollDoubleLayout/lot_user4_head Landroid/widget/ImageView;
invokestatic com/product/android/ui/widget/ScrollDoubleLayout/access$300(Lcom/product/android/ui/widget/ScrollDoubleLayout;JLandroid/widget/ImageView;)V
aload 0
getfield com/product/android/ui/widget/ScrollDoubleLayout$2/this$0 Lcom/product/android/ui/widget/ScrollDoubleLayout;
aload 0
getfield com/product/android/ui/widget/ScrollDoubleLayout$2/this$0 Lcom/product/android/ui/widget/ScrollDoubleLayout;
getfield com/product/android/ui/widget/ScrollDoubleLayout/lot_user4_depart Landroid/widget/TextView;
aload 11
invokevirtual com/product/android/ui/widget/ScrollDoubleLayout/setDepartment(Landroid/widget/TextView;Ljava/lang/String;)V
aload 0
getfield com/product/android/ui/widget/ScrollDoubleLayout$2/this$0 Lcom/product/android/ui/widget/ScrollDoubleLayout;
getfield com/product/android/ui/widget/ScrollDoubleLayout/lot_user4_name Landroid/widget/TextView;
aload 12
invokevirtual android/widget/TextView/setText(Ljava/lang/CharSequence;)V
aload 0
getfield com/product/android/ui/widget/ScrollDoubleLayout$2/this$0 Lcom/product/android/ui/widget/ScrollDoubleLayout;
getfield com/product/android/ui/widget/ScrollDoubleLayout/lot_user4_prise Landroid/widget/TextView;
aload 13
invokevirtual android/widget/TextView/setText(Ljava/lang/CharSequence;)V
aload 0
getfield com/product/android/ui/widget/ScrollDoubleLayout$2/this$0 Lcom/product/android/ui/widget/ScrollDoubleLayout;
getfield com/product/android/ui/widget/ScrollDoubleLayout/lot_user4_time Landroid/widget/TextView;
aload 14
invokevirtual android/widget/TextView/setText(Ljava/lang/CharSequence;)V
L35:
aload 0
getfield com/product/android/ui/widget/ScrollDoubleLayout$2/this$0 Lcom/product/android/ui/widget/ScrollDoubleLayout;
getfield com/product/android/ui/widget/ScrollDoubleLayout/layout13 Landroid/widget/LinearLayout;
bipush 8
invokevirtual android/widget/LinearLayout/setVisibility(I)V
aload 0
getfield com/product/android/ui/widget/ScrollDoubleLayout$2/this$0 Lcom/product/android/ui/widget/ScrollDoubleLayout;
getfield com/product/android/ui/widget/ScrollDoubleLayout/layout24 Landroid/widget/LinearLayout;
iconst_0
invokevirtual android/widget/LinearLayout/setVisibility(I)V
aload 0
getfield com/product/android/ui/widget/ScrollDoubleLayout$2/this$0 Lcom/product/android/ui/widget/ScrollDoubleLayout;
getfield com/product/android/ui/widget/ScrollDoubleLayout/layout13 Landroid/widget/LinearLayout;
aload 0
getfield com/product/android/ui/widget/ScrollDoubleLayout$2/this$0 Lcom/product/android/ui/widget/ScrollDoubleLayout;
getfield com/product/android/ui/widget/ScrollDoubleLayout/animationSet1 Landroid/view/animation/AnimationSet;
invokevirtual android/widget/LinearLayout/startAnimation(Landroid/view/animation/Animation;)V
aload 0
getfield com/product/android/ui/widget/ScrollDoubleLayout$2/this$0 Lcom/product/android/ui/widget/ScrollDoubleLayout;
getfield com/product/android/ui/widget/ScrollDoubleLayout/layout24 Landroid/widget/LinearLayout;
aload 0
getfield com/product/android/ui/widget/ScrollDoubleLayout$2/this$0 Lcom/product/android/ui/widget/ScrollDoubleLayout;
getfield com/product/android/ui/widget/ScrollDoubleLayout/animationSet2 Landroid/view/animation/AnimationSet;
invokevirtual android/widget/LinearLayout/startAnimation(Landroid/view/animation/Animation;)V
return
L8:
astore 1
aload 1
invokevirtual java/lang/Exception/printStackTrace()V
goto L34
L11:
astore 1
aload 1
invokevirtual java/lang/Exception/printStackTrace()V
goto L36
L26:
aload 0
getfield com/product/android/ui/widget/ScrollDoubleLayout$2/this$0 Lcom/product/android/ui/widget/ScrollDoubleLayout;
invokestatic com/product/android/ui/widget/ScrollDoubleLayout/access$000(Lcom/product/android/ui/widget/ScrollDoubleLayout;)I
iconst_m1
if_icmpeq L37
lconst_0
lstore 2
L12:
aload 10
invokestatic java/lang/Long/parseLong(Ljava/lang/String;)J
lstore 4
L13:
lload 4
lstore 2
L38:
aload 0
getfield com/product/android/ui/widget/ScrollDoubleLayout$2/this$0 Lcom/product/android/ui/widget/ScrollDoubleLayout;
lload 2
aload 0
getfield com/product/android/ui/widget/ScrollDoubleLayout$2/this$0 Lcom/product/android/ui/widget/ScrollDoubleLayout;
getfield com/product/android/ui/widget/ScrollDoubleLayout/lot_user1_head Landroid/widget/ImageView;
invokestatic com/product/android/ui/widget/ScrollDoubleLayout/access$300(Lcom/product/android/ui/widget/ScrollDoubleLayout;JLandroid/widget/ImageView;)V
aload 0
getfield com/product/android/ui/widget/ScrollDoubleLayout$2/this$0 Lcom/product/android/ui/widget/ScrollDoubleLayout;
aload 0
getfield com/product/android/ui/widget/ScrollDoubleLayout$2/this$0 Lcom/product/android/ui/widget/ScrollDoubleLayout;
getfield com/product/android/ui/widget/ScrollDoubleLayout/lot_user1_depart Landroid/widget/TextView;
aload 6
invokevirtual com/product/android/ui/widget/ScrollDoubleLayout/setDepartment(Landroid/widget/TextView;Ljava/lang/String;)V
aload 0
getfield com/product/android/ui/widget/ScrollDoubleLayout$2/this$0 Lcom/product/android/ui/widget/ScrollDoubleLayout;
getfield com/product/android/ui/widget/ScrollDoubleLayout/lot_user1_name Landroid/widget/TextView;
aload 7
invokevirtual android/widget/TextView/setText(Ljava/lang/CharSequence;)V
aload 0
getfield com/product/android/ui/widget/ScrollDoubleLayout$2/this$0 Lcom/product/android/ui/widget/ScrollDoubleLayout;
getfield com/product/android/ui/widget/ScrollDoubleLayout/lot_user1_prise Landroid/widget/TextView;
aload 8
invokevirtual android/widget/TextView/setText(Ljava/lang/CharSequence;)V
aload 0
getfield com/product/android/ui/widget/ScrollDoubleLayout$2/this$0 Lcom/product/android/ui/widget/ScrollDoubleLayout;
getfield com/product/android/ui/widget/ScrollDoubleLayout/lot_user1_time Landroid/widget/TextView;
aload 9
invokevirtual android/widget/TextView/setText(Ljava/lang/CharSequence;)V
L37:
aload 0
getfield com/product/android/ui/widget/ScrollDoubleLayout$2/this$0 Lcom/product/android/ui/widget/ScrollDoubleLayout;
invokestatic com/product/android/ui/widget/ScrollDoubleLayout/access$100(Lcom/product/android/ui/widget/ScrollDoubleLayout;)I
iconst_m1
if_icmpeq L39
lconst_0
lstore 2
L15:
aload 15
invokestatic java/lang/Long/parseLong(Ljava/lang/String;)J
lstore 4
L16:
lload 4
lstore 2
L40:
aload 0
getfield com/product/android/ui/widget/ScrollDoubleLayout$2/this$0 Lcom/product/android/ui/widget/ScrollDoubleLayout;
lload 2
aload 0
getfield com/product/android/ui/widget/ScrollDoubleLayout$2/this$0 Lcom/product/android/ui/widget/ScrollDoubleLayout;
getfield com/product/android/ui/widget/ScrollDoubleLayout/lot_user3_head Landroid/widget/ImageView;
invokestatic com/product/android/ui/widget/ScrollDoubleLayout/access$300(Lcom/product/android/ui/widget/ScrollDoubleLayout;JLandroid/widget/ImageView;)V
aload 0
getfield com/product/android/ui/widget/ScrollDoubleLayout$2/this$0 Lcom/product/android/ui/widget/ScrollDoubleLayout;
aload 0
getfield com/product/android/ui/widget/ScrollDoubleLayout$2/this$0 Lcom/product/android/ui/widget/ScrollDoubleLayout;
getfield com/product/android/ui/widget/ScrollDoubleLayout/lot_user3_depart Landroid/widget/TextView;
aload 11
invokevirtual com/product/android/ui/widget/ScrollDoubleLayout/setDepartment(Landroid/widget/TextView;Ljava/lang/String;)V
aload 0
getfield com/product/android/ui/widget/ScrollDoubleLayout$2/this$0 Lcom/product/android/ui/widget/ScrollDoubleLayout;
getfield com/product/android/ui/widget/ScrollDoubleLayout/lot_user3_name Landroid/widget/TextView;
aload 12
invokevirtual android/widget/TextView/setText(Ljava/lang/CharSequence;)V
aload 0
getfield com/product/android/ui/widget/ScrollDoubleLayout$2/this$0 Lcom/product/android/ui/widget/ScrollDoubleLayout;
getfield com/product/android/ui/widget/ScrollDoubleLayout/lot_user3_prise Landroid/widget/TextView;
aload 13
invokevirtual android/widget/TextView/setText(Ljava/lang/CharSequence;)V
aload 0
getfield com/product/android/ui/widget/ScrollDoubleLayout$2/this$0 Lcom/product/android/ui/widget/ScrollDoubleLayout;
getfield com/product/android/ui/widget/ScrollDoubleLayout/lot_user3_time Landroid/widget/TextView;
aload 14
invokevirtual android/widget/TextView/setText(Ljava/lang/CharSequence;)V
L39:
aload 0
getfield com/product/android/ui/widget/ScrollDoubleLayout$2/this$0 Lcom/product/android/ui/widget/ScrollDoubleLayout;
getfield com/product/android/ui/widget/ScrollDoubleLayout/layout13 Landroid/widget/LinearLayout;
iconst_0
invokevirtual android/widget/LinearLayout/setVisibility(I)V
aload 0
getfield com/product/android/ui/widget/ScrollDoubleLayout$2/this$0 Lcom/product/android/ui/widget/ScrollDoubleLayout;
getfield com/product/android/ui/widget/ScrollDoubleLayout/layout24 Landroid/widget/LinearLayout;
bipush 8
invokevirtual android/widget/LinearLayout/setVisibility(I)V
aload 0
getfield com/product/android/ui/widget/ScrollDoubleLayout$2/this$0 Lcom/product/android/ui/widget/ScrollDoubleLayout;
getfield com/product/android/ui/widget/ScrollDoubleLayout/layout13 Landroid/widget/LinearLayout;
aload 0
getfield com/product/android/ui/widget/ScrollDoubleLayout$2/this$0 Lcom/product/android/ui/widget/ScrollDoubleLayout;
getfield com/product/android/ui/widget/ScrollDoubleLayout/animationSet2 Landroid/view/animation/AnimationSet;
invokevirtual android/widget/LinearLayout/startAnimation(Landroid/view/animation/Animation;)V
aload 0
getfield com/product/android/ui/widget/ScrollDoubleLayout$2/this$0 Lcom/product/android/ui/widget/ScrollDoubleLayout;
getfield com/product/android/ui/widget/ScrollDoubleLayout/layout24 Landroid/widget/LinearLayout;
aload 0
getfield com/product/android/ui/widget/ScrollDoubleLayout$2/this$0 Lcom/product/android/ui/widget/ScrollDoubleLayout;
getfield com/product/android/ui/widget/ScrollDoubleLayout/animationSet1 Landroid/view/animation/AnimationSet;
invokevirtual android/widget/LinearLayout/startAnimation(Landroid/view/animation/Animation;)V
return
L14:
astore 1
aload 1
invokevirtual java/lang/Exception/printStackTrace()V
goto L38
L17:
astore 1
aload 1
invokevirtual java/lang/Exception/printStackTrace()V
goto L40
L27:
aload 0
getfield com/product/android/ui/widget/ScrollDoubleLayout$2/this$0 Lcom/product/android/ui/widget/ScrollDoubleLayout;
iconst_0
invokevirtual com/product/android/ui/widget/ScrollDoubleLayout/setVisibility(Z)V
return
.limit locals 16
.limit stack 4
.end method
