.bytecode 50.0
.class public synchronized com/nd/schoollife/ui/team/activity/AlterTeamSignActivity
.super com/nd/schoollife/ui/common/activity/BaseSchoollifeActivity
.inner class inner com/nd/schoollife/ui/team/activity/AlterTeamSignActivity$1
.inner class inner com/nd/schoollife/ui/team/activity/AlterTeamSignActivity$2
.inner class inner com/nd/schoollife/ui/team/activity/AlterTeamSignActivity$3
.inner class inner com/nd/schoollife/ui/team/activity/AlterTeamSignActivity$4
.inner class private AlterTeamOnClickListener inner com/nd/schoollife/ui/team/activity/AlterTeamSignActivity$AlterTeamOnClickListener outer com/nd/schoollife/ui/team/activity/AlterTeamSignActivity
.inner class private SelItemGridViewOnClickListener inner com/nd/schoollife/ui/team/activity/AlterTeamSignActivity$SelItemGridViewOnClickListener outer com/nd/schoollife/ui/team/activity/AlterTeamSignActivity
.inner class private SelItemGridViewOnLongClickListener inner com/nd/schoollife/ui/team/activity/AlterTeamSignActivity$SelItemGridViewOnLongClickListener outer com/nd/schoollife/ui/team/activity/AlterTeamSignActivity
.inner class private TeamSignGridListener inner com/nd/schoollife/ui/team/activity/AlterTeamSignActivity$TeamSignGridListener outer com/nd/schoollife/ui/team/activity/AlterTeamSignActivity

.field private static final 'DEFAULT_TAG_SIZE' I = 12


.field static final 'MAX_SEL_NUM' I = 5


.field public static final 'RESULT_OK' I = 1


.field private 'alterTeamOnClickListener' Lcom/nd/schoollife/ui/team/activity/AlterTeamSignActivity$AlterTeamOnClickListener;

.field private 'isCommiting' Z

.field private 'isUpdateTeamSigns' Z

.field private 'mCurrentPage' I

.field private 'mTagNum' I

.field private 'selTags' Lcom/nd/schoollife/ui/team/adapter/TeamTagList;

.field private 'teamID' J

.field private 'teamTags' Lcom/nd/schoollife/ui/team/adapter/TeamTagList;

.method public <init>()V
aload 0
invokespecial com/nd/schoollife/ui/common/activity/BaseSchoollifeActivity/<init>()V
aload 0
aconst_null
putfield com/nd/schoollife/ui/team/activity/AlterTeamSignActivity/selTags Lcom/nd/schoollife/ui/team/adapter/TeamTagList;
aload 0
aconst_null
putfield com/nd/schoollife/ui/team/activity/AlterTeamSignActivity/teamTags Lcom/nd/schoollife/ui/team/adapter/TeamTagList;
aload 0
aconst_null
putfield com/nd/schoollife/ui/team/activity/AlterTeamSignActivity/alterTeamOnClickListener Lcom/nd/schoollife/ui/team/activity/AlterTeamSignActivity$AlterTeamOnClickListener;
aload 0
lconst_0
putfield com/nd/schoollife/ui/team/activity/AlterTeamSignActivity/teamID J
aload 0
iconst_1
putfield com/nd/schoollife/ui/team/activity/AlterTeamSignActivity/mCurrentPage I
return
.limit locals 1
.limit stack 3
.end method

.method static synthetic access$1008(Lcom/nd/schoollife/ui/team/activity/AlterTeamSignActivity;)I
aload 0
getfield com/nd/schoollife/ui/team/activity/AlterTeamSignActivity/mCurrentPage I
istore 1
aload 0
iload 1
iconst_1
iadd
putfield com/nd/schoollife/ui/team/activity/AlterTeamSignActivity/mCurrentPage I
iload 1
ireturn
.limit locals 2
.limit stack 3
.end method

.method static synthetic access$1102(Lcom/nd/schoollife/ui/team/activity/AlterTeamSignActivity;I)I
aload 0
iload 1
putfield com/nd/schoollife/ui/team/activity/AlterTeamSignActivity/mTagNum I
iload 1
ireturn
.limit locals 2
.limit stack 2
.end method

.method static synthetic access$1200(Lcom/nd/schoollife/ui/team/activity/AlterTeamSignActivity;)Landroid/content/Context;
aload 0
getfield com/nd/schoollife/ui/team/activity/AlterTeamSignActivity/mCtx Landroid/content/Context;
areturn
.limit locals 1
.limit stack 1
.end method

.method static synthetic access$1300(Lcom/nd/schoollife/ui/team/activity/AlterTeamSignActivity;)Landroid/content/Context;
aload 0
getfield com/nd/schoollife/ui/team/activity/AlterTeamSignActivity/mCtx Landroid/content/Context;
areturn
.limit locals 1
.limit stack 1
.end method

.method static synthetic access$1402(Lcom/nd/schoollife/ui/team/activity/AlterTeamSignActivity;Z)Z
aload 0
iload 1
putfield com/nd/schoollife/ui/team/activity/AlterTeamSignActivity/isUpdateTeamSigns Z
iload 1
ireturn
.limit locals 2
.limit stack 2
.end method

.method static synthetic access$1500(Lcom/nd/schoollife/ui/team/activity/AlterTeamSignActivity;)V
aload 0
invokespecial com/nd/schoollife/ui/team/activity/AlterTeamSignActivity/commit()V
return
.limit locals 1
.limit stack 1
.end method

.method static synthetic access$402(Lcom/nd/schoollife/ui/team/activity/AlterTeamSignActivity;Z)Z
aload 0
iload 1
putfield com/nd/schoollife/ui/team/activity/AlterTeamSignActivity/isCommiting Z
iload 1
ireturn
.limit locals 2
.limit stack 2
.end method

.method static synthetic access$500(Lcom/nd/schoollife/ui/team/activity/AlterTeamSignActivity;)Lcom/nd/schoollife/ui/team/adapter/TeamTagList;
aload 0
getfield com/nd/schoollife/ui/team/activity/AlterTeamSignActivity/selTags Lcom/nd/schoollife/ui/team/adapter/TeamTagList;
areturn
.limit locals 1
.limit stack 1
.end method

.method static synthetic access$600(Lcom/nd/schoollife/ui/team/activity/AlterTeamSignActivity;)Lcom/nd/schoollife/ui/team/adapter/TeamTagList;
aload 0
getfield com/nd/schoollife/ui/team/activity/AlterTeamSignActivity/teamTags Lcom/nd/schoollife/ui/team/adapter/TeamTagList;
areturn
.limit locals 1
.limit stack 1
.end method

.method static synthetic access$700(Lcom/nd/schoollife/ui/team/activity/AlterTeamSignActivity;)V
aload 0
invokespecial com/nd/schoollife/ui/team/activity/AlterTeamSignActivity/updateCurSelSignCrid()V
return
.limit locals 1
.limit stack 1
.end method

.method static synthetic access$800(Lcom/nd/schoollife/ui/team/activity/AlterTeamSignActivity;Lcom/nd/android/forumsdk/business/bean/structure/TagInfoBean;)V
aload 0
aload 1
invokespecial com/nd/schoollife/ui/team/activity/AlterTeamSignActivity/uncheckTeamSign(Lcom/nd/android/forumsdk/business/bean/structure/TagInfoBean;)V
return
.limit locals 2
.limit stack 2
.end method

.method static synthetic access$900(Lcom/nd/schoollife/ui/team/activity/AlterTeamSignActivity;I)V
aload 0
iload 1
invokespecial com/nd/schoollife/ui/team/activity/AlterTeamSignActivity/popSelSignMenu(I)V
return
.limit locals 2
.limit stack 2
.end method

.method private commit()V
aload 0
invokespecial com/nd/schoollife/ui/team/activity/AlterTeamSignActivity/onCommitTask()V
return
.limit locals 1
.limit stack 1
.end method

.method private onCommitTask()V
aload 0
getfield com/nd/schoollife/ui/team/activity/AlterTeamSignActivity/isCommiting Z
ifeq L0
return
L0:
aload 0
iconst_1
putfield com/nd/schoollife/ui/team/activity/AlterTeamSignActivity/isCommiting Z
new com/nd/schoollife/ui/team/activity/AlterTeamSignActivity$1
dup
aload 0
invokespecial com/nd/schoollife/ui/team/activity/AlterTeamSignActivity$1/<init>(Lcom/nd/schoollife/ui/team/activity/AlterTeamSignActivity;)V
astore 3
new com/nd/schoollife/ui/team/task/TeamTask
dup
aload 0
sipush 4099
getstatic com/nd/schoollife/ui/common/task/CallStyle/CALL_STYLE_SUBMIT Lcom/nd/schoollife/ui/common/task/CallStyle;
aload 3
invokespecial com/nd/schoollife/ui/team/task/TeamTask/<init>(Landroid/content/Context;ILcom/nd/schoollife/ui/common/task/CallStyle;Lcom/nd/schoollife/ui/team/task/TeamTask$TeamTaskCallback;)V
astore 5
ldc ""
astore 3
aload 0
getfield com/nd/schoollife/ui/team/activity/AlterTeamSignActivity/selTags Lcom/nd/schoollife/ui/team/adapter/TeamTagList;
invokevirtual com/nd/schoollife/ui/team/adapter/TeamTagList/size()I
istore 2
aload 3
astore 4
iload 2
ifeq L1
iconst_0
istore 1
L2:
aload 3
astore 4
iload 1
iload 2
iconst_1
isub
if_icmpgt L1
new java/lang/StringBuilder
dup
invokespecial java/lang/StringBuilder/<init>()V
aload 3
invokevirtual java/lang/StringBuilder/append(Ljava/lang/String;)Ljava/lang/StringBuilder;
aload 0
getfield com/nd/schoollife/ui/team/activity/AlterTeamSignActivity/selTags Lcom/nd/schoollife/ui/team/adapter/TeamTagList;
iload 1
invokevirtual com/nd/schoollife/ui/team/adapter/TeamTagList/getTagInfoByIndex(I)Lcom/nd/android/forumsdk/business/bean/structure/TagInfoBean;
invokevirtual com/nd/android/forumsdk/business/bean/structure/TagInfoBean/getId()J
invokevirtual java/lang/StringBuilder/append(J)Ljava/lang/StringBuilder;
ldc ":"
invokevirtual java/lang/StringBuilder/append(Ljava/lang/String;)Ljava/lang/StringBuilder;
invokevirtual java/lang/StringBuilder/toString()Ljava/lang/String;
astore 3
iload 1
iconst_1
iadd
istore 1
goto L2
L1:
aload 5
iconst_2
anewarray java/lang/String
dup
iconst_0
new java/lang/StringBuilder
dup
invokespecial java/lang/StringBuilder/<init>()V
aload 0
getfield com/nd/schoollife/ui/team/activity/AlterTeamSignActivity/teamID J
invokevirtual java/lang/StringBuilder/append(J)Ljava/lang/StringBuilder;
ldc ""
invokevirtual java/lang/StringBuilder/append(Ljava/lang/String;)Ljava/lang/StringBuilder;
invokevirtual java/lang/StringBuilder/toString()Ljava/lang/String;
aastore
dup
iconst_1
aload 4
aastore
invokevirtual com/nd/schoollife/ui/team/task/TeamTask/execute([Ljava/lang/Object;)Lcom/common/android/utils/concurrent/NdTinyHttpAsyncTask;
pop
return
.limit locals 6
.limit stack 7
.end method

.method private onNextTeamSignTask()V
aload 0
getfield com/nd/schoollife/ui/team/activity/AlterTeamSignActivity/isUpdateTeamSigns Z
ifeq L0
return
L0:
aload 0
iconst_1
putfield com/nd/schoollife/ui/team/activity/AlterTeamSignActivity/isUpdateTeamSigns Z
new com/nd/schoollife/ui/team/activity/AlterTeamSignActivity$4
dup
aload 0
invokespecial com/nd/schoollife/ui/team/activity/AlterTeamSignActivity$4/<init>(Lcom/nd/schoollife/ui/team/activity/AlterTeamSignActivity;)V
astore 1
new com/nd/schoollife/ui/team/task/TeamTask
dup
aload 0
sipush 4098
getstatic com/nd/schoollife/ui/common/task/CallStyle/CALL_STYLE_REFLASH Lcom/nd/schoollife/ui/common/task/CallStyle;
aload 1
invokespecial com/nd/schoollife/ui/team/task/TeamTask/<init>(Landroid/content/Context;ILcom/nd/schoollife/ui/common/task/CallStyle;Lcom/nd/schoollife/ui/team/task/TeamTask$TeamTaskCallback;)V
astore 1
aload 0
getfield com/nd/schoollife/ui/team/activity/AlterTeamSignActivity/mCurrentPage I
bipush 12
imul
aload 0
getfield com/nd/schoollife/ui/team/activity/AlterTeamSignActivity/mTagNum I
if_icmpge L1
aload 0
aload 0
getfield com/nd/schoollife/ui/team/activity/AlterTeamSignActivity/mCurrentPage I
iconst_1
iadd
putfield com/nd/schoollife/ui/team/activity/AlterTeamSignActivity/mCurrentPage I
aload 1
iconst_2
anewarray java/lang/String
dup
iconst_0
new java/lang/StringBuilder
dup
invokespecial java/lang/StringBuilder/<init>()V
aload 0
getfield com/nd/schoollife/ui/team/activity/AlterTeamSignActivity/mCurrentPage I
invokevirtual java/lang/StringBuilder/append(I)Ljava/lang/StringBuilder;
ldc ""
invokevirtual java/lang/StringBuilder/append(Ljava/lang/String;)Ljava/lang/StringBuilder;
invokevirtual java/lang/StringBuilder/toString()Ljava/lang/String;
aastore
dup
iconst_1
ldc "12"
aastore
invokevirtual com/nd/schoollife/ui/team/task/TeamTask/execute([Ljava/lang/Object;)Lcom/common/android/utils/concurrent/NdTinyHttpAsyncTask;
pop
return
L1:
aload 0
iconst_1
putfield com/nd/schoollife/ui/team/activity/AlterTeamSignActivity/mCurrentPage I
aload 1
iconst_2
anewarray java/lang/String
dup
iconst_0
new java/lang/StringBuilder
dup
invokespecial java/lang/StringBuilder/<init>()V
aload 0
getfield com/nd/schoollife/ui/team/activity/AlterTeamSignActivity/mCurrentPage I
invokevirtual java/lang/StringBuilder/append(I)Ljava/lang/StringBuilder;
ldc ""
invokevirtual java/lang/StringBuilder/append(Ljava/lang/String;)Ljava/lang/StringBuilder;
invokevirtual java/lang/StringBuilder/toString()Ljava/lang/String;
aastore
dup
iconst_1
ldc "12"
aastore
invokevirtual com/nd/schoollife/ui/team/task/TeamTask/execute([Ljava/lang/Object;)Lcom/common/android/utils/concurrent/NdTinyHttpAsyncTask;
pop
return
.limit locals 2
.limit stack 6
.end method

.method private popSelSignMenu(I)V
new java/lang/StringBuilder
dup
invokespecial java/lang/StringBuilder/<init>()V
aload 0
getfield com/nd/schoollife/ui/team/activity/AlterTeamSignActivity/mCtx Landroid/content/Context;
getstatic com/nd/schoollife/R$string/create_community_confirm_delete_tag I
invokevirtual android/content/Context/getString(I)Ljava/lang/String;
invokevirtual java/lang/StringBuilder/append(Ljava/lang/String;)Ljava/lang/StringBuilder;
ldc "\""
invokevirtual java/lang/StringBuilder/append(Ljava/lang/String;)Ljava/lang/StringBuilder;
aload 0
getfield com/nd/schoollife/ui/team/activity/AlterTeamSignActivity/selTags Lcom/nd/schoollife/ui/team/adapter/TeamTagList;
iload 1
invokevirtual com/nd/schoollife/ui/team/adapter/TeamTagList/getTagInfoByIndex(I)Lcom/nd/android/forumsdk/business/bean/structure/TagInfoBean;
invokevirtual com/nd/android/forumsdk/business/bean/structure/TagInfoBean/getName()Ljava/lang/String;
invokevirtual java/lang/StringBuilder/append(Ljava/lang/String;)Ljava/lang/StringBuilder;
ldc "\"?"
invokevirtual java/lang/StringBuilder/append(Ljava/lang/String;)Ljava/lang/StringBuilder;
invokevirtual java/lang/StringBuilder/toString()Ljava/lang/String;
astore 2
aload 0
aload 0
getfield com/nd/schoollife/ui/team/activity/AlterTeamSignActivity/mCtx Landroid/content/Context;
getstatic com/nd/schoollife/R$string/operator I
invokevirtual android/content/Context/getString(I)Ljava/lang/String;
aload 2
aload 0
getfield com/nd/schoollife/ui/team/activity/AlterTeamSignActivity/mCtx Landroid/content/Context;
getstatic com/nd/schoollife/R$string/confirm I
invokevirtual android/content/Context/getString(I)Ljava/lang/String;
aload 0
getfield com/nd/schoollife/ui/team/activity/AlterTeamSignActivity/mCtx Landroid/content/Context;
getstatic com/nd/schoollife/R$string/cancel I
invokevirtual android/content/Context/getString(I)Ljava/lang/String;
new com/nd/schoollife/ui/team/activity/AlterTeamSignActivity$2
dup
aload 0
iload 1
invokespecial com/nd/schoollife/ui/team/activity/AlterTeamSignActivity$2/<init>(Lcom/nd/schoollife/ui/team/activity/AlterTeamSignActivity;I)V
new com/nd/schoollife/ui/team/activity/AlterTeamSignActivity$3
dup
aload 0
invokespecial com/nd/schoollife/ui/team/activity/AlterTeamSignActivity$3/<init>(Lcom/nd/schoollife/ui/team/activity/AlterTeamSignActivity;)V
invokevirtual com/nd/schoollife/ui/team/activity/AlterTeamSignActivity/showConfirmDialog(Ljava/lang/String;Ljava/lang/String;Ljava/lang/String;Ljava/lang/String;Landroid/view/View$OnClickListener;Landroid/view/View$OnClickListener;)V
return
.limit locals 3
.limit stack 9
.end method

.method private uncheckTeamSign(Lcom/nd/android/forumsdk/business/bean/structure/TagInfoBean;)V
aload 0
getfield com/nd/schoollife/ui/team/activity/AlterTeamSignActivity/teamTags Lcom/nd/schoollife/ui/team/adapter/TeamTagList;
aload 1
invokevirtual com/nd/schoollife/ui/team/adapter/TeamTagList/findTagInfo(Lcom/nd/android/forumsdk/business/bean/structure/TagInfoBean;)I
istore 2
iload 2
iflt L0
aload 0
getstatic com/nd/schoollife/R$id/gv_alter_team_sign_team_signs I
invokevirtual com/nd/schoollife/ui/team/activity/AlterTeamSignActivity/findViewById(I)Landroid/view/View;
checkcast android/widget/GridView
iload 2
invokevirtual android/widget/GridView/getChildAt(I)Landroid/view/View;
checkcast com/nd/schoollife/ui/team/view/ExtCheckButton
iconst_0
invokevirtual com/nd/schoollife/ui/team/view/ExtCheckButton/setCheck(Z)V
L0:
return
.limit locals 3
.limit stack 2
.end method

.method private updateCurSelSignCrid()V
aload 0
getstatic com/nd/schoollife/R$id/gv_alter_team_sign_sel_signs I
invokevirtual com/nd/schoollife/ui/team/activity/AlterTeamSignActivity/findViewById(I)Landroid/view/View;
checkcast android/widget/GridView
new com/nd/schoollife/ui/team/adapter/TagSelectedGridviewAdapter
dup
aload 0
aload 0
getfield com/nd/schoollife/ui/team/activity/AlterTeamSignActivity/selTags Lcom/nd/schoollife/ui/team/adapter/TeamTagList;
invokespecial com/nd/schoollife/ui/team/adapter/TagSelectedGridviewAdapter/<init>(Landroid/content/Context;Lcom/nd/schoollife/ui/team/adapter/TeamTagList;)V
invokevirtual android/widget/GridView/setAdapter(Landroid/widget/ListAdapter;)V
return
.limit locals 1
.limit stack 5
.end method

.method protected initContentView()V
aload 0
getstatic com/nd/schoollife/R$layout/activity_alter_team_sign I
invokevirtual com/nd/schoollife/ui/team/activity/AlterTeamSignActivity/setContentView(I)V
aload 0
invokespecial com/nd/schoollife/ui/team/activity/AlterTeamSignActivity/updateCurSelSignCrid()V
return
.limit locals 1
.limit stack 2
.end method

.method protected initData(Landroid/os/Bundle;)V
aload 0
new com/nd/schoollife/ui/team/adapter/TeamTagList
dup
invokespecial com/nd/schoollife/ui/team/adapter/TeamTagList/<init>()V
putfield com/nd/schoollife/ui/team/activity/AlterTeamSignActivity/selTags Lcom/nd/schoollife/ui/team/adapter/TeamTagList;
aload 0
new com/nd/schoollife/ui/team/adapter/TeamTagList
dup
invokespecial com/nd/schoollife/ui/team/adapter/TeamTagList/<init>()V
putfield com/nd/schoollife/ui/team/activity/AlterTeamSignActivity/teamTags Lcom/nd/schoollife/ui/team/adapter/TeamTagList;
aload 0
new com/nd/schoollife/ui/team/activity/AlterTeamSignActivity$AlterTeamOnClickListener
dup
aload 0
aconst_null
invokespecial com/nd/schoollife/ui/team/activity/AlterTeamSignActivity$AlterTeamOnClickListener/<init>(Lcom/nd/schoollife/ui/team/activity/AlterTeamSignActivity;Lcom/nd/schoollife/ui/team/activity/AlterTeamSignActivity$1;)V
putfield com/nd/schoollife/ui/team/activity/AlterTeamSignActivity/alterTeamOnClickListener Lcom/nd/schoollife/ui/team/activity/AlterTeamSignActivity$AlterTeamOnClickListener;
aload 0
iconst_0
putfield com/nd/schoollife/ui/team/activity/AlterTeamSignActivity/isUpdateTeamSigns Z
aload 0
iconst_0
putfield com/nd/schoollife/ui/team/activity/AlterTeamSignActivity/isCommiting Z
aload 0
invokevirtual com/nd/schoollife/ui/team/activity/AlterTeamSignActivity/getIntent()Landroid/content/Intent;
astore 1
aload 0
aload 1
ldc "LONG_TEAM_OR_COMMUNITY_ID"
lconst_0
invokevirtual android/content/Intent/getLongExtra(Ljava/lang/String;J)J
putfield com/nd/schoollife/ui/team/activity/AlterTeamSignActivity/teamID J
iconst_0
istore 2
L0:
iload 2
iconst_5
if_icmpge L1
aload 1
new java/lang/StringBuilder
dup
invokespecial java/lang/StringBuilder/<init>()V
ldc "tagname"
invokevirtual java/lang/StringBuilder/append(Ljava/lang/String;)Ljava/lang/StringBuilder;
iload 2
invokevirtual java/lang/StringBuilder/append(I)Ljava/lang/StringBuilder;
invokevirtual java/lang/StringBuilder/toString()Ljava/lang/String;
invokevirtual android/content/Intent/getStringExtra(Ljava/lang/String;)Ljava/lang/String;
astore 5
aload 5
ifnull L1
aload 5
ldc "none"
invokevirtual java/lang/String/equals(Ljava/lang/Object;)Z
ifeq L2
L1:
return
L2:
aload 1
new java/lang/StringBuilder
dup
invokespecial java/lang/StringBuilder/<init>()V
ldc "tagid"
invokevirtual java/lang/StringBuilder/append(Ljava/lang/String;)Ljava/lang/StringBuilder;
iload 2
invokevirtual java/lang/StringBuilder/append(I)Ljava/lang/StringBuilder;
invokevirtual java/lang/StringBuilder/toString()Ljava/lang/String;
lconst_0
invokevirtual android/content/Intent/getLongExtra(Ljava/lang/String;J)J
lstore 3
new com/nd/android/forumsdk/business/bean/structure/TagInfoBean
dup
invokespecial com/nd/android/forumsdk/business/bean/structure/TagInfoBean/<init>()V
astore 6
aload 6
lload 3
invokevirtual com/nd/android/forumsdk/business/bean/structure/TagInfoBean/setId(J)V
aload 6
aload 5
invokevirtual com/nd/android/forumsdk/business/bean/structure/TagInfoBean/setName(Ljava/lang/String;)V
aload 0
getfield com/nd/schoollife/ui/team/activity/AlterTeamSignActivity/selTags Lcom/nd/schoollife/ui/team/adapter/TeamTagList;
aload 6
invokevirtual com/nd/schoollife/ui/team/adapter/TeamTagList/addTagInfo(Lcom/nd/android/forumsdk/business/bean/structure/TagInfoBean;)I
pop
iload 2
iconst_1
iadd
istore 2
goto L0
.limit locals 7
.limit stack 5
.end method

.method protected initEvent()V
aload 0
getstatic com/nd/schoollife/R$id/btn_alter_team_sign_next_team_signs I
invokevirtual com/nd/schoollife/ui/team/activity/AlterTeamSignActivity/findViewById(I)Landroid/view/View;
checkcast android/widget/Button
aload 0
getfield com/nd/schoollife/ui/team/activity/AlterTeamSignActivity/alterTeamOnClickListener Lcom/nd/schoollife/ui/team/activity/AlterTeamSignActivity$AlterTeamOnClickListener;
invokevirtual android/widget/Button/setOnClickListener(Landroid/view/View$OnClickListener;)V
aload 0
getstatic com/nd/schoollife/R$id/btn_alter_team_sign_commit I
invokevirtual com/nd/schoollife/ui/team/activity/AlterTeamSignActivity/findViewById(I)Landroid/view/View;
checkcast android/widget/Button
aload 0
getfield com/nd/schoollife/ui/team/activity/AlterTeamSignActivity/alterTeamOnClickListener Lcom/nd/schoollife/ui/team/activity/AlterTeamSignActivity$AlterTeamOnClickListener;
invokevirtual android/widget/Button/setOnClickListener(Landroid/view/View$OnClickListener;)V
aload 0
getstatic com/nd/schoollife/R$id/btn_common_head_back I
invokevirtual com/nd/schoollife/ui/team/activity/AlterTeamSignActivity/findViewById(I)Landroid/view/View;
checkcast android/widget/Button
aload 0
getfield com/nd/schoollife/ui/team/activity/AlterTeamSignActivity/alterTeamOnClickListener Lcom/nd/schoollife/ui/team/activity/AlterTeamSignActivity$AlterTeamOnClickListener;
invokevirtual android/widget/Button/setOnClickListener(Landroid/view/View$OnClickListener;)V
aload 0
getstatic com/nd/schoollife/R$id/gv_alter_team_sign_sel_signs I
invokevirtual com/nd/schoollife/ui/team/activity/AlterTeamSignActivity/findViewById(I)Landroid/view/View;
checkcast android/widget/GridView
astore 1
aload 1
new com/nd/schoollife/ui/team/activity/AlterTeamSignActivity$SelItemGridViewOnLongClickListener
dup
aload 0
aconst_null
invokespecial com/nd/schoollife/ui/team/activity/AlterTeamSignActivity$SelItemGridViewOnLongClickListener/<init>(Lcom/nd/schoollife/ui/team/activity/AlterTeamSignActivity;Lcom/nd/schoollife/ui/team/activity/AlterTeamSignActivity$1;)V
invokevirtual android/widget/GridView/setOnItemLongClickListener(Landroid/widget/AdapterView$OnItemLongClickListener;)V
aload 1
new com/nd/schoollife/ui/team/activity/AlterTeamSignActivity$SelItemGridViewOnClickListener
dup
aload 0
aconst_null
invokespecial com/nd/schoollife/ui/team/activity/AlterTeamSignActivity$SelItemGridViewOnClickListener/<init>(Lcom/nd/schoollife/ui/team/activity/AlterTeamSignActivity;Lcom/nd/schoollife/ui/team/activity/AlterTeamSignActivity$1;)V
invokevirtual android/widget/GridView/setOnItemClickListener(Landroid/widget/AdapterView$OnItemClickListener;)V
aload 0
getstatic com/nd/schoollife/R$id/gv_alter_team_sign_team_signs I
invokevirtual com/nd/schoollife/ui/team/activity/AlterTeamSignActivity/findViewById(I)Landroid/view/View;
checkcast android/widget/GridView
new com/nd/schoollife/ui/team/activity/AlterTeamSignActivity$TeamSignGridListener
dup
aload 0
aconst_null
invokespecial com/nd/schoollife/ui/team/activity/AlterTeamSignActivity$TeamSignGridListener/<init>(Lcom/nd/schoollife/ui/team/activity/AlterTeamSignActivity;Lcom/nd/schoollife/ui/team/activity/AlterTeamSignActivity$1;)V
invokevirtual android/widget/GridView/setOnItemClickListener(Landroid/widget/AdapterView$OnItemClickListener;)V
aload 0
invokevirtual com/nd/schoollife/ui/team/activity/AlterTeamSignActivity/nextTeamSigns()V
return
.limit locals 2
.limit stack 5
.end method

.method protected initHeadView(Landroid/content/Context;)Landroid/view/View;
aload 1
invokestatic android/view/LayoutInflater/from(Landroid/content/Context;)Landroid/view/LayoutInflater;
getstatic com/nd/schoollife/R$layout/common_head I
aconst_null
invokevirtual android/view/LayoutInflater/inflate(ILandroid/view/ViewGroup;)Landroid/view/View;
astore 1
aload 1
getstatic com/nd/schoollife/R$id/tv_common_head_title I
invokevirtual android/view/View/findViewById(I)Landroid/view/View;
checkcast android/widget/TextView
aload 0
getstatic com/nd/schoollife/R$string/alter_team_tags I
invokevirtual com/nd/schoollife/ui/team/activity/AlterTeamSignActivity/getString(I)Ljava/lang/String;
invokevirtual android/widget/TextView/setText(Ljava/lang/CharSequence;)V
aload 1
areturn
.limit locals 2
.limit stack 3
.end method

.method public nextTeamSigns()V
aload 0
invokespecial com/nd/schoollife/ui/team/activity/AlterTeamSignActivity/onNextTeamSignTask()V
return
.limit locals 1
.limit stack 1
.end method
