.bytecode 50.0
.class synchronized com/nd/schoollife/ui/team/activity/CreateTeamActivity$CreateTeamOnClickListener
.super java/lang/Object
.implements android/view/View$OnClickListener
.inner class private CreateTeamOnClickListener inner com/nd/schoollife/ui/team/activity/CreateTeamActivity$CreateTeamOnClickListener outer com/nd/schoollife/ui/team/activity/CreateTeamActivity

.field final synthetic 'this$0' Lcom/nd/schoollife/ui/team/activity/CreateTeamActivity;

.method private <init>(Lcom/nd/schoollife/ui/team/activity/CreateTeamActivity;)V
aload 0
aload 1
putfield com/nd/schoollife/ui/team/activity/CreateTeamActivity$CreateTeamOnClickListener/this$0 Lcom/nd/schoollife/ui/team/activity/CreateTeamActivity;
aload 0
invokespecial java/lang/Object/<init>()V
return
.limit locals 2
.limit stack 2
.end method

.method synthetic <init>(Lcom/nd/schoollife/ui/team/activity/CreateTeamActivity;Lcom/nd/schoollife/ui/team/activity/CreateTeamActivity$1;)V
aload 0
aload 1
invokespecial com/nd/schoollife/ui/team/activity/CreateTeamActivity$CreateTeamOnClickListener/<init>(Lcom/nd/schoollife/ui/team/activity/CreateTeamActivity;)V
return
.limit locals 3
.limit stack 2
.end method

.method public onClick(Landroid/view/View;)V
aload 1
invokevirtual android/view/View/getId()I
istore 2
iload 2
getstatic com/nd/schoollife/R$id/btn_create_team_commit I
if_icmpne L0
aload 0
getfield com/nd/schoollife/ui/team/activity/CreateTeamActivity$CreateTeamOnClickListener/this$0 Lcom/nd/schoollife/ui/team/activity/CreateTeamActivity;
invokestatic com/nd/schoollife/ui/team/activity/CreateTeamActivity/access$2400(Lcom/nd/schoollife/ui/team/activity/CreateTeamActivity;)V
L1:
return
L0:
iload 2
getstatic com/nd/schoollife/R$id/btn_create_team_next_team_signs I
if_icmpne L2
aload 0
getfield com/nd/schoollife/ui/team/activity/CreateTeamActivity$CreateTeamOnClickListener/this$0 Lcom/nd/schoollife/ui/team/activity/CreateTeamActivity;
invokevirtual com/nd/schoollife/ui/team/activity/CreateTeamActivity/nextTeamSigns()V
return
L2:
iload 2
getstatic com/nd/schoollife/R$id/btn_create_team_team_img I
if_icmpne L3
aload 0
getfield com/nd/schoollife/ui/team/activity/CreateTeamActivity$CreateTeamOnClickListener/this$0 Lcom/nd/schoollife/ui/team/activity/CreateTeamActivity;
invokestatic com/nd/schoollife/ui/team/activity/CreateTeamActivity/access$2500(Lcom/nd/schoollife/ui/team/activity/CreateTeamActivity;)V
return
L3:
iload 2
getstatic com/nd/schoollife/R$id/btn_common_head_back I
if_icmpne L1
aload 0
getfield com/nd/schoollife/ui/team/activity/CreateTeamActivity$CreateTeamOnClickListener/this$0 Lcom/nd/schoollife/ui/team/activity/CreateTeamActivity;
invokestatic com/nd/schoollife/ui/team/activity/CreateTeamActivity/access$2600(Lcom/nd/schoollife/ui/team/activity/CreateTeamActivity;)Landroid/view/inputmethod/InputMethodManager;
invokevirtual android/view/inputmethod/InputMethodManager/isActive()Z
ifeq L4
aload 0
getfield com/nd/schoollife/ui/team/activity/CreateTeamActivity$CreateTeamOnClickListener/this$0 Lcom/nd/schoollife/ui/team/activity/CreateTeamActivity;
invokestatic com/nd/schoollife/ui/team/activity/CreateTeamActivity/access$2600(Lcom/nd/schoollife/ui/team/activity/CreateTeamActivity;)Landroid/view/inputmethod/InputMethodManager;
aload 0
getfield com/nd/schoollife/ui/team/activity/CreateTeamActivity$CreateTeamOnClickListener/this$0 Lcom/nd/schoollife/ui/team/activity/CreateTeamActivity;
getstatic com/nd/schoollife/R$id/sv_create_team I
invokevirtual com/nd/schoollife/ui/team/activity/CreateTeamActivity/findViewById(I)Landroid/view/View;
checkcast android/widget/ScrollView
invokevirtual android/widget/ScrollView/getWindowToken()Landroid/os/IBinder;
iconst_2
invokevirtual android/view/inputmethod/InputMethodManager/hideSoftInputFromWindow(Landroid/os/IBinder;I)Z
pop
L4:
aload 0
getfield com/nd/schoollife/ui/team/activity/CreateTeamActivity$CreateTeamOnClickListener/this$0 Lcom/nd/schoollife/ui/team/activity/CreateTeamActivity;
invokevirtual com/nd/schoollife/ui/team/activity/CreateTeamActivity/finish()V
return
.limit locals 3
.limit stack 3
.end method
