.bytecode 50.0
.class public synchronized com/nd/schoollife/ui/team/activity/TeamHomeActivity
.super com/nd/schoollife/ui/common/activity/BaseSchoollifeActivity
.implements android/view/View$OnClickListener
.implements com/nd/schoollife/ui/common/view/RefreshBtn$RefreshBtnOnClickListener
.implements com/nd/schoollife/ui/common/base/interfaces/AsyncTaskCallback
.implements com/nd/schoollife/ui/common/base/interfaces/OnReloadClickedListener
.implements com/nd/schoollife/ui/common/view/widget/CustomPullToRefreshListView$PullToActionListener
.inner class inner com/nd/schoollife/ui/team/activity/TeamHomeActivity$1
.inner class inner com/nd/schoollife/ui/team/activity/TeamHomeActivity$2
.inner class inner com/nd/schoollife/ui/team/activity/TeamHomeActivity$3
.inner class inner com/nd/schoollife/ui/team/activity/TeamHomeActivity$4
.inner class inner com/nd/schoollife/ui/team/activity/TeamHomeActivity$5

.field private static final 'KEY_SAVE_TEAM_ID' Ljava/lang/String; = "KEY_SAVE_TEAM_ID"

.field public static final 'TAG' Ljava/lang/String;

.field private 'btnFocuse' Landroid/widget/Button;

.field private 'btnUnfocuse' Landroid/widget/Button;

.field private 'civAvatar' Lcom/nd/schoollife/ui/common/view/CircleImageView;

.field private 'isInit' Z

.field private 'mCommentEditViewLayout' Landroid/widget/LinearLayout;

.field private 'mGrade' I

.field private 'mInputContentManager' Lcom/nd/schoollife/ui/common/process/InputContentViewManager;

.field private 'mListView' Lcom/nd/schoollife/ui/common/view/widget/CustomPullToRefreshListView;

.field private 'mLlMenu' Landroid/widget/LinearLayout;

.field private 'mName' Landroid/widget/TextView;

.field private 'mPostInfoBeans' Ljava/util/List; signature "Ljava/util/List<Lcom/nd/android/forumsdk/business/bean/result/PostInfoBean;>;"

.field private 'mPostListAdapter' Lcom/nd/schoollife/ui/post/adapter/PostListAdapter;

.field private 'mPostsList' Lcom/nd/android/forumsdk/business/bean/result/ResultPostList;

.field private 'mPraiseChangeReceiver' Lcom/nd/schoollife/common/receiver/PraiseChangeReceiver;

.field private 'mRefreshBtn' Lcom/nd/schoollife/ui/common/view/RefreshBtn;

.field private 'mSlideHolder' Lcom/nd/schoollife/ui/team/view/SlideHolder;

.field private 'mTeamId' J

.field private 'mTeamName' Ljava/lang/String;

.field private 'postTask' Lcom/nd/schoollife/ui/post/task/PostProcessTask;

.method static <clinit>()V
ldc com/nd/schoollife/ui/team/activity/TeamHomeActivity
invokevirtual java/lang/Class/getSimpleName()Ljava/lang/String;
putstatic com/nd/schoollife/ui/team/activity/TeamHomeActivity/TAG Ljava/lang/String;
return
.limit locals 0
.limit stack 1
.end method

.method public <init>()V
aload 0
invokespecial com/nd/schoollife/ui/common/activity/BaseSchoollifeActivity/<init>()V
aload 0
iconst_0
putfield com/nd/schoollife/ui/team/activity/TeamHomeActivity/isInit Z
aload 0
iconst_0
putfield com/nd/schoollife/ui/team/activity/TeamHomeActivity/mGrade I
return
.limit locals 1
.limit stack 2
.end method

.method static synthetic access$000(Lcom/nd/schoollife/ui/team/activity/TeamHomeActivity;)Lcom/nd/schoollife/ui/team/view/SlideHolder;
aload 0
getfield com/nd/schoollife/ui/team/activity/TeamHomeActivity/mSlideHolder Lcom/nd/schoollife/ui/team/view/SlideHolder;
areturn
.limit locals 1
.limit stack 1
.end method

.method static synthetic access$100(Lcom/nd/schoollife/ui/team/activity/TeamHomeActivity;)Lcom/nd/schoollife/ui/common/process/InputContentViewManager;
aload 0
getfield com/nd/schoollife/ui/team/activity/TeamHomeActivity/mInputContentManager Lcom/nd/schoollife/ui/common/process/InputContentViewManager;
areturn
.limit locals 1
.limit stack 1
.end method

.method static synthetic access$200(Lcom/nd/schoollife/ui/team/activity/TeamHomeActivity;J)I
aload 0
lload 1
invokespecial com/nd/schoollife/ui/team/activity/TeamHomeActivity/findPost(J)I
ireturn
.limit locals 3
.limit stack 3
.end method

.method static synthetic access$300(Lcom/nd/schoollife/ui/team/activity/TeamHomeActivity;)Ljava/util/List;
aload 0
getfield com/nd/schoollife/ui/team/activity/TeamHomeActivity/mPostInfoBeans Ljava/util/List;
areturn
.limit locals 1
.limit stack 1
.end method

.method static synthetic access$400(Lcom/nd/schoollife/ui/team/activity/TeamHomeActivity;)Lcom/nd/schoollife/ui/post/adapter/PostListAdapter;
aload 0
getfield com/nd/schoollife/ui/team/activity/TeamHomeActivity/mPostListAdapter Lcom/nd/schoollife/ui/post/adapter/PostListAdapter;
areturn
.limit locals 1
.limit stack 1
.end method

.method static synthetic access$500(Lcom/nd/schoollife/ui/team/activity/TeamHomeActivity;)V
aload 0
invokespecial com/nd/schoollife/ui/team/activity/TeamHomeActivity/unFocusTeamTask()V
return
.limit locals 1
.limit stack 1
.end method

.method private fillTeamInfoValue(Lcom/nd/android/forumsdk/business/bean/structure/TeamInfoBean;)V
aload 1
ifnull L0
aload 1
invokevirtual com/nd/android/forumsdk/business/bean/structure/TeamInfoBean/getAvatar()Ljava/lang/String;
astore 2
aload 2
invokestatic android/text/TextUtils/isEmpty(Ljava/lang/CharSequence;)Z
ifne L1
invokestatic com/nostra13/universalimageloader/core/ImageLoader/getInstance()Lcom/nostra13/universalimageloader/core/ImageLoader;
aload 2
invokestatic com/nd/schoollife/ui/common/util/TeamUtils/getTeamAvatarUrl(Ljava/lang/String;)Ljava/lang/String;
aload 0
getstatic com/nd/schoollife/R$id/iv_community_item_head I
invokevirtual com/nd/schoollife/ui/team/activity/TeamHomeActivity/findViewById(I)Landroid/view/View;
checkcast android/widget/ImageView
getstatic com/nd/schoollife/common/utils/ui/SchoolLifeGlobal/imgLoaderOptions Lcom/nostra13/universalimageloader/core/DisplayImageOptions;
invokevirtual com/nostra13/universalimageloader/core/ImageLoader/displayImage(Ljava/lang/String;Landroid/widget/ImageView;Lcom/nostra13/universalimageloader/core/DisplayImageOptions;)V
L1:
aload 1
invokevirtual com/nd/android/forumsdk/business/bean/structure/TeamInfoBean/getName()Ljava/lang/String;
astore 2
aload 2
invokestatic android/text/TextUtils/isEmpty(Ljava/lang/CharSequence;)Z
ifne L2
aload 0
getstatic com/nd/schoollife/R$id/tv_common_head_title I
invokevirtual com/nd/schoollife/ui/team/activity/TeamHomeActivity/findViewById(I)Landroid/view/View;
checkcast android/widget/TextView
aload 2
invokevirtual android/widget/TextView/setText(Ljava/lang/CharSequence;)V
aload 0
getstatic com/nd/schoollife/R$id/tv_community_item_title I
invokevirtual com/nd/schoollife/ui/team/activity/TeamHomeActivity/findViewById(I)Landroid/view/View;
checkcast android/widget/TextView
aload 2
invokevirtual android/widget/TextView/setText(Ljava/lang/CharSequence;)V
aload 0
aload 2
putfield com/nd/schoollife/ui/team/activity/TeamHomeActivity/mTeamName Ljava/lang/String;
L2:
aload 1
invokevirtual com/nd/android/forumsdk/business/bean/structure/TeamInfoBean/getIntro()Ljava/lang/String;
astore 2
aload 2
invokestatic android/text/TextUtils/isEmpty(Ljava/lang/CharSequence;)Z
ifne L3
aload 0
getstatic com/nd/schoollife/R$id/tv_community_item_instroction I
invokevirtual com/nd/schoollife/ui/team/activity/TeamHomeActivity/findViewById(I)Landroid/view/View;
checkcast android/widget/TextView
aload 2
invokevirtual android/widget/TextView/setText(Ljava/lang/CharSequence;)V
L3:
aload 0
aload 1
invokevirtual com/nd/android/forumsdk/business/bean/structure/TeamInfoBean/getGrade()I
putfield com/nd/schoollife/ui/team/activity/TeamHomeActivity/mGrade I
aload 0
getfield com/nd/schoollife/ui/team/activity/TeamHomeActivity/mGrade I
ifeq L4
aload 0
getfield com/nd/schoollife/ui/team/activity/TeamHomeActivity/mGrade I
iconst_1
if_icmpne L5
L4:
aload 0
getstatic com/nd/schoollife/R$id/tv_team_host_slider_menu_usr_position I
invokevirtual com/nd/schoollife/ui/team/activity/TeamHomeActivity/findViewById(I)Landroid/view/View;
checkcast android/widget/TextView
bipush 8
invokevirtual android/widget/TextView/setVisibility(I)V
L6:
getstatic com/product/android/business/ApplicationVariable/INSTANCE Lcom/product/android/business/ApplicationVariable;
invokevirtual com/product/android/business/ApplicationVariable/getOapUid()J
aload 0
getfield com/nd/schoollife/ui/team/activity/TeamHomeActivity/civAvatar Lcom/nd/schoollife/ui/common/view/CircleImageView;
iconst_3
invokestatic com/product/android/business/headImage/HeadImageLoader/displayImage(JLandroid/widget/ImageView;B)V
aload 0
getfield com/nd/schoollife/ui/team/activity/TeamHomeActivity/mName Landroid/widget/TextView;
getstatic com/product/android/business/ApplicationVariable/INSTANCE Lcom/product/android/business/ApplicationVariable;
invokevirtual com/product/android/business/ApplicationVariable/getUserName()Ljava/lang/String;
invokevirtual android/widget/TextView/setText(Ljava/lang/CharSequence;)V
L0:
return
L5:
aload 0
getfield com/nd/schoollife/ui/team/activity/TeamHomeActivity/mGrade I
iconst_2
if_icmpne L7
aload 0
getstatic com/nd/schoollife/R$id/tv_team_host_slider_menu_usr_position I
invokevirtual com/nd/schoollife/ui/team/activity/TeamHomeActivity/findViewById(I)Landroid/view/View;
checkcast android/widget/TextView
iconst_0
invokevirtual android/widget/TextView/setVisibility(I)V
aload 0
getstatic com/nd/schoollife/R$id/tv_team_host_slider_menu_usr_position I
invokevirtual com/nd/schoollife/ui/team/activity/TeamHomeActivity/findViewById(I)Landroid/view/View;
checkcast android/widget/TextView
aload 0
getstatic com/nd/schoollife/R$string/community_role_manager I
invokevirtual com/nd/schoollife/ui/team/activity/TeamHomeActivity/getString(I)Ljava/lang/String;
invokevirtual android/widget/TextView/setText(Ljava/lang/CharSequence;)V
goto L6
L7:
aload 0
getfield com/nd/schoollife/ui/team/activity/TeamHomeActivity/mGrade I
iconst_3
if_icmpne L6
aload 0
getstatic com/nd/schoollife/R$id/tv_team_host_slider_menu_usr_position I
invokevirtual com/nd/schoollife/ui/team/activity/TeamHomeActivity/findViewById(I)Landroid/view/View;
checkcast android/widget/TextView
iconst_0
invokevirtual android/widget/TextView/setVisibility(I)V
aload 0
getstatic com/nd/schoollife/R$id/tv_team_host_slider_menu_usr_position I
invokevirtual com/nd/schoollife/ui/team/activity/TeamHomeActivity/findViewById(I)Landroid/view/View;
checkcast android/widget/TextView
aload 0
getstatic com/nd/schoollife/R$string/team_role_creator I
invokevirtual com/nd/schoollife/ui/team/activity/TeamHomeActivity/getString(I)Ljava/lang/String;
invokevirtual android/widget/TextView/setText(Ljava/lang/CharSequence;)V
goto L6
.limit locals 3
.limit stack 4
.end method

.method private findPost(J)I
iconst_0
istore 3
L0:
iload 3
aload 0
getfield com/nd/schoollife/ui/team/activity/TeamHomeActivity/mPostInfoBeans Ljava/util/List;
invokeinterface java/util/List/size()I 0
if_icmpge L1
aload 0
getfield com/nd/schoollife/ui/team/activity/TeamHomeActivity/mPostInfoBeans Ljava/util/List;
iload 3
invokeinterface java/util/List/get(I)Ljava/lang/Object; 1
checkcast com/nd/android/forumsdk/business/bean/result/PostInfoBean
astore 4
aload 4
ifnull L2
aload 4
invokevirtual com/nd/android/forumsdk/business/bean/result/PostInfoBean/getTid()J
lload 1
lcmp
ifne L2
iload 3
ireturn
L2:
iload 3
iconst_1
iadd
istore 3
goto L0
L1:
iconst_m1
ireturn
.limit locals 5
.limit stack 4
.end method

.method private focusTeamTask()V
aload 0
invokevirtual com/nd/schoollife/ui/team/activity/TeamHomeActivity/showLoading()V
new com/nd/schoollife/ui/team/task/TeamTask
dup
aload 0
sipush 4104
getstatic com/nd/schoollife/ui/common/task/CallStyle/CALL_STYLE_SUBMIT Lcom/nd/schoollife/ui/common/task/CallStyle;
aload 0
invokespecial com/nd/schoollife/ui/team/task/TeamTask/<init>(Landroid/content/Context;ILcom/nd/schoollife/ui/common/task/CallStyle;Lcom/nd/schoollife/ui/common/base/interfaces/AsyncTaskCallback;)V
iconst_2
anewarray java/lang/String
dup
iconst_0
aload 0
getfield com/nd/schoollife/ui/team/activity/TeamHomeActivity/mTeamId J
invokestatic java/lang/String/valueOf(J)Ljava/lang/String;
aastore
dup
iconst_1
iconst_1
invokestatic java/lang/String/valueOf(Z)Ljava/lang/String;
aastore
invokevirtual com/nd/schoollife/ui/team/task/TeamTask/execute([Ljava/lang/Object;)Lcom/common/android/utils/concurrent/NdTinyHttpAsyncTask;
pop
return
.limit locals 1
.limit stack 6
.end method

.method private fromResultToBean(Lcom/nd/android/forumsdk/business/bean/result/ResultGetTeamInfo;)Lcom/nd/android/forumsdk/business/bean/structure/TeamInfoBean;
new com/nd/android/forumsdk/business/bean/structure/TeamInfoBean
dup
invokespecial com/nd/android/forumsdk/business/bean/structure/TeamInfoBean/<init>()V
astore 2
aload 2
aload 0
getfield com/nd/schoollife/ui/team/activity/TeamHomeActivity/mTeamId J
invokevirtual com/nd/android/forumsdk/business/bean/structure/TeamInfoBean/setId(J)V
aload 1
ifnull L0
aload 1
invokevirtual com/nd/android/forumsdk/business/bean/result/ResultGetTeamInfo/getSucc_list()Ljava/util/ArrayList;
astore 1
aload 1
ifnull L0
aload 1
invokevirtual java/util/ArrayList/size()I
ifle L0
aload 1
iconst_0
invokevirtual java/util/ArrayList/get(I)Ljava/lang/Object;
checkcast com/nd/android/forumsdk/business/bean/structure/GetTeamInfoSuccListBean
astore 1
aload 2
aload 1
invokevirtual com/nd/android/forumsdk/business/bean/structure/GetTeamInfoSuccListBean/getAvatar()Ljava/lang/String;
invokevirtual com/nd/android/forumsdk/business/bean/structure/TeamInfoBean/setAvatar(Ljava/lang/String;)V
aload 2
aload 1
invokevirtual com/nd/android/forumsdk/business/bean/structure/GetTeamInfoSuccListBean/getIntro()Ljava/lang/String;
invokevirtual com/nd/android/forumsdk/business/bean/structure/TeamInfoBean/setIntro(Ljava/lang/String;)V
aload 2
aload 1
invokevirtual com/nd/android/forumsdk/business/bean/structure/GetTeamInfoSuccListBean/getName()Ljava/lang/String;
invokevirtual com/nd/android/forumsdk/business/bean/structure/TeamInfoBean/setName(Ljava/lang/String;)V
aload 2
aload 1
invokevirtual com/nd/android/forumsdk/business/bean/structure/GetTeamInfoSuccListBean/getGrade()I
invokevirtual com/nd/android/forumsdk/business/bean/structure/TeamInfoBean/setGrade(I)V
aload 2
aload 1
invokevirtual com/nd/android/forumsdk/business/bean/structure/GetTeamInfoSuccListBean/getMembernum()I
invokevirtual com/nd/android/forumsdk/business/bean/structure/TeamInfoBean/setMembernum(I)V
L0:
aload 2
areturn
.limit locals 3
.limit stack 3
.end method

.method private loadHeaderViewByStatus()V
aload 0
getfield com/nd/schoollife/ui/team/activity/TeamHomeActivity/mGrade I
ifeq L0
aload 0
getstatic com/nd/schoollife/R$id/ll_community_join_bg I
invokevirtual com/nd/schoollife/ui/team/activity/TeamHomeActivity/findViewById(I)Landroid/view/View;
bipush 8
invokevirtual android/view/View/setVisibility(I)V
aload 0
getfield com/nd/schoollife/ui/team/activity/TeamHomeActivity/btnFocuse Landroid/widget/Button;
bipush 8
invokevirtual android/widget/Button/setVisibility(I)V
L1:
aload 0
getfield com/nd/schoollife/ui/team/activity/TeamHomeActivity/mGrade I
iconst_3
if_icmpeq L2
aload 0
getfield com/nd/schoollife/ui/team/activity/TeamHomeActivity/mGrade I
ifeq L2
aload 0
getfield com/nd/schoollife/ui/team/activity/TeamHomeActivity/btnUnfocuse Landroid/widget/Button;
iconst_0
invokevirtual android/widget/Button/setVisibility(I)V
return
L0:
aload 0
getstatic com/nd/schoollife/R$id/ll_community_join_bg I
invokevirtual com/nd/schoollife/ui/team/activity/TeamHomeActivity/findViewById(I)Landroid/view/View;
iconst_0
invokevirtual android/view/View/setVisibility(I)V
aload 0
getfield com/nd/schoollife/ui/team/activity/TeamHomeActivity/btnFocuse Landroid/widget/Button;
iconst_0
invokevirtual android/widget/Button/setVisibility(I)V
goto L1
L2:
aload 0
getfield com/nd/schoollife/ui/team/activity/TeamHomeActivity/btnUnfocuse Landroid/widget/Button;
bipush 8
invokevirtual android/widget/Button/setVisibility(I)V
return
.limit locals 1
.limit stack 2
.end method

.method private loadPostData(Lcom/nd/schoollife/ui/common/task/CallStyle;)V
aload 0
getfield com/nd/schoollife/ui/team/activity/TeamHomeActivity/mListView Lcom/nd/schoollife/ui/common/view/widget/CustomPullToRefreshListView;
aload 1
invokevirtual com/nd/schoollife/ui/common/view/widget/CustomPullToRefreshListView/setPageCtrlAction(Lcom/nd/schoollife/ui/common/task/CallStyle;)V
aload 0
new com/nd/schoollife/ui/post/task/PostProcessTask
dup
aload 0
bipush 14
aload 1
aload 0
invokespecial com/nd/schoollife/ui/post/task/PostProcessTask/<init>(Landroid/content/Context;ILcom/nd/schoollife/ui/common/task/CallStyle;Lcom/nd/schoollife/ui/common/base/interfaces/AsyncTaskCallback;)V
putfield com/nd/schoollife/ui/team/activity/TeamHomeActivity/postTask Lcom/nd/schoollife/ui/post/task/PostProcessTask;
aload 0
getfield com/nd/schoollife/ui/team/activity/TeamHomeActivity/postTask Lcom/nd/schoollife/ui/post/task/PostProcessTask;
iconst_4
anewarray java/lang/String
dup
iconst_0
aload 0
getfield com/nd/schoollife/ui/team/activity/TeamHomeActivity/mTeamId J
invokestatic java/lang/String/valueOf(J)Ljava/lang/String;
aastore
dup
iconst_1
new java/lang/StringBuilder
dup
invokespecial java/lang/StringBuilder/<init>()V
ldc ""
invokevirtual java/lang/StringBuilder/append(Ljava/lang/String;)Ljava/lang/StringBuilder;
aload 0
getfield com/nd/schoollife/ui/team/activity/TeamHomeActivity/mPostListAdapter Lcom/nd/schoollife/ui/post/adapter/PostListAdapter;
aload 1
invokevirtual com/nd/schoollife/ui/post/adapter/PostListAdapter/getMaxActive(Lcom/nd/schoollife/ui/common/task/CallStyle;)J
invokevirtual java/lang/StringBuilder/append(J)Ljava/lang/StringBuilder;
invokevirtual java/lang/StringBuilder/toString()Ljava/lang/String;
aastore
dup
iconst_2
new java/lang/StringBuilder
dup
invokespecial java/lang/StringBuilder/<init>()V
ldc ""
invokevirtual java/lang/StringBuilder/append(Ljava/lang/String;)Ljava/lang/StringBuilder;
aload 0
getfield com/nd/schoollife/ui/team/activity/TeamHomeActivity/mPostListAdapter Lcom/nd/schoollife/ui/post/adapter/PostListAdapter;
aload 1
invokevirtual com/nd/schoollife/ui/post/adapter/PostListAdapter/getMinActive(Lcom/nd/schoollife/ui/common/task/CallStyle;)J
invokevirtual java/lang/StringBuilder/append(J)Ljava/lang/StringBuilder;
invokevirtual java/lang/StringBuilder/toString()Ljava/lang/String;
aastore
dup
iconst_3
bipush 30
invokestatic java/lang/String/valueOf(I)Ljava/lang/String;
aastore
invokevirtual com/nd/schoollife/ui/post/task/PostProcessTask/execute([Ljava/lang/Object;)Lcom/common/android/utils/concurrent/NdTinyHttpAsyncTask;
pop
return
.limit locals 2
.limit stack 7
.end method

.method private showPostView()V
aload 0
getfield com/nd/schoollife/ui/team/activity/TeamHomeActivity/mPostInfoBeans Ljava/util/List;
invokeinterface java/util/List/size()I 0
ifne L0
aload 0
getfield com/nd/schoollife/ui/team/activity/TeamHomeActivity/mListView Lcom/nd/schoollife/ui/common/view/widget/CustomPullToRefreshListView;
bipush 8
invokevirtual com/nd/schoollife/ui/common/view/widget/CustomPullToRefreshListView/setVisibility(I)V
aload 0
getstatic com/nd/schoollife/R$id/ll_team_home_post_nodata I
invokevirtual com/nd/schoollife/ui/team/activity/TeamHomeActivity/findViewById(I)Landroid/view/View;
iconst_0
invokevirtual android/view/View/setVisibility(I)V
return
L0:
aload 0
getfield com/nd/schoollife/ui/team/activity/TeamHomeActivity/mListView Lcom/nd/schoollife/ui/common/view/widget/CustomPullToRefreshListView;
iconst_0
invokevirtual com/nd/schoollife/ui/common/view/widget/CustomPullToRefreshListView/setVisibility(I)V
aload 0
getstatic com/nd/schoollife/R$id/ll_team_home_post_nodata I
invokevirtual com/nd/schoollife/ui/team/activity/TeamHomeActivity/findViewById(I)Landroid/view/View;
bipush 8
invokevirtual android/view/View/setVisibility(I)V
return
.limit locals 1
.limit stack 2
.end method

.method private startGetTeamInfoTask()V
aload 0
getfield com/nd/schoollife/ui/team/activity/TeamHomeActivity/mTeamId J
lconst_0
lcmp
ifne L0
aload 0
getfield com/nd/schoollife/ui/team/activity/TeamHomeActivity/mRefreshBtn Lcom/nd/schoollife/ui/common/view/RefreshBtn;
bipush 8
invokevirtual com/nd/schoollife/ui/common/view/RefreshBtn/setVisibility(I)V
return
L0:
aload 0
invokevirtual com/nd/schoollife/ui/team/activity/TeamHomeActivity/showLoading()V
new com/nd/schoollife/ui/team/task/TeamTask
dup
aload 0
sipush 4097
getstatic com/nd/schoollife/ui/common/task/CallStyle/CALL_STYLE_INIT Lcom/nd/schoollife/ui/common/task/CallStyle;
aload 0
invokespecial com/nd/schoollife/ui/team/task/TeamTask/<init>(Landroid/content/Context;ILcom/nd/schoollife/ui/common/task/CallStyle;Lcom/nd/schoollife/ui/common/base/interfaces/AsyncTaskCallback;)V
iconst_1
anewarray java/lang/String
dup
iconst_0
aload 0
getfield com/nd/schoollife/ui/team/activity/TeamHomeActivity/mTeamId J
invokestatic java/lang/String/valueOf(J)Ljava/lang/String;
aastore
invokevirtual com/nd/schoollife/ui/team/task/TeamTask/execute([Ljava/lang/Object;)Lcom/common/android/utils/concurrent/NdTinyHttpAsyncTask;
pop
return
.limit locals 1
.limit stack 6
.end method

.method private unFocusTeamTask()V
aload 0
invokevirtual com/nd/schoollife/ui/team/activity/TeamHomeActivity/showLoading()V
new com/nd/schoollife/ui/team/task/TeamTask
dup
aload 0
sipush 4104
getstatic com/nd/schoollife/ui/common/task/CallStyle/CALL_STYLE_SUBMIT Lcom/nd/schoollife/ui/common/task/CallStyle;
aload 0
invokespecial com/nd/schoollife/ui/team/task/TeamTask/<init>(Landroid/content/Context;ILcom/nd/schoollife/ui/common/task/CallStyle;Lcom/nd/schoollife/ui/common/base/interfaces/AsyncTaskCallback;)V
iconst_2
anewarray java/lang/String
dup
iconst_0
aload 0
getfield com/nd/schoollife/ui/team/activity/TeamHomeActivity/mTeamId J
invokestatic java/lang/String/valueOf(J)Ljava/lang/String;
aastore
dup
iconst_1
iconst_0
invokestatic java/lang/String/valueOf(Z)Ljava/lang/String;
aastore
invokevirtual com/nd/schoollife/ui/team/task/TeamTask/execute([Ljava/lang/Object;)Lcom/common/android/utils/concurrent/NdTinyHttpAsyncTask;
pop
return
.limit locals 1
.limit stack 6
.end method

.method private unFocuseTeam()V
aload 0
ldc "\u63d0\u793a"
new java/lang/StringBuilder
dup
invokespecial java/lang/StringBuilder/<init>()V
ldc "\u662f\u5426\u53d6\u6d88\u5173\u6ce8"
invokevirtual java/lang/StringBuilder/append(Ljava/lang/String;)Ljava/lang/StringBuilder;
aload 0
getfield com/nd/schoollife/ui/team/activity/TeamHomeActivity/mTeamName Ljava/lang/String;
invokevirtual java/lang/StringBuilder/append(Ljava/lang/String;)Ljava/lang/StringBuilder;
ldc "?"
invokevirtual java/lang/StringBuilder/append(Ljava/lang/String;)Ljava/lang/StringBuilder;
invokevirtual java/lang/StringBuilder/toString()Ljava/lang/String;
ldc ""
ldc ""
new com/nd/schoollife/ui/team/activity/TeamHomeActivity$4
dup
aload 0
invokespecial com/nd/schoollife/ui/team/activity/TeamHomeActivity$4/<init>(Lcom/nd/schoollife/ui/team/activity/TeamHomeActivity;)V
new com/nd/schoollife/ui/team/activity/TeamHomeActivity$5
dup
aload 0
invokespecial com/nd/schoollife/ui/team/activity/TeamHomeActivity$5/<init>(Lcom/nd/schoollife/ui/team/activity/TeamHomeActivity;)V
invokevirtual com/nd/schoollife/ui/team/activity/TeamHomeActivity/showConfirmDialog(Ljava/lang/String;Ljava/lang/String;Ljava/lang/String;Ljava/lang/String;Landroid/view/View$OnClickListener;Landroid/view/View$OnClickListener;)V
return
.limit locals 1
.limit stack 9
.end method

.method protected initContentView()V
aload 0
getstatic com/nd/schoollife/R$layout/activity_team_home I
invokevirtual com/nd/schoollife/ui/team/activity/TeamHomeActivity/setContentView(I)V
aload 0
aload 0
getstatic com/nd/schoollife/R$id/rb_community_refresh I
invokevirtual com/nd/schoollife/ui/team/activity/TeamHomeActivity/findViewById(I)Landroid/view/View;
checkcast com/nd/schoollife/ui/common/view/RefreshBtn
putfield com/nd/schoollife/ui/team/activity/TeamHomeActivity/mRefreshBtn Lcom/nd/schoollife/ui/common/view/RefreshBtn;
aload 0
aload 0
getstatic com/nd/schoollife/R$id/slideHolder I
invokevirtual com/nd/schoollife/ui/team/activity/TeamHomeActivity/findViewById(I)Landroid/view/View;
checkcast com/nd/schoollife/ui/team/view/SlideHolder
putfield com/nd/schoollife/ui/team/activity/TeamHomeActivity/mSlideHolder Lcom/nd/schoollife/ui/team/view/SlideHolder;
aload 0
aload 0
getstatic com/nd/schoollife/R$id/ll_team_host_slider_menu I
invokevirtual com/nd/schoollife/ui/team/activity/TeamHomeActivity/findViewById(I)Landroid/view/View;
checkcast android/widget/LinearLayout
putfield com/nd/schoollife/ui/team/activity/TeamHomeActivity/mLlMenu Landroid/widget/LinearLayout;
aload 0
aload 0
getstatic com/nd/schoollife/R$id/lv_community_posts I
invokevirtual com/nd/schoollife/ui/team/activity/TeamHomeActivity/findViewById(I)Landroid/view/View;
checkcast com/nd/schoollife/ui/common/view/widget/CustomPullToRefreshListView
putfield com/nd/schoollife/ui/team/activity/TeamHomeActivity/mListView Lcom/nd/schoollife/ui/common/view/widget/CustomPullToRefreshListView;
aload 0
getfield com/nd/schoollife/ui/team/activity/TeamHomeActivity/mListView Lcom/nd/schoollife/ui/common/view/widget/CustomPullToRefreshListView;
getstatic com/nd/schoollife/ui/common/view/widget/CustomPullToRefreshListView$ActionMode/BOTH Lcom/nd/schoollife/ui/common/view/widget/CustomPullToRefreshListView$ActionMode;
invokevirtual com/nd/schoollife/ui/common/view/widget/CustomPullToRefreshListView/setActionMode(Lcom/nd/schoollife/ui/common/view/widget/CustomPullToRefreshListView$ActionMode;)V
aload 0
getfield com/nd/schoollife/ui/team/activity/TeamHomeActivity/mListView Lcom/nd/schoollife/ui/common/view/widget/CustomPullToRefreshListView;
aload 0
invokevirtual com/nd/schoollife/ui/common/view/widget/CustomPullToRefreshListView/setPullToActionListerner(Lcom/nd/schoollife/ui/common/view/widget/CustomPullToRefreshListView$PullToActionListener;)V
aload 0
getstatic com/nd/schoollife/R$id/btn_common_head_right_appeal I
invokevirtual com/nd/schoollife/ui/team/activity/TeamHomeActivity/findViewById(I)Landroid/view/View;
iconst_0
invokevirtual android/view/View/setVisibility(I)V
aload 0
getfield com/nd/schoollife/ui/team/activity/TeamHomeActivity/mSlideHolder Lcom/nd/schoollife/ui/team/view/SlideHolder;
iconst_m1
invokevirtual com/nd/schoollife/ui/team/view/SlideHolder/setDirection(I)V
aload 0
aload 0
getstatic com/nd/schoollife/R$id/btn_team_host_slider_menu_quit_team I
invokevirtual com/nd/schoollife/ui/team/activity/TeamHomeActivity/findViewById(I)Landroid/view/View;
checkcast android/widget/Button
putfield com/nd/schoollife/ui/team/activity/TeamHomeActivity/btnUnfocuse Landroid/widget/Button;
aload 0
aload 0
getstatic com/nd/schoollife/R$id/civ_team_avatar I
invokevirtual com/nd/schoollife/ui/team/activity/TeamHomeActivity/findViewById(I)Landroid/view/View;
checkcast com/nd/schoollife/ui/common/view/CircleImageView
putfield com/nd/schoollife/ui/team/activity/TeamHomeActivity/civAvatar Lcom/nd/schoollife/ui/common/view/CircleImageView;
aload 0
aload 0
getstatic com/nd/schoollife/R$id/tv_team_host_slider_menu_usr_name I
invokevirtual com/nd/schoollife/ui/team/activity/TeamHomeActivity/findViewById(I)Landroid/view/View;
checkcast android/widget/TextView
putfield com/nd/schoollife/ui/team/activity/TeamHomeActivity/mName Landroid/widget/TextView;
aload 0
getfield com/nd/schoollife/ui/team/activity/TeamHomeActivity/mLlMenu Landroid/widget/LinearLayout;
invokevirtual android/widget/LinearLayout/getLayoutParams()Landroid/view/ViewGroup$LayoutParams;
astore 1
aload 1
aload 0
getfield com/nd/schoollife/ui/team/activity/TeamHomeActivity/mCtx Landroid/content/Context;
invokestatic com/nd/schoollife/common/utils/ui/DisplayUtil/getScreenWidth(Landroid/content/Context;)I
iconst_5
idiv
iconst_4
imul
putfield android/view/ViewGroup$LayoutParams/width I
aload 1
iconst_m1
putfield android/view/ViewGroup$LayoutParams/height I
aload 0
getfield com/nd/schoollife/ui/team/activity/TeamHomeActivity/mLlMenu Landroid/widget/LinearLayout;
aload 1
invokevirtual android/widget/LinearLayout/setLayoutParams(Landroid/view/ViewGroup$LayoutParams;)V
aload 0
aload 0
getstatic com/nd/schoollife/R$id/ll_inputcontent I
invokevirtual com/nd/schoollife/ui/team/activity/TeamHomeActivity/findViewById(I)Landroid/view/View;
checkcast android/widget/LinearLayout
putfield com/nd/schoollife/ui/team/activity/TeamHomeActivity/mCommentEditViewLayout Landroid/widget/LinearLayout;
aload 0
new com/nd/schoollife/ui/common/process/InputContentViewManager
dup
aload 0
aload 0
getfield com/nd/schoollife/ui/team/activity/TeamHomeActivity/mCommentEditViewLayout Landroid/widget/LinearLayout;
aload 0
invokespecial com/nd/schoollife/ui/common/process/InputContentViewManager/<init>(Landroid/app/Activity;Landroid/view/ViewGroup;Lcom/nd/schoollife/ui/common/base/interfaces/AsyncTaskCallback;)V
putfield com/nd/schoollife/ui/team/activity/TeamHomeActivity/mInputContentManager Lcom/nd/schoollife/ui/common/process/InputContentViewManager;
aload 0
new com/nd/schoollife/ui/post/adapter/PostListAdapter
dup
aload 0
getfield com/nd/schoollife/ui/team/activity/TeamHomeActivity/mCtx Landroid/content/Context;
new com/nd/schoollife/ui/common/view/widget/pagination/ActivePageInfo
dup
bipush 30
invokespecial com/nd/schoollife/ui/common/view/widget/pagination/ActivePageInfo/<init>(I)V
aload 0
getfield com/nd/schoollife/ui/team/activity/TeamHomeActivity/mInputContentManager Lcom/nd/schoollife/ui/common/process/InputContentViewManager;
invokespecial com/nd/schoollife/ui/post/adapter/PostListAdapter/<init>(Landroid/content/Context;Lcom/nd/schoollife/ui/common/view/widget/pagination/ActivePageInfo;Lcom/nd/schoollife/ui/common/process/InputContentViewManager;)V
putfield com/nd/schoollife/ui/team/activity/TeamHomeActivity/mPostListAdapter Lcom/nd/schoollife/ui/post/adapter/PostListAdapter;
aload 0
getfield com/nd/schoollife/ui/team/activity/TeamHomeActivity/mListView Lcom/nd/schoollife/ui/common/view/widget/CustomPullToRefreshListView;
aload 0
getfield com/nd/schoollife/ui/team/activity/TeamHomeActivity/mPostListAdapter Lcom/nd/schoollife/ui/post/adapter/PostListAdapter;
invokevirtual com/nd/schoollife/ui/common/view/widget/CustomPullToRefreshListView/setAdapter(Landroid/widget/ListAdapter;)V
aload 0
aload 0
getstatic com/nd/schoollife/R$id/btn_community_application I
invokevirtual com/nd/schoollife/ui/team/activity/TeamHomeActivity/findViewById(I)Landroid/view/View;
checkcast android/widget/Button
putfield com/nd/schoollife/ui/team/activity/TeamHomeActivity/btnFocuse Landroid/widget/Button;
aload 0
getfield com/nd/schoollife/ui/team/activity/TeamHomeActivity/btnFocuse Landroid/widget/Button;
aload 0
getstatic com/nd/schoollife/R$string/team_submit I
invokevirtual com/nd/schoollife/ui/team/activity/TeamHomeActivity/getString(I)Ljava/lang/String;
invokevirtual android/widget/Button/setText(Ljava/lang/CharSequence;)V
aload 0
iconst_1
putfield com/nd/schoollife/ui/team/activity/TeamHomeActivity/isInit Z
aload 0
invokespecial com/nd/schoollife/ui/team/activity/TeamHomeActivity/startGetTeamInfoTask()V
return
.limit locals 2
.limit stack 7
.end method

.method protected initData(Landroid/os/Bundle;)V
.catch java/lang/Exception from L0 to L1 using L2
.catch java/lang/Exception from L3 to L4 using L2
.catch java/lang/Exception from L4 to L5 using L2
L0:
aload 0
aload 0
invokevirtual com/nd/schoollife/ui/team/activity/TeamHomeActivity/getIntent()Landroid/content/Intent;
ldc "LONG_TEAM_OR_COMMUNITY_ID"
lconst_0
invokevirtual android/content/Intent/getLongExtra(Ljava/lang/String;J)J
putfield com/nd/schoollife/ui/team/activity/TeamHomeActivity/mTeamId J
aload 0
getfield com/nd/schoollife/ui/team/activity/TeamHomeActivity/mTeamId J
lconst_0
lcmp
ifne L4
L1:
aload 1
ifnull L4
L3:
aload 0
aload 1
ldc "KEY_SAVE_TEAM_ID"
invokevirtual android/os/Bundle/getLong(Ljava/lang/String;)J
putfield com/nd/schoollife/ui/team/activity/TeamHomeActivity/mTeamId J
L4:
aload 0
getfield com/nd/schoollife/ui/team/activity/TeamHomeActivity/mTeamId J
lconst_0
lcmp
ifne L5
aload 0
getfield com/nd/schoollife/ui/team/activity/TeamHomeActivity/mCtx Landroid/content/Context;
ldc "\u4f20\u9012\u8fc7\u6765\u7684id\u4e3a\u7a7a"
invokestatic com/nd/schoollife/common/utils/ui/ToastUtil/showLongToast4Debug(Landroid/content/Context;Ljava/lang/String;)V
L5:
aload 0
new java/util/ArrayList
dup
invokespecial java/util/ArrayList/<init>()V
putfield com/nd/schoollife/ui/team/activity/TeamHomeActivity/mPostInfoBeans Ljava/util/List;
return
L2:
astore 1
aload 1
invokevirtual java/lang/Exception/printStackTrace()V
goto L5
.limit locals 2
.limit stack 5
.end method

.method protected initEvent()V
aload 0
getstatic com/nd/schoollife/R$id/btn_common_head_back I
invokevirtual com/nd/schoollife/ui/team/activity/TeamHomeActivity/findViewById(I)Landroid/view/View;
aload 0
invokevirtual android/view/View/setOnClickListener(Landroid/view/View$OnClickListener;)V
aload 0
getstatic com/nd/schoollife/R$id/btn_common_head_edit I
invokevirtual com/nd/schoollife/ui/team/activity/TeamHomeActivity/findViewById(I)Landroid/view/View;
aload 0
invokevirtual android/view/View/setOnClickListener(Landroid/view/View$OnClickListener;)V
aload 0
getstatic com/nd/schoollife/R$id/btn_post_no_data_send_post I
invokevirtual com/nd/schoollife/ui/team/activity/TeamHomeActivity/findViewById(I)Landroid/view/View;
aload 0
invokevirtual android/view/View/setOnClickListener(Landroid/view/View$OnClickListener;)V
aload 0
getstatic com/nd/schoollife/R$id/btn_common_head_menu I
invokevirtual com/nd/schoollife/ui/team/activity/TeamHomeActivity/findViewById(I)Landroid/view/View;
aload 0
invokevirtual android/view/View/setOnClickListener(Landroid/view/View$OnClickListener;)V
aload 0
getstatic com/nd/schoollife/R$id/rl_community_item I
invokevirtual com/nd/schoollife/ui/team/activity/TeamHomeActivity/findViewById(I)Landroid/view/View;
aload 0
invokevirtual android/view/View/setOnClickListener(Landroid/view/View$OnClickListener;)V
aload 0
getstatic com/nd/schoollife/R$id/btn_team_host_slider_menu_team_info I
invokevirtual com/nd/schoollife/ui/team/activity/TeamHomeActivity/findViewById(I)Landroid/view/View;
aload 0
invokevirtual android/view/View/setOnClickListener(Landroid/view/View$OnClickListener;)V
aload 0
getfield com/nd/schoollife/ui/team/activity/TeamHomeActivity/btnFocuse Landroid/widget/Button;
aload 0
invokevirtual android/widget/Button/setOnClickListener(Landroid/view/View$OnClickListener;)V
aload 0
getfield com/nd/schoollife/ui/team/activity/TeamHomeActivity/mRefreshBtn Lcom/nd/schoollife/ui/common/view/RefreshBtn;
aload 0
invokevirtual com/nd/schoollife/ui/common/view/RefreshBtn/setRefreshOnClickListener(Lcom/nd/schoollife/ui/common/view/RefreshBtn$RefreshBtnOnClickListener;)V
aload 0
getfield com/nd/schoollife/ui/team/activity/TeamHomeActivity/btnUnfocuse Landroid/widget/Button;
aload 0
invokevirtual android/widget/Button/setOnClickListener(Landroid/view/View$OnClickListener;)V
aload 0
getfield com/nd/schoollife/ui/team/activity/TeamHomeActivity/mInputContentManager Lcom/nd/schoollife/ui/common/process/InputContentViewManager;
new com/nd/schoollife/ui/team/activity/TeamHomeActivity$1
dup
aload 0
invokespecial com/nd/schoollife/ui/team/activity/TeamHomeActivity$1/<init>(Lcom/nd/schoollife/ui/team/activity/TeamHomeActivity;)V
invokevirtual com/nd/schoollife/ui/common/process/InputContentViewManager/setOnCommentViewShowListener(Lcom/nd/schoollife/ui/common/process/InputContentViewManager$OnCommentViewShowListener;)V
aload 0
getfield com/nd/schoollife/ui/team/activity/TeamHomeActivity/mListView Lcom/nd/schoollife/ui/common/view/widget/CustomPullToRefreshListView;
new com/nd/schoollife/ui/team/activity/TeamHomeActivity$2
dup
aload 0
invokespecial com/nd/schoollife/ui/team/activity/TeamHomeActivity$2/<init>(Lcom/nd/schoollife/ui/team/activity/TeamHomeActivity;)V
invokevirtual com/nd/schoollife/ui/common/view/widget/CustomPullToRefreshListView/setOnScrollListener(Landroid/widget/AbsListView$OnScrollListener;)V
aload 0
new com/nd/schoollife/common/receiver/PraiseChangeReceiver
dup
new com/nd/schoollife/ui/team/activity/TeamHomeActivity$3
dup
aload 0
invokespecial com/nd/schoollife/ui/team/activity/TeamHomeActivity$3/<init>(Lcom/nd/schoollife/ui/team/activity/TeamHomeActivity;)V
invokespecial com/nd/schoollife/common/receiver/PraiseChangeReceiver/<init>(Lcom/nd/schoollife/ui/common/process/PraiseListener;)V
putfield com/nd/schoollife/ui/team/activity/TeamHomeActivity/mPraiseChangeReceiver Lcom/nd/schoollife/common/receiver/PraiseChangeReceiver;
new android/content/IntentFilter
dup
invokespecial android/content/IntentFilter/<init>()V
astore 1
aload 1
ldc "com.nd.schoollife.praisechange"
invokevirtual android/content/IntentFilter/addAction(Ljava/lang/String;)V
aload 0
aload 0
getfield com/nd/schoollife/ui/team/activity/TeamHomeActivity/mPraiseChangeReceiver Lcom/nd/schoollife/common/receiver/PraiseChangeReceiver;
aload 1
invokevirtual com/nd/schoollife/ui/team/activity/TeamHomeActivity/registerReceiver(Landroid/content/BroadcastReceiver;Landroid/content/IntentFilter;)Landroid/content/Intent;
pop
aload 0
aload 0
invokevirtual com/nd/schoollife/ui/team/activity/TeamHomeActivity/setOnReloadClickListener(Lcom/nd/schoollife/ui/common/base/interfaces/OnReloadClickedListener;)V
return
.limit locals 2
.limit stack 6
.end method

.method protected initHeadView(Landroid/content/Context;)Landroid/view/View;
aconst_null
areturn
.limit locals 2
.limit stack 1
.end method

.method protected onActivityResult(IILandroid/content/Intent;)V
.catch java/lang/Exception from L0 to L1 using L2
.catch java/lang/Exception from L3 to L4 using L2
.catch java/lang/Exception from L5 to L6 using L2
.catch java/lang/Exception from L7 to L8 using L2
.catch java/lang/Exception from L9 to L10 using L2
.catch java/lang/Exception from L11 to L12 using L2
.catch java/lang/Exception from L13 to L14 using L2
.catch java/lang/Exception from L15 to L16 using L2
iload 2
iconst_m1
if_icmpeq L17
L18:
return
L17:
iload 1
lookupswitch
100 : L0
101 : L3
102 : L5
103 : L19
999 : L15
default : L20
L20:
return
L0:
aload 0
getfield com/nd/schoollife/ui/team/activity/TeamHomeActivity/mInputContentManager Lcom/nd/schoollife/ui/common/process/InputContentViewManager;
aload 3
invokevirtual com/nd/schoollife/ui/common/process/InputContentViewManager/onResultCamera(Landroid/content/Intent;)V
L1:
return
L2:
astore 3
aload 3
invokevirtual java/lang/Exception/printStackTrace()V
return
L3:
aload 0
getfield com/nd/schoollife/ui/team/activity/TeamHomeActivity/mInputContentManager Lcom/nd/schoollife/ui/common/process/InputContentViewManager;
aload 3
invokevirtual com/nd/schoollife/ui/common/process/InputContentViewManager/onResultPic(Landroid/content/Intent;)V
L4:
return
L5:
aload 0
getfield com/nd/schoollife/ui/team/activity/TeamHomeActivity/mInputContentManager Lcom/nd/schoollife/ui/common/process/InputContentViewManager;
aload 3
invokevirtual com/nd/schoollife/ui/common/process/InputContentViewManager/onResultAt(Landroid/content/Intent;)V
L6:
return
L19:
aload 3
ifnull L18
L7:
aload 3
ldc "IS_DEL"
iconst_0
invokevirtual android/content/Intent/getBooleanExtra(Ljava/lang/String;Z)Z
istore 4
aload 3
ldc "IS_PRAISE"
iconst_m1
invokevirtual android/content/Intent/getIntExtra(Ljava/lang/String;I)I
istore 1
aload 0
aload 3
ldc "INT_POST_ID"
ldc2_w -1L
invokevirtual android/content/Intent/getLongExtra(Ljava/lang/String;J)J
invokespecial com/nd/schoollife/ui/team/activity/TeamHomeActivity/findPost(J)I
istore 2
L8:
iload 2
iconst_m1
if_icmpeq L18
iload 4
ifeq L21
L9:
aload 0
getfield com/nd/schoollife/ui/team/activity/TeamHomeActivity/mPostListAdapter Lcom/nd/schoollife/ui/post/adapter/PostListAdapter;
invokevirtual com/nd/schoollife/ui/post/adapter/PostListAdapter/getList()Ljava/util/List;
iload 2
invokeinterface java/util/List/remove(I)Ljava/lang/Object; 1
pop
aload 0
getfield com/nd/schoollife/ui/team/activity/TeamHomeActivity/mPostListAdapter Lcom/nd/schoollife/ui/post/adapter/PostListAdapter;
invokevirtual com/nd/schoollife/ui/post/adapter/PostListAdapter/notifyDataSetChanged()V
L10:
return
L21:
iload 1
iconst_m1
if_icmpeq L18
L11:
aload 0
getfield com/nd/schoollife/ui/team/activity/TeamHomeActivity/mPostListAdapter Lcom/nd/schoollife/ui/post/adapter/PostListAdapter;
invokevirtual com/nd/schoollife/ui/post/adapter/PostListAdapter/getList()Ljava/util/List;
astore 3
L12:
aload 3
ifnull L18
L13:
aload 3
invokeinterface java/util/List/size()I 0
iload 2
iconst_1
iadd
if_icmplt L18
aload 3
iload 2
invokeinterface java/util/List/get(I)Ljava/lang/Object; 1
ifnull L18
aload 3
iload 2
invokeinterface java/util/List/get(I)Ljava/lang/Object; 1
checkcast com/nd/android/forumsdk/business/bean/result/PostInfoBean
iload 1
invokevirtual com/nd/android/forumsdk/business/bean/result/PostInfoBean/setPraised(I)V
aload 0
getfield com/nd/schoollife/ui/team/activity/TeamHomeActivity/mPostListAdapter Lcom/nd/schoollife/ui/post/adapter/PostListAdapter;
invokevirtual com/nd/schoollife/ui/post/adapter/PostListAdapter/notifyDataSetChanged()V
L14:
return
L15:
aload 0
getfield com/nd/schoollife/ui/team/activity/TeamHomeActivity/mRefreshBtn Lcom/nd/schoollife/ui/common/view/RefreshBtn;
invokevirtual com/nd/schoollife/ui/common/view/RefreshBtn/isRoting()Z
ifne L18
aload 0
getfield com/nd/schoollife/ui/team/activity/TeamHomeActivity/mRefreshBtn Lcom/nd/schoollife/ui/common/view/RefreshBtn;
invokevirtual com/nd/schoollife/ui/common/view/RefreshBtn/performClick()Z
pop
L16:
return
.limit locals 5
.limit stack 5
.end method

.method public onBackPressed()V
aload 0
getfield com/nd/schoollife/ui/team/activity/TeamHomeActivity/mSlideHolder Lcom/nd/schoollife/ui/team/view/SlideHolder;
invokevirtual com/nd/schoollife/ui/team/view/SlideHolder/isOpened()Z
ifeq L0
aload 0
getfield com/nd/schoollife/ui/team/activity/TeamHomeActivity/mSlideHolder Lcom/nd/schoollife/ui/team/view/SlideHolder;
invokevirtual com/nd/schoollife/ui/team/view/SlideHolder/toggle()V
return
L0:
aload 0
invokevirtual com/nd/schoollife/ui/team/activity/TeamHomeActivity/finish()V
return
.limit locals 1
.limit stack 1
.end method

.method public onClick(Landroid/view/View;)V
aload 1
invokevirtual android/view/View/getId()I
istore 2
iload 2
getstatic com/nd/schoollife/R$id/btn_common_head_back I
if_icmpne L0
aload 0
invokevirtual com/nd/schoollife/ui/team/activity/TeamHomeActivity/finish()V
L1:
return
L0:
iload 2
getstatic com/nd/schoollife/R$id/btn_common_head_edit I
if_icmpeq L2
iload 2
getstatic com/nd/schoollife/R$id/btn_post_no_data_send_post I
if_icmpne L3
L2:
new android/content/Intent
dup
aload 0
ldc com/nd/schoollife/ui/post/activity/PostSendActivity
invokespecial android/content/Intent/<init>(Landroid/content/Context;Ljava/lang/Class;)V
astore 1
aload 1
ldc "LONG_TEAM_OR_COMMUNITY_ID"
aload 0
getfield com/nd/schoollife/ui/team/activity/TeamHomeActivity/mTeamId J
invokevirtual android/content/Intent/putExtra(Ljava/lang/String;J)Landroid/content/Intent;
pop
aload 1
ldc "INT_SCOPE_TYPE"
getstatic com/nd/android/forumsdk/business/constant/RequestConst$ScopeType/TEAM Lcom/nd/android/forumsdk/business/constant/RequestConst$ScopeType;
invokevirtual android/content/Intent/putExtra(Ljava/lang/String;Ljava/io/Serializable;)Landroid/content/Intent;
pop
aload 0
aload 1
sipush 999
invokevirtual com/nd/schoollife/ui/team/activity/TeamHomeActivity/startActivityForResult(Landroid/content/Intent;I)V
return
L3:
iload 2
getstatic com/nd/schoollife/R$id/btn_common_head_menu I
if_icmpne L4
aload 0
getfield com/nd/schoollife/ui/team/activity/TeamHomeActivity/mInputContentManager Lcom/nd/schoollife/ui/common/process/InputContentViewManager;
ifnull L5
aload 0
getfield com/nd/schoollife/ui/team/activity/TeamHomeActivity/mInputContentManager Lcom/nd/schoollife/ui/common/process/InputContentViewManager;
invokevirtual com/nd/schoollife/ui/common/process/InputContentViewManager/hideView()V
L5:
aload 0
getfield com/nd/schoollife/ui/team/activity/TeamHomeActivity/mSlideHolder Lcom/nd/schoollife/ui/team/view/SlideHolder;
invokevirtual com/nd/schoollife/ui/team/view/SlideHolder/toggle()V
return
L4:
iload 2
getstatic com/nd/schoollife/R$id/btn_team_host_slider_menu_team_info I
if_icmpeq L6
iload 2
getstatic com/nd/schoollife/R$id/rl_community_item I
if_icmpne L7
L6:
new android/content/Intent
dup
aload 0
ldc com/nd/schoollife/ui/team/activity/TeamInfoActivity
invokespecial android/content/Intent/<init>(Landroid/content/Context;Ljava/lang/Class;)V
astore 1
aload 1
ldc "LONG_TEAM_OR_COMMUNITY_ID"
aload 0
getfield com/nd/schoollife/ui/team/activity/TeamHomeActivity/mTeamId J
invokevirtual android/content/Intent/putExtra(Ljava/lang/String;J)Landroid/content/Intent;
pop
aload 0
aload 1
invokevirtual com/nd/schoollife/ui/team/activity/TeamHomeActivity/startActivity(Landroid/content/Intent;)V
return
L7:
iload 2
getstatic com/nd/schoollife/R$id/btn_team_host_slider_menu_quit_team I
if_icmpne L8
aload 0
invokespecial com/nd/schoollife/ui/team/activity/TeamHomeActivity/unFocuseTeam()V
return
L8:
iload 2
getstatic com/nd/schoollife/R$id/tv_community_posts_more I
if_icmpne L9
aload 0
new android/content/Intent
dup
aload 0
ldc com/nd/schoollife/ui/post/activity/PostListActivity
invokespecial android/content/Intent/<init>(Landroid/content/Context;Ljava/lang/Class;)V
invokevirtual com/nd/schoollife/ui/team/activity/TeamHomeActivity/startActivity(Landroid/content/Intent;)V
return
L9:
iload 2
getstatic com/nd/schoollife/R$id/btn_community_application I
if_icmpne L1
aload 0
invokespecial com/nd/schoollife/ui/team/activity/TeamHomeActivity/focusTeamTask()V
return
.limit locals 3
.limit stack 5
.end method

.method protected onDestroy()V
aload 0
getfield com/nd/schoollife/ui/team/activity/TeamHomeActivity/mPraiseChangeReceiver Lcom/nd/schoollife/common/receiver/PraiseChangeReceiver;
ifnull L0
aload 0
aload 0
getfield com/nd/schoollife/ui/team/activity/TeamHomeActivity/mPraiseChangeReceiver Lcom/nd/schoollife/common/receiver/PraiseChangeReceiver;
invokevirtual com/nd/schoollife/ui/team/activity/TeamHomeActivity/unregisterReceiver(Landroid/content/BroadcastReceiver;)V
L0:
aload 0
invokespecial com/nd/schoollife/ui/common/activity/BaseSchoollifeActivity/onDestroy()V
return
.limit locals 1
.limit stack 2
.end method

.method public onPullDownToRefresh(Lcom/handmark/pulltorefresh/library/PullToRefreshBase;)V
.signature "(Lcom/handmark/pulltorefresh/library/PullToRefreshBase<Landroid/widget/ListView;>;)V"
aload 0
getfield com/nd/schoollife/ui/team/activity/TeamHomeActivity/mInputContentManager Lcom/nd/schoollife/ui/common/process/InputContentViewManager;
ifnull L0
aload 0
getfield com/nd/schoollife/ui/team/activity/TeamHomeActivity/mInputContentManager Lcom/nd/schoollife/ui/common/process/InputContentViewManager;
invokevirtual com/nd/schoollife/ui/common/process/InputContentViewManager/hideView()V
L0:
aload 0
getfield com/nd/schoollife/ui/team/activity/TeamHomeActivity/mRefreshBtn Lcom/nd/schoollife/ui/common/view/RefreshBtn;
invokevirtual com/nd/schoollife/ui/common/view/RefreshBtn/isRoting()Z
ifne L1
aload 0
getfield com/nd/schoollife/ui/team/activity/TeamHomeActivity/mRefreshBtn Lcom/nd/schoollife/ui/common/view/RefreshBtn;
invokevirtual com/nd/schoollife/ui/common/view/RefreshBtn/performClick()Z
pop
L1:
aload 0
getstatic com/nd/schoollife/ui/common/task/CallStyle/CALL_STYLE_REFLASH Lcom/nd/schoollife/ui/common/task/CallStyle;
invokespecial com/nd/schoollife/ui/team/activity/TeamHomeActivity/loadPostData(Lcom/nd/schoollife/ui/common/task/CallStyle;)V
return
.limit locals 2
.limit stack 2
.end method

.method public onPullUpToLoadMore(Lcom/handmark/pulltorefresh/library/PullToRefreshBase;)V
.signature "(Lcom/handmark/pulltorefresh/library/PullToRefreshBase<Landroid/widget/ListView;>;)V"
aload 0
getfield com/nd/schoollife/ui/team/activity/TeamHomeActivity/mInputContentManager Lcom/nd/schoollife/ui/common/process/InputContentViewManager;
ifnull L0
aload 0
getfield com/nd/schoollife/ui/team/activity/TeamHomeActivity/mInputContentManager Lcom/nd/schoollife/ui/common/process/InputContentViewManager;
invokevirtual com/nd/schoollife/ui/common/process/InputContentViewManager/hideView()V
L0:
aload 0
getstatic com/nd/schoollife/ui/common/task/CallStyle/CALL_STYLE_LOADMORE Lcom/nd/schoollife/ui/common/task/CallStyle;
invokespecial com/nd/schoollife/ui/team/activity/TeamHomeActivity/loadPostData(Lcom/nd/schoollife/ui/common/task/CallStyle;)V
return
.limit locals 2
.limit stack 2
.end method

.method public onRefreshOnClick(Lcom/nd/schoollife/ui/common/view/RefreshBtn;)Z
aload 0
getfield com/nd/schoollife/ui/team/activity/TeamHomeActivity/postTask Lcom/nd/schoollife/ui/post/task/PostProcessTask;
ifnull L0
aload 0
getfield com/nd/schoollife/ui/team/activity/TeamHomeActivity/postTask Lcom/nd/schoollife/ui/post/task/PostProcessTask;
invokevirtual com/nd/schoollife/ui/post/task/PostProcessTask/getStatus()Lcom/common/android/utils/concurrent/NdTinyHttpAsyncTask$Status;
getstatic com/common/android/utils/concurrent/NdTinyHttpAsyncTask$Status/RUNNING Lcom/common/android/utils/concurrent/NdTinyHttpAsyncTask$Status;
if_acmpne L0
aload 0
getfield com/nd/schoollife/ui/team/activity/TeamHomeActivity/mCtx Landroid/content/Context;
aload 0
getfield com/nd/schoollife/ui/team/activity/TeamHomeActivity/mCtx Landroid/content/Context;
getstatic com/nd/schoollife/R$string/str_common_loading I
invokevirtual android/content/Context/getString(I)Ljava/lang/String;
invokestatic com/nd/schoollife/common/utils/ui/ToastUtil/showLongToast(Landroid/content/Context;Ljava/lang/String;)V
iconst_0
ireturn
L0:
aload 0
getfield com/nd/schoollife/ui/team/activity/TeamHomeActivity/mListView Lcom/nd/schoollife/ui/common/view/widget/CustomPullToRefreshListView;
aload 0
getfield com/nd/schoollife/ui/team/activity/TeamHomeActivity/isInit Z
invokevirtual com/nd/schoollife/ui/common/view/widget/CustomPullToRefreshListView/callPullDownToRefresh(Z)V
aload 0
getfield com/nd/schoollife/ui/team/activity/TeamHomeActivity/isInit Z
ifeq L1
aload 0
iconst_0
putfield com/nd/schoollife/ui/team/activity/TeamHomeActivity/isInit Z
L1:
iconst_1
ireturn
.limit locals 2
.limit stack 3
.end method

.method public onReloadClicked()V
aload 0
invokespecial com/nd/schoollife/ui/team/activity/TeamHomeActivity/startGetTeamInfoTask()V
return
.limit locals 1
.limit stack 1
.end method

.method protected onResume()V
aload 0
invokespecial com/nd/schoollife/ui/common/activity/BaseSchoollifeActivity/onResume()V
aload 0
getfield com/nd/schoollife/ui/team/activity/TeamHomeActivity/isInit Z
ifne L0
aload 0
getstatic com/nd/schoollife/ui/common/task/CallStyle/CALL_STYLE_REFLASH Lcom/nd/schoollife/ui/common/task/CallStyle;
invokespecial com/nd/schoollife/ui/team/activity/TeamHomeActivity/loadPostData(Lcom/nd/schoollife/ui/common/task/CallStyle;)V
L0:
return
.limit locals 1
.limit stack 2
.end method

.method protected onSaveInstanceState(Landroid/os/Bundle;)V
aload 0
aload 1
invokespecial com/nd/schoollife/ui/common/activity/BaseSchoollifeActivity/onSaveInstanceState(Landroid/os/Bundle;)V
aload 1
ldc "KEY_SAVE_TEAM_ID"
aload 0
getfield com/nd/schoollife/ui/team/activity/TeamHomeActivity/mTeamId J
invokevirtual android/os/Bundle/putLong(Ljava/lang/String;J)V
return
.limit locals 2
.limit stack 4
.end method

.method public processOnPostExecute(ILcom/nd/schoollife/ui/common/task/CallStyle;Ljava/lang/Object;)V
iload 1
bipush 14
if_icmpne L0
aload 3
ifnull L0
aload 3
instanceof com/nd/android/forumsdk/business/bean/ForumResultBase
ifeq L0
aload 0
aload 3
checkcast com/nd/android/forumsdk/business/bean/result/ResultPostList
putfield com/nd/schoollife/ui/team/activity/TeamHomeActivity/mPostsList Lcom/nd/android/forumsdk/business/bean/result/ResultPostList;
aload 0
getfield com/nd/schoollife/ui/team/activity/TeamHomeActivity/mPostsList Lcom/nd/android/forumsdk/business/bean/result/ResultPostList;
invokevirtual com/nd/android/forumsdk/business/bean/result/ResultPostList/isSuccess()Z
ifeq L1
aload 0
getfield com/nd/schoollife/ui/team/activity/TeamHomeActivity/mPostsList Lcom/nd/android/forumsdk/business/bean/result/ResultPostList;
invokevirtual com/nd/android/forumsdk/business/bean/result/ResultPostList/getData()Ljava/util/List;
ifnull L1
aload 0
getfield com/nd/schoollife/ui/team/activity/TeamHomeActivity/mPostListAdapter Lcom/nd/schoollife/ui/post/adapter/PostListAdapter;
aload 0
getfield com/nd/schoollife/ui/team/activity/TeamHomeActivity/mPostsList Lcom/nd/android/forumsdk/business/bean/result/ResultPostList;
invokevirtual com/nd/android/forumsdk/business/bean/result/ResultPostList/getData()Ljava/util/List;
aload 0
getfield com/nd/schoollife/ui/team/activity/TeamHomeActivity/mPostsList Lcom/nd/android/forumsdk/business/bean/result/ResultPostList;
invokevirtual com/nd/android/forumsdk/business/bean/result/ResultPostList/getMax_ts()J
aload 0
getfield com/nd/schoollife/ui/team/activity/TeamHomeActivity/mPostsList Lcom/nd/android/forumsdk/business/bean/result/ResultPostList;
invokevirtual com/nd/android/forumsdk/business/bean/result/ResultPostList/getMin_ts()J
iconst_1
invokevirtual com/nd/schoollife/ui/post/adapter/PostListAdapter/updateData(Ljava/util/List;JJZ)V
aload 0
aload 0
getfield com/nd/schoollife/ui/team/activity/TeamHomeActivity/mPostListAdapter Lcom/nd/schoollife/ui/post/adapter/PostListAdapter;
invokevirtual com/nd/schoollife/ui/post/adapter/PostListAdapter/getList()Ljava/util/List;
putfield com/nd/schoollife/ui/team/activity/TeamHomeActivity/mPostInfoBeans Ljava/util/List;
L2:
aload 2
getstatic com/nd/schoollife/ui/common/task/CallStyle/CALL_STYLE_REFLASH Lcom/nd/schoollife/ui/common/task/CallStyle;
if_acmpeq L3
aload 2
getstatic com/nd/schoollife/ui/common/task/CallStyle/CALL_STYLE_INIT Lcom/nd/schoollife/ui/common/task/CallStyle;
if_acmpne L4
L3:
aload 0
iconst_0
putfield com/nd/schoollife/ui/team/activity/TeamHomeActivity/isInit Z
aload 0
getfield com/nd/schoollife/ui/team/activity/TeamHomeActivity/mListView Lcom/nd/schoollife/ui/common/view/widget/CustomPullToRefreshListView;
invokevirtual com/nd/schoollife/ui/common/view/widget/CustomPullToRefreshListView/onRefreshComplete()V
L5:
aload 0
getfield com/nd/schoollife/ui/team/activity/TeamHomeActivity/mRefreshBtn Lcom/nd/schoollife/ui/common/view/RefreshBtn;
ifnull L6
aload 0
getfield com/nd/schoollife/ui/team/activity/TeamHomeActivity/mRefreshBtn Lcom/nd/schoollife/ui/common/view/RefreshBtn;
invokevirtual com/nd/schoollife/ui/common/view/RefreshBtn/isRoting()Z
ifeq L6
aload 0
getfield com/nd/schoollife/ui/team/activity/TeamHomeActivity/mRefreshBtn Lcom/nd/schoollife/ui/common/view/RefreshBtn;
invokevirtual com/nd/schoollife/ui/common/view/RefreshBtn/stopRoting()V
L6:
aload 0
invokespecial com/nd/schoollife/ui/team/activity/TeamHomeActivity/showPostView()V
aload 0
invokevirtual com/nd/schoollife/ui/team/activity/TeamHomeActivity/dismissLoading()V
L7:
return
L1:
aload 0
getfield com/nd/schoollife/ui/team/activity/TeamHomeActivity/mPostsList Lcom/nd/android/forumsdk/business/bean/result/ResultPostList;
invokevirtual com/nd/android/forumsdk/business/bean/result/ResultPostList/getErrorBean()Lcom/nd/android/forumsdk/business/bean/ForumErrorBean;
ifnull L2
aload 0
getfield com/nd/schoollife/ui/team/activity/TeamHomeActivity/mCtx Landroid/content/Context;
new java/lang/StringBuilder
dup
invokespecial java/lang/StringBuilder/<init>()V
ldc ""
invokevirtual java/lang/StringBuilder/append(Ljava/lang/String;)Ljava/lang/StringBuilder;
aload 0
getfield com/nd/schoollife/ui/team/activity/TeamHomeActivity/mPostsList Lcom/nd/android/forumsdk/business/bean/result/ResultPostList;
invokevirtual com/nd/android/forumsdk/business/bean/result/ResultPostList/getErrorBean()Lcom/nd/android/forumsdk/business/bean/ForumErrorBean;
invokevirtual com/nd/android/forumsdk/business/bean/ForumErrorBean/getMsg()Ljava/lang/String;
invokevirtual java/lang/StringBuilder/append(Ljava/lang/String;)Ljava/lang/StringBuilder;
invokevirtual java/lang/StringBuilder/toString()Ljava/lang/String;
invokestatic com/nd/schoollife/common/utils/ui/ToastUtil/showLongToast(Landroid/content/Context;Ljava/lang/String;)V
goto L2
L4:
aload 0
getfield com/nd/schoollife/ui/team/activity/TeamHomeActivity/mListView Lcom/nd/schoollife/ui/common/view/widget/CustomPullToRefreshListView;
invokevirtual com/nd/schoollife/ui/common/view/widget/CustomPullToRefreshListView/onLoadMoreComplate()V
goto L5
L0:
iload 1
sipush 4097
if_icmpne L8
aload 3
instanceof com/nd/android/forumsdk/business/bean/ForumResultBase
ifeq L8
aload 3
checkcast com/nd/android/forumsdk/business/bean/result/ResultGetTeamInfo
astore 3
aload 3
invokevirtual com/nd/android/forumsdk/business/bean/result/ResultGetTeamInfo/getResultCode()I
sipush 200
if_icmpne L9
aload 2
getstatic com/nd/schoollife/ui/common/task/CallStyle/CALL_STYLE_INIT Lcom/nd/schoollife/ui/common/task/CallStyle;
if_acmpne L7
aload 0
aload 0
aload 3
invokespecial com/nd/schoollife/ui/team/activity/TeamHomeActivity/fromResultToBean(Lcom/nd/android/forumsdk/business/bean/result/ResultGetTeamInfo;)Lcom/nd/android/forumsdk/business/bean/structure/TeamInfoBean;
invokespecial com/nd/schoollife/ui/team/activity/TeamHomeActivity/fillTeamInfoValue(Lcom/nd/android/forumsdk/business/bean/structure/TeamInfoBean;)V
aload 0
getstatic com/nd/schoollife/ui/common/task/CallStyle/CALL_STYLE_INIT Lcom/nd/schoollife/ui/common/task/CallStyle;
invokespecial com/nd/schoollife/ui/team/activity/TeamHomeActivity/loadPostData(Lcom/nd/schoollife/ui/common/task/CallStyle;)V
aload 0
invokespecial com/nd/schoollife/ui/team/activity/TeamHomeActivity/loadHeaderViewByStatus()V
return
L9:
aload 0
getfield com/nd/schoollife/ui/team/activity/TeamHomeActivity/mCtx Landroid/content/Context;
aload 3
invokevirtual com/nd/android/forumsdk/business/bean/result/ResultGetTeamInfo/getResultMsg()Ljava/lang/String;
invokestatic com/nd/schoollife/common/utils/ui/ToastUtil/showShortToast(Landroid/content/Context;Ljava/lang/String;)V
return
L8:
iload 1
sipush 4104
if_icmpne L10
aload 3
instanceof com/nd/android/forumsdk/business/bean/ForumResultBase
ifeq L10
aload 3
checkcast com/nd/android/forumsdk/business/bean/ForumResultBase
astore 3
aload 3
invokevirtual com/nd/android/forumsdk/business/bean/ForumResultBase/getResultCode()I
sipush 200
if_icmpne L11
aload 0
getfield com/nd/schoollife/ui/team/activity/TeamHomeActivity/mCtx Landroid/content/Context;
invokestatic com/nd/schoollife/common/utils/common/AppSp/getInstatce(Landroid/content/Context;)Lcom/nd/schoollife/common/utils/common/AppSp;
ldc "FLAG_GET_MYRSS_INT"
iconst_1
invokevirtual com/nd/schoollife/common/utils/common/AppSp/setValue(Ljava/lang/String;Z)V
new com/nd/schoollife/ui/square/task/SquareDataTask
dup
aload 0
sipush 1543
getstatic com/nd/schoollife/ui/common/task/CallStyle/CALL_STYLE_NONE Lcom/nd/schoollife/ui/common/task/CallStyle;
aload 0
invokespecial com/nd/schoollife/ui/square/task/SquareDataTask/<init>(Landroid/content/Context;ILcom/nd/schoollife/ui/common/task/CallStyle;Lcom/nd/schoollife/ui/common/base/interfaces/AsyncTaskCallback;)V
iconst_2
anewarray java/lang/String
dup
iconst_0
ldc "8"
aastore
dup
iconst_1
new java/lang/StringBuilder
dup
invokespecial java/lang/StringBuilder/<init>()V
aload 0
getfield com/nd/schoollife/ui/team/activity/TeamHomeActivity/mTeamId J
invokevirtual java/lang/StringBuilder/append(J)Ljava/lang/StringBuilder;
ldc ""
invokevirtual java/lang/StringBuilder/append(Ljava/lang/String;)Ljava/lang/StringBuilder;
invokevirtual java/lang/StringBuilder/toString()Ljava/lang/String;
aastore
invokevirtual com/nd/schoollife/ui/square/task/SquareDataTask/execute([Ljava/lang/Object;)Lcom/common/android/utils/concurrent/NdTinyHttpAsyncTask;
pop
aload 2
getstatic com/nd/schoollife/ui/common/task/CallStyle/CALL_STYLE_SUBMIT Lcom/nd/schoollife/ui/common/task/CallStyle;
if_acmpne L7
aload 0
getfield com/nd/schoollife/ui/team/activity/TeamHomeActivity/mGrade I
ifne L12
aload 0
iconst_1
putfield com/nd/schoollife/ui/team/activity/TeamHomeActivity/mGrade I
aload 0
aload 0
getfield com/nd/schoollife/ui/team/activity/TeamHomeActivity/mCtx Landroid/content/Context;
getstatic com/nd/schoollife/R$string/str_do_focusteam_success I
invokevirtual android/content/Context/getString(I)Ljava/lang/String;
invokestatic com/nd/schoollife/common/utils/ui/ToastUtil/showShortToast(Landroid/content/Context;Ljava/lang/String;)V
L13:
aload 0
invokespecial com/nd/schoollife/ui/team/activity/TeamHomeActivity/loadHeaderViewByStatus()V
return
L12:
aload 0
iconst_0
putfield com/nd/schoollife/ui/team/activity/TeamHomeActivity/mGrade I
aload 0
getfield com/nd/schoollife/ui/team/activity/TeamHomeActivity/mSlideHolder Lcom/nd/schoollife/ui/team/view/SlideHolder;
invokevirtual com/nd/schoollife/ui/team/view/SlideHolder/isOpened()Z
ifeq L13
aload 0
getfield com/nd/schoollife/ui/team/activity/TeamHomeActivity/mSlideHolder Lcom/nd/schoollife/ui/team/view/SlideHolder;
invokevirtual com/nd/schoollife/ui/team/view/SlideHolder/toggle()V
goto L13
L11:
aload 0
getfield com/nd/schoollife/ui/team/activity/TeamHomeActivity/mCtx Landroid/content/Context;
aload 3
invokevirtual com/nd/android/forumsdk/business/bean/ForumResultBase/getResultMsg()Ljava/lang/String;
invokestatic com/nd/schoollife/common/utils/ui/ToastUtil/showShortToast(Landroid/content/Context;Ljava/lang/String;)V
return
L10:
iload 1
bipush 12
if_icmpne L7
aload 3
instanceof com/nd/schoollife/common/bean/result/CommentInfoBean
ifeq L7
aload 3
checkcast com/nd/schoollife/common/bean/result/CommentInfoBean
astore 2
aload 2
invokevirtual com/nd/schoollife/common/bean/result/CommentInfoBean/isSuccess()Z
ifeq L14
aload 0
getfield com/nd/schoollife/ui/team/activity/TeamHomeActivity/mCtx Landroid/content/Context;
aload 0
getfield com/nd/schoollife/ui/team/activity/TeamHomeActivity/mCtx Landroid/content/Context;
getstatic com/nd/schoollife/R$string/str_do_comment_success I
invokevirtual android/content/Context/getString(I)Ljava/lang/String;
invokestatic com/nd/schoollife/common/utils/ui/ToastUtil/showShortCustomToast(Landroid/content/Context;Ljava/lang/String;)V
aload 0
getfield com/nd/schoollife/ui/team/activity/TeamHomeActivity/mInputContentManager Lcom/nd/schoollife/ui/common/process/InputContentViewManager;
ifnull L15
aload 0
getfield com/nd/schoollife/ui/team/activity/TeamHomeActivity/mInputContentManager Lcom/nd/schoollife/ui/common/process/InputContentViewManager;
aload 2
invokevirtual com/nd/schoollife/ui/common/process/InputContentViewManager/updateOperatorPanelCommentCount(Lcom/nd/schoollife/common/bean/result/CommentInfoBean;)V
L15:
aload 0
getfield com/nd/schoollife/ui/team/activity/TeamHomeActivity/mInputContentManager Lcom/nd/schoollife/ui/common/process/InputContentViewManager;
ifnull L7
aload 0
getfield com/nd/schoollife/ui/team/activity/TeamHomeActivity/mInputContentManager Lcom/nd/schoollife/ui/common/process/InputContentViewManager;
aload 2
invokevirtual com/nd/schoollife/common/bean/result/CommentInfoBean/isSuccess()Z
invokevirtual com/nd/schoollife/ui/common/process/InputContentViewManager/onSendResult(Z)V
return
L14:
aload 2
invokevirtual com/nd/schoollife/common/bean/result/CommentInfoBean/isBusinessError()Z
ifeq L15
aload 2
invokevirtual com/nd/schoollife/common/bean/result/CommentInfoBean/getErrorBean()Lcom/nd/android/forumsdk/business/bean/ForumErrorBean;
ifnull L15
aload 0
getfield com/nd/schoollife/ui/team/activity/TeamHomeActivity/mCtx Landroid/content/Context;
aload 0
getfield com/nd/schoollife/ui/team/activity/TeamHomeActivity/mCtx Landroid/content/Context;
getstatic com/nd/schoollife/R$string/str_do_comment_fail I
invokevirtual android/content/Context/getString(I)Ljava/lang/String;
invokestatic com/nd/schoollife/common/utils/ui/ToastUtil/showShortToast(Landroid/content/Context;Ljava/lang/String;)V
getstatic com/nd/schoollife/ui/team/activity/TeamHomeActivity/TAG Ljava/lang/String;
new java/lang/StringBuilder
dup
invokespecial java/lang/StringBuilder/<init>()V
ldc "error\uff1a"
invokevirtual java/lang/StringBuilder/append(Ljava/lang/String;)Ljava/lang/StringBuilder;
aload 2
invokevirtual com/nd/schoollife/common/bean/result/CommentInfoBean/getErrorBean()Lcom/nd/android/forumsdk/business/bean/ForumErrorBean;
invokevirtual com/nd/android/forumsdk/business/bean/ForumErrorBean/getMsg()Ljava/lang/String;
invokevirtual java/lang/StringBuilder/append(Ljava/lang/String;)Ljava/lang/StringBuilder;
invokevirtual java/lang/StringBuilder/toString()Ljava/lang/String;
invokestatic com/nd/schoollife/common/utils/ui/LogUtil/e(Ljava/lang/String;Ljava/lang/String;)V
goto L15
.limit locals 4
.limit stack 7
.end method
