.bytecode 50.0
.class public final synchronized com/google/gson/internal/bind/TypeAdapters
.super java/lang/Object
.inner class static final inner com/google/gson/internal/bind/TypeAdapters$1
.inner class static final inner com/google/gson/internal/bind/TypeAdapters$10
.inner class static final inner com/google/gson/internal/bind/TypeAdapters$11
.inner class static final inner com/google/gson/internal/bind/TypeAdapters$12
.inner class static final inner com/google/gson/internal/bind/TypeAdapters$13
.inner class static final inner com/google/gson/internal/bind/TypeAdapters$14
.inner class static final inner com/google/gson/internal/bind/TypeAdapters$15
.inner class static final inner com/google/gson/internal/bind/TypeAdapters$16
.inner class static final inner com/google/gson/internal/bind/TypeAdapters$17
.inner class static final inner com/google/gson/internal/bind/TypeAdapters$18
.inner class static final inner com/google/gson/internal/bind/TypeAdapters$19
.inner class static final inner com/google/gson/internal/bind/TypeAdapters$2
.inner class static final inner com/google/gson/internal/bind/TypeAdapters$20
.inner class static final inner com/google/gson/internal/bind/TypeAdapters$21
.inner class static final inner com/google/gson/internal/bind/TypeAdapters$22
.inner class inner com/google/gson/internal/bind/TypeAdapters$22$1
.inner class static final inner com/google/gson/internal/bind/TypeAdapters$23
.inner class static final inner com/google/gson/internal/bind/TypeAdapters$24
.inner class static final inner com/google/gson/internal/bind/TypeAdapters$25
.inner class static final inner com/google/gson/internal/bind/TypeAdapters$26
.inner class static final inner com/google/gson/internal/bind/TypeAdapters$27
.inner class static final inner com/google/gson/internal/bind/TypeAdapters$28
.inner class static final inner com/google/gson/internal/bind/TypeAdapters$29
.inner class static final inner com/google/gson/internal/bind/TypeAdapters$3
.inner class static final inner com/google/gson/internal/bind/TypeAdapters$30
.inner class static final inner com/google/gson/internal/bind/TypeAdapters$31
.inner class static synthetic inner com/google/gson/internal/bind/TypeAdapters$32
.inner class static final inner com/google/gson/internal/bind/TypeAdapters$4
.inner class static final inner com/google/gson/internal/bind/TypeAdapters$5
.inner class static final inner com/google/gson/internal/bind/TypeAdapters$6
.inner class static final inner com/google/gson/internal/bind/TypeAdapters$7
.inner class static final inner com/google/gson/internal/bind/TypeAdapters$8
.inner class static final inner com/google/gson/internal/bind/TypeAdapters$9
.inner class private static final EnumTypeAdapter inner com/google/gson/internal/bind/TypeAdapters$EnumTypeAdapter outer com/google/gson/internal/bind/TypeAdapters

.field public static final 'BIG_DECIMAL' Lcom/google/gson/TypeAdapter; signature "Lcom/google/gson/TypeAdapter<Ljava/math/BigDecimal;>;"

.field public static final 'BIG_INTEGER' Lcom/google/gson/TypeAdapter; signature "Lcom/google/gson/TypeAdapter<Ljava/math/BigInteger;>;"

.field public static final 'BIT_SET' Lcom/google/gson/TypeAdapter; signature "Lcom/google/gson/TypeAdapter<Ljava/util/BitSet;>;"

.field public static final 'BIT_SET_FACTORY' Lcom/google/gson/TypeAdapterFactory;

.field public static final 'BOOLEAN' Lcom/google/gson/TypeAdapter; signature "Lcom/google/gson/TypeAdapter<Ljava/lang/Boolean;>;"

.field public static final 'BOOLEAN_AS_STRING' Lcom/google/gson/TypeAdapter; signature "Lcom/google/gson/TypeAdapter<Ljava/lang/Boolean;>;"

.field public static final 'BOOLEAN_FACTORY' Lcom/google/gson/TypeAdapterFactory;

.field public static final 'BYTE' Lcom/google/gson/TypeAdapter; signature "Lcom/google/gson/TypeAdapter<Ljava/lang/Number;>;"

.field public static final 'BYTE_FACTORY' Lcom/google/gson/TypeAdapterFactory;

.field public static final 'CALENDAR' Lcom/google/gson/TypeAdapter; signature "Lcom/google/gson/TypeAdapter<Ljava/util/Calendar;>;"

.field public static final 'CALENDAR_FACTORY' Lcom/google/gson/TypeAdapterFactory;

.field public static final 'CHARACTER' Lcom/google/gson/TypeAdapter; signature "Lcom/google/gson/TypeAdapter<Ljava/lang/Character;>;"

.field public static final 'CHARACTER_FACTORY' Lcom/google/gson/TypeAdapterFactory;

.field public static final 'CLASS' Lcom/google/gson/TypeAdapter; signature "Lcom/google/gson/TypeAdapter<Ljava/lang/Class;>;"

.field public static final 'CLASS_FACTORY' Lcom/google/gson/TypeAdapterFactory;

.field public static final 'DOUBLE' Lcom/google/gson/TypeAdapter; signature "Lcom/google/gson/TypeAdapter<Ljava/lang/Number;>;"

.field public static final 'ENUM_FACTORY' Lcom/google/gson/TypeAdapterFactory;

.field public static final 'FLOAT' Lcom/google/gson/TypeAdapter; signature "Lcom/google/gson/TypeAdapter<Ljava/lang/Number;>;"

.field public static final 'INET_ADDRESS' Lcom/google/gson/TypeAdapter; signature "Lcom/google/gson/TypeAdapter<Ljava/net/InetAddress;>;"

.field public static final 'INET_ADDRESS_FACTORY' Lcom/google/gson/TypeAdapterFactory;

.field public static final 'INTEGER' Lcom/google/gson/TypeAdapter; signature "Lcom/google/gson/TypeAdapter<Ljava/lang/Number;>;"

.field public static final 'INTEGER_FACTORY' Lcom/google/gson/TypeAdapterFactory;

.field public static final 'JSON_ELEMENT' Lcom/google/gson/TypeAdapter; signature "Lcom/google/gson/TypeAdapter<Lcom/google/gson/JsonElement;>;"

.field public static final 'JSON_ELEMENT_FACTORY' Lcom/google/gson/TypeAdapterFactory;

.field public static final 'LOCALE' Lcom/google/gson/TypeAdapter; signature "Lcom/google/gson/TypeAdapter<Ljava/util/Locale;>;"

.field public static final 'LOCALE_FACTORY' Lcom/google/gson/TypeAdapterFactory;

.field public static final 'LONG' Lcom/google/gson/TypeAdapter; signature "Lcom/google/gson/TypeAdapter<Ljava/lang/Number;>;"

.field public static final 'NUMBER' Lcom/google/gson/TypeAdapter; signature "Lcom/google/gson/TypeAdapter<Ljava/lang/Number;>;"

.field public static final 'NUMBER_FACTORY' Lcom/google/gson/TypeAdapterFactory;

.field public static final 'SHORT' Lcom/google/gson/TypeAdapter; signature "Lcom/google/gson/TypeAdapter<Ljava/lang/Number;>;"

.field public static final 'SHORT_FACTORY' Lcom/google/gson/TypeAdapterFactory;

.field public static final 'STRING' Lcom/google/gson/TypeAdapter; signature "Lcom/google/gson/TypeAdapter<Ljava/lang/String;>;"

.field public static final 'STRING_BUFFER' Lcom/google/gson/TypeAdapter; signature "Lcom/google/gson/TypeAdapter<Ljava/lang/StringBuffer;>;"

.field public static final 'STRING_BUFFER_FACTORY' Lcom/google/gson/TypeAdapterFactory;

.field public static final 'STRING_BUILDER' Lcom/google/gson/TypeAdapter; signature "Lcom/google/gson/TypeAdapter<Ljava/lang/StringBuilder;>;"

.field public static final 'STRING_BUILDER_FACTORY' Lcom/google/gson/TypeAdapterFactory;

.field public static final 'STRING_FACTORY' Lcom/google/gson/TypeAdapterFactory;

.field public static final 'TIMESTAMP_FACTORY' Lcom/google/gson/TypeAdapterFactory;

.field public static final 'URI' Lcom/google/gson/TypeAdapter; signature "Lcom/google/gson/TypeAdapter<Ljava/net/URI;>;"

.field public static final 'URI_FACTORY' Lcom/google/gson/TypeAdapterFactory;

.field public static final 'URL' Lcom/google/gson/TypeAdapter; signature "Lcom/google/gson/TypeAdapter<Ljava/net/URL;>;"

.field public static final 'URL_FACTORY' Lcom/google/gson/TypeAdapterFactory;

.field public static final 'UUID' Lcom/google/gson/TypeAdapter; signature "Lcom/google/gson/TypeAdapter<Ljava/util/UUID;>;"

.field public static final 'UUID_FACTORY' Lcom/google/gson/TypeAdapterFactory;

.method static <clinit>()V
new com/google/gson/internal/bind/TypeAdapters$1
dup
invokespecial com/google/gson/internal/bind/TypeAdapters$1/<init>()V
putstatic com/google/gson/internal/bind/TypeAdapters/CLASS Lcom/google/gson/TypeAdapter;
ldc java/lang/Class
getstatic com/google/gson/internal/bind/TypeAdapters/CLASS Lcom/google/gson/TypeAdapter;
invokestatic com/google/gson/internal/bind/TypeAdapters/newFactory(Ljava/lang/Class;Lcom/google/gson/TypeAdapter;)Lcom/google/gson/TypeAdapterFactory;
putstatic com/google/gson/internal/bind/TypeAdapters/CLASS_FACTORY Lcom/google/gson/TypeAdapterFactory;
new com/google/gson/internal/bind/TypeAdapters$2
dup
invokespecial com/google/gson/internal/bind/TypeAdapters$2/<init>()V
putstatic com/google/gson/internal/bind/TypeAdapters/BIT_SET Lcom/google/gson/TypeAdapter;
ldc java/util/BitSet
getstatic com/google/gson/internal/bind/TypeAdapters/BIT_SET Lcom/google/gson/TypeAdapter;
invokestatic com/google/gson/internal/bind/TypeAdapters/newFactory(Ljava/lang/Class;Lcom/google/gson/TypeAdapter;)Lcom/google/gson/TypeAdapterFactory;
putstatic com/google/gson/internal/bind/TypeAdapters/BIT_SET_FACTORY Lcom/google/gson/TypeAdapterFactory;
new com/google/gson/internal/bind/TypeAdapters$3
dup
invokespecial com/google/gson/internal/bind/TypeAdapters$3/<init>()V
putstatic com/google/gson/internal/bind/TypeAdapters/BOOLEAN Lcom/google/gson/TypeAdapter;
new com/google/gson/internal/bind/TypeAdapters$4
dup
invokespecial com/google/gson/internal/bind/TypeAdapters$4/<init>()V
putstatic com/google/gson/internal/bind/TypeAdapters/BOOLEAN_AS_STRING Lcom/google/gson/TypeAdapter;
getstatic java/lang/Boolean/TYPE Ljava/lang/Class;
ldc java/lang/Boolean
getstatic com/google/gson/internal/bind/TypeAdapters/BOOLEAN Lcom/google/gson/TypeAdapter;
invokestatic com/google/gson/internal/bind/TypeAdapters/newFactory(Ljava/lang/Class;Ljava/lang/Class;Lcom/google/gson/TypeAdapter;)Lcom/google/gson/TypeAdapterFactory;
putstatic com/google/gson/internal/bind/TypeAdapters/BOOLEAN_FACTORY Lcom/google/gson/TypeAdapterFactory;
new com/google/gson/internal/bind/TypeAdapters$5
dup
invokespecial com/google/gson/internal/bind/TypeAdapters$5/<init>()V
putstatic com/google/gson/internal/bind/TypeAdapters/BYTE Lcom/google/gson/TypeAdapter;
getstatic java/lang/Byte/TYPE Ljava/lang/Class;
ldc java/lang/Byte
getstatic com/google/gson/internal/bind/TypeAdapters/BYTE Lcom/google/gson/TypeAdapter;
invokestatic com/google/gson/internal/bind/TypeAdapters/newFactory(Ljava/lang/Class;Ljava/lang/Class;Lcom/google/gson/TypeAdapter;)Lcom/google/gson/TypeAdapterFactory;
putstatic com/google/gson/internal/bind/TypeAdapters/BYTE_FACTORY Lcom/google/gson/TypeAdapterFactory;
new com/google/gson/internal/bind/TypeAdapters$6
dup
invokespecial com/google/gson/internal/bind/TypeAdapters$6/<init>()V
putstatic com/google/gson/internal/bind/TypeAdapters/SHORT Lcom/google/gson/TypeAdapter;
getstatic java/lang/Short/TYPE Ljava/lang/Class;
ldc java/lang/Short
getstatic com/google/gson/internal/bind/TypeAdapters/SHORT Lcom/google/gson/TypeAdapter;
invokestatic com/google/gson/internal/bind/TypeAdapters/newFactory(Ljava/lang/Class;Ljava/lang/Class;Lcom/google/gson/TypeAdapter;)Lcom/google/gson/TypeAdapterFactory;
putstatic com/google/gson/internal/bind/TypeAdapters/SHORT_FACTORY Lcom/google/gson/TypeAdapterFactory;
new com/google/gson/internal/bind/TypeAdapters$7
dup
invokespecial com/google/gson/internal/bind/TypeAdapters$7/<init>()V
putstatic com/google/gson/internal/bind/TypeAdapters/INTEGER Lcom/google/gson/TypeAdapter;
getstatic java/lang/Integer/TYPE Ljava/lang/Class;
ldc java/lang/Integer
getstatic com/google/gson/internal/bind/TypeAdapters/INTEGER Lcom/google/gson/TypeAdapter;
invokestatic com/google/gson/internal/bind/TypeAdapters/newFactory(Ljava/lang/Class;Ljava/lang/Class;Lcom/google/gson/TypeAdapter;)Lcom/google/gson/TypeAdapterFactory;
putstatic com/google/gson/internal/bind/TypeAdapters/INTEGER_FACTORY Lcom/google/gson/TypeAdapterFactory;
new com/google/gson/internal/bind/TypeAdapters$8
dup
invokespecial com/google/gson/internal/bind/TypeAdapters$8/<init>()V
putstatic com/google/gson/internal/bind/TypeAdapters/LONG Lcom/google/gson/TypeAdapter;
new com/google/gson/internal/bind/TypeAdapters$9
dup
invokespecial com/google/gson/internal/bind/TypeAdapters$9/<init>()V
putstatic com/google/gson/internal/bind/TypeAdapters/FLOAT Lcom/google/gson/TypeAdapter;
new com/google/gson/internal/bind/TypeAdapters$10
dup
invokespecial com/google/gson/internal/bind/TypeAdapters$10/<init>()V
putstatic com/google/gson/internal/bind/TypeAdapters/DOUBLE Lcom/google/gson/TypeAdapter;
new com/google/gson/internal/bind/TypeAdapters$11
dup
invokespecial com/google/gson/internal/bind/TypeAdapters$11/<init>()V
putstatic com/google/gson/internal/bind/TypeAdapters/NUMBER Lcom/google/gson/TypeAdapter;
ldc java/lang/Number
getstatic com/google/gson/internal/bind/TypeAdapters/NUMBER Lcom/google/gson/TypeAdapter;
invokestatic com/google/gson/internal/bind/TypeAdapters/newFactory(Ljava/lang/Class;Lcom/google/gson/TypeAdapter;)Lcom/google/gson/TypeAdapterFactory;
putstatic com/google/gson/internal/bind/TypeAdapters/NUMBER_FACTORY Lcom/google/gson/TypeAdapterFactory;
new com/google/gson/internal/bind/TypeAdapters$12
dup
invokespecial com/google/gson/internal/bind/TypeAdapters$12/<init>()V
putstatic com/google/gson/internal/bind/TypeAdapters/CHARACTER Lcom/google/gson/TypeAdapter;
getstatic java/lang/Character/TYPE Ljava/lang/Class;
ldc java/lang/Character
getstatic com/google/gson/internal/bind/TypeAdapters/CHARACTER Lcom/google/gson/TypeAdapter;
invokestatic com/google/gson/internal/bind/TypeAdapters/newFactory(Ljava/lang/Class;Ljava/lang/Class;Lcom/google/gson/TypeAdapter;)Lcom/google/gson/TypeAdapterFactory;
putstatic com/google/gson/internal/bind/TypeAdapters/CHARACTER_FACTORY Lcom/google/gson/TypeAdapterFactory;
new com/google/gson/internal/bind/TypeAdapters$13
dup
invokespecial com/google/gson/internal/bind/TypeAdapters$13/<init>()V
putstatic com/google/gson/internal/bind/TypeAdapters/STRING Lcom/google/gson/TypeAdapter;
new com/google/gson/internal/bind/TypeAdapters$14
dup
invokespecial com/google/gson/internal/bind/TypeAdapters$14/<init>()V
putstatic com/google/gson/internal/bind/TypeAdapters/BIG_DECIMAL Lcom/google/gson/TypeAdapter;
new com/google/gson/internal/bind/TypeAdapters$15
dup
invokespecial com/google/gson/internal/bind/TypeAdapters$15/<init>()V
putstatic com/google/gson/internal/bind/TypeAdapters/BIG_INTEGER Lcom/google/gson/TypeAdapter;
ldc java/lang/String
getstatic com/google/gson/internal/bind/TypeAdapters/STRING Lcom/google/gson/TypeAdapter;
invokestatic com/google/gson/internal/bind/TypeAdapters/newFactory(Ljava/lang/Class;Lcom/google/gson/TypeAdapter;)Lcom/google/gson/TypeAdapterFactory;
putstatic com/google/gson/internal/bind/TypeAdapters/STRING_FACTORY Lcom/google/gson/TypeAdapterFactory;
new com/google/gson/internal/bind/TypeAdapters$16
dup
invokespecial com/google/gson/internal/bind/TypeAdapters$16/<init>()V
putstatic com/google/gson/internal/bind/TypeAdapters/STRING_BUILDER Lcom/google/gson/TypeAdapter;
ldc java/lang/StringBuilder
getstatic com/google/gson/internal/bind/TypeAdapters/STRING_BUILDER Lcom/google/gson/TypeAdapter;
invokestatic com/google/gson/internal/bind/TypeAdapters/newFactory(Ljava/lang/Class;Lcom/google/gson/TypeAdapter;)Lcom/google/gson/TypeAdapterFactory;
putstatic com/google/gson/internal/bind/TypeAdapters/STRING_BUILDER_FACTORY Lcom/google/gson/TypeAdapterFactory;
new com/google/gson/internal/bind/TypeAdapters$17
dup
invokespecial com/google/gson/internal/bind/TypeAdapters$17/<init>()V
putstatic com/google/gson/internal/bind/TypeAdapters/STRING_BUFFER Lcom/google/gson/TypeAdapter;
ldc java/lang/StringBuffer
getstatic com/google/gson/internal/bind/TypeAdapters/STRING_BUFFER Lcom/google/gson/TypeAdapter;
invokestatic com/google/gson/internal/bind/TypeAdapters/newFactory(Ljava/lang/Class;Lcom/google/gson/TypeAdapter;)Lcom/google/gson/TypeAdapterFactory;
putstatic com/google/gson/internal/bind/TypeAdapters/STRING_BUFFER_FACTORY Lcom/google/gson/TypeAdapterFactory;
new com/google/gson/internal/bind/TypeAdapters$18
dup
invokespecial com/google/gson/internal/bind/TypeAdapters$18/<init>()V
putstatic com/google/gson/internal/bind/TypeAdapters/URL Lcom/google/gson/TypeAdapter;
ldc java/net/URL
getstatic com/google/gson/internal/bind/TypeAdapters/URL Lcom/google/gson/TypeAdapter;
invokestatic com/google/gson/internal/bind/TypeAdapters/newFactory(Ljava/lang/Class;Lcom/google/gson/TypeAdapter;)Lcom/google/gson/TypeAdapterFactory;
putstatic com/google/gson/internal/bind/TypeAdapters/URL_FACTORY Lcom/google/gson/TypeAdapterFactory;
new com/google/gson/internal/bind/TypeAdapters$19
dup
invokespecial com/google/gson/internal/bind/TypeAdapters$19/<init>()V
putstatic com/google/gson/internal/bind/TypeAdapters/URI Lcom/google/gson/TypeAdapter;
ldc java/net/URI
getstatic com/google/gson/internal/bind/TypeAdapters/URI Lcom/google/gson/TypeAdapter;
invokestatic com/google/gson/internal/bind/TypeAdapters/newFactory(Ljava/lang/Class;Lcom/google/gson/TypeAdapter;)Lcom/google/gson/TypeAdapterFactory;
putstatic com/google/gson/internal/bind/TypeAdapters/URI_FACTORY Lcom/google/gson/TypeAdapterFactory;
new com/google/gson/internal/bind/TypeAdapters$20
dup
invokespecial com/google/gson/internal/bind/TypeAdapters$20/<init>()V
putstatic com/google/gson/internal/bind/TypeAdapters/INET_ADDRESS Lcom/google/gson/TypeAdapter;
ldc java/net/InetAddress
getstatic com/google/gson/internal/bind/TypeAdapters/INET_ADDRESS Lcom/google/gson/TypeAdapter;
invokestatic com/google/gson/internal/bind/TypeAdapters/newTypeHierarchyFactory(Ljava/lang/Class;Lcom/google/gson/TypeAdapter;)Lcom/google/gson/TypeAdapterFactory;
putstatic com/google/gson/internal/bind/TypeAdapters/INET_ADDRESS_FACTORY Lcom/google/gson/TypeAdapterFactory;
new com/google/gson/internal/bind/TypeAdapters$21
dup
invokespecial com/google/gson/internal/bind/TypeAdapters$21/<init>()V
putstatic com/google/gson/internal/bind/TypeAdapters/UUID Lcom/google/gson/TypeAdapter;
ldc java/util/UUID
getstatic com/google/gson/internal/bind/TypeAdapters/UUID Lcom/google/gson/TypeAdapter;
invokestatic com/google/gson/internal/bind/TypeAdapters/newFactory(Ljava/lang/Class;Lcom/google/gson/TypeAdapter;)Lcom/google/gson/TypeAdapterFactory;
putstatic com/google/gson/internal/bind/TypeAdapters/UUID_FACTORY Lcom/google/gson/TypeAdapterFactory;
new com/google/gson/internal/bind/TypeAdapters$22
dup
invokespecial com/google/gson/internal/bind/TypeAdapters$22/<init>()V
putstatic com/google/gson/internal/bind/TypeAdapters/TIMESTAMP_FACTORY Lcom/google/gson/TypeAdapterFactory;
new com/google/gson/internal/bind/TypeAdapters$23
dup
invokespecial com/google/gson/internal/bind/TypeAdapters$23/<init>()V
putstatic com/google/gson/internal/bind/TypeAdapters/CALENDAR Lcom/google/gson/TypeAdapter;
ldc java/util/Calendar
ldc java/util/GregorianCalendar
getstatic com/google/gson/internal/bind/TypeAdapters/CALENDAR Lcom/google/gson/TypeAdapter;
invokestatic com/google/gson/internal/bind/TypeAdapters/newFactoryForMultipleTypes(Ljava/lang/Class;Ljava/lang/Class;Lcom/google/gson/TypeAdapter;)Lcom/google/gson/TypeAdapterFactory;
putstatic com/google/gson/internal/bind/TypeAdapters/CALENDAR_FACTORY Lcom/google/gson/TypeAdapterFactory;
new com/google/gson/internal/bind/TypeAdapters$24
dup
invokespecial com/google/gson/internal/bind/TypeAdapters$24/<init>()V
putstatic com/google/gson/internal/bind/TypeAdapters/LOCALE Lcom/google/gson/TypeAdapter;
ldc java/util/Locale
getstatic com/google/gson/internal/bind/TypeAdapters/LOCALE Lcom/google/gson/TypeAdapter;
invokestatic com/google/gson/internal/bind/TypeAdapters/newFactory(Ljava/lang/Class;Lcom/google/gson/TypeAdapter;)Lcom/google/gson/TypeAdapterFactory;
putstatic com/google/gson/internal/bind/TypeAdapters/LOCALE_FACTORY Lcom/google/gson/TypeAdapterFactory;
new com/google/gson/internal/bind/TypeAdapters$25
dup
invokespecial com/google/gson/internal/bind/TypeAdapters$25/<init>()V
putstatic com/google/gson/internal/bind/TypeAdapters/JSON_ELEMENT Lcom/google/gson/TypeAdapter;
ldc com/google/gson/JsonElement
getstatic com/google/gson/internal/bind/TypeAdapters/JSON_ELEMENT Lcom/google/gson/TypeAdapter;
invokestatic com/google/gson/internal/bind/TypeAdapters/newTypeHierarchyFactory(Ljava/lang/Class;Lcom/google/gson/TypeAdapter;)Lcom/google/gson/TypeAdapterFactory;
putstatic com/google/gson/internal/bind/TypeAdapters/JSON_ELEMENT_FACTORY Lcom/google/gson/TypeAdapterFactory;
invokestatic com/google/gson/internal/bind/TypeAdapters/newEnumTypeHierarchyFactory()Lcom/google/gson/TypeAdapterFactory;
putstatic com/google/gson/internal/bind/TypeAdapters/ENUM_FACTORY Lcom/google/gson/TypeAdapterFactory;
return
.limit locals 0
.limit stack 3
.end method

.method private <init>()V
aload 0
invokespecial java/lang/Object/<init>()V
return
.limit locals 1
.limit stack 1
.end method

.method public static newEnumTypeHierarchyFactory()Lcom/google/gson/TypeAdapterFactory;
new com/google/gson/internal/bind/TypeAdapters$26
dup
invokespecial com/google/gson/internal/bind/TypeAdapters$26/<init>()V
areturn
.limit locals 0
.limit stack 2
.end method

.method public static newFactory(Lcom/google/gson/reflect/TypeToken;Lcom/google/gson/TypeAdapter;)Lcom/google/gson/TypeAdapterFactory;
.signature "<TT:Ljava/lang/Object;>(Lcom/google/gson/reflect/TypeToken<TTT;>;Lcom/google/gson/TypeAdapter<TTT;>;)Lcom/google/gson/TypeAdapterFactory;"
new com/google/gson/internal/bind/TypeAdapters$27
dup
aload 0
aload 1
invokespecial com/google/gson/internal/bind/TypeAdapters$27/<init>(Lcom/google/gson/reflect/TypeToken;Lcom/google/gson/TypeAdapter;)V
areturn
.limit locals 2
.limit stack 4
.end method

.method public static newFactory(Ljava/lang/Class;Lcom/google/gson/TypeAdapter;)Lcom/google/gson/TypeAdapterFactory;
.signature "<TT:Ljava/lang/Object;>(Ljava/lang/Class<TTT;>;Lcom/google/gson/TypeAdapter<TTT;>;)Lcom/google/gson/TypeAdapterFactory;"
new com/google/gson/internal/bind/TypeAdapters$28
dup
aload 0
aload 1
invokespecial com/google/gson/internal/bind/TypeAdapters$28/<init>(Ljava/lang/Class;Lcom/google/gson/TypeAdapter;)V
areturn
.limit locals 2
.limit stack 4
.end method

.method public static newFactory(Ljava/lang/Class;Ljava/lang/Class;Lcom/google/gson/TypeAdapter;)Lcom/google/gson/TypeAdapterFactory;
.signature "<TT:Ljava/lang/Object;>(Ljava/lang/Class<TTT;>;Ljava/lang/Class<TTT;>;Lcom/google/gson/TypeAdapter<-TTT;>;)Lcom/google/gson/TypeAdapterFactory;"
new com/google/gson/internal/bind/TypeAdapters$29
dup
aload 0
aload 1
aload 2
invokespecial com/google/gson/internal/bind/TypeAdapters$29/<init>(Ljava/lang/Class;Ljava/lang/Class;Lcom/google/gson/TypeAdapter;)V
areturn
.limit locals 3
.limit stack 5
.end method

.method public static newFactoryForMultipleTypes(Ljava/lang/Class;Ljava/lang/Class;Lcom/google/gson/TypeAdapter;)Lcom/google/gson/TypeAdapterFactory;
.signature "<TT:Ljava/lang/Object;>(Ljava/lang/Class<TTT;>;Ljava/lang/Class<+TTT;>;Lcom/google/gson/TypeAdapter<-TTT;>;)Lcom/google/gson/TypeAdapterFactory;"
new com/google/gson/internal/bind/TypeAdapters$30
dup
aload 0
aload 1
aload 2
invokespecial com/google/gson/internal/bind/TypeAdapters$30/<init>(Ljava/lang/Class;Ljava/lang/Class;Lcom/google/gson/TypeAdapter;)V
areturn
.limit locals 3
.limit stack 5
.end method

.method public static newTypeHierarchyFactory(Ljava/lang/Class;Lcom/google/gson/TypeAdapter;)Lcom/google/gson/TypeAdapterFactory;
.signature "<TT:Ljava/lang/Object;>(Ljava/lang/Class<TTT;>;Lcom/google/gson/TypeAdapter<TTT;>;)Lcom/google/gson/TypeAdapterFactory;"
new com/google/gson/internal/bind/TypeAdapters$31
dup
aload 0
aload 1
invokespecial com/google/gson/internal/bind/TypeAdapters$31/<init>(Ljava/lang/Class;Lcom/google/gson/TypeAdapter;)V
areturn
.limit locals 2
.limit stack 4
.end method
