.bytecode 50.0
.class synchronized synthetic com/google/gson/internal/bind/TypeAdapters$32
.super java/lang/Object
.enclosing method com/google/gson/internal/bind/TypeAdapters
.inner class static synthetic inner com/google/gson/internal/bind/TypeAdapters$32

.field static final synthetic '$SwitchMap$com$google$gson$stream$JsonToken' [I

.method static <clinit>()V
.catch java/lang/NoSuchFieldError from L0 to L1 using L2
.catch java/lang/NoSuchFieldError from L1 to L3 using L4
.catch java/lang/NoSuchFieldError from L3 to L5 using L6
.catch java/lang/NoSuchFieldError from L5 to L7 using L8
.catch java/lang/NoSuchFieldError from L7 to L9 using L10
.catch java/lang/NoSuchFieldError from L9 to L11 using L12
.catch java/lang/NoSuchFieldError from L11 to L13 using L14
.catch java/lang/NoSuchFieldError from L13 to L15 using L16
.catch java/lang/NoSuchFieldError from L15 to L17 using L18
.catch java/lang/NoSuchFieldError from L17 to L19 using L20
invokestatic com/google/gson/stream/JsonToken/values()[Lcom/google/gson/stream/JsonToken;
arraylength
newarray int
putstatic com/google/gson/internal/bind/TypeAdapters$32/$SwitchMap$com$google$gson$stream$JsonToken [I
L0:
getstatic com/google/gson/internal/bind/TypeAdapters$32/$SwitchMap$com$google$gson$stream$JsonToken [I
getstatic com/google/gson/stream/JsonToken/NUMBER Lcom/google/gson/stream/JsonToken;
invokevirtual com/google/gson/stream/JsonToken/ordinal()I
iconst_1
iastore
L1:
getstatic com/google/gson/internal/bind/TypeAdapters$32/$SwitchMap$com$google$gson$stream$JsonToken [I
getstatic com/google/gson/stream/JsonToken/BOOLEAN Lcom/google/gson/stream/JsonToken;
invokevirtual com/google/gson/stream/JsonToken/ordinal()I
iconst_2
iastore
L3:
getstatic com/google/gson/internal/bind/TypeAdapters$32/$SwitchMap$com$google$gson$stream$JsonToken [I
getstatic com/google/gson/stream/JsonToken/STRING Lcom/google/gson/stream/JsonToken;
invokevirtual com/google/gson/stream/JsonToken/ordinal()I
iconst_3
iastore
L5:
getstatic com/google/gson/internal/bind/TypeAdapters$32/$SwitchMap$com$google$gson$stream$JsonToken [I
getstatic com/google/gson/stream/JsonToken/NULL Lcom/google/gson/stream/JsonToken;
invokevirtual com/google/gson/stream/JsonToken/ordinal()I
iconst_4
iastore
L7:
getstatic com/google/gson/internal/bind/TypeAdapters$32/$SwitchMap$com$google$gson$stream$JsonToken [I
getstatic com/google/gson/stream/JsonToken/BEGIN_ARRAY Lcom/google/gson/stream/JsonToken;
invokevirtual com/google/gson/stream/JsonToken/ordinal()I
iconst_5
iastore
L9:
getstatic com/google/gson/internal/bind/TypeAdapters$32/$SwitchMap$com$google$gson$stream$JsonToken [I
getstatic com/google/gson/stream/JsonToken/BEGIN_OBJECT Lcom/google/gson/stream/JsonToken;
invokevirtual com/google/gson/stream/JsonToken/ordinal()I
bipush 6
iastore
L11:
getstatic com/google/gson/internal/bind/TypeAdapters$32/$SwitchMap$com$google$gson$stream$JsonToken [I
getstatic com/google/gson/stream/JsonToken/END_DOCUMENT Lcom/google/gson/stream/JsonToken;
invokevirtual com/google/gson/stream/JsonToken/ordinal()I
bipush 7
iastore
L13:
getstatic com/google/gson/internal/bind/TypeAdapters$32/$SwitchMap$com$google$gson$stream$JsonToken [I
getstatic com/google/gson/stream/JsonToken/NAME Lcom/google/gson/stream/JsonToken;
invokevirtual com/google/gson/stream/JsonToken/ordinal()I
bipush 8
iastore
L15:
getstatic com/google/gson/internal/bind/TypeAdapters$32/$SwitchMap$com$google$gson$stream$JsonToken [I
getstatic com/google/gson/stream/JsonToken/END_OBJECT Lcom/google/gson/stream/JsonToken;
invokevirtual com/google/gson/stream/JsonToken/ordinal()I
bipush 9
iastore
L17:
getstatic com/google/gson/internal/bind/TypeAdapters$32/$SwitchMap$com$google$gson$stream$JsonToken [I
getstatic com/google/gson/stream/JsonToken/END_ARRAY Lcom/google/gson/stream/JsonToken;
invokevirtual com/google/gson/stream/JsonToken/ordinal()I
bipush 10
iastore
L19:
return
L20:
astore 0
return
L18:
astore 0
goto L17
L16:
astore 0
goto L15
L14:
astore 0
goto L13
L12:
astore 0
goto L11
L10:
astore 0
goto L9
L8:
astore 0
goto L7
L6:
astore 0
goto L5
L4:
astore 0
goto L3
L2:
astore 0
goto L1
.limit locals 1
.limit stack 3
.end method
