.bytecode 50.0
.class synchronized cmb/pb/ui/cmbwidget/a
.super java/lang/Object
.implements android/view/View$OnFocusChangeListener

.field final synthetic 'a' Lcmb/pb/ui/cmbwidget/CmbEditText;

.method private <init>(Lcmb/pb/ui/cmbwidget/CmbEditText;)V
aload 0
aload 1
putfield cmb/pb/ui/cmbwidget/a/a Lcmb/pb/ui/cmbwidget/CmbEditText;
aload 0
invokespecial java/lang/Object/<init>()V
return
.limit locals 2
.limit stack 2
.end method

.method synthetic <init>(Lcmb/pb/ui/cmbwidget/CmbEditText;Lcmb/pb/ui/cmbwidget/a;)V
aload 0
aload 1
invokespecial cmb/pb/ui/cmbwidget/a/<init>(Lcmb/pb/ui/cmbwidget/CmbEditText;)V
return
.limit locals 3
.limit stack 2
.end method

.method public onFocusChange(Landroid/view/View;Z)V
iconst_0
istore 3
iload 2
ifeq L0
aload 0
getfield cmb/pb/ui/cmbwidget/a/a Lcmb/pb/ui/cmbwidget/CmbEditText;
aload 0
getfield cmb/pb/ui/cmbwidget/a/a Lcmb/pb/ui/cmbwidget/CmbEditText;
invokestatic cmb/pb/ui/cmbwidget/CmbEditText/a(Lcmb/pb/ui/cmbwidget/CmbEditText;Landroid/view/View;)V
aload 0
getfield cmb/pb/ui/cmbwidget/a/a Lcmb/pb/ui/cmbwidget/CmbEditText;
invokestatic cmb/pb/ui/cmbwidget/CmbEditText/a(Lcmb/pb/ui/cmbwidget/CmbEditText;)V
aload 0
getfield cmb/pb/ui/cmbwidget/a/a Lcmb/pb/ui/cmbwidget/CmbEditText;
aload 0
getfield cmb/pb/ui/cmbwidget/a/a Lcmb/pb/ui/cmbwidget/CmbEditText;
invokestatic cmb/pb/ui/cmbwidget/CmbEditText/a(Lcmb/pb/ui/cmbwidget/CmbEditText;Landroid/widget/EditText;)V
aload 0
getfield cmb/pb/ui/cmbwidget/a/a Lcmb/pb/ui/cmbwidget/CmbEditText;
invokestatic cmb/pb/ui/cmbwidget/CmbEditText/b(Lcmb/pb/ui/cmbwidget/CmbEditText;)Z
ifne L1
aload 0
getfield cmb/pb/ui/cmbwidget/a/a Lcmb/pb/ui/cmbwidget/CmbEditText;
invokevirtual cmb/pb/ui/cmbwidget/CmbEditText/c()V
L1:
aload 0
getfield cmb/pb/ui/cmbwidget/a/a Lcmb/pb/ui/cmbwidget/CmbEditText;
astore 1
iload 3
istore 2
aload 0
getfield cmb/pb/ui/cmbwidget/a/a Lcmb/pb/ui/cmbwidget/CmbEditText;
invokevirtual cmb/pb/ui/cmbwidget/CmbEditText/getText()Landroid/text/Editable;
invokeinterface android/text/Editable/length()I 0
ifle L2
iconst_1
istore 2
L2:
aload 1
iload 2
invokevirtual cmb/pb/ui/cmbwidget/CmbEditText/a(Z)V
return
L0:
aload 0
getfield cmb/pb/ui/cmbwidget/a/a Lcmb/pb/ui/cmbwidget/CmbEditText;
invokevirtual cmb/pb/ui/cmbwidget/CmbEditText/d()V
aload 0
getfield cmb/pb/ui/cmbwidget/a/a Lcmb/pb/ui/cmbwidget/CmbEditText;
iconst_0
invokevirtual cmb/pb/ui/cmbwidget/CmbEditText/a(Z)V
return
.limit locals 4
.limit stack 2
.end method
