.bytecode 50.0
.class public synchronized com/nd/address/ui/AddressSelector
.super android/app/Activity
.inner class inner com/nd/address/ui/AddressSelector$1
.inner class inner com/nd/address/ui/AddressSelector$2
.inner class inner com/nd/address/ui/AddressSelector$3

.field public static final 'CODE' Ljava/lang/String; = "code"

.field public static final 'IS_OK_CLICK' Ljava/lang/String; = "isClick"

.field private final 'SAVE_CODE' Ljava/lang/String;

.field private 'mAdapter' Lcom/nd/address/ui/TreeViewAdapter;

.field private 'mAddresses' Ljava/util/List; signature "Ljava/util/List<Lcom/nd/address/bean/Address;>;"

.field private 'mBtnCancel' Landroid/widget/Button;

.field private 'mBtnOK' Landroid/widget/Button;

.field private 'mCurCode' Ljava/lang/String;

.field private 'mInitClick' Z

.field private 'mInitCode' Ljava/lang/String;

.field private 'mListView' Landroid/widget/ListView;

.field private 'packageName' Ljava/lang/String;

.method public <init>()V
aload 0
invokespecial android/app/Activity/<init>()V
aload 0
aconst_null
putfield com/nd/address/ui/AddressSelector/mInitCode Ljava/lang/String;
aload 0
iconst_1
putfield com/nd/address/ui/AddressSelector/mInitClick Z
aload 0
aconst_null
putfield com/nd/address/ui/AddressSelector/mCurCode Ljava/lang/String;
aload 0
new java/util/ArrayList
dup
invokespecial java/util/ArrayList/<init>()V
putfield com/nd/address/ui/AddressSelector/mAddresses Ljava/util/List;
aload 0
ldc "curCode"
putfield com/nd/address/ui/AddressSelector/SAVE_CODE Ljava/lang/String;
return
.limit locals 1
.limit stack 3
.end method

.method private Fileds2Address(Ljava/util/List;)Ljava/util/List;
.signature "(Ljava/util/List<Lcom/nd/rj/common/administrativeregions/lib/Fileds;>;)Ljava/util/List<Lcom/nd/address/bean/Address;>;"
new java/util/ArrayList
dup
invokespecial java/util/ArrayList/<init>()V
astore 2
aload 1
invokeinterface java/util/List/iterator()Ljava/util/Iterator; 0
astore 1
L0:
aload 1
invokeinterface java/util/Iterator/hasNext()Z 0
ifne L1
aload 2
areturn
L1:
aload 1
invokeinterface java/util/Iterator/next()Ljava/lang/Object; 0
checkcast com/nd/rj/common/administrativeregions/lib/Fileds
astore 3
aload 2
new com/nd/address/bean/Address
dup
aload 3
iconst_1
invokevirtual com/nd/rj/common/administrativeregions/lib/Fileds/getName(Z)Ljava/lang/String;
aload 3
invokevirtual com/nd/rj/common/administrativeregions/lib/Fileds/getCode()Ljava/lang/String;
aload 3
invokevirtual com/nd/rj/common/administrativeregions/lib/Fileds/getLevel()Lcom/nd/rj/common/administrativeregions/lib/Level;
invokespecial com/nd/address/bean/Address/<init>(Ljava/lang/String;Ljava/lang/String;Lcom/nd/rj/common/administrativeregions/lib/Level;)V
invokeinterface java/util/List/add(Ljava/lang/Object;)Z 1
pop
goto L0
.limit locals 4
.limit stack 6
.end method

.method static synthetic access$0(Lcom/nd/address/ui/AddressSelector;)Ljava/util/List;
aload 0
getfield com/nd/address/ui/AddressSelector/mAddresses Ljava/util/List;
areturn
.limit locals 1
.limit stack 1
.end method

.method static synthetic access$1(Lcom/nd/address/ui/AddressSelector;Ljava/lang/String;)V
aload 0
aload 1
putfield com/nd/address/ui/AddressSelector/mCurCode Ljava/lang/String;
return
.limit locals 2
.limit stack 2
.end method

.method static synthetic access$2(Lcom/nd/address/ui/AddressSelector;Lcom/nd/rj/common/administrativeregions/lib/Level;)V
aload 0
aload 1
invokespecial com/nd/address/ui/AddressSelector/clearData(Lcom/nd/rj/common/administrativeregions/lib/Level;)V
return
.limit locals 2
.limit stack 2
.end method

.method static synthetic access$3(Lcom/nd/address/ui/AddressSelector;)Ljava/lang/String;
aload 0
getfield com/nd/address/ui/AddressSelector/mCurCode Ljava/lang/String;
areturn
.limit locals 1
.limit stack 1
.end method

.method static synthetic access$4(Lcom/nd/address/ui/AddressSelector;Ljava/lang/String;Lcom/nd/rj/common/administrativeregions/lib/Level;)V
aload 0
aload 1
aload 2
invokespecial com/nd/address/ui/AddressSelector/setSelectStatus(Ljava/lang/String;Lcom/nd/rj/common/administrativeregions/lib/Level;)V
return
.limit locals 3
.limit stack 3
.end method

.method static synthetic access$5(Lcom/nd/address/ui/AddressSelector;Ljava/lang/String;)I
aload 0
aload 1
invokespecial com/nd/address/ui/AddressSelector/loadData(Ljava/lang/String;)I
ireturn
.limit locals 2
.limit stack 2
.end method

.method static synthetic access$6(Lcom/nd/address/ui/AddressSelector;)Lcom/nd/address/ui/TreeViewAdapter;
aload 0
getfield com/nd/address/ui/AddressSelector/mAdapter Lcom/nd/address/ui/TreeViewAdapter;
areturn
.limit locals 1
.limit stack 1
.end method

.method static synthetic access$7(Lcom/nd/address/ui/AddressSelector;)Ljava/lang/String;
aload 0
getfield com/nd/address/ui/AddressSelector/mInitCode Ljava/lang/String;
areturn
.limit locals 1
.limit stack 1
.end method

.method private clearData(Lcom/nd/rj/common/administrativeregions/lib/Level;)V
new java/util/ArrayList
dup
invokespecial java/util/ArrayList/<init>()V
astore 4
aload 4
aload 0
getfield com/nd/address/ui/AddressSelector/mAddresses Ljava/util/List;
invokeinterface java/util/List/addAll(Ljava/util/Collection;)Z 1
pop
aload 0
getfield com/nd/address/ui/AddressSelector/mAddresses Ljava/util/List;
invokeinterface java/util/List/size()I 0
istore 3
iconst_0
istore 2
L0:
iload 2
iload 3
if_icmplt L1
return
L1:
aload 4
iload 2
invokeinterface java/util/List/get(I)Ljava/lang/Object; 1
checkcast com/nd/address/bean/Address
invokevirtual com/nd/address/bean/Address/getLevel()Lcom/nd/rj/common/administrativeregions/lib/Level;
aload 1
if_acmpne L2
aload 0
getfield com/nd/address/ui/AddressSelector/mAddresses Ljava/util/List;
aload 4
iload 2
invokeinterface java/util/List/get(I)Ljava/lang/Object; 1
invokeinterface java/util/List/remove(Ljava/lang/Object;)Z 1
pop
L2:
iload 2
iconst_1
iadd
istore 2
goto L0
.limit locals 5
.limit stack 3
.end method

.method private initData(Ljava/lang/String;)V
aload 1
ifnull L0
aload 1
invokestatic com/nd/rj/common/administrativeregions/lib/Fileds/isCodeValid(Ljava/lang/String;)Z
ifne L1
L0:
return
L1:
getstatic com/nd/rj/common/administrativeregions/lib/AdministrativeRegionsHandle/INSTANCE Lcom/nd/rj/common/administrativeregions/lib/AdministrativeRegionsHandle;
aload 1
invokevirtual com/nd/rj/common/administrativeregions/lib/AdministrativeRegionsHandle/getAllParentByCode(Ljava/lang/String;)Ljava/util/Map;
astore 6
aload 6
getstatic com/nd/rj/common/administrativeregions/lib/Level/LEVEL_1 Lcom/nd/rj/common/administrativeregions/lib/Level;
invokeinterface java/util/Map/get(Ljava/lang/Object;)Ljava/lang/Object; 1
checkcast com/nd/rj/common/administrativeregions/lib/Fileds
astore 5
aload 5
ifnonnull L2
aload 0
aload 1
invokespecial com/nd/address/ui/AddressSelector/loadData(Ljava/lang/String;)I
pop
aload 0
aload 1
invokespecial com/nd/address/ui/AddressSelector/setBtnState(Ljava/lang/String;)V
return
L2:
aload 6
getstatic com/nd/rj/common/administrativeregions/lib/Level/LEVEL_2 Lcom/nd/rj/common/administrativeregions/lib/Level;
invokeinterface java/util/Map/get(Ljava/lang/Object;)Ljava/lang/Object; 1
checkcast com/nd/rj/common/administrativeregions/lib/Fileds
astore 6
aload 6
ifnonnull L3
aload 0
aload 5
invokevirtual com/nd/rj/common/administrativeregions/lib/Fileds/getCode()Ljava/lang/String;
invokespecial com/nd/address/ui/AddressSelector/loadData(Ljava/lang/String;)I
pop
aload 0
aload 1
invokespecial com/nd/address/ui/AddressSelector/loadData(Ljava/lang/String;)I
pop
aload 0
aload 1
invokespecial com/nd/address/ui/AddressSelector/setBtnState(Ljava/lang/String;)V
return
L3:
aload 0
aload 5
invokevirtual com/nd/rj/common/administrativeregions/lib/Fileds/getCode()Ljava/lang/String;
invokespecial com/nd/address/ui/AddressSelector/loadData(Ljava/lang/String;)I
pop
aload 0
aload 6
invokevirtual com/nd/rj/common/administrativeregions/lib/Fileds/getCode()Ljava/lang/String;
invokespecial com/nd/address/ui/AddressSelector/loadData(Ljava/lang/String;)I
pop
iconst_0
istore 3
aload 0
getfield com/nd/address/ui/AddressSelector/mAddresses Ljava/util/List;
invokeinterface java/util/List/size()I 0
istore 4
iconst_0
istore 2
L4:
iload 2
iload 4
if_icmplt L5
iload 3
istore 2
L6:
aload 0
getfield com/nd/address/ui/AddressSelector/mAdapter Lcom/nd/address/ui/TreeViewAdapter;
invokevirtual com/nd/address/ui/TreeViewAdapter/notifyDataSetChanged()V
iload 2
iconst_3
if_icmplt L7
aload 0
getfield com/nd/address/ui/AddressSelector/mListView Landroid/widget/ListView;
iload 2
iconst_3
isub
invokevirtual android/widget/ListView/setSelection(I)V
return
L5:
aload 0
getfield com/nd/address/ui/AddressSelector/mAddresses Ljava/util/List;
iload 2
invokeinterface java/util/List/get(I)Ljava/lang/Object; 1
checkcast com/nd/address/bean/Address
astore 5
aload 5
invokevirtual com/nd/address/bean/Address/getLevel()Lcom/nd/rj/common/administrativeregions/lib/Level;
getstatic com/nd/rj/common/administrativeregions/lib/Level/LEVEL_3 Lcom/nd/rj/common/administrativeregions/lib/Level;
if_acmpne L8
aload 5
invokevirtual com/nd/address/bean/Address/getCode()Ljava/lang/String;
aload 1
invokevirtual java/lang/String/equals(Ljava/lang/Object;)Z
ifeq L8
aload 5
iconst_1
invokevirtual com/nd/address/bean/Address/setSelected(Z)V
aload 0
getfield com/nd/address/ui/AddressSelector/mBtnOK Landroid/widget/Button;
iconst_1
invokevirtual android/widget/Button/setEnabled(Z)V
goto L6
L8:
iload 2
iconst_1
iadd
istore 2
goto L4
L7:
aload 0
getfield com/nd/address/ui/AddressSelector/mListView Landroid/widget/ListView;
iload 2
invokevirtual android/widget/ListView/setSelection(I)V
return
.limit locals 7
.limit stack 3
.end method

.method private initEvent()V
aload 0
getfield com/nd/address/ui/AddressSelector/mAddresses Ljava/util/List;
aload 0
getstatic com/nd/rj/common/administrativeregions/lib/AdministrativeRegionsHandle/INSTANCE Lcom/nd/rj/common/administrativeregions/lib/AdministrativeRegionsHandle;
aconst_null
invokevirtual com/nd/rj/common/administrativeregions/lib/AdministrativeRegionsHandle/getDirectChildrenByCode(Ljava/lang/String;)Ljava/util/List;
invokespecial com/nd/address/ui/AddressSelector/Fileds2Address(Ljava/util/List;)Ljava/util/List;
invokeinterface java/util/List/addAll(Ljava/util/Collection;)Z 1
pop
aload 0
new com/nd/address/ui/TreeViewAdapter
dup
aload 0
getfield com/nd/address/ui/AddressSelector/mAddresses Ljava/util/List;
aload 0
invokespecial com/nd/address/ui/TreeViewAdapter/<init>(Ljava/util/List;Landroid/content/Context;)V
putfield com/nd/address/ui/AddressSelector/mAdapter Lcom/nd/address/ui/TreeViewAdapter;
aload 0
getfield com/nd/address/ui/AddressSelector/mListView Landroid/widget/ListView;
aload 0
getfield com/nd/address/ui/AddressSelector/mAdapter Lcom/nd/address/ui/TreeViewAdapter;
invokevirtual android/widget/ListView/setAdapter(Landroid/widget/ListAdapter;)V
aload 0
getfield com/nd/address/ui/AddressSelector/mListView Landroid/widget/ListView;
new com/nd/address/ui/AddressSelector$1
dup
aload 0
invokespecial com/nd/address/ui/AddressSelector$1/<init>(Lcom/nd/address/ui/AddressSelector;)V
invokevirtual android/widget/ListView/setOnItemClickListener(Landroid/widget/AdapterView$OnItemClickListener;)V
aload 0
getfield com/nd/address/ui/AddressSelector/mBtnOK Landroid/widget/Button;
new com/nd/address/ui/AddressSelector$2
dup
aload 0
invokespecial com/nd/address/ui/AddressSelector$2/<init>(Lcom/nd/address/ui/AddressSelector;)V
invokevirtual android/widget/Button/setOnClickListener(Landroid/view/View$OnClickListener;)V
aload 0
getfield com/nd/address/ui/AddressSelector/mBtnCancel Landroid/widget/Button;
new com/nd/address/ui/AddressSelector$3
dup
aload 0
invokespecial com/nd/address/ui/AddressSelector$3/<init>(Lcom/nd/address/ui/AddressSelector;)V
invokevirtual android/widget/Button/setOnClickListener(Landroid/view/View$OnClickListener;)V
return
.limit locals 1
.limit stack 5
.end method

.method private initView()V
aload 0
iconst_1
invokevirtual com/nd/address/ui/AddressSelector/requestWindowFeature(I)Z
pop
aload 0
aload 0
invokevirtual com/nd/address/ui/AddressSelector/getResources()Landroid/content/res/Resources;
ldc "activity_address_selector"
ldc "layout"
aload 0
getfield com/nd/address/ui/AddressSelector/packageName Ljava/lang/String;
invokevirtual android/content/res/Resources/getIdentifier(Ljava/lang/String;Ljava/lang/String;Ljava/lang/String;)I
invokevirtual com/nd/address/ui/AddressSelector/setContentView(I)V
getstatic com/nd/rj/common/administrativeregions/lib/SQLiteHandle/INSTANCE Lcom/nd/rj/common/administrativeregions/lib/SQLiteHandle;
aload 0
invokevirtual com/nd/rj/common/administrativeregions/lib/SQLiteHandle/openDatabase(Landroid/content/Context;)V
aload 0
aload 0
aload 0
invokevirtual com/nd/address/ui/AddressSelector/getResources()Landroid/content/res/Resources;
ldc "lv_address_selector"
ldc "id"
aload 0
getfield com/nd/address/ui/AddressSelector/packageName Ljava/lang/String;
invokevirtual android/content/res/Resources/getIdentifier(Ljava/lang/String;Ljava/lang/String;Ljava/lang/String;)I
invokevirtual com/nd/address/ui/AddressSelector/findViewById(I)Landroid/view/View;
checkcast android/widget/ListView
putfield com/nd/address/ui/AddressSelector/mListView Landroid/widget/ListView;
aload 0
aload 0
aload 0
invokevirtual com/nd/address/ui/AddressSelector/getResources()Landroid/content/res/Resources;
ldc "btn_OK"
ldc "id"
aload 0
getfield com/nd/address/ui/AddressSelector/packageName Ljava/lang/String;
invokevirtual android/content/res/Resources/getIdentifier(Ljava/lang/String;Ljava/lang/String;Ljava/lang/String;)I
invokevirtual com/nd/address/ui/AddressSelector/findViewById(I)Landroid/view/View;
checkcast android/widget/Button
putfield com/nd/address/ui/AddressSelector/mBtnOK Landroid/widget/Button;
aload 0
aload 0
aload 0
invokevirtual com/nd/address/ui/AddressSelector/getResources()Landroid/content/res/Resources;
ldc "btn_cancel"
ldc "id"
aload 0
getfield com/nd/address/ui/AddressSelector/packageName Ljava/lang/String;
invokevirtual android/content/res/Resources/getIdentifier(Ljava/lang/String;Ljava/lang/String;Ljava/lang/String;)I
invokevirtual com/nd/address/ui/AddressSelector/findViewById(I)Landroid/view/View;
checkcast android/widget/Button
putfield com/nd/address/ui/AddressSelector/mBtnCancel Landroid/widget/Button;
return
.limit locals 1
.limit stack 6
.end method

.method private loadData(Ljava/lang/String;)I
iconst_m1
istore 3
aload 0
getfield com/nd/address/ui/AddressSelector/mAddresses Ljava/util/List;
invokeinterface java/util/List/size()I 0
istore 4
iconst_0
istore 2
L0:
iload 2
iload 4
if_icmplt L1
L2:
iload 3
iconst_m1
if_icmpne L3
iload 3
ireturn
L1:
aload 0
getfield com/nd/address/ui/AddressSelector/mAddresses Ljava/util/List;
iload 2
invokeinterface java/util/List/get(I)Ljava/lang/Object; 1
checkcast com/nd/address/bean/Address
invokevirtual com/nd/address/bean/Address/getCode()Ljava/lang/String;
aload 1
invokevirtual java/lang/String/equals(Ljava/lang/Object;)Z
ifeq L4
iload 2
istore 3
aload 0
getfield com/nd/address/ui/AddressSelector/mAddresses Ljava/util/List;
iload 2
invokeinterface java/util/List/get(I)Ljava/lang/Object; 1
checkcast com/nd/address/bean/Address
iconst_1
invokevirtual com/nd/address/bean/Address/setSelected(Z)V
goto L2
L4:
iload 2
iconst_1
iadd
istore 2
goto L0
L3:
aload 0
getfield com/nd/address/ui/AddressSelector/mAddresses Ljava/util/List;
iload 3
iconst_1
iadd
aload 0
getstatic com/nd/rj/common/administrativeregions/lib/AdministrativeRegionsHandle/INSTANCE Lcom/nd/rj/common/administrativeregions/lib/AdministrativeRegionsHandle;
aload 1
invokevirtual com/nd/rj/common/administrativeregions/lib/AdministrativeRegionsHandle/getDirectChildrenByCode(Ljava/lang/String;)Ljava/util/List;
invokespecial com/nd/address/ui/AddressSelector/Fileds2Address(Ljava/util/List;)Ljava/util/List;
invokeinterface java/util/List/addAll(ILjava/util/Collection;)Z 2
pop
aload 0
getfield com/nd/address/ui/AddressSelector/mAdapter Lcom/nd/address/ui/TreeViewAdapter;
invokevirtual com/nd/address/ui/TreeViewAdapter/notifyDataSetChanged()V
aload 0
getfield com/nd/address/ui/AddressSelector/mListView Landroid/widget/ListView;
iload 3
invokevirtual android/widget/ListView/setSelection(I)V
iload 3
ireturn
.limit locals 5
.limit stack 5
.end method

.method private setBtnState(Ljava/lang/String;)V
aload 0
getfield com/nd/address/ui/AddressSelector/mInitClick Z
ifne L0
aload 0
getfield com/nd/address/ui/AddressSelector/mAdapter Lcom/nd/address/ui/TreeViewAdapter;
aload 1
invokevirtual com/nd/address/ui/TreeViewAdapter/isHasChildren(Ljava/lang/String;)Z
ifne L1
L0:
aload 0
getfield com/nd/address/ui/AddressSelector/mBtnOK Landroid/widget/Button;
iconst_1
invokevirtual android/widget/Button/setEnabled(Z)V
return
L1:
aload 0
getfield com/nd/address/ui/AddressSelector/mBtnOK Landroid/widget/Button;
iconst_0
invokevirtual android/widget/Button/setEnabled(Z)V
return
.limit locals 2
.limit stack 2
.end method

.method private setSelectStatus(Ljava/lang/String;Lcom/nd/rj/common/administrativeregions/lib/Level;)V
aload 0
getfield com/nd/address/ui/AddressSelector/mAddresses Ljava/util/List;
invokeinterface java/util/List/size()I 0
istore 4
iconst_0
istore 3
L0:
iload 3
iload 4
if_icmplt L1
return
L1:
aload 0
getfield com/nd/address/ui/AddressSelector/mAddresses Ljava/util/List;
iload 3
invokeinterface java/util/List/get(I)Ljava/lang/Object; 1
checkcast com/nd/address/bean/Address
astore 5
aload 5
invokevirtual com/nd/address/bean/Address/getLevel()Lcom/nd/rj/common/administrativeregions/lib/Level;
aload 2
if_acmpne L2
aload 5
invokevirtual com/nd/address/bean/Address/getCode()Ljava/lang/String;
aload 1
invokevirtual java/lang/String/equals(Ljava/lang/Object;)Z
ifne L3
aload 5
iconst_0
invokevirtual com/nd/address/bean/Address/setSelected(Z)V
L2:
iload 3
iconst_1
iadd
istore 3
goto L0
L3:
aload 0
getfield com/nd/address/ui/AddressSelector/mInitClick Z
ifne L4
aload 0
getfield com/nd/address/ui/AddressSelector/mAdapter Lcom/nd/address/ui/TreeViewAdapter;
aload 1
invokevirtual com/nd/address/ui/TreeViewAdapter/isHasChildren(Ljava/lang/String;)Z
ifne L5
aload 5
invokevirtual com/nd/address/bean/Address/isSelected()Z
ifeq L5
L4:
aload 0
getfield com/nd/address/ui/AddressSelector/mBtnOK Landroid/widget/Button;
iconst_1
invokevirtual android/widget/Button/setEnabled(Z)V
goto L2
L5:
aload 0
getfield com/nd/address/ui/AddressSelector/mBtnOK Landroid/widget/Button;
iconst_0
invokevirtual android/widget/Button/setEnabled(Z)V
goto L2
.limit locals 6
.limit stack 2
.end method

.method protected onCreate(Landroid/os/Bundle;)V
aload 0
aload 1
invokespecial android/app/Activity/onCreate(Landroid/os/Bundle;)V
aload 0
aload 0
invokevirtual com/nd/address/ui/AddressSelector/getIntent()Landroid/content/Intent;
ldc "code"
invokevirtual android/content/Intent/getStringExtra(Ljava/lang/String;)Ljava/lang/String;
putfield com/nd/address/ui/AddressSelector/mInitCode Ljava/lang/String;
aload 0
aload 0
invokevirtual com/nd/address/ui/AddressSelector/getIntent()Landroid/content/Intent;
ldc "isClick"
iconst_1
invokevirtual android/content/Intent/getBooleanExtra(Ljava/lang/String;Z)Z
putfield com/nd/address/ui/AddressSelector/mInitClick Z
aload 0
getstatic com/nd/address/utils/AddressUtil/INSTANCE Lcom/nd/address/utils/AddressUtil;
invokevirtual com/nd/address/utils/AddressUtil/getPackageName()Ljava/lang/String;
putfield com/nd/address/ui/AddressSelector/packageName Ljava/lang/String;
aload 0
getfield com/nd/address/ui/AddressSelector/packageName Ljava/lang/String;
invokestatic android/text/TextUtils/isEmpty(Ljava/lang/CharSequence;)Z
ifeq L0
aload 0
aload 0
invokevirtual com/nd/address/ui/AddressSelector/getPackageName()Ljava/lang/String;
putfield com/nd/address/ui/AddressSelector/packageName Ljava/lang/String;
L0:
aload 1
ifnull L1
aload 0
aload 1
ldc "curCode"
invokevirtual android/os/Bundle/getString(Ljava/lang/String;)Ljava/lang/String;
putfield com/nd/address/ui/AddressSelector/mCurCode Ljava/lang/String;
aload 0
invokespecial com/nd/address/ui/AddressSelector/initView()V
aload 0
invokespecial com/nd/address/ui/AddressSelector/initEvent()V
aload 0
aload 0
getfield com/nd/address/ui/AddressSelector/mCurCode Ljava/lang/String;
invokespecial com/nd/address/ui/AddressSelector/initData(Ljava/lang/String;)V
return
L1:
aload 0
aload 0
getfield com/nd/address/ui/AddressSelector/mInitCode Ljava/lang/String;
putfield com/nd/address/ui/AddressSelector/mCurCode Ljava/lang/String;
aload 0
invokespecial com/nd/address/ui/AddressSelector/initView()V
aload 0
invokespecial com/nd/address/ui/AddressSelector/initEvent()V
aload 0
aload 0
getfield com/nd/address/ui/AddressSelector/mInitCode Ljava/lang/String;
invokespecial com/nd/address/ui/AddressSelector/initData(Ljava/lang/String;)V
return
.limit locals 2
.limit stack 4
.end method

.method protected onSaveInstanceState(Landroid/os/Bundle;)V
aload 0
aload 1
invokespecial android/app/Activity/onSaveInstanceState(Landroid/os/Bundle;)V
aload 1
ldc "curCode"
aload 0
getfield com/nd/address/ui/AddressSelector/mCurCode Ljava/lang/String;
invokevirtual android/os/Bundle/putString(Ljava/lang/String;Ljava/lang/String;)V
return
.limit locals 2
.limit stack 3
.end method
