.bytecode 50.0
.class public synchronized com/android/u/weibo/weibo/business/comm/NdCommentSdk
.super com/android/u/weibo/weibo/business/comm/NdBaseSdk

.method public <init>()V
aload 0
invokespecial com/android/u/weibo/weibo/business/comm/NdBaseSdk/<init>()V
return
.limit locals 1
.limit stack 1
.end method

.method public deleteReply(Landroid/content/Context;JJ)V
.throws org/json/JSONException
.throws com/android/u/weibo/weibo/controller/WeiBoException
new java/lang/StringBuilder
dup
invokespecial java/lang/StringBuilder/<init>()V
astore 7
aload 7
getstatic com/android/u/weibo/weibo/business/comm/WbRequireUrl/DELETE_COMMENT Ljava/lang/String;
invokevirtual java/lang/StringBuilder/append(Ljava/lang/String;)Ljava/lang/StringBuilder;
pop
aload 0
aload 7
ldc "tid"
lload 2
invokestatic java/lang/Long/valueOf(J)Ljava/lang/Long;
invokevirtual com/android/u/weibo/weibo/business/comm/NdCommentSdk/addRequestParam(Ljava/lang/StringBuilder;Ljava/lang/String;Ljava/lang/Object;)V
aload 0
aload 7
ldc "rid"
lload 4
invokestatic java/lang/Long/valueOf(J)Ljava/lang/Long;
invokevirtual com/android/u/weibo/weibo/business/comm/NdCommentSdk/addRequestParam(Ljava/lang/StringBuilder;Ljava/lang/String;Ljava/lang/Object;)V
new com/android/u/weibo/weibo/business/comm/NdHttpToolkit
dup
aload 1
aload 7
invokevirtual java/lang/StringBuilder/toString()Ljava/lang/String;
invokespecial com/android/u/weibo/weibo/business/comm/NdHttpToolkit/<init>(Landroid/content/Context;Ljava/lang/String;)V
astore 7
aload 7
invokevirtual com/android/u/weibo/weibo/business/comm/NdHttpToolkit/DoDelete()I
istore 6
aload 7
invokevirtual com/android/u/weibo/weibo/business/comm/NdHttpToolkit/getResponse()Ljava/lang/String;
astore 7
iload 6
sipush 200
if_icmpne L0
return
L0:
aload 1
iload 6
new org/json/JSONObject
dup
aload 7
invokespecial org/json/JSONObject/<init>(Ljava/lang/String;)V
invokestatic com/android/u/weibo/weibo/business/comm/NdHttpToolkit/parseWeiboErrMsg(Landroid/content/Context;ILorg/json/JSONObject;)V
return
.limit locals 8
.limit stack 5
.end method

.method public getAtReplyInfoList(Landroid/content/Context;J)Lcom/android/u/weibo/weibo/business/bean/ReplyInfoList;
.throws org/json/JSONException
.throws com/android/u/weibo/weibo/controller/WeiBoException
new java/lang/StringBuilder
dup
invokespecial java/lang/StringBuilder/<init>()V
astore 4
aload 4
getstatic com/android/u/weibo/weibo/business/comm/WbRequireUrl/GET_AT_ME_REPLY_LIST Ljava/lang/Object;
invokevirtual java/lang/StringBuilder/append(Ljava/lang/Object;)Ljava/lang/StringBuilder;
pop
aload 0
aload 4
lload 2
invokevirtual com/android/u/weibo/weibo/business/comm/NdCommentSdk/addIdMaxParam(Ljava/lang/StringBuilder;J)V
new com/android/u/weibo/weibo/business/comm/NdHttpToolkit
dup
aload 1
aload 4
invokevirtual java/lang/StringBuilder/toString()Ljava/lang/String;
invokespecial com/android/u/weibo/weibo/business/comm/NdHttpToolkit/<init>(Landroid/content/Context;Ljava/lang/String;)V
astore 4
aload 0
aload 1
aload 4
invokevirtual com/android/u/weibo/weibo/business/comm/NdHttpToolkit/DoGet()I
aload 4
invokevirtual com/android/u/weibo/weibo/business/comm/NdHttpToolkit/getResponse()Ljava/lang/String;
invokevirtual com/android/u/weibo/weibo/business/comm/NdCommentSdk/parseAtReplyInfoListFromResponse(Landroid/content/Context;ILjava/lang/String;)Lcom/android/u/weibo/weibo/business/bean/ReplyInfoList;
areturn
.limit locals 5
.limit stack 4
.end method

.method public getReplyInfoList(Landroid/content/Context;JJ)Lcom/android/u/weibo/weibo/business/bean/ReplyInfoList;
.throws org/json/JSONException
.throws com/android/u/weibo/weibo/controller/WeiBoException
new java/lang/StringBuilder
dup
invokespecial java/lang/StringBuilder/<init>()V
astore 6
aload 6
getstatic com/android/u/weibo/weibo/business/comm/WbRequireUrl/GET_COMMENT_LIST Ljava/lang/String;
invokevirtual java/lang/StringBuilder/append(Ljava/lang/String;)Ljava/lang/StringBuilder;
pop
aload 0
aload 6
ldc "tid"
lload 2
invokestatic java/lang/Long/valueOf(J)Ljava/lang/Long;
invokevirtual com/android/u/weibo/weibo/business/comm/NdCommentSdk/addRequestParam(Ljava/lang/StringBuilder;Ljava/lang/String;Ljava/lang/Object;)V
aload 0
aload 6
lload 4
invokevirtual com/android/u/weibo/weibo/business/comm/NdCommentSdk/addIdMaxParam(Ljava/lang/StringBuilder;J)V
new com/android/u/weibo/weibo/business/comm/NdHttpToolkit
dup
aload 1
aload 6
invokevirtual java/lang/StringBuilder/toString()Ljava/lang/String;
invokespecial com/android/u/weibo/weibo/business/comm/NdHttpToolkit/<init>(Landroid/content/Context;Ljava/lang/String;)V
astore 6
aload 0
aload 1
aload 6
invokevirtual com/android/u/weibo/weibo/business/comm/NdHttpToolkit/DoGet()I
aload 6
invokevirtual com/android/u/weibo/weibo/business/comm/NdHttpToolkit/getResponse()Ljava/lang/String;
invokevirtual com/android/u/weibo/weibo/business/comm/NdCommentSdk/parseReplyInfoListFromResponse(Landroid/content/Context;ILjava/lang/String;)Lcom/android/u/weibo/weibo/business/bean/ReplyInfoList;
areturn
.limit locals 7
.limit stack 5
.end method

.method public getReplyMeInfoList(Landroid/content/Context;J)Lcom/android/u/weibo/weibo/business/bean/ReplyInfoList;
.throws org/json/JSONException
.throws com/android/u/weibo/weibo/controller/WeiBoException
new java/lang/StringBuilder
dup
invokespecial java/lang/StringBuilder/<init>()V
astore 4
aload 4
getstatic com/android/u/weibo/weibo/business/comm/WbRequireUrl/GET_COMMENT_LIST_TO_ME Ljava/lang/String;
invokevirtual java/lang/StringBuilder/append(Ljava/lang/String;)Ljava/lang/StringBuilder;
pop
aload 0
aload 4
lload 2
invokevirtual com/android/u/weibo/weibo/business/comm/NdCommentSdk/addIdMaxParam(Ljava/lang/StringBuilder;J)V
new com/android/u/weibo/weibo/business/comm/NdHttpToolkit
dup
aload 1
aload 4
invokevirtual java/lang/StringBuilder/toString()Ljava/lang/String;
invokespecial com/android/u/weibo/weibo/business/comm/NdHttpToolkit/<init>(Landroid/content/Context;Ljava/lang/String;)V
astore 4
aload 0
aload 1
aload 4
invokevirtual com/android/u/weibo/weibo/business/comm/NdHttpToolkit/DoGet()I
aload 4
invokevirtual com/android/u/weibo/weibo/business/comm/NdHttpToolkit/getResponse()Ljava/lang/String;
invokevirtual com/android/u/weibo/weibo/business/comm/NdCommentSdk/parseReplyInfoListFromResponse(Landroid/content/Context;ILjava/lang/String;)Lcom/android/u/weibo/weibo/business/bean/ReplyInfoList;
areturn
.limit locals 5
.limit stack 4
.end method

.method public postReplyInfo(Landroid/content/Context;Ljava/lang/String;JII)Lcom/android/u/weibo/weibo/business/bean/ReplyInfo;
.throws java/lang/IllegalStateException
.throws java/io/UnsupportedEncodingException
.throws java/io/IOException
.throws com/android/u/weibo/weibo/controller/WeiBoException
.throws org/json/JSONException
new java/lang/StringBuilder
dup
invokespecial java/lang/StringBuilder/<init>()V
astore 7
aload 7
getstatic com/android/u/weibo/weibo/business/comm/WbRequireUrl/COMMENT_TOPIC Ljava/lang/String;
invokevirtual java/lang/StringBuilder/append(Ljava/lang/String;)Ljava/lang/StringBuilder;
pop
aload 0
aload 7
ldc "tid"
lload 3
invokestatic java/lang/Long/valueOf(J)Ljava/lang/Long;
invokevirtual com/android/u/weibo/weibo/business/comm/NdCommentSdk/addRequestParam(Ljava/lang/StringBuilder;Ljava/lang/String;Ljava/lang/Object;)V
new com/android/u/weibo/weibo/business/comm/NdHttpToolkit
dup
aload 1
aload 7
invokevirtual java/lang/StringBuilder/toString()Ljava/lang/String;
invokespecial com/android/u/weibo/weibo/business/comm/NdHttpToolkit/<init>(Landroid/content/Context;Ljava/lang/String;)V
astore 7
new org/json/JSONObject
dup
invokespecial org/json/JSONObject/<init>()V
astore 8
aload 8
ldc "content"
aload 2
invokestatic android/net/Uri/encode(Ljava/lang/String;)Ljava/lang/String;
invokevirtual org/json/JSONObject/put(Ljava/lang/String;Ljava/lang/Object;)Lorg/json/JSONObject;
pop
aload 8
ldc "reflag"
iload 6
invokevirtual org/json/JSONObject/put(Ljava/lang/String;I)Lorg/json/JSONObject;
pop
aload 8
ldc "relay"
iload 5
invokevirtual org/json/JSONObject/put(Ljava/lang/String;I)Lorg/json/JSONObject;
pop
aload 0
aload 1
aload 7
aload 8
invokevirtual com/android/u/weibo/weibo/business/comm/NdHttpToolkit/DoPost(Lorg/json/JSONObject;)I
aload 7
invokevirtual com/android/u/weibo/weibo/business/comm/NdHttpToolkit/getResponse()Ljava/lang/String;
invokevirtual com/android/u/weibo/weibo/business/comm/NdCommentSdk/parseReplyInfoFromResponse(Landroid/content/Context;ILjava/lang/String;)Lcom/android/u/weibo/weibo/business/bean/ReplyInfo;
areturn
.limit locals 9
.limit stack 5
.end method

.method public replyReplyInfo(Landroid/content/Context;Ljava/lang/String;JJIII)Lcom/android/u/weibo/weibo/business/bean/ReplyInfo;
.throws java/lang/IllegalStateException
.throws java/io/UnsupportedEncodingException
.throws java/io/IOException
.throws org/json/JSONException
.throws com/android/u/weibo/weibo/controller/WeiBoException
new java/lang/StringBuilder
dup
invokespecial java/lang/StringBuilder/<init>()V
astore 10
aload 10
getstatic com/android/u/weibo/weibo/business/comm/WbRequireUrl/REPLY_COMMENT Ljava/lang/String;
invokevirtual java/lang/StringBuilder/append(Ljava/lang/String;)Ljava/lang/StringBuilder;
pop
aload 0
aload 10
ldc "tid"
lload 3
invokestatic java/lang/Long/valueOf(J)Ljava/lang/Long;
invokevirtual com/android/u/weibo/weibo/business/comm/NdCommentSdk/addRequestParam(Ljava/lang/StringBuilder;Ljava/lang/String;Ljava/lang/Object;)V
aload 0
aload 10
ldc "rid"
lload 5
invokestatic java/lang/Long/valueOf(J)Ljava/lang/Long;
invokevirtual com/android/u/weibo/weibo/business/comm/NdCommentSdk/addRequestParam(Ljava/lang/StringBuilder;Ljava/lang/String;Ljava/lang/Object;)V
new com/android/u/weibo/weibo/business/comm/NdHttpToolkit
dup
aload 1
aload 10
invokevirtual java/lang/StringBuilder/toString()Ljava/lang/String;
invokespecial com/android/u/weibo/weibo/business/comm/NdHttpToolkit/<init>(Landroid/content/Context;Ljava/lang/String;)V
astore 10
new org/json/JSONObject
dup
invokespecial org/json/JSONObject/<init>()V
astore 11
aload 11
ldc "content"
aload 2
invokestatic android/net/Uri/encode(Ljava/lang/String;)Ljava/lang/String;
invokevirtual org/json/JSONObject/put(Ljava/lang/String;Ljava/lang/Object;)Lorg/json/JSONObject;
pop
aload 11
ldc "reflag"
iload 8
invokevirtual org/json/JSONObject/put(Ljava/lang/String;I)Lorg/json/JSONObject;
pop
aload 11
ldc "relay"
iload 7
invokevirtual org/json/JSONObject/put(Ljava/lang/String;I)Lorg/json/JSONObject;
pop
aload 11
ldc "without_mention"
iload 9
invokevirtual org/json/JSONObject/put(Ljava/lang/String;I)Lorg/json/JSONObject;
pop
aload 0
aload 1
aload 10
aload 11
invokevirtual com/android/u/weibo/weibo/business/comm/NdHttpToolkit/DoPost(Lorg/json/JSONObject;)I
aload 10
invokevirtual com/android/u/weibo/weibo/business/comm/NdHttpToolkit/getResponse()Ljava/lang/String;
invokevirtual com/android/u/weibo/weibo/business/comm/NdCommentSdk/parseReplyInfoFromResponse(Landroid/content/Context;ILjava/lang/String;)Lcom/android/u/weibo/weibo/business/bean/ReplyInfo;
areturn
.limit locals 12
.limit stack 5
.end method
