.bytecode 50.0
.class synchronized com/android/u/weibo/weibo/ui/activity/CommentListActivity$5
.super android/content/BroadcastReceiver
.enclosing method com/android/u/weibo/weibo/ui/activity/CommentListActivity
.inner class inner com/android/u/weibo/weibo/ui/activity/CommentListActivity$5

.field final synthetic 'this$0' Lcom/android/u/weibo/weibo/ui/activity/CommentListActivity;

.method <init>(Lcom/android/u/weibo/weibo/ui/activity/CommentListActivity;)V
aload 0
aload 1
putfield com/android/u/weibo/weibo/ui/activity/CommentListActivity$5/this$0 Lcom/android/u/weibo/weibo/ui/activity/CommentListActivity;
aload 0
invokespecial android/content/BroadcastReceiver/<init>()V
return
.limit locals 2
.limit stack 2
.end method

.method public onReceive(Landroid/content/Context;Landroid/content/Intent;)V
.catch org/json/JSONException from L0 to L1 using L2
aload 2
ldc "localCreateAt"
lconst_0
invokevirtual android/content/Intent/getLongExtra(Ljava/lang/String;J)J
lstore 3
aload 2
ldc "createAt"
invokevirtual android/content/Intent/hasExtra(Ljava/lang/String;)Z
ifeq L3
aload 0
getfield com/android/u/weibo/weibo/ui/activity/CommentListActivity$5/this$0 Lcom/android/u/weibo/weibo/ui/activity/CommentListActivity;
invokestatic com/android/u/weibo/weibo/ui/activity/CommentListActivity/access$300(Lcom/android/u/weibo/weibo/ui/activity/CommentListActivity;)Lcom/android/u/weibo/weibo/ui/adapter/ThreeTypeAdapter;
lload 3
ldc2_w -1L
invokevirtual com/android/u/weibo/weibo/ui/adapter/ThreeTypeAdapter/updateLocalComment(JJ)V
L4:
aload 0
getfield com/android/u/weibo/weibo/ui/activity/CommentListActivity$5/this$0 Lcom/android/u/weibo/weibo/ui/activity/CommentListActivity;
invokestatic com/android/u/weibo/weibo/ui/activity/CommentListActivity/access$300(Lcom/android/u/weibo/weibo/ui/activity/CommentListActivity;)Lcom/android/u/weibo/weibo/ui/adapter/ThreeTypeAdapter;
getfield com/android/u/weibo/weibo/ui/adapter/ThreeTypeAdapter/mType Lcom/android/u/weibo/weibo/ui/adapter/ThreeTypeAdapter$ListViewDataType;
getstatic com/android/u/weibo/weibo/ui/adapter/ThreeTypeAdapter$ListViewDataType/COMMENT Lcom/android/u/weibo/weibo/ui/adapter/ThreeTypeAdapter$ListViewDataType;
if_acmpne L5
aload 0
getfield com/android/u/weibo/weibo/ui/activity/CommentListActivity$5/this$0 Lcom/android/u/weibo/weibo/ui/activity/CommentListActivity;
invokestatic com/android/u/weibo/weibo/ui/activity/CommentListActivity/access$300(Lcom/android/u/weibo/weibo/ui/activity/CommentListActivity;)Lcom/android/u/weibo/weibo/ui/adapter/ThreeTypeAdapter;
invokevirtual com/android/u/weibo/weibo/ui/adapter/ThreeTypeAdapter/notifyDataSetChanged()V
L5:
return
L3:
aconst_null
astore 1
L0:
new com/android/u/weibo/weibo/business/parser/ReplyInfoParser
dup
invokespecial com/android/u/weibo/weibo/business/parser/ReplyInfoParser/<init>()V
new org/json/JSONObject
dup
aload 2
ldc "comment"
invokevirtual android/content/Intent/getStringExtra(Ljava/lang/String;)Ljava/lang/String;
invokespecial org/json/JSONObject/<init>(Ljava/lang/String;)V
invokevirtual com/android/u/weibo/weibo/business/parser/ReplyInfoParser/parse(Lorg/json/JSONObject;)Lcom/android/u/weibo/weibo/business/bean/ReplyInfo;
astore 2
L1:
aload 2
astore 1
L6:
aload 1
ifnull L4
aload 1
iconst_0
invokestatic com/android/u/weibo/weibo/utils/ConvertTweetListUtils/convertReply(Lcom/android/u/weibo/weibo/business/bean/ReplyInfo;Z)V
aload 0
getfield com/android/u/weibo/weibo/ui/activity/CommentListActivity$5/this$0 Lcom/android/u/weibo/weibo/ui/activity/CommentListActivity;
invokestatic com/android/u/weibo/weibo/ui/activity/CommentListActivity/access$300(Lcom/android/u/weibo/weibo/ui/activity/CommentListActivity;)Lcom/android/u/weibo/weibo/ui/adapter/ThreeTypeAdapter;
aload 1
lload 3
invokevirtual com/android/u/weibo/weibo/ui/adapter/ThreeTypeAdapter/updateLocalComment(Lcom/android/u/weibo/weibo/business/bean/ReplyInfo;J)V
goto L4
L2:
astore 2
aload 2
invokevirtual org/json/JSONException/printStackTrace()V
goto L6
.limit locals 5
.limit stack 5
.end method
