.bytecode 50.0
.class synchronized com/android/u/weibo/weibo/ui/activity/CommentListActivity$ServerCallback$8
.super java/lang/Object
.implements java/lang/Runnable
.enclosing method com/android/u/weibo/weibo/ui/activity/CommentListActivity$ServerCallback/onError(ILcom/android/u/weibo/weibo/controller/NdWeiboException;J)V
.inner class private ServerCallback inner com/android/u/weibo/weibo/ui/activity/CommentListActivity$ServerCallback outer com/android/u/weibo/weibo/ui/activity/CommentListActivity
.inner class inner com/android/u/weibo/weibo/ui/activity/CommentListActivity$ServerCallback$8

.field final synthetic 'this$1' Lcom/android/u/weibo/weibo/ui/activity/CommentListActivity$ServerCallback;

.method <init>(Lcom/android/u/weibo/weibo/ui/activity/CommentListActivity$ServerCallback;)V
aload 0
aload 1
putfield com/android/u/weibo/weibo/ui/activity/CommentListActivity$ServerCallback$8/this$1 Lcom/android/u/weibo/weibo/ui/activity/CommentListActivity$ServerCallback;
aload 0
invokespecial java/lang/Object/<init>()V
return
.limit locals 2
.limit stack 2
.end method

.method public run()V
aload 0
getfield com/android/u/weibo/weibo/ui/activity/CommentListActivity$ServerCallback$8/this$1 Lcom/android/u/weibo/weibo/ui/activity/CommentListActivity$ServerCallback;
getfield com/android/u/weibo/weibo/ui/activity/CommentListActivity$ServerCallback/this$0 Lcom/android/u/weibo/weibo/ui/activity/CommentListActivity;
invokestatic com/android/u/weibo/weibo/ui/activity/CommentListActivity/access$1200(Lcom/android/u/weibo/weibo/ui/activity/CommentListActivity;)Lcom/handmark/pulltorefresh/library/PullToRefreshListView;
invokevirtual com/handmark/pulltorefresh/library/PullToRefreshListView/onRefreshComplete()V
aload 0
getfield com/android/u/weibo/weibo/ui/activity/CommentListActivity$ServerCallback$8/this$1 Lcom/android/u/weibo/weibo/ui/activity/CommentListActivity$ServerCallback;
getfield com/android/u/weibo/weibo/ui/activity/CommentListActivity$ServerCallback/this$0 Lcom/android/u/weibo/weibo/ui/activity/CommentListActivity;
invokestatic com/android/u/weibo/weibo/ui/activity/CommentListActivity/access$300(Lcom/android/u/weibo/weibo/ui/activity/CommentListActivity;)Lcom/android/u/weibo/weibo/ui/adapter/ThreeTypeAdapter;
getfield com/android/u/weibo/weibo/ui/adapter/ThreeTypeAdapter/mType Lcom/android/u/weibo/weibo/ui/adapter/ThreeTypeAdapter$ListViewDataType;
getstatic com/android/u/weibo/weibo/ui/adapter/ThreeTypeAdapter$ListViewDataType/COMMENT Lcom/android/u/weibo/weibo/ui/adapter/ThreeTypeAdapter$ListViewDataType;
if_acmpne L0
aload 0
getfield com/android/u/weibo/weibo/ui/activity/CommentListActivity$ServerCallback$8/this$1 Lcom/android/u/weibo/weibo/ui/activity/CommentListActivity$ServerCallback;
getfield com/android/u/weibo/weibo/ui/activity/CommentListActivity$ServerCallback/this$0 Lcom/android/u/weibo/weibo/ui/activity/CommentListActivity;
invokestatic com/android/u/weibo/weibo/ui/activity/CommentListActivity/access$300(Lcom/android/u/weibo/weibo/ui/activity/CommentListActivity;)Lcom/android/u/weibo/weibo/ui/adapter/ThreeTypeAdapter;
aconst_null
putfield com/android/u/weibo/weibo/ui/adapter/ThreeTypeAdapter/mReplyList Lcom/android/u/weibo/weibo/business/bean/ReplyInfoList;
L1:
aload 0
getfield com/android/u/weibo/weibo/ui/activity/CommentListActivity$ServerCallback$8/this$1 Lcom/android/u/weibo/weibo/ui/activity/CommentListActivity$ServerCallback;
getfield com/android/u/weibo/weibo/ui/activity/CommentListActivity$ServerCallback/this$0 Lcom/android/u/weibo/weibo/ui/activity/CommentListActivity;
invokestatic com/android/u/weibo/weibo/ui/activity/CommentListActivity/access$300(Lcom/android/u/weibo/weibo/ui/activity/CommentListActivity;)Lcom/android/u/weibo/weibo/ui/adapter/ThreeTypeAdapter;
invokevirtual com/android/u/weibo/weibo/ui/adapter/ThreeTypeAdapter/notifyDataSetChanged()V
aload 0
getfield com/android/u/weibo/weibo/ui/activity/CommentListActivity$ServerCallback$8/this$1 Lcom/android/u/weibo/weibo/ui/activity/CommentListActivity$ServerCallback;
getfield com/android/u/weibo/weibo/ui/activity/CommentListActivity$ServerCallback/this$0 Lcom/android/u/weibo/weibo/ui/activity/CommentListActivity;
invokestatic com/android/u/weibo/weibo/ui/activity/CommentListActivity/access$300(Lcom/android/u/weibo/weibo/ui/activity/CommentListActivity;)Lcom/android/u/weibo/weibo/ui/adapter/ThreeTypeAdapter;
invokevirtual com/android/u/weibo/weibo/ui/adapter/ThreeTypeAdapter/stopProgress()V
return
L0:
aload 0
getfield com/android/u/weibo/weibo/ui/activity/CommentListActivity$ServerCallback$8/this$1 Lcom/android/u/weibo/weibo/ui/activity/CommentListActivity$ServerCallback;
getfield com/android/u/weibo/weibo/ui/activity/CommentListActivity$ServerCallback/this$0 Lcom/android/u/weibo/weibo/ui/activity/CommentListActivity;
invokestatic com/android/u/weibo/weibo/ui/activity/CommentListActivity/access$300(Lcom/android/u/weibo/weibo/ui/activity/CommentListActivity;)Lcom/android/u/weibo/weibo/ui/adapter/ThreeTypeAdapter;
getfield com/android/u/weibo/weibo/ui/adapter/ThreeTypeAdapter/mType Lcom/android/u/weibo/weibo/ui/adapter/ThreeTypeAdapter$ListViewDataType;
getstatic com/android/u/weibo/weibo/ui/adapter/ThreeTypeAdapter$ListViewDataType/RETWEET Lcom/android/u/weibo/weibo/ui/adapter/ThreeTypeAdapter$ListViewDataType;
if_acmpne L2
aload 0
getfield com/android/u/weibo/weibo/ui/activity/CommentListActivity$ServerCallback$8/this$1 Lcom/android/u/weibo/weibo/ui/activity/CommentListActivity$ServerCallback;
getfield com/android/u/weibo/weibo/ui/activity/CommentListActivity$ServerCallback/this$0 Lcom/android/u/weibo/weibo/ui/activity/CommentListActivity;
invokestatic com/android/u/weibo/weibo/ui/activity/CommentListActivity/access$300(Lcom/android/u/weibo/weibo/ui/activity/CommentListActivity;)Lcom/android/u/weibo/weibo/ui/adapter/ThreeTypeAdapter;
aconst_null
putfield com/android/u/weibo/weibo/ui/adapter/ThreeTypeAdapter/mRetweetList Lcom/android/u/weibo/weibo/business/bean/TopicInfoList;
goto L1
L2:
aload 0
getfield com/android/u/weibo/weibo/ui/activity/CommentListActivity$ServerCallback$8/this$1 Lcom/android/u/weibo/weibo/ui/activity/CommentListActivity$ServerCallback;
getfield com/android/u/weibo/weibo/ui/activity/CommentListActivity$ServerCallback/this$0 Lcom/android/u/weibo/weibo/ui/activity/CommentListActivity;
invokestatic com/android/u/weibo/weibo/ui/activity/CommentListActivity/access$300(Lcom/android/u/weibo/weibo/ui/activity/CommentListActivity;)Lcom/android/u/weibo/weibo/ui/adapter/ThreeTypeAdapter;
getfield com/android/u/weibo/weibo/ui/adapter/ThreeTypeAdapter/mType Lcom/android/u/weibo/weibo/ui/adapter/ThreeTypeAdapter$ListViewDataType;
getstatic com/android/u/weibo/weibo/ui/adapter/ThreeTypeAdapter$ListViewDataType/LIKE Lcom/android/u/weibo/weibo/ui/adapter/ThreeTypeAdapter$ListViewDataType;
if_acmpne L1
aload 0
getfield com/android/u/weibo/weibo/ui/activity/CommentListActivity$ServerCallback$8/this$1 Lcom/android/u/weibo/weibo/ui/activity/CommentListActivity$ServerCallback;
getfield com/android/u/weibo/weibo/ui/activity/CommentListActivity$ServerCallback/this$0 Lcom/android/u/weibo/weibo/ui/activity/CommentListActivity;
invokestatic com/android/u/weibo/weibo/ui/activity/CommentListActivity/access$300(Lcom/android/u/weibo/weibo/ui/activity/CommentListActivity;)Lcom/android/u/weibo/weibo/ui/adapter/ThreeTypeAdapter;
aconst_null
putfield com/android/u/weibo/weibo/ui/adapter/ThreeTypeAdapter/mUserList Lcom/android/u/weibo/weibo/business/bean/PraisorList;
goto L1
.limit locals 1
.limit stack 2
.end method
