.bytecode 50.0
.class synchronized com/android/u/weibo/weibo/ui/activity/CommentListActivity$6
.super android/content/BroadcastReceiver
.enclosing method com/android/u/weibo/weibo/ui/activity/CommentListActivity
.inner class inner com/android/u/weibo/weibo/ui/activity/CommentListActivity$6

.field final synthetic 'this$0' Lcom/android/u/weibo/weibo/ui/activity/CommentListActivity;

.method <init>(Lcom/android/u/weibo/weibo/ui/activity/CommentListActivity;)V
aload 0
aload 1
putfield com/android/u/weibo/weibo/ui/activity/CommentListActivity$6/this$0 Lcom/android/u/weibo/weibo/ui/activity/CommentListActivity;
aload 0
invokespecial android/content/BroadcastReceiver/<init>()V
return
.limit locals 2
.limit stack 2
.end method

.method public onReceive(Landroid/content/Context;Landroid/content/Intent;)V
.catch org/json/JSONException from L0 to L1 using L2
aload 2
ldc "retweet"
invokevirtual android/content/Intent/getStringExtra(Ljava/lang/String;)Ljava/lang/String;
astore 2
aload 2
invokestatic android/text/TextUtils/isEmpty(Ljava/lang/CharSequence;)Z
ifeq L3
L4:
return
L3:
aconst_null
astore 1
L0:
new com/android/u/weibo/weibo/business/parser/TopicInfoParser
dup
invokespecial com/android/u/weibo/weibo/business/parser/TopicInfoParser/<init>()V
new org/json/JSONObject
dup
aload 2
invokespecial org/json/JSONObject/<init>(Ljava/lang/String;)V
invokevirtual com/android/u/weibo/weibo/business/parser/TopicInfoParser/parse(Lorg/json/JSONObject;)Lcom/android/u/weibo/weibo/business/bean/TopicInfo;
astore 2
L1:
aload 2
astore 1
L5:
aload 1
ifnull L4
aload 1
iconst_0
invokestatic com/android/u/weibo/weibo/utils/ConvertTweetListUtils/convertTopic(Lcom/android/u/weibo/weibo/business/bean/TopicInfo;Z)V
aload 0
getfield com/android/u/weibo/weibo/ui/activity/CommentListActivity$6/this$0 Lcom/android/u/weibo/weibo/ui/activity/CommentListActivity;
invokestatic com/android/u/weibo/weibo/ui/activity/CommentListActivity/access$300(Lcom/android/u/weibo/weibo/ui/activity/CommentListActivity;)Lcom/android/u/weibo/weibo/ui/adapter/ThreeTypeAdapter;
aload 1
invokevirtual com/android/u/weibo/weibo/ui/adapter/ThreeTypeAdapter/updateRetweet(Lcom/android/u/weibo/weibo/business/bean/TopicInfo;)Z
ifeq L6
aload 0
getfield com/android/u/weibo/weibo/ui/activity/CommentListActivity$6/this$0 Lcom/android/u/weibo/weibo/ui/activity/CommentListActivity;
invokestatic com/android/u/weibo/weibo/ui/activity/CommentListActivity/access$100(Lcom/android/u/weibo/weibo/ui/activity/CommentListActivity;)Lcom/android/u/weibo/weibo/business/bean/TopicInfo;
astore 1
aload 1
aload 1
getfield com/android/u/weibo/weibo/business/bean/TopicInfo/forwards I
iconst_1
iadd
putfield com/android/u/weibo/weibo/business/bean/TopicInfo/forwards I
aload 0
getfield com/android/u/weibo/weibo/ui/activity/CommentListActivity$6/this$0 Lcom/android/u/weibo/weibo/ui/activity/CommentListActivity;
invokevirtual com/android/u/weibo/weibo/ui/activity/CommentListActivity/refreshCommentHeaderCount()V
L6:
aload 0
getfield com/android/u/weibo/weibo/ui/activity/CommentListActivity$6/this$0 Lcom/android/u/weibo/weibo/ui/activity/CommentListActivity;
invokestatic com/android/u/weibo/weibo/ui/activity/CommentListActivity/access$300(Lcom/android/u/weibo/weibo/ui/activity/CommentListActivity;)Lcom/android/u/weibo/weibo/ui/adapter/ThreeTypeAdapter;
getfield com/android/u/weibo/weibo/ui/adapter/ThreeTypeAdapter/mType Lcom/android/u/weibo/weibo/ui/adapter/ThreeTypeAdapter$ListViewDataType;
getstatic com/android/u/weibo/weibo/ui/adapter/ThreeTypeAdapter$ListViewDataType/RETWEET Lcom/android/u/weibo/weibo/ui/adapter/ThreeTypeAdapter$ListViewDataType;
if_acmpne L4
aload 0
getfield com/android/u/weibo/weibo/ui/activity/CommentListActivity$6/this$0 Lcom/android/u/weibo/weibo/ui/activity/CommentListActivity;
invokestatic com/android/u/weibo/weibo/ui/activity/CommentListActivity/access$300(Lcom/android/u/weibo/weibo/ui/activity/CommentListActivity;)Lcom/android/u/weibo/weibo/ui/adapter/ThreeTypeAdapter;
invokevirtual com/android/u/weibo/weibo/ui/adapter/ThreeTypeAdapter/notifyDataSetChanged()V
return
L2:
astore 2
aload 2
invokevirtual org/json/JSONException/printStackTrace()V
goto L5
.limit locals 3
.limit stack 4
.end method
