.bytecode 50.0
.class synchronized com/android/u/weibo/weibo/ui/activity/HashtagsListActivity$4
.super android/content/BroadcastReceiver
.enclosing method com/android/u/weibo/weibo/ui/activity/HashtagsListActivity
.inner class inner com/android/u/weibo/weibo/ui/activity/HashtagsListActivity$4

.field final synthetic 'this$0' Lcom/android/u/weibo/weibo/ui/activity/HashtagsListActivity;

.method <init>(Lcom/android/u/weibo/weibo/ui/activity/HashtagsListActivity;)V
aload 0
aload 1
putfield com/android/u/weibo/weibo/ui/activity/HashtagsListActivity$4/this$0 Lcom/android/u/weibo/weibo/ui/activity/HashtagsListActivity;
aload 0
invokespecial android/content/BroadcastReceiver/<init>()V
return
.limit locals 2
.limit stack 2
.end method

.method public onReceive(Landroid/content/Context;Landroid/content/Intent;)V
aload 2
invokevirtual android/content/Intent/getAction()Ljava/lang/String;
astore 1
ldc "like-event"
aload 1
invokevirtual java/lang/String/equals(Ljava/lang/Object;)Z
ifeq L0
aload 2
ldc "afterDelete2Refresh"
iconst_0
invokevirtual android/content/Intent/getBooleanExtra(Ljava/lang/String;Z)Z
ifeq L1
aload 0
getfield com/android/u/weibo/weibo/ui/activity/HashtagsListActivity$4/this$0 Lcom/android/u/weibo/weibo/ui/activity/HashtagsListActivity;
invokestatic com/android/u/weibo/weibo/ui/activity/HashtagsListActivity/access$500(Lcom/android/u/weibo/weibo/ui/activity/HashtagsListActivity;)Lcom/handmark/pulltorefresh/library/PullToRefreshListView;
iconst_0
invokevirtual com/handmark/pulltorefresh/library/PullToRefreshListView/setRefreshing(Z)V
L2:
return
L1:
aload 2
ldc "id"
lconst_0
invokevirtual android/content/Intent/getLongExtra(Ljava/lang/String;J)J
lstore 3
aload 2
ldc "like"
iconst_0
invokevirtual android/content/Intent/getBooleanExtra(Ljava/lang/String;Z)Z
istore 5
aload 0
getfield com/android/u/weibo/weibo/ui/activity/HashtagsListActivity$4/this$0 Lcom/android/u/weibo/weibo/ui/activity/HashtagsListActivity;
invokestatic com/android/u/weibo/weibo/ui/activity/HashtagsListActivity/access$100(Lcom/android/u/weibo/weibo/ui/activity/HashtagsListActivity;)Lcom/android/u/weibo/weibo/ui/adapter/TweetListAdapterBase;
lload 3
iload 5
invokevirtual com/android/u/weibo/weibo/ui/adapter/TweetListAdapterBase/setLike(JZ)V
aload 0
getfield com/android/u/weibo/weibo/ui/activity/HashtagsListActivity$4/this$0 Lcom/android/u/weibo/weibo/ui/activity/HashtagsListActivity;
invokestatic com/android/u/weibo/weibo/ui/activity/HashtagsListActivity/access$100(Lcom/android/u/weibo/weibo/ui/activity/HashtagsListActivity;)Lcom/android/u/weibo/weibo/ui/adapter/TweetListAdapterBase;
invokevirtual com/android/u/weibo/weibo/ui/adapter/TweetListAdapterBase/notifyDataSetChanged()V
return
L0:
ldc "refresh_data"
aload 1
invokevirtual java/lang/String/equals(Ljava/lang/Object;)Z
ifeq L2
aload 2
aload 0
getfield com/android/u/weibo/weibo/ui/activity/HashtagsListActivity$4/this$0 Lcom/android/u/weibo/weibo/ui/activity/HashtagsListActivity;
invokestatic com/android/u/weibo/weibo/ui/activity/HashtagsListActivity/access$100(Lcom/android/u/weibo/weibo/ui/activity/HashtagsListActivity;)Lcom/android/u/weibo/weibo/ui/adapter/TweetListAdapterBase;
invokestatic com/android/u/weibo/weibo/utils/WeiboUtil/recvRefreshDataBroadCast(Landroid/content/Intent;Lcom/android/u/weibo/weibo/ui/adapter/TweetListAdapterBase;)V
return
.limit locals 6
.limit stack 4
.end method
