.bytecode 50.0
.class synchronized com/android/u/weibo/weibo/ui/activity/TweetListActivity$1
.super android/content/BroadcastReceiver
.enclosing method com/android/u/weibo/weibo/ui/activity/TweetListActivity
.inner class inner com/android/u/weibo/weibo/ui/activity/TweetListActivity$1

.field final synthetic 'this$0' Lcom/android/u/weibo/weibo/ui/activity/TweetListActivity;

.method <init>(Lcom/android/u/weibo/weibo/ui/activity/TweetListActivity;)V
aload 0
aload 1
putfield com/android/u/weibo/weibo/ui/activity/TweetListActivity$1/this$0 Lcom/android/u/weibo/weibo/ui/activity/TweetListActivity;
aload 0
invokespecial android/content/BroadcastReceiver/<init>()V
return
.limit locals 2
.limit stack 2
.end method

.method public onReceive(Landroid/content/Context;Landroid/content/Intent;)V
aload 2
ldc "code"
iconst_0
invokevirtual android/content/Intent/getIntExtra(Ljava/lang/String;I)I
tableswitch 1006
L0
default : L1
L1:
return
L0:
aload 2
ldc "oapuid"
lconst_0
invokevirtual android/content/Intent/getLongExtra(Ljava/lang/String;J)J
getstatic com/product/android/business/ApplicationVariable/INSTANCE Lcom/product/android/business/ApplicationVariable;
invokevirtual com/product/android/business/ApplicationVariable/getIUser()Lcom/product/android/business/login/IGetUserInfo;
invokeinterface com/product/android/business/login/IGetUserInfo/getOapUid()J 0
lcmp
ifne L1
getstatic com/product/android/business/ApplicationVariable/INSTANCE Lcom/product/android/business/ApplicationVariable;
invokevirtual com/product/android/business/ApplicationVariable/getIUser()Lcom/product/android/business/login/IGetUserInfo;
invokeinterface com/product/android/business/login/IGetUserInfo/getOapUid()J 0
getstatic com/product/android/business/ApplicationVariable/INSTANCE Lcom/product/android/business/ApplicationVariable;
invokevirtual com/product/android/business/ApplicationVariable/getIUser()Lcom/product/android/business/login/IGetUserInfo;
invokeinterface com/product/android/business/login/IGetUserInfo/getBindUser()Lcom/product/android/business/login/BindUser; 0
invokevirtual com/product/android/business/login/BindUser/getSysavatar()I
aload 0
getfield com/android/u/weibo/weibo/ui/activity/TweetListActivity$1/this$0 Lcom/android/u/weibo/weibo/ui/activity/TweetListActivity;
invokestatic com/android/u/weibo/weibo/ui/activity/TweetListActivity/access$900(Lcom/android/u/weibo/weibo/ui/activity/TweetListActivity;)Landroid/widget/ImageView;
invokestatic com/product/android/business/headImage/HeadImageLoader/displayImage(JILandroid/widget/ImageView;)V
return
.limit locals 3
.limit stack 4
.end method
