.bytecode 50.0
.class synchronized com/android/u/weibo/weibo/ui/activity/TweetProfileActivity$8
.super android/content/BroadcastReceiver
.enclosing method com/android/u/weibo/weibo/ui/activity/TweetProfileActivity
.inner class inner com/android/u/weibo/weibo/ui/activity/TweetProfileActivity$8

.field final synthetic 'this$0' Lcom/android/u/weibo/weibo/ui/activity/TweetProfileActivity;

.method <init>(Lcom/android/u/weibo/weibo/ui/activity/TweetProfileActivity;)V
aload 0
aload 1
putfield com/android/u/weibo/weibo/ui/activity/TweetProfileActivity$8/this$0 Lcom/android/u/weibo/weibo/ui/activity/TweetProfileActivity;
aload 0
invokespecial android/content/BroadcastReceiver/<init>()V
return
.limit locals 2
.limit stack 2
.end method

.method public onReceive(Landroid/content/Context;Landroid/content/Intent;)V
aload 2
ldc "afterDelete2Refresh"
iconst_0
invokevirtual android/content/Intent/getBooleanExtra(Ljava/lang/String;Z)Z
ifeq L0
aload 0
getfield com/android/u/weibo/weibo/ui/activity/TweetProfileActivity$8/this$0 Lcom/android/u/weibo/weibo/ui/activity/TweetProfileActivity;
invokestatic com/android/u/weibo/weibo/ui/activity/TweetProfileActivity/access$800(Lcom/android/u/weibo/weibo/ui/activity/TweetProfileActivity;)Lcom/android/u/weibo/weibo/ui/adapter/TweetListAdapter;
invokevirtual com/android/u/weibo/weibo/ui/adapter/TweetListAdapter/getData()Lcom/android/u/weibo/weibo/business/bean/TopicInfoList;
astore 1
aload 1
ifnull L1
aload 1
aload 2
ldc "deleteTweetId"
lconst_0
invokevirtual android/content/Intent/getLongExtra(Ljava/lang/String;J)J
invokevirtual com/android/u/weibo/weibo/business/bean/TopicInfoList/removeItemByID(J)V
aload 0
getfield com/android/u/weibo/weibo/ui/activity/TweetProfileActivity$8/this$0 Lcom/android/u/weibo/weibo/ui/activity/TweetProfileActivity;
invokestatic com/android/u/weibo/weibo/ui/activity/TweetProfileActivity/access$800(Lcom/android/u/weibo/weibo/ui/activity/TweetProfileActivity;)Lcom/android/u/weibo/weibo/ui/adapter/TweetListAdapter;
invokevirtual com/android/u/weibo/weibo/ui/adapter/TweetListAdapter/notifyDataSetChanged()V
L1:
aload 0
getfield com/android/u/weibo/weibo/ui/activity/TweetProfileActivity$8/this$0 Lcom/android/u/weibo/weibo/ui/activity/TweetProfileActivity;
invokestatic com/android/u/weibo/weibo/ui/activity/TweetProfileActivity/access$800(Lcom/android/u/weibo/weibo/ui/activity/TweetProfileActivity;)Lcom/android/u/weibo/weibo/ui/adapter/TweetListAdapter;
invokevirtual com/android/u/weibo/weibo/ui/adapter/TweetListAdapter/getData()Lcom/android/u/weibo/weibo/business/bean/TopicInfoList;
ifnull L2
aload 0
getfield com/android/u/weibo/weibo/ui/activity/TweetProfileActivity$8/this$0 Lcom/android/u/weibo/weibo/ui/activity/TweetProfileActivity;
invokestatic com/android/u/weibo/weibo/ui/activity/TweetProfileActivity/access$800(Lcom/android/u/weibo/weibo/ui/activity/TweetProfileActivity;)Lcom/android/u/weibo/weibo/ui/adapter/TweetListAdapter;
invokevirtual com/android/u/weibo/weibo/ui/adapter/TweetListAdapter/getData()Lcom/android/u/weibo/weibo/business/bean/TopicInfoList;
invokevirtual com/android/u/weibo/weibo/business/bean/TopicInfoList/isEmpty()Z
ifeq L3
L2:
aload 0
getfield com/android/u/weibo/weibo/ui/activity/TweetProfileActivity$8/this$0 Lcom/android/u/weibo/weibo/ui/activity/TweetProfileActivity;
iconst_1
invokestatic com/android/u/weibo/weibo/ui/activity/TweetProfileActivity/access$2200(Lcom/android/u/weibo/weibo/ui/activity/TweetProfileActivity;Z)V
return
L0:
aload 2
ldc "id"
lconst_0
invokevirtual android/content/Intent/getLongExtra(Ljava/lang/String;J)J
lstore 3
aload 2
ldc "like"
iconst_0
invokevirtual android/content/Intent/getBooleanExtra(Ljava/lang/String;Z)Z
istore 5
aload 0
getfield com/android/u/weibo/weibo/ui/activity/TweetProfileActivity$8/this$0 Lcom/android/u/weibo/weibo/ui/activity/TweetProfileActivity;
invokestatic com/android/u/weibo/weibo/ui/activity/TweetProfileActivity/access$800(Lcom/android/u/weibo/weibo/ui/activity/TweetProfileActivity;)Lcom/android/u/weibo/weibo/ui/adapter/TweetListAdapter;
lload 3
iload 5
invokevirtual com/android/u/weibo/weibo/ui/adapter/TweetListAdapter/setLike(JZ)V
aload 0
getfield com/android/u/weibo/weibo/ui/activity/TweetProfileActivity$8/this$0 Lcom/android/u/weibo/weibo/ui/activity/TweetProfileActivity;
invokestatic com/android/u/weibo/weibo/ui/activity/TweetProfileActivity/access$800(Lcom/android/u/weibo/weibo/ui/activity/TweetProfileActivity;)Lcom/android/u/weibo/weibo/ui/adapter/TweetListAdapter;
invokevirtual com/android/u/weibo/weibo/ui/adapter/TweetListAdapter/notifyDataSetChanged()V
goto L1
L3:
aload 0
getfield com/android/u/weibo/weibo/ui/activity/TweetProfileActivity$8/this$0 Lcom/android/u/weibo/weibo/ui/activity/TweetProfileActivity;
iconst_0
invokestatic com/android/u/weibo/weibo/ui/activity/TweetProfileActivity/access$2200(Lcom/android/u/weibo/weibo/ui/activity/TweetProfileActivity;Z)V
return
.limit locals 6
.limit stack 5
.end method
