.bytecode 50.0
.class synchronized com/android/u/weibo/weibo/ui/activity/TweetProfileActivity$9
.super android/content/BroadcastReceiver
.enclosing method com/android/u/weibo/weibo/ui/activity/TweetProfileActivity
.inner class inner com/android/u/weibo/weibo/ui/activity/TweetProfileActivity$9

.field final synthetic 'this$0' Lcom/android/u/weibo/weibo/ui/activity/TweetProfileActivity;

.method <init>(Lcom/android/u/weibo/weibo/ui/activity/TweetProfileActivity;)V
aload 0
aload 1
putfield com/android/u/weibo/weibo/ui/activity/TweetProfileActivity$9/this$0 Lcom/android/u/weibo/weibo/ui/activity/TweetProfileActivity;
aload 0
invokespecial android/content/BroadcastReceiver/<init>()V
return
.limit locals 2
.limit stack 2
.end method

.method public onReceive(Landroid/content/Context;Landroid/content/Intent;)V
aload 2
ldc "code"
iconst_0
invokevirtual android/content/Intent/getIntExtra(Ljava/lang/String;I)I
tableswitch 1000
L0
L1
L2
L3
L4
L5
L6
default : L7
L7:
return
L0:
aload 0
getfield com/android/u/weibo/weibo/ui/activity/TweetProfileActivity$9/this$0 Lcom/android/u/weibo/weibo/ui/activity/TweetProfileActivity;
invokestatic com/android/u/weibo/weibo/ui/activity/TweetProfileActivity/access$2300(Lcom/android/u/weibo/weibo/ui/activity/TweetProfileActivity;)I
iconst_1
if_icmpeq L7
aconst_null
astore 1
aconst_null
astore 5
aconst_null
astore 3
aconst_null
astore 4
aload 2
ldc "headUri"
invokevirtual android/content/Intent/hasExtra(Ljava/lang/String;)Z
ifeq L8
aload 2
ldc "headUri"
invokevirtual android/content/Intent/getParcelableExtra(Ljava/lang/String;)Landroid/os/Parcelable;
checkcast android/net/Uri
astore 1
new java/io/File
dup
aload 0
getfield com/android/u/weibo/weibo/ui/activity/TweetProfileActivity$9/this$0 Lcom/android/u/weibo/weibo/ui/activity/TweetProfileActivity;
aload 1
invokestatic com/common/android/utils/ImageUtils/getImgLocalPathByUri(Landroid/content/Context;Landroid/net/Uri;)Ljava/lang/String;
invokespecial java/io/File/<init>(Ljava/lang/String;)V
astore 3
L8:
aload 2
ldc "showUriStr"
invokevirtual android/content/Intent/hasExtra(Ljava/lang/String;)Z
ifeq L9
aload 2
ldc "showUriStr"
invokevirtual android/content/Intent/getParcelableExtra(Ljava/lang/String;)Landroid/os/Parcelable;
checkcast android/net/Uri
astore 5
new java/io/File
dup
aload 0
getfield com/android/u/weibo/weibo/ui/activity/TweetProfileActivity$9/this$0 Lcom/android/u/weibo/weibo/ui/activity/TweetProfileActivity;
aload 5
invokestatic com/common/android/utils/ImageUtils/getImgLocalPathByUri(Landroid/content/Context;Landroid/net/Uri;)Ljava/lang/String;
invokespecial java/io/File/<init>(Ljava/lang/String;)V
astore 4
L9:
aload 0
getfield com/android/u/weibo/weibo/ui/activity/TweetProfileActivity$9/this$0 Lcom/android/u/weibo/weibo/ui/activity/TweetProfileActivity;
invokestatic com/android/u/weibo/weibo/ui/activity/TweetProfileActivity/access$1200(Lcom/android/u/weibo/weibo/ui/activity/TweetProfileActivity;)Lcom/android/u/weibo/weibo/ui/activity/TweetProfileActivity$HeaderViewHolder;
getfield com/android/u/weibo/weibo/ui/activity/TweetProfileActivity$HeaderViewHolder/pbarAvatar Landroid/widget/ProgressBar;
iconst_0
invokevirtual android/widget/ProgressBar/setVisibility(I)V
new com/android/u/weibo/cropimage/business/UpdateImage
dup
aload 0
getfield com/android/u/weibo/weibo/ui/activity/TweetProfileActivity$9/this$0 Lcom/android/u/weibo/weibo/ui/activity/TweetProfileActivity;
aload 1
aload 5
aload 0
getfield com/android/u/weibo/weibo/ui/activity/TweetProfileActivity$9/this$0 Lcom/android/u/weibo/weibo/ui/activity/TweetProfileActivity;
invokestatic com/android/u/weibo/weibo/ui/activity/TweetProfileActivity/access$2400(Lcom/android/u/weibo/weibo/ui/activity/TweetProfileActivity;)Landroid/os/Handler;
invokespecial com/android/u/weibo/cropimage/business/UpdateImage/<init>(Landroid/app/Activity;Landroid/net/Uri;Landroid/net/Uri;Landroid/os/Handler;)V
invokevirtual com/android/u/weibo/cropimage/business/UpdateImage/update()V
aload 3
ifnull L10
aload 3
invokevirtual java/io/File/exists()Z
ifeq L10
aload 3
invokevirtual java/io/File/delete()Z
pop
L10:
aload 4
ifnull L7
aload 4
invokevirtual java/io/File/exists()Z
ifeq L7
aload 4
invokevirtual java/io/File/delete()Z
pop
return
L1:
aload 0
getfield com/android/u/weibo/weibo/ui/activity/TweetProfileActivity$9/this$0 Lcom/android/u/weibo/weibo/ui/activity/TweetProfileActivity;
invokestatic com/android/u/weibo/weibo/ui/activity/TweetProfileActivity/access$2300(Lcom/android/u/weibo/weibo/ui/activity/TweetProfileActivity;)I
iconst_1
if_icmpeq L7
aload 2
ldc "taglist"
invokevirtual android/content/Intent/getSerializableExtra(Ljava/lang/String;)Ljava/io/Serializable;
checkcast java/util/ArrayList
astore 1
aload 0
getfield com/android/u/weibo/weibo/ui/activity/TweetProfileActivity$9/this$0 Lcom/android/u/weibo/weibo/ui/activity/TweetProfileActivity;
invokestatic com/android/u/weibo/weibo/ui/activity/TweetProfileActivity/access$2500(Lcom/android/u/weibo/weibo/ui/activity/TweetProfileActivity;)Lcom/android/u/weibo/weibo/ui/fragment/HomePageTabFragment;
ifnull L7
aload 0
getfield com/android/u/weibo/weibo/ui/activity/TweetProfileActivity$9/this$0 Lcom/android/u/weibo/weibo/ui/activity/TweetProfileActivity;
invokestatic com/android/u/weibo/weibo/ui/activity/TweetProfileActivity/access$2500(Lcom/android/u/weibo/weibo/ui/activity/TweetProfileActivity;)Lcom/android/u/weibo/weibo/ui/fragment/HomePageTabFragment;
aload 1
invokevirtual com/android/u/weibo/weibo/ui/fragment/HomePageTabFragment/updateTagList(Ljava/util/ArrayList;)V
return
L2:
aload 0
getfield com/android/u/weibo/weibo/ui/activity/TweetProfileActivity$9/this$0 Lcom/android/u/weibo/weibo/ui/activity/TweetProfileActivity;
invokestatic com/android/u/weibo/weibo/ui/activity/TweetProfileActivity/access$2300(Lcom/android/u/weibo/weibo/ui/activity/TweetProfileActivity;)I
iconst_1
if_icmpeq L7
aload 2
ldc "albumlist"
invokevirtual android/content/Intent/getSerializableExtra(Ljava/lang/String;)Ljava/io/Serializable;
checkcast java/util/ArrayList
astore 1
aload 0
getfield com/android/u/weibo/weibo/ui/activity/TweetProfileActivity$9/this$0 Lcom/android/u/weibo/weibo/ui/activity/TweetProfileActivity;
invokestatic com/android/u/weibo/weibo/ui/activity/TweetProfileActivity/access$2500(Lcom/android/u/weibo/weibo/ui/activity/TweetProfileActivity;)Lcom/android/u/weibo/weibo/ui/fragment/HomePageTabFragment;
ifnull L7
aload 0
getfield com/android/u/weibo/weibo/ui/activity/TweetProfileActivity$9/this$0 Lcom/android/u/weibo/weibo/ui/activity/TweetProfileActivity;
invokestatic com/android/u/weibo/weibo/ui/activity/TweetProfileActivity/access$2500(Lcom/android/u/weibo/weibo/ui/activity/TweetProfileActivity;)Lcom/android/u/weibo/weibo/ui/fragment/HomePageTabFragment;
aload 1
invokevirtual com/android/u/weibo/weibo/ui/fragment/HomePageTabFragment/updateImageList(Ljava/util/ArrayList;)V
return
L3:
aload 2
ldc "blacklist"
invokevirtual android/content/Intent/getSerializableExtra(Ljava/lang/String;)Ljava/io/Serializable;
checkcast java/util/ArrayList
astore 1
aload 0
getfield com/android/u/weibo/weibo/ui/activity/TweetProfileActivity$9/this$0 Lcom/android/u/weibo/weibo/ui/activity/TweetProfileActivity;
invokestatic com/android/u/weibo/weibo/ui/activity/TweetProfileActivity/access$2500(Lcom/android/u/weibo/weibo/ui/activity/TweetProfileActivity;)Lcom/android/u/weibo/weibo/ui/fragment/HomePageTabFragment;
ifnull L7
aload 0
getfield com/android/u/weibo/weibo/ui/activity/TweetProfileActivity$9/this$0 Lcom/android/u/weibo/weibo/ui/activity/TweetProfileActivity;
invokestatic com/android/u/weibo/weibo/ui/activity/TweetProfileActivity/access$2500(Lcom/android/u/weibo/weibo/ui/activity/TweetProfileActivity;)Lcom/android/u/weibo/weibo/ui/fragment/HomePageTabFragment;
aload 1
invokevirtual com/android/u/weibo/weibo/ui/fragment/HomePageTabFragment/updateBalckList(Ljava/util/ArrayList;)V
return
L4:
aload 0
getfield com/android/u/weibo/weibo/ui/activity/TweetProfileActivity$9/this$0 Lcom/android/u/weibo/weibo/ui/activity/TweetProfileActivity;
invokestatic com/android/u/weibo/weibo/ui/activity/TweetProfileActivity/access$2300(Lcom/android/u/weibo/weibo/ui/activity/TweetProfileActivity;)I
iconst_1
if_icmpeq L7
aload 2
ldc "binduser"
invokevirtual android/content/Intent/getSerializableExtra(Ljava/lang/String;)Ljava/io/Serializable;
checkcast com/product/android/business/login/BindUser
astore 1
aload 1
ifnull L7
aload 0
getfield com/android/u/weibo/weibo/ui/activity/TweetProfileActivity$9/this$0 Lcom/android/u/weibo/weibo/ui/activity/TweetProfileActivity;
invokestatic com/android/u/weibo/weibo/ui/activity/TweetProfileActivity/access$1200(Lcom/android/u/weibo/weibo/ui/activity/TweetProfileActivity;)Lcom/android/u/weibo/weibo/ui/activity/TweetProfileActivity$HeaderViewHolder;
getfield com/android/u/weibo/weibo/ui/activity/TweetProfileActivity$HeaderViewHolder/txtSignature Landroid/widget/TextView;
aload 1
invokevirtual com/product/android/business/login/BindUser/getSignature()Ljava/lang/String;
invokevirtual android/widget/TextView/setText(Ljava/lang/CharSequence;)V
return
L5:
aload 0
getfield com/android/u/weibo/weibo/ui/activity/TweetProfileActivity$9/this$0 Lcom/android/u/weibo/weibo/ui/activity/TweetProfileActivity;
invokestatic com/android/u/weibo/weibo/ui/activity/TweetProfileActivity/access$2300(Lcom/android/u/weibo/weibo/ui/activity/TweetProfileActivity;)I
ifeq L7
aload 2
ldc "oapuser"
invokevirtual android/content/Intent/getSerializableExtra(Ljava/lang/String;)Ljava/io/Serializable;
checkcast com/product/android/commonInterface/contact/OapUser
astore 1
aload 1
ifnull L7
aload 0
getfield com/android/u/weibo/weibo/ui/activity/TweetProfileActivity$9/this$0 Lcom/android/u/weibo/weibo/ui/activity/TweetProfileActivity;
aconst_null
aload 1
invokevirtual com/product/android/commonInterface/contact/OapUser/getAge()Ljava/lang/String;
aload 1
invokevirtual com/product/android/commonInterface/contact/OapUser/getGender()I
invokestatic com/android/u/weibo/weibo/ui/activity/TweetProfileActivity/access$2600(Lcom/android/u/weibo/weibo/ui/activity/TweetProfileActivity;Ljava/lang/String;Ljava/lang/String;I)V
return
L6:
aload 2
ldc "oapuid"
lconst_0
invokevirtual android/content/Intent/getLongExtra(Ljava/lang/String;J)J
aload 0
getfield com/android/u/weibo/weibo/ui/activity/TweetProfileActivity$9/this$0 Lcom/android/u/weibo/weibo/ui/activity/TweetProfileActivity;
invokestatic com/android/u/weibo/weibo/ui/activity/TweetProfileActivity/access$200(Lcom/android/u/weibo/weibo/ui/activity/TweetProfileActivity;)J
lcmp
ifne L7
aload 0
getfield com/android/u/weibo/weibo/ui/activity/TweetProfileActivity$9/this$0 Lcom/android/u/weibo/weibo/ui/activity/TweetProfileActivity;
invokestatic com/android/u/weibo/weibo/ui/activity/TweetProfileActivity/access$1300(Lcom/android/u/weibo/weibo/ui/activity/TweetProfileActivity;)V
return
.limit locals 6
.limit stack 6
.end method
