.bytecode 50.0
.class synchronized com/android/u/weibo/flower/ui/dialog/SendFlowerDialog$3
.super com/common/android/utils/task/genericTask/TaskAdapter
.enclosing method com/android/u/weibo/flower/ui/dialog/SendFlowerDialog
.inner class inner com/android/u/weibo/flower/ui/dialog/SendFlowerDialog$3

.field final synthetic 'this$0' Lcom/android/u/weibo/flower/ui/dialog/SendFlowerDialog;

.method <init>(Lcom/android/u/weibo/flower/ui/dialog/SendFlowerDialog;)V
aload 0
aload 1
putfield com/android/u/weibo/flower/ui/dialog/SendFlowerDialog$3/this$0 Lcom/android/u/weibo/flower/ui/dialog/SendFlowerDialog;
aload 0
invokespecial com/common/android/utils/task/genericTask/TaskAdapter/<init>()V
return
.limit locals 2
.limit stack 2
.end method

.method public onPostExecute(Lcom/common/android/utils/task/genericTask/GenericTask;Lcom/common/android/utils/task/genericTask/TaskResult;)V
aload 0
getfield com/android/u/weibo/flower/ui/dialog/SendFlowerDialog$3/this$0 Lcom/android/u/weibo/flower/ui/dialog/SendFlowerDialog;
invokestatic com/android/u/weibo/flower/ui/dialog/SendFlowerDialog/access$200(Lcom/android/u/weibo/flower/ui/dialog/SendFlowerDialog;)Landroid/app/ProgressDialog;
ifnull L0
aload 0
getfield com/android/u/weibo/flower/ui/dialog/SendFlowerDialog$3/this$0 Lcom/android/u/weibo/flower/ui/dialog/SendFlowerDialog;
invokestatic com/android/u/weibo/flower/ui/dialog/SendFlowerDialog/access$200(Lcom/android/u/weibo/flower/ui/dialog/SendFlowerDialog;)Landroid/app/ProgressDialog;
invokevirtual android/app/ProgressDialog/dismiss()V
L0:
aload 2
getstatic com/common/android/utils/task/genericTask/TaskResult/OK Lcom/common/android/utils/task/genericTask/TaskResult;
if_acmpne L1
aload 0
getfield com/android/u/weibo/flower/ui/dialog/SendFlowerDialog$3/this$0 Lcom/android/u/weibo/flower/ui/dialog/SendFlowerDialog;
invokestatic com/android/u/weibo/flower/ui/dialog/SendFlowerDialog/access$000(Lcom/android/u/weibo/flower/ui/dialog/SendFlowerDialog;)Lcom/common/android/ui/wheel/WheelView;
iconst_0
invokevirtual com/common/android/ui/wheel/WheelView/setVisibility(I)V
aload 0
getfield com/android/u/weibo/flower/ui/dialog/SendFlowerDialog$3/this$0 Lcom/android/u/weibo/flower/ui/dialog/SendFlowerDialog;
aload 0
getfield com/android/u/weibo/flower/ui/dialog/SendFlowerDialog$3/this$0 Lcom/android/u/weibo/flower/ui/dialog/SendFlowerDialog;
invokestatic com/android/u/weibo/flower/ui/dialog/SendFlowerDialog/access$000(Lcom/android/u/weibo/flower/ui/dialog/SendFlowerDialog;)Lcom/common/android/ui/wheel/WheelView;
iconst_1
getstatic com/android/u/weibo/weibo/controller/GlobalSetting/flowerNum I
iconst_0
invokestatic com/android/u/weibo/flower/ui/dialog/SendFlowerDialog/access$300(Lcom/android/u/weibo/flower/ui/dialog/SendFlowerDialog;Lcom/common/android/ui/wheel/WheelView;IIZ)Lcom/common/android/ui/wheel/NumericWheelAdapter;
pop
aload 0
getfield com/android/u/weibo/flower/ui/dialog/SendFlowerDialog$3/this$0 Lcom/android/u/weibo/flower/ui/dialog/SendFlowerDialog;
invokestatic com/android/u/weibo/flower/ui/dialog/SendFlowerDialog/access$000(Lcom/android/u/weibo/flower/ui/dialog/SendFlowerDialog;)Lcom/common/android/ui/wheel/WheelView;
iconst_0
iconst_0
invokevirtual com/common/android/ui/wheel/WheelView/setCurrentItem(IZ)V
aload 0
getfield com/android/u/weibo/flower/ui/dialog/SendFlowerDialog$3/this$0 Lcom/android/u/weibo/flower/ui/dialog/SendFlowerDialog;
invokestatic com/android/u/weibo/flower/ui/dialog/SendFlowerDialog/access$400(Lcom/android/u/weibo/flower/ui/dialog/SendFlowerDialog;)Landroid/widget/TextView;
aload 0
getfield com/android/u/weibo/flower/ui/dialog/SendFlowerDialog$3/this$0 Lcom/android/u/weibo/flower/ui/dialog/SendFlowerDialog;
getfield com/android/u/weibo/flower/ui/dialog/SendFlowerDialog/mContext Landroid/content/Context;
getstatic com/android/u/weibo/R$string/send_flower_flower_num I
iconst_1
anewarray java/lang/Object
dup
iconst_0
getstatic com/android/u/weibo/weibo/controller/GlobalSetting/flowerNum I
invokestatic java/lang/Integer/valueOf(I)Ljava/lang/Integer;
aastore
invokevirtual android/content/Context/getString(I[Ljava/lang/Object;)Ljava/lang/String;
invokevirtual android/widget/TextView/setText(Ljava/lang/CharSequence;)V
getstatic com/android/u/weibo/weibo/controller/GlobalSetting/flowerNum I
ifgt L2
getstatic com/android/u/weibo/R$string/no_flowers I
invokestatic com/common/android/utils/ToastUtils/display(I)V
L2:
return
L1:
aload 0
getfield com/android/u/weibo/flower/ui/dialog/SendFlowerDialog$3/this$0 Lcom/android/u/weibo/flower/ui/dialog/SendFlowerDialog;
invokestatic com/android/u/weibo/flower/ui/dialog/SendFlowerDialog/access$500(Lcom/android/u/weibo/flower/ui/dialog/SendFlowerDialog;)Landroid/widget/Button;
iconst_0
invokevirtual android/widget/Button/setClickable(Z)V
aload 0
getfield com/android/u/weibo/flower/ui/dialog/SendFlowerDialog$3/this$0 Lcom/android/u/weibo/flower/ui/dialog/SendFlowerDialog;
getfield com/android/u/weibo/flower/ui/dialog/SendFlowerDialog/mContext Landroid/content/Context;
aload 0
getfield com/android/u/weibo/flower/ui/dialog/SendFlowerDialog$3/this$0 Lcom/android/u/weibo/flower/ui/dialog/SendFlowerDialog;
getfield com/android/u/weibo/flower/ui/dialog/SendFlowerDialog/mContext Landroid/content/Context;
getstatic com/android/u/weibo/R$string/option_fail I
invokevirtual android/content/Context/getString(I)Ljava/lang/String;
invokestatic com/common/android/utils/ToastUtils/displayTimeLong(Landroid/content/Context;Ljava/lang/String;)V
return
.limit locals 3
.limit stack 7
.end method

.method public onPreExecute(Lcom/common/android/utils/task/genericTask/GenericTask;)V
aload 0
getfield com/android/u/weibo/flower/ui/dialog/SendFlowerDialog$3/this$0 Lcom/android/u/weibo/flower/ui/dialog/SendFlowerDialog;
aload 0
getfield com/android/u/weibo/flower/ui/dialog/SendFlowerDialog$3/this$0 Lcom/android/u/weibo/flower/ui/dialog/SendFlowerDialog;
getfield com/android/u/weibo/flower/ui/dialog/SendFlowerDialog/mContext Landroid/content/Context;
aload 0
getfield com/android/u/weibo/flower/ui/dialog/SendFlowerDialog$3/this$0 Lcom/android/u/weibo/flower/ui/dialog/SendFlowerDialog;
getfield com/android/u/weibo/flower/ui/dialog/SendFlowerDialog/mContext Landroid/content/Context;
getstatic com/android/u/weibo/R$string/send_flower_getdata I
invokevirtual android/content/Context/getString(I)Ljava/lang/String;
aload 0
getfield com/android/u/weibo/flower/ui/dialog/SendFlowerDialog$3/this$0 Lcom/android/u/weibo/flower/ui/dialog/SendFlowerDialog;
getfield com/android/u/weibo/flower/ui/dialog/SendFlowerDialog/mContext Landroid/content/Context;
getstatic com/android/u/weibo/R$string/send_flower_getdata I
invokevirtual android/content/Context/getString(I)Ljava/lang/String;
iconst_1
invokestatic android/app/ProgressDialog/show(Landroid/content/Context;Ljava/lang/CharSequence;Ljava/lang/CharSequence;Z)Landroid/app/ProgressDialog;
invokestatic com/android/u/weibo/flower/ui/dialog/SendFlowerDialog/access$202(Lcom/android/u/weibo/flower/ui/dialog/SendFlowerDialog;Landroid/app/ProgressDialog;)Landroid/app/ProgressDialog;
pop
aload 0
getfield com/android/u/weibo/flower/ui/dialog/SendFlowerDialog$3/this$0 Lcom/android/u/weibo/flower/ui/dialog/SendFlowerDialog;
invokestatic com/android/u/weibo/flower/ui/dialog/SendFlowerDialog/access$200(Lcom/android/u/weibo/flower/ui/dialog/SendFlowerDialog;)Landroid/app/ProgressDialog;
iconst_1
invokevirtual android/app/ProgressDialog/setCancelable(Z)V
aload 0
getfield com/android/u/weibo/flower/ui/dialog/SendFlowerDialog$3/this$0 Lcom/android/u/weibo/flower/ui/dialog/SendFlowerDialog;
invokestatic com/android/u/weibo/flower/ui/dialog/SendFlowerDialog/access$200(Lcom/android/u/weibo/flower/ui/dialog/SendFlowerDialog;)Landroid/app/ProgressDialog;
invokevirtual android/app/ProgressDialog/show()V
aload 0
aload 1
invokespecial com/common/android/utils/task/genericTask/TaskAdapter/onPreExecute(Lcom/common/android/utils/task/genericTask/GenericTask;)V
return
.limit locals 2
.limit stack 5
.end method
