.bytecode 50.0
.class synchronized com/android/u/weibo/flower/ui/dialog/SendFlowerDialog$1
.super java/lang/Object
.implements android/view/View$OnClickListener
.enclosing method com/android/u/weibo/flower/ui/dialog/SendFlowerDialog
.inner class inner com/android/u/weibo/flower/ui/dialog/SendFlowerDialog$1

.field final synthetic 'this$0' Lcom/android/u/weibo/flower/ui/dialog/SendFlowerDialog;

.method <init>(Lcom/android/u/weibo/flower/ui/dialog/SendFlowerDialog;)V
aload 0
aload 1
putfield com/android/u/weibo/flower/ui/dialog/SendFlowerDialog$1/this$0 Lcom/android/u/weibo/flower/ui/dialog/SendFlowerDialog;
aload 0
invokespecial java/lang/Object/<init>()V
return
.limit locals 2
.limit stack 2
.end method

.method public onClick(Landroid/view/View;)V
aload 1
invokevirtual android/view/View/getId()I
istore 2
iload 2
getstatic com/android/u/weibo/R$id/btn_largess I
if_icmpne L0
aload 0
getfield com/android/u/weibo/flower/ui/dialog/SendFlowerDialog$1/this$0 Lcom/android/u/weibo/flower/ui/dialog/SendFlowerDialog;
getfield com/android/u/weibo/flower/ui/dialog/SendFlowerDialog/mContext Landroid/content/Context;
invokestatic com/common/android/utils/NetWorkUtils/JudgeNetWorkStatus(Landroid/content/Context;)Z
ifne L1
getstatic com/android/u/weibo/R$string/send_flower_fail_no_network I
invokestatic com/common/android/utils/ToastUtils/display(I)V
L2:
return
L1:
aload 0
getfield com/android/u/weibo/flower/ui/dialog/SendFlowerDialog$1/this$0 Lcom/android/u/weibo/flower/ui/dialog/SendFlowerDialog;
getfield com/android/u/weibo/flower/ui/dialog/SendFlowerDialog/mFromBackSys Z
ifne L3
getstatic com/android/u/weibo/weibo/controller/GlobalSetting/flowerNum I
ifle L4
L3:
aload 0
getfield com/android/u/weibo/flower/ui/dialog/SendFlowerDialog$1/this$0 Lcom/android/u/weibo/flower/ui/dialog/SendFlowerDialog;
getfield com/android/u/weibo/flower/ui/dialog/SendFlowerDialog/mFromBackSys Z
ifeq L5
aload 0
getfield com/android/u/weibo/flower/ui/dialog/SendFlowerDialog$1/this$0 Lcom/android/u/weibo/flower/ui/dialog/SendFlowerDialog;
getfield com/android/u/weibo/flower/ui/dialog/SendFlowerDialog/mFlowerNum I
ifgt L5
L4:
aload 0
getfield com/android/u/weibo/flower/ui/dialog/SendFlowerDialog$1/this$0 Lcom/android/u/weibo/flower/ui/dialog/SendFlowerDialog;
getfield com/android/u/weibo/flower/ui/dialog/SendFlowerDialog/mContext Landroid/content/Context;
aload 0
getfield com/android/u/weibo/flower/ui/dialog/SendFlowerDialog$1/this$0 Lcom/android/u/weibo/flower/ui/dialog/SendFlowerDialog;
getfield com/android/u/weibo/flower/ui/dialog/SendFlowerDialog/mContext Landroid/content/Context;
getstatic com/android/u/weibo/R$string/no_flowers I
invokevirtual android/content/Context/getString(I)Ljava/lang/String;
invokestatic com/common/android/utils/ToastUtils/displayTimeLong(Landroid/content/Context;Ljava/lang/String;)V
return
L5:
aload 0
getfield com/android/u/weibo/flower/ui/dialog/SendFlowerDialog$1/this$0 Lcom/android/u/weibo/flower/ui/dialog/SendFlowerDialog;
invokestatic com/android/u/weibo/flower/ui/dialog/SendFlowerDialog/access$000(Lcom/android/u/weibo/flower/ui/dialog/SendFlowerDialog;)Lcom/common/android/ui/wheel/WheelView;
invokevirtual com/common/android/ui/wheel/WheelView/getCurrentItem()I
istore 2
aload 0
getfield com/android/u/weibo/flower/ui/dialog/SendFlowerDialog$1/this$0 Lcom/android/u/weibo/flower/ui/dialog/SendFlowerDialog;
iload 2
iconst_1
iadd
invokevirtual com/android/u/weibo/flower/ui/dialog/SendFlowerDialog/startLargess(I)V
return
L0:
iload 2
getstatic com/android/u/weibo/R$id/btn_cancel I
if_icmpne L2
aload 0
getfield com/android/u/weibo/flower/ui/dialog/SendFlowerDialog$1/this$0 Lcom/android/u/weibo/flower/ui/dialog/SendFlowerDialog;
invokevirtual com/android/u/weibo/flower/ui/dialog/SendFlowerDialog/dismissDialogL()V
return
.limit locals 3
.limit stack 3
.end method
