.bytecode 50.0
.class public synchronized com/nd/android/u/tast/experience/adapter/MoreExperienceAdapter
.super android/widget/BaseAdapter
.inner class inner com/nd/android/u/tast/experience/adapter/MoreExperienceAdapter$1
.inner class inner com/nd/android/u/tast/experience/adapter/MoreExperienceAdapter$2
.inner class inner com/nd/android/u/tast/experience/adapter/MoreExperienceAdapter$3
.inner class inner com/nd/android/u/tast/experience/adapter/MoreExperienceAdapter$4
.inner class inner com/nd/android/u/tast/experience/adapter/MoreExperienceAdapter$5

.field private 'mActivity' Landroid/app/Activity;

.field private 'mInflater' Landroid/view/LayoutInflater;

.field private 'mList' Ljava/util/List; signature "Ljava/util/List<Lcom/nd/android/u/tast/experience/bean/MoreExperienceItem;>;"

.field private 'mRootView' Landroid/view/View;

.method public <init>(Landroid/app/Activity;Landroid/view/View;Landroid/widget/ListView;)V
aload 0
invokespecial android/widget/BaseAdapter/<init>()V
aload 0
aload 1
putfield com/nd/android/u/tast/experience/adapter/MoreExperienceAdapter/mActivity Landroid/app/Activity;
aload 0
aload 2
putfield com/nd/android/u/tast/experience/adapter/MoreExperienceAdapter/mRootView Landroid/view/View;
aload 0
aload 1
ldc "layout_inflater"
invokevirtual android/app/Activity/getSystemService(Ljava/lang/String;)Ljava/lang/Object;
checkcast android/view/LayoutInflater
putfield com/nd/android/u/tast/experience/adapter/MoreExperienceAdapter/mInflater Landroid/view/LayoutInflater;
return
.limit locals 4
.limit stack 3
.end method

.method static synthetic access$000(Lcom/nd/android/u/tast/experience/adapter/MoreExperienceAdapter;)Landroid/app/Activity;
aload 0
getfield com/nd/android/u/tast/experience/adapter/MoreExperienceAdapter/mActivity Landroid/app/Activity;
areturn
.limit locals 1
.limit stack 1
.end method

.method private getFailView(Lcom/nd/android/u/tast/experience/bean/MoreExperienceItem;)Landroid/view/View;
aload 0
getfield com/nd/android/u/tast/experience/adapter/MoreExperienceAdapter/mInflater Landroid/view/LayoutInflater;
getstatic com/nd/android/u/tasklib/R$layout/more_experience_item2 I
aconst_null
invokevirtual android/view/LayoutInflater/inflate(ILandroid/view/ViewGroup;)Landroid/view/View;
astore 2
aload 2
getstatic com/nd/android/u/tasklib/R$id/leftText I
invokevirtual android/view/View/findViewById(I)Landroid/view/View;
checkcast android/widget/TextView
aload 1
invokevirtual com/nd/android/u/tast/experience/bean/MoreExperienceItem/getItemname()Ljava/lang/String;
invokevirtual android/widget/TextView/setText(Ljava/lang/CharSequence;)V
aload 2
getstatic com/nd/android/u/tasklib/R$id/middle I
invokevirtual android/view/View/findViewById(I)Landroid/view/View;
checkcast android/widget/TextView
astore 3
aload 2
getstatic com/nd/android/u/tasklib/R$id/rightImage I
invokevirtual android/view/View/findViewById(I)Landroid/view/View;
checkcast android/widget/ImageView
getstatic com/nd/android/u/tasklib/R$drawable/more_regret I
invokevirtual android/widget/ImageView/setImageResource(I)V
aload 1
invokevirtual com/nd/android/u/tast/experience/bean/MoreExperienceItem/getmItemCode()Ljava/lang/String;
ldc "FULLSIGN"
invokevirtual java/lang/String/equals(Ljava/lang/Object;)Z
ifeq L0
aload 3
iconst_0
invokevirtual android/widget/TextView/setVisibility(I)V
aload 3
aload 1
invokevirtual com/nd/android/u/tast/experience/bean/MoreExperienceItem/getCondition()Ljava/lang/String;
invokevirtual android/widget/TextView/setText(Ljava/lang/CharSequence;)V
L0:
aload 2
areturn
.limit locals 4
.limit stack 3
.end method

.method private getFinishView(Lcom/nd/android/u/tast/experience/bean/MoreExperienceItem;)Landroid/view/View;
aload 0
getfield com/nd/android/u/tast/experience/adapter/MoreExperienceAdapter/mInflater Landroid/view/LayoutInflater;
getstatic com/nd/android/u/tasklib/R$layout/more_experience_item3 I
aconst_null
invokevirtual android/view/LayoutInflater/inflate(ILandroid/view/ViewGroup;)Landroid/view/View;
astore 2
aload 2
getstatic com/nd/android/u/tasklib/R$id/leftText I
invokevirtual android/view/View/findViewById(I)Landroid/view/View;
checkcast android/widget/TextView
aload 1
invokevirtual com/nd/android/u/tast/experience/bean/MoreExperienceItem/getItemname()Ljava/lang/String;
invokevirtual android/widget/TextView/setText(Ljava/lang/CharSequence;)V
aload 2
getstatic com/nd/android/u/tasklib/R$id/middleText I
invokevirtual android/view/View/findViewById(I)Landroid/view/View;
checkcast android/widget/TextView
astore 3
aload 2
getstatic com/nd/android/u/tasklib/R$id/middleButton I
invokevirtual android/view/View/findViewById(I)Landroid/view/View;
checkcast android/widget/Button
astore 4
aload 1
invokevirtual com/nd/android/u/tast/experience/bean/MoreExperienceItem/getmItemCode()Ljava/lang/String;
ldc "SIGNIN"
invokevirtual java/lang/String/equals(Ljava/lang/Object;)Z
ifeq L0
aload 4
iconst_0
invokevirtual android/widget/Button/setVisibility(I)V
aload 3
bipush 8
invokevirtual android/widget/TextView/setVisibility(I)V
aload 4
new com/nd/android/u/tast/experience/adapter/MoreExperienceAdapter$2
dup
aload 0
aload 1
invokespecial com/nd/android/u/tast/experience/adapter/MoreExperienceAdapter$2/<init>(Lcom/nd/android/u/tast/experience/adapter/MoreExperienceAdapter;Lcom/nd/android/u/tast/experience/bean/MoreExperienceItem;)V
invokevirtual android/widget/Button/setOnClickListener(Landroid/view/View$OnClickListener;)V
L1:
aload 2
getstatic com/nd/android/u/tasklib/R$id/rightImage I
invokevirtual android/view/View/findViewById(I)Landroid/view/View;
checkcast android/widget/ImageView
getstatic com/nd/android/u/tasklib/R$drawable/more_finished I
invokevirtual android/widget/ImageView/setImageResource(I)V
aload 2
areturn
L0:
aload 1
invokevirtual com/nd/android/u/tast/experience/bean/MoreExperienceItem/getmItemCode()Ljava/lang/String;
ldc "FLOWER"
invokevirtual java/lang/String/equals(Ljava/lang/Object;)Z
ifeq L2
aload 4
bipush 8
invokevirtual android/widget/Button/setVisibility(I)V
aload 3
bipush 8
invokevirtual android/widget/TextView/setVisibility(I)V
aload 2
new com/nd/android/u/tast/experience/adapter/MoreExperienceAdapter$3
dup
aload 0
aload 1
invokespecial com/nd/android/u/tast/experience/adapter/MoreExperienceAdapter$3/<init>(Lcom/nd/android/u/tast/experience/adapter/MoreExperienceAdapter;Lcom/nd/android/u/tast/experience/bean/MoreExperienceItem;)V
invokevirtual android/view/View/setOnClickListener(Landroid/view/View$OnClickListener;)V
goto L1
L2:
aload 1
invokevirtual com/nd/android/u/tast/experience/bean/MoreExperienceItem/getmItemCode()Ljava/lang/String;
ldc "BIRTHBLESS"
invokevirtual java/lang/String/equals(Ljava/lang/Object;)Z
ifeq L3
aload 4
bipush 8
invokevirtual android/widget/Button/setVisibility(I)V
aload 3
bipush 8
invokevirtual android/widget/TextView/setVisibility(I)V
aload 2
new com/nd/android/u/tast/experience/adapter/MoreExperienceAdapter$4
dup
aload 0
aload 1
invokespecial com/nd/android/u/tast/experience/adapter/MoreExperienceAdapter$4/<init>(Lcom/nd/android/u/tast/experience/adapter/MoreExperienceAdapter;Lcom/nd/android/u/tast/experience/bean/MoreExperienceItem;)V
invokevirtual android/view/View/setOnClickListener(Landroid/view/View$OnClickListener;)V
goto L1
L3:
aload 4
bipush 8
invokevirtual android/widget/Button/setVisibility(I)V
aload 3
iconst_0
invokevirtual android/widget/TextView/setVisibility(I)V
goto L1
.limit locals 5
.limit stack 5
.end method

.method private getNormalView(Lcom/nd/android/u/tast/experience/bean/MoreExperienceItem;)Landroid/view/View;
aload 0
getfield com/nd/android/u/tast/experience/adapter/MoreExperienceAdapter/mInflater Landroid/view/LayoutInflater;
getstatic com/nd/android/u/tasklib/R$layout/more_experience_item1 I
aconst_null
invokevirtual android/view/LayoutInflater/inflate(ILandroid/view/ViewGroup;)Landroid/view/View;
astore 2
aload 2
getstatic com/nd/android/u/tasklib/R$id/leftText I
invokevirtual android/view/View/findViewById(I)Landroid/view/View;
checkcast android/widget/TextView
astore 4
aload 2
getstatic com/nd/android/u/tasklib/R$id/middle I
invokevirtual android/view/View/findViewById(I)Landroid/view/View;
checkcast android/widget/TextView
astore 5
aload 2
getstatic com/nd/android/u/tasklib/R$id/rightText I
invokevirtual android/view/View/findViewById(I)Landroid/view/View;
checkcast android/widget/TextView
astore 3
aload 2
getstatic com/nd/android/u/tasklib/R$id/ivRight I
invokevirtual android/view/View/findViewById(I)Landroid/view/View;
checkcast android/widget/ImageView
astore 6
aload 4
aload 1
invokevirtual com/nd/android/u/tast/experience/bean/MoreExperienceItem/getItemname()Ljava/lang/String;
invokevirtual android/widget/TextView/setText(Ljava/lang/CharSequence;)V
aload 1
invokevirtual com/nd/android/u/tast/experience/bean/MoreExperienceItem/getmItemCode()Ljava/lang/String;
ldc "SCORE"
invokevirtual java/lang/String/equals(Ljava/lang/Object;)Z
ifeq L0
aload 5
bipush 8
invokevirtual android/widget/TextView/setVisibility(I)V
L1:
new java/lang/StringBuffer
dup
invokespecial java/lang/StringBuffer/<init>()V
astore 4
aload 1
invokevirtual com/nd/android/u/tast/experience/bean/MoreExperienceItem/getExp()I
ifle L2
aload 1
invokevirtual com/nd/android/u/tast/experience/bean/MoreExperienceItem/getMoney()I
ifle L2
aload 4
aload 1
invokevirtual com/nd/android/u/tast/experience/bean/MoreExperienceItem/getExp()I
invokevirtual java/lang/StringBuffer/append(I)Ljava/lang/StringBuffer;
pop
aload 4
aload 0
getfield com/nd/android/u/tast/experience/adapter/MoreExperienceAdapter/mActivity Landroid/app/Activity;
getstatic com/nd/android/u/tasklib/R$string/experience I
invokevirtual android/app/Activity/getString(I)Ljava/lang/String;
invokevirtual java/lang/StringBuffer/append(Ljava/lang/String;)Ljava/lang/StringBuffer;
pop
aload 4
ldc ","
invokevirtual java/lang/StringBuffer/append(Ljava/lang/String;)Ljava/lang/StringBuffer;
pop
aload 4
aload 1
invokevirtual com/nd/android/u/tast/experience/bean/MoreExperienceItem/getMoney()I
invokevirtual java/lang/StringBuffer/append(I)Ljava/lang/StringBuffer;
pop
aload 4
aload 0
getfield com/nd/android/u/tast/experience/adapter/MoreExperienceAdapter/mActivity Landroid/app/Activity;
getstatic com/nd/android/u/tasklib/R$string/xymoney I
invokevirtual android/app/Activity/getString(I)Ljava/lang/String;
invokevirtual java/lang/StringBuffer/append(Ljava/lang/String;)Ljava/lang/StringBuffer;
pop
L3:
aload 3
aload 4
invokevirtual java/lang/StringBuffer/toString()Ljava/lang/String;
invokevirtual android/widget/TextView/setText(Ljava/lang/CharSequence;)V
aload 2
new com/nd/android/u/tast/experience/adapter/MoreExperienceAdapter$5
dup
aload 0
aload 1
invokespecial com/nd/android/u/tast/experience/adapter/MoreExperienceAdapter$5/<init>(Lcom/nd/android/u/tast/experience/adapter/MoreExperienceAdapter;Lcom/nd/android/u/tast/experience/bean/MoreExperienceItem;)V
invokevirtual android/view/View/setOnClickListener(Landroid/view/View$OnClickListener;)V
aload 2
areturn
L0:
aload 1
invokevirtual com/nd/android/u/tast/experience/bean/MoreExperienceItem/getmItemCode()Ljava/lang/String;
ldc "VOTE_FB"
invokevirtual java/lang/String/equals(Ljava/lang/Object;)Z
ifeq L4
aload 5
bipush 8
invokevirtual android/widget/TextView/setVisibility(I)V
aload 3
bipush 8
invokevirtual android/widget/TextView/setVisibility(I)V
goto L1
L4:
aload 1
invokevirtual com/nd/android/u/tast/experience/bean/MoreExperienceItem/getmItemCode()Ljava/lang/String;
ldc "FULLSIGN"
invokevirtual java/lang/String/equals(Ljava/lang/Object;)Z
ifeq L5
aload 3
bipush 8
invokevirtual android/widget/TextView/setVisibility(I)V
aload 6
iconst_0
invokevirtual android/widget/ImageView/setVisibility(I)V
aload 5
iconst_0
invokevirtual android/widget/TextView/setVisibility(I)V
aload 5
aload 1
invokevirtual com/nd/android/u/tast/experience/bean/MoreExperienceItem/getCondition()Ljava/lang/String;
invokevirtual android/widget/TextView/setText(Ljava/lang/CharSequence;)V
aload 1
invokevirtual com/nd/android/u/tast/experience/bean/MoreExperienceItem/getStatusImg()I
ifne L6
aload 6
aload 0
getfield com/nd/android/u/tast/experience/adapter/MoreExperienceAdapter/mActivity Landroid/app/Activity;
invokevirtual android/app/Activity/getResources()Landroid/content/res/Resources;
getstatic com/nd/android/u/tasklib/R$drawable/more_full_exp I
invokevirtual android/content/res/Resources/getDrawable(I)Landroid/graphics/drawable/Drawable;
invokevirtual android/widget/ImageView/setBackgroundDrawable(Landroid/graphics/drawable/Drawable;)V
goto L1
L6:
aload 1
invokevirtual com/nd/android/u/tast/experience/bean/MoreExperienceItem/getStatusImg()I
iconst_1
if_icmpne L7
aload 6
aload 0
getfield com/nd/android/u/tast/experience/adapter/MoreExperienceAdapter/mActivity Landroid/app/Activity;
invokevirtual android/app/Activity/getResources()Landroid/content/res/Resources;
getstatic com/nd/android/u/tasklib/R$drawable/more_big_exp I
invokevirtual android/content/res/Resources/getDrawable(I)Landroid/graphics/drawable/Drawable;
invokevirtual android/widget/ImageView/setBackgroundDrawable(Landroid/graphics/drawable/Drawable;)V
goto L1
L7:
aload 1
invokevirtual com/nd/android/u/tast/experience/bean/MoreExperienceItem/getStatusImg()I
iconst_2
if_icmpne L1
aload 6
aload 0
getfield com/nd/android/u/tast/experience/adapter/MoreExperienceAdapter/mActivity Landroid/app/Activity;
invokevirtual android/app/Activity/getResources()Landroid/content/res/Resources;
getstatic com/nd/android/u/tasklib/R$drawable/more_small_exp I
invokevirtual android/content/res/Resources/getDrawable(I)Landroid/graphics/drawable/Drawable;
invokevirtual android/widget/ImageView/setBackgroundDrawable(Landroid/graphics/drawable/Drawable;)V
goto L1
L5:
aload 5
iconst_0
invokevirtual android/widget/TextView/setVisibility(I)V
aload 5
aload 1
invokevirtual com/nd/android/u/tast/experience/bean/MoreExperienceItem/getCondition()Ljava/lang/String;
invokevirtual android/widget/TextView/setText(Ljava/lang/CharSequence;)V
goto L1
L2:
aload 1
invokevirtual com/nd/android/u/tast/experience/bean/MoreExperienceItem/getMoney()I
ifle L8
aload 4
aload 1
invokevirtual com/nd/android/u/tast/experience/bean/MoreExperienceItem/getMoney()I
invokevirtual java/lang/StringBuffer/append(I)Ljava/lang/StringBuffer;
pop
aload 4
aload 0
getfield com/nd/android/u/tast/experience/adapter/MoreExperienceAdapter/mActivity Landroid/app/Activity;
getstatic com/nd/android/u/tasklib/R$string/xymoney I
invokevirtual android/app/Activity/getString(I)Ljava/lang/String;
invokevirtual java/lang/StringBuffer/append(Ljava/lang/String;)Ljava/lang/StringBuffer;
pop
goto L3
L8:
aload 4
aload 1
invokevirtual com/nd/android/u/tast/experience/bean/MoreExperienceItem/getExp()I
invokevirtual java/lang/StringBuffer/append(I)Ljava/lang/StringBuffer;
pop
aload 4
aload 0
getfield com/nd/android/u/tast/experience/adapter/MoreExperienceAdapter/mActivity Landroid/app/Activity;
getstatic com/nd/android/u/tasklib/R$string/experience I
invokevirtual android/app/Activity/getString(I)Ljava/lang/String;
invokevirtual java/lang/StringBuffer/append(Ljava/lang/String;)Ljava/lang/StringBuffer;
pop
goto L3
.limit locals 7
.limit stack 5
.end method

.method public static onClickEvent(Lcom/nd/android/u/tast/experience/bean/MoreExperienceItem;Landroid/app/Activity;)V
aload 0
invokevirtual com/nd/android/u/tast/experience/bean/MoreExperienceItem/getmItemCode()Ljava/lang/String;
ldc "SCORE"
invokevirtual java/lang/String/equals(Ljava/lang/Object;)Z
ifeq L0
aload 1
new android/content/Intent
dup
aload 1
ldc com/nd/android/u/tast/experience/activity/ReceiveExpActivity
invokespecial android/content/Intent/<init>(Landroid/content/Context;Ljava/lang/Class;)V
invokevirtual android/app/Activity/startActivity(Landroid/content/Intent;)V
L1:
return
L0:
aload 0
invokevirtual com/nd/android/u/tast/experience/bean/MoreExperienceItem/getmItemCode()Ljava/lang/String;
ldc "BIRTHBLESS"
invokevirtual java/lang/String/equals(Ljava/lang/Object;)Z
ifeq L2
aload 1
new android/content/Intent
dup
aload 1
ldc com/nd/android/u/tast/birthday/activity/BirthdayActivity
invokespecial android/content/Intent/<init>(Landroid/content/Context;Ljava/lang/Class;)V
invokevirtual android/app/Activity/startActivity(Landroid/content/Intent;)V
return
L2:
aload 0
invokevirtual com/nd/android/u/tast/experience/bean/MoreExperienceItem/getmItemCode()Ljava/lang/String;
ldc "VOTE"
invokevirtual java/lang/String/equals(Ljava/lang/Object;)Z
ifne L3
aload 0
invokevirtual com/nd/android/u/tast/experience/bean/MoreExperienceItem/getmItemCode()Ljava/lang/String;
ldc "VOTE_FB"
invokevirtual java/lang/String/equals(Ljava/lang/Object;)Z
ifeq L4
L3:
aload 0
invokevirtual com/nd/android/u/tast/experience/bean/MoreExperienceItem/getStatus()Lcom/nd/android/u/tast/experience/activity/DateWidgetActivity$MORE_EXP_STATUS;
getstatic com/nd/android/u/tast/experience/activity/DateWidgetActivity$MORE_EXP_STATUS/FINISH Lcom/nd/android/u/tast/experience/activity/DateWidgetActivity$MORE_EXP_STATUS;
if_acmpeq L1
new android/content/Intent
dup
aload 1
ldc com/nd/android/u/tast/experience/activity/TaskWebViewActivity
invokespecial android/content/Intent/<init>(Landroid/content/Context;Ljava/lang/Class;)V
astore 7
aload 7
getstatic com/nd/android/u/tast/experience/activity/TaskWebViewActivity/EXTARS_WEBVIEW_URL Ljava/lang/String;
aload 0
invokevirtual com/nd/android/u/tast/experience/bean/MoreExperienceItem/getUrl()Ljava/lang/String;
invokevirtual android/content/Intent/putExtra(Ljava/lang/String;Ljava/lang/String;)Landroid/content/Intent;
pop
aload 7
getstatic com/nd/android/u/tast/experience/activity/TaskWebViewActivity/EXTARS_WEBVIEW_NEED_TITLE Ljava/lang/String;
aload 0
invokevirtual com/nd/android/u/tast/experience/bean/MoreExperienceItem/getItemname()Ljava/lang/String;
invokevirtual android/content/Intent/putExtra(Ljava/lang/String;Ljava/lang/String;)Landroid/content/Intent;
pop
aload 7
getstatic com/nd/android/u/tast/experience/activity/TaskWebViewActivity/EXTARS_WEBVIEW_BOTTOMHIDE Ljava/lang/String;
iconst_1
invokevirtual android/content/Intent/putExtra(Ljava/lang/String;Z)Landroid/content/Intent;
pop
aload 7
getstatic com/nd/android/u/tast/experience/activity/TaskWebViewActivity/EXTARS_WEBVIEW_HASCOOKIE Ljava/lang/String;
iconst_0
invokevirtual android/content/Intent/putExtra(Ljava/lang/String;Z)Landroid/content/Intent;
pop
aload 7
getstatic com/nd/android/u/tast/experience/activity/TaskWebViewActivity/EXTARS_WEBVIEW_CHECK_OVERRIDEURL Ljava/lang/String;
iconst_1
invokevirtual android/content/Intent/putExtra(Ljava/lang/String;Z)Landroid/content/Intent;
pop
aload 7
getstatic com/nd/android/u/tast/experience/activity/TaskWebViewActivity/EXTARS_WEBVIEW_ZOOMSUPPORT Ljava/lang/String;
iconst_0
invokevirtual android/content/Intent/putExtra(Ljava/lang/String;Z)Landroid/content/Intent;
pop
aload 0
invokevirtual com/nd/android/u/tast/experience/bean/MoreExperienceItem/getmItemCode()Ljava/lang/String;
ldc "VOTE"
invokevirtual java/lang/String/equals(Ljava/lang/Object;)Z
ifeq L5
aload 7
getstatic com/nd/android/u/tast/experience/activity/TaskWebViewActivity/EXTARS_WEBVIEW_REFRESH Ljava/lang/String;
iconst_0
invokevirtual android/content/Intent/putExtra(Ljava/lang/String;Z)Landroid/content/Intent;
pop
L5:
aload 1
aload 7
invokevirtual android/app/Activity/startActivity(Landroid/content/Intent;)V
return
L4:
aload 0
invokevirtual com/nd/android/u/tast/experience/bean/MoreExperienceItem/getmItemCode()Ljava/lang/String;
ldc "SIGNIN"
invokevirtual java/lang/String/equals(Ljava/lang/Object;)Z
ifeq L6
aload 0
invokevirtual com/nd/android/u/tast/experience/bean/MoreExperienceItem/getStatus()Lcom/nd/android/u/tast/experience/activity/DateWidgetActivity$MORE_EXP_STATUS;
getstatic com/nd/android/u/tast/experience/activity/DateWidgetActivity$MORE_EXP_STATUS/NORMAL Lcom/nd/android/u/tast/experience/activity/DateWidgetActivity$MORE_EXP_STATUS;
if_acmpne L7
aload 1
new android/content/Intent
dup
aload 1
ldc com/nd/android/u/tast/experience/activity/DateWidgetActivity
invokespecial android/content/Intent/<init>(Landroid/content/Context;Ljava/lang/Class;)V
invokevirtual android/app/Activity/startActivity(Landroid/content/Intent;)V
return
L7:
new com/nd/android/u/tast/experience/calendar/SignInPopWindow
dup
aload 1
invokespecial com/nd/android/u/tast/experience/calendar/SignInPopWindow/<init>(Landroid/app/Activity;)V
astore 0
aload 0
invokevirtual com/nd/android/u/tast/experience/calendar/SignInPopWindow/init()V
aload 0
invokevirtual com/nd/android/u/tast/experience/calendar/SignInPopWindow/showPopWindow()V
return
L6:
aload 0
invokevirtual com/nd/android/u/tast/experience/bean/MoreExperienceItem/getmItemCode()Ljava/lang/String;
ldc "PHOTO"
invokevirtual java/lang/String/equals(Ljava/lang/Object;)Z
ifeq L8
getstatic com/product/android/business/ApplicationVariable/INSTANCE Lcom/product/android/business/ApplicationVariable;
invokevirtual com/product/android/business/ApplicationVariable/getIUser()Lcom/product/android/business/login/IGetUserInfo;
invokeinterface com/product/android/business/login/IGetUserInfo/getBindUser()Lcom/product/android/business/login/BindUser; 0
invokevirtual com/product/android/business/login/BindUser/getUid()J
lstore 3
getstatic com/product/android/business/ApplicationVariable/INSTANCE Lcom/product/android/business/ApplicationVariable;
invokevirtual com/product/android/business/ApplicationVariable/getIUser()Lcom/product/android/business/login/IGetUserInfo;
invokeinterface com/product/android/business/login/IGetUserInfo/getBindUser()Lcom/product/android/business/login/BindUser; 0
invokevirtual com/product/android/business/login/BindUser/getUap_uid()J
lstore 5
new com/product/android/commonInterface/BaseCommonStruct
dup
invokespecial com/product/android/commonInterface/BaseCommonStruct/<init>()V
astore 0
aload 0
aload 1
putfield com/product/android/commonInterface/BaseCommonStruct/obj1 Ljava/lang/Object;
aload 0
iconst_2
newarray long
dup
iconst_0
lload 5
lastore
dup
iconst_1
lload 3
lastore
putfield com/product/android/commonInterface/BaseCommonStruct/obj2 Ljava/lang/Object;
getstatic com/product/android/commonInterface/CommonInterfaceManager/INSTANCE Lcom/product/android/commonInterface/CommonInterfaceManager;
bipush 7
ldc_w 72002
aload 0
invokevirtual com/product/android/commonInterface/CommonInterfaceManager/CommonInterfaceID(IILcom/product/android/commonInterface/BaseCommonStruct;)I
pop
return
L8:
aload 0
invokevirtual com/nd/android/u/tast/experience/bean/MoreExperienceItem/getmItemCode()Ljava/lang/String;
ldc "FLOWER"
invokevirtual java/lang/String/equals(Ljava/lang/Object;)Z
ifeq L1
new com/product/android/commonInterface/BaseCommonStruct
dup
invokespecial com/product/android/commonInterface/BaseCommonStruct/<init>()V
astore 0
aload 0
aload 1
putfield com/product/android/commonInterface/BaseCommonStruct/obj1 Ljava/lang/Object;
getstatic com/product/android/commonInterface/CommonInterfaceManager/INSTANCE Lcom/product/android/commonInterface/CommonInterfaceManager;
bipush 9
ldc_w 90006
aload 0
invokevirtual com/product/android/commonInterface/CommonInterfaceManager/CommonInterfaceID(IILcom/product/android/commonInterface/BaseCommonStruct;)I
istore 2
iload 2
ifeq L1
ldc "MoreExperienceAdapter"
new java/lang/StringBuilder
dup
invokespecial java/lang/StringBuilder/<init>()V
ldc "send flower onClick result:"
invokevirtual java/lang/StringBuilder/append(Ljava/lang/String;)Ljava/lang/StringBuilder;
iload 2
invokevirtual java/lang/StringBuilder/append(I)Ljava/lang/StringBuilder;
ldc "  --id:"
invokevirtual java/lang/StringBuilder/append(Ljava/lang/String;)Ljava/lang/StringBuilder;
ldc_w 90006
invokevirtual java/lang/StringBuilder/append(I)Ljava/lang/StringBuilder;
invokevirtual java/lang/StringBuilder/toString()Ljava/lang/String;
invokestatic android/util/Log/e(Ljava/lang/String;Ljava/lang/String;)I
pop
return
.limit locals 8
.limit stack 6
.end method

.method public getCount()I
aload 0
getfield com/nd/android/u/tast/experience/adapter/MoreExperienceAdapter/mList Ljava/util/List;
ifnonnull L0
iconst_0
ireturn
L0:
aload 0
getfield com/nd/android/u/tast/experience/adapter/MoreExperienceAdapter/mList Ljava/util/List;
invokeinterface java/util/List/size()I 0
ireturn
.limit locals 1
.limit stack 1
.end method

.method public getItem(I)Lcom/nd/android/u/tast/experience/bean/MoreExperienceItem;
aload 0
getfield com/nd/android/u/tast/experience/adapter/MoreExperienceAdapter/mList Ljava/util/List;
iload 1
invokeinterface java/util/List/get(I)Ljava/lang/Object; 1
checkcast com/nd/android/u/tast/experience/bean/MoreExperienceItem
areturn
.limit locals 2
.limit stack 2
.end method

.method public volatile synthetic getItem(I)Ljava/lang/Object;
aload 0
iload 1
invokevirtual com/nd/android/u/tast/experience/adapter/MoreExperienceAdapter/getItem(I)Lcom/nd/android/u/tast/experience/bean/MoreExperienceItem;
areturn
.limit locals 2
.limit stack 2
.end method

.method public getItemId(I)J
iload 1
i2l
lreturn
.limit locals 2
.limit stack 2
.end method

.method public getView(ILandroid/view/View;Landroid/view/ViewGroup;)Landroid/view/View;
aload 0
iload 1
invokevirtual com/nd/android/u/tast/experience/adapter/MoreExperienceAdapter/getItem(I)Lcom/nd/android/u/tast/experience/bean/MoreExperienceItem;
astore 2
aload 2
invokevirtual com/nd/android/u/tast/experience/bean/MoreExperienceItem/getStatus()Lcom/nd/android/u/tast/experience/activity/DateWidgetActivity$MORE_EXP_STATUS;
getstatic com/nd/android/u/tast/experience/activity/DateWidgetActivity$MORE_EXP_STATUS/FAIL Lcom/nd/android/u/tast/experience/activity/DateWidgetActivity$MORE_EXP_STATUS;
if_acmpne L0
aload 0
aload 2
invokespecial com/nd/android/u/tast/experience/adapter/MoreExperienceAdapter/getFailView(Lcom/nd/android/u/tast/experience/bean/MoreExperienceItem;)Landroid/view/View;
areturn
L0:
aload 2
invokevirtual com/nd/android/u/tast/experience/bean/MoreExperienceItem/getStatus()Lcom/nd/android/u/tast/experience/activity/DateWidgetActivity$MORE_EXP_STATUS;
getstatic com/nd/android/u/tast/experience/activity/DateWidgetActivity$MORE_EXP_STATUS/FINISH Lcom/nd/android/u/tast/experience/activity/DateWidgetActivity$MORE_EXP_STATUS;
if_acmpne L1
aload 0
aload 2
invokespecial com/nd/android/u/tast/experience/adapter/MoreExperienceAdapter/getFinishView(Lcom/nd/android/u/tast/experience/bean/MoreExperienceItem;)Landroid/view/View;
areturn
L1:
aload 0
aload 2
invokespecial com/nd/android/u/tast/experience/adapter/MoreExperienceAdapter/getNormalView(Lcom/nd/android/u/tast/experience/bean/MoreExperienceItem;)Landroid/view/View;
areturn
.limit locals 4
.limit stack 2
.end method

.method public setData(Ljava/util/List;)V
.signature "(Ljava/util/List<Lcom/nd/android/u/tast/experience/bean/MoreExperienceItem;>;)V"
aload 0
aload 1
putfield com/nd/android/u/tast/experience/adapter/MoreExperienceAdapter/mList Ljava/util/List;
aload 0
getfield com/nd/android/u/tast/experience/adapter/MoreExperienceAdapter/mList Ljava/util/List;
new com/nd/android/u/tast/experience/adapter/MoreExperienceAdapter$1
dup
aload 0
invokespecial com/nd/android/u/tast/experience/adapter/MoreExperienceAdapter$1/<init>(Lcom/nd/android/u/tast/experience/adapter/MoreExperienceAdapter;)V
invokestatic java/util/Collections/sort(Ljava/util/List;Ljava/util/Comparator;)V
aload 0
getfield com/nd/android/u/tast/experience/adapter/MoreExperienceAdapter/mRootView Landroid/view/View;
ifnonnull L0
aload 0
getfield com/nd/android/u/tast/experience/adapter/MoreExperienceAdapter/mList Ljava/util/List;
invokeinterface java/util/List/iterator()Ljava/util/Iterator; 0
astore 1
L1:
aload 1
invokeinterface java/util/Iterator/hasNext()Z 0
ifeq L0
aload 1
invokeinterface java/util/Iterator/next()Ljava/lang/Object; 0
checkcast com/nd/android/u/tast/experience/bean/MoreExperienceItem
invokevirtual com/nd/android/u/tast/experience/bean/MoreExperienceItem/getmItemCode()Ljava/lang/String;
ldc "SIGNIN"
invokevirtual java/lang/String/equals(Ljava/lang/Object;)Z
ifeq L1
aload 1
invokeinterface java/util/Iterator/remove()V 0
L0:
return
.limit locals 2
.limit stack 4
.end method
