.bytecode 50.0
.class public synchronized com/nd/android/u/tast/experience/adapter/ReceiveExpAdapter
.super android/widget/BaseAdapter
.inner class inner com/nd/android/u/tast/experience/adapter/ReceiveExpAdapter$1
.inner class public static final enum RECEIVE_EXP_STATUS inner com/nd/android/u/tast/experience/adapter/ReceiveExpAdapter$RECEIVE_EXP_STATUS outer com/nd/android/u/tast/experience/adapter/ReceiveExpAdapter
.inner class private ReceiveExpTask inner com/nd/android/u/tast/experience/adapter/ReceiveExpAdapter$ReceiveExpTask outer com/nd/android/u/tast/experience/adapter/ReceiveExpAdapter
.inner class public static ReceiveExperienceItem inner com/nd/android/u/tast/experience/adapter/ReceiveExpAdapter$ReceiveExperienceItem outer com/nd/android/u/tast/experience/adapter/ReceiveExpAdapter
.inner class private ViewHolder inner com/nd/android/u/tast/experience/adapter/ReceiveExpAdapter$ViewHolder outer com/nd/android/u/tast/experience/adapter/ReceiveExpAdapter

.field private 'mContext' Landroid/content/Context;

.field private 'mList' Ljava/util/List; signature "Ljava/util/List<Lcom/nd/android/u/tast/experience/adapter/ReceiveExpAdapter$ReceiveExperienceItem;>;"

.field private 'mListener' Lcom/nd/android/u/tast/experience/adapter/ReceiveExperienceAdapter$OnUpdateLevelListener;

.method public <init>(Landroid/content/Context;Lcom/nd/android/u/tast/experience/adapter/ReceiveExperienceAdapter$OnUpdateLevelListener;)V
aload 0
invokespecial android/widget/BaseAdapter/<init>()V
aload 0
aload 1
putfield com/nd/android/u/tast/experience/adapter/ReceiveExpAdapter/mContext Landroid/content/Context;
aload 0
aload 2
putfield com/nd/android/u/tast/experience/adapter/ReceiveExpAdapter/mListener Lcom/nd/android/u/tast/experience/adapter/ReceiveExperienceAdapter$OnUpdateLevelListener;
return
.limit locals 3
.limit stack 2
.end method

.method static synthetic access$100(Lcom/nd/android/u/tast/experience/adapter/ReceiveExpAdapter;Ljava/lang/String;I)V
aload 0
aload 1
iload 2
invokespecial com/nd/android/u/tast/experience/adapter/ReceiveExpAdapter/receiveExp(Ljava/lang/String;I)V
return
.limit locals 3
.limit stack 3
.end method

.method static synthetic access$300(Lcom/nd/android/u/tast/experience/adapter/ReceiveExpAdapter;)Landroid/content/Context;
aload 0
getfield com/nd/android/u/tast/experience/adapter/ReceiveExpAdapter/mContext Landroid/content/Context;
areturn
.limit locals 1
.limit stack 1
.end method

.method static synthetic access$400(Lcom/nd/android/u/tast/experience/adapter/ReceiveExpAdapter;)Lcom/nd/android/u/tast/experience/adapter/ReceiveExperienceAdapter$OnUpdateLevelListener;
aload 0
getfield com/nd/android/u/tast/experience/adapter/ReceiveExpAdapter/mListener Lcom/nd/android/u/tast/experience/adapter/ReceiveExperienceAdapter$OnUpdateLevelListener;
areturn
.limit locals 1
.limit stack 1
.end method

.method private isOnline(Landroid/content/Context;)Z
aload 1
ldc "connectivity"
invokevirtual android/content/Context/getSystemService(Ljava/lang/String;)Ljava/lang/Object;
checkcast android/net/ConnectivityManager
invokevirtual android/net/ConnectivityManager/getActiveNetworkInfo()Landroid/net/NetworkInfo;
astore 1
aload 1
ifnull L0
aload 1
invokevirtual android/net/NetworkInfo/isConnected()Z
ifeq L0
iconst_1
ireturn
L0:
iconst_0
ireturn
.limit locals 2
.limit stack 2
.end method

.method private receiveExp(Ljava/lang/String;I)V
aload 0
aload 0
getfield com/nd/android/u/tast/experience/adapter/ReceiveExpAdapter/mContext Landroid/content/Context;
invokespecial com/nd/android/u/tast/experience/adapter/ReceiveExpAdapter/isOnline(Landroid/content/Context;)Z
ifne L0
aload 0
getfield com/nd/android/u/tast/experience/adapter/ReceiveExpAdapter/mContext Landroid/content/Context;
getstatic com/nd/android/u/tasklib/R$string/network_not_available I
iconst_0
invokestatic android/widget/Toast/makeText(Landroid/content/Context;II)Landroid/widget/Toast;
invokevirtual android/widget/Toast/show()V
return
L0:
new com/nd/android/u/tast/experience/adapter/ReceiveExpAdapter$ReceiveExpTask
dup
aload 0
aconst_null
invokespecial com/nd/android/u/tast/experience/adapter/ReceiveExpAdapter$ReceiveExpTask/<init>(Lcom/nd/android/u/tast/experience/adapter/ReceiveExpAdapter;Lcom/nd/android/u/tast/experience/adapter/ReceiveExpAdapter$1;)V
iconst_2
anewarray java/lang/String
dup
iconst_0
aload 1
aastore
dup
iconst_1
iload 2
invokestatic java/lang/String/valueOf(I)Ljava/lang/String;
aastore
invokevirtual com/nd/android/u/tast/experience/adapter/ReceiveExpAdapter$ReceiveExpTask/execute([Ljava/lang/Object;)Landroid/os/AsyncTask;
pop
return
.limit locals 3
.limit stack 5
.end method

.method public getCount()I
aload 0
getfield com/nd/android/u/tast/experience/adapter/ReceiveExpAdapter/mList Ljava/util/List;
ifnonnull L0
iconst_0
ireturn
L0:
aload 0
getfield com/nd/android/u/tast/experience/adapter/ReceiveExpAdapter/mList Ljava/util/List;
invokeinterface java/util/List/size()I 0
ireturn
.limit locals 1
.limit stack 1
.end method

.method public getItem(I)Lcom/nd/android/u/tast/experience/adapter/ReceiveExpAdapter$ReceiveExperienceItem;
aload 0
getfield com/nd/android/u/tast/experience/adapter/ReceiveExpAdapter/mList Ljava/util/List;
iload 1
invokeinterface java/util/List/get(I)Ljava/lang/Object; 1
checkcast com/nd/android/u/tast/experience/adapter/ReceiveExpAdapter$ReceiveExperienceItem
areturn
.limit locals 2
.limit stack 2
.end method

.method public volatile synthetic getItem(I)Ljava/lang/Object;
aload 0
iload 1
invokevirtual com/nd/android/u/tast/experience/adapter/ReceiveExpAdapter/getItem(I)Lcom/nd/android/u/tast/experience/adapter/ReceiveExpAdapter$ReceiveExperienceItem;
areturn
.limit locals 2
.limit stack 2
.end method

.method public getItemId(I)J
iload 1
i2l
lreturn
.limit locals 2
.limit stack 2
.end method

.method public getView(ILandroid/view/View;Landroid/view/ViewGroup;)Landroid/view/View;
aload 0
iload 1
invokevirtual com/nd/android/u/tast/experience/adapter/ReceiveExpAdapter/getItem(I)Lcom/nd/android/u/tast/experience/adapter/ReceiveExpAdapter$ReceiveExperienceItem;
astore 4
aload 2
ifnonnull L0
new com/nd/android/u/tast/experience/adapter/ReceiveExpAdapter$ViewHolder
dup
aload 0
aconst_null
invokespecial com/nd/android/u/tast/experience/adapter/ReceiveExpAdapter$ViewHolder/<init>(Lcom/nd/android/u/tast/experience/adapter/ReceiveExpAdapter;Lcom/nd/android/u/tast/experience/adapter/ReceiveExpAdapter$1;)V
astore 3
aload 0
getfield com/nd/android/u/tast/experience/adapter/ReceiveExpAdapter/mContext Landroid/content/Context;
invokestatic android/view/LayoutInflater/from(Landroid/content/Context;)Landroid/view/LayoutInflater;
getstatic com/nd/android/u/tasklib/R$layout/layout_exp_item I
aconst_null
invokevirtual android/view/LayoutInflater/inflate(ILandroid/view/ViewGroup;)Landroid/view/View;
astore 2
aload 3
aload 2
getstatic com/nd/android/u/tasklib/R$id/tv_item_name I
invokevirtual android/view/View/findViewById(I)Landroid/view/View;
checkcast android/widget/TextView
putfield com/nd/android/u/tast/experience/adapter/ReceiveExpAdapter$ViewHolder/tvItemName Landroid/widget/TextView;
aload 3
aload 2
getstatic com/nd/android/u/tasklib/R$id/tv_exp I
invokevirtual android/view/View/findViewById(I)Landroid/view/View;
checkcast android/widget/TextView
putfield com/nd/android/u/tast/experience/adapter/ReceiveExpAdapter$ViewHolder/tvExp Landroid/widget/TextView;
aload 3
aload 2
getstatic com/nd/android/u/tasklib/R$id/tv_receive_exp I
invokevirtual android/view/View/findViewById(I)Landroid/view/View;
checkcast android/widget/TextView
putfield com/nd/android/u/tast/experience/adapter/ReceiveExpAdapter$ViewHolder/tvReceive Landroid/widget/TextView;
aload 2
aload 3
invokevirtual android/view/View/setTag(Ljava/lang/Object;)V
L1:
aload 4
getfield com/nd/android/u/tast/experience/adapter/ReceiveExpAdapter$ReceiveExperienceItem/mExp I
ifgt L2
aload 3
getfield com/nd/android/u/tast/experience/adapter/ReceiveExpAdapter$ViewHolder/tvExp Landroid/widget/TextView;
bipush 8
invokevirtual android/widget/TextView/setVisibility(I)V
L3:
aload 4
getfield com/nd/android/u/tast/experience/adapter/ReceiveExpAdapter$ReceiveExperienceItem/mStatus Lcom/nd/android/u/tast/experience/adapter/ReceiveExpAdapter$RECEIVE_EXP_STATUS;
getstatic com/nd/android/u/tast/experience/adapter/ReceiveExpAdapter$RECEIVE_EXP_STATUS/NOT_RECEIVED Lcom/nd/android/u/tast/experience/adapter/ReceiveExpAdapter$RECEIVE_EXP_STATUS;
if_acmpne L4
aload 3
getfield com/nd/android/u/tast/experience/adapter/ReceiveExpAdapter$ViewHolder/tvReceive Landroid/widget/TextView;
getstatic com/nd/android/u/tasklib/R$drawable/ic_receive_exp I
invokevirtual android/widget/TextView/setBackgroundResource(I)V
L5:
aload 3
getfield com/nd/android/u/tast/experience/adapter/ReceiveExpAdapter$ViewHolder/tvReceive Landroid/widget/TextView;
new com/nd/android/u/tast/experience/adapter/ReceiveExpAdapter$1
dup
aload 0
aload 4
invokespecial com/nd/android/u/tast/experience/adapter/ReceiveExpAdapter$1/<init>(Lcom/nd/android/u/tast/experience/adapter/ReceiveExpAdapter;Lcom/nd/android/u/tast/experience/adapter/ReceiveExpAdapter$ReceiveExperienceItem;)V
invokevirtual android/widget/TextView/setOnClickListener(Landroid/view/View$OnClickListener;)V
aload 3
getfield com/nd/android/u/tast/experience/adapter/ReceiveExpAdapter$ViewHolder/tvItemName Landroid/widget/TextView;
aload 4
getfield com/nd/android/u/tast/experience/adapter/ReceiveExpAdapter$ReceiveExperienceItem/mItemName Ljava/lang/String;
invokevirtual android/widget/TextView/setText(Ljava/lang/CharSequence;)V
aload 2
areturn
L0:
aload 2
invokevirtual android/view/View/getTag()Ljava/lang/Object;
checkcast com/nd/android/u/tast/experience/adapter/ReceiveExpAdapter$ViewHolder
astore 3
goto L1
L2:
aload 3
getfield com/nd/android/u/tast/experience/adapter/ReceiveExpAdapter$ViewHolder/tvExp Landroid/widget/TextView;
iconst_0
invokevirtual android/widget/TextView/setVisibility(I)V
aload 3
getfield com/nd/android/u/tast/experience/adapter/ReceiveExpAdapter$ViewHolder/tvExp Landroid/widget/TextView;
new java/lang/StringBuilder
dup
invokespecial java/lang/StringBuilder/<init>()V
ldc "+"
invokevirtual java/lang/StringBuilder/append(Ljava/lang/String;)Ljava/lang/StringBuilder;
aload 4
getfield com/nd/android/u/tast/experience/adapter/ReceiveExpAdapter$ReceiveExperienceItem/mExp I
invokestatic java/lang/String/valueOf(I)Ljava/lang/String;
invokevirtual java/lang/StringBuilder/append(Ljava/lang/String;)Ljava/lang/StringBuilder;
invokevirtual java/lang/StringBuilder/toString()Ljava/lang/String;
invokevirtual android/widget/TextView/setText(Ljava/lang/CharSequence;)V
goto L3
L4:
aload 4
getfield com/nd/android/u/tast/experience/adapter/ReceiveExpAdapter$ReceiveExperienceItem/mStatus Lcom/nd/android/u/tast/experience/adapter/ReceiveExpAdapter$RECEIVE_EXP_STATUS;
getstatic com/nd/android/u/tast/experience/adapter/ReceiveExpAdapter$RECEIVE_EXP_STATUS/RECEIVED Lcom/nd/android/u/tast/experience/adapter/ReceiveExpAdapter$RECEIVE_EXP_STATUS;
if_acmpne L5
aload 3
getfield com/nd/android/u/tast/experience/adapter/ReceiveExpAdapter$ViewHolder/tvReceive Landroid/widget/TextView;
getstatic com/nd/android/u/tasklib/R$drawable/ic_have_received I
invokevirtual android/widget/TextView/setBackgroundResource(I)V
goto L5
.limit locals 5
.limit stack 5
.end method

.method public setData(Ljava/util/List;)V
.signature "(Ljava/util/List<Lcom/nd/android/u/tast/experience/adapter/ReceiveExpAdapter$ReceiveExperienceItem;>;)V"
aload 0
getfield com/nd/android/u/tast/experience/adapter/ReceiveExpAdapter/mList Ljava/util/List;
ifnull L0
aload 0
getfield com/nd/android/u/tast/experience/adapter/ReceiveExpAdapter/mList Ljava/util/List;
invokeinterface java/util/List/clear()V 0
L0:
aload 0
aload 1
putfield com/nd/android/u/tast/experience/adapter/ReceiveExpAdapter/mList Ljava/util/List;
return
.limit locals 2
.limit stack 2
.end method

.method public upDate(Ljava/lang/String;I)V
aload 0
getfield com/nd/android/u/tast/experience/adapter/ReceiveExpAdapter/mList Ljava/util/List;
ifnull L0
iconst_0
istore 3
L1:
iload 3
aload 0
getfield com/nd/android/u/tast/experience/adapter/ReceiveExpAdapter/mList Ljava/util/List;
invokeinterface java/util/List/size()I 0
if_icmpge L2
aload 1
aload 0
getfield com/nd/android/u/tast/experience/adapter/ReceiveExpAdapter/mList Ljava/util/List;
iload 3
invokeinterface java/util/List/get(I)Ljava/lang/Object; 1
checkcast com/nd/android/u/tast/experience/adapter/ReceiveExpAdapter$ReceiveExperienceItem
getfield com/nd/android/u/tast/experience/adapter/ReceiveExpAdapter$ReceiveExperienceItem/mItemCode Ljava/lang/String;
invokevirtual java/lang/String/equals(Ljava/lang/Object;)Z
ifeq L3
aload 0
getfield com/nd/android/u/tast/experience/adapter/ReceiveExpAdapter/mList Ljava/util/List;
iload 3
invokeinterface java/util/List/get(I)Ljava/lang/Object; 1
checkcast com/nd/android/u/tast/experience/adapter/ReceiveExpAdapter$ReceiveExperienceItem
getfield com/nd/android/u/tast/experience/adapter/ReceiveExpAdapter$ReceiveExperienceItem/mActionId I
iload 2
if_icmpne L3
aload 0
getfield com/nd/android/u/tast/experience/adapter/ReceiveExpAdapter/mList Ljava/util/List;
iload 3
invokeinterface java/util/List/get(I)Ljava/lang/Object; 1
checkcast com/nd/android/u/tast/experience/adapter/ReceiveExpAdapter$ReceiveExperienceItem
getstatic com/nd/android/u/tast/experience/adapter/ReceiveExpAdapter$RECEIVE_EXP_STATUS/RECEIVED Lcom/nd/android/u/tast/experience/adapter/ReceiveExpAdapter$RECEIVE_EXP_STATUS;
putfield com/nd/android/u/tast/experience/adapter/ReceiveExpAdapter$ReceiveExperienceItem/mStatus Lcom/nd/android/u/tast/experience/adapter/ReceiveExpAdapter$RECEIVE_EXP_STATUS;
L3:
iload 3
iconst_1
iadd
istore 3
goto L1
L2:
aload 0
invokevirtual com/nd/android/u/tast/experience/adapter/ReceiveExpAdapter/notifyDataSetChanged()V
aload 0
getfield com/nd/android/u/tast/experience/adapter/ReceiveExpAdapter/mListener Lcom/nd/android/u/tast/experience/adapter/ReceiveExperienceAdapter$OnUpdateLevelListener;
ifnull L0
aload 0
getfield com/nd/android/u/tast/experience/adapter/ReceiveExpAdapter/mListener Lcom/nd/android/u/tast/experience/adapter/ReceiveExperienceAdapter$OnUpdateLevelListener;
invokeinterface com/nd/android/u/tast/experience/adapter/ReceiveExperienceAdapter$OnUpdateLevelListener/onUpdate()V 0
L0:
return
.limit locals 4
.limit stack 3
.end method
