.bytecode 50.0
.class public synchronized com/nd/android/u/tast/experience/adapter/ReceiveExperienceAdapter
.super android/widget/BaseAdapter
.inner class inner com/nd/android/u/tast/experience/adapter/ReceiveExperienceAdapter$1
.inner class inner com/nd/android/u/tast/experience/adapter/ReceiveExperienceAdapter$2
.inner class public static abstract interface OnUpdateLevelListener inner com/nd/android/u/tast/experience/adapter/ReceiveExperienceAdapter$OnUpdateLevelListener outer com/nd/android/u/tast/experience/adapter/ReceiveExperienceAdapter
.inner class private ReceiveExpTask inner com/nd/android/u/tast/experience/adapter/ReceiveExperienceAdapter$ReceiveExpTask outer com/nd/android/u/tast/experience/adapter/ReceiveExperienceAdapter

.field private 'mActivity' Landroid/app/Activity;

.field private 'mInflater' Landroid/view/LayoutInflater;

.field private 'mList' Ljava/util/List; signature "Ljava/util/List<Lcom/nd/android/u/tast/experience/adapter/ReceiveExpAdapter$ReceiveExperienceItem;>;"

.field private 'mListView' Landroid/widget/ListView;

.field private 'mListener' Lcom/nd/android/u/tast/experience/adapter/ReceiveExperienceAdapter$OnUpdateLevelListener;

.method public <init>(Landroid/app/Activity;Landroid/widget/ListView;Lcom/nd/android/u/tast/experience/adapter/ReceiveExperienceAdapter$OnUpdateLevelListener;)V
aload 0
invokespecial android/widget/BaseAdapter/<init>()V
aload 0
aload 1
putfield com/nd/android/u/tast/experience/adapter/ReceiveExperienceAdapter/mActivity Landroid/app/Activity;
aload 0
aload 2
putfield com/nd/android/u/tast/experience/adapter/ReceiveExperienceAdapter/mListView Landroid/widget/ListView;
aload 0
aload 1
ldc "layout_inflater"
invokevirtual android/app/Activity/getSystemService(Ljava/lang/String;)Ljava/lang/Object;
checkcast android/view/LayoutInflater
putfield com/nd/android/u/tast/experience/adapter/ReceiveExperienceAdapter/mInflater Landroid/view/LayoutInflater;
aload 0
aload 3
putfield com/nd/android/u/tast/experience/adapter/ReceiveExperienceAdapter/mListener Lcom/nd/android/u/tast/experience/adapter/ReceiveExperienceAdapter$OnUpdateLevelListener;
return
.limit locals 4
.limit stack 3
.end method

.method static synthetic access$000(Lcom/nd/android/u/tast/experience/adapter/ReceiveExperienceAdapter;Ljava/lang/String;I)V
aload 0
aload 1
iload 2
invokespecial com/nd/android/u/tast/experience/adapter/ReceiveExperienceAdapter/receiveExp(Ljava/lang/String;I)V
return
.limit locals 3
.limit stack 3
.end method

.method static synthetic access$200(Lcom/nd/android/u/tast/experience/adapter/ReceiveExperienceAdapter;)Landroid/app/Activity;
aload 0
getfield com/nd/android/u/tast/experience/adapter/ReceiveExperienceAdapter/mActivity Landroid/app/Activity;
areturn
.limit locals 1
.limit stack 1
.end method

.method static synthetic access$300(Lcom/nd/android/u/tast/experience/adapter/ReceiveExperienceAdapter;)Lcom/nd/android/u/tast/experience/adapter/ReceiveExperienceAdapter$OnUpdateLevelListener;
aload 0
getfield com/nd/android/u/tast/experience/adapter/ReceiveExperienceAdapter/mListener Lcom/nd/android/u/tast/experience/adapter/ReceiveExperienceAdapter$OnUpdateLevelListener;
areturn
.limit locals 1
.limit stack 1
.end method

.method private isOnline(Landroid/content/Context;)Z
aload 1
ldc "connectivity"
invokevirtual android/content/Context/getSystemService(Ljava/lang/String;)Ljava/lang/Object;
checkcast android/net/ConnectivityManager
invokevirtual android/net/ConnectivityManager/getActiveNetworkInfo()Landroid/net/NetworkInfo;
astore 1
aload 1
ifnull L0
aload 1
invokevirtual android/net/NetworkInfo/isConnected()Z
ifeq L0
iconst_1
ireturn
L0:
iconst_0
ireturn
.limit locals 2
.limit stack 2
.end method

.method private receiveExp(Ljava/lang/String;I)V
aload 0
aload 0
getfield com/nd/android/u/tast/experience/adapter/ReceiveExperienceAdapter/mActivity Landroid/app/Activity;
invokespecial com/nd/android/u/tast/experience/adapter/ReceiveExperienceAdapter/isOnline(Landroid/content/Context;)Z
ifne L0
aload 0
getfield com/nd/android/u/tast/experience/adapter/ReceiveExperienceAdapter/mActivity Landroid/app/Activity;
getstatic com/nd/android/u/tasklib/R$string/network_not_available I
iconst_0
invokestatic android/widget/Toast/makeText(Landroid/content/Context;II)Landroid/widget/Toast;
invokevirtual android/widget/Toast/show()V
return
L0:
new com/nd/android/u/tast/experience/adapter/ReceiveExperienceAdapter$ReceiveExpTask
dup
aload 0
aconst_null
invokespecial com/nd/android/u/tast/experience/adapter/ReceiveExperienceAdapter$ReceiveExpTask/<init>(Lcom/nd/android/u/tast/experience/adapter/ReceiveExperienceAdapter;Lcom/nd/android/u/tast/experience/adapter/ReceiveExperienceAdapter$1;)V
iconst_2
anewarray java/lang/String
dup
iconst_0
aload 1
aastore
dup
iconst_1
iload 2
invokestatic java/lang/String/valueOf(I)Ljava/lang/String;
aastore
invokevirtual com/nd/android/u/tast/experience/adapter/ReceiveExperienceAdapter$ReceiveExpTask/execute([Ljava/lang/Object;)Landroid/os/AsyncTask;
pop
return
.limit locals 3
.limit stack 5
.end method

.method public getCount()I
aload 0
getfield com/nd/android/u/tast/experience/adapter/ReceiveExperienceAdapter/mList Ljava/util/List;
ifnonnull L0
iconst_0
ireturn
L0:
aload 0
getfield com/nd/android/u/tast/experience/adapter/ReceiveExperienceAdapter/mList Ljava/util/List;
invokeinterface java/util/List/size()I 0
ireturn
.limit locals 1
.limit stack 1
.end method

.method public getItem(I)Lcom/nd/android/u/tast/experience/adapter/ReceiveExpAdapter$ReceiveExperienceItem;
aload 0
getfield com/nd/android/u/tast/experience/adapter/ReceiveExperienceAdapter/mList Ljava/util/List;
iload 1
invokeinterface java/util/List/get(I)Ljava/lang/Object; 1
checkcast com/nd/android/u/tast/experience/adapter/ReceiveExpAdapter$ReceiveExperienceItem
areturn
.limit locals 2
.limit stack 2
.end method

.method public volatile synthetic getItem(I)Ljava/lang/Object;
aload 0
iload 1
invokevirtual com/nd/android/u/tast/experience/adapter/ReceiveExperienceAdapter/getItem(I)Lcom/nd/android/u/tast/experience/adapter/ReceiveExpAdapter$ReceiveExperienceItem;
areturn
.limit locals 2
.limit stack 2
.end method

.method public getItemId(I)J
iload 1
i2l
lreturn
.limit locals 2
.limit stack 2
.end method

.method public getView(ILandroid/view/View;Landroid/view/ViewGroup;)Landroid/view/View;
aload 0
iload 1
invokevirtual com/nd/android/u/tast/experience/adapter/ReceiveExperienceAdapter/getItem(I)Lcom/nd/android/u/tast/experience/adapter/ReceiveExpAdapter$ReceiveExperienceItem;
astore 2
aload 0
getfield com/nd/android/u/tast/experience/adapter/ReceiveExperienceAdapter/mInflater Landroid/view/LayoutInflater;
getstatic com/nd/android/u/tasklib/R$layout/receive_experience_item I
aconst_null
invokevirtual android/view/LayoutInflater/inflate(ILandroid/view/ViewGroup;)Landroid/view/View;
astore 3
aload 3
getstatic com/nd/android/u/tasklib/R$id/leftText I
invokevirtual android/view/View/findViewById(I)Landroid/view/View;
checkcast android/widget/TextView
astore 4
aload 3
getstatic com/nd/android/u/tasklib/R$id/exp_and_money_tv I
invokevirtual android/view/View/findViewById(I)Landroid/view/View;
checkcast android/widget/TextView
astore 5
aload 2
getfield com/nd/android/u/tast/experience/adapter/ReceiveExpAdapter$ReceiveExperienceItem/mExp I
ifle L0
aload 2
getfield com/nd/android/u/tast/experience/adapter/ReceiveExpAdapter$ReceiveExperienceItem/mMoney I
ifle L0
invokestatic java/util/Locale/getDefault()Ljava/util/Locale;
ldc "%s\uff1a"
iconst_1
anewarray java/lang/Object
dup
iconst_0
aload 2
getfield com/nd/android/u/tast/experience/adapter/ReceiveExpAdapter$ReceiveExperienceItem/mItemName Ljava/lang/String;
aastore
invokestatic java/lang/String/format(Ljava/util/Locale;Ljava/lang/String;[Ljava/lang/Object;)Ljava/lang/String;
astore 6
aload 5
invokestatic java/util/Locale/getDefault()Ljava/util/Locale;
ldc "%d\u7ecf\u9a8c\uff0c%d\u91d1\u5e01"
iconst_2
anewarray java/lang/Object
dup
iconst_0
aload 2
getfield com/nd/android/u/tast/experience/adapter/ReceiveExpAdapter$ReceiveExperienceItem/mExp I
invokestatic java/lang/Integer/valueOf(I)Ljava/lang/Integer;
aastore
dup
iconst_1
aload 2
getfield com/nd/android/u/tast/experience/adapter/ReceiveExpAdapter$ReceiveExperienceItem/mMoney I
invokestatic java/lang/Integer/valueOf(I)Ljava/lang/Integer;
aastore
invokestatic java/lang/String/format(Ljava/util/Locale;Ljava/lang/String;[Ljava/lang/Object;)Ljava/lang/String;
invokevirtual android/widget/TextView/setText(Ljava/lang/CharSequence;)V
aload 4
aload 6
invokevirtual android/widget/TextView/setText(Ljava/lang/CharSequence;)V
L1:
aload 3
getstatic com/nd/android/u/tasklib/R$id/rightButton I
invokevirtual android/view/View/findViewById(I)Landroid/view/View;
checkcast android/widget/Button
astore 4
aload 3
getstatic com/nd/android/u/tasklib/R$id/rightImage I
invokevirtual android/view/View/findViewById(I)Landroid/view/View;
checkcast android/widget/ImageView
astore 5
aload 2
getfield com/nd/android/u/tast/experience/adapter/ReceiveExpAdapter$ReceiveExperienceItem/mStatus Lcom/nd/android/u/tast/experience/adapter/ReceiveExpAdapter$RECEIVE_EXP_STATUS;
getstatic com/nd/android/u/tast/experience/adapter/ReceiveExpAdapter$RECEIVE_EXP_STATUS/NOT_RECEIVED Lcom/nd/android/u/tast/experience/adapter/ReceiveExpAdapter$RECEIVE_EXP_STATUS;
if_acmpne L2
aload 4
iconst_0
invokevirtual android/widget/Button/setVisibility(I)V
aload 5
bipush 8
invokevirtual android/widget/ImageView/setVisibility(I)V
aload 4
new com/nd/android/u/tast/experience/adapter/ReceiveExperienceAdapter$1
dup
aload 0
aload 2
invokespecial com/nd/android/u/tast/experience/adapter/ReceiveExperienceAdapter$1/<init>(Lcom/nd/android/u/tast/experience/adapter/ReceiveExperienceAdapter;Lcom/nd/android/u/tast/experience/adapter/ReceiveExpAdapter$ReceiveExperienceItem;)V
invokevirtual android/widget/Button/setOnClickListener(Landroid/view/View$OnClickListener;)V
L3:
aload 3
new com/nd/android/u/tast/experience/adapter/ReceiveExperienceAdapter$2
dup
aload 0
invokespecial com/nd/android/u/tast/experience/adapter/ReceiveExperienceAdapter$2/<init>(Lcom/nd/android/u/tast/experience/adapter/ReceiveExperienceAdapter;)V
invokevirtual android/view/View/setOnClickListener(Landroid/view/View$OnClickListener;)V
aload 3
areturn
L0:
aload 2
getfield com/nd/android/u/tast/experience/adapter/ReceiveExpAdapter$ReceiveExperienceItem/mMoney I
ifle L4
invokestatic java/util/Locale/getDefault()Ljava/util/Locale;
ldc "%s\uff1a"
iconst_1
anewarray java/lang/Object
dup
iconst_0
aload 2
getfield com/nd/android/u/tast/experience/adapter/ReceiveExpAdapter$ReceiveExperienceItem/mItemName Ljava/lang/String;
aastore
invokestatic java/lang/String/format(Ljava/util/Locale;Ljava/lang/String;[Ljava/lang/Object;)Ljava/lang/String;
astore 6
aload 5
invokestatic java/util/Locale/getDefault()Ljava/util/Locale;
ldc "%d\u91d1\u5e01"
iconst_1
anewarray java/lang/Object
dup
iconst_0
aload 2
getfield com/nd/android/u/tast/experience/adapter/ReceiveExpAdapter$ReceiveExperienceItem/mMoney I
invokestatic java/lang/Integer/valueOf(I)Ljava/lang/Integer;
aastore
invokestatic java/lang/String/format(Ljava/util/Locale;Ljava/lang/String;[Ljava/lang/Object;)Ljava/lang/String;
invokevirtual android/widget/TextView/setText(Ljava/lang/CharSequence;)V
aload 4
aload 6
invokevirtual android/widget/TextView/setText(Ljava/lang/CharSequence;)V
goto L1
L4:
invokestatic java/util/Locale/getDefault()Ljava/util/Locale;
ldc "%s\uff1a"
iconst_1
anewarray java/lang/Object
dup
iconst_0
aload 2
getfield com/nd/android/u/tast/experience/adapter/ReceiveExpAdapter$ReceiveExperienceItem/mItemName Ljava/lang/String;
aastore
invokestatic java/lang/String/format(Ljava/util/Locale;Ljava/lang/String;[Ljava/lang/Object;)Ljava/lang/String;
astore 6
aload 5
invokestatic java/util/Locale/getDefault()Ljava/util/Locale;
ldc "%d\u7ecf\u9a8c"
iconst_1
anewarray java/lang/Object
dup
iconst_0
aload 2
getfield com/nd/android/u/tast/experience/adapter/ReceiveExpAdapter$ReceiveExperienceItem/mExp I
invokestatic java/lang/Integer/valueOf(I)Ljava/lang/Integer;
aastore
invokestatic java/lang/String/format(Ljava/util/Locale;Ljava/lang/String;[Ljava/lang/Object;)Ljava/lang/String;
invokevirtual android/widget/TextView/setText(Ljava/lang/CharSequence;)V
aload 4
aload 6
invokevirtual android/widget/TextView/setText(Ljava/lang/CharSequence;)V
goto L1
L2:
aload 2
getfield com/nd/android/u/tast/experience/adapter/ReceiveExpAdapter$ReceiveExperienceItem/mStatus Lcom/nd/android/u/tast/experience/adapter/ReceiveExpAdapter$RECEIVE_EXP_STATUS;
getstatic com/nd/android/u/tast/experience/adapter/ReceiveExpAdapter$RECEIVE_EXP_STATUS/RECEIVED Lcom/nd/android/u/tast/experience/adapter/ReceiveExpAdapter$RECEIVE_EXP_STATUS;
if_acmpne L3
aload 4
bipush 8
invokevirtual android/widget/Button/setVisibility(I)V
aload 5
iconst_0
invokevirtual android/widget/ImageView/setVisibility(I)V
goto L3
.limit locals 7
.limit stack 7
.end method

.method public setData(Ljava/util/List;)V
.signature "(Ljava/util/List<Lcom/nd/android/u/tast/experience/adapter/ReceiveExpAdapter$ReceiveExperienceItem;>;)V"
aload 0
getfield com/nd/android/u/tast/experience/adapter/ReceiveExperienceAdapter/mList Ljava/util/List;
ifnull L0
aload 0
getfield com/nd/android/u/tast/experience/adapter/ReceiveExperienceAdapter/mList Ljava/util/List;
invokeinterface java/util/List/clear()V 0
L0:
aload 0
aload 1
putfield com/nd/android/u/tast/experience/adapter/ReceiveExperienceAdapter/mList Ljava/util/List;
return
.limit locals 2
.limit stack 2
.end method

.method public upDate(Ljava/lang/String;I)V
aload 0
getfield com/nd/android/u/tast/experience/adapter/ReceiveExperienceAdapter/mList Ljava/util/List;
ifnull L0
iconst_0
istore 3
L1:
iload 3
aload 0
getfield com/nd/android/u/tast/experience/adapter/ReceiveExperienceAdapter/mList Ljava/util/List;
invokeinterface java/util/List/size()I 0
if_icmpge L2
aload 1
aload 0
getfield com/nd/android/u/tast/experience/adapter/ReceiveExperienceAdapter/mList Ljava/util/List;
iload 3
invokeinterface java/util/List/get(I)Ljava/lang/Object; 1
checkcast com/nd/android/u/tast/experience/adapter/ReceiveExpAdapter$ReceiveExperienceItem
getfield com/nd/android/u/tast/experience/adapter/ReceiveExpAdapter$ReceiveExperienceItem/mItemCode Ljava/lang/String;
invokevirtual java/lang/String/equals(Ljava/lang/Object;)Z
ifeq L3
aload 0
getfield com/nd/android/u/tast/experience/adapter/ReceiveExperienceAdapter/mList Ljava/util/List;
iload 3
invokeinterface java/util/List/get(I)Ljava/lang/Object; 1
checkcast com/nd/android/u/tast/experience/adapter/ReceiveExpAdapter$ReceiveExperienceItem
getfield com/nd/android/u/tast/experience/adapter/ReceiveExpAdapter$ReceiveExperienceItem/mActionId I
iload 2
if_icmpne L3
aload 0
getfield com/nd/android/u/tast/experience/adapter/ReceiveExperienceAdapter/mList Ljava/util/List;
iload 3
invokeinterface java/util/List/get(I)Ljava/lang/Object; 1
checkcast com/nd/android/u/tast/experience/adapter/ReceiveExpAdapter$ReceiveExperienceItem
getstatic com/nd/android/u/tast/experience/adapter/ReceiveExpAdapter$RECEIVE_EXP_STATUS/RECEIVED Lcom/nd/android/u/tast/experience/adapter/ReceiveExpAdapter$RECEIVE_EXP_STATUS;
putfield com/nd/android/u/tast/experience/adapter/ReceiveExpAdapter$ReceiveExperienceItem/mStatus Lcom/nd/android/u/tast/experience/adapter/ReceiveExpAdapter$RECEIVE_EXP_STATUS;
L3:
iload 3
iconst_1
iadd
istore 3
goto L1
L2:
aload 0
getfield com/nd/android/u/tast/experience/adapter/ReceiveExperienceAdapter/mListView Landroid/widget/ListView;
invokestatic com/nd/android/u/tast/experience/activity/DateWidgetActivity/setListViewHeightBasedOnChildren(Landroid/widget/ListView;)V
aload 0
invokevirtual com/nd/android/u/tast/experience/adapter/ReceiveExperienceAdapter/notifyDataSetChanged()V
aload 0
getfield com/nd/android/u/tast/experience/adapter/ReceiveExperienceAdapter/mListener Lcom/nd/android/u/tast/experience/adapter/ReceiveExperienceAdapter$OnUpdateLevelListener;
ifnull L0
aload 0
getfield com/nd/android/u/tast/experience/adapter/ReceiveExperienceAdapter/mListener Lcom/nd/android/u/tast/experience/adapter/ReceiveExperienceAdapter$OnUpdateLevelListener;
invokeinterface com/nd/android/u/tast/experience/adapter/ReceiveExperienceAdapter$OnUpdateLevelListener/onUpdate()V 0
L0:
return
.limit locals 4
.limit stack 3
.end method
