.bytecode 50.0
.class synchronized com/nd/android/u/tast/experience/adapter/ReceiveExpAdapter$ReceiveExpTask
.super android/os/AsyncTask
.signature "Landroid/os/AsyncTask<Ljava/lang/String;Ljava/lang/Void;Ljava/lang/Integer;>;"
.inner class private ReceiveExpTask inner com/nd/android/u/tast/experience/adapter/ReceiveExpAdapter$ReceiveExpTask outer com/nd/android/u/tast/experience/adapter/ReceiveExpAdapter

.field 'actionId' I

.field 'itemCode' Ljava/lang/String;

.field private 'levelUp' I

.field private 'mPD' Landroid/app/ProgressDialog;

.field final synthetic 'this$0' Lcom/nd/android/u/tast/experience/adapter/ReceiveExpAdapter;

.method private <init>(Lcom/nd/android/u/tast/experience/adapter/ReceiveExpAdapter;)V
aload 0
aload 1
putfield com/nd/android/u/tast/experience/adapter/ReceiveExpAdapter$ReceiveExpTask/this$0 Lcom/nd/android/u/tast/experience/adapter/ReceiveExpAdapter;
aload 0
invokespecial android/os/AsyncTask/<init>()V
aload 0
ldc ""
putfield com/nd/android/u/tast/experience/adapter/ReceiveExpAdapter$ReceiveExpTask/itemCode Ljava/lang/String;
aload 0
iconst_0
putfield com/nd/android/u/tast/experience/adapter/ReceiveExpAdapter$ReceiveExpTask/actionId I
aload 0
iconst_0
putfield com/nd/android/u/tast/experience/adapter/ReceiveExpAdapter$ReceiveExpTask/levelUp I
return
.limit locals 2
.limit stack 2
.end method

.method synthetic <init>(Lcom/nd/android/u/tast/experience/adapter/ReceiveExpAdapter;Lcom/nd/android/u/tast/experience/adapter/ReceiveExpAdapter$1;)V
aload 0
aload 1
invokespecial com/nd/android/u/tast/experience/adapter/ReceiveExpAdapter$ReceiveExpTask/<init>(Lcom/nd/android/u/tast/experience/adapter/ReceiveExpAdapter;)V
return
.limit locals 3
.limit stack 2
.end method

.method protected transient doInBackground([Ljava/lang/String;)Ljava/lang/Integer;
.catch com/common/android/utils/http/HttpAuthException from L0 to L1 using L2
.catch com/common/android/utils/http/ResponseException from L0 to L1 using L3
.catch com/common/android/utils/http/HttpServerException from L0 to L1 using L4
.catch com/common/android/utils/http/HttpException from L0 to L1 using L5
.catch com/common/android/utils/http/HttpAuthException from L6 to L7 using L8
.catch com/common/android/utils/http/ResponseException from L6 to L7 using L9
.catch com/common/android/utils/http/HttpServerException from L6 to L7 using L10
.catch com/common/android/utils/http/HttpException from L6 to L7 using L11
.catch com/common/android/utils/http/ResponseException from L12 to L13 using L14
.catch com/common/android/utils/http/HttpException from L12 to L13 using L15
aload 0
aload 1
iconst_0
aaload
putfield com/nd/android/u/tast/experience/adapter/ReceiveExpAdapter$ReceiveExpTask/itemCode Ljava/lang/String;
aload 0
aload 1
iconst_1
aaload
invokestatic java/lang/Integer/valueOf(Ljava/lang/String;)Ljava/lang/Integer;
invokevirtual java/lang/Integer/intValue()I
putfield com/nd/android/u/tast/experience/adapter/ReceiveExpAdapter$ReceiveExpTask/actionId I
new com/nd/android/u/tast/com/AjaxCom
dup
invokespecial com/nd/android/u/tast/com/AjaxCom/<init>()V
astore 5
aconst_null
astore 1
L0:
aload 5
aload 0
getfield com/nd/android/u/tast/experience/adapter/ReceiveExpAdapter$ReceiveExpTask/itemCode Ljava/lang/String;
aload 0
getfield com/nd/android/u/tast/experience/adapter/ReceiveExpAdapter$ReceiveExpTask/actionId I
invokevirtual com/nd/android/u/tast/com/AjaxCom/getReceivescore(Ljava/lang/String;I)Lorg/json/JSONObject;
astore 4
L1:
aload 4
astore 1
L16:
aload 1
ifnonnull L17
iconst_m1
invokestatic java/lang/Integer/valueOf(I)Ljava/lang/Integer;
areturn
L2:
astore 4
ldc "ReceiveExperienceAdapter"
aload 4
invokevirtual com/common/android/utils/http/HttpAuthException/getMessage()Ljava/lang/String;
invokestatic android/util/Log/e(Ljava/lang/String;Ljava/lang/String;)I
pop
goto L16
L3:
astore 4
ldc "ReceiveExperienceAdapter"
aload 4
invokevirtual com/common/android/utils/http/ResponseException/getMessage()Ljava/lang/String;
invokestatic android/util/Log/e(Ljava/lang/String;Ljava/lang/String;)I
pop
goto L16
L4:
astore 4
ldc "ReceiveExperienceAdapter"
aload 4
invokevirtual com/common/android/utils/http/HttpServerException/getMessage()Ljava/lang/String;
invokestatic android/util/Log/e(Ljava/lang/String;Ljava/lang/String;)I
pop
goto L16
L5:
astore 4
ldc "ReceiveExperienceAdapter"
aload 4
invokevirtual com/common/android/utils/http/HttpException/getMessage()Ljava/lang/String;
invokestatic android/util/Log/e(Ljava/lang/String;Ljava/lang/String;)I
pop
goto L16
L17:
aload 1
ldc "code"
invokevirtual org/json/JSONObject/optInt(Ljava/lang/String;)I
sipush 200
if_icmpeq L18
iconst_m1
invokestatic java/lang/Integer/valueOf(I)Ljava/lang/Integer;
areturn
L18:
aload 1
ldc "exp"
invokevirtual org/json/JSONObject/optInt(Ljava/lang/String;)I
istore 2
aload 0
aload 1
ldc "levelup"
invokevirtual org/json/JSONObject/optInt(Ljava/lang/String;)I
putfield com/nd/android/u/tast/experience/adapter/ReceiveExpAdapter$ReceiveExpTask/levelUp I
aload 1
ldc "money"
invokevirtual org/json/JSONObject/optInt(Ljava/lang/String;)I
istore 3
aload 0
getfield com/nd/android/u/tast/experience/adapter/ReceiveExpAdapter$ReceiveExpTask/levelUp I
ifle L19
aconst_null
astore 1
L6:
aload 5
lconst_0
invokevirtual com/nd/android/u/tast/com/AjaxCom/getUserscore(J)Lorg/json/JSONObject;
astore 4
L7:
aload 4
astore 1
L20:
aload 1
ldc "code"
invokestatic com/common/android/utils/JSONUtils/getInt(Lorg/json/JSONObject;Ljava/lang/String;)I
istore 3
aload 1
ifnull L13
iload 3
sipush 200
if_icmpne L13
invokestatic com/nd/android/u/tast/TaskGlobalVariable/getInstance()Lcom/nd/android/u/tast/TaskGlobalVariable;
getfield com/nd/android/u/tast/TaskGlobalVariable/mOapScore Lcom/product/android/commonInterface/task/OapScore;
aload 1
invokevirtual com/product/android/commonInterface/task/OapScore/setScoreData(Lorg/json/JSONObject;)V
L12:
invokestatic com/nd/android/u/tast/com/TaskComFactory/getInstance()Lcom/nd/android/u/tast/com/TaskComFactory;
invokevirtual com/nd/android/u/tast/com/TaskComFactory/getLotteryCom()Lcom/nd/android/u/tast/com/OapLotteryCom;
sipush 10000
invokevirtual com/nd/android/u/tast/com/OapLotteryCom/getItemByType(I)I
istore 3
invokestatic com/nd/android/u/tast/TaskGlobalVariable/getInstance()Lcom/nd/android/u/tast/TaskGlobalVariable;
getfield com/nd/android/u/tast/TaskGlobalVariable/mOapScore Lcom/product/android/commonInterface/task/OapScore;
iload 3
invokevirtual com/product/android/commonInterface/task/OapScore/setLotterychance(I)V
L13:
iload 2
invokestatic java/lang/Integer/valueOf(I)Ljava/lang/Integer;
areturn
L8:
astore 4
aload 4
invokevirtual com/common/android/utils/http/HttpAuthException/printStackTrace()V
goto L20
L9:
astore 4
aload 4
invokevirtual com/common/android/utils/http/ResponseException/printStackTrace()V
goto L20
L10:
astore 4
aload 4
invokevirtual com/common/android/utils/http/HttpServerException/printStackTrace()V
goto L20
L11:
astore 4
aload 4
invokevirtual com/common/android/utils/http/HttpException/printStackTrace()V
goto L20
L14:
astore 1
aload 1
invokevirtual com/common/android/utils/http/ResponseException/printStackTrace()V
goto L13
L15:
astore 1
aload 1
invokevirtual com/common/android/utils/http/HttpException/printStackTrace()V
goto L13
L19:
invokestatic com/nd/android/u/tast/TaskGlobalVariable/getInstance()Lcom/nd/android/u/tast/TaskGlobalVariable;
getfield com/nd/android/u/tast/TaskGlobalVariable/mOapScore Lcom/product/android/commonInterface/task/OapScore;
invokestatic com/nd/android/u/tast/TaskGlobalVariable/getInstance()Lcom/nd/android/u/tast/TaskGlobalVariable;
getfield com/nd/android/u/tast/TaskGlobalVariable/mOapScore Lcom/product/android/commonInterface/task/OapScore;
invokevirtual com/product/android/commonInterface/task/OapScore/getTotalexp()I
iload 2
iadd
invokevirtual com/product/android/commonInterface/task/OapScore/setTotalexp(I)V
invokestatic com/nd/android/u/tast/TaskGlobalVariable/getInstance()Lcom/nd/android/u/tast/TaskGlobalVariable;
getfield com/nd/android/u/tast/TaskGlobalVariable/mOapScore Lcom/product/android/commonInterface/task/OapScore;
invokestatic com/nd/android/u/tast/TaskGlobalVariable/getInstance()Lcom/nd/android/u/tast/TaskGlobalVariable;
getfield com/nd/android/u/tast/TaskGlobalVariable/mOapScore Lcom/product/android/commonInterface/task/OapScore;
invokevirtual com/product/android/commonInterface/task/OapScore/getTotalmoney()I
iload 3
iadd
invokevirtual com/product/android/commonInterface/task/OapScore/setTotalmoney(I)V
goto L13
.limit locals 6
.limit stack 3
.end method

.method protected volatile synthetic doInBackground([Ljava/lang/Object;)Ljava/lang/Object;
aload 0
aload 1
checkcast [Ljava/lang/String;
invokevirtual com/nd/android/u/tast/experience/adapter/ReceiveExpAdapter$ReceiveExpTask/doInBackground([Ljava/lang/String;)Ljava/lang/Integer;
areturn
.limit locals 2
.limit stack 2
.end method

.method protected onPostExecute(Ljava/lang/Integer;)V
aload 0
getfield com/nd/android/u/tast/experience/adapter/ReceiveExpAdapter$ReceiveExpTask/mPD Landroid/app/ProgressDialog;
ifnull L0
aload 0
getfield com/nd/android/u/tast/experience/adapter/ReceiveExpAdapter$ReceiveExpTask/mPD Landroid/app/ProgressDialog;
invokevirtual android/app/ProgressDialog/dismiss()V
aload 0
aconst_null
putfield com/nd/android/u/tast/experience/adapter/ReceiveExpAdapter$ReceiveExpTask/mPD Landroid/app/ProgressDialog;
L0:
aload 1
invokevirtual java/lang/Integer/intValue()I
iconst_m1
if_icmpne L1
aload 0
getfield com/nd/android/u/tast/experience/adapter/ReceiveExpAdapter$ReceiveExpTask/this$0 Lcom/nd/android/u/tast/experience/adapter/ReceiveExpAdapter;
invokestatic com/nd/android/u/tast/experience/adapter/ReceiveExpAdapter/access$300(Lcom/nd/android/u/tast/experience/adapter/ReceiveExpAdapter;)Landroid/content/Context;
ldc "\u9886\u53d6\u5931\u8d25"
iconst_0
invokestatic android/widget/Toast/makeText(Landroid/content/Context;Ljava/lang/CharSequence;I)Landroid/widget/Toast;
invokevirtual android/widget/Toast/show()V
return
L1:
aload 0
getfield com/nd/android/u/tast/experience/adapter/ReceiveExpAdapter$ReceiveExpTask/levelUp I
ifle L2
aload 0
getfield com/nd/android/u/tast/experience/adapter/ReceiveExpAdapter$ReceiveExpTask/this$0 Lcom/nd/android/u/tast/experience/adapter/ReceiveExpAdapter;
invokestatic com/nd/android/u/tast/experience/adapter/ReceiveExpAdapter/access$400(Lcom/nd/android/u/tast/experience/adapter/ReceiveExpAdapter;)Lcom/nd/android/u/tast/experience/adapter/ReceiveExperienceAdapter$OnUpdateLevelListener;
ifnull L2
aload 0
getfield com/nd/android/u/tast/experience/adapter/ReceiveExpAdapter$ReceiveExpTask/this$0 Lcom/nd/android/u/tast/experience/adapter/ReceiveExpAdapter;
invokestatic com/nd/android/u/tast/experience/adapter/ReceiveExpAdapter/access$400(Lcom/nd/android/u/tast/experience/adapter/ReceiveExpAdapter;)Lcom/nd/android/u/tast/experience/adapter/ReceiveExperienceAdapter$OnUpdateLevelListener;
invokeinterface com/nd/android/u/tast/experience/adapter/ReceiveExperienceAdapter$OnUpdateLevelListener/onLevelUpNotify()V 0
L2:
aload 0
getfield com/nd/android/u/tast/experience/adapter/ReceiveExpAdapter$ReceiveExpTask/this$0 Lcom/nd/android/u/tast/experience/adapter/ReceiveExpAdapter;
aload 0
getfield com/nd/android/u/tast/experience/adapter/ReceiveExpAdapter$ReceiveExpTask/itemCode Ljava/lang/String;
aload 0
getfield com/nd/android/u/tast/experience/adapter/ReceiveExpAdapter$ReceiveExpTask/actionId I
invokevirtual com/nd/android/u/tast/experience/adapter/ReceiveExpAdapter/upDate(Ljava/lang/String;I)V
aload 0
getfield com/nd/android/u/tast/experience/adapter/ReceiveExpAdapter$ReceiveExpTask/this$0 Lcom/nd/android/u/tast/experience/adapter/ReceiveExpAdapter;
invokestatic com/nd/android/u/tast/experience/adapter/ReceiveExpAdapter/access$300(Lcom/nd/android/u/tast/experience/adapter/ReceiveExpAdapter;)Landroid/content/Context;
ldc "\u9886\u53d6\u6210\u529f"
iconst_0
invokestatic android/widget/Toast/makeText(Landroid/content/Context;Ljava/lang/CharSequence;I)Landroid/widget/Toast;
invokevirtual android/widget/Toast/show()V
return
.limit locals 2
.limit stack 3
.end method

.method protected volatile synthetic onPostExecute(Ljava/lang/Object;)V
aload 0
aload 1
checkcast java/lang/Integer
invokevirtual com/nd/android/u/tast/experience/adapter/ReceiveExpAdapter$ReceiveExpTask/onPostExecute(Ljava/lang/Integer;)V
return
.limit locals 2
.limit stack 2
.end method

.method protected onPreExecute()V
aload 0
aload 0
getfield com/nd/android/u/tast/experience/adapter/ReceiveExpAdapter$ReceiveExpTask/this$0 Lcom/nd/android/u/tast/experience/adapter/ReceiveExpAdapter;
invokestatic com/nd/android/u/tast/experience/adapter/ReceiveExpAdapter/access$300(Lcom/nd/android/u/tast/experience/adapter/ReceiveExpAdapter;)Landroid/content/Context;
ldc ""
ldc "\u9886\u53d6\u4e2d\uff0c\u8bf7\u7a0d\u5019"
invokestatic android/app/ProgressDialog/show(Landroid/content/Context;Ljava/lang/CharSequence;Ljava/lang/CharSequence;)Landroid/app/ProgressDialog;
putfield com/nd/android/u/tast/experience/adapter/ReceiveExpAdapter$ReceiveExpTask/mPD Landroid/app/ProgressDialog;
return
.limit locals 1
.limit stack 4
.end method
