.bytecode 50.0
.class synchronized com/nd/android/u/cloud/activity/fragment/CheckFragment$1
.super java/lang/Object
.implements android/view/View$OnClickListener
.enclosing method com/nd/android/u/cloud/activity/fragment/CheckFragment/initComponent(Landroid/view/View;)V
.inner class inner com/nd/android/u/cloud/activity/fragment/CheckFragment$1

.field final synthetic 'this$0' Lcom/nd/android/u/cloud/activity/fragment/CheckFragment;

.method <init>(Lcom/nd/android/u/cloud/activity/fragment/CheckFragment;)V
aload 0
aload 1
putfield com/nd/android/u/cloud/activity/fragment/CheckFragment$1/this$0 Lcom/nd/android/u/cloud/activity/fragment/CheckFragment;
aload 0
invokespecial java/lang/Object/<init>()V
return
.limit locals 2
.limit stack 2
.end method

.method public onClick(Landroid/view/View;)V
aload 0
getfield com/nd/android/u/cloud/activity/fragment/CheckFragment$1/this$0 Lcom/nd/android/u/cloud/activity/fragment/CheckFragment;
invokevirtual com/nd/android/u/cloud/activity/fragment/CheckFragment/getActivity()Landroid/support/v4/app/FragmentActivity;
astore 3
aload 0
getfield com/nd/android/u/cloud/activity/fragment/CheckFragment$1/this$0 Lcom/nd/android/u/cloud/activity/fragment/CheckFragment;
invokestatic com/nd/android/u/cloud/activity/fragment/CheckFragment/access$000(Lcom/nd/android/u/cloud/activity/fragment/CheckFragment;)Lcom/nd/android/u/cloud/view/widge/Item_Input;
invokevirtual com/nd/android/u/cloud/view/widge/Item_Input/getValue()Ljava/lang/String;
astore 1
aload 1
invokestatic android/text/TextUtils/isEmpty(Ljava/lang/CharSequence;)Z
ifeq L0
aload 3
ldc_w 2131494697
invokestatic com/common/android/utils/ToastUtils/display(Landroid/content/Context;I)V
return
L0:
aload 0
getfield com/nd/android/u/cloud/activity/fragment/CheckFragment$1/this$0 Lcom/nd/android/u/cloud/activity/fragment/CheckFragment;
invokestatic com/nd/android/u/cloud/activity/fragment/CheckFragment/access$100(Lcom/nd/android/u/cloud/activity/fragment/CheckFragment;)Lcom/nd/android/u/cloud/view/widge/Item_Input;
invokevirtual com/nd/android/u/cloud/view/widge/Item_Input/getValue()Ljava/lang/String;
astore 2
aload 2
invokestatic android/text/TextUtils/isEmpty(Ljava/lang/CharSequence;)Z
ifeq L1
aload 3
ldc_w 2131494698
invokestatic com/common/android/utils/ToastUtils/display(Landroid/content/Context;I)V
return
L1:
aload 0
getfield com/nd/android/u/cloud/activity/fragment/CheckFragment$1/this$0 Lcom/nd/android/u/cloud/activity/fragment/CheckFragment;
invokestatic com/nd/android/u/cloud/activity/fragment/CheckFragment/access$200(Lcom/nd/android/u/cloud/activity/fragment/CheckFragment;)Lcom/nd/android/u/cloud/view/widge/Item_Input;
invokevirtual com/nd/android/u/cloud/view/widge/Item_Input/getValue()Ljava/lang/String;
astore 3
new com/nd/android/u/cloud/activity/fragment/CheckFragment$SubmitCheckTask
dup
aload 0
getfield com/nd/android/u/cloud/activity/fragment/CheckFragment$1/this$0 Lcom/nd/android/u/cloud/activity/fragment/CheckFragment;
invokevirtual com/nd/android/u/cloud/activity/fragment/CheckFragment/getActivity()Landroid/support/v4/app/FragmentActivity;
invokespecial com/nd/android/u/cloud/activity/fragment/CheckFragment$SubmitCheckTask/<init>(Landroid/app/Activity;)V
iconst_3
anewarray java/lang/String
dup
iconst_0
aload 1
aastore
dup
iconst_1
aload 2
aastore
dup
iconst_2
aload 3
aastore
invokevirtual com/nd/android/u/cloud/activity/fragment/CheckFragment$SubmitCheckTask/execute([Ljava/lang/Object;)Lcom/common/android/utils/concurrent/NdTinyHttpAsyncTask;
pop
return
.limit locals 4
.limit stack 5
.end method
