.bytecode 50.0
.class synchronized com/nd/android/u/ui/widge/chatfragment/BottomFragment$6
.super android/os/Handler
.enclosing method com/nd/android/u/ui/widge/chatfragment/BottomFragment
.inner class inner com/nd/android/u/ui/widge/chatfragment/BottomFragment$6

.field final synthetic 'this$0' Lcom/nd/android/u/ui/widge/chatfragment/BottomFragment;

.method <init>(Lcom/nd/android/u/ui/widge/chatfragment/BottomFragment;)V
aload 0
aload 1
putfield com/nd/android/u/ui/widge/chatfragment/BottomFragment$6/this$0 Lcom/nd/android/u/ui/widge/chatfragment/BottomFragment;
aload 0
invokespecial android/os/Handler/<init>()V
return
.limit locals 2
.limit stack 2
.end method

.method public handleMessage(Landroid/os/Message;)V
aload 1
getfield android/os/Message/what I
tableswitch 0
L0
L1
default : L2
L2:
return
L0:
aload 0
getfield com/nd/android/u/ui/widge/chatfragment/BottomFragment$6/this$0 Lcom/nd/android/u/ui/widge/chatfragment/BottomFragment;
invokestatic com/nd/android/u/ui/widge/chatfragment/BottomFragment/access$1000(Lcom/nd/android/u/ui/widge/chatfragment/BottomFragment;)Landroid/widget/GridView;
invokevirtual android/widget/GridView/getVisibility()I
ifne L3
aload 0
getfield com/nd/android/u/ui/widge/chatfragment/BottomFragment$6/this$0 Lcom/nd/android/u/ui/widge/chatfragment/BottomFragment;
invokestatic com/nd/android/u/ui/widge/chatfragment/BottomFragment/access$1000(Lcom/nd/android/u/ui/widge/chatfragment/BottomFragment;)Landroid/widget/GridView;
bipush 8
invokevirtual android/widget/GridView/setVisibility(I)V
return
L3:
aload 0
getfield com/nd/android/u/ui/widge/chatfragment/BottomFragment$6/this$0 Lcom/nd/android/u/ui/widge/chatfragment/BottomFragment;
invokestatic com/nd/android/u/ui/widge/chatfragment/BottomFragment/access$1000(Lcom/nd/android/u/ui/widge/chatfragment/BottomFragment;)Landroid/widget/GridView;
iconst_0
invokevirtual android/widget/GridView/setVisibility(I)V
aload 0
getfield com/nd/android/u/ui/widge/chatfragment/BottomFragment$6/this$0 Lcom/nd/android/u/ui/widge/chatfragment/BottomFragment;
invokestatic com/nd/android/u/ui/widge/chatfragment/BottomFragment/access$1100(Lcom/nd/android/u/ui/widge/chatfragment/BottomFragment;)Lcom/common/android/utils/smiley/SmileyView;
iconst_0
invokevirtual com/common/android/utils/smiley/SmileyView/setShow(Z)V
aload 0
getfield com/nd/android/u/ui/widge/chatfragment/BottomFragment$6/this$0 Lcom/nd/android/u/ui/widge/chatfragment/BottomFragment;
invokestatic com/nd/android/u/ui/widge/chatfragment/BottomFragment/access$000(Lcom/nd/android/u/ui/widge/chatfragment/BottomFragment;)Lcom/common/android/ui/widget/SpenEditText;
invokevirtual com/common/android/ui/widget/SpenEditText/getVisibility()I
bipush 8
if_icmpne L2
aload 0
getfield com/nd/android/u/ui/widge/chatfragment/BottomFragment$6/this$0 Lcom/nd/android/u/ui/widge/chatfragment/BottomFragment;
invokestatic com/nd/android/u/ui/widge/chatfragment/BottomFragment/access$000(Lcom/nd/android/u/ui/widge/chatfragment/BottomFragment;)Lcom/common/android/ui/widget/SpenEditText;
iconst_0
invokevirtual com/common/android/ui/widget/SpenEditText/setVisibility(I)V
aload 0
getfield com/nd/android/u/ui/widge/chatfragment/BottomFragment$6/this$0 Lcom/nd/android/u/ui/widge/chatfragment/BottomFragment;
invokestatic com/nd/android/u/ui/widge/chatfragment/BottomFragment/access$000(Lcom/nd/android/u/ui/widge/chatfragment/BottomFragment;)Lcom/common/android/ui/widget/SpenEditText;
invokevirtual com/common/android/ui/widget/SpenEditText/length()I
ifle L4
aload 0
getfield com/nd/android/u/ui/widge/chatfragment/BottomFragment$6/this$0 Lcom/nd/android/u/ui/widge/chatfragment/BottomFragment;
invokestatic com/nd/android/u/ui/widge/chatfragment/BottomFragment/access$100(Lcom/nd/android/u/ui/widge/chatfragment/BottomFragment;)Landroid/widget/LinearLayout;
bipush 8
invokevirtual android/widget/LinearLayout/setVisibility(I)V
aload 0
getfield com/nd/android/u/ui/widge/chatfragment/BottomFragment$6/this$0 Lcom/nd/android/u/ui/widge/chatfragment/BottomFragment;
invokestatic com/nd/android/u/ui/widge/chatfragment/BottomFragment/access$200(Lcom/nd/android/u/ui/widge/chatfragment/BottomFragment;)Landroid/widget/Button;
iconst_0
invokevirtual android/widget/Button/setVisibility(I)V
L5:
aload 0
getfield com/nd/android/u/ui/widge/chatfragment/BottomFragment$6/this$0 Lcom/nd/android/u/ui/widge/chatfragment/BottomFragment;
invokestatic com/nd/android/u/ui/widge/chatfragment/BottomFragment/access$400(Lcom/nd/android/u/ui/widge/chatfragment/BottomFragment;)Landroid/widget/Button;
bipush 8
invokevirtual android/widget/Button/setVisibility(I)V
aload 0
getfield com/nd/android/u/ui/widge/chatfragment/BottomFragment$6/this$0 Lcom/nd/android/u/ui/widge/chatfragment/BottomFragment;
invokestatic com/nd/android/u/ui/widge/chatfragment/BottomFragment/access$600(Lcom/nd/android/u/ui/widge/chatfragment/BottomFragment;)Landroid/widget/ImageView;
getstatic com/nd/android/u/chat/R$drawable/chat_record_btn I
invokevirtual android/widget/ImageView/setImageResource(I)V
return
L4:
aload 0
getfield com/nd/android/u/ui/widge/chatfragment/BottomFragment$6/this$0 Lcom/nd/android/u/ui/widge/chatfragment/BottomFragment;
invokestatic com/nd/android/u/ui/widge/chatfragment/BottomFragment/access$300(Lcom/nd/android/u/ui/widge/chatfragment/BottomFragment;)Z
ifeq L6
aload 0
getfield com/nd/android/u/ui/widge/chatfragment/BottomFragment$6/this$0 Lcom/nd/android/u/ui/widge/chatfragment/BottomFragment;
invokestatic com/nd/android/u/ui/widge/chatfragment/BottomFragment/access$100(Lcom/nd/android/u/ui/widge/chatfragment/BottomFragment;)Landroid/widget/LinearLayout;
iconst_0
invokevirtual android/widget/LinearLayout/setVisibility(I)V
L6:
aload 0
getfield com/nd/android/u/ui/widge/chatfragment/BottomFragment$6/this$0 Lcom/nd/android/u/ui/widge/chatfragment/BottomFragment;
invokestatic com/nd/android/u/ui/widge/chatfragment/BottomFragment/access$200(Lcom/nd/android/u/ui/widge/chatfragment/BottomFragment;)Landroid/widget/Button;
bipush 8
invokevirtual android/widget/Button/setVisibility(I)V
goto L5
L1:
aload 0
getfield com/nd/android/u/ui/widge/chatfragment/BottomFragment$6/this$0 Lcom/nd/android/u/ui/widge/chatfragment/BottomFragment;
invokevirtual com/nd/android/u/ui/widge/chatfragment/BottomFragment/showSimplyPopWindow()V
aload 0
getfield com/nd/android/u/ui/widge/chatfragment/BottomFragment$6/this$0 Lcom/nd/android/u/ui/widge/chatfragment/BottomFragment;
invokestatic com/nd/android/u/ui/widge/chatfragment/BottomFragment/access$000(Lcom/nd/android/u/ui/widge/chatfragment/BottomFragment;)Lcom/common/android/ui/widget/SpenEditText;
invokevirtual com/common/android/ui/widget/SpenEditText/getVisibility()I
bipush 8
if_icmpne L2
aload 0
getfield com/nd/android/u/ui/widge/chatfragment/BottomFragment$6/this$0 Lcom/nd/android/u/ui/widge/chatfragment/BottomFragment;
invokestatic com/nd/android/u/ui/widge/chatfragment/BottomFragment/access$000(Lcom/nd/android/u/ui/widge/chatfragment/BottomFragment;)Lcom/common/android/ui/widget/SpenEditText;
iconst_0
invokevirtual com/common/android/ui/widget/SpenEditText/setVisibility(I)V
aload 0
getfield com/nd/android/u/ui/widge/chatfragment/BottomFragment$6/this$0 Lcom/nd/android/u/ui/widge/chatfragment/BottomFragment;
invokestatic com/nd/android/u/ui/widge/chatfragment/BottomFragment/access$000(Lcom/nd/android/u/ui/widge/chatfragment/BottomFragment;)Lcom/common/android/ui/widget/SpenEditText;
invokevirtual com/common/android/ui/widget/SpenEditText/length()I
ifle L7
aload 0
getfield com/nd/android/u/ui/widge/chatfragment/BottomFragment$6/this$0 Lcom/nd/android/u/ui/widge/chatfragment/BottomFragment;
invokestatic com/nd/android/u/ui/widge/chatfragment/BottomFragment/access$100(Lcom/nd/android/u/ui/widge/chatfragment/BottomFragment;)Landroid/widget/LinearLayout;
bipush 8
invokevirtual android/widget/LinearLayout/setVisibility(I)V
aload 0
getfield com/nd/android/u/ui/widge/chatfragment/BottomFragment$6/this$0 Lcom/nd/android/u/ui/widge/chatfragment/BottomFragment;
invokestatic com/nd/android/u/ui/widge/chatfragment/BottomFragment/access$200(Lcom/nd/android/u/ui/widge/chatfragment/BottomFragment;)Landroid/widget/Button;
iconst_0
invokevirtual android/widget/Button/setVisibility(I)V
L8:
aload 0
getfield com/nd/android/u/ui/widge/chatfragment/BottomFragment$6/this$0 Lcom/nd/android/u/ui/widge/chatfragment/BottomFragment;
invokestatic com/nd/android/u/ui/widge/chatfragment/BottomFragment/access$400(Lcom/nd/android/u/ui/widge/chatfragment/BottomFragment;)Landroid/widget/Button;
bipush 8
invokevirtual android/widget/Button/setVisibility(I)V
aload 0
getfield com/nd/android/u/ui/widge/chatfragment/BottomFragment$6/this$0 Lcom/nd/android/u/ui/widge/chatfragment/BottomFragment;
aload 0
getfield com/nd/android/u/ui/widge/chatfragment/BottomFragment$6/this$0 Lcom/nd/android/u/ui/widge/chatfragment/BottomFragment;
invokestatic com/nd/android/u/ui/widge/chatfragment/BottomFragment/access$000(Lcom/nd/android/u/ui/widge/chatfragment/BottomFragment;)Lcom/common/android/ui/widget/SpenEditText;
invokestatic com/nd/android/u/ui/widge/chatfragment/BottomFragment/access$500(Lcom/nd/android/u/ui/widge/chatfragment/BottomFragment;Landroid/view/View;)V
aload 0
getfield com/nd/android/u/ui/widge/chatfragment/BottomFragment$6/this$0 Lcom/nd/android/u/ui/widge/chatfragment/BottomFragment;
invokestatic com/nd/android/u/ui/widge/chatfragment/BottomFragment/access$600(Lcom/nd/android/u/ui/widge/chatfragment/BottomFragment;)Landroid/widget/ImageView;
getstatic com/nd/android/u/chat/R$drawable/chat_bt_text_bg I
invokevirtual android/widget/ImageView/setImageResource(I)V
return
L7:
aload 0
getfield com/nd/android/u/ui/widge/chatfragment/BottomFragment$6/this$0 Lcom/nd/android/u/ui/widge/chatfragment/BottomFragment;
invokestatic com/nd/android/u/ui/widge/chatfragment/BottomFragment/access$300(Lcom/nd/android/u/ui/widge/chatfragment/BottomFragment;)Z
ifeq L9
aload 0
getfield com/nd/android/u/ui/widge/chatfragment/BottomFragment$6/this$0 Lcom/nd/android/u/ui/widge/chatfragment/BottomFragment;
invokestatic com/nd/android/u/ui/widge/chatfragment/BottomFragment/access$100(Lcom/nd/android/u/ui/widge/chatfragment/BottomFragment;)Landroid/widget/LinearLayout;
iconst_0
invokevirtual android/widget/LinearLayout/setVisibility(I)V
L9:
aload 0
getfield com/nd/android/u/ui/widge/chatfragment/BottomFragment$6/this$0 Lcom/nd/android/u/ui/widge/chatfragment/BottomFragment;
invokestatic com/nd/android/u/ui/widge/chatfragment/BottomFragment/access$200(Lcom/nd/android/u/ui/widge/chatfragment/BottomFragment;)Landroid/widget/Button;
bipush 8
invokevirtual android/widget/Button/setVisibility(I)V
goto L8
.limit locals 2
.limit stack 2
.end method
