.bytecode 50.0
.class synchronized com/nd/android/u/ui/widge/chatfragment/HeadFragment$3
.super android/os/Handler
.enclosing method com/nd/android/u/ui/widge/chatfragment/HeadFragment
.inner class inner com/nd/android/u/ui/widge/chatfragment/HeadFragment$3

.field final synthetic 'this$0' Lcom/nd/android/u/ui/widge/chatfragment/HeadFragment;

.method <init>(Lcom/nd/android/u/ui/widge/chatfragment/HeadFragment;)V
aload 0
aload 1
putfield com/nd/android/u/ui/widge/chatfragment/HeadFragment$3/this$0 Lcom/nd/android/u/ui/widge/chatfragment/HeadFragment;
aload 0
invokespecial android/os/Handler/<init>()V
return
.limit locals 2
.limit stack 2
.end method

.method public handleMessage(Landroid/os/Message;)V
aload 0
aload 1
invokespecial android/os/Handler/handleMessage(Landroid/os/Message;)V
aload 1
getfield android/os/Message/what I
tableswitch 0
L0
L1
L2
L3
default : L4
L4:
return
L0:
aload 1
invokevirtual android/os/Message/getData()Landroid/os/Bundle;
astore 1
aload 1
ifnonnull L5
aload 0
getfield com/nd/android/u/ui/widge/chatfragment/HeadFragment$3/this$0 Lcom/nd/android/u/ui/widge/chatfragment/HeadFragment;
aconst_null
invokestatic com/nd/android/u/ui/widge/chatfragment/HeadFragment/access$300(Lcom/nd/android/u/ui/widge/chatfragment/HeadFragment;[I)V
return
L5:
aload 0
getfield com/nd/android/u/ui/widge/chatfragment/HeadFragment$3/this$0 Lcom/nd/android/u/ui/widge/chatfragment/HeadFragment;
aload 1
ldc "MULTI_POINTS"
invokevirtual android/os/Bundle/getIntArray(Ljava/lang/String;)[I
invokestatic com/nd/android/u/ui/widge/chatfragment/HeadFragment/access$300(Lcom/nd/android/u/ui/widge/chatfragment/HeadFragment;[I)V
return
L1:
aload 0
getfield com/nd/android/u/ui/widge/chatfragment/HeadFragment$3/this$0 Lcom/nd/android/u/ui/widge/chatfragment/HeadFragment;
invokestatic com/nd/android/u/ui/widge/chatfragment/HeadFragment/access$400(Lcom/nd/android/u/ui/widge/chatfragment/HeadFragment;)Landroid/widget/TextView;
getstatic com/nd/android/u/chat/R$drawable/img_birthday I
iconst_0
iconst_0
iconst_0
invokevirtual android/widget/TextView/setCompoundDrawablesWithIntrinsicBounds(IIII)V
return
L2:
aload 0
getfield com/nd/android/u/ui/widge/chatfragment/HeadFragment$3/this$0 Lcom/nd/android/u/ui/widge/chatfragment/HeadFragment;
invokestatic com/nd/android/u/ui/widge/chatfragment/HeadFragment/access$400(Lcom/nd/android/u/ui/widge/chatfragment/HeadFragment;)Landroid/widget/TextView;
aload 1
getfield android/os/Message/obj Ljava/lang/Object;
checkcast java/lang/String
invokevirtual android/widget/TextView/setText(Ljava/lang/CharSequence;)V
return
L3:
aload 0
getfield com/nd/android/u/ui/widge/chatfragment/HeadFragment$3/this$0 Lcom/nd/android/u/ui/widge/chatfragment/HeadFragment;
invokestatic com/nd/android/u/ui/widge/chatfragment/HeadFragment/access$400(Lcom/nd/android/u/ui/widge/chatfragment/HeadFragment;)Landroid/widget/TextView;
aload 1
getfield android/os/Message/obj Ljava/lang/Object;
checkcast java/lang/String
invokevirtual android/widget/TextView/setText(Ljava/lang/CharSequence;)V
return
.limit locals 2
.limit stack 5
.end method
