.bytecode 50.0
.class synchronized com/nd/android/u/ui/widge/chatfragment/PopQuickReply$1
.super java/lang/Object
.implements android/widget/AdapterView$OnItemClickListener
.enclosing method com/nd/android/u/ui/widge/chatfragment/PopQuickReply
.inner class inner com/nd/android/u/ui/widge/chatfragment/PopQuickReply$1

.field final synthetic 'this$0' Lcom/nd/android/u/ui/widge/chatfragment/PopQuickReply;

.method <init>(Lcom/nd/android/u/ui/widge/chatfragment/PopQuickReply;)V
aload 0
aload 1
putfield com/nd/android/u/ui/widge/chatfragment/PopQuickReply$1/this$0 Lcom/nd/android/u/ui/widge/chatfragment/PopQuickReply;
aload 0
invokespecial java/lang/Object/<init>()V
return
.limit locals 2
.limit stack 2
.end method

.method public onItemClick(Landroid/widget/AdapterView;Landroid/view/View;IJ)V
.signature "(Landroid/widget/AdapterView<*>;Landroid/view/View;IJ)V"
aload 0
getfield com/nd/android/u/ui/widge/chatfragment/PopQuickReply$1/this$0 Lcom/nd/android/u/ui/widge/chatfragment/PopQuickReply;
invokestatic com/nd/android/u/ui/widge/chatfragment/PopQuickReply/access$000(Lcom/nd/android/u/ui/widge/chatfragment/PopQuickReply;)I
ifne L0
iload 3
aload 0
getfield com/nd/android/u/ui/widge/chatfragment/PopQuickReply$1/this$0 Lcom/nd/android/u/ui/widge/chatfragment/PopQuickReply;
invokestatic com/nd/android/u/ui/widge/chatfragment/PopQuickReply/access$100(Lcom/nd/android/u/ui/widge/chatfragment/PopQuickReply;)Lcom/nd/android/u/controller/bean/QuickReplyList;
invokevirtual com/nd/android/u/controller/bean/QuickReplyList/size()I
iconst_1
isub
if_icmpne L0
new android/content/Intent
dup
aload 0
getfield com/nd/android/u/ui/widge/chatfragment/PopQuickReply$1/this$0 Lcom/nd/android/u/ui/widge/chatfragment/PopQuickReply;
invokestatic com/nd/android/u/ui/widge/chatfragment/PopQuickReply/access$200(Lcom/nd/android/u/ui/widge/chatfragment/PopQuickReply;)Landroid/content/Context;
ldc com/nd/android/u/ui/activity/chat_relative_quickreply/QuickReplyAcitivty
invokespecial android/content/Intent/<init>(Landroid/content/Context;Ljava/lang/Class;)V
astore 1
aload 0
getfield com/nd/android/u/ui/widge/chatfragment/PopQuickReply$1/this$0 Lcom/nd/android/u/ui/widge/chatfragment/PopQuickReply;
invokestatic com/nd/android/u/ui/widge/chatfragment/PopQuickReply/access$200(Lcom/nd/android/u/ui/widge/chatfragment/PopQuickReply;)Landroid/content/Context;
checkcast android/app/Activity
aload 1
invokevirtual android/app/Activity/startActivity(Landroid/content/Intent;)V
aload 0
getfield com/nd/android/u/ui/widge/chatfragment/PopQuickReply$1/this$0 Lcom/nd/android/u/ui/widge/chatfragment/PopQuickReply;
iconst_1
invokestatic com/nd/android/u/ui/widge/chatfragment/PopQuickReply/access$302(Lcom/nd/android/u/ui/widge/chatfragment/PopQuickReply;Z)Z
pop
L1:
aload 0
getfield com/nd/android/u/ui/widge/chatfragment/PopQuickReply$1/this$0 Lcom/nd/android/u/ui/widge/chatfragment/PopQuickReply;
invokevirtual com/nd/android/u/ui/widge/chatfragment/PopQuickReply/dismiss()V
return
L0:
aload 0
getfield com/nd/android/u/ui/widge/chatfragment/PopQuickReply$1/this$0 Lcom/nd/android/u/ui/widge/chatfragment/PopQuickReply;
invokestatic com/nd/android/u/ui/widge/chatfragment/PopQuickReply/access$400(Lcom/nd/android/u/ui/widge/chatfragment/PopQuickReply;)Lcom/nd/android/u/ui/widge/chatfragment/PopQuickReply$onItemSelectListener;
ifnull L1
aload 0
getfield com/nd/android/u/ui/widge/chatfragment/PopQuickReply$1/this$0 Lcom/nd/android/u/ui/widge/chatfragment/PopQuickReply;
invokestatic com/nd/android/u/ui/widge/chatfragment/PopQuickReply/access$400(Lcom/nd/android/u/ui/widge/chatfragment/PopQuickReply;)Lcom/nd/android/u/ui/widge/chatfragment/PopQuickReply$onItemSelectListener;
aload 0
getfield com/nd/android/u/ui/widge/chatfragment/PopQuickReply$1/this$0 Lcom/nd/android/u/ui/widge/chatfragment/PopQuickReply;
invokestatic com/nd/android/u/ui/widge/chatfragment/PopQuickReply/access$100(Lcom/nd/android/u/ui/widge/chatfragment/PopQuickReply;)Lcom/nd/android/u/controller/bean/QuickReplyList;
iload 3
invokevirtual com/nd/android/u/controller/bean/QuickReplyList/get(I)Ljava/lang/Object;
checkcast com/nd/android/u/controller/bean/QuickReply
invokevirtual com/nd/android/u/controller/bean/QuickReply/getText()Ljava/lang/String;
invokeinterface com/nd/android/u/ui/widge/chatfragment/PopQuickReply$onItemSelectListener/onItemSelect(Ljava/lang/String;)V 1
goto L1
.limit locals 6
.limit stack 4
.end method
