.bytecode 50.0
.class public final synchronized enum com/nd/teamfile/sdk/type/FileType$MIME_SOURCE
.super java/lang/Enum
.signature "Ljava/lang/Enum<Lcom/nd/teamfile/sdk/type/FileType$MIME_SOURCE;>;"
.inner class public static final enum MIME_SOURCE inner com/nd/teamfile/sdk/type/FileType$MIME_SOURCE outer com/nd/teamfile/sdk/type/FileType

.field private static final synthetic '$VALUES' [Lcom/nd/teamfile/sdk/type/FileType$MIME_SOURCE;

.field public static final enum 'AMR' Lcom/nd/teamfile/sdk/type/FileType$MIME_SOURCE;

.field public static final enum 'APK' Lcom/nd/teamfile/sdk/type/FileType$MIME_SOURCE;

.field public static final enum 'ASF' Lcom/nd/teamfile/sdk/type/FileType$MIME_SOURCE;

.field public static final enum 'AVI' Lcom/nd/teamfile/sdk/type/FileType$MIME_SOURCE;

.field public static final enum 'BIN' Lcom/nd/teamfile/sdk/type/FileType$MIME_SOURCE;

.field public static final enum 'BMP' Lcom/nd/teamfile/sdk/type/FileType$MIME_SOURCE;

.field public static final enum 'C' Lcom/nd/teamfile/sdk/type/FileType$MIME_SOURCE;

.field public static final enum 'CLASS' Lcom/nd/teamfile/sdk/type/FileType$MIME_SOURCE;

.field public static final enum 'CONF' Lcom/nd/teamfile/sdk/type/FileType$MIME_SOURCE;

.field public static final enum 'CPP' Lcom/nd/teamfile/sdk/type/FileType$MIME_SOURCE;

.field public static final enum 'DOC' Lcom/nd/teamfile/sdk/type/FileType$MIME_SOURCE;

.field public static final enum 'DOCX' Lcom/nd/teamfile/sdk/type/FileType$MIME_SOURCE;

.field public static final enum 'EXE' Lcom/nd/teamfile/sdk/type/FileType$MIME_SOURCE;

.field public static final enum 'GIF' Lcom/nd/teamfile/sdk/type/FileType$MIME_SOURCE;

.field public static final enum 'GTAR' Lcom/nd/teamfile/sdk/type/FileType$MIME_SOURCE;

.field public static final enum 'GZ' Lcom/nd/teamfile/sdk/type/FileType$MIME_SOURCE;

.field public static final enum 'H' Lcom/nd/teamfile/sdk/type/FileType$MIME_SOURCE;

.field public static final enum 'HTM' Lcom/nd/teamfile/sdk/type/FileType$MIME_SOURCE;

.field public static final enum 'HTML' Lcom/nd/teamfile/sdk/type/FileType$MIME_SOURCE;

.field public static final enum 'JAR' Lcom/nd/teamfile/sdk/type/FileType$MIME_SOURCE;

.field public static final enum 'JAVA' Lcom/nd/teamfile/sdk/type/FileType$MIME_SOURCE;

.field public static final enum 'JPE' Lcom/nd/teamfile/sdk/type/FileType$MIME_SOURCE;

.field public static final enum 'JPEG' Lcom/nd/teamfile/sdk/type/FileType$MIME_SOURCE;

.field public static final enum 'JPG' Lcom/nd/teamfile/sdk/type/FileType$MIME_SOURCE;

.field public static final enum 'JS' Lcom/nd/teamfile/sdk/type/FileType$MIME_SOURCE;

.field public static final enum 'LOG' Lcom/nd/teamfile/sdk/type/FileType$MIME_SOURCE;

.field public static final enum 'M3U' Lcom/nd/teamfile/sdk/type/FileType$MIME_SOURCE;

.field public static final enum 'M4A' Lcom/nd/teamfile/sdk/type/FileType$MIME_SOURCE;

.field public static final enum 'M4B' Lcom/nd/teamfile/sdk/type/FileType$MIME_SOURCE;

.field public static final enum 'M4P' Lcom/nd/teamfile/sdk/type/FileType$MIME_SOURCE;

.field public static final enum 'M4U' Lcom/nd/teamfile/sdk/type/FileType$MIME_SOURCE;

.field public static final enum 'M4V' Lcom/nd/teamfile/sdk/type/FileType$MIME_SOURCE;

.field public static final enum 'MOV' Lcom/nd/teamfile/sdk/type/FileType$MIME_SOURCE;

.field public static final enum 'MP2' Lcom/nd/teamfile/sdk/type/FileType$MIME_SOURCE;

.field public static final enum 'MP3' Lcom/nd/teamfile/sdk/type/FileType$MIME_SOURCE;

.field public static final enum 'MP4' Lcom/nd/teamfile/sdk/type/FileType$MIME_SOURCE;

.field public static final enum 'MPC' Lcom/nd/teamfile/sdk/type/FileType$MIME_SOURCE;

.field public static final enum 'MPE' Lcom/nd/teamfile/sdk/type/FileType$MIME_SOURCE;

.field public static final enum 'MPEG' Lcom/nd/teamfile/sdk/type/FileType$MIME_SOURCE;

.field public static final enum 'MPEGA' Lcom/nd/teamfile/sdk/type/FileType$MIME_SOURCE;

.field public static final enum 'MPG' Lcom/nd/teamfile/sdk/type/FileType$MIME_SOURCE;

.field public static final enum 'MPG4' Lcom/nd/teamfile/sdk/type/FileType$MIME_SOURCE;

.field public static final enum 'MPGA' Lcom/nd/teamfile/sdk/type/FileType$MIME_SOURCE;

.field public static final enum 'MSG' Lcom/nd/teamfile/sdk/type/FileType$MIME_SOURCE;

.field public static final enum 'OGG' Lcom/nd/teamfile/sdk/type/FileType$MIME_SOURCE;

.field public static final enum 'PDF' Lcom/nd/teamfile/sdk/type/FileType$MIME_SOURCE;

.field public static final enum 'PNG' Lcom/nd/teamfile/sdk/type/FileType$MIME_SOURCE;

.field public static final enum 'PPS' Lcom/nd/teamfile/sdk/type/FileType$MIME_SOURCE;

.field public static final enum 'PPT' Lcom/nd/teamfile/sdk/type/FileType$MIME_SOURCE;

.field public static final enum 'PROP' Lcom/nd/teamfile/sdk/type/FileType$MIME_SOURCE;

.field public static final enum 'PSD' Lcom/nd/teamfile/sdk/type/FileType$MIME_SOURCE;

.field public static final enum 'RAR' Lcom/nd/teamfile/sdk/type/FileType$MIME_SOURCE;

.field public static final enum 'RC' Lcom/nd/teamfile/sdk/type/FileType$MIME_SOURCE;

.field public static final enum 'RM' Lcom/nd/teamfile/sdk/type/FileType$MIME_SOURCE;

.field public static final enum 'RMVB' Lcom/nd/teamfile/sdk/type/FileType$MIME_SOURCE;

.field public static final enum 'RSS' Lcom/nd/teamfile/sdk/type/FileType$MIME_SOURCE;

.field public static final enum 'RTF' Lcom/nd/teamfile/sdk/type/FileType$MIME_SOURCE;

.field public static final enum 'SH' Lcom/nd/teamfile/sdk/type/FileType$MIME_SOURCE;

.field public static final enum 'TAR' Lcom/nd/teamfile/sdk/type/FileType$MIME_SOURCE;

.field public static final enum 'TAZ' Lcom/nd/teamfile/sdk/type/FileType$MIME_SOURCE;

.field public static final enum 'TEXT' Lcom/nd/teamfile/sdk/type/FileType$MIME_SOURCE;

.field public static final enum 'TGZ' Lcom/nd/teamfile/sdk/type/FileType$MIME_SOURCE;

.field public static final enum 'TORRENT' Lcom/nd/teamfile/sdk/type/FileType$MIME_SOURCE;

.field public static final enum 'TXT' Lcom/nd/teamfile/sdk/type/FileType$MIME_SOURCE;

.field public static final enum 'VOB' Lcom/nd/teamfile/sdk/type/FileType$MIME_SOURCE;

.field public static final enum 'VSD' Lcom/nd/teamfile/sdk/type/FileType$MIME_SOURCE;

.field public static final enum 'WAV' Lcom/nd/teamfile/sdk/type/FileType$MIME_SOURCE;

.field public static final enum 'WBMP' Lcom/nd/teamfile/sdk/type/FileType$MIME_SOURCE;

.field public static final enum 'WMA' Lcom/nd/teamfile/sdk/type/FileType$MIME_SOURCE;

.field public static final enum 'WMV' Lcom/nd/teamfile/sdk/type/FileType$MIME_SOURCE;

.field public static final enum 'WPS' Lcom/nd/teamfile/sdk/type/FileType$MIME_SOURCE;

.field public static final enum 'XHTML' Lcom/nd/teamfile/sdk/type/FileType$MIME_SOURCE;

.field public static final enum 'XLS' Lcom/nd/teamfile/sdk/type/FileType$MIME_SOURCE;

.field public static final enum 'XLT' Lcom/nd/teamfile/sdk/type/FileType$MIME_SOURCE;

.field public static final enum 'XML' Lcom/nd/teamfile/sdk/type/FileType$MIME_SOURCE;

.field public static final enum 'Z' Lcom/nd/teamfile/sdk/type/FileType$MIME_SOURCE;

.field public static final enum 'ZIP' Lcom/nd/teamfile/sdk/type/FileType$MIME_SOURCE;

.field public static final enum '_3G2' Lcom/nd/teamfile/sdk/type/FileType$MIME_SOURCE;

.field public static final enum '_3GP' Lcom/nd/teamfile/sdk/type/FileType$MIME_SOURCE;

.field public static final enum '_3GPP' Lcom/nd/teamfile/sdk/type/FileType$MIME_SOURCE;

.field 'largeSourceId' I

.field 'mimeType' Ljava/lang/String;

.field 'sourceId' I

.method static <clinit>()V
new com/nd/teamfile/sdk/type/FileType$MIME_SOURCE
dup
ldc "TAZ"
iconst_0
ldc "application/x-gtar"
getstatic com/nd/teamfile/R$drawable/zip I
getstatic com/nd/teamfile/R$drawable/large_zip_type_icon I
invokespecial com/nd/teamfile/sdk/type/FileType$MIME_SOURCE/<init>(Ljava/lang/String;ILjava/lang/String;II)V
putstatic com/nd/teamfile/sdk/type/FileType$MIME_SOURCE/TAZ Lcom/nd/teamfile/sdk/type/FileType$MIME_SOURCE;
new com/nd/teamfile/sdk/type/FileType$MIME_SOURCE
dup
ldc "XHTML"
iconst_1
ldc "application/xhtml+xml"
getstatic com/nd/teamfile/R$drawable/file I
getstatic com/nd/teamfile/R$drawable/large_file_type_icon I
invokespecial com/nd/teamfile/sdk/type/FileType$MIME_SOURCE/<init>(Ljava/lang/String;ILjava/lang/String;II)V
putstatic com/nd/teamfile/sdk/type/FileType$MIME_SOURCE/XHTML Lcom/nd/teamfile/sdk/type/FileType$MIME_SOURCE;
new com/nd/teamfile/sdk/type/FileType$MIME_SOURCE
dup
ldc "_3GPP"
iconst_2
ldc "audio/3gpp"
getstatic com/nd/teamfile/R$drawable/music I
getstatic com/nd/teamfile/R$drawable/large_music_type_icon I
invokespecial com/nd/teamfile/sdk/type/FileType$MIME_SOURCE/<init>(Ljava/lang/String;ILjava/lang/String;II)V
putstatic com/nd/teamfile/sdk/type/FileType$MIME_SOURCE/_3GPP Lcom/nd/teamfile/sdk/type/FileType$MIME_SOURCE;
new com/nd/teamfile/sdk/type/FileType$MIME_SOURCE
dup
ldc "AMR"
iconst_3
ldc "audio/amr"
getstatic com/nd/teamfile/R$drawable/music I
getstatic com/nd/teamfile/R$drawable/large_music_type_icon I
invokespecial com/nd/teamfile/sdk/type/FileType$MIME_SOURCE/<init>(Ljava/lang/String;ILjava/lang/String;II)V
putstatic com/nd/teamfile/sdk/type/FileType$MIME_SOURCE/AMR Lcom/nd/teamfile/sdk/type/FileType$MIME_SOURCE;
new com/nd/teamfile/sdk/type/FileType$MIME_SOURCE
dup
ldc "MPEGA"
iconst_4
ldc "audio/mpeg"
getstatic com/nd/teamfile/R$drawable/photo I
getstatic com/nd/teamfile/R$drawable/large_photo_type_icon I
invokespecial com/nd/teamfile/sdk/type/FileType$MIME_SOURCE/<init>(Ljava/lang/String;ILjava/lang/String;II)V
putstatic com/nd/teamfile/sdk/type/FileType$MIME_SOURCE/MPEGA Lcom/nd/teamfile/sdk/type/FileType$MIME_SOURCE;
new com/nd/teamfile/sdk/type/FileType$MIME_SOURCE
dup
ldc "RM"
iconst_5
ldc "audio/x-pn-realaudio"
getstatic com/nd/teamfile/R$drawable/unknow I
getstatic com/nd/teamfile/R$drawable/large_unknown_type_icon I
invokespecial com/nd/teamfile/sdk/type/FileType$MIME_SOURCE/<init>(Ljava/lang/String;ILjava/lang/String;II)V
putstatic com/nd/teamfile/sdk/type/FileType$MIME_SOURCE/RM Lcom/nd/teamfile/sdk/type/FileType$MIME_SOURCE;
new com/nd/teamfile/sdk/type/FileType$MIME_SOURCE
dup
ldc "JPE"
bipush 6
ldc "image/jpeg"
getstatic com/nd/teamfile/R$drawable/photo I
getstatic com/nd/teamfile/R$drawable/large_photo_type_icon I
invokespecial com/nd/teamfile/sdk/type/FileType$MIME_SOURCE/<init>(Ljava/lang/String;ILjava/lang/String;II)V
putstatic com/nd/teamfile/sdk/type/FileType$MIME_SOURCE/JPE Lcom/nd/teamfile/sdk/type/FileType$MIME_SOURCE;
new com/nd/teamfile/sdk/type/FileType$MIME_SOURCE
dup
ldc "WBMP"
bipush 7
ldc "image/vnd.wap.wbmp"
getstatic com/nd/teamfile/R$drawable/photo I
getstatic com/nd/teamfile/R$drawable/large_photo_type_icon I
invokespecial com/nd/teamfile/sdk/type/FileType$MIME_SOURCE/<init>(Ljava/lang/String;ILjava/lang/String;II)V
putstatic com/nd/teamfile/sdk/type/FileType$MIME_SOURCE/WBMP Lcom/nd/teamfile/sdk/type/FileType$MIME_SOURCE;
new com/nd/teamfile/sdk/type/FileType$MIME_SOURCE
dup
ldc "PSD"
bipush 8
ldc "image/x-photoshop"
getstatic com/nd/teamfile/R$drawable/photo I
getstatic com/nd/teamfile/R$drawable/large_photo_type_icon I
invokespecial com/nd/teamfile/sdk/type/FileType$MIME_SOURCE/<init>(Ljava/lang/String;ILjava/lang/String;II)V
putstatic com/nd/teamfile/sdk/type/FileType$MIME_SOURCE/PSD Lcom/nd/teamfile/sdk/type/FileType$MIME_SOURCE;
new com/nd/teamfile/sdk/type/FileType$MIME_SOURCE
dup
ldc "TEXT"
bipush 9
ldc "text/plain"
getstatic com/nd/teamfile/R$drawable/file I
getstatic com/nd/teamfile/R$drawable/large_file_type_icon I
invokespecial com/nd/teamfile/sdk/type/FileType$MIME_SOURCE/<init>(Ljava/lang/String;ILjava/lang/String;II)V
putstatic com/nd/teamfile/sdk/type/FileType$MIME_SOURCE/TEXT Lcom/nd/teamfile/sdk/type/FileType$MIME_SOURCE;
new com/nd/teamfile/sdk/type/FileType$MIME_SOURCE
dup
ldc "_3G2"
bipush 10
ldc "video/3gpp"
getstatic com/nd/teamfile/R$drawable/unknow I
getstatic com/nd/teamfile/R$drawable/large_unknown_type_icon I
invokespecial com/nd/teamfile/sdk/type/FileType$MIME_SOURCE/<init>(Ljava/lang/String;ILjava/lang/String;II)V
putstatic com/nd/teamfile/sdk/type/FileType$MIME_SOURCE/_3G2 Lcom/nd/teamfile/sdk/type/FileType$MIME_SOURCE;
new com/nd/teamfile/sdk/type/FileType$MIME_SOURCE
dup
ldc "VOB"
bipush 11
ldc "video/mpeg"
getstatic com/nd/teamfile/R$drawable/music I
getstatic com/nd/teamfile/R$drawable/large_music_type_icon I
invokespecial com/nd/teamfile/sdk/type/FileType$MIME_SOURCE/<init>(Ljava/lang/String;ILjava/lang/String;II)V
putstatic com/nd/teamfile/sdk/type/FileType$MIME_SOURCE/VOB Lcom/nd/teamfile/sdk/type/FileType$MIME_SOURCE;
new com/nd/teamfile/sdk/type/FileType$MIME_SOURCE
dup
ldc "RSS"
bipush 12
ldc "application/rss+xml"
getstatic com/nd/teamfile/R$drawable/file I
getstatic com/nd/teamfile/R$drawable/large_file_type_icon I
invokespecial com/nd/teamfile/sdk/type/FileType$MIME_SOURCE/<init>(Ljava/lang/String;ILjava/lang/String;II)V
putstatic com/nd/teamfile/sdk/type/FileType$MIME_SOURCE/RSS Lcom/nd/teamfile/sdk/type/FileType$MIME_SOURCE;
new com/nd/teamfile/sdk/type/FileType$MIME_SOURCE
dup
ldc "DOCX"
bipush 13
ldc "application/vnd.openxmlformats-officedocument.wordprocessingml.document"
getstatic com/nd/teamfile/R$drawable/word I
getstatic com/nd/teamfile/R$drawable/large_word_type_icon I
invokespecial com/nd/teamfile/sdk/type/FileType$MIME_SOURCE/<init>(Ljava/lang/String;ILjava/lang/String;II)V
putstatic com/nd/teamfile/sdk/type/FileType$MIME_SOURCE/DOCX Lcom/nd/teamfile/sdk/type/FileType$MIME_SOURCE;
new com/nd/teamfile/sdk/type/FileType$MIME_SOURCE
dup
ldc "XLS"
bipush 14
ldc "application/vnd.ms-excel"
getstatic com/nd/teamfile/R$drawable/excel I
getstatic com/nd/teamfile/R$drawable/large_excel_type_icon I
invokespecial com/nd/teamfile/sdk/type/FileType$MIME_SOURCE/<init>(Ljava/lang/String;ILjava/lang/String;II)V
putstatic com/nd/teamfile/sdk/type/FileType$MIME_SOURCE/XLS Lcom/nd/teamfile/sdk/type/FileType$MIME_SOURCE;
new com/nd/teamfile/sdk/type/FileType$MIME_SOURCE
dup
ldc "XLT"
bipush 15
ldc "application/vnd.ms-excel"
getstatic com/nd/teamfile/R$drawable/excel I
getstatic com/nd/teamfile/R$drawable/large_excel_type_icon I
invokespecial com/nd/teamfile/sdk/type/FileType$MIME_SOURCE/<init>(Ljava/lang/String;ILjava/lang/String;II)V
putstatic com/nd/teamfile/sdk/type/FileType$MIME_SOURCE/XLT Lcom/nd/teamfile/sdk/type/FileType$MIME_SOURCE;
new com/nd/teamfile/sdk/type/FileType$MIME_SOURCE
dup
ldc "VSD"
bipush 16
ldc "application/vnd.visio"
getstatic com/nd/teamfile/R$drawable/unknow I
getstatic com/nd/teamfile/R$drawable/large_unknown_type_icon I
invokespecial com/nd/teamfile/sdk/type/FileType$MIME_SOURCE/<init>(Ljava/lang/String;ILjava/lang/String;II)V
putstatic com/nd/teamfile/sdk/type/FileType$MIME_SOURCE/VSD Lcom/nd/teamfile/sdk/type/FileType$MIME_SOURCE;
new com/nd/teamfile/sdk/type/FileType$MIME_SOURCE
dup
ldc "TORRENT"
bipush 17
ldc "application/x-bittorrent"
getstatic com/nd/teamfile/R$drawable/file I
getstatic com/nd/teamfile/R$drawable/large_file_type_icon I
invokespecial com/nd/teamfile/sdk/type/FileType$MIME_SOURCE/<init>(Ljava/lang/String;ILjava/lang/String;II)V
putstatic com/nd/teamfile/sdk/type/FileType$MIME_SOURCE/TORRENT Lcom/nd/teamfile/sdk/type/FileType$MIME_SOURCE;
new com/nd/teamfile/sdk/type/FileType$MIME_SOURCE
dup
ldc "_3GP"
bipush 18
ldc "video/3gpp"
getstatic com/nd/teamfile/R$drawable/music I
getstatic com/nd/teamfile/R$drawable/large_music_type_icon I
invokespecial com/nd/teamfile/sdk/type/FileType$MIME_SOURCE/<init>(Ljava/lang/String;ILjava/lang/String;II)V
putstatic com/nd/teamfile/sdk/type/FileType$MIME_SOURCE/_3GP Lcom/nd/teamfile/sdk/type/FileType$MIME_SOURCE;
new com/nd/teamfile/sdk/type/FileType$MIME_SOURCE
dup
ldc "APK"
bipush 19
ldc "application/vnd.android.package-archive"
getstatic com/nd/teamfile/R$drawable/app I
getstatic com/nd/teamfile/R$drawable/large_app_type_icon I
invokespecial com/nd/teamfile/sdk/type/FileType$MIME_SOURCE/<init>(Ljava/lang/String;ILjava/lang/String;II)V
putstatic com/nd/teamfile/sdk/type/FileType$MIME_SOURCE/APK Lcom/nd/teamfile/sdk/type/FileType$MIME_SOURCE;
new com/nd/teamfile/sdk/type/FileType$MIME_SOURCE
dup
ldc "ASF"
bipush 20
ldc "video/x-ms-asf"
getstatic com/nd/teamfile/R$drawable/music I
getstatic com/nd/teamfile/R$drawable/large_music_type_icon I
invokespecial com/nd/teamfile/sdk/type/FileType$MIME_SOURCE/<init>(Ljava/lang/String;ILjava/lang/String;II)V
putstatic com/nd/teamfile/sdk/type/FileType$MIME_SOURCE/ASF Lcom/nd/teamfile/sdk/type/FileType$MIME_SOURCE;
new com/nd/teamfile/sdk/type/FileType$MIME_SOURCE
dup
ldc "AVI"
bipush 21
ldc "video/x-msvideo"
getstatic com/nd/teamfile/R$drawable/music I
getstatic com/nd/teamfile/R$drawable/large_music_type_icon I
invokespecial com/nd/teamfile/sdk/type/FileType$MIME_SOURCE/<init>(Ljava/lang/String;ILjava/lang/String;II)V
putstatic com/nd/teamfile/sdk/type/FileType$MIME_SOURCE/AVI Lcom/nd/teamfile/sdk/type/FileType$MIME_SOURCE;
new com/nd/teamfile/sdk/type/FileType$MIME_SOURCE
dup
ldc "BIN"
bipush 22
ldc "application/octet-stream"
getstatic com/nd/teamfile/R$drawable/file I
getstatic com/nd/teamfile/R$drawable/large_file_type_icon I
invokespecial com/nd/teamfile/sdk/type/FileType$MIME_SOURCE/<init>(Ljava/lang/String;ILjava/lang/String;II)V
putstatic com/nd/teamfile/sdk/type/FileType$MIME_SOURCE/BIN Lcom/nd/teamfile/sdk/type/FileType$MIME_SOURCE;
new com/nd/teamfile/sdk/type/FileType$MIME_SOURCE
dup
ldc "BMP"
bipush 23
ldc "image/bmp"
getstatic com/nd/teamfile/R$drawable/photo I
getstatic com/nd/teamfile/R$drawable/large_photo_type_icon I
invokespecial com/nd/teamfile/sdk/type/FileType$MIME_SOURCE/<init>(Ljava/lang/String;ILjava/lang/String;II)V
putstatic com/nd/teamfile/sdk/type/FileType$MIME_SOURCE/BMP Lcom/nd/teamfile/sdk/type/FileType$MIME_SOURCE;
new com/nd/teamfile/sdk/type/FileType$MIME_SOURCE
dup
ldc "C"
bipush 24
ldc "text/plain"
getstatic com/nd/teamfile/R$drawable/txt I
getstatic com/nd/teamfile/R$drawable/large_txt_type_icon I
invokespecial com/nd/teamfile/sdk/type/FileType$MIME_SOURCE/<init>(Ljava/lang/String;ILjava/lang/String;II)V
putstatic com/nd/teamfile/sdk/type/FileType$MIME_SOURCE/C Lcom/nd/teamfile/sdk/type/FileType$MIME_SOURCE;
new com/nd/teamfile/sdk/type/FileType$MIME_SOURCE
dup
ldc "CLASS"
bipush 25
ldc "application/octet-stream"
getstatic com/nd/teamfile/R$drawable/file I
getstatic com/nd/teamfile/R$drawable/large_file_type_icon I
invokespecial com/nd/teamfile/sdk/type/FileType$MIME_SOURCE/<init>(Ljava/lang/String;ILjava/lang/String;II)V
putstatic com/nd/teamfile/sdk/type/FileType$MIME_SOURCE/CLASS Lcom/nd/teamfile/sdk/type/FileType$MIME_SOURCE;
new com/nd/teamfile/sdk/type/FileType$MIME_SOURCE
dup
ldc "CONF"
bipush 26
ldc "text/plain"
getstatic com/nd/teamfile/R$drawable/txt I
getstatic com/nd/teamfile/R$drawable/large_txt_type_icon I
invokespecial com/nd/teamfile/sdk/type/FileType$MIME_SOURCE/<init>(Ljava/lang/String;ILjava/lang/String;II)V
putstatic com/nd/teamfile/sdk/type/FileType$MIME_SOURCE/CONF Lcom/nd/teamfile/sdk/type/FileType$MIME_SOURCE;
new com/nd/teamfile/sdk/type/FileType$MIME_SOURCE
dup
ldc "CPP"
bipush 27
ldc "text/plain"
getstatic com/nd/teamfile/R$drawable/txt I
getstatic com/nd/teamfile/R$drawable/large_txt_type_icon I
invokespecial com/nd/teamfile/sdk/type/FileType$MIME_SOURCE/<init>(Ljava/lang/String;ILjava/lang/String;II)V
putstatic com/nd/teamfile/sdk/type/FileType$MIME_SOURCE/CPP Lcom/nd/teamfile/sdk/type/FileType$MIME_SOURCE;
new com/nd/teamfile/sdk/type/FileType$MIME_SOURCE
dup
ldc "DOC"
bipush 28
ldc "application/msword"
getstatic com/nd/teamfile/R$drawable/word I
getstatic com/nd/teamfile/R$drawable/large_word_type_icon I
invokespecial com/nd/teamfile/sdk/type/FileType$MIME_SOURCE/<init>(Ljava/lang/String;ILjava/lang/String;II)V
putstatic com/nd/teamfile/sdk/type/FileType$MIME_SOURCE/DOC Lcom/nd/teamfile/sdk/type/FileType$MIME_SOURCE;
new com/nd/teamfile/sdk/type/FileType$MIME_SOURCE
dup
ldc "EXE"
bipush 29
ldc "application/octet-stream"
getstatic com/nd/teamfile/R$drawable/app I
getstatic com/nd/teamfile/R$drawable/large_app_type_icon I
invokespecial com/nd/teamfile/sdk/type/FileType$MIME_SOURCE/<init>(Ljava/lang/String;ILjava/lang/String;II)V
putstatic com/nd/teamfile/sdk/type/FileType$MIME_SOURCE/EXE Lcom/nd/teamfile/sdk/type/FileType$MIME_SOURCE;
new com/nd/teamfile/sdk/type/FileType$MIME_SOURCE
dup
ldc "GIF"
bipush 30
ldc "image/gif"
getstatic com/nd/teamfile/R$drawable/photo I
getstatic com/nd/teamfile/R$drawable/large_photo_type_icon I
invokespecial com/nd/teamfile/sdk/type/FileType$MIME_SOURCE/<init>(Ljava/lang/String;ILjava/lang/String;II)V
putstatic com/nd/teamfile/sdk/type/FileType$MIME_SOURCE/GIF Lcom/nd/teamfile/sdk/type/FileType$MIME_SOURCE;
new com/nd/teamfile/sdk/type/FileType$MIME_SOURCE
dup
ldc "GTAR"
bipush 31
ldc "application/x-gtar"
getstatic com/nd/teamfile/R$drawable/zip I
getstatic com/nd/teamfile/R$drawable/large_zip_type_icon I
invokespecial com/nd/teamfile/sdk/type/FileType$MIME_SOURCE/<init>(Ljava/lang/String;ILjava/lang/String;II)V
putstatic com/nd/teamfile/sdk/type/FileType$MIME_SOURCE/GTAR Lcom/nd/teamfile/sdk/type/FileType$MIME_SOURCE;
new com/nd/teamfile/sdk/type/FileType$MIME_SOURCE
dup
ldc "GZ"
bipush 32
ldc "application/x-gzip"
getstatic com/nd/teamfile/R$drawable/zip I
getstatic com/nd/teamfile/R$drawable/large_zip_type_icon I
invokespecial com/nd/teamfile/sdk/type/FileType$MIME_SOURCE/<init>(Ljava/lang/String;ILjava/lang/String;II)V
putstatic com/nd/teamfile/sdk/type/FileType$MIME_SOURCE/GZ Lcom/nd/teamfile/sdk/type/FileType$MIME_SOURCE;
new com/nd/teamfile/sdk/type/FileType$MIME_SOURCE
dup
ldc "H"
bipush 33
ldc "text/plain"
getstatic com/nd/teamfile/R$drawable/txt I
getstatic com/nd/teamfile/R$drawable/large_txt_type_icon I
invokespecial com/nd/teamfile/sdk/type/FileType$MIME_SOURCE/<init>(Ljava/lang/String;ILjava/lang/String;II)V
putstatic com/nd/teamfile/sdk/type/FileType$MIME_SOURCE/H Lcom/nd/teamfile/sdk/type/FileType$MIME_SOURCE;
new com/nd/teamfile/sdk/type/FileType$MIME_SOURCE
dup
ldc "HTM"
bipush 34
ldc "text/html"
getstatic com/nd/teamfile/R$drawable/txt I
getstatic com/nd/teamfile/R$drawable/large_txt_type_icon I
invokespecial com/nd/teamfile/sdk/type/FileType$MIME_SOURCE/<init>(Ljava/lang/String;ILjava/lang/String;II)V
putstatic com/nd/teamfile/sdk/type/FileType$MIME_SOURCE/HTM Lcom/nd/teamfile/sdk/type/FileType$MIME_SOURCE;
new com/nd/teamfile/sdk/type/FileType$MIME_SOURCE
dup
ldc "HTML"
bipush 35
ldc "text/html"
getstatic com/nd/teamfile/R$drawable/txt I
getstatic com/nd/teamfile/R$drawable/large_txt_type_icon I
invokespecial com/nd/teamfile/sdk/type/FileType$MIME_SOURCE/<init>(Ljava/lang/String;ILjava/lang/String;II)V
putstatic com/nd/teamfile/sdk/type/FileType$MIME_SOURCE/HTML Lcom/nd/teamfile/sdk/type/FileType$MIME_SOURCE;
new com/nd/teamfile/sdk/type/FileType$MIME_SOURCE
dup
ldc "JAR"
bipush 36
ldc "application/java-archive"
getstatic com/nd/teamfile/R$drawable/zip I
getstatic com/nd/teamfile/R$drawable/large_zip_type_icon I
invokespecial com/nd/teamfile/sdk/type/FileType$MIME_SOURCE/<init>(Ljava/lang/String;ILjava/lang/String;II)V
putstatic com/nd/teamfile/sdk/type/FileType$MIME_SOURCE/JAR Lcom/nd/teamfile/sdk/type/FileType$MIME_SOURCE;
new com/nd/teamfile/sdk/type/FileType$MIME_SOURCE
dup
ldc "JAVA"
bipush 37
ldc "text/plain"
getstatic com/nd/teamfile/R$drawable/txt I
getstatic com/nd/teamfile/R$drawable/large_txt_type_icon I
invokespecial com/nd/teamfile/sdk/type/FileType$MIME_SOURCE/<init>(Ljava/lang/String;ILjava/lang/String;II)V
putstatic com/nd/teamfile/sdk/type/FileType$MIME_SOURCE/JAVA Lcom/nd/teamfile/sdk/type/FileType$MIME_SOURCE;
new com/nd/teamfile/sdk/type/FileType$MIME_SOURCE
dup
ldc "JPEG"
bipush 38
ldc "image/jpeg"
getstatic com/nd/teamfile/R$drawable/photo I
getstatic com/nd/teamfile/R$drawable/large_photo_type_icon I
invokespecial com/nd/teamfile/sdk/type/FileType$MIME_SOURCE/<init>(Ljava/lang/String;ILjava/lang/String;II)V
putstatic com/nd/teamfile/sdk/type/FileType$MIME_SOURCE/JPEG Lcom/nd/teamfile/sdk/type/FileType$MIME_SOURCE;
new com/nd/teamfile/sdk/type/FileType$MIME_SOURCE
dup
ldc "JPG"
bipush 39
ldc "image/jpeg"
getstatic com/nd/teamfile/R$drawable/photo I
getstatic com/nd/teamfile/R$drawable/large_photo_type_icon I
invokespecial com/nd/teamfile/sdk/type/FileType$MIME_SOURCE/<init>(Ljava/lang/String;ILjava/lang/String;II)V
putstatic com/nd/teamfile/sdk/type/FileType$MIME_SOURCE/JPG Lcom/nd/teamfile/sdk/type/FileType$MIME_SOURCE;
new com/nd/teamfile/sdk/type/FileType$MIME_SOURCE
dup
ldc "JS"
bipush 40
ldc "application/x-javascript"
getstatic com/nd/teamfile/R$drawable/file I
getstatic com/nd/teamfile/R$drawable/large_file_type_icon I
invokespecial com/nd/teamfile/sdk/type/FileType$MIME_SOURCE/<init>(Ljava/lang/String;ILjava/lang/String;II)V
putstatic com/nd/teamfile/sdk/type/FileType$MIME_SOURCE/JS Lcom/nd/teamfile/sdk/type/FileType$MIME_SOURCE;
new com/nd/teamfile/sdk/type/FileType$MIME_SOURCE
dup
ldc "LOG"
bipush 41
ldc "text/plain"
getstatic com/nd/teamfile/R$drawable/txt I
getstatic com/nd/teamfile/R$drawable/large_txt_type_icon I
invokespecial com/nd/teamfile/sdk/type/FileType$MIME_SOURCE/<init>(Ljava/lang/String;ILjava/lang/String;II)V
putstatic com/nd/teamfile/sdk/type/FileType$MIME_SOURCE/LOG Lcom/nd/teamfile/sdk/type/FileType$MIME_SOURCE;
new com/nd/teamfile/sdk/type/FileType$MIME_SOURCE
dup
ldc "M3U"
bipush 42
ldc "audio/x-mpegurl"
getstatic com/nd/teamfile/R$drawable/music I
getstatic com/nd/teamfile/R$drawable/large_music_type_icon I
invokespecial com/nd/teamfile/sdk/type/FileType$MIME_SOURCE/<init>(Ljava/lang/String;ILjava/lang/String;II)V
putstatic com/nd/teamfile/sdk/type/FileType$MIME_SOURCE/M3U Lcom/nd/teamfile/sdk/type/FileType$MIME_SOURCE;
new com/nd/teamfile/sdk/type/FileType$MIME_SOURCE
dup
ldc "M4A"
bipush 43
ldc "audio/mp4a-latm"
getstatic com/nd/teamfile/R$drawable/music I
getstatic com/nd/teamfile/R$drawable/large_music_type_icon I
invokespecial com/nd/teamfile/sdk/type/FileType$MIME_SOURCE/<init>(Ljava/lang/String;ILjava/lang/String;II)V
putstatic com/nd/teamfile/sdk/type/FileType$MIME_SOURCE/M4A Lcom/nd/teamfile/sdk/type/FileType$MIME_SOURCE;
new com/nd/teamfile/sdk/type/FileType$MIME_SOURCE
dup
ldc "M4B"
bipush 44
ldc "audio/mp4a-latm"
getstatic com/nd/teamfile/R$drawable/music I
getstatic com/nd/teamfile/R$drawable/large_music_type_icon I
invokespecial com/nd/teamfile/sdk/type/FileType$MIME_SOURCE/<init>(Ljava/lang/String;ILjava/lang/String;II)V
putstatic com/nd/teamfile/sdk/type/FileType$MIME_SOURCE/M4B Lcom/nd/teamfile/sdk/type/FileType$MIME_SOURCE;
new com/nd/teamfile/sdk/type/FileType$MIME_SOURCE
dup
ldc "M4P"
bipush 45
ldc "audio/mp4a-latm"
getstatic com/nd/teamfile/R$drawable/music I
getstatic com/nd/teamfile/R$drawable/large_music_type_icon I
invokespecial com/nd/teamfile/sdk/type/FileType$MIME_SOURCE/<init>(Ljava/lang/String;ILjava/lang/String;II)V
putstatic com/nd/teamfile/sdk/type/FileType$MIME_SOURCE/M4P Lcom/nd/teamfile/sdk/type/FileType$MIME_SOURCE;
new com/nd/teamfile/sdk/type/FileType$MIME_SOURCE
dup
ldc "M4U"
bipush 46
ldc "video/vnd.mpegurl"
getstatic com/nd/teamfile/R$drawable/music I
getstatic com/nd/teamfile/R$drawable/large_music_type_icon I
invokespecial com/nd/teamfile/sdk/type/FileType$MIME_SOURCE/<init>(Ljava/lang/String;ILjava/lang/String;II)V
putstatic com/nd/teamfile/sdk/type/FileType$MIME_SOURCE/M4U Lcom/nd/teamfile/sdk/type/FileType$MIME_SOURCE;
new com/nd/teamfile/sdk/type/FileType$MIME_SOURCE
dup
ldc "M4V"
bipush 47
ldc "video/x-m4v"
getstatic com/nd/teamfile/R$drawable/music I
getstatic com/nd/teamfile/R$drawable/large_music_type_icon I
invokespecial com/nd/teamfile/sdk/type/FileType$MIME_SOURCE/<init>(Ljava/lang/String;ILjava/lang/String;II)V
putstatic com/nd/teamfile/sdk/type/FileType$MIME_SOURCE/M4V Lcom/nd/teamfile/sdk/type/FileType$MIME_SOURCE;
new com/nd/teamfile/sdk/type/FileType$MIME_SOURCE
dup
ldc "MOV"
bipush 48
ldc "video/quicktime"
getstatic com/nd/teamfile/R$drawable/music I
getstatic com/nd/teamfile/R$drawable/large_music_type_icon I
invokespecial com/nd/teamfile/sdk/type/FileType$MIME_SOURCE/<init>(Ljava/lang/String;ILjava/lang/String;II)V
putstatic com/nd/teamfile/sdk/type/FileType$MIME_SOURCE/MOV Lcom/nd/teamfile/sdk/type/FileType$MIME_SOURCE;
new com/nd/teamfile/sdk/type/FileType$MIME_SOURCE
dup
ldc "MP2"
bipush 49
ldc "audio/x-mpeg"
getstatic com/nd/teamfile/R$drawable/music I
getstatic com/nd/teamfile/R$drawable/large_music_type_icon I
invokespecial com/nd/teamfile/sdk/type/FileType$MIME_SOURCE/<init>(Ljava/lang/String;ILjava/lang/String;II)V
putstatic com/nd/teamfile/sdk/type/FileType$MIME_SOURCE/MP2 Lcom/nd/teamfile/sdk/type/FileType$MIME_SOURCE;
new com/nd/teamfile/sdk/type/FileType$MIME_SOURCE
dup
ldc "MP3"
bipush 50
ldc "audio/x-mpeg"
getstatic com/nd/teamfile/R$drawable/music I
getstatic com/nd/teamfile/R$drawable/large_music_type_icon I
invokespecial com/nd/teamfile/sdk/type/FileType$MIME_SOURCE/<init>(Ljava/lang/String;ILjava/lang/String;II)V
putstatic com/nd/teamfile/sdk/type/FileType$MIME_SOURCE/MP3 Lcom/nd/teamfile/sdk/type/FileType$MIME_SOURCE;
new com/nd/teamfile/sdk/type/FileType$MIME_SOURCE
dup
ldc "MP4"
bipush 51
ldc "video/mp4"
getstatic com/nd/teamfile/R$drawable/music I
getstatic com/nd/teamfile/R$drawable/large_music_type_icon I
invokespecial com/nd/teamfile/sdk/type/FileType$MIME_SOURCE/<init>(Ljava/lang/String;ILjava/lang/String;II)V
putstatic com/nd/teamfile/sdk/type/FileType$MIME_SOURCE/MP4 Lcom/nd/teamfile/sdk/type/FileType$MIME_SOURCE;
new com/nd/teamfile/sdk/type/FileType$MIME_SOURCE
dup
ldc "MPC"
bipush 52
ldc "application/vnd.mpohun.certificate"
getstatic com/nd/teamfile/R$drawable/file I
getstatic com/nd/teamfile/R$drawable/large_file_type_icon I
invokespecial com/nd/teamfile/sdk/type/FileType$MIME_SOURCE/<init>(Ljava/lang/String;ILjava/lang/String;II)V
putstatic com/nd/teamfile/sdk/type/FileType$MIME_SOURCE/MPC Lcom/nd/teamfile/sdk/type/FileType$MIME_SOURCE;
new com/nd/teamfile/sdk/type/FileType$MIME_SOURCE
dup
ldc "MPE"
bipush 53
ldc "video/mpeg"
getstatic com/nd/teamfile/R$drawable/music I
getstatic com/nd/teamfile/R$drawable/large_music_type_icon I
invokespecial com/nd/teamfile/sdk/type/FileType$MIME_SOURCE/<init>(Ljava/lang/String;ILjava/lang/String;II)V
putstatic com/nd/teamfile/sdk/type/FileType$MIME_SOURCE/MPE Lcom/nd/teamfile/sdk/type/FileType$MIME_SOURCE;
new com/nd/teamfile/sdk/type/FileType$MIME_SOURCE
dup
ldc "MPEG"
bipush 54
ldc "video/mpeg"
getstatic com/nd/teamfile/R$drawable/music I
getstatic com/nd/teamfile/R$drawable/large_music_type_icon I
invokespecial com/nd/teamfile/sdk/type/FileType$MIME_SOURCE/<init>(Ljava/lang/String;ILjava/lang/String;II)V
putstatic com/nd/teamfile/sdk/type/FileType$MIME_SOURCE/MPEG Lcom/nd/teamfile/sdk/type/FileType$MIME_SOURCE;
new com/nd/teamfile/sdk/type/FileType$MIME_SOURCE
dup
ldc "MPG"
bipush 55
ldc "video/mpeg"
getstatic com/nd/teamfile/R$drawable/music I
getstatic com/nd/teamfile/R$drawable/large_music_type_icon I
invokespecial com/nd/teamfile/sdk/type/FileType$MIME_SOURCE/<init>(Ljava/lang/String;ILjava/lang/String;II)V
putstatic com/nd/teamfile/sdk/type/FileType$MIME_SOURCE/MPG Lcom/nd/teamfile/sdk/type/FileType$MIME_SOURCE;
new com/nd/teamfile/sdk/type/FileType$MIME_SOURCE
dup
ldc "MPG4"
bipush 56
ldc "video/mp4"
getstatic com/nd/teamfile/R$drawable/music I
getstatic com/nd/teamfile/R$drawable/large_music_type_icon I
invokespecial com/nd/teamfile/sdk/type/FileType$MIME_SOURCE/<init>(Ljava/lang/String;ILjava/lang/String;II)V
putstatic com/nd/teamfile/sdk/type/FileType$MIME_SOURCE/MPG4 Lcom/nd/teamfile/sdk/type/FileType$MIME_SOURCE;
new com/nd/teamfile/sdk/type/FileType$MIME_SOURCE
dup
ldc "MPGA"
bipush 57
ldc "audio/mpeg"
getstatic com/nd/teamfile/R$drawable/music I
getstatic com/nd/teamfile/R$drawable/large_music_type_icon I
invokespecial com/nd/teamfile/sdk/type/FileType$MIME_SOURCE/<init>(Ljava/lang/String;ILjava/lang/String;II)V
putstatic com/nd/teamfile/sdk/type/FileType$MIME_SOURCE/MPGA Lcom/nd/teamfile/sdk/type/FileType$MIME_SOURCE;
new com/nd/teamfile/sdk/type/FileType$MIME_SOURCE
dup
ldc "MSG"
bipush 58
ldc "application/vnd.ms-outlook"
getstatic com/nd/teamfile/R$drawable/file I
getstatic com/nd/teamfile/R$drawable/large_file_type_icon I
invokespecial com/nd/teamfile/sdk/type/FileType$MIME_SOURCE/<init>(Ljava/lang/String;ILjava/lang/String;II)V
putstatic com/nd/teamfile/sdk/type/FileType$MIME_SOURCE/MSG Lcom/nd/teamfile/sdk/type/FileType$MIME_SOURCE;
new com/nd/teamfile/sdk/type/FileType$MIME_SOURCE
dup
ldc "OGG"
bipush 59
ldc "audio/ogg"
getstatic com/nd/teamfile/R$drawable/music I
getstatic com/nd/teamfile/R$drawable/large_music_type_icon I
invokespecial com/nd/teamfile/sdk/type/FileType$MIME_SOURCE/<init>(Ljava/lang/String;ILjava/lang/String;II)V
putstatic com/nd/teamfile/sdk/type/FileType$MIME_SOURCE/OGG Lcom/nd/teamfile/sdk/type/FileType$MIME_SOURCE;
new com/nd/teamfile/sdk/type/FileType$MIME_SOURCE
dup
ldc "PDF"
bipush 60
ldc "application/pdf"
getstatic com/nd/teamfile/R$drawable/pdf I
getstatic com/nd/teamfile/R$drawable/large_pdf_type_icon I
invokespecial com/nd/teamfile/sdk/type/FileType$MIME_SOURCE/<init>(Ljava/lang/String;ILjava/lang/String;II)V
putstatic com/nd/teamfile/sdk/type/FileType$MIME_SOURCE/PDF Lcom/nd/teamfile/sdk/type/FileType$MIME_SOURCE;
new com/nd/teamfile/sdk/type/FileType$MIME_SOURCE
dup
ldc "PNG"
bipush 61
ldc "image/png"
getstatic com/nd/teamfile/R$drawable/photo I
getstatic com/nd/teamfile/R$drawable/large_photo_type_icon I
invokespecial com/nd/teamfile/sdk/type/FileType$MIME_SOURCE/<init>(Ljava/lang/String;ILjava/lang/String;II)V
putstatic com/nd/teamfile/sdk/type/FileType$MIME_SOURCE/PNG Lcom/nd/teamfile/sdk/type/FileType$MIME_SOURCE;
new com/nd/teamfile/sdk/type/FileType$MIME_SOURCE
dup
ldc "PPS"
bipush 62
ldc "application/vnd.ms-powerpoint"
getstatic com/nd/teamfile/R$drawable/file I
getstatic com/nd/teamfile/R$drawable/large_file_type_icon I
invokespecial com/nd/teamfile/sdk/type/FileType$MIME_SOURCE/<init>(Ljava/lang/String;ILjava/lang/String;II)V
putstatic com/nd/teamfile/sdk/type/FileType$MIME_SOURCE/PPS Lcom/nd/teamfile/sdk/type/FileType$MIME_SOURCE;
new com/nd/teamfile/sdk/type/FileType$MIME_SOURCE
dup
ldc "PPT"
bipush 63
ldc "application/vnd.ms-powerpoint"
getstatic com/nd/teamfile/R$drawable/ppt I
getstatic com/nd/teamfile/R$drawable/large_ppt_type_icon I
invokespecial com/nd/teamfile/sdk/type/FileType$MIME_SOURCE/<init>(Ljava/lang/String;ILjava/lang/String;II)V
putstatic com/nd/teamfile/sdk/type/FileType$MIME_SOURCE/PPT Lcom/nd/teamfile/sdk/type/FileType$MIME_SOURCE;
new com/nd/teamfile/sdk/type/FileType$MIME_SOURCE
dup
ldc "PROP"
bipush 64
ldc "text/plain"
getstatic com/nd/teamfile/R$drawable/txt I
getstatic com/nd/teamfile/R$drawable/large_txt_type_icon I
invokespecial com/nd/teamfile/sdk/type/FileType$MIME_SOURCE/<init>(Ljava/lang/String;ILjava/lang/String;II)V
putstatic com/nd/teamfile/sdk/type/FileType$MIME_SOURCE/PROP Lcom/nd/teamfile/sdk/type/FileType$MIME_SOURCE;
new com/nd/teamfile/sdk/type/FileType$MIME_SOURCE
dup
ldc "RAR"
bipush 65
ldc "application/x-rar-compressed"
getstatic com/nd/teamfile/R$drawable/file I
getstatic com/nd/teamfile/R$drawable/large_file_type_icon I
invokespecial com/nd/teamfile/sdk/type/FileType$MIME_SOURCE/<init>(Ljava/lang/String;ILjava/lang/String;II)V
putstatic com/nd/teamfile/sdk/type/FileType$MIME_SOURCE/RAR Lcom/nd/teamfile/sdk/type/FileType$MIME_SOURCE;
new com/nd/teamfile/sdk/type/FileType$MIME_SOURCE
dup
ldc "RC"
bipush 66
ldc "text/plain"
getstatic com/nd/teamfile/R$drawable/txt I
getstatic com/nd/teamfile/R$drawable/large_txt_type_icon I
invokespecial com/nd/teamfile/sdk/type/FileType$MIME_SOURCE/<init>(Ljava/lang/String;ILjava/lang/String;II)V
putstatic com/nd/teamfile/sdk/type/FileType$MIME_SOURCE/RC Lcom/nd/teamfile/sdk/type/FileType$MIME_SOURCE;
new com/nd/teamfile/sdk/type/FileType$MIME_SOURCE
dup
ldc "RMVB"
bipush 67
ldc "audio/x-pn-realaudio"
getstatic com/nd/teamfile/R$drawable/music I
getstatic com/nd/teamfile/R$drawable/large_music_type_icon I
invokespecial com/nd/teamfile/sdk/type/FileType$MIME_SOURCE/<init>(Ljava/lang/String;ILjava/lang/String;II)V
putstatic com/nd/teamfile/sdk/type/FileType$MIME_SOURCE/RMVB Lcom/nd/teamfile/sdk/type/FileType$MIME_SOURCE;
new com/nd/teamfile/sdk/type/FileType$MIME_SOURCE
dup
ldc "RTF"
bipush 68
ldc "application/rtf"
getstatic com/nd/teamfile/R$drawable/file I
getstatic com/nd/teamfile/R$drawable/large_file_type_icon I
invokespecial com/nd/teamfile/sdk/type/FileType$MIME_SOURCE/<init>(Ljava/lang/String;ILjava/lang/String;II)V
putstatic com/nd/teamfile/sdk/type/FileType$MIME_SOURCE/RTF Lcom/nd/teamfile/sdk/type/FileType$MIME_SOURCE;
new com/nd/teamfile/sdk/type/FileType$MIME_SOURCE
dup
ldc "SH"
bipush 69
ldc "text/plain"
getstatic com/nd/teamfile/R$drawable/txt I
getstatic com/nd/teamfile/R$drawable/large_txt_type_icon I
invokespecial com/nd/teamfile/sdk/type/FileType$MIME_SOURCE/<init>(Ljava/lang/String;ILjava/lang/String;II)V
putstatic com/nd/teamfile/sdk/type/FileType$MIME_SOURCE/SH Lcom/nd/teamfile/sdk/type/FileType$MIME_SOURCE;
new com/nd/teamfile/sdk/type/FileType$MIME_SOURCE
dup
ldc "TAR"
bipush 70
ldc "application/x-tar"
getstatic com/nd/teamfile/R$drawable/file I
getstatic com/nd/teamfile/R$drawable/large_file_type_icon I
invokespecial com/nd/teamfile/sdk/type/FileType$MIME_SOURCE/<init>(Ljava/lang/String;ILjava/lang/String;II)V
putstatic com/nd/teamfile/sdk/type/FileType$MIME_SOURCE/TAR Lcom/nd/teamfile/sdk/type/FileType$MIME_SOURCE;
new com/nd/teamfile/sdk/type/FileType$MIME_SOURCE
dup
ldc "TGZ"
bipush 71
ldc "application/x-compressed"
getstatic com/nd/teamfile/R$drawable/zip I
getstatic com/nd/teamfile/R$drawable/large_zip_type_icon I
invokespecial com/nd/teamfile/sdk/type/FileType$MIME_SOURCE/<init>(Ljava/lang/String;ILjava/lang/String;II)V
putstatic com/nd/teamfile/sdk/type/FileType$MIME_SOURCE/TGZ Lcom/nd/teamfile/sdk/type/FileType$MIME_SOURCE;
new com/nd/teamfile/sdk/type/FileType$MIME_SOURCE
dup
ldc "TXT"
bipush 72
ldc "text/plain"
getstatic com/nd/teamfile/R$drawable/txt I
getstatic com/nd/teamfile/R$drawable/large_txt_type_icon I
invokespecial com/nd/teamfile/sdk/type/FileType$MIME_SOURCE/<init>(Ljava/lang/String;ILjava/lang/String;II)V
putstatic com/nd/teamfile/sdk/type/FileType$MIME_SOURCE/TXT Lcom/nd/teamfile/sdk/type/FileType$MIME_SOURCE;
new com/nd/teamfile/sdk/type/FileType$MIME_SOURCE
dup
ldc "WAV"
bipush 73
ldc "audio/x-wav"
getstatic com/nd/teamfile/R$drawable/music I
getstatic com/nd/teamfile/R$drawable/large_music_type_icon I
invokespecial com/nd/teamfile/sdk/type/FileType$MIME_SOURCE/<init>(Ljava/lang/String;ILjava/lang/String;II)V
putstatic com/nd/teamfile/sdk/type/FileType$MIME_SOURCE/WAV Lcom/nd/teamfile/sdk/type/FileType$MIME_SOURCE;
new com/nd/teamfile/sdk/type/FileType$MIME_SOURCE
dup
ldc "WMA"
bipush 74
ldc "audio/x-ms-wma"
getstatic com/nd/teamfile/R$drawable/music I
getstatic com/nd/teamfile/R$drawable/large_music_type_icon I
invokespecial com/nd/teamfile/sdk/type/FileType$MIME_SOURCE/<init>(Ljava/lang/String;ILjava/lang/String;II)V
putstatic com/nd/teamfile/sdk/type/FileType$MIME_SOURCE/WMA Lcom/nd/teamfile/sdk/type/FileType$MIME_SOURCE;
new com/nd/teamfile/sdk/type/FileType$MIME_SOURCE
dup
ldc "WMV"
bipush 75
ldc "audio/x-ms-wmv"
getstatic com/nd/teamfile/R$drawable/music I
getstatic com/nd/teamfile/R$drawable/large_music_type_icon I
invokespecial com/nd/teamfile/sdk/type/FileType$MIME_SOURCE/<init>(Ljava/lang/String;ILjava/lang/String;II)V
putstatic com/nd/teamfile/sdk/type/FileType$MIME_SOURCE/WMV Lcom/nd/teamfile/sdk/type/FileType$MIME_SOURCE;
new com/nd/teamfile/sdk/type/FileType$MIME_SOURCE
dup
ldc "WPS"
bipush 76
ldc "application/vnd.ms-works"
getstatic com/nd/teamfile/R$drawable/file I
getstatic com/nd/teamfile/R$drawable/large_file_type_icon I
invokespecial com/nd/teamfile/sdk/type/FileType$MIME_SOURCE/<init>(Ljava/lang/String;ILjava/lang/String;II)V
putstatic com/nd/teamfile/sdk/type/FileType$MIME_SOURCE/WPS Lcom/nd/teamfile/sdk/type/FileType$MIME_SOURCE;
new com/nd/teamfile/sdk/type/FileType$MIME_SOURCE
dup
ldc "XML"
bipush 77
ldc "text/plain"
getstatic com/nd/teamfile/R$drawable/txt I
getstatic com/nd/teamfile/R$drawable/large_txt_type_icon I
invokespecial com/nd/teamfile/sdk/type/FileType$MIME_SOURCE/<init>(Ljava/lang/String;ILjava/lang/String;II)V
putstatic com/nd/teamfile/sdk/type/FileType$MIME_SOURCE/XML Lcom/nd/teamfile/sdk/type/FileType$MIME_SOURCE;
new com/nd/teamfile/sdk/type/FileType$MIME_SOURCE
dup
ldc "Z"
bipush 78
ldc "application/x-compress"
getstatic com/nd/teamfile/R$drawable/zip I
getstatic com/nd/teamfile/R$drawable/large_zip_type_icon I
invokespecial com/nd/teamfile/sdk/type/FileType$MIME_SOURCE/<init>(Ljava/lang/String;ILjava/lang/String;II)V
putstatic com/nd/teamfile/sdk/type/FileType$MIME_SOURCE/Z Lcom/nd/teamfile/sdk/type/FileType$MIME_SOURCE;
new com/nd/teamfile/sdk/type/FileType$MIME_SOURCE
dup
ldc "ZIP"
bipush 79
ldc "application/zip"
getstatic com/nd/teamfile/R$drawable/zip I
getstatic com/nd/teamfile/R$drawable/large_zip_type_icon I
invokespecial com/nd/teamfile/sdk/type/FileType$MIME_SOURCE/<init>(Ljava/lang/String;ILjava/lang/String;II)V
putstatic com/nd/teamfile/sdk/type/FileType$MIME_SOURCE/ZIP Lcom/nd/teamfile/sdk/type/FileType$MIME_SOURCE;
bipush 80
anewarray com/nd/teamfile/sdk/type/FileType$MIME_SOURCE
dup
iconst_0
getstatic com/nd/teamfile/sdk/type/FileType$MIME_SOURCE/TAZ Lcom/nd/teamfile/sdk/type/FileType$MIME_SOURCE;
aastore
dup
iconst_1
getstatic com/nd/teamfile/sdk/type/FileType$MIME_SOURCE/XHTML Lcom/nd/teamfile/sdk/type/FileType$MIME_SOURCE;
aastore
dup
iconst_2
getstatic com/nd/teamfile/sdk/type/FileType$MIME_SOURCE/_3GPP Lcom/nd/teamfile/sdk/type/FileType$MIME_SOURCE;
aastore
dup
iconst_3
getstatic com/nd/teamfile/sdk/type/FileType$MIME_SOURCE/AMR Lcom/nd/teamfile/sdk/type/FileType$MIME_SOURCE;
aastore
dup
iconst_4
getstatic com/nd/teamfile/sdk/type/FileType$MIME_SOURCE/MPEGA Lcom/nd/teamfile/sdk/type/FileType$MIME_SOURCE;
aastore
dup
iconst_5
getstatic com/nd/teamfile/sdk/type/FileType$MIME_SOURCE/RM Lcom/nd/teamfile/sdk/type/FileType$MIME_SOURCE;
aastore
dup
bipush 6
getstatic com/nd/teamfile/sdk/type/FileType$MIME_SOURCE/JPE Lcom/nd/teamfile/sdk/type/FileType$MIME_SOURCE;
aastore
dup
bipush 7
getstatic com/nd/teamfile/sdk/type/FileType$MIME_SOURCE/WBMP Lcom/nd/teamfile/sdk/type/FileType$MIME_SOURCE;
aastore
dup
bipush 8
getstatic com/nd/teamfile/sdk/type/FileType$MIME_SOURCE/PSD Lcom/nd/teamfile/sdk/type/FileType$MIME_SOURCE;
aastore
dup
bipush 9
getstatic com/nd/teamfile/sdk/type/FileType$MIME_SOURCE/TEXT Lcom/nd/teamfile/sdk/type/FileType$MIME_SOURCE;
aastore
dup
bipush 10
getstatic com/nd/teamfile/sdk/type/FileType$MIME_SOURCE/_3G2 Lcom/nd/teamfile/sdk/type/FileType$MIME_SOURCE;
aastore
dup
bipush 11
getstatic com/nd/teamfile/sdk/type/FileType$MIME_SOURCE/VOB Lcom/nd/teamfile/sdk/type/FileType$MIME_SOURCE;
aastore
dup
bipush 12
getstatic com/nd/teamfile/sdk/type/FileType$MIME_SOURCE/RSS Lcom/nd/teamfile/sdk/type/FileType$MIME_SOURCE;
aastore
dup
bipush 13
getstatic com/nd/teamfile/sdk/type/FileType$MIME_SOURCE/DOCX Lcom/nd/teamfile/sdk/type/FileType$MIME_SOURCE;
aastore
dup
bipush 14
getstatic com/nd/teamfile/sdk/type/FileType$MIME_SOURCE/XLS Lcom/nd/teamfile/sdk/type/FileType$MIME_SOURCE;
aastore
dup
bipush 15
getstatic com/nd/teamfile/sdk/type/FileType$MIME_SOURCE/XLT Lcom/nd/teamfile/sdk/type/FileType$MIME_SOURCE;
aastore
dup
bipush 16
getstatic com/nd/teamfile/sdk/type/FileType$MIME_SOURCE/VSD Lcom/nd/teamfile/sdk/type/FileType$MIME_SOURCE;
aastore
dup
bipush 17
getstatic com/nd/teamfile/sdk/type/FileType$MIME_SOURCE/TORRENT Lcom/nd/teamfile/sdk/type/FileType$MIME_SOURCE;
aastore
dup
bipush 18
getstatic com/nd/teamfile/sdk/type/FileType$MIME_SOURCE/_3GP Lcom/nd/teamfile/sdk/type/FileType$MIME_SOURCE;
aastore
dup
bipush 19
getstatic com/nd/teamfile/sdk/type/FileType$MIME_SOURCE/APK Lcom/nd/teamfile/sdk/type/FileType$MIME_SOURCE;
aastore
dup
bipush 20
getstatic com/nd/teamfile/sdk/type/FileType$MIME_SOURCE/ASF Lcom/nd/teamfile/sdk/type/FileType$MIME_SOURCE;
aastore
dup
bipush 21
getstatic com/nd/teamfile/sdk/type/FileType$MIME_SOURCE/AVI Lcom/nd/teamfile/sdk/type/FileType$MIME_SOURCE;
aastore
dup
bipush 22
getstatic com/nd/teamfile/sdk/type/FileType$MIME_SOURCE/BIN Lcom/nd/teamfile/sdk/type/FileType$MIME_SOURCE;
aastore
dup
bipush 23
getstatic com/nd/teamfile/sdk/type/FileType$MIME_SOURCE/BMP Lcom/nd/teamfile/sdk/type/FileType$MIME_SOURCE;
aastore
dup
bipush 24
getstatic com/nd/teamfile/sdk/type/FileType$MIME_SOURCE/C Lcom/nd/teamfile/sdk/type/FileType$MIME_SOURCE;
aastore
dup
bipush 25
getstatic com/nd/teamfile/sdk/type/FileType$MIME_SOURCE/CLASS Lcom/nd/teamfile/sdk/type/FileType$MIME_SOURCE;
aastore
dup
bipush 26
getstatic com/nd/teamfile/sdk/type/FileType$MIME_SOURCE/CONF Lcom/nd/teamfile/sdk/type/FileType$MIME_SOURCE;
aastore
dup
bipush 27
getstatic com/nd/teamfile/sdk/type/FileType$MIME_SOURCE/CPP Lcom/nd/teamfile/sdk/type/FileType$MIME_SOURCE;
aastore
dup
bipush 28
getstatic com/nd/teamfile/sdk/type/FileType$MIME_SOURCE/DOC Lcom/nd/teamfile/sdk/type/FileType$MIME_SOURCE;
aastore
dup
bipush 29
getstatic com/nd/teamfile/sdk/type/FileType$MIME_SOURCE/EXE Lcom/nd/teamfile/sdk/type/FileType$MIME_SOURCE;
aastore
dup
bipush 30
getstatic com/nd/teamfile/sdk/type/FileType$MIME_SOURCE/GIF Lcom/nd/teamfile/sdk/type/FileType$MIME_SOURCE;
aastore
dup
bipush 31
getstatic com/nd/teamfile/sdk/type/FileType$MIME_SOURCE/GTAR Lcom/nd/teamfile/sdk/type/FileType$MIME_SOURCE;
aastore
dup
bipush 32
getstatic com/nd/teamfile/sdk/type/FileType$MIME_SOURCE/GZ Lcom/nd/teamfile/sdk/type/FileType$MIME_SOURCE;
aastore
dup
bipush 33
getstatic com/nd/teamfile/sdk/type/FileType$MIME_SOURCE/H Lcom/nd/teamfile/sdk/type/FileType$MIME_SOURCE;
aastore
dup
bipush 34
getstatic com/nd/teamfile/sdk/type/FileType$MIME_SOURCE/HTM Lcom/nd/teamfile/sdk/type/FileType$MIME_SOURCE;
aastore
dup
bipush 35
getstatic com/nd/teamfile/sdk/type/FileType$MIME_SOURCE/HTML Lcom/nd/teamfile/sdk/type/FileType$MIME_SOURCE;
aastore
dup
bipush 36
getstatic com/nd/teamfile/sdk/type/FileType$MIME_SOURCE/JAR Lcom/nd/teamfile/sdk/type/FileType$MIME_SOURCE;
aastore
dup
bipush 37
getstatic com/nd/teamfile/sdk/type/FileType$MIME_SOURCE/JAVA Lcom/nd/teamfile/sdk/type/FileType$MIME_SOURCE;
aastore
dup
bipush 38
getstatic com/nd/teamfile/sdk/type/FileType$MIME_SOURCE/JPEG Lcom/nd/teamfile/sdk/type/FileType$MIME_SOURCE;
aastore
dup
bipush 39
getstatic com/nd/teamfile/sdk/type/FileType$MIME_SOURCE/JPG Lcom/nd/teamfile/sdk/type/FileType$MIME_SOURCE;
aastore
dup
bipush 40
getstatic com/nd/teamfile/sdk/type/FileType$MIME_SOURCE/JS Lcom/nd/teamfile/sdk/type/FileType$MIME_SOURCE;
aastore
dup
bipush 41
getstatic com/nd/teamfile/sdk/type/FileType$MIME_SOURCE/LOG Lcom/nd/teamfile/sdk/type/FileType$MIME_SOURCE;
aastore
dup
bipush 42
getstatic com/nd/teamfile/sdk/type/FileType$MIME_SOURCE/M3U Lcom/nd/teamfile/sdk/type/FileType$MIME_SOURCE;
aastore
dup
bipush 43
getstatic com/nd/teamfile/sdk/type/FileType$MIME_SOURCE/M4A Lcom/nd/teamfile/sdk/type/FileType$MIME_SOURCE;
aastore
dup
bipush 44
getstatic com/nd/teamfile/sdk/type/FileType$MIME_SOURCE/M4B Lcom/nd/teamfile/sdk/type/FileType$MIME_SOURCE;
aastore
dup
bipush 45
getstatic com/nd/teamfile/sdk/type/FileType$MIME_SOURCE/M4P Lcom/nd/teamfile/sdk/type/FileType$MIME_SOURCE;
aastore
dup
bipush 46
getstatic com/nd/teamfile/sdk/type/FileType$MIME_SOURCE/M4U Lcom/nd/teamfile/sdk/type/FileType$MIME_SOURCE;
aastore
dup
bipush 47
getstatic com/nd/teamfile/sdk/type/FileType$MIME_SOURCE/M4V Lcom/nd/teamfile/sdk/type/FileType$MIME_SOURCE;
aastore
dup
bipush 48
getstatic com/nd/teamfile/sdk/type/FileType$MIME_SOURCE/MOV Lcom/nd/teamfile/sdk/type/FileType$MIME_SOURCE;
aastore
dup
bipush 49
getstatic com/nd/teamfile/sdk/type/FileType$MIME_SOURCE/MP2 Lcom/nd/teamfile/sdk/type/FileType$MIME_SOURCE;
aastore
dup
bipush 50
getstatic com/nd/teamfile/sdk/type/FileType$MIME_SOURCE/MP3 Lcom/nd/teamfile/sdk/type/FileType$MIME_SOURCE;
aastore
dup
bipush 51
getstatic com/nd/teamfile/sdk/type/FileType$MIME_SOURCE/MP4 Lcom/nd/teamfile/sdk/type/FileType$MIME_SOURCE;
aastore
dup
bipush 52
getstatic com/nd/teamfile/sdk/type/FileType$MIME_SOURCE/MPC Lcom/nd/teamfile/sdk/type/FileType$MIME_SOURCE;
aastore
dup
bipush 53
getstatic com/nd/teamfile/sdk/type/FileType$MIME_SOURCE/MPE Lcom/nd/teamfile/sdk/type/FileType$MIME_SOURCE;
aastore
dup
bipush 54
getstatic com/nd/teamfile/sdk/type/FileType$MIME_SOURCE/MPEG Lcom/nd/teamfile/sdk/type/FileType$MIME_SOURCE;
aastore
dup
bipush 55
getstatic com/nd/teamfile/sdk/type/FileType$MIME_SOURCE/MPG Lcom/nd/teamfile/sdk/type/FileType$MIME_SOURCE;
aastore
dup
bipush 56
getstatic com/nd/teamfile/sdk/type/FileType$MIME_SOURCE/MPG4 Lcom/nd/teamfile/sdk/type/FileType$MIME_SOURCE;
aastore
dup
bipush 57
getstatic com/nd/teamfile/sdk/type/FileType$MIME_SOURCE/MPGA Lcom/nd/teamfile/sdk/type/FileType$MIME_SOURCE;
aastore
dup
bipush 58
getstatic com/nd/teamfile/sdk/type/FileType$MIME_SOURCE/MSG Lcom/nd/teamfile/sdk/type/FileType$MIME_SOURCE;
aastore
dup
bipush 59
getstatic com/nd/teamfile/sdk/type/FileType$MIME_SOURCE/OGG Lcom/nd/teamfile/sdk/type/FileType$MIME_SOURCE;
aastore
dup
bipush 60
getstatic com/nd/teamfile/sdk/type/FileType$MIME_SOURCE/PDF Lcom/nd/teamfile/sdk/type/FileType$MIME_SOURCE;
aastore
dup
bipush 61
getstatic com/nd/teamfile/sdk/type/FileType$MIME_SOURCE/PNG Lcom/nd/teamfile/sdk/type/FileType$MIME_SOURCE;
aastore
dup
bipush 62
getstatic com/nd/teamfile/sdk/type/FileType$MIME_SOURCE/PPS Lcom/nd/teamfile/sdk/type/FileType$MIME_SOURCE;
aastore
dup
bipush 63
getstatic com/nd/teamfile/sdk/type/FileType$MIME_SOURCE/PPT Lcom/nd/teamfile/sdk/type/FileType$MIME_SOURCE;
aastore
dup
bipush 64
getstatic com/nd/teamfile/sdk/type/FileType$MIME_SOURCE/PROP Lcom/nd/teamfile/sdk/type/FileType$MIME_SOURCE;
aastore
dup
bipush 65
getstatic com/nd/teamfile/sdk/type/FileType$MIME_SOURCE/RAR Lcom/nd/teamfile/sdk/type/FileType$MIME_SOURCE;
aastore
dup
bipush 66
getstatic com/nd/teamfile/sdk/type/FileType$MIME_SOURCE/RC Lcom/nd/teamfile/sdk/type/FileType$MIME_SOURCE;
aastore
dup
bipush 67
getstatic com/nd/teamfile/sdk/type/FileType$MIME_SOURCE/RMVB Lcom/nd/teamfile/sdk/type/FileType$MIME_SOURCE;
aastore
dup
bipush 68
getstatic com/nd/teamfile/sdk/type/FileType$MIME_SOURCE/RTF Lcom/nd/teamfile/sdk/type/FileType$MIME_SOURCE;
aastore
dup
bipush 69
getstatic com/nd/teamfile/sdk/type/FileType$MIME_SOURCE/SH Lcom/nd/teamfile/sdk/type/FileType$MIME_SOURCE;
aastore
dup
bipush 70
getstatic com/nd/teamfile/sdk/type/FileType$MIME_SOURCE/TAR Lcom/nd/teamfile/sdk/type/FileType$MIME_SOURCE;
aastore
dup
bipush 71
getstatic com/nd/teamfile/sdk/type/FileType$MIME_SOURCE/TGZ Lcom/nd/teamfile/sdk/type/FileType$MIME_SOURCE;
aastore
dup
bipush 72
getstatic com/nd/teamfile/sdk/type/FileType$MIME_SOURCE/TXT Lcom/nd/teamfile/sdk/type/FileType$MIME_SOURCE;
aastore
dup
bipush 73
getstatic com/nd/teamfile/sdk/type/FileType$MIME_SOURCE/WAV Lcom/nd/teamfile/sdk/type/FileType$MIME_SOURCE;
aastore
dup
bipush 74
getstatic com/nd/teamfile/sdk/type/FileType$MIME_SOURCE/WMA Lcom/nd/teamfile/sdk/type/FileType$MIME_SOURCE;
aastore
dup
bipush 75
getstatic com/nd/teamfile/sdk/type/FileType$MIME_SOURCE/WMV Lcom/nd/teamfile/sdk/type/FileType$MIME_SOURCE;
aastore
dup
bipush 76
getstatic com/nd/teamfile/sdk/type/FileType$MIME_SOURCE/WPS Lcom/nd/teamfile/sdk/type/FileType$MIME_SOURCE;
aastore
dup
bipush 77
getstatic com/nd/teamfile/sdk/type/FileType$MIME_SOURCE/XML Lcom/nd/teamfile/sdk/type/FileType$MIME_SOURCE;
aastore
dup
bipush 78
getstatic com/nd/teamfile/sdk/type/FileType$MIME_SOURCE/Z Lcom/nd/teamfile/sdk/type/FileType$MIME_SOURCE;
aastore
dup
bipush 79
getstatic com/nd/teamfile/sdk/type/FileType$MIME_SOURCE/ZIP Lcom/nd/teamfile/sdk/type/FileType$MIME_SOURCE;
aastore
putstatic com/nd/teamfile/sdk/type/FileType$MIME_SOURCE/$VALUES [Lcom/nd/teamfile/sdk/type/FileType$MIME_SOURCE;
return
.limit locals 0
.limit stack 7
.end method

.method private <init>(Ljava/lang/String;ILjava/lang/String;II)V
.signature "(Ljava/lang/String;II)V"
aload 0
aload 1
iload 2
invokespecial java/lang/Enum/<init>(Ljava/lang/String;I)V
aload 0
aload 3
putfield com/nd/teamfile/sdk/type/FileType$MIME_SOURCE/mimeType Ljava/lang/String;
aload 0
iload 4
putfield com/nd/teamfile/sdk/type/FileType$MIME_SOURCE/sourceId I
aload 0
iload 5
putfield com/nd/teamfile/sdk/type/FileType$MIME_SOURCE/largeSourceId I
return
.limit locals 6
.limit stack 3
.end method

.method public static valueOf(Ljava/lang/String;)Lcom/nd/teamfile/sdk/type/FileType$MIME_SOURCE;
ldc com/nd/teamfile/sdk/type/FileType$MIME_SOURCE
aload 0
invokestatic java/lang/Enum/valueOf(Ljava/lang/Class;Ljava/lang/String;)Ljava/lang/Enum;
checkcast com/nd/teamfile/sdk/type/FileType$MIME_SOURCE
areturn
.limit locals 1
.limit stack 2
.end method

.method public static values()[Lcom/nd/teamfile/sdk/type/FileType$MIME_SOURCE;
getstatic com/nd/teamfile/sdk/type/FileType$MIME_SOURCE/$VALUES [Lcom/nd/teamfile/sdk/type/FileType$MIME_SOURCE;
invokevirtual [Lcom/nd/teamfile/sdk/type/FileType$MIME_SOURCE;/clone()Ljava/lang/Object;
checkcast [Lcom/nd/teamfile/sdk/type/FileType$MIME_SOURCE;
areturn
.limit locals 0
.limit stack 1
.end method
