.bytecode 50.0
.class synchronized com/nd/teamfile/sdk/type/FileType$1
.super java/util/HashMap
.signature "Ljava/util/HashMap<Ljava/lang/String;Lcom/nd/teamfile/sdk/type/FileType$MIME_SOURCE;>;"
.enclosing method com/nd/teamfile/sdk/type/FileType
.inner class inner com/nd/teamfile/sdk/type/FileType$1

.field private static final 'serialVersionUID' J = 6509951825930096927L


.field final synthetic 'this$0' Lcom/nd/teamfile/sdk/type/FileType;

.method <init>(Lcom/nd/teamfile/sdk/type/FileType;)V
aload 0
aload 1
putfield com/nd/teamfile/sdk/type/FileType$1/this$0 Lcom/nd/teamfile/sdk/type/FileType;
aload 0
invokespecial java/util/HashMap/<init>()V
aload 0
ldc ".3gp"
getstatic com/nd/teamfile/sdk/type/FileType$MIME_SOURCE/_3GP Lcom/nd/teamfile/sdk/type/FileType$MIME_SOURCE;
invokevirtual com/nd/teamfile/sdk/type/FileType$1/put(Ljava/lang/Object;Ljava/lang/Object;)Ljava/lang/Object;
pop
aload 0
ldc ".asf"
getstatic com/nd/teamfile/sdk/type/FileType$MIME_SOURCE/ASF Lcom/nd/teamfile/sdk/type/FileType$MIME_SOURCE;
invokevirtual com/nd/teamfile/sdk/type/FileType$1/put(Ljava/lang/Object;Ljava/lang/Object;)Ljava/lang/Object;
pop
aload 0
ldc ".avi"
getstatic com/nd/teamfile/sdk/type/FileType$MIME_SOURCE/AVI Lcom/nd/teamfile/sdk/type/FileType$MIME_SOURCE;
invokevirtual com/nd/teamfile/sdk/type/FileType$1/put(Ljava/lang/Object;Ljava/lang/Object;)Ljava/lang/Object;
pop
aload 0
ldc ".bin"
getstatic com/nd/teamfile/sdk/type/FileType$MIME_SOURCE/BIN Lcom/nd/teamfile/sdk/type/FileType$MIME_SOURCE;
invokevirtual com/nd/teamfile/sdk/type/FileType$1/put(Ljava/lang/Object;Ljava/lang/Object;)Ljava/lang/Object;
pop
aload 0
ldc ".bmp"
getstatic com/nd/teamfile/sdk/type/FileType$MIME_SOURCE/BMP Lcom/nd/teamfile/sdk/type/FileType$MIME_SOURCE;
invokevirtual com/nd/teamfile/sdk/type/FileType$1/put(Ljava/lang/Object;Ljava/lang/Object;)Ljava/lang/Object;
pop
aload 0
ldc ".c"
getstatic com/nd/teamfile/sdk/type/FileType$MIME_SOURCE/C Lcom/nd/teamfile/sdk/type/FileType$MIME_SOURCE;
invokevirtual com/nd/teamfile/sdk/type/FileType$1/put(Ljava/lang/Object;Ljava/lang/Object;)Ljava/lang/Object;
pop
aload 0
ldc ".class"
getstatic com/nd/teamfile/sdk/type/FileType$MIME_SOURCE/CLASS Lcom/nd/teamfile/sdk/type/FileType$MIME_SOURCE;
invokevirtual com/nd/teamfile/sdk/type/FileType$1/put(Ljava/lang/Object;Ljava/lang/Object;)Ljava/lang/Object;
pop
aload 0
ldc ".conf"
getstatic com/nd/teamfile/sdk/type/FileType$MIME_SOURCE/CONF Lcom/nd/teamfile/sdk/type/FileType$MIME_SOURCE;
invokevirtual com/nd/teamfile/sdk/type/FileType$1/put(Ljava/lang/Object;Ljava/lang/Object;)Ljava/lang/Object;
pop
aload 0
ldc ".cpp"
getstatic com/nd/teamfile/sdk/type/FileType$MIME_SOURCE/CPP Lcom/nd/teamfile/sdk/type/FileType$MIME_SOURCE;
invokevirtual com/nd/teamfile/sdk/type/FileType$1/put(Ljava/lang/Object;Ljava/lang/Object;)Ljava/lang/Object;
pop
aload 0
ldc ".doc"
getstatic com/nd/teamfile/sdk/type/FileType$MIME_SOURCE/DOC Lcom/nd/teamfile/sdk/type/FileType$MIME_SOURCE;
invokevirtual com/nd/teamfile/sdk/type/FileType$1/put(Ljava/lang/Object;Ljava/lang/Object;)Ljava/lang/Object;
pop
aload 0
ldc ".exe"
getstatic com/nd/teamfile/sdk/type/FileType$MIME_SOURCE/EXE Lcom/nd/teamfile/sdk/type/FileType$MIME_SOURCE;
invokevirtual com/nd/teamfile/sdk/type/FileType$1/put(Ljava/lang/Object;Ljava/lang/Object;)Ljava/lang/Object;
pop
aload 0
ldc ".gif"
getstatic com/nd/teamfile/sdk/type/FileType$MIME_SOURCE/GIF Lcom/nd/teamfile/sdk/type/FileType$MIME_SOURCE;
invokevirtual com/nd/teamfile/sdk/type/FileType$1/put(Ljava/lang/Object;Ljava/lang/Object;)Ljava/lang/Object;
pop
aload 0
ldc ".gtar"
getstatic com/nd/teamfile/sdk/type/FileType$MIME_SOURCE/GTAR Lcom/nd/teamfile/sdk/type/FileType$MIME_SOURCE;
invokevirtual com/nd/teamfile/sdk/type/FileType$1/put(Ljava/lang/Object;Ljava/lang/Object;)Ljava/lang/Object;
pop
aload 0
ldc ".gz"
getstatic com/nd/teamfile/sdk/type/FileType$MIME_SOURCE/GZ Lcom/nd/teamfile/sdk/type/FileType$MIME_SOURCE;
invokevirtual com/nd/teamfile/sdk/type/FileType$1/put(Ljava/lang/Object;Ljava/lang/Object;)Ljava/lang/Object;
pop
aload 0
ldc ".h"
getstatic com/nd/teamfile/sdk/type/FileType$MIME_SOURCE/H Lcom/nd/teamfile/sdk/type/FileType$MIME_SOURCE;
invokevirtual com/nd/teamfile/sdk/type/FileType$1/put(Ljava/lang/Object;Ljava/lang/Object;)Ljava/lang/Object;
pop
aload 0
ldc ".htm"
getstatic com/nd/teamfile/sdk/type/FileType$MIME_SOURCE/HTM Lcom/nd/teamfile/sdk/type/FileType$MIME_SOURCE;
invokevirtual com/nd/teamfile/sdk/type/FileType$1/put(Ljava/lang/Object;Ljava/lang/Object;)Ljava/lang/Object;
pop
aload 0
ldc ".html"
getstatic com/nd/teamfile/sdk/type/FileType$MIME_SOURCE/HTML Lcom/nd/teamfile/sdk/type/FileType$MIME_SOURCE;
invokevirtual com/nd/teamfile/sdk/type/FileType$1/put(Ljava/lang/Object;Ljava/lang/Object;)Ljava/lang/Object;
pop
aload 0
ldc ".jar"
getstatic com/nd/teamfile/sdk/type/FileType$MIME_SOURCE/JAR Lcom/nd/teamfile/sdk/type/FileType$MIME_SOURCE;
invokevirtual com/nd/teamfile/sdk/type/FileType$1/put(Ljava/lang/Object;Ljava/lang/Object;)Ljava/lang/Object;
pop
aload 0
ldc ".java"
getstatic com/nd/teamfile/sdk/type/FileType$MIME_SOURCE/JAVA Lcom/nd/teamfile/sdk/type/FileType$MIME_SOURCE;
invokevirtual com/nd/teamfile/sdk/type/FileType$1/put(Ljava/lang/Object;Ljava/lang/Object;)Ljava/lang/Object;
pop
aload 0
ldc ".jpeg"
getstatic com/nd/teamfile/sdk/type/FileType$MIME_SOURCE/JPEG Lcom/nd/teamfile/sdk/type/FileType$MIME_SOURCE;
invokevirtual com/nd/teamfile/sdk/type/FileType$1/put(Ljava/lang/Object;Ljava/lang/Object;)Ljava/lang/Object;
pop
aload 0
ldc ".jpg"
getstatic com/nd/teamfile/sdk/type/FileType$MIME_SOURCE/JPG Lcom/nd/teamfile/sdk/type/FileType$MIME_SOURCE;
invokevirtual com/nd/teamfile/sdk/type/FileType$1/put(Ljava/lang/Object;Ljava/lang/Object;)Ljava/lang/Object;
pop
aload 0
ldc ".js"
getstatic com/nd/teamfile/sdk/type/FileType$MIME_SOURCE/JS Lcom/nd/teamfile/sdk/type/FileType$MIME_SOURCE;
invokevirtual com/nd/teamfile/sdk/type/FileType$1/put(Ljava/lang/Object;Ljava/lang/Object;)Ljava/lang/Object;
pop
aload 0
ldc ".log"
getstatic com/nd/teamfile/sdk/type/FileType$MIME_SOURCE/LOG Lcom/nd/teamfile/sdk/type/FileType$MIME_SOURCE;
invokevirtual com/nd/teamfile/sdk/type/FileType$1/put(Ljava/lang/Object;Ljava/lang/Object;)Ljava/lang/Object;
pop
aload 0
ldc ".m3u"
getstatic com/nd/teamfile/sdk/type/FileType$MIME_SOURCE/M3U Lcom/nd/teamfile/sdk/type/FileType$MIME_SOURCE;
invokevirtual com/nd/teamfile/sdk/type/FileType$1/put(Ljava/lang/Object;Ljava/lang/Object;)Ljava/lang/Object;
pop
aload 0
ldc ".m4a"
getstatic com/nd/teamfile/sdk/type/FileType$MIME_SOURCE/M4A Lcom/nd/teamfile/sdk/type/FileType$MIME_SOURCE;
invokevirtual com/nd/teamfile/sdk/type/FileType$1/put(Ljava/lang/Object;Ljava/lang/Object;)Ljava/lang/Object;
pop
aload 0
ldc ".m4b"
getstatic com/nd/teamfile/sdk/type/FileType$MIME_SOURCE/M4B Lcom/nd/teamfile/sdk/type/FileType$MIME_SOURCE;
invokevirtual com/nd/teamfile/sdk/type/FileType$1/put(Ljava/lang/Object;Ljava/lang/Object;)Ljava/lang/Object;
pop
aload 0
ldc ".m4p"
getstatic com/nd/teamfile/sdk/type/FileType$MIME_SOURCE/M4P Lcom/nd/teamfile/sdk/type/FileType$MIME_SOURCE;
invokevirtual com/nd/teamfile/sdk/type/FileType$1/put(Ljava/lang/Object;Ljava/lang/Object;)Ljava/lang/Object;
pop
aload 0
ldc ".m4u"
getstatic com/nd/teamfile/sdk/type/FileType$MIME_SOURCE/M4U Lcom/nd/teamfile/sdk/type/FileType$MIME_SOURCE;
invokevirtual com/nd/teamfile/sdk/type/FileType$1/put(Ljava/lang/Object;Ljava/lang/Object;)Ljava/lang/Object;
pop
aload 0
ldc ".m4v"
getstatic com/nd/teamfile/sdk/type/FileType$MIME_SOURCE/M4V Lcom/nd/teamfile/sdk/type/FileType$MIME_SOURCE;
invokevirtual com/nd/teamfile/sdk/type/FileType$1/put(Ljava/lang/Object;Ljava/lang/Object;)Ljava/lang/Object;
pop
aload 0
ldc ".mov"
getstatic com/nd/teamfile/sdk/type/FileType$MIME_SOURCE/MOV Lcom/nd/teamfile/sdk/type/FileType$MIME_SOURCE;
invokevirtual com/nd/teamfile/sdk/type/FileType$1/put(Ljava/lang/Object;Ljava/lang/Object;)Ljava/lang/Object;
pop
aload 0
ldc ".mp2"
getstatic com/nd/teamfile/sdk/type/FileType$MIME_SOURCE/MP2 Lcom/nd/teamfile/sdk/type/FileType$MIME_SOURCE;
invokevirtual com/nd/teamfile/sdk/type/FileType$1/put(Ljava/lang/Object;Ljava/lang/Object;)Ljava/lang/Object;
pop
aload 0
ldc ".mp3"
getstatic com/nd/teamfile/sdk/type/FileType$MIME_SOURCE/MP3 Lcom/nd/teamfile/sdk/type/FileType$MIME_SOURCE;
invokevirtual com/nd/teamfile/sdk/type/FileType$1/put(Ljava/lang/Object;Ljava/lang/Object;)Ljava/lang/Object;
pop
aload 0
ldc ".mp4"
getstatic com/nd/teamfile/sdk/type/FileType$MIME_SOURCE/MP4 Lcom/nd/teamfile/sdk/type/FileType$MIME_SOURCE;
invokevirtual com/nd/teamfile/sdk/type/FileType$1/put(Ljava/lang/Object;Ljava/lang/Object;)Ljava/lang/Object;
pop
aload 0
ldc ".mpc"
getstatic com/nd/teamfile/sdk/type/FileType$MIME_SOURCE/MPC Lcom/nd/teamfile/sdk/type/FileType$MIME_SOURCE;
invokevirtual com/nd/teamfile/sdk/type/FileType$1/put(Ljava/lang/Object;Ljava/lang/Object;)Ljava/lang/Object;
pop
aload 0
ldc ".mpe"
getstatic com/nd/teamfile/sdk/type/FileType$MIME_SOURCE/MPE Lcom/nd/teamfile/sdk/type/FileType$MIME_SOURCE;
invokevirtual com/nd/teamfile/sdk/type/FileType$1/put(Ljava/lang/Object;Ljava/lang/Object;)Ljava/lang/Object;
pop
aload 0
ldc ".mpeg"
getstatic com/nd/teamfile/sdk/type/FileType$MIME_SOURCE/MPEG Lcom/nd/teamfile/sdk/type/FileType$MIME_SOURCE;
invokevirtual com/nd/teamfile/sdk/type/FileType$1/put(Ljava/lang/Object;Ljava/lang/Object;)Ljava/lang/Object;
pop
aload 0
ldc ".mpg"
getstatic com/nd/teamfile/sdk/type/FileType$MIME_SOURCE/MPG Lcom/nd/teamfile/sdk/type/FileType$MIME_SOURCE;
invokevirtual com/nd/teamfile/sdk/type/FileType$1/put(Ljava/lang/Object;Ljava/lang/Object;)Ljava/lang/Object;
pop
aload 0
ldc ".mpg4"
getstatic com/nd/teamfile/sdk/type/FileType$MIME_SOURCE/MPG4 Lcom/nd/teamfile/sdk/type/FileType$MIME_SOURCE;
invokevirtual com/nd/teamfile/sdk/type/FileType$1/put(Ljava/lang/Object;Ljava/lang/Object;)Ljava/lang/Object;
pop
aload 0
ldc ".mpga"
getstatic com/nd/teamfile/sdk/type/FileType$MIME_SOURCE/MPGA Lcom/nd/teamfile/sdk/type/FileType$MIME_SOURCE;
invokevirtual com/nd/teamfile/sdk/type/FileType$1/put(Ljava/lang/Object;Ljava/lang/Object;)Ljava/lang/Object;
pop
aload 0
ldc ".msg"
getstatic com/nd/teamfile/sdk/type/FileType$MIME_SOURCE/MSG Lcom/nd/teamfile/sdk/type/FileType$MIME_SOURCE;
invokevirtual com/nd/teamfile/sdk/type/FileType$1/put(Ljava/lang/Object;Ljava/lang/Object;)Ljava/lang/Object;
pop
aload 0
ldc ".ogg"
getstatic com/nd/teamfile/sdk/type/FileType$MIME_SOURCE/OGG Lcom/nd/teamfile/sdk/type/FileType$MIME_SOURCE;
invokevirtual com/nd/teamfile/sdk/type/FileType$1/put(Ljava/lang/Object;Ljava/lang/Object;)Ljava/lang/Object;
pop
aload 0
ldc ".pdf"
getstatic com/nd/teamfile/sdk/type/FileType$MIME_SOURCE/PDF Lcom/nd/teamfile/sdk/type/FileType$MIME_SOURCE;
invokevirtual com/nd/teamfile/sdk/type/FileType$1/put(Ljava/lang/Object;Ljava/lang/Object;)Ljava/lang/Object;
pop
aload 0
ldc ".png"
getstatic com/nd/teamfile/sdk/type/FileType$MIME_SOURCE/PNG Lcom/nd/teamfile/sdk/type/FileType$MIME_SOURCE;
invokevirtual com/nd/teamfile/sdk/type/FileType$1/put(Ljava/lang/Object;Ljava/lang/Object;)Ljava/lang/Object;
pop
aload 0
ldc ".pps"
getstatic com/nd/teamfile/sdk/type/FileType$MIME_SOURCE/PPS Lcom/nd/teamfile/sdk/type/FileType$MIME_SOURCE;
invokevirtual com/nd/teamfile/sdk/type/FileType$1/put(Ljava/lang/Object;Ljava/lang/Object;)Ljava/lang/Object;
pop
aload 0
ldc ".ppt"
getstatic com/nd/teamfile/sdk/type/FileType$MIME_SOURCE/PPT Lcom/nd/teamfile/sdk/type/FileType$MIME_SOURCE;
invokevirtual com/nd/teamfile/sdk/type/FileType$1/put(Ljava/lang/Object;Ljava/lang/Object;)Ljava/lang/Object;
pop
aload 0
ldc ".prop"
getstatic com/nd/teamfile/sdk/type/FileType$MIME_SOURCE/PROP Lcom/nd/teamfile/sdk/type/FileType$MIME_SOURCE;
invokevirtual com/nd/teamfile/sdk/type/FileType$1/put(Ljava/lang/Object;Ljava/lang/Object;)Ljava/lang/Object;
pop
aload 0
ldc ".rar"
getstatic com/nd/teamfile/sdk/type/FileType$MIME_SOURCE/RAR Lcom/nd/teamfile/sdk/type/FileType$MIME_SOURCE;
invokevirtual com/nd/teamfile/sdk/type/FileType$1/put(Ljava/lang/Object;Ljava/lang/Object;)Ljava/lang/Object;
pop
aload 0
ldc ".rc"
getstatic com/nd/teamfile/sdk/type/FileType$MIME_SOURCE/RC Lcom/nd/teamfile/sdk/type/FileType$MIME_SOURCE;
invokevirtual com/nd/teamfile/sdk/type/FileType$1/put(Ljava/lang/Object;Ljava/lang/Object;)Ljava/lang/Object;
pop
aload 0
ldc ".rmvb"
getstatic com/nd/teamfile/sdk/type/FileType$MIME_SOURCE/RMVB Lcom/nd/teamfile/sdk/type/FileType$MIME_SOURCE;
invokevirtual com/nd/teamfile/sdk/type/FileType$1/put(Ljava/lang/Object;Ljava/lang/Object;)Ljava/lang/Object;
pop
aload 0
ldc ".rtf"
getstatic com/nd/teamfile/sdk/type/FileType$MIME_SOURCE/RTF Lcom/nd/teamfile/sdk/type/FileType$MIME_SOURCE;
invokevirtual com/nd/teamfile/sdk/type/FileType$1/put(Ljava/lang/Object;Ljava/lang/Object;)Ljava/lang/Object;
pop
aload 0
ldc ".sh"
getstatic com/nd/teamfile/sdk/type/FileType$MIME_SOURCE/SH Lcom/nd/teamfile/sdk/type/FileType$MIME_SOURCE;
invokevirtual com/nd/teamfile/sdk/type/FileType$1/put(Ljava/lang/Object;Ljava/lang/Object;)Ljava/lang/Object;
pop
aload 0
ldc ".tar"
getstatic com/nd/teamfile/sdk/type/FileType$MIME_SOURCE/TAR Lcom/nd/teamfile/sdk/type/FileType$MIME_SOURCE;
invokevirtual com/nd/teamfile/sdk/type/FileType$1/put(Ljava/lang/Object;Ljava/lang/Object;)Ljava/lang/Object;
pop
aload 0
ldc ".tgz"
getstatic com/nd/teamfile/sdk/type/FileType$MIME_SOURCE/TGZ Lcom/nd/teamfile/sdk/type/FileType$MIME_SOURCE;
invokevirtual com/nd/teamfile/sdk/type/FileType$1/put(Ljava/lang/Object;Ljava/lang/Object;)Ljava/lang/Object;
pop
aload 0
ldc ".txt"
getstatic com/nd/teamfile/sdk/type/FileType$MIME_SOURCE/TXT Lcom/nd/teamfile/sdk/type/FileType$MIME_SOURCE;
invokevirtual com/nd/teamfile/sdk/type/FileType$1/put(Ljava/lang/Object;Ljava/lang/Object;)Ljava/lang/Object;
pop
aload 0
ldc ".wav"
getstatic com/nd/teamfile/sdk/type/FileType$MIME_SOURCE/WAV Lcom/nd/teamfile/sdk/type/FileType$MIME_SOURCE;
invokevirtual com/nd/teamfile/sdk/type/FileType$1/put(Ljava/lang/Object;Ljava/lang/Object;)Ljava/lang/Object;
pop
aload 0
ldc ".wma"
getstatic com/nd/teamfile/sdk/type/FileType$MIME_SOURCE/WMA Lcom/nd/teamfile/sdk/type/FileType$MIME_SOURCE;
invokevirtual com/nd/teamfile/sdk/type/FileType$1/put(Ljava/lang/Object;Ljava/lang/Object;)Ljava/lang/Object;
pop
aload 0
ldc ".wmv"
getstatic com/nd/teamfile/sdk/type/FileType$MIME_SOURCE/WMV Lcom/nd/teamfile/sdk/type/FileType$MIME_SOURCE;
invokevirtual com/nd/teamfile/sdk/type/FileType$1/put(Ljava/lang/Object;Ljava/lang/Object;)Ljava/lang/Object;
pop
aload 0
ldc ".wps"
getstatic com/nd/teamfile/sdk/type/FileType$MIME_SOURCE/WPS Lcom/nd/teamfile/sdk/type/FileType$MIME_SOURCE;
invokevirtual com/nd/teamfile/sdk/type/FileType$1/put(Ljava/lang/Object;Ljava/lang/Object;)Ljava/lang/Object;
pop
aload 0
ldc ".xml"
getstatic com/nd/teamfile/sdk/type/FileType$MIME_SOURCE/XML Lcom/nd/teamfile/sdk/type/FileType$MIME_SOURCE;
invokevirtual com/nd/teamfile/sdk/type/FileType$1/put(Ljava/lang/Object;Ljava/lang/Object;)Ljava/lang/Object;
pop
aload 0
ldc ".z"
getstatic com/nd/teamfile/sdk/type/FileType$MIME_SOURCE/Z Lcom/nd/teamfile/sdk/type/FileType$MIME_SOURCE;
invokevirtual com/nd/teamfile/sdk/type/FileType$1/put(Ljava/lang/Object;Ljava/lang/Object;)Ljava/lang/Object;
pop
aload 0
ldc ".zip"
getstatic com/nd/teamfile/sdk/type/FileType$MIME_SOURCE/ZIP Lcom/nd/teamfile/sdk/type/FileType$MIME_SOURCE;
invokevirtual com/nd/teamfile/sdk/type/FileType$1/put(Ljava/lang/Object;Ljava/lang/Object;)Ljava/lang/Object;
pop
aload 0
ldc ".apk"
getstatic com/nd/teamfile/sdk/type/FileType$MIME_SOURCE/APK Lcom/nd/teamfile/sdk/type/FileType$MIME_SOURCE;
invokevirtual com/nd/teamfile/sdk/type/FileType$1/put(Ljava/lang/Object;Ljava/lang/Object;)Ljava/lang/Object;
pop
aload 0
ldc ".rss"
getstatic com/nd/teamfile/sdk/type/FileType$MIME_SOURCE/RSS Lcom/nd/teamfile/sdk/type/FileType$MIME_SOURCE;
invokevirtual com/nd/teamfile/sdk/type/FileType$1/put(Ljava/lang/Object;Ljava/lang/Object;)Ljava/lang/Object;
pop
aload 0
ldc ".docx"
getstatic com/nd/teamfile/sdk/type/FileType$MIME_SOURCE/DOCX Lcom/nd/teamfile/sdk/type/FileType$MIME_SOURCE;
invokevirtual com/nd/teamfile/sdk/type/FileType$1/put(Ljava/lang/Object;Ljava/lang/Object;)Ljava/lang/Object;
pop
aload 0
ldc ".xls"
getstatic com/nd/teamfile/sdk/type/FileType$MIME_SOURCE/XLS Lcom/nd/teamfile/sdk/type/FileType$MIME_SOURCE;
invokevirtual com/nd/teamfile/sdk/type/FileType$1/put(Ljava/lang/Object;Ljava/lang/Object;)Ljava/lang/Object;
pop
aload 0
ldc ".xlsx"
getstatic com/nd/teamfile/sdk/type/FileType$MIME_SOURCE/XLS Lcom/nd/teamfile/sdk/type/FileType$MIME_SOURCE;
invokevirtual com/nd/teamfile/sdk/type/FileType$1/put(Ljava/lang/Object;Ljava/lang/Object;)Ljava/lang/Object;
pop
aload 0
ldc ".xlsm"
getstatic com/nd/teamfile/sdk/type/FileType$MIME_SOURCE/XLS Lcom/nd/teamfile/sdk/type/FileType$MIME_SOURCE;
invokevirtual com/nd/teamfile/sdk/type/FileType$1/put(Ljava/lang/Object;Ljava/lang/Object;)Ljava/lang/Object;
pop
aload 0
ldc ".xlt"
getstatic com/nd/teamfile/sdk/type/FileType$MIME_SOURCE/XLT Lcom/nd/teamfile/sdk/type/FileType$MIME_SOURCE;
invokevirtual com/nd/teamfile/sdk/type/FileType$1/put(Ljava/lang/Object;Ljava/lang/Object;)Ljava/lang/Object;
pop
aload 0
ldc ".vsd"
getstatic com/nd/teamfile/sdk/type/FileType$MIME_SOURCE/VSD Lcom/nd/teamfile/sdk/type/FileType$MIME_SOURCE;
invokevirtual com/nd/teamfile/sdk/type/FileType$1/put(Ljava/lang/Object;Ljava/lang/Object;)Ljava/lang/Object;
pop
aload 0
ldc ".torrent"
getstatic com/nd/teamfile/sdk/type/FileType$MIME_SOURCE/TORRENT Lcom/nd/teamfile/sdk/type/FileType$MIME_SOURCE;
invokevirtual com/nd/teamfile/sdk/type/FileType$1/put(Ljava/lang/Object;Ljava/lang/Object;)Ljava/lang/Object;
pop
aload 0
ldc ".taz"
getstatic com/nd/teamfile/sdk/type/FileType$MIME_SOURCE/TAZ Lcom/nd/teamfile/sdk/type/FileType$MIME_SOURCE;
invokevirtual com/nd/teamfile/sdk/type/FileType$1/put(Ljava/lang/Object;Ljava/lang/Object;)Ljava/lang/Object;
pop
aload 0
ldc ".xhtm"
getstatic com/nd/teamfile/sdk/type/FileType$MIME_SOURCE/XHTML Lcom/nd/teamfile/sdk/type/FileType$MIME_SOURCE;
invokevirtual com/nd/teamfile/sdk/type/FileType$1/put(Ljava/lang/Object;Ljava/lang/Object;)Ljava/lang/Object;
pop
aload 0
ldc ".3gpp"
getstatic com/nd/teamfile/sdk/type/FileType$MIME_SOURCE/_3GPP Lcom/nd/teamfile/sdk/type/FileType$MIME_SOURCE;
invokevirtual com/nd/teamfile/sdk/type/FileType$1/put(Ljava/lang/Object;Ljava/lang/Object;)Ljava/lang/Object;
pop
aload 0
ldc ".amr"
getstatic com/nd/teamfile/sdk/type/FileType$MIME_SOURCE/AMR Lcom/nd/teamfile/sdk/type/FileType$MIME_SOURCE;
invokevirtual com/nd/teamfile/sdk/type/FileType$1/put(Ljava/lang/Object;Ljava/lang/Object;)Ljava/lang/Object;
pop
aload 0
ldc ".mpega"
getstatic com/nd/teamfile/sdk/type/FileType$MIME_SOURCE/MPEGA Lcom/nd/teamfile/sdk/type/FileType$MIME_SOURCE;
invokevirtual com/nd/teamfile/sdk/type/FileType$1/put(Ljava/lang/Object;Ljava/lang/Object;)Ljava/lang/Object;
pop
aload 0
ldc ".rm"
getstatic com/nd/teamfile/sdk/type/FileType$MIME_SOURCE/RM Lcom/nd/teamfile/sdk/type/FileType$MIME_SOURCE;
invokevirtual com/nd/teamfile/sdk/type/FileType$1/put(Ljava/lang/Object;Ljava/lang/Object;)Ljava/lang/Object;
pop
aload 0
ldc ".jpe"
getstatic com/nd/teamfile/sdk/type/FileType$MIME_SOURCE/JPE Lcom/nd/teamfile/sdk/type/FileType$MIME_SOURCE;
invokevirtual com/nd/teamfile/sdk/type/FileType$1/put(Ljava/lang/Object;Ljava/lang/Object;)Ljava/lang/Object;
pop
aload 0
ldc ".wbmp"
getstatic com/nd/teamfile/sdk/type/FileType$MIME_SOURCE/WBMP Lcom/nd/teamfile/sdk/type/FileType$MIME_SOURCE;
invokevirtual com/nd/teamfile/sdk/type/FileType$1/put(Ljava/lang/Object;Ljava/lang/Object;)Ljava/lang/Object;
pop
aload 0
ldc ".psd"
getstatic com/nd/teamfile/sdk/type/FileType$MIME_SOURCE/PSD Lcom/nd/teamfile/sdk/type/FileType$MIME_SOURCE;
invokevirtual com/nd/teamfile/sdk/type/FileType$1/put(Ljava/lang/Object;Ljava/lang/Object;)Ljava/lang/Object;
pop
aload 0
ldc ".text"
getstatic com/nd/teamfile/sdk/type/FileType$MIME_SOURCE/TEXT Lcom/nd/teamfile/sdk/type/FileType$MIME_SOURCE;
invokevirtual com/nd/teamfile/sdk/type/FileType$1/put(Ljava/lang/Object;Ljava/lang/Object;)Ljava/lang/Object;
pop
aload 0
ldc ".3g2"
getstatic com/nd/teamfile/sdk/type/FileType$MIME_SOURCE/_3G2 Lcom/nd/teamfile/sdk/type/FileType$MIME_SOURCE;
invokevirtual com/nd/teamfile/sdk/type/FileType$1/put(Ljava/lang/Object;Ljava/lang/Object;)Ljava/lang/Object;
pop
aload 0
ldc ".vob"
getstatic com/nd/teamfile/sdk/type/FileType$MIME_SOURCE/VOB Lcom/nd/teamfile/sdk/type/FileType$MIME_SOURCE;
invokevirtual com/nd/teamfile/sdk/type/FileType$1/put(Ljava/lang/Object;Ljava/lang/Object;)Ljava/lang/Object;
pop
return
.limit locals 2
.limit stack 3
.end method
