.bytecode 50.0
.class public synchronized android/support/v4/view/KeyEventCompat
.super java/lang/Object
.inner class static BaseKeyEventVersionImpl inner android/support/v4/view/KeyEventCompat$BaseKeyEventVersionImpl outer android/support/v4/view/KeyEventCompat
.inner class static HoneycombKeyEventVersionImpl inner android/support/v4/view/KeyEventCompat$HoneycombKeyEventVersionImpl outer android/support/v4/view/KeyEventCompat
.inner class static abstract interface KeyEventVersionImpl inner android/support/v4/view/KeyEventCompat$KeyEventVersionImpl outer android/support/v4/view/KeyEventCompat

.field static final 'IMPL' Landroid/support/v4/view/KeyEventCompat$KeyEventVersionImpl;

.method static <clinit>()V
getstatic android/os/Build$VERSION/SDK_INT I
bipush 11
if_icmplt L0
new android/support/v4/view/KeyEventCompat$HoneycombKeyEventVersionImpl
dup
invokespecial android/support/v4/view/KeyEventCompat$HoneycombKeyEventVersionImpl/<init>()V
putstatic android/support/v4/view/KeyEventCompat/IMPL Landroid/support/v4/view/KeyEventCompat$KeyEventVersionImpl;
return
L0:
new android/support/v4/view/KeyEventCompat$BaseKeyEventVersionImpl
dup
invokespecial android/support/v4/view/KeyEventCompat$BaseKeyEventVersionImpl/<init>()V
putstatic android/support/v4/view/KeyEventCompat/IMPL Landroid/support/v4/view/KeyEventCompat$KeyEventVersionImpl;
return
.limit locals 0
.limit stack 2
.end method

.method public <init>()V
aload 0
invokespecial java/lang/Object/<init>()V
return
.limit locals 1
.limit stack 1
.end method

.method public static hasModifiers(Landroid/view/KeyEvent;I)Z
getstatic android/support/v4/view/KeyEventCompat/IMPL Landroid/support/v4/view/KeyEventCompat$KeyEventVersionImpl;
aload 0
invokevirtual android/view/KeyEvent/getMetaState()I
iload 1
invokeinterface android/support/v4/view/KeyEventCompat$KeyEventVersionImpl/metaStateHasModifiers(II)Z 2
ireturn
.limit locals 2
.limit stack 3
.end method

.method public static hasNoModifiers(Landroid/view/KeyEvent;)Z
getstatic android/support/v4/view/KeyEventCompat/IMPL Landroid/support/v4/view/KeyEventCompat$KeyEventVersionImpl;
aload 0
invokevirtual android/view/KeyEvent/getMetaState()I
invokeinterface android/support/v4/view/KeyEventCompat$KeyEventVersionImpl/metaStateHasNoModifiers(I)Z 1
ireturn
.limit locals 1
.limit stack 2
.end method

.method public static metaStateHasModifiers(II)Z
getstatic android/support/v4/view/KeyEventCompat/IMPL Landroid/support/v4/view/KeyEventCompat$KeyEventVersionImpl;
iload 0
iload 1
invokeinterface android/support/v4/view/KeyEventCompat$KeyEventVersionImpl/metaStateHasModifiers(II)Z 2
ireturn
.limit locals 2
.limit stack 3
.end method

.method public static metaStateHasNoModifiers(I)Z
getstatic android/support/v4/view/KeyEventCompat/IMPL Landroid/support/v4/view/KeyEventCompat$KeyEventVersionImpl;
iload 0
invokeinterface android/support/v4/view/KeyEventCompat$KeyEventVersionImpl/metaStateHasNoModifiers(I)Z 1
ireturn
.limit locals 1
.limit stack 2
.end method

.method public static normalizeMetaState(I)I
getstatic android/support/v4/view/KeyEventCompat/IMPL Landroid/support/v4/view/KeyEventCompat$KeyEventVersionImpl;
iload 0
invokeinterface android/support/v4/view/KeyEventCompat$KeyEventVersionImpl/normalizeMetaState(I)I 1
ireturn
.limit locals 1
.limit stack 2
.end method
