.bytecode 50.0
.class public synchronized android/support/v4/view/ViewCompatJB
.super java/lang/Object

.method public <init>()V
aload 0
invokespecial java/lang/Object/<init>()V
return
.limit locals 1
.limit stack 1
.end method

.method public static getAccessibilityNodeProvider(Landroid/view/View;)Ljava/lang/Object;
aload 0
invokevirtual android/view/View/getAccessibilityNodeProvider()Landroid/view/accessibility/AccessibilityNodeProvider;
areturn
.limit locals 1
.limit stack 1
.end method

.method public static getImportantForAccessibility(Landroid/view/View;)I
aload 0
invokevirtual android/view/View/getImportantForAccessibility()I
ireturn
.limit locals 1
.limit stack 1
.end method

.method public static hasTransientState(Landroid/view/View;)Z
aload 0
invokevirtual android/view/View/hasTransientState()Z
ireturn
.limit locals 1
.limit stack 1
.end method

.method public static performAccessibilityAction(Landroid/view/View;ILandroid/os/Bundle;)Z
aload 0
iload 1
aload 2
invokevirtual android/view/View/performAccessibilityAction(ILandroid/os/Bundle;)Z
ireturn
.limit locals 3
.limit stack 3
.end method

.method public static postInvalidateOnAnimation(Landroid/view/View;)V
aload 0
invokevirtual android/view/View/postInvalidateOnAnimation()V
return
.limit locals 1
.limit stack 1
.end method

.method public static postInvalidateOnAnimation(Landroid/view/View;IIII)V
aload 0
iload 1
iload 2
iload 3
iload 4
invokevirtual android/view/View/postInvalidate(IIII)V
return
.limit locals 5
.limit stack 5
.end method

.method public static postOnAnimation(Landroid/view/View;Ljava/lang/Runnable;)V
aload 0
aload 1
invokevirtual android/view/View/postOnAnimation(Ljava/lang/Runnable;)V
return
.limit locals 2
.limit stack 2
.end method

.method public static postOnAnimationDelayed(Landroid/view/View;Ljava/lang/Runnable;J)V
aload 0
aload 1
lload 2
invokevirtual android/view/View/postOnAnimationDelayed(Ljava/lang/Runnable;J)V
return
.limit locals 4
.limit stack 4
.end method

.method public static setHasTransientState(Landroid/view/View;Z)V
aload 0
iload 1
invokevirtual android/view/View/setHasTransientState(Z)V
return
.limit locals 2
.limit stack 2
.end method

.method public static setImportantForAccessibility(Landroid/view/View;I)V
aload 0
iload 1
invokevirtual android/view/View/setImportantForAccessibility(I)V
return
.limit locals 2
.limit stack 2
.end method
