.bytecode 50.0
.class synchronized android/support/v4/view/ViewCompat$JBViewCompatImpl
.super android/support/v4/view/ViewCompat$ICSViewCompatImpl
.inner class static JBViewCompatImpl inner android/support/v4/view/ViewCompat$JBViewCompatImpl outer android/support/v4/view/ViewCompat

.method <init>()V
aload 0
invokespecial android/support/v4/view/ViewCompat$ICSViewCompatImpl/<init>()V
return
.limit locals 1
.limit stack 1
.end method

.method public getAccessibilityNodeProvider(Landroid/view/View;)Landroid/support/v4/view/accessibility/AccessibilityNodeProviderCompat;
aload 1
invokestatic android/support/v4/view/ViewCompatJB/getAccessibilityNodeProvider(Landroid/view/View;)Ljava/lang/Object;
astore 1
aload 1
ifnull L0
new android/support/v4/view/accessibility/AccessibilityNodeProviderCompat
dup
aload 1
invokespecial android/support/v4/view/accessibility/AccessibilityNodeProviderCompat/<init>(Ljava/lang/Object;)V
areturn
L0:
aconst_null
areturn
.limit locals 2
.limit stack 3
.end method

.method public getImportantForAccessibility(Landroid/view/View;)I
aload 1
invokestatic android/support/v4/view/ViewCompatJB/getImportantForAccessibility(Landroid/view/View;)I
ireturn
.limit locals 2
.limit stack 1
.end method

.method public hasTransientState(Landroid/view/View;)Z
aload 1
invokestatic android/support/v4/view/ViewCompatJB/hasTransientState(Landroid/view/View;)Z
ireturn
.limit locals 2
.limit stack 1
.end method

.method public performAccessibilityAction(Landroid/view/View;ILandroid/os/Bundle;)Z
aload 1
iload 2
aload 3
invokestatic android/support/v4/view/ViewCompatJB/performAccessibilityAction(Landroid/view/View;ILandroid/os/Bundle;)Z
ireturn
.limit locals 4
.limit stack 3
.end method

.method public postInvalidateOnAnimation(Landroid/view/View;)V
aload 1
invokestatic android/support/v4/view/ViewCompatJB/postInvalidateOnAnimation(Landroid/view/View;)V
return
.limit locals 2
.limit stack 1
.end method

.method public postInvalidateOnAnimation(Landroid/view/View;IIII)V
aload 1
iload 2
iload 3
iload 4
iload 5
invokestatic android/support/v4/view/ViewCompatJB/postInvalidateOnAnimation(Landroid/view/View;IIII)V
return
.limit locals 6
.limit stack 5
.end method

.method public postOnAnimation(Landroid/view/View;Ljava/lang/Runnable;)V
aload 1
aload 2
invokestatic android/support/v4/view/ViewCompatJB/postOnAnimation(Landroid/view/View;Ljava/lang/Runnable;)V
return
.limit locals 3
.limit stack 2
.end method

.method public postOnAnimationDelayed(Landroid/view/View;Ljava/lang/Runnable;J)V
aload 1
aload 2
lload 3
invokestatic android/support/v4/view/ViewCompatJB/postOnAnimationDelayed(Landroid/view/View;Ljava/lang/Runnable;J)V
return
.limit locals 5
.limit stack 4
.end method

.method public setHasTransientState(Landroid/view/View;Z)V
aload 1
iload 2
invokestatic android/support/v4/view/ViewCompatJB/setHasTransientState(Landroid/view/View;Z)V
return
.limit locals 3
.limit stack 2
.end method

.method public setImportantForAccessibility(Landroid/view/View;I)V
aload 1
iload 2
invokestatic android/support/v4/view/ViewCompatJB/setImportantForAccessibility(Landroid/view/View;I)V
return
.limit locals 3
.limit stack 2
.end method
