.bytecode 50.0
.class synchronized com/common/android/utils/download/DownloadModule$downloadRunnable
.super java/lang/Object
.implements java/lang/Runnable
.inner class downloadRunnable inner com/common/android/utils/download/DownloadModule$downloadRunnable outer com/common/android/utils/download/DownloadModule

.field 'message' Landroid/os/Message;

.field final synthetic 'this$0' Lcom/common/android/utils/download/DownloadModule;

.method <init>(Lcom/common/android/utils/download/DownloadModule;)V
aload 0
aload 1
putfield com/common/android/utils/download/DownloadModule$downloadRunnable/this$0 Lcom/common/android/utils/download/DownloadModule;
aload 0
invokespecial java/lang/Object/<init>()V
aload 0
aload 0
getfield com/common/android/utils/download/DownloadModule$downloadRunnable/this$0 Lcom/common/android/utils/download/DownloadModule;
invokestatic com/common/android/utils/download/DownloadModule/access$600(Lcom/common/android/utils/download/DownloadModule;)Landroid/os/Handler;
invokevirtual android/os/Handler/obtainMessage()Landroid/os/Message;
putfield com/common/android/utils/download/DownloadModule$downloadRunnable/message Landroid/os/Message;
return
.limit locals 2
.limit stack 2
.end method

.method public run()V
.catch java/lang/Exception from L0 to L1 using L2
.catch java/lang/Exception from L3 to L4 using L2
.catch java/lang/Exception from L4 to L5 using L2
.catch java/lang/Exception from L5 to L6 using L2
aload 0
getfield com/common/android/utils/download/DownloadModule$downloadRunnable/message Landroid/os/Message;
iconst_0
putfield android/os/Message/what I
L0:
aload 0
getfield com/common/android/utils/download/DownloadModule$downloadRunnable/this$0 Lcom/common/android/utils/download/DownloadModule;
aload 0
getfield com/common/android/utils/download/DownloadModule$downloadRunnable/this$0 Lcom/common/android/utils/download/DownloadModule;
invokestatic com/common/android/utils/download/DownloadModule/access$000(Lcom/common/android/utils/download/DownloadModule;)Ljava/lang/String;
invokevirtual com/common/android/utils/download/DownloadModule/getFilename(Ljava/lang/String;)Ljava/lang/String;
astore 1
L1:
aload 1
ifnull L4
L3:
aload 0
getfield com/common/android/utils/download/DownloadModule$downloadRunnable/this$0 Lcom/common/android/utils/download/DownloadModule;
aload 1
ldc "utf-8"
invokestatic java/net/URLDecoder/decode(Ljava/lang/String;Ljava/lang/String;)Ljava/lang/String;
invokestatic com/common/android/utils/download/DownloadModule/access$302(Lcom/common/android/utils/download/DownloadModule;Ljava/lang/String;)Ljava/lang/String;
pop
L4:
aload 0
getfield com/common/android/utils/download/DownloadModule$downloadRunnable/this$0 Lcom/common/android/utils/download/DownloadModule;
new java/io/File
dup
aload 0
getfield com/common/android/utils/download/DownloadModule$downloadRunnable/this$0 Lcom/common/android/utils/download/DownloadModule;
invokestatic com/common/android/utils/download/DownloadModule/access$500(Lcom/common/android/utils/download/DownloadModule;)Ljava/io/File;
invokevirtual java/io/File/getPath()Ljava/lang/String;
aload 0
getfield com/common/android/utils/download/DownloadModule$downloadRunnable/this$0 Lcom/common/android/utils/download/DownloadModule;
invokestatic com/common/android/utils/download/DownloadModule/access$300(Lcom/common/android/utils/download/DownloadModule;)Ljava/lang/String;
invokespecial java/io/File/<init>(Ljava/lang/String;Ljava/lang/String;)V
invokestatic com/common/android/utils/download/DownloadModule/access$402(Lcom/common/android/utils/download/DownloadModule;Ljava/io/File;)Ljava/io/File;
pop
aload 0
getfield com/common/android/utils/download/DownloadModule$downloadRunnable/this$0 Lcom/common/android/utils/download/DownloadModule;
invokestatic com/common/android/utils/download/DownloadModule/access$400(Lcom/common/android/utils/download/DownloadModule;)Ljava/io/File;
invokevirtual java/io/File/exists()Z
ifne L5
aload 0
getfield com/common/android/utils/download/DownloadModule$downloadRunnable/this$0 Lcom/common/android/utils/download/DownloadModule;
invokestatic com/common/android/utils/download/DownloadModule/access$400(Lcom/common/android/utils/download/DownloadModule;)Ljava/io/File;
invokevirtual java/io/File/createNewFile()Z
pop
L5:
aload 0
getfield com/common/android/utils/download/DownloadModule$downloadRunnable/this$0 Lcom/common/android/utils/download/DownloadModule;
aload 0
getfield com/common/android/utils/download/DownloadModule$downloadRunnable/this$0 Lcom/common/android/utils/download/DownloadModule;
invokestatic com/common/android/utils/download/DownloadModule/access$000(Lcom/common/android/utils/download/DownloadModule;)Ljava/lang/String;
aload 0
getfield com/common/android/utils/download/DownloadModule$downloadRunnable/this$0 Lcom/common/android/utils/download/DownloadModule;
invokestatic com/common/android/utils/download/DownloadModule/access$400(Lcom/common/android/utils/download/DownloadModule;)Ljava/io/File;
invokevirtual com/common/android/utils/download/DownloadModule/downloadFile(Ljava/lang/String;Ljava/io/File;)J
lconst_0
lcmp
ifle L6
aload 0
getfield com/common/android/utils/download/DownloadModule$downloadRunnable/this$0 Lcom/common/android/utils/download/DownloadModule;
invokestatic com/common/android/utils/download/DownloadModule/access$600(Lcom/common/android/utils/download/DownloadModule;)Landroid/os/Handler;
aload 0
getfield com/common/android/utils/download/DownloadModule$downloadRunnable/message Landroid/os/Message;
invokevirtual android/os/Handler/sendMessage(Landroid/os/Message;)Z
pop
L6:
return
L2:
astore 1
aload 1
invokevirtual java/lang/Exception/printStackTrace()V
aload 0
getfield com/common/android/utils/download/DownloadModule$downloadRunnable/message Landroid/os/Message;
iconst_1
putfield android/os/Message/what I
aload 0
getfield com/common/android/utils/download/DownloadModule$downloadRunnable/this$0 Lcom/common/android/utils/download/DownloadModule;
invokestatic com/common/android/utils/download/DownloadModule/access$600(Lcom/common/android/utils/download/DownloadModule;)Landroid/os/Handler;
aload 0
getfield com/common/android/utils/download/DownloadModule$downloadRunnable/message Landroid/os/Message;
invokevirtual android/os/Handler/sendMessage(Landroid/os/Message;)Z
pop
return
.limit locals 2
.limit stack 5
.end method
