.bytecode 50.0
.class synchronized com/common/android/ui/LocalAlbum/LocalAlbumMultiSelect$1$1
.super java/lang/Object
.implements java/lang/Runnable
.enclosing method com/common/android/ui/LocalAlbum/LocalAlbumMultiSelect$1/run()V
.inner class inner com/common/android/ui/LocalAlbum/LocalAlbumMultiSelect$1
.inner class inner com/common/android/ui/LocalAlbum/LocalAlbumMultiSelect$1$1

.field final synthetic 'this$1' Lcom/common/android/ui/LocalAlbum/LocalAlbumMultiSelect$1;

.field final synthetic 'val$list' Ljava/util/ArrayList;

.method <init>(Lcom/common/android/ui/LocalAlbum/LocalAlbumMultiSelect$1;Ljava/util/ArrayList;)V
aload 0
aload 1
putfield com/common/android/ui/LocalAlbum/LocalAlbumMultiSelect$1$1/this$1 Lcom/common/android/ui/LocalAlbum/LocalAlbumMultiSelect$1;
aload 0
aload 2
putfield com/common/android/ui/LocalAlbum/LocalAlbumMultiSelect$1$1/val$list Ljava/util/ArrayList;
aload 0
invokespecial java/lang/Object/<init>()V
return
.limit locals 3
.limit stack 2
.end method

.method public run()V
aload 0
getfield com/common/android/ui/LocalAlbum/LocalAlbumMultiSelect$1$1/val$list Ljava/util/ArrayList;
ifnull L0
aload 0
getfield com/common/android/ui/LocalAlbum/LocalAlbumMultiSelect$1$1/this$1 Lcom/common/android/ui/LocalAlbum/LocalAlbumMultiSelect$1;
getfield com/common/android/ui/LocalAlbum/LocalAlbumMultiSelect$1/this$0 Lcom/common/android/ui/LocalAlbum/LocalAlbumMultiSelect;
aload 0
getfield com/common/android/ui/LocalAlbum/LocalAlbumMultiSelect$1$1/val$list Ljava/util/ArrayList;
invokestatic com/common/android/ui/LocalAlbum/LocalAlbumMultiSelect/access$302(Lcom/common/android/ui/LocalAlbum/LocalAlbumMultiSelect;Ljava/util/ArrayList;)Ljava/util/ArrayList;
pop
L0:
aload 0
getfield com/common/android/ui/LocalAlbum/LocalAlbumMultiSelect$1$1/this$1 Lcom/common/android/ui/LocalAlbum/LocalAlbumMultiSelect$1;
getfield com/common/android/ui/LocalAlbum/LocalAlbumMultiSelect$1/this$0 Lcom/common/android/ui/LocalAlbum/LocalAlbumMultiSelect;
invokestatic com/common/android/ui/LocalAlbum/LocalAlbumMultiSelect/access$400(Lcom/common/android/ui/LocalAlbum/LocalAlbumMultiSelect;)Lcom/common/android/ui/LocalAlbum/LocalAlbumMultiSelect$HeadGridViewAdapter;
invokevirtual com/common/android/ui/LocalAlbum/LocalAlbumMultiSelect$HeadGridViewAdapter/notifyDataSetChanged()V
aload 0
getfield com/common/android/ui/LocalAlbum/LocalAlbumMultiSelect$1$1/this$1 Lcom/common/android/ui/LocalAlbum/LocalAlbumMultiSelect$1;
getfield com/common/android/ui/LocalAlbum/LocalAlbumMultiSelect$1/this$0 Lcom/common/android/ui/LocalAlbum/LocalAlbumMultiSelect;
invokestatic com/common/android/ui/LocalAlbum/LocalAlbumMultiSelect/access$500(Lcom/common/android/ui/LocalAlbum/LocalAlbumMultiSelect;)Lcom/common/android/ui/LocalAlbum/LocalAlbumMultiSelect$AlbumListAdapter;
invokevirtual com/common/android/ui/LocalAlbum/LocalAlbumMultiSelect$AlbumListAdapter/notifyDataSetChanged()V
aload 0
getfield com/common/android/ui/LocalAlbum/LocalAlbumMultiSelect$1$1/this$1 Lcom/common/android/ui/LocalAlbum/LocalAlbumMultiSelect$1;
getfield com/common/android/ui/LocalAlbum/LocalAlbumMultiSelect$1/this$0 Lcom/common/android/ui/LocalAlbum/LocalAlbumMultiSelect;
invokestatic com/common/android/ui/LocalAlbum/LocalAlbumMultiSelect/access$600(Lcom/common/android/ui/LocalAlbum/LocalAlbumMultiSelect;)Lcom/common/android/ui/LocalAlbum/LocalAlbumMultiSelect$SelectMoreGridViewAdapter;
invokevirtual com/common/android/ui/LocalAlbum/LocalAlbumMultiSelect$SelectMoreGridViewAdapter/notifyDataSetChanged()V
aload 0
getfield com/common/android/ui/LocalAlbum/LocalAlbumMultiSelect$1$1/this$1 Lcom/common/android/ui/LocalAlbum/LocalAlbumMultiSelect$1;
getfield com/common/android/ui/LocalAlbum/LocalAlbumMultiSelect$1/this$0 Lcom/common/android/ui/LocalAlbum/LocalAlbumMultiSelect;
invokestatic com/common/android/ui/LocalAlbum/LocalAlbumMultiSelect/access$700(Lcom/common/android/ui/LocalAlbum/LocalAlbumMultiSelect;)V
aload 0
getfield com/common/android/ui/LocalAlbum/LocalAlbumMultiSelect$1$1/this$1 Lcom/common/android/ui/LocalAlbum/LocalAlbumMultiSelect$1;
getfield com/common/android/ui/LocalAlbum/LocalAlbumMultiSelect$1/this$0 Lcom/common/android/ui/LocalAlbum/LocalAlbumMultiSelect;
invokevirtual com/common/android/ui/LocalAlbum/LocalAlbumMultiSelect/setFinishBtnText()V
return
.limit locals 1
.limit stack 2
.end method
