.bytecode 50.0
.class synchronized com/nd/android/u/cloud/activity/guide/JimeiDlgFindPsw$1
.super java/lang/Object
.implements android/view/View$OnClickListener
.enclosing method com/nd/android/u/cloud/activity/guide/JimeiDlgFindPsw
.inner class inner com/nd/android/u/cloud/activity/guide/JimeiDlgFindPsw$1

.field final synthetic 'this$0' Lcom/nd/android/u/cloud/activity/guide/JimeiDlgFindPsw;

.method <init>(Lcom/nd/android/u/cloud/activity/guide/JimeiDlgFindPsw;)V
aload 0
aload 1
putfield com/nd/android/u/cloud/activity/guide/JimeiDlgFindPsw$1/this$0 Lcom/nd/android/u/cloud/activity/guide/JimeiDlgFindPsw;
aload 0
invokespecial java/lang/Object/<init>()V
return
.limit locals 2
.limit stack 2
.end method

.method public onClick(Landroid/view/View;)V
aload 1
invokevirtual android/view/View/getId()I
tableswitch 2131624682
L0
L1
default : L2
L2:
return
L0:
aload 0
getfield com/nd/android/u/cloud/activity/guide/JimeiDlgFindPsw$1/this$0 Lcom/nd/android/u/cloud/activity/guide/JimeiDlgFindPsw;
invokestatic com/nd/android/u/cloud/activity/guide/JimeiDlgFindPsw/access$000(Lcom/nd/android/u/cloud/activity/guide/JimeiDlgFindPsw;)Lcom/nd/android/u/cloud/activity/guide/DlgFindPsw$OnDlgBtnListener;
ifnull L3
aload 0
getfield com/nd/android/u/cloud/activity/guide/JimeiDlgFindPsw$1/this$0 Lcom/nd/android/u/cloud/activity/guide/JimeiDlgFindPsw;
invokestatic com/nd/android/u/cloud/activity/guide/JimeiDlgFindPsw/access$000(Lcom/nd/android/u/cloud/activity/guide/JimeiDlgFindPsw;)Lcom/nd/android/u/cloud/activity/guide/DlgFindPsw$OnDlgBtnListener;
invokeinterface com/nd/android/u/cloud/activity/guide/DlgFindPsw$OnDlgBtnListener/onCancel()V 0
L3:
aload 0
getfield com/nd/android/u/cloud/activity/guide/JimeiDlgFindPsw$1/this$0 Lcom/nd/android/u/cloud/activity/guide/JimeiDlgFindPsw;
invokevirtual com/nd/android/u/cloud/activity/guide/JimeiDlgFindPsw/dismiss()V
return
L1:
aload 0
getfield com/nd/android/u/cloud/activity/guide/JimeiDlgFindPsw$1/this$0 Lcom/nd/android/u/cloud/activity/guide/JimeiDlgFindPsw;
invokestatic com/nd/android/u/cloud/activity/guide/JimeiDlgFindPsw/access$000(Lcom/nd/android/u/cloud/activity/guide/JimeiDlgFindPsw;)Lcom/nd/android/u/cloud/activity/guide/DlgFindPsw$OnDlgBtnListener;
ifnull L4
aload 0
getfield com/nd/android/u/cloud/activity/guide/JimeiDlgFindPsw$1/this$0 Lcom/nd/android/u/cloud/activity/guide/JimeiDlgFindPsw;
invokestatic com/nd/android/u/cloud/activity/guide/JimeiDlgFindPsw/access$000(Lcom/nd/android/u/cloud/activity/guide/JimeiDlgFindPsw;)Lcom/nd/android/u/cloud/activity/guide/DlgFindPsw$OnDlgBtnListener;
invokeinterface com/nd/android/u/cloud/activity/guide/DlgFindPsw$OnDlgBtnListener/onOK()V 0
L4:
aload 0
getfield com/nd/android/u/cloud/activity/guide/JimeiDlgFindPsw$1/this$0 Lcom/nd/android/u/cloud/activity/guide/JimeiDlgFindPsw;
invokevirtual com/nd/android/u/cloud/activity/guide/JimeiDlgFindPsw/dismiss()V
return
.limit locals 2
.limit stack 1
.end method
