.bytecode 50.0
.class synchronized com/nd/android/u/tast/experience/activity/DateWidgetActivity$8$2
.super java/lang/Object
.implements java/lang/Runnable
.enclosing method com/nd/android/u/tast/experience/activity/DateWidgetActivity$8/run()V
.inner class inner com/nd/android/u/tast/experience/activity/DateWidgetActivity$8
.inner class inner com/nd/android/u/tast/experience/activity/DateWidgetActivity$8$2

.field final synthetic 'this$1' Lcom/nd/android/u/tast/experience/activity/DateWidgetActivity$8;

.field final synthetic 'val$getSignResultBuf' Ljava/lang/StringBuffer;

.field final synthetic 'val$signHistoryList' Ljava/lang/StringBuilder;

.method <init>(Lcom/nd/android/u/tast/experience/activity/DateWidgetActivity$8;Ljava/lang/StringBuilder;Ljava/lang/StringBuffer;)V
aload 0
aload 1
putfield com/nd/android/u/tast/experience/activity/DateWidgetActivity$8$2/this$1 Lcom/nd/android/u/tast/experience/activity/DateWidgetActivity$8;
aload 0
aload 2
putfield com/nd/android/u/tast/experience/activity/DateWidgetActivity$8$2/val$signHistoryList Ljava/lang/StringBuilder;
aload 0
aload 3
putfield com/nd/android/u/tast/experience/activity/DateWidgetActivity$8$2/val$getSignResultBuf Ljava/lang/StringBuffer;
aload 0
invokespecial java/lang/Object/<init>()V
return
.limit locals 4
.limit stack 2
.end method

.method public run()V
aload 0
getfield com/nd/android/u/tast/experience/activity/DateWidgetActivity$8$2/this$1 Lcom/nd/android/u/tast/experience/activity/DateWidgetActivity$8;
getfield com/nd/android/u/tast/experience/activity/DateWidgetActivity$8/this$0 Lcom/nd/android/u/tast/experience/activity/DateWidgetActivity;
aload 0
getfield com/nd/android/u/tast/experience/activity/DateWidgetActivity$8$2/this$1 Lcom/nd/android/u/tast/experience/activity/DateWidgetActivity$8;
getfield com/nd/android/u/tast/experience/activity/DateWidgetActivity$8/this$0 Lcom/nd/android/u/tast/experience/activity/DateWidgetActivity;
invokestatic com/nd/android/u/tast/experience/activity/DateWidgetActivity/access$1600(Lcom/nd/android/u/tast/experience/activity/DateWidgetActivity;)Ljava/lang/String;
invokestatic com/nd/android/u/tast/experience/activity/DateWidgetActivity/access$3300(Lcom/nd/android/u/tast/experience/activity/DateWidgetActivity;Ljava/lang/String;)Z
ifne L0
aload 0
getfield com/nd/android/u/tast/experience/activity/DateWidgetActivity$8$2/this$1 Lcom/nd/android/u/tast/experience/activity/DateWidgetActivity$8;
getfield com/nd/android/u/tast/experience/activity/DateWidgetActivity$8/this$0 Lcom/nd/android/u/tast/experience/activity/DateWidgetActivity;
aload 0
getfield com/nd/android/u/tast/experience/activity/DateWidgetActivity$8$2/this$1 Lcom/nd/android/u/tast/experience/activity/DateWidgetActivity$8;
getfield com/nd/android/u/tast/experience/activity/DateWidgetActivity$8/this$0 Lcom/nd/android/u/tast/experience/activity/DateWidgetActivity;
invokestatic com/nd/android/u/tast/experience/activity/DateWidgetActivity/access$3400(Lcom/nd/android/u/tast/experience/activity/DateWidgetActivity;)Ljava/util/Calendar;
invokestatic com/nd/android/u/tast/experience/activity/DateWidgetActivity/access$502(Lcom/nd/android/u/tast/experience/activity/DateWidgetActivity;Ljava/util/Calendar;)Ljava/util/Calendar;
pop
L0:
aload 0
getfield com/nd/android/u/tast/experience/activity/DateWidgetActivity$8$2/val$signHistoryList Ljava/lang/StringBuilder;
invokevirtual java/lang/StringBuilder/length()I
ifle L1
aload 0
getfield com/nd/android/u/tast/experience/activity/DateWidgetActivity$8$2/this$1 Lcom/nd/android/u/tast/experience/activity/DateWidgetActivity$8;
getfield com/nd/android/u/tast/experience/activity/DateWidgetActivity$8/this$0 Lcom/nd/android/u/tast/experience/activity/DateWidgetActivity;
aload 0
getfield com/nd/android/u/tast/experience/activity/DateWidgetActivity$8$2/val$signHistoryList Ljava/lang/StringBuilder;
invokevirtual java/lang/StringBuilder/toString()Ljava/lang/String;
invokestatic com/nd/android/u/tast/experience/activity/DateWidgetActivity/access$1102(Lcom/nd/android/u/tast/experience/activity/DateWidgetActivity;Ljava/lang/String;)Ljava/lang/String;
pop
L1:
aload 0
getfield com/nd/android/u/tast/experience/activity/DateWidgetActivity$8$2/this$1 Lcom/nd/android/u/tast/experience/activity/DateWidgetActivity$8;
getfield com/nd/android/u/tast/experience/activity/DateWidgetActivity$8/this$0 Lcom/nd/android/u/tast/experience/activity/DateWidgetActivity;
aload 0
getfield com/nd/android/u/tast/experience/activity/DateWidgetActivity$8$2/this$1 Lcom/nd/android/u/tast/experience/activity/DateWidgetActivity$8;
getfield com/nd/android/u/tast/experience/activity/DateWidgetActivity$8/this$0 Lcom/nd/android/u/tast/experience/activity/DateWidgetActivity;
invokestatic com/nd/android/u/tast/experience/activity/DateWidgetActivity/access$1100(Lcom/nd/android/u/tast/experience/activity/DateWidgetActivity;)Ljava/lang/String;
invokestatic com/nd/android/u/tast/experience/activity/DateWidgetActivity/access$1200(Lcom/nd/android/u/tast/experience/activity/DateWidgetActivity;Ljava/lang/String;)V
aload 0
getfield com/nd/android/u/tast/experience/activity/DateWidgetActivity$8$2/val$getSignResultBuf Ljava/lang/StringBuffer;
invokevirtual java/lang/StringBuffer/length()I
ifle L2
aload 0
getfield com/nd/android/u/tast/experience/activity/DateWidgetActivity$8$2/this$1 Lcom/nd/android/u/tast/experience/activity/DateWidgetActivity$8;
getfield com/nd/android/u/tast/experience/activity/DateWidgetActivity$8/this$0 Lcom/nd/android/u/tast/experience/activity/DateWidgetActivity;
aload 0
getfield com/nd/android/u/tast/experience/activity/DateWidgetActivity$8$2/val$getSignResultBuf Ljava/lang/StringBuffer;
invokevirtual java/lang/StringBuffer/toString()Ljava/lang/String;
invokestatic com/common/android/utils/ToastUtils/displayTimeLong(Landroid/content/Context;Ljava/lang/String;)V
L2:
return
.limit locals 1
.limit stack 2
.end method
