.bytecode 50.0
.class synchronized com/nd/android/u/tast/experience/activity/DateWidgetActivity$8
.super java/lang/Object
.implements java/lang/Runnable
.enclosing method com/nd/android/u/tast/experience/activity/DateWidgetActivity/doSign()V
.inner class inner com/nd/android/u/tast/experience/activity/DateWidgetActivity$8
.inner class inner com/nd/android/u/tast/experience/activity/DateWidgetActivity$8$1
.inner class inner com/nd/android/u/tast/experience/activity/DateWidgetActivity$8$2

.field private 'exp' I

.field private 'flower' I

.field private 'fullSignStatus' I

.field private 'levelUp' Z

.field private 'money' I

.field final synthetic 'this$0' Lcom/nd/android/u/tast/experience/activity/DateWidgetActivity;

.method <init>(Lcom/nd/android/u/tast/experience/activity/DateWidgetActivity;)V
aload 0
aload 1
putfield com/nd/android/u/tast/experience/activity/DateWidgetActivity$8/this$0 Lcom/nd/android/u/tast/experience/activity/DateWidgetActivity;
aload 0
invokespecial java/lang/Object/<init>()V
aload 0
iconst_0
putfield com/nd/android/u/tast/experience/activity/DateWidgetActivity$8/levelUp Z
aload 0
iconst_0
putfield com/nd/android/u/tast/experience/activity/DateWidgetActivity$8/exp I
aload 0
iconst_0
putfield com/nd/android/u/tast/experience/activity/DateWidgetActivity$8/money I
aload 0
iconst_0
putfield com/nd/android/u/tast/experience/activity/DateWidgetActivity$8/flower I
aload 0
iconst_0
putfield com/nd/android/u/tast/experience/activity/DateWidgetActivity$8/fullSignStatus I
return
.limit locals 2
.limit stack 2
.end method

.method static synthetic access$2200(Lcom/nd/android/u/tast/experience/activity/DateWidgetActivity$8;)I
aload 0
getfield com/nd/android/u/tast/experience/activity/DateWidgetActivity$8/exp I
ireturn
.limit locals 1
.limit stack 1
.end method

.method static synthetic access$2400(Lcom/nd/android/u/tast/experience/activity/DateWidgetActivity$8;)I
aload 0
getfield com/nd/android/u/tast/experience/activity/DateWidgetActivity$8/money I
ireturn
.limit locals 1
.limit stack 1
.end method

.method static synthetic access$2600(Lcom/nd/android/u/tast/experience/activity/DateWidgetActivity$8;)I
aload 0
getfield com/nd/android/u/tast/experience/activity/DateWidgetActivity$8/flower I
ireturn
.limit locals 1
.limit stack 1
.end method

.method static synthetic access$2900(Lcom/nd/android/u/tast/experience/activity/DateWidgetActivity$8;)Z
aload 0
getfield com/nd/android/u/tast/experience/activity/DateWidgetActivity$8/levelUp Z
ireturn
.limit locals 1
.limit stack 1
.end method

.method public run()V
.catch com/common/android/utils/http/HttpAuthException from L0 to L1 using L2
.catch com/common/android/utils/http/ResponseException from L0 to L1 using L3
.catch com/common/android/utils/http/HttpServerException from L0 to L1 using L4
.catch com/common/android/utils/http/HttpException from L0 to L1 using L5
.catch com/common/android/utils/http/HttpAuthException from L6 to L7 using L2
.catch com/common/android/utils/http/ResponseException from L6 to L7 using L3
.catch com/common/android/utils/http/HttpServerException from L6 to L7 using L4
.catch com/common/android/utils/http/HttpException from L6 to L7 using L5
.catch com/common/android/utils/http/HttpAuthException from L8 to L9 using L2
.catch com/common/android/utils/http/ResponseException from L8 to L9 using L3
.catch com/common/android/utils/http/HttpServerException from L8 to L9 using L4
.catch com/common/android/utils/http/HttpException from L8 to L9 using L5
.catch java/text/ParseException from L10 to L11 using L12
.catch java/text/ParseException from L13 to L14 using L12
new com/nd/android/u/tast/com/AjaxCom
dup
invokespecial com/nd/android/u/tast/com/AjaxCom/<init>()V
astore 2
L0:
aload 2
invokevirtual com/nd/android/u/tast/com/AjaxCom/getscore()Lorg/json/JSONObject;
astore 3
aload 3
ldc "code"
invokevirtual org/json/JSONObject/optInt(Ljava/lang/String;)I
istore 1
L1:
iload 1
sipush 200
if_icmpeq L6
iload 1
sipush 201
if_icmpne L9
L6:
invokestatic com/nd/android/u/tast/TaskGlobalVariable/getInstance()Lcom/nd/android/u/tast/TaskGlobalVariable;
getfield com/nd/android/u/tast/TaskGlobalVariable/mOapScore Lcom/product/android/commonInterface/task/OapScore;
iconst_1
invokevirtual com/product/android/commonInterface/task/OapScore/setSignstatus(I)V
new java/text/SimpleDateFormat
dup
ldc "yyyy-MM-dd"
invokespecial java/text/SimpleDateFormat/<init>(Ljava/lang/String;)V
new java/util/Date
dup
invokestatic java/lang/System/currentTimeMillis()J
invokespecial java/util/Date/<init>(J)V
invokevirtual java/text/SimpleDateFormat/format(Ljava/util/Date;)Ljava/lang/String;
astore 4
invokestatic com/product/android/business/manager/DataUpdateManager/getInstance()Lcom/product/android/business/manager/DataUpdateManager;
ldc "sign_in_one_day"
aload 4
invokevirtual com/product/android/business/manager/DataUpdateManager/save(Ljava/lang/String;Ljava/lang/String;)V
aload 0
aload 3
ldc "totalexp"
invokestatic com/common/android/utils/JSONUtils/getInt(Lorg/json/JSONObject;Ljava/lang/String;)I
putfield com/nd/android/u/tast/experience/activity/DateWidgetActivity$8/exp I
aload 0
aload 3
ldc "totalflower"
invokestatic com/common/android/utils/JSONUtils/getInt(Lorg/json/JSONObject;Ljava/lang/String;)I
putfield com/nd/android/u/tast/experience/activity/DateWidgetActivity$8/flower I
aload 0
aload 3
ldc "totalmoney"
invokestatic com/common/android/utils/JSONUtils/getInt(Lorg/json/JSONObject;Ljava/lang/String;)I
putfield com/nd/android/u/tast/experience/activity/DateWidgetActivity$8/money I
aload 0
aload 3
ldc "fullsignstatus"
invokestatic com/common/android/utils/JSONUtils/getInt(Lorg/json/JSONObject;Ljava/lang/String;)I
putfield com/nd/android/u/tast/experience/activity/DateWidgetActivity$8/fullSignStatus I
aload 0
getfield com/nd/android/u/tast/experience/activity/DateWidgetActivity$8/this$0 Lcom/nd/android/u/tast/experience/activity/DateWidgetActivity;
aload 3
ldc "signday"
invokevirtual org/json/JSONObject/optString(Ljava/lang/String;)Ljava/lang/String;
invokestatic com/nd/android/u/tast/experience/activity/DateWidgetActivity/access$1602(Lcom/nd/android/u/tast/experience/activity/DateWidgetActivity;Ljava/lang/String;)Ljava/lang/String;
pop
aload 0
getfield com/nd/android/u/tast/experience/activity/DateWidgetActivity$8/this$0 Lcom/nd/android/u/tast/experience/activity/DateWidgetActivity;
invokestatic com/nd/android/u/tast/experience/activity/DateWidgetActivity/access$1700(Lcom/nd/android/u/tast/experience/activity/DateWidgetActivity;)Lcom/nd/android/u/tast/experience/calendar/SaveDate;
aload 0
getfield com/nd/android/u/tast/experience/activity/DateWidgetActivity$8/this$0 Lcom/nd/android/u/tast/experience/activity/DateWidgetActivity;
aload 0
getfield com/nd/android/u/tast/experience/activity/DateWidgetActivity$8/this$0 Lcom/nd/android/u/tast/experience/activity/DateWidgetActivity;
invokestatic com/nd/android/u/tast/experience/activity/DateWidgetActivity/access$1600(Lcom/nd/android/u/tast/experience/activity/DateWidgetActivity;)Ljava/lang/String;
invokevirtual com/nd/android/u/tast/experience/calendar/SaveDate/saveDate(Landroid/content/Context;Ljava/lang/String;)V
new java/math/BigDecimal
dup
aload 3
ldc "fullsignpercent"
invokestatic com/common/android/utils/JSONUtils/getDouble(Lorg/json/JSONObject;Ljava/lang/String;)D
ldc2_w 100.0D
dmul
invokespecial java/math/BigDecimal/<init>(D)V
iconst_1
iconst_4
invokevirtual java/math/BigDecimal/setScale(II)Ljava/math/BigDecimal;
astore 4
aload 0
getfield com/nd/android/u/tast/experience/activity/DateWidgetActivity$8/this$0 Lcom/nd/android/u/tast/experience/activity/DateWidgetActivity;
new java/lang/StringBuilder
dup
invokespecial java/lang/StringBuilder/<init>()V
aload 4
invokevirtual java/lang/StringBuilder/append(Ljava/lang/Object;)Ljava/lang/StringBuilder;
ldc "%"
invokevirtual java/lang/StringBuilder/append(Ljava/lang/String;)Ljava/lang/StringBuilder;
invokevirtual java/lang/StringBuilder/toString()Ljava/lang/String;
invokestatic com/nd/android/u/tast/experience/activity/DateWidgetActivity/access$1802(Lcom/nd/android/u/tast/experience/activity/DateWidgetActivity;Ljava/lang/String;)Ljava/lang/String;
pop
aload 0
getfield com/nd/android/u/tast/experience/activity/DateWidgetActivity$8/this$0 Lcom/nd/android/u/tast/experience/activity/DateWidgetActivity;
aload 0
getfield com/nd/android/u/tast/experience/activity/DateWidgetActivity$8/exp I
aload 0
getfield com/nd/android/u/tast/experience/activity/DateWidgetActivity$8/money I
aload 0
getfield com/nd/android/u/tast/experience/activity/DateWidgetActivity$8/flower I
invokevirtual com/nd/android/u/tast/experience/activity/DateWidgetActivity/updateGlobalScoreData(III)V
L7:
iload 1
sipush 200
if_icmpne L9
L8:
aload 0
aload 0
getfield com/nd/android/u/tast/experience/activity/DateWidgetActivity$8/this$0 Lcom/nd/android/u/tast/experience/activity/DateWidgetActivity;
aload 3
aload 2
invokevirtual com/nd/android/u/tast/experience/activity/DateWidgetActivity/reGetScore(Lorg/json/JSONObject;Lcom/nd/android/u/tast/com/AjaxCom;)Z
putfield com/nd/android/u/tast/experience/activity/DateWidgetActivity$8/levelUp Z
L9:
aload 0
getfield com/nd/android/u/tast/experience/activity/DateWidgetActivity$8/this$0 Lcom/nd/android/u/tast/experience/activity/DateWidgetActivity;
new com/nd/android/u/tast/experience/activity/DateWidgetActivity$8$1
dup
aload 0
invokespecial com/nd/android/u/tast/experience/activity/DateWidgetActivity$8$1/<init>(Lcom/nd/android/u/tast/experience/activity/DateWidgetActivity$8;)V
invokevirtual com/nd/android/u/tast/experience/activity/DateWidgetActivity/runOnUiThread(Ljava/lang/Runnable;)V
new java/lang/StringBuffer
dup
invokespecial java/lang/StringBuffer/<init>()V
astore 4
aconst_null
astore 2
L10:
aload 0
getfield com/nd/android/u/tast/experience/activity/DateWidgetActivity$8/this$0 Lcom/nd/android/u/tast/experience/activity/DateWidgetActivity;
invokestatic com/nd/android/u/tast/experience/activity/DateWidgetActivity/access$1600(Lcom/nd/android/u/tast/experience/activity/DateWidgetActivity;)Ljava/lang/String;
invokestatic android/text/TextUtils/isEmpty(Ljava/lang/CharSequence;)Z
ifne L13
aload 0
getfield com/nd/android/u/tast/experience/activity/DateWidgetActivity$8/this$0 Lcom/nd/android/u/tast/experience/activity/DateWidgetActivity;
invokestatic com/nd/android/u/tast/experience/activity/DateWidgetActivity/access$1600(Lcom/nd/android/u/tast/experience/activity/DateWidgetActivity;)Ljava/lang/String;
astore 3
aload 0
getfield com/nd/android/u/tast/experience/activity/DateWidgetActivity$8/this$0 Lcom/nd/android/u/tast/experience/activity/DateWidgetActivity;
invokestatic com/nd/android/u/tast/experience/activity/DateWidgetActivity/access$3100(Lcom/nd/android/u/tast/experience/activity/DateWidgetActivity;)Ljava/text/SimpleDateFormat;
aload 3
invokevirtual java/text/SimpleDateFormat/parse(Ljava/lang/String;)Ljava/util/Date;
astore 3
L11:
aload 3
astore 2
L15:
new java/lang/StringBuilder
dup
invokespecial java/lang/StringBuilder/<init>()V
astore 3
aload 2
ifnull L16
aload 3
aload 2
iconst_0
invokestatic com/nd/android/u/tast/experience/activity/DateWidgetActivity/getYearOrMonth(Ljava/util/Date;I)I
aload 2
iconst_1
invokestatic com/nd/android/u/tast/experience/activity/DateWidgetActivity/getYearOrMonth(Ljava/util/Date;I)I
aload 0
getfield com/nd/android/u/tast/experience/activity/DateWidgetActivity$8/this$0 Lcom/nd/android/u/tast/experience/activity/DateWidgetActivity;
invokestatic com/nd/android/u/tast/experience/activity/DateWidgetActivity/access$1100(Lcom/nd/android/u/tast/experience/activity/DateWidgetActivity;)Ljava/lang/String;
aload 4
invokestatic com/nd/android/u/tast/experience/activity/DateWidgetActivity/getSignStr(IILjava/lang/String;Ljava/lang/StringBuffer;)Ljava/lang/String;
invokevirtual java/lang/StringBuilder/append(Ljava/lang/String;)Ljava/lang/StringBuilder;
pop
L16:
aload 0
getfield com/nd/android/u/tast/experience/activity/DateWidgetActivity$8/this$0 Lcom/nd/android/u/tast/experience/activity/DateWidgetActivity;
new com/nd/android/u/tast/experience/activity/DateWidgetActivity$8$2
dup
aload 0
aload 3
aload 4
invokespecial com/nd/android/u/tast/experience/activity/DateWidgetActivity$8$2/<init>(Lcom/nd/android/u/tast/experience/activity/DateWidgetActivity$8;Ljava/lang/StringBuilder;Ljava/lang/StringBuffer;)V
invokevirtual com/nd/android/u/tast/experience/activity/DateWidgetActivity/runOnUiThread(Ljava/lang/Runnable;)V
return
L2:
astore 2
aload 2
invokevirtual com/common/android/utils/http/HttpAuthException/printStackTrace()V
goto L9
L3:
astore 2
aload 2
invokevirtual com/common/android/utils/http/ResponseException/printStackTrace()V
goto L9
L4:
astore 2
aload 2
invokevirtual com/common/android/utils/http/HttpServerException/printStackTrace()V
goto L9
L5:
astore 2
aload 2
invokevirtual com/common/android/utils/http/HttpException/printStackTrace()V
goto L9
L13:
aload 0
getfield com/nd/android/u/tast/experience/activity/DateWidgetActivity$8/this$0 Lcom/nd/android/u/tast/experience/activity/DateWidgetActivity;
invokestatic com/nd/android/u/tast/experience/activity/DateWidgetActivity/access$600(Lcom/nd/android/u/tast/experience/activity/DateWidgetActivity;)Landroid/widget/TextView;
invokevirtual android/widget/TextView/getText()Ljava/lang/CharSequence;
invokeinterface java/lang/CharSequence/toString()Ljava/lang/String; 0
astore 3
aload 0
getfield com/nd/android/u/tast/experience/activity/DateWidgetActivity$8/this$0 Lcom/nd/android/u/tast/experience/activity/DateWidgetActivity;
invokestatic com/nd/android/u/tast/experience/activity/DateWidgetActivity/access$3200(Lcom/nd/android/u/tast/experience/activity/DateWidgetActivity;)Ljava/text/SimpleDateFormat;
aload 3
invokevirtual java/text/SimpleDateFormat/parse(Ljava/lang/String;)Ljava/util/Date;
astore 3
L14:
aload 3
astore 2
goto L15
L12:
astore 3
aload 4
ldc "Top_Date get Error."
invokevirtual java/lang/StringBuffer/append(Ljava/lang/String;)Ljava/lang/StringBuffer;
pop
goto L15
.limit locals 5
.limit stack 6
.end method
