.bytecode 50.0
.class public synchronized com/nd/android/u/tast/experience/activity/DateWidgetActivity
.super android/app/Activity
.implements com/nd/android/u/tast/experience/view/FullAttendanceListener
.inner class inner com/nd/android/u/tast/experience/activity/DateWidgetActivity$1
.inner class static final inner com/nd/android/u/tast/experience/activity/DateWidgetActivity$10
.inner class inner com/nd/android/u/tast/experience/activity/DateWidgetActivity$10$1
.inner class inner com/nd/android/u/tast/experience/activity/DateWidgetActivity$2
.inner class inner com/nd/android/u/tast/experience/activity/DateWidgetActivity$3
.inner class inner com/nd/android/u/tast/experience/activity/DateWidgetActivity$4
.inner class inner com/nd/android/u/tast/experience/activity/DateWidgetActivity$4$1
.inner class inner com/nd/android/u/tast/experience/activity/DateWidgetActivity$5
.inner class inner com/nd/android/u/tast/experience/activity/DateWidgetActivity$6
.inner class inner com/nd/android/u/tast/experience/activity/DateWidgetActivity$7
.inner class inner com/nd/android/u/tast/experience/activity/DateWidgetActivity$8
.inner class inner com/nd/android/u/tast/experience/activity/DateWidgetActivity$8$1
.inner class inner com/nd/android/u/tast/experience/activity/DateWidgetActivity$8$2
.inner class inner com/nd/android/u/tast/experience/activity/DateWidgetActivity$9
.inner class public static final enum MORE_EXP_STATUS inner com/nd/android/u/tast/experience/activity/DateWidgetActivity$MORE_EXP_STATUS outer com/nd/android/u/tast/experience/activity/DateWidgetActivity

.field private static final 'BIG_SIGN' I = 1


.field private static 'Calendar_DayBgColor' I = 0


.field private static final 'FAIL_SIGN' I = 3


.field public static final 'FLAG_TO_TASKMAIN' Ljava/lang/String; = "flag_to_taskmain"

.field private static final 'FULL_SIGN' I = 0


.field private static 'REFRESH_NUM' I = 0


.field private static final 'SAVE_FULL_SIGN_AND_EXP' I = 123658


.field private static final 'SMALL_SIGN' I = 2


.field private static final 'SUCCESS_SIGN' I = 4


.field protected static 'signExpTipsArray' [Ljava/lang/String;

.field protected static 'signStatusArray' [Ljava/lang/String;

.field private 'BirthDay' I

.field private 'BirthMonth' I

.field private 'Calendar_Width' I

.field private 'Cell_Height' I

.field private 'Cell_Width' I

.field private 'IsAnniversary' Z

.field private 'JoinDay' I

.field private 'JoinMonth' I

.field private 'Next_MonthOnClickListener' Landroid/view/View$OnClickListener;

.field private 'Pre_MonthOnClickListener' Landroid/view/View$OnClickListener;

.field private 'SignInList' Ljava/lang/String;

.field private 'StrBirthDay' Ljava/lang/String;

.field private 'StrJoinDay' Ljava/lang/String;

.field private 'StrToday' Ljava/lang/String;

.field private 'Top_Date' Landroid/widget/TextView;

.field private 'activity' Lcom/nd/android/u/tast/experience/activity/DateWidgetActivity;

.field private 'animationDrawable' Landroid/graphics/drawable/AnimationDrawable;

.field private 'animationIV' Landroid/widget/ImageView;

.field private 'anniversary_layout' Landroid/widget/LinearLayout;

.field private 'anniversary_txv' Landroid/widget/TextView;

.field private 'back_img' Landroid/widget/Button;

.field private 'calCalendar' Ljava/util/Calendar;

.field private 'calStartDate' Ljava/util/Calendar;

.field private 'calToday' Ljava/util/Calendar;

.field private 'calendarView_layout' Landroid/widget/LinearLayout;

.field private 'context' Landroid/content/Context;

.field private 'dateMD' Ljava/text/SimpleDateFormat;

.field private 'days' Ljava/util/ArrayList; signature "Ljava/util/ArrayList<Lcom/nd/android/u/tast/experience/calendar/DateWidgetDayCell;>;"

.field private 'duration' I

.field private 'endDate' Ljava/util/Calendar;

.field private 'fotmat' Ljava/text/SimpleDateFormat;

.field private 'fotmat1' Ljava/text/SimpleDateFormat;

.field private 'handler' Landroid/os/Handler;

.field private 'iFirstDayOfWeek' I

.field private 'iMonthViewCurrentMonth' I

.field private 'iMonthViewCurrentYear' I

.field private 'isHasInternet' Z

.field private 'isToTaskMain' I

.field private 'jfanniversary_txv' Landroid/widget/TextView;

.field private 'layContent' Landroid/widget/LinearLayout;

.field private 'leftDays' I

.field private 'mAdapter' Lcom/nd/android/u/tast/experience/adapter/MoreExperienceAdapter;

.field private 'mBirthdayLeft' Landroid/widget/TextView;

.field private 'mBusy' Z

.field private 'mExperience' Landroid/widget/TextView;

.field private 'mFlower' Landroid/widget/TextView;

.field private 'mFullSignStatus' I

.field private 'mGold' Landroid/widget/TextView;

.field private 'mHasSign' Z

.field private 'mRewardExp' I

.field private 'mScrollListener' Landroid/widget/AbsListView$OnScrollListener;

.field private 'mSignInfoContainer' Landroid/view/View;

.field private 'mSignLeftContainer' Landroid/view/View;

.field private 'mSignSuccess' Landroid/view/View;

.field private 'mSignTimes' Landroid/widget/TextView;

.field private 'mSignTip' Landroid/widget/TextView;

.field private 'morepoints_listview' Landroid/widget/ListView;

.field private 'pop_Cell_Height' I

.field private 'pop_Cell_Width' I

.field private 'return_OnClickListener' Landroid/view/View$OnClickListener;

.field private 'saveDate' Lcom/nd/android/u/tast/experience/calendar/SaveDate;

.field private 'screenHeight' F

.field private 'screenWidth' I

.field private 'signDay' Ljava/lang/String;

.field private 'signPercent' Ljava/lang/String;

.field private 'signed_tips_list' [Ljava/lang/String;

.field private 'signin_animIV' Landroid/widget/ImageView;

.field private 'signin_animaDrawable' Landroid/graphics/drawable/AnimationDrawable;

.field private 'signin_tips_list' [Ljava/lang/String;

.field private 'signintips_txv' Landroid/widget/TextView;

.field private 'special_day_list' [Ljava/lang/String;

.field private 'startDate' Ljava/util/Calendar;

.field private 'today' Ljava/util/Date;

.field private 'tvMoreexperience' Landroid/widget/TextView;

.field private 'tvSignHoldTips' Landroid/widget/TextView;

.method static <clinit>()V
getstatic com/product/android/business/ApplicationVariable/INSTANCE Lcom/product/android/business/ApplicationVariable;
getfield com/product/android/business/ApplicationVariable/applicationContext Landroid/content/Context;
invokevirtual android/content/Context/getResources()Landroid/content/res/Resources;
getstatic com/nd/android/u/tasklib/R$array/signExpTips I
invokevirtual android/content/res/Resources/getStringArray(I)[Ljava/lang/String;
putstatic com/nd/android/u/tast/experience/activity/DateWidgetActivity/signExpTipsArray [Ljava/lang/String;
getstatic com/product/android/business/ApplicationVariable/INSTANCE Lcom/product/android/business/ApplicationVariable;
getfield com/product/android/business/ApplicationVariable/applicationContext Landroid/content/Context;
invokevirtual android/content/Context/getResources()Landroid/content/res/Resources;
getstatic com/nd/android/u/tasklib/R$array/full_sign_type I
invokevirtual android/content/res/Resources/getStringArray(I)[Ljava/lang/String;
putstatic com/nd/android/u/tast/experience/activity/DateWidgetActivity/signStatusArray [Ljava/lang/String;
iconst_0
putstatic com/nd/android/u/tast/experience/activity/DateWidgetActivity/Calendar_DayBgColor I
bipush 30
putstatic com/nd/android/u/tast/experience/activity/DateWidgetActivity/REFRESH_NUM I
return
.limit locals 0
.limit stack 2
.end method

.method public <init>()V
aload 0
invokespecial android/app/Activity/<init>()V
aload 0
aconst_null
putfield com/nd/android/u/tast/experience/activity/DateWidgetActivity/layContent Landroid/widget/LinearLayout;
aload 0
new java/util/ArrayList
dup
invokespecial java/util/ArrayList/<init>()V
putfield com/nd/android/u/tast/experience/activity/DateWidgetActivity/days Ljava/util/ArrayList;
aload 0
invokestatic java/util/Calendar/getInstance()Ljava/util/Calendar;
putfield com/nd/android/u/tast/experience/activity/DateWidgetActivity/calStartDate Ljava/util/Calendar;
aload 0
invokestatic java/util/Calendar/getInstance()Ljava/util/Calendar;
putfield com/nd/android/u/tast/experience/activity/DateWidgetActivity/calToday Ljava/util/Calendar;
aload 0
invokestatic java/util/Calendar/getInstance()Ljava/util/Calendar;
putfield com/nd/android/u/tast/experience/activity/DateWidgetActivity/calCalendar Ljava/util/Calendar;
aload 0
iconst_0
putfield com/nd/android/u/tast/experience/activity/DateWidgetActivity/iMonthViewCurrentMonth I
aload 0
iconst_0
putfield com/nd/android/u/tast/experience/activity/DateWidgetActivity/iMonthViewCurrentYear I
aload 0
iconst_1
putfield com/nd/android/u/tast/experience/activity/DateWidgetActivity/iFirstDayOfWeek I
aload 0
iconst_0
putfield com/nd/android/u/tast/experience/activity/DateWidgetActivity/screenWidth I
aload 0
fconst_0
putfield com/nd/android/u/tast/experience/activity/DateWidgetActivity/screenHeight F
aload 0
iconst_0
putfield com/nd/android/u/tast/experience/activity/DateWidgetActivity/Calendar_Width I
aload 0
iconst_0
putfield com/nd/android/u/tast/experience/activity/DateWidgetActivity/Cell_Width I
aload 0
iconst_0
putfield com/nd/android/u/tast/experience/activity/DateWidgetActivity/Cell_Height I
aload 0
iconst_0
putfield com/nd/android/u/tast/experience/activity/DateWidgetActivity/pop_Cell_Width I
aload 0
iconst_0
putfield com/nd/android/u/tast/experience/activity/DateWidgetActivity/pop_Cell_Height I
aload 0
aconst_null
putfield com/nd/android/u/tast/experience/activity/DateWidgetActivity/Top_Date Landroid/widget/TextView;
aload 0
aconst_null
putfield com/nd/android/u/tast/experience/activity/DateWidgetActivity/calendarView_layout Landroid/widget/LinearLayout;
aload 0
aconst_null
putfield com/nd/android/u/tast/experience/activity/DateWidgetActivity/startDate Ljava/util/Calendar;
aload 0
aconst_null
putfield com/nd/android/u/tast/experience/activity/DateWidgetActivity/endDate Ljava/util/Calendar;
aload 0
aload 0
putfield com/nd/android/u/tast/experience/activity/DateWidgetActivity/activity Lcom/nd/android/u/tast/experience/activity/DateWidgetActivity;
aload 0
aconst_null
putfield com/nd/android/u/tast/experience/activity/DateWidgetActivity/back_img Landroid/widget/Button;
aload 0
iconst_0
putfield com/nd/android/u/tast/experience/activity/DateWidgetActivity/mHasSign Z
aload 0
iconst_1
putfield com/nd/android/u/tast/experience/activity/DateWidgetActivity/isHasInternet Z
aload 0
new java/text/SimpleDateFormat
dup
ldc "yyyy\u5e74MM\u6708"
invokespecial java/text/SimpleDateFormat/<init>(Ljava/lang/String;)V
putfield com/nd/android/u/tast/experience/activity/DateWidgetActivity/fotmat Ljava/text/SimpleDateFormat;
aload 0
new java/text/SimpleDateFormat
dup
ldc "yyyy-MM-dd"
invokespecial java/text/SimpleDateFormat/<init>(Ljava/lang/String;)V
putfield com/nd/android/u/tast/experience/activity/DateWidgetActivity/fotmat1 Ljava/text/SimpleDateFormat;
aload 0
ldc ""
putfield com/nd/android/u/tast/experience/activity/DateWidgetActivity/SignInList Ljava/lang/String;
aload 0
new java/text/SimpleDateFormat
dup
ldc "MM-dd"
invokespecial java/text/SimpleDateFormat/<init>(Ljava/lang/String;)V
putfield com/nd/android/u/tast/experience/activity/DateWidgetActivity/dateMD Ljava/text/SimpleDateFormat;
aload 0
aconst_null
putfield com/nd/android/u/tast/experience/activity/DateWidgetActivity/anniversary_layout Landroid/widget/LinearLayout;
aload 0
aconst_null
putfield com/nd/android/u/tast/experience/activity/DateWidgetActivity/anniversary_txv Landroid/widget/TextView;
aload 0
aconst_null
putfield com/nd/android/u/tast/experience/activity/DateWidgetActivity/signintips_txv Landroid/widget/TextView;
aload 0
aconst_null
putfield com/nd/android/u/tast/experience/activity/DateWidgetActivity/jfanniversary_txv Landroid/widget/TextView;
aload 0
iconst_0
putfield com/nd/android/u/tast/experience/activity/DateWidgetActivity/JoinMonth I
aload 0
iconst_0
putfield com/nd/android/u/tast/experience/activity/DateWidgetActivity/JoinDay I
aload 0
iconst_0
putfield com/nd/android/u/tast/experience/activity/DateWidgetActivity/BirthMonth I
aload 0
iconst_0
putfield com/nd/android/u/tast/experience/activity/DateWidgetActivity/BirthDay I
aload 0
ldc ""
putfield com/nd/android/u/tast/experience/activity/DateWidgetActivity/StrBirthDay Ljava/lang/String;
aload 0
ldc ""
putfield com/nd/android/u/tast/experience/activity/DateWidgetActivity/StrJoinDay Ljava/lang/String;
aload 0
ldc ""
putfield com/nd/android/u/tast/experience/activity/DateWidgetActivity/StrToday Ljava/lang/String;
aload 0
iconst_0
putfield com/nd/android/u/tast/experience/activity/DateWidgetActivity/IsAnniversary Z
aload 0
iconst_0
putfield com/nd/android/u/tast/experience/activity/DateWidgetActivity/mBusy Z
aload 0
aconst_null
putfield com/nd/android/u/tast/experience/activity/DateWidgetActivity/morepoints_listview Landroid/widget/ListView;
aload 0
iconst_0
putfield com/nd/android/u/tast/experience/activity/DateWidgetActivity/duration I
aload 0
new com/nd/android/u/tast/experience/calendar/SaveDate
dup
invokespecial com/nd/android/u/tast/experience/calendar/SaveDate/<init>()V
putfield com/nd/android/u/tast/experience/activity/DateWidgetActivity/saveDate Lcom/nd/android/u/tast/experience/calendar/SaveDate;
aload 0
iconst_0
putfield com/nd/android/u/tast/experience/activity/DateWidgetActivity/leftDays I
aload 0
aconst_null
putfield com/nd/android/u/tast/experience/activity/DateWidgetActivity/signDay Ljava/lang/String;
aload 0
new com/nd/android/u/tast/experience/activity/DateWidgetActivity$1
dup
aload 0
invokespecial com/nd/android/u/tast/experience/activity/DateWidgetActivity$1/<init>(Lcom/nd/android/u/tast/experience/activity/DateWidgetActivity;)V
putfield com/nd/android/u/tast/experience/activity/DateWidgetActivity/handler Landroid/os/Handler;
aload 0
iconst_0
putfield com/nd/android/u/tast/experience/activity/DateWidgetActivity/isToTaskMain I
aload 0
new com/nd/android/u/tast/experience/activity/DateWidgetActivity$2
dup
aload 0
invokespecial com/nd/android/u/tast/experience/activity/DateWidgetActivity$2/<init>(Lcom/nd/android/u/tast/experience/activity/DateWidgetActivity;)V
putfield com/nd/android/u/tast/experience/activity/DateWidgetActivity/Pre_MonthOnClickListener Landroid/view/View$OnClickListener;
aload 0
new com/nd/android/u/tast/experience/activity/DateWidgetActivity$3
dup
aload 0
invokespecial com/nd/android/u/tast/experience/activity/DateWidgetActivity$3/<init>(Lcom/nd/android/u/tast/experience/activity/DateWidgetActivity;)V
putfield com/nd/android/u/tast/experience/activity/DateWidgetActivity/Next_MonthOnClickListener Landroid/view/View$OnClickListener;
aload 0
new com/nd/android/u/tast/experience/activity/DateWidgetActivity$5
dup
aload 0
invokespecial com/nd/android/u/tast/experience/activity/DateWidgetActivity$5/<init>(Lcom/nd/android/u/tast/experience/activity/DateWidgetActivity;)V
putfield com/nd/android/u/tast/experience/activity/DateWidgetActivity/return_OnClickListener Landroid/view/View$OnClickListener;
aload 0
new com/nd/android/u/tast/experience/activity/DateWidgetActivity$7
dup
aload 0
invokespecial com/nd/android/u/tast/experience/activity/DateWidgetActivity$7/<init>(Lcom/nd/android/u/tast/experience/activity/DateWidgetActivity;)V
putfield com/nd/android/u/tast/experience/activity/DateWidgetActivity/mScrollListener Landroid/widget/AbsListView$OnScrollListener;
aload 0
ldc ""
putfield com/nd/android/u/tast/experience/activity/DateWidgetActivity/signPercent Ljava/lang/String;
return
.limit locals 1
.limit stack 4
.end method

.method private Add(Ljava/util/Date;II)Ljava/util/Date;
invokestatic java/util/Calendar/getInstance()Ljava/util/Calendar;
astore 4
aload 4
aload 1
invokevirtual java/util/Calendar/setTime(Ljava/util/Date;)V
aload 4
iload 2
iload 3
invokevirtual java/util/Calendar/add(II)V
aload 4
invokevirtual java/util/Calendar/getTime()Ljava/util/Date;
areturn
.limit locals 5
.limit stack 3
.end method

.method private DrawCalendarView()V
aload 0
getfield com/nd/android/u/tast/experience/activity/DateWidgetActivity/mHasSign Z
ifne L0
aload 0
getfield com/nd/android/u/tast/experience/activity/DateWidgetActivity/calendarView_layout Landroid/widget/LinearLayout;
ifnull L0
aload 0
invokespecial com/nd/android/u/tast/experience/activity/DateWidgetActivity/draw()V
aload 0
getfield com/nd/android/u/tast/experience/activity/DateWidgetActivity/signintips_txv Landroid/widget/TextView;
ldc "\u7b7e\u5230\u4e2d..."
invokevirtual android/widget/TextView/setText(Ljava/lang/CharSequence;)V
aload 0
invokespecial com/nd/android/u/tast/experience/activity/DateWidgetActivity/doSign()V
aload 0
iconst_1
putfield com/nd/android/u/tast/experience/activity/DateWidgetActivity/mHasSign Z
L0:
return
.limit locals 1
.limit stack 2
.end method

.method private UpdateCurrentMonthDisplay()V
new java/lang/StringBuilder
dup
invokespecial java/lang/StringBuilder/<init>()V
aload 0
getfield com/nd/android/u/tast/experience/activity/DateWidgetActivity/calStartDate Ljava/util/Calendar;
iconst_1
invokevirtual java/util/Calendar/get(I)I
invokevirtual java/lang/StringBuilder/append(I)Ljava/lang/StringBuilder;
ldc "\u5e74"
invokevirtual java/lang/StringBuilder/append(Ljava/lang/String;)Ljava/lang/StringBuilder;
aload 0
getfield com/nd/android/u/tast/experience/activity/DateWidgetActivity/calStartDate Ljava/util/Calendar;
iconst_2
invokevirtual java/util/Calendar/get(I)I
iconst_1
iadd
invokevirtual java/lang/StringBuilder/append(I)Ljava/lang/StringBuilder;
ldc "\u6708"
invokevirtual java/lang/StringBuilder/append(Ljava/lang/String;)Ljava/lang/StringBuilder;
invokevirtual java/lang/StringBuilder/toString()Ljava/lang/String;
astore 1
aload 0
getfield com/nd/android/u/tast/experience/activity/DateWidgetActivity/Top_Date Landroid/widget/TextView;
aload 1
invokevirtual android/widget/TextView/setText(Ljava/lang/CharSequence;)V
return
.limit locals 2
.limit stack 3
.end method

.method private UpdateStartDateForMonth()V
aload 0
aload 0
getfield com/nd/android/u/tast/experience/activity/DateWidgetActivity/calStartDate Ljava/util/Calendar;
iconst_2
invokevirtual java/util/Calendar/get(I)I
putfield com/nd/android/u/tast/experience/activity/DateWidgetActivity/iMonthViewCurrentMonth I
aload 0
aload 0
getfield com/nd/android/u/tast/experience/activity/DateWidgetActivity/calStartDate Ljava/util/Calendar;
iconst_1
invokevirtual java/util/Calendar/get(I)I
putfield com/nd/android/u/tast/experience/activity/DateWidgetActivity/iMonthViewCurrentYear I
aload 0
getfield com/nd/android/u/tast/experience/activity/DateWidgetActivity/calStartDate Ljava/util/Calendar;
iconst_5
iconst_1
invokevirtual java/util/Calendar/set(II)V
aload 0
getfield com/nd/android/u/tast/experience/activity/DateWidgetActivity/calStartDate Ljava/util/Calendar;
bipush 11
iconst_0
invokevirtual java/util/Calendar/set(II)V
aload 0
getfield com/nd/android/u/tast/experience/activity/DateWidgetActivity/calStartDate Ljava/util/Calendar;
bipush 12
iconst_0
invokevirtual java/util/Calendar/set(II)V
aload 0
getfield com/nd/android/u/tast/experience/activity/DateWidgetActivity/calStartDate Ljava/util/Calendar;
bipush 13
iconst_0
invokevirtual java/util/Calendar/set(II)V
aload 0
invokespecial com/nd/android/u/tast/experience/activity/DateWidgetActivity/UpdateCurrentMonthDisplay()V
iconst_0
istore 1
aload 0
getfield com/nd/android/u/tast/experience/activity/DateWidgetActivity/iFirstDayOfWeek I
istore 3
iload 3
iconst_2
if_icmpne L0
aload 0
getfield com/nd/android/u/tast/experience/activity/DateWidgetActivity/calStartDate Ljava/util/Calendar;
bipush 7
invokevirtual java/util/Calendar/get(I)I
iconst_2
isub
istore 2
iload 2
istore 1
iload 2
ifge L0
bipush 6
istore 1
L0:
iload 3
iconst_1
if_icmpne L1
aload 0
getfield com/nd/android/u/tast/experience/activity/DateWidgetActivity/calStartDate Ljava/util/Calendar;
bipush 7
invokevirtual java/util/Calendar/get(I)I
iconst_1
isub
istore 2
iload 2
istore 1
iload 2
ifge L1
bipush 6
istore 1
L1:
aload 0
getfield com/nd/android/u/tast/experience/activity/DateWidgetActivity/calStartDate Ljava/util/Calendar;
bipush 7
iload 1
ineg
invokevirtual java/util/Calendar/add(II)V
return
.limit locals 4
.limit stack 3
.end method

.method static synthetic access$000(Lcom/nd/android/u/tast/experience/activity/DateWidgetActivity;)Landroid/widget/TextView;
aload 0
getfield com/nd/android/u/tast/experience/activity/DateWidgetActivity/tvMoreexperience Landroid/widget/TextView;
areturn
.limit locals 1
.limit stack 1
.end method

.method static synthetic access$1000(Lcom/nd/android/u/tast/experience/activity/DateWidgetActivity;Ljava/lang/String;Z)V
aload 0
aload 1
iload 2
invokespecial com/nd/android/u/tast/experience/activity/DateWidgetActivity/updateCalendar(Ljava/lang/String;Z)V
return
.limit locals 3
.limit stack 3
.end method

.method static synthetic access$102(Lcom/nd/android/u/tast/experience/activity/DateWidgetActivity;I)I
aload 0
iload 1
putfield com/nd/android/u/tast/experience/activity/DateWidgetActivity/mRewardExp I
iload 1
ireturn
.limit locals 2
.limit stack 2
.end method

.method static synthetic access$1100(Lcom/nd/android/u/tast/experience/activity/DateWidgetActivity;)Ljava/lang/String;
aload 0
getfield com/nd/android/u/tast/experience/activity/DateWidgetActivity/SignInList Ljava/lang/String;
areturn
.limit locals 1
.limit stack 1
.end method

.method static synthetic access$1102(Lcom/nd/android/u/tast/experience/activity/DateWidgetActivity;Ljava/lang/String;)Ljava/lang/String;
aload 0
aload 1
putfield com/nd/android/u/tast/experience/activity/DateWidgetActivity/SignInList Ljava/lang/String;
aload 1
areturn
.limit locals 2
.limit stack 2
.end method

.method static synthetic access$1200(Lcom/nd/android/u/tast/experience/activity/DateWidgetActivity;Ljava/lang/String;)V
aload 0
aload 1
invokespecial com/nd/android/u/tast/experience/activity/DateWidgetActivity/updateCalendar(Ljava/lang/String;)V
return
.limit locals 2
.limit stack 2
.end method

.method static synthetic access$1300(Lcom/nd/android/u/tast/experience/activity/DateWidgetActivity;)V
aload 0
invokespecial com/nd/android/u/tast/experience/activity/DateWidgetActivity/back_ImMain()V
return
.limit locals 1
.limit stack 1
.end method

.method static synthetic access$1400(Lcom/nd/android/u/tast/experience/activity/DateWidgetActivity;)Landroid/graphics/drawable/AnimationDrawable;
aload 0
getfield com/nd/android/u/tast/experience/activity/DateWidgetActivity/signin_animaDrawable Landroid/graphics/drawable/AnimationDrawable;
areturn
.limit locals 1
.limit stack 1
.end method

.method static synthetic access$1500(Lcom/nd/android/u/tast/experience/activity/DateWidgetActivity;)Landroid/widget/ImageView;
aload 0
getfield com/nd/android/u/tast/experience/activity/DateWidgetActivity/signin_animIV Landroid/widget/ImageView;
areturn
.limit locals 1
.limit stack 1
.end method

.method static synthetic access$1600(Lcom/nd/android/u/tast/experience/activity/DateWidgetActivity;)Ljava/lang/String;
aload 0
getfield com/nd/android/u/tast/experience/activity/DateWidgetActivity/signDay Ljava/lang/String;
areturn
.limit locals 1
.limit stack 1
.end method

.method static synthetic access$1602(Lcom/nd/android/u/tast/experience/activity/DateWidgetActivity;Ljava/lang/String;)Ljava/lang/String;
aload 0
aload 1
putfield com/nd/android/u/tast/experience/activity/DateWidgetActivity/signDay Ljava/lang/String;
aload 1
areturn
.limit locals 2
.limit stack 2
.end method

.method static synthetic access$1700(Lcom/nd/android/u/tast/experience/activity/DateWidgetActivity;)Lcom/nd/android/u/tast/experience/calendar/SaveDate;
aload 0
getfield com/nd/android/u/tast/experience/activity/DateWidgetActivity/saveDate Lcom/nd/android/u/tast/experience/calendar/SaveDate;
areturn
.limit locals 1
.limit stack 1
.end method

.method static synthetic access$1802(Lcom/nd/android/u/tast/experience/activity/DateWidgetActivity;Ljava/lang/String;)Ljava/lang/String;
aload 0
aload 1
putfield com/nd/android/u/tast/experience/activity/DateWidgetActivity/signPercent Ljava/lang/String;
aload 1
areturn
.limit locals 2
.limit stack 2
.end method

.method static synthetic access$1900(Lcom/nd/android/u/tast/experience/activity/DateWidgetActivity;)Landroid/widget/TextView;
aload 0
getfield com/nd/android/u/tast/experience/activity/DateWidgetActivity/signintips_txv Landroid/widget/TextView;
areturn
.limit locals 1
.limit stack 1
.end method

.method static synthetic access$2000(Lcom/nd/android/u/tast/experience/activity/DateWidgetActivity;)Landroid/widget/TextView;
aload 0
getfield com/nd/android/u/tast/experience/activity/DateWidgetActivity/mSignTip Landroid/widget/TextView;
areturn
.limit locals 1
.limit stack 1
.end method

.method static synthetic access$202(Lcom/nd/android/u/tast/experience/activity/DateWidgetActivity;I)I
aload 0
iload 1
putfield com/nd/android/u/tast/experience/activity/DateWidgetActivity/mFullSignStatus I
iload 1
ireturn
.limit locals 2
.limit stack 2
.end method

.method static synthetic access$2100(Lcom/nd/android/u/tast/experience/activity/DateWidgetActivity;)Landroid/view/View;
aload 0
getfield com/nd/android/u/tast/experience/activity/DateWidgetActivity/mSignSuccess Landroid/view/View;
areturn
.limit locals 1
.limit stack 1
.end method

.method static synthetic access$2300(Lcom/nd/android/u/tast/experience/activity/DateWidgetActivity;)Landroid/widget/TextView;
aload 0
getfield com/nd/android/u/tast/experience/activity/DateWidgetActivity/mExperience Landroid/widget/TextView;
areturn
.limit locals 1
.limit stack 1
.end method

.method static synthetic access$2500(Lcom/nd/android/u/tast/experience/activity/DateWidgetActivity;)Landroid/widget/TextView;
aload 0
getfield com/nd/android/u/tast/experience/activity/DateWidgetActivity/mGold Landroid/widget/TextView;
areturn
.limit locals 1
.limit stack 1
.end method

.method static synthetic access$2700(Lcom/nd/android/u/tast/experience/activity/DateWidgetActivity;)Landroid/widget/TextView;
aload 0
getfield com/nd/android/u/tast/experience/activity/DateWidgetActivity/mFlower Landroid/widget/TextView;
areturn
.limit locals 1
.limit stack 1
.end method

.method static synthetic access$2800(Ljava/lang/String;)I
aload 0
invokestatic com/nd/android/u/tast/experience/activity/DateWidgetActivity/getSignDayIndex(Ljava/lang/String;)I
ireturn
.limit locals 1
.limit stack 1
.end method

.method static synthetic access$300(Lcom/nd/android/u/tast/experience/activity/DateWidgetActivity;)I
aload 0
getfield com/nd/android/u/tast/experience/activity/DateWidgetActivity/iMonthViewCurrentMonth I
ireturn
.limit locals 1
.limit stack 1
.end method

.method static synthetic access$3000(Lcom/nd/android/u/tast/experience/activity/DateWidgetActivity;)V
aload 0
invokespecial com/nd/android/u/tast/experience/activity/DateWidgetActivity/startAnimation()V
return
.limit locals 1
.limit stack 1
.end method

.method static synthetic access$302(Lcom/nd/android/u/tast/experience/activity/DateWidgetActivity;I)I
aload 0
iload 1
putfield com/nd/android/u/tast/experience/activity/DateWidgetActivity/iMonthViewCurrentMonth I
iload 1
ireturn
.limit locals 2
.limit stack 2
.end method

.method static synthetic access$308(Lcom/nd/android/u/tast/experience/activity/DateWidgetActivity;)I
aload 0
getfield com/nd/android/u/tast/experience/activity/DateWidgetActivity/iMonthViewCurrentMonth I
istore 1
aload 0
iload 1
iconst_1
iadd
putfield com/nd/android/u/tast/experience/activity/DateWidgetActivity/iMonthViewCurrentMonth I
iload 1
ireturn
.limit locals 2
.limit stack 3
.end method

.method static synthetic access$310(Lcom/nd/android/u/tast/experience/activity/DateWidgetActivity;)I
aload 0
getfield com/nd/android/u/tast/experience/activity/DateWidgetActivity/iMonthViewCurrentMonth I
istore 1
aload 0
iload 1
iconst_1
isub
putfield com/nd/android/u/tast/experience/activity/DateWidgetActivity/iMonthViewCurrentMonth I
iload 1
ireturn
.limit locals 2
.limit stack 3
.end method

.method static synthetic access$3100(Lcom/nd/android/u/tast/experience/activity/DateWidgetActivity;)Ljava/text/SimpleDateFormat;
aload 0
getfield com/nd/android/u/tast/experience/activity/DateWidgetActivity/fotmat1 Ljava/text/SimpleDateFormat;
areturn
.limit locals 1
.limit stack 1
.end method

.method static synthetic access$3200(Lcom/nd/android/u/tast/experience/activity/DateWidgetActivity;)Ljava/text/SimpleDateFormat;
aload 0
getfield com/nd/android/u/tast/experience/activity/DateWidgetActivity/fotmat Ljava/text/SimpleDateFormat;
areturn
.limit locals 1
.limit stack 1
.end method

.method static synthetic access$3300(Lcom/nd/android/u/tast/experience/activity/DateWidgetActivity;Ljava/lang/String;)Z
aload 0
aload 1
invokespecial com/nd/android/u/tast/experience/activity/DateWidgetActivity/checkTime(Ljava/lang/String;)Z
ireturn
.limit locals 2
.limit stack 2
.end method

.method static synthetic access$3400(Lcom/nd/android/u/tast/experience/activity/DateWidgetActivity;)Ljava/util/Calendar;
aload 0
invokespecial com/nd/android/u/tast/experience/activity/DateWidgetActivity/getCalendarStartDate()Ljava/util/Calendar;
areturn
.limit locals 1
.limit stack 1
.end method

.method static synthetic access$3500(Lcom/nd/android/u/tast/experience/activity/DateWidgetActivity;)Landroid/graphics/drawable/AnimationDrawable;
aload 0
getfield com/nd/android/u/tast/experience/activity/DateWidgetActivity/animationDrawable Landroid/graphics/drawable/AnimationDrawable;
areturn
.limit locals 1
.limit stack 1
.end method

.method static synthetic access$3600(Lcom/nd/android/u/tast/experience/activity/DateWidgetActivity;)Landroid/widget/ImageView;
aload 0
getfield com/nd/android/u/tast/experience/activity/DateWidgetActivity/animationIV Landroid/widget/ImageView;
areturn
.limit locals 1
.limit stack 1
.end method

.method static synthetic access$3700(Lcom/nd/android/u/tast/experience/activity/DateWidgetActivity;)Landroid/content/Context;
aload 0
getfield com/nd/android/u/tast/experience/activity/DateWidgetActivity/context Landroid/content/Context;
areturn
.limit locals 1
.limit stack 1
.end method

.method static synthetic access$400(Lcom/nd/android/u/tast/experience/activity/DateWidgetActivity;)I
aload 0
getfield com/nd/android/u/tast/experience/activity/DateWidgetActivity/iMonthViewCurrentYear I
ireturn
.limit locals 1
.limit stack 1
.end method

.method static synthetic access$408(Lcom/nd/android/u/tast/experience/activity/DateWidgetActivity;)I
aload 0
getfield com/nd/android/u/tast/experience/activity/DateWidgetActivity/iMonthViewCurrentYear I
istore 1
aload 0
iload 1
iconst_1
iadd
putfield com/nd/android/u/tast/experience/activity/DateWidgetActivity/iMonthViewCurrentYear I
iload 1
ireturn
.limit locals 2
.limit stack 3
.end method

.method static synthetic access$410(Lcom/nd/android/u/tast/experience/activity/DateWidgetActivity;)I
aload 0
getfield com/nd/android/u/tast/experience/activity/DateWidgetActivity/iMonthViewCurrentYear I
istore 1
aload 0
iload 1
iconst_1
isub
putfield com/nd/android/u/tast/experience/activity/DateWidgetActivity/iMonthViewCurrentYear I
iload 1
ireturn
.limit locals 2
.limit stack 3
.end method

.method static synthetic access$500(Lcom/nd/android/u/tast/experience/activity/DateWidgetActivity;)Ljava/util/Calendar;
aload 0
getfield com/nd/android/u/tast/experience/activity/DateWidgetActivity/calStartDate Ljava/util/Calendar;
areturn
.limit locals 1
.limit stack 1
.end method

.method static synthetic access$502(Lcom/nd/android/u/tast/experience/activity/DateWidgetActivity;Ljava/util/Calendar;)Ljava/util/Calendar;
aload 0
aload 1
putfield com/nd/android/u/tast/experience/activity/DateWidgetActivity/calStartDate Ljava/util/Calendar;
aload 1
areturn
.limit locals 2
.limit stack 2
.end method

.method static synthetic access$600(Lcom/nd/android/u/tast/experience/activity/DateWidgetActivity;)Landroid/widget/TextView;
aload 0
getfield com/nd/android/u/tast/experience/activity/DateWidgetActivity/Top_Date Landroid/widget/TextView;
areturn
.limit locals 1
.limit stack 1
.end method

.method static synthetic access$700(Lcom/nd/android/u/tast/experience/activity/DateWidgetActivity;)V
aload 0
invokespecial com/nd/android/u/tast/experience/activity/DateWidgetActivity/UpdateStartDateForMonth()V
return
.limit locals 1
.limit stack 1
.end method

.method static synthetic access$800(Lcom/nd/android/u/tast/experience/activity/DateWidgetActivity;)Ljava/util/Calendar;
aload 0
getfield com/nd/android/u/tast/experience/activity/DateWidgetActivity/startDate Ljava/util/Calendar;
areturn
.limit locals 1
.limit stack 1
.end method

.method static synthetic access$802(Lcom/nd/android/u/tast/experience/activity/DateWidgetActivity;Ljava/util/Calendar;)Ljava/util/Calendar;
aload 0
aload 1
putfield com/nd/android/u/tast/experience/activity/DateWidgetActivity/startDate Ljava/util/Calendar;
aload 1
areturn
.limit locals 2
.limit stack 2
.end method

.method static synthetic access$902(Lcom/nd/android/u/tast/experience/activity/DateWidgetActivity;Ljava/util/Calendar;)Ljava/util/Calendar;
aload 0
aload 1
putfield com/nd/android/u/tast/experience/activity/DateWidgetActivity/endDate Ljava/util/Calendar;
aload 1
areturn
.limit locals 2
.limit stack 2
.end method

.method private back_ImMain()V
aload 0
getfield com/nd/android/u/tast/experience/activity/DateWidgetActivity/isToTaskMain I
iconst_1
if_icmpne L0
aload 0
new android/content/Intent
dup
aload 0
ldc com/nd/android/u/tast/main/activity/TaskMainActivity
invokespecial android/content/Intent/<init>(Landroid/content/Context;Ljava/lang/Class;)V
invokevirtual com/nd/android/u/tast/experience/activity/DateWidgetActivity/startActivity(Landroid/content/Intent;)V
L0:
aload 0
invokevirtual com/nd/android/u/tast/experience/activity/DateWidgetActivity/finish()V
return
.limit locals 1
.limit stack 5
.end method

.method private checkTime(Ljava/lang/String;)Z
.catch java/lang/IndexOutOfBoundsException from L0 to L1 using L2
.catch java/lang/NumberFormatException from L0 to L1 using L3
aload 1
invokestatic android/text/TextUtils/isEmpty(Ljava/lang/CharSequence;)Z
ifne L4
aload 1
ldc "-"
invokevirtual java/lang/String/split(Ljava/lang/String;)[Ljava/lang/String;
astore 1
ldc "GMT+08:00"
invokestatic java/util/TimeZone/getTimeZone(Ljava/lang/String;)Ljava/util/TimeZone;
invokestatic java/util/Calendar/getInstance(Ljava/util/TimeZone;)Ljava/util/Calendar;
astore 4
aload 1
ifnull L5
L0:
aload 1
iconst_0
aaload
invokestatic java/lang/Integer/parseInt(Ljava/lang/String;)I
aload 4
iconst_1
invokevirtual java/util/Calendar/get(I)I
if_icmpne L5
aload 1
iconst_1
aaload
invokestatic java/lang/Integer/parseInt(Ljava/lang/String;)I
aload 4
iconst_2
invokevirtual java/util/Calendar/get(I)I
if_icmpne L5
aload 1
iconst_2
aaload
invokestatic java/lang/Integer/parseInt(Ljava/lang/String;)I
istore 2
aload 4
iconst_5
invokevirtual java/util/Calendar/get(I)I
istore 3
L1:
iload 2
iload 3
if_icmpne L5
iconst_1
ireturn
L5:
iconst_0
ireturn
L2:
astore 1
ldc "DateWidgetActivity IndexOutOfBoundsException"
ldc ""
invokestatic android/util/Log/e(Ljava/lang/String;Ljava/lang/String;)I
pop
iconst_0
ireturn
L3:
astore 1
ldc "DateWidgetActivity NumberFormatException"
ldc ""
invokestatic android/util/Log/e(Ljava/lang/String;Ljava/lang/String;)I
pop
iconst_0
ireturn
L4:
iconst_0
ireturn
.limit locals 5
.limit stack 3
.end method

.method private createLayout(I)Landroid/widget/LinearLayout;
new android/widget/LinearLayout
dup
aload 0
invokespecial android/widget/LinearLayout/<init>(Landroid/content/Context;)V
astore 2
aload 2
new android/widget/LinearLayout$LayoutParams
dup
iconst_m1
bipush -2
invokespecial android/widget/LinearLayout$LayoutParams/<init>(II)V
invokevirtual android/widget/LinearLayout/setLayoutParams(Landroid/view/ViewGroup$LayoutParams;)V
aload 2
iload 1
invokevirtual android/widget/LinearLayout/setOrientation(I)V
aload 2
areturn
.limit locals 3
.limit stack 5
.end method

.method private doSign()V
aload 0
getfield com/nd/android/u/tast/experience/activity/DateWidgetActivity/isHasInternet Z
ifeq L0
new java/lang/Thread
dup
new com/nd/android/u/tast/experience/activity/DateWidgetActivity$8
dup
aload 0
invokespecial com/nd/android/u/tast/experience/activity/DateWidgetActivity$8/<init>(Lcom/nd/android/u/tast/experience/activity/DateWidgetActivity;)V
invokespecial java/lang/Thread/<init>(Ljava/lang/Runnable;)V
invokevirtual java/lang/Thread/start()V
return
L0:
aload 0
getfield com/nd/android/u/tast/experience/activity/DateWidgetActivity/signintips_txv Landroid/widget/TextView;
ldc "\u7b7e\u5230\u5931\u8d25\uff0c\u8bf7\u7a0d\u540e\u91cd\u8bd5\uff01"
invokevirtual android/widget/TextView/setText(Ljava/lang/CharSequence;)V
aload 0
getfield com/nd/android/u/tast/experience/activity/DateWidgetActivity/mSignTip Landroid/widget/TextView;
iconst_0
invokevirtual android/widget/TextView/setVisibility(I)V
aload 0
getfield com/nd/android/u/tast/experience/activity/DateWidgetActivity/mSignSuccess Landroid/view/View;
bipush 8
invokevirtual android/view/View/setVisibility(I)V
aload 0
getfield com/nd/android/u/tast/experience/activity/DateWidgetActivity/mSignTip Landroid/widget/TextView;
ldc "\u7b7e\u5230\u5931\u8d25"
invokevirtual android/widget/TextView/setText(Ljava/lang/CharSequence;)V
aload 0
ldc ""
invokespecial com/nd/android/u/tast/experience/activity/DateWidgetActivity/updateCalendar(Ljava/lang/String;)V
return
.limit locals 1
.limit stack 5
.end method

.method private draw()V
aload 0
getfield com/nd/android/u/tast/experience/activity/DateWidgetActivity/calendarView_layout Landroid/widget/LinearLayout;
invokevirtual android/widget/LinearLayout/getChildCount()I
ifle L0
aload 0
getfield com/nd/android/u/tast/experience/activity/DateWidgetActivity/calendarView_layout Landroid/widget/LinearLayout;
invokevirtual android/widget/LinearLayout/removeAllViews()V
L0:
aload 0
aload 0
getfield com/nd/android/u/tast/experience/activity/DateWidgetActivity/screenWidth I
bipush 40
isub
bipush 7
idiv
putfield com/nd/android/u/tast/experience/activity/DateWidgetActivity/pop_Cell_Width I
aload 0
aload 0
getfield com/nd/android/u/tast/experience/activity/DateWidgetActivity/pop_Cell_Width I
iconst_2
idiv
putfield com/nd/android/u/tast/experience/activity/DateWidgetActivity/pop_Cell_Height I
aload 0
aload 0
invokevirtual com/nd/android/u/tast/experience/activity/DateWidgetActivity/GetStartDate()Ljava/util/Calendar;
putfield com/nd/android/u/tast/experience/activity/DateWidgetActivity/startDate Ljava/util/Calendar;
aload 0
aload 0
invokevirtual com/nd/android/u/tast/experience/activity/DateWidgetActivity/GetTodayDate()Ljava/util/Calendar;
putfield com/nd/android/u/tast/experience/activity/DateWidgetActivity/calToday Ljava/util/Calendar;
aload 0
aload 0
aload 0
getfield com/nd/android/u/tast/experience/activity/DateWidgetActivity/startDate Ljava/util/Calendar;
invokevirtual com/nd/android/u/tast/experience/activity/DateWidgetActivity/GetEndDate(Ljava/util/Calendar;)Ljava/util/Calendar;
putfield com/nd/android/u/tast/experience/activity/DateWidgetActivity/endDate Ljava/util/Calendar;
aload 0
invokespecial com/nd/android/u/tast/experience/activity/DateWidgetActivity/getTopDataView()Landroid/view/View;
astore 1
aload 0
aload 0
invokespecial com/nd/android/u/tast/experience/activity/DateWidgetActivity/getCalendarStartDate()Ljava/util/Calendar;
putfield com/nd/android/u/tast/experience/activity/DateWidgetActivity/calStartDate Ljava/util/Calendar;
aload 0
getfield com/nd/android/u/tast/experience/activity/DateWidgetActivity/calendarView_layout Landroid/widget/LinearLayout;
bipush 17
invokevirtual android/widget/LinearLayout/setGravity(I)V
aload 0
getfield com/nd/android/u/tast/experience/activity/DateWidgetActivity/calendarView_layout Landroid/widget/LinearLayout;
aload 1
invokevirtual android/widget/LinearLayout/addView(Landroid/view/View;)V
aload 0
getfield com/nd/android/u/tast/experience/activity/DateWidgetActivity/calendarView_layout Landroid/widget/LinearLayout;
aload 0
invokespecial com/nd/android/u/tast/experience/activity/DateWidgetActivity/generateCalendarMain()Landroid/view/View;
invokevirtual android/widget/LinearLayout/addView(Landroid/view/View;)V
aload 0
getfield com/nd/android/u/tast/experience/activity/DateWidgetActivity/calendarView_layout Landroid/widget/LinearLayout;
getstatic com/nd/android/u/tasklib/R$drawable/calendar_bg I
invokevirtual android/widget/LinearLayout/setBackgroundResource(I)V
return
.limit locals 2
.limit stack 3
.end method

.method private findControls()V
aload 0
invokevirtual com/nd/android/u/tast/experience/activity/DateWidgetActivity/getWindowManager()Landroid/view/WindowManager;
invokeinterface android/view/WindowManager/getDefaultDisplay()Landroid/view/Display; 0
astore 1
aload 0
aload 1
invokevirtual android/view/Display/getWidth()I
putfield com/nd/android/u/tast/experience/activity/DateWidgetActivity/screenWidth I
aload 0
aload 1
invokevirtual android/view/Display/getHeight()I
i2f
ldc_w 0.7F
fmul
putfield com/nd/android/u/tast/experience/activity/DateWidgetActivity/screenHeight F
aload 0
aload 0
getfield com/nd/android/u/tast/experience/activity/DateWidgetActivity/screenWidth I
bipush 9
imul
bipush 10
idiv
putfield com/nd/android/u/tast/experience/activity/DateWidgetActivity/Calendar_Width I
aload 0
aload 0
getfield com/nd/android/u/tast/experience/activity/DateWidgetActivity/Calendar_Width I
bipush 7
idiv
putfield com/nd/android/u/tast/experience/activity/DateWidgetActivity/Cell_Width I
aload 0
aload 0
getfield com/nd/android/u/tast/experience/activity/DateWidgetActivity/Cell_Width I
iconst_2
imul
iconst_3
idiv
putfield com/nd/android/u/tast/experience/activity/DateWidgetActivity/Cell_Height I
aload 0
aload 0
getstatic com/nd/android/u/tasklib/R$id/calendarView_layout I
invokevirtual com/nd/android/u/tast/experience/activity/DateWidgetActivity/findViewById(I)Landroid/view/View;
checkcast android/widget/LinearLayout
putfield com/nd/android/u/tast/experience/activity/DateWidgetActivity/calendarView_layout Landroid/widget/LinearLayout;
aload 0
invokevirtual com/nd/android/u/tast/experience/activity/DateWidgetActivity/getResources()Landroid/content/res/Resources;
getstatic com/nd/android/u/tasklib/R$color/calendar_font_color I
invokevirtual android/content/res/Resources/getColor(I)I
putstatic com/nd/android/u/tast/experience/activity/DateWidgetActivity/Calendar_DayBgColor I
aload 0
aload 0
getstatic com/nd/android/u/tasklib/R$id/header_btn_left I
invokevirtual com/nd/android/u/tast/experience/activity/DateWidgetActivity/findViewById(I)Landroid/view/View;
checkcast android/widget/Button
putfield com/nd/android/u/tast/experience/activity/DateWidgetActivity/back_img Landroid/widget/Button;
aload 0
aload 0
getstatic com/nd/android/u/tasklib/R$id/anniversary_layout I
invokevirtual com/nd/android/u/tast/experience/activity/DateWidgetActivity/findViewById(I)Landroid/view/View;
checkcast android/widget/LinearLayout
putfield com/nd/android/u/tast/experience/activity/DateWidgetActivity/anniversary_layout Landroid/widget/LinearLayout;
aload 0
aload 0
getstatic com/nd/android/u/tasklib/R$id/anniversary_txv I
invokevirtual com/nd/android/u/tast/experience/activity/DateWidgetActivity/findViewById(I)Landroid/view/View;
checkcast android/widget/TextView
putfield com/nd/android/u/tast/experience/activity/DateWidgetActivity/anniversary_txv Landroid/widget/TextView;
aload 0
aload 0
getstatic com/nd/android/u/tasklib/R$id/jfanniversary_txv I
invokevirtual com/nd/android/u/tast/experience/activity/DateWidgetActivity/findViewById(I)Landroid/view/View;
checkcast android/widget/TextView
putfield com/nd/android/u/tast/experience/activity/DateWidgetActivity/jfanniversary_txv Landroid/widget/TextView;
aload 0
aload 0
getstatic com/nd/android/u/tasklib/R$id/sign_tip I
invokevirtual com/nd/android/u/tast/experience/activity/DateWidgetActivity/findViewById(I)Landroid/view/View;
checkcast android/widget/TextView
putfield com/nd/android/u/tast/experience/activity/DateWidgetActivity/signintips_txv Landroid/widget/TextView;
aload 0
aload 0
getstatic com/nd/android/u/tasklib/R$id/animationIV I
invokevirtual com/nd/android/u/tast/experience/activity/DateWidgetActivity/findViewById(I)Landroid/view/View;
checkcast android/widget/ImageView
putfield com/nd/android/u/tast/experience/activity/DateWidgetActivity/animationIV Landroid/widget/ImageView;
aload 0
aload 0
getfield com/nd/android/u/tast/experience/activity/DateWidgetActivity/animationIV Landroid/widget/ImageView;
invokevirtual android/widget/ImageView/getDrawable()Landroid/graphics/drawable/Drawable;
checkcast android/graphics/drawable/AnimationDrawable
putfield com/nd/android/u/tast/experience/activity/DateWidgetActivity/animationDrawable Landroid/graphics/drawable/AnimationDrawable;
aload 0
aload 0
getstatic com/nd/android/u/tasklib/R$id/signin_animIV I
invokevirtual com/nd/android/u/tast/experience/activity/DateWidgetActivity/findViewById(I)Landroid/view/View;
checkcast android/widget/ImageView
putfield com/nd/android/u/tast/experience/activity/DateWidgetActivity/signin_animIV Landroid/widget/ImageView;
aload 0
aload 0
getfield com/nd/android/u/tast/experience/activity/DateWidgetActivity/signin_animIV Landroid/widget/ImageView;
invokevirtual android/widget/ImageView/getDrawable()Landroid/graphics/drawable/Drawable;
checkcast android/graphics/drawable/AnimationDrawable
putfield com/nd/android/u/tast/experience/activity/DateWidgetActivity/signin_animaDrawable Landroid/graphics/drawable/AnimationDrawable;
aload 0
aload 0
getstatic com/nd/android/u/tasklib/R$id/morepoints_listview I
invokevirtual com/nd/android/u/tast/experience/activity/DateWidgetActivity/findViewById(I)Landroid/view/View;
checkcast android/widget/ListView
putfield com/nd/android/u/tast/experience/activity/DateWidgetActivity/morepoints_listview Landroid/widget/ListView;
aload 0
new com/nd/android/u/tast/experience/adapter/MoreExperienceAdapter
dup
aload 0
aconst_null
aload 0
getfield com/nd/android/u/tast/experience/activity/DateWidgetActivity/morepoints_listview Landroid/widget/ListView;
invokespecial com/nd/android/u/tast/experience/adapter/MoreExperienceAdapter/<init>(Landroid/app/Activity;Landroid/view/View;Landroid/widget/ListView;)V
putfield com/nd/android/u/tast/experience/activity/DateWidgetActivity/mAdapter Lcom/nd/android/u/tast/experience/adapter/MoreExperienceAdapter;
aload 0
getfield com/nd/android/u/tast/experience/activity/DateWidgetActivity/morepoints_listview Landroid/widget/ListView;
aload 0
getfield com/nd/android/u/tast/experience/activity/DateWidgetActivity/mAdapter Lcom/nd/android/u/tast/experience/adapter/MoreExperienceAdapter;
invokevirtual android/widget/ListView/setAdapter(Landroid/widget/ListAdapter;)V
aload 0
aload 0
getfield com/nd/android/u/tast/experience/activity/DateWidgetActivity/context Landroid/content/Context;
invokestatic com/nd/rj/common/util/ComfunHelp/isNetworkAvailable(Landroid/content/Context;)Z
putfield com/nd/android/u/tast/experience/activity/DateWidgetActivity/isHasInternet Z
aload 0
aload 0
getstatic com/nd/android/u/tasklib/R$id/sign_times I
invokevirtual com/nd/android/u/tast/experience/activity/DateWidgetActivity/findViewById(I)Landroid/view/View;
checkcast android/widget/TextView
putfield com/nd/android/u/tast/experience/activity/DateWidgetActivity/mSignTimes Landroid/widget/TextView;
aload 0
aload 0
getstatic com/nd/android/u/tasklib/R$id/sign_tip I
invokevirtual com/nd/android/u/tast/experience/activity/DateWidgetActivity/findViewById(I)Landroid/view/View;
checkcast android/widget/TextView
putfield com/nd/android/u/tast/experience/activity/DateWidgetActivity/mSignTip Landroid/widget/TextView;
aload 0
aload 0
getstatic com/nd/android/u/tasklib/R$id/sign_success I
invokevirtual com/nd/android/u/tast/experience/activity/DateWidgetActivity/findViewById(I)Landroid/view/View;
putfield com/nd/android/u/tast/experience/activity/DateWidgetActivity/mSignSuccess Landroid/view/View;
aload 0
aload 0
getfield com/nd/android/u/tast/experience/activity/DateWidgetActivity/mSignSuccess Landroid/view/View;
getstatic com/nd/android/u/tasklib/R$id/experience I
invokevirtual android/view/View/findViewById(I)Landroid/view/View;
checkcast android/widget/TextView
putfield com/nd/android/u/tast/experience/activity/DateWidgetActivity/mExperience Landroid/widget/TextView;
aload 0
aload 0
getfield com/nd/android/u/tast/experience/activity/DateWidgetActivity/mSignSuccess Landroid/view/View;
getstatic com/nd/android/u/tasklib/R$id/gold I
invokevirtual android/view/View/findViewById(I)Landroid/view/View;
checkcast android/widget/TextView
putfield com/nd/android/u/tast/experience/activity/DateWidgetActivity/mGold Landroid/widget/TextView;
aload 0
aload 0
getfield com/nd/android/u/tast/experience/activity/DateWidgetActivity/mSignSuccess Landroid/view/View;
getstatic com/nd/android/u/tasklib/R$id/flower I
invokevirtual android/view/View/findViewById(I)Landroid/view/View;
checkcast android/widget/TextView
putfield com/nd/android/u/tast/experience/activity/DateWidgetActivity/mFlower Landroid/widget/TextView;
aload 0
aload 0
getstatic com/nd/android/u/tasklib/R$id/sign_left_container I
invokevirtual com/nd/android/u/tast/experience/activity/DateWidgetActivity/findViewById(I)Landroid/view/View;
putfield com/nd/android/u/tast/experience/activity/DateWidgetActivity/mSignLeftContainer Landroid/view/View;
aload 0
aload 0
getstatic com/nd/android/u/tasklib/R$id/birthday_left I
invokevirtual com/nd/android/u/tast/experience/activity/DateWidgetActivity/findViewById(I)Landroid/view/View;
checkcast android/widget/TextView
putfield com/nd/android/u/tast/experience/activity/DateWidgetActivity/mBirthdayLeft Landroid/widget/TextView;
aload 0
aload 0
getstatic com/nd/android/u/tasklib/R$id/more_experience I
invokevirtual com/nd/android/u/tast/experience/activity/DateWidgetActivity/findViewById(I)Landroid/view/View;
checkcast android/widget/TextView
putfield com/nd/android/u/tast/experience/activity/DateWidgetActivity/tvMoreexperience Landroid/widget/TextView;
aload 0
aload 0
getstatic com/nd/android/u/tasklib/R$id/tv_sign_hold_tips I
invokevirtual com/nd/android/u/tast/experience/activity/DateWidgetActivity/findViewById(I)Landroid/view/View;
checkcast android/widget/TextView
putfield com/nd/android/u/tast/experience/activity/DateWidgetActivity/tvSignHoldTips Landroid/widget/TextView;
aload 0
getfield com/nd/android/u/tast/experience/activity/DateWidgetActivity/Top_Date Landroid/widget/TextView;
ifnonnull L0
aload 0
new android/widget/TextView
dup
aload 0
invokespecial android/widget/TextView/<init>(Landroid/content/Context;)V
putfield com/nd/android/u/tast/experience/activity/DateWidgetActivity/Top_Date Landroid/widget/TextView;
L0:
return
.limit locals 2
.limit stack 6
.end method

.method private generateCalendarHeader(Z)Landroid/view/View;
aload 0
iconst_0
invokespecial com/nd/android/u/tast/experience/activity/DateWidgetActivity/createLayout(I)Landroid/widget/LinearLayout;
astore 3
iconst_0
istore 2
L0:
iload 2
bipush 7
if_icmpge L1
new com/nd/android/u/tast/experience/calendar/DateWidgetDayHeader
dup
aload 0
aload 0
getfield com/nd/android/u/tast/experience/activity/DateWidgetActivity/Cell_Width I
aload 0
getfield com/nd/android/u/tast/experience/activity/DateWidgetActivity/Cell_Height I
iload 1
invokespecial com/nd/android/u/tast/experience/calendar/DateWidgetDayHeader/<init>(Landroid/content/Context;IIZ)V
astore 4
aload 4
iload 2
aload 0
getfield com/nd/android/u/tast/experience/activity/DateWidgetActivity/iFirstDayOfWeek I
invokestatic com/nd/android/u/tast/experience/calendar/DayStyle/getWeekDay(II)I
invokevirtual com/nd/android/u/tast/experience/calendar/DateWidgetDayHeader/setData(I)V
aload 3
aload 4
invokevirtual android/widget/LinearLayout/addView(Landroid/view/View;)V
iload 2
iconst_1
iadd
istore 2
goto L0
L1:
aload 3
areturn
.limit locals 5
.limit stack 6
.end method

.method private generateCalendarMain()Landroid/view/View;
aload 0
aload 0
iconst_1
invokespecial com/nd/android/u/tast/experience/activity/DateWidgetActivity/createLayout(I)Landroid/widget/LinearLayout;
putfield com/nd/android/u/tast/experience/activity/DateWidgetActivity/layContent Landroid/widget/LinearLayout;
aload 0
getfield com/nd/android/u/tast/experience/activity/DateWidgetActivity/layContent Landroid/widget/LinearLayout;
aload 0
iconst_0
invokespecial com/nd/android/u/tast/experience/activity/DateWidgetActivity/generateCalendarHeader(Z)Landroid/view/View;
invokevirtual android/widget/LinearLayout/addView(Landroid/view/View;)V
aload 0
getfield com/nd/android/u/tast/experience/activity/DateWidgetActivity/days Ljava/util/ArrayList;
invokevirtual java/util/ArrayList/clear()V
iconst_0
istore 1
L0:
iload 1
bipush 6
if_icmpge L1
aload 0
getfield com/nd/android/u/tast/experience/activity/DateWidgetActivity/layContent Landroid/widget/LinearLayout;
aload 0
invokespecial com/nd/android/u/tast/experience/activity/DateWidgetActivity/generateCalendarRow()Landroid/view/View;
invokevirtual android/widget/LinearLayout/addView(Landroid/view/View;)V
iload 1
iconst_1
iadd
istore 1
goto L0
L1:
aload 0
getfield com/nd/android/u/tast/experience/activity/DateWidgetActivity/layContent Landroid/widget/LinearLayout;
bipush 17
invokevirtual android/widget/LinearLayout/setGravity(I)V
aload 0
getfield com/nd/android/u/tast/experience/activity/DateWidgetActivity/layContent Landroid/widget/LinearLayout;
areturn
.limit locals 2
.limit stack 3
.end method

.method private generateCalendarRow()Landroid/view/View;
aload 0
iconst_0
invokespecial com/nd/android/u/tast/experience/activity/DateWidgetActivity/createLayout(I)Landroid/widget/LinearLayout;
astore 2
iconst_0
istore 1
L0:
iload 1
bipush 7
if_icmpge L1
new com/nd/android/u/tast/experience/calendar/DateWidgetDayCell
dup
aload 0
aload 0
getfield com/nd/android/u/tast/experience/activity/DateWidgetActivity/Cell_Width I
aload 0
getfield com/nd/android/u/tast/experience/activity/DateWidgetActivity/Cell_Height I
invokespecial com/nd/android/u/tast/experience/calendar/DateWidgetDayCell/<init>(Landroid/content/Context;II)V
astore 3
aload 0
getfield com/nd/android/u/tast/experience/activity/DateWidgetActivity/days Ljava/util/ArrayList;
aload 3
invokevirtual java/util/ArrayList/add(Ljava/lang/Object;)Z
pop
aload 2
aload 3
invokevirtual android/widget/LinearLayout/addView(Landroid/view/View;)V
iload 1
iconst_1
iadd
istore 1
goto L0
L1:
aload 2
areturn
.limit locals 4
.limit stack 5
.end method

.method private getCalendarStartDate()Ljava/util/Calendar;
.catch java/text/ParseException from L0 to L1 using L2
aload 0
getfield com/nd/android/u/tast/experience/activity/DateWidgetActivity/signDay Ljava/lang/String;
ifnull L3
L0:
new java/text/SimpleDateFormat
dup
ldc "yyyy-MM-dd"
invokespecial java/text/SimpleDateFormat/<init>(Ljava/lang/String;)V
aload 0
getfield com/nd/android/u/tast/experience/activity/DateWidgetActivity/signDay Ljava/lang/String;
invokevirtual java/text/SimpleDateFormat/parse(Ljava/lang/String;)Ljava/util/Date;
astore 1
aload 0
getfield com/nd/android/u/tast/experience/activity/DateWidgetActivity/calToday Ljava/util/Calendar;
aload 1
invokevirtual java/util/Date/getTime()J
invokevirtual java/util/Calendar/setTimeInMillis(J)V
aload 0
getfield com/nd/android/u/tast/experience/activity/DateWidgetActivity/calStartDate Ljava/util/Calendar;
aload 1
invokevirtual java/util/Date/getTime()J
invokevirtual java/util/Calendar/setTimeInMillis(J)V
L1:
aload 0
getfield com/nd/android/u/tast/experience/activity/DateWidgetActivity/calToday Ljava/util/Calendar;
aload 0
getfield com/nd/android/u/tast/experience/activity/DateWidgetActivity/iFirstDayOfWeek I
invokevirtual java/util/Calendar/setFirstDayOfWeek(I)V
aload 0
getfield com/nd/android/u/tast/experience/activity/DateWidgetActivity/calStartDate Ljava/util/Calendar;
aload 0
getfield com/nd/android/u/tast/experience/activity/DateWidgetActivity/iFirstDayOfWeek I
invokevirtual java/util/Calendar/setFirstDayOfWeek(I)V
aload 0
invokespecial com/nd/android/u/tast/experience/activity/DateWidgetActivity/UpdateStartDateForMonth()V
aload 0
getfield com/nd/android/u/tast/experience/activity/DateWidgetActivity/calStartDate Ljava/util/Calendar;
areturn
L2:
astore 1
aload 1
invokevirtual java/text/ParseException/printStackTrace()V
aload 0
getfield com/nd/android/u/tast/experience/activity/DateWidgetActivity/calToday Ljava/util/Calendar;
invokestatic java/lang/System/currentTimeMillis()J
invokevirtual java/util/Calendar/setTimeInMillis(J)V
aload 0
getfield com/nd/android/u/tast/experience/activity/DateWidgetActivity/calStartDate Ljava/util/Calendar;
invokestatic java/lang/System/currentTimeMillis()J
invokevirtual java/util/Calendar/setTimeInMillis(J)V
goto L1
L3:
aload 0
getfield com/nd/android/u/tast/experience/activity/DateWidgetActivity/calToday Ljava/util/Calendar;
invokestatic java/lang/System/currentTimeMillis()J
invokevirtual java/util/Calendar/setTimeInMillis(J)V
aload 0
getfield com/nd/android/u/tast/experience/activity/DateWidgetActivity/calStartDate Ljava/util/Calendar;
invokestatic java/lang/System/currentTimeMillis()J
invokevirtual java/util/Calendar/setTimeInMillis(J)V
goto L1
.limit locals 2
.limit stack 3
.end method

.method public static getCalendar_DayBgColor()I
getstatic com/nd/android/u/tast/experience/activity/DateWidgetActivity/Calendar_DayBgColor I
ireturn
.limit locals 0
.limit stack 1
.end method

.method public static getDefaultSignArray()[C
bipush 31
newarray char
astore 1
iconst_0
istore 0
L0:
iload 0
bipush 31
if_icmpge L1
aload 1
iload 0
bipush 48
castore
iload 0
iconst_1
iadd
istore 0
goto L0
L1:
aload 1
areturn
.limit locals 2
.limit stack 3
.end method

.method private static getSignDayIndex(Ljava/lang/String;)I
aload 0
invokestatic android/text/TextUtils/isEmpty(Ljava/lang/CharSequence;)Z
ifeq L0
invokestatic com/product/android/utils/TimeUtils/getNowTime()Ljava/util/Date;
invokevirtual java/util/Date/getDate()I
ireturn
L0:
aload 0
ldc "-"
invokestatic android/text/TextUtils/split(Ljava/lang/String;Ljava/lang/String;)[Ljava/lang/String;
astore 0
aload 0
arraylength
iconst_3
if_icmpeq L1
iconst_m1
ireturn
L1:
aload 0
iconst_2
aaload
invokestatic java/lang/Integer/valueOf(Ljava/lang/String;)Ljava/lang/Integer;
invokevirtual java/lang/Integer/intValue()I
iconst_1
isub
ireturn
.limit locals 1
.limit stack 2
.end method

.method public static getSignStr(IILjava/lang/String;Ljava/lang/StringBuffer;)Ljava/lang/String;
.catch com/common/android/utils/http/HttpAuthException from L0 to L1 using L2
.catch com/common/android/utils/http/ResponseException from L0 to L1 using L3
.catch com/common/android/utils/http/HttpServerException from L0 to L1 using L4
.catch com/common/android/utils/http/HttpException from L0 to L1 using L5
new com/nd/android/u/tast/com/AjaxCom
dup
invokespecial com/nd/android/u/tast/com/AjaxCom/<init>()V
astore 5
L0:
aload 5
iload 0
iload 1
invokevirtual com/nd/android/u/tast/com/AjaxCom/getSignlist(II)Lorg/json/JSONObject;
astore 5
L1:
aload 5
ldc "code"
invokevirtual org/json/JSONObject/optInt(Ljava/lang/String;)I
sipush 200
if_icmpeq L6
aload 3
getstatic com/product/android/business/ApplicationVariable/INSTANCE Lcom/product/android/business/ApplicationVariable;
getfield com/product/android/business/ApplicationVariable/applicationContext Landroid/content/Context;
invokevirtual android/content/Context/getResources()Landroid/content/res/Resources;
getstatic com/nd/android/u/tasklib/R$string/sign_fail I
invokevirtual android/content/res/Resources/getString(I)Ljava/lang/String;
invokevirtual java/lang/StringBuffer/append(Ljava/lang/String;)Ljava/lang/StringBuffer;
pop
aload 2
areturn
L2:
astore 5
aload 5
invokevirtual com/common/android/utils/http/HttpAuthException/printStackTrace()V
aload 3
getstatic com/product/android/business/ApplicationVariable/INSTANCE Lcom/product/android/business/ApplicationVariable;
getfield com/product/android/business/ApplicationVariable/applicationContext Landroid/content/Context;
invokevirtual android/content/Context/getResources()Landroid/content/res/Resources;
getstatic com/nd/android/u/tasklib/R$string/sign_get_his_fail I
invokevirtual android/content/res/Resources/getString(I)Ljava/lang/String;
invokevirtual java/lang/StringBuffer/append(Ljava/lang/String;)Ljava/lang/StringBuffer;
pop
aload 2
areturn
L3:
astore 5
aload 5
invokevirtual com/common/android/utils/http/ResponseException/printStackTrace()V
aload 3
getstatic com/product/android/business/ApplicationVariable/INSTANCE Lcom/product/android/business/ApplicationVariable;
getfield com/product/android/business/ApplicationVariable/applicationContext Landroid/content/Context;
invokevirtual android/content/Context/getResources()Landroid/content/res/Resources;
getstatic com/nd/android/u/tasklib/R$string/sign_get_his_fail I
invokevirtual android/content/res/Resources/getString(I)Ljava/lang/String;
invokevirtual java/lang/StringBuffer/append(Ljava/lang/String;)Ljava/lang/StringBuffer;
pop
aload 2
areturn
L4:
astore 5
aload 5
invokevirtual com/common/android/utils/http/HttpServerException/printStackTrace()V
aload 3
getstatic com/product/android/business/ApplicationVariable/INSTANCE Lcom/product/android/business/ApplicationVariable;
getfield com/product/android/business/ApplicationVariable/applicationContext Landroid/content/Context;
invokevirtual android/content/Context/getResources()Landroid/content/res/Resources;
getstatic com/nd/android/u/tasklib/R$string/sign_get_his_fail I
invokevirtual android/content/res/Resources/getString(I)Ljava/lang/String;
invokevirtual java/lang/StringBuffer/append(Ljava/lang/String;)Ljava/lang/StringBuffer;
pop
aload 2
areturn
L5:
astore 5
aload 5
invokevirtual com/common/android/utils/http/HttpException/printStackTrace()V
aload 3
getstatic com/product/android/business/ApplicationVariable/INSTANCE Lcom/product/android/business/ApplicationVariable;
getfield com/product/android/business/ApplicationVariable/applicationContext Landroid/content/Context;
invokevirtual android/content/Context/getResources()Landroid/content/res/Resources;
getstatic com/nd/android/u/tasklib/R$string/sign_get_his_fail I
invokevirtual android/content/res/Resources/getString(I)Ljava/lang/String;
invokevirtual java/lang/StringBuffer/append(Ljava/lang/String;)Ljava/lang/StringBuffer;
pop
aload 2
areturn
L6:
invokestatic com/nd/android/u/tast/experience/activity/DateWidgetActivity/getDefaultSignArray()[C
astore 2
aload 5
ldc "signdata"
invokevirtual org/json/JSONObject/optJSONArray(Ljava/lang/String;)Lorg/json/JSONArray;
astore 3
aload 3
ifnull L7
aload 3
invokevirtual org/json/JSONArray/length()I
ifle L7
aload 3
invokevirtual org/json/JSONArray/length()I
istore 1
iconst_0
istore 0
L8:
iload 0
iload 1
if_icmpge L7
aload 3
iload 0
invokevirtual org/json/JSONArray/optJSONObject(I)Lorg/json/JSONObject;
ldc "signday"
invokevirtual org/json/JSONObject/optString(Ljava/lang/String;)Ljava/lang/String;
invokestatic com/nd/android/u/tast/experience/activity/DateWidgetActivity/getSignDayIndex(Ljava/lang/String;)I
istore 4
iload 4
iconst_m1
if_icmpne L9
L10:
iload 0
iconst_1
iadd
istore 0
goto L8
L9:
aload 2
iload 4
bipush 49
castore
goto L10
L7:
new java/lang/String
dup
aload 2
invokespecial java/lang/String/<init>([C)V
areturn
.limit locals 6
.limit stack 3
.end method

.method private getTopDataView()Landroid/view/View;
aload 0
invokevirtual com/nd/android/u/tast/experience/activity/DateWidgetActivity/getLayoutInflater()Landroid/view/LayoutInflater;
getstatic com/nd/android/u/tasklib/R$layout/calendar_topdateview I
aconst_null
invokevirtual android/view/LayoutInflater/inflate(ILandroid/view/ViewGroup;)Landroid/view/View;
astore 1
aload 1
getstatic com/nd/android/u/tasklib/R$id/pre_month_layout I
invokevirtual android/view/View/findViewById(I)Landroid/view/View;
checkcast android/widget/RelativeLayout
astore 2
aload 1
getstatic com/nd/android/u/tasklib/R$id/next_month_layout I
invokevirtual android/view/View/findViewById(I)Landroid/view/View;
checkcast android/widget/RelativeLayout
astore 3
aload 0
aload 1
getstatic com/nd/android/u/tasklib/R$id/pop_date_tv I
invokevirtual android/view/View/findViewById(I)Landroid/view/View;
checkcast android/widget/TextView
putfield com/nd/android/u/tast/experience/activity/DateWidgetActivity/Top_Date Landroid/widget/TextView;
aload 0
getfield com/nd/android/u/tast/experience/activity/DateWidgetActivity/Top_Date Landroid/widget/TextView;
aload 0
invokevirtual com/nd/android/u/tast/experience/activity/DateWidgetActivity/getResources()Landroid/content/res/Resources;
getstatic com/nd/android/u/tasklib/R$color/calendar_yearsAndmonths_color I
invokevirtual android/content/res/Resources/getColor(I)I
invokevirtual android/widget/TextView/setTextColor(I)V
aload 2
aload 0
getfield com/nd/android/u/tast/experience/activity/DateWidgetActivity/Pre_MonthOnClickListener Landroid/view/View$OnClickListener;
invokevirtual android/widget/RelativeLayout/setOnClickListener(Landroid/view/View$OnClickListener;)V
aload 3
aload 0
getfield com/nd/android/u/tast/experience/activity/DateWidgetActivity/Next_MonthOnClickListener Landroid/view/View$OnClickListener;
invokevirtual android/widget/RelativeLayout/setOnClickListener(Landroid/view/View$OnClickListener;)V
aload 1
areturn
.limit locals 4
.limit stack 3
.end method

.method public static getYearOrMonth(Ljava/util/Date;I)I
aload 0
invokestatic com/nd/android/u/tast/buss/TaskPubFunction/DateFormat(Ljava/util/Date;)Ljava/lang/String;
ldc "-"
invokevirtual java/lang/String/split(Ljava/lang/String;)[Ljava/lang/String;
astore 0
iconst_m1
istore 2
iload 1
ifne L0
aload 0
iconst_0
aaload
invokestatic java/lang/Integer/parseInt(Ljava/lang/String;)I
istore 2
L0:
iload 1
iconst_1
if_icmpne L1
aload 0
iconst_1
aaload
invokestatic java/lang/Integer/parseInt(Ljava/lang/String;)I
istore 2
L1:
iload 2
ireturn
.limit locals 3
.limit stack 2
.end method

.method private initControls()V
aload 0
getfield com/nd/android/u/tast/experience/activity/DateWidgetActivity/back_img Landroid/widget/Button;
aload 0
getfield com/nd/android/u/tast/experience/activity/DateWidgetActivity/return_OnClickListener Landroid/view/View$OnClickListener;
invokevirtual android/widget/Button/setOnClickListener(Landroid/view/View$OnClickListener;)V
aload 0
new java/util/Date
dup
invokespecial java/util/Date/<init>()V
putfield com/nd/android/u/tast/experience/activity/DateWidgetActivity/today Ljava/util/Date;
aload 0
aload 0
aload 0
getfield com/nd/android/u/tast/experience/activity/DateWidgetActivity/today Ljava/util/Date;
invokevirtual com/nd/android/u/tast/experience/activity/DateWidgetActivity/DateFormatMD(Ljava/util/Date;)Ljava/lang/String;
putfield com/nd/android/u/tast/experience/activity/DateWidgetActivity/StrToday Ljava/lang/String;
aload 0
aload 0
invokevirtual com/nd/android/u/tast/experience/activity/DateWidgetActivity/getResources()Landroid/content/res/Resources;
getstatic com/nd/android/u/tasklib/R$array/signin_tips_list I
invokevirtual android/content/res/Resources/getStringArray(I)[Ljava/lang/String;
putfield com/nd/android/u/tast/experience/activity/DateWidgetActivity/signin_tips_list [Ljava/lang/String;
aload 0
aload 0
invokevirtual com/nd/android/u/tast/experience/activity/DateWidgetActivity/getResources()Landroid/content/res/Resources;
getstatic com/nd/android/u/tasklib/R$array/signed_tips_list I
invokevirtual android/content/res/Resources/getStringArray(I)[Ljava/lang/String;
putfield com/nd/android/u/tast/experience/activity/DateWidgetActivity/signed_tips_list [Ljava/lang/String;
aload 0
aload 0
invokevirtual com/nd/android/u/tast/experience/activity/DateWidgetActivity/getResources()Landroid/content/res/Resources;
getstatic com/nd/android/u/tasklib/R$array/special_day_list I
invokevirtual android/content/res/Resources/getStringArray(I)[Ljava/lang/String;
putfield com/nd/android/u/tast/experience/activity/DateWidgetActivity/special_day_list [Ljava/lang/String;
aload 0
getfield com/nd/android/u/tast/experience/activity/DateWidgetActivity/SignInList Ljava/lang/String;
invokestatic android/text/TextUtils/isEmpty(Ljava/lang/CharSequence;)Z
ifeq L0
aload 0
new java/lang/String
dup
invokestatic com/nd/android/u/tast/experience/activity/DateWidgetActivity/getDefaultSignArray()[C
invokespecial java/lang/String/<init>([C)V
putfield com/nd/android/u/tast/experience/activity/DateWidgetActivity/SignInList Ljava/lang/String;
L0:
aload 0
invokespecial com/nd/android/u/tast/experience/activity/DateWidgetActivity/updateTopViewUI()V
return
.limit locals 1
.limit stack 4
.end method

.method public static initMoreExperience(Landroid/app/Activity;Landroid/widget/ListView;Lcom/nd/android/u/tast/experience/adapter/MoreExperienceAdapter;Lcom/nd/android/u/tast/experience/view/FullAttendanceListener;Landroid/os/Handler;)V
new java/lang/Thread
dup
new com/nd/android/u/tast/experience/activity/DateWidgetActivity$10
dup
aload 4
aload 0
aload 3
aload 2
aload 1
invokespecial com/nd/android/u/tast/experience/activity/DateWidgetActivity$10/<init>(Landroid/os/Handler;Landroid/app/Activity;Lcom/nd/android/u/tast/experience/view/FullAttendanceListener;Lcom/nd/android/u/tast/experience/adapter/MoreExperienceAdapter;Landroid/widget/ListView;)V
invokespecial java/lang/Thread/<init>(Ljava/lang/Runnable;)V
invokevirtual java/lang/Thread/start()V
return
.limit locals 5
.limit stack 9
.end method

.method public static setCalendar_DayBgColor(I)V
iload 0
putstatic com/nd/android/u/tast/experience/activity/DateWidgetActivity/Calendar_DayBgColor I
return
.limit locals 1
.limit stack 1
.end method

.method public static setListViewHeightBasedOnChildren(Landroid/widget/ListView;)V
aload 0
ifnonnull L0
L1:
return
L0:
aload 0
invokevirtual android/widget/ListView/getAdapter()Landroid/widget/ListAdapter;
astore 3
aload 3
ifnull L1
iconst_0
istore 2
iconst_0
istore 1
L2:
iload 1
aload 3
invokeinterface android/widget/ListAdapter/getCount()I 0
if_icmpge L3
aload 3
iload 1
aconst_null
aload 0
invokeinterface android/widget/ListAdapter/getView(ILandroid/view/View;Landroid/view/ViewGroup;)Landroid/view/View; 3
astore 4
aload 4
new android/widget/LinearLayout$LayoutParams
dup
iconst_m1
iconst_m1
invokespecial android/widget/LinearLayout$LayoutParams/<init>(II)V
invokevirtual android/view/View/setLayoutParams(Landroid/view/ViewGroup$LayoutParams;)V
aload 4
iconst_0
iconst_0
invokevirtual android/view/View/measure(II)V
iload 2
aload 4
invokevirtual android/view/View/getMeasuredHeight()I
iadd
istore 2
iload 1
iconst_1
iadd
istore 1
goto L2
L3:
aload 0
invokevirtual android/widget/ListView/getLayoutParams()Landroid/view/ViewGroup$LayoutParams;
astore 4
aload 4
aload 0
invokevirtual android/widget/ListView/getDividerHeight()I
aload 3
invokeinterface android/widget/ListAdapter/getCount()I 0
iconst_1
isub
imul
iload 2
iadd
putfield android/view/ViewGroup$LayoutParams/height I
aload 0
aload 4
invokevirtual android/widget/ListView/setLayoutParams(Landroid/view/ViewGroup$LayoutParams;)V
return
.limit locals 5
.limit stack 5
.end method

.method private setOringeColor(Ljava/lang/String;II)Landroid/text/SpannableStringBuilder;
new android/text/SpannableStringBuilder
dup
aload 1
invokespecial android/text/SpannableStringBuilder/<init>(Ljava/lang/CharSequence;)V
astore 1
aload 1
new android/text/style/ForegroundColorSpan
dup
aload 0
invokevirtual com/nd/android/u/tast/experience/activity/DateWidgetActivity/getResources()Landroid/content/res/Resources;
getstatic com/nd/android/u/tasklib/R$color/sign_color3 I
invokevirtual android/content/res/Resources/getColor(I)I
invokespecial android/text/style/ForegroundColorSpan/<init>(I)V
bipush 6
iload 2
bipush 6
iadd
iconst_0
invokevirtual android/text/SpannableStringBuilder/setSpan(Ljava/lang/Object;III)V
aload 1
new android/text/style/ForegroundColorSpan
dup
aload 0
invokevirtual com/nd/android/u/tast/experience/activity/DateWidgetActivity/getResources()Landroid/content/res/Resources;
getstatic com/nd/android/u/tasklib/R$color/sign_color3 I
invokevirtual android/content/res/Resources/getColor(I)I
invokespecial android/text/style/ForegroundColorSpan/<init>(I)V
iload 2
bipush 6
iadd
bipush 7
iadd
iload 2
bipush 6
iadd
bipush 7
iadd
iload 3
iadd
iconst_0
invokevirtual android/text/SpannableStringBuilder/setSpan(Ljava/lang/Object;III)V
aload 1
areturn
.limit locals 4
.limit stack 5
.end method

.method private startAnimation()V
aload 0
getfield com/nd/android/u/tast/experience/activity/DateWidgetActivity/animationIV Landroid/widget/ImageView;
iconst_0
invokevirtual android/widget/ImageView/setVisibility(I)V
aload 0
getfield com/nd/android/u/tast/experience/activity/DateWidgetActivity/animationDrawable Landroid/graphics/drawable/AnimationDrawable;
invokevirtual android/graphics/drawable/AnimationDrawable/stop()V
aload 0
getfield com/nd/android/u/tast/experience/activity/DateWidgetActivity/animationDrawable Landroid/graphics/drawable/AnimationDrawable;
invokevirtual android/graphics/drawable/AnimationDrawable/start()V
iconst_0
istore 2
iconst_0
istore 1
L0:
iload 1
aload 0
getfield com/nd/android/u/tast/experience/activity/DateWidgetActivity/animationDrawable Landroid/graphics/drawable/AnimationDrawable;
invokevirtual android/graphics/drawable/AnimationDrawable/getNumberOfFrames()I
if_icmpge L1
iload 2
aload 0
getfield com/nd/android/u/tast/experience/activity/DateWidgetActivity/animationDrawable Landroid/graphics/drawable/AnimationDrawable;
iload 1
invokevirtual android/graphics/drawable/AnimationDrawable/getDuration(I)I
iadd
istore 2
iload 1
iconst_1
iadd
istore 1
goto L0
L1:
new android/os/Handler
dup
invokespecial android/os/Handler/<init>()V
new com/nd/android/u/tast/experience/activity/DateWidgetActivity$9
dup
aload 0
invokespecial com/nd/android/u/tast/experience/activity/DateWidgetActivity$9/<init>(Lcom/nd/android/u/tast/experience/activity/DateWidgetActivity;)V
aload 0
getfield com/nd/android/u/tast/experience/activity/DateWidgetActivity/duration I
i2l
invokevirtual android/os/Handler/postDelayed(Ljava/lang/Runnable;J)Z
pop
return
.limit locals 3
.limit stack 4
.end method

.method private updateCalendar(II)V
new java/lang/Thread
dup
new com/nd/android/u/tast/experience/activity/DateWidgetActivity$4
dup
aload 0
iload 1
iload 2
invokespecial com/nd/android/u/tast/experience/activity/DateWidgetActivity$4/<init>(Lcom/nd/android/u/tast/experience/activity/DateWidgetActivity;II)V
invokespecial java/lang/Thread/<init>(Ljava/lang/Runnable;)V
invokevirtual java/lang/Thread/start()V
return
.limit locals 3
.limit stack 7
.end method

.method private updateCalendar(Ljava/lang/String;)V
.catch java/lang/NumberFormatException from L0 to L1 using L2
.catch java/text/ParseException from L3 to L4 using L5
.catch java/lang/NumberFormatException from L6 to L7 using L2
.catch java/lang/NumberFormatException from L8 to L9 using L2
aload 1
invokevirtual java/lang/String/toCharArray()[C
astore 10
iconst_0
istore 2
aload 10
arraylength
istore 5
iconst_0
istore 3
L10:
iload 3
iload 5
if_icmpge L11
iload 2
istore 4
aload 10
iload 3
caload
bipush 49
if_icmpne L12
iload 2
iconst_1
iadd
istore 4
L12:
iload 3
iconst_1
iadd
istore 3
iload 4
istore 2
goto L10
L11:
aload 0
getfield com/nd/android/u/tast/experience/activity/DateWidgetActivity/mSignTimes Landroid/widget/TextView;
iload 2
invokestatic java/lang/String/valueOf(I)Ljava/lang/String;
invokevirtual android/widget/TextView/setText(Ljava/lang/CharSequence;)V
invokestatic java/util/Calendar/getInstance()Ljava/util/Calendar;
astore 10
aload 10
iconst_5
invokevirtual java/util/Calendar/getActualMaximum(I)I
istore 3
L0:
aload 0
getfield com/nd/android/u/tast/experience/activity/DateWidgetActivity/signDay Ljava/lang/String;
invokestatic com/common/android/utils/StringUtils/isEmpty(Ljava/lang/String;)Z
ifne L8
aload 0
getfield com/nd/android/u/tast/experience/activity/DateWidgetActivity/signDay Ljava/lang/String;
ldc "-"
invokevirtual java/lang/String/split(Ljava/lang/String;)[Ljava/lang/String;
astore 11
aload 11
arraylength
iconst_2
if_icmpge L6
aload 0
iload 3
aload 10
iconst_5
invokevirtual java/util/Calendar/get(I)I
isub
putfield com/nd/android/u/tast/experience/activity/DateWidgetActivity/leftDays I
L1:
iload 3
iload 2
isub
ifne L13
aload 0
iconst_4
putfield com/nd/android/u/tast/experience/activity/DateWidgetActivity/mFullSignStatus I
aload 0
iconst_0
putfield com/nd/android/u/tast/experience/activity/DateWidgetActivity/mRewardExp I
L13:
aload 1
invokestatic android/text/TextUtils/isEmpty(Ljava/lang/CharSequence;)Z
ifne L14
aload 0
aload 0
getfield com/nd/android/u/tast/experience/activity/DateWidgetActivity/mFullSignStatus I
aload 0
getfield com/nd/android/u/tast/experience/activity/DateWidgetActivity/mRewardExp I
invokevirtual com/nd/android/u/tast/experience/activity/DateWidgetActivity/OnNotification(II)V
L14:
aload 0
getfield com/nd/android/u/tast/experience/activity/DateWidgetActivity/calCalendar Ljava/util/Calendar;
aload 0
getfield com/nd/android/u/tast/experience/activity/DateWidgetActivity/calStartDate Ljava/util/Calendar;
invokevirtual java/util/Calendar/getTimeInMillis()J
invokevirtual java/util/Calendar/setTimeInMillis(J)V
iconst_0
istore 2
L15:
iload 2
aload 0
getfield com/nd/android/u/tast/experience/activity/DateWidgetActivity/days Ljava/util/ArrayList;
invokevirtual java/util/ArrayList/size()I
if_icmpge L16
aload 0
getfield com/nd/android/u/tast/experience/activity/DateWidgetActivity/calCalendar Ljava/util/Calendar;
iconst_1
invokevirtual java/util/Calendar/get(I)I
istore 3
aload 0
getfield com/nd/android/u/tast/experience/activity/DateWidgetActivity/calCalendar Ljava/util/Calendar;
iconst_2
invokevirtual java/util/Calendar/get(I)I
istore 4
aload 0
getfield com/nd/android/u/tast/experience/activity/DateWidgetActivity/calCalendar Ljava/util/Calendar;
iconst_5
invokevirtual java/util/Calendar/get(I)I
istore 5
aload 0
getfield com/nd/android/u/tast/experience/activity/DateWidgetActivity/calCalendar Ljava/util/Calendar;
bipush 7
invokevirtual java/util/Calendar/get(I)I
istore 6
aload 0
getfield com/nd/android/u/tast/experience/activity/DateWidgetActivity/days Ljava/util/ArrayList;
iload 2
invokevirtual java/util/ArrayList/get(I)Ljava/lang/Object;
checkcast com/nd/android/u/tast/experience/calendar/DateWidgetDayCell
astore 10
iconst_0
istore 7
iload 7
istore 8
aload 0
getfield com/nd/android/u/tast/experience/activity/DateWidgetActivity/calToday Ljava/util/Calendar;
iconst_1
invokevirtual java/util/Calendar/get(I)I
iload 3
if_icmpne L17
iload 7
istore 8
aload 0
getfield com/nd/android/u/tast/experience/activity/DateWidgetActivity/calToday Ljava/util/Calendar;
iconst_2
invokevirtual java/util/Calendar/get(I)I
iload 4
if_icmpne L17
iload 7
istore 8
aload 0
getfield com/nd/android/u/tast/experience/activity/DateWidgetActivity/calToday Ljava/util/Calendar;
iconst_5
invokevirtual java/util/Calendar/get(I)I
iload 5
if_icmpne L17
iconst_1
istore 8
L17:
iconst_0
istore 7
iload 6
bipush 7
if_icmpeq L18
iload 6
iconst_1
if_icmpne L19
L18:
iconst_1
istore 7
L19:
iload 7
istore 9
iload 4
ifne L3
iload 7
istore 9
iload 5
iconst_1
if_icmpne L3
iconst_1
istore 9
L3:
aload 10
iload 3
iload 4
iload 5
iload 8
invokestatic java/lang/Boolean/valueOf(Z)Ljava/lang/Boolean;
iload 9
invokestatic java/lang/Boolean/valueOf(Z)Ljava/lang/Boolean;
aload 0
getfield com/nd/android/u/tast/experience/activity/DateWidgetActivity/iMonthViewCurrentMonth I
iconst_0
aload 1
aload 0
getfield com/nd/android/u/tast/experience/activity/DateWidgetActivity/fotmat Ljava/text/SimpleDateFormat;
aload 0
getfield com/nd/android/u/tast/experience/activity/DateWidgetActivity/Top_Date Landroid/widget/TextView;
invokevirtual android/widget/TextView/getText()Ljava/lang/CharSequence;
invokeinterface java/lang/CharSequence/toString()Ljava/lang/String; 0
invokevirtual java/text/SimpleDateFormat/parse(Ljava/lang/String;)Ljava/util/Date;
iconst_1
invokestatic com/nd/android/u/tast/experience/activity/DateWidgetActivity/getYearOrMonth(Ljava/util/Date;I)I
invokestatic java/lang/Integer/valueOf(I)Ljava/lang/Integer;
invokevirtual java/lang/Integer/intValue()I
aload 0
getfield com/nd/android/u/tast/experience/activity/DateWidgetActivity/JoinMonth I
aload 0
getfield com/nd/android/u/tast/experience/activity/DateWidgetActivity/JoinDay I
aload 0
getfield com/nd/android/u/tast/experience/activity/DateWidgetActivity/BirthMonth I
aload 0
getfield com/nd/android/u/tast/experience/activity/DateWidgetActivity/BirthDay I
aload 0
getfield com/nd/android/u/tast/experience/activity/DateWidgetActivity/IsAnniversary Z
aload 0
getfield com/nd/android/u/tast/experience/activity/DateWidgetActivity/special_day_list [Ljava/lang/String;
invokevirtual com/nd/android/u/tast/experience/calendar/DateWidgetDayCell/setData(IIILjava/lang/Boolean;Ljava/lang/Boolean;IZLjava/lang/String;IIIIIZ[Ljava/lang/String;)V
aload 10
invokevirtual com/nd/android/u/tast/experience/calendar/DateWidgetDayCell/invalidate()V
L4:
aload 0
getfield com/nd/android/u/tast/experience/activity/DateWidgetActivity/calCalendar Ljava/util/Calendar;
iconst_5
iconst_1
invokevirtual java/util/Calendar/add(II)V
iload 2
iconst_1
iadd
istore 2
goto L15
L6:
aload 0
iload 3
aload 11
iconst_2
aaload
invokestatic java/lang/Integer/parseInt(Ljava/lang/String;)I
isub
putfield com/nd/android/u/tast/experience/activity/DateWidgetActivity/leftDays I
L7:
goto L1
L2:
astore 11
aload 11
invokevirtual java/lang/NumberFormatException/printStackTrace()V
aload 0
iload 3
aload 10
iconst_5
invokevirtual java/util/Calendar/get(I)I
isub
putfield com/nd/android/u/tast/experience/activity/DateWidgetActivity/leftDays I
goto L1
L8:
aload 0
iload 3
aload 10
iconst_5
invokevirtual java/util/Calendar/get(I)I
isub
putfield com/nd/android/u/tast/experience/activity/DateWidgetActivity/leftDays I
L9:
goto L1
L5:
astore 10
aload 10
invokevirtual java/text/ParseException/printStackTrace()V
goto L4
L16:
aload 0
getfield com/nd/android/u/tast/experience/activity/DateWidgetActivity/layContent Landroid/widget/LinearLayout;
invokevirtual android/widget/LinearLayout/invalidate()V
return
.limit locals 12
.limit stack 16
.end method

.method private updateCalendar(Ljava/lang/String;Z)V
.catch java/text/ParseException from L0 to L1 using L2
L0:
aload 0
getfield com/nd/android/u/tast/experience/activity/DateWidgetActivity/fotmat Ljava/text/SimpleDateFormat;
aload 1
invokevirtual java/text/SimpleDateFormat/parse(Ljava/lang/String;)Ljava/util/Date;
astore 1
L1:
iload 2
ifeq L3
iconst_m1
istore 3
L4:
aload 0
aload 1
iconst_2
iload 3
invokespecial com/nd/android/u/tast/experience/activity/DateWidgetActivity/Add(Ljava/util/Date;II)Ljava/util/Date;
astore 1
aload 0
aload 1
iconst_0
invokestatic com/nd/android/u/tast/experience/activity/DateWidgetActivity/getYearOrMonth(Ljava/util/Date;I)I
aload 1
iconst_1
invokestatic com/nd/android/u/tast/experience/activity/DateWidgetActivity/getYearOrMonth(Ljava/util/Date;I)I
invokespecial com/nd/android/u/tast/experience/activity/DateWidgetActivity/updateCalendar(II)V
return
L2:
astore 1
return
L3:
iconst_1
istore 3
goto L4
.limit locals 4
.limit stack 4
.end method

.method private updateTopViewUI()V
ldc ""
astore 2
ldc ""
astore 3
ldc ""
aload 0
getfield com/nd/android/u/tast/experience/activity/DateWidgetActivity/StrBirthDay Ljava/lang/String;
invokevirtual java/lang/String/equals(Ljava/lang/Object;)Z
ifne L0
ldc ""
aload 0
getfield com/nd/android/u/tast/experience/activity/DateWidgetActivity/StrJoinDay Ljava/lang/String;
invokevirtual java/lang/String/equals(Ljava/lang/Object;)Z
ifeq L1
L0:
aload 0
getfield com/nd/android/u/tast/experience/activity/DateWidgetActivity/signed_tips_list [Ljava/lang/String;
iconst_0
aaload
astore 2
aload 0
getfield com/nd/android/u/tast/experience/activity/DateWidgetActivity/signin_tips_list [Ljava/lang/String;
iconst_0
aaload
astore 3
L1:
aload 2
astore 4
aload 3
astore 5
aload 0
getfield com/nd/android/u/tast/experience/activity/DateWidgetActivity/special_day_list [Ljava/lang/String;
arraylength
ifle L2
iconst_0
istore 1
L3:
aload 2
astore 4
aload 3
astore 5
iload 1
aload 0
getfield com/nd/android/u/tast/experience/activity/DateWidgetActivity/special_day_list [Ljava/lang/String;
arraylength
if_icmpge L2
aload 0
getfield com/nd/android/u/tast/experience/activity/DateWidgetActivity/StrToday Ljava/lang/String;
aload 0
getfield com/nd/android/u/tast/experience/activity/DateWidgetActivity/special_day_list [Ljava/lang/String;
iload 1
aaload
invokevirtual java/lang/String/equals(Ljava/lang/Object;)Z
ifeq L4
aload 0
getfield com/nd/android/u/tast/experience/activity/DateWidgetActivity/signed_tips_list [Ljava/lang/String;
iconst_2
aaload
astore 2
aload 0
getfield com/nd/android/u/tast/experience/activity/DateWidgetActivity/signin_tips_list [Ljava/lang/String;
iconst_2
aaload
astore 3
L4:
iload 1
iconst_1
iadd
istore 1
goto L3
L2:
ldc ""
aload 0
getfield com/nd/android/u/tast/experience/activity/DateWidgetActivity/StrJoinDay Ljava/lang/String;
invokevirtual java/lang/String/equals(Ljava/lang/Object;)Z
ifne L5
aload 0
aload 0
getfield com/nd/android/u/tast/experience/activity/DateWidgetActivity/StrJoinDay Ljava/lang/String;
iconst_1
invokestatic com/nd/android/u/tast/TaskUtil/getMonthOrDate(Ljava/lang/String;I)I
putfield com/nd/android/u/tast/experience/activity/DateWidgetActivity/JoinMonth I
aload 0
aload 0
getfield com/nd/android/u/tast/experience/activity/DateWidgetActivity/StrJoinDay Ljava/lang/String;
iconst_2
invokestatic com/nd/android/u/tast/TaskUtil/getMonthOrDate(Ljava/lang/String;I)I
putfield com/nd/android/u/tast/experience/activity/DateWidgetActivity/JoinDay I
aload 0
iconst_0
putfield com/nd/android/u/tast/experience/activity/DateWidgetActivity/IsAnniversary Z
aload 0
getfield com/nd/android/u/tast/experience/activity/DateWidgetActivity/today Ljava/util/Date;
iconst_0
invokestatic com/nd/android/u/tast/experience/activity/DateWidgetActivity/getYearOrMonth(Ljava/util/Date;I)I
aload 0
getfield com/nd/android/u/tast/experience/activity/DateWidgetActivity/StrJoinDay Ljava/lang/String;
iconst_0
invokestatic com/nd/android/u/tast/TaskUtil/getMonthOrDate(Ljava/lang/String;I)I
if_icmple L5
aload 0
iconst_1
putfield com/nd/android/u/tast/experience/activity/DateWidgetActivity/IsAnniversary Z
L5:
aload 0
getstatic com/product/android/business/ApplicationVariable/INSTANCE Lcom/product/android/business/ApplicationVariable;
invokevirtual com/product/android/business/ApplicationVariable/getIUser()Lcom/product/android/business/login/IGetUserInfo;
invokeinterface com/product/android/business/login/IGetUserInfo/getBindUser()Lcom/product/android/business/login/BindUser; 0
invokevirtual com/product/android/business/login/BindUser/getBirthday()Ljava/lang/String;
putfield com/nd/android/u/tast/experience/activity/DateWidgetActivity/StrBirthDay Ljava/lang/String;
ldc ""
aload 0
getfield com/nd/android/u/tast/experience/activity/DateWidgetActivity/StrBirthDay Ljava/lang/String;
invokevirtual java/lang/String/equals(Ljava/lang/Object;)Z
ifne L6
aload 0
aload 0
getfield com/nd/android/u/tast/experience/activity/DateWidgetActivity/StrBirthDay Ljava/lang/String;
iconst_1
invokestatic com/nd/android/u/tast/TaskUtil/getMonthOrDate(Ljava/lang/String;I)I
putfield com/nd/android/u/tast/experience/activity/DateWidgetActivity/BirthMonth I
aload 0
aload 0
getfield com/nd/android/u/tast/experience/activity/DateWidgetActivity/StrBirthDay Ljava/lang/String;
iconst_2
invokestatic com/nd/android/u/tast/TaskUtil/getMonthOrDate(Ljava/lang/String;I)I
putfield com/nd/android/u/tast/experience/activity/DateWidgetActivity/BirthDay I
L6:
aload 0
getfield com/nd/android/u/tast/experience/activity/DateWidgetActivity/anniversary_txv Landroid/widget/TextView;
aload 4
invokevirtual android/widget/TextView/setText(Ljava/lang/CharSequence;)V
aload 0
getfield com/nd/android/u/tast/experience/activity/DateWidgetActivity/jfanniversary_txv Landroid/widget/TextView;
aload 5
invokevirtual android/widget/TextView/setText(Ljava/lang/CharSequence;)V
aload 0
getfield com/nd/android/u/tast/experience/activity/DateWidgetActivity/anniversary_layout Landroid/widget/LinearLayout;
bipush 8
invokevirtual android/widget/LinearLayout/setVisibility(I)V
return
.limit locals 6
.limit stack 3
.end method

.method public DateFormatMD(Ljava/util/Date;)Ljava/lang/String;
aload 0
getfield com/nd/android/u/tast/experience/activity/DateWidgetActivity/dateMD Ljava/text/SimpleDateFormat;
aload 1
invokevirtual java/text/SimpleDateFormat/format(Ljava/util/Date;)Ljava/lang/String;
areturn
.limit locals 2
.limit stack 2
.end method

.method protected GetDateShortString(Ljava/util/Calendar;)Ljava/lang/String;
new java/lang/StringBuilder
dup
invokespecial java/lang/StringBuilder/<init>()V
aload 1
iconst_1
invokevirtual java/util/Calendar/get(I)I
invokevirtual java/lang/StringBuilder/append(I)Ljava/lang/StringBuilder;
ldc "/"
invokevirtual java/lang/StringBuilder/append(Ljava/lang/String;)Ljava/lang/StringBuilder;
invokevirtual java/lang/StringBuilder/toString()Ljava/lang/String;
astore 2
new java/lang/StringBuilder
dup
invokespecial java/lang/StringBuilder/<init>()V
aload 2
invokevirtual java/lang/StringBuilder/append(Ljava/lang/String;)Ljava/lang/StringBuilder;
aload 1
iconst_2
invokevirtual java/util/Calendar/get(I)I
iconst_1
iadd
invokevirtual java/lang/StringBuilder/append(I)Ljava/lang/StringBuilder;
ldc "/"
invokevirtual java/lang/StringBuilder/append(Ljava/lang/String;)Ljava/lang/StringBuilder;
invokevirtual java/lang/StringBuilder/toString()Ljava/lang/String;
astore 2
new java/lang/StringBuilder
dup
invokespecial java/lang/StringBuilder/<init>()V
aload 2
invokevirtual java/lang/StringBuilder/append(Ljava/lang/String;)Ljava/lang/StringBuilder;
aload 1
iconst_5
invokevirtual java/util/Calendar/get(I)I
invokevirtual java/lang/StringBuilder/append(I)Ljava/lang/StringBuilder;
invokevirtual java/lang/StringBuilder/toString()Ljava/lang/String;
areturn
.limit locals 3
.limit stack 3
.end method

.method public GetEndDate(Ljava/util/Calendar;)Ljava/util/Calendar;
aload 0
aload 1
invokevirtual java/util/Calendar/clone()Ljava/lang/Object;
checkcast java/util/Calendar
putfield com/nd/android/u/tast/experience/activity/DateWidgetActivity/endDate Ljava/util/Calendar;
aload 0
getfield com/nd/android/u/tast/experience/activity/DateWidgetActivity/endDate Ljava/util/Calendar;
iconst_5
bipush 41
invokevirtual java/util/Calendar/add(II)V
aload 0
getfield com/nd/android/u/tast/experience/activity/DateWidgetActivity/endDate Ljava/util/Calendar;
areturn
.limit locals 2
.limit stack 3
.end method

.method public GetStartDate()Ljava/util/Calendar;
invokestatic java/util/Calendar/getInstance()Ljava/util/Calendar;
astore 3
aload 3
iconst_5
iconst_1
invokevirtual java/util/Calendar/set(II)V
aload 3
bipush 11
iconst_0
invokevirtual java/util/Calendar/set(II)V
aload 3
bipush 12
iconst_0
invokevirtual java/util/Calendar/set(II)V
aload 3
bipush 13
iconst_0
invokevirtual java/util/Calendar/set(II)V
aload 3
iconst_2
invokevirtual java/util/Calendar/setFirstDayOfWeek(I)V
aload 3
bipush 7
invokevirtual java/util/Calendar/get(I)I
iconst_2
isub
istore 2
iload 2
istore 1
iload 2
ifge L0
bipush 6
istore 1
L0:
aload 3
bipush 7
iload 1
ineg
invokevirtual java/util/Calendar/add(II)V
aload 3
areturn
.limit locals 4
.limit stack 3
.end method

.method public GetTodayDate()Ljava/util/Calendar;
invokestatic java/util/Calendar/getInstance()Ljava/util/Calendar;
astore 1
aload 1
bipush 11
iconst_0
invokevirtual java/util/Calendar/set(II)V
aload 1
bipush 12
iconst_0
invokevirtual java/util/Calendar/set(II)V
aload 1
bipush 13
iconst_0
invokevirtual java/util/Calendar/set(II)V
aload 1
iconst_2
invokevirtual java/util/Calendar/setFirstDayOfWeek(I)V
aload 1
areturn
.limit locals 2
.limit stack 3
.end method

.method public OnNotification(II)V
aload 0
getfield com/nd/android/u/tast/experience/activity/DateWidgetActivity/leftDays I
invokestatic java/lang/String/valueOf(I)Ljava/lang/String;
invokevirtual java/lang/String/length()I
pop
iload 2
invokestatic java/lang/String/valueOf(I)Ljava/lang/String;
invokevirtual java/lang/String/length()I
pop
iload 1
ifne L0
aload 0
getfield com/nd/android/u/tast/experience/activity/DateWidgetActivity/tvSignHoldTips Landroid/widget/TextView;
getstatic com/nd/android/u/tast/experience/activity/DateWidgetActivity/signExpTipsArray [Ljava/lang/String;
iconst_0
aaload
iconst_3
anewarray java/lang/Object
dup
iconst_0
aload 0
getfield com/nd/android/u/tast/experience/activity/DateWidgetActivity/signPercent Ljava/lang/String;
aastore
dup
iconst_1
aload 0
getfield com/nd/android/u/tast/experience/activity/DateWidgetActivity/leftDays I
invokestatic java/lang/Integer/valueOf(I)Ljava/lang/Integer;
aastore
dup
iconst_2
iload 2
invokestatic java/lang/Integer/valueOf(I)Ljava/lang/Integer;
aastore
invokestatic java/lang/String/format(Ljava/lang/String;[Ljava/lang/Object;)Ljava/lang/String;
invokevirtual android/widget/TextView/setText(Ljava/lang/CharSequence;)V
L1:
return
L0:
iload 1
iconst_1
if_icmpne L2
aload 0
getfield com/nd/android/u/tast/experience/activity/DateWidgetActivity/tvSignHoldTips Landroid/widget/TextView;
getstatic com/nd/android/u/tast/experience/activity/DateWidgetActivity/signExpTipsArray [Ljava/lang/String;
iconst_1
aaload
iconst_3
anewarray java/lang/Object
dup
iconst_0
aload 0
getfield com/nd/android/u/tast/experience/activity/DateWidgetActivity/signPercent Ljava/lang/String;
aastore
dup
iconst_1
aload 0
getfield com/nd/android/u/tast/experience/activity/DateWidgetActivity/leftDays I
invokestatic java/lang/Integer/valueOf(I)Ljava/lang/Integer;
aastore
dup
iconst_2
iload 2
invokestatic java/lang/Integer/valueOf(I)Ljava/lang/Integer;
aastore
invokestatic java/lang/String/format(Ljava/lang/String;[Ljava/lang/Object;)Ljava/lang/String;
invokevirtual android/widget/TextView/setText(Ljava/lang/CharSequence;)V
return
L2:
iload 1
iconst_2
if_icmpne L3
aload 0
getfield com/nd/android/u/tast/experience/activity/DateWidgetActivity/tvSignHoldTips Landroid/widget/TextView;
getstatic com/nd/android/u/tast/experience/activity/DateWidgetActivity/signExpTipsArray [Ljava/lang/String;
iconst_2
aaload
iconst_3
anewarray java/lang/Object
dup
iconst_0
aload 0
getfield com/nd/android/u/tast/experience/activity/DateWidgetActivity/signPercent Ljava/lang/String;
aastore
dup
iconst_1
aload 0
getfield com/nd/android/u/tast/experience/activity/DateWidgetActivity/leftDays I
invokestatic java/lang/Integer/valueOf(I)Ljava/lang/Integer;
aastore
dup
iconst_2
iload 2
invokestatic java/lang/Integer/valueOf(I)Ljava/lang/Integer;
aastore
invokestatic java/lang/String/format(Ljava/lang/String;[Ljava/lang/Object;)Ljava/lang/String;
invokevirtual android/widget/TextView/setText(Ljava/lang/CharSequence;)V
return
L3:
iload 1
iconst_3
if_icmpne L4
aload 0
getfield com/nd/android/u/tast/experience/activity/DateWidgetActivity/tvSignHoldTips Landroid/widget/TextView;
getstatic com/nd/android/u/tast/experience/activity/DateWidgetActivity/signExpTipsArray [Ljava/lang/String;
iconst_3
aaload
invokevirtual android/widget/TextView/setText(Ljava/lang/CharSequence;)V
return
L4:
iload 1
iconst_4
if_icmpne L1
aload 0
getfield com/nd/android/u/tast/experience/activity/DateWidgetActivity/tvSignHoldTips Landroid/widget/TextView;
getstatic com/nd/android/u/tast/experience/activity/DateWidgetActivity/signExpTipsArray [Ljava/lang/String;
iconst_4
aaload
invokevirtual android/widget/TextView/setText(Ljava/lang/CharSequence;)V
return
.limit locals 3
.limit stack 6
.end method

.method public onCreate(Landroid/os/Bundle;)V
aload 0
aload 1
invokespecial android/app/Activity/onCreate(Landroid/os/Bundle;)V
aload 0
invokevirtual com/nd/android/u/tast/experience/activity/DateWidgetActivity/getIntent()Landroid/content/Intent;
ifnull L0
aload 0
aload 0
invokevirtual com/nd/android/u/tast/experience/activity/DateWidgetActivity/getIntent()Landroid/content/Intent;
ldc "flag_to_taskmain"
iconst_0
invokevirtual android/content/Intent/getIntExtra(Ljava/lang/String;I)I
putfield com/nd/android/u/tast/experience/activity/DateWidgetActivity/isToTaskMain I
L0:
aload 0
getstatic com/nd/android/u/tasklib/R$layout/calendar_main I
invokevirtual com/nd/android/u/tast/experience/activity/DateWidgetActivity/setContentView(I)V
aload 0
aload 0
getfield com/nd/android/u/tast/experience/activity/DateWidgetActivity/activity Lcom/nd/android/u/tast/experience/activity/DateWidgetActivity;
putfield com/nd/android/u/tast/experience/activity/DateWidgetActivity/context Landroid/content/Context;
aload 0
invokespecial com/nd/android/u/tast/experience/activity/DateWidgetActivity/findControls()V
aload 0
invokespecial com/nd/android/u/tast/experience/activity/DateWidgetActivity/initControls()V
return
.limit locals 2
.limit stack 4
.end method

.method public onKeyDown(ILandroid/view/KeyEvent;)Z
iload 1
iconst_4
if_icmpne L0
aload 0
invokespecial com/nd/android/u/tast/experience/activity/DateWidgetActivity/back_ImMain()V
iconst_1
ireturn
L0:
aload 0
iload 1
aload 2
invokespecial android/app/Activity/onKeyDown(ILandroid/view/KeyEvent;)Z
ireturn
.limit locals 3
.limit stack 3
.end method

.method public onResume()V
aload 0
invokespecial android/app/Activity/onResume()V
aload 0
invokespecial com/nd/android/u/tast/experience/activity/DateWidgetActivity/DrawCalendarView()V
aload 0
aload 0
getfield com/nd/android/u/tast/experience/activity/DateWidgetActivity/morepoints_listview Landroid/widget/ListView;
aload 0
getfield com/nd/android/u/tast/experience/activity/DateWidgetActivity/mAdapter Lcom/nd/android/u/tast/experience/adapter/MoreExperienceAdapter;
aload 0
aload 0
getfield com/nd/android/u/tast/experience/activity/DateWidgetActivity/handler Landroid/os/Handler;
invokestatic com/nd/android/u/tast/experience/activity/DateWidgetActivity/initMoreExperience(Landroid/app/Activity;Landroid/widget/ListView;Lcom/nd/android/u/tast/experience/adapter/MoreExperienceAdapter;Lcom/nd/android/u/tast/experience/view/FullAttendanceListener;Landroid/os/Handler;)V
return
.limit locals 1
.limit stack 5
.end method

.method protected reGetScore(Lorg/json/JSONObject;Lcom/nd/android/u/tast/com/AjaxCom;)Z
.catch com/common/android/utils/http/HttpAuthException from L0 to L1 using L2
.catch com/common/android/utils/http/ResponseException from L0 to L1 using L3
.catch com/common/android/utils/http/HttpServerException from L0 to L1 using L4
.catch com/common/android/utils/http/HttpException from L0 to L1 using L5
.catch com/common/android/utils/http/ResponseException from L6 to L7 using L8
.catch com/common/android/utils/http/HttpException from L6 to L7 using L9
iconst_0
istore 4
aconst_null
astore 6
aload 1
ldc "levelup"
invokestatic com/common/android/utils/JSONUtils/getInt(Lorg/json/JSONObject;Ljava/lang/String;)I
ifle L10
iconst_1
istore 5
L0:
aload 2
lconst_0
invokevirtual com/nd/android/u/tast/com/AjaxCom/getUserscore(J)Lorg/json/JSONObject;
astore 1
L1:
aload 1
ldc "code"
invokestatic com/common/android/utils/JSONUtils/getInt(Lorg/json/JSONObject;Ljava/lang/String;)I
istore 3
iload 5
istore 4
aload 1
ifnull L10
iload 5
istore 4
iload 3
sipush 200
if_icmpne L10
invokestatic com/nd/android/u/tast/TaskGlobalVariable/getInstance()Lcom/nd/android/u/tast/TaskGlobalVariable;
getfield com/nd/android/u/tast/TaskGlobalVariable/mOapScore Lcom/product/android/commonInterface/task/OapScore;
aload 1
invokevirtual com/product/android/commonInterface/task/OapScore/setScoreData(Lorg/json/JSONObject;)V
L6:
invokestatic com/nd/android/u/tast/com/TaskComFactory/getInstance()Lcom/nd/android/u/tast/com/TaskComFactory;
invokevirtual com/nd/android/u/tast/com/TaskComFactory/getLotteryCom()Lcom/nd/android/u/tast/com/OapLotteryCom;
sipush 10000
invokevirtual com/nd/android/u/tast/com/OapLotteryCom/getItemByType(I)I
istore 3
invokestatic com/nd/android/u/tast/TaskGlobalVariable/getInstance()Lcom/nd/android/u/tast/TaskGlobalVariable;
getfield com/nd/android/u/tast/TaskGlobalVariable/mOapScore Lcom/product/android/commonInterface/task/OapScore;
iload 3
invokevirtual com/product/android/commonInterface/task/OapScore/setLotterychance(I)V
L7:
iload 5
istore 4
L10:
iload 4
ireturn
L2:
astore 1
aload 1
invokevirtual com/common/android/utils/http/HttpAuthException/printStackTrace()V
aload 6
astore 1
goto L1
L3:
astore 1
aload 1
invokevirtual com/common/android/utils/http/ResponseException/printStackTrace()V
aload 6
astore 1
goto L1
L4:
astore 1
aload 1
invokevirtual com/common/android/utils/http/HttpServerException/printStackTrace()V
aload 6
astore 1
goto L1
L5:
astore 1
aload 1
invokevirtual com/common/android/utils/http/HttpException/printStackTrace()V
aload 6
astore 1
goto L1
L8:
astore 1
aload 1
invokevirtual com/common/android/utils/http/ResponseException/printStackTrace()V
iconst_1
ireturn
L9:
astore 1
aload 1
invokevirtual com/common/android/utils/http/HttpException/printStackTrace()V
iconst_1
ireturn
.limit locals 7
.limit stack 3
.end method

.method public setFlagBusy(Z)V
aload 0
iload 1
putfield com/nd/android/u/tast/experience/activity/DateWidgetActivity/mBusy Z
return
.limit locals 2
.limit stack 2
.end method

.method public startSigninAnimation()V
aload 0
getfield com/nd/android/u/tast/experience/activity/DateWidgetActivity/signin_animIV Landroid/widget/ImageView;
iconst_0
invokevirtual android/widget/ImageView/setVisibility(I)V
aload 0
getfield com/nd/android/u/tast/experience/activity/DateWidgetActivity/signin_animaDrawable Landroid/graphics/drawable/AnimationDrawable;
invokevirtual android/graphics/drawable/AnimationDrawable/stop()V
aload 0
getfield com/nd/android/u/tast/experience/activity/DateWidgetActivity/signin_animaDrawable Landroid/graphics/drawable/AnimationDrawable;
invokevirtual android/graphics/drawable/AnimationDrawable/start()V
aload 0
iconst_0
putfield com/nd/android/u/tast/experience/activity/DateWidgetActivity/duration I
iconst_0
istore 1
L0:
iload 1
aload 0
getfield com/nd/android/u/tast/experience/activity/DateWidgetActivity/signin_animaDrawable Landroid/graphics/drawable/AnimationDrawable;
invokevirtual android/graphics/drawable/AnimationDrawable/getNumberOfFrames()I
if_icmpge L1
aload 0
aload 0
getfield com/nd/android/u/tast/experience/activity/DateWidgetActivity/duration I
aload 0
getfield com/nd/android/u/tast/experience/activity/DateWidgetActivity/signin_animaDrawable Landroid/graphics/drawable/AnimationDrawable;
iload 1
invokevirtual android/graphics/drawable/AnimationDrawable/getDuration(I)I
iadd
putfield com/nd/android/u/tast/experience/activity/DateWidgetActivity/duration I
iload 1
iconst_1
iadd
istore 1
goto L0
L1:
new android/os/Handler
dup
invokespecial android/os/Handler/<init>()V
new com/nd/android/u/tast/experience/activity/DateWidgetActivity$6
dup
aload 0
invokespecial com/nd/android/u/tast/experience/activity/DateWidgetActivity$6/<init>(Lcom/nd/android/u/tast/experience/activity/DateWidgetActivity;)V
aload 0
getfield com/nd/android/u/tast/experience/activity/DateWidgetActivity/duration I
i2l
invokevirtual android/os/Handler/postDelayed(Ljava/lang/Runnable;J)Z
pop
return
.limit locals 2
.limit stack 4
.end method

.method protected updateGlobalScoreData(III)V
invokestatic com/nd/android/u/tast/TaskGlobalVariable/getInstance()Lcom/nd/android/u/tast/TaskGlobalVariable;
getfield com/nd/android/u/tast/TaskGlobalVariable/mOapScore Lcom/product/android/commonInterface/task/OapScore;
iconst_1
invokevirtual com/product/android/commonInterface/task/OapScore/setSignstatus(I)V
invokestatic com/nd/android/u/tast/TaskGlobalVariable/getInstance()Lcom/nd/android/u/tast/TaskGlobalVariable;
getfield com/nd/android/u/tast/TaskGlobalVariable/mOapScore Lcom/product/android/commonInterface/task/OapScore;
invokestatic com/nd/android/u/tast/TaskGlobalVariable/getInstance()Lcom/nd/android/u/tast/TaskGlobalVariable;
getfield com/nd/android/u/tast/TaskGlobalVariable/mOapScore Lcom/product/android/commonInterface/task/OapScore;
invokevirtual com/product/android/commonInterface/task/OapScore/getTotalexp()I
iload 1
iadd
invokevirtual com/product/android/commonInterface/task/OapScore/setTotalexp(I)V
invokestatic com/nd/android/u/tast/TaskGlobalVariable/getInstance()Lcom/nd/android/u/tast/TaskGlobalVariable;
getfield com/nd/android/u/tast/TaskGlobalVariable/mOapScore Lcom/product/android/commonInterface/task/OapScore;
invokestatic com/nd/android/u/tast/TaskGlobalVariable/getInstance()Lcom/nd/android/u/tast/TaskGlobalVariable;
getfield com/nd/android/u/tast/TaskGlobalVariable/mOapScore Lcom/product/android/commonInterface/task/OapScore;
invokevirtual com/product/android/commonInterface/task/OapScore/getTotalmoney()I
iload 2
iadd
invokevirtual com/product/android/commonInterface/task/OapScore/setTotalmoney(I)V
new com/product/android/commonInterface/BaseCommonStruct
dup
invokespecial com/product/android/commonInterface/BaseCommonStruct/<init>()V
astore 4
aload 4
iload 3
putfield com/product/android/commonInterface/BaseCommonStruct/iPara I
getstatic com/product/android/commonInterface/CommonInterfaceManager/INSTANCE Lcom/product/android/commonInterface/CommonInterfaceManager;
iconst_3
sipush 30002
aload 4
invokevirtual com/product/android/commonInterface/CommonInterfaceManager/CommonInterfaceID(IILcom/product/android/commonInterface/BaseCommonStruct;)I
pop
return
.limit locals 5
.limit stack 4
.end method
