.bytecode 50.0
.class synchronized com/nd/android/u/tast/experience/activity/DateWidgetActivity$4
.super java/lang/Object
.implements java/lang/Runnable
.enclosing method com/nd/android/u/tast/experience/activity/DateWidgetActivity/updateCalendar(II)V
.inner class inner com/nd/android/u/tast/experience/activity/DateWidgetActivity$4
.inner class inner com/nd/android/u/tast/experience/activity/DateWidgetActivity$4$1

.field final synthetic 'this$0' Lcom/nd/android/u/tast/experience/activity/DateWidgetActivity;

.field final synthetic 'val$month' I

.field final synthetic 'val$year' I

.method <init>(Lcom/nd/android/u/tast/experience/activity/DateWidgetActivity;II)V
aload 0
aload 1
putfield com/nd/android/u/tast/experience/activity/DateWidgetActivity$4/this$0 Lcom/nd/android/u/tast/experience/activity/DateWidgetActivity;
aload 0
iload 2
putfield com/nd/android/u/tast/experience/activity/DateWidgetActivity$4/val$year I
aload 0
iload 3
putfield com/nd/android/u/tast/experience/activity/DateWidgetActivity$4/val$month I
aload 0
invokespecial java/lang/Object/<init>()V
return
.limit locals 4
.limit stack 2
.end method

.method public run()V
aload 0
getfield com/nd/android/u/tast/experience/activity/DateWidgetActivity$4/this$0 Lcom/nd/android/u/tast/experience/activity/DateWidgetActivity;
invokestatic com/nd/android/u/tast/experience/activity/DateWidgetActivity/access$1100(Lcom/nd/android/u/tast/experience/activity/DateWidgetActivity;)Ljava/lang/String;
invokestatic android/text/TextUtils/isEmpty(Ljava/lang/CharSequence;)Z
ifeq L0
invokestatic com/nd/android/u/tast/experience/activity/DateWidgetActivity/getDefaultSignArray()[C
astore 1
aload 0
getfield com/nd/android/u/tast/experience/activity/DateWidgetActivity$4/this$0 Lcom/nd/android/u/tast/experience/activity/DateWidgetActivity;
new java/lang/String
dup
aload 1
invokespecial java/lang/String/<init>([C)V
invokestatic com/nd/android/u/tast/experience/activity/DateWidgetActivity/access$1102(Lcom/nd/android/u/tast/experience/activity/DateWidgetActivity;Ljava/lang/String;)Ljava/lang/String;
pop
L0:
new java/lang/StringBuffer
dup
invokespecial java/lang/StringBuffer/<init>()V
astore 1
aload 0
getfield com/nd/android/u/tast/experience/activity/DateWidgetActivity$4/this$0 Lcom/nd/android/u/tast/experience/activity/DateWidgetActivity;
aload 0
getfield com/nd/android/u/tast/experience/activity/DateWidgetActivity$4/val$year I
aload 0
getfield com/nd/android/u/tast/experience/activity/DateWidgetActivity$4/val$month I
aload 0
getfield com/nd/android/u/tast/experience/activity/DateWidgetActivity$4/this$0 Lcom/nd/android/u/tast/experience/activity/DateWidgetActivity;
invokestatic com/nd/android/u/tast/experience/activity/DateWidgetActivity/access$1100(Lcom/nd/android/u/tast/experience/activity/DateWidgetActivity;)Ljava/lang/String;
aload 1
invokestatic com/nd/android/u/tast/experience/activity/DateWidgetActivity/getSignStr(IILjava/lang/String;Ljava/lang/StringBuffer;)Ljava/lang/String;
invokestatic com/nd/android/u/tast/experience/activity/DateWidgetActivity/access$1102(Lcom/nd/android/u/tast/experience/activity/DateWidgetActivity;Ljava/lang/String;)Ljava/lang/String;
pop
aload 0
getfield com/nd/android/u/tast/experience/activity/DateWidgetActivity$4/this$0 Lcom/nd/android/u/tast/experience/activity/DateWidgetActivity;
new com/nd/android/u/tast/experience/activity/DateWidgetActivity$4$1
dup
aload 0
aload 1
invokespecial com/nd/android/u/tast/experience/activity/DateWidgetActivity$4$1/<init>(Lcom/nd/android/u/tast/experience/activity/DateWidgetActivity$4;Ljava/lang/StringBuffer;)V
invokevirtual com/nd/android/u/tast/experience/activity/DateWidgetActivity/runOnUiThread(Ljava/lang/Runnable;)V
return
.limit locals 2
.limit stack 5
.end method
