.bytecode 50.0
.class synchronized com/nd/android/u/tast/experience/activity/DateWidgetActivity$8$1
.super java/lang/Object
.implements java/lang/Runnable
.enclosing method com/nd/android/u/tast/experience/activity/DateWidgetActivity$8/run()V
.inner class inner com/nd/android/u/tast/experience/activity/DateWidgetActivity$8
.inner class inner com/nd/android/u/tast/experience/activity/DateWidgetActivity$8$1

.field final synthetic 'this$1' Lcom/nd/android/u/tast/experience/activity/DateWidgetActivity$8;

.method <init>(Lcom/nd/android/u/tast/experience/activity/DateWidgetActivity$8;)V
aload 0
aload 1
putfield com/nd/android/u/tast/experience/activity/DateWidgetActivity$8$1/this$1 Lcom/nd/android/u/tast/experience/activity/DateWidgetActivity$8;
aload 0
invokespecial java/lang/Object/<init>()V
return
.limit locals 2
.limit stack 2
.end method

.method public run()V
.catch all from L0 to L1 using L2
.catch all from L1 to L3 using L2
.catch all from L4 to L5 using L2
.catch all from L5 to L6 using L2
.catch all from L7 to L8 using L2
.catch all from L9 to L10 using L2
.catch all from L11 to L12 using L2
aload 0
monitorenter
L0:
invokestatic com/nd/android/u/tast/TaskGlobalVariable/getInstance()Lcom/nd/android/u/tast/TaskGlobalVariable;
getfield com/nd/android/u/tast/TaskGlobalVariable/mOapScore Lcom/product/android/commonInterface/task/OapScore;
invokevirtual com/product/android/commonInterface/task/OapScore/getSignstatus()I
iconst_1
if_icmpne L11
aload 0
getfield com/nd/android/u/tast/experience/activity/DateWidgetActivity$8$1/this$1 Lcom/nd/android/u/tast/experience/activity/DateWidgetActivity$8;
getfield com/nd/android/u/tast/experience/activity/DateWidgetActivity$8/this$0 Lcom/nd/android/u/tast/experience/activity/DateWidgetActivity;
invokestatic com/nd/android/u/tast/experience/activity/DateWidgetActivity/access$1900(Lcom/nd/android/u/tast/experience/activity/DateWidgetActivity;)Landroid/widget/TextView;
ldc "\u6210\u529f\u7b7e\u5230\uff01"
invokevirtual android/widget/TextView/setText(Ljava/lang/CharSequence;)V
aload 0
getfield com/nd/android/u/tast/experience/activity/DateWidgetActivity$8$1/this$1 Lcom/nd/android/u/tast/experience/activity/DateWidgetActivity$8;
getfield com/nd/android/u/tast/experience/activity/DateWidgetActivity$8/this$0 Lcom/nd/android/u/tast/experience/activity/DateWidgetActivity;
invokestatic com/nd/android/u/tast/experience/activity/DateWidgetActivity/access$2000(Lcom/nd/android/u/tast/experience/activity/DateWidgetActivity;)Landroid/widget/TextView;
bipush 8
invokevirtual android/widget/TextView/setVisibility(I)V
aload 0
getfield com/nd/android/u/tast/experience/activity/DateWidgetActivity$8$1/this$1 Lcom/nd/android/u/tast/experience/activity/DateWidgetActivity$8;
getfield com/nd/android/u/tast/experience/activity/DateWidgetActivity$8/this$0 Lcom/nd/android/u/tast/experience/activity/DateWidgetActivity;
invokestatic com/nd/android/u/tast/experience/activity/DateWidgetActivity/access$2100(Lcom/nd/android/u/tast/experience/activity/DateWidgetActivity;)Landroid/view/View;
iconst_0
invokevirtual android/view/View/setVisibility(I)V
aload 0
getfield com/nd/android/u/tast/experience/activity/DateWidgetActivity$8$1/this$1 Lcom/nd/android/u/tast/experience/activity/DateWidgetActivity$8;
getfield com/nd/android/u/tast/experience/activity/DateWidgetActivity$8/this$0 Lcom/nd/android/u/tast/experience/activity/DateWidgetActivity;
invokestatic com/nd/android/u/tast/experience/activity/DateWidgetActivity/access$2300(Lcom/nd/android/u/tast/experience/activity/DateWidgetActivity;)Landroid/widget/TextView;
aload 0
getfield com/nd/android/u/tast/experience/activity/DateWidgetActivity$8$1/this$1 Lcom/nd/android/u/tast/experience/activity/DateWidgetActivity$8;
invokestatic com/nd/android/u/tast/experience/activity/DateWidgetActivity$8/access$2200(Lcom/nd/android/u/tast/experience/activity/DateWidgetActivity$8;)I
invokestatic java/lang/String/valueOf(I)Ljava/lang/String;
invokevirtual android/widget/TextView/setText(Ljava/lang/CharSequence;)V
aload 0
getfield com/nd/android/u/tast/experience/activity/DateWidgetActivity$8$1/this$1 Lcom/nd/android/u/tast/experience/activity/DateWidgetActivity$8;
invokestatic com/nd/android/u/tast/experience/activity/DateWidgetActivity$8/access$2400(Lcom/nd/android/u/tast/experience/activity/DateWidgetActivity$8;)I
ifne L7
aload 0
getfield com/nd/android/u/tast/experience/activity/DateWidgetActivity$8$1/this$1 Lcom/nd/android/u/tast/experience/activity/DateWidgetActivity$8;
getfield com/nd/android/u/tast/experience/activity/DateWidgetActivity$8/this$0 Lcom/nd/android/u/tast/experience/activity/DateWidgetActivity;
getstatic com/nd/android/u/tasklib/R$id/gold_text I
invokevirtual com/nd/android/u/tast/experience/activity/DateWidgetActivity/findViewById(I)Landroid/view/View;
bipush 8
invokevirtual android/view/View/setVisibility(I)V
aload 0
getfield com/nd/android/u/tast/experience/activity/DateWidgetActivity$8$1/this$1 Lcom/nd/android/u/tast/experience/activity/DateWidgetActivity$8;
getfield com/nd/android/u/tast/experience/activity/DateWidgetActivity$8/this$0 Lcom/nd/android/u/tast/experience/activity/DateWidgetActivity;
invokestatic com/nd/android/u/tast/experience/activity/DateWidgetActivity/access$2500(Lcom/nd/android/u/tast/experience/activity/DateWidgetActivity;)Landroid/widget/TextView;
bipush 8
invokevirtual android/widget/TextView/setVisibility(I)V
L1:
aload 0
getfield com/nd/android/u/tast/experience/activity/DateWidgetActivity$8$1/this$1 Lcom/nd/android/u/tast/experience/activity/DateWidgetActivity$8;
getfield com/nd/android/u/tast/experience/activity/DateWidgetActivity$8/this$0 Lcom/nd/android/u/tast/experience/activity/DateWidgetActivity;
invokestatic com/nd/android/u/tast/experience/activity/DateWidgetActivity/access$2700(Lcom/nd/android/u/tast/experience/activity/DateWidgetActivity;)Landroid/widget/TextView;
aload 0
getfield com/nd/android/u/tast/experience/activity/DateWidgetActivity$8$1/this$1 Lcom/nd/android/u/tast/experience/activity/DateWidgetActivity$8;
invokestatic com/nd/android/u/tast/experience/activity/DateWidgetActivity$8/access$2600(Lcom/nd/android/u/tast/experience/activity/DateWidgetActivity$8;)I
invokestatic java/lang/String/valueOf(I)Ljava/lang/String;
invokevirtual android/widget/TextView/setText(Ljava/lang/CharSequence;)V
aload 0
getfield com/nd/android/u/tast/experience/activity/DateWidgetActivity$8$1/this$1 Lcom/nd/android/u/tast/experience/activity/DateWidgetActivity$8;
getfield com/nd/android/u/tast/experience/activity/DateWidgetActivity$8/this$0 Lcom/nd/android/u/tast/experience/activity/DateWidgetActivity;
invokestatic com/nd/android/u/tast/experience/activity/DateWidgetActivity/access$1600(Lcom/nd/android/u/tast/experience/activity/DateWidgetActivity;)Ljava/lang/String;
invokestatic com/nd/android/u/tast/experience/activity/DateWidgetActivity/access$2800(Ljava/lang/String;)I
istore 1
L3:
iload 1
iconst_m1
if_icmpeq L5
L4:
new java/lang/StringBuilder
dup
aload 0
getfield com/nd/android/u/tast/experience/activity/DateWidgetActivity$8$1/this$1 Lcom/nd/android/u/tast/experience/activity/DateWidgetActivity$8;
getfield com/nd/android/u/tast/experience/activity/DateWidgetActivity$8/this$0 Lcom/nd/android/u/tast/experience/activity/DateWidgetActivity;
invokestatic com/nd/android/u/tast/experience/activity/DateWidgetActivity/access$1100(Lcom/nd/android/u/tast/experience/activity/DateWidgetActivity;)Ljava/lang/String;
invokespecial java/lang/StringBuilder/<init>(Ljava/lang/String;)V
astore 2
aload 2
iload 1
bipush 49
invokevirtual java/lang/StringBuilder/setCharAt(IC)V
aload 0
getfield com/nd/android/u/tast/experience/activity/DateWidgetActivity$8$1/this$1 Lcom/nd/android/u/tast/experience/activity/DateWidgetActivity$8;
getfield com/nd/android/u/tast/experience/activity/DateWidgetActivity$8/this$0 Lcom/nd/android/u/tast/experience/activity/DateWidgetActivity;
aload 2
invokevirtual java/lang/StringBuilder/toString()Ljava/lang/String;
invokestatic com/nd/android/u/tast/experience/activity/DateWidgetActivity/access$1102(Lcom/nd/android/u/tast/experience/activity/DateWidgetActivity;Ljava/lang/String;)Ljava/lang/String;
pop
aload 0
getfield com/nd/android/u/tast/experience/activity/DateWidgetActivity$8$1/this$1 Lcom/nd/android/u/tast/experience/activity/DateWidgetActivity$8;
getfield com/nd/android/u/tast/experience/activity/DateWidgetActivity$8/this$0 Lcom/nd/android/u/tast/experience/activity/DateWidgetActivity;
aload 0
getfield com/nd/android/u/tast/experience/activity/DateWidgetActivity$8$1/this$1 Lcom/nd/android/u/tast/experience/activity/DateWidgetActivity$8;
getfield com/nd/android/u/tast/experience/activity/DateWidgetActivity$8/this$0 Lcom/nd/android/u/tast/experience/activity/DateWidgetActivity;
invokestatic com/nd/android/u/tast/experience/activity/DateWidgetActivity/access$1100(Lcom/nd/android/u/tast/experience/activity/DateWidgetActivity;)Ljava/lang/String;
invokestatic com/nd/android/u/tast/experience/activity/DateWidgetActivity/access$1200(Lcom/nd/android/u/tast/experience/activity/DateWidgetActivity;Ljava/lang/String;)V
L5:
aload 0
getfield com/nd/android/u/tast/experience/activity/DateWidgetActivity$8$1/this$1 Lcom/nd/android/u/tast/experience/activity/DateWidgetActivity$8;
invokestatic com/nd/android/u/tast/experience/activity/DateWidgetActivity$8/access$2900(Lcom/nd/android/u/tast/experience/activity/DateWidgetActivity$8;)Z
ifeq L9
aload 0
getfield com/nd/android/u/tast/experience/activity/DateWidgetActivity$8$1/this$1 Lcom/nd/android/u/tast/experience/activity/DateWidgetActivity$8;
getfield com/nd/android/u/tast/experience/activity/DateWidgetActivity$8/this$0 Lcom/nd/android/u/tast/experience/activity/DateWidgetActivity;
invokestatic com/nd/android/u/tast/experience/activity/DateWidgetActivity/access$3000(Lcom/nd/android/u/tast/experience/activity/DateWidgetActivity;)V
L6:
aload 0
monitorexit
return
L7:
aload 0
getfield com/nd/android/u/tast/experience/activity/DateWidgetActivity$8$1/this$1 Lcom/nd/android/u/tast/experience/activity/DateWidgetActivity$8;
getfield com/nd/android/u/tast/experience/activity/DateWidgetActivity$8/this$0 Lcom/nd/android/u/tast/experience/activity/DateWidgetActivity;
invokestatic com/nd/android/u/tast/experience/activity/DateWidgetActivity/access$2500(Lcom/nd/android/u/tast/experience/activity/DateWidgetActivity;)Landroid/widget/TextView;
aload 0
getfield com/nd/android/u/tast/experience/activity/DateWidgetActivity$8$1/this$1 Lcom/nd/android/u/tast/experience/activity/DateWidgetActivity$8;
invokestatic com/nd/android/u/tast/experience/activity/DateWidgetActivity$8/access$2400(Lcom/nd/android/u/tast/experience/activity/DateWidgetActivity$8;)I
invokestatic java/lang/String/valueOf(I)Ljava/lang/String;
invokevirtual android/widget/TextView/setText(Ljava/lang/CharSequence;)V
L8:
goto L1
L2:
astore 2
aload 0
monitorexit
aload 2
athrow
L9:
aload 0
getfield com/nd/android/u/tast/experience/activity/DateWidgetActivity$8$1/this$1 Lcom/nd/android/u/tast/experience/activity/DateWidgetActivity$8;
getfield com/nd/android/u/tast/experience/activity/DateWidgetActivity$8/this$0 Lcom/nd/android/u/tast/experience/activity/DateWidgetActivity;
invokevirtual com/nd/android/u/tast/experience/activity/DateWidgetActivity/startSigninAnimation()V
L10:
goto L6
L11:
aload 0
getfield com/nd/android/u/tast/experience/activity/DateWidgetActivity$8$1/this$1 Lcom/nd/android/u/tast/experience/activity/DateWidgetActivity$8;
getfield com/nd/android/u/tast/experience/activity/DateWidgetActivity$8/this$0 Lcom/nd/android/u/tast/experience/activity/DateWidgetActivity;
invokestatic com/nd/android/u/tast/experience/activity/DateWidgetActivity/access$1900(Lcom/nd/android/u/tast/experience/activity/DateWidgetActivity;)Landroid/widget/TextView;
ldc "\u7b7e\u5230\u5931\u8d25\uff0c\u8bf7\u7a0d\u540e\u91cd\u8bd5\uff01"
invokevirtual android/widget/TextView/setText(Ljava/lang/CharSequence;)V
aload 0
getfield com/nd/android/u/tast/experience/activity/DateWidgetActivity$8$1/this$1 Lcom/nd/android/u/tast/experience/activity/DateWidgetActivity$8;
getfield com/nd/android/u/tast/experience/activity/DateWidgetActivity$8/this$0 Lcom/nd/android/u/tast/experience/activity/DateWidgetActivity;
invokestatic com/nd/android/u/tast/experience/activity/DateWidgetActivity/access$2000(Lcom/nd/android/u/tast/experience/activity/DateWidgetActivity;)Landroid/widget/TextView;
iconst_0
invokevirtual android/widget/TextView/setVisibility(I)V
aload 0
getfield com/nd/android/u/tast/experience/activity/DateWidgetActivity$8$1/this$1 Lcom/nd/android/u/tast/experience/activity/DateWidgetActivity$8;
getfield com/nd/android/u/tast/experience/activity/DateWidgetActivity$8/this$0 Lcom/nd/android/u/tast/experience/activity/DateWidgetActivity;
invokestatic com/nd/android/u/tast/experience/activity/DateWidgetActivity/access$2100(Lcom/nd/android/u/tast/experience/activity/DateWidgetActivity;)Landroid/view/View;
bipush 8
invokevirtual android/view/View/setVisibility(I)V
aload 0
getfield com/nd/android/u/tast/experience/activity/DateWidgetActivity$8$1/this$1 Lcom/nd/android/u/tast/experience/activity/DateWidgetActivity$8;
getfield com/nd/android/u/tast/experience/activity/DateWidgetActivity$8/this$0 Lcom/nd/android/u/tast/experience/activity/DateWidgetActivity;
invokestatic com/nd/android/u/tast/experience/activity/DateWidgetActivity/access$2000(Lcom/nd/android/u/tast/experience/activity/DateWidgetActivity;)Landroid/widget/TextView;
ldc "\u7b7e\u5230\u5931\u8d25"
invokevirtual android/widget/TextView/setText(Ljava/lang/CharSequence;)V
L12:
goto L6
.limit locals 3
.limit stack 3
.end method
