.bytecode 50.0
.class synchronized com/nd/android/u/tast/experience/activity/MoreExperienceActivity$2
.super android/os/Handler
.enclosing method com/nd/android/u/tast/experience/activity/MoreExperienceActivity
.inner class inner com/nd/android/u/tast/experience/activity/MoreExperienceActivity$2

.field final synthetic 'this$0' Lcom/nd/android/u/tast/experience/activity/MoreExperienceActivity;

.method <init>(Lcom/nd/android/u/tast/experience/activity/MoreExperienceActivity;)V
aload 0
aload 1
putfield com/nd/android/u/tast/experience/activity/MoreExperienceActivity$2/this$0 Lcom/nd/android/u/tast/experience/activity/MoreExperienceActivity;
aload 0
invokespecial android/os/Handler/<init>()V
return
.limit locals 2
.limit stack 2
.end method

.method public handleMessage(Landroid/os/Message;)V
aload 1
getfield android/os/Message/what I
tableswitch -1
L0
L1
L2
default : L3
L3:
return
L1:
aload 0
getfield com/nd/android/u/tast/experience/activity/MoreExperienceActivity$2/this$0 Lcom/nd/android/u/tast/experience/activity/MoreExperienceActivity;
invokestatic com/nd/android/u/tast/experience/activity/MoreExperienceActivity/access$000(Lcom/nd/android/u/tast/experience/activity/MoreExperienceActivity;)Landroid/widget/ProgressBar;
ifnull L4
aload 0
getfield com/nd/android/u/tast/experience/activity/MoreExperienceActivity$2/this$0 Lcom/nd/android/u/tast/experience/activity/MoreExperienceActivity;
invokestatic com/nd/android/u/tast/experience/activity/MoreExperienceActivity/access$000(Lcom/nd/android/u/tast/experience/activity/MoreExperienceActivity;)Landroid/widget/ProgressBar;
bipush 8
invokevirtual android/widget/ProgressBar/setVisibility(I)V
L4:
aload 0
getfield com/nd/android/u/tast/experience/activity/MoreExperienceActivity$2/this$0 Lcom/nd/android/u/tast/experience/activity/MoreExperienceActivity;
invokestatic com/nd/android/u/tast/experience/activity/MoreExperienceActivity/access$100(Lcom/nd/android/u/tast/experience/activity/MoreExperienceActivity;)Landroid/widget/TextView;
iconst_0
invokevirtual android/widget/TextView/setVisibility(I)V
aload 0
getfield com/nd/android/u/tast/experience/activity/MoreExperienceActivity$2/this$0 Lcom/nd/android/u/tast/experience/activity/MoreExperienceActivity;
invokestatic com/nd/android/u/tast/experience/activity/MoreExperienceActivity/access$200(Lcom/nd/android/u/tast/experience/activity/MoreExperienceActivity;)Landroid/widget/ListView;
iconst_0
invokevirtual android/widget/ListView/setVisibility(I)V
return
L0:
aload 0
getfield com/nd/android/u/tast/experience/activity/MoreExperienceActivity$2/this$0 Lcom/nd/android/u/tast/experience/activity/MoreExperienceActivity;
invokestatic com/nd/android/u/tast/experience/activity/MoreExperienceActivity/access$000(Lcom/nd/android/u/tast/experience/activity/MoreExperienceActivity;)Landroid/widget/ProgressBar;
ifnull L5
aload 0
getfield com/nd/android/u/tast/experience/activity/MoreExperienceActivity$2/this$0 Lcom/nd/android/u/tast/experience/activity/MoreExperienceActivity;
invokestatic com/nd/android/u/tast/experience/activity/MoreExperienceActivity/access$000(Lcom/nd/android/u/tast/experience/activity/MoreExperienceActivity;)Landroid/widget/ProgressBar;
bipush 8
invokevirtual android/widget/ProgressBar/setVisibility(I)V
L5:
aload 0
getfield com/nd/android/u/tast/experience/activity/MoreExperienceActivity$2/this$0 Lcom/nd/android/u/tast/experience/activity/MoreExperienceActivity;
invokestatic com/nd/android/u/tast/experience/activity/MoreExperienceActivity/access$100(Lcom/nd/android/u/tast/experience/activity/MoreExperienceActivity;)Landroid/widget/TextView;
iconst_0
invokevirtual android/widget/TextView/setVisibility(I)V
aload 0
getfield com/nd/android/u/tast/experience/activity/MoreExperienceActivity$2/this$0 Lcom/nd/android/u/tast/experience/activity/MoreExperienceActivity;
invokestatic com/nd/android/u/tast/experience/activity/MoreExperienceActivity/access$100(Lcom/nd/android/u/tast/experience/activity/MoreExperienceActivity;)Landroid/widget/TextView;
getstatic com/nd/android/u/tasklib/R$string/common_get_data_error I
invokevirtual android/widget/TextView/setText(I)V
aload 0
getfield com/nd/android/u/tast/experience/activity/MoreExperienceActivity$2/this$0 Lcom/nd/android/u/tast/experience/activity/MoreExperienceActivity;
invokestatic com/nd/android/u/tast/experience/activity/MoreExperienceActivity/access$200(Lcom/nd/android/u/tast/experience/activity/MoreExperienceActivity;)Landroid/widget/ListView;
bipush 8
invokevirtual android/widget/ListView/setVisibility(I)V
return
L2:
aload 0
getfield com/nd/android/u/tast/experience/activity/MoreExperienceActivity$2/this$0 Lcom/nd/android/u/tast/experience/activity/MoreExperienceActivity;
invokestatic com/nd/android/u/tast/experience/activity/MoreExperienceActivity/access$000(Lcom/nd/android/u/tast/experience/activity/MoreExperienceActivity;)Landroid/widget/ProgressBar;
ifnull L6
aload 0
getfield com/nd/android/u/tast/experience/activity/MoreExperienceActivity$2/this$0 Lcom/nd/android/u/tast/experience/activity/MoreExperienceActivity;
invokestatic com/nd/android/u/tast/experience/activity/MoreExperienceActivity/access$000(Lcom/nd/android/u/tast/experience/activity/MoreExperienceActivity;)Landroid/widget/ProgressBar;
bipush 8
invokevirtual android/widget/ProgressBar/setVisibility(I)V
L6:
aload 0
getfield com/nd/android/u/tast/experience/activity/MoreExperienceActivity$2/this$0 Lcom/nd/android/u/tast/experience/activity/MoreExperienceActivity;
invokestatic com/nd/android/u/tast/experience/activity/MoreExperienceActivity/access$100(Lcom/nd/android/u/tast/experience/activity/MoreExperienceActivity;)Landroid/widget/TextView;
iconst_0
invokevirtual android/widget/TextView/setVisibility(I)V
aload 0
getfield com/nd/android/u/tast/experience/activity/MoreExperienceActivity$2/this$0 Lcom/nd/android/u/tast/experience/activity/MoreExperienceActivity;
invokestatic com/nd/android/u/tast/experience/activity/MoreExperienceActivity/access$100(Lcom/nd/android/u/tast/experience/activity/MoreExperienceActivity;)Landroid/widget/TextView;
getstatic com/nd/android/u/tasklib/R$string/score_more_exp_no_data I
invokevirtual android/widget/TextView/setText(I)V
aload 0
getfield com/nd/android/u/tast/experience/activity/MoreExperienceActivity$2/this$0 Lcom/nd/android/u/tast/experience/activity/MoreExperienceActivity;
invokestatic com/nd/android/u/tast/experience/activity/MoreExperienceActivity/access$200(Lcom/nd/android/u/tast/experience/activity/MoreExperienceActivity;)Landroid/widget/ListView;
bipush 8
invokevirtual android/widget/ListView/setVisibility(I)V
return
.limit locals 2
.limit stack 2
.end method
