.bytecode 50.0
.class synchronized com/nd/android/u/tast/experience/activity/ReceiveExperienceActivity$4
.super android/os/Handler
.enclosing method com/nd/android/u/tast/experience/activity/ReceiveExperienceActivity
.inner class inner com/nd/android/u/tast/experience/activity/ReceiveExperienceActivity$4

.field final synthetic 'this$0' Lcom/nd/android/u/tast/experience/activity/ReceiveExperienceActivity;

.method <init>(Lcom/nd/android/u/tast/experience/activity/ReceiveExperienceActivity;)V
aload 0
aload 1
putfield com/nd/android/u/tast/experience/activity/ReceiveExperienceActivity$4/this$0 Lcom/nd/android/u/tast/experience/activity/ReceiveExperienceActivity;
aload 0
invokespecial android/os/Handler/<init>()V
return
.limit locals 2
.limit stack 2
.end method

.method public handleMessage(Landroid/os/Message;)V
aload 1
getfield android/os/Message/what I
tableswitch -1
L0
L1
L2
default : L3
L3:
return
L1:
aload 0
getfield com/nd/android/u/tast/experience/activity/ReceiveExperienceActivity$4/this$0 Lcom/nd/android/u/tast/experience/activity/ReceiveExperienceActivity;
invokestatic com/nd/android/u/tast/experience/activity/ReceiveExperienceActivity/access$100(Lcom/nd/android/u/tast/experience/activity/ReceiveExperienceActivity;)Landroid/widget/ProgressBar;
ifnull L4
aload 0
getfield com/nd/android/u/tast/experience/activity/ReceiveExperienceActivity$4/this$0 Lcom/nd/android/u/tast/experience/activity/ReceiveExperienceActivity;
invokestatic com/nd/android/u/tast/experience/activity/ReceiveExperienceActivity/access$100(Lcom/nd/android/u/tast/experience/activity/ReceiveExperienceActivity;)Landroid/widget/ProgressBar;
bipush 8
invokevirtual android/widget/ProgressBar/setVisibility(I)V
L4:
aload 0
getfield com/nd/android/u/tast/experience/activity/ReceiveExperienceActivity$4/this$0 Lcom/nd/android/u/tast/experience/activity/ReceiveExperienceActivity;
invokestatic com/nd/android/u/tast/experience/activity/ReceiveExperienceActivity/access$200(Lcom/nd/android/u/tast/experience/activity/ReceiveExperienceActivity;)Landroid/widget/ListView;
iconst_0
invokevirtual android/widget/ListView/setVisibility(I)V
return
L0:
aload 0
getfield com/nd/android/u/tast/experience/activity/ReceiveExperienceActivity$4/this$0 Lcom/nd/android/u/tast/experience/activity/ReceiveExperienceActivity;
invokestatic com/nd/android/u/tast/experience/activity/ReceiveExperienceActivity/access$100(Lcom/nd/android/u/tast/experience/activity/ReceiveExperienceActivity;)Landroid/widget/ProgressBar;
ifnull L5
aload 0
getfield com/nd/android/u/tast/experience/activity/ReceiveExperienceActivity$4/this$0 Lcom/nd/android/u/tast/experience/activity/ReceiveExperienceActivity;
invokestatic com/nd/android/u/tast/experience/activity/ReceiveExperienceActivity/access$100(Lcom/nd/android/u/tast/experience/activity/ReceiveExperienceActivity;)Landroid/widget/ProgressBar;
bipush 8
invokevirtual android/widget/ProgressBar/setVisibility(I)V
L5:
aload 0
getfield com/nd/android/u/tast/experience/activity/ReceiveExperienceActivity$4/this$0 Lcom/nd/android/u/tast/experience/activity/ReceiveExperienceActivity;
invokestatic com/nd/android/u/tast/experience/activity/ReceiveExperienceActivity/access$200(Lcom/nd/android/u/tast/experience/activity/ReceiveExperienceActivity;)Landroid/widget/ListView;
bipush 8
invokevirtual android/widget/ListView/setVisibility(I)V
aload 0
getfield com/nd/android/u/tast/experience/activity/ReceiveExperienceActivity$4/this$0 Lcom/nd/android/u/tast/experience/activity/ReceiveExperienceActivity;
aload 0
getfield com/nd/android/u/tast/experience/activity/ReceiveExperienceActivity$4/this$0 Lcom/nd/android/u/tast/experience/activity/ReceiveExperienceActivity;
getstatic com/nd/android/u/tasklib/R$string/common_get_data_error I
invokevirtual com/nd/android/u/tast/experience/activity/ReceiveExperienceActivity/getString(I)Ljava/lang/String;
invokestatic com/common/android/utils/ToastUtils/displayTimeLong(Landroid/content/Context;Ljava/lang/String;)V
return
L2:
aload 0
getfield com/nd/android/u/tast/experience/activity/ReceiveExperienceActivity$4/this$0 Lcom/nd/android/u/tast/experience/activity/ReceiveExperienceActivity;
invokestatic com/nd/android/u/tast/experience/activity/ReceiveExperienceActivity/access$100(Lcom/nd/android/u/tast/experience/activity/ReceiveExperienceActivity;)Landroid/widget/ProgressBar;
ifnull L6
aload 0
getfield com/nd/android/u/tast/experience/activity/ReceiveExperienceActivity$4/this$0 Lcom/nd/android/u/tast/experience/activity/ReceiveExperienceActivity;
invokestatic com/nd/android/u/tast/experience/activity/ReceiveExperienceActivity/access$100(Lcom/nd/android/u/tast/experience/activity/ReceiveExperienceActivity;)Landroid/widget/ProgressBar;
bipush 8
invokevirtual android/widget/ProgressBar/setVisibility(I)V
L6:
aload 0
getfield com/nd/android/u/tast/experience/activity/ReceiveExperienceActivity$4/this$0 Lcom/nd/android/u/tast/experience/activity/ReceiveExperienceActivity;
invokestatic com/nd/android/u/tast/experience/activity/ReceiveExperienceActivity/access$200(Lcom/nd/android/u/tast/experience/activity/ReceiveExperienceActivity;)Landroid/widget/ListView;
bipush 8
invokevirtual android/widget/ListView/setVisibility(I)V
aload 0
getfield com/nd/android/u/tast/experience/activity/ReceiveExperienceActivity$4/this$0 Lcom/nd/android/u/tast/experience/activity/ReceiveExperienceActivity;
aload 0
getfield com/nd/android/u/tast/experience/activity/ReceiveExperienceActivity$4/this$0 Lcom/nd/android/u/tast/experience/activity/ReceiveExperienceActivity;
getstatic com/nd/android/u/tasklib/R$string/no_get_exp_data I
invokevirtual com/nd/android/u/tast/experience/activity/ReceiveExperienceActivity/getString(I)Ljava/lang/String;
invokestatic com/common/android/utils/ToastUtils/displayTimeLong(Landroid/content/Context;Ljava/lang/String;)V
return
.limit locals 2
.limit stack 3
.end method
