.bytecode 50.0
.class synchronized com/nd/android/u/tast/experience/activity/ReceiveExpActivity$GetTodayTask
.super android/os/AsyncTask
.signature "Landroid/os/AsyncTask<Ljava/lang/Void;Ljava/lang/Void;Lcom/nd/android/u/tast/experience/bean/MoreExperienceItem;>;"
.inner class private GetTodayTask inner com/nd/android/u/tast/experience/activity/ReceiveExpActivity$GetTodayTask outer com/nd/android/u/tast/experience/activity/ReceiveExpActivity

.field final synthetic 'this$0' Lcom/nd/android/u/tast/experience/activity/ReceiveExpActivity;

.method private <init>(Lcom/nd/android/u/tast/experience/activity/ReceiveExpActivity;)V
aload 0
aload 1
putfield com/nd/android/u/tast/experience/activity/ReceiveExpActivity$GetTodayTask/this$0 Lcom/nd/android/u/tast/experience/activity/ReceiveExpActivity;
aload 0
invokespecial android/os/AsyncTask/<init>()V
return
.limit locals 2
.limit stack 2
.end method

.method synthetic <init>(Lcom/nd/android/u/tast/experience/activity/ReceiveExpActivity;Lcom/nd/android/u/tast/experience/activity/ReceiveExpActivity$1;)V
aload 0
aload 1
invokespecial com/nd/android/u/tast/experience/activity/ReceiveExpActivity$GetTodayTask/<init>(Lcom/nd/android/u/tast/experience/activity/ReceiveExpActivity;)V
return
.limit locals 3
.limit stack 2
.end method

.method protected transient doInBackground([Ljava/lang/Void;)Lcom/nd/android/u/tast/experience/bean/MoreExperienceItem;
getstatic com/nd/android/u/tast/buss/TaskModelManager/INSTANCE Lcom/nd/android/u/tast/buss/TaskModelManager;
invokevirtual com/nd/android/u/tast/buss/TaskModelManager/getMyReceivedAward()Lcom/nd/android/u/tast/experience/bean/MoreExperienceItem;
areturn
.limit locals 2
.limit stack 1
.end method

.method protected volatile synthetic doInBackground([Ljava/lang/Object;)Ljava/lang/Object;
aload 0
aload 1
checkcast [Ljava/lang/Void;
invokevirtual com/nd/android/u/tast/experience/activity/ReceiveExpActivity$GetTodayTask/doInBackground([Ljava/lang/Void;)Lcom/nd/android/u/tast/experience/bean/MoreExperienceItem;
areturn
.limit locals 2
.limit stack 2
.end method

.method protected onPostExecute(Lcom/nd/android/u/tast/experience/bean/MoreExperienceItem;)V
aload 1
ifnull L0
aload 1
invokevirtual com/nd/android/u/tast/experience/bean/MoreExperienceItem/getExp()I
ifne L1
aload 1
invokevirtual com/nd/android/u/tast/experience/bean/MoreExperienceItem/getMoney()I
ifne L1
aload 1
invokevirtual com/nd/android/u/tast/experience/bean/MoreExperienceItem/getFlower()I
ifeq L2
L1:
aload 0
getfield com/nd/android/u/tast/experience/activity/ReceiveExpActivity$GetTodayTask/this$0 Lcom/nd/android/u/tast/experience/activity/ReceiveExpActivity;
getstatic com/nd/android/u/tasklib/R$id/layout_exp_tips I
invokevirtual com/nd/android/u/tast/experience/activity/ReceiveExpActivity/findViewById(I)Landroid/view/View;
iconst_0
invokevirtual android/view/View/setVisibility(I)V
L3:
aload 1
invokevirtual com/nd/android/u/tast/experience/bean/MoreExperienceItem/getExp()I
ifeq L4
aload 0
getfield com/nd/android/u/tast/experience/activity/ReceiveExpActivity$GetTodayTask/this$0 Lcom/nd/android/u/tast/experience/activity/ReceiveExpActivity;
invokestatic com/nd/android/u/tast/experience/activity/ReceiveExpActivity/access$700(Lcom/nd/android/u/tast/experience/activity/ReceiveExpActivity;)Landroid/widget/TextView;
aload 1
invokevirtual com/nd/android/u/tast/experience/bean/MoreExperienceItem/getExp()I
invokestatic java/lang/String/valueOf(I)Ljava/lang/String;
invokevirtual android/widget/TextView/setText(Ljava/lang/CharSequence;)V
aload 0
getfield com/nd/android/u/tast/experience/activity/ReceiveExpActivity$GetTodayTask/this$0 Lcom/nd/android/u/tast/experience/activity/ReceiveExpActivity;
invokestatic com/nd/android/u/tast/experience/activity/ReceiveExpActivity/access$800(Lcom/nd/android/u/tast/experience/activity/ReceiveExpActivity;)Landroid/widget/TextView;
iconst_0
invokevirtual android/widget/TextView/setVisibility(I)V
L5:
aload 1
invokevirtual com/nd/android/u/tast/experience/bean/MoreExperienceItem/getFlower()I
ifeq L6
aload 1
invokevirtual com/nd/android/u/tast/experience/bean/MoreExperienceItem/getExp()I
ifne L7
aload 0
getfield com/nd/android/u/tast/experience/activity/ReceiveExpActivity$GetTodayTask/this$0 Lcom/nd/android/u/tast/experience/activity/ReceiveExpActivity;
invokestatic com/nd/android/u/tast/experience/activity/ReceiveExpActivity/access$900(Lcom/nd/android/u/tast/experience/activity/ReceiveExpActivity;)Landroid/widget/TextView;
aload 1
invokevirtual com/nd/android/u/tast/experience/bean/MoreExperienceItem/getFlower()I
invokestatic java/lang/String/valueOf(I)Ljava/lang/String;
invokevirtual android/widget/TextView/setText(Ljava/lang/CharSequence;)V
L8:
aload 0
getfield com/nd/android/u/tast/experience/activity/ReceiveExpActivity$GetTodayTask/this$0 Lcom/nd/android/u/tast/experience/activity/ReceiveExpActivity;
invokestatic com/nd/android/u/tast/experience/activity/ReceiveExpActivity/access$900(Lcom/nd/android/u/tast/experience/activity/ReceiveExpActivity;)Landroid/widget/TextView;
new java/lang/StringBuilder
dup
invokespecial java/lang/StringBuilder/<init>()V
ldc ", "
invokevirtual java/lang/StringBuilder/append(Ljava/lang/String;)Ljava/lang/StringBuilder;
aload 1
invokevirtual com/nd/android/u/tast/experience/bean/MoreExperienceItem/getFlower()I
invokestatic java/lang/String/valueOf(I)Ljava/lang/String;
invokevirtual java/lang/StringBuilder/append(Ljava/lang/String;)Ljava/lang/StringBuilder;
invokevirtual java/lang/StringBuilder/toString()Ljava/lang/String;
invokevirtual android/widget/TextView/setText(Ljava/lang/CharSequence;)V
aload 0
getfield com/nd/android/u/tast/experience/activity/ReceiveExpActivity$GetTodayTask/this$0 Lcom/nd/android/u/tast/experience/activity/ReceiveExpActivity;
invokestatic com/nd/android/u/tast/experience/activity/ReceiveExpActivity/access$1000(Lcom/nd/android/u/tast/experience/activity/ReceiveExpActivity;)Landroid/widget/TextView;
iconst_0
invokevirtual android/widget/TextView/setVisibility(I)V
L0:
return
L2:
aload 0
getfield com/nd/android/u/tast/experience/activity/ReceiveExpActivity$GetTodayTask/this$0 Lcom/nd/android/u/tast/experience/activity/ReceiveExpActivity;
getstatic com/nd/android/u/tasklib/R$id/layout_exp_tips I
invokevirtual com/nd/android/u/tast/experience/activity/ReceiveExpActivity/findViewById(I)Landroid/view/View;
iconst_4
invokevirtual android/view/View/setVisibility(I)V
goto L3
L4:
aload 0
getfield com/nd/android/u/tast/experience/activity/ReceiveExpActivity$GetTodayTask/this$0 Lcom/nd/android/u/tast/experience/activity/ReceiveExpActivity;
invokestatic com/nd/android/u/tast/experience/activity/ReceiveExpActivity/access$800(Lcom/nd/android/u/tast/experience/activity/ReceiveExpActivity;)Landroid/widget/TextView;
bipush 8
invokevirtual android/widget/TextView/setVisibility(I)V
goto L5
L7:
aload 0
getfield com/nd/android/u/tast/experience/activity/ReceiveExpActivity$GetTodayTask/this$0 Lcom/nd/android/u/tast/experience/activity/ReceiveExpActivity;
invokestatic com/nd/android/u/tast/experience/activity/ReceiveExpActivity/access$900(Lcom/nd/android/u/tast/experience/activity/ReceiveExpActivity;)Landroid/widget/TextView;
new java/lang/StringBuilder
dup
invokespecial java/lang/StringBuilder/<init>()V
ldc ", "
invokevirtual java/lang/StringBuilder/append(Ljava/lang/String;)Ljava/lang/StringBuilder;
aload 1
invokevirtual com/nd/android/u/tast/experience/bean/MoreExperienceItem/getFlower()I
invokestatic java/lang/String/valueOf(I)Ljava/lang/String;
invokevirtual java/lang/StringBuilder/append(Ljava/lang/String;)Ljava/lang/StringBuilder;
invokevirtual java/lang/StringBuilder/toString()Ljava/lang/String;
invokevirtual android/widget/TextView/setText(Ljava/lang/CharSequence;)V
goto L8
L6:
aload 0
getfield com/nd/android/u/tast/experience/activity/ReceiveExpActivity$GetTodayTask/this$0 Lcom/nd/android/u/tast/experience/activity/ReceiveExpActivity;
invokestatic com/nd/android/u/tast/experience/activity/ReceiveExpActivity/access$1000(Lcom/nd/android/u/tast/experience/activity/ReceiveExpActivity;)Landroid/widget/TextView;
bipush 8
invokevirtual android/widget/TextView/setVisibility(I)V
return
.limit locals 2
.limit stack 3
.end method

.method protected volatile synthetic onPostExecute(Ljava/lang/Object;)V
aload 0
aload 1
checkcast com/nd/android/u/tast/experience/bean/MoreExperienceItem
invokevirtual com/nd/android/u/tast/experience/activity/ReceiveExpActivity$GetTodayTask/onPostExecute(Lcom/nd/android/u/tast/experience/bean/MoreExperienceItem;)V
return
.limit locals 2
.limit stack 2
.end method
