.bytecode 50.0
.class final synchronized com/nd/android/u/tast/experience/activity/ReceiveExpActivity$1
.super java/lang/Object
.implements java/lang/Runnable
.enclosing method com/nd/android/u/tast/experience/activity/ReceiveExpActivity/initReceiveExperience(Landroid/app/Activity;Landroid/widget/ListView;Lcom/nd/android/u/tast/experience/adapter/ReceiveExpAdapter;Landroid/os/Handler;)V
.inner class static final inner com/nd/android/u/tast/experience/activity/ReceiveExpActivity$1
.inner class inner com/nd/android/u/tast/experience/activity/ReceiveExpActivity$1$1

.field final synthetic 'val$activity' Landroid/app/Activity;

.field final synthetic 'val$adapter' Lcom/nd/android/u/tast/experience/adapter/ReceiveExpAdapter;

.field final synthetic 'val$hd' Landroid/os/Handler;

.field final synthetic 'val$lv' Landroid/widget/ListView;

.method <init>(Landroid/os/Handler;Landroid/app/Activity;Lcom/nd/android/u/tast/experience/adapter/ReceiveExpAdapter;Landroid/widget/ListView;)V
aload 0
aload 1
putfield com/nd/android/u/tast/experience/activity/ReceiveExpActivity$1/val$hd Landroid/os/Handler;
aload 0
aload 2
putfield com/nd/android/u/tast/experience/activity/ReceiveExpActivity$1/val$activity Landroid/app/Activity;
aload 0
aload 3
putfield com/nd/android/u/tast/experience/activity/ReceiveExpActivity$1/val$adapter Lcom/nd/android/u/tast/experience/adapter/ReceiveExpAdapter;
aload 0
aload 4
putfield com/nd/android/u/tast/experience/activity/ReceiveExpActivity$1/val$lv Landroid/widget/ListView;
aload 0
invokespecial java/lang/Object/<init>()V
return
.limit locals 5
.limit stack 2
.end method

.method public run()V
.catch com/common/android/utils/http/HttpAuthException from L0 to L1 using L2
.catch com/common/android/utils/http/ResponseException from L0 to L1 using L3
.catch com/common/android/utils/http/HttpServerException from L0 to L1 using L4
.catch com/common/android/utils/http/HttpException from L0 to L1 using L5
.catch org/json/JSONException from L6 to L7 using L8
.catch org/json/JSONException from L9 to L10 using L8
.catch org/json/JSONException from L11 to L12 using L8
.catch org/json/JSONException from L13 to L14 using L8
.catch org/json/JSONException from L15 to L16 using L8
.catch org/json/JSONException from L16 to L17 using L8
.catch org/json/JSONException from L18 to L19 using L8
new com/nd/android/u/tast/com/AjaxCom
dup
invokespecial com/nd/android/u/tast/com/AjaxCom/<init>()V
astore 5
aconst_null
astore 4
L0:
aload 5
invokevirtual com/nd/android/u/tast/com/AjaxCom/getActionlist()Lorg/json/JSONObject;
astore 5
L1:
aload 5
astore 4
L20:
aload 4
ifnonnull L21
aload 0
getfield com/nd/android/u/tast/experience/activity/ReceiveExpActivity$1/val$hd Landroid/os/Handler;
ifnull L22
aload 0
getfield com/nd/android/u/tast/experience/activity/ReceiveExpActivity$1/val$hd Landroid/os/Handler;
iconst_m1
invokevirtual android/os/Handler/sendEmptyMessage(I)Z
pop
L22:
return
L2:
astore 5
aload 5
invokevirtual com/common/android/utils/http/HttpAuthException/printStackTrace()V
goto L20
L3:
astore 5
aload 5
invokevirtual com/common/android/utils/http/ResponseException/printStackTrace()V
goto L20
L4:
astore 5
aload 5
invokevirtual com/common/android/utils/http/HttpServerException/printStackTrace()V
goto L20
L5:
astore 5
aload 5
invokevirtual com/common/android/utils/http/HttpException/printStackTrace()V
goto L20
L21:
new java/util/ArrayList
dup
invokespecial java/util/ArrayList/<init>()V
astore 5
L6:
aload 4
ldc "code"
invokevirtual org/json/JSONObject/getInt(Ljava/lang/String;)I
sipush 200
if_icmpeq L9
aload 0
getfield com/nd/android/u/tast/experience/activity/ReceiveExpActivity$1/val$hd Landroid/os/Handler;
ifnull L22
aload 0
getfield com/nd/android/u/tast/experience/activity/ReceiveExpActivity$1/val$hd Landroid/os/Handler;
iconst_m1
invokevirtual android/os/Handler/sendEmptyMessage(I)Z
pop
L7:
return
L8:
astore 4
ldc "ReceiveExperienceActivity"
aload 4
invokevirtual org/json/JSONException/getMessage()Ljava/lang/String;
invokestatic android/util/Log/e(Ljava/lang/String;Ljava/lang/String;)I
pop
L23:
aload 5
invokeinterface java/util/List/isEmpty()Z 0
ifne L22
aload 0
getfield com/nd/android/u/tast/experience/activity/ReceiveExpActivity$1/val$activity Landroid/app/Activity;
new com/nd/android/u/tast/experience/activity/ReceiveExpActivity$1$1
dup
aload 0
aload 5
invokespecial com/nd/android/u/tast/experience/activity/ReceiveExpActivity$1$1/<init>(Lcom/nd/android/u/tast/experience/activity/ReceiveExpActivity$1;Ljava/util/List;)V
invokevirtual android/app/Activity/runOnUiThread(Ljava/lang/Runnable;)V
return
L9:
aload 4
ldc "action"
invokevirtual org/json/JSONObject/optJSONArray(Ljava/lang/String;)Lorg/json/JSONArray;
astore 4
aload 4
invokevirtual org/json/JSONArray/length()I
istore 2
L10:
iload 2
ifne L24
L11:
aload 0
getfield com/nd/android/u/tast/experience/activity/ReceiveExpActivity$1/val$hd Landroid/os/Handler;
ifnull L22
aload 0
getfield com/nd/android/u/tast/experience/activity/ReceiveExpActivity$1/val$hd Landroid/os/Handler;
iconst_1
invokevirtual android/os/Handler/sendEmptyMessage(I)Z
pop
L12:
return
L25:
iload 1
iload 2
if_icmpge L23
L13:
aload 4
iload 1
invokevirtual org/json/JSONArray/optJSONObject(I)Lorg/json/JSONObject;
astore 6
new com/nd/android/u/tast/experience/adapter/ReceiveExpAdapter$ReceiveExperienceItem
dup
invokespecial com/nd/android/u/tast/experience/adapter/ReceiveExpAdapter$ReceiveExperienceItem/<init>()V
astore 7
aload 7
aload 6
ldc "itemcode"
invokevirtual org/json/JSONObject/optString(Ljava/lang/String;)Ljava/lang/String;
putfield com/nd/android/u/tast/experience/adapter/ReceiveExpAdapter$ReceiveExperienceItem/mItemCode Ljava/lang/String;
aload 7
aload 6
ldc "itemname"
invokevirtual org/json/JSONObject/optString(Ljava/lang/String;)Ljava/lang/String;
putfield com/nd/android/u/tast/experience/adapter/ReceiveExpAdapter$ReceiveExperienceItem/mItemName Ljava/lang/String;
aload 7
aload 6
ldc "exp"
invokevirtual org/json/JSONObject/optInt(Ljava/lang/String;)I
putfield com/nd/android/u/tast/experience/adapter/ReceiveExpAdapter$ReceiveExperienceItem/mExp I
aload 7
aload 6
ldc "money"
invokevirtual org/json/JSONObject/optInt(Ljava/lang/String;)I
putfield com/nd/android/u/tast/experience/adapter/ReceiveExpAdapter$ReceiveExperienceItem/mMoney I
aload 7
aload 6
ldc "actionid"
invokevirtual org/json/JSONObject/optInt(Ljava/lang/String;)I
putfield com/nd/android/u/tast/experience/adapter/ReceiveExpAdapter$ReceiveExperienceItem/mActionId I
aload 6
ldc "status"
invokevirtual org/json/JSONObject/optInt(Ljava/lang/String;)I
istore 3
L14:
iload 3
ifne L26
L15:
aload 7
getstatic com/nd/android/u/tast/experience/adapter/ReceiveExpAdapter$RECEIVE_EXP_STATUS/NOT_RECEIVED Lcom/nd/android/u/tast/experience/adapter/ReceiveExpAdapter$RECEIVE_EXP_STATUS;
putfield com/nd/android/u/tast/experience/adapter/ReceiveExpAdapter$ReceiveExperienceItem/mStatus Lcom/nd/android/u/tast/experience/adapter/ReceiveExpAdapter$RECEIVE_EXP_STATUS;
L16:
aload 5
aload 7
invokeinterface java/util/List/add(Ljava/lang/Object;)Z 1
pop
L17:
iload 1
iconst_1
iadd
istore 1
goto L25
L26:
iload 3
iconst_1
if_icmpne L16
L18:
aload 7
getstatic com/nd/android/u/tast/experience/adapter/ReceiveExpAdapter$RECEIVE_EXP_STATUS/RECEIVED Lcom/nd/android/u/tast/experience/adapter/ReceiveExpAdapter$RECEIVE_EXP_STATUS;
putfield com/nd/android/u/tast/experience/adapter/ReceiveExpAdapter$ReceiveExperienceItem/mStatus Lcom/nd/android/u/tast/experience/adapter/ReceiveExpAdapter$RECEIVE_EXP_STATUS;
L19:
goto L16
L24:
iconst_0
istore 1
goto L25
.limit locals 8
.limit stack 5
.end method
