.bytecode 50.0
.class synchronized com/nd/android/u/tast/experience/activity/TaskWebViewActivity$3
.super android/webkit/WebChromeClient
.enclosing method com/nd/android/u/tast/experience/activity/TaskWebViewActivity/initWebViewComponent()V
.inner class inner com/nd/android/u/tast/experience/activity/TaskWebViewActivity$3

.field final synthetic 'this$0' Lcom/nd/android/u/tast/experience/activity/TaskWebViewActivity;

.method <init>(Lcom/nd/android/u/tast/experience/activity/TaskWebViewActivity;)V
aload 0
aload 1
putfield com/nd/android/u/tast/experience/activity/TaskWebViewActivity$3/this$0 Lcom/nd/android/u/tast/experience/activity/TaskWebViewActivity;
aload 0
invokespecial android/webkit/WebChromeClient/<init>()V
return
.limit locals 2
.limit stack 2
.end method

.method public onProgressChanged(Landroid/webkit/WebView;I)V
aload 0
aload 1
iload 2
invokespecial android/webkit/WebChromeClient/onProgressChanged(Landroid/webkit/WebView;I)V
iload 2
bipush 100
if_icmpne L0
aload 0
getfield com/nd/android/u/tast/experience/activity/TaskWebViewActivity$3/this$0 Lcom/nd/android/u/tast/experience/activity/TaskWebViewActivity;
getfield com/nd/android/u/tast/experience/activity/TaskWebViewActivity/handler Landroid/os/Handler;
iconst_1
invokevirtual android/os/Handler/sendEmptyMessage(I)Z
pop
L0:
return
.limit locals 3
.limit stack 3
.end method

.method public onReceivedTitle(Landroid/webkit/WebView;Ljava/lang/String;)V
aload 0
aload 1
aload 2
invokespecial android/webkit/WebChromeClient/onReceivedTitle(Landroid/webkit/WebView;Ljava/lang/String;)V
aload 0
getfield com/nd/android/u/tast/experience/activity/TaskWebViewActivity$3/this$0 Lcom/nd/android/u/tast/experience/activity/TaskWebViewActivity;
invokestatic com/nd/android/u/tast/experience/activity/TaskWebViewActivity/access$400(Lcom/nd/android/u/tast/experience/activity/TaskWebViewActivity;)Ljava/lang/String;
ifnull L0
aload 0
getfield com/nd/android/u/tast/experience/activity/TaskWebViewActivity$3/this$0 Lcom/nd/android/u/tast/experience/activity/TaskWebViewActivity;
invokestatic com/nd/android/u/tast/experience/activity/TaskWebViewActivity/access$400(Lcom/nd/android/u/tast/experience/activity/TaskWebViewActivity;)Ljava/lang/String;
invokevirtual java/lang/String/length()I
ifle L0
aload 0
getfield com/nd/android/u/tast/experience/activity/TaskWebViewActivity$3/this$0 Lcom/nd/android/u/tast/experience/activity/TaskWebViewActivity;
invokestatic com/nd/android/u/tast/experience/activity/TaskWebViewActivity/access$500(Lcom/nd/android/u/tast/experience/activity/TaskWebViewActivity;)Landroid/widget/TextView;
aload 0
getfield com/nd/android/u/tast/experience/activity/TaskWebViewActivity$3/this$0 Lcom/nd/android/u/tast/experience/activity/TaskWebViewActivity;
invokestatic com/nd/android/u/tast/experience/activity/TaskWebViewActivity/access$400(Lcom/nd/android/u/tast/experience/activity/TaskWebViewActivity;)Ljava/lang/String;
invokevirtual android/widget/TextView/setText(Ljava/lang/CharSequence;)V
return
L0:
aload 0
getfield com/nd/android/u/tast/experience/activity/TaskWebViewActivity$3/this$0 Lcom/nd/android/u/tast/experience/activity/TaskWebViewActivity;
invokestatic com/nd/android/u/tast/experience/activity/TaskWebViewActivity/access$500(Lcom/nd/android/u/tast/experience/activity/TaskWebViewActivity;)Landroid/widget/TextView;
aload 2
invokevirtual android/widget/TextView/setText(Ljava/lang/CharSequence;)V
return
.limit locals 3
.limit stack 3
.end method
