.bytecode 50.0
.class synchronized com/nd/android/u/tast/experience/activity/TaskWebViewActivity$7
.super java/lang/Object
.implements com/common/android/utils/download/ProgressDownloadManager$onDonwloadListener
.enclosing method com/nd/android/u/tast/experience/activity/TaskWebViewActivity
.inner class inner com/nd/android/u/tast/experience/activity/TaskWebViewActivity$7

.field final synthetic 'this$0' Lcom/nd/android/u/tast/experience/activity/TaskWebViewActivity;

.method <init>(Lcom/nd/android/u/tast/experience/activity/TaskWebViewActivity;)V
aload 0
aload 1
putfield com/nd/android/u/tast/experience/activity/TaskWebViewActivity$7/this$0 Lcom/nd/android/u/tast/experience/activity/TaskWebViewActivity;
aload 0
invokespecial java/lang/Object/<init>()V
return
.limit locals 2
.limit stack 2
.end method

.method public onFail(ILjava/lang/String;)V
.catch java/lang/Exception from L0 to L1 using L2
iload 1
ifle L3
L0:
iload 1
invokestatic com/common/android/utils/ToastUtils/display(I)V
L1:
aload 0
getfield com/nd/android/u/tast/experience/activity/TaskWebViewActivity$7/this$0 Lcom/nd/android/u/tast/experience/activity/TaskWebViewActivity;
aload 2
invokestatic com/common/android/utils/ToastUtils/display(Landroid/content/Context;Ljava/lang/String;)V
return
L2:
astore 3
ldc "TaskWebViewActivity"
aload 3
invokevirtual java/lang/Exception/getMessage()Ljava/lang/String;
invokestatic android/util/Log/e(Ljava/lang/String;Ljava/lang/String;)I
pop
goto L1
L3:
aload 2
invokestatic com/common/android/utils/ToastUtils/display(Ljava/lang/String;)V
goto L1
.limit locals 4
.limit stack 2
.end method

.method public onProgress(JJ)V
return
.limit locals 5
.limit stack 0
.end method

.method public onSuccess(Ljava/io/File;)V
.catch java/lang/IllegalArgumentException from L0 to L1 using L2
.catch java/lang/IllegalStateException from L0 to L1 using L3
.catch java/io/IOException from L0 to L1 using L4
L0:
aload 0
getfield com/nd/android/u/tast/experience/activity/TaskWebViewActivity$7/this$0 Lcom/nd/android/u/tast/experience/activity/TaskWebViewActivity;
invokestatic com/nd/android/u/tast/experience/activity/TaskWebViewActivity/access$900(Lcom/nd/android/u/tast/experience/activity/TaskWebViewActivity;)Lcom/common/android/utils/audio/AudioAnimManager;
aload 1
invokevirtual com/common/android/utils/audio/AudioAnimManager/playAudio(Ljava/io/File;)V
L1:
return
L2:
astore 1
aload 1
invokevirtual java/lang/IllegalArgumentException/printStackTrace()V
return
L3:
astore 1
aload 1
invokevirtual java/lang/IllegalStateException/printStackTrace()V
return
L4:
astore 1
aload 1
invokevirtual java/io/IOException/printStackTrace()V
return
.limit locals 2
.limit stack 2
.end method
