.bytecode 50.0
.class synchronized com/nd/android/u/tast/experience/activity/TaskWebViewActivity$1
.super android/os/Handler
.enclosing method com/nd/android/u/tast/experience/activity/TaskWebViewActivity
.inner class inner com/nd/android/u/tast/experience/activity/TaskWebViewActivity$1

.field final synthetic 'this$0' Lcom/nd/android/u/tast/experience/activity/TaskWebViewActivity;

.method <init>(Lcom/nd/android/u/tast/experience/activity/TaskWebViewActivity;)V
aload 0
aload 1
putfield com/nd/android/u/tast/experience/activity/TaskWebViewActivity$1/this$0 Lcom/nd/android/u/tast/experience/activity/TaskWebViewActivity;
aload 0
invokespecial android/os/Handler/<init>()V
return
.limit locals 2
.limit stack 2
.end method

.method public handleMessage(Landroid/os/Message;)V
invokestatic java/lang/Thread/currentThread()Ljava/lang/Thread;
invokevirtual java/lang/Thread/isInterrupted()Z
ifne L0
aload 1
getfield android/os/Message/what I
tableswitch 0
L1
L2
default : L0
L0:
aload 0
aload 1
invokespecial android/os/Handler/handleMessage(Landroid/os/Message;)V
return
L1:
aload 0
getfield com/nd/android/u/tast/experience/activity/TaskWebViewActivity$1/this$0 Lcom/nd/android/u/tast/experience/activity/TaskWebViewActivity;
invokestatic com/nd/android/u/tast/experience/activity/TaskWebViewActivity/access$000(Lcom/nd/android/u/tast/experience/activity/TaskWebViewActivity;)Landroid/widget/ProgressBar;
iconst_0
invokevirtual android/widget/ProgressBar/setVisibility(I)V
aload 0
getfield com/nd/android/u/tast/experience/activity/TaskWebViewActivity$1/this$0 Lcom/nd/android/u/tast/experience/activity/TaskWebViewActivity;
invokestatic com/nd/android/u/tast/experience/activity/TaskWebViewActivity/access$100(Lcom/nd/android/u/tast/experience/activity/TaskWebViewActivity;)Landroid/widget/ImageView;
bipush 8
invokevirtual android/widget/ImageView/setVisibility(I)V
goto L0
L2:
aload 0
getfield com/nd/android/u/tast/experience/activity/TaskWebViewActivity$1/this$0 Lcom/nd/android/u/tast/experience/activity/TaskWebViewActivity;
invokestatic com/nd/android/u/tast/experience/activity/TaskWebViewActivity/access$200(Lcom/nd/android/u/tast/experience/activity/TaskWebViewActivity;)V
aload 0
getfield com/nd/android/u/tast/experience/activity/TaskWebViewActivity$1/this$0 Lcom/nd/android/u/tast/experience/activity/TaskWebViewActivity;
invokestatic com/nd/android/u/tast/experience/activity/TaskWebViewActivity/access$000(Lcom/nd/android/u/tast/experience/activity/TaskWebViewActivity;)Landroid/widget/ProgressBar;
bipush 8
invokevirtual android/widget/ProgressBar/setVisibility(I)V
aload 0
getfield com/nd/android/u/tast/experience/activity/TaskWebViewActivity$1/this$0 Lcom/nd/android/u/tast/experience/activity/TaskWebViewActivity;
invokestatic com/nd/android/u/tast/experience/activity/TaskWebViewActivity/access$100(Lcom/nd/android/u/tast/experience/activity/TaskWebViewActivity;)Landroid/widget/ImageView;
iconst_0
invokevirtual android/widget/ImageView/setVisibility(I)V
goto L0
.limit locals 2
.limit stack 2
.end method
