.bytecode 50.0
.class synchronized com/nd/rj/common/microblogging/SNSAuthorized$2
.super android/os/Handler
.enclosing method com/nd/rj/common/microblogging/SNSAuthorized
.inner class inner com/nd/rj/common/microblogging/SNSAuthorized$2

.field final synthetic 'this$0' Lcom/nd/rj/common/microblogging/SNSAuthorized;

.method <init>(Lcom/nd/rj/common/microblogging/SNSAuthorized;)V
aload 0
aload 1
putfield com/nd/rj/common/microblogging/SNSAuthorized$2/this$0 Lcom/nd/rj/common/microblogging/SNSAuthorized;
aload 0
invokespecial android/os/Handler/<init>()V
return
.limit locals 2
.limit stack 2
.end method

.method public handleMessage(Landroid/os/Message;)V
aload 1
getfield android/os/Message/what I
tableswitch 0
L0
L1
L2
L3
L4
L5
L6
default : L7
L7:
return
L0:
aload 0
getfield com/nd/rj/common/microblogging/SNSAuthorized$2/this$0 Lcom/nd/rj/common/microblogging/SNSAuthorized;
invokestatic com/nd/rj/common/microblogging/SNSAuthorized/access$300(Lcom/nd/rj/common/microblogging/SNSAuthorized;)Landroid/webkit/WebView;
aload 0
getfield com/nd/rj/common/microblogging/SNSAuthorized$2/this$0 Lcom/nd/rj/common/microblogging/SNSAuthorized;
invokestatic com/nd/rj/common/microblogging/SNSAuthorized/access$200(Lcom/nd/rj/common/microblogging/SNSAuthorized;)Ljava/lang/String;
invokevirtual android/webkit/WebView/loadUrl(Ljava/lang/String;)V
return
L1:
aload 0
getfield com/nd/rj/common/microblogging/SNSAuthorized$2/this$0 Lcom/nd/rj/common/microblogging/SNSAuthorized;
getstatic com/nd/rj/common/R$id/mesgTipId I
invokevirtual com/nd/rj/common/microblogging/SNSAuthorized/findViewById(I)Landroid/view/View;
bipush 8
invokevirtual android/view/View/setVisibility(I)V
aload 0
getfield com/nd/rj/common/microblogging/SNSAuthorized$2/this$0 Lcom/nd/rj/common/microblogging/SNSAuthorized;
invokestatic com/nd/rj/common/microblogging/SNSAuthorized/access$300(Lcom/nd/rj/common/microblogging/SNSAuthorized;)Landroid/webkit/WebView;
iconst_0
invokevirtual android/webkit/WebView/setVisibility(I)V
aload 0
getfield com/nd/rj/common/microblogging/SNSAuthorized$2/this$0 Lcom/nd/rj/common/microblogging/SNSAuthorized;
invokestatic com/nd/rj/common/microblogging/SNSAuthorized/access$300(Lcom/nd/rj/common/microblogging/SNSAuthorized;)Landroid/webkit/WebView;
invokevirtual android/webkit/WebView/requestFocus()Z
pop
return
L2:
aload 0
getfield com/nd/rj/common/microblogging/SNSAuthorized$2/this$0 Lcom/nd/rj/common/microblogging/SNSAuthorized;
getstatic com/nd/rj/common/R$id/progress_largeId I
invokevirtual com/nd/rj/common/microblogging/SNSAuthorized/findViewById(I)Landroid/view/View;
bipush 8
invokevirtual android/view/View/setVisibility(I)V
aload 0
getfield com/nd/rj/common/microblogging/SNSAuthorized$2/this$0 Lcom/nd/rj/common/microblogging/SNSAuthorized;
invokestatic com/nd/rj/common/microblogging/SNSAuthorized/access$500(Lcom/nd/rj/common/microblogging/SNSAuthorized;)Landroid/widget/TextView;
aload 0
getfield com/nd/rj/common/microblogging/SNSAuthorized$2/this$0 Lcom/nd/rj/common/microblogging/SNSAuthorized;
getstatic com/nd/rj/common/R$string/sns_setauth I
invokevirtual com/nd/rj/common/microblogging/SNSAuthorized/getString(I)Ljava/lang/String;
iconst_1
anewarray java/lang/Object
dup
iconst_0
aload 0
getfield com/nd/rj/common/microblogging/SNSAuthorized$2/this$0 Lcom/nd/rj/common/microblogging/SNSAuthorized;
invokestatic com/nd/rj/common/microblogging/SNSAuthorized/access$400(Lcom/nd/rj/common/microblogging/SNSAuthorized;)Ljava/lang/String;
aastore
invokestatic java/lang/String/format(Ljava/lang/String;[Ljava/lang/Object;)Ljava/lang/String;
invokevirtual android/widget/TextView/setText(Ljava/lang/CharSequence;)V
aload 0
getfield com/nd/rj/common/microblogging/SNSAuthorized$2/this$0 Lcom/nd/rj/common/microblogging/SNSAuthorized;
invokestatic com/nd/rj/common/microblogging/SNSAuthorized/access$600(Lcom/nd/rj/common/microblogging/SNSAuthorized;)Lcom/nd/rj/common/microblogging/help/ConfigSet;
iconst_1
invokevirtual com/nd/rj/common/microblogging/help/ConfigSet/saveBindState(Z)V
aload 0
getfield com/nd/rj/common/microblogging/SNSAuthorized$2/this$0 Lcom/nd/rj/common/microblogging/SNSAuthorized;
invokestatic com/nd/rj/common/microblogging/SNSAuthorized/access$900(Lcom/nd/rj/common/microblogging/SNSAuthorized;)Landroid/widget/CheckBox;
aload 0
getfield com/nd/rj/common/microblogging/SNSAuthorized$2/this$0 Lcom/nd/rj/common/microblogging/SNSAuthorized;
invokestatic com/nd/rj/common/microblogging/SNSAuthorized/access$800(Lcom/nd/rj/common/microblogging/SNSAuthorized;)Lcom/nd/rj/common/microblogging/SNSModleMgr;
aload 0
getfield com/nd/rj/common/microblogging/SNSAuthorized$2/this$0 Lcom/nd/rj/common/microblogging/SNSAuthorized;
invokestatic com/nd/rj/common/microblogging/SNSAuthorized/access$700(Lcom/nd/rj/common/microblogging/SNSAuthorized;)I
invokevirtual com/nd/rj/common/microblogging/SNSModleMgr/checkFollow(I)Z
invokevirtual android/widget/CheckBox/setChecked(Z)V
return
L3:
aload 0
getfield com/nd/rj/common/microblogging/SNSAuthorized$2/this$0 Lcom/nd/rj/common/microblogging/SNSAuthorized;
invokestatic com/nd/rj/common/microblogging/SNSAuthorized/access$600(Lcom/nd/rj/common/microblogging/SNSAuthorized;)Lcom/nd/rj/common/microblogging/help/ConfigSet;
iconst_1
invokevirtual com/nd/rj/common/microblogging/help/ConfigSet/saveBindState(Z)V
aload 0
getfield com/nd/rj/common/microblogging/SNSAuthorized$2/this$0 Lcom/nd/rj/common/microblogging/SNSAuthorized;
invokevirtual com/nd/rj/common/microblogging/SNSAuthorized/ProcessFollow()V
aload 0
getfield com/nd/rj/common/microblogging/SNSAuthorized$2/this$0 Lcom/nd/rj/common/microblogging/SNSAuthorized;
invokestatic com/nd/rj/common/microblogging/SNSAuthorized/access$800(Lcom/nd/rj/common/microblogging/SNSAuthorized;)Lcom/nd/rj/common/microblogging/SNSModleMgr;
aload 0
getfield com/nd/rj/common/microblogging/SNSAuthorized$2/this$0 Lcom/nd/rj/common/microblogging/SNSAuthorized;
invokestatic com/nd/rj/common/microblogging/SNSAuthorized/access$700(Lcom/nd/rj/common/microblogging/SNSAuthorized;)I
invokevirtual com/nd/rj/common/microblogging/SNSModleMgr/querybind(I)I
pop
aload 0
getfield com/nd/rj/common/microblogging/SNSAuthorized$2/this$0 Lcom/nd/rj/common/microblogging/SNSAuthorized;
iconst_m1
invokevirtual com/nd/rj/common/microblogging/SNSAuthorized/setResult(I)V
aload 0
getfield com/nd/rj/common/microblogging/SNSAuthorized$2/this$0 Lcom/nd/rj/common/microblogging/SNSAuthorized;
invokevirtual com/nd/rj/common/microblogging/SNSAuthorized/finish()V
return
L4:
aload 0
getfield com/nd/rj/common/microblogging/SNSAuthorized$2/this$0 Lcom/nd/rj/common/microblogging/SNSAuthorized;
getstatic com/nd/rj/common/R$id/progress_largeId I
invokevirtual com/nd/rj/common/microblogging/SNSAuthorized/findViewById(I)Landroid/view/View;
bipush 8
invokevirtual android/view/View/setVisibility(I)V
aload 0
getfield com/nd/rj/common/microblogging/SNSAuthorized$2/this$0 Lcom/nd/rj/common/microblogging/SNSAuthorized;
invokestatic com/nd/rj/common/microblogging/SNSAuthorized/access$500(Lcom/nd/rj/common/microblogging/SNSAuthorized;)Landroid/widget/TextView;
aload 0
getfield com/nd/rj/common/microblogging/SNSAuthorized$2/this$0 Lcom/nd/rj/common/microblogging/SNSAuthorized;
getstatic com/nd/rj/common/R$string/sns_setauthfail I
invokevirtual com/nd/rj/common/microblogging/SNSAuthorized/getString(I)Ljava/lang/String;
iconst_1
anewarray java/lang/Object
dup
iconst_0
aload 0
getfield com/nd/rj/common/microblogging/SNSAuthorized$2/this$0 Lcom/nd/rj/common/microblogging/SNSAuthorized;
invokestatic com/nd/rj/common/microblogging/SNSAuthorized/access$400(Lcom/nd/rj/common/microblogging/SNSAuthorized;)Ljava/lang/String;
aastore
invokestatic java/lang/String/format(Ljava/lang/String;[Ljava/lang/Object;)Ljava/lang/String;
invokevirtual android/widget/TextView/setText(Ljava/lang/CharSequence;)V
return
L5:
aload 0
getfield com/nd/rj/common/microblogging/SNSAuthorized$2/this$0 Lcom/nd/rj/common/microblogging/SNSAuthorized;
invokevirtual com/nd/rj/common/microblogging/SNSAuthorized/ProcessFollow()V
return
L6:
aload 0
getfield com/nd/rj/common/microblogging/SNSAuthorized$2/this$0 Lcom/nd/rj/common/microblogging/SNSAuthorized;
invokestatic com/nd/rj/common/microblogging/SNSAuthorized/access$900(Lcom/nd/rj/common/microblogging/SNSAuthorized;)Landroid/widget/CheckBox;
aload 0
getfield com/nd/rj/common/microblogging/SNSAuthorized$2/this$0 Lcom/nd/rj/common/microblogging/SNSAuthorized;
invokestatic com/nd/rj/common/microblogging/SNSAuthorized/access$800(Lcom/nd/rj/common/microblogging/SNSAuthorized;)Lcom/nd/rj/common/microblogging/SNSModleMgr;
aload 0
getfield com/nd/rj/common/microblogging/SNSAuthorized$2/this$0 Lcom/nd/rj/common/microblogging/SNSAuthorized;
invokestatic com/nd/rj/common/microblogging/SNSAuthorized/access$700(Lcom/nd/rj/common/microblogging/SNSAuthorized;)I
invokevirtual com/nd/rj/common/microblogging/SNSModleMgr/checkFollow(I)Z
invokevirtual android/widget/CheckBox/setChecked(Z)V
return
.limit locals 2
.limit stack 6
.end method
