.bytecode 50.0
.class public synchronized com/nd/rj/common/microblogging/SNSSet
.super android/app/Activity
.inner class inner com/nd/rj/common/microblogging/SNSSet$1
.inner class inner com/nd/rj/common/microblogging/SNSSet$2
.inner class inner com/nd/rj/common/microblogging/SNSSet$3

.field public static 'APP_CODE' Ljava/lang/String;

.field public static 'APP_ID' I

.field public static 'BMP' Landroid/graphics/Bitmap;

.field public static 'CONTENT' Ljava/lang/String;

.field public static 'DOWNLOAD_URL' Ljava/lang/String;

.field public static 'PARAMS' Ljava/util/HashMap; signature "Ljava/util/HashMap<Ljava/lang/Integer;Ljava/lang/String;>;"

.field private 'OnClickListItem' Landroid/widget/AdapterView$OnItemClickListener;

.field private 'm_Adapter' Lcom/nd/rj/common/microblogging/SNSItemSetAdapter;

.field private 'm_btnBack' Landroid/widget/Button;

.field private 'm_cancel' Landroid/widget/Button;

.field private 'm_listViwe' Landroid/widget/ListView;

.field private 'm_nOperationType' I

.field private 'onBack' Landroid/view/View$OnClickListener;

.field private 'onCancel' Landroid/view/View$OnClickListener;

.method static <clinit>()V
invokestatic com/nd/rj/common/microblogging/SNSSet/initStaticData()V
return
.limit locals 0
.limit stack 0
.end method

.method public <init>()V
aload 0
invokespecial android/app/Activity/<init>()V
aload 0
iconst_0
putfield com/nd/rj/common/microblogging/SNSSet/m_nOperationType I
aload 0
new com/nd/rj/common/microblogging/SNSSet$1
dup
aload 0
invokespecial com/nd/rj/common/microblogging/SNSSet$1/<init>(Lcom/nd/rj/common/microblogging/SNSSet;)V
putfield com/nd/rj/common/microblogging/SNSSet/onBack Landroid/view/View$OnClickListener;
aload 0
new com/nd/rj/common/microblogging/SNSSet$2
dup
aload 0
invokespecial com/nd/rj/common/microblogging/SNSSet$2/<init>(Lcom/nd/rj/common/microblogging/SNSSet;)V
putfield com/nd/rj/common/microblogging/SNSSet/onCancel Landroid/view/View$OnClickListener;
aload 0
new com/nd/rj/common/microblogging/SNSSet$3
dup
aload 0
invokespecial com/nd/rj/common/microblogging/SNSSet$3/<init>(Lcom/nd/rj/common/microblogging/SNSSet;)V
putfield com/nd/rj/common/microblogging/SNSSet/OnClickListItem Landroid/widget/AdapterView$OnItemClickListener;
return
.limit locals 1
.limit stack 4
.end method

.method private InitData()V
aload 0
new com/nd/rj/common/microblogging/SNSItemSetAdapter
dup
aload 0
invokespecial com/nd/rj/common/microblogging/SNSItemSetAdapter/<init>(Landroid/content/Context;)V
putfield com/nd/rj/common/microblogging/SNSSet/m_Adapter Lcom/nd/rj/common/microblogging/SNSItemSetAdapter;
aload 0
getfield com/nd/rj/common/microblogging/SNSSet/m_listViwe Landroid/widget/ListView;
aload 0
getfield com/nd/rj/common/microblogging/SNSSet/m_Adapter Lcom/nd/rj/common/microblogging/SNSItemSetAdapter;
invokevirtual android/widget/ListView/setAdapter(Landroid/widget/ListAdapter;)V
aload 0
invokespecial com/nd/rj/common/microblogging/SNSSet/SetOperationType()V
return
.limit locals 1
.limit stack 4
.end method

.method private SetCtrl()V
aload 0
aload 0
getstatic com/nd/rj/common/R$id/snsSetbackId I
invokevirtual com/nd/rj/common/microblogging/SNSSet/findViewById(I)Landroid/view/View;
checkcast android/widget/Button
putfield com/nd/rj/common/microblogging/SNSSet/m_btnBack Landroid/widget/Button;
aload 0
aload 0
getstatic com/nd/rj/common/R$id/cancelId I
invokevirtual com/nd/rj/common/microblogging/SNSSet/findViewById(I)Landroid/view/View;
checkcast android/widget/Button
putfield com/nd/rj/common/microblogging/SNSSet/m_cancel Landroid/widget/Button;
aload 0
aload 0
getstatic com/nd/rj/common/R$id/setlistInfoId I
invokevirtual com/nd/rj/common/microblogging/SNSSet/findViewById(I)Landroid/view/View;
checkcast android/widget/ListView
putfield com/nd/rj/common/microblogging/SNSSet/m_listViwe Landroid/widget/ListView;
aload 0
getfield com/nd/rj/common/microblogging/SNSSet/m_btnBack Landroid/widget/Button;
aload 0
getfield com/nd/rj/common/microblogging/SNSSet/onBack Landroid/view/View$OnClickListener;
invokevirtual android/widget/Button/setOnClickListener(Landroid/view/View$OnClickListener;)V
aload 0
getfield com/nd/rj/common/microblogging/SNSSet/m_cancel Landroid/widget/Button;
aload 0
getfield com/nd/rj/common/microblogging/SNSSet/onCancel Landroid/view/View$OnClickListener;
invokevirtual android/widget/Button/setOnClickListener(Landroid/view/View$OnClickListener;)V
aload 0
getfield com/nd/rj/common/microblogging/SNSSet/m_listViwe Landroid/widget/ListView;
aload 0
getfield com/nd/rj/common/microblogging/SNSSet/OnClickListItem Landroid/widget/AdapterView$OnItemClickListener;
invokevirtual android/widget/ListView/setOnItemClickListener(Landroid/widget/AdapterView$OnItemClickListener;)V
aload 0
invokestatic com/nd/rj/common/util/ComfunHelp/getAppName(Landroid/content/Context;)Ljava/lang/String;
astore 1
aload 0
getstatic com/nd/rj/common/R$string/sns_setTitleMsg I
invokevirtual com/nd/rj/common/microblogging/SNSSet/getString(I)Ljava/lang/String;
astore 2
aload 0
getstatic com/nd/rj/common/R$id/autoCompleteTextView1 I
invokevirtual com/nd/rj/common/microblogging/SNSSet/findViewById(I)Landroid/view/View;
checkcast android/widget/TextView
aload 2
iconst_1
anewarray java/lang/Object
dup
iconst_0
aload 1
aastore
invokestatic java/lang/String/format(Ljava/lang/String;[Ljava/lang/Object;)Ljava/lang/String;
invokevirtual android/widget/TextView/setText(Ljava/lang/CharSequence;)V
return
.limit locals 3
.limit stack 6
.end method

.method private SetOperationType()V
aload 0
getfield com/nd/rj/common/microblogging/SNSSet/m_nOperationType I
ifne L0
aload 0
getfield com/nd/rj/common/microblogging/SNSSet/m_cancel Landroid/widget/Button;
ldc "\u53d6\u6d88\u5173\u8054"
invokevirtual android/widget/Button/setText(Ljava/lang/CharSequence;)V
aload 0
getfield com/nd/rj/common/microblogging/SNSSet/m_cancel Landroid/widget/Button;
getstatic com/nd/rj/common/R$drawable/nd_sns_button_icontext_selector_b I
invokevirtual android/widget/Button/setBackgroundResource(I)V
L1:
aload 0
getfield com/nd/rj/common/microblogging/SNSSet/m_Adapter Lcom/nd/rj/common/microblogging/SNSItemSetAdapter;
aload 0
getfield com/nd/rj/common/microblogging/SNSSet/m_nOperationType I
invokevirtual com/nd/rj/common/microblogging/SNSItemSetAdapter/SetOpt(I)V
aload 0
getfield com/nd/rj/common/microblogging/SNSSet/m_Adapter Lcom/nd/rj/common/microblogging/SNSItemSetAdapter;
invokevirtual com/nd/rj/common/microblogging/SNSItemSetAdapter/notifyDataSetChanged()V
return
L0:
aload 0
getfield com/nd/rj/common/microblogging/SNSSet/m_cancel Landroid/widget/Button;
ldc "\u5b8c\u6210"
invokevirtual android/widget/Button/setText(Ljava/lang/CharSequence;)V
aload 0
getfield com/nd/rj/common/microblogging/SNSSet/m_cancel Landroid/widget/Button;
getstatic com/nd/rj/common/R$drawable/nd_sns_button_delete_icontext_selector I
invokevirtual android/widget/Button/setBackgroundResource(I)V
goto L1
.limit locals 1
.limit stack 2
.end method

.method static synthetic access$000(Lcom/nd/rj/common/microblogging/SNSSet;)Lcom/nd/rj/common/microblogging/SNSItemSetAdapter;
aload 0
getfield com/nd/rj/common/microblogging/SNSSet/m_Adapter Lcom/nd/rj/common/microblogging/SNSItemSetAdapter;
areturn
.limit locals 1
.limit stack 1
.end method

.method static synthetic access$100()V
invokestatic com/nd/rj/common/microblogging/SNSSet/initStaticData()V
return
.limit locals 0
.limit stack 0
.end method

.method static synthetic access$200(Lcom/nd/rj/common/microblogging/SNSSet;)I
aload 0
getfield com/nd/rj/common/microblogging/SNSSet/m_nOperationType I
ireturn
.limit locals 1
.limit stack 1
.end method

.method static synthetic access$202(Lcom/nd/rj/common/microblogging/SNSSet;I)I
aload 0
iload 1
putfield com/nd/rj/common/microblogging/SNSSet/m_nOperationType I
iload 1
ireturn
.limit locals 2
.limit stack 2
.end method

.method static synthetic access$300(Lcom/nd/rj/common/microblogging/SNSSet;)V
aload 0
invokespecial com/nd/rj/common/microblogging/SNSSet/SetOperationType()V
return
.limit locals 1
.limit stack 1
.end method

.method private static initStaticData()V
iconst_m1
putstatic com/nd/rj/common/microblogging/SNSSet/APP_ID I
aconst_null
putstatic com/nd/rj/common/microblogging/SNSSet/APP_CODE Ljava/lang/String;
aconst_null
putstatic com/nd/rj/common/microblogging/SNSSet/PARAMS Ljava/util/HashMap;
aconst_null
putstatic com/nd/rj/common/microblogging/SNSSet/CONTENT Ljava/lang/String;
aconst_null
putstatic com/nd/rj/common/microblogging/SNSSet/BMP Landroid/graphics/Bitmap;
aconst_null
putstatic com/nd/rj/common/microblogging/SNSSet/DOWNLOAD_URL Ljava/lang/String;
return
.limit locals 0
.limit stack 1
.end method

.method public onActivityResult(IILandroid/content/Intent;)V
aload 0
iload 1
iload 2
aload 3
invokespecial android/app/Activity/onActivityResult(IILandroid/content/Intent;)V
iload 1
tableswitch 1002
L0
default : L1
L1:
return
L0:
aload 0
getfield com/nd/rj/common/microblogging/SNSSet/m_Adapter Lcom/nd/rj/common/microblogging/SNSItemSetAdapter;
invokevirtual com/nd/rj/common/microblogging/SNSItemSetAdapter/ReshData()V
aload 0
getfield com/nd/rj/common/microblogging/SNSSet/m_Adapter Lcom/nd/rj/common/microblogging/SNSItemSetAdapter;
invokevirtual com/nd/rj/common/microblogging/SNSItemSetAdapter/notifyDataSetChanged()V
return
.limit locals 4
.limit stack 4
.end method

.method protected onCreate(Landroid/os/Bundle;)V
aload 0
aload 1
invokespecial android/app/Activity/onCreate(Landroid/os/Bundle;)V
aload 0
iconst_1
invokevirtual com/nd/rj/common/microblogging/SNSSet/requestWindowFeature(I)Z
pop
aload 0
getstatic com/nd/rj/common/R$layout/nd_sns_set I
invokevirtual com/nd/rj/common/microblogging/SNSSet/setContentView(I)V
aload 0
invokespecial com/nd/rj/common/microblogging/SNSSet/SetCtrl()V
aload 0
invokespecial com/nd/rj/common/microblogging/SNSSet/InitData()V
return
.limit locals 2
.limit stack 2
.end method
