.bytecode 50.0
.class public synchronized com/nd/schoollife/ui/team/view/ExRadioGroup
.super java/lang/Object

.field private 'checkRadio' Lcom/nd/schoollife/ui/team/view/ExRadioButton;

.field private 'radios' Ljava/util/Vector; signature "Ljava/util/Vector<Lcom/nd/schoollife/ui/team/view/ExRadioButton;>;"

.method public <init>()V
aload 0
invokespecial java/lang/Object/<init>()V
aload 0
aconst_null
putfield com/nd/schoollife/ui/team/view/ExRadioGroup/radios Ljava/util/Vector;
aload 0
aconst_null
putfield com/nd/schoollife/ui/team/view/ExRadioGroup/checkRadio Lcom/nd/schoollife/ui/team/view/ExRadioButton;
aload 0
invokespecial com/nd/schoollife/ui/team/view/ExRadioGroup/init()V
return
.limit locals 1
.limit stack 2
.end method

.method private init()V
aload 0
new java/util/Vector
dup
invokespecial java/util/Vector/<init>()V
putfield com/nd/schoollife/ui/team/view/ExRadioGroup/radios Ljava/util/Vector;
aload 0
aconst_null
putfield com/nd/schoollife/ui/team/view/ExRadioGroup/checkRadio Lcom/nd/schoollife/ui/team/view/ExRadioButton;
return
.limit locals 1
.limit stack 3
.end method

.method public addExRadioButton(Lcom/nd/schoollife/ui/team/view/ExRadioButton;)V
aload 0
aload 1
invokevirtual com/nd/schoollife/ui/team/view/ExRadioGroup/findRadio(Lcom/nd/schoollife/ui/team/view/ExRadioButton;)I
ifle L0
return
L0:
aload 0
getfield com/nd/schoollife/ui/team/view/ExRadioGroup/radios Ljava/util/Vector;
aload 1
invokevirtual java/util/Vector/add(Ljava/lang/Object;)Z
pop
aload 1
aload 0
invokevirtual com/nd/schoollife/ui/team/view/ExRadioButton/setExRadioGroup(Lcom/nd/schoollife/ui/team/view/ExRadioGroup;)V
return
.limit locals 2
.limit stack 2
.end method

.method public findRadio(Lcom/nd/schoollife/ui/team/view/ExRadioButton;)I
aload 1
ifnonnull L0
iconst_m1
istore 3
L1:
iload 3
ireturn
L0:
aload 0
getfield com/nd/schoollife/ui/team/view/ExRadioGroup/radios Ljava/util/Vector;
invokevirtual java/util/Vector/size()I
istore 4
iconst_0
istore 2
L2:
iload 2
iload 4
if_icmpge L3
iload 2
istore 3
aload 0
getfield com/nd/schoollife/ui/team/view/ExRadioGroup/radios Ljava/util/Vector;
iload 2
invokevirtual java/util/Vector/get(I)Ljava/lang/Object;
checkcast com/nd/schoollife/ui/team/view/ExRadioButton
aload 1
invokevirtual java/lang/Object/equals(Ljava/lang/Object;)Z
ifne L1
iload 2
iconst_1
iadd
istore 2
goto L2
L3:
iconst_m1
ireturn
.limit locals 5
.limit stack 2
.end method

.method public getCheckButton()Lcom/nd/schoollife/ui/team/view/ExRadioButton;
aload 0
getfield com/nd/schoollife/ui/team/view/ExRadioGroup/checkRadio Lcom/nd/schoollife/ui/team/view/ExRadioButton;
areturn
.limit locals 1
.limit stack 1
.end method

.method public getRadioCheck(I)Z
iload 1
iflt L0
iload 1
aload 0
getfield com/nd/schoollife/ui/team/view/ExRadioGroup/radios Ljava/util/Vector;
invokevirtual java/util/Vector/size()I
if_icmpge L0
aload 0
getfield com/nd/schoollife/ui/team/view/ExRadioGroup/radios Ljava/util/Vector;
iload 1
invokevirtual java/util/Vector/get(I)Ljava/lang/Object;
checkcast com/nd/schoollife/ui/team/view/ExRadioButton
invokevirtual com/nd/schoollife/ui/team/view/ExRadioButton/getCheck()Z
ireturn
L0:
iconst_0
ireturn
.limit locals 2
.limit stack 2
.end method

.method public notifyRadioClick(Lcom/nd/schoollife/ui/team/view/ExRadioButton;)V
aload 0
getfield com/nd/schoollife/ui/team/view/ExRadioGroup/checkRadio Lcom/nd/schoollife/ui/team/view/ExRadioButton;
ifnonnull L0
aload 0
aload 1
putfield com/nd/schoollife/ui/team/view/ExRadioGroup/checkRadio Lcom/nd/schoollife/ui/team/view/ExRadioButton;
L1:
return
L0:
aload 0
getfield com/nd/schoollife/ui/team/view/ExRadioGroup/checkRadio Lcom/nd/schoollife/ui/team/view/ExRadioButton;
aload 1
invokevirtual java/lang/Object/equals(Ljava/lang/Object;)Z
ifne L1
aload 0
getfield com/nd/schoollife/ui/team/view/ExRadioGroup/checkRadio Lcom/nd/schoollife/ui/team/view/ExRadioButton;
iconst_0
invokevirtual com/nd/schoollife/ui/team/view/ExRadioButton/setCheck(Z)V
aload 0
aload 1
putfield com/nd/schoollife/ui/team/view/ExRadioGroup/checkRadio Lcom/nd/schoollife/ui/team/view/ExRadioButton;
return
.limit locals 2
.limit stack 2
.end method

.method public radioCount()I
aload 0
getfield com/nd/schoollife/ui/team/view/ExRadioGroup/radios Ljava/util/Vector;
invokevirtual java/util/Vector/size()I
ireturn
.limit locals 1
.limit stack 1
.end method

.method public removeRadioButton(Lcom/nd/schoollife/ui/team/view/ExRadioButton;)V
aload 0
aload 1
invokevirtual com/nd/schoollife/ui/team/view/ExRadioGroup/findRadio(Lcom/nd/schoollife/ui/team/view/ExRadioButton;)I
istore 2
iload 2
ifge L0
return
L0:
aload 1
aconst_null
invokevirtual com/nd/schoollife/ui/team/view/ExRadioButton/setExRadioGroup(Lcom/nd/schoollife/ui/team/view/ExRadioGroup;)V
aload 0
getfield com/nd/schoollife/ui/team/view/ExRadioGroup/radios Ljava/util/Vector;
iload 2
invokevirtual java/util/Vector/remove(I)Ljava/lang/Object;
pop
return
.limit locals 3
.limit stack 2
.end method

.method public size()I
aload 0
getfield com/nd/schoollife/ui/team/view/ExRadioGroup/radios Ljava/util/Vector;
invokevirtual java/util/Vector/size()I
ireturn
.limit locals 1
.limit stack 1
.end method
