.bytecode 50.0
.class public synchronized com/nd/android/u/tast/experience/calendar/DateWidgetDayCell
.super android/view/View
.inner class public static abstract interface OnItemClick inner com/nd/android/u/tast/experience/calendar/DateWidgetDayCell$OnItemClick outer com/nd/android/u/tast/experience/calendar/DateWidgetDayCell

.field private static 'ANIM_ALPHA_DURATION' I

.field private static 'fTextSize' I

.field private 'BirthDay' I

.field private 'BirthMonth' I

.field private 'IsAnniversary' Z

.field private 'JoinDay' I

.field private 'JoinMonth' I

.field private 'MyMonth' I

.field private 'SelectMonth' I

.field private 'SignInList' Ljava/lang/String;

.field private 'bHoliday' Z

.field private 'bIsActiveMonth' Z

.field private 'bSelected' Z

.field private 'bToday' Z

.field private 'bTouchedDown' Z

.field private 'drawFont' Ljava/lang/String;

.field private 'hasRecord' Z

.field private 'height' I

.field private 'iDateDay' I

.field private 'iDateMonth' I

.field private 'iDateYear' I

.field private 'itemClick' Lcom/nd/android/u/tast/experience/calendar/DateWidgetDayCell$OnItemClick;

.field private 'pt' Landroid/graphics/Paint;

.field private 'rect' Landroid/graphics/RectF;

.field private 'sDate' Ljava/lang/String;

.field private 'special_day_list' [Ljava/lang/String;

.field private 'width' I

.method static <clinit>()V
bipush 20
putstatic com/nd/android/u/tast/experience/calendar/DateWidgetDayCell/fTextSize I
bipush 100
putstatic com/nd/android/u/tast/experience/calendar/DateWidgetDayCell/ANIM_ALPHA_DURATION I
return
.limit locals 0
.limit stack 1
.end method

.method public <init>(Landroid/content/Context;II)V
aload 0
aload 1
invokespecial android/view/View/<init>(Landroid/content/Context;)V
aload 0
aconst_null
putfield com/nd/android/u/tast/experience/calendar/DateWidgetDayCell/itemClick Lcom/nd/android/u/tast/experience/calendar/DateWidgetDayCell$OnItemClick;
aload 0
new android/graphics/Paint
dup
invokespecial android/graphics/Paint/<init>()V
putfield com/nd/android/u/tast/experience/calendar/DateWidgetDayCell/pt Landroid/graphics/Paint;
aload 0
new android/graphics/RectF
dup
invokespecial android/graphics/RectF/<init>()V
putfield com/nd/android/u/tast/experience/calendar/DateWidgetDayCell/rect Landroid/graphics/RectF;
aload 0
ldc ""
putfield com/nd/android/u/tast/experience/calendar/DateWidgetDayCell/sDate Ljava/lang/String;
aload 0
ldc ""
putfield com/nd/android/u/tast/experience/calendar/DateWidgetDayCell/drawFont Ljava/lang/String;
aload 0
iconst_0
putfield com/nd/android/u/tast/experience/calendar/DateWidgetDayCell/iDateYear I
aload 0
iconst_0
putfield com/nd/android/u/tast/experience/calendar/DateWidgetDayCell/iDateMonth I
aload 0
iconst_0
putfield com/nd/android/u/tast/experience/calendar/DateWidgetDayCell/iDateDay I
aload 0
iconst_0
putfield com/nd/android/u/tast/experience/calendar/DateWidgetDayCell/bSelected Z
aload 0
iconst_0
putfield com/nd/android/u/tast/experience/calendar/DateWidgetDayCell/bIsActiveMonth Z
aload 0
iconst_0
putfield com/nd/android/u/tast/experience/calendar/DateWidgetDayCell/bToday Z
aload 0
iconst_0
putfield com/nd/android/u/tast/experience/calendar/DateWidgetDayCell/bTouchedDown Z
aload 0
iconst_0
putfield com/nd/android/u/tast/experience/calendar/DateWidgetDayCell/bHoliday Z
aload 0
iconst_0
putfield com/nd/android/u/tast/experience/calendar/DateWidgetDayCell/hasRecord Z
aload 0
iconst_0
putfield com/nd/android/u/tast/experience/calendar/DateWidgetDayCell/IsAnniversary Z
aload 0
iconst_0
putfield com/nd/android/u/tast/experience/calendar/DateWidgetDayCell/width I
aload 0
iconst_0
putfield com/nd/android/u/tast/experience/calendar/DateWidgetDayCell/height I
aload 0
ldc ""
putfield com/nd/android/u/tast/experience/calendar/DateWidgetDayCell/SignInList Ljava/lang/String;
aload 0
iconst_0
putfield com/nd/android/u/tast/experience/calendar/DateWidgetDayCell/SelectMonth I
aload 0
iconst_0
putfield com/nd/android/u/tast/experience/calendar/DateWidgetDayCell/JoinMonth I
aload 0
iconst_0
putfield com/nd/android/u/tast/experience/calendar/DateWidgetDayCell/JoinDay I
aload 0
iconst_0
putfield com/nd/android/u/tast/experience/calendar/DateWidgetDayCell/BirthMonth I
aload 0
iconst_0
putfield com/nd/android/u/tast/experience/calendar/DateWidgetDayCell/BirthDay I
aload 0
iconst_0
putfield com/nd/android/u/tast/experience/calendar/DateWidgetDayCell/MyMonth I
aload 0
invokevirtual com/nd/android/u/tast/experience/calendar/DateWidgetDayCell/getResources()Landroid/content/res/Resources;
getstatic com/nd/android/u/tasklib/R$dimen/number_text_size I
invokevirtual android/content/res/Resources/getDimension(I)F
f2i
putstatic com/nd/android/u/tast/experience/calendar/DateWidgetDayCell/fTextSize I
aload 0
iconst_1
invokevirtual com/nd/android/u/tast/experience/calendar/DateWidgetDayCell/setFocusable(Z)V
aload 0
iload 2
putfield com/nd/android/u/tast/experience/calendar/DateWidgetDayCell/width I
aload 0
iload 3
putfield com/nd/android/u/tast/experience/calendar/DateWidgetDayCell/height I
aload 0
new android/widget/LinearLayout$LayoutParams
dup
iload 2
iload 3
invokespecial android/widget/LinearLayout$LayoutParams/<init>(II)V
invokevirtual com/nd/android/u/tast/experience/calendar/DateWidgetDayCell/setLayoutParams(Landroid/view/ViewGroup$LayoutParams;)V
return
.limit locals 4
.limit stack 5
.end method

.method private drawDayView(Landroid/graphics/Canvas;Z)V
aload 0
getfield com/nd/android/u/tast/experience/calendar/DateWidgetDayCell/rect Landroid/graphics/RectF;
getfield android/graphics/RectF/left F
f2i
istore 3
aload 0
getfield com/nd/android/u/tast/experience/calendar/DateWidgetDayCell/rect Landroid/graphics/RectF;
invokevirtual android/graphics/RectF/width()F
f2i
istore 4
aload 0
invokevirtual com/nd/android/u/tast/experience/calendar/DateWidgetDayCell/getHeight()I
istore 5
aload 0
getfield com/nd/android/u/tast/experience/calendar/DateWidgetDayCell/pt Landroid/graphics/Paint;
iconst_m1
invokevirtual android/graphics/Paint/setColor(I)V
aload 0
getfield com/nd/android/u/tast/experience/calendar/DateWidgetDayCell/bIsActiveMonth Z
ifeq L0
aload 0
getfield com/nd/android/u/tast/experience/calendar/DateWidgetDayCell/bToday Z
ifeq L0
aload 0
getfield com/nd/android/u/tast/experience/calendar/DateWidgetDayCell/pt Landroid/graphics/Paint;
ldc_w -12943024
invokevirtual android/graphics/Paint/setColor(I)V
L0:
aload 0
getfield com/nd/android/u/tast/experience/calendar/DateWidgetDayCell/pt Landroid/graphics/Paint;
getstatic android/graphics/Paint$Style/FILL Landroid/graphics/Paint$Style;
invokevirtual android/graphics/Paint/setStyle(Landroid/graphics/Paint$Style;)V
aload 0
getfield com/nd/android/u/tast/experience/calendar/DateWidgetDayCell/pt Landroid/graphics/Paint;
ldc_w 4.0F
invokevirtual android/graphics/Paint/setStrokeWidth(F)V
aload 1
aload 0
getfield com/nd/android/u/tast/experience/calendar/DateWidgetDayCell/rect Landroid/graphics/RectF;
aload 0
getfield com/nd/android/u/tast/experience/calendar/DateWidgetDayCell/pt Landroid/graphics/Paint;
invokevirtual android/graphics/Canvas/drawRect(Landroid/graphics/RectF;Landroid/graphics/Paint;)V
aload 0
invokevirtual com/nd/android/u/tast/experience/calendar/DateWidgetDayCell/getResources()Landroid/content/res/Resources;
getstatic com/nd/android/u/tasklib/R$drawable/todo_sift_bg I
invokestatic android/graphics/BitmapFactory/decodeResource(Landroid/content/res/Resources;I)Landroid/graphics/Bitmap;
aload 0
getfield com/nd/android/u/tast/experience/calendar/DateWidgetDayCell/width I
iconst_2
isub
aload 0
getfield com/nd/android/u/tast/experience/calendar/DateWidgetDayCell/height I
iconst_2
isub
iconst_1
invokestatic android/graphics/Bitmap/createScaledBitmap(Landroid/graphics/Bitmap;IIZ)Landroid/graphics/Bitmap;
astore 6
aload 1
aload 6
iload 3
iload 4
iconst_1
ishr
iadd
aload 6
invokevirtual android/graphics/Bitmap/getWidth()I
iconst_2
idiv
isub
i2f
iload 5
iconst_1
isub
aload 6
invokevirtual android/graphics/Bitmap/getHeight()I
isub
i2f
aload 0
getfield com/nd/android/u/tast/experience/calendar/DateWidgetDayCell/pt Landroid/graphics/Paint;
invokevirtual android/graphics/Canvas/drawBitmap(Landroid/graphics/Bitmap;FFLandroid/graphics/Paint;)V
aload 0
getfield com/nd/android/u/tast/experience/calendar/DateWidgetDayCell/bIsActiveMonth Z
ifeq L1
aload 0
aload 0
getfield com/nd/android/u/tast/experience/calendar/DateWidgetDayCell/SelectMonth I
putfield com/nd/android/u/tast/experience/calendar/DateWidgetDayCell/MyMonth I
aload 0
aload 0
getfield com/nd/android/u/tast/experience/calendar/DateWidgetDayCell/sDate Ljava/lang/String;
putfield com/nd/android/u/tast/experience/calendar/DateWidgetDayCell/drawFont Ljava/lang/String;
aload 0
getfield com/nd/android/u/tast/experience/calendar/DateWidgetDayCell/MyMonth I
aload 0
getfield com/nd/android/u/tast/experience/calendar/DateWidgetDayCell/BirthMonth I
if_icmpne L1
aload 0
getfield com/nd/android/u/tast/experience/calendar/DateWidgetDayCell/sDate Ljava/lang/String;
invokestatic java/lang/Integer/valueOf(Ljava/lang/String;)Ljava/lang/Integer;
invokevirtual java/lang/Integer/intValue()I
aload 0
getfield com/nd/android/u/tast/experience/calendar/DateWidgetDayCell/BirthDay I
if_icmpne L1
aload 0
getfield com/nd/android/u/tast/experience/calendar/DateWidgetDayCell/rect Landroid/graphics/RectF;
getfield android/graphics/RectF/left F
f2i
istore 3
aload 0
getfield com/nd/android/u/tast/experience/calendar/DateWidgetDayCell/rect Landroid/graphics/RectF;
invokevirtual android/graphics/RectF/width()F
f2i
istore 4
aload 0
getfield com/nd/android/u/tast/experience/calendar/DateWidgetDayCell/pt Landroid/graphics/Paint;
aload 0
getfield com/nd/android/u/tast/experience/calendar/DateWidgetDayCell/drawFont Ljava/lang/String;
invokevirtual android/graphics/Paint/measureText(Ljava/lang/String;)F
f2i
istore 5
aload 0
invokevirtual com/nd/android/u/tast/experience/calendar/DateWidgetDayCell/getResources()Landroid/content/res/Resources;
getstatic com/nd/android/u/tasklib/R$drawable/birthday I
invokestatic android/graphics/BitmapFactory/decodeResource(Landroid/content/res/Resources;I)Landroid/graphics/Bitmap;
astore 6
aload 1
aload 6
iload 3
iload 4
iconst_1
ishr
iadd
iload 5
iconst_1
ishr
isub
aload 6
invokevirtual android/graphics/Bitmap/getWidth()I
iconst_1
ishr
isub
aload 0
getfield com/nd/android/u/tast/experience/calendar/DateWidgetDayCell/pt Landroid/graphics/Paint;
aload 0
getfield com/nd/android/u/tast/experience/calendar/DateWidgetDayCell/drawFont Ljava/lang/String;
invokevirtual android/graphics/Paint/measureText(Ljava/lang/String;)F
f2i
iconst_1
ishr
iadd
i2f
aload 0
invokevirtual com/nd/android/u/tast/experience/calendar/DateWidgetDayCell/getHeight()I
aload 6
invokevirtual android/graphics/Bitmap/getHeight()I
isub
iconst_1
ishr
i2f
aload 0
getfield com/nd/android/u/tast/experience/calendar/DateWidgetDayCell/pt Landroid/graphics/Paint;
invokevirtual android/graphics/Canvas/drawBitmap(Landroid/graphics/Bitmap;FFLandroid/graphics/Paint;)V
L1:
return
.limit locals 7
.limit stack 5
.end method

.method public static getColorBkg(ZZ)I
iload 1
ifeq L0
invokestatic com/nd/android/u/tast/experience/activity/DateWidgetActivity/getCalendar_DayBgColor()I
ireturn
L0:
invokestatic com/nd/android/u/tast/experience/activity/DateWidgetActivity/getCalendar_DayBgColor()I
ireturn
.limit locals 2
.limit stack 1
.end method

.method private getTextHeight()I
aload 0
getfield com/nd/android/u/tast/experience/calendar/DateWidgetDayCell/pt Landroid/graphics/Paint;
invokevirtual android/graphics/Paint/ascent()F
fneg
aload 0
getfield com/nd/android/u/tast/experience/calendar/DateWidgetDayCell/pt Landroid/graphics/Paint;
invokevirtual android/graphics/Paint/descent()F
fadd
f2i
ireturn
.limit locals 1
.limit stack 2
.end method

.method public IsViewFocused()Z
aload 0
invokevirtual com/nd/android/u/tast/experience/calendar/DateWidgetDayCell/isFocused()Z
ifne L0
aload 0
getfield com/nd/android/u/tast/experience/calendar/DateWidgetDayCell/bTouchedDown Z
ifeq L1
L0:
iconst_1
ireturn
L1:
iconst_0
ireturn
.limit locals 1
.limit stack 1
.end method

.method public doItemClick()V
aload 0
getfield com/nd/android/u/tast/experience/calendar/DateWidgetDayCell/itemClick Lcom/nd/android/u/tast/experience/calendar/DateWidgetDayCell$OnItemClick;
ifnull L0
aload 0
getfield com/nd/android/u/tast/experience/calendar/DateWidgetDayCell/itemClick Lcom/nd/android/u/tast/experience/calendar/DateWidgetDayCell$OnItemClick;
aload 0
invokeinterface com/nd/android/u/tast/experience/calendar/DateWidgetDayCell$OnItemClick/OnClick(Lcom/nd/android/u/tast/experience/calendar/DateWidgetDayCell;)V 1
L0:
return
.limit locals 1
.limit stack 2
.end method

.method public drawDayNumber(Landroid/graphics/Canvas;)V
aload 0
getfield com/nd/android/u/tast/experience/calendar/DateWidgetDayCell/pt Landroid/graphics/Paint;
aconst_null
invokevirtual android/graphics/Paint/setTypeface(Landroid/graphics/Typeface;)Landroid/graphics/Typeface;
pop
aload 0
getfield com/nd/android/u/tast/experience/calendar/DateWidgetDayCell/pt Landroid/graphics/Paint;
iconst_1
invokevirtual android/graphics/Paint/setAntiAlias(Z)V
aload 0
getfield com/nd/android/u/tast/experience/calendar/DateWidgetDayCell/pt Landroid/graphics/Paint;
aconst_null
invokevirtual android/graphics/Paint/setShader(Landroid/graphics/Shader;)Landroid/graphics/Shader;
pop
aload 0
getfield com/nd/android/u/tast/experience/calendar/DateWidgetDayCell/pt Landroid/graphics/Paint;
iconst_1
invokevirtual android/graphics/Paint/setFakeBoldText(Z)V
aload 0
getfield com/nd/android/u/tast/experience/calendar/DateWidgetDayCell/pt Landroid/graphics/Paint;
getstatic com/nd/android/u/tast/experience/calendar/DateWidgetDayCell/fTextSize I
i2f
invokevirtual android/graphics/Paint/setTextSize(F)V
aload 0
getfield com/nd/android/u/tast/experience/calendar/DateWidgetDayCell/pt Landroid/graphics/Paint;
invokestatic com/nd/android/u/tast/experience/activity/DateWidgetActivity/getCalendar_DayBgColor()I
invokevirtual android/graphics/Paint/setColor(I)V
aload 0
getfield com/nd/android/u/tast/experience/calendar/DateWidgetDayCell/pt Landroid/graphics/Paint;
iconst_0
invokevirtual android/graphics/Paint/setUnderlineText(Z)V
aload 0
getfield com/nd/android/u/tast/experience/calendar/DateWidgetDayCell/bIsActiveMonth Z
ifeq L0
aload 0
aload 0
getfield com/nd/android/u/tast/experience/calendar/DateWidgetDayCell/SelectMonth I
putfield com/nd/android/u/tast/experience/calendar/DateWidgetDayCell/MyMonth I
aload 0
aload 0
getfield com/nd/android/u/tast/experience/calendar/DateWidgetDayCell/sDate Ljava/lang/String;
putfield com/nd/android/u/tast/experience/calendar/DateWidgetDayCell/drawFont Ljava/lang/String;
aload 0
getfield com/nd/android/u/tast/experience/calendar/DateWidgetDayCell/special_day_list [Ljava/lang/String;
arraylength
ifle L1
iconst_0
istore 2
L2:
iload 2
aload 0
getfield com/nd/android/u/tast/experience/calendar/DateWidgetDayCell/special_day_list [Ljava/lang/String;
arraylength
if_icmpge L1
aload 0
getfield com/nd/android/u/tast/experience/calendar/DateWidgetDayCell/special_day_list [Ljava/lang/String;
iload 2
aaload
ldc "-"
invokevirtual java/lang/String/split(Ljava/lang/String;)[Ljava/lang/String;
iconst_0
aaload
invokestatic java/lang/Integer/valueOf(Ljava/lang/String;)Ljava/lang/Integer;
invokevirtual java/lang/Integer/intValue()I
istore 3
aload 0
getfield com/nd/android/u/tast/experience/calendar/DateWidgetDayCell/special_day_list [Ljava/lang/String;
iload 2
aaload
ldc "-"
invokevirtual java/lang/String/split(Ljava/lang/String;)[Ljava/lang/String;
iconst_1
aaload
invokestatic java/lang/Integer/valueOf(Ljava/lang/String;)Ljava/lang/Integer;
invokevirtual java/lang/Integer/intValue()I
istore 4
aload 0
getfield com/nd/android/u/tast/experience/calendar/DateWidgetDayCell/MyMonth I
iload 3
if_icmpne L3
aload 0
getfield com/nd/android/u/tast/experience/calendar/DateWidgetDayCell/sDate Ljava/lang/String;
invokestatic java/lang/Integer/valueOf(Ljava/lang/String;)Ljava/lang/Integer;
invokevirtual java/lang/Integer/intValue()I
iload 4
if_icmpne L3
aload 0
ldc "\u7279"
putfield com/nd/android/u/tast/experience/calendar/DateWidgetDayCell/drawFont Ljava/lang/String;
L3:
iload 2
iconst_1
iadd
istore 2
goto L2
L1:
aload 0
getfield com/nd/android/u/tast/experience/calendar/DateWidgetDayCell/MyMonth I
aload 0
getfield com/nd/android/u/tast/experience/calendar/DateWidgetDayCell/JoinMonth I
if_icmpne L4
aload 0
getfield com/nd/android/u/tast/experience/calendar/DateWidgetDayCell/sDate Ljava/lang/String;
invokestatic java/lang/Integer/valueOf(Ljava/lang/String;)Ljava/lang/Integer;
invokevirtual java/lang/Integer/intValue()I
aload 0
getfield com/nd/android/u/tast/experience/calendar/DateWidgetDayCell/JoinDay I
if_icmpne L4
aload 0
getfield com/nd/android/u/tast/experience/calendar/DateWidgetDayCell/IsAnniversary Z
ifeq L4
aload 0
ldc "\u5468"
putfield com/nd/android/u/tast/experience/calendar/DateWidgetDayCell/drawFont Ljava/lang/String;
L4:
aload 0
getfield com/nd/android/u/tast/experience/calendar/DateWidgetDayCell/rect Landroid/graphics/RectF;
getfield android/graphics/RectF/left F
f2i
aload 0
getfield com/nd/android/u/tast/experience/calendar/DateWidgetDayCell/rect Landroid/graphics/RectF;
invokevirtual android/graphics/RectF/width()F
f2i
iconst_1
ishr
iadd
aload 0
getfield com/nd/android/u/tast/experience/calendar/DateWidgetDayCell/pt Landroid/graphics/Paint;
aload 0
getfield com/nd/android/u/tast/experience/calendar/DateWidgetDayCell/drawFont Ljava/lang/String;
invokevirtual android/graphics/Paint/measureText(Ljava/lang/String;)F
f2i
iconst_1
ishr
isub
istore 2
aload 0
invokevirtual com/nd/android/u/tast/experience/calendar/DateWidgetDayCell/getHeight()I
aload 0
invokevirtual com/nd/android/u/tast/experience/calendar/DateWidgetDayCell/getHeight()I
aload 0
invokespecial com/nd/android/u/tast/experience/calendar/DateWidgetDayCell/getTextHeight()I
isub
iconst_2
idiv
isub
i2f
aload 0
getfield com/nd/android/u/tast/experience/calendar/DateWidgetDayCell/pt Landroid/graphics/Paint;
invokevirtual android/graphics/Paint/getFontMetrics()Landroid/graphics/Paint$FontMetrics;
getfield android/graphics/Paint$FontMetrics/bottom F
fsub
f2i
istore 3
aload 0
getfield com/nd/android/u/tast/experience/calendar/DateWidgetDayCell/MyMonth I
aload 0
getfield com/nd/android/u/tast/experience/calendar/DateWidgetDayCell/BirthMonth I
if_icmpne L5
aload 0
getfield com/nd/android/u/tast/experience/calendar/DateWidgetDayCell/sDate Ljava/lang/String;
invokestatic java/lang/Integer/valueOf(Ljava/lang/String;)Ljava/lang/Integer;
invokevirtual java/lang/Integer/intValue()I
aload 0
getfield com/nd/android/u/tast/experience/calendar/DateWidgetDayCell/BirthDay I
if_icmpeq L6
L5:
aload 0
getfield com/nd/android/u/tast/experience/calendar/DateWidgetDayCell/bHoliday Z
ifeq L7
aload 0
getfield com/nd/android/u/tast/experience/calendar/DateWidgetDayCell/pt Landroid/graphics/Paint;
ldc_w -10964877
invokevirtual android/graphics/Paint/setColor(I)V
L8:
ldc "\u5468"
aload 0
getfield com/nd/android/u/tast/experience/calendar/DateWidgetDayCell/drawFont Ljava/lang/String;
invokevirtual java/lang/String/equals(Ljava/lang/Object;)Z
ifeq L9
aload 0
getfield com/nd/android/u/tast/experience/calendar/DateWidgetDayCell/pt Landroid/graphics/Paint;
sipush -30656
invokevirtual android/graphics/Paint/setColor(I)V
L10:
aload 1
aload 0
getfield com/nd/android/u/tast/experience/calendar/DateWidgetDayCell/drawFont Ljava/lang/String;
iload 2
i2f
iload 3
i2f
aload 0
getfield com/nd/android/u/tast/experience/calendar/DateWidgetDayCell/pt Landroid/graphics/Paint;
invokevirtual android/graphics/Canvas/drawText(Ljava/lang/String;FFLandroid/graphics/Paint;)V
L6:
ldc "1"
aload 0
aload 0
getfield com/nd/android/u/tast/experience/calendar/DateWidgetDayCell/sDate Ljava/lang/String;
invokevirtual com/nd/android/u/tast/experience/calendar/DateWidgetDayCell/getis_SignIn(Ljava/lang/String;)Ljava/lang/String;
invokevirtual java/lang/String/equals(Ljava/lang/Object;)Z
ifeq L0
aload 0
invokevirtual com/nd/android/u/tast/experience/calendar/DateWidgetDayCell/getResources()Landroid/content/res/Resources;
getstatic com/nd/android/u/tasklib/R$drawable/signed I
invokestatic android/graphics/BitmapFactory/decodeResource(Landroid/content/res/Resources;I)Landroid/graphics/Bitmap;
astore 5
aload 1
aload 5
iload 2
aload 5
invokevirtual android/graphics/Bitmap/getWidth()I
iconst_1
ishr
isub
aload 0
getfield com/nd/android/u/tast/experience/calendar/DateWidgetDayCell/pt Landroid/graphics/Paint;
aload 0
getfield com/nd/android/u/tast/experience/calendar/DateWidgetDayCell/drawFont Ljava/lang/String;
invokevirtual android/graphics/Paint/measureText(Ljava/lang/String;)F
f2i
iconst_1
ishr
iadd
i2f
aload 0
invokevirtual com/nd/android/u/tast/experience/calendar/DateWidgetDayCell/getHeight()I
aload 5
invokevirtual android/graphics/Bitmap/getHeight()I
isub
iconst_1
ishr
i2f
aload 0
getfield com/nd/android/u/tast/experience/calendar/DateWidgetDayCell/pt Landroid/graphics/Paint;
invokevirtual android/graphics/Canvas/drawBitmap(Landroid/graphics/Bitmap;FFLandroid/graphics/Paint;)V
L0:
return
L7:
aload 0
getfield com/nd/android/u/tast/experience/calendar/DateWidgetDayCell/pt Landroid/graphics/Paint;
ldc_w -10596285
invokevirtual android/graphics/Paint/setColor(I)V
goto L8
L9:
ldc "\u7279"
aload 0
getfield com/nd/android/u/tast/experience/calendar/DateWidgetDayCell/drawFont Ljava/lang/String;
invokevirtual java/lang/String/equals(Ljava/lang/Object;)Z
ifeq L10
aload 0
getfield com/nd/android/u/tast/experience/calendar/DateWidgetDayCell/pt Landroid/graphics/Paint;
sipush -30656
invokevirtual android/graphics/Paint/setColor(I)V
goto L10
.limit locals 6
.limit stack 5
.end method

.method public getDate()Ljava/util/Calendar;
invokestatic java/util/Calendar/getInstance()Ljava/util/Calendar;
astore 1
aload 1
invokevirtual java/util/Calendar/clear()V
aload 1
iconst_1
aload 0
getfield com/nd/android/u/tast/experience/calendar/DateWidgetDayCell/iDateYear I
invokevirtual java/util/Calendar/set(II)V
aload 1
iconst_2
aload 0
getfield com/nd/android/u/tast/experience/calendar/DateWidgetDayCell/SelectMonth I
invokevirtual java/util/Calendar/set(II)V
aload 1
iconst_5
aload 0
getfield com/nd/android/u/tast/experience/calendar/DateWidgetDayCell/iDateDay I
invokevirtual java/util/Calendar/set(II)V
aload 1
areturn
.limit locals 2
.limit stack 3
.end method

.method public getis_SignIn(Ljava/lang/String;)Ljava/lang/String;
.catch java/lang/Exception from L0 to L1 using L2
L0:
ldc ""
aload 0
getfield com/nd/android/u/tast/experience/calendar/DateWidgetDayCell/SignInList Ljava/lang/String;
invokevirtual java/lang/String/equals(Ljava/lang/Object;)Z
ifne L1
aload 0
getfield com/nd/android/u/tast/experience/calendar/DateWidgetDayCell/SignInList Ljava/lang/String;
invokevirtual java/lang/String/length()I
bipush 31
if_icmpne L1
aload 0
getfield com/nd/android/u/tast/experience/calendar/DateWidgetDayCell/SignInList Ljava/lang/String;
invokevirtual java/lang/String/toCharArray()[C
aload 1
invokestatic java/lang/Integer/valueOf(Ljava/lang/String;)Ljava/lang/Integer;
invokevirtual java/lang/Integer/intValue()I
iconst_1
isub
caload
invokestatic java/lang/String/valueOf(C)Ljava/lang/String;
areturn
L1:
ldc "0"
areturn
L2:
astore 1
ldc "0"
areturn
.limit locals 2
.limit stack 3
.end method

.method protected onDraw(Landroid/graphics/Canvas;)V
aload 0
aload 1
invokespecial android/view/View/onDraw(Landroid/graphics/Canvas;)V
aload 0
getfield com/nd/android/u/tast/experience/calendar/DateWidgetDayCell/rect Landroid/graphics/RectF;
fconst_0
fconst_0
aload 0
invokevirtual com/nd/android/u/tast/experience/calendar/DateWidgetDayCell/getWidth()I
i2f
aload 0
invokevirtual com/nd/android/u/tast/experience/calendar/DateWidgetDayCell/getHeight()I
i2f
invokevirtual android/graphics/RectF/set(FFFF)V
aload 0
aload 1
aload 0
invokevirtual com/nd/android/u/tast/experience/calendar/DateWidgetDayCell/IsViewFocused()Z
invokespecial com/nd/android/u/tast/experience/calendar/DateWidgetDayCell/drawDayView(Landroid/graphics/Canvas;Z)V
aload 0
aload 1
invokevirtual com/nd/android/u/tast/experience/calendar/DateWidgetDayCell/drawDayNumber(Landroid/graphics/Canvas;)V
return
.limit locals 2
.limit stack 5
.end method

.method public setData(IIILjava/lang/Boolean;Ljava/lang/Boolean;IZLjava/lang/String;IIIIIZ[Ljava/lang/String;)V
aload 0
iload 1
putfield com/nd/android/u/tast/experience/calendar/DateWidgetDayCell/iDateYear I
aload 0
iload 2
putfield com/nd/android/u/tast/experience/calendar/DateWidgetDayCell/iDateMonth I
aload 0
iload 3
putfield com/nd/android/u/tast/experience/calendar/DateWidgetDayCell/iDateDay I
aload 0
iload 9
putfield com/nd/android/u/tast/experience/calendar/DateWidgetDayCell/SelectMonth I
aload 0
aload 0
getfield com/nd/android/u/tast/experience/calendar/DateWidgetDayCell/iDateDay I
invokestatic java/lang/Integer/toString(I)Ljava/lang/String;
putfield com/nd/android/u/tast/experience/calendar/DateWidgetDayCell/sDate Ljava/lang/String;
aload 0
getfield com/nd/android/u/tast/experience/calendar/DateWidgetDayCell/iDateMonth I
iload 6
if_icmpne L0
iconst_1
istore 16
L1:
aload 0
iload 16
putfield com/nd/android/u/tast/experience/calendar/DateWidgetDayCell/bIsActiveMonth Z
aload 0
aload 4
invokevirtual java/lang/Boolean/booleanValue()Z
putfield com/nd/android/u/tast/experience/calendar/DateWidgetDayCell/bToday Z
aload 0
aload 5
invokevirtual java/lang/Boolean/booleanValue()Z
putfield com/nd/android/u/tast/experience/calendar/DateWidgetDayCell/bHoliday Z
aload 0
iload 7
putfield com/nd/android/u/tast/experience/calendar/DateWidgetDayCell/hasRecord Z
aload 0
aload 8
putfield com/nd/android/u/tast/experience/calendar/DateWidgetDayCell/SignInList Ljava/lang/String;
aload 0
iload 10
putfield com/nd/android/u/tast/experience/calendar/DateWidgetDayCell/JoinMonth I
aload 0
iload 11
putfield com/nd/android/u/tast/experience/calendar/DateWidgetDayCell/JoinDay I
aload 0
iload 12
putfield com/nd/android/u/tast/experience/calendar/DateWidgetDayCell/BirthMonth I
aload 0
iload 13
putfield com/nd/android/u/tast/experience/calendar/DateWidgetDayCell/BirthDay I
aload 0
iload 14
putfield com/nd/android/u/tast/experience/calendar/DateWidgetDayCell/IsAnniversary Z
aload 0
aload 15
putfield com/nd/android/u/tast/experience/calendar/DateWidgetDayCell/special_day_list [Ljava/lang/String;
return
L0:
iconst_0
istore 16
goto L1
.limit locals 17
.limit stack 2
.end method

.method public setItemClick(Lcom/nd/android/u/tast/experience/calendar/DateWidgetDayCell$OnItemClick;)V
aload 0
aload 1
putfield com/nd/android/u/tast/experience/calendar/DateWidgetDayCell/itemClick Lcom/nd/android/u/tast/experience/calendar/DateWidgetDayCell$OnItemClick;
return
.limit locals 2
.limit stack 2
.end method

.method public setSelected(Z)V
aload 0
getfield com/nd/android/u/tast/experience/calendar/DateWidgetDayCell/bSelected Z
iload 1
if_icmpeq L0
aload 0
iload 1
putfield com/nd/android/u/tast/experience/calendar/DateWidgetDayCell/bSelected Z
aload 0
invokevirtual com/nd/android/u/tast/experience/calendar/DateWidgetDayCell/invalidate()V
L0:
return
.limit locals 2
.limit stack 2
.end method
