.bytecode 50.0
.class synchronized com/nd/android/u/tast/experience/calendar/SignInPopWindow$2
.super java/lang/Object
.implements android/view/View$OnClickListener
.enclosing method com/nd/android/u/tast/experience/calendar/SignInPopWindow
.inner class inner com/nd/android/u/tast/experience/calendar/SignInPopWindow$2

.field final synthetic 'this$0' Lcom/nd/android/u/tast/experience/calendar/SignInPopWindow;

.method <init>(Lcom/nd/android/u/tast/experience/calendar/SignInPopWindow;)V
aload 0
aload 1
putfield com/nd/android/u/tast/experience/calendar/SignInPopWindow$2/this$0 Lcom/nd/android/u/tast/experience/calendar/SignInPopWindow;
aload 0
invokespecial java/lang/Object/<init>()V
return
.limit locals 2
.limit stack 2
.end method

.method public onClick(Landroid/view/View;)V
aload 0
getfield com/nd/android/u/tast/experience/calendar/SignInPopWindow$2/this$0 Lcom/nd/android/u/tast/experience/calendar/SignInPopWindow;
invokestatic com/nd/android/u/tast/experience/calendar/SignInPopWindow/access$008(Lcom/nd/android/u/tast/experience/calendar/SignInPopWindow;)I
pop
aload 0
getfield com/nd/android/u/tast/experience/calendar/SignInPopWindow$2/this$0 Lcom/nd/android/u/tast/experience/calendar/SignInPopWindow;
invokestatic com/nd/android/u/tast/experience/calendar/SignInPopWindow/access$000(Lcom/nd/android/u/tast/experience/calendar/SignInPopWindow;)I
bipush 12
if_icmpne L0
aload 0
getfield com/nd/android/u/tast/experience/calendar/SignInPopWindow$2/this$0 Lcom/nd/android/u/tast/experience/calendar/SignInPopWindow;
iconst_0
invokestatic com/nd/android/u/tast/experience/calendar/SignInPopWindow/access$002(Lcom/nd/android/u/tast/experience/calendar/SignInPopWindow;I)I
pop
aload 0
getfield com/nd/android/u/tast/experience/calendar/SignInPopWindow$2/this$0 Lcom/nd/android/u/tast/experience/calendar/SignInPopWindow;
invokestatic com/nd/android/u/tast/experience/calendar/SignInPopWindow/access$108(Lcom/nd/android/u/tast/experience/calendar/SignInPopWindow;)I
pop
L0:
aload 0
getfield com/nd/android/u/tast/experience/calendar/SignInPopWindow$2/this$0 Lcom/nd/android/u/tast/experience/calendar/SignInPopWindow;
invokestatic com/nd/android/u/tast/experience/calendar/SignInPopWindow/access$200(Lcom/nd/android/u/tast/experience/calendar/SignInPopWindow;)Ljava/util/Calendar;
iconst_5
iconst_1
invokevirtual java/util/Calendar/set(II)V
aload 0
getfield com/nd/android/u/tast/experience/calendar/SignInPopWindow$2/this$0 Lcom/nd/android/u/tast/experience/calendar/SignInPopWindow;
invokestatic com/nd/android/u/tast/experience/calendar/SignInPopWindow/access$200(Lcom/nd/android/u/tast/experience/calendar/SignInPopWindow;)Ljava/util/Calendar;
iconst_2
aload 0
getfield com/nd/android/u/tast/experience/calendar/SignInPopWindow$2/this$0 Lcom/nd/android/u/tast/experience/calendar/SignInPopWindow;
invokestatic com/nd/android/u/tast/experience/calendar/SignInPopWindow/access$000(Lcom/nd/android/u/tast/experience/calendar/SignInPopWindow;)I
invokevirtual java/util/Calendar/set(II)V
aload 0
getfield com/nd/android/u/tast/experience/calendar/SignInPopWindow$2/this$0 Lcom/nd/android/u/tast/experience/calendar/SignInPopWindow;
invokestatic com/nd/android/u/tast/experience/calendar/SignInPopWindow/access$200(Lcom/nd/android/u/tast/experience/calendar/SignInPopWindow;)Ljava/util/Calendar;
iconst_1
aload 0
getfield com/nd/android/u/tast/experience/calendar/SignInPopWindow$2/this$0 Lcom/nd/android/u/tast/experience/calendar/SignInPopWindow;
invokestatic com/nd/android/u/tast/experience/calendar/SignInPopWindow/access$100(Lcom/nd/android/u/tast/experience/calendar/SignInPopWindow;)I
invokevirtual java/util/Calendar/set(II)V
aload 0
getfield com/nd/android/u/tast/experience/calendar/SignInPopWindow$2/this$0 Lcom/nd/android/u/tast/experience/calendar/SignInPopWindow;
invokestatic com/nd/android/u/tast/experience/calendar/SignInPopWindow/access$300(Lcom/nd/android/u/tast/experience/calendar/SignInPopWindow;)Landroid/widget/TextView;
invokevirtual android/widget/TextView/getText()Ljava/lang/CharSequence;
invokeinterface java/lang/CharSequence/toString()Ljava/lang/String; 0
astore 1
aload 0
getfield com/nd/android/u/tast/experience/calendar/SignInPopWindow$2/this$0 Lcom/nd/android/u/tast/experience/calendar/SignInPopWindow;
invokestatic com/nd/android/u/tast/experience/calendar/SignInPopWindow/access$400(Lcom/nd/android/u/tast/experience/calendar/SignInPopWindow;)V
aload 0
getfield com/nd/android/u/tast/experience/calendar/SignInPopWindow$2/this$0 Lcom/nd/android/u/tast/experience/calendar/SignInPopWindow;
aload 0
getfield com/nd/android/u/tast/experience/calendar/SignInPopWindow$2/this$0 Lcom/nd/android/u/tast/experience/calendar/SignInPopWindow;
invokestatic com/nd/android/u/tast/experience/calendar/SignInPopWindow/access$200(Lcom/nd/android/u/tast/experience/calendar/SignInPopWindow;)Ljava/util/Calendar;
invokevirtual java/util/Calendar/clone()Ljava/lang/Object;
checkcast java/util/Calendar
invokestatic com/nd/android/u/tast/experience/calendar/SignInPopWindow/access$502(Lcom/nd/android/u/tast/experience/calendar/SignInPopWindow;Ljava/util/Calendar;)Ljava/util/Calendar;
pop
aload 0
getfield com/nd/android/u/tast/experience/calendar/SignInPopWindow$2/this$0 Lcom/nd/android/u/tast/experience/calendar/SignInPopWindow;
aload 0
getfield com/nd/android/u/tast/experience/calendar/SignInPopWindow$2/this$0 Lcom/nd/android/u/tast/experience/calendar/SignInPopWindow;
aload 0
getfield com/nd/android/u/tast/experience/calendar/SignInPopWindow$2/this$0 Lcom/nd/android/u/tast/experience/calendar/SignInPopWindow;
invokestatic com/nd/android/u/tast/experience/calendar/SignInPopWindow/access$500(Lcom/nd/android/u/tast/experience/calendar/SignInPopWindow;)Ljava/util/Calendar;
invokevirtual com/nd/android/u/tast/experience/calendar/SignInPopWindow/GetEndDate(Ljava/util/Calendar;)Ljava/util/Calendar;
invokestatic com/nd/android/u/tast/experience/calendar/SignInPopWindow/access$602(Lcom/nd/android/u/tast/experience/calendar/SignInPopWindow;Ljava/util/Calendar;)Ljava/util/Calendar;
pop
aload 0
getfield com/nd/android/u/tast/experience/calendar/SignInPopWindow$2/this$0 Lcom/nd/android/u/tast/experience/calendar/SignInPopWindow;
aload 1
iconst_0
invokestatic com/nd/android/u/tast/experience/calendar/SignInPopWindow/access$700(Lcom/nd/android/u/tast/experience/calendar/SignInPopWindow;Ljava/lang/String;Z)V
return
.limit locals 2
.limit stack 3
.end method
