.bytecode 50.0
.class public synchronized com/nd/android/u/tast/experience/calendar/SignInPopWindow
.super java/lang/Object
.inner class inner com/nd/android/u/tast/experience/calendar/SignInPopWindow$1
.inner class inner com/nd/android/u/tast/experience/calendar/SignInPopWindow$2
.inner class inner com/nd/android/u/tast/experience/calendar/SignInPopWindow$3
.inner class inner com/nd/android/u/tast/experience/calendar/SignInPopWindow$3$1
.inner class inner com/nd/android/u/tast/experience/calendar/SignInPopWindow$4

.field private static final 'TAG' Ljava/lang/String; = "SignInPopWindow"

.field private 'BirthDay' I

.field private 'BirthMonth' I

.field private 'IsAnniversary' Z

.field private 'JoinDay' I

.field private 'JoinMonth' I

.field private 'Next_MonthOnClickListener' Landroid/view/View$OnClickListener;

.field private 'PopSignInList' Ljava/lang/String;

.field private 'PopTop_Date' Landroid/widget/TextView;

.field private 'Pre_MonthOnClickListener' Landroid/view/View$OnClickListener;

.field private 'SignInList' Ljava/lang/String;

.field private 'StrJoinDay' Ljava/lang/String;

.field private 'calPopStartDate' Ljava/util/Calendar;

.field private 'closePopWin_OnClickListener' Landroid/view/View$OnClickListener;

.field private 'flag' Z

.field private 'fotmat' Ljava/text/SimpleDateFormat;

.field private 'height' I

.field private 'iFirstDayOfWeek' I

.field private 'iMonthViewCurrentMonth' I

.field private 'iMonthViewCurrentYear' I

.field private 'layPopContent' Landroid/widget/LinearLayout;

.field private 'mContext' Landroid/app/Activity;

.field private 'mLayoutInflater' Landroid/view/LayoutInflater;

.field private 'mPopupWindow' Landroid/widget/PopupWindow;

.field private 'mView' Landroid/view/View;

.field private 'parentHandler' Landroid/os/Handler;

.field private 'pop_calCalendar' Ljava/util/Calendar;

.field private 'pop_calToday' Ljava/util/Calendar;

.field private 'pop_days' Ljava/util/ArrayList; signature "Ljava/util/ArrayList<Lcom/nd/android/u/tast/experience/calendar/DateWidgetDayCell;>;"

.field private 'pop_endDate' Ljava/util/Calendar;

.field private 'pop_startDate' Ljava/util/Calendar;

.field private 'shareDate' Ljava/lang/String;

.field private 'special_day_list' [Ljava/lang/String;

.field private 'width' I

.method public <init>(Landroid/app/Activity;)V
aload 0
invokespecial java/lang/Object/<init>()V
aload 0
new java/text/SimpleDateFormat
dup
ldc "yyyy\u5e74MM\u6708"
invokespecial java/text/SimpleDateFormat/<init>(Ljava/lang/String;)V
putfield com/nd/android/u/tast/experience/calendar/SignInPopWindow/fotmat Ljava/text/SimpleDateFormat;
aload 0
new java/util/ArrayList
dup
invokespecial java/util/ArrayList/<init>()V
putfield com/nd/android/u/tast/experience/calendar/SignInPopWindow/pop_days Ljava/util/ArrayList;
aload 0
invokestatic java/util/Calendar/getInstance()Ljava/util/Calendar;
putfield com/nd/android/u/tast/experience/calendar/SignInPopWindow/calPopStartDate Ljava/util/Calendar;
aload 0
invokestatic java/util/Calendar/getInstance()Ljava/util/Calendar;
putfield com/nd/android/u/tast/experience/calendar/SignInPopWindow/pop_calToday Ljava/util/Calendar;
aload 0
invokestatic java/util/Calendar/getInstance()Ljava/util/Calendar;
putfield com/nd/android/u/tast/experience/calendar/SignInPopWindow/pop_calCalendar Ljava/util/Calendar;
aload 0
aconst_null
putfield com/nd/android/u/tast/experience/calendar/SignInPopWindow/pop_startDate Ljava/util/Calendar;
aload 0
aconst_null
putfield com/nd/android/u/tast/experience/calendar/SignInPopWindow/pop_endDate Ljava/util/Calendar;
aload 0
iconst_0
putfield com/nd/android/u/tast/experience/calendar/SignInPopWindow/width I
aload 0
iconst_0
putfield com/nd/android/u/tast/experience/calendar/SignInPopWindow/height I
aload 0
iconst_0
putfield com/nd/android/u/tast/experience/calendar/SignInPopWindow/iMonthViewCurrentMonth I
aload 0
iconst_0
putfield com/nd/android/u/tast/experience/calendar/SignInPopWindow/iMonthViewCurrentYear I
aload 0
iconst_1
putfield com/nd/android/u/tast/experience/calendar/SignInPopWindow/iFirstDayOfWeek I
aload 0
iconst_0
putfield com/nd/android/u/tast/experience/calendar/SignInPopWindow/IsAnniversary Z
aload 0
ldc ""
putfield com/nd/android/u/tast/experience/calendar/SignInPopWindow/StrJoinDay Ljava/lang/String;
aload 0
iconst_0
putfield com/nd/android/u/tast/experience/calendar/SignInPopWindow/JoinMonth I
aload 0
iconst_0
putfield com/nd/android/u/tast/experience/calendar/SignInPopWindow/JoinDay I
aload 0
iconst_0
putfield com/nd/android/u/tast/experience/calendar/SignInPopWindow/BirthMonth I
aload 0
iconst_0
putfield com/nd/android/u/tast/experience/calendar/SignInPopWindow/BirthDay I
aload 0
ldc ""
putfield com/nd/android/u/tast/experience/calendar/SignInPopWindow/SignInList Ljava/lang/String;
aload 0
ldc ""
putfield com/nd/android/u/tast/experience/calendar/SignInPopWindow/PopSignInList Ljava/lang/String;
aload 0
aconst_null
putfield com/nd/android/u/tast/experience/calendar/SignInPopWindow/mLayoutInflater Landroid/view/LayoutInflater;
aload 0
aconst_null
putfield com/nd/android/u/tast/experience/calendar/SignInPopWindow/layPopContent Landroid/widget/LinearLayout;
aload 0
aconst_null
putfield com/nd/android/u/tast/experience/calendar/SignInPopWindow/PopTop_Date Landroid/widget/TextView;
aload 0
new com/nd/android/u/tast/experience/calendar/SignInPopWindow$1
dup
aload 0
invokespecial com/nd/android/u/tast/experience/calendar/SignInPopWindow$1/<init>(Lcom/nd/android/u/tast/experience/calendar/SignInPopWindow;)V
putfield com/nd/android/u/tast/experience/calendar/SignInPopWindow/Pre_MonthOnClickListener Landroid/view/View$OnClickListener;
aload 0
new com/nd/android/u/tast/experience/calendar/SignInPopWindow$2
dup
aload 0
invokespecial com/nd/android/u/tast/experience/calendar/SignInPopWindow$2/<init>(Lcom/nd/android/u/tast/experience/calendar/SignInPopWindow;)V
putfield com/nd/android/u/tast/experience/calendar/SignInPopWindow/Next_MonthOnClickListener Landroid/view/View$OnClickListener;
aload 0
new com/nd/android/u/tast/experience/calendar/SignInPopWindow$4
dup
aload 0
invokespecial com/nd/android/u/tast/experience/calendar/SignInPopWindow$4/<init>(Lcom/nd/android/u/tast/experience/calendar/SignInPopWindow;)V
putfield com/nd/android/u/tast/experience/calendar/SignInPopWindow/closePopWin_OnClickListener Landroid/view/View$OnClickListener;
aload 0
aload 1
putfield com/nd/android/u/tast/experience/calendar/SignInPopWindow/mContext Landroid/app/Activity;
aload 0
aload 1
ldc_w 16908290
invokevirtual android/app/Activity/findViewById(I)Landroid/view/View;
checkcast android/view/ViewGroup
iconst_0
invokevirtual android/view/ViewGroup/getChildAt(I)Landroid/view/View;
putfield com/nd/android/u/tast/experience/calendar/SignInPopWindow/mView Landroid/view/View;
getstatic com/product/android/business/ApplicationVariable/INSTANCE Lcom/product/android/business/ApplicationVariable;
invokevirtual com/product/android/business/ApplicationVariable/getIUser()Lcom/product/android/business/login/IGetUserInfo;
invokeinterface com/product/android/business/login/IGetUserInfo/getBindUser()Lcom/product/android/business/login/BindUser; 0
invokevirtual com/product/android/business/login/BindUser/getBirthday()Ljava/lang/String;
astore 2
aload 2
invokestatic com/common/android/utils/StringUtils/isEmpty(Ljava/lang/String;)Z
ifne L0
aload 0
aload 2
iconst_1
invokestatic com/nd/android/u/tast/TaskUtil/getMonthOrDate(Ljava/lang/String;I)I
putfield com/nd/android/u/tast/experience/calendar/SignInPopWindow/BirthMonth I
aload 0
aload 2
iconst_2
invokestatic com/nd/android/u/tast/TaskUtil/getMonthOrDate(Ljava/lang/String;I)I
putfield com/nd/android/u/tast/experience/calendar/SignInPopWindow/BirthDay I
L0:
aload 0
aload 1
invokevirtual android/app/Activity/getResources()Landroid/content/res/Resources;
getstatic com/nd/android/u/tasklib/R$array/special_day_list I
invokevirtual android/content/res/Resources/getStringArray(I)[Ljava/lang/String;
putfield com/nd/android/u/tast/experience/calendar/SignInPopWindow/special_day_list [Ljava/lang/String;
aload 0
new com/nd/android/u/tast/experience/calendar/SaveDate
dup
invokespecial com/nd/android/u/tast/experience/calendar/SaveDate/<init>()V
aload 1
invokevirtual com/nd/android/u/tast/experience/calendar/SaveDate/getDate(Landroid/content/Context;)Ljava/lang/String;
putfield com/nd/android/u/tast/experience/calendar/SignInPopWindow/shareDate Ljava/lang/String;
aload 0
invokespecial com/nd/android/u/tast/experience/calendar/SignInPopWindow/initPopup()V
aload 0
invokevirtual com/nd/android/u/tast/experience/calendar/SignInPopWindow/initView()V
return
.limit locals 3
.limit stack 4
.end method

.method private Add(Ljava/util/Date;II)Ljava/util/Date;
invokestatic java/util/Calendar/getInstance()Ljava/util/Calendar;
astore 4
aload 4
aload 1
invokevirtual java/util/Calendar/setTime(Ljava/util/Date;)V
aload 4
iload 2
iload 3
invokevirtual java/util/Calendar/add(II)V
aload 4
invokevirtual java/util/Calendar/getTime()Ljava/util/Date;
areturn
.limit locals 5
.limit stack 3
.end method

.method private GetNumFromDate(Ljava/util/Calendar;Ljava/util/Calendar;)I
aload 1
invokevirtual java/util/Calendar/clone()Ljava/lang/Object;
checkcast java/util/Calendar
astore 1
aload 2
invokevirtual java/util/Calendar/clone()Ljava/lang/Object;
checkcast java/util/Calendar
astore 2
aload 0
aload 1
invokespecial com/nd/android/u/tast/experience/calendar/SignInPopWindow/setTimeToMidnight(Ljava/util/Calendar;)V
aload 0
aload 2
invokespecial com/nd/android/u/tast/experience/calendar/SignInPopWindow/setTimeToMidnight(Ljava/util/Calendar;)V
aload 0
aload 1
invokevirtual java/util/Calendar/getTimeInMillis()J
aload 2
invokevirtual java/util/Calendar/getTimeInMillis()J
lsub
invokespecial com/nd/android/u/tast/experience/calendar/SignInPopWindow/millisecondsToDays(J)I
ireturn
.limit locals 3
.limit stack 5
.end method

.method private UpdatePopCurrentMonthDisplay()V
new java/lang/StringBuilder
dup
invokespecial java/lang/StringBuilder/<init>()V
aload 0
getfield com/nd/android/u/tast/experience/calendar/SignInPopWindow/calPopStartDate Ljava/util/Calendar;
iconst_1
invokevirtual java/util/Calendar/get(I)I
invokevirtual java/lang/StringBuilder/append(I)Ljava/lang/StringBuilder;
ldc "\u5e74"
invokevirtual java/lang/StringBuilder/append(Ljava/lang/String;)Ljava/lang/StringBuilder;
aload 0
getfield com/nd/android/u/tast/experience/calendar/SignInPopWindow/calPopStartDate Ljava/util/Calendar;
iconst_2
invokevirtual java/util/Calendar/get(I)I
iconst_1
iadd
invokevirtual java/lang/StringBuilder/append(I)Ljava/lang/StringBuilder;
ldc "\u6708"
invokevirtual java/lang/StringBuilder/append(Ljava/lang/String;)Ljava/lang/StringBuilder;
invokevirtual java/lang/StringBuilder/toString()Ljava/lang/String;
astore 1
aload 0
getfield com/nd/android/u/tast/experience/calendar/SignInPopWindow/PopTop_Date Landroid/widget/TextView;
aload 1
invokevirtual android/widget/TextView/setText(Ljava/lang/CharSequence;)V
return
.limit locals 2
.limit stack 3
.end method

.method private UpdatePopStartDateForMonth()V
aload 0
aload 0
getfield com/nd/android/u/tast/experience/calendar/SignInPopWindow/calPopStartDate Ljava/util/Calendar;
iconst_2
invokevirtual java/util/Calendar/get(I)I
putfield com/nd/android/u/tast/experience/calendar/SignInPopWindow/iMonthViewCurrentMonth I
aload 0
aload 0
getfield com/nd/android/u/tast/experience/calendar/SignInPopWindow/calPopStartDate Ljava/util/Calendar;
iconst_1
invokevirtual java/util/Calendar/get(I)I
putfield com/nd/android/u/tast/experience/calendar/SignInPopWindow/iMonthViewCurrentYear I
aload 0
getfield com/nd/android/u/tast/experience/calendar/SignInPopWindow/calPopStartDate Ljava/util/Calendar;
iconst_5
iconst_1
invokevirtual java/util/Calendar/set(II)V
aload 0
getfield com/nd/android/u/tast/experience/calendar/SignInPopWindow/calPopStartDate Ljava/util/Calendar;
bipush 11
iconst_0
invokevirtual java/util/Calendar/set(II)V
aload 0
getfield com/nd/android/u/tast/experience/calendar/SignInPopWindow/calPopStartDate Ljava/util/Calendar;
bipush 12
iconst_0
invokevirtual java/util/Calendar/set(II)V
aload 0
getfield com/nd/android/u/tast/experience/calendar/SignInPopWindow/calPopStartDate Ljava/util/Calendar;
bipush 13
iconst_0
invokevirtual java/util/Calendar/set(II)V
aload 0
invokespecial com/nd/android/u/tast/experience/calendar/SignInPopWindow/UpdatePopCurrentMonthDisplay()V
iconst_0
istore 1
aload 0
getfield com/nd/android/u/tast/experience/calendar/SignInPopWindow/iFirstDayOfWeek I
istore 3
iload 3
iconst_2
if_icmpne L0
aload 0
getfield com/nd/android/u/tast/experience/calendar/SignInPopWindow/calPopStartDate Ljava/util/Calendar;
bipush 7
invokevirtual java/util/Calendar/get(I)I
iconst_2
isub
istore 2
iload 2
istore 1
iload 2
ifge L0
bipush 6
istore 1
L0:
iload 3
iconst_1
if_icmpne L1
aload 0
getfield com/nd/android/u/tast/experience/calendar/SignInPopWindow/calPopStartDate Ljava/util/Calendar;
bipush 7
invokevirtual java/util/Calendar/get(I)I
iconst_1
isub
istore 2
iload 2
istore 1
iload 2
ifge L1
bipush 6
istore 1
L1:
aload 0
getfield com/nd/android/u/tast/experience/calendar/SignInPopWindow/calPopStartDate Ljava/util/Calendar;
bipush 7
iload 1
ineg
invokevirtual java/util/Calendar/add(II)V
return
.limit locals 4
.limit stack 3
.end method

.method static synthetic access$000(Lcom/nd/android/u/tast/experience/calendar/SignInPopWindow;)I
aload 0
getfield com/nd/android/u/tast/experience/calendar/SignInPopWindow/iMonthViewCurrentMonth I
ireturn
.limit locals 1
.limit stack 1
.end method

.method static synthetic access$002(Lcom/nd/android/u/tast/experience/calendar/SignInPopWindow;I)I
aload 0
iload 1
putfield com/nd/android/u/tast/experience/calendar/SignInPopWindow/iMonthViewCurrentMonth I
iload 1
ireturn
.limit locals 2
.limit stack 2
.end method

.method static synthetic access$008(Lcom/nd/android/u/tast/experience/calendar/SignInPopWindow;)I
aload 0
getfield com/nd/android/u/tast/experience/calendar/SignInPopWindow/iMonthViewCurrentMonth I
istore 1
aload 0
iload 1
iconst_1
iadd
putfield com/nd/android/u/tast/experience/calendar/SignInPopWindow/iMonthViewCurrentMonth I
iload 1
ireturn
.limit locals 2
.limit stack 3
.end method

.method static synthetic access$010(Lcom/nd/android/u/tast/experience/calendar/SignInPopWindow;)I
aload 0
getfield com/nd/android/u/tast/experience/calendar/SignInPopWindow/iMonthViewCurrentMonth I
istore 1
aload 0
iload 1
iconst_1
isub
putfield com/nd/android/u/tast/experience/calendar/SignInPopWindow/iMonthViewCurrentMonth I
iload 1
ireturn
.limit locals 2
.limit stack 3
.end method

.method static synthetic access$100(Lcom/nd/android/u/tast/experience/calendar/SignInPopWindow;)I
aload 0
getfield com/nd/android/u/tast/experience/calendar/SignInPopWindow/iMonthViewCurrentYear I
ireturn
.limit locals 1
.limit stack 1
.end method

.method static synthetic access$1000(Lcom/nd/android/u/tast/experience/calendar/SignInPopWindow;)V
aload 0
invokespecial com/nd/android/u/tast/experience/calendar/SignInPopWindow/closePopWin()V
return
.limit locals 1
.limit stack 1
.end method

.method static synthetic access$108(Lcom/nd/android/u/tast/experience/calendar/SignInPopWindow;)I
aload 0
getfield com/nd/android/u/tast/experience/calendar/SignInPopWindow/iMonthViewCurrentYear I
istore 1
aload 0
iload 1
iconst_1
iadd
putfield com/nd/android/u/tast/experience/calendar/SignInPopWindow/iMonthViewCurrentYear I
iload 1
ireturn
.limit locals 2
.limit stack 3
.end method

.method static synthetic access$110(Lcom/nd/android/u/tast/experience/calendar/SignInPopWindow;)I
aload 0
getfield com/nd/android/u/tast/experience/calendar/SignInPopWindow/iMonthViewCurrentYear I
istore 1
aload 0
iload 1
iconst_1
isub
putfield com/nd/android/u/tast/experience/calendar/SignInPopWindow/iMonthViewCurrentYear I
iload 1
ireturn
.limit locals 2
.limit stack 3
.end method

.method static synthetic access$200(Lcom/nd/android/u/tast/experience/calendar/SignInPopWindow;)Ljava/util/Calendar;
aload 0
getfield com/nd/android/u/tast/experience/calendar/SignInPopWindow/calPopStartDate Ljava/util/Calendar;
areturn
.limit locals 1
.limit stack 1
.end method

.method static synthetic access$300(Lcom/nd/android/u/tast/experience/calendar/SignInPopWindow;)Landroid/widget/TextView;
aload 0
getfield com/nd/android/u/tast/experience/calendar/SignInPopWindow/PopTop_Date Landroid/widget/TextView;
areturn
.limit locals 1
.limit stack 1
.end method

.method static synthetic access$400(Lcom/nd/android/u/tast/experience/calendar/SignInPopWindow;)V
aload 0
invokespecial com/nd/android/u/tast/experience/calendar/SignInPopWindow/UpdatePopStartDateForMonth()V
return
.limit locals 1
.limit stack 1
.end method

.method static synthetic access$500(Lcom/nd/android/u/tast/experience/calendar/SignInPopWindow;)Ljava/util/Calendar;
aload 0
getfield com/nd/android/u/tast/experience/calendar/SignInPopWindow/pop_startDate Ljava/util/Calendar;
areturn
.limit locals 1
.limit stack 1
.end method

.method static synthetic access$502(Lcom/nd/android/u/tast/experience/calendar/SignInPopWindow;Ljava/util/Calendar;)Ljava/util/Calendar;
aload 0
aload 1
putfield com/nd/android/u/tast/experience/calendar/SignInPopWindow/pop_startDate Ljava/util/Calendar;
aload 1
areturn
.limit locals 2
.limit stack 2
.end method

.method static synthetic access$602(Lcom/nd/android/u/tast/experience/calendar/SignInPopWindow;Ljava/util/Calendar;)Ljava/util/Calendar;
aload 0
aload 1
putfield com/nd/android/u/tast/experience/calendar/SignInPopWindow/pop_endDate Ljava/util/Calendar;
aload 1
areturn
.limit locals 2
.limit stack 2
.end method

.method static synthetic access$700(Lcom/nd/android/u/tast/experience/calendar/SignInPopWindow;Ljava/lang/String;Z)V
aload 0
aload 1
iload 2
invokespecial com/nd/android/u/tast/experience/calendar/SignInPopWindow/updateCalendar(Ljava/lang/String;Z)V
return
.limit locals 3
.limit stack 3
.end method

.method static synthetic access$800(Lcom/nd/android/u/tast/experience/calendar/SignInPopWindow;)Ljava/lang/String;
aload 0
getfield com/nd/android/u/tast/experience/calendar/SignInPopWindow/PopSignInList Ljava/lang/String;
areturn
.limit locals 1
.limit stack 1
.end method

.method static synthetic access$802(Lcom/nd/android/u/tast/experience/calendar/SignInPopWindow;Ljava/lang/String;)Ljava/lang/String;
aload 0
aload 1
putfield com/nd/android/u/tast/experience/calendar/SignInPopWindow/PopSignInList Ljava/lang/String;
aload 1
areturn
.limit locals 2
.limit stack 2
.end method

.method static synthetic access$900(Lcom/nd/android/u/tast/experience/calendar/SignInPopWindow;)Landroid/app/Activity;
aload 0
getfield com/nd/android/u/tast/experience/calendar/SignInPopWindow/mContext Landroid/app/Activity;
areturn
.limit locals 1
.limit stack 1
.end method

.method private closeButtonLayout(III)Landroid/widget/LinearLayout;
new android/widget/LinearLayout
dup
aload 0
getfield com/nd/android/u/tast/experience/calendar/SignInPopWindow/mContext Landroid/app/Activity;
invokespecial android/widget/LinearLayout/<init>(Landroid/content/Context;)V
astore 4
aload 4
new android/widget/LinearLayout$LayoutParams
dup
iload 2
iload 3
invokespecial android/widget/LinearLayout$LayoutParams/<init>(II)V
invokevirtual android/widget/LinearLayout/setLayoutParams(Landroid/view/ViewGroup$LayoutParams;)V
aload 4
iload 1
invokevirtual android/widget/LinearLayout/setOrientation(I)V
aload 4
areturn
.limit locals 5
.limit stack 5
.end method

.method private closePopWin()V
aload 0
getfield com/nd/android/u/tast/experience/calendar/SignInPopWindow/mPopupWindow Landroid/widget/PopupWindow;
ifnull L0
aload 0
getfield com/nd/android/u/tast/experience/calendar/SignInPopWindow/mPopupWindow Landroid/widget/PopupWindow;
invokevirtual android/widget/PopupWindow/isShowing()Z
ifeq L0
aload 0
getfield com/nd/android/u/tast/experience/calendar/SignInPopWindow/mPopupWindow Landroid/widget/PopupWindow;
invokevirtual android/widget/PopupWindow/dismiss()V
L0:
return
.limit locals 1
.limit stack 1
.end method

.method private createLayout(I)Landroid/widget/LinearLayout;
new android/widget/LinearLayout
dup
aload 0
getfield com/nd/android/u/tast/experience/calendar/SignInPopWindow/mContext Landroid/app/Activity;
invokespecial android/widget/LinearLayout/<init>(Landroid/content/Context;)V
astore 2
aload 2
new android/widget/LinearLayout$LayoutParams
dup
iconst_m1
bipush -2
invokespecial android/widget/LinearLayout$LayoutParams/<init>(II)V
invokevirtual android/widget/LinearLayout/setLayoutParams(Landroid/view/ViewGroup$LayoutParams;)V
aload 2
iload 1
invokevirtual android/widget/LinearLayout/setOrientation(I)V
aload 2
areturn
.limit locals 3
.limit stack 5
.end method

.method private drawCalendarHeader(Z)Landroid/view/View;
aload 0
iconst_0
invokespecial com/nd/android/u/tast/experience/calendar/SignInPopWindow/createLayout(I)Landroid/widget/LinearLayout;
astore 3
iconst_0
istore 2
L0:
iload 2
bipush 7
if_icmpge L1
new com/nd/android/u/tast/experience/calendar/DateWidgetDayHeader
dup
aload 0
getfield com/nd/android/u/tast/experience/calendar/SignInPopWindow/mContext Landroid/app/Activity;
aload 0
getfield com/nd/android/u/tast/experience/calendar/SignInPopWindow/width I
aload 0
getfield com/nd/android/u/tast/experience/calendar/SignInPopWindow/height I
iload 1
invokespecial com/nd/android/u/tast/experience/calendar/DateWidgetDayHeader/<init>(Landroid/content/Context;IIZ)V
astore 4
aload 4
iload 2
aload 0
getfield com/nd/android/u/tast/experience/calendar/SignInPopWindow/iFirstDayOfWeek I
invokestatic com/nd/android/u/tast/experience/calendar/DayStyle/getWeekDay(II)I
invokevirtual com/nd/android/u/tast/experience/calendar/DateWidgetDayHeader/setData(I)V
aload 3
aload 4
invokevirtual android/widget/LinearLayout/addView(Landroid/view/View;)V
iload 2
iconst_1
iadd
istore 2
goto L0
L1:
aload 3
areturn
.limit locals 5
.limit stack 6
.end method

.method private drawCalendarMain()Landroid/view/View;
aload 0
aload 0
iconst_1
invokespecial com/nd/android/u/tast/experience/calendar/SignInPopWindow/createLayout(I)Landroid/widget/LinearLayout;
putfield com/nd/android/u/tast/experience/calendar/SignInPopWindow/layPopContent Landroid/widget/LinearLayout;
aload 0
getfield com/nd/android/u/tast/experience/calendar/SignInPopWindow/layPopContent Landroid/widget/LinearLayout;
aload 0
iconst_1
invokespecial com/nd/android/u/tast/experience/calendar/SignInPopWindow/drawCalendarHeader(Z)Landroid/view/View;
invokevirtual android/widget/LinearLayout/addView(Landroid/view/View;)V
aload 0
getfield com/nd/android/u/tast/experience/calendar/SignInPopWindow/pop_days Ljava/util/ArrayList;
invokevirtual java/util/ArrayList/clear()V
iconst_0
istore 1
L0:
iload 1
bipush 6
if_icmpge L1
aload 0
getfield com/nd/android/u/tast/experience/calendar/SignInPopWindow/layPopContent Landroid/widget/LinearLayout;
aload 0
invokespecial com/nd/android/u/tast/experience/calendar/SignInPopWindow/drawCalendarRow()Landroid/view/View;
invokevirtual android/widget/LinearLayout/addView(Landroid/view/View;)V
iload 1
iconst_1
iadd
istore 1
goto L0
L1:
aload 0
getfield com/nd/android/u/tast/experience/calendar/SignInPopWindow/layPopContent Landroid/widget/LinearLayout;
areturn
.limit locals 2
.limit stack 3
.end method

.method private drawCalendarRow()Landroid/view/View;
aload 0
iconst_0
invokespecial com/nd/android/u/tast/experience/calendar/SignInPopWindow/createLayout(I)Landroid/widget/LinearLayout;
astore 2
iconst_0
istore 1
L0:
iload 1
bipush 7
if_icmpge L1
new com/nd/android/u/tast/experience/calendar/DateWidgetDayCell
dup
aload 0
getfield com/nd/android/u/tast/experience/calendar/SignInPopWindow/mContext Landroid/app/Activity;
aload 0
getfield com/nd/android/u/tast/experience/calendar/SignInPopWindow/width I
aload 0
getfield com/nd/android/u/tast/experience/calendar/SignInPopWindow/height I
invokespecial com/nd/android/u/tast/experience/calendar/DateWidgetDayCell/<init>(Landroid/content/Context;II)V
astore 3
aload 0
getfield com/nd/android/u/tast/experience/calendar/SignInPopWindow/pop_days Ljava/util/ArrayList;
aload 3
invokevirtual java/util/ArrayList/add(Ljava/lang/Object;)Z
pop
aload 2
aload 3
invokevirtual android/widget/LinearLayout/addView(Landroid/view/View;)V
iload 1
iconst_1
iadd
istore 1
goto L0
L1:
aload 2
areturn
.limit locals 4
.limit stack 5
.end method

.method private drawCalendarStartDate()Ljava/util/Calendar;
.catch java/text/ParseException from L0 to L1 using L2
aload 0
getfield com/nd/android/u/tast/experience/calendar/SignInPopWindow/shareDate Ljava/lang/String;
ifnull L3
L0:
new java/text/SimpleDateFormat
dup
ldc "yyyy-MM-dd"
invokespecial java/text/SimpleDateFormat/<init>(Ljava/lang/String;)V
aload 0
getfield com/nd/android/u/tast/experience/calendar/SignInPopWindow/shareDate Ljava/lang/String;
invokevirtual java/text/SimpleDateFormat/parse(Ljava/lang/String;)Ljava/util/Date;
astore 1
aload 0
getfield com/nd/android/u/tast/experience/calendar/SignInPopWindow/pop_calToday Ljava/util/Calendar;
aload 1
invokevirtual java/util/Date/getTime()J
invokevirtual java/util/Calendar/setTimeInMillis(J)V
aload 0
getfield com/nd/android/u/tast/experience/calendar/SignInPopWindow/calPopStartDate Ljava/util/Calendar;
aload 1
invokevirtual java/util/Date/getTime()J
invokevirtual java/util/Calendar/setTimeInMillis(J)V
L1:
aload 0
getfield com/nd/android/u/tast/experience/calendar/SignInPopWindow/pop_calToday Ljava/util/Calendar;
aload 0
getfield com/nd/android/u/tast/experience/calendar/SignInPopWindow/iFirstDayOfWeek I
invokevirtual java/util/Calendar/setFirstDayOfWeek(I)V
aload 0
getfield com/nd/android/u/tast/experience/calendar/SignInPopWindow/calPopStartDate Ljava/util/Calendar;
aload 0
getfield com/nd/android/u/tast/experience/calendar/SignInPopWindow/iFirstDayOfWeek I
invokevirtual java/util/Calendar/setFirstDayOfWeek(I)V
aload 0
invokespecial com/nd/android/u/tast/experience/calendar/SignInPopWindow/UpdatePopStartDateForMonth()V
aload 0
getfield com/nd/android/u/tast/experience/calendar/SignInPopWindow/calPopStartDate Ljava/util/Calendar;
areturn
L2:
astore 1
aload 1
invokevirtual java/text/ParseException/printStackTrace()V
aload 0
getfield com/nd/android/u/tast/experience/calendar/SignInPopWindow/pop_calToday Ljava/util/Calendar;
invokestatic java/lang/System/currentTimeMillis()J
invokevirtual java/util/Calendar/setTimeInMillis(J)V
aload 0
getfield com/nd/android/u/tast/experience/calendar/SignInPopWindow/calPopStartDate Ljava/util/Calendar;
invokestatic java/lang/System/currentTimeMillis()J
invokevirtual java/util/Calendar/setTimeInMillis(J)V
goto L1
L3:
aload 0
getfield com/nd/android/u/tast/experience/calendar/SignInPopWindow/pop_calToday Ljava/util/Calendar;
invokestatic java/lang/System/currentTimeMillis()J
invokevirtual java/util/Calendar/setTimeInMillis(J)V
aload 0
getfield com/nd/android/u/tast/experience/calendar/SignInPopWindow/calPopStartDate Ljava/util/Calendar;
invokestatic java/lang/System/currentTimeMillis()J
invokevirtual java/util/Calendar/setTimeInMillis(J)V
goto L1
.limit locals 2
.limit stack 3
.end method

.method public static getMonthOrDate(Ljava/lang/String;I)I
aload 0
ldc " "
invokevirtual java/lang/String/split(Ljava/lang/String;)[Ljava/lang/String;
iconst_0
aaload
ldc "-"
invokevirtual java/lang/String/split(Ljava/lang/String;)[Ljava/lang/String;
iload 1
aaload
invokestatic java/lang/Integer/parseInt(Ljava/lang/String;)I
ireturn
.limit locals 2
.limit stack 2
.end method

.method private getTopDataPopView()Landroid/view/View;
aload 0
getfield com/nd/android/u/tast/experience/calendar/SignInPopWindow/mLayoutInflater Landroid/view/LayoutInflater;
getstatic com/nd/android/u/tasklib/R$layout/calendar_topdateview I
aconst_null
invokevirtual android/view/LayoutInflater/inflate(ILandroid/view/ViewGroup;)Landroid/view/View;
astore 1
aload 1
getstatic com/nd/android/u/tasklib/R$id/pre_month_layout I
invokevirtual android/view/View/findViewById(I)Landroid/view/View;
checkcast android/widget/RelativeLayout
astore 2
aload 1
getstatic com/nd/android/u/tasklib/R$id/next_month_layout I
invokevirtual android/view/View/findViewById(I)Landroid/view/View;
checkcast android/widget/RelativeLayout
astore 3
aload 0
aload 1
getstatic com/nd/android/u/tasklib/R$id/pop_date_tv I
invokevirtual android/view/View/findViewById(I)Landroid/view/View;
checkcast android/widget/TextView
putfield com/nd/android/u/tast/experience/calendar/SignInPopWindow/PopTop_Date Landroid/widget/TextView;
aload 0
getfield com/nd/android/u/tast/experience/calendar/SignInPopWindow/PopTop_Date Landroid/widget/TextView;
aload 0
getfield com/nd/android/u/tast/experience/calendar/SignInPopWindow/mContext Landroid/app/Activity;
invokevirtual android/app/Activity/getResources()Landroid/content/res/Resources;
getstatic com/nd/android/u/tasklib/R$color/calendar_yearsAndmonths_color I
invokevirtual android/content/res/Resources/getColor(I)I
invokevirtual android/widget/TextView/setTextColor(I)V
aload 2
aload 0
getfield com/nd/android/u/tast/experience/calendar/SignInPopWindow/Pre_MonthOnClickListener Landroid/view/View$OnClickListener;
invokevirtual android/widget/RelativeLayout/setOnClickListener(Landroid/view/View$OnClickListener;)V
aload 3
aload 0
getfield com/nd/android/u/tast/experience/calendar/SignInPopWindow/Next_MonthOnClickListener Landroid/view/View$OnClickListener;
invokevirtual android/widget/RelativeLayout/setOnClickListener(Landroid/view/View$OnClickListener;)V
aload 1
areturn
.limit locals 4
.limit stack 3
.end method

.method public static getYearOrMonth(Ljava/util/Date;I)I
aload 0
invokestatic com/nd/android/u/tast/buss/TaskPubFunction/DateFormat(Ljava/util/Date;)Ljava/lang/String;
ldc "-"
invokevirtual java/lang/String/split(Ljava/lang/String;)[Ljava/lang/String;
astore 0
iconst_m1
istore 2
iload 1
ifne L0
aload 0
iconst_0
aaload
invokestatic java/lang/Integer/parseInt(Ljava/lang/String;)I
istore 2
L0:
iload 1
iconst_1
if_icmpne L1
aload 0
iconst_1
aaload
invokestatic java/lang/Integer/parseInt(Ljava/lang/String;)I
istore 2
L1:
iload 2
ireturn
.limit locals 3
.limit stack 2
.end method

.method private initPopup()V
aload 0
aload 0
getfield com/nd/android/u/tast/experience/calendar/SignInPopWindow/mContext Landroid/app/Activity;
invokevirtual android/app/Activity/getWindowManager()Landroid/view/WindowManager;
invokeinterface android/view/WindowManager/getDefaultDisplay()Landroid/view/Display; 0
invokevirtual android/view/Display/getWidth()I
aload 0
getfield com/nd/android/u/tast/experience/calendar/SignInPopWindow/mContext Landroid/app/Activity;
invokevirtual android/app/Activity/getResources()Landroid/content/res/Resources;
getstatic com/nd/android/u/tasklib/R$dimen/pop_margin I
invokevirtual android/content/res/Resources/getDimension(I)F
f2i
iconst_2
imul
isub
bipush 7
idiv
putfield com/nd/android/u/tast/experience/calendar/SignInPopWindow/width I
aload 0
aload 0
getfield com/nd/android/u/tast/experience/calendar/SignInPopWindow/width I
iconst_2
imul
iconst_3
idiv
putfield com/nd/android/u/tast/experience/calendar/SignInPopWindow/height I
return
.limit locals 1
.limit stack 4
.end method

.method private millisecondsToDays(J)I
lload 1
ldc2_w 86400000L
ldiv
l2f
invokestatic java/lang/Math/round(F)I
ireturn
.limit locals 3
.limit stack 4
.end method

.method private setTimeToMidnight(Ljava/util/Calendar;)V
aload 1
bipush 11
iconst_0
invokevirtual java/util/Calendar/set(II)V
aload 1
bipush 12
iconst_0
invokevirtual java/util/Calendar/set(II)V
aload 1
bipush 13
iconst_0
invokevirtual java/util/Calendar/set(II)V
aload 1
bipush 14
iconst_0
invokevirtual java/util/Calendar/set(II)V
return
.limit locals 2
.limit stack 3
.end method

.method private updateCalendar(II)V
new java/lang/Thread
dup
new com/nd/android/u/tast/experience/calendar/SignInPopWindow$3
dup
aload 0
iload 1
iload 2
invokespecial com/nd/android/u/tast/experience/calendar/SignInPopWindow$3/<init>(Lcom/nd/android/u/tast/experience/calendar/SignInPopWindow;II)V
invokespecial java/lang/Thread/<init>(Ljava/lang/Runnable;)V
invokevirtual java/lang/Thread/start()V
return
.limit locals 3
.limit stack 7
.end method

.method private updateCalendar(Ljava/lang/String;Z)V
.catch java/text/ParseException from L0 to L1 using L2
L0:
aload 0
getfield com/nd/android/u/tast/experience/calendar/SignInPopWindow/fotmat Ljava/text/SimpleDateFormat;
aload 1
invokevirtual java/text/SimpleDateFormat/parse(Ljava/lang/String;)Ljava/util/Date;
astore 1
L1:
iload 2
ifeq L3
iconst_m1
istore 3
L4:
aload 0
aload 1
iconst_2
iload 3
invokespecial com/nd/android/u/tast/experience/calendar/SignInPopWindow/Add(Ljava/util/Date;II)Ljava/util/Date;
astore 1
aload 0
aload 1
iconst_0
invokestatic com/nd/android/u/tast/experience/calendar/SignInPopWindow/getYearOrMonth(Ljava/util/Date;I)I
aload 1
iconst_1
invokestatic com/nd/android/u/tast/experience/calendar/SignInPopWindow/getYearOrMonth(Ljava/util/Date;I)I
invokespecial com/nd/android/u/tast/experience/calendar/SignInPopWindow/updateCalendar(II)V
return
L2:
astore 1
return
L3:
iconst_1
istore 3
goto L4
.limit locals 4
.limit stack 4
.end method

.method protected GetDateShortString(Ljava/util/Calendar;)Ljava/lang/String;
new java/lang/StringBuilder
dup
invokespecial java/lang/StringBuilder/<init>()V
aload 1
iconst_1
invokevirtual java/util/Calendar/get(I)I
invokevirtual java/lang/StringBuilder/append(I)Ljava/lang/StringBuilder;
ldc "/"
invokevirtual java/lang/StringBuilder/append(Ljava/lang/String;)Ljava/lang/StringBuilder;
invokevirtual java/lang/StringBuilder/toString()Ljava/lang/String;
astore 2
new java/lang/StringBuilder
dup
invokespecial java/lang/StringBuilder/<init>()V
aload 2
invokevirtual java/lang/StringBuilder/append(Ljava/lang/String;)Ljava/lang/StringBuilder;
aload 1
iconst_2
invokevirtual java/util/Calendar/get(I)I
iconst_1
iadd
invokevirtual java/lang/StringBuilder/append(I)Ljava/lang/StringBuilder;
ldc "/"
invokevirtual java/lang/StringBuilder/append(Ljava/lang/String;)Ljava/lang/StringBuilder;
invokevirtual java/lang/StringBuilder/toString()Ljava/lang/String;
astore 2
new java/lang/StringBuilder
dup
invokespecial java/lang/StringBuilder/<init>()V
aload 2
invokevirtual java/lang/StringBuilder/append(Ljava/lang/String;)Ljava/lang/StringBuilder;
aload 1
iconst_5
invokevirtual java/util/Calendar/get(I)I
invokevirtual java/lang/StringBuilder/append(I)Ljava/lang/StringBuilder;
invokevirtual java/lang/StringBuilder/toString()Ljava/lang/String;
areturn
.limit locals 3
.limit stack 3
.end method

.method public GetEndDate(Ljava/util/Calendar;)Ljava/util/Calendar;
invokestatic java/util/Calendar/getInstance()Ljava/util/Calendar;
pop
aload 1
invokevirtual java/util/Calendar/clone()Ljava/lang/Object;
checkcast java/util/Calendar
astore 1
aload 1
iconst_5
bipush 41
invokevirtual java/util/Calendar/add(II)V
aload 1
areturn
.limit locals 2
.limit stack 3
.end method

.method public GetStartDate()Ljava/util/Calendar;
invokestatic java/util/Calendar/getInstance()Ljava/util/Calendar;
astore 3
aload 3
iconst_5
iconst_1
invokevirtual java/util/Calendar/set(II)V
aload 3
bipush 11
iconst_0
invokevirtual java/util/Calendar/set(II)V
aload 3
bipush 12
iconst_0
invokevirtual java/util/Calendar/set(II)V
aload 3
bipush 13
iconst_0
invokevirtual java/util/Calendar/set(II)V
aload 3
iconst_2
invokevirtual java/util/Calendar/setFirstDayOfWeek(I)V
aload 3
bipush 7
invokevirtual java/util/Calendar/get(I)I
iconst_2
isub
istore 2
iload 2
istore 1
iload 2
ifge L0
bipush 6
istore 1
L0:
aload 3
bipush 7
iload 1
ineg
invokevirtual java/util/Calendar/add(II)V
aload 3
areturn
.limit locals 4
.limit stack 3
.end method

.method public GetTodayDate()Ljava/util/Calendar;
invokestatic java/util/Calendar/getInstance()Ljava/util/Calendar;
astore 1
aload 1
bipush 11
iconst_0
invokevirtual java/util/Calendar/set(II)V
aload 1
bipush 12
iconst_0
invokevirtual java/util/Calendar/set(II)V
aload 1
bipush 13
iconst_0
invokevirtual java/util/Calendar/set(II)V
aload 1
iconst_2
invokevirtual java/util/Calendar/setFirstDayOfWeek(I)V
aload 1
areturn
.limit locals 2
.limit stack 3
.end method

.method public hidePopWindow()V
aload 0
getfield com/nd/android/u/tast/experience/calendar/SignInPopWindow/mPopupWindow Landroid/widget/PopupWindow;
invokevirtual android/widget/PopupWindow/isShowing()Z
ifeq L0
aload 0
getfield com/nd/android/u/tast/experience/calendar/SignInPopWindow/mPopupWindow Landroid/widget/PopupWindow;
invokevirtual android/widget/PopupWindow/dismiss()V
L0:
return
.limit locals 1
.limit stack 1
.end method

.method public init()V
.catch java/text/ParseException from L0 to L1 using L2
L0:
aload 0
getfield com/nd/android/u/tast/experience/calendar/SignInPopWindow/fotmat Ljava/text/SimpleDateFormat;
aload 0
getfield com/nd/android/u/tast/experience/calendar/SignInPopWindow/PopTop_Date Landroid/widget/TextView;
invokevirtual android/widget/TextView/getText()Ljava/lang/CharSequence;
invokeinterface java/lang/CharSequence/toString()Ljava/lang/String; 0
invokevirtual java/text/SimpleDateFormat/parse(Ljava/lang/String;)Ljava/util/Date;
astore 1
L1:
aload 0
aload 1
iconst_0
invokestatic com/nd/android/u/tast/experience/calendar/SignInPopWindow/getYearOrMonth(Ljava/util/Date;I)I
aload 1
iconst_1
invokestatic com/nd/android/u/tast/experience/calendar/SignInPopWindow/getYearOrMonth(Ljava/util/Date;I)I
invokespecial com/nd/android/u/tast/experience/calendar/SignInPopWindow/updateCalendar(II)V
return
L2:
astore 1
return
.limit locals 2
.limit stack 4
.end method

.method public initView()V
aload 0
aconst_null
putfield com/nd/android/u/tast/experience/calendar/SignInPopWindow/mPopupWindow Landroid/widget/PopupWindow;
aload 0
getfield com/nd/android/u/tast/experience/calendar/SignInPopWindow/mPopupWindow Landroid/widget/PopupWindow;
ifnonnull L0
aload 0
aload 0
invokevirtual com/nd/android/u/tast/experience/calendar/SignInPopWindow/GetStartDate()Ljava/util/Calendar;
putfield com/nd/android/u/tast/experience/calendar/SignInPopWindow/pop_startDate Ljava/util/Calendar;
aload 0
aload 0
invokevirtual com/nd/android/u/tast/experience/calendar/SignInPopWindow/GetTodayDate()Ljava/util/Calendar;
putfield com/nd/android/u/tast/experience/calendar/SignInPopWindow/pop_calToday Ljava/util/Calendar;
aload 0
aload 0
aload 0
getfield com/nd/android/u/tast/experience/calendar/SignInPopWindow/pop_startDate Ljava/util/Calendar;
invokevirtual com/nd/android/u/tast/experience/calendar/SignInPopWindow/GetEndDate(Ljava/util/Calendar;)Ljava/util/Calendar;
putfield com/nd/android/u/tast/experience/calendar/SignInPopWindow/pop_endDate Ljava/util/Calendar;
aload 0
aload 0
getfield com/nd/android/u/tast/experience/calendar/SignInPopWindow/mContext Landroid/app/Activity;
invokevirtual android/app/Activity/getLayoutInflater()Landroid/view/LayoutInflater;
putfield com/nd/android/u/tast/experience/calendar/SignInPopWindow/mLayoutInflater Landroid/view/LayoutInflater;
aload 0
getfield com/nd/android/u/tast/experience/calendar/SignInPopWindow/mLayoutInflater Landroid/view/LayoutInflater;
getstatic com/nd/android/u/tasklib/R$layout/popupwindow I
aconst_null
invokevirtual android/view/LayoutInflater/inflate(ILandroid/view/ViewGroup;)Landroid/view/View;
astore 1
aload 1
getstatic com/nd/android/u/tasklib/R$id/pop_calendarView I
invokevirtual android/view/View/findViewById(I)Landroid/view/View;
checkcast android/widget/LinearLayout
astore 2
new android/widget/Button
dup
aload 0
getfield com/nd/android/u/tast/experience/calendar/SignInPopWindow/mContext Landroid/app/Activity;
invokespecial android/widget/Button/<init>(Landroid/content/Context;)V
astore 3
aload 3
ldc "\u5173\u95ed"
invokevirtual android/widget/Button/setText(Ljava/lang/CharSequence;)V
aload 3
getstatic com/nd/android/u/tasklib/R$drawable/bt_close_calendar I
invokevirtual android/widget/Button/setBackgroundResource(I)V
aload 0
iconst_1
aload 0
getfield com/nd/android/u/tast/experience/calendar/SignInPopWindow/width I
bipush 7
imul
iconst_4
isub
aload 0
getfield com/nd/android/u/tast/experience/calendar/SignInPopWindow/height I
invokespecial com/nd/android/u/tast/experience/calendar/SignInPopWindow/closeButtonLayout(III)Landroid/widget/LinearLayout;
astore 4
aload 3
iconst_2
iconst_2
iconst_2
iconst_2
invokevirtual android/widget/Button/setPadding(IIII)V
aload 3
aload 0
getfield com/nd/android/u/tast/experience/calendar/SignInPopWindow/closePopWin_OnClickListener Landroid/view/View$OnClickListener;
invokevirtual android/widget/Button/setOnClickListener(Landroid/view/View$OnClickListener;)V
aload 4
aload 3
invokevirtual android/widget/LinearLayout/addView(Landroid/view/View;)V
aload 2
aload 0
invokespecial com/nd/android/u/tast/experience/calendar/SignInPopWindow/getTopDataPopView()Landroid/view/View;
invokevirtual android/widget/LinearLayout/addView(Landroid/view/View;)V
aload 2
aload 0
invokespecial com/nd/android/u/tast/experience/calendar/SignInPopWindow/drawCalendarMain()Landroid/view/View;
invokevirtual android/widget/LinearLayout/addView(Landroid/view/View;)V
aload 2
aload 4
invokevirtual android/widget/LinearLayout/addView(Landroid/view/View;)V
aload 0
aload 0
invokespecial com/nd/android/u/tast/experience/calendar/SignInPopWindow/drawCalendarStartDate()Ljava/util/Calendar;
putfield com/nd/android/u/tast/experience/calendar/SignInPopWindow/calPopStartDate Ljava/util/Calendar;
aload 0
aload 0
getfield com/nd/android/u/tast/experience/calendar/SignInPopWindow/SignInList Ljava/lang/String;
invokevirtual com/nd/android/u/tast/experience/calendar/SignInPopWindow/updatePopCalendar(Ljava/lang/String;)Lcom/nd/android/u/tast/experience/calendar/DateWidgetDayCell;
astore 3
aload 2
getstatic com/nd/android/u/tasklib/R$drawable/calendar_bg I
invokevirtual android/widget/LinearLayout/setBackgroundResource(I)V
aload 3
ifnull L1
aload 3
invokevirtual com/nd/android/u/tast/experience/calendar/DateWidgetDayCell/requestFocus()Z
pop
L1:
aload 0
new android/widget/PopupWindow
dup
aload 1
iconst_m1
iconst_m1
iconst_1
invokespecial android/widget/PopupWindow/<init>(Landroid/view/View;IIZ)V
putfield com/nd/android/u/tast/experience/calendar/SignInPopWindow/mPopupWindow Landroid/widget/PopupWindow;
L0:
aload 0
getfield com/nd/android/u/tast/experience/calendar/SignInPopWindow/mPopupWindow Landroid/widget/PopupWindow;
new android/graphics/drawable/BitmapDrawable
dup
invokespecial android/graphics/drawable/BitmapDrawable/<init>()V
invokevirtual android/widget/PopupWindow/setBackgroundDrawable(Landroid/graphics/drawable/Drawable;)V
return
.limit locals 5
.limit stack 7
.end method

.method public setData(Ljava/lang/String;IIII)V
aload 0
aload 1
putfield com/nd/android/u/tast/experience/calendar/SignInPopWindow/SignInList Ljava/lang/String;
aload 0
iload 2
putfield com/nd/android/u/tast/experience/calendar/SignInPopWindow/JoinMonth I
aload 0
iload 3
putfield com/nd/android/u/tast/experience/calendar/SignInPopWindow/JoinDay I
aload 0
iload 4
putfield com/nd/android/u/tast/experience/calendar/SignInPopWindow/BirthMonth I
aload 0
iload 5
putfield com/nd/android/u/tast/experience/calendar/SignInPopWindow/BirthDay I
return
.limit locals 6
.limit stack 2
.end method

.method public showPopWindow()V
aload 0
getfield com/nd/android/u/tast/experience/calendar/SignInPopWindow/mPopupWindow Landroid/widget/PopupWindow;
invokevirtual android/widget/PopupWindow/isShowing()Z
ifeq L0
aload 0
getfield com/nd/android/u/tast/experience/calendar/SignInPopWindow/mPopupWindow Landroid/widget/PopupWindow;
invokevirtual android/widget/PopupWindow/dismiss()V
return
L0:
aload 0
getfield com/nd/android/u/tast/experience/calendar/SignInPopWindow/mPopupWindow Landroid/widget/PopupWindow;
aload 0
getfield com/nd/android/u/tast/experience/calendar/SignInPopWindow/mView Landroid/view/View;
bipush 17
iconst_0
iconst_0
invokevirtual android/widget/PopupWindow/showAtLocation(Landroid/view/View;III)V
aload 0
getfield com/nd/android/u/tast/experience/calendar/SignInPopWindow/mPopupWindow Landroid/widget/PopupWindow;
iconst_1
invokevirtual android/widget/PopupWindow/setFocusable(Z)V
aload 0
getfield com/nd/android/u/tast/experience/calendar/SignInPopWindow/mPopupWindow Landroid/widget/PopupWindow;
iconst_1
invokevirtual android/widget/PopupWindow/setTouchable(Z)V
aload 0
getfield com/nd/android/u/tast/experience/calendar/SignInPopWindow/mPopupWindow Landroid/widget/PopupWindow;
iconst_1
invokevirtual android/widget/PopupWindow/setOutsideTouchable(Z)V
aload 0
getfield com/nd/android/u/tast/experience/calendar/SignInPopWindow/mPopupWindow Landroid/widget/PopupWindow;
invokevirtual android/widget/PopupWindow/update()V
return
.limit locals 1
.limit stack 5
.end method

.method public updatePopCalendar(Ljava/lang/String;)Lcom/nd/android/u/tast/experience/calendar/DateWidgetDayCell;
.catch java/lang/Exception from L0 to L1 using L2
.catch java/text/ParseException from L3 to L4 using L5
aload 0
getfield com/nd/android/u/tast/experience/calendar/SignInPopWindow/pop_calCalendar Ljava/util/Calendar;
aload 0
getfield com/nd/android/u/tast/experience/calendar/SignInPopWindow/calPopStartDate Ljava/util/Calendar;
invokevirtual java/util/Calendar/getTimeInMillis()J
invokevirtual java/util/Calendar/setTimeInMillis(J)V
aload 0
iconst_0
putfield com/nd/android/u/tast/experience/calendar/SignInPopWindow/IsAnniversary Z
L0:
aload 0
getfield com/nd/android/u/tast/experience/calendar/SignInPopWindow/fotmat Ljava/text/SimpleDateFormat;
aload 0
getfield com/nd/android/u/tast/experience/calendar/SignInPopWindow/PopTop_Date Landroid/widget/TextView;
invokevirtual android/widget/TextView/getText()Ljava/lang/CharSequence;
invokeinterface java/lang/CharSequence/toString()Ljava/lang/String; 0
invokevirtual java/text/SimpleDateFormat/parse(Ljava/lang/String;)Ljava/util/Date;
iconst_0
invokestatic com/nd/android/u/tast/experience/calendar/SignInPopWindow/getYearOrMonth(Ljava/util/Date;I)I
invokestatic java/lang/Integer/valueOf(I)Ljava/lang/Integer;
invokevirtual java/lang/Integer/intValue()I
aload 0
getfield com/nd/android/u/tast/experience/calendar/SignInPopWindow/StrJoinDay Ljava/lang/String;
iconst_0
invokestatic com/nd/android/u/tast/experience/calendar/SignInPopWindow/getMonthOrDate(Ljava/lang/String;I)I
if_icmple L1
aload 0
iconst_1
putfield com/nd/android/u/tast/experience/calendar/SignInPopWindow/IsAnniversary Z
L1:
iconst_0
istore 2
L6:
iload 2
aload 0
getfield com/nd/android/u/tast/experience/calendar/SignInPopWindow/pop_days Ljava/util/ArrayList;
invokevirtual java/util/ArrayList/size()I
if_icmpge L7
aload 0
getfield com/nd/android/u/tast/experience/calendar/SignInPopWindow/pop_calCalendar Ljava/util/Calendar;
iconst_1
invokevirtual java/util/Calendar/get(I)I
istore 3
aload 0
getfield com/nd/android/u/tast/experience/calendar/SignInPopWindow/pop_calCalendar Ljava/util/Calendar;
iconst_2
invokevirtual java/util/Calendar/get(I)I
istore 4
aload 0
getfield com/nd/android/u/tast/experience/calendar/SignInPopWindow/pop_calCalendar Ljava/util/Calendar;
iconst_5
invokevirtual java/util/Calendar/get(I)I
istore 5
aload 0
getfield com/nd/android/u/tast/experience/calendar/SignInPopWindow/pop_calCalendar Ljava/util/Calendar;
bipush 7
invokevirtual java/util/Calendar/get(I)I
istore 6
aload 0
getfield com/nd/android/u/tast/experience/calendar/SignInPopWindow/pop_days Ljava/util/ArrayList;
iload 2
invokevirtual java/util/ArrayList/get(I)Ljava/lang/Object;
checkcast com/nd/android/u/tast/experience/calendar/DateWidgetDayCell
astore 10
iconst_0
istore 7
iload 7
istore 8
aload 0
getfield com/nd/android/u/tast/experience/calendar/SignInPopWindow/pop_calToday Ljava/util/Calendar;
iconst_1
invokevirtual java/util/Calendar/get(I)I
iload 3
if_icmpne L8
iload 7
istore 8
aload 0
getfield com/nd/android/u/tast/experience/calendar/SignInPopWindow/pop_calToday Ljava/util/Calendar;
iconst_2
invokevirtual java/util/Calendar/get(I)I
iload 4
if_icmpne L8
iload 7
istore 8
aload 0
getfield com/nd/android/u/tast/experience/calendar/SignInPopWindow/pop_calToday Ljava/util/Calendar;
iconst_5
invokevirtual java/util/Calendar/get(I)I
iload 5
if_icmpne L8
iconst_1
istore 8
L8:
iconst_0
istore 7
iload 6
bipush 7
if_icmpeq L9
iload 6
iconst_1
if_icmpne L10
L9:
iconst_1
istore 7
L10:
iload 7
istore 9
iload 4
ifne L3
iload 7
istore 9
iload 5
iconst_1
if_icmpne L3
iconst_1
istore 9
L3:
aload 0
getfield com/nd/android/u/tast/experience/calendar/SignInPopWindow/fotmat Ljava/text/SimpleDateFormat;
aload 0
getfield com/nd/android/u/tast/experience/calendar/SignInPopWindow/PopTop_Date Landroid/widget/TextView;
invokevirtual android/widget/TextView/getText()Ljava/lang/CharSequence;
invokeinterface java/lang/CharSequence/toString()Ljava/lang/String; 0
invokevirtual java/text/SimpleDateFormat/parse(Ljava/lang/String;)Ljava/util/Date;
iconst_1
invokestatic com/nd/android/u/tast/experience/calendar/SignInPopWindow/getYearOrMonth(Ljava/util/Date;I)I
invokestatic java/lang/Integer/valueOf(I)Ljava/lang/Integer;
invokevirtual java/lang/Integer/intValue()I
istore 6
aload 10
iload 3
iload 4
iload 5
iload 8
invokestatic java/lang/Boolean/valueOf(Z)Ljava/lang/Boolean;
iload 9
invokestatic java/lang/Boolean/valueOf(Z)Ljava/lang/Boolean;
aload 0
getfield com/nd/android/u/tast/experience/calendar/SignInPopWindow/iMonthViewCurrentMonth I
iconst_0
aload 1
iload 6
aload 0
getfield com/nd/android/u/tast/experience/calendar/SignInPopWindow/JoinMonth I
aload 0
getfield com/nd/android/u/tast/experience/calendar/SignInPopWindow/JoinDay I
aload 0
getfield com/nd/android/u/tast/experience/calendar/SignInPopWindow/BirthMonth I
aload 0
getfield com/nd/android/u/tast/experience/calendar/SignInPopWindow/BirthDay I
aload 0
getfield com/nd/android/u/tast/experience/calendar/SignInPopWindow/IsAnniversary Z
aload 0
getfield com/nd/android/u/tast/experience/calendar/SignInPopWindow/special_day_list [Ljava/lang/String;
invokevirtual com/nd/android/u/tast/experience/calendar/DateWidgetDayCell/setData(IIILjava/lang/Boolean;Ljava/lang/Boolean;IZLjava/lang/String;IIIIIZ[Ljava/lang/String;)V
aload 10
invokevirtual com/nd/android/u/tast/experience/calendar/DateWidgetDayCell/invalidate()V
L4:
aload 0
getfield com/nd/android/u/tast/experience/calendar/SignInPopWindow/pop_calCalendar Ljava/util/Calendar;
iconst_5
iconst_1
invokevirtual java/util/Calendar/add(II)V
iload 2
iconst_1
iadd
istore 2
goto L6
L2:
astore 10
aload 0
iconst_0
putfield com/nd/android/u/tast/experience/calendar/SignInPopWindow/IsAnniversary Z
goto L1
L5:
astore 10
ldc "SignInpopWindow"
aload 10
invokevirtual java/text/ParseException/getMessage()Ljava/lang/String;
invokestatic android/util/Log/e(Ljava/lang/String;Ljava/lang/String;)I
pop
goto L4
L7:
aload 0
getfield com/nd/android/u/tast/experience/calendar/SignInPopWindow/layPopContent Landroid/widget/LinearLayout;
invokevirtual android/widget/LinearLayout/invalidate()V
aconst_null
areturn
.limit locals 11
.limit stack 16
.end method
