.bytecode 50.0
.class synchronized com/nd/android/u/ui/activity/chat_relative_image/adapter/PhotoAdapter$2
.super java/lang/Object
.implements android/view/View$OnClickListener
.enclosing method com/nd/android/u/ui/activity/chat_relative_image/adapter/PhotoAdapter/getView(ILcom/nd/android/u/ui/activity/chat_relative_image/adapter/PhotoBaseAdapter$ViewHolder;Landroid/view/View;)Landroid/view/View;
.inner class inner com/nd/android/u/ui/activity/chat_relative_image/adapter/PhotoAdapter$2

.field final synthetic 'this$0' Lcom/nd/android/u/ui/activity/chat_relative_image/adapter/PhotoAdapter;

.field final synthetic 'val$holder' Lcom/nd/android/u/ui/activity/chat_relative_image/adapter/PhotoBaseAdapter$ViewHolder;

.field final synthetic 'val$photo' Lcom/nd/android/u/ui/activity/chat_relative_image/bean/Photo;

.method <init>(Lcom/nd/android/u/ui/activity/chat_relative_image/adapter/PhotoAdapter;Lcom/nd/android/u/ui/activity/chat_relative_image/bean/Photo;Lcom/nd/android/u/ui/activity/chat_relative_image/adapter/PhotoBaseAdapter$ViewHolder;)V
aload 0
aload 1
putfield com/nd/android/u/ui/activity/chat_relative_image/adapter/PhotoAdapter$2/this$0 Lcom/nd/android/u/ui/activity/chat_relative_image/adapter/PhotoAdapter;
aload 0
aload 2
putfield com/nd/android/u/ui/activity/chat_relative_image/adapter/PhotoAdapter$2/val$photo Lcom/nd/android/u/ui/activity/chat_relative_image/bean/Photo;
aload 0
aload 3
putfield com/nd/android/u/ui/activity/chat_relative_image/adapter/PhotoAdapter$2/val$holder Lcom/nd/android/u/ui/activity/chat_relative_image/adapter/PhotoBaseAdapter$ViewHolder;
aload 0
invokespecial java/lang/Object/<init>()V
return
.limit locals 4
.limit stack 2
.end method

.method public onClick(Landroid/view/View;)V
aload 0
getfield com/nd/android/u/ui/activity/chat_relative_image/adapter/PhotoAdapter$2/this$0 Lcom/nd/android/u/ui/activity/chat_relative_image/adapter/PhotoAdapter;
invokestatic com/nd/android/u/ui/activity/chat_relative_image/adapter/PhotoAdapter/access$000(Lcom/nd/android/u/ui/activity/chat_relative_image/adapter/PhotoAdapter;)Ljava/util/List;
aload 0
getfield com/nd/android/u/ui/activity/chat_relative_image/adapter/PhotoAdapter$2/val$photo Lcom/nd/android/u/ui/activity/chat_relative_image/bean/Photo;
invokeinterface java/util/List/contains(Ljava/lang/Object;)Z 1
ifeq L0
aload 0
getfield com/nd/android/u/ui/activity/chat_relative_image/adapter/PhotoAdapter$2/this$0 Lcom/nd/android/u/ui/activity/chat_relative_image/adapter/PhotoAdapter;
invokestatic com/nd/android/u/ui/activity/chat_relative_image/adapter/PhotoAdapter/access$000(Lcom/nd/android/u/ui/activity/chat_relative_image/adapter/PhotoAdapter;)Ljava/util/List;
aload 0
getfield com/nd/android/u/ui/activity/chat_relative_image/adapter/PhotoAdapter$2/val$photo Lcom/nd/android/u/ui/activity/chat_relative_image/bean/Photo;
invokeinterface java/util/List/remove(Ljava/lang/Object;)Z 1
pop
aload 0
getfield com/nd/android/u/ui/activity/chat_relative_image/adapter/PhotoAdapter$2/this$0 Lcom/nd/android/u/ui/activity/chat_relative_image/adapter/PhotoAdapter;
aload 0
getfield com/nd/android/u/ui/activity/chat_relative_image/adapter/PhotoAdapter$2/val$holder Lcom/nd/android/u/ui/activity/chat_relative_image/adapter/PhotoBaseAdapter$ViewHolder;
iconst_0
invokestatic com/nd/android/u/ui/activity/chat_relative_image/adapter/PhotoAdapter/access$100(Lcom/nd/android/u/ui/activity/chat_relative_image/adapter/PhotoAdapter;Lcom/nd/android/u/ui/activity/chat_relative_image/adapter/PhotoBaseAdapter$ViewHolder;I)V
aload 0
getfield com/nd/android/u/ui/activity/chat_relative_image/adapter/PhotoAdapter$2/this$0 Lcom/nd/android/u/ui/activity/chat_relative_image/adapter/PhotoAdapter;
invokevirtual com/nd/android/u/ui/activity/chat_relative_image/adapter/PhotoAdapter/notifyDataSetChanged()V
return
L0:
aload 0
getfield com/nd/android/u/ui/activity/chat_relative_image/adapter/PhotoAdapter$2/this$0 Lcom/nd/android/u/ui/activity/chat_relative_image/adapter/PhotoAdapter;
invokestatic com/nd/android/u/ui/activity/chat_relative_image/adapter/PhotoAdapter/access$000(Lcom/nd/android/u/ui/activity/chat_relative_image/adapter/PhotoAdapter;)Ljava/util/List;
invokeinterface java/util/List/size()I 0
bipush 9
if_icmplt L1
aload 0
getfield com/nd/android/u/ui/activity/chat_relative_image/adapter/PhotoAdapter$2/this$0 Lcom/nd/android/u/ui/activity/chat_relative_image/adapter/PhotoAdapter;
getfield com/nd/android/u/ui/activity/chat_relative_image/adapter/PhotoAdapter/context Landroid/content/Context;
getstatic com/nd/android/u/chat/R$string/send_image_num_limit I
iconst_0
invokestatic android/widget/Toast/makeText(Landroid/content/Context;II)Landroid/widget/Toast;
invokevirtual android/widget/Toast/show()V
return
L1:
aload 0
getfield com/nd/android/u/ui/activity/chat_relative_image/adapter/PhotoAdapter$2/this$0 Lcom/nd/android/u/ui/activity/chat_relative_image/adapter/PhotoAdapter;
invokestatic com/nd/android/u/ui/activity/chat_relative_image/adapter/PhotoAdapter/access$000(Lcom/nd/android/u/ui/activity/chat_relative_image/adapter/PhotoAdapter;)Ljava/util/List;
aload 0
getfield com/nd/android/u/ui/activity/chat_relative_image/adapter/PhotoAdapter$2/val$photo Lcom/nd/android/u/ui/activity/chat_relative_image/bean/Photo;
invokeinterface java/util/List/add(Ljava/lang/Object;)Z 1
pop
aload 0
getfield com/nd/android/u/ui/activity/chat_relative_image/adapter/PhotoAdapter$2/this$0 Lcom/nd/android/u/ui/activity/chat_relative_image/adapter/PhotoAdapter;
aload 0
getfield com/nd/android/u/ui/activity/chat_relative_image/adapter/PhotoAdapter$2/val$holder Lcom/nd/android/u/ui/activity/chat_relative_image/adapter/PhotoBaseAdapter$ViewHolder;
aload 0
getfield com/nd/android/u/ui/activity/chat_relative_image/adapter/PhotoAdapter$2/this$0 Lcom/nd/android/u/ui/activity/chat_relative_image/adapter/PhotoAdapter;
invokestatic com/nd/android/u/ui/activity/chat_relative_image/adapter/PhotoAdapter/access$000(Lcom/nd/android/u/ui/activity/chat_relative_image/adapter/PhotoAdapter;)Ljava/util/List;
invokeinterface java/util/List/size()I 0
invokestatic com/nd/android/u/ui/activity/chat_relative_image/adapter/PhotoAdapter/access$100(Lcom/nd/android/u/ui/activity/chat_relative_image/adapter/PhotoAdapter;Lcom/nd/android/u/ui/activity/chat_relative_image/adapter/PhotoBaseAdapter$ViewHolder;I)V
return
.limit locals 2
.limit stack 3
.end method
