.bytecode 50.0
.class public synchronized com/common/android/utils/concurrent/DuplicateCheckNdThreadPoolExecutor
.super com/common/android/utils/concurrent/NdThreadPoolExecutor

.method public <init>(IIJLjava/util/concurrent/TimeUnit;Ljava/util/concurrent/BlockingQueue;Ljava/util/concurrent/ThreadFactory;)V
.signature "(IIJLjava/util/concurrent/TimeUnit;Ljava/util/concurrent/BlockingQueue<Ljava/lang/Runnable;>;Ljava/util/concurrent/ThreadFactory;)V"
aload 0
iload 1
iload 2
lload 3
aload 5
aload 6
aload 7
invokespecial com/common/android/utils/concurrent/NdThreadPoolExecutor/<init>(IIJLjava/util/concurrent/TimeUnit;Ljava/util/concurrent/BlockingQueue;Ljava/util/concurrent/ThreadFactory;)V
return
.limit locals 8
.limit stack 8
.end method

.method public execute(Ljava/lang/Runnable;)V
aload 1
ifnonnull L0
return
L0:
aload 1
invokevirtual java/lang/Object/getClass()Ljava/lang/Class;
invokevirtual java/lang/Class/getName()Ljava/lang/String;
astore 2
getstatic com/common/android/utils/concurrent/DuplicateCheckNdThreadPoolExecutor/mQueueTask Ljava/util/concurrent/BlockingQueue;
invokeinterface java/util/concurrent/BlockingQueue/iterator()Ljava/util/Iterator; 0
astore 3
L1:
aload 3
invokeinterface java/util/Iterator/hasNext()Z 0
ifeq L2
aload 2
aload 3
invokeinterface java/util/Iterator/next()Ljava/lang/Object; 0
checkcast com/common/android/utils/concurrent/NdAbstractTask
invokevirtual java/lang/Object/getClass()Ljava/lang/Class;
invokevirtual java/lang/Class/getName()Ljava/lang/String;
invokevirtual java/lang/String/equals(Ljava/lang/Object;)Z
ifeq L1
return
L2:
aload 0
aload 1
invokespecial com/common/android/utils/concurrent/NdThreadPoolExecutor/execute(Ljava/lang/Runnable;)V
return
.limit locals 4
.limit stack 2
.end method
