.bytecode 50.0
.class synchronized com/common/android/utils/concurrent/NdThreadPoolExecutor$1
.super java/util/TimerTask
.enclosing method com/common/android/utils/concurrent/NdThreadPoolExecutor/beforeExecute(Ljava/lang/Thread;Ljava/lang/Runnable;)V
.inner class inner com/common/android/utils/concurrent/NdThreadPoolExecutor$1

.field final synthetic 'this$0' Lcom/common/android/utils/concurrent/NdThreadPoolExecutor;

.field final synthetic 'val$nr' Lcom/common/android/utils/concurrent/NdAbstractTask;

.field final synthetic 'val$timeT' Ljava/lang/Thread;

.method <init>(Lcom/common/android/utils/concurrent/NdThreadPoolExecutor;Ljava/lang/Thread;Lcom/common/android/utils/concurrent/NdAbstractTask;)V
aload 0
aload 1
putfield com/common/android/utils/concurrent/NdThreadPoolExecutor$1/this$0 Lcom/common/android/utils/concurrent/NdThreadPoolExecutor;
aload 0
aload 2
putfield com/common/android/utils/concurrent/NdThreadPoolExecutor$1/val$timeT Ljava/lang/Thread;
aload 0
aload 3
putfield com/common/android/utils/concurrent/NdThreadPoolExecutor$1/val$nr Lcom/common/android/utils/concurrent/NdAbstractTask;
aload 0
invokespecial java/util/TimerTask/<init>()V
return
.limit locals 4
.limit stack 2
.end method

.method public run()V
ldc "NdThreadPoolExecutor"
new java/lang/StringBuilder
dup
invokespecial java/lang/StringBuilder/<init>()V
ldc "thread\uff1a"
invokevirtual java/lang/StringBuilder/append(Ljava/lang/String;)Ljava/lang/StringBuilder;
aload 0
getfield com/common/android/utils/concurrent/NdThreadPoolExecutor$1/val$timeT Ljava/lang/Thread;
invokevirtual java/lang/Thread/getName()Ljava/lang/String;
invokevirtual java/lang/StringBuilder/append(Ljava/lang/String;)Ljava/lang/StringBuilder;
ldc " timeout and should be interrupt, task id: "
invokevirtual java/lang/StringBuilder/append(Ljava/lang/String;)Ljava/lang/StringBuilder;
aload 0
getfield com/common/android/utils/concurrent/NdThreadPoolExecutor$1/val$nr Lcom/common/android/utils/concurrent/NdAbstractTask;
invokevirtual com/common/android/utils/concurrent/NdAbstractTask/getId()Lcom/common/android/utils/concurrent/ETaskTypeId;
invokevirtual java/lang/StringBuilder/append(Ljava/lang/Object;)Ljava/lang/StringBuilder;
invokevirtual java/lang/StringBuilder/toString()Ljava/lang/String;
invokestatic android/util/Log/d(Ljava/lang/String;Ljava/lang/String;)I
pop
return
.limit locals 1
.limit stack 3
.end method
