.bytecode 50.0
.class synchronized com/nd/android/backpacksystem/widget/DlgSendGiftWithMsg$2
.super java/lang/Object
.implements android/view/View$OnClickListener
.enclosing method com/nd/android/backpacksystem/widget/DlgSendGiftWithMsg
.inner class inner com/nd/android/backpacksystem/widget/DlgSendGiftWithMsg$2

.field final synthetic 'this$0' Lcom/nd/android/backpacksystem/widget/DlgSendGiftWithMsg;

.method <init>(Lcom/nd/android/backpacksystem/widget/DlgSendGiftWithMsg;)V
aload 0
aload 1
putfield com/nd/android/backpacksystem/widget/DlgSendGiftWithMsg$2/this$0 Lcom/nd/android/backpacksystem/widget/DlgSendGiftWithMsg;
aload 0
invokespecial java/lang/Object/<init>()V
return
.limit locals 2
.limit stack 2
.end method

.method public onClick(Landroid/view/View;)V
.catch java/lang/IllegalArgumentException from L0 to L1 using L2
.catch java/lang/IllegalStateException from L0 to L1 using L3
.catch java/io/IOException from L0 to L1 using L4
aload 1
invokevirtual android/view/View/getId()I
istore 2
getstatic com/nd/android/backpacksystem/R$id/llRecordMsg I
iload 2
if_icmpne L1
aload 0
getfield com/nd/android/backpacksystem/widget/DlgSendGiftWithMsg$2/this$0 Lcom/nd/android/backpacksystem/widget/DlgSendGiftWithMsg;
invokestatic com/nd/android/backpacksystem/widget/DlgSendGiftWithMsg/access$100(Lcom/nd/android/backpacksystem/widget/DlgSendGiftWithMsg;)Z
ifeq L0
invokestatic com/common/android/utils/audio/AudioPlayer/getInstance()Lcom/common/android/utils/audio/AudioPlayer;
invokevirtual com/common/android/utils/audio/AudioPlayer/stopPlay()V
L5:
return
L0:
new java/io/File
dup
aload 0
getfield com/nd/android/backpacksystem/widget/DlgSendGiftWithMsg$2/this$0 Lcom/nd/android/backpacksystem/widget/DlgSendGiftWithMsg;
invokestatic com/nd/android/backpacksystem/widget/DlgSendGiftWithMsg/access$200(Lcom/nd/android/backpacksystem/widget/DlgSendGiftWithMsg;)Ljava/lang/String;
invokespecial java/io/File/<init>(Ljava/lang/String;)V
invokevirtual java/io/File/exists()Z
ifeq L5
invokestatic com/common/android/utils/audio/AudioPlayer/getInstance()Lcom/common/android/utils/audio/AudioPlayer;
new java/io/File
dup
aload 0
getfield com/nd/android/backpacksystem/widget/DlgSendGiftWithMsg$2/this$0 Lcom/nd/android/backpacksystem/widget/DlgSendGiftWithMsg;
invokestatic com/nd/android/backpacksystem/widget/DlgSendGiftWithMsg/access$200(Lcom/nd/android/backpacksystem/widget/DlgSendGiftWithMsg;)Ljava/lang/String;
invokespecial java/io/File/<init>(Ljava/lang/String;)V
aload 0
getfield com/nd/android/backpacksystem/widget/DlgSendGiftWithMsg$2/this$0 Lcom/nd/android/backpacksystem/widget/DlgSendGiftWithMsg;
invokestatic com/nd/android/backpacksystem/widget/DlgSendGiftWithMsg/access$300(Lcom/nd/android/backpacksystem/widget/DlgSendGiftWithMsg;)Landroid/app/Activity;
invokevirtual com/common/android/utils/audio/AudioPlayer/play(Ljava/io/File;Landroid/content/Context;)V
invokestatic com/common/android/utils/audio/AudioPlayer/getInstance()Lcom/common/android/utils/audio/AudioPlayer;
aload 0
getfield com/nd/android/backpacksystem/widget/DlgSendGiftWithMsg$2/this$0 Lcom/nd/android/backpacksystem/widget/DlgSendGiftWithMsg;
invokestatic com/nd/android/backpacksystem/widget/DlgSendGiftWithMsg/access$400(Lcom/nd/android/backpacksystem/widget/DlgSendGiftWithMsg;)Lcom/common/android/utils/audio/AudioPlayer$onPlayFinishListener;
invokevirtual com/common/android/utils/audio/AudioPlayer/setOnPlayFinishListener(Lcom/common/android/utils/audio/AudioPlayer$onPlayFinishListener;)V
invokestatic com/common/android/utils/audio/AudioPlayer/getInstance()Lcom/common/android/utils/audio/AudioPlayer;
aload 0
getfield com/nd/android/backpacksystem/widget/DlgSendGiftWithMsg$2/this$0 Lcom/nd/android/backpacksystem/widget/DlgSendGiftWithMsg;
invokestatic com/nd/android/backpacksystem/widget/DlgSendGiftWithMsg/access$500(Lcom/nd/android/backpacksystem/widget/DlgSendGiftWithMsg;)Lcom/common/android/utils/audio/AudioPlayer$onPlayStopListener;
invokevirtual com/common/android/utils/audio/AudioPlayer/setOnPlayStopListener(Lcom/common/android/utils/audio/AudioPlayer$onPlayStopListener;)V
aload 0
getfield com/nd/android/backpacksystem/widget/DlgSendGiftWithMsg$2/this$0 Lcom/nd/android/backpacksystem/widget/DlgSendGiftWithMsg;
iconst_1
invokestatic com/nd/android/backpacksystem/widget/DlgSendGiftWithMsg/access$102(Lcom/nd/android/backpacksystem/widget/DlgSendGiftWithMsg;Z)Z
pop
aload 0
getfield com/nd/android/backpacksystem/widget/DlgSendGiftWithMsg$2/this$0 Lcom/nd/android/backpacksystem/widget/DlgSendGiftWithMsg;
aload 0
getfield com/nd/android/backpacksystem/widget/DlgSendGiftWithMsg$2/this$0 Lcom/nd/android/backpacksystem/widget/DlgSendGiftWithMsg;
invokestatic com/nd/android/backpacksystem/widget/DlgSendGiftWithMsg/access$700(Lcom/nd/android/backpacksystem/widget/DlgSendGiftWithMsg;)Landroid/widget/ImageView;
invokevirtual android/widget/ImageView/getDrawable()Landroid/graphics/drawable/Drawable;
checkcast android/graphics/drawable/AnimationDrawable
invokestatic com/nd/android/backpacksystem/widget/DlgSendGiftWithMsg/access$602(Lcom/nd/android/backpacksystem/widget/DlgSendGiftWithMsg;Landroid/graphics/drawable/AnimationDrawable;)Landroid/graphics/drawable/AnimationDrawable;
pop
aload 0
getfield com/nd/android/backpacksystem/widget/DlgSendGiftWithMsg$2/this$0 Lcom/nd/android/backpacksystem/widget/DlgSendGiftWithMsg;
invokestatic com/nd/android/backpacksystem/widget/DlgSendGiftWithMsg/access$600(Lcom/nd/android/backpacksystem/widget/DlgSendGiftWithMsg;)Landroid/graphics/drawable/AnimationDrawable;
invokevirtual android/graphics/drawable/AnimationDrawable/start()V
L1:
getstatic com/nd/android/backpacksystem/R$id/btnDeleteRecord I
iload 2
if_icmpne L6
invokestatic com/common/android/utils/audio/AudioPlayer/getInstance()Lcom/common/android/utils/audio/AudioPlayer;
invokevirtual com/common/android/utils/audio/AudioPlayer/stopPlay()V
aload 0
getfield com/nd/android/backpacksystem/widget/DlgSendGiftWithMsg$2/this$0 Lcom/nd/android/backpacksystem/widget/DlgSendGiftWithMsg;
iconst_1
invokestatic com/nd/android/backpacksystem/widget/DlgSendGiftWithMsg/access$800(Lcom/nd/android/backpacksystem/widget/DlgSendGiftWithMsg;Z)V
L6:
getstatic com/nd/android/backpacksystem/R$id/btnFace I
iload 2
if_icmpne L7
aload 0
getfield com/nd/android/backpacksystem/widget/DlgSendGiftWithMsg$2/this$0 Lcom/nd/android/backpacksystem/widget/DlgSendGiftWithMsg;
iconst_1
invokestatic com/nd/android/backpacksystem/widget/DlgSendGiftWithMsg/access$900(Lcom/nd/android/backpacksystem/widget/DlgSendGiftWithMsg;Z)V
return
L2:
astore 1
aload 0
getfield com/nd/android/backpacksystem/widget/DlgSendGiftWithMsg$2/this$0 Lcom/nd/android/backpacksystem/widget/DlgSendGiftWithMsg;
iconst_0
invokestatic com/nd/android/backpacksystem/widget/DlgSendGiftWithMsg/access$102(Lcom/nd/android/backpacksystem/widget/DlgSendGiftWithMsg;Z)Z
pop
goto L1
L3:
astore 1
aload 0
getfield com/nd/android/backpacksystem/widget/DlgSendGiftWithMsg$2/this$0 Lcom/nd/android/backpacksystem/widget/DlgSendGiftWithMsg;
iconst_0
invokestatic com/nd/android/backpacksystem/widget/DlgSendGiftWithMsg/access$102(Lcom/nd/android/backpacksystem/widget/DlgSendGiftWithMsg;Z)Z
pop
goto L1
L4:
astore 1
aload 0
getfield com/nd/android/backpacksystem/widget/DlgSendGiftWithMsg$2/this$0 Lcom/nd/android/backpacksystem/widget/DlgSendGiftWithMsg;
iconst_0
invokestatic com/nd/android/backpacksystem/widget/DlgSendGiftWithMsg/access$102(Lcom/nd/android/backpacksystem/widget/DlgSendGiftWithMsg;Z)Z
pop
goto L1
L7:
getstatic com/nd/android/backpacksystem/R$id/btnRecord I
iload 2
if_icmpne L8
aload 0
getfield com/nd/android/backpacksystem/widget/DlgSendGiftWithMsg$2/this$0 Lcom/nd/android/backpacksystem/widget/DlgSendGiftWithMsg;
iconst_0
invokestatic com/nd/android/backpacksystem/widget/DlgSendGiftWithMsg/access$900(Lcom/nd/android/backpacksystem/widget/DlgSendGiftWithMsg;Z)V
return
L8:
getstatic com/nd/android/backpacksystem/R$id/btnSend I
iload 2
if_icmpne L5
aload 0
getfield com/nd/android/backpacksystem/widget/DlgSendGiftWithMsg$2/this$0 Lcom/nd/android/backpacksystem/widget/DlgSendGiftWithMsg;
invokevirtual com/nd/android/backpacksystem/widget/DlgSendGiftWithMsg/doSend()V
return
.limit locals 3
.limit stack 4
.end method
