.bytecode 50.0
.class synchronized com/nd/android/u/cloud/activity/welcome/SelectSchoolListView$HighSchoolAdapter$1
.super java/lang/Object
.implements android/view/View$OnClickListener
.enclosing method com/nd/android/u/cloud/activity/welcome/SelectSchoolListView$HighSchoolAdapter/getView(ILandroid/view/View;Landroid/view/ViewGroup;)Landroid/view/View;
.inner class HighSchoolAdapter inner com/nd/android/u/cloud/activity/welcome/SelectSchoolListView$HighSchoolAdapter outer com/nd/android/u/cloud/activity/welcome/SelectSchoolListView
.inner class inner com/nd/android/u/cloud/activity/welcome/SelectSchoolListView$HighSchoolAdapter$1

.field final synthetic 'this$1' Lcom/nd/android/u/cloud/activity/welcome/SelectSchoolListView$HighSchoolAdapter;

.field final synthetic 'val$pos' I

.method <init>(Lcom/nd/android/u/cloud/activity/welcome/SelectSchoolListView$HighSchoolAdapter;I)V
aload 0
aload 1
putfield com/nd/android/u/cloud/activity/welcome/SelectSchoolListView$HighSchoolAdapter$1/this$1 Lcom/nd/android/u/cloud/activity/welcome/SelectSchoolListView$HighSchoolAdapter;
aload 0
iload 2
putfield com/nd/android/u/cloud/activity/welcome/SelectSchoolListView$HighSchoolAdapter$1/val$pos I
aload 0
invokespecial java/lang/Object/<init>()V
return
.limit locals 3
.limit stack 2
.end method

.method public onClick(Landroid/view/View;)V
aload 0
getfield com/nd/android/u/cloud/activity/welcome/SelectSchoolListView$HighSchoolAdapter$1/this$1 Lcom/nd/android/u/cloud/activity/welcome/SelectSchoolListView$HighSchoolAdapter;
getfield com/nd/android/u/cloud/activity/welcome/SelectSchoolListView$HighSchoolAdapter/this$0 Lcom/nd/android/u/cloud/activity/welcome/SelectSchoolListView;
invokestatic com/nd/android/u/cloud/activity/welcome/SelectSchoolListView/access$000(Lcom/nd/android/u/cloud/activity/welcome/SelectSchoolListView;)Lcom/nd/android/u/cloud/activity/welcome/SelectSchoolListView$OnDataSelectedListener;
ifnull L0
aload 0
getfield com/nd/android/u/cloud/activity/welcome/SelectSchoolListView$HighSchoolAdapter$1/this$1 Lcom/nd/android/u/cloud/activity/welcome/SelectSchoolListView$HighSchoolAdapter;
invokestatic com/nd/android/u/cloud/activity/welcome/SelectSchoolListView$HighSchoolAdapter/access$100(Lcom/nd/android/u/cloud/activity/welcome/SelectSchoolListView$HighSchoolAdapter;)Ljava/util/List;
ifnull L1
aload 0
getfield com/nd/android/u/cloud/activity/welcome/SelectSchoolListView$HighSchoolAdapter$1/this$1 Lcom/nd/android/u/cloud/activity/welcome/SelectSchoolListView$HighSchoolAdapter;
invokestatic com/nd/android/u/cloud/activity/welcome/SelectSchoolListView$HighSchoolAdapter/access$100(Lcom/nd/android/u/cloud/activity/welcome/SelectSchoolListView$HighSchoolAdapter;)Ljava/util/List;
invokeinterface java/util/List/size()I 0
aload 0
getfield com/nd/android/u/cloud/activity/welcome/SelectSchoolListView$HighSchoolAdapter$1/val$pos I
if_icmpgt L2
L1:
return
L2:
aload 0
getfield com/nd/android/u/cloud/activity/welcome/SelectSchoolListView$HighSchoolAdapter$1/this$1 Lcom/nd/android/u/cloud/activity/welcome/SelectSchoolListView$HighSchoolAdapter;
invokestatic com/nd/android/u/cloud/activity/welcome/SelectSchoolListView$HighSchoolAdapter/access$100(Lcom/nd/android/u/cloud/activity/welcome/SelectSchoolListView$HighSchoolAdapter;)Ljava/util/List;
aload 0
getfield com/nd/android/u/cloud/activity/welcome/SelectSchoolListView$HighSchoolAdapter$1/val$pos I
invokeinterface java/util/List/get(I)Ljava/lang/Object; 1
checkcast com/nd/android/u/cloud/readschoolinfo/HighSchoolInfo
astore 1
aload 0
getfield com/nd/android/u/cloud/activity/welcome/SelectSchoolListView$HighSchoolAdapter$1/this$1 Lcom/nd/android/u/cloud/activity/welcome/SelectSchoolListView$HighSchoolAdapter;
getfield com/nd/android/u/cloud/activity/welcome/SelectSchoolListView$HighSchoolAdapter/this$0 Lcom/nd/android/u/cloud/activity/welcome/SelectSchoolListView;
invokestatic com/nd/android/u/cloud/activity/welcome/SelectSchoolListView/access$000(Lcom/nd/android/u/cloud/activity/welcome/SelectSchoolListView;)Lcom/nd/android/u/cloud/activity/welcome/SelectSchoolListView$OnDataSelectedListener;
aload 1
invokevirtual com/nd/android/u/cloud/readschoolinfo/HighSchoolInfo/getSchoolName()Ljava/lang/String;
aload 1
invokevirtual com/nd/android/u/cloud/readschoolinfo/HighSchoolInfo/getSchoolCode()Ljava/lang/String;
invokeinterface com/nd/android/u/cloud/activity/welcome/SelectSchoolListView$OnDataSelectedListener/dataSelected(Ljava/lang/String;Ljava/lang/String;)V 2
L0:
aload 0
getfield com/nd/android/u/cloud/activity/welcome/SelectSchoolListView$HighSchoolAdapter$1/this$1 Lcom/nd/android/u/cloud/activity/welcome/SelectSchoolListView$HighSchoolAdapter;
getfield com/nd/android/u/cloud/activity/welcome/SelectSchoolListView$HighSchoolAdapter/this$0 Lcom/nd/android/u/cloud/activity/welcome/SelectSchoolListView;
invokevirtual com/nd/android/u/cloud/activity/welcome/SelectSchoolListView/disappear()V
return
.limit locals 2
.limit stack 3
.end method
