.bytecode 50.0
.class synchronized com/nd/android/u/cloud/activity/welcome/WelcomeChangeInfoActivity$1
.super java/lang/Object
.implements android/text/TextWatcher
.enclosing method com/nd/android/u/cloud/activity/welcome/WelcomeChangeInfoActivity/initEvent()V
.inner class inner com/nd/android/u/cloud/activity/welcome/WelcomeChangeInfoActivity$1

.field final synthetic 'this$0' Lcom/nd/android/u/cloud/activity/welcome/WelcomeChangeInfoActivity;

.method <init>(Lcom/nd/android/u/cloud/activity/welcome/WelcomeChangeInfoActivity;)V
aload 0
aload 1
putfield com/nd/android/u/cloud/activity/welcome/WelcomeChangeInfoActivity$1/this$0 Lcom/nd/android/u/cloud/activity/welcome/WelcomeChangeInfoActivity;
aload 0
invokespecial java/lang/Object/<init>()V
return
.limit locals 2
.limit stack 2
.end method

.method public afterTextChanged(Landroid/text/Editable;)V
aload 0
getfield com/nd/android/u/cloud/activity/welcome/WelcomeChangeInfoActivity$1/this$0 Lcom/nd/android/u/cloud/activity/welcome/WelcomeChangeInfoActivity;
invokestatic com/nd/android/u/cloud/activity/welcome/WelcomeChangeInfoActivity/access$000(Lcom/nd/android/u/cloud/activity/welcome/WelcomeChangeInfoActivity;)Z
ifeq L0
return
L0:
aload 1
invokevirtual java/lang/Object/toString()Ljava/lang/String;
astore 1
aload 0
getfield com/nd/android/u/cloud/activity/welcome/WelcomeChangeInfoActivity$1/this$0 Lcom/nd/android/u/cloud/activity/welcome/WelcomeChangeInfoActivity;
invokestatic com/nd/android/u/cloud/activity/welcome/WelcomeChangeInfoActivity/access$100(Lcom/nd/android/u/cloud/activity/welcome/WelcomeChangeInfoActivity;)Lcom/nd/android/u/cloud/activity/welcome/SelectSchoolListView;
aload 1
invokevirtual com/nd/android/u/cloud/activity/welcome/SelectSchoolListView/updateInfo(Ljava/lang/String;)V
aload 1
invokestatic android/text/TextUtils/isEmpty(Ljava/lang/CharSequence;)Z
ifne L1
aload 0
getfield com/nd/android/u/cloud/activity/welcome/WelcomeChangeInfoActivity$1/this$0 Lcom/nd/android/u/cloud/activity/welcome/WelcomeChangeInfoActivity;
invokestatic com/nd/android/u/cloud/activity/welcome/WelcomeChangeInfoActivity/access$200(Lcom/nd/android/u/cloud/activity/welcome/WelcomeChangeInfoActivity;)Landroid/widget/ImageButton;
iconst_0
invokevirtual android/widget/ImageButton/setVisibility(I)V
return
L1:
aload 0
getfield com/nd/android/u/cloud/activity/welcome/WelcomeChangeInfoActivity$1/this$0 Lcom/nd/android/u/cloud/activity/welcome/WelcomeChangeInfoActivity;
invokestatic com/nd/android/u/cloud/activity/welcome/WelcomeChangeInfoActivity/access$200(Lcom/nd/android/u/cloud/activity/welcome/WelcomeChangeInfoActivity;)Landroid/widget/ImageButton;
iconst_4
invokevirtual android/widget/ImageButton/setVisibility(I)V
aload 0
getfield com/nd/android/u/cloud/activity/welcome/WelcomeChangeInfoActivity$1/this$0 Lcom/nd/android/u/cloud/activity/welcome/WelcomeChangeInfoActivity;
ldc ""
invokestatic com/nd/android/u/cloud/activity/welcome/WelcomeChangeInfoActivity/access$302(Lcom/nd/android/u/cloud/activity/welcome/WelcomeChangeInfoActivity;Ljava/lang/String;)Ljava/lang/String;
pop
return
.limit locals 2
.limit stack 2
.end method

.method public beforeTextChanged(Ljava/lang/CharSequence;III)V
return
.limit locals 5
.limit stack 0
.end method

.method public onTextChanged(Ljava/lang/CharSequence;III)V
return
.limit locals 5
.limit stack 0
.end method
