.bytecode 50.0
.class synchronized com/nd/schoollife/ui/post/view/PostDetailCommentListItemView$3
.super java/lang/Object
.implements android/view/View$OnClickListener
.enclosing method com/nd/schoollife/ui/post/view/PostDetailCommentListItemView/initView(Landroid/content/Context;)V
.inner class inner com/nd/schoollife/ui/post/view/PostDetailCommentListItemView$3

.field final synthetic 'this$0' Lcom/nd/schoollife/ui/post/view/PostDetailCommentListItemView;

.method <init>(Lcom/nd/schoollife/ui/post/view/PostDetailCommentListItemView;)V
aload 0
aload 1
putfield com/nd/schoollife/ui/post/view/PostDetailCommentListItemView$3/this$0 Lcom/nd/schoollife/ui/post/view/PostDetailCommentListItemView;
aload 0
invokespecial java/lang/Object/<init>()V
return
.limit locals 2
.limit stack 2
.end method

.method public onClick(Landroid/view/View;)V
.catch java/lang/Exception from L0 to L1 using L2
new android/content/Intent
dup
aload 0
getfield com/nd/schoollife/ui/post/view/PostDetailCommentListItemView$3/this$0 Lcom/nd/schoollife/ui/post/view/PostDetailCommentListItemView;
invokestatic com/nd/schoollife/ui/post/view/PostDetailCommentListItemView/access$000(Lcom/nd/schoollife/ui/post/view/PostDetailCommentListItemView;)Landroid/content/Context;
ldc com/nd/schoollife/ui/post/activity/CommentDetailActivity
invokespecial android/content/Intent/<init>(Landroid/content/Context;Ljava/lang/Class;)V
astore 2
L0:
aload 2
ldc "comment_id"
aload 1
invokevirtual android/view/View/getTag()Ljava/lang/Object;
checkcast java/lang/String
invokestatic java/lang/Long/valueOf(Ljava/lang/String;)Ljava/lang/Long;
invokevirtual android/content/Intent/putExtra(Ljava/lang/String;Ljava/io/Serializable;)Landroid/content/Intent;
pop
aload 2
ldc "POST_SENDER_UID"
aload 0
getfield com/nd/schoollife/ui/post/view/PostDetailCommentListItemView$3/this$0 Lcom/nd/schoollife/ui/post/view/PostDetailCommentListItemView;
invokestatic com/nd/schoollife/ui/post/view/PostDetailCommentListItemView/access$100(Lcom/nd/schoollife/ui/post/view/PostDetailCommentListItemView;)J
invokevirtual android/content/Intent/putExtra(Ljava/lang/String;J)Landroid/content/Intent;
pop
aload 2
ldc "SCOPE_TYPE"
aload 0
getfield com/nd/schoollife/ui/post/view/PostDetailCommentListItemView$3/this$0 Lcom/nd/schoollife/ui/post/view/PostDetailCommentListItemView;
invokestatic com/nd/schoollife/ui/post/view/PostDetailCommentListItemView/access$200(Lcom/nd/schoollife/ui/post/view/PostDetailCommentListItemView;)I
invokevirtual android/content/Intent/putExtra(Ljava/lang/String;I)Landroid/content/Intent;
pop
aload 2
ldc "SCOPE_ROLE"
aload 0
getfield com/nd/schoollife/ui/post/view/PostDetailCommentListItemView$3/this$0 Lcom/nd/schoollife/ui/post/view/PostDetailCommentListItemView;
invokestatic com/nd/schoollife/ui/post/view/PostDetailCommentListItemView/access$300(Lcom/nd/schoollife/ui/post/view/PostDetailCommentListItemView;)I
invokevirtual android/content/Intent/putExtra(Ljava/lang/String;I)Landroid/content/Intent;
pop
L1:
aload 0
getfield com/nd/schoollife/ui/post/view/PostDetailCommentListItemView$3/this$0 Lcom/nd/schoollife/ui/post/view/PostDetailCommentListItemView;
invokestatic com/nd/schoollife/ui/post/view/PostDetailCommentListItemView/access$000(Lcom/nd/schoollife/ui/post/view/PostDetailCommentListItemView;)Landroid/content/Context;
aload 2
invokevirtual android/content/Context/startActivity(Landroid/content/Intent;)V
return
L2:
astore 1
getstatic com/nd/schoollife/ui/post/view/PostDetailCommentListItemView/TAG Ljava/lang/String;
aload 1
invokevirtual java/lang/Exception/getMessage()Ljava/lang/String;
invokestatic android/util/Log/e(Ljava/lang/String;Ljava/lang/String;)I
pop
goto L1
.limit locals 3
.limit stack 4
.end method
