.bytecode 50.0
.class synchronized com/nd/android/u/cloud/activity/Bind91Account$progressBind
.super com/common/android/utils/task/progressTask/ProgressTask
.inner class private progressBind inner com/nd/android/u/cloud/activity/Bind91Account$progressBind outer com/nd/android/u/cloud/activity/Bind91Account

.field final synthetic 'this$0' Lcom/nd/android/u/cloud/activity/Bind91Account;

.method public <init>(Lcom/nd/android/u/cloud/activity/Bind91Account;Landroid/content/Context;I)V
aload 0
aload 1
putfield com/nd/android/u/cloud/activity/Bind91Account$progressBind/this$0 Lcom/nd/android/u/cloud/activity/Bind91Account;
aload 0
aload 2
iload 3
invokespecial com/common/android/utils/task/progressTask/ProgressTask/<init>(Landroid/content/Context;I)V
return
.limit locals 4
.limit stack 3
.end method

.method protected doFail(I)V
iload 1
sipush 1000
if_icmple L0
aload 0
getfield com/nd/android/u/cloud/activity/Bind91Account$progressBind/this$0 Lcom/nd/android/u/cloud/activity/Bind91Account;
invokestatic com/nd/android/u/cloud/activity/Bind91Account/access$000(Lcom/nd/android/u/cloud/activity/Bind91Account;)Lcom/nd/rj/common/login/NdLogin91Assistant;
invokevirtual com/nd/rj/common/login/NdLogin91Assistant/getErrmsg()Ljava/lang/String;
astore 2
aload 2
invokestatic android/text/TextUtils/isEmpty(Ljava/lang/CharSequence;)Z
ifeq L1
aload 0
getfield com/nd/android/u/cloud/activity/Bind91Account$progressBind/this$0 Lcom/nd/android/u/cloud/activity/Bind91Account;
invokestatic com/nd/android/u/cloud/activity/Bind91Account/access$700(Lcom/nd/android/u/cloud/activity/Bind91Account;)Landroid/content/Context;
iload 1
invokestatic com/nd/rj/common/login/NdLoginComFun/ShowToast(Landroid/content/Context;I)V
return
L1:
aload 0
getfield com/nd/android/u/cloud/activity/Bind91Account$progressBind/this$0 Lcom/nd/android/u/cloud/activity/Bind91Account;
invokestatic com/nd/android/u/cloud/activity/Bind91Account/access$700(Lcom/nd/android/u/cloud/activity/Bind91Account;)Landroid/content/Context;
aload 2
invokestatic com/nd/rj/common/login/NdLoginComFun/ShowToast(Landroid/content/Context;Ljava/lang/String;)V
return
L0:
aload 0
getfield com/nd/android/u/cloud/activity/Bind91Account$progressBind/mErrorMsg Ljava/lang/StringBuilder;
invokevirtual java/lang/StringBuilder/toString()Ljava/lang/String;
astore 2
aload 2
invokestatic android/text/TextUtils/isEmpty(Ljava/lang/CharSequence;)Z
ifeq L2
aload 0
aload 0
getfield com/nd/android/u/cloud/activity/Bind91Account$progressBind/this$0 Lcom/nd/android/u/cloud/activity/Bind91Account;
invokestatic com/nd/android/u/cloud/activity/Bind91Account/access$700(Lcom/nd/android/u/cloud/activity/Bind91Account;)Landroid/content/Context;
iload 1
invokevirtual com/nd/android/u/cloud/activity/Bind91Account$progressBind/showToast(Landroid/content/Context;I)V
return
L2:
aload 0
aload 0
getfield com/nd/android/u/cloud/activity/Bind91Account$progressBind/this$0 Lcom/nd/android/u/cloud/activity/Bind91Account;
invokestatic com/nd/android/u/cloud/activity/Bind91Account/access$700(Lcom/nd/android/u/cloud/activity/Bind91Account;)Landroid/content/Context;
aload 2
invokevirtual com/nd/android/u/cloud/activity/Bind91Account$progressBind/showToast(Landroid/content/Context;Ljava/lang/String;)V
return
.limit locals 3
.limit stack 3
.end method

.method protected transient doInBackground([Ljava/lang/Void;)Ljava/lang/Integer;
iconst_0
istore 3
aload 0
getfield com/nd/android/u/cloud/activity/Bind91Account$progressBind/this$0 Lcom/nd/android/u/cloud/activity/Bind91Account;
invokestatic com/nd/android/u/cloud/activity/Bind91Account/access$000(Lcom/nd/android/u/cloud/activity/Bind91Account;)Lcom/nd/rj/common/login/NdLogin91Assistant;
invokevirtual com/nd/rj/common/login/NdLogin91Assistant/isInitSuccessful()Z
ifne L0
aload 0
getfield com/nd/android/u/cloud/activity/Bind91Account$progressBind/this$0 Lcom/nd/android/u/cloud/activity/Bind91Account;
invokestatic com/nd/android/u/cloud/activity/Bind91Account/access$000(Lcom/nd/android/u/cloud/activity/Bind91Account;)Lcom/nd/rj/common/login/NdLogin91Assistant;
invokevirtual com/nd/rj/common/login/NdLogin91Assistant/doInit()I
istore 3
L0:
iload 3
istore 2
iload 3
ifne L1
aload 0
getfield com/nd/android/u/cloud/activity/Bind91Account$progressBind/this$0 Lcom/nd/android/u/cloud/activity/Bind91Account;
invokestatic com/nd/android/u/cloud/activity/Bind91Account/access$400(Lcom/nd/android/u/cloud/activity/Bind91Account;)Landroid/widget/EditText;
invokevirtual android/widget/EditText/getText()Landroid/text/Editable;
invokevirtual java/lang/Object/toString()Ljava/lang/String;
astore 1
aload 0
getfield com/nd/android/u/cloud/activity/Bind91Account$progressBind/this$0 Lcom/nd/android/u/cloud/activity/Bind91Account;
invokestatic com/nd/android/u/cloud/activity/Bind91Account/access$000(Lcom/nd/android/u/cloud/activity/Bind91Account;)Lcom/nd/rj/common/login/NdLogin91Assistant;
aload 1
aload 0
getfield com/nd/android/u/cloud/activity/Bind91Account$progressBind/this$0 Lcom/nd/android/u/cloud/activity/Bind91Account;
invokestatic com/nd/android/u/cloud/activity/Bind91Account/access$500(Lcom/nd/android/u/cloud/activity/Bind91Account;)Landroid/widget/EditText;
invokevirtual android/widget/EditText/getText()Landroid/text/Editable;
invokevirtual java/lang/Object/toString()Ljava/lang/String;
ldc "GB2312"
invokestatic com/nd/rj/common/util/EncryptTool/getMD5str(Ljava/lang/String;Ljava/lang/String;)Ljava/lang/String;
invokevirtual java/lang/String/toLowerCase()Ljava/lang/String;
aload 0
getfield com/nd/android/u/cloud/activity/Bind91Account$progressBind/this$0 Lcom/nd/android/u/cloud/activity/Bind91Account;
invokestatic com/nd/android/u/cloud/activity/Bind91Account/access$200(Lcom/nd/android/u/cloud/activity/Bind91Account;)Landroid/widget/EditText;
invokevirtual android/widget/EditText/getText()Landroid/text/Editable;
invokevirtual java/lang/Object/toString()Ljava/lang/String;
invokevirtual com/nd/rj/common/login/NdLogin91Assistant/doLogin(Ljava/lang/String;Ljava/lang/String;Ljava/lang/String;)I
istore 3
iload 3
sipush 20054
if_icmpne L2
iload 3
invokestatic java/lang/Integer/valueOf(I)Ljava/lang/Integer;
areturn
L2:
iload 3
istore 2
iload 3
ifne L1
aload 0
getfield com/nd/android/u/cloud/activity/Bind91Account$progressBind/this$0 Lcom/nd/android/u/cloud/activity/Bind91Account;
invokestatic com/nd/android/u/cloud/activity/Bind91Account/access$000(Lcom/nd/android/u/cloud/activity/Bind91Account;)Lcom/nd/rj/common/login/NdLogin91Assistant;
invokevirtual com/nd/rj/common/login/NdLogin91Assistant/getCookie()Ljava/lang/String;
astore 4
invokestatic com/nd/android/u/cloud/com/WorkIdLoginCom/getInstance()Lcom/nd/android/u/cloud/com/WorkIdLoginCom;
aload 1
aload 4
aload 0
getfield com/nd/android/u/cloud/activity/Bind91Account$progressBind/this$0 Lcom/nd/android/u/cloud/activity/Bind91Account;
invokestatic com/nd/android/u/cloud/activity/Bind91Account/access$600(Lcom/nd/android/u/cloud/activity/Bind91Account;)Landroid/widget/EditText;
invokevirtual android/widget/EditText/getText()Landroid/text/Editable;
invokevirtual java/lang/Object/toString()Ljava/lang/String;
aload 0
getfield com/nd/android/u/cloud/activity/Bind91Account$progressBind/mErrorMsg Ljava/lang/StringBuilder;
invokevirtual com/nd/android/u/cloud/com/WorkIdLoginCom/doAccountBind(Ljava/lang/String;Ljava/lang/String;Ljava/lang/String;Ljava/lang/StringBuilder;)I
istore 3
iload 3
istore 2
iload 3
sipush 200
if_icmpne L1
iconst_0
invokestatic java/lang/Integer/valueOf(I)Ljava/lang/Integer;
areturn
L1:
iload 2
invokestatic java/lang/Integer/valueOf(I)Ljava/lang/Integer;
areturn
.limit locals 5
.limit stack 5
.end method

.method protected volatile synthetic doInBackground([Ljava/lang/Object;)Ljava/lang/Object;
aload 0
aload 1
checkcast [Ljava/lang/Void;
invokevirtual com/nd/android/u/cloud/activity/Bind91Account$progressBind/doInBackground([Ljava/lang/Void;)Ljava/lang/Integer;
areturn
.limit locals 2
.limit stack 2
.end method

.method protected doSuccess()V
aload 0
aload 0
getfield com/nd/android/u/cloud/activity/Bind91Account$progressBind/this$0 Lcom/nd/android/u/cloud/activity/Bind91Account;
invokestatic com/nd/android/u/cloud/activity/Bind91Account/access$700(Lcom/nd/android/u/cloud/activity/Bind91Account;)Landroid/content/Context;
ldc_w 2131493045
invokevirtual com/nd/android/u/cloud/activity/Bind91Account$progressBind/showToast(Landroid/content/Context;I)V
aload 0
getfield com/nd/android/u/cloud/activity/Bind91Account$progressBind/this$0 Lcom/nd/android/u/cloud/activity/Bind91Account;
invokevirtual com/nd/android/u/cloud/activity/Bind91Account/rightBtnHandle()V
return
.limit locals 1
.limit stack 3
.end method
