.bytecode 50.0
.class synchronized com/nd/android/u/cloud/activity/Bind91Account$5
.super android/os/Handler
.enclosing method com/nd/android/u/cloud/activity/Bind91Account
.inner class inner com/nd/android/u/cloud/activity/Bind91Account$5

.field final synthetic 'this$0' Lcom/nd/android/u/cloud/activity/Bind91Account;

.method <init>(Lcom/nd/android/u/cloud/activity/Bind91Account;)V
aload 0
aload 1
putfield com/nd/android/u/cloud/activity/Bind91Account$5/this$0 Lcom/nd/android/u/cloud/activity/Bind91Account;
aload 0
invokespecial android/os/Handler/<init>()V
return
.limit locals 2
.limit stack 2
.end method

.method public handleMessage(Landroid/os/Message;)V
aload 1
getfield android/os/Message/what I
tableswitch 989802
L0
L1
L2
default : L1
L1:
return
L0:
aload 1
getfield android/os/Message/obj Ljava/lang/Object;
checkcast com/product/android/business/bean/UserInfo
astore 1
aload 0
getfield com/nd/android/u/cloud/activity/Bind91Account$5/this$0 Lcom/nd/android/u/cloud/activity/Bind91Account;
invokestatic com/nd/android/u/cloud/activity/Bind91Account/access$400(Lcom/nd/android/u/cloud/activity/Bind91Account;)Landroid/widget/EditText;
aload 1
invokevirtual com/product/android/business/bean/UserInfo/getUserName()Ljava/lang/String;
invokevirtual android/widget/EditText/setText(Ljava/lang/CharSequence;)V
aload 0
getfield com/nd/android/u/cloud/activity/Bind91Account$5/this$0 Lcom/nd/android/u/cloud/activity/Bind91Account;
invokestatic com/nd/android/u/cloud/activity/Bind91Account/access$500(Lcom/nd/android/u/cloud/activity/Bind91Account;)Landroid/widget/EditText;
aload 1
invokevirtual com/product/android/business/bean/UserInfo/getUserPass()Ljava/lang/String;
invokevirtual android/widget/EditText/setText(Ljava/lang/CharSequence;)V
new com/nd/android/u/cloud/ui/dialog/Bind91AccountNoPwdDialog
dup
aload 0
getfield com/nd/android/u/cloud/activity/Bind91Account$5/this$0 Lcom/nd/android/u/cloud/activity/Bind91Account;
invokespecial com/nd/android/u/cloud/ui/dialog/Bind91AccountNoPwdDialog/<init>(Landroid/content/Context;)V
invokevirtual com/nd/android/u/cloud/ui/dialog/Bind91AccountNoPwdDialog/create()Landroid/app/AlertDialog;
invokevirtual android/app/AlertDialog/show()V
return
L2:
aload 1
getfield android/os/Message/obj Ljava/lang/Object;
checkcast com/product/android/business/bean/UserInfo
astore 1
aload 0
getfield com/nd/android/u/cloud/activity/Bind91Account$5/this$0 Lcom/nd/android/u/cloud/activity/Bind91Account;
invokestatic com/nd/android/u/cloud/activity/Bind91Account/access$400(Lcom/nd/android/u/cloud/activity/Bind91Account;)Landroid/widget/EditText;
aload 1
invokevirtual com/product/android/business/bean/UserInfo/getUserName()Ljava/lang/String;
invokevirtual android/widget/EditText/setText(Ljava/lang/CharSequence;)V
aload 0
getfield com/nd/android/u/cloud/activity/Bind91Account$5/this$0 Lcom/nd/android/u/cloud/activity/Bind91Account;
invokestatic com/nd/android/u/cloud/activity/Bind91Account/access$500(Lcom/nd/android/u/cloud/activity/Bind91Account;)Landroid/widget/EditText;
aload 1
invokevirtual com/product/android/business/bean/UserInfo/getUserPass()Ljava/lang/String;
invokevirtual android/widget/EditText/setText(Ljava/lang/CharSequence;)V
aload 0
getfield com/nd/android/u/cloud/activity/Bind91Account$5/this$0 Lcom/nd/android/u/cloud/activity/Bind91Account;
invokestatic com/nd/android/u/cloud/activity/Bind91Account/access$700(Lcom/nd/android/u/cloud/activity/Bind91Account;)Landroid/content/Context;
ldc_w 2131493041
invokestatic com/nd/rj/common/login/NdLoginComFun/ShowToast(Landroid/content/Context;I)V
return
.limit locals 2
.limit stack 3
.end method
