.bytecode 50.0
.class synchronized com/nd/android/u/cloud/activity/ChangeWorkerLoginUserPassword$4
.super java/lang/Object
.implements android/view/View$OnClickListener
.enclosing method com/nd/android/u/cloud/activity/ChangeWorkerLoginUserPassword/_onCreate(Landroid/os/Bundle;)Z
.inner class inner com/nd/android/u/cloud/activity/ChangeWorkerLoginUserPassword$4

.field final synthetic 'this$0' Lcom/nd/android/u/cloud/activity/ChangeWorkerLoginUserPassword;

.method <init>(Lcom/nd/android/u/cloud/activity/ChangeWorkerLoginUserPassword;)V
aload 0
aload 1
putfield com/nd/android/u/cloud/activity/ChangeWorkerLoginUserPassword$4/this$0 Lcom/nd/android/u/cloud/activity/ChangeWorkerLoginUserPassword;
aload 0
invokespecial java/lang/Object/<init>()V
return
.limit locals 2
.limit stack 2
.end method

.method public onClick(Landroid/view/View;)V
aload 0
getfield com/nd/android/u/cloud/activity/ChangeWorkerLoginUserPassword$4/this$0 Lcom/nd/android/u/cloud/activity/ChangeWorkerLoginUserPassword;
invokestatic com/nd/android/u/cloud/activity/ChangeWorkerLoginUserPassword/access$100(Lcom/nd/android/u/cloud/activity/ChangeWorkerLoginUserPassword;)I
istore 2
iload 2
ifne L0
invokestatic ims/utils/IMSUtils/JudgeNetWorkStatus()Z
ifne L1
aload 0
getfield com/nd/android/u/cloud/activity/ChangeWorkerLoginUserPassword$4/this$0 Lcom/nd/android/u/cloud/activity/ChangeWorkerLoginUserPassword;
invokestatic com/nd/android/u/cloud/activity/ChangeWorkerLoginUserPassword/access$000(Lcom/nd/android/u/cloud/activity/ChangeWorkerLoginUserPassword;)Landroid/content/Context;
ldc_w 2131494478
invokestatic com/common/android/utils/ToastUtils/display(Landroid/content/Context;I)V
return
L1:
new com/nd/android/u/cloud/activity/ChangeWorkerLoginUserPassword$ChangeJobNumberPwdTask
dup
aload 0
getfield com/nd/android/u/cloud/activity/ChangeWorkerLoginUserPassword$4/this$0 Lcom/nd/android/u/cloud/activity/ChangeWorkerLoginUserPassword;
aload 0
getfield com/nd/android/u/cloud/activity/ChangeWorkerLoginUserPassword$4/this$0 Lcom/nd/android/u/cloud/activity/ChangeWorkerLoginUserPassword;
invokestatic com/nd/android/u/cloud/activity/ChangeWorkerLoginUserPassword/access$400(Lcom/nd/android/u/cloud/activity/ChangeWorkerLoginUserPassword;)Z
aload 0
getfield com/nd/android/u/cloud/activity/ChangeWorkerLoginUserPassword$4/this$0 Lcom/nd/android/u/cloud/activity/ChangeWorkerLoginUserPassword;
invokestatic com/nd/android/u/cloud/activity/ChangeWorkerLoginUserPassword/access$500(Lcom/nd/android/u/cloud/activity/ChangeWorkerLoginUserPassword;)Lcom/product/android/business/login/JobNumberUserInfo;
invokespecial com/nd/android/u/cloud/activity/ChangeWorkerLoginUserPassword$ChangeJobNumberPwdTask/<init>(Landroid/app/Activity;ZLcom/product/android/business/login/JobNumberUserInfo;)V
iconst_2
anewarray java/lang/String
dup
iconst_0
aload 0
getfield com/nd/android/u/cloud/activity/ChangeWorkerLoginUserPassword$4/this$0 Lcom/nd/android/u/cloud/activity/ChangeWorkerLoginUserPassword;
invokestatic com/nd/android/u/cloud/activity/ChangeWorkerLoginUserPassword/access$200(Lcom/nd/android/u/cloud/activity/ChangeWorkerLoginUserPassword;)Landroid/widget/EditText;
invokevirtual android/widget/EditText/getText()Landroid/text/Editable;
invokevirtual java/lang/Object/toString()Ljava/lang/String;
aastore
dup
iconst_1
aload 0
getfield com/nd/android/u/cloud/activity/ChangeWorkerLoginUserPassword$4/this$0 Lcom/nd/android/u/cloud/activity/ChangeWorkerLoginUserPassword;
invokestatic com/nd/android/u/cloud/activity/ChangeWorkerLoginUserPassword/access$300(Lcom/nd/android/u/cloud/activity/ChangeWorkerLoginUserPassword;)Landroid/widget/EditText;
invokevirtual android/widget/EditText/getText()Landroid/text/Editable;
invokevirtual java/lang/Object/toString()Ljava/lang/String;
aastore
invokevirtual com/nd/android/u/cloud/activity/ChangeWorkerLoginUserPassword$ChangeJobNumberPwdTask/execute([Ljava/lang/Object;)Lcom/common/android/utils/concurrent/NdTinyHttpAsyncTask;
pop
return
L0:
aload 0
getfield com/nd/android/u/cloud/activity/ChangeWorkerLoginUserPassword$4/this$0 Lcom/nd/android/u/cloud/activity/ChangeWorkerLoginUserPassword;
invokestatic com/nd/android/u/cloud/activity/ChangeWorkerLoginUserPassword/access$000(Lcom/nd/android/u/cloud/activity/ChangeWorkerLoginUserPassword;)Landroid/content/Context;
iload 2
invokestatic com/common/android/utils/ToastUtils/display(Landroid/content/Context;I)V
return
.limit locals 3
.limit stack 5
.end method
