.bytecode 50.0
.class synchronized com/nd/android/u/cloud/activity/MessageDetailActivity$ReSendMessageTask
.super com/common/android/utils/task/genericTask/GenericTask
.inner class private ReSendMessageTask inner com/nd/android/u/cloud/activity/MessageDetailActivity$ReSendMessageTask outer com/nd/android/u/cloud/activity/MessageDetailActivity

.field final synthetic 'this$0' Lcom/nd/android/u/cloud/activity/MessageDetailActivity;

.method private <init>(Lcom/nd/android/u/cloud/activity/MessageDetailActivity;)V
aload 0
aload 1
putfield com/nd/android/u/cloud/activity/MessageDetailActivity$ReSendMessageTask/this$0 Lcom/nd/android/u/cloud/activity/MessageDetailActivity;
aload 0
invokespecial com/common/android/utils/task/genericTask/GenericTask/<init>()V
return
.limit locals 2
.limit stack 2
.end method

.method synthetic <init>(Lcom/nd/android/u/cloud/activity/MessageDetailActivity;Lcom/nd/android/u/cloud/activity/MessageDetailActivity$1;)V
aload 0
aload 1
invokespecial com/nd/android/u/cloud/activity/MessageDetailActivity$ReSendMessageTask/<init>(Lcom/nd/android/u/cloud/activity/MessageDetailActivity;)V
return
.limit locals 3
.limit stack 2
.end method

.method protected transient _doInBackground([Lcom/common/android/utils/task/genericTask/TaskParams;)Lcom/common/android/utils/task/genericTask/TaskResult;
.catch com/common/android/utils/http/HttpAuthException from L0 to L1 using L2
.catch com/common/android/utils/http/ResponseException from L0 to L1 using L3
.catch com/common/android/utils/http/HttpServerException from L0 to L1 using L4
.catch com/common/android/utils/http/HttpException from L0 to L1 using L5
.catch org/json/JSONException from L0 to L1 using L6
.catch com/common/android/utils/http/HttpAuthException from L7 to L8 using L2
.catch com/common/android/utils/http/ResponseException from L7 to L8 using L3
.catch com/common/android/utils/http/HttpServerException from L7 to L8 using L4
.catch com/common/android/utils/http/HttpException from L7 to L8 using L5
.catch org/json/JSONException from L7 to L8 using L6
aload 0
getfield com/nd/android/u/cloud/activity/MessageDetailActivity$ReSendMessageTask/this$0 Lcom/nd/android/u/cloud/activity/MessageDetailActivity;
invokestatic com/nd/android/u/cloud/activity/MessageDetailActivity/access$100(Lcom/nd/android/u/cloud/activity/MessageDetailActivity;)Lcom/nd/android/u/contact/dataStructure/MessageInfo;
invokevirtual com/nd/android/u/contact/dataStructure/MessageInfo/getReceiver_ids()Ljava/lang/String;
ldc ","
invokevirtual java/lang/String/split(Ljava/lang/String;)[Ljava/lang/String;
astore 1
L0:
aload 0
getfield com/nd/android/u/cloud/activity/MessageDetailActivity$ReSendMessageTask/this$0 Lcom/nd/android/u/cloud/activity/MessageDetailActivity;
invokestatic com/nd/android/u/cloud/activity/MessageDetailActivity/access$100(Lcom/nd/android/u/cloud/activity/MessageDetailActivity;)Lcom/nd/android/u/contact/dataStructure/MessageInfo;
invokevirtual com/nd/android/u/contact/dataStructure/MessageInfo/getMsgtype()I
istore 3
L1:
iload 3
istore 2
iload 3
iconst_5
if_icmpne L7
iconst_1
istore 2
L7:
invokestatic com/nd/android/u/cloud/oapprocess/OapRequestProcessImpl/getInstance()Lcom/nd/android/u/cloud/oapprocess/OapRequestProcessImpl;
iload 2
aload 1
aload 0
getfield com/nd/android/u/cloud/activity/MessageDetailActivity$ReSendMessageTask/this$0 Lcom/nd/android/u/cloud/activity/MessageDetailActivity;
invokestatic com/nd/android/u/cloud/activity/MessageDetailActivity/access$100(Lcom/nd/android/u/cloud/activity/MessageDetailActivity;)Lcom/nd/android/u/contact/dataStructure/MessageInfo;
invokevirtual com/nd/android/u/contact/dataStructure/MessageInfo/getReceiveradmit()I
new java/lang/StringBuilder
dup
invokespecial java/lang/StringBuilder/<init>()V
aload 0
getfield com/nd/android/u/cloud/activity/MessageDetailActivity$ReSendMessageTask/this$0 Lcom/nd/android/u/cloud/activity/MessageDetailActivity;
invokestatic com/nd/android/u/cloud/activity/MessageDetailActivity/access$500(Lcom/nd/android/u/cloud/activity/MessageDetailActivity;)Ljava/lang/String;
invokevirtual java/lang/StringBuilder/append(Ljava/lang/String;)Ljava/lang/StringBuilder;
ldc ":"
invokevirtual java/lang/StringBuilder/append(Ljava/lang/String;)Ljava/lang/StringBuilder;
aload 0
getfield com/nd/android/u/cloud/activity/MessageDetailActivity$ReSendMessageTask/this$0 Lcom/nd/android/u/cloud/activity/MessageDetailActivity;
invokestatic com/nd/android/u/cloud/activity/MessageDetailActivity/access$100(Lcom/nd/android/u/cloud/activity/MessageDetailActivity;)Lcom/nd/android/u/contact/dataStructure/MessageInfo;
invokevirtual com/nd/android/u/contact/dataStructure/MessageInfo/getMsg()Ljava/lang/String;
invokevirtual java/lang/StringBuilder/append(Ljava/lang/String;)Ljava/lang/StringBuilder;
invokevirtual java/lang/StringBuilder/toString()Ljava/lang/String;
invokevirtual com/nd/android/u/cloud/oapprocess/OapRequestProcessImpl/sendsms(I[Ljava/lang/String;ILjava/lang/String;)Ljava/lang/String;
astore 1
aload 0
getfield com/nd/android/u/cloud/activity/MessageDetailActivity$ReSendMessageTask/this$0 Lcom/nd/android/u/cloud/activity/MessageDetailActivity;
invokestatic com/nd/android/u/cloud/activity/MessageDetailActivity/access$100(Lcom/nd/android/u/cloud/activity/MessageDetailActivity;)Lcom/nd/android/u/contact/dataStructure/MessageInfo;
aload 1
invokevirtual com/nd/android/u/contact/dataStructure/MessageInfo/setSmsid(Ljava/lang/String;)V
ldc "MessageDetailActivity"
new java/lang/StringBuilder
dup
invokespecial java/lang/StringBuilder/<init>()V
ldc "smsid: "
invokevirtual java/lang/StringBuilder/append(Ljava/lang/String;)Ljava/lang/StringBuilder;
aload 1
invokevirtual java/lang/StringBuilder/append(Ljava/lang/String;)Ljava/lang/StringBuilder;
invokevirtual java/lang/StringBuilder/toString()Ljava/lang/String;
invokestatic android/util/Log/v(Ljava/lang/String;Ljava/lang/String;)I
pop
L8:
getstatic com/common/android/utils/task/genericTask/TaskResult/OK Lcom/common/android/utils/task/genericTask/TaskResult;
areturn
L2:
astore 1
aload 1
invokevirtual com/common/android/utils/http/HttpAuthException/printStackTrace()V
aload 1
invokevirtual com/common/android/utils/http/HttpAuthException/getStatusCode()I
istore 2
aload 0
new java/lang/StringBuilder
dup
invokespecial java/lang/StringBuilder/<init>()V
iload 2
invokevirtual java/lang/StringBuilder/append(I)Ljava/lang/StringBuilder;
ldc ""
invokevirtual java/lang/StringBuilder/append(Ljava/lang/String;)Ljava/lang/StringBuilder;
invokevirtual java/lang/StringBuilder/toString()Ljava/lang/String;
putfield com/nd/android/u/cloud/activity/MessageDetailActivity$ReSendMessageTask/message Ljava/lang/String;
getstatic com/common/android/utils/task/genericTask/TaskResult/FAILED Lcom/common/android/utils/task/genericTask/TaskResult;
areturn
L3:
astore 1
aload 1
invokevirtual com/common/android/utils/http/ResponseException/printStackTrace()V
aload 1
invokevirtual com/common/android/utils/http/ResponseException/getStatusCode()I
istore 2
aload 0
new java/lang/StringBuilder
dup
invokespecial java/lang/StringBuilder/<init>()V
iload 2
invokevirtual java/lang/StringBuilder/append(I)Ljava/lang/StringBuilder;
ldc ""
invokevirtual java/lang/StringBuilder/append(Ljava/lang/String;)Ljava/lang/StringBuilder;
invokevirtual java/lang/StringBuilder/toString()Ljava/lang/String;
putfield com/nd/android/u/cloud/activity/MessageDetailActivity$ReSendMessageTask/message Ljava/lang/String;
getstatic com/common/android/utils/task/genericTask/TaskResult/FAILED Lcom/common/android/utils/task/genericTask/TaskResult;
areturn
L4:
astore 1
aload 1
invokevirtual com/common/android/utils/http/HttpServerException/printStackTrace()V
aload 1
invokevirtual com/common/android/utils/http/HttpServerException/getStatusCode()I
istore 2
aload 0
new java/lang/StringBuilder
dup
invokespecial java/lang/StringBuilder/<init>()V
iload 2
invokevirtual java/lang/StringBuilder/append(I)Ljava/lang/StringBuilder;
ldc ""
invokevirtual java/lang/StringBuilder/append(Ljava/lang/String;)Ljava/lang/StringBuilder;
invokevirtual java/lang/StringBuilder/toString()Ljava/lang/String;
putfield com/nd/android/u/cloud/activity/MessageDetailActivity$ReSendMessageTask/message Ljava/lang/String;
getstatic com/common/android/utils/task/genericTask/TaskResult/FAILED Lcom/common/android/utils/task/genericTask/TaskResult;
areturn
L5:
astore 1
aload 1
invokevirtual com/common/android/utils/http/HttpException/printStackTrace()V
aload 1
invokevirtual com/common/android/utils/http/HttpException/getStatusCode()I
istore 2
aload 0
new java/lang/StringBuilder
dup
invokespecial java/lang/StringBuilder/<init>()V
iload 2
invokevirtual java/lang/StringBuilder/append(I)Ljava/lang/StringBuilder;
ldc ""
invokevirtual java/lang/StringBuilder/append(Ljava/lang/String;)Ljava/lang/StringBuilder;
invokevirtual java/lang/StringBuilder/toString()Ljava/lang/String;
putfield com/nd/android/u/cloud/activity/MessageDetailActivity$ReSendMessageTask/message Ljava/lang/String;
getstatic com/common/android/utils/task/genericTask/TaskResult/FAILED Lcom/common/android/utils/task/genericTask/TaskResult;
areturn
L6:
astore 1
aload 1
invokevirtual org/json/JSONException/printStackTrace()V
aload 0
new java/lang/StringBuilder
dup
invokespecial java/lang/StringBuilder/<init>()V
iconst_0
invokevirtual java/lang/StringBuilder/append(I)Ljava/lang/StringBuilder;
ldc ""
invokevirtual java/lang/StringBuilder/append(Ljava/lang/String;)Ljava/lang/StringBuilder;
invokevirtual java/lang/StringBuilder/toString()Ljava/lang/String;
putfield com/nd/android/u/cloud/activity/MessageDetailActivity$ReSendMessageTask/message Ljava/lang/String;
getstatic com/common/android/utils/task/genericTask/TaskResult/FAILED Lcom/common/android/utils/task/genericTask/TaskResult;
areturn
.limit locals 4
.limit stack 6
.end method
