.bytecode 50.0
.class synchronized com/nd/android/u/cloud/activity/MessageDetailActivity$3
.super com/common/android/utils/task/genericTask/TaskAdapter
.enclosing method com/nd/android/u/cloud/activity/MessageDetailActivity
.inner class inner com/nd/android/u/cloud/activity/MessageDetailActivity$3

.field final synthetic 'this$0' Lcom/nd/android/u/cloud/activity/MessageDetailActivity;

.method <init>(Lcom/nd/android/u/cloud/activity/MessageDetailActivity;)V
aload 0
aload 1
putfield com/nd/android/u/cloud/activity/MessageDetailActivity$3/this$0 Lcom/nd/android/u/cloud/activity/MessageDetailActivity;
aload 0
invokespecial com/common/android/utils/task/genericTask/TaskAdapter/<init>()V
return
.limit locals 2
.limit stack 2
.end method

.method public onPostExecute(Lcom/common/android/utils/task/genericTask/GenericTask;Lcom/common/android/utils/task/genericTask/TaskResult;)V
aload 2
getstatic com/common/android/utils/task/genericTask/TaskResult/OK Lcom/common/android/utils/task/genericTask/TaskResult;
if_acmpne L0
ldc "MessageDetailActivity"
ldc "\u53d1\u9001\u6210\u529f"
invokestatic android/util/Log/v(Ljava/lang/String;Ljava/lang/String;)I
pop
aload 0
getfield com/nd/android/u/cloud/activity/MessageDetailActivity$3/this$0 Lcom/nd/android/u/cloud/activity/MessageDetailActivity;
invokestatic com/nd/android/u/cloud/activity/MessageDetailActivity/access$100(Lcom/nd/android/u/cloud/activity/MessageDetailActivity;)Lcom/nd/android/u/contact/dataStructure/MessageInfo;
invokestatic java/util/Calendar/getInstance()Ljava/util/Calendar;
invokevirtual java/util/Calendar/getTime()Ljava/util/Date;
invokevirtual com/nd/android/u/contact/dataStructure/MessageInfo/setTime(Ljava/util/Date;)V
aload 0
getfield com/nd/android/u/cloud/activity/MessageDetailActivity$3/this$0 Lcom/nd/android/u/cloud/activity/MessageDetailActivity;
invokestatic com/nd/android/u/cloud/activity/MessageDetailActivity/access$100(Lcom/nd/android/u/cloud/activity/MessageDetailActivity;)Lcom/nd/android/u/contact/dataStructure/MessageInfo;
bipush 100
invokevirtual com/nd/android/u/contact/dataStructure/MessageInfo/setIssuccess(I)V
ldc com/nd/android/u/contact/dao/MessageInfoDAO
invokestatic com/nd/android/u/contact/db/ContactDaoFactory/getImpl(Ljava/lang/Class;)Ljava/lang/Object;
checkcast com/nd/android/u/contact/dao/MessageInfoDAO
aload 0
getfield com/nd/android/u/cloud/activity/MessageDetailActivity$3/this$0 Lcom/nd/android/u/cloud/activity/MessageDetailActivity;
invokestatic com/nd/android/u/cloud/activity/MessageDetailActivity/access$100(Lcom/nd/android/u/cloud/activity/MessageDetailActivity;)Lcom/nd/android/u/contact/dataStructure/MessageInfo;
invokeinterface com/nd/android/u/contact/dao/MessageInfoDAO/insertMessageInfo(Lcom/nd/android/u/contact/dataStructure/MessageInfo;)J 1
pop2
aload 0
getfield com/nd/android/u/cloud/activity/MessageDetailActivity$3/this$0 Lcom/nd/android/u/cloud/activity/MessageDetailActivity;
ldc_w 2131495015
invokestatic com/common/android/utils/ToastUtils/display(Landroid/content/Context;I)V
aload 0
getfield com/nd/android/u/cloud/activity/MessageDetailActivity$3/this$0 Lcom/nd/android/u/cloud/activity/MessageDetailActivity;
invokevirtual com/nd/android/u/cloud/activity/MessageDetailActivity/finish()V
L1:
aload 0
getfield com/nd/android/u/cloud/activity/MessageDetailActivity$3/this$0 Lcom/nd/android/u/cloud/activity/MessageDetailActivity;
invokestatic com/nd/android/u/cloud/activity/MessageDetailActivity/access$300(Lcom/nd/android/u/cloud/activity/MessageDetailActivity;)Landroid/app/ProgressDialog;
ifnull L2
aload 0
getfield com/nd/android/u/cloud/activity/MessageDetailActivity$3/this$0 Lcom/nd/android/u/cloud/activity/MessageDetailActivity;
invokestatic com/nd/android/u/cloud/activity/MessageDetailActivity/access$300(Lcom/nd/android/u/cloud/activity/MessageDetailActivity;)Landroid/app/ProgressDialog;
invokevirtual android/app/ProgressDialog/dismiss()V
L2:
return
L0:
aload 1
invokevirtual com/common/android/utils/task/genericTask/GenericTask/getMessage()Ljava/lang/String;
astore 1
aload 1
ifnull L3
aload 1
ldc "403"
invokevirtual java/lang/String/equals(Ljava/lang/Object;)Z
ifeq L3
aload 0
getfield com/nd/android/u/cloud/activity/MessageDetailActivity$3/this$0 Lcom/nd/android/u/cloud/activity/MessageDetailActivity;
ldc_w 2131494516
invokestatic com/common/android/utils/ToastUtils/display(Landroid/content/Context;I)V
L4:
aload 0
getfield com/nd/android/u/cloud/activity/MessageDetailActivity$3/this$0 Lcom/nd/android/u/cloud/activity/MessageDetailActivity;
invokestatic com/nd/android/u/cloud/activity/MessageDetailActivity/access$100(Lcom/nd/android/u/cloud/activity/MessageDetailActivity;)Lcom/nd/android/u/contact/dataStructure/MessageInfo;
invokestatic java/util/Calendar/getInstance()Ljava/util/Calendar;
invokevirtual java/util/Calendar/getTime()Ljava/util/Date;
invokevirtual com/nd/android/u/contact/dataStructure/MessageInfo/setTime(Ljava/util/Date;)V
aload 0
getfield com/nd/android/u/cloud/activity/MessageDetailActivity$3/this$0 Lcom/nd/android/u/cloud/activity/MessageDetailActivity;
invokestatic com/nd/android/u/cloud/activity/MessageDetailActivity/access$100(Lcom/nd/android/u/cloud/activity/MessageDetailActivity;)Lcom/nd/android/u/contact/dataStructure/MessageInfo;
iconst_m1
invokevirtual com/nd/android/u/contact/dataStructure/MessageInfo/setIssuccess(I)V
ldc com/nd/android/u/contact/dao/MessageInfoDAO
invokestatic com/nd/android/u/contact/db/ContactDaoFactory/getImpl(Ljava/lang/Class;)Ljava/lang/Object;
checkcast com/nd/android/u/contact/dao/MessageInfoDAO
aload 0
getfield com/nd/android/u/cloud/activity/MessageDetailActivity$3/this$0 Lcom/nd/android/u/cloud/activity/MessageDetailActivity;
invokestatic com/nd/android/u/cloud/activity/MessageDetailActivity/access$100(Lcom/nd/android/u/cloud/activity/MessageDetailActivity;)Lcom/nd/android/u/contact/dataStructure/MessageInfo;
invokeinterface com/nd/android/u/contact/dao/MessageInfoDAO/insertMessageInfo(Lcom/nd/android/u/contact/dataStructure/MessageInfo;)J 1
pop2
goto L1
L3:
aload 1
ifnull L5
aload 1
ldc "406"
invokevirtual java/lang/String/equals(Ljava/lang/Object;)Z
ifeq L5
aload 0
getfield com/nd/android/u/cloud/activity/MessageDetailActivity$3/this$0 Lcom/nd/android/u/cloud/activity/MessageDetailActivity;
ldc_w 2131494977
invokestatic com/common/android/utils/ToastUtils/display(Landroid/content/Context;I)V
goto L4
L5:
aload 1
ifnull L6
aload 1
ldc "411"
invokevirtual java/lang/String/equals(Ljava/lang/Object;)Z
ifeq L6
aload 0
getfield com/nd/android/u/cloud/activity/MessageDetailActivity$3/this$0 Lcom/nd/android/u/cloud/activity/MessageDetailActivity;
ldc_w 2131495469
invokestatic com/common/android/utils/ToastUtils/display(Landroid/content/Context;I)V
goto L4
L6:
aload 0
getfield com/nd/android/u/cloud/activity/MessageDetailActivity$3/this$0 Lcom/nd/android/u/cloud/activity/MessageDetailActivity;
ldc_w 2131495014
invokestatic com/common/android/utils/ToastUtils/display(Landroid/content/Context;I)V
goto L4
.limit locals 3
.limit stack 2
.end method

.method public onPreExecute(Lcom/common/android/utils/task/genericTask/GenericTask;)V
aload 0
getfield com/nd/android/u/cloud/activity/MessageDetailActivity$3/this$0 Lcom/nd/android/u/cloud/activity/MessageDetailActivity;
aload 0
getfield com/nd/android/u/cloud/activity/MessageDetailActivity$3/this$0 Lcom/nd/android/u/cloud/activity/MessageDetailActivity;
invokevirtual com/nd/android/u/cloud/activity/MessageDetailActivity/getResources()Landroid/content/res/Resources;
ldc_w 2131494978
invokevirtual android/content/res/Resources/getString(I)Ljava/lang/String;
invokestatic com/nd/android/u/cloud/activity/MessageDetailActivity/access$400(Lcom/nd/android/u/cloud/activity/MessageDetailActivity;Ljava/lang/String;)V
return
.limit locals 2
.limit stack 3
.end method
