.bytecode 50.0
.class synchronized com/nd/android/u/cloud/activity/MessageDetailActivity$2
.super java/lang/Object
.implements android/view/View$OnClickListener
.enclosing method com/nd/android/u/cloud/activity/MessageDetailActivity
.inner class inner com/nd/android/u/cloud/activity/MessageDetailActivity$2

.field final synthetic 'this$0' Lcom/nd/android/u/cloud/activity/MessageDetailActivity;

.method <init>(Lcom/nd/android/u/cloud/activity/MessageDetailActivity;)V
aload 0
aload 1
putfield com/nd/android/u/cloud/activity/MessageDetailActivity$2/this$0 Lcom/nd/android/u/cloud/activity/MessageDetailActivity;
aload 0
invokespecial java/lang/Object/<init>()V
return
.limit locals 2
.limit stack 2
.end method

.method public onClick(Landroid/view/View;)V
aload 1
invokevirtual android/view/View/getId()I
lookupswitch
2131625528 : L0
2131625984 : L1
default : L2
L2:
return
L1:
aload 0
getfield com/nd/android/u/cloud/activity/MessageDetailActivity$2/this$0 Lcom/nd/android/u/cloud/activity/MessageDetailActivity;
invokestatic com/nd/android/u/cloud/activity/MessageDetailActivity/access$100(Lcom/nd/android/u/cloud/activity/MessageDetailActivity;)Lcom/nd/android/u/contact/dataStructure/MessageInfo;
invokevirtual com/nd/android/u/contact/dataStructure/MessageInfo/getReplynum()I
istore 2
ldc "MessageDetailActivity"
new java/lang/StringBuilder
dup
invokespecial java/lang/StringBuilder/<init>()V
ldc "\u77ed\u4fe1\u7684\u72b6\u6001: "
invokevirtual java/lang/StringBuilder/append(Ljava/lang/String;)Ljava/lang/StringBuilder;
iload 2
invokevirtual java/lang/StringBuilder/append(I)Ljava/lang/StringBuilder;
invokevirtual java/lang/StringBuilder/toString()Ljava/lang/String;
invokestatic android/util/Log/v(Ljava/lang/String;Ljava/lang/String;)I
pop
aload 0
getfield com/nd/android/u/cloud/activity/MessageDetailActivity$2/this$0 Lcom/nd/android/u/cloud/activity/MessageDetailActivity;
invokestatic com/nd/android/u/cloud/activity/MessageDetailActivity/access$100(Lcom/nd/android/u/cloud/activity/MessageDetailActivity;)Lcom/nd/android/u/contact/dataStructure/MessageInfo;
invokevirtual com/nd/android/u/contact/dataStructure/MessageInfo/getSucnum()I
istore 3
aload 0
getfield com/nd/android/u/cloud/activity/MessageDetailActivity$2/this$0 Lcom/nd/android/u/cloud/activity/MessageDetailActivity;
invokestatic com/nd/android/u/cloud/activity/MessageDetailActivity/access$100(Lcom/nd/android/u/cloud/activity/MessageDetailActivity;)Lcom/nd/android/u/contact/dataStructure/MessageInfo;
invokevirtual com/nd/android/u/contact/dataStructure/MessageInfo/getFailednum()I
istore 4
aload 0
getfield com/nd/android/u/cloud/activity/MessageDetailActivity$2/this$0 Lcom/nd/android/u/cloud/activity/MessageDetailActivity;
invokestatic com/nd/android/u/cloud/activity/MessageDetailActivity/access$100(Lcom/nd/android/u/cloud/activity/MessageDetailActivity;)Lcom/nd/android/u/contact/dataStructure/MessageInfo;
invokevirtual com/nd/android/u/contact/dataStructure/MessageInfo/getTotalnum()I
istore 5
iload 2
iconst_2
if_icmpne L3
iload 5
iload 3
iload 4
iadd
if_icmpeq L4
L3:
aload 0
getfield com/nd/android/u/cloud/activity/MessageDetailActivity$2/this$0 Lcom/nd/android/u/cloud/activity/MessageDetailActivity;
ldc_w 2131495542
invokestatic com/common/android/utils/ToastUtils/display(Landroid/content/Context;I)V
aload 0
getfield com/nd/android/u/cloud/activity/MessageDetailActivity$2/this$0 Lcom/nd/android/u/cloud/activity/MessageDetailActivity;
iconst_0
invokevirtual com/nd/android/u/cloud/activity/MessageDetailActivity/sendMessage2C(Z)V
return
L4:
new android/content/Intent
dup
invokespecial android/content/Intent/<init>()V
astore 1
aload 1
ldc "total"
aload 0
getfield com/nd/android/u/cloud/activity/MessageDetailActivity$2/this$0 Lcom/nd/android/u/cloud/activity/MessageDetailActivity;
invokestatic com/nd/android/u/cloud/activity/MessageDetailActivity/access$100(Lcom/nd/android/u/cloud/activity/MessageDetailActivity;)Lcom/nd/android/u/contact/dataStructure/MessageInfo;
invokevirtual com/nd/android/u/contact/dataStructure/MessageInfo/getTotalnum()I
invokevirtual android/content/Intent/putExtra(Ljava/lang/String;I)Landroid/content/Intent;
pop
aload 1
ldc "success"
aload 0
getfield com/nd/android/u/cloud/activity/MessageDetailActivity$2/this$0 Lcom/nd/android/u/cloud/activity/MessageDetailActivity;
invokestatic com/nd/android/u/cloud/activity/MessageDetailActivity/access$100(Lcom/nd/android/u/cloud/activity/MessageDetailActivity;)Lcom/nd/android/u/contact/dataStructure/MessageInfo;
invokevirtual com/nd/android/u/contact/dataStructure/MessageInfo/getSucnum()I
invokevirtual android/content/Intent/putExtra(Ljava/lang/String;I)Landroid/content/Intent;
pop
aload 1
ldc "fail"
aload 0
getfield com/nd/android/u/cloud/activity/MessageDetailActivity$2/this$0 Lcom/nd/android/u/cloud/activity/MessageDetailActivity;
invokestatic com/nd/android/u/cloud/activity/MessageDetailActivity/access$100(Lcom/nd/android/u/cloud/activity/MessageDetailActivity;)Lcom/nd/android/u/contact/dataStructure/MessageInfo;
invokevirtual com/nd/android/u/contact/dataStructure/MessageInfo/getFailednum()I
invokevirtual android/content/Intent/putExtra(Ljava/lang/String;I)Landroid/content/Intent;
pop
aload 1
ldc "smsid"
aload 0
getfield com/nd/android/u/cloud/activity/MessageDetailActivity$2/this$0 Lcom/nd/android/u/cloud/activity/MessageDetailActivity;
invokestatic com/nd/android/u/cloud/activity/MessageDetailActivity/access$100(Lcom/nd/android/u/cloud/activity/MessageDetailActivity;)Lcom/nd/android/u/contact/dataStructure/MessageInfo;
invokevirtual com/nd/android/u/contact/dataStructure/MessageInfo/getSmsid()Ljava/lang/String;
invokevirtual android/content/Intent/putExtra(Ljava/lang/String;Ljava/lang/String;)Landroid/content/Intent;
pop
aload 1
aload 0
getfield com/nd/android/u/cloud/activity/MessageDetailActivity$2/this$0 Lcom/nd/android/u/cloud/activity/MessageDetailActivity;
ldc com/nd/android/u/cloud/activity/MessageSendListActivity
invokevirtual android/content/Intent/setClass(Landroid/content/Context;Ljava/lang/Class;)Landroid/content/Intent;
pop
aload 0
getfield com/nd/android/u/cloud/activity/MessageDetailActivity$2/this$0 Lcom/nd/android/u/cloud/activity/MessageDetailActivity;
aload 1
invokevirtual com/nd/android/u/cloud/activity/MessageDetailActivity/startActivity(Landroid/content/Intent;)V
return
L0:
aload 0
getfield com/nd/android/u/cloud/activity/MessageDetailActivity$2/this$0 Lcom/nd/android/u/cloud/activity/MessageDetailActivity;
iconst_1
invokevirtual com/nd/android/u/cloud/activity/MessageDetailActivity/sendMessage2C(Z)V
return
.limit locals 6
.limit stack 3
.end method
