.bytecode 50.0
.class synchronized com/nd/android/u/cloud/activity/SelectHighSchoolActivity$3
.super java/lang/Object
.implements android/text/TextWatcher
.enclosing method com/nd/android/u/cloud/activity/SelectHighSchoolActivity/initEvent()V
.inner class inner com/nd/android/u/cloud/activity/SelectHighSchoolActivity$3

.field final synthetic 'this$0' Lcom/nd/android/u/cloud/activity/SelectHighSchoolActivity;

.method <init>(Lcom/nd/android/u/cloud/activity/SelectHighSchoolActivity;)V
aload 0
aload 1
putfield com/nd/android/u/cloud/activity/SelectHighSchoolActivity$3/this$0 Lcom/nd/android/u/cloud/activity/SelectHighSchoolActivity;
aload 0
invokespecial java/lang/Object/<init>()V
return
.limit locals 2
.limit stack 2
.end method

.method public afterTextChanged(Landroid/text/Editable;)V
return
.limit locals 2
.limit stack 0
.end method

.method public beforeTextChanged(Ljava/lang/CharSequence;III)V
return
.limit locals 5
.limit stack 0
.end method

.method public onTextChanged(Ljava/lang/CharSequence;III)V
aload 0
getfield com/nd/android/u/cloud/activity/SelectHighSchoolActivity$3/this$0 Lcom/nd/android/u/cloud/activity/SelectHighSchoolActivity;
iconst_1
invokestatic com/nd/android/u/cloud/activity/SelectHighSchoolActivity/access$002(Lcom/nd/android/u/cloud/activity/SelectHighSchoolActivity;Z)Z
pop
aload 0
getfield com/nd/android/u/cloud/activity/SelectHighSchoolActivity$3/this$0 Lcom/nd/android/u/cloud/activity/SelectHighSchoolActivity;
invokestatic com/nd/android/u/cloud/activity/SelectHighSchoolActivity/access$300(Lcom/nd/android/u/cloud/activity/SelectHighSchoolActivity;)Landroid/widget/ImageView;
iconst_0
invokevirtual android/widget/ImageView/setVisibility(I)V
aload 1
invokestatic android/text/TextUtils/isEmpty(Ljava/lang/CharSequence;)Z
ifne L0
aload 0
getfield com/nd/android/u/cloud/activity/SelectHighSchoolActivity$3/this$0 Lcom/nd/android/u/cloud/activity/SelectHighSchoolActivity;
invokestatic com/nd/android/u/cloud/activity/SelectHighSchoolActivity/access$400(Lcom/nd/android/u/cloud/activity/SelectHighSchoolActivity;)Landroid/widget/ImageView;
invokevirtual android/widget/ImageView/getVisibility()I
bipush 8
if_icmpne L1
aload 0
getfield com/nd/android/u/cloud/activity/SelectHighSchoolActivity$3/this$0 Lcom/nd/android/u/cloud/activity/SelectHighSchoolActivity;
invokestatic com/nd/android/u/cloud/activity/SelectHighSchoolActivity/access$400(Lcom/nd/android/u/cloud/activity/SelectHighSchoolActivity;)Landroid/widget/ImageView;
iconst_0
invokevirtual android/widget/ImageView/setVisibility(I)V
L1:
aload 0
getfield com/nd/android/u/cloud/activity/SelectHighSchoolActivity$3/this$0 Lcom/nd/android/u/cloud/activity/SelectHighSchoolActivity;
invokestatic com/nd/android/u/cloud/activity/SelectHighSchoolActivity/access$500(Lcom/nd/android/u/cloud/activity/SelectHighSchoolActivity;)Lcom/nd/android/u/cloud/activity/welcome/SelectSchoolListView;
aload 1
invokeinterface java/lang/CharSequence/toString()Ljava/lang/String; 0
invokevirtual com/nd/android/u/cloud/activity/welcome/SelectSchoolListView/updateInfo(Ljava/lang/String;)V
return
L0:
aload 0
getfield com/nd/android/u/cloud/activity/SelectHighSchoolActivity$3/this$0 Lcom/nd/android/u/cloud/activity/SelectHighSchoolActivity;
invokestatic com/nd/android/u/cloud/activity/SelectHighSchoolActivity/access$400(Lcom/nd/android/u/cloud/activity/SelectHighSchoolActivity;)Landroid/widget/ImageView;
invokevirtual android/widget/ImageView/getVisibility()I
ifne L2
aload 0
getfield com/nd/android/u/cloud/activity/SelectHighSchoolActivity$3/this$0 Lcom/nd/android/u/cloud/activity/SelectHighSchoolActivity;
invokestatic com/nd/android/u/cloud/activity/SelectHighSchoolActivity/access$400(Lcom/nd/android/u/cloud/activity/SelectHighSchoolActivity;)Landroid/widget/ImageView;
bipush 8
invokevirtual android/widget/ImageView/setVisibility(I)V
L2:
aload 0
getfield com/nd/android/u/cloud/activity/SelectHighSchoolActivity$3/this$0 Lcom/nd/android/u/cloud/activity/SelectHighSchoolActivity;
aconst_null
invokestatic com/nd/android/u/cloud/activity/SelectHighSchoolActivity/access$102(Lcom/nd/android/u/cloud/activity/SelectHighSchoolActivity;Lcom/nd/android/u/cloud/readschoolinfo/HighSchoolInfo;)Lcom/nd/android/u/cloud/readschoolinfo/HighSchoolInfo;
pop
goto L1
.limit locals 5
.limit stack 2
.end method
