.bytecode 50.0
.class synchronized com/nd/android/u/cloud/activity/SendFlowerTaskActivity$5
.super java/lang/Object
.implements android/text/TextWatcher
.enclosing method com/nd/android/u/cloud/activity/SendFlowerTaskActivity
.inner class inner com/nd/android/u/cloud/activity/SendFlowerTaskActivity$5

.field final synthetic 'this$0' Lcom/nd/android/u/cloud/activity/SendFlowerTaskActivity;

.method <init>(Lcom/nd/android/u/cloud/activity/SendFlowerTaskActivity;)V
aload 0
aload 1
putfield com/nd/android/u/cloud/activity/SendFlowerTaskActivity$5/this$0 Lcom/nd/android/u/cloud/activity/SendFlowerTaskActivity;
aload 0
invokespecial java/lang/Object/<init>()V
return
.limit locals 2
.limit stack 2
.end method

.method public afterTextChanged(Landroid/text/Editable;)V
return
.limit locals 2
.limit stack 0
.end method

.method public beforeTextChanged(Ljava/lang/CharSequence;III)V
return
.limit locals 5
.limit stack 0
.end method

.method public onTextChanged(Ljava/lang/CharSequence;III)V
aload 0
getfield com/nd/android/u/cloud/activity/SendFlowerTaskActivity$5/this$0 Lcom/nd/android/u/cloud/activity/SendFlowerTaskActivity;
invokestatic com/nd/android/u/cloud/activity/SendFlowerTaskActivity/access$700(Lcom/nd/android/u/cloud/activity/SendFlowerTaskActivity;)Landroid/widget/AutoCompleteTextView;
invokevirtual android/widget/AutoCompleteTextView/isPerformingCompletion()Z
ifeq L0
return
L0:
aload 1
invokeinterface java/lang/CharSequence/length()I 0
ifne L1
aload 0
getfield com/nd/android/u/cloud/activity/SendFlowerTaskActivity$5/this$0 Lcom/nd/android/u/cloud/activity/SendFlowerTaskActivity;
invokestatic com/nd/android/u/cloud/activity/SendFlowerTaskActivity/access$800(Lcom/nd/android/u/cloud/activity/SendFlowerTaskActivity;)Landroid/widget/Button;
aload 0
getfield com/nd/android/u/cloud/activity/SendFlowerTaskActivity$5/this$0 Lcom/nd/android/u/cloud/activity/SendFlowerTaskActivity;
ldc_w 2131494922
invokevirtual com/nd/android/u/cloud/activity/SendFlowerTaskActivity/getString(I)Ljava/lang/String;
invokevirtual android/widget/Button/setText(Ljava/lang/CharSequence;)V
return
L1:
aload 0
getfield com/nd/android/u/cloud/activity/SendFlowerTaskActivity$5/this$0 Lcom/nd/android/u/cloud/activity/SendFlowerTaskActivity;
invokestatic com/nd/android/u/cloud/activity/SendFlowerTaskActivity/access$800(Lcom/nd/android/u/cloud/activity/SendFlowerTaskActivity;)Landroid/widget/Button;
aload 0
getfield com/nd/android/u/cloud/activity/SendFlowerTaskActivity$5/this$0 Lcom/nd/android/u/cloud/activity/SendFlowerTaskActivity;
ldc_w 2131493033
invokevirtual com/nd/android/u/cloud/activity/SendFlowerTaskActivity/getString(I)Ljava/lang/String;
invokevirtual android/widget/Button/setText(Ljava/lang/CharSequence;)V
aload 0
getfield com/nd/android/u/cloud/activity/SendFlowerTaskActivity$5/this$0 Lcom/nd/android/u/cloud/activity/SendFlowerTaskActivity;
aload 1
invokeinterface java/lang/CharSequence/toString()Ljava/lang/String; 0
invokestatic com/nd/android/u/cloud/activity/SendFlowerTaskActivity/access$100(Lcom/nd/android/u/cloud/activity/SendFlowerTaskActivity;Ljava/lang/String;)V
return
.limit locals 5
.limit stack 3
.end method
