.bytecode 50.0
.class public synchronized com/nd/android/u/contact/com/OapSeniorSystemCom
.super com/nd/android/u/contact/com/base/OapSeniorSystemSupportCom

.method public <init>()V
aload 0
invokespecial com/nd/android/u/contact/com/base/OapSeniorSystemSupportCom/<init>()V
return
.limit locals 1
.limit stack 1
.end method

.method public agreeJuniorApply(JJ)Z
.throws com/common/android/utils/http/HttpException
aload 0
lload 1
lload 3
invokevirtual com/nd/android/u/contact/com/OapSeniorSystemCom/agreeJuniorApplyBase(JJ)Lorg/json/JSONObject;
astore 6
aload 6
ldc "code"
invokestatic com/common/android/utils/JSONUtils/getInt(Lorg/json/JSONObject;Ljava/lang/String;)I
istore 5
iload 5
sipush 200
if_icmpne L0
iconst_1
ireturn
L0:
new com/common/android/utils/http/HttpException
dup
aload 6
ldc "msg"
invokestatic com/common/android/utils/JSONUtils/getString(Lorg/json/JSONObject;Ljava/lang/String;)Ljava/lang/String;
iload 5
invokespecial com/common/android/utils/http/HttpException/<init>(Ljava/lang/String;I)V
athrow
.limit locals 7
.limit stack 5
.end method

.method public alreadyApplyCoach(JJ)Z
.throws com/common/android/utils/http/HttpException
iconst_0
istore 7
aload 0
lload 1
lload 3
invokevirtual com/nd/android/u/contact/com/OapSeniorSystemCom/alreadyApplyCoachBase(JJ)Lorg/json/JSONObject;
astore 8
aload 8
ldc "code"
invokestatic com/common/android/utils/JSONUtils/getInt(Lorg/json/JSONObject;Ljava/lang/String;)I
istore 5
iload 5
sipush 200
if_icmpne L0
iload 7
istore 6
aload 8
ldc "total"
invokevirtual org/json/JSONObject/has(Ljava/lang/String;)Z
ifeq L1
iload 7
istore 6
aload 8
ldc "total"
invokestatic com/common/android/utils/JSONUtils/getInt(Lorg/json/JSONObject;Ljava/lang/String;)I
ifle L1
iconst_1
istore 6
L1:
iload 6
ireturn
L0:
new com/common/android/utils/http/HttpException
dup
aload 8
ldc "msg"
invokestatic com/common/android/utils/JSONUtils/getString(Lorg/json/JSONObject;Ljava/lang/String;)Ljava/lang/String;
iload 5
invokespecial com/common/android/utils/http/HttpException/<init>(Ljava/lang/String;I)V
athrow
.limit locals 9
.limit stack 5
.end method

.method public applySenior(JJ)Z
.throws com/common/android/utils/http/HttpException
aload 0
lload 1
lload 3
invokevirtual com/nd/android/u/contact/com/OapSeniorSystemCom/applySeniorBase(JJ)Lorg/json/JSONObject;
astore 6
aload 6
ldc "code"
invokestatic com/common/android/utils/JSONUtils/getInt(Lorg/json/JSONObject;Ljava/lang/String;)I
istore 5
iload 5
sipush 200
if_icmpne L0
iconst_1
ireturn
L0:
new com/common/android/utils/http/HttpException
dup
aload 6
ldc "msg"
invokestatic com/common/android/utils/JSONUtils/getString(Lorg/json/JSONObject;Ljava/lang/String;)Ljava/lang/String;
iload 5
invokespecial com/common/android/utils/http/HttpException/<init>(Ljava/lang/String;I)V
athrow
.limit locals 7
.limit stack 5
.end method

.method public clearApply(J)Z
.throws com/common/android/utils/http/HttpException
aload 0
lload 1
invokevirtual com/nd/android/u/contact/com/OapSeniorSystemCom/clearJuniorApplyBase(J)Lorg/json/JSONObject;
astore 4
aload 4
ldc "code"
invokestatic com/common/android/utils/JSONUtils/getInt(Lorg/json/JSONObject;Ljava/lang/String;)I
istore 3
iload 3
sipush 200
if_icmpne L0
iconst_1
ireturn
L0:
new com/common/android/utils/http/HttpException
dup
aload 4
ldc "msg"
invokestatic com/common/android/utils/JSONUtils/getString(Lorg/json/JSONObject;Ljava/lang/String;)Ljava/lang/String;
iload 3
invokespecial com/common/android/utils/http/HttpException/<init>(Ljava/lang/String;I)V
athrow
.limit locals 5
.limit stack 4
.end method

.method public editSeniorInfo(JLjava/lang/String;Ljava/lang/String;Ljava/lang/String;Ljava/lang/String;)Z
.throws com/common/android/utils/http/HttpException
aload 0
lload 1
aload 3
aload 4
aload 5
aload 6
invokevirtual com/nd/android/u/contact/com/OapSeniorSystemCom/editSeniorInfoBase(JLjava/lang/String;Ljava/lang/String;Ljava/lang/String;Ljava/lang/String;)Lorg/json/JSONObject;
astore 3
aload 3
ldc "code"
invokestatic com/common/android/utils/JSONUtils/getInt(Lorg/json/JSONObject;Ljava/lang/String;)I
istore 7
iload 7
sipush 200
if_icmpne L0
iconst_1
ireturn
L0:
new com/common/android/utils/http/HttpException
dup
aload 3
ldc "msg"
invokestatic com/common/android/utils/JSONUtils/getString(Lorg/json/JSONObject;Ljava/lang/String;)Ljava/lang/String;
iload 7
invokespecial com/common/android/utils/http/HttpException/<init>(Ljava/lang/String;I)V
athrow
.limit locals 8
.limit stack 7
.end method

.method public getEnrolTime()J
.throws com/common/android/utils/http/HttpException
aload 0
invokevirtual com/nd/android/u/contact/com/OapSeniorSystemCom/getEnrolDate()Lorg/json/JSONObject;
astore 2
aload 2
ldc "code"
invokestatic com/common/android/utils/JSONUtils/getInt(Lorg/json/JSONObject;Ljava/lang/String;)I
istore 1
iload 1
sipush 200
if_icmpne L0
aload 2
ldc "enrolDate"
invokevirtual org/json/JSONObject/has(Ljava/lang/String;)Z
ifeq L1
aload 2
ldc "enrolDate"
invokestatic com/common/android/utils/JSONUtils/getLong(Lorg/json/JSONObject;Ljava/lang/String;)J
lreturn
L0:
new com/common/android/utils/http/HttpException
dup
aload 2
ldc "msg"
invokestatic com/common/android/utils/JSONUtils/getString(Lorg/json/JSONObject;Ljava/lang/String;)Ljava/lang/String;
iload 1
invokespecial com/common/android/utils/http/HttpException/<init>(Ljava/lang/String;I)V
athrow
L1:
lconst_0
lreturn
.limit locals 3
.limit stack 4
.end method

.method public getMyJuniorList(JII)Lcom/nd/android/u/contact/dataStructure/SeniorInfoListResult;
.throws com/common/android/utils/http/HttpException
aload 0
lload 1
iload 3
iload 4
invokevirtual com/nd/android/u/contact/com/OapSeniorSystemCom/getMyJuniorListBase(JII)Lorg/json/JSONObject;
astore 6
new com/nd/android/u/contact/dataStructure/SeniorInfoListResult
dup
invokespecial com/nd/android/u/contact/dataStructure/SeniorInfoListResult/<init>()V
astore 5
aload 6
ldc "code"
invokestatic com/common/android/utils/JSONUtils/getInt(Lorg/json/JSONObject;Ljava/lang/String;)I
istore 3
aload 5
iload 3
putfield com/nd/android/u/contact/dataStructure/SeniorInfoListResult/errorCode I
iload 3
sipush 200
if_icmpne L0
aload 6
ldc "list"
invokevirtual org/json/JSONObject/optJSONArray(Ljava/lang/String;)Lorg/json/JSONArray;
astore 6
iconst_0
istore 3
aload 6
invokevirtual org/json/JSONArray/length()I
istore 4
L1:
iload 3
iload 4
if_icmpge L2
aload 6
iload 3
invokevirtual org/json/JSONArray/optJSONObject(I)Lorg/json/JSONObject;
astore 7
new com/nd/android/u/contact/dataStructure/SeniorInfo
dup
invokespecial com/nd/android/u/contact/dataStructure/SeniorInfo/<init>()V
astore 8
aload 8
aload 7
invokevirtual com/nd/android/u/contact/dataStructure/SeniorInfo/loadFromJson(Lorg/json/JSONObject;)V
aload 5
aload 8
invokevirtual com/nd/android/u/contact/dataStructure/SeniorInfoListResult/add(Ljava/lang/Object;)Z
pop
iload 3
iconst_1
iadd
istore 3
goto L1
L0:
aload 5
aload 6
ldc "msg"
invokestatic com/common/android/utils/JSONUtils/getString(Lorg/json/JSONObject;Ljava/lang/String;)Ljava/lang/String;
putfield com/nd/android/u/contact/dataStructure/SeniorInfoListResult/errorMsg Ljava/lang/String;
new com/common/android/utils/http/HttpException
dup
aload 5
getfield com/nd/android/u/contact/dataStructure/SeniorInfoListResult/errorMsg Ljava/lang/String;
iload 3
invokespecial com/common/android/utils/http/HttpException/<init>(Ljava/lang/String;I)V
athrow
L2:
aload 5
areturn
.limit locals 9
.limit stack 5
.end method

.method public getMySeniorCount(J)I
.throws com/common/android/utils/http/HttpException
aload 0
lload 1
invokevirtual com/nd/android/u/contact/com/OapSeniorSystemCom/getMySeniorCountBase(J)Lorg/json/JSONObject;
astore 4
aload 4
ldc "code"
invokestatic com/common/android/utils/JSONUtils/getInt(Lorg/json/JSONObject;Ljava/lang/String;)I
istore 3
iload 3
sipush 200
if_icmpne L0
aload 4
ldc "total"
invokevirtual org/json/JSONObject/optInt(Ljava/lang/String;)I
ireturn
L0:
new com/common/android/utils/http/HttpException
dup
aload 4
ldc "msg"
invokestatic com/common/android/utils/JSONUtils/getString(Lorg/json/JSONObject;Ljava/lang/String;)Ljava/lang/String;
iload 3
invokespecial com/common/android/utils/http/HttpException/<init>(Ljava/lang/String;I)V
athrow
.limit locals 5
.limit stack 4
.end method

.method public getMySeniorList(JII)Lcom/nd/android/u/contact/dataStructure/SeniorInfoListResult;
.throws com/common/android/utils/http/HttpException
aload 0
lload 1
iload 3
iload 4
invokevirtual com/nd/android/u/contact/com/OapSeniorSystemCom/getMySeniorListBase(JII)Lorg/json/JSONObject;
astore 6
new com/nd/android/u/contact/dataStructure/SeniorInfoListResult
dup
invokespecial com/nd/android/u/contact/dataStructure/SeniorInfoListResult/<init>()V
astore 5
aload 6
ldc "code"
invokestatic com/common/android/utils/JSONUtils/getInt(Lorg/json/JSONObject;Ljava/lang/String;)I
istore 3
aload 5
iload 3
putfield com/nd/android/u/contact/dataStructure/SeniorInfoListResult/errorCode I
iload 3
sipush 200
if_icmpne L0
aload 6
ldc "list"
invokevirtual org/json/JSONObject/optJSONArray(Ljava/lang/String;)Lorg/json/JSONArray;
astore 6
iconst_0
istore 3
aload 6
invokevirtual org/json/JSONArray/length()I
istore 4
L1:
iload 3
iload 4
if_icmpge L2
aload 6
iload 3
invokevirtual org/json/JSONArray/optJSONObject(I)Lorg/json/JSONObject;
astore 7
new com/nd/android/u/contact/dataStructure/SeniorInfo
dup
invokespecial com/nd/android/u/contact/dataStructure/SeniorInfo/<init>()V
astore 8
aload 8
aload 7
invokevirtual com/nd/android/u/contact/dataStructure/SeniorInfo/loadFromJson(Lorg/json/JSONObject;)V
aload 5
aload 8
invokevirtual com/nd/android/u/contact/dataStructure/SeniorInfoListResult/add(Ljava/lang/Object;)Z
pop
iload 3
iconst_1
iadd
istore 3
goto L1
L0:
aload 5
aload 6
ldc "msg"
invokestatic com/common/android/utils/JSONUtils/getString(Lorg/json/JSONObject;Ljava/lang/String;)Ljava/lang/String;
putfield com/nd/android/u/contact/dataStructure/SeniorInfoListResult/errorMsg Ljava/lang/String;
new com/common/android/utils/http/HttpException
dup
aload 5
getfield com/nd/android/u/contact/dataStructure/SeniorInfoListResult/errorMsg Ljava/lang/String;
iload 3
invokespecial com/common/android/utils/http/HttpException/<init>(Ljava/lang/String;I)V
athrow
L2:
aload 5
areturn
.limit locals 9
.limit stack 5
.end method

.method public getNewJuniorApplyCount(J)I
.throws com/common/android/utils/http/HttpException
aload 0
lload 1
invokevirtual com/nd/android/u/contact/com/OapSeniorSystemCom/getNewJuniorApplyCountBase(J)Lorg/json/JSONObject;
astore 4
aload 4
ldc "code"
invokestatic com/common/android/utils/JSONUtils/getInt(Lorg/json/JSONObject;Ljava/lang/String;)I
istore 3
iload 3
sipush 200
if_icmpne L0
aload 4
ldc "total"
invokevirtual org/json/JSONObject/optInt(Ljava/lang/String;)I
ireturn
L0:
new com/common/android/utils/http/HttpException
dup
aload 4
ldc "msg"
invokestatic com/common/android/utils/JSONUtils/getString(Lorg/json/JSONObject;Ljava/lang/String;)Ljava/lang/String;
iload 3
invokespecial com/common/android/utils/http/HttpException/<init>(Ljava/lang/String;I)V
athrow
.limit locals 5
.limit stack 4
.end method

.method public getNewJuniorApplyList(JII)Lcom/nd/android/u/contact/dataStructure/SeniorInfoListResult;
.throws com/common/android/utils/http/HttpException
aload 0
lload 1
iload 3
iload 4
invokevirtual com/nd/android/u/contact/com/OapSeniorSystemCom/getNewJuniorApplyListBase(JII)Lorg/json/JSONObject;
astore 6
new com/nd/android/u/contact/dataStructure/SeniorInfoListResult
dup
invokespecial com/nd/android/u/contact/dataStructure/SeniorInfoListResult/<init>()V
astore 5
aload 6
ldc "code"
invokestatic com/common/android/utils/JSONUtils/getInt(Lorg/json/JSONObject;Ljava/lang/String;)I
istore 3
aload 6
ldc "total"
invokestatic com/common/android/utils/JSONUtils/getInt(Lorg/json/JSONObject;Ljava/lang/String;)I
istore 4
aload 6
ldc "count"
invokevirtual org/json/JSONObject/has(Ljava/lang/String;)Z
ifeq L0
aload 5
aload 6
ldc "count"
invokestatic com/common/android/utils/JSONUtils/getInt(Lorg/json/JSONObject;Ljava/lang/String;)I
putfield com/nd/android/u/contact/dataStructure/SeniorInfoListResult/count I
L0:
aload 5
iload 4
putfield com/nd/android/u/contact/dataStructure/SeniorInfoListResult/total I
aload 5
iload 3
putfield com/nd/android/u/contact/dataStructure/SeniorInfoListResult/errorCode I
iload 3
sipush 200
if_icmpne L1
aload 6
ldc "list"
invokevirtual org/json/JSONObject/optJSONArray(Ljava/lang/String;)Lorg/json/JSONArray;
astore 6
iconst_0
istore 3
aload 6
invokevirtual org/json/JSONArray/length()I
istore 4
L2:
iload 3
iload 4
if_icmpge L3
aload 6
iload 3
invokevirtual org/json/JSONArray/optJSONObject(I)Lorg/json/JSONObject;
astore 7
new com/nd/android/u/contact/dataStructure/SeniorInfo
dup
invokespecial com/nd/android/u/contact/dataStructure/SeniorInfo/<init>()V
astore 8
aload 8
aload 7
invokevirtual com/nd/android/u/contact/dataStructure/SeniorInfo/loadFromJson(Lorg/json/JSONObject;)V
aload 5
aload 8
invokevirtual com/nd/android/u/contact/dataStructure/SeniorInfoListResult/add(Ljava/lang/Object;)Z
pop
iload 3
iconst_1
iadd
istore 3
goto L2
L1:
aload 5
aload 6
ldc "msg"
invokestatic com/common/android/utils/JSONUtils/getString(Lorg/json/JSONObject;Ljava/lang/String;)Ljava/lang/String;
putfield com/nd/android/u/contact/dataStructure/SeniorInfoListResult/errorMsg Ljava/lang/String;
new com/common/android/utils/http/HttpException
dup
aload 5
getfield com/nd/android/u/contact/dataStructure/SeniorInfoListResult/errorMsg Ljava/lang/String;
iload 3
invokespecial com/common/android/utils/http/HttpException/<init>(Ljava/lang/String;I)V
athrow
L3:
aload 5
areturn
.limit locals 9
.limit stack 5
.end method

.method public getNewSeniorList(JII)Lcom/nd/android/u/contact/dataStructure/SeniorInfoListResult;
.throws com/common/android/utils/http/HttpException
aload 0
lload 1
iload 3
iload 4
invokevirtual com/nd/android/u/contact/com/OapSeniorSystemCom/getNewSeniorListBase(JII)Lorg/json/JSONObject;
astore 7
aload 7
ifnonnull L0
aconst_null
areturn
L0:
new com/nd/android/u/contact/dataStructure/SeniorInfoListResult
dup
invokespecial com/nd/android/u/contact/dataStructure/SeniorInfoListResult/<init>()V
astore 6
aload 7
ldc "code"
invokestatic com/common/android/utils/JSONUtils/getInt(Lorg/json/JSONObject;Ljava/lang/String;)I
istore 4
aload 7
ldc "total"
invokestatic com/common/android/utils/JSONUtils/getInt(Lorg/json/JSONObject;Ljava/lang/String;)I
istore 5
aload 7
ldc "count"
invokevirtual org/json/JSONObject/has(Ljava/lang/String;)Z
ifeq L1
aload 6
aload 7
ldc "count"
invokestatic com/common/android/utils/JSONUtils/getInt(Lorg/json/JSONObject;Ljava/lang/String;)I
putfield com/nd/android/u/contact/dataStructure/SeniorInfoListResult/count I
L1:
aload 6
iload 5
putfield com/nd/android/u/contact/dataStructure/SeniorInfoListResult/total I
aload 6
iload 4
putfield com/nd/android/u/contact/dataStructure/SeniorInfoListResult/errorCode I
iload 4
sipush 200
if_icmpne L2
aload 7
ldc "list"
invokevirtual org/json/JSONObject/optJSONArray(Ljava/lang/String;)Lorg/json/JSONArray;
astore 7
iconst_0
istore 4
aload 7
invokevirtual org/json/JSONArray/length()I
istore 5
L3:
iload 4
iload 5
if_icmpge L4
aload 7
iload 4
invokevirtual org/json/JSONArray/optJSONObject(I)Lorg/json/JSONObject;
astore 8
new com/nd/android/u/contact/dataStructure/SeniorInfo
dup
invokespecial com/nd/android/u/contact/dataStructure/SeniorInfo/<init>()V
astore 9
aload 9
aload 8
invokevirtual com/nd/android/u/contact/dataStructure/SeniorInfo/loadFromJson(Lorg/json/JSONObject;)V
aload 6
aload 9
invokevirtual com/nd/android/u/contact/dataStructure/SeniorInfoListResult/add(Ljava/lang/Object;)Z
pop
iload 4
iconst_1
iadd
istore 4
goto L3
L4:
ldc com/nd/android/u/contact/dao/MySeniorDao
invokestatic com/nd/android/u/contact/db/ContactDaoFactory/getImpl(Ljava/lang/Class;)Ljava/lang/Object;
checkcast com/nd/android/u/contact/dao/MySeniorDao
iload 3
aload 6
invokeinterface com/nd/android/u/contact/dao/MySeniorDao/insertFindSeniorList(ILcom/nd/android/u/contact/dataStructure/SeniorInfoListResult;)V 2
aload 6
areturn
L2:
aload 6
aload 7
ldc "msg"
invokestatic com/common/android/utils/JSONUtils/getString(Lorg/json/JSONObject;Ljava/lang/String;)Ljava/lang/String;
putfield com/nd/android/u/contact/dataStructure/SeniorInfoListResult/errorMsg Ljava/lang/String;
new com/common/android/utils/http/HttpException
dup
aload 6
getfield com/nd/android/u/contact/dataStructure/SeniorInfoListResult/errorMsg Ljava/lang/String;
iload 4
invokespecial com/common/android/utils/http/HttpException/<init>(Ljava/lang/String;I)V
athrow
.limit locals 10
.limit stack 5
.end method

.method public getSeniorDetail(J)Lcom/nd/android/u/contact/dataStructure/SeniorInfo;
.throws com/common/android/utils/http/HttpException
aload 0
lload 1
invokevirtual com/nd/android/u/contact/com/OapSeniorSystemCom/getSeniorDetailBase(J)Lorg/json/JSONObject;
astore 5
aload 5
ldc "code"
invokestatic com/common/android/utils/JSONUtils/getInt(Lorg/json/JSONObject;Ljava/lang/String;)I
istore 3
iload 3
sipush 200
if_icmpne L0
new com/nd/android/u/contact/dataStructure/SeniorInfo
dup
invokespecial com/nd/android/u/contact/dataStructure/SeniorInfo/<init>()V
astore 4
aload 5
ldc "older"
invokestatic com/common/android/utils/JSONUtils/getJSONObject(Lorg/json/JSONObject;Ljava/lang/String;)Lorg/json/JSONObject;
astore 5
aload 5
ifnull L1
aload 4
aload 5
invokevirtual com/nd/android/u/contact/dataStructure/SeniorInfo/loadFromJson(Lorg/json/JSONObject;)V
L1:
aload 4
areturn
L0:
new com/common/android/utils/http/HttpException
dup
aload 5
ldc "msg"
invokestatic com/common/android/utils/JSONUtils/getString(Lorg/json/JSONObject;Ljava/lang/String;)Ljava/lang/String;
iload 3
invokespecial com/common/android/utils/http/HttpException/<init>(Ljava/lang/String;I)V
athrow
.limit locals 6
.limit stack 4
.end method

.method public getStudentCreateTime(J)J
.throws com/common/android/utils/http/HttpException
aload 0
lload 1
invokevirtual com/nd/android/u/contact/com/OapSeniorSystemCom/getStudentCreateTimeBase(J)Lorg/json/JSONObject;
astore 3
aload 3
ifnull L0
aload 3
ldc "joindate"
invokestatic com/common/android/utils/JSONUtils/getLong(Lorg/json/JSONObject;Ljava/lang/String;)J
lreturn
L0:
lconst_0
lreturn
.limit locals 4
.limit stack 3
.end method

.method public isAlreadyBeanSenior(J)Z
.throws com/common/android/utils/http/HttpException
aload 0
lload 1
invokevirtual com/nd/android/u/contact/com/OapSeniorSystemCom/isAlreadyBeanSeniorBase(J)Lorg/json/JSONObject;
astore 4
aload 4
ldc "code"
invokestatic com/common/android/utils/JSONUtils/getInt(Lorg/json/JSONObject;Ljava/lang/String;)I
istore 3
iload 3
sipush 200
if_icmpne L0
aload 4
ldc "isOlder"
invokestatic com/common/android/utils/JSONUtils/getInt(Lorg/json/JSONObject;Ljava/lang/String;)I
iconst_1
if_icmpne L1
iconst_1
ireturn
L1:
iconst_0
ireturn
L0:
new com/common/android/utils/http/HttpException
dup
aload 4
ldc "msg"
invokestatic com/common/android/utils/JSONUtils/getString(Lorg/json/JSONObject;Ljava/lang/String;)Ljava/lang/String;
iload 3
invokespecial com/common/android/utils/http/HttpException/<init>(Ljava/lang/String;I)V
athrow
.limit locals 5
.limit stack 4
.end method

.method public newSeniorApply(JLjava/lang/String;Ljava/lang/String;Ljava/lang/String;Ljava/lang/String;)Z
.throws com/common/android/utils/http/HttpException
aload 0
lload 1
aload 3
aload 4
aload 5
aload 6
invokevirtual com/nd/android/u/contact/com/OapSeniorSystemCom/newSeniorApplyBase(JLjava/lang/String;Ljava/lang/String;Ljava/lang/String;Ljava/lang/String;)Lorg/json/JSONObject;
astore 3
aload 3
ldc "code"
invokestatic com/common/android/utils/JSONUtils/getInt(Lorg/json/JSONObject;Ljava/lang/String;)I
istore 7
iload 7
sipush 200
if_icmpne L0
iconst_1
ireturn
L0:
new com/common/android/utils/http/HttpException
dup
aload 3
ldc "msg"
invokestatic com/common/android/utils/JSONUtils/getString(Lorg/json/JSONObject;Ljava/lang/String;)Ljava/lang/String;
iload 7
invokespecial com/common/android/utils/http/HttpException/<init>(Ljava/lang/String;I)V
athrow
.limit locals 8
.limit stack 7
.end method
