.bytecode 50.0
.class synchronized com/nd/android/u/cloud/activity/findfriends/FindFriendsActivity$3
.super java/lang/Object
.implements com/nd/android/u/cloud/activity/welcome/SelectSchoolListView$OnDataSelectedListener
.enclosing method com/nd/android/u/cloud/activity/findfriends/FindFriendsActivity
.inner class inner com/nd/android/u/cloud/activity/findfriends/FindFriendsActivity$3

.field final synthetic 'this$0' Lcom/nd/android/u/cloud/activity/findfriends/FindFriendsActivity;

.method <init>(Lcom/nd/android/u/cloud/activity/findfriends/FindFriendsActivity;)V
aload 0
aload 1
putfield com/nd/android/u/cloud/activity/findfriends/FindFriendsActivity$3/this$0 Lcom/nd/android/u/cloud/activity/findfriends/FindFriendsActivity;
aload 0
invokespecial java/lang/Object/<init>()V
return
.limit locals 2
.limit stack 2
.end method

.method public dataSelected(Ljava/lang/String;Ljava/lang/String;)V
aload 0
getfield com/nd/android/u/cloud/activity/findfriends/FindFriendsActivity$3/this$0 Lcom/nd/android/u/cloud/activity/findfriends/FindFriendsActivity;
new com/nd/android/u/cloud/readschoolinfo/HighSchoolInfo
dup
invokespecial com/nd/android/u/cloud/readschoolinfo/HighSchoolInfo/<init>()V
invokestatic com/nd/android/u/cloud/activity/findfriends/FindFriendsActivity/access$202(Lcom/nd/android/u/cloud/activity/findfriends/FindFriendsActivity;Lcom/nd/android/u/cloud/readschoolinfo/HighSchoolInfo;)Lcom/nd/android/u/cloud/readschoolinfo/HighSchoolInfo;
pop
aload 0
getfield com/nd/android/u/cloud/activity/findfriends/FindFriendsActivity$3/this$0 Lcom/nd/android/u/cloud/activity/findfriends/FindFriendsActivity;
invokestatic com/nd/android/u/cloud/activity/findfriends/FindFriendsActivity/access$200(Lcom/nd/android/u/cloud/activity/findfriends/FindFriendsActivity;)Lcom/nd/android/u/cloud/readschoolinfo/HighSchoolInfo;
aload 2
invokevirtual com/nd/android/u/cloud/readschoolinfo/HighSchoolInfo/setSchoolCode(Ljava/lang/String;)V
aload 0
getfield com/nd/android/u/cloud/activity/findfriends/FindFriendsActivity$3/this$0 Lcom/nd/android/u/cloud/activity/findfriends/FindFriendsActivity;
invokestatic com/nd/android/u/cloud/activity/findfriends/FindFriendsActivity/access$200(Lcom/nd/android/u/cloud/activity/findfriends/FindFriendsActivity;)Lcom/nd/android/u/cloud/readschoolinfo/HighSchoolInfo;
aload 1
invokevirtual com/nd/android/u/cloud/readschoolinfo/HighSchoolInfo/setSchoolName(Ljava/lang/String;)V
aload 0
getfield com/nd/android/u/cloud/activity/findfriends/FindFriendsActivity$3/this$0 Lcom/nd/android/u/cloud/activity/findfriends/FindFriendsActivity;
invokestatic com/nd/android/u/cloud/activity/findfriends/FindFriendsActivity/access$500(Lcom/nd/android/u/cloud/activity/findfriends/FindFriendsActivity;)Landroid/widget/EditText;
aload 1
invokevirtual android/widget/EditText/setText(Ljava/lang/CharSequence;)V
aload 0
getfield com/nd/android/u/cloud/activity/findfriends/FindFriendsActivity$3/this$0 Lcom/nd/android/u/cloud/activity/findfriends/FindFriendsActivity;
invokestatic com/nd/android/u/cloud/activity/findfriends/FindFriendsActivity/access$500(Lcom/nd/android/u/cloud/activity/findfriends/FindFriendsActivity;)Landroid/widget/EditText;
aload 1
invokevirtual java/lang/String/length()I
invokevirtual android/widget/EditText/setSelection(I)V
aload 0
getfield com/nd/android/u/cloud/activity/findfriends/FindFriendsActivity$3/this$0 Lcom/nd/android/u/cloud/activity/findfriends/FindFriendsActivity;
iconst_1
invokestatic com/nd/android/u/cloud/activity/findfriends/FindFriendsActivity/access$300(Lcom/nd/android/u/cloud/activity/findfriends/FindFriendsActivity;Z)V
aload 0
getfield com/nd/android/u/cloud/activity/findfriends/FindFriendsActivity$3/this$0 Lcom/nd/android/u/cloud/activity/findfriends/FindFriendsActivity;
aload 0
getfield com/nd/android/u/cloud/activity/findfriends/FindFriendsActivity$3/this$0 Lcom/nd/android/u/cloud/activity/findfriends/FindFriendsActivity;
invokestatic com/nd/android/u/cloud/activity/findfriends/FindFriendsActivity/access$500(Lcom/nd/android/u/cloud/activity/findfriends/FindFriendsActivity;)Landroid/widget/EditText;
invokevirtual com/nd/android/u/cloud/activity/findfriends/FindFriendsActivity/hideSoftInput(Landroid/widget/EditText;)V
return
.limit locals 3
.limit stack 3
.end method
