.bytecode 50.0
.class synchronized com/nd/android/u/cloud/activity/findfriends/FindFriendsSelectBaseActivity$SelDataAdapter
.super android/widget/BaseAdapter
.inner class SelDataAdapter inner com/nd/android/u/cloud/activity/findfriends/FindFriendsSelectBaseActivity$SelDataAdapter outer com/nd/android/u/cloud/activity/findfriends/FindFriendsSelectBaseActivity

.field final synthetic 'this$0' Lcom/nd/android/u/cloud/activity/findfriends/FindFriendsSelectBaseActivity;

.method <init>(Lcom/nd/android/u/cloud/activity/findfriends/FindFriendsSelectBaseActivity;)V
aload 0
aload 1
putfield com/nd/android/u/cloud/activity/findfriends/FindFriendsSelectBaseActivity$SelDataAdapter/this$0 Lcom/nd/android/u/cloud/activity/findfriends/FindFriendsSelectBaseActivity;
aload 0
invokespecial android/widget/BaseAdapter/<init>()V
return
.limit locals 2
.limit stack 2
.end method

.method public getCount()I
aload 0
getfield com/nd/android/u/cloud/activity/findfriends/FindFriendsSelectBaseActivity$SelDataAdapter/this$0 Lcom/nd/android/u/cloud/activity/findfriends/FindFriendsSelectBaseActivity;
invokevirtual com/nd/android/u/cloud/activity/findfriends/FindFriendsSelectBaseActivity/getDataCount()I
ireturn
.limit locals 1
.limit stack 1
.end method

.method public getItem(I)Ljava/lang/Object;
aload 0
getfield com/nd/android/u/cloud/activity/findfriends/FindFriendsSelectBaseActivity$SelDataAdapter/this$0 Lcom/nd/android/u/cloud/activity/findfriends/FindFriendsSelectBaseActivity;
iload 1
invokevirtual com/nd/android/u/cloud/activity/findfriends/FindFriendsSelectBaseActivity/getDataItem(I)Ljava/lang/Object;
areturn
.limit locals 2
.limit stack 2
.end method

.method public getItemId(I)J
lconst_0
lreturn
.limit locals 2
.limit stack 2
.end method

.method public getView(ILandroid/view/View;Landroid/view/ViewGroup;)Landroid/view/View;
aload 2
ifnonnull L0
aload 0
getfield com/nd/android/u/cloud/activity/findfriends/FindFriendsSelectBaseActivity$SelDataAdapter/this$0 Lcom/nd/android/u/cloud/activity/findfriends/FindFriendsSelectBaseActivity;
getfield com/nd/android/u/cloud/activity/findfriends/FindFriendsSelectBaseActivity/mInflater Landroid/view/LayoutInflater;
ldc_w 2130903312
aconst_null
invokevirtual android/view/LayoutInflater/inflate(ILandroid/view/ViewGroup;)Landroid/view/View;
astore 2
new com/nd/android/u/cloud/activity/findfriends/FindFriendsSelectBaseActivity$SelectViewHolder
dup
aload 0
getfield com/nd/android/u/cloud/activity/findfriends/FindFriendsSelectBaseActivity$SelDataAdapter/this$0 Lcom/nd/android/u/cloud/activity/findfriends/FindFriendsSelectBaseActivity;
invokespecial com/nd/android/u/cloud/activity/findfriends/FindFriendsSelectBaseActivity$SelectViewHolder/<init>(Lcom/nd/android/u/cloud/activity/findfriends/FindFriendsSelectBaseActivity;)V
astore 3
aload 3
aload 2
ldc_w 2131624227
invokevirtual android/view/View/findViewById(I)Landroid/view/View;
checkcast android/widget/TextView
putfield com/nd/android/u/cloud/activity/findfriends/FindFriendsSelectBaseActivity$SelectViewHolder/tvName Landroid/widget/TextView;
aload 3
aload 2
ldc_w 2131625256
invokevirtual android/view/View/findViewById(I)Landroid/view/View;
checkcast android/widget/ImageView
putfield com/nd/android/u/cloud/activity/findfriends/FindFriendsSelectBaseActivity$SelectViewHolder/ivSelected Landroid/widget/ImageView;
aload 2
aload 3
invokevirtual android/view/View/setTag(Ljava/lang/Object;)V
L1:
aload 3
getfield com/nd/android/u/cloud/activity/findfriends/FindFriendsSelectBaseActivity$SelectViewHolder/tvName Landroid/widget/TextView;
aload 0
getfield com/nd/android/u/cloud/activity/findfriends/FindFriendsSelectBaseActivity$SelDataAdapter/this$0 Lcom/nd/android/u/cloud/activity/findfriends/FindFriendsSelectBaseActivity;
iload 1
invokevirtual com/nd/android/u/cloud/activity/findfriends/FindFriendsSelectBaseActivity/getName(I)Ljava/lang/String;
invokevirtual android/widget/TextView/setText(Ljava/lang/CharSequence;)V
iload 1
aload 0
getfield com/nd/android/u/cloud/activity/findfriends/FindFriendsSelectBaseActivity$SelDataAdapter/this$0 Lcom/nd/android/u/cloud/activity/findfriends/FindFriendsSelectBaseActivity;
getfield com/nd/android/u/cloud/activity/findfriends/FindFriendsSelectBaseActivity/mSelectedItemPos I
if_icmpne L2
aload 3
getfield com/nd/android/u/cloud/activity/findfriends/FindFriendsSelectBaseActivity$SelectViewHolder/ivSelected Landroid/widget/ImageView;
iconst_0
invokevirtual android/widget/ImageView/setVisibility(I)V
aload 2
areturn
L0:
aload 2
invokevirtual android/view/View/getTag()Ljava/lang/Object;
checkcast com/nd/android/u/cloud/activity/findfriends/FindFriendsSelectBaseActivity$SelectViewHolder
astore 3
goto L1
L2:
aload 3
getfield com/nd/android/u/cloud/activity/findfriends/FindFriendsSelectBaseActivity$SelectViewHolder/ivSelected Landroid/widget/ImageView;
bipush 8
invokevirtual android/widget/ImageView/setVisibility(I)V
aload 2
areturn
.limit locals 4
.limit stack 3
.end method
