.bytecode 50.0
.class synchronized com/nd/android/u/cloud/activity/findfriends/FindFriendsActivity$2
.super java/lang/Object
.implements android/text/TextWatcher
.enclosing method com/nd/android/u/cloud/activity/findfriends/FindFriendsActivity/initEvent()V
.inner class inner com/nd/android/u/cloud/activity/findfriends/FindFriendsActivity$2

.field final synthetic 'this$0' Lcom/nd/android/u/cloud/activity/findfriends/FindFriendsActivity;

.method <init>(Lcom/nd/android/u/cloud/activity/findfriends/FindFriendsActivity;)V
aload 0
aload 1
putfield com/nd/android/u/cloud/activity/findfriends/FindFriendsActivity$2/this$0 Lcom/nd/android/u/cloud/activity/findfriends/FindFriendsActivity;
aload 0
invokespecial java/lang/Object/<init>()V
return
.limit locals 2
.limit stack 2
.end method

.method public afterTextChanged(Landroid/text/Editable;)V
return
.limit locals 2
.limit stack 0
.end method

.method public beforeTextChanged(Ljava/lang/CharSequence;III)V
return
.limit locals 5
.limit stack 0
.end method

.method public onTextChanged(Ljava/lang/CharSequence;III)V
iconst_1
istore 5
aload 1
invokestatic android/text/TextUtils/isEmpty(Ljava/lang/CharSequence;)Z
ifne L0
aload 0
getfield com/nd/android/u/cloud/activity/findfriends/FindFriendsActivity$2/this$0 Lcom/nd/android/u/cloud/activity/findfriends/FindFriendsActivity;
invokestatic com/nd/android/u/cloud/activity/findfriends/FindFriendsActivity/access$100(Lcom/nd/android/u/cloud/activity/findfriends/FindFriendsActivity;)Landroid/widget/ImageView;
invokevirtual android/widget/ImageView/getVisibility()I
bipush 8
if_icmpne L1
aload 0
getfield com/nd/android/u/cloud/activity/findfriends/FindFriendsActivity$2/this$0 Lcom/nd/android/u/cloud/activity/findfriends/FindFriendsActivity;
invokestatic com/nd/android/u/cloud/activity/findfriends/FindFriendsActivity/access$100(Lcom/nd/android/u/cloud/activity/findfriends/FindFriendsActivity;)Landroid/widget/ImageView;
iconst_0
invokevirtual android/widget/ImageView/setVisibility(I)V
L1:
aload 0
getfield com/nd/android/u/cloud/activity/findfriends/FindFriendsActivity$2/this$0 Lcom/nd/android/u/cloud/activity/findfriends/FindFriendsActivity;
invokestatic com/nd/android/u/cloud/activity/findfriends/FindFriendsActivity/access$400(Lcom/nd/android/u/cloud/activity/findfriends/FindFriendsActivity;)Lcom/nd/android/u/cloud/activity/welcome/SelectSchoolListView;
aload 1
invokeinterface java/lang/CharSequence/toString()Ljava/lang/String; 0
invokevirtual com/nd/android/u/cloud/activity/welcome/SelectSchoolListView/updateInfo(Ljava/lang/String;)V
aload 0
getfield com/nd/android/u/cloud/activity/findfriends/FindFriendsActivity$2/this$0 Lcom/nd/android/u/cloud/activity/findfriends/FindFriendsActivity;
astore 1
aload 0
getfield com/nd/android/u/cloud/activity/findfriends/FindFriendsActivity$2/this$0 Lcom/nd/android/u/cloud/activity/findfriends/FindFriendsActivity;
invokestatic com/nd/android/u/cloud/activity/findfriends/FindFriendsActivity/access$400(Lcom/nd/android/u/cloud/activity/findfriends/FindFriendsActivity;)Lcom/nd/android/u/cloud/activity/welcome/SelectSchoolListView;
invokevirtual com/nd/android/u/cloud/activity/welcome/SelectSchoolListView/getVisibility()I
bipush 8
if_icmpne L2
L3:
aload 1
iload 5
invokestatic com/nd/android/u/cloud/activity/findfriends/FindFriendsActivity/access$300(Lcom/nd/android/u/cloud/activity/findfriends/FindFriendsActivity;Z)V
return
L0:
aload 0
getfield com/nd/android/u/cloud/activity/findfriends/FindFriendsActivity$2/this$0 Lcom/nd/android/u/cloud/activity/findfriends/FindFriendsActivity;
invokestatic com/nd/android/u/cloud/activity/findfriends/FindFriendsActivity/access$100(Lcom/nd/android/u/cloud/activity/findfriends/FindFriendsActivity;)Landroid/widget/ImageView;
invokevirtual android/widget/ImageView/getVisibility()I
ifne L4
aload 0
getfield com/nd/android/u/cloud/activity/findfriends/FindFriendsActivity$2/this$0 Lcom/nd/android/u/cloud/activity/findfriends/FindFriendsActivity;
invokestatic com/nd/android/u/cloud/activity/findfriends/FindFriendsActivity/access$100(Lcom/nd/android/u/cloud/activity/findfriends/FindFriendsActivity;)Landroid/widget/ImageView;
bipush 8
invokevirtual android/widget/ImageView/setVisibility(I)V
L4:
aload 0
getfield com/nd/android/u/cloud/activity/findfriends/FindFriendsActivity$2/this$0 Lcom/nd/android/u/cloud/activity/findfriends/FindFriendsActivity;
aconst_null
invokestatic com/nd/android/u/cloud/activity/findfriends/FindFriendsActivity/access$202(Lcom/nd/android/u/cloud/activity/findfriends/FindFriendsActivity;Lcom/nd/android/u/cloud/readschoolinfo/HighSchoolInfo;)Lcom/nd/android/u/cloud/readschoolinfo/HighSchoolInfo;
pop
aload 0
getfield com/nd/android/u/cloud/activity/findfriends/FindFriendsActivity$2/this$0 Lcom/nd/android/u/cloud/activity/findfriends/FindFriendsActivity;
iconst_1
invokestatic com/nd/android/u/cloud/activity/findfriends/FindFriendsActivity/access$300(Lcom/nd/android/u/cloud/activity/findfriends/FindFriendsActivity;Z)V
goto L1
L2:
iconst_0
istore 5
goto L3
.limit locals 6
.limit stack 2
.end method
