.bytecode 50.0
.class public synchronized abstract com/nd/android/u/cloud/activity/findfriends/FindFriendsSelectBaseActivity
.super com/product/android/ui/activity/BaseActivity
.implements android/view/View$OnClickListener
.implements android/widget/AdapterView$OnItemClickListener
.inner class SelDataAdapter inner com/nd/android/u/cloud/activity/findfriends/FindFriendsSelectBaseActivity$SelDataAdapter outer com/nd/android/u/cloud/activity/findfriends/FindFriendsSelectBaseActivity
.inner class SelectViewHolder inner com/nd/android/u/cloud/activity/findfriends/FindFriendsSelectBaseActivity$SelectViewHolder outer com/nd/android/u/cloud/activity/findfriends/FindFriendsSelectBaseActivity

.field private 'mAdapter' Lcom/nd/android/u/cloud/activity/findfriends/FindFriendsSelectBaseActivity$SelDataAdapter;

.field protected 'mDefaultCode' Ljava/lang/String;

.field 'mInflater' Landroid/view/LayoutInflater;

.field protected 'mListView' Landroid/widget/ListView;

.field protected 'mSelectedItemPos' I

.field private 'mTitle' Ljava/lang/String;

.field private 'mTvTitle' Landroid/widget/TextView;

.method public <init>()V
aload 0
invokespecial com/product/android/ui/activity/BaseActivity/<init>()V
aload 0
iconst_m1
putfield com/nd/android/u/cloud/activity/findfriends/FindFriendsSelectBaseActivity/mSelectedItemPos I
return
.limit locals 1
.limit stack 2
.end method

.method protected abstract clickSure()V
.end method

.method protected abstract getDataCount()I
.end method

.method protected abstract getDataItem(I)Ljava/lang/Object;
.end method

.method protected abstract getName(I)Ljava/lang/String;
.end method

.method protected initComponent()V
aload 0
invokespecial com/product/android/ui/activity/BaseActivity/initComponent()V
aload 0
aload 0
ldc_w 2131624196
invokevirtual com/nd/android/u/cloud/activity/findfriends/FindFriendsSelectBaseActivity/findViewById(I)Landroid/view/View;
checkcast android/widget/TextView
putfield com/nd/android/u/cloud/activity/findfriends/FindFriendsSelectBaseActivity/mTvTitle Landroid/widget/TextView;
aload 0
aload 0
ldc_w 2131624198
invokevirtual com/nd/android/u/cloud/activity/findfriends/FindFriendsSelectBaseActivity/findViewById(I)Landroid/view/View;
checkcast android/widget/ListView
putfield com/nd/android/u/cloud/activity/findfriends/FindFriendsSelectBaseActivity/mListView Landroid/widget/ListView;
return
.limit locals 1
.limit stack 3
.end method

.method protected initComponentValue()V
aload 0
invokespecial com/product/android/ui/activity/BaseActivity/initComponentValue()V
aload 0
aload 0
invokevirtual com/nd/android/u/cloud/activity/findfriends/FindFriendsSelectBaseActivity/getIntent()Landroid/content/Intent;
ldc "select_title"
invokevirtual android/content/Intent/getStringExtra(Ljava/lang/String;)Ljava/lang/String;
putfield com/nd/android/u/cloud/activity/findfriends/FindFriendsSelectBaseActivity/mTitle Ljava/lang/String;
aload 0
getfield com/nd/android/u/cloud/activity/findfriends/FindFriendsSelectBaseActivity/mTvTitle Landroid/widget/TextView;
aload 0
getfield com/nd/android/u/cloud/activity/findfriends/FindFriendsSelectBaseActivity/mTitle Ljava/lang/String;
invokevirtual android/widget/TextView/setText(Ljava/lang/CharSequence;)V
aload 0
aload 0
invokevirtual com/nd/android/u/cloud/activity/findfriends/FindFriendsSelectBaseActivity/getIntent()Landroid/content/Intent;
ldc "select_conditions"
invokevirtual android/content/Intent/getStringExtra(Ljava/lang/String;)Ljava/lang/String;
putfield com/nd/android/u/cloud/activity/findfriends/FindFriendsSelectBaseActivity/mDefaultCode Ljava/lang/String;
aload 0
new com/nd/android/u/cloud/activity/findfriends/FindFriendsSelectBaseActivity$SelDataAdapter
dup
aload 0
invokespecial com/nd/android/u/cloud/activity/findfriends/FindFriendsSelectBaseActivity$SelDataAdapter/<init>(Lcom/nd/android/u/cloud/activity/findfriends/FindFriendsSelectBaseActivity;)V
putfield com/nd/android/u/cloud/activity/findfriends/FindFriendsSelectBaseActivity/mAdapter Lcom/nd/android/u/cloud/activity/findfriends/FindFriendsSelectBaseActivity$SelDataAdapter;
aload 0
getfield com/nd/android/u/cloud/activity/findfriends/FindFriendsSelectBaseActivity/mListView Landroid/widget/ListView;
aload 0
getfield com/nd/android/u/cloud/activity/findfriends/FindFriendsSelectBaseActivity/mAdapter Lcom/nd/android/u/cloud/activity/findfriends/FindFriendsSelectBaseActivity$SelDataAdapter;
invokevirtual android/widget/ListView/setAdapter(Landroid/widget/ListAdapter;)V
aload 0
getfield com/nd/android/u/cloud/activity/findfriends/FindFriendsSelectBaseActivity/mListView Landroid/widget/ListView;
aload 0
invokevirtual android/widget/ListView/setOnItemClickListener(Landroid/widget/AdapterView$OnItemClickListener;)V
return
.limit locals 1
.limit stack 4
.end method

.method protected initEvent()V
aload 0
invokespecial com/product/android/ui/activity/BaseActivity/initEvent()V
aload 0
ldc_w 2131624201
invokevirtual com/nd/android/u/cloud/activity/findfriends/FindFriendsSelectBaseActivity/findViewById(I)Landroid/view/View;
aload 0
invokevirtual android/view/View/setOnClickListener(Landroid/view/View$OnClickListener;)V
aload 0
ldc_w 2131624046
invokevirtual com/nd/android/u/cloud/activity/findfriends/FindFriendsSelectBaseActivity/findViewById(I)Landroid/view/View;
aload 0
invokevirtual android/view/View/setOnClickListener(Landroid/view/View$OnClickListener;)V
return
.limit locals 1
.limit stack 2
.end method

.method public onClick(Landroid/view/View;)V
aload 1
invokevirtual android/view/View/getId()I
ldc_w 2131624201
if_icmpne L0
aload 0
invokevirtual com/nd/android/u/cloud/activity/findfriends/FindFriendsSelectBaseActivity/clickSure()V
L1:
return
L0:
aload 1
invokevirtual android/view/View/getId()I
ldc_w 2131624046
if_icmpne L1
aload 0
iconst_0
invokevirtual com/nd/android/u/cloud/activity/findfriends/FindFriendsSelectBaseActivity/setResult(I)V
aload 0
invokevirtual com/nd/android/u/cloud/activity/findfriends/FindFriendsSelectBaseActivity/finish()V
return
.limit locals 2
.limit stack 2
.end method

.method protected onCreate(Landroid/os/Bundle;)V
aload 0
aload 1
invokespecial com/product/android/ui/activity/BaseActivity/onCreate(Landroid/os/Bundle;)V
aload 0
iconst_1
invokevirtual com/nd/android/u/cloud/activity/findfriends/FindFriendsSelectBaseActivity/requestWindowFeature(I)Z
pop
aload 0
aload 0
ldc "layout_inflater"
invokevirtual com/nd/android/u/cloud/activity/findfriends/FindFriendsSelectBaseActivity/getSystemService(Ljava/lang/String;)Ljava/lang/Object;
checkcast android/view/LayoutInflater
putfield com/nd/android/u/cloud/activity/findfriends/FindFriendsSelectBaseActivity/mInflater Landroid/view/LayoutInflater;
aload 0
ldc_w 2130903071
invokevirtual com/nd/android/u/cloud/activity/findfriends/FindFriendsSelectBaseActivity/setContentView(I)V
aload 0
invokevirtual com/nd/android/u/cloud/activity/findfriends/FindFriendsSelectBaseActivity/initComponent()V
aload 0
invokevirtual com/nd/android/u/cloud/activity/findfriends/FindFriendsSelectBaseActivity/initComponentValue()V
aload 0
invokevirtual com/nd/android/u/cloud/activity/findfriends/FindFriendsSelectBaseActivity/initEvent()V
return
.limit locals 2
.limit stack 3
.end method

.method public onItemClick(Landroid/widget/AdapterView;Landroid/view/View;IJ)V
.signature "(Landroid/widget/AdapterView<*>;Landroid/view/View;IJ)V"
aload 0
getfield com/nd/android/u/cloud/activity/findfriends/FindFriendsSelectBaseActivity/mSelectedItemPos I
iload 3
if_icmpne L0
aload 0
iconst_m1
putfield com/nd/android/u/cloud/activity/findfriends/FindFriendsSelectBaseActivity/mSelectedItemPos I
L1:
aload 0
getfield com/nd/android/u/cloud/activity/findfriends/FindFriendsSelectBaseActivity/mAdapter Lcom/nd/android/u/cloud/activity/findfriends/FindFriendsSelectBaseActivity$SelDataAdapter;
invokevirtual com/nd/android/u/cloud/activity/findfriends/FindFriendsSelectBaseActivity$SelDataAdapter/notifyDataSetChanged()V
return
L0:
aload 0
iload 3
putfield com/nd/android/u/cloud/activity/findfriends/FindFriendsSelectBaseActivity/mSelectedItemPos I
goto L1
.limit locals 6
.limit stack 2
.end method
