.bytecode 50.0
.class synchronized com/nd/android/u/tast/main/activity/TaskMainActivity$GetShowOffTask
.super android/os/AsyncTask
.signature "Landroid/os/AsyncTask<Ljava/lang/Void;Ljava/lang/Void;Lcom/nd/android/u/tast/experience/bean/ShowOffBean;>;"
.inner class private GetShowOffTask inner com/nd/android/u/tast/main/activity/TaskMainActivity$GetShowOffTask outer com/nd/android/u/tast/main/activity/TaskMainActivity

.field final synthetic 'this$0' Lcom/nd/android/u/tast/main/activity/TaskMainActivity;

.method private <init>(Lcom/nd/android/u/tast/main/activity/TaskMainActivity;)V
aload 0
aload 1
putfield com/nd/android/u/tast/main/activity/TaskMainActivity$GetShowOffTask/this$0 Lcom/nd/android/u/tast/main/activity/TaskMainActivity;
aload 0
invokespecial android/os/AsyncTask/<init>()V
return
.limit locals 2
.limit stack 2
.end method

.method synthetic <init>(Lcom/nd/android/u/tast/main/activity/TaskMainActivity;Lcom/nd/android/u/tast/main/activity/TaskMainActivity$1;)V
aload 0
aload 1
invokespecial com/nd/android/u/tast/main/activity/TaskMainActivity$GetShowOffTask/<init>(Lcom/nd/android/u/tast/main/activity/TaskMainActivity;)V
return
.limit locals 3
.limit stack 2
.end method

.method protected transient doInBackground([Ljava/lang/Void;)Lcom/nd/android/u/tast/experience/bean/ShowOffBean;
getstatic com/nd/android/u/tast/buss/TaskModelManager/INSTANCE Lcom/nd/android/u/tast/buss/TaskModelManager;
invokevirtual com/nd/android/u/tast/buss/TaskModelManager/getShowOff()Lcom/nd/android/u/tast/experience/bean/ShowOffBean;
areturn
.limit locals 2
.limit stack 1
.end method

.method protected volatile synthetic doInBackground([Ljava/lang/Object;)Ljava/lang/Object;
aload 0
aload 1
checkcast [Ljava/lang/Void;
invokevirtual com/nd/android/u/tast/main/activity/TaskMainActivity$GetShowOffTask/doInBackground([Ljava/lang/Void;)Lcom/nd/android/u/tast/experience/bean/ShowOffBean;
areturn
.limit locals 2
.limit stack 2
.end method

.method protected onPostExecute(Lcom/nd/android/u/tast/experience/bean/ShowOffBean;)V
aload 0
aload 1
invokespecial android/os/AsyncTask/onPostExecute(Ljava/lang/Object;)V
aload 1
ifnonnull L0
aload 0
getfield com/nd/android/u/tast/main/activity/TaskMainActivity$GetShowOffTask/this$0 Lcom/nd/android/u/tast/main/activity/TaskMainActivity;
getstatic com/nd/android/u/tasklib/R$string/get_show_off_data_error I
invokestatic com/common/android/utils/ToastUtils/display(Landroid/content/Context;I)V
return
L0:
aload 0
getfield com/nd/android/u/tast/main/activity/TaskMainActivity$GetShowOffTask/this$0 Lcom/nd/android/u/tast/main/activity/TaskMainActivity;
invokestatic com/nd/android/u/tast/main/activity/TaskMainActivity/access$400(Lcom/nd/android/u/tast/main/activity/TaskMainActivity;)Landroid/widget/TextView;
new java/lang/StringBuilder
dup
invokespecial java/lang/StringBuilder/<init>()V
aload 1
invokevirtual com/nd/android/u/tast/experience/bean/ShowOffBean/getLevel()I
invokevirtual java/lang/StringBuilder/append(I)Ljava/lang/StringBuilder;
ldc ""
invokevirtual java/lang/StringBuilder/append(Ljava/lang/String;)Ljava/lang/StringBuilder;
invokevirtual java/lang/StringBuilder/toString()Ljava/lang/String;
invokevirtual android/widget/TextView/setText(Ljava/lang/CharSequence;)V
aload 0
getfield com/nd/android/u/tast/main/activity/TaskMainActivity$GetShowOffTask/this$0 Lcom/nd/android/u/tast/main/activity/TaskMainActivity;
invokestatic com/nd/android/u/tast/main/activity/TaskMainActivity/access$500(Lcom/nd/android/u/tast/main/activity/TaskMainActivity;)Landroid/widget/TextView;
aload 1
invokevirtual com/nd/android/u/tast/experience/bean/ShowOffBean/getSummary()Ljava/lang/String;
invokevirtual android/widget/TextView/setText(Ljava/lang/CharSequence;)V
aload 1
invokevirtual com/nd/android/u/tast/experience/bean/ShowOffBean/getRanges()Ljava/util/ArrayList;
astore 2
aload 2
ifnull L1
aload 2
invokevirtual java/util/ArrayList/size()I
ifne L2
L1:
aload 0
getfield com/nd/android/u/tast/main/activity/TaskMainActivity$GetShowOffTask/this$0 Lcom/nd/android/u/tast/main/activity/TaskMainActivity;
invokestatic com/nd/android/u/tast/main/activity/TaskMainActivity/access$600(Lcom/nd/android/u/tast/main/activity/TaskMainActivity;)Landroid/view/View;
bipush 8
invokevirtual android/view/View/setVisibility(I)V
L3:
aload 0
getfield com/nd/android/u/tast/main/activity/TaskMainActivity$GetShowOffTask/this$0 Lcom/nd/android/u/tast/main/activity/TaskMainActivity;
invokestatic com/nd/android/u/tast/main/activity/TaskMainActivity/access$900(Lcom/nd/android/u/tast/main/activity/TaskMainActivity;)V
return
L2:
aload 0
getfield com/nd/android/u/tast/main/activity/TaskMainActivity$GetShowOffTask/this$0 Lcom/nd/android/u/tast/main/activity/TaskMainActivity;
invokestatic com/nd/android/u/tast/main/activity/TaskMainActivity/access$600(Lcom/nd/android/u/tast/main/activity/TaskMainActivity;)Landroid/view/View;
iconst_0
invokevirtual android/view/View/setVisibility(I)V
aload 0
getfield com/nd/android/u/tast/main/activity/TaskMainActivity$GetShowOffTask/this$0 Lcom/nd/android/u/tast/main/activity/TaskMainActivity;
invokestatic com/nd/android/u/tast/main/activity/TaskMainActivity/access$700(Lcom/nd/android/u/tast/main/activity/TaskMainActivity;)Landroid/widget/TextView;
aload 0
getfield com/nd/android/u/tast/main/activity/TaskMainActivity$GetShowOffTask/this$0 Lcom/nd/android/u/tast/main/activity/TaskMainActivity;
getstatic com/nd/android/u/tasklib/R$string/surpass I
invokevirtual com/nd/android/u/tast/main/activity/TaskMainActivity/getString(I)Ljava/lang/String;
iconst_1
anewarray java/lang/Object
dup
iconst_0
aload 1
invokevirtual com/nd/android/u/tast/experience/bean/ShowOffBean/getRange()I
invokestatic java/lang/Integer/valueOf(I)Ljava/lang/Integer;
aastore
invokestatic java/lang/String/format(Ljava/lang/String;[Ljava/lang/Object;)Ljava/lang/String;
invokevirtual android/widget/TextView/setText(Ljava/lang/CharSequence;)V
aload 0
getfield com/nd/android/u/tast/main/activity/TaskMainActivity$GetShowOffTask/this$0 Lcom/nd/android/u/tast/main/activity/TaskMainActivity;
invokestatic com/nd/android/u/tast/main/activity/TaskMainActivity/access$800(Lcom/nd/android/u/tast/main/activity/TaskMainActivity;)Landroid/widget/GridView;
new com/nd/android/u/tast/main/adapter/HeaderAdapter
dup
aload 0
getfield com/nd/android/u/tast/main/activity/TaskMainActivity$GetShowOffTask/this$0 Lcom/nd/android/u/tast/main/activity/TaskMainActivity;
aload 2
invokespecial com/nd/android/u/tast/main/adapter/HeaderAdapter/<init>(Landroid/content/Context;Ljava/util/ArrayList;)V
invokevirtual android/widget/GridView/setAdapter(Landroid/widget/ListAdapter;)V
goto L3
.limit locals 3
.limit stack 6
.end method

.method protected volatile synthetic onPostExecute(Ljava/lang/Object;)V
aload 0
aload 1
checkcast com/nd/android/u/tast/experience/bean/ShowOffBean
invokevirtual com/nd/android/u/tast/main/activity/TaskMainActivity$GetShowOffTask/onPostExecute(Lcom/nd/android/u/tast/experience/bean/ShowOffBean;)V
return
.limit locals 2
.limit stack 2
.end method
