.bytecode 50.0
.class synchronized com/android/u/weibo/weibo/ui/adapter/ThreeTypeAdapter$2
.super java/lang/Object
.implements android/view/View$OnClickListener
.enclosing method com/android/u/weibo/weibo/ui/adapter/ThreeTypeAdapter/processData(ILcom/android/u/weibo/weibo/ui/adapter/ItemViewHolder;)V
.inner class inner com/android/u/weibo/weibo/ui/adapter/ThreeTypeAdapter$2

.field final synthetic 'this$0' Lcom/android/u/weibo/weibo/ui/adapter/ThreeTypeAdapter;

.field final synthetic 'val$c' Lcom/android/u/weibo/weibo/business/bean/ReplyInfo;

.field final synthetic 'val$viewHolder' Lcom/android/u/weibo/weibo/ui/adapter/ItemViewHolder;

.method <init>(Lcom/android/u/weibo/weibo/ui/adapter/ThreeTypeAdapter;Lcom/android/u/weibo/weibo/ui/adapter/ItemViewHolder;Lcom/android/u/weibo/weibo/business/bean/ReplyInfo;)V
aload 0
aload 1
putfield com/android/u/weibo/weibo/ui/adapter/ThreeTypeAdapter$2/this$0 Lcom/android/u/weibo/weibo/ui/adapter/ThreeTypeAdapter;
aload 0
aload 2
putfield com/android/u/weibo/weibo/ui/adapter/ThreeTypeAdapter$2/val$viewHolder Lcom/android/u/weibo/weibo/ui/adapter/ItemViewHolder;
aload 0
aload 3
putfield com/android/u/weibo/weibo/ui/adapter/ThreeTypeAdapter$2/val$c Lcom/android/u/weibo/weibo/business/bean/ReplyInfo;
aload 0
invokespecial java/lang/Object/<init>()V
return
.limit locals 4
.limit stack 2
.end method

.method public onClick(Landroid/view/View;)V
aload 0
getfield com/android/u/weibo/weibo/ui/adapter/ThreeTypeAdapter$2/this$0 Lcom/android/u/weibo/weibo/ui/adapter/ThreeTypeAdapter;
invokestatic com/android/u/weibo/weibo/ui/adapter/ThreeTypeAdapter/access$000(Lcom/android/u/weibo/weibo/ui/adapter/ThreeTypeAdapter;)Landroid/content/Context;
invokestatic com/common/android/utils/NetWorkUtils/JudgeNetWorkStatus(Landroid/content/Context;)Z
ifne L0
aload 0
getfield com/android/u/weibo/weibo/ui/adapter/ThreeTypeAdapter$2/this$0 Lcom/android/u/weibo/weibo/ui/adapter/ThreeTypeAdapter;
invokestatic com/android/u/weibo/weibo/ui/adapter/ThreeTypeAdapter/access$000(Lcom/android/u/weibo/weibo/ui/adapter/ThreeTypeAdapter;)Landroid/content/Context;
getstatic com/android/u/weibo/R$string/net_warn_no_network I
iconst_0
invokestatic android/widget/Toast/makeText(Landroid/content/Context;II)Landroid/widget/Toast;
invokevirtual android/widget/Toast/show()V
L1:
return
L0:
aload 0
getfield com/android/u/weibo/weibo/ui/adapter/ThreeTypeAdapter$2/val$viewHolder Lcom/android/u/weibo/weibo/ui/adapter/ItemViewHolder;
getfield com/android/u/weibo/weibo/ui/adapter/ItemViewHolder/txtTime Landroid/widget/TextView;
aload 0
getfield com/android/u/weibo/weibo/ui/adapter/ThreeTypeAdapter$2/this$0 Lcom/android/u/weibo/weibo/ui/adapter/ThreeTypeAdapter;
invokestatic com/android/u/weibo/weibo/ui/adapter/ThreeTypeAdapter/access$000(Lcom/android/u/weibo/weibo/ui/adapter/ThreeTypeAdapter;)Landroid/content/Context;
invokevirtual android/content/Context/getResources()Landroid/content/res/Resources;
getstatic com/android/u/weibo/R$string/is_posing_tweet I
invokevirtual android/content/res/Resources/getString(I)Ljava/lang/String;
invokevirtual android/widget/TextView/setText(Ljava/lang/CharSequence;)V
aload 0
getfield com/android/u/weibo/weibo/ui/adapter/ThreeTypeAdapter$2/this$0 Lcom/android/u/weibo/weibo/ui/adapter/ThreeTypeAdapter;
invokestatic com/android/u/weibo/weibo/ui/adapter/ThreeTypeAdapter/access$000(Lcom/android/u/weibo/weibo/ui/adapter/ThreeTypeAdapter;)Landroid/content/Context;
instanceof com/android/u/weibo/weibo/ui/activity/CommentListActivity
ifeq L1
aload 0
getfield com/android/u/weibo/weibo/ui/adapter/ThreeTypeAdapter$2/this$0 Lcom/android/u/weibo/weibo/ui/adapter/ThreeTypeAdapter;
invokestatic com/android/u/weibo/weibo/ui/adapter/ThreeTypeAdapter/access$000(Lcom/android/u/weibo/weibo/ui/adapter/ThreeTypeAdapter;)Landroid/content/Context;
checkcast com/android/u/weibo/weibo/ui/activity/CommentListActivity
aload 0
getfield com/android/u/weibo/weibo/ui/adapter/ThreeTypeAdapter$2/val$c Lcom/android/u/weibo/weibo/business/bean/ReplyInfo;
invokevirtual com/android/u/weibo/weibo/ui/activity/CommentListActivity/send(Lcom/android/u/weibo/weibo/business/bean/ReplyInfo;)V
return
.limit locals 2
.limit stack 3
.end method
