.bytecode 50.0
.class synchronized com/nd/android/u/cloud/activity/login/NdRegistMobile$3
.super java/lang/Thread
.enclosing method com/nd/android/u/cloud/activity/login/NdRegistMobile/sendHandlerMsg()V
.inner class inner com/nd/android/u/cloud/activity/login/NdRegistMobile$3

.field 'count' I

.field final synthetic 'this$0' Lcom/nd/android/u/cloud/activity/login/NdRegistMobile;

.method <init>(Lcom/nd/android/u/cloud/activity/login/NdRegistMobile;)V
aload 0
aload 1
putfield com/nd/android/u/cloud/activity/login/NdRegistMobile$3/this$0 Lcom/nd/android/u/cloud/activity/login/NdRegistMobile;
aload 0
invokespecial java/lang/Thread/<init>()V
aload 0
bipush 60
putfield com/nd/android/u/cloud/activity/login/NdRegistMobile$3/count I
return
.limit locals 2
.limit stack 2
.end method

.method public run()V
.catch java/lang/InterruptedException from L0 to L1 using L2
L3:
aload 0
getfield com/nd/android/u/cloud/activity/login/NdRegistMobile$3/count I
iconst_m1
if_icmple L4
L0:
ldc2_w 1000L
invokestatic java/lang/Thread/sleep(J)V
aload 0
getfield com/nd/android/u/cloud/activity/login/NdRegistMobile$3/this$0 Lcom/nd/android/u/cloud/activity/login/NdRegistMobile;
invokestatic com/nd/android/u/cloud/activity/login/NdRegistMobile/access$600(Lcom/nd/android/u/cloud/activity/login/NdRegistMobile;)Landroid/os/Handler;
bipush 110
new java/lang/StringBuilder
dup
invokespecial java/lang/StringBuilder/<init>()V
aload 0
getfield com/nd/android/u/cloud/activity/login/NdRegistMobile$3/count I
invokevirtual java/lang/StringBuilder/append(I)Ljava/lang/StringBuilder;
ldc ""
invokevirtual java/lang/StringBuilder/append(Ljava/lang/String;)Ljava/lang/StringBuilder;
invokevirtual java/lang/StringBuilder/toString()Ljava/lang/String;
invokevirtual android/os/Handler/obtainMessage(ILjava/lang/Object;)Landroid/os/Message;
invokevirtual android/os/Message/sendToTarget()V
aload 0
aload 0
getfield com/nd/android/u/cloud/activity/login/NdRegistMobile$3/count I
iconst_1
isub
putfield com/nd/android/u/cloud/activity/login/NdRegistMobile$3/count I
L1:
goto L3
L2:
astore 1
aload 1
invokevirtual java/lang/InterruptedException/printStackTrace()V
goto L3
L4:
aload 0
getfield com/nd/android/u/cloud/activity/login/NdRegistMobile$3/this$0 Lcom/nd/android/u/cloud/activity/login/NdRegistMobile;
invokestatic com/nd/android/u/cloud/activity/login/NdRegistMobile/access$500(Lcom/nd/android/u/cloud/activity/login/NdRegistMobile;)Landroid/widget/TextView;
aload 0
getfield com/nd/android/u/cloud/activity/login/NdRegistMobile$3/this$0 Lcom/nd/android/u/cloud/activity/login/NdRegistMobile;
invokevirtual android/widget/TextView/setOnClickListener(Landroid/view/View$OnClickListener;)V
return
.limit locals 2
.limit stack 4
.end method
