.bytecode 50.0
.class synchronized com/product/android/ui/activity/WebViewActivity$10
.super java/lang/Object
.implements com/common/android/ui/widget/DatePopupWindow$onDateSetListener
.enclosing method com/product/android/ui/activity/WebViewActivity
.inner class inner com/product/android/ui/activity/WebViewActivity$10

.field final synthetic 'this$0' Lcom/product/android/ui/activity/WebViewActivity;

.method <init>(Lcom/product/android/ui/activity/WebViewActivity;)V
aload 0
aload 1
putfield com/product/android/ui/activity/WebViewActivity$10/this$0 Lcom/product/android/ui/activity/WebViewActivity;
aload 0
invokespecial java/lang/Object/<init>()V
return
.limit locals 2
.limit stack 2
.end method

.method public onDateSet(III)V
aload 0
getfield com/product/android/ui/activity/WebViewActivity$10/this$0 Lcom/product/android/ui/activity/WebViewActivity;
new java/lang/StringBuilder
dup
invokespecial java/lang/StringBuilder/<init>()V
iload 1
invokevirtual java/lang/StringBuilder/append(I)Ljava/lang/StringBuilder;
ldc "-"
invokevirtual java/lang/StringBuilder/append(Ljava/lang/String;)Ljava/lang/StringBuilder;
iload 2
invokevirtual java/lang/StringBuilder/append(I)Ljava/lang/StringBuilder;
invokevirtual java/lang/StringBuilder/toString()Ljava/lang/String;
invokestatic com/product/android/ui/activity/WebViewActivity/access$302(Lcom/product/android/ui/activity/WebViewActivity;Ljava/lang/String;)Ljava/lang/String;
pop
aload 0
getfield com/product/android/ui/activity/WebViewActivity$10/this$0 Lcom/product/android/ui/activity/WebViewActivity;
invokestatic com/product/android/ui/activity/WebViewActivity/access$400(Lcom/product/android/ui/activity/WebViewActivity;)Landroid/webkit/WebView;
new java/lang/StringBuilder
dup
invokespecial java/lang/StringBuilder/<init>()V
ldc "javascript:setMonth('"
invokevirtual java/lang/StringBuilder/append(Ljava/lang/String;)Ljava/lang/StringBuilder;
aload 0
getfield com/product/android/ui/activity/WebViewActivity$10/this$0 Lcom/product/android/ui/activity/WebViewActivity;
invokestatic com/product/android/ui/activity/WebViewActivity/access$300(Lcom/product/android/ui/activity/WebViewActivity;)Ljava/lang/String;
invokevirtual java/lang/StringBuilder/append(Ljava/lang/String;)Ljava/lang/StringBuilder;
ldc "')"
invokevirtual java/lang/StringBuilder/append(Ljava/lang/String;)Ljava/lang/StringBuilder;
invokevirtual java/lang/StringBuilder/toString()Ljava/lang/String;
invokevirtual android/webkit/WebView/loadUrl(Ljava/lang/String;)V
return
.limit locals 4
.limit stack 3
.end method
