.bytecode 50.0
.class final synchronized com/product/android/ui/activity/WebViewActivity$JavaScriptInterface
.super java/lang/Object
.inner class final JavaScriptInterface inner com/product/android/ui/activity/WebViewActivity$JavaScriptInterface outer com/product/android/ui/activity/WebViewActivity

.field final synthetic 'this$0' Lcom/product/android/ui/activity/WebViewActivity;

.method <init>(Lcom/product/android/ui/activity/WebViewActivity;)V
aload 0
aload 1
putfield com/product/android/ui/activity/WebViewActivity$JavaScriptInterface/this$0 Lcom/product/android/ui/activity/WebViewActivity;
aload 0
invokespecial java/lang/Object/<init>()V
return
.limit locals 2
.limit stack 2
.end method

.method public getDate()Ljava/lang/String;
.annotation visible Landroid/webkit/JavascriptInterface;
.end annotation
aload 0
getfield com/product/android/ui/activity/WebViewActivity$JavaScriptInterface/this$0 Lcom/product/android/ui/activity/WebViewActivity;
invokestatic com/product/android/ui/activity/WebViewActivity/access$300(Lcom/product/android/ui/activity/WebViewActivity;)Ljava/lang/String;
areturn
.limit locals 1
.limit stack 1
.end method

.method public quitGame()V
.annotation visible Landroid/webkit/JavascriptInterface;
.end annotation
aload 0
getfield com/product/android/ui/activity/WebViewActivity$JavaScriptInterface/this$0 Lcom/product/android/ui/activity/WebViewActivity;
invokevirtual com/product/android/ui/activity/WebViewActivity/finish()V
return
.limit locals 1
.limit stack 1
.end method

.method public showDatePicker(Ljava/lang/String;)V
.annotation visible Landroid/webkit/JavascriptInterface;
.end annotation
ldc "debug"
new java/lang/StringBuilder
dup
invokespecial java/lang/StringBuilder/<init>()V
ldc "showDatePicker:"
invokevirtual java/lang/StringBuilder/append(Ljava/lang/String;)Ljava/lang/StringBuilder;
aload 1
invokevirtual java/lang/StringBuilder/append(Ljava/lang/String;)Ljava/lang/StringBuilder;
invokevirtual java/lang/StringBuilder/toString()Ljava/lang/String;
invokestatic android/util/Log/d(Ljava/lang/String;Ljava/lang/String;)I
pop
iconst_0
istore 4
iconst_0
istore 5
aload 1
ifnonnull L0
ldc "NewWebViewActivity"
new java/lang/StringBuilder
dup
invokespecial java/lang/StringBuilder/<init>()V
ldc "date-->"
invokevirtual java/lang/StringBuilder/append(Ljava/lang/String;)Ljava/lang/StringBuilder;
aload 1
invokevirtual java/lang/StringBuilder/append(Ljava/lang/String;)Ljava/lang/StringBuilder;
invokevirtual java/lang/StringBuilder/toString()Ljava/lang/String;
invokestatic com/product/android/utils/LogUtils/e(Ljava/lang/String;Ljava/lang/String;)V
iload 4
istore 3
iload 5
istore 2
L1:
aload 0
getfield com/product/android/ui/activity/WebViewActivity$JavaScriptInterface/this$0 Lcom/product/android/ui/activity/WebViewActivity;
invokestatic com/product/android/ui/activity/WebViewActivity/access$1900(Lcom/product/android/ui/activity/WebViewActivity;)Lcom/common/android/ui/widget/DatePopupWindow;
ifnonnull L2
aload 0
getfield com/product/android/ui/activity/WebViewActivity$JavaScriptInterface/this$0 Lcom/product/android/ui/activity/WebViewActivity;
ldc "layout_inflater"
invokevirtual com/product/android/ui/activity/WebViewActivity/getSystemService(Ljava/lang/String;)Ljava/lang/Object;
checkcast android/view/LayoutInflater
getstatic com/nd/android/u/allcommon/R$layout/datectrlyearmonth I
aconst_null
iconst_0
invokevirtual android/view/LayoutInflater/inflate(ILandroid/view/ViewGroup;Z)Landroid/view/View;
astore 1
aload 0
getfield com/product/android/ui/activity/WebViewActivity$JavaScriptInterface/this$0 Lcom/product/android/ui/activity/WebViewActivity;
new com/common/android/ui/widget/DatePopupWindow
dup
aload 1
iconst_m1
bipush -2
iconst_0
invokespecial com/common/android/ui/widget/DatePopupWindow/<init>(Landroid/view/View;IIZ)V
invokestatic com/product/android/ui/activity/WebViewActivity/access$1902(Lcom/product/android/ui/activity/WebViewActivity;Lcom/common/android/ui/widget/DatePopupWindow;)Lcom/common/android/ui/widget/DatePopupWindow;
pop
aload 0
getfield com/product/android/ui/activity/WebViewActivity$JavaScriptInterface/this$0 Lcom/product/android/ui/activity/WebViewActivity;
invokestatic com/product/android/ui/activity/WebViewActivity/access$1900(Lcom/product/android/ui/activity/WebViewActivity;)Lcom/common/android/ui/widget/DatePopupWindow;
aload 0
getfield com/product/android/ui/activity/WebViewActivity$JavaScriptInterface/this$0 Lcom/product/android/ui/activity/WebViewActivity;
invokestatic com/product/android/ui/activity/WebViewActivity/access$2000(Lcom/product/android/ui/activity/WebViewActivity;)Lcom/common/android/ui/widget/DatePopupWindow$onDateSetListener;
invokevirtual com/common/android/ui/widget/DatePopupWindow/setOnDateSetListener(Lcom/common/android/ui/widget/DatePopupWindow$onDateSetListener;)V
aload 0
getfield com/product/android/ui/activity/WebViewActivity$JavaScriptInterface/this$0 Lcom/product/android/ui/activity/WebViewActivity;
invokestatic com/product/android/ui/activity/WebViewActivity/access$1900(Lcom/product/android/ui/activity/WebViewActivity;)Lcom/common/android/ui/widget/DatePopupWindow;
new android/graphics/drawable/BitmapDrawable
dup
invokespecial android/graphics/drawable/BitmapDrawable/<init>()V
invokevirtual com/common/android/ui/widget/DatePopupWindow/setBackgroundDrawable(Landroid/graphics/drawable/Drawable;)V
aload 0
getfield com/product/android/ui/activity/WebViewActivity$JavaScriptInterface/this$0 Lcom/product/android/ui/activity/WebViewActivity;
invokestatic com/product/android/ui/activity/WebViewActivity/access$1900(Lcom/product/android/ui/activity/WebViewActivity;)Lcom/common/android/ui/widget/DatePopupWindow;
iconst_1
invokevirtual com/common/android/ui/widget/DatePopupWindow/setOutsideTouchable(Z)V
L2:
iload 3
ifeq L3
iload 2
ifne L4
L3:
aload 0
getfield com/product/android/ui/activity/WebViewActivity$JavaScriptInterface/this$0 Lcom/product/android/ui/activity/WebViewActivity;
invokestatic com/product/android/ui/activity/WebViewActivity/access$1900(Lcom/product/android/ui/activity/WebViewActivity;)Lcom/common/android/ui/widget/DatePopupWindow;
invokevirtual com/common/android/ui/widget/DatePopupWindow/SetToday()V
L5:
aload 0
getfield com/product/android/ui/activity/WebViewActivity$JavaScriptInterface/this$0 Lcom/product/android/ui/activity/WebViewActivity;
invokestatic com/product/android/ui/activity/WebViewActivity/access$1900(Lcom/product/android/ui/activity/WebViewActivity;)Lcom/common/android/ui/widget/DatePopupWindow;
aload 0
getfield com/product/android/ui/activity/WebViewActivity$JavaScriptInterface/this$0 Lcom/product/android/ui/activity/WebViewActivity;
invokestatic com/product/android/ui/activity/WebViewActivity/access$400(Lcom/product/android/ui/activity/WebViewActivity;)Landroid/webkit/WebView;
bipush 17
iconst_0
iconst_0
invokevirtual com/common/android/ui/widget/DatePopupWindow/showAtLocation(Landroid/view/View;III)V
return
L0:
aload 0
getfield com/product/android/ui/activity/WebViewActivity$JavaScriptInterface/this$0 Lcom/product/android/ui/activity/WebViewActivity;
aload 1
ldc "-"
invokevirtual java/lang/String/split(Ljava/lang/String;)[Ljava/lang/String;
invokestatic com/product/android/ui/activity/WebViewActivity/access$1802(Lcom/product/android/ui/activity/WebViewActivity;[Ljava/lang/String;)[Ljava/lang/String;
pop
iload 5
istore 2
iload 4
istore 3
aload 0
getfield com/product/android/ui/activity/WebViewActivity$JavaScriptInterface/this$0 Lcom/product/android/ui/activity/WebViewActivity;
invokestatic com/product/android/ui/activity/WebViewActivity/access$1800(Lcom/product/android/ui/activity/WebViewActivity;)[Ljava/lang/String;
ifnull L1
iload 5
istore 2
iload 4
istore 3
aload 0
getfield com/product/android/ui/activity/WebViewActivity$JavaScriptInterface/this$0 Lcom/product/android/ui/activity/WebViewActivity;
invokestatic com/product/android/ui/activity/WebViewActivity/access$1800(Lcom/product/android/ui/activity/WebViewActivity;)[Ljava/lang/String;
arraylength
iconst_1
if_icmple L1
iload 5
istore 2
iload 4
istore 3
aload 0
getfield com/product/android/ui/activity/WebViewActivity$JavaScriptInterface/this$0 Lcom/product/android/ui/activity/WebViewActivity;
invokestatic com/product/android/ui/activity/WebViewActivity/access$1800(Lcom/product/android/ui/activity/WebViewActivity;)[Ljava/lang/String;
iconst_0
aaload
ifnull L1
iload 5
istore 2
iload 4
istore 3
aload 0
getfield com/product/android/ui/activity/WebViewActivity$JavaScriptInterface/this$0 Lcom/product/android/ui/activity/WebViewActivity;
invokestatic com/product/android/ui/activity/WebViewActivity/access$1800(Lcom/product/android/ui/activity/WebViewActivity;)[Ljava/lang/String;
iconst_1
aaload
ifnull L1
aload 0
getfield com/product/android/ui/activity/WebViewActivity$JavaScriptInterface/this$0 Lcom/product/android/ui/activity/WebViewActivity;
invokestatic com/product/android/ui/activity/WebViewActivity/access$1800(Lcom/product/android/ui/activity/WebViewActivity;)[Ljava/lang/String;
iconst_0
aaload
invokestatic com/common/android/utils/FormatUtils/parseInt(Ljava/lang/String;)I
istore 3
aload 0
getfield com/product/android/ui/activity/WebViewActivity$JavaScriptInterface/this$0 Lcom/product/android/ui/activity/WebViewActivity;
invokestatic com/product/android/ui/activity/WebViewActivity/access$1800(Lcom/product/android/ui/activity/WebViewActivity;)[Ljava/lang/String;
iconst_1
aaload
invokestatic com/common/android/utils/FormatUtils/parseInt(Ljava/lang/String;)I
istore 2
goto L1
L4:
aload 0
getfield com/product/android/ui/activity/WebViewActivity$JavaScriptInterface/this$0 Lcom/product/android/ui/activity/WebViewActivity;
invokestatic com/product/android/ui/activity/WebViewActivity/access$1900(Lcom/product/android/ui/activity/WebViewActivity;)Lcom/common/android/ui/widget/DatePopupWindow;
iload 3
iload 2
invokevirtual com/common/android/ui/widget/DatePopupWindow/SetDateInfo(II)V
goto L5
.limit locals 6
.limit stack 7
.end method
