.bytecode 50.0
.class synchronized com/product/android/ui/activity/WebViewActivity$1
.super android/os/Handler
.enclosing method com/product/android/ui/activity/WebViewActivity
.inner class inner com/product/android/ui/activity/WebViewActivity$1

.field final synthetic 'this$0' Lcom/product/android/ui/activity/WebViewActivity;

.method <init>(Lcom/product/android/ui/activity/WebViewActivity;)V
aload 0
aload 1
putfield com/product/android/ui/activity/WebViewActivity$1/this$0 Lcom/product/android/ui/activity/WebViewActivity;
aload 0
invokespecial android/os/Handler/<init>()V
return
.limit locals 2
.limit stack 2
.end method

.method public handleMessage(Landroid/os/Message;)V
.catch java/lang/Exception from L0 to L1 using L2
.catch java/lang/IllegalArgumentException from L3 to L4 using L5
.catch java/lang/IllegalStateException from L3 to L4 using L6
.catch java/io/IOException from L3 to L4 using L7
invokestatic java/lang/Thread/currentThread()Ljava/lang/Thread;
invokevirtual java/lang/Thread/isInterrupted()Z
ifne L8
aload 1
getfield android/os/Message/what I
lookupswitch
0 : L9
1 : L10
3 : L11
101 : L12
102 : L13
default : L8
L8:
aload 0
aload 1
invokespecial android/os/Handler/handleMessage(Landroid/os/Message;)V
return
L9:
aload 0
getfield com/product/android/ui/activity/WebViewActivity$1/this$0 Lcom/product/android/ui/activity/WebViewActivity;
invokestatic com/product/android/ui/activity/WebViewActivity/access$000(Lcom/product/android/ui/activity/WebViewActivity;)Landroid/widget/ProgressBar;
iconst_0
invokevirtual android/widget/ProgressBar/setVisibility(I)V
aload 0
getfield com/product/android/ui/activity/WebViewActivity$1/this$0 Lcom/product/android/ui/activity/WebViewActivity;
invokestatic com/product/android/ui/activity/WebViewActivity/access$100(Lcom/product/android/ui/activity/WebViewActivity;)Landroid/widget/ImageView;
bipush 8
invokevirtual android/widget/ImageView/setVisibility(I)V
goto L8
L10:
aload 0
getfield com/product/android/ui/activity/WebViewActivity$1/this$0 Lcom/product/android/ui/activity/WebViewActivity;
invokestatic com/product/android/ui/activity/WebViewActivity/access$200(Lcom/product/android/ui/activity/WebViewActivity;)V
aload 0
getfield com/product/android/ui/activity/WebViewActivity$1/this$0 Lcom/product/android/ui/activity/WebViewActivity;
invokestatic com/product/android/ui/activity/WebViewActivity/access$000(Lcom/product/android/ui/activity/WebViewActivity;)Landroid/widget/ProgressBar;
bipush 8
invokevirtual android/widget/ProgressBar/setVisibility(I)V
aload 0
getfield com/product/android/ui/activity/WebViewActivity$1/this$0 Lcom/product/android/ui/activity/WebViewActivity;
invokestatic com/product/android/ui/activity/WebViewActivity/access$100(Lcom/product/android/ui/activity/WebViewActivity;)Landroid/widget/ImageView;
iconst_0
invokevirtual android/widget/ImageView/setVisibility(I)V
goto L8
L11:
aload 0
getfield com/product/android/ui/activity/WebViewActivity$1/this$0 Lcom/product/android/ui/activity/WebViewActivity;
invokestatic com/product/android/ui/activity/WebViewActivity/access$400(Lcom/product/android/ui/activity/WebViewActivity;)Landroid/webkit/WebView;
new java/lang/StringBuilder
dup
invokespecial java/lang/StringBuilder/<init>()V
ldc "javascript:setMonth('"
invokevirtual java/lang/StringBuilder/append(Ljava/lang/String;)Ljava/lang/StringBuilder;
aload 0
getfield com/product/android/ui/activity/WebViewActivity$1/this$0 Lcom/product/android/ui/activity/WebViewActivity;
invokestatic com/product/android/ui/activity/WebViewActivity/access$300(Lcom/product/android/ui/activity/WebViewActivity;)Ljava/lang/String;
invokevirtual java/lang/StringBuilder/append(Ljava/lang/String;)Ljava/lang/StringBuilder;
ldc "')"
invokevirtual java/lang/StringBuilder/append(Ljava/lang/String;)Ljava/lang/StringBuilder;
invokevirtual java/lang/StringBuilder/toString()Ljava/lang/String;
invokevirtual android/webkit/WebView/loadUrl(Ljava/lang/String;)V
goto L8
L12:
aload 1
getfield android/os/Message/arg1 I
istore 2
aload 1
getfield android/os/Message/obj Ljava/lang/Object;
checkcast java/lang/String
astore 3
iload 2
ifle L14
L0:
iload 2
invokestatic com/common/android/utils/ToastUtils/display(I)V
L1:
aload 0
getfield com/product/android/ui/activity/WebViewActivity$1/this$0 Lcom/product/android/ui/activity/WebViewActivity;
aload 3
invokestatic com/common/android/utils/ToastUtils/display(Landroid/content/Context;Ljava/lang/String;)V
goto L8
L14:
aload 3
invokestatic com/common/android/utils/ToastUtils/display(Ljava/lang/String;)V
goto L1
L13:
aload 1
getfield android/os/Message/obj Ljava/lang/Object;
checkcast java/io/File
astore 3
L3:
aload 0
getfield com/product/android/ui/activity/WebViewActivity$1/this$0 Lcom/product/android/ui/activity/WebViewActivity;
invokestatic com/product/android/ui/activity/WebViewActivity/access$500(Lcom/product/android/ui/activity/WebViewActivity;)Lcom/common/android/utils/audio/AudioAnimManager;
aload 3
invokevirtual com/common/android/utils/audio/AudioAnimManager/playAudio(Ljava/io/File;)V
L4:
goto L8
L5:
astore 3
aload 3
invokevirtual java/lang/IllegalArgumentException/printStackTrace()V
goto L8
L6:
astore 3
aload 3
invokevirtual java/lang/IllegalStateException/printStackTrace()V
goto L8
L7:
astore 3
aload 3
invokevirtual java/io/IOException/printStackTrace()V
goto L8
L2:
astore 4
goto L1
.limit locals 5
.limit stack 3
.end method
