.bytecode 50.0
.class public final synchronized com/alipay/android/phone/mrpc/core/a/e
.super com/alipay/android/phone/mrpc/core/a/b

.field private 'c' I

.field private 'd' Ljava/lang/Object;

.method public <init>(ILjava/lang/String;Ljava/lang/Object;)V
aload 0
aload 2
aload 3
invokespecial com/alipay/android/phone/mrpc/core/a/b/<init>(Ljava/lang/String;Ljava/lang/Object;)V
aload 0
iload 1
putfield com/alipay/android/phone/mrpc/core/a/e/c I
return
.limit locals 4
.limit stack 3
.end method

.method public final a(Ljava/lang/Object;)V
aload 0
aload 1
putfield com/alipay/android/phone/mrpc/core/a/e/d Ljava/lang/Object;
return
.limit locals 2
.limit stack 2
.end method

.method public final a()[B
.catch java/lang/Exception from L0 to L1 using L2
.catch java/lang/Exception from L1 to L3 using L2
.catch java/lang/Exception from L4 to L5 using L2
.catch java/lang/Exception from L5 to L6 using L2
L0:
new java/util/ArrayList
dup
invokespecial java/util/ArrayList/<init>()V
astore 2
aload 0
getfield com/alipay/android/phone/mrpc/core/a/e/d Ljava/lang/Object;
ifnull L1
aload 2
new org/apache/http/message/BasicNameValuePair
dup
ldc "extParam"
aload 0
getfield com/alipay/android/phone/mrpc/core/a/e/d Ljava/lang/Object;
invokestatic com/alipay/a/a/f/a(Ljava/lang/Object;)Ljava/lang/String;
invokespecial org/apache/http/message/BasicNameValuePair/<init>(Ljava/lang/String;Ljava/lang/String;)V
invokevirtual java/util/ArrayList/add(Ljava/lang/Object;)Z
pop
L1:
aload 2
new org/apache/http/message/BasicNameValuePair
dup
ldc "operationType"
aload 0
getfield com/alipay/android/phone/mrpc/core/a/e/a Ljava/lang/String;
invokespecial org/apache/http/message/BasicNameValuePair/<init>(Ljava/lang/String;Ljava/lang/String;)V
invokevirtual java/util/ArrayList/add(Ljava/lang/Object;)Z
pop
aload 2
new org/apache/http/message/BasicNameValuePair
dup
ldc "id"
new java/lang/StringBuilder
dup
invokespecial java/lang/StringBuilder/<init>()V
aload 0
getfield com/alipay/android/phone/mrpc/core/a/e/c I
invokevirtual java/lang/StringBuilder/append(I)Ljava/lang/StringBuilder;
invokevirtual java/lang/StringBuilder/toString()Ljava/lang/String;
invokespecial org/apache/http/message/BasicNameValuePair/<init>(Ljava/lang/String;Ljava/lang/String;)V
invokevirtual java/util/ArrayList/add(Ljava/lang/Object;)Z
pop
new java/lang/StringBuilder
dup
ldc "mParams is:"
invokespecial java/lang/StringBuilder/<init>(Ljava/lang/String;)V
aload 0
getfield com/alipay/android/phone/mrpc/core/a/e/b Ljava/lang/Object;
invokevirtual java/lang/StringBuilder/append(Ljava/lang/Object;)Ljava/lang/StringBuilder;
pop
aload 0
getfield com/alipay/android/phone/mrpc/core/a/e/b Ljava/lang/Object;
ifnonnull L5
L3:
ldc "[]"
astore 1
L4:
aload 2
new org/apache/http/message/BasicNameValuePair
dup
ldc "requestData"
aload 1
invokespecial org/apache/http/message/BasicNameValuePair/<init>(Ljava/lang/String;Ljava/lang/String;)V
invokevirtual java/util/ArrayList/add(Ljava/lang/Object;)Z
pop
aload 2
ldc "utf-8"
invokestatic org/apache/http/client/utils/URLEncodedUtils/format(Ljava/util/List;Ljava/lang/String;)Ljava/lang/String;
invokevirtual java/lang/String/getBytes()[B
areturn
L5:
aload 0
getfield com/alipay/android/phone/mrpc/core/a/e/b Ljava/lang/Object;
invokestatic com/alipay/a/a/f/a(Ljava/lang/Object;)Ljava/lang/String;
astore 1
L6:
goto L4
L2:
astore 2
new java/lang/StringBuilder
dup
ldc "request  ="
invokespecial java/lang/StringBuilder/<init>(Ljava/lang/String;)V
aload 0
getfield com/alipay/android/phone/mrpc/core/a/e/b Ljava/lang/Object;
invokevirtual java/lang/StringBuilder/append(Ljava/lang/Object;)Ljava/lang/StringBuilder;
ldc ":"
invokevirtual java/lang/StringBuilder/append(Ljava/lang/String;)Ljava/lang/StringBuilder;
aload 2
invokevirtual java/lang/StringBuilder/append(Ljava/lang/Object;)Ljava/lang/StringBuilder;
invokevirtual java/lang/StringBuilder/toString()Ljava/lang/String;
ifnonnull L7
ldc ""
astore 1
L8:
new com/alipay/android/phone/mrpc/core/c
dup
bipush 9
invokestatic java/lang/Integer/valueOf(I)Ljava/lang/Integer;
aload 1
aload 2
invokespecial com/alipay/android/phone/mrpc/core/c/<init>(Ljava/lang/Integer;Ljava/lang/String;Ljava/lang/Throwable;)V
athrow
L7:
aload 2
invokevirtual java/lang/Exception/getMessage()Ljava/lang/String;
astore 1
goto L8
.limit locals 3
.limit stack 6
.end method
