.bytecode 50.0
.class synchronized com/nd/android/u/contact/dialog/RankFilterDialog$3
.super java/lang/Object
.implements android/content/DialogInterface$OnClickListener
.enclosing method com/nd/android/u/contact/dialog/RankFilterDialog/initEvent()V
.inner class inner com/nd/android/u/contact/dialog/RankFilterDialog$3

.field final synthetic 'this$0' Lcom/nd/android/u/contact/dialog/RankFilterDialog;

.method <init>(Lcom/nd/android/u/contact/dialog/RankFilterDialog;)V
aload 0
aload 1
putfield com/nd/android/u/contact/dialog/RankFilterDialog$3/this$0 Lcom/nd/android/u/contact/dialog/RankFilterDialog;
aload 0
invokespecial java/lang/Object/<init>()V
return
.limit locals 2
.limit stack 2
.end method

.method public onClick(Landroid/content/DialogInterface;I)V
aload 0
getfield com/nd/android/u/contact/dialog/RankFilterDialog$3/this$0 Lcom/nd/android/u/contact/dialog/RankFilterDialog;
invokestatic com/nd/android/u/contact/dialog/RankFilterDialog/access$000(Lcom/nd/android/u/contact/dialog/RankFilterDialog;)V
aload 1
invokeinterface android/content/DialogInterface/dismiss()V 0
aload 0
getfield com/nd/android/u/contact/dialog/RankFilterDialog$3/this$0 Lcom/nd/android/u/contact/dialog/RankFilterDialog;
invokestatic com/nd/android/u/contact/dialog/RankFilterDialog/access$100(Lcom/nd/android/u/contact/dialog/RankFilterDialog;)Landroid/os/Handler;
ifnull L0
aload 0
getfield com/nd/android/u/contact/dialog/RankFilterDialog$3/this$0 Lcom/nd/android/u/contact/dialog/RankFilterDialog;
invokestatic com/nd/android/u/contact/dialog/RankFilterDialog/access$300(Lcom/nd/android/u/contact/dialog/RankFilterDialog;)Lcom/product/android/commonInterface/contact/RankFilterInfo;
aload 0
getfield com/nd/android/u/contact/dialog/RankFilterDialog$3/this$0 Lcom/nd/android/u/contact/dialog/RankFilterDialog;
invokestatic com/nd/android/u/contact/dialog/RankFilterDialog/access$200(Lcom/nd/android/u/contact/dialog/RankFilterDialog;)I
invokevirtual com/product/android/commonInterface/contact/RankFilterInfo/setGenderSelect(I)V
aload 0
getfield com/nd/android/u/contact/dialog/RankFilterDialog$3/this$0 Lcom/nd/android/u/contact/dialog/RankFilterDialog;
invokestatic com/nd/android/u/contact/dialog/RankFilterDialog/access$300(Lcom/nd/android/u/contact/dialog/RankFilterDialog;)Lcom/product/android/commonInterface/contact/RankFilterInfo;
aload 0
getfield com/nd/android/u/contact/dialog/RankFilterDialog$3/this$0 Lcom/nd/android/u/contact/dialog/RankFilterDialog;
invokestatic com/nd/android/u/contact/dialog/RankFilterDialog/access$400(Lcom/nd/android/u/contact/dialog/RankFilterDialog;)I
invokevirtual com/product/android/commonInterface/contact/RankFilterInfo/setTimeSelect(I)V
aload 0
getfield com/nd/android/u/contact/dialog/RankFilterDialog$3/this$0 Lcom/nd/android/u/contact/dialog/RankFilterDialog;
invokestatic com/nd/android/u/contact/dialog/RankFilterDialog/access$300(Lcom/nd/android/u/contact/dialog/RankFilterDialog;)Lcom/product/android/commonInterface/contact/RankFilterInfo;
aload 0
getfield com/nd/android/u/contact/dialog/RankFilterDialog$3/this$0 Lcom/nd/android/u/contact/dialog/RankFilterDialog;
invokestatic com/nd/android/u/contact/dialog/RankFilterDialog/access$500(Lcom/nd/android/u/contact/dialog/RankFilterDialog;)I
invokevirtual com/product/android/commonInterface/contact/RankFilterInfo/setDepartid(I)V
aload 0
getfield com/nd/android/u/contact/dialog/RankFilterDialog$3/this$0 Lcom/nd/android/u/contact/dialog/RankFilterDialog;
invokestatic com/nd/android/u/contact/dialog/RankFilterDialog/access$300(Lcom/nd/android/u/contact/dialog/RankFilterDialog;)Lcom/product/android/commonInterface/contact/RankFilterInfo;
aload 0
getfield com/nd/android/u/contact/dialog/RankFilterDialog$3/this$0 Lcom/nd/android/u/contact/dialog/RankFilterDialog;
invokestatic com/nd/android/u/contact/dialog/RankFilterDialog/access$600(Lcom/nd/android/u/contact/dialog/RankFilterDialog;)I
invokevirtual com/product/android/commonInterface/contact/RankFilterInfo/setUnitid(I)V
aload 0
getfield com/nd/android/u/contact/dialog/RankFilterDialog$3/this$0 Lcom/nd/android/u/contact/dialog/RankFilterDialog;
invokestatic com/nd/android/u/contact/dialog/RankFilterDialog/access$300(Lcom/nd/android/u/contact/dialog/RankFilterDialog;)Lcom/product/android/commonInterface/contact/RankFilterInfo;
aload 0
getfield com/nd/android/u/contact/dialog/RankFilterDialog$3/this$0 Lcom/nd/android/u/contact/dialog/RankFilterDialog;
invokestatic com/nd/android/u/contact/dialog/RankFilterDialog/access$700(Lcom/nd/android/u/contact/dialog/RankFilterDialog;)Ljava/lang/String;
invokevirtual com/product/android/commonInterface/contact/RankFilterInfo/setOrgSelectName(Ljava/lang/String;)V
aload 0
getfield com/nd/android/u/contact/dialog/RankFilterDialog$3/this$0 Lcom/nd/android/u/contact/dialog/RankFilterDialog;
invokestatic com/nd/android/u/contact/dialog/RankFilterDialog/access$100(Lcom/nd/android/u/contact/dialog/RankFilterDialog;)Landroid/os/Handler;
invokevirtual android/os/Handler/obtainMessage()Landroid/os/Message;
astore 1
aload 1
bipush 100
putfield android/os/Message/what I
aload 1
aload 0
getfield com/nd/android/u/contact/dialog/RankFilterDialog$3/this$0 Lcom/nd/android/u/contact/dialog/RankFilterDialog;
invokestatic com/nd/android/u/contact/dialog/RankFilterDialog/access$300(Lcom/nd/android/u/contact/dialog/RankFilterDialog;)Lcom/product/android/commonInterface/contact/RankFilterInfo;
putfield android/os/Message/obj Ljava/lang/Object;
aload 0
getfield com/nd/android/u/contact/dialog/RankFilterDialog$3/this$0 Lcom/nd/android/u/contact/dialog/RankFilterDialog;
invokestatic com/nd/android/u/contact/dialog/RankFilterDialog/access$100(Lcom/nd/android/u/contact/dialog/RankFilterDialog;)Landroid/os/Handler;
aload 1
invokevirtual android/os/Handler/sendMessage(Landroid/os/Message;)Z
pop
L0:
return
.limit locals 3
.limit stack 2
.end method
