.bytecode 50.0
.class public final synchronized com/nd/android/u/contact/activity/CreateGroupActivity$DoRefreshFrinedListTask
.super com/common/android/utils/task/genericTask/GenericTask
.inner class public final DoRefreshFrinedListTask inner com/nd/android/u/contact/activity/CreateGroupActivity$DoRefreshFrinedListTask outer com/nd/android/u/contact/activity/CreateGroupActivity

.field 'errCode' I

.field final synthetic 'this$0' Lcom/nd/android/u/contact/activity/CreateGroupActivity;

.method public <init>(Lcom/nd/android/u/contact/activity/CreateGroupActivity;)V
aload 0
aload 1
putfield com/nd/android/u/contact/activity/CreateGroupActivity$DoRefreshFrinedListTask/this$0 Lcom/nd/android/u/contact/activity/CreateGroupActivity;
aload 0
invokespecial com/common/android/utils/task/genericTask/GenericTask/<init>()V
aload 0
iconst_0
putfield com/nd/android/u/contact/activity/CreateGroupActivity$DoRefreshFrinedListTask/errCode I
return
.limit locals 2
.limit stack 2
.end method

.method public transient _doInBackground([Lcom/common/android/utils/task/genericTask/TaskParams;)Lcom/common/android/utils/task/genericTask/TaskResult;
aload 0
getfield com/nd/android/u/contact/activity/CreateGroupActivity$DoRefreshFrinedListTask/this$0 Lcom/nd/android/u/contact/activity/CreateGroupActivity;
invokestatic com/nd/android/u/contact/activity/CreateGroupActivity/access$300(Lcom/nd/android/u/contact/activity/CreateGroupActivity;)Landroid/widget/EditText;
invokevirtual android/widget/EditText/getText()Landroid/text/Editable;
invokevirtual java/lang/Object/toString()Ljava/lang/String;
invokevirtual java/lang/String/trim()Ljava/lang/String;
astore 1
aload 0
getfield com/nd/android/u/contact/activity/CreateGroupActivity$DoRefreshFrinedListTask/this$0 Lcom/nd/android/u/contact/activity/CreateGroupActivity;
invokestatic com/nd/android/u/contact/activity/CreateGroupActivity/access$400(Lcom/nd/android/u/contact/activity/CreateGroupActivity;)Landroid/widget/EditText;
invokevirtual android/widget/EditText/getText()Landroid/text/Editable;
invokevirtual java/lang/Object/toString()Ljava/lang/String;
astore 3
aload 0
getfield com/nd/android/u/contact/activity/CreateGroupActivity$DoRefreshFrinedListTask/this$0 Lcom/nd/android/u/contact/activity/CreateGroupActivity;
invokestatic com/nd/android/u/contact/activity/CreateGroupActivity/access$500(Lcom/nd/android/u/contact/activity/CreateGroupActivity;)Landroid/widget/RadioGroup;
invokevirtual android/widget/RadioGroup/getCheckedRadioButtonId()I
istore 2
iload 2
getstatic com/nd/android/u/contact/R$id/create_group_radio1 I
if_icmpne L0
aload 0
getfield com/nd/android/u/contact/activity/CreateGroupActivity$DoRefreshFrinedListTask/this$0 Lcom/nd/android/u/contact/activity/CreateGroupActivity;
iconst_1
putfield com/nd/android/u/contact/activity/CreateGroupActivity/joinperm I
L1:
aload 0
getfield com/nd/android/u/contact/activity/CreateGroupActivity$DoRefreshFrinedListTask/this$0 Lcom/nd/android/u/contact/activity/CreateGroupActivity;
invokestatic com/nd/android/u/contact/business_new/Controller/ContactOperatorFactory/getInstance()Lcom/nd/android/u/contact/business_new/Controller/ContactOperatorFactory;
invokestatic com/nd/android/u/contact/business_new/ProcesssImpl/ProductLoaderImpl/XYGroupLoader/getInstance()Lcom/nd/android/u/contact/business_new/Common/OperatorInterface/LoaderInterface/IGroupLoader;
invokevirtual com/nd/android/u/contact/business_new/Controller/ContactOperatorFactory/getGroupOperator(Lcom/nd/android/u/contact/business_new/Common/OperatorInterface/LoaderInterface/IGroupLoader;)Lcom/nd/android/u/contact/business_new/Common/OperatorInterface/IGroupOperator;
aload 1
aload 3
iconst_2
iconst_1
aload 0
getfield com/nd/android/u/contact/activity/CreateGroupActivity$DoRefreshFrinedListTask/this$0 Lcom/nd/android/u/contact/activity/CreateGroupActivity;
getfield com/nd/android/u/contact/activity/CreateGroupActivity/joinperm I
iconst_0
invokeinterface com/nd/android/u/contact/business_new/Common/OperatorInterface/IGroupOperator/createGroup(Ljava/lang/String;Ljava/lang/String;IIII)Lcom/nd/android/u/contact/business_new/Common/OperatorInterface/GroupInterface/IGroup; 6
checkcast com/nd/android/u/contact/business_new/ProcesssImpl/GroupImpl/AbsGroup
invokestatic com/nd/android/u/contact/activity/CreateGroupActivity/access$002(Lcom/nd/android/u/contact/activity/CreateGroupActivity;Lcom/nd/android/u/contact/business_new/ProcesssImpl/GroupImpl/AbsGroup;)Lcom/nd/android/u/contact/business_new/ProcesssImpl/GroupImpl/AbsGroup;
pop
aload 0
getfield com/nd/android/u/contact/activity/CreateGroupActivity$DoRefreshFrinedListTask/this$0 Lcom/nd/android/u/contact/activity/CreateGroupActivity;
invokestatic com/nd/android/u/contact/activity/CreateGroupActivity/access$000(Lcom/nd/android/u/contact/activity/CreateGroupActivity;)Lcom/nd/android/u/contact/business_new/ProcesssImpl/GroupImpl/AbsGroup;
ifnull L2
getstatic com/common/android/utils/task/genericTask/TaskResult/OK Lcom/common/android/utils/task/genericTask/TaskResult;
areturn
L0:
iload 2
getstatic com/nd/android/u/contact/R$id/create_group_radio2 I
if_icmpne L3
aload 0
getfield com/nd/android/u/contact/activity/CreateGroupActivity$DoRefreshFrinedListTask/this$0 Lcom/nd/android/u/contact/activity/CreateGroupActivity;
iconst_0
putfield com/nd/android/u/contact/activity/CreateGroupActivity/joinperm I
goto L1
L3:
iload 2
getstatic com/nd/android/u/contact/R$id/create_group_radio3 I
if_icmpne L1
aload 0
getfield com/nd/android/u/contact/activity/CreateGroupActivity$DoRefreshFrinedListTask/this$0 Lcom/nd/android/u/contact/activity/CreateGroupActivity;
iconst_2
putfield com/nd/android/u/contact/activity/CreateGroupActivity/joinperm I
goto L1
L2:
getstatic com/common/android/utils/task/genericTask/TaskResult/FAILED Lcom/common/android/utils/task/genericTask/TaskResult;
areturn
.limit locals 4
.limit stack 8
.end method
