.bytecode 50.0
.class synchronized com/nd/android/u/contact/activity/ManagerFriendsGroupActivity$FriendGroupAdapter$1
.super java/lang/Object
.implements android/view/View$OnFocusChangeListener
.enclosing method com/nd/android/u/contact/activity/ManagerFriendsGroupActivity$FriendGroupAdapter/initItemEvent(Lcom/nd/android/u/contact/activity/ManagerFriendsGroupActivity$ViewHolder;I)V
.inner class private FriendGroupAdapter inner com/nd/android/u/contact/activity/ManagerFriendsGroupActivity$FriendGroupAdapter outer com/nd/android/u/contact/activity/ManagerFriendsGroupActivity
.inner class inner com/nd/android/u/contact/activity/ManagerFriendsGroupActivity$FriendGroupAdapter$1

.field final synthetic 'this$1' Lcom/nd/android/u/contact/activity/ManagerFriendsGroupActivity$FriendGroupAdapter;

.field final synthetic 'val$position' I

.field final synthetic 'val$temp' Lcom/nd/android/u/contact/activity/ManagerFriendsGroupActivity$ViewHolder;

.field final synthetic 'val$tmp' Lcom/nd/android/u/contact/business_new/Common/OperatorInterface/FriednInterface/IFriendGroup;

.method <init>(Lcom/nd/android/u/contact/activity/ManagerFriendsGroupActivity$FriendGroupAdapter;ILcom/nd/android/u/contact/activity/ManagerFriendsGroupActivity$ViewHolder;Lcom/nd/android/u/contact/business_new/Common/OperatorInterface/FriednInterface/IFriendGroup;)V
aload 0
aload 1
putfield com/nd/android/u/contact/activity/ManagerFriendsGroupActivity$FriendGroupAdapter$1/this$1 Lcom/nd/android/u/contact/activity/ManagerFriendsGroupActivity$FriendGroupAdapter;
aload 0
iload 2
putfield com/nd/android/u/contact/activity/ManagerFriendsGroupActivity$FriendGroupAdapter$1/val$position I
aload 0
aload 3
putfield com/nd/android/u/contact/activity/ManagerFriendsGroupActivity$FriendGroupAdapter$1/val$temp Lcom/nd/android/u/contact/activity/ManagerFriendsGroupActivity$ViewHolder;
aload 0
aload 4
putfield com/nd/android/u/contact/activity/ManagerFriendsGroupActivity$FriendGroupAdapter$1/val$tmp Lcom/nd/android/u/contact/business_new/Common/OperatorInterface/FriednInterface/IFriendGroup;
aload 0
invokespecial java/lang/Object/<init>()V
return
.limit locals 5
.limit stack 2
.end method

.method public onFocusChange(Landroid/view/View;Z)V
aload 1
checkcast android/widget/EditText
astore 3
iload 2
ifeq L0
aload 0
getfield com/nd/android/u/contact/activity/ManagerFriendsGroupActivity$FriendGroupAdapter$1/this$1 Lcom/nd/android/u/contact/activity/ManagerFriendsGroupActivity$FriendGroupAdapter;
getfield com/nd/android/u/contact/activity/ManagerFriendsGroupActivity$FriendGroupAdapter/this$0 Lcom/nd/android/u/contact/activity/ManagerFriendsGroupActivity;
aload 0
getfield com/nd/android/u/contact/activity/ManagerFriendsGroupActivity$FriendGroupAdapter$1/val$position I
invokestatic com/nd/android/u/contact/activity/ManagerFriendsGroupActivity/access$502(Lcom/nd/android/u/contact/activity/ManagerFriendsGroupActivity;I)I
pop
aload 3
iconst_1
invokevirtual android/widget/EditText/setCursorVisible(Z)V
aload 3
aload 3
invokevirtual android/widget/EditText/getText()Landroid/text/Editable;
invokevirtual java/lang/Object/toString()Ljava/lang/String;
invokevirtual java/lang/String/length()I
invokevirtual android/widget/EditText/setSelection(I)V
aload 0
getfield com/nd/android/u/contact/activity/ManagerFriendsGroupActivity$FriendGroupAdapter$1/val$temp Lcom/nd/android/u/contact/activity/ManagerFriendsGroupActivity$ViewHolder;
getfield com/nd/android/u/contact/activity/ManagerFriendsGroupActivity$ViewHolder/mBtnClearFriendGroupName Landroid/widget/Button;
iconst_0
invokevirtual android/widget/Button/setVisibility(I)V
return
L0:
aload 0
getfield com/nd/android/u/contact/activity/ManagerFriendsGroupActivity$FriendGroupAdapter$1/val$temp Lcom/nd/android/u/contact/activity/ManagerFriendsGroupActivity$ViewHolder;
getfield com/nd/android/u/contact/activity/ManagerFriendsGroupActivity$ViewHolder/mBtnClearFriendGroupName Landroid/widget/Button;
iconst_4
invokevirtual android/widget/Button/setVisibility(I)V
aload 0
getfield com/nd/android/u/contact/activity/ManagerFriendsGroupActivity$FriendGroupAdapter$1/this$1 Lcom/nd/android/u/contact/activity/ManagerFriendsGroupActivity$FriendGroupAdapter;
aload 1
aload 0
getfield com/nd/android/u/contact/activity/ManagerFriendsGroupActivity$FriendGroupAdapter$1/val$tmp Lcom/nd/android/u/contact/business_new/Common/OperatorInterface/FriednInterface/IFriendGroup;
invokestatic com/nd/android/u/contact/activity/ManagerFriendsGroupActivity$FriendGroupAdapter/access$600(Lcom/nd/android/u/contact/activity/ManagerFriendsGroupActivity$FriendGroupAdapter;Landroid/view/View;Lcom/nd/android/u/contact/business_new/Common/OperatorInterface/FriednInterface/IFriendGroup;)V
aload 3
iconst_0
invokevirtual android/widget/EditText/setCursorVisible(Z)V
return
.limit locals 4
.limit stack 3
.end method
