.bytecode 50.0
.class synchronized com/nd/android/u/contact/activity/PhotoWallActivity$6
.super java/lang/Object
.implements android/text/TextWatcher
.enclosing method com/nd/android/u/contact/activity/PhotoWallActivity
.inner class inner com/nd/android/u/contact/activity/PhotoWallActivity$6

.field final synthetic 'this$0' Lcom/nd/android/u/contact/activity/PhotoWallActivity;

.method <init>(Lcom/nd/android/u/contact/activity/PhotoWallActivity;)V
aload 0
aload 1
putfield com/nd/android/u/contact/activity/PhotoWallActivity$6/this$0 Lcom/nd/android/u/contact/activity/PhotoWallActivity;
aload 0
invokespecial java/lang/Object/<init>()V
return
.limit locals 2
.limit stack 2
.end method

.method public afterTextChanged(Landroid/text/Editable;)V
return
.limit locals 2
.limit stack 0
.end method

.method public beforeTextChanged(Ljava/lang/CharSequence;III)V
return
.limit locals 5
.limit stack 0
.end method

.method public onTextChanged(Ljava/lang/CharSequence;III)V
aload 1
invokeinterface java/lang/CharSequence/length()I 0
ifne L0
aload 0
getfield com/nd/android/u/contact/activity/PhotoWallActivity$6/this$0 Lcom/nd/android/u/contact/activity/PhotoWallActivity;
invokestatic com/nd/android/u/contact/activity/PhotoWallActivity/access$1200(Lcom/nd/android/u/contact/activity/PhotoWallActivity;)Landroid/widget/Button;
aload 0
getfield com/nd/android/u/contact/activity/PhotoWallActivity$6/this$0 Lcom/nd/android/u/contact/activity/PhotoWallActivity;
getstatic com/nd/android/u/contact/R$string/search_cancel I
invokevirtual com/nd/android/u/contact/activity/PhotoWallActivity/getString(I)Ljava/lang/String;
invokevirtual android/widget/Button/setText(Ljava/lang/CharSequence;)V
getstatic com/product/android/business/config/Configuration/PRODUCT Lcom/product/android/business/ProductTypeDef$Product;
getstatic com/product/android/business/ProductTypeDef$Product/PRODUCT_91XY Lcom/product/android/business/ProductTypeDef$Product;
if_acmpne L1
aload 0
getfield com/nd/android/u/contact/activity/PhotoWallActivity$6/this$0 Lcom/nd/android/u/contact/activity/PhotoWallActivity;
invokestatic com/nd/android/u/contact/activity/PhotoWallActivity/access$1300(Lcom/nd/android/u/contact/activity/PhotoWallActivity;)Landroid/widget/Button;
getstatic com/nd/android/u/contact/R$drawable/btn_search_auto I
invokevirtual android/widget/Button/setBackgroundResource(I)V
return
L1:
aload 0
getfield com/nd/android/u/contact/activity/PhotoWallActivity$6/this$0 Lcom/nd/android/u/contact/activity/PhotoWallActivity;
invokestatic com/nd/android/u/contact/activity/PhotoWallActivity/access$1300(Lcom/nd/android/u/contact/activity/PhotoWallActivity;)Landroid/widget/Button;
bipush 8
invokevirtual android/widget/Button/setVisibility(I)V
return
L0:
aload 0
getfield com/nd/android/u/contact/activity/PhotoWallActivity$6/this$0 Lcom/nd/android/u/contact/activity/PhotoWallActivity;
invokestatic com/nd/android/u/contact/activity/PhotoWallActivity/access$1200(Lcom/nd/android/u/contact/activity/PhotoWallActivity;)Landroid/widget/Button;
aload 0
getfield com/nd/android/u/contact/activity/PhotoWallActivity$6/this$0 Lcom/nd/android/u/contact/activity/PhotoWallActivity;
getstatic com/nd/android/u/contact/R$string/begin_to_search I
invokevirtual com/nd/android/u/contact/activity/PhotoWallActivity/getString(I)Ljava/lang/String;
invokevirtual android/widget/Button/setText(Ljava/lang/CharSequence;)V
getstatic com/product/android/business/config/Configuration/PRODUCT Lcom/product/android/business/ProductTypeDef$Product;
getstatic com/product/android/business/ProductTypeDef$Product/PRODUCT_91XY Lcom/product/android/business/ProductTypeDef$Product;
if_acmpne L2
aload 0
getfield com/nd/android/u/contact/activity/PhotoWallActivity$6/this$0 Lcom/nd/android/u/contact/activity/PhotoWallActivity;
invokestatic com/nd/android/u/contact/activity/PhotoWallActivity/access$1300(Lcom/nd/android/u/contact/activity/PhotoWallActivity;)Landroid/widget/Button;
getstatic com/nd/android/u/contact/R$drawable/bt_search_cancel_bg I
invokevirtual android/widget/Button/setBackgroundResource(I)V
L3:
aload 0
getfield com/nd/android/u/contact/activity/PhotoWallActivity$6/this$0 Lcom/nd/android/u/contact/activity/PhotoWallActivity;
aload 1
invokeinterface java/lang/CharSequence/toString()Ljava/lang/String; 0
invokestatic com/nd/android/u/contact/activity/PhotoWallActivity/access$1400(Lcom/nd/android/u/contact/activity/PhotoWallActivity;Ljava/lang/String;)V
return
L2:
aload 0
getfield com/nd/android/u/contact/activity/PhotoWallActivity$6/this$0 Lcom/nd/android/u/contact/activity/PhotoWallActivity;
invokestatic com/nd/android/u/contact/activity/PhotoWallActivity/access$1300(Lcom/nd/android/u/contact/activity/PhotoWallActivity;)Landroid/widget/Button;
iconst_0
invokevirtual android/widget/Button/setVisibility(I)V
goto L3
.limit locals 5
.limit stack 3
.end method
