.bytecode 50.0
.class synchronized com/nd/android/u/contact/activity/SearchGroupActivity$2
.super java/lang/Object
.implements android/view/View$OnClickListener
.enclosing method com/nd/android/u/contact/activity/SearchGroupActivity
.inner class inner com/nd/android/u/contact/activity/SearchGroupActivity$2

.field 'groupid' Ljava/lang/String;

.field 'key' Ljava/lang/String;

.field final synthetic 'this$0' Lcom/nd/android/u/contact/activity/SearchGroupActivity;

.method <init>(Lcom/nd/android/u/contact/activity/SearchGroupActivity;)V
aload 0
aload 1
putfield com/nd/android/u/contact/activity/SearchGroupActivity$2/this$0 Lcom/nd/android/u/contact/activity/SearchGroupActivity;
aload 0
invokespecial java/lang/Object/<init>()V
return
.limit locals 2
.limit stack 2
.end method

.method public onClick(Landroid/view/View;)V
new android/os/Bundle
dup
invokespecial android/os/Bundle/<init>()V
astore 1
aload 0
getfield com/nd/android/u/contact/activity/SearchGroupActivity$2/this$0 Lcom/nd/android/u/contact/activity/SearchGroupActivity;
invokestatic com/nd/android/u/contact/activity/SearchGroupActivity/access$000(Lcom/nd/android/u/contact/activity/SearchGroupActivity;)I
tableswitch 0
L0
L1
default : L2
L2:
new android/content/Intent
dup
invokespecial android/content/Intent/<init>()V
astore 2
aload 2
aload 0
getfield com/nd/android/u/contact/activity/SearchGroupActivity$2/this$0 Lcom/nd/android/u/contact/activity/SearchGroupActivity;
ldc com/nd/android/u/contact/activity/SearchGroupResultActivity
invokevirtual android/content/Intent/setClass(Landroid/content/Context;Ljava/lang/Class;)Landroid/content/Intent;
pop
aload 1
ldc "type"
aload 0
getfield com/nd/android/u/contact/activity/SearchGroupActivity$2/this$0 Lcom/nd/android/u/contact/activity/SearchGroupActivity;
invokestatic com/nd/android/u/contact/activity/SearchGroupActivity/access$000(Lcom/nd/android/u/contact/activity/SearchGroupActivity;)I
invokevirtual android/os/Bundle/putInt(Ljava/lang/String;I)V
aload 2
aload 1
invokevirtual android/content/Intent/putExtras(Landroid/os/Bundle;)Landroid/content/Intent;
pop
aload 0
getfield com/nd/android/u/contact/activity/SearchGroupActivity$2/this$0 Lcom/nd/android/u/contact/activity/SearchGroupActivity;
aload 2
invokevirtual com/nd/android/u/contact/activity/SearchGroupActivity/startActivity(Landroid/content/Intent;)V
return
L0:
aload 0
aload 0
getfield com/nd/android/u/contact/activity/SearchGroupActivity$2/this$0 Lcom/nd/android/u/contact/activity/SearchGroupActivity;
invokestatic com/nd/android/u/contact/activity/SearchGroupActivity/access$300(Lcom/nd/android/u/contact/activity/SearchGroupActivity;)Landroid/widget/EditText;
invokevirtual android/widget/EditText/getText()Landroid/text/Editable;
invokevirtual java/lang/Object/toString()Ljava/lang/String;
putfield com/nd/android/u/contact/activity/SearchGroupActivity$2/groupid Ljava/lang/String;
aload 0
getfield com/nd/android/u/contact/activity/SearchGroupActivity$2/groupid Ljava/lang/String;
ifnull L3
aload 0
getfield com/nd/android/u/contact/activity/SearchGroupActivity$2/groupid Ljava/lang/String;
ldc ""
invokevirtual java/lang/String/equals(Ljava/lang/Object;)Z
ifeq L4
L3:
aload 0
getfield com/nd/android/u/contact/activity/SearchGroupActivity$2/this$0 Lcom/nd/android/u/contact/activity/SearchGroupActivity;
getstatic com/nd/android/u/contact/R$string/please_enter_group_name I
invokestatic com/common/android/utils/ToastUtils/display(Landroid/content/Context;I)V
return
L4:
aload 1
ldc "groupid"
aload 0
getfield com/nd/android/u/contact/activity/SearchGroupActivity$2/groupid Ljava/lang/String;
invokevirtual android/os/Bundle/putString(Ljava/lang/String;Ljava/lang/String;)V
goto L2
L1:
aload 0
aload 0
getfield com/nd/android/u/contact/activity/SearchGroupActivity$2/this$0 Lcom/nd/android/u/contact/activity/SearchGroupActivity;
invokestatic com/nd/android/u/contact/activity/SearchGroupActivity/access$700(Lcom/nd/android/u/contact/activity/SearchGroupActivity;)Landroid/widget/EditText;
invokevirtual android/widget/EditText/getText()Landroid/text/Editable;
invokevirtual java/lang/Object/toString()Ljava/lang/String;
putfield com/nd/android/u/contact/activity/SearchGroupActivity$2/key Ljava/lang/String;
aload 0
getfield com/nd/android/u/contact/activity/SearchGroupActivity$2/key Ljava/lang/String;
ifnull L5
aload 0
getfield com/nd/android/u/contact/activity/SearchGroupActivity$2/key Ljava/lang/String;
ldc ""
invokevirtual java/lang/String/equals(Ljava/lang/Object;)Z
ifeq L6
L5:
aload 0
getfield com/nd/android/u/contact/activity/SearchGroupActivity$2/this$0 Lcom/nd/android/u/contact/activity/SearchGroupActivity;
getstatic com/nd/android/u/contact/R$string/please_enter_key I
invokestatic com/common/android/utils/ToastUtils/display(Landroid/content/Context;I)V
return
L6:
aload 1
ldc "key"
aload 0
getfield com/nd/android/u/contact/activity/SearchGroupActivity$2/key Ljava/lang/String;
invokevirtual android/os/Bundle/putString(Ljava/lang/String;Ljava/lang/String;)V
goto L2
.limit locals 3
.limit stack 3
.end method
