.bytecode 50.0
.class synchronized com/nd/android/u/contact/activity/SearchGroupActivity$1
.super java/lang/Object
.implements android/view/View$OnClickListener
.enclosing method com/nd/android/u/contact/activity/SearchGroupActivity
.inner class inner com/nd/android/u/contact/activity/SearchGroupActivity$1

.field final synthetic 'this$0' Lcom/nd/android/u/contact/activity/SearchGroupActivity;

.method <init>(Lcom/nd/android/u/contact/activity/SearchGroupActivity;)V
aload 0
aload 1
putfield com/nd/android/u/contact/activity/SearchGroupActivity$1/this$0 Lcom/nd/android/u/contact/activity/SearchGroupActivity;
aload 0
invokespecial java/lang/Object/<init>()V
return
.limit locals 2
.limit stack 2
.end method

.method public onClick(Landroid/view/View;)V
aload 1
invokevirtual android/view/View/getId()I
istore 2
iload 2
getstatic com/nd/android/u/contact/R$id/search_group_img1 I
if_icmpeq L0
iload 2
getstatic com/nd/android/u/contact/R$id/search_group_relative_userid I
if_icmpne L1
L0:
aload 0
getfield com/nd/android/u/contact/activity/SearchGroupActivity$1/this$0 Lcom/nd/android/u/contact/activity/SearchGroupActivity;
invokestatic com/nd/android/u/contact/activity/SearchGroupActivity/access$000(Lcom/nd/android/u/contact/activity/SearchGroupActivity;)I
ifne L2
L3:
return
L2:
aload 0
getfield com/nd/android/u/contact/activity/SearchGroupActivity$1/this$0 Lcom/nd/android/u/contact/activity/SearchGroupActivity;
invokestatic com/nd/android/u/contact/activity/SearchGroupActivity/access$100(Lcom/nd/android/u/contact/activity/SearchGroupActivity;)Landroid/widget/LinearLayout;
iconst_0
invokevirtual android/widget/LinearLayout/setVisibility(I)V
aload 0
getfield com/nd/android/u/contact/activity/SearchGroupActivity$1/this$0 Lcom/nd/android/u/contact/activity/SearchGroupActivity;
invokestatic com/nd/android/u/contact/activity/SearchGroupActivity/access$200(Lcom/nd/android/u/contact/activity/SearchGroupActivity;)Landroid/widget/LinearLayout;
bipush 8
invokevirtual android/widget/LinearLayout/setVisibility(I)V
aload 0
getfield com/nd/android/u/contact/activity/SearchGroupActivity$1/this$0 Lcom/nd/android/u/contact/activity/SearchGroupActivity;
invokestatic com/nd/android/u/contact/activity/SearchGroupActivity/access$300(Lcom/nd/android/u/contact/activity/SearchGroupActivity;)Landroid/widget/EditText;
invokevirtual android/widget/EditText/requestFocus()Z
pop
aload 0
getfield com/nd/android/u/contact/activity/SearchGroupActivity$1/this$0 Lcom/nd/android/u/contact/activity/SearchGroupActivity;
invokestatic com/nd/android/u/contact/activity/SearchGroupActivity/access$400(Lcom/nd/android/u/contact/activity/SearchGroupActivity;)Landroid/widget/ImageView;
getstatic com/nd/android/u/contact/R$drawable/expand I
invokevirtual android/widget/ImageView/setBackgroundResource(I)V
aload 0
getfield com/nd/android/u/contact/activity/SearchGroupActivity$1/this$0 Lcom/nd/android/u/contact/activity/SearchGroupActivity;
invokestatic com/nd/android/u/contact/activity/SearchGroupActivity/access$500(Lcom/nd/android/u/contact/activity/SearchGroupActivity;)Landroid/widget/ImageView;
getstatic com/nd/android/u/contact/R$drawable/expander_ic_folder I
invokevirtual android/widget/ImageView/setBackgroundResource(I)V
aload 0
getfield com/nd/android/u/contact/activity/SearchGroupActivity$1/this$0 Lcom/nd/android/u/contact/activity/SearchGroupActivity;
invokestatic com/nd/android/u/contact/activity/SearchGroupActivity/access$600(Lcom/nd/android/u/contact/activity/SearchGroupActivity;)Landroid/view/inputmethod/InputMethodManager;
aload 0
getfield com/nd/android/u/contact/activity/SearchGroupActivity$1/this$0 Lcom/nd/android/u/contact/activity/SearchGroupActivity;
invokestatic com/nd/android/u/contact/activity/SearchGroupActivity/access$300(Lcom/nd/android/u/contact/activity/SearchGroupActivity;)Landroid/widget/EditText;
iconst_0
invokevirtual android/view/inputmethod/InputMethodManager/showSoftInput(Landroid/view/View;I)Z
pop
aload 0
getfield com/nd/android/u/contact/activity/SearchGroupActivity$1/this$0 Lcom/nd/android/u/contact/activity/SearchGroupActivity;
iconst_0
invokestatic com/nd/android/u/contact/activity/SearchGroupActivity/access$002(Lcom/nd/android/u/contact/activity/SearchGroupActivity;I)I
pop
return
L1:
iload 2
getstatic com/nd/android/u/contact/R$id/search_group_img2 I
if_icmpeq L4
iload 2
getstatic com/nd/android/u/contact/R$id/search_group_relative_nickname I
if_icmpne L3
L4:
aload 0
getfield com/nd/android/u/contact/activity/SearchGroupActivity$1/this$0 Lcom/nd/android/u/contact/activity/SearchGroupActivity;
invokestatic com/nd/android/u/contact/activity/SearchGroupActivity/access$000(Lcom/nd/android/u/contact/activity/SearchGroupActivity;)I
iconst_1
if_icmpeq L3
aload 0
getfield com/nd/android/u/contact/activity/SearchGroupActivity$1/this$0 Lcom/nd/android/u/contact/activity/SearchGroupActivity;
invokestatic com/nd/android/u/contact/activity/SearchGroupActivity/access$200(Lcom/nd/android/u/contact/activity/SearchGroupActivity;)Landroid/widget/LinearLayout;
iconst_0
invokevirtual android/widget/LinearLayout/setVisibility(I)V
aload 0
getfield com/nd/android/u/contact/activity/SearchGroupActivity$1/this$0 Lcom/nd/android/u/contact/activity/SearchGroupActivity;
invokestatic com/nd/android/u/contact/activity/SearchGroupActivity/access$100(Lcom/nd/android/u/contact/activity/SearchGroupActivity;)Landroid/widget/LinearLayout;
bipush 8
invokevirtual android/widget/LinearLayout/setVisibility(I)V
aload 0
getfield com/nd/android/u/contact/activity/SearchGroupActivity$1/this$0 Lcom/nd/android/u/contact/activity/SearchGroupActivity;
invokestatic com/nd/android/u/contact/activity/SearchGroupActivity/access$500(Lcom/nd/android/u/contact/activity/SearchGroupActivity;)Landroid/widget/ImageView;
getstatic com/nd/android/u/contact/R$drawable/expand I
invokevirtual android/widget/ImageView/setBackgroundResource(I)V
aload 0
getfield com/nd/android/u/contact/activity/SearchGroupActivity$1/this$0 Lcom/nd/android/u/contact/activity/SearchGroupActivity;
invokestatic com/nd/android/u/contact/activity/SearchGroupActivity/access$400(Lcom/nd/android/u/contact/activity/SearchGroupActivity;)Landroid/widget/ImageView;
getstatic com/nd/android/u/contact/R$drawable/expander_ic_folder I
invokevirtual android/widget/ImageView/setBackgroundResource(I)V
aload 0
getfield com/nd/android/u/contact/activity/SearchGroupActivity$1/this$0 Lcom/nd/android/u/contact/activity/SearchGroupActivity;
invokestatic com/nd/android/u/contact/activity/SearchGroupActivity/access$700(Lcom/nd/android/u/contact/activity/SearchGroupActivity;)Landroid/widget/EditText;
invokevirtual android/widget/EditText/requestFocus()Z
pop
aload 0
getfield com/nd/android/u/contact/activity/SearchGroupActivity$1/this$0 Lcom/nd/android/u/contact/activity/SearchGroupActivity;
invokestatic com/nd/android/u/contact/activity/SearchGroupActivity/access$600(Lcom/nd/android/u/contact/activity/SearchGroupActivity;)Landroid/view/inputmethod/InputMethodManager;
aload 0
getfield com/nd/android/u/contact/activity/SearchGroupActivity$1/this$0 Lcom/nd/android/u/contact/activity/SearchGroupActivity;
invokestatic com/nd/android/u/contact/activity/SearchGroupActivity/access$700(Lcom/nd/android/u/contact/activity/SearchGroupActivity;)Landroid/widget/EditText;
iconst_0
invokevirtual android/view/inputmethod/InputMethodManager/showSoftInput(Landroid/view/View;I)Z
pop
aload 0
getfield com/nd/android/u/contact/activity/SearchGroupActivity$1/this$0 Lcom/nd/android/u/contact/activity/SearchGroupActivity;
iconst_1
invokestatic com/nd/android/u/contact/activity/SearchGroupActivity/access$002(Lcom/nd/android/u/contact/activity/SearchGroupActivity;I)I
pop
return
.limit locals 3
.limit stack 3
.end method
