.bytecode 50.0
.class synchronized com/nd/android/u/contact/activity/TransferGroupActivity$3
.super java/lang/Object
.implements android/widget/AdapterView$OnItemClickListener
.enclosing method com/nd/android/u/contact/activity/TransferGroupActivity/initEvent()V
.inner class inner com/nd/android/u/contact/activity/TransferGroupActivity$3

.field final synthetic 'this$0' Lcom/nd/android/u/contact/activity/TransferGroupActivity;

.method <init>(Lcom/nd/android/u/contact/activity/TransferGroupActivity;)V
aload 0
aload 1
putfield com/nd/android/u/contact/activity/TransferGroupActivity$3/this$0 Lcom/nd/android/u/contact/activity/TransferGroupActivity;
aload 0
invokespecial java/lang/Object/<init>()V
return
.limit locals 2
.limit stack 2
.end method

.method public onItemClick(Landroid/widget/AdapterView;Landroid/view/View;IJ)V
.signature "(Landroid/widget/AdapterView<*>;Landroid/view/View;IJ)V"
aload 0
getfield com/nd/android/u/contact/activity/TransferGroupActivity$3/this$0 Lcom/nd/android/u/contact/activity/TransferGroupActivity;
invokestatic com/nd/android/u/contact/activity/TransferGroupActivity/access$400(Lcom/nd/android/u/contact/activity/TransferGroupActivity;)Lcom/nd/android/u/contact/adapter/TransferGroupMemberAdapter;
iload 3
invokevirtual com/nd/android/u/contact/adapter/TransferGroupMemberAdapter/getItem(I)Ljava/lang/Object;
checkcast com/product/android/commonInterface/contact/OapUser
astore 1
aload 0
getfield com/nd/android/u/contact/activity/TransferGroupActivity$3/this$0 Lcom/nd/android/u/contact/activity/TransferGroupActivity;
invokestatic com/nd/android/u/contact/activity/TransferGroupActivity/access$400(Lcom/nd/android/u/contact/activity/TransferGroupActivity;)Lcom/nd/android/u/contact/adapter/TransferGroupMemberAdapter;
invokevirtual com/nd/android/u/contact/adapter/TransferGroupMemberAdapter/getSelectid()J
aload 1
invokevirtual com/product/android/commonInterface/contact/OapUser/getFid()J
lcmp
ifne L0
aload 0
getfield com/nd/android/u/contact/activity/TransferGroupActivity$3/this$0 Lcom/nd/android/u/contact/activity/TransferGroupActivity;
invokestatic com/nd/android/u/contact/activity/TransferGroupActivity/access$600(Lcom/nd/android/u/contact/activity/TransferGroupActivity;)Landroid/widget/Button;
iconst_0
invokevirtual android/widget/Button/setEnabled(Z)V
aload 0
getfield com/nd/android/u/contact/activity/TransferGroupActivity$3/this$0 Lcom/nd/android/u/contact/activity/TransferGroupActivity;
invokestatic com/nd/android/u/contact/activity/TransferGroupActivity/access$400(Lcom/nd/android/u/contact/activity/TransferGroupActivity;)Lcom/nd/android/u/contact/adapter/TransferGroupMemberAdapter;
ldc2_w -1L
invokevirtual com/nd/android/u/contact/adapter/TransferGroupMemberAdapter/setSelectid(J)V
L1:
aload 0
getfield com/nd/android/u/contact/activity/TransferGroupActivity$3/this$0 Lcom/nd/android/u/contact/activity/TransferGroupActivity;
invokestatic com/nd/android/u/contact/activity/TransferGroupActivity/access$400(Lcom/nd/android/u/contact/activity/TransferGroupActivity;)Lcom/nd/android/u/contact/adapter/TransferGroupMemberAdapter;
invokevirtual com/nd/android/u/contact/adapter/TransferGroupMemberAdapter/notifyDataSetChanged()V
return
L0:
aload 0
getfield com/nd/android/u/contact/activity/TransferGroupActivity$3/this$0 Lcom/nd/android/u/contact/activity/TransferGroupActivity;
invokestatic com/nd/android/u/contact/activity/TransferGroupActivity/access$700(Lcom/nd/android/u/contact/activity/TransferGroupActivity;)Landroid/widget/Button;
iconst_1
invokevirtual android/widget/Button/setEnabled(Z)V
aload 0
getfield com/nd/android/u/contact/activity/TransferGroupActivity$3/this$0 Lcom/nd/android/u/contact/activity/TransferGroupActivity;
invokestatic com/nd/android/u/contact/activity/TransferGroupActivity/access$400(Lcom/nd/android/u/contact/activity/TransferGroupActivity;)Lcom/nd/android/u/contact/adapter/TransferGroupMemberAdapter;
aload 1
invokevirtual com/product/android/commonInterface/contact/OapUser/getFid()J
invokevirtual com/nd/android/u/contact/adapter/TransferGroupMemberAdapter/setSelectid(J)V
goto L1
.limit locals 6
.limit stack 4
.end method
