.bytecode 50.0
.class synchronized com/nd/android/u/news/ui/view/NewsFootView$ZanTask
.super com/common/android/utils/concurrent/NdTinyHttpAsyncTask
.signature "Lcom/common/android/utils/concurrent/NdTinyHttpAsyncTask<Ljava/lang/Integer;Ljava/lang/Void;Ljava/lang/Object;>;"
.inner class private ZanTask inner com/nd/android/u/news/ui/view/NewsFootView$ZanTask outer com/nd/android/u/news/ui/view/NewsFootView

.field private 'paramStatus' I

.field final synthetic 'this$0' Lcom/nd/android/u/news/ui/view/NewsFootView;

.method private <init>(Lcom/nd/android/u/news/ui/view/NewsFootView;)V
aload 0
aload 1
putfield com/nd/android/u/news/ui/view/NewsFootView$ZanTask/this$0 Lcom/nd/android/u/news/ui/view/NewsFootView;
aload 0
invokespecial com/common/android/utils/concurrent/NdTinyHttpAsyncTask/<init>()V
return
.limit locals 2
.limit stack 2
.end method

.method synthetic <init>(Lcom/nd/android/u/news/ui/view/NewsFootView;Lcom/nd/android/u/news/ui/view/NewsFootView$1;)V
aload 0
aload 1
invokespecial com/nd/android/u/news/ui/view/NewsFootView$ZanTask/<init>(Lcom/nd/android/u/news/ui/view/NewsFootView;)V
return
.limit locals 3
.limit stack 2
.end method

.method protected transient doInBackground([Ljava/lang/Integer;)Ljava/lang/Object;
aconst_null
astore 2
aload 0
aload 1
iconst_0
aaload
invokevirtual java/lang/Integer/intValue()I
putfield com/nd/android/u/news/ui/view/NewsFootView$ZanTask/paramStatus I
ldc "news"
aload 0
getfield com/nd/android/u/news/ui/view/NewsFootView$ZanTask/this$0 Lcom/nd/android/u/news/ui/view/NewsFootView;
invokestatic com/nd/android/u/news/ui/view/NewsFootView/access$100(Lcom/nd/android/u/news/ui/view/NewsFootView;)Ljava/lang/String;
invokevirtual java/lang/String/equals(Ljava/lang/Object;)Z
ifeq L0
aload 0
getfield com/nd/android/u/news/ui/view/NewsFootView$ZanTask/paramStatus I
iconst_1
if_icmpne L1
getstatic com/nd/android/u/news/controller/NewsManager/INSTANCE Lcom/nd/android/u/news/controller/NewsManager;
aload 0
getfield com/nd/android/u/news/ui/view/NewsFootView$ZanTask/this$0 Lcom/nd/android/u/news/ui/view/NewsFootView;
invokestatic com/nd/android/u/news/ui/view/NewsFootView/access$200(Lcom/nd/android/u/news/ui/view/NewsFootView;)J
invokevirtual com/nd/android/u/news/controller/NewsManager/createPraise(J)Lcom/nd/android/forumsdk/business/bean/result/PraiseInfoBean;
astore 1
L2:
aload 1
areturn
L1:
aload 2
astore 1
aload 0
getfield com/nd/android/u/news/ui/view/NewsFootView$ZanTask/paramStatus I
ifne L2
getstatic com/nd/android/u/news/controller/NewsManager/INSTANCE Lcom/nd/android/u/news/controller/NewsManager;
aload 0
getfield com/nd/android/u/news/ui/view/NewsFootView$ZanTask/this$0 Lcom/nd/android/u/news/ui/view/NewsFootView;
invokestatic com/nd/android/u/news/ui/view/NewsFootView/access$200(Lcom/nd/android/u/news/ui/view/NewsFootView;)J
invokevirtual com/nd/android/u/news/controller/NewsManager/cancelPraise(J)Lcom/nd/android/forumsdk/business/bean/result/PraiseInfoBean;
areturn
L0:
aload 2
astore 1
ldc "gallery"
aload 0
getfield com/nd/android/u/news/ui/view/NewsFootView$ZanTask/this$0 Lcom/nd/android/u/news/ui/view/NewsFootView;
invokestatic com/nd/android/u/news/ui/view/NewsFootView/access$100(Lcom/nd/android/u/news/ui/view/NewsFootView;)Ljava/lang/String;
invokevirtual java/lang/String/equals(Ljava/lang/Object;)Z
ifeq L2
aload 0
getfield com/nd/android/u/news/ui/view/NewsFootView$ZanTask/paramStatus I
iconst_1
if_icmpne L3
getstatic com/nd/android/u/news/controller/NewsManager/INSTANCE Lcom/nd/android/u/news/controller/NewsManager;
aload 0
getfield com/nd/android/u/news/ui/view/NewsFootView$ZanTask/this$0 Lcom/nd/android/u/news/ui/view/NewsFootView;
invokestatic com/nd/android/u/news/ui/view/NewsFootView/access$200(Lcom/nd/android/u/news/ui/view/NewsFootView;)J
invokevirtual com/nd/android/u/news/controller/NewsManager/createPicPraise(J)Lcom/nd/android/forumsdk/business/bean/result/PraiseInfoBean;
areturn
L3:
aload 2
astore 1
aload 0
getfield com/nd/android/u/news/ui/view/NewsFootView$ZanTask/paramStatus I
ifne L2
getstatic com/nd/android/u/news/controller/NewsManager/INSTANCE Lcom/nd/android/u/news/controller/NewsManager;
aload 0
getfield com/nd/android/u/news/ui/view/NewsFootView$ZanTask/this$0 Lcom/nd/android/u/news/ui/view/NewsFootView;
invokestatic com/nd/android/u/news/ui/view/NewsFootView/access$200(Lcom/nd/android/u/news/ui/view/NewsFootView;)J
invokevirtual com/nd/android/u/news/controller/NewsManager/cancelPicPraise(J)Lcom/nd/android/forumsdk/business/bean/result/PraiseInfoBean;
areturn
.limit locals 3
.limit stack 3
.end method

.method protected volatile synthetic doInBackground([Ljava/lang/Object;)Ljava/lang/Object;
aload 0
aload 1
checkcast [Ljava/lang/Integer;
invokevirtual com/nd/android/u/news/ui/view/NewsFootView$ZanTask/doInBackground([Ljava/lang/Integer;)Ljava/lang/Object;
areturn
.limit locals 2
.limit stack 2
.end method

.method protected onPostExecute(Ljava/lang/Object;)V
aload 1
ifnull L0
aload 1
instanceof com/nd/android/forumsdk/business/bean/result/PraiseInfoBean
ifeq L0
aload 1
checkcast com/nd/android/forumsdk/business/bean/result/PraiseInfoBean
astore 2
aload 1
checkcast com/nd/android/forumsdk/business/bean/result/PraiseInfoBean
invokevirtual com/nd/android/forumsdk/business/bean/result/PraiseInfoBean/isSuccess()Z
ifne L1
aload 0
getfield com/nd/android/u/news/ui/view/NewsFootView$ZanTask/this$0 Lcom/nd/android/u/news/ui/view/NewsFootView;
invokevirtual com/nd/android/u/news/ui/view/NewsFootView/getResources()Landroid/content/res/Resources;
getstatic com/nd/android/u/news/R$string/zan_error I
invokevirtual android/content/res/Resources/getString(I)Ljava/lang/String;
aload 2
invokestatic com/nd/android/u/news/NewsUtil/getErrorMsg(Ljava/lang/String;Lcom/nd/android/forumsdk/business/bean/ForumResultBase;)Ljava/lang/String;
invokestatic com/common/android/utils/ToastUtils/display(Ljava/lang/String;)V
aload 0
getfield com/nd/android/u/news/ui/view/NewsFootView$ZanTask/paramStatus I
iconst_1
if_icmpne L2
aload 0
getfield com/nd/android/u/news/ui/view/NewsFootView$ZanTask/this$0 Lcom/nd/android/u/news/ui/view/NewsFootView;
invokestatic com/nd/android/u/news/ui/view/NewsFootView/access$300(Lcom/nd/android/u/news/ui/view/NewsFootView;)I
ifeq L3
aload 0
getfield com/nd/android/u/news/ui/view/NewsFootView$ZanTask/this$0 Lcom/nd/android/u/news/ui/view/NewsFootView;
iconst_0
invokestatic com/nd/android/u/news/ui/view/NewsFootView/access$302(Lcom/nd/android/u/news/ui/view/NewsFootView;I)I
pop
aload 0
getfield com/nd/android/u/news/ui/view/NewsFootView$ZanTask/this$0 Lcom/nd/android/u/news/ui/view/NewsFootView;
invokestatic com/nd/android/u/news/ui/view/NewsFootView/access$500(Lcom/nd/android/u/news/ui/view/NewsFootView;)Landroid/widget/TextView;
aload 0
getfield com/nd/android/u/news/ui/view/NewsFootView$ZanTask/this$0 Lcom/nd/android/u/news/ui/view/NewsFootView;
invokestatic com/nd/android/u/news/ui/view/NewsFootView/access$400(Lcom/nd/android/u/news/ui/view/NewsFootView;)Landroid/graphics/drawable/Drawable;
aconst_null
aconst_null
aconst_null
invokevirtual android/widget/TextView/setCompoundDrawablesWithIntrinsicBounds(Landroid/graphics/drawable/Drawable;Landroid/graphics/drawable/Drawable;Landroid/graphics/drawable/Drawable;Landroid/graphics/drawable/Drawable;)V
aload 0
getfield com/nd/android/u/news/ui/view/NewsFootView$ZanTask/this$0 Lcom/nd/android/u/news/ui/view/NewsFootView;
aload 0
getfield com/nd/android/u/news/ui/view/NewsFootView$ZanTask/this$0 Lcom/nd/android/u/news/ui/view/NewsFootView;
invokestatic com/nd/android/u/news/ui/view/NewsFootView/access$500(Lcom/nd/android/u/news/ui/view/NewsFootView;)Landroid/widget/TextView;
aload 0
getfield com/nd/android/u/news/ui/view/NewsFootView$ZanTask/this$0 Lcom/nd/android/u/news/ui/view/NewsFootView;
invokestatic com/nd/android/u/news/ui/view/NewsFootView/access$606(Lcom/nd/android/u/news/ui/view/NewsFootView;)I
invokevirtual com/nd/android/u/news/ui/view/NewsFootView/setText(Landroid/widget/TextView;I)V
aload 0
getfield com/nd/android/u/news/ui/view/NewsFootView$ZanTask/this$0 Lcom/nd/android/u/news/ui/view/NewsFootView;
invokestatic com/nd/android/u/news/ui/view/NewsFootView/access$700(Lcom/nd/android/u/news/ui/view/NewsFootView;)Lcom/nd/android/forumsdk/business/bean/result/NewsInfoBean;
iconst_0
invokevirtual com/nd/android/forumsdk/business/bean/result/NewsInfoBean/setPraised(I)V
aload 0
getfield com/nd/android/u/news/ui/view/NewsFootView$ZanTask/this$0 Lcom/nd/android/u/news/ui/view/NewsFootView;
invokestatic com/nd/android/u/news/ui/view/NewsFootView/access$800(Lcom/nd/android/u/news/ui/view/NewsFootView;)Lcom/nd/android/u/news/ui/view/NewsFootView$OnZanActionListener;
ifnull L3
aload 0
getfield com/nd/android/u/news/ui/view/NewsFootView$ZanTask/this$0 Lcom/nd/android/u/news/ui/view/NewsFootView;
invokestatic com/nd/android/u/news/ui/view/NewsFootView/access$800(Lcom/nd/android/u/news/ui/view/NewsFootView;)Lcom/nd/android/u/news/ui/view/NewsFootView$OnZanActionListener;
invokeinterface com/nd/android/u/news/ui/view/NewsFootView$OnZanActionListener/cancelZan()V 0
L3:
aload 0
getfield com/nd/android/u/news/ui/view/NewsFootView$ZanTask/this$0 Lcom/nd/android/u/news/ui/view/NewsFootView;
invokestatic com/nd/android/u/news/ui/view/NewsFootView/access$700(Lcom/nd/android/u/news/ui/view/NewsFootView;)Lcom/nd/android/forumsdk/business/bean/result/NewsInfoBean;
aload 0
getfield com/nd/android/u/news/ui/view/NewsFootView$ZanTask/this$0 Lcom/nd/android/u/news/ui/view/NewsFootView;
invokestatic com/nd/android/u/news/ui/view/NewsFootView/access$600(Lcom/nd/android/u/news/ui/view/NewsFootView;)I
invokevirtual com/nd/android/forumsdk/business/bean/result/NewsInfoBean/setPraises(I)V
L0:
return
L2:
aload 0
getfield com/nd/android/u/news/ui/view/NewsFootView$ZanTask/this$0 Lcom/nd/android/u/news/ui/view/NewsFootView;
invokestatic com/nd/android/u/news/ui/view/NewsFootView/access$300(Lcom/nd/android/u/news/ui/view/NewsFootView;)I
iconst_1
if_icmpeq L3
aload 0
getfield com/nd/android/u/news/ui/view/NewsFootView$ZanTask/this$0 Lcom/nd/android/u/news/ui/view/NewsFootView;
iconst_1
invokestatic com/nd/android/u/news/ui/view/NewsFootView/access$302(Lcom/nd/android/u/news/ui/view/NewsFootView;I)I
pop
aload 0
getfield com/nd/android/u/news/ui/view/NewsFootView$ZanTask/this$0 Lcom/nd/android/u/news/ui/view/NewsFootView;
invokestatic com/nd/android/u/news/ui/view/NewsFootView/access$500(Lcom/nd/android/u/news/ui/view/NewsFootView;)Landroid/widget/TextView;
aload 0
getfield com/nd/android/u/news/ui/view/NewsFootView$ZanTask/this$0 Lcom/nd/android/u/news/ui/view/NewsFootView;
invokestatic com/nd/android/u/news/ui/view/NewsFootView/access$900(Lcom/nd/android/u/news/ui/view/NewsFootView;)Landroid/graphics/drawable/Drawable;
aconst_null
aconst_null
aconst_null
invokevirtual android/widget/TextView/setCompoundDrawablesWithIntrinsicBounds(Landroid/graphics/drawable/Drawable;Landroid/graphics/drawable/Drawable;Landroid/graphics/drawable/Drawable;Landroid/graphics/drawable/Drawable;)V
aload 0
getfield com/nd/android/u/news/ui/view/NewsFootView$ZanTask/this$0 Lcom/nd/android/u/news/ui/view/NewsFootView;
aload 0
getfield com/nd/android/u/news/ui/view/NewsFootView$ZanTask/this$0 Lcom/nd/android/u/news/ui/view/NewsFootView;
invokestatic com/nd/android/u/news/ui/view/NewsFootView/access$500(Lcom/nd/android/u/news/ui/view/NewsFootView;)Landroid/widget/TextView;
aload 0
getfield com/nd/android/u/news/ui/view/NewsFootView$ZanTask/this$0 Lcom/nd/android/u/news/ui/view/NewsFootView;
invokestatic com/nd/android/u/news/ui/view/NewsFootView/access$604(Lcom/nd/android/u/news/ui/view/NewsFootView;)I
invokevirtual com/nd/android/u/news/ui/view/NewsFootView/setText(Landroid/widget/TextView;I)V
aload 0
getfield com/nd/android/u/news/ui/view/NewsFootView$ZanTask/this$0 Lcom/nd/android/u/news/ui/view/NewsFootView;
invokestatic com/nd/android/u/news/ui/view/NewsFootView/access$700(Lcom/nd/android/u/news/ui/view/NewsFootView;)Lcom/nd/android/forumsdk/business/bean/result/NewsInfoBean;
iconst_1
invokevirtual com/nd/android/forumsdk/business/bean/result/NewsInfoBean/setPraised(I)V
aload 0
getfield com/nd/android/u/news/ui/view/NewsFootView$ZanTask/this$0 Lcom/nd/android/u/news/ui/view/NewsFootView;
invokestatic com/nd/android/u/news/ui/view/NewsFootView/access$800(Lcom/nd/android/u/news/ui/view/NewsFootView;)Lcom/nd/android/u/news/ui/view/NewsFootView$OnZanActionListener;
ifnull L3
aload 0
getfield com/nd/android/u/news/ui/view/NewsFootView$ZanTask/this$0 Lcom/nd/android/u/news/ui/view/NewsFootView;
invokestatic com/nd/android/u/news/ui/view/NewsFootView/access$800(Lcom/nd/android/u/news/ui/view/NewsFootView;)Lcom/nd/android/u/news/ui/view/NewsFootView$OnZanActionListener;
invokeinterface com/nd/android/u/news/ui/view/NewsFootView$OnZanActionListener/zan()V 0
goto L3
L1:
aload 0
getfield com/nd/android/u/news/ui/view/NewsFootView$ZanTask/paramStatus I
aload 0
getfield com/nd/android/u/news/ui/view/NewsFootView$ZanTask/this$0 Lcom/nd/android/u/news/ui/view/NewsFootView;
invokestatic com/nd/android/u/news/ui/view/NewsFootView/access$300(Lcom/nd/android/u/news/ui/view/NewsFootView;)I
if_icmpeq L0
aload 0
getfield com/nd/android/u/news/ui/view/NewsFootView$ZanTask/this$0 Lcom/nd/android/u/news/ui/view/NewsFootView;
invokestatic com/nd/android/u/news/ui/view/NewsFootView/access$300(Lcom/nd/android/u/news/ui/view/NewsFootView;)I
iconst_1
if_icmpne L4
aload 0
getfield com/nd/android/u/news/ui/view/NewsFootView$ZanTask/this$0 Lcom/nd/android/u/news/ui/view/NewsFootView;
new com/nd/android/u/news/ui/view/NewsFootView$ZanTask
dup
aload 0
getfield com/nd/android/u/news/ui/view/NewsFootView$ZanTask/this$0 Lcom/nd/android/u/news/ui/view/NewsFootView;
invokespecial com/nd/android/u/news/ui/view/NewsFootView$ZanTask/<init>(Lcom/nd/android/u/news/ui/view/NewsFootView;)V
invokestatic com/nd/android/u/news/ui/view/NewsFootView/access$1002(Lcom/nd/android/u/news/ui/view/NewsFootView;Lcom/nd/android/u/news/ui/view/NewsFootView$ZanTask;)Lcom/nd/android/u/news/ui/view/NewsFootView$ZanTask;
pop
aload 0
getfield com/nd/android/u/news/ui/view/NewsFootView$ZanTask/this$0 Lcom/nd/android/u/news/ui/view/NewsFootView;
invokestatic com/nd/android/u/news/ui/view/NewsFootView/access$1000(Lcom/nd/android/u/news/ui/view/NewsFootView;)Lcom/nd/android/u/news/ui/view/NewsFootView$ZanTask;
iconst_1
anewarray java/lang/Integer
dup
iconst_0
iconst_1
invokestatic java/lang/Integer/valueOf(I)Ljava/lang/Integer;
aastore
invokevirtual com/nd/android/u/news/ui/view/NewsFootView$ZanTask/execute([Ljava/lang/Object;)Lcom/common/android/utils/concurrent/NdTinyHttpAsyncTask;
pop
return
L4:
aload 0
getfield com/nd/android/u/news/ui/view/NewsFootView$ZanTask/this$0 Lcom/nd/android/u/news/ui/view/NewsFootView;
new com/nd/android/u/news/ui/view/NewsFootView$ZanTask
dup
aload 0
getfield com/nd/android/u/news/ui/view/NewsFootView$ZanTask/this$0 Lcom/nd/android/u/news/ui/view/NewsFootView;
invokespecial com/nd/android/u/news/ui/view/NewsFootView$ZanTask/<init>(Lcom/nd/android/u/news/ui/view/NewsFootView;)V
invokestatic com/nd/android/u/news/ui/view/NewsFootView/access$1002(Lcom/nd/android/u/news/ui/view/NewsFootView;Lcom/nd/android/u/news/ui/view/NewsFootView$ZanTask;)Lcom/nd/android/u/news/ui/view/NewsFootView$ZanTask;
pop
aload 0
getfield com/nd/android/u/news/ui/view/NewsFootView$ZanTask/this$0 Lcom/nd/android/u/news/ui/view/NewsFootView;
invokestatic com/nd/android/u/news/ui/view/NewsFootView/access$1000(Lcom/nd/android/u/news/ui/view/NewsFootView;)Lcom/nd/android/u/news/ui/view/NewsFootView$ZanTask;
iconst_1
anewarray java/lang/Integer
dup
iconst_0
iconst_0
invokestatic java/lang/Integer/valueOf(I)Ljava/lang/Integer;
aastore
invokevirtual com/nd/android/u/news/ui/view/NewsFootView$ZanTask/execute([Ljava/lang/Object;)Lcom/common/android/utils/concurrent/NdTinyHttpAsyncTask;
pop
return
.limit locals 3
.limit stack 5
.end method
