.bytecode 50.0
.class synchronized com/nd/android/u/ui/activity/background_setting/CommonSettingActivity$1
.super java/lang/Object
.implements android/view/View$OnClickListener
.enclosing method com/nd/android/u/ui/activity/background_setting/CommonSettingActivity
.inner class inner com/nd/android/u/ui/activity/background_setting/CommonSettingActivity$1

.field final synthetic 'this$0' Lcom/nd/android/u/ui/activity/background_setting/CommonSettingActivity;

.method <init>(Lcom/nd/android/u/ui/activity/background_setting/CommonSettingActivity;)V
aload 0
aload 1
putfield com/nd/android/u/ui/activity/background_setting/CommonSettingActivity$1/this$0 Lcom/nd/android/u/ui/activity/background_setting/CommonSettingActivity;
aload 0
invokespecial java/lang/Object/<init>()V
return
.limit locals 2
.limit stack 2
.end method

.method public onClick(Landroid/view/View;)V
iconst_0
istore 2
aload 1
invokevirtual android/view/View/getId()I
istore 3
iload 3
getstatic com/nd/android/u/chat/R$id/receive_msg_time_layout I
if_icmpne L0
new android/content/Intent
dup
invokespecial android/content/Intent/<init>()V
astore 1
aload 1
aload 0
getfield com/nd/android/u/ui/activity/background_setting/CommonSettingActivity$1/this$0 Lcom/nd/android/u/ui/activity/background_setting/CommonSettingActivity;
ldc com/nd/android/u/ui/activity/background_setting/ReceiveMsgPeriodActivity
invokevirtual android/content/Intent/setClass(Landroid/content/Context;Ljava/lang/Class;)Landroid/content/Intent;
pop
aload 0
getfield com/nd/android/u/ui/activity/background_setting/CommonSettingActivity$1/this$0 Lcom/nd/android/u/ui/activity/background_setting/CommonSettingActivity;
aload 1
invokevirtual com/nd/android/u/ui/activity/background_setting/CommonSettingActivity/startActivity(Landroid/content/Intent;)V
L1:
invokestatic com/nd/android/u/controller/factory/ChatDaoFactory/getInstance()Lcom/nd/android/u/controller/factory/ChatDaoFactory;
invokevirtual com/nd/android/u/controller/factory/ChatDaoFactory/getCommonSettingConfigDao()Lcom/nd/android/u/business/db/dao/CommonSettingConfigDao;
invokestatic com/nd/android/u/controller/ChatGlobalVariable/getInstance()Lcom/nd/android/u/controller/ChatGlobalVariable;
invokevirtual com/nd/android/u/controller/ChatGlobalVariable/getCommonconfig()Lcom/nd/android/u/controller/bean/CommonSettingConfig;
invokevirtual com/nd/android/u/business/db/dao/CommonSettingConfigDao/insertCommonSettingConfig(Lcom/nd/android/u/controller/bean/CommonSettingConfig;)J
pop2
return
L0:
iload 3
getstatic com/nd/android/u/chat/R$id/new_msg_notification_layout I
if_icmpne L2
aload 0
getfield com/nd/android/u/ui/activity/background_setting/CommonSettingActivity$1/this$0 Lcom/nd/android/u/ui/activity/background_setting/CommonSettingActivity;
invokestatic com/nd/android/u/ui/activity/background_setting/CommonSettingActivity/access$000(Lcom/nd/android/u/ui/activity/background_setting/CommonSettingActivity;)Landroid/widget/ToggleButton;
invokevirtual android/widget/ToggleButton/isChecked()Z
ifeq L3
aload 0
getfield com/nd/android/u/ui/activity/background_setting/CommonSettingActivity$1/this$0 Lcom/nd/android/u/ui/activity/background_setting/CommonSettingActivity;
invokestatic com/nd/android/u/ui/activity/background_setting/CommonSettingActivity/access$000(Lcom/nd/android/u/ui/activity/background_setting/CommonSettingActivity;)Landroid/widget/ToggleButton;
iconst_0
invokevirtual android/widget/ToggleButton/setChecked(Z)V
aload 0
getfield com/nd/android/u/ui/activity/background_setting/CommonSettingActivity$1/this$0 Lcom/nd/android/u/ui/activity/background_setting/CommonSettingActivity;
iconst_0
invokestatic com/nd/android/u/ui/activity/background_setting/CommonSettingActivity/access$100(Lcom/nd/android/u/ui/activity/background_setting/CommonSettingActivity;Z)V
invokestatic com/nd/android/u/controller/ChatGlobalVariable/getInstance()Lcom/nd/android/u/controller/ChatGlobalVariable;
invokevirtual com/nd/android/u/controller/ChatGlobalVariable/getCommonconfig()Lcom/nd/android/u/controller/bean/CommonSettingConfig;
iconst_0
invokevirtual com/nd/android/u/controller/bean/CommonSettingConfig/setNewmsg_notification(I)V
goto L1
L3:
aload 0
getfield com/nd/android/u/ui/activity/background_setting/CommonSettingActivity$1/this$0 Lcom/nd/android/u/ui/activity/background_setting/CommonSettingActivity;
invokestatic com/nd/android/u/ui/activity/background_setting/CommonSettingActivity/access$000(Lcom/nd/android/u/ui/activity/background_setting/CommonSettingActivity;)Landroid/widget/ToggleButton;
iconst_1
invokevirtual android/widget/ToggleButton/setChecked(Z)V
aload 0
getfield com/nd/android/u/ui/activity/background_setting/CommonSettingActivity$1/this$0 Lcom/nd/android/u/ui/activity/background_setting/CommonSettingActivity;
iconst_1
invokestatic com/nd/android/u/ui/activity/background_setting/CommonSettingActivity/access$100(Lcom/nd/android/u/ui/activity/background_setting/CommonSettingActivity;Z)V
invokestatic com/nd/android/u/controller/ChatGlobalVariable/getInstance()Lcom/nd/android/u/controller/ChatGlobalVariable;
invokevirtual com/nd/android/u/controller/ChatGlobalVariable/getCommonconfig()Lcom/nd/android/u/controller/bean/CommonSettingConfig;
iconst_1
invokevirtual com/nd/android/u/controller/bean/CommonSettingConfig/setNewmsg_notification(I)V
goto L1
L2:
iload 3
getstatic com/nd/android/u/chat/R$id/new_msg_notification_cb I
if_icmpne L4
aload 0
getfield com/nd/android/u/ui/activity/background_setting/CommonSettingActivity$1/this$0 Lcom/nd/android/u/ui/activity/background_setting/CommonSettingActivity;
invokestatic com/nd/android/u/ui/activity/background_setting/CommonSettingActivity/access$000(Lcom/nd/android/u/ui/activity/background_setting/CommonSettingActivity;)Landroid/widget/ToggleButton;
invokevirtual android/widget/ToggleButton/isChecked()Z
ifeq L5
aload 0
getfield com/nd/android/u/ui/activity/background_setting/CommonSettingActivity$1/this$0 Lcom/nd/android/u/ui/activity/background_setting/CommonSettingActivity;
iconst_1
invokestatic com/nd/android/u/ui/activity/background_setting/CommonSettingActivity/access$100(Lcom/nd/android/u/ui/activity/background_setting/CommonSettingActivity;Z)V
invokestatic com/nd/android/u/controller/ChatGlobalVariable/getInstance()Lcom/nd/android/u/controller/ChatGlobalVariable;
invokevirtual com/nd/android/u/controller/ChatGlobalVariable/getCommonconfig()Lcom/nd/android/u/controller/bean/CommonSettingConfig;
iconst_1
invokevirtual com/nd/android/u/controller/bean/CommonSettingConfig/setNewmsg_notification(I)V
goto L1
L5:
aload 0
getfield com/nd/android/u/ui/activity/background_setting/CommonSettingActivity$1/this$0 Lcom/nd/android/u/ui/activity/background_setting/CommonSettingActivity;
iconst_0
invokestatic com/nd/android/u/ui/activity/background_setting/CommonSettingActivity/access$100(Lcom/nd/android/u/ui/activity/background_setting/CommonSettingActivity;Z)V
invokestatic com/nd/android/u/controller/ChatGlobalVariable/getInstance()Lcom/nd/android/u/controller/ChatGlobalVariable;
invokevirtual com/nd/android/u/controller/ChatGlobalVariable/getCommonconfig()Lcom/nd/android/u/controller/bean/CommonSettingConfig;
iconst_0
invokevirtual com/nd/android/u/controller/bean/CommonSettingConfig/setNewmsg_notification(I)V
goto L1
L4:
iload 3
getstatic com/nd/android/u/chat/R$id/sound_layout I
if_icmpne L6
aload 0
getfield com/nd/android/u/ui/activity/background_setting/CommonSettingActivity$1/this$0 Lcom/nd/android/u/ui/activity/background_setting/CommonSettingActivity;
invokestatic com/nd/android/u/ui/activity/background_setting/CommonSettingActivity/access$200(Lcom/nd/android/u/ui/activity/background_setting/CommonSettingActivity;)Landroid/widget/ToggleButton;
invokevirtual android/widget/ToggleButton/isChecked()Z
ifeq L7
aload 0
getfield com/nd/android/u/ui/activity/background_setting/CommonSettingActivity$1/this$0 Lcom/nd/android/u/ui/activity/background_setting/CommonSettingActivity;
invokestatic com/nd/android/u/ui/activity/background_setting/CommonSettingActivity/access$200(Lcom/nd/android/u/ui/activity/background_setting/CommonSettingActivity;)Landroid/widget/ToggleButton;
iconst_0
invokevirtual android/widget/ToggleButton/setChecked(Z)V
invokestatic com/nd/android/u/controller/ChatGlobalVariable/getInstance()Lcom/nd/android/u/controller/ChatGlobalVariable;
invokevirtual com/nd/android/u/controller/ChatGlobalVariable/getCommonconfig()Lcom/nd/android/u/controller/bean/CommonSettingConfig;
iconst_0
invokevirtual com/nd/android/u/controller/bean/CommonSettingConfig/setSilent(I)V
goto L1
L7:
aload 0
getfield com/nd/android/u/ui/activity/background_setting/CommonSettingActivity$1/this$0 Lcom/nd/android/u/ui/activity/background_setting/CommonSettingActivity;
invokestatic com/nd/android/u/ui/activity/background_setting/CommonSettingActivity/access$200(Lcom/nd/android/u/ui/activity/background_setting/CommonSettingActivity;)Landroid/widget/ToggleButton;
iconst_1
invokevirtual android/widget/ToggleButton/setChecked(Z)V
invokestatic com/nd/android/u/controller/ChatGlobalVariable/getInstance()Lcom/nd/android/u/controller/ChatGlobalVariable;
invokevirtual com/nd/android/u/controller/ChatGlobalVariable/getCommonconfig()Lcom/nd/android/u/controller/bean/CommonSettingConfig;
iconst_1
invokevirtual com/nd/android/u/controller/bean/CommonSettingConfig/setSilent(I)V
goto L1
L6:
iload 3
getstatic com/nd/android/u/chat/R$id/sound_cb I
if_icmpne L8
aload 0
getfield com/nd/android/u/ui/activity/background_setting/CommonSettingActivity$1/this$0 Lcom/nd/android/u/ui/activity/background_setting/CommonSettingActivity;
invokestatic com/nd/android/u/ui/activity/background_setting/CommonSettingActivity/access$200(Lcom/nd/android/u/ui/activity/background_setting/CommonSettingActivity;)Landroid/widget/ToggleButton;
invokevirtual android/widget/ToggleButton/isChecked()Z
ifeq L9
invokestatic com/nd/android/u/controller/ChatGlobalVariable/getInstance()Lcom/nd/android/u/controller/ChatGlobalVariable;
invokevirtual com/nd/android/u/controller/ChatGlobalVariable/getCommonconfig()Lcom/nd/android/u/controller/bean/CommonSettingConfig;
iconst_1
invokevirtual com/nd/android/u/controller/bean/CommonSettingConfig/setSilent(I)V
goto L1
L9:
invokestatic com/nd/android/u/controller/ChatGlobalVariable/getInstance()Lcom/nd/android/u/controller/ChatGlobalVariable;
invokevirtual com/nd/android/u/controller/ChatGlobalVariable/getCommonconfig()Lcom/nd/android/u/controller/bean/CommonSettingConfig;
iconst_0
invokevirtual com/nd/android/u/controller/bean/CommonSettingConfig/setSilent(I)V
goto L1
L8:
iload 3
getstatic com/nd/android/u/chat/R$id/touchVibrate_layout I
if_icmpne L10
aload 0
getfield com/nd/android/u/ui/activity/background_setting/CommonSettingActivity$1/this$0 Lcom/nd/android/u/ui/activity/background_setting/CommonSettingActivity;
invokestatic com/nd/android/u/ui/activity/background_setting/CommonSettingActivity/access$300(Lcom/nd/android/u/ui/activity/background_setting/CommonSettingActivity;)Landroid/widget/ToggleButton;
invokevirtual android/widget/ToggleButton/isChecked()Z
ifeq L11
aload 0
getfield com/nd/android/u/ui/activity/background_setting/CommonSettingActivity$1/this$0 Lcom/nd/android/u/ui/activity/background_setting/CommonSettingActivity;
invokestatic com/nd/android/u/ui/activity/background_setting/CommonSettingActivity/access$300(Lcom/nd/android/u/ui/activity/background_setting/CommonSettingActivity;)Landroid/widget/ToggleButton;
iconst_0
invokevirtual android/widget/ToggleButton/setChecked(Z)V
invokestatic com/nd/android/u/controller/ChatGlobalVariable/getInstance()Lcom/nd/android/u/controller/ChatGlobalVariable;
invokevirtual com/nd/android/u/controller/ChatGlobalVariable/getCommonconfig()Lcom/nd/android/u/controller/bean/CommonSettingConfig;
iconst_0
invokevirtual com/nd/android/u/controller/bean/CommonSettingConfig/setTouchVibrate(I)V
goto L1
L11:
aload 0
getfield com/nd/android/u/ui/activity/background_setting/CommonSettingActivity$1/this$0 Lcom/nd/android/u/ui/activity/background_setting/CommonSettingActivity;
invokestatic com/nd/android/u/ui/activity/background_setting/CommonSettingActivity/access$300(Lcom/nd/android/u/ui/activity/background_setting/CommonSettingActivity;)Landroid/widget/ToggleButton;
iconst_1
invokevirtual android/widget/ToggleButton/setChecked(Z)V
invokestatic com/nd/android/u/controller/ChatGlobalVariable/getInstance()Lcom/nd/android/u/controller/ChatGlobalVariable;
invokevirtual com/nd/android/u/controller/ChatGlobalVariable/getCommonconfig()Lcom/nd/android/u/controller/bean/CommonSettingConfig;
iconst_1
invokevirtual com/nd/android/u/controller/bean/CommonSettingConfig/setTouchVibrate(I)V
goto L1
L10:
iload 3
getstatic com/nd/android/u/chat/R$id/touchVibrate_cb I
if_icmpne L12
aload 0
getfield com/nd/android/u/ui/activity/background_setting/CommonSettingActivity$1/this$0 Lcom/nd/android/u/ui/activity/background_setting/CommonSettingActivity;
invokestatic com/nd/android/u/ui/activity/background_setting/CommonSettingActivity/access$300(Lcom/nd/android/u/ui/activity/background_setting/CommonSettingActivity;)Landroid/widget/ToggleButton;
invokevirtual android/widget/ToggleButton/isChecked()Z
ifeq L13
invokestatic com/nd/android/u/controller/ChatGlobalVariable/getInstance()Lcom/nd/android/u/controller/ChatGlobalVariable;
invokevirtual com/nd/android/u/controller/ChatGlobalVariable/getCommonconfig()Lcom/nd/android/u/controller/bean/CommonSettingConfig;
iconst_1
invokevirtual com/nd/android/u/controller/bean/CommonSettingConfig/setTouchVibrate(I)V
goto L1
L13:
invokestatic com/nd/android/u/controller/ChatGlobalVariable/getInstance()Lcom/nd/android/u/controller/ChatGlobalVariable;
invokevirtual com/nd/android/u/controller/ChatGlobalVariable/getCommonconfig()Lcom/nd/android/u/controller/bean/CommonSettingConfig;
iconst_0
invokevirtual com/nd/android/u/controller/bean/CommonSettingConfig/setTouchVibrate(I)V
goto L1
L12:
iload 3
getstatic com/nd/android/u/chat/R$id/group_msg_layout I
if_icmpne L14
getstatic com/nd/android/u/ChatEntry/INSTANCE Lcom/nd/android/u/ChatEntry;
getfield com/nd/android/u/ChatEntry/chatCallOtherModel_UI Lcom/nd/android/u/ui/chatInterfaceImpl/IChatCallOtherModel_UI;
aload 0
getfield com/nd/android/u/ui/activity/background_setting/CommonSettingActivity$1/this$0 Lcom/nd/android/u/ui/activity/background_setting/CommonSettingActivity;
aload 0
getfield com/nd/android/u/ui/activity/background_setting/CommonSettingActivity$1/this$0 Lcom/nd/android/u/ui/activity/background_setting/CommonSettingActivity;
invokestatic com/nd/android/u/ui/activity/background_setting/CommonSettingActivity/access$400(Lcom/nd/android/u/ui/activity/background_setting/CommonSettingActivity;)I
aload 0
getfield com/nd/android/u/ui/activity/background_setting/CommonSettingActivity$1/this$0 Lcom/nd/android/u/ui/activity/background_setting/CommonSettingActivity;
invokestatic com/nd/android/u/ui/activity/background_setting/CommonSettingActivity/access$500(Lcom/nd/android/u/ui/activity/background_setting/CommonSettingActivity;)Lcom/product/android/commonInterface/chat/IGroupReceiveSettingListener;
invokeinterface com/nd/android/u/ui/chatInterfaceImpl/IChatCallOtherModel_UI/showGroupMessageReceiveSettingDialog(Landroid/content/Context;ILcom/product/android/commonInterface/chat/IGroupReceiveSettingListener;)V 3
goto L1
L14:
iload 3
getstatic com/nd/android/u/chat/R$id/popup_reminder_layout I
if_icmpne L15
aload 0
getfield com/nd/android/u/ui/activity/background_setting/CommonSettingActivity$1/this$0 Lcom/nd/android/u/ui/activity/background_setting/CommonSettingActivity;
invokestatic com/nd/android/u/ui/activity/background_setting/CommonSettingActivity/access$600(Lcom/nd/android/u/ui/activity/background_setting/CommonSettingActivity;)Landroid/widget/ToggleButton;
invokevirtual android/widget/ToggleButton/isChecked()Z
ifeq L16
aload 0
getfield com/nd/android/u/ui/activity/background_setting/CommonSettingActivity$1/this$0 Lcom/nd/android/u/ui/activity/background_setting/CommonSettingActivity;
invokestatic com/nd/android/u/ui/activity/background_setting/CommonSettingActivity/access$600(Lcom/nd/android/u/ui/activity/background_setting/CommonSettingActivity;)Landroid/widget/ToggleButton;
iconst_0
invokevirtual android/widget/ToggleButton/setChecked(Z)V
invokestatic com/nd/android/u/controller/ChatGlobalVariable/getInstance()Lcom/nd/android/u/controller/ChatGlobalVariable;
invokevirtual com/nd/android/u/controller/ChatGlobalVariable/getCommonconfig()Lcom/nd/android/u/controller/bean/CommonSettingConfig;
iconst_0
invokevirtual com/nd/android/u/controller/bean/CommonSettingConfig/setPopup_reminder(I)V
goto L1
L16:
aload 0
getfield com/nd/android/u/ui/activity/background_setting/CommonSettingActivity$1/this$0 Lcom/nd/android/u/ui/activity/background_setting/CommonSettingActivity;
invokestatic com/nd/android/u/ui/activity/background_setting/CommonSettingActivity/access$600(Lcom/nd/android/u/ui/activity/background_setting/CommonSettingActivity;)Landroid/widget/ToggleButton;
iconst_1
invokevirtual android/widget/ToggleButton/setChecked(Z)V
invokestatic com/nd/android/u/controller/ChatGlobalVariable/getInstance()Lcom/nd/android/u/controller/ChatGlobalVariable;
invokevirtual com/nd/android/u/controller/ChatGlobalVariable/getCommonconfig()Lcom/nd/android/u/controller/bean/CommonSettingConfig;
iconst_1
invokevirtual com/nd/android/u/controller/bean/CommonSettingConfig/setPopup_reminder(I)V
goto L1
L15:
iload 3
getstatic com/nd/android/u/chat/R$id/popup_reminder_cb I
if_icmpne L17
aload 0
getfield com/nd/android/u/ui/activity/background_setting/CommonSettingActivity$1/this$0 Lcom/nd/android/u/ui/activity/background_setting/CommonSettingActivity;
invokestatic com/nd/android/u/ui/activity/background_setting/CommonSettingActivity/access$600(Lcom/nd/android/u/ui/activity/background_setting/CommonSettingActivity;)Landroid/widget/ToggleButton;
invokevirtual android/widget/ToggleButton/isChecked()Z
ifeq L18
invokestatic com/nd/android/u/controller/ChatGlobalVariable/getInstance()Lcom/nd/android/u/controller/ChatGlobalVariable;
invokevirtual com/nd/android/u/controller/ChatGlobalVariable/getCommonconfig()Lcom/nd/android/u/controller/bean/CommonSettingConfig;
iconst_1
invokevirtual com/nd/android/u/controller/bean/CommonSettingConfig/setPopup_reminder(I)V
goto L1
L18:
invokestatic com/nd/android/u/controller/ChatGlobalVariable/getInstance()Lcom/nd/android/u/controller/ChatGlobalVariable;
invokevirtual com/nd/android/u/controller/ChatGlobalVariable/getCommonconfig()Lcom/nd/android/u/controller/bean/CommonSettingConfig;
iconst_0
invokevirtual com/nd/android/u/controller/bean/CommonSettingConfig/setPopup_reminder(I)V
goto L1
L17:
iload 3
getstatic com/nd/android/u/chat/R$id/light_reminder_cb I
if_icmpne L19
aload 0
getfield com/nd/android/u/ui/activity/background_setting/CommonSettingActivity$1/this$0 Lcom/nd/android/u/ui/activity/background_setting/CommonSettingActivity;
invokestatic com/nd/android/u/ui/activity/background_setting/CommonSettingActivity/access$700(Lcom/nd/android/u/ui/activity/background_setting/CommonSettingActivity;)Landroid/widget/ToggleButton;
invokevirtual android/widget/ToggleButton/isChecked()Z
istore 4
iload 4
ifne L20
invokestatic com/nd/android/u/commonWidget/NotificationMsg/getInstance()Lcom/nd/android/u/commonWidget/NotificationMsg;
invokevirtual com/nd/android/u/commonWidget/NotificationMsg/cancelLigthNotify()V
L20:
invokestatic com/nd/android/u/controller/ChatGlobalVariable/getInstance()Lcom/nd/android/u/controller/ChatGlobalVariable;
invokevirtual com/nd/android/u/controller/ChatGlobalVariable/getCommonconfig()Lcom/nd/android/u/controller/bean/CommonSettingConfig;
astore 1
iload 4
ifeq L21
L22:
aload 1
iload 2
invokevirtual com/nd/android/u/controller/bean/CommonSettingConfig/setLightReminder(I)V
goto L1
L21:
iconst_1
istore 2
goto L22
L19:
iload 3
getstatic com/nd/android/u/chat/R$id/lightReminder I
if_icmpne L23
aload 0
getfield com/nd/android/u/ui/activity/background_setting/CommonSettingActivity$1/this$0 Lcom/nd/android/u/ui/activity/background_setting/CommonSettingActivity;
invokestatic com/nd/android/u/ui/activity/background_setting/CommonSettingActivity/access$700(Lcom/nd/android/u/ui/activity/background_setting/CommonSettingActivity;)Landroid/widget/ToggleButton;
invokevirtual android/widget/ToggleButton/performClick()Z
pop
goto L1
L23:
iload 3
getstatic com/nd/android/u/chat/R$id/clearChatRecord I
if_icmpne L1
getstatic com/nd/android/u/business/db/dao/RecentContactRecords/INSTANCE Lcom/nd/android/u/business/db/dao/RecentContactRecords;
invokevirtual com/nd/android/u/business/db/dao/RecentContactRecords/deleteAll()V
aload 0
getfield com/nd/android/u/ui/activity/background_setting/CommonSettingActivity$1/this$0 Lcom/nd/android/u/ui/activity/background_setting/CommonSettingActivity;
ldc "\u6700\u8fd1\u804a\u5929\u8bb0\u5f55\u6e05\u7406\u6210\u529f"
iconst_0
invokestatic android/widget/Toast/makeText(Landroid/content/Context;Ljava/lang/CharSequence;I)Landroid/widget/Toast;
invokevirtual android/widget/Toast/show()V
sipush 1000
bipush 30
aconst_null
invokestatic com/nd/android/u/chatUiUtils/SendMessageUtil/notifyOtherMessage(IILjava/lang/Object;)V
goto L1
.limit locals 5
.limit stack 4
.end method
