.bytecode 50.0
.class synchronized com/nd/android/u/ui/activity/background_setting/ReceiveMsgPeriodActivity$1
.super java/lang/Object
.implements android/view/View$OnClickListener
.enclosing method com/nd/android/u/ui/activity/background_setting/ReceiveMsgPeriodActivity/initEvent()V
.inner class inner com/nd/android/u/ui/activity/background_setting/ReceiveMsgPeriodActivity$1
.inner class inner com/nd/android/u/ui/activity/background_setting/ReceiveMsgPeriodActivity$1$1

.field final synthetic 'this$0' Lcom/nd/android/u/ui/activity/background_setting/ReceiveMsgPeriodActivity;

.method <init>(Lcom/nd/android/u/ui/activity/background_setting/ReceiveMsgPeriodActivity;)V
aload 0
aload 1
putfield com/nd/android/u/ui/activity/background_setting/ReceiveMsgPeriodActivity$1/this$0 Lcom/nd/android/u/ui/activity/background_setting/ReceiveMsgPeriodActivity;
aload 0
invokespecial java/lang/Object/<init>()V
return
.limit locals 2
.limit stack 2
.end method

.method public onClick(Landroid/view/View;)V
aload 0
getfield com/nd/android/u/ui/activity/background_setting/ReceiveMsgPeriodActivity$1/this$0 Lcom/nd/android/u/ui/activity/background_setting/ReceiveMsgPeriodActivity;
getfield com/nd/android/u/ui/activity/background_setting/ReceiveMsgPeriodActivity/c Ljava/util/Calendar;
bipush 11
invokevirtual java/util/Calendar/get(I)I
istore 2
aload 0
getfield com/nd/android/u/ui/activity/background_setting/ReceiveMsgPeriodActivity$1/this$0 Lcom/nd/android/u/ui/activity/background_setting/ReceiveMsgPeriodActivity;
getfield com/nd/android/u/ui/activity/background_setting/ReceiveMsgPeriodActivity/c Ljava/util/Calendar;
bipush 12
invokevirtual java/util/Calendar/get(I)I
istore 3
aload 0
getfield com/nd/android/u/ui/activity/background_setting/ReceiveMsgPeriodActivity$1/this$0 Lcom/nd/android/u/ui/activity/background_setting/ReceiveMsgPeriodActivity;
invokestatic com/nd/android/u/ui/activity/background_setting/ReceiveMsgPeriodActivity/access$000(Lcom/nd/android/u/ui/activity/background_setting/ReceiveMsgPeriodActivity;)Landroid/widget/TextView;
invokevirtual android/widget/TextView/getText()Ljava/lang/CharSequence;
invokeinterface java/lang/CharSequence/toString()Ljava/lang/String; 0
invokestatic com/common/android/utils/StringUtils/isEmpty(Ljava/lang/String;)Z
ifne L0
aload 0
getfield com/nd/android/u/ui/activity/background_setting/ReceiveMsgPeriodActivity$1/this$0 Lcom/nd/android/u/ui/activity/background_setting/ReceiveMsgPeriodActivity;
invokestatic com/nd/android/u/ui/activity/background_setting/ReceiveMsgPeriodActivity/access$000(Lcom/nd/android/u/ui/activity/background_setting/ReceiveMsgPeriodActivity;)Landroid/widget/TextView;
invokevirtual android/widget/TextView/getText()Ljava/lang/CharSequence;
invokeinterface java/lang/CharSequence/toString()Ljava/lang/String; 0
ldc " "
invokevirtual java/lang/String/split(Ljava/lang/String;)[Ljava/lang/String;
astore 1
aload 1
iconst_0
aaload
ldc ":"
invokevirtual java/lang/String/split(Ljava/lang/String;)[Ljava/lang/String;
astore 6
aload 6
iconst_0
aaload
invokestatic com/common/android/utils/FormatUtils/parseInt(Ljava/lang/String;)I
istore 5
aload 6
iconst_1
aaload
invokestatic com/common/android/utils/FormatUtils/parseInt(Ljava/lang/String;)I
istore 4
aload 1
iconst_1
aaload
ldc "AM"
invokevirtual java/lang/String/equals(Ljava/lang/Object;)Z
ifeq L1
iload 5
istore 2
iload 4
istore 3
iload 5
bipush 12
if_icmpne L0
iconst_0
istore 2
iload 4
istore 3
L0:
new android/app/TimePickerDialog
dup
aload 0
getfield com/nd/android/u/ui/activity/background_setting/ReceiveMsgPeriodActivity$1/this$0 Lcom/nd/android/u/ui/activity/background_setting/ReceiveMsgPeriodActivity;
new com/nd/android/u/ui/activity/background_setting/ReceiveMsgPeriodActivity$1$1
dup
aload 0
invokespecial com/nd/android/u/ui/activity/background_setting/ReceiveMsgPeriodActivity$1$1/<init>(Lcom/nd/android/u/ui/activity/background_setting/ReceiveMsgPeriodActivity$1;)V
iload 2
iload 3
iconst_0
invokespecial android/app/TimePickerDialog/<init>(Landroid/content/Context;Landroid/app/TimePickerDialog$OnTimeSetListener;IIZ)V
invokevirtual android/app/TimePickerDialog/show()V
return
L1:
iload 5
istore 2
iload 4
istore 3
iload 5
bipush 12
if_icmpeq L0
iload 5
bipush 12
iadd
istore 2
iload 4
istore 3
goto L0
.limit locals 7
.limit stack 7
.end method
