.bytecode 50.0
.class synchronized com/nd/android/u/ui/activity/background_setting/ReceiveMsgPeriodActivity$3
.super java/lang/Object
.implements android/view/View$OnClickListener
.enclosing method com/nd/android/u/ui/activity/background_setting/ReceiveMsgPeriodActivity
.inner class inner com/nd/android/u/ui/activity/background_setting/ReceiveMsgPeriodActivity$3

.field final synthetic 'this$0' Lcom/nd/android/u/ui/activity/background_setting/ReceiveMsgPeriodActivity;

.method <init>(Lcom/nd/android/u/ui/activity/background_setting/ReceiveMsgPeriodActivity;)V
aload 0
aload 1
putfield com/nd/android/u/ui/activity/background_setting/ReceiveMsgPeriodActivity$3/this$0 Lcom/nd/android/u/ui/activity/background_setting/ReceiveMsgPeriodActivity;
aload 0
invokespecial java/lang/Object/<init>()V
return
.limit locals 2
.limit stack 2
.end method

.method public onClick(Landroid/view/View;)V
aload 1
invokevirtual android/view/View/getId()I
istore 2
iload 2
getstatic com/nd/android/u/chat/R$id/rec_msg_backgroup_ly I
if_icmpne L0
aload 0
getfield com/nd/android/u/ui/activity/background_setting/ReceiveMsgPeriodActivity$3/this$0 Lcom/nd/android/u/ui/activity/background_setting/ReceiveMsgPeriodActivity;
invokestatic com/nd/android/u/ui/activity/background_setting/ReceiveMsgPeriodActivity/access$200(Lcom/nd/android/u/ui/activity/background_setting/ReceiveMsgPeriodActivity;)Landroid/widget/CheckBox;
invokevirtual android/widget/CheckBox/isChecked()Z
ifeq L1
aload 0
getfield com/nd/android/u/ui/activity/background_setting/ReceiveMsgPeriodActivity$3/this$0 Lcom/nd/android/u/ui/activity/background_setting/ReceiveMsgPeriodActivity;
invokestatic com/nd/android/u/ui/activity/background_setting/ReceiveMsgPeriodActivity/access$200(Lcom/nd/android/u/ui/activity/background_setting/ReceiveMsgPeriodActivity;)Landroid/widget/CheckBox;
iconst_0
invokevirtual android/widget/CheckBox/setChecked(Z)V
aload 0
getfield com/nd/android/u/ui/activity/background_setting/ReceiveMsgPeriodActivity$3/this$0 Lcom/nd/android/u/ui/activity/background_setting/ReceiveMsgPeriodActivity;
iconst_1
invokestatic com/nd/android/u/ui/activity/background_setting/ReceiveMsgPeriodActivity/access$300(Lcom/nd/android/u/ui/activity/background_setting/ReceiveMsgPeriodActivity;Z)V
invokestatic com/nd/android/u/controller/ChatGlobalVariable/getInstance()Lcom/nd/android/u/controller/ChatGlobalVariable;
invokevirtual com/nd/android/u/controller/ChatGlobalVariable/getCommonconfig()Lcom/nd/android/u/controller/bean/CommonSettingConfig;
iconst_0
invokevirtual com/nd/android/u/controller/bean/CommonSettingConfig/setRecmsg_background(I)V
L2:
invokestatic com/nd/android/u/controller/factory/ChatDaoFactory/getInstance()Lcom/nd/android/u/controller/factory/ChatDaoFactory;
invokevirtual com/nd/android/u/controller/factory/ChatDaoFactory/getCommonSettingConfigDao()Lcom/nd/android/u/business/db/dao/CommonSettingConfigDao;
invokestatic com/nd/android/u/controller/ChatGlobalVariable/getInstance()Lcom/nd/android/u/controller/ChatGlobalVariable;
invokevirtual com/nd/android/u/controller/ChatGlobalVariable/getCommonconfig()Lcom/nd/android/u/controller/bean/CommonSettingConfig;
invokevirtual com/nd/android/u/business/db/dao/CommonSettingConfigDao/insertCommonSettingConfig(Lcom/nd/android/u/controller/bean/CommonSettingConfig;)J
pop2
return
L1:
aload 0
getfield com/nd/android/u/ui/activity/background_setting/ReceiveMsgPeriodActivity$3/this$0 Lcom/nd/android/u/ui/activity/background_setting/ReceiveMsgPeriodActivity;
invokestatic com/nd/android/u/ui/activity/background_setting/ReceiveMsgPeriodActivity/access$200(Lcom/nd/android/u/ui/activity/background_setting/ReceiveMsgPeriodActivity;)Landroid/widget/CheckBox;
iconst_1
invokevirtual android/widget/CheckBox/setChecked(Z)V
aload 0
getfield com/nd/android/u/ui/activity/background_setting/ReceiveMsgPeriodActivity$3/this$0 Lcom/nd/android/u/ui/activity/background_setting/ReceiveMsgPeriodActivity;
iconst_0
invokestatic com/nd/android/u/ui/activity/background_setting/ReceiveMsgPeriodActivity/access$300(Lcom/nd/android/u/ui/activity/background_setting/ReceiveMsgPeriodActivity;Z)V
invokestatic com/nd/android/u/controller/ChatGlobalVariable/getInstance()Lcom/nd/android/u/controller/ChatGlobalVariable;
invokevirtual com/nd/android/u/controller/ChatGlobalVariable/getCommonconfig()Lcom/nd/android/u/controller/bean/CommonSettingConfig;
iconst_1
invokevirtual com/nd/android/u/controller/bean/CommonSettingConfig/setRecmsg_background(I)V
goto L2
L0:
iload 2
getstatic com/nd/android/u/chat/R$id/rec_msg_backgroup_cb I
if_icmpne L2
aload 0
getfield com/nd/android/u/ui/activity/background_setting/ReceiveMsgPeriodActivity$3/this$0 Lcom/nd/android/u/ui/activity/background_setting/ReceiveMsgPeriodActivity;
invokestatic com/nd/android/u/ui/activity/background_setting/ReceiveMsgPeriodActivity/access$200(Lcom/nd/android/u/ui/activity/background_setting/ReceiveMsgPeriodActivity;)Landroid/widget/CheckBox;
invokevirtual android/widget/CheckBox/isChecked()Z
ifeq L3
aload 0
getfield com/nd/android/u/ui/activity/background_setting/ReceiveMsgPeriodActivity$3/this$0 Lcom/nd/android/u/ui/activity/background_setting/ReceiveMsgPeriodActivity;
iconst_0
invokestatic com/nd/android/u/ui/activity/background_setting/ReceiveMsgPeriodActivity/access$300(Lcom/nd/android/u/ui/activity/background_setting/ReceiveMsgPeriodActivity;Z)V
invokestatic com/nd/android/u/controller/ChatGlobalVariable/getInstance()Lcom/nd/android/u/controller/ChatGlobalVariable;
invokevirtual com/nd/android/u/controller/ChatGlobalVariable/getCommonconfig()Lcom/nd/android/u/controller/bean/CommonSettingConfig;
iconst_1
invokevirtual com/nd/android/u/controller/bean/CommonSettingConfig/setRecmsg_background(I)V
goto L2
L3:
aload 0
getfield com/nd/android/u/ui/activity/background_setting/ReceiveMsgPeriodActivity$3/this$0 Lcom/nd/android/u/ui/activity/background_setting/ReceiveMsgPeriodActivity;
iconst_1
invokestatic com/nd/android/u/ui/activity/background_setting/ReceiveMsgPeriodActivity/access$300(Lcom/nd/android/u/ui/activity/background_setting/ReceiveMsgPeriodActivity;Z)V
invokestatic com/nd/android/u/controller/ChatGlobalVariable/getInstance()Lcom/nd/android/u/controller/ChatGlobalVariable;
invokevirtual com/nd/android/u/controller/ChatGlobalVariable/getCommonconfig()Lcom/nd/android/u/controller/bean/CommonSettingConfig;
iconst_0
invokevirtual com/nd/android/u/controller/bean/CommonSettingConfig/setRecmsg_background(I)V
goto L2
.limit locals 3
.limit stack 2
.end method
