.bytecode 50.0
.class synchronized com/nd/android/u/cloud/view/widge/DropDownPopWindow$DropDownAdapter
.super android/widget/BaseAdapter
.inner class DropDownAdapter inner com/nd/android/u/cloud/view/widge/DropDownPopWindow$DropDownAdapter outer com/nd/android/u/cloud/view/widge/DropDownPopWindow
.inner class Holder inner com/nd/android/u/cloud/view/widge/DropDownPopWindow$DropDownAdapter$Holder outer com/nd/android/u/cloud/view/widge/DropDownPopWindow$DropDownAdapter

.field final synthetic 'this$0' Lcom/nd/android/u/cloud/view/widge/DropDownPopWindow;

.method <init>(Lcom/nd/android/u/cloud/view/widge/DropDownPopWindow;)V
aload 0
aload 1
putfield com/nd/android/u/cloud/view/widge/DropDownPopWindow$DropDownAdapter/this$0 Lcom/nd/android/u/cloud/view/widge/DropDownPopWindow;
aload 0
invokespecial android/widget/BaseAdapter/<init>()V
return
.limit locals 2
.limit stack 2
.end method

.method public getCount()I
aload 0
getfield com/nd/android/u/cloud/view/widge/DropDownPopWindow$DropDownAdapter/this$0 Lcom/nd/android/u/cloud/view/widge/DropDownPopWindow;
invokestatic com/nd/android/u/cloud/view/widge/DropDownPopWindow/access$000(Lcom/nd/android/u/cloud/view/widge/DropDownPopWindow;)Ljava/util/ArrayList;
ifnonnull L0
iconst_0
ireturn
L0:
aload 0
getfield com/nd/android/u/cloud/view/widge/DropDownPopWindow$DropDownAdapter/this$0 Lcom/nd/android/u/cloud/view/widge/DropDownPopWindow;
invokestatic com/nd/android/u/cloud/view/widge/DropDownPopWindow/access$000(Lcom/nd/android/u/cloud/view/widge/DropDownPopWindow;)Ljava/util/ArrayList;
invokevirtual java/util/ArrayList/size()I
ireturn
.limit locals 1
.limit stack 1
.end method

.method public getItem(I)Ljava/lang/Object;
aconst_null
areturn
.limit locals 2
.limit stack 1
.end method

.method public getItemId(I)J
lconst_0
lreturn
.limit locals 2
.limit stack 2
.end method

.method public getView(ILandroid/view/View;Landroid/view/ViewGroup;)Landroid/view/View;
aload 2
ifnonnull L0
new com/nd/android/u/cloud/view/widge/DropDownPopWindow$DropDownAdapter$Holder
dup
aload 0
invokespecial com/nd/android/u/cloud/view/widge/DropDownPopWindow$DropDownAdapter$Holder/<init>(Lcom/nd/android/u/cloud/view/widge/DropDownPopWindow$DropDownAdapter;)V
astore 3
aload 0
getfield com/nd/android/u/cloud/view/widge/DropDownPopWindow$DropDownAdapter/this$0 Lcom/nd/android/u/cloud/view/widge/DropDownPopWindow;
invokestatic com/nd/android/u/cloud/view/widge/DropDownPopWindow/access$100(Lcom/nd/android/u/cloud/view/widge/DropDownPopWindow;)Landroid/content/Context;
invokestatic android/view/LayoutInflater/from(Landroid/content/Context;)Landroid/view/LayoutInflater;
ldc_w 2130903304
aconst_null
invokevirtual android/view/LayoutInflater/inflate(ILandroid/view/ViewGroup;)Landroid/view/View;
astore 2
aload 3
aload 2
ldc_w 2131625244
invokevirtual android/view/View/findViewById(I)Landroid/view/View;
checkcast android/widget/TextView
putfield com/nd/android/u/cloud/view/widge/DropDownPopWindow$DropDownAdapter$Holder/textView Landroid/widget/TextView;
aload 3
aload 2
ldc_w 2131625243
invokevirtual android/view/View/findViewById(I)Landroid/view/View;
checkcast android/widget/ImageView
putfield com/nd/android/u/cloud/view/widge/DropDownPopWindow$DropDownAdapter$Holder/imageView Landroid/widget/ImageView;
aload 2
aload 3
invokevirtual android/view/View/setTag(Ljava/lang/Object;)V
L1:
aload 0
getfield com/nd/android/u/cloud/view/widge/DropDownPopWindow$DropDownAdapter/this$0 Lcom/nd/android/u/cloud/view/widge/DropDownPopWindow;
invokestatic com/nd/android/u/cloud/view/widge/DropDownPopWindow/access$000(Lcom/nd/android/u/cloud/view/widge/DropDownPopWindow;)Ljava/util/ArrayList;
ifnull L2
iload 1
aload 0
getfield com/nd/android/u/cloud/view/widge/DropDownPopWindow$DropDownAdapter/this$0 Lcom/nd/android/u/cloud/view/widge/DropDownPopWindow;
invokestatic com/nd/android/u/cloud/view/widge/DropDownPopWindow/access$000(Lcom/nd/android/u/cloud/view/widge/DropDownPopWindow;)Ljava/util/ArrayList;
invokevirtual java/util/ArrayList/size()I
if_icmpge L2
aload 3
getfield com/nd/android/u/cloud/view/widge/DropDownPopWindow$DropDownAdapter$Holder/textView Landroid/widget/TextView;
aload 0
getfield com/nd/android/u/cloud/view/widge/DropDownPopWindow$DropDownAdapter/this$0 Lcom/nd/android/u/cloud/view/widge/DropDownPopWindow;
invokestatic com/nd/android/u/cloud/view/widge/DropDownPopWindow/access$000(Lcom/nd/android/u/cloud/view/widge/DropDownPopWindow;)Ljava/util/ArrayList;
iload 1
invokevirtual java/util/ArrayList/get(I)Ljava/lang/Object;
checkcast java/lang/CharSequence
invokevirtual android/widget/TextView/setText(Ljava/lang/CharSequence;)V
L3:
aload 0
getfield com/nd/android/u/cloud/view/widge/DropDownPopWindow$DropDownAdapter/this$0 Lcom/nd/android/u/cloud/view/widge/DropDownPopWindow;
invokestatic com/nd/android/u/cloud/view/widge/DropDownPopWindow/access$200(Lcom/nd/android/u/cloud/view/widge/DropDownPopWindow;)Ljava/util/ArrayList;
ifnull L4
iload 1
aload 0
getfield com/nd/android/u/cloud/view/widge/DropDownPopWindow$DropDownAdapter/this$0 Lcom/nd/android/u/cloud/view/widge/DropDownPopWindow;
invokestatic com/nd/android/u/cloud/view/widge/DropDownPopWindow/access$200(Lcom/nd/android/u/cloud/view/widge/DropDownPopWindow;)Ljava/util/ArrayList;
invokevirtual java/util/ArrayList/size()I
if_icmpge L4
aload 3
getfield com/nd/android/u/cloud/view/widge/DropDownPopWindow$DropDownAdapter$Holder/imageView Landroid/widget/ImageView;
aload 0
getfield com/nd/android/u/cloud/view/widge/DropDownPopWindow$DropDownAdapter/this$0 Lcom/nd/android/u/cloud/view/widge/DropDownPopWindow;
invokestatic com/nd/android/u/cloud/view/widge/DropDownPopWindow/access$200(Lcom/nd/android/u/cloud/view/widge/DropDownPopWindow;)Ljava/util/ArrayList;
iload 1
invokevirtual java/util/ArrayList/get(I)Ljava/lang/Object;
checkcast java/lang/Integer
invokevirtual java/lang/Integer/intValue()I
invokevirtual android/widget/ImageView/setImageResource(I)V
aload 2
areturn
L0:
aload 2
invokevirtual android/view/View/getTag()Ljava/lang/Object;
checkcast com/nd/android/u/cloud/view/widge/DropDownPopWindow$DropDownAdapter$Holder
astore 3
goto L1
L2:
aload 3
getfield com/nd/android/u/cloud/view/widge/DropDownPopWindow$DropDownAdapter$Holder/textView Landroid/widget/TextView;
ldc ""
invokevirtual android/widget/TextView/setText(Ljava/lang/CharSequence;)V
goto L3
L4:
aload 3
getfield com/nd/android/u/cloud/view/widge/DropDownPopWindow$DropDownAdapter$Holder/imageView Landroid/widget/ImageView;
iconst_0
invokevirtual android/widget/ImageView/setImageResource(I)V
aload 2
areturn
.limit locals 4
.limit stack 3
.end method
