.bytecode 50.0
.class synchronized com/nd/android/u/cloud/view/widge/Item_Input$2
.super java/lang/Object
.implements android/text/TextWatcher
.enclosing method com/nd/android/u/cloud/view/widge/Item_Input/initView(Landroid/content/Context;)V
.inner class inner com/nd/android/u/cloud/view/widge/Item_Input$2

.field final synthetic 'this$0' Lcom/nd/android/u/cloud/view/widge/Item_Input;

.method <init>(Lcom/nd/android/u/cloud/view/widge/Item_Input;)V
aload 0
aload 1
putfield com/nd/android/u/cloud/view/widge/Item_Input$2/this$0 Lcom/nd/android/u/cloud/view/widge/Item_Input;
aload 0
invokespecial java/lang/Object/<init>()V
return
.limit locals 2
.limit stack 2
.end method

.method public afterTextChanged(Landroid/text/Editable;)V
return
.limit locals 2
.limit stack 0
.end method

.method public beforeTextChanged(Ljava/lang/CharSequence;III)V
return
.limit locals 5
.limit stack 0
.end method

.method public onTextChanged(Ljava/lang/CharSequence;III)V
aload 1
ifnull L0
aload 1
invokeinterface java/lang/CharSequence/toString()Ljava/lang/String; 0
ldc ""
invokevirtual java/lang/String/equals(Ljava/lang/Object;)Z
ifne L0
aload 0
getfield com/nd/android/u/cloud/view/widge/Item_Input$2/this$0 Lcom/nd/android/u/cloud/view/widge/Item_Input;
invokestatic com/nd/android/u/cloud/view/widge/Item_Input/access$100(Lcom/nd/android/u/cloud/view/widge/Item_Input;)Z
ifeq L1
aload 0
getfield com/nd/android/u/cloud/view/widge/Item_Input$2/this$0 Lcom/nd/android/u/cloud/view/widge/Item_Input;
invokestatic com/nd/android/u/cloud/view/widge/Item_Input/access$200(Lcom/nd/android/u/cloud/view/widge/Item_Input;)Landroid/widget/ImageButton;
iconst_0
invokevirtual android/widget/ImageButton/setVisibility(I)V
return
L1:
aload 0
getfield com/nd/android/u/cloud/view/widge/Item_Input$2/this$0 Lcom/nd/android/u/cloud/view/widge/Item_Input;
invokestatic com/nd/android/u/cloud/view/widge/Item_Input/access$200(Lcom/nd/android/u/cloud/view/widge/Item_Input;)Landroid/widget/ImageButton;
iconst_4
invokevirtual android/widget/ImageButton/setVisibility(I)V
return
L0:
aload 0
getfield com/nd/android/u/cloud/view/widge/Item_Input$2/this$0 Lcom/nd/android/u/cloud/view/widge/Item_Input;
invokestatic com/nd/android/u/cloud/view/widge/Item_Input/access$200(Lcom/nd/android/u/cloud/view/widge/Item_Input;)Landroid/widget/ImageButton;
iconst_4
invokevirtual android/widget/ImageButton/setVisibility(I)V
return
.limit locals 5
.limit stack 2
.end method
