.bytecode 50.0
.class synchronized com/nd/android/u/cloud/view/widge/SelectSectionView$1
.super java/lang/Object
.implements android/view/View$OnClickListener
.enclosing method com/nd/android/u/cloud/view/widge/SelectSectionView
.inner class inner com/nd/android/u/cloud/view/widge/SelectSectionView$1

.field final synthetic 'this$0' Lcom/nd/android/u/cloud/view/widge/SelectSectionView;

.method <init>(Lcom/nd/android/u/cloud/view/widge/SelectSectionView;)V
aload 0
aload 1
putfield com/nd/android/u/cloud/view/widge/SelectSectionView$1/this$0 Lcom/nd/android/u/cloud/view/widge/SelectSectionView;
aload 0
invokespecial java/lang/Object/<init>()V
return
.limit locals 2
.limit stack 2
.end method

.method public onClick(Landroid/view/View;)V
aload 0
getfield com/nd/android/u/cloud/view/widge/SelectSectionView$1/this$0 Lcom/nd/android/u/cloud/view/widge/SelectSectionView;
invokestatic com/nd/android/u/cloud/view/widge/SelectSectionView/access$000(Lcom/nd/android/u/cloud/view/widge/SelectSectionView;)Landroid/widget/CheckBox;
invokevirtual android/widget/CheckBox/isChecked()Z
ifeq L0
aload 0
getfield com/nd/android/u/cloud/view/widge/SelectSectionView$1/this$0 Lcom/nd/android/u/cloud/view/widge/SelectSectionView;
invokestatic com/nd/android/u/cloud/view/widge/SelectSectionView/access$100(Lcom/nd/android/u/cloud/view/widge/SelectSectionView;)Lcom/nd/android/u/contact/dataStructure/OapGrade;
iconst_0
invokevirtual com/nd/android/u/contact/dataStructure/OapGrade/setChecked(Z)V
aload 0
getfield com/nd/android/u/cloud/view/widge/SelectSectionView$1/this$0 Lcom/nd/android/u/cloud/view/widge/SelectSectionView;
invokestatic com/nd/android/u/cloud/view/widge/SelectSectionView/access$200(Lcom/nd/android/u/cloud/view/widge/SelectSectionView;)Ljava/util/ArrayList;
aload 0
getfield com/nd/android/u/cloud/view/widge/SelectSectionView$1/this$0 Lcom/nd/android/u/cloud/view/widge/SelectSectionView;
invokestatic com/nd/android/u/cloud/view/widge/SelectSectionView/access$100(Lcom/nd/android/u/cloud/view/widge/SelectSectionView;)Lcom/nd/android/u/contact/dataStructure/OapGrade;
invokevirtual java/util/ArrayList/contains(Ljava/lang/Object;)Z
ifeq L1
aload 0
getfield com/nd/android/u/cloud/view/widge/SelectSectionView$1/this$0 Lcom/nd/android/u/cloud/view/widge/SelectSectionView;
invokestatic com/nd/android/u/cloud/view/widge/SelectSectionView/access$200(Lcom/nd/android/u/cloud/view/widge/SelectSectionView;)Ljava/util/ArrayList;
aload 0
getfield com/nd/android/u/cloud/view/widge/SelectSectionView$1/this$0 Lcom/nd/android/u/cloud/view/widge/SelectSectionView;
invokestatic com/nd/android/u/cloud/view/widge/SelectSectionView/access$100(Lcom/nd/android/u/cloud/view/widge/SelectSectionView;)Lcom/nd/android/u/contact/dataStructure/OapGrade;
invokevirtual java/util/ArrayList/remove(Ljava/lang/Object;)Z
pop
L1:
aload 0
getfield com/nd/android/u/cloud/view/widge/SelectSectionView$1/this$0 Lcom/nd/android/u/cloud/view/widge/SelectSectionView;
invokestatic com/nd/android/u/cloud/view/widge/SelectSectionView/access$000(Lcom/nd/android/u/cloud/view/widge/SelectSectionView;)Landroid/widget/CheckBox;
iconst_0
invokevirtual android/widget/CheckBox/setChecked(Z)V
aload 0
getfield com/nd/android/u/cloud/view/widge/SelectSectionView$1/this$0 Lcom/nd/android/u/cloud/view/widge/SelectSectionView;
invokestatic com/nd/android/u/cloud/view/widge/SelectSectionView/access$200(Lcom/nd/android/u/cloud/view/widge/SelectSectionView;)Ljava/util/ArrayList;
invokevirtual java/util/ArrayList/size()I
ifne L2
aload 0
getfield com/nd/android/u/cloud/view/widge/SelectSectionView$1/this$0 Lcom/nd/android/u/cloud/view/widge/SelectSectionView;
invokestatic com/nd/android/u/cloud/view/widge/SelectSectionView/access$300(Lcom/nd/android/u/cloud/view/widge/SelectSectionView;)Landroid/os/Handler;
ifnull L2
aload 0
getfield com/nd/android/u/cloud/view/widge/SelectSectionView$1/this$0 Lcom/nd/android/u/cloud/view/widge/SelectSectionView;
invokestatic com/nd/android/u/cloud/view/widge/SelectSectionView/access$300(Lcom/nd/android/u/cloud/view/widge/SelectSectionView;)Landroid/os/Handler;
iconst_1
invokevirtual android/os/Handler/sendEmptyMessage(I)Z
pop
L2:
return
L0:
ldc "SelectClassView"
ldc "MyOnClickListeren checked"
invokestatic android/util/Log/v(Ljava/lang/String;Ljava/lang/String;)I
pop
aload 0
getfield com/nd/android/u/cloud/view/widge/SelectSectionView$1/this$0 Lcom/nd/android/u/cloud/view/widge/SelectSectionView;
invokestatic com/nd/android/u/cloud/view/widge/SelectSectionView/access$200(Lcom/nd/android/u/cloud/view/widge/SelectSectionView;)Ljava/util/ArrayList;
aload 0
getfield com/nd/android/u/cloud/view/widge/SelectSectionView$1/this$0 Lcom/nd/android/u/cloud/view/widge/SelectSectionView;
invokestatic com/nd/android/u/cloud/view/widge/SelectSectionView/access$100(Lcom/nd/android/u/cloud/view/widge/SelectSectionView;)Lcom/nd/android/u/contact/dataStructure/OapGrade;
invokevirtual java/util/ArrayList/contains(Ljava/lang/Object;)Z
ifne L3
aload 0
getfield com/nd/android/u/cloud/view/widge/SelectSectionView$1/this$0 Lcom/nd/android/u/cloud/view/widge/SelectSectionView;
invokestatic com/nd/android/u/cloud/view/widge/SelectSectionView/access$200(Lcom/nd/android/u/cloud/view/widge/SelectSectionView;)Ljava/util/ArrayList;
invokevirtual java/util/ArrayList/size()I
bipush 19
if_icmple L4
aload 0
getfield com/nd/android/u/cloud/view/widge/SelectSectionView$1/this$0 Lcom/nd/android/u/cloud/view/widge/SelectSectionView;
invokestatic com/nd/android/u/cloud/view/widge/SelectSectionView/access$000(Lcom/nd/android/u/cloud/view/widge/SelectSectionView;)Landroid/widget/CheckBox;
iconst_0
invokevirtual android/widget/CheckBox/setChecked(Z)V
aload 0
getfield com/nd/android/u/cloud/view/widge/SelectSectionView$1/this$0 Lcom/nd/android/u/cloud/view/widge/SelectSectionView;
invokestatic com/nd/android/u/cloud/view/widge/SelectSectionView/access$400(Lcom/nd/android/u/cloud/view/widge/SelectSectionView;)Landroid/content/Context;
ldc_w 2131494965
invokestatic com/common/android/utils/ToastUtils/display(Landroid/content/Context;I)V
return
L4:
aload 0
getfield com/nd/android/u/cloud/view/widge/SelectSectionView$1/this$0 Lcom/nd/android/u/cloud/view/widge/SelectSectionView;
invokestatic com/nd/android/u/cloud/view/widge/SelectSectionView/access$100(Lcom/nd/android/u/cloud/view/widge/SelectSectionView;)Lcom/nd/android/u/contact/dataStructure/OapGrade;
iconst_1
invokevirtual com/nd/android/u/contact/dataStructure/OapGrade/setChecked(Z)V
aload 0
getfield com/nd/android/u/cloud/view/widge/SelectSectionView$1/this$0 Lcom/nd/android/u/cloud/view/widge/SelectSectionView;
invokestatic com/nd/android/u/cloud/view/widge/SelectSectionView/access$200(Lcom/nd/android/u/cloud/view/widge/SelectSectionView;)Ljava/util/ArrayList;
aload 0
getfield com/nd/android/u/cloud/view/widge/SelectSectionView$1/this$0 Lcom/nd/android/u/cloud/view/widge/SelectSectionView;
invokestatic com/nd/android/u/cloud/view/widge/SelectSectionView/access$100(Lcom/nd/android/u/cloud/view/widge/SelectSectionView;)Lcom/nd/android/u/contact/dataStructure/OapGrade;
invokevirtual java/util/ArrayList/add(Ljava/lang/Object;)Z
pop
L3:
aload 0
getfield com/nd/android/u/cloud/view/widge/SelectSectionView$1/this$0 Lcom/nd/android/u/cloud/view/widge/SelectSectionView;
invokestatic com/nd/android/u/cloud/view/widge/SelectSectionView/access$000(Lcom/nd/android/u/cloud/view/widge/SelectSectionView;)Landroid/widget/CheckBox;
iconst_1
invokevirtual android/widget/CheckBox/setChecked(Z)V
aload 0
getfield com/nd/android/u/cloud/view/widge/SelectSectionView$1/this$0 Lcom/nd/android/u/cloud/view/widge/SelectSectionView;
invokestatic com/nd/android/u/cloud/view/widge/SelectSectionView/access$200(Lcom/nd/android/u/cloud/view/widge/SelectSectionView;)Ljava/util/ArrayList;
invokevirtual java/util/ArrayList/size()I
iconst_1
if_icmpne L2
aload 0
getfield com/nd/android/u/cloud/view/widge/SelectSectionView$1/this$0 Lcom/nd/android/u/cloud/view/widge/SelectSectionView;
invokestatic com/nd/android/u/cloud/view/widge/SelectSectionView/access$300(Lcom/nd/android/u/cloud/view/widge/SelectSectionView;)Landroid/os/Handler;
ifnull L2
aload 0
getfield com/nd/android/u/cloud/view/widge/SelectSectionView$1/this$0 Lcom/nd/android/u/cloud/view/widge/SelectSectionView;
invokestatic com/nd/android/u/cloud/view/widge/SelectSectionView/access$300(Lcom/nd/android/u/cloud/view/widge/SelectSectionView;)Landroid/os/Handler;
iconst_2
invokevirtual android/os/Handler/sendEmptyMessage(I)Z
pop
return
.limit locals 2
.limit stack 2
.end method
