.bytecode 50.0
.class public synchronized com/nd/android/u/tast/lottery/activity/LotMainActivity
.super android/app/Activity
.implements android/view/View$OnClickListener
.inner class inner com/nd/android/u/tast/lottery/activity/LotMainActivity$1
.inner class inner com/nd/android/u/tast/lottery/activity/LotMainActivity$2
.inner class inner com/nd/android/u/tast/lottery/activity/LotMainActivity$3
.inner class inner com/nd/android/u/tast/lottery/activity/LotMainActivity$3$1
.inner class inner com/nd/android/u/tast/lottery/activity/LotMainActivity$3$2
.inner class inner com/nd/android/u/tast/lottery/activity/LotMainActivity$4
.inner class inner com/nd/android/u/tast/lottery/activity/LotMainActivity$5
.inner class inner com/nd/android/u/tast/lottery/activity/LotMainActivity$6
.inner class private GetLotteryCountTask inner com/nd/android/u/tast/lottery/activity/LotMainActivity$GetLotteryCountTask outer com/nd/android/u/tast/lottery/activity/LotMainActivity
.inner class private GetLotteryask inner com/nd/android/u/tast/lottery/activity/LotMainActivity$GetLotteryask outer com/nd/android/u/tast/lottery/activity/LotMainActivity

.field private 'JACKPOT_IMG_URL' Ljava/lang/String;

.field private final 'PRISE_NUM' I

.field private final 'TIME_POS' I

.field private 'aiv_lot10_img' Landroid/widget/ImageView;

.field private 'aiv_lot11_img' Landroid/widget/ImageView;

.field private 'aiv_lot12_img' Landroid/widget/ImageView;

.field private 'aiv_lot13_img' Landroid/widget/ImageView;

.field private 'aiv_lot14_img' Landroid/widget/ImageView;

.field private 'aiv_lot15_img' Landroid/widget/ImageView;

.field private 'aiv_lot16_img' Landroid/widget/ImageView;

.field private 'aiv_lot17_img' Landroid/widget/ImageView;

.field private 'aiv_lot18_img' Landroid/widget/ImageView;

.field private 'aiv_lot19_img' Landroid/widget/ImageView;

.field private 'aiv_lot1_img' Landroid/widget/ImageView;

.field private 'aiv_lot20_img' Landroid/widget/ImageView;

.field private 'aiv_lot2_img' Landroid/widget/ImageView;

.field private 'aiv_lot3_img' Landroid/widget/ImageView;

.field private 'aiv_lot4_img' Landroid/widget/ImageView;

.field private 'aiv_lot5_img' Landroid/widget/ImageView;

.field private 'aiv_lot6_img' Landroid/widget/ImageView;

.field private 'aiv_lot7_img' Landroid/widget/ImageView;

.field private 'aiv_lot8_img' Landroid/widget/ImageView;

.field private 'aiv_lot9_img' Landroid/widget/ImageView;

.field private 'answer' I

.field private 'btn_back' Landroid/widget/ImageButton;

.field private 'ctx' Landroid/content/Context;

.field private 'iv_lot_num_f' Landroid/widget/ImageView;

.field private 'iv_lot_num_s' Landroid/widget/ImageView;

.field private 'iv_lot_num_t' Landroid/widget/ImageView;

.field private 'll_lot0105' Landroid/widget/LinearLayout;

.field private 'll_lot0610' Landroid/widget/LinearLayout;

.field private 'll_lot1' Landroid/widget/LinearLayout;

.field private 'll_lot10' Landroid/widget/LinearLayout;

.field private 'll_lot11' Landroid/widget/LinearLayout;

.field private 'll_lot1115' Landroid/widget/LinearLayout;

.field private 'll_lot12' Landroid/widget/LinearLayout;

.field private 'll_lot13' Landroid/widget/LinearLayout;

.field private 'll_lot14' Landroid/widget/LinearLayout;

.field private 'll_lot15' Landroid/widget/LinearLayout;

.field private 'll_lot16' Landroid/widget/LinearLayout;

.field private 'll_lot1620' Landroid/widget/LinearLayout;

.field private 'll_lot17' Landroid/widget/LinearLayout;

.field private 'll_lot18' Landroid/widget/LinearLayout;

.field private 'll_lot19' Landroid/widget/LinearLayout;

.field private 'll_lot2' Landroid/widget/LinearLayout;

.field private 'll_lot20' Landroid/widget/LinearLayout;

.field private 'll_lot3' Landroid/widget/LinearLayout;

.field private 'll_lot4' Landroid/widget/LinearLayout;

.field private 'll_lot5' Landroid/widget/LinearLayout;

.field private 'll_lot6' Landroid/widget/LinearLayout;

.field private 'll_lot7' Landroid/widget/LinearLayout;

.field private 'll_lot8' Landroid/widget/LinearLayout;

.field private 'll_lot9' Landroid/widget/LinearLayout;

.field private 'll_start_lot' Landroid/widget/LinearLayout;

.field private 'lot10_name' Landroid/widget/TextView;

.field private 'lot11_name' Landroid/widget/TextView;

.field private 'lot12_name' Landroid/widget/TextView;

.field private 'lot13_name' Landroid/widget/TextView;

.field private 'lot14_name' Landroid/widget/TextView;

.field private 'lot15_name' Landroid/widget/TextView;

.field private 'lot16_name' Landroid/widget/TextView;

.field private 'lot17_name' Landroid/widget/TextView;

.field private 'lot18_name' Landroid/widget/TextView;

.field private 'lot19_name' Landroid/widget/TextView;

.field private 'lot1_name' Landroid/widget/TextView;

.field private 'lot20_name' Landroid/widget/TextView;

.field private 'lot2_name' Landroid/widget/TextView;

.field private 'lot3_name' Landroid/widget/TextView;

.field private 'lot4_name' Landroid/widget/TextView;

.field private 'lot5_name' Landroid/widget/TextView;

.field private 'lot6_name' Landroid/widget/TextView;

.field private 'lot7_name' Landroid/widget/TextView;

.field private 'lot8_name' Landroid/widget/TextView;

.field private 'lot9_name' Landroid/widget/TextView;

.field private 'lotlay' Landroid/widget/RelativeLayout;

.field private 'mCanLot' Z

.field private 'mCurrentCircleNum' I

.field private 'mCurrentPos' I

.field private 'mGetLotCountTask' Lcom/common/android/utils/task/genericTask/GenericTask;

.field private 'mGetLotCountTaskListener' Lcom/common/android/utils/task/genericTask/TaskListener;

.field private 'mGetLotInfoTask' Lcom/common/android/utils/task/genericTask/GenericTask;

.field private 'mGetLotInfoTaskListener' Lcom/common/android/utils/task/genericTask/TaskListener;

.field private 'mHasLoted' Z

.field private 'mItemtype' I

.field private 'mLotNum' I

.field private 'mLotNumSave' Z

.field private 'mLotOnBgBitmapDrawable' Landroid/graphics/drawable/BitmapDrawable;

.field private 'mLotPriseList' Ljava/util/List; signature "Ljava/util/List<Lcom/nd/android/u/tast/lottery/dataStructure/LotPrise;>;"

.field private 'mLotUsersList' Ljava/util/List; signature "Ljava/util/List<Lcom/nd/android/u/tast/lottery/dataStructure/LotUsersData;>;"

.field private 'mPrise' Lcom/nd/android/u/tast/lottery/dataStructure/LotUserData;

.field private 'mTurnId' I

.field private 'm_dialog' Landroid/app/ProgressDialog;

.field private 'myListener' Lcom/nd/android/u/tast/lottery/util/LotResultDialogListener;

.field private 'scrollDoubleLayout1' Lcom/product/android/ui/widget/ScrollDoubleLayout;

.field private 'timeThread' Ljava/lang/Runnable;

.field private 'timerCnt' I

.field private 'timerHandler' Landroid/os/Handler;

.field private 'tv_no_lot_users' Landroid/widget/TextView;

.method public <init>()V
aload 0
invokespecial android/app/Activity/<init>()V
aload 0
new java/util/ArrayList
dup
invokespecial java/util/ArrayList/<init>()V
putfield com/nd/android/u/tast/lottery/activity/LotMainActivity/mLotUsersList Ljava/util/List;
aload 0
new java/util/ArrayList
dup
invokespecial java/util/ArrayList/<init>()V
putfield com/nd/android/u/tast/lottery/activity/LotMainActivity/mLotPriseList Ljava/util/List;
aload 0
bipush 20
putfield com/nd/android/u/tast/lottery/activity/LotMainActivity/PRISE_NUM I
aload 0
bipush 100
putfield com/nd/android/u/tast/lottery/activity/LotMainActivity/TIME_POS I
aload 0
iconst_2
putfield com/nd/android/u/tast/lottery/activity/LotMainActivity/mCurrentCircleNum I
aload 0
iconst_1
putfield com/nd/android/u/tast/lottery/activity/LotMainActivity/mCurrentPos I
aload 0
iconst_m1
putfield com/nd/android/u/tast/lottery/activity/LotMainActivity/answer I
aload 0
aload 0
getfield com/nd/android/u/tast/lottery/activity/LotMainActivity/mCurrentPos I
putfield com/nd/android/u/tast/lottery/activity/LotMainActivity/timerCnt I
aload 0
iconst_0
putfield com/nd/android/u/tast/lottery/activity/LotMainActivity/mCanLot Z
aload 0
iconst_0
putfield com/nd/android/u/tast/lottery/activity/LotMainActivity/mLotNum I
aload 0
iconst_1
putfield com/nd/android/u/tast/lottery/activity/LotMainActivity/mLotNumSave Z
aload 0
iconst_0
putfield com/nd/android/u/tast/lottery/activity/LotMainActivity/mHasLoted Z
aload 0
sipush 10000
putfield com/nd/android/u/tast/lottery/activity/LotMainActivity/mItemtype I
aload 0
iconst_0
putfield com/nd/android/u/tast/lottery/activity/LotMainActivity/mTurnId I
aload 0
new com/nd/android/u/tast/lottery/activity/LotMainActivity$2
dup
aload 0
invokespecial com/nd/android/u/tast/lottery/activity/LotMainActivity$2/<init>(Lcom/nd/android/u/tast/lottery/activity/LotMainActivity;)V
putfield com/nd/android/u/tast/lottery/activity/LotMainActivity/myListener Lcom/nd/android/u/tast/lottery/util/LotResultDialogListener;
aload 0
new com/nd/android/u/tast/lottery/activity/LotMainActivity$4
dup
aload 0
invokespecial com/nd/android/u/tast/lottery/activity/LotMainActivity$4/<init>(Lcom/nd/android/u/tast/lottery/activity/LotMainActivity;)V
putfield com/nd/android/u/tast/lottery/activity/LotMainActivity/timeThread Ljava/lang/Runnable;
aload 0
new com/nd/android/u/tast/lottery/activity/LotMainActivity$5
dup
aload 0
invokespecial com/nd/android/u/tast/lottery/activity/LotMainActivity$5/<init>(Lcom/nd/android/u/tast/lottery/activity/LotMainActivity;)V
putfield com/nd/android/u/tast/lottery/activity/LotMainActivity/mGetLotCountTaskListener Lcom/common/android/utils/task/genericTask/TaskListener;
aload 0
new com/nd/android/u/tast/lottery/activity/LotMainActivity$6
dup
aload 0
invokespecial com/nd/android/u/tast/lottery/activity/LotMainActivity$6/<init>(Lcom/nd/android/u/tast/lottery/activity/LotMainActivity;)V
putfield com/nd/android/u/tast/lottery/activity/LotMainActivity/mGetLotInfoTaskListener Lcom/common/android/utils/task/genericTask/TaskListener;
return
.limit locals 1
.limit stack 4
.end method

.method static synthetic access$002(Lcom/nd/android/u/tast/lottery/activity/LotMainActivity;Z)Z
aload 0
iload 1
putfield com/nd/android/u/tast/lottery/activity/LotMainActivity/mCanLot Z
iload 1
ireturn
.limit locals 2
.limit stack 2
.end method

.method static synthetic access$100(Lcom/nd/android/u/tast/lottery/activity/LotMainActivity;)I
aload 0
getfield com/nd/android/u/tast/lottery/activity/LotMainActivity/answer I
ireturn
.limit locals 1
.limit stack 1
.end method

.method static synthetic access$1000(Lcom/nd/android/u/tast/lottery/activity/LotMainActivity;)I
aload 0
getfield com/nd/android/u/tast/lottery/activity/LotMainActivity/mTurnId I
ireturn
.limit locals 1
.limit stack 1
.end method

.method static synthetic access$1002(Lcom/nd/android/u/tast/lottery/activity/LotMainActivity;I)I
aload 0
iload 1
putfield com/nd/android/u/tast/lottery/activity/LotMainActivity/mTurnId I
iload 1
ireturn
.limit locals 2
.limit stack 2
.end method

.method static synthetic access$102(Lcom/nd/android/u/tast/lottery/activity/LotMainActivity;I)I
aload 0
iload 1
putfield com/nd/android/u/tast/lottery/activity/LotMainActivity/answer I
iload 1
ireturn
.limit locals 2
.limit stack 2
.end method

.method static synthetic access$1100(Lcom/nd/android/u/tast/lottery/activity/LotMainActivity;)V
aload 0
invokespecial com/nd/android/u/tast/lottery/activity/LotMainActivity/getLotteryInfo()V
return
.limit locals 1
.limit stack 1
.end method

.method static synthetic access$1200(Lcom/nd/android/u/tast/lottery/activity/LotMainActivity;)Ljava/util/List;
aload 0
getfield com/nd/android/u/tast/lottery/activity/LotMainActivity/mLotPriseList Ljava/util/List;
areturn
.limit locals 1
.limit stack 1
.end method

.method static synthetic access$1302(Lcom/nd/android/u/tast/lottery/activity/LotMainActivity;Z)Z
aload 0
iload 1
putfield com/nd/android/u/tast/lottery/activity/LotMainActivity/mHasLoted Z
iload 1
ireturn
.limit locals 2
.limit stack 2
.end method

.method static synthetic access$1400(Lcom/nd/android/u/tast/lottery/activity/LotMainActivity;)I
aload 0
getfield com/nd/android/u/tast/lottery/activity/LotMainActivity/mLotNum I
ireturn
.limit locals 1
.limit stack 1
.end method

.method static synthetic access$1402(Lcom/nd/android/u/tast/lottery/activity/LotMainActivity;I)I
aload 0
iload 1
putfield com/nd/android/u/tast/lottery/activity/LotMainActivity/mLotNum I
iload 1
ireturn
.limit locals 2
.limit stack 2
.end method

.method static synthetic access$1410(Lcom/nd/android/u/tast/lottery/activity/LotMainActivity;)I
aload 0
getfield com/nd/android/u/tast/lottery/activity/LotMainActivity/mLotNum I
istore 1
aload 0
iload 1
iconst_1
isub
putfield com/nd/android/u/tast/lottery/activity/LotMainActivity/mLotNum I
iload 1
ireturn
.limit locals 2
.limit stack 3
.end method

.method static synthetic access$1500(Lcom/nd/android/u/tast/lottery/activity/LotMainActivity;)V
aload 0
invokespecial com/nd/android/u/tast/lottery/activity/LotMainActivity/initLotTimes()V
return
.limit locals 1
.limit stack 1
.end method

.method static synthetic access$1600(Lcom/nd/android/u/tast/lottery/activity/LotMainActivity;)Landroid/os/Handler;
aload 0
getfield com/nd/android/u/tast/lottery/activity/LotMainActivity/timerHandler Landroid/os/Handler;
areturn
.limit locals 1
.limit stack 1
.end method

.method static synthetic access$1700(Lcom/nd/android/u/tast/lottery/activity/LotMainActivity;)I
aload 0
getfield com/nd/android/u/tast/lottery/activity/LotMainActivity/mCurrentCircleNum I
ireturn
.limit locals 1
.limit stack 1
.end method

.method static synthetic access$1708(Lcom/nd/android/u/tast/lottery/activity/LotMainActivity;)I
aload 0
getfield com/nd/android/u/tast/lottery/activity/LotMainActivity/mCurrentCircleNum I
istore 1
aload 0
iload 1
iconst_1
iadd
putfield com/nd/android/u/tast/lottery/activity/LotMainActivity/mCurrentCircleNum I
iload 1
ireturn
.limit locals 2
.limit stack 3
.end method

.method static synthetic access$1800(Lcom/nd/android/u/tast/lottery/activity/LotMainActivity;)Ljava/lang/Runnable;
aload 0
getfield com/nd/android/u/tast/lottery/activity/LotMainActivity/timeThread Ljava/lang/Runnable;
areturn
.limit locals 1
.limit stack 1
.end method

.method static synthetic access$200(Lcom/nd/android/u/tast/lottery/activity/LotMainActivity;)I
aload 0
getfield com/nd/android/u/tast/lottery/activity/LotMainActivity/mCurrentPos I
ireturn
.limit locals 1
.limit stack 1
.end method

.method static synthetic access$2000(Lcom/nd/android/u/tast/lottery/activity/LotMainActivity;)Ljava/util/List;
aload 0
getfield com/nd/android/u/tast/lottery/activity/LotMainActivity/mLotUsersList Ljava/util/List;
areturn
.limit locals 1
.limit stack 1
.end method

.method static synthetic access$202(Lcom/nd/android/u/tast/lottery/activity/LotMainActivity;I)I
aload 0
iload 1
putfield com/nd/android/u/tast/lottery/activity/LotMainActivity/mCurrentPos I
iload 1
ireturn
.limit locals 2
.limit stack 2
.end method

.method static synthetic access$2200(Lcom/nd/android/u/tast/lottery/activity/LotMainActivity;)Landroid/app/ProgressDialog;
aload 0
getfield com/nd/android/u/tast/lottery/activity/LotMainActivity/m_dialog Landroid/app/ProgressDialog;
areturn
.limit locals 1
.limit stack 1
.end method

.method static synthetic access$2202(Lcom/nd/android/u/tast/lottery/activity/LotMainActivity;Landroid/app/ProgressDialog;)Landroid/app/ProgressDialog;
aload 0
aload 1
putfield com/nd/android/u/tast/lottery/activity/LotMainActivity/m_dialog Landroid/app/ProgressDialog;
aload 1
areturn
.limit locals 2
.limit stack 2
.end method

.method static synthetic access$2300(Lcom/nd/android/u/tast/lottery/activity/LotMainActivity;)V
aload 0
invokespecial com/nd/android/u/tast/lottery/activity/LotMainActivity/initLotUsersList()V
return
.limit locals 1
.limit stack 1
.end method

.method static synthetic access$2400(Lcom/nd/android/u/tast/lottery/activity/LotMainActivity;)V
aload 0
invokespecial com/nd/android/u/tast/lottery/activity/LotMainActivity/initPriseList()V
return
.limit locals 1
.limit stack 1
.end method

.method static synthetic access$300(Lcom/nd/android/u/tast/lottery/activity/LotMainActivity;)I
aload 0
getfield com/nd/android/u/tast/lottery/activity/LotMainActivity/timerCnt I
ireturn
.limit locals 1
.limit stack 1
.end method

.method static synthetic access$302(Lcom/nd/android/u/tast/lottery/activity/LotMainActivity;I)I
aload 0
iload 1
putfield com/nd/android/u/tast/lottery/activity/LotMainActivity/timerCnt I
iload 1
ireturn
.limit locals 2
.limit stack 2
.end method

.method static synthetic access$308(Lcom/nd/android/u/tast/lottery/activity/LotMainActivity;)I
aload 0
getfield com/nd/android/u/tast/lottery/activity/LotMainActivity/timerCnt I
istore 1
aload 0
iload 1
iconst_1
iadd
putfield com/nd/android/u/tast/lottery/activity/LotMainActivity/timerCnt I
iload 1
ireturn
.limit locals 2
.limit stack 3
.end method

.method static synthetic access$400(Lcom/nd/android/u/tast/lottery/activity/LotMainActivity;I)V
aload 0
iload 1
invokespecial com/nd/android/u/tast/lottery/activity/LotMainActivity/chgBackGrountNormal(I)V
return
.limit locals 2
.limit stack 2
.end method

.method static synthetic access$500(Lcom/nd/android/u/tast/lottery/activity/LotMainActivity;)Landroid/content/Context;
aload 0
getfield com/nd/android/u/tast/lottery/activity/LotMainActivity/ctx Landroid/content/Context;
areturn
.limit locals 1
.limit stack 1
.end method

.method static synthetic access$600(Lcom/nd/android/u/tast/lottery/activity/LotMainActivity;I)V
aload 0
iload 1
invokespecial com/nd/android/u/tast/lottery/activity/LotMainActivity/chgBackGrountOver(I)V
return
.limit locals 2
.limit stack 2
.end method

.method static synthetic access$700(Lcom/nd/android/u/tast/lottery/activity/LotMainActivity;)Lcom/nd/android/u/tast/lottery/dataStructure/LotUserData;
aload 0
getfield com/nd/android/u/tast/lottery/activity/LotMainActivity/mPrise Lcom/nd/android/u/tast/lottery/dataStructure/LotUserData;
areturn
.limit locals 1
.limit stack 1
.end method

.method static synthetic access$702(Lcom/nd/android/u/tast/lottery/activity/LotMainActivity;Lcom/nd/android/u/tast/lottery/dataStructure/LotUserData;)Lcom/nd/android/u/tast/lottery/dataStructure/LotUserData;
aload 0
aload 1
putfield com/nd/android/u/tast/lottery/activity/LotMainActivity/mPrise Lcom/nd/android/u/tast/lottery/dataStructure/LotUserData;
aload 1
areturn
.limit locals 2
.limit stack 2
.end method

.method static synthetic access$800(Lcom/nd/android/u/tast/lottery/activity/LotMainActivity;)Lcom/nd/android/u/tast/lottery/util/LotResultDialogListener;
aload 0
getfield com/nd/android/u/tast/lottery/activity/LotMainActivity/myListener Lcom/nd/android/u/tast/lottery/util/LotResultDialogListener;
areturn
.limit locals 1
.limit stack 1
.end method

.method static synthetic access$900(Lcom/nd/android/u/tast/lottery/activity/LotMainActivity;)I
aload 0
getfield com/nd/android/u/tast/lottery/activity/LotMainActivity/mItemtype I
ireturn
.limit locals 1
.limit stack 1
.end method

.method private chgBackGrountNormal(I)V
iload 1
tableswitch 1
L0
L1
L2
L3
L4
L5
L6
L7
L8
L9
L10
L11
L12
L13
L14
L15
L16
L17
L18
L19
default : L20
L20:
ldc "DYF"
new java/lang/StringBuilder
dup
invokespecial java/lang/StringBuilder/<init>()V
ldc "chgBackGrountNormal default:"
invokevirtual java/lang/StringBuilder/append(Ljava/lang/String;)Ljava/lang/StringBuilder;
iload 1
invokevirtual java/lang/StringBuilder/append(I)Ljava/lang/StringBuilder;
invokevirtual java/lang/StringBuilder/toString()Ljava/lang/String;
invokestatic android/util/Log/e(Ljava/lang/String;Ljava/lang/String;)I
pop
aload 0
getfield com/nd/android/u/tast/lottery/activity/LotMainActivity/ll_lot1 Landroid/widget/LinearLayout;
getstatic com/nd/android/u/tasklib/R$drawable/prise_bg1 I
invokevirtual android/widget/LinearLayout/setBackgroundResource(I)V
aload 0
getfield com/nd/android/u/tast/lottery/activity/LotMainActivity/ll_lot2 Landroid/widget/LinearLayout;
getstatic com/nd/android/u/tasklib/R$drawable/prise_bg2 I
invokevirtual android/widget/LinearLayout/setBackgroundResource(I)V
aload 0
getfield com/nd/android/u/tast/lottery/activity/LotMainActivity/ll_lot3 Landroid/widget/LinearLayout;
getstatic com/nd/android/u/tasklib/R$drawable/prise_bg1 I
invokevirtual android/widget/LinearLayout/setBackgroundResource(I)V
aload 0
getfield com/nd/android/u/tast/lottery/activity/LotMainActivity/ll_lot4 Landroid/widget/LinearLayout;
getstatic com/nd/android/u/tasklib/R$drawable/prise_bg2 I
invokevirtual android/widget/LinearLayout/setBackgroundResource(I)V
aload 0
getfield com/nd/android/u/tast/lottery/activity/LotMainActivity/ll_lot5 Landroid/widget/LinearLayout;
getstatic com/nd/android/u/tasklib/R$drawable/prise_bg1 I
invokevirtual android/widget/LinearLayout/setBackgroundResource(I)V
aload 0
getfield com/nd/android/u/tast/lottery/activity/LotMainActivity/ll_lot6 Landroid/widget/LinearLayout;
getstatic com/nd/android/u/tasklib/R$drawable/prise_bg2 I
invokevirtual android/widget/LinearLayout/setBackgroundResource(I)V
aload 0
getfield com/nd/android/u/tast/lottery/activity/LotMainActivity/ll_lot7 Landroid/widget/LinearLayout;
getstatic com/nd/android/u/tasklib/R$drawable/prise_bg1 I
invokevirtual android/widget/LinearLayout/setBackgroundResource(I)V
aload 0
getfield com/nd/android/u/tast/lottery/activity/LotMainActivity/ll_lot8 Landroid/widget/LinearLayout;
getstatic com/nd/android/u/tasklib/R$drawable/prise_bg2 I
invokevirtual android/widget/LinearLayout/setBackgroundResource(I)V
aload 0
getfield com/nd/android/u/tast/lottery/activity/LotMainActivity/ll_lot9 Landroid/widget/LinearLayout;
getstatic com/nd/android/u/tasklib/R$drawable/prise_bg1 I
invokevirtual android/widget/LinearLayout/setBackgroundResource(I)V
aload 0
getfield com/nd/android/u/tast/lottery/activity/LotMainActivity/ll_lot10 Landroid/widget/LinearLayout;
getstatic com/nd/android/u/tasklib/R$drawable/prise_bg2 I
invokevirtual android/widget/LinearLayout/setBackgroundResource(I)V
aload 0
getfield com/nd/android/u/tast/lottery/activity/LotMainActivity/ll_lot11 Landroid/widget/LinearLayout;
getstatic com/nd/android/u/tasklib/R$drawable/prise_bg1 I
invokevirtual android/widget/LinearLayout/setBackgroundResource(I)V
aload 0
getfield com/nd/android/u/tast/lottery/activity/LotMainActivity/ll_lot12 Landroid/widget/LinearLayout;
getstatic com/nd/android/u/tasklib/R$drawable/prise_bg2 I
invokevirtual android/widget/LinearLayout/setBackgroundResource(I)V
aload 0
getfield com/nd/android/u/tast/lottery/activity/LotMainActivity/ll_lot13 Landroid/widget/LinearLayout;
getstatic com/nd/android/u/tasklib/R$drawable/prise_bg1 I
invokevirtual android/widget/LinearLayout/setBackgroundResource(I)V
aload 0
getfield com/nd/android/u/tast/lottery/activity/LotMainActivity/ll_lot14 Landroid/widget/LinearLayout;
getstatic com/nd/android/u/tasklib/R$drawable/prise_bg2 I
invokevirtual android/widget/LinearLayout/setBackgroundResource(I)V
aload 0
getfield com/nd/android/u/tast/lottery/activity/LotMainActivity/ll_lot15 Landroid/widget/LinearLayout;
getstatic com/nd/android/u/tasklib/R$drawable/prise_bg1 I
invokevirtual android/widget/LinearLayout/setBackgroundResource(I)V
aload 0
getfield com/nd/android/u/tast/lottery/activity/LotMainActivity/ll_lot16 Landroid/widget/LinearLayout;
getstatic com/nd/android/u/tasklib/R$drawable/prise_bg2 I
invokevirtual android/widget/LinearLayout/setBackgroundResource(I)V
aload 0
getfield com/nd/android/u/tast/lottery/activity/LotMainActivity/ll_lot17 Landroid/widget/LinearLayout;
getstatic com/nd/android/u/tasklib/R$drawable/prise_bg1 I
invokevirtual android/widget/LinearLayout/setBackgroundResource(I)V
aload 0
getfield com/nd/android/u/tast/lottery/activity/LotMainActivity/ll_lot18 Landroid/widget/LinearLayout;
getstatic com/nd/android/u/tasklib/R$drawable/prise_bg2 I
invokevirtual android/widget/LinearLayout/setBackgroundResource(I)V
aload 0
getfield com/nd/android/u/tast/lottery/activity/LotMainActivity/ll_lot19 Landroid/widget/LinearLayout;
getstatic com/nd/android/u/tasklib/R$drawable/prise_bg1 I
invokevirtual android/widget/LinearLayout/setBackgroundResource(I)V
aload 0
getfield com/nd/android/u/tast/lottery/activity/LotMainActivity/ll_lot20 Landroid/widget/LinearLayout;
getstatic com/nd/android/u/tasklib/R$drawable/prise_bg2 I
invokevirtual android/widget/LinearLayout/setBackgroundResource(I)V
return
L0:
aload 0
getfield com/nd/android/u/tast/lottery/activity/LotMainActivity/ll_lot1 Landroid/widget/LinearLayout;
getstatic com/nd/android/u/tasklib/R$drawable/prise_bg1 I
invokevirtual android/widget/LinearLayout/setBackgroundResource(I)V
return
L1:
aload 0
getfield com/nd/android/u/tast/lottery/activity/LotMainActivity/ll_lot2 Landroid/widget/LinearLayout;
getstatic com/nd/android/u/tasklib/R$drawable/prise_bg2 I
invokevirtual android/widget/LinearLayout/setBackgroundResource(I)V
return
L2:
aload 0
getfield com/nd/android/u/tast/lottery/activity/LotMainActivity/ll_lot3 Landroid/widget/LinearLayout;
getstatic com/nd/android/u/tasklib/R$drawable/prise_bg1 I
invokevirtual android/widget/LinearLayout/setBackgroundResource(I)V
return
L3:
aload 0
getfield com/nd/android/u/tast/lottery/activity/LotMainActivity/ll_lot4 Landroid/widget/LinearLayout;
getstatic com/nd/android/u/tasklib/R$drawable/prise_bg2 I
invokevirtual android/widget/LinearLayout/setBackgroundResource(I)V
return
L4:
aload 0
getfield com/nd/android/u/tast/lottery/activity/LotMainActivity/ll_lot5 Landroid/widget/LinearLayout;
getstatic com/nd/android/u/tasklib/R$drawable/prise_bg1 I
invokevirtual android/widget/LinearLayout/setBackgroundResource(I)V
return
L5:
aload 0
getfield com/nd/android/u/tast/lottery/activity/LotMainActivity/ll_lot6 Landroid/widget/LinearLayout;
getstatic com/nd/android/u/tasklib/R$drawable/prise_bg2 I
invokevirtual android/widget/LinearLayout/setBackgroundResource(I)V
return
L6:
aload 0
getfield com/nd/android/u/tast/lottery/activity/LotMainActivity/ll_lot7 Landroid/widget/LinearLayout;
getstatic com/nd/android/u/tasklib/R$drawable/prise_bg1 I
invokevirtual android/widget/LinearLayout/setBackgroundResource(I)V
return
L7:
aload 0
getfield com/nd/android/u/tast/lottery/activity/LotMainActivity/ll_lot8 Landroid/widget/LinearLayout;
getstatic com/nd/android/u/tasklib/R$drawable/prise_bg2 I
invokevirtual android/widget/LinearLayout/setBackgroundResource(I)V
return
L8:
aload 0
getfield com/nd/android/u/tast/lottery/activity/LotMainActivity/ll_lot9 Landroid/widget/LinearLayout;
getstatic com/nd/android/u/tasklib/R$drawable/prise_bg1 I
invokevirtual android/widget/LinearLayout/setBackgroundResource(I)V
return
L9:
aload 0
getfield com/nd/android/u/tast/lottery/activity/LotMainActivity/ll_lot10 Landroid/widget/LinearLayout;
getstatic com/nd/android/u/tasklib/R$drawable/prise_bg2 I
invokevirtual android/widget/LinearLayout/setBackgroundResource(I)V
return
L10:
aload 0
getfield com/nd/android/u/tast/lottery/activity/LotMainActivity/ll_lot11 Landroid/widget/LinearLayout;
getstatic com/nd/android/u/tasklib/R$drawable/prise_bg1 I
invokevirtual android/widget/LinearLayout/setBackgroundResource(I)V
return
L11:
aload 0
getfield com/nd/android/u/tast/lottery/activity/LotMainActivity/ll_lot12 Landroid/widget/LinearLayout;
getstatic com/nd/android/u/tasklib/R$drawable/prise_bg2 I
invokevirtual android/widget/LinearLayout/setBackgroundResource(I)V
return
L12:
aload 0
getfield com/nd/android/u/tast/lottery/activity/LotMainActivity/ll_lot13 Landroid/widget/LinearLayout;
getstatic com/nd/android/u/tasklib/R$drawable/prise_bg1 I
invokevirtual android/widget/LinearLayout/setBackgroundResource(I)V
return
L13:
aload 0
getfield com/nd/android/u/tast/lottery/activity/LotMainActivity/ll_lot14 Landroid/widget/LinearLayout;
getstatic com/nd/android/u/tasklib/R$drawable/prise_bg2 I
invokevirtual android/widget/LinearLayout/setBackgroundResource(I)V
return
L14:
aload 0
getfield com/nd/android/u/tast/lottery/activity/LotMainActivity/ll_lot15 Landroid/widget/LinearLayout;
getstatic com/nd/android/u/tasklib/R$drawable/prise_bg1 I
invokevirtual android/widget/LinearLayout/setBackgroundResource(I)V
return
L15:
aload 0
getfield com/nd/android/u/tast/lottery/activity/LotMainActivity/ll_lot16 Landroid/widget/LinearLayout;
getstatic com/nd/android/u/tasklib/R$drawable/prise_bg2 I
invokevirtual android/widget/LinearLayout/setBackgroundResource(I)V
return
L16:
aload 0
getfield com/nd/android/u/tast/lottery/activity/LotMainActivity/ll_lot17 Landroid/widget/LinearLayout;
getstatic com/nd/android/u/tasklib/R$drawable/prise_bg1 I
invokevirtual android/widget/LinearLayout/setBackgroundResource(I)V
return
L17:
aload 0
getfield com/nd/android/u/tast/lottery/activity/LotMainActivity/ll_lot18 Landroid/widget/LinearLayout;
getstatic com/nd/android/u/tasklib/R$drawable/prise_bg2 I
invokevirtual android/widget/LinearLayout/setBackgroundResource(I)V
return
L18:
aload 0
getfield com/nd/android/u/tast/lottery/activity/LotMainActivity/ll_lot19 Landroid/widget/LinearLayout;
getstatic com/nd/android/u/tasklib/R$drawable/prise_bg1 I
invokevirtual android/widget/LinearLayout/setBackgroundResource(I)V
return
L19:
aload 0
getfield com/nd/android/u/tast/lottery/activity/LotMainActivity/ll_lot20 Landroid/widget/LinearLayout;
getstatic com/nd/android/u/tasklib/R$drawable/prise_bg2 I
invokevirtual android/widget/LinearLayout/setBackgroundResource(I)V
return
.limit locals 2
.limit stack 3
.end method

.method private chgBackGrountOver(I)V
aload 0
getfield com/nd/android/u/tast/lottery/activity/LotMainActivity/mLotOnBgBitmapDrawable Landroid/graphics/drawable/BitmapDrawable;
ifnonnull L0
L1:
return
L0:
aload 0
getfield com/nd/android/u/tast/lottery/activity/LotMainActivity/mLotOnBgBitmapDrawable Landroid/graphics/drawable/BitmapDrawable;
invokevirtual android/graphics/drawable/BitmapDrawable/getBitmap()Landroid/graphics/Bitmap;
astore 2
aload 2
ifnull L1
aload 2
invokevirtual android/graphics/Bitmap/isRecycled()Z
ifne L1
iload 1
tableswitch 1
L2
L3
L4
L5
L6
L7
L8
L9
L10
L11
L12
L13
L14
L15
L16
L17
L18
L19
L20
L21
default : L22
L22:
ldc "DYF"
new java/lang/StringBuilder
dup
invokespecial java/lang/StringBuilder/<init>()V
ldc "chgBackGrountOver default:"
invokevirtual java/lang/StringBuilder/append(Ljava/lang/String;)Ljava/lang/StringBuilder;
iload 1
invokevirtual java/lang/StringBuilder/append(I)Ljava/lang/StringBuilder;
invokevirtual java/lang/StringBuilder/toString()Ljava/lang/String;
invokestatic android/util/Log/e(Ljava/lang/String;Ljava/lang/String;)I
pop
return
L2:
aload 0
getfield com/nd/android/u/tast/lottery/activity/LotMainActivity/ll_lot1 Landroid/widget/LinearLayout;
aload 0
getfield com/nd/android/u/tast/lottery/activity/LotMainActivity/mLotOnBgBitmapDrawable Landroid/graphics/drawable/BitmapDrawable;
invokevirtual android/widget/LinearLayout/setBackgroundDrawable(Landroid/graphics/drawable/Drawable;)V
return
L3:
aload 0
getfield com/nd/android/u/tast/lottery/activity/LotMainActivity/ll_lot2 Landroid/widget/LinearLayout;
aload 0
getfield com/nd/android/u/tast/lottery/activity/LotMainActivity/mLotOnBgBitmapDrawable Landroid/graphics/drawable/BitmapDrawable;
invokevirtual android/widget/LinearLayout/setBackgroundDrawable(Landroid/graphics/drawable/Drawable;)V
return
L4:
aload 0
getfield com/nd/android/u/tast/lottery/activity/LotMainActivity/ll_lot3 Landroid/widget/LinearLayout;
aload 0
getfield com/nd/android/u/tast/lottery/activity/LotMainActivity/mLotOnBgBitmapDrawable Landroid/graphics/drawable/BitmapDrawable;
invokevirtual android/widget/LinearLayout/setBackgroundDrawable(Landroid/graphics/drawable/Drawable;)V
return
L5:
aload 0
getfield com/nd/android/u/tast/lottery/activity/LotMainActivity/ll_lot4 Landroid/widget/LinearLayout;
aload 0
getfield com/nd/android/u/tast/lottery/activity/LotMainActivity/mLotOnBgBitmapDrawable Landroid/graphics/drawable/BitmapDrawable;
invokevirtual android/widget/LinearLayout/setBackgroundDrawable(Landroid/graphics/drawable/Drawable;)V
return
L6:
aload 0
getfield com/nd/android/u/tast/lottery/activity/LotMainActivity/ll_lot5 Landroid/widget/LinearLayout;
aload 0
getfield com/nd/android/u/tast/lottery/activity/LotMainActivity/mLotOnBgBitmapDrawable Landroid/graphics/drawable/BitmapDrawable;
invokevirtual android/widget/LinearLayout/setBackgroundDrawable(Landroid/graphics/drawable/Drawable;)V
return
L7:
aload 0
getfield com/nd/android/u/tast/lottery/activity/LotMainActivity/ll_lot6 Landroid/widget/LinearLayout;
aload 0
getfield com/nd/android/u/tast/lottery/activity/LotMainActivity/mLotOnBgBitmapDrawable Landroid/graphics/drawable/BitmapDrawable;
invokevirtual android/widget/LinearLayout/setBackgroundDrawable(Landroid/graphics/drawable/Drawable;)V
return
L8:
aload 0
getfield com/nd/android/u/tast/lottery/activity/LotMainActivity/ll_lot7 Landroid/widget/LinearLayout;
aload 0
getfield com/nd/android/u/tast/lottery/activity/LotMainActivity/mLotOnBgBitmapDrawable Landroid/graphics/drawable/BitmapDrawable;
invokevirtual android/widget/LinearLayout/setBackgroundDrawable(Landroid/graphics/drawable/Drawable;)V
return
L9:
aload 0
getfield com/nd/android/u/tast/lottery/activity/LotMainActivity/ll_lot8 Landroid/widget/LinearLayout;
aload 0
getfield com/nd/android/u/tast/lottery/activity/LotMainActivity/mLotOnBgBitmapDrawable Landroid/graphics/drawable/BitmapDrawable;
invokevirtual android/widget/LinearLayout/setBackgroundDrawable(Landroid/graphics/drawable/Drawable;)V
return
L10:
aload 0
getfield com/nd/android/u/tast/lottery/activity/LotMainActivity/ll_lot9 Landroid/widget/LinearLayout;
aload 0
getfield com/nd/android/u/tast/lottery/activity/LotMainActivity/mLotOnBgBitmapDrawable Landroid/graphics/drawable/BitmapDrawable;
invokevirtual android/widget/LinearLayout/setBackgroundDrawable(Landroid/graphics/drawable/Drawable;)V
return
L11:
aload 0
getfield com/nd/android/u/tast/lottery/activity/LotMainActivity/ll_lot10 Landroid/widget/LinearLayout;
aload 0
getfield com/nd/android/u/tast/lottery/activity/LotMainActivity/mLotOnBgBitmapDrawable Landroid/graphics/drawable/BitmapDrawable;
invokevirtual android/widget/LinearLayout/setBackgroundDrawable(Landroid/graphics/drawable/Drawable;)V
return
L12:
aload 0
getfield com/nd/android/u/tast/lottery/activity/LotMainActivity/ll_lot11 Landroid/widget/LinearLayout;
aload 0
getfield com/nd/android/u/tast/lottery/activity/LotMainActivity/mLotOnBgBitmapDrawable Landroid/graphics/drawable/BitmapDrawable;
invokevirtual android/widget/LinearLayout/setBackgroundDrawable(Landroid/graphics/drawable/Drawable;)V
return
L13:
aload 0
getfield com/nd/android/u/tast/lottery/activity/LotMainActivity/ll_lot12 Landroid/widget/LinearLayout;
aload 0
getfield com/nd/android/u/tast/lottery/activity/LotMainActivity/mLotOnBgBitmapDrawable Landroid/graphics/drawable/BitmapDrawable;
invokevirtual android/widget/LinearLayout/setBackgroundDrawable(Landroid/graphics/drawable/Drawable;)V
return
L14:
aload 0
getfield com/nd/android/u/tast/lottery/activity/LotMainActivity/ll_lot13 Landroid/widget/LinearLayout;
aload 0
getfield com/nd/android/u/tast/lottery/activity/LotMainActivity/mLotOnBgBitmapDrawable Landroid/graphics/drawable/BitmapDrawable;
invokevirtual android/widget/LinearLayout/setBackgroundDrawable(Landroid/graphics/drawable/Drawable;)V
return
L15:
aload 0
getfield com/nd/android/u/tast/lottery/activity/LotMainActivity/ll_lot14 Landroid/widget/LinearLayout;
aload 0
getfield com/nd/android/u/tast/lottery/activity/LotMainActivity/mLotOnBgBitmapDrawable Landroid/graphics/drawable/BitmapDrawable;
invokevirtual android/widget/LinearLayout/setBackgroundDrawable(Landroid/graphics/drawable/Drawable;)V
return
L16:
aload 0
getfield com/nd/android/u/tast/lottery/activity/LotMainActivity/ll_lot15 Landroid/widget/LinearLayout;
aload 0
getfield com/nd/android/u/tast/lottery/activity/LotMainActivity/mLotOnBgBitmapDrawable Landroid/graphics/drawable/BitmapDrawable;
invokevirtual android/widget/LinearLayout/setBackgroundDrawable(Landroid/graphics/drawable/Drawable;)V
return
L17:
aload 0
getfield com/nd/android/u/tast/lottery/activity/LotMainActivity/ll_lot16 Landroid/widget/LinearLayout;
aload 0
getfield com/nd/android/u/tast/lottery/activity/LotMainActivity/mLotOnBgBitmapDrawable Landroid/graphics/drawable/BitmapDrawable;
invokevirtual android/widget/LinearLayout/setBackgroundDrawable(Landroid/graphics/drawable/Drawable;)V
return
L18:
aload 0
getfield com/nd/android/u/tast/lottery/activity/LotMainActivity/ll_lot17 Landroid/widget/LinearLayout;
aload 0
getfield com/nd/android/u/tast/lottery/activity/LotMainActivity/mLotOnBgBitmapDrawable Landroid/graphics/drawable/BitmapDrawable;
invokevirtual android/widget/LinearLayout/setBackgroundDrawable(Landroid/graphics/drawable/Drawable;)V
return
L19:
aload 0
getfield com/nd/android/u/tast/lottery/activity/LotMainActivity/ll_lot18 Landroid/widget/LinearLayout;
aload 0
getfield com/nd/android/u/tast/lottery/activity/LotMainActivity/mLotOnBgBitmapDrawable Landroid/graphics/drawable/BitmapDrawable;
invokevirtual android/widget/LinearLayout/setBackgroundDrawable(Landroid/graphics/drawable/Drawable;)V
return
L20:
aload 0
getfield com/nd/android/u/tast/lottery/activity/LotMainActivity/ll_lot19 Landroid/widget/LinearLayout;
aload 0
getfield com/nd/android/u/tast/lottery/activity/LotMainActivity/mLotOnBgBitmapDrawable Landroid/graphics/drawable/BitmapDrawable;
invokevirtual android/widget/LinearLayout/setBackgroundDrawable(Landroid/graphics/drawable/Drawable;)V
return
L21:
aload 0
getfield com/nd/android/u/tast/lottery/activity/LotMainActivity/ll_lot20 Landroid/widget/LinearLayout;
aload 0
getfield com/nd/android/u/tast/lottery/activity/LotMainActivity/mLotOnBgBitmapDrawable Landroid/graphics/drawable/BitmapDrawable;
invokevirtual android/widget/LinearLayout/setBackgroundDrawable(Landroid/graphics/drawable/Drawable;)V
return
.limit locals 3
.limit stack 3
.end method

.method private getLotteryCount()V
aload 0
getfield com/nd/android/u/tast/lottery/activity/LotMainActivity/mGetLotCountTask Lcom/common/android/utils/task/genericTask/GenericTask;
ifnull L0
aload 0
getfield com/nd/android/u/tast/lottery/activity/LotMainActivity/mGetLotCountTask Lcom/common/android/utils/task/genericTask/GenericTask;
invokevirtual com/common/android/utils/task/genericTask/GenericTask/getStatus()Landroid/os/AsyncTask$Status;
getstatic android/os/AsyncTask$Status/RUNNING Landroid/os/AsyncTask$Status;
if_acmpne L0
return
L0:
aload 0
new com/nd/android/u/tast/lottery/activity/LotMainActivity$GetLotteryCountTask
dup
aload 0
aconst_null
invokespecial com/nd/android/u/tast/lottery/activity/LotMainActivity$GetLotteryCountTask/<init>(Lcom/nd/android/u/tast/lottery/activity/LotMainActivity;Lcom/nd/android/u/tast/lottery/activity/LotMainActivity$1;)V
putfield com/nd/android/u/tast/lottery/activity/LotMainActivity/mGetLotCountTask Lcom/common/android/utils/task/genericTask/GenericTask;
aload 0
getfield com/nd/android/u/tast/lottery/activity/LotMainActivity/mGetLotCountTask Lcom/common/android/utils/task/genericTask/GenericTask;
aload 0
getfield com/nd/android/u/tast/lottery/activity/LotMainActivity/mGetLotCountTaskListener Lcom/common/android/utils/task/genericTask/TaskListener;
invokevirtual com/common/android/utils/task/genericTask/GenericTask/setListener(Lcom/common/android/utils/task/genericTask/TaskListener;)V
new com/common/android/utils/task/genericTask/TaskParams
dup
invokespecial com/common/android/utils/task/genericTask/TaskParams/<init>()V
astore 1
aload 0
getfield com/nd/android/u/tast/lottery/activity/LotMainActivity/mGetLotCountTask Lcom/common/android/utils/task/genericTask/GenericTask;
iconst_1
anewarray com/common/android/utils/task/genericTask/TaskParams
dup
iconst_0
aload 1
aastore
invokevirtual com/common/android/utils/task/genericTask/GenericTask/execute([Ljava/lang/Object;)Landroid/os/AsyncTask;
pop
return
.limit locals 2
.limit stack 5
.end method

.method private getLotteryInfo()V
aload 0
getfield com/nd/android/u/tast/lottery/activity/LotMainActivity/mGetLotInfoTask Lcom/common/android/utils/task/genericTask/GenericTask;
ifnull L0
aload 0
getfield com/nd/android/u/tast/lottery/activity/LotMainActivity/mGetLotInfoTask Lcom/common/android/utils/task/genericTask/GenericTask;
invokevirtual com/common/android/utils/task/genericTask/GenericTask/getStatus()Landroid/os/AsyncTask$Status;
getstatic android/os/AsyncTask$Status/RUNNING Landroid/os/AsyncTask$Status;
if_acmpne L0
return
L0:
aload 0
new com/nd/android/u/tast/lottery/activity/LotMainActivity$GetLotteryask
dup
aload 0
aconst_null
invokespecial com/nd/android/u/tast/lottery/activity/LotMainActivity$GetLotteryask/<init>(Lcom/nd/android/u/tast/lottery/activity/LotMainActivity;Lcom/nd/android/u/tast/lottery/activity/LotMainActivity$1;)V
putfield com/nd/android/u/tast/lottery/activity/LotMainActivity/mGetLotInfoTask Lcom/common/android/utils/task/genericTask/GenericTask;
aload 0
getfield com/nd/android/u/tast/lottery/activity/LotMainActivity/mGetLotInfoTask Lcom/common/android/utils/task/genericTask/GenericTask;
aload 0
getfield com/nd/android/u/tast/lottery/activity/LotMainActivity/mGetLotInfoTaskListener Lcom/common/android/utils/task/genericTask/TaskListener;
invokevirtual com/common/android/utils/task/genericTask/GenericTask/setListener(Lcom/common/android/utils/task/genericTask/TaskListener;)V
new com/common/android/utils/task/genericTask/TaskParams
dup
invokespecial com/common/android/utils/task/genericTask/TaskParams/<init>()V
astore 1
aload 0
getfield com/nd/android/u/tast/lottery/activity/LotMainActivity/mGetLotInfoTask Lcom/common/android/utils/task/genericTask/GenericTask;
iconst_1
anewarray com/common/android/utils/task/genericTask/TaskParams
dup
iconst_0
aload 1
aastore
invokevirtual com/common/android/utils/task/genericTask/GenericTask/execute([Ljava/lang/Object;)Landroid/os/AsyncTask;
pop
return
.limit locals 2
.limit stack 5
.end method

.method private getResidfromNum(I)I
iload 1
tableswitch 0
L0
L1
L2
L3
L4
L5
L6
L7
L8
L9
default : L10
L10:
getstatic com/nd/android/u/tasklib/R$drawable/lot_num0 I
ireturn
L0:
getstatic com/nd/android/u/tasklib/R$drawable/lot_num0 I
ireturn
L1:
getstatic com/nd/android/u/tasklib/R$drawable/lot_num1 I
ireturn
L2:
getstatic com/nd/android/u/tasklib/R$drawable/lot_num2 I
ireturn
L3:
getstatic com/nd/android/u/tasklib/R$drawable/lot_num3 I
ireturn
L4:
getstatic com/nd/android/u/tasklib/R$drawable/lot_num4 I
ireturn
L5:
getstatic com/nd/android/u/tasklib/R$drawable/lot_num5 I
ireturn
L6:
getstatic com/nd/android/u/tasklib/R$drawable/lot_num6 I
ireturn
L7:
getstatic com/nd/android/u/tasklib/R$drawable/lot_num7 I
ireturn
L8:
getstatic com/nd/android/u/tasklib/R$drawable/lot_num8 I
ireturn
L9:
getstatic com/nd/android/u/tasklib/R$drawable/lot_num9 I
ireturn
.limit locals 2
.limit stack 1
.end method

.method private initLotTimes()V
aload 0
getfield com/nd/android/u/tast/lottery/activity/LotMainActivity/mLotNum I
bipush 100
idiv
istore 1
aload 0
getfield com/nd/android/u/tast/lottery/activity/LotMainActivity/mLotNum I
bipush 100
irem
bipush 10
idiv
istore 2
aload 0
getfield com/nd/android/u/tast/lottery/activity/LotMainActivity/mLotNum I
bipush 10
irem
istore 3
iload 1
bipush 10
if_icmplt L0
aload 0
getfield com/nd/android/u/tast/lottery/activity/LotMainActivity/iv_lot_num_f Landroid/widget/ImageView;
aload 0
bipush 9
invokespecial com/nd/android/u/tast/lottery/activity/LotMainActivity/getResidfromNum(I)I
invokevirtual android/widget/ImageView/setBackgroundResource(I)V
aload 0
getfield com/nd/android/u/tast/lottery/activity/LotMainActivity/iv_lot_num_s Landroid/widget/ImageView;
aload 0
bipush 9
invokespecial com/nd/android/u/tast/lottery/activity/LotMainActivity/getResidfromNum(I)I
invokevirtual android/widget/ImageView/setBackgroundResource(I)V
aload 0
getfield com/nd/android/u/tast/lottery/activity/LotMainActivity/iv_lot_num_t Landroid/widget/ImageView;
aload 0
bipush 9
invokespecial com/nd/android/u/tast/lottery/activity/LotMainActivity/getResidfromNum(I)I
invokevirtual android/widget/ImageView/setBackgroundResource(I)V
aload 0
getfield com/nd/android/u/tast/lottery/activity/LotMainActivity/iv_lot_num_f Landroid/widget/ImageView;
iconst_0
invokevirtual android/widget/ImageView/setVisibility(I)V
aload 0
getfield com/nd/android/u/tast/lottery/activity/LotMainActivity/iv_lot_num_s Landroid/widget/ImageView;
iconst_0
invokevirtual android/widget/ImageView/setVisibility(I)V
aload 0
getfield com/nd/android/u/tast/lottery/activity/LotMainActivity/iv_lot_num_t Landroid/widget/ImageView;
iconst_0
invokevirtual android/widget/ImageView/setVisibility(I)V
return
L0:
iload 1
ifle L1
aload 0
getfield com/nd/android/u/tast/lottery/activity/LotMainActivity/iv_lot_num_f Landroid/widget/ImageView;
iconst_0
invokevirtual android/widget/ImageView/setVisibility(I)V
aload 0
getfield com/nd/android/u/tast/lottery/activity/LotMainActivity/iv_lot_num_f Landroid/widget/ImageView;
aload 0
iload 1
invokespecial com/nd/android/u/tast/lottery/activity/LotMainActivity/getResidfromNum(I)I
invokevirtual android/widget/ImageView/setBackgroundResource(I)V
aload 0
getfield com/nd/android/u/tast/lottery/activity/LotMainActivity/iv_lot_num_s Landroid/widget/ImageView;
iconst_0
invokevirtual android/widget/ImageView/setVisibility(I)V
aload 0
getfield com/nd/android/u/tast/lottery/activity/LotMainActivity/iv_lot_num_s Landroid/widget/ImageView;
aload 0
iload 2
invokespecial com/nd/android/u/tast/lottery/activity/LotMainActivity/getResidfromNum(I)I
invokevirtual android/widget/ImageView/setBackgroundResource(I)V
aload 0
getfield com/nd/android/u/tast/lottery/activity/LotMainActivity/iv_lot_num_t Landroid/widget/ImageView;
iconst_0
invokevirtual android/widget/ImageView/setVisibility(I)V
aload 0
getfield com/nd/android/u/tast/lottery/activity/LotMainActivity/iv_lot_num_t Landroid/widget/ImageView;
aload 0
iload 3
invokespecial com/nd/android/u/tast/lottery/activity/LotMainActivity/getResidfromNum(I)I
invokevirtual android/widget/ImageView/setBackgroundResource(I)V
return
L1:
aload 0
getfield com/nd/android/u/tast/lottery/activity/LotMainActivity/iv_lot_num_f Landroid/widget/ImageView;
bipush 8
invokevirtual android/widget/ImageView/setVisibility(I)V
iload 2
ifle L2
aload 0
getfield com/nd/android/u/tast/lottery/activity/LotMainActivity/iv_lot_num_s Landroid/widget/ImageView;
iconst_0
invokevirtual android/widget/ImageView/setVisibility(I)V
aload 0
getfield com/nd/android/u/tast/lottery/activity/LotMainActivity/iv_lot_num_s Landroid/widget/ImageView;
aload 0
iload 2
invokespecial com/nd/android/u/tast/lottery/activity/LotMainActivity/getResidfromNum(I)I
invokevirtual android/widget/ImageView/setBackgroundResource(I)V
aload 0
getfield com/nd/android/u/tast/lottery/activity/LotMainActivity/iv_lot_num_t Landroid/widget/ImageView;
iconst_0
invokevirtual android/widget/ImageView/setVisibility(I)V
aload 0
getfield com/nd/android/u/tast/lottery/activity/LotMainActivity/iv_lot_num_t Landroid/widget/ImageView;
aload 0
iload 3
invokespecial com/nd/android/u/tast/lottery/activity/LotMainActivity/getResidfromNum(I)I
invokevirtual android/widget/ImageView/setBackgroundResource(I)V
return
L2:
aload 0
getfield com/nd/android/u/tast/lottery/activity/LotMainActivity/iv_lot_num_s Landroid/widget/ImageView;
iconst_4
invokevirtual android/widget/ImageView/setVisibility(I)V
aload 0
getfield com/nd/android/u/tast/lottery/activity/LotMainActivity/iv_lot_num_t Landroid/widget/ImageView;
iconst_0
invokevirtual android/widget/ImageView/setVisibility(I)V
aload 0
getfield com/nd/android/u/tast/lottery/activity/LotMainActivity/iv_lot_num_t Landroid/widget/ImageView;
aload 0
iload 3
invokespecial com/nd/android/u/tast/lottery/activity/LotMainActivity/getResidfromNum(I)I
invokevirtual android/widget/ImageView/setBackgroundResource(I)V
return
.limit locals 4
.limit stack 3
.end method

.method private initLotUsersList()V
aload 0
getfield com/nd/android/u/tast/lottery/activity/LotMainActivity/mLotUsersList Ljava/util/List;
ifnonnull L0
aload 0
getfield com/nd/android/u/tast/lottery/activity/LotMainActivity/tv_no_lot_users Landroid/widget/TextView;
iconst_0
invokevirtual android/widget/TextView/setVisibility(I)V
aload 0
getfield com/nd/android/u/tast/lottery/activity/LotMainActivity/lotlay Landroid/widget/RelativeLayout;
bipush 8
invokevirtual android/widget/RelativeLayout/setVisibility(I)V
return
L0:
aload 0
getfield com/nd/android/u/tast/lottery/activity/LotMainActivity/mLotUsersList Ljava/util/List;
invokeinterface java/util/List/size()I 0
ifle L1
aload 0
getfield com/nd/android/u/tast/lottery/activity/LotMainActivity/tv_no_lot_users Landroid/widget/TextView;
bipush 8
invokevirtual android/widget/TextView/setVisibility(I)V
aload 0
getfield com/nd/android/u/tast/lottery/activity/LotMainActivity/lotlay Landroid/widget/RelativeLayout;
iconst_0
invokevirtual android/widget/RelativeLayout/setVisibility(I)V
new java/util/ArrayList
dup
invokespecial java/util/ArrayList/<init>()V
astore 1
new java/util/ArrayList
dup
invokespecial java/util/ArrayList/<init>()V
astore 2
aload 0
getfield com/nd/android/u/tast/lottery/activity/LotMainActivity/mLotUsersList Ljava/util/List;
invokeinterface java/util/List/iterator()Ljava/util/Iterator; 0
astore 3
L2:
aload 3
invokeinterface java/util/Iterator/hasNext()Z 0
ifeq L3
aload 3
invokeinterface java/util/Iterator/next()Ljava/lang/Object; 0
checkcast com/nd/android/u/tast/lottery/dataStructure/LotUsersData
astore 4
aload 4
invokevirtual com/nd/android/u/tast/lottery/dataStructure/LotUsersData/getLotUser1()Lcom/nd/android/u/tast/lottery/dataStructure/LotUserData;
ifnull L4
new java/lang/StringBuilder
dup
invokespecial java/lang/StringBuilder/<init>()V
ldc ""
invokevirtual java/lang/StringBuilder/append(Ljava/lang/String;)Ljava/lang/StringBuilder;
aload 4
invokevirtual com/nd/android/u/tast/lottery/dataStructure/LotUsersData/getLotUser1()Lcom/nd/android/u/tast/lottery/dataStructure/LotUserData;
invokevirtual com/nd/android/u/tast/lottery/dataStructure/LotUserData/getUid()J
invokevirtual java/lang/StringBuilder/append(J)Ljava/lang/StringBuilder;
invokevirtual java/lang/StringBuilder/toString()Ljava/lang/String;
astore 5
aload 4
invokevirtual com/nd/android/u/tast/lottery/dataStructure/LotUsersData/getLotUser1()Lcom/nd/android/u/tast/lottery/dataStructure/LotUserData;
invokevirtual com/nd/android/u/tast/lottery/dataStructure/LotUserData/getUser_name()Ljava/lang/String;
astore 6
aload 4
invokevirtual com/nd/android/u/tast/lottery/dataStructure/LotUsersData/getLotUser1()Lcom/nd/android/u/tast/lottery/dataStructure/LotUserData;
invokevirtual com/nd/android/u/tast/lottery/dataStructure/LotUserData/getPrize_name()Ljava/lang/String;
astore 7
aload 4
invokevirtual com/nd/android/u/tast/lottery/dataStructure/LotUsersData/getLotUser1()Lcom/nd/android/u/tast/lottery/dataStructure/LotUserData;
invokevirtual com/nd/android/u/tast/lottery/dataStructure/LotUserData/getCreate_dt()Ljava/lang/String;
astore 8
aload 5
ifnull L4
aload 6
ifnull L4
aload 7
ifnull L4
aload 8
ifnull L4
aload 1
iconst_5
anewarray java/lang/String
dup
iconst_0
aload 5
aastore
dup
iconst_1
ldc ""
aastore
dup
iconst_2
aload 6
aastore
dup
iconst_3
aload 7
aastore
dup
iconst_4
aload 8
aastore
invokeinterface java/util/List/add(Ljava/lang/Object;)Z 1
pop
L4:
aload 4
invokevirtual com/nd/android/u/tast/lottery/dataStructure/LotUsersData/getLotUser2()Lcom/nd/android/u/tast/lottery/dataStructure/LotUserData;
ifnull L2
new java/lang/StringBuilder
dup
invokespecial java/lang/StringBuilder/<init>()V
ldc ""
invokevirtual java/lang/StringBuilder/append(Ljava/lang/String;)Ljava/lang/StringBuilder;
aload 4
invokevirtual com/nd/android/u/tast/lottery/dataStructure/LotUsersData/getLotUser2()Lcom/nd/android/u/tast/lottery/dataStructure/LotUserData;
invokevirtual com/nd/android/u/tast/lottery/dataStructure/LotUserData/getUid()J
invokevirtual java/lang/StringBuilder/append(J)Ljava/lang/StringBuilder;
invokevirtual java/lang/StringBuilder/toString()Ljava/lang/String;
astore 5
aload 4
invokevirtual com/nd/android/u/tast/lottery/dataStructure/LotUsersData/getLotUser2()Lcom/nd/android/u/tast/lottery/dataStructure/LotUserData;
invokevirtual com/nd/android/u/tast/lottery/dataStructure/LotUserData/getUser_name()Ljava/lang/String;
astore 6
aload 4
invokevirtual com/nd/android/u/tast/lottery/dataStructure/LotUsersData/getLotUser2()Lcom/nd/android/u/tast/lottery/dataStructure/LotUserData;
invokevirtual com/nd/android/u/tast/lottery/dataStructure/LotUserData/getPrize_name()Ljava/lang/String;
astore 7
aload 4
invokevirtual com/nd/android/u/tast/lottery/dataStructure/LotUsersData/getLotUser2()Lcom/nd/android/u/tast/lottery/dataStructure/LotUserData;
invokevirtual com/nd/android/u/tast/lottery/dataStructure/LotUserData/getCreate_dt()Ljava/lang/String;
astore 4
aload 5
ifnull L2
aload 6
ifnull L2
aload 7
ifnull L2
aload 4
ifnull L2
aload 2
iconst_5
anewarray java/lang/String
dup
iconst_0
aload 5
aastore
dup
iconst_1
ldc ""
aastore
dup
iconst_2
aload 6
aastore
dup
iconst_3
aload 7
aastore
dup
iconst_4
aload 4
aastore
invokeinterface java/util/List/add(Ljava/lang/Object;)Z 1
pop
goto L2
L1:
aload 0
getfield com/nd/android/u/tast/lottery/activity/LotMainActivity/tv_no_lot_users Landroid/widget/TextView;
iconst_0
invokevirtual android/widget/TextView/setVisibility(I)V
aload 0
getfield com/nd/android/u/tast/lottery/activity/LotMainActivity/lotlay Landroid/widget/RelativeLayout;
bipush 8
invokevirtual android/widget/RelativeLayout/setVisibility(I)V
return
L3:
aload 0
getfield com/nd/android/u/tast/lottery/activity/LotMainActivity/scrollDoubleLayout1 Lcom/product/android/ui/widget/ScrollDoubleLayout;
aload 1
aload 2
invokevirtual com/product/android/ui/widget/ScrollDoubleLayout/update(Ljava/util/List;Ljava/util/List;)V
return
.limit locals 9
.limit stack 5
.end method

.method private initPriseList()V
aload 0
getfield com/nd/android/u/tast/lottery/activity/LotMainActivity/mLotPriseList Ljava/util/List;
invokeinterface java/util/List/size()I 0
istore 2
getstatic com/product/android/business/ApplicationVariable/INSTANCE Lcom/product/android/business/ApplicationVariable;
invokevirtual com/product/android/business/ApplicationVariable/getIUser()Lcom/product/android/business/login/IGetUserInfo;
invokeinterface com/product/android/business/login/IGetUserInfo/getSid()Ljava/lang/String; 0
astore 5
getstatic com/product/android/business/ApplicationVariable/INSTANCE Lcom/product/android/business/ApplicationVariable;
invokevirtual com/product/android/business/ApplicationVariable/getIUser()Lcom/product/android/business/login/IGetUserInfo;
invokeinterface com/product/android/business/login/IGetUserInfo/getOapUnitId()I 0
i2l
lstore 3
iconst_0
istore 1
L0:
iload 1
iload 2
if_icmpge L1
aload 0
getfield com/nd/android/u/tast/lottery/activity/LotMainActivity/mLotPriseList Ljava/util/List;
iload 1
invokeinterface java/util/List/get(I)Ljava/lang/Object; 1
checkcast com/nd/android/u/tast/lottery/dataStructure/LotPrise
astore 6
aload 0
getfield com/nd/android/u/tast/lottery/activity/LotMainActivity/JACKPOT_IMG_URL Ljava/lang/String;
iconst_3
anewarray java/lang/Object
dup
iconst_0
aload 6
invokevirtual com/nd/android/u/tast/lottery/dataStructure/LotPrise/getCate_id()J
invokestatic java/lang/Long/valueOf(J)Ljava/lang/Long;
aastore
dup
iconst_1
lload 3
invokestatic java/lang/Long/valueOf(J)Ljava/lang/Long;
aastore
dup
iconst_2
sipush 280
invokestatic java/lang/Integer/valueOf(I)Ljava/lang/Integer;
aastore
invokestatic java/lang/String/format(Ljava/lang/String;[Ljava/lang/Object;)Ljava/lang/String;
astore 7
iload 1
tableswitch 0
L2
L3
L4
L5
L6
L7
L8
L9
L10
L11
L12
L13
L14
L15
L16
L17
L18
L19
L20
L21
default : L22
L22:
iload 1
iconst_1
iadd
istore 1
goto L0
L2:
aload 0
aload 0
getfield com/nd/android/u/tast/lottery/activity/LotMainActivity/aiv_lot1_img Landroid/widget/ImageView;
aload 0
getfield com/nd/android/u/tast/lottery/activity/LotMainActivity/lot1_name Landroid/widget/TextView;
aload 5
aload 7
aload 6
invokevirtual com/nd/android/u/tast/lottery/dataStructure/LotPrise/getCate_name()Ljava/lang/String;
invokespecial com/nd/android/u/tast/lottery/activity/LotMainActivity/setValue(Landroid/widget/ImageView;Landroid/widget/TextView;Ljava/lang/String;Ljava/lang/String;Ljava/lang/String;)V
goto L22
L3:
aload 0
aload 0
getfield com/nd/android/u/tast/lottery/activity/LotMainActivity/aiv_lot2_img Landroid/widget/ImageView;
aload 0
getfield com/nd/android/u/tast/lottery/activity/LotMainActivity/lot2_name Landroid/widget/TextView;
aload 5
aload 7
aload 6
invokevirtual com/nd/android/u/tast/lottery/dataStructure/LotPrise/getCate_name()Ljava/lang/String;
invokespecial com/nd/android/u/tast/lottery/activity/LotMainActivity/setValue(Landroid/widget/ImageView;Landroid/widget/TextView;Ljava/lang/String;Ljava/lang/String;Ljava/lang/String;)V
goto L22
L4:
aload 0
aload 0
getfield com/nd/android/u/tast/lottery/activity/LotMainActivity/aiv_lot3_img Landroid/widget/ImageView;
aload 0
getfield com/nd/android/u/tast/lottery/activity/LotMainActivity/lot3_name Landroid/widget/TextView;
aload 5
aload 7
aload 6
invokevirtual com/nd/android/u/tast/lottery/dataStructure/LotPrise/getCate_name()Ljava/lang/String;
invokespecial com/nd/android/u/tast/lottery/activity/LotMainActivity/setValue(Landroid/widget/ImageView;Landroid/widget/TextView;Ljava/lang/String;Ljava/lang/String;Ljava/lang/String;)V
goto L22
L5:
aload 0
aload 0
getfield com/nd/android/u/tast/lottery/activity/LotMainActivity/aiv_lot4_img Landroid/widget/ImageView;
aload 0
getfield com/nd/android/u/tast/lottery/activity/LotMainActivity/lot4_name Landroid/widget/TextView;
aload 5
aload 7
aload 6
invokevirtual com/nd/android/u/tast/lottery/dataStructure/LotPrise/getCate_name()Ljava/lang/String;
invokespecial com/nd/android/u/tast/lottery/activity/LotMainActivity/setValue(Landroid/widget/ImageView;Landroid/widget/TextView;Ljava/lang/String;Ljava/lang/String;Ljava/lang/String;)V
goto L22
L6:
aload 0
aload 0
getfield com/nd/android/u/tast/lottery/activity/LotMainActivity/aiv_lot5_img Landroid/widget/ImageView;
aload 0
getfield com/nd/android/u/tast/lottery/activity/LotMainActivity/lot5_name Landroid/widget/TextView;
aload 5
aload 7
aload 6
invokevirtual com/nd/android/u/tast/lottery/dataStructure/LotPrise/getCate_name()Ljava/lang/String;
invokespecial com/nd/android/u/tast/lottery/activity/LotMainActivity/setValue(Landroid/widget/ImageView;Landroid/widget/TextView;Ljava/lang/String;Ljava/lang/String;Ljava/lang/String;)V
goto L22
L7:
aload 0
aload 0
getfield com/nd/android/u/tast/lottery/activity/LotMainActivity/aiv_lot6_img Landroid/widget/ImageView;
aload 0
getfield com/nd/android/u/tast/lottery/activity/LotMainActivity/lot6_name Landroid/widget/TextView;
aload 5
aload 7
aload 6
invokevirtual com/nd/android/u/tast/lottery/dataStructure/LotPrise/getCate_name()Ljava/lang/String;
invokespecial com/nd/android/u/tast/lottery/activity/LotMainActivity/setValue(Landroid/widget/ImageView;Landroid/widget/TextView;Ljava/lang/String;Ljava/lang/String;Ljava/lang/String;)V
goto L22
L8:
aload 0
aload 0
getfield com/nd/android/u/tast/lottery/activity/LotMainActivity/aiv_lot7_img Landroid/widget/ImageView;
aload 0
getfield com/nd/android/u/tast/lottery/activity/LotMainActivity/lot7_name Landroid/widget/TextView;
aload 5
aload 7
aload 6
invokevirtual com/nd/android/u/tast/lottery/dataStructure/LotPrise/getCate_name()Ljava/lang/String;
invokespecial com/nd/android/u/tast/lottery/activity/LotMainActivity/setValue(Landroid/widget/ImageView;Landroid/widget/TextView;Ljava/lang/String;Ljava/lang/String;Ljava/lang/String;)V
goto L22
L9:
aload 0
aload 0
getfield com/nd/android/u/tast/lottery/activity/LotMainActivity/aiv_lot8_img Landroid/widget/ImageView;
aload 0
getfield com/nd/android/u/tast/lottery/activity/LotMainActivity/lot8_name Landroid/widget/TextView;
aload 5
aload 7
aload 6
invokevirtual com/nd/android/u/tast/lottery/dataStructure/LotPrise/getCate_name()Ljava/lang/String;
invokespecial com/nd/android/u/tast/lottery/activity/LotMainActivity/setValue(Landroid/widget/ImageView;Landroid/widget/TextView;Ljava/lang/String;Ljava/lang/String;Ljava/lang/String;)V
goto L22
L10:
aload 0
aload 0
getfield com/nd/android/u/tast/lottery/activity/LotMainActivity/aiv_lot9_img Landroid/widget/ImageView;
aload 0
getfield com/nd/android/u/tast/lottery/activity/LotMainActivity/lot9_name Landroid/widget/TextView;
aload 5
aload 7
aload 6
invokevirtual com/nd/android/u/tast/lottery/dataStructure/LotPrise/getCate_name()Ljava/lang/String;
invokespecial com/nd/android/u/tast/lottery/activity/LotMainActivity/setValue(Landroid/widget/ImageView;Landroid/widget/TextView;Ljava/lang/String;Ljava/lang/String;Ljava/lang/String;)V
goto L22
L11:
aload 0
aload 0
getfield com/nd/android/u/tast/lottery/activity/LotMainActivity/aiv_lot10_img Landroid/widget/ImageView;
aload 0
getfield com/nd/android/u/tast/lottery/activity/LotMainActivity/lot10_name Landroid/widget/TextView;
aload 5
aload 7
aload 6
invokevirtual com/nd/android/u/tast/lottery/dataStructure/LotPrise/getCate_name()Ljava/lang/String;
invokespecial com/nd/android/u/tast/lottery/activity/LotMainActivity/setValue(Landroid/widget/ImageView;Landroid/widget/TextView;Ljava/lang/String;Ljava/lang/String;Ljava/lang/String;)V
goto L22
L12:
aload 0
aload 0
getfield com/nd/android/u/tast/lottery/activity/LotMainActivity/aiv_lot11_img Landroid/widget/ImageView;
aload 0
getfield com/nd/android/u/tast/lottery/activity/LotMainActivity/lot11_name Landroid/widget/TextView;
aload 5
aload 7
aload 6
invokevirtual com/nd/android/u/tast/lottery/dataStructure/LotPrise/getCate_name()Ljava/lang/String;
invokespecial com/nd/android/u/tast/lottery/activity/LotMainActivity/setValue(Landroid/widget/ImageView;Landroid/widget/TextView;Ljava/lang/String;Ljava/lang/String;Ljava/lang/String;)V
goto L22
L13:
aload 0
aload 0
getfield com/nd/android/u/tast/lottery/activity/LotMainActivity/aiv_lot12_img Landroid/widget/ImageView;
aload 0
getfield com/nd/android/u/tast/lottery/activity/LotMainActivity/lot12_name Landroid/widget/TextView;
aload 5
aload 7
aload 6
invokevirtual com/nd/android/u/tast/lottery/dataStructure/LotPrise/getCate_name()Ljava/lang/String;
invokespecial com/nd/android/u/tast/lottery/activity/LotMainActivity/setValue(Landroid/widget/ImageView;Landroid/widget/TextView;Ljava/lang/String;Ljava/lang/String;Ljava/lang/String;)V
goto L22
L14:
aload 0
aload 0
getfield com/nd/android/u/tast/lottery/activity/LotMainActivity/aiv_lot13_img Landroid/widget/ImageView;
aload 0
getfield com/nd/android/u/tast/lottery/activity/LotMainActivity/lot13_name Landroid/widget/TextView;
aload 5
aload 7
aload 6
invokevirtual com/nd/android/u/tast/lottery/dataStructure/LotPrise/getCate_name()Ljava/lang/String;
invokespecial com/nd/android/u/tast/lottery/activity/LotMainActivity/setValue(Landroid/widget/ImageView;Landroid/widget/TextView;Ljava/lang/String;Ljava/lang/String;Ljava/lang/String;)V
goto L22
L15:
aload 0
aload 0
getfield com/nd/android/u/tast/lottery/activity/LotMainActivity/aiv_lot14_img Landroid/widget/ImageView;
aload 0
getfield com/nd/android/u/tast/lottery/activity/LotMainActivity/lot14_name Landroid/widget/TextView;
aload 5
aload 7
aload 6
invokevirtual com/nd/android/u/tast/lottery/dataStructure/LotPrise/getCate_name()Ljava/lang/String;
invokespecial com/nd/android/u/tast/lottery/activity/LotMainActivity/setValue(Landroid/widget/ImageView;Landroid/widget/TextView;Ljava/lang/String;Ljava/lang/String;Ljava/lang/String;)V
goto L22
L16:
aload 0
aload 0
getfield com/nd/android/u/tast/lottery/activity/LotMainActivity/aiv_lot15_img Landroid/widget/ImageView;
aload 0
getfield com/nd/android/u/tast/lottery/activity/LotMainActivity/lot15_name Landroid/widget/TextView;
aload 5
aload 7
aload 6
invokevirtual com/nd/android/u/tast/lottery/dataStructure/LotPrise/getCate_name()Ljava/lang/String;
invokespecial com/nd/android/u/tast/lottery/activity/LotMainActivity/setValue(Landroid/widget/ImageView;Landroid/widget/TextView;Ljava/lang/String;Ljava/lang/String;Ljava/lang/String;)V
goto L22
L17:
aload 0
aload 0
getfield com/nd/android/u/tast/lottery/activity/LotMainActivity/aiv_lot16_img Landroid/widget/ImageView;
aload 0
getfield com/nd/android/u/tast/lottery/activity/LotMainActivity/lot16_name Landroid/widget/TextView;
aload 5
aload 7
aload 6
invokevirtual com/nd/android/u/tast/lottery/dataStructure/LotPrise/getCate_name()Ljava/lang/String;
invokespecial com/nd/android/u/tast/lottery/activity/LotMainActivity/setValue(Landroid/widget/ImageView;Landroid/widget/TextView;Ljava/lang/String;Ljava/lang/String;Ljava/lang/String;)V
goto L22
L18:
aload 0
aload 0
getfield com/nd/android/u/tast/lottery/activity/LotMainActivity/aiv_lot17_img Landroid/widget/ImageView;
aload 0
getfield com/nd/android/u/tast/lottery/activity/LotMainActivity/lot17_name Landroid/widget/TextView;
aload 5
aload 7
aload 6
invokevirtual com/nd/android/u/tast/lottery/dataStructure/LotPrise/getCate_name()Ljava/lang/String;
invokespecial com/nd/android/u/tast/lottery/activity/LotMainActivity/setValue(Landroid/widget/ImageView;Landroid/widget/TextView;Ljava/lang/String;Ljava/lang/String;Ljava/lang/String;)V
goto L22
L19:
aload 0
aload 0
getfield com/nd/android/u/tast/lottery/activity/LotMainActivity/aiv_lot18_img Landroid/widget/ImageView;
aload 0
getfield com/nd/android/u/tast/lottery/activity/LotMainActivity/lot18_name Landroid/widget/TextView;
aload 5
aload 7
aload 6
invokevirtual com/nd/android/u/tast/lottery/dataStructure/LotPrise/getCate_name()Ljava/lang/String;
invokespecial com/nd/android/u/tast/lottery/activity/LotMainActivity/setValue(Landroid/widget/ImageView;Landroid/widget/TextView;Ljava/lang/String;Ljava/lang/String;Ljava/lang/String;)V
goto L22
L20:
aload 0
aload 0
getfield com/nd/android/u/tast/lottery/activity/LotMainActivity/aiv_lot19_img Landroid/widget/ImageView;
aload 0
getfield com/nd/android/u/tast/lottery/activity/LotMainActivity/lot19_name Landroid/widget/TextView;
aload 5
aload 7
aload 6
invokevirtual com/nd/android/u/tast/lottery/dataStructure/LotPrise/getCate_name()Ljava/lang/String;
invokespecial com/nd/android/u/tast/lottery/activity/LotMainActivity/setValue(Landroid/widget/ImageView;Landroid/widget/TextView;Ljava/lang/String;Ljava/lang/String;Ljava/lang/String;)V
goto L22
L21:
aload 0
aload 0
getfield com/nd/android/u/tast/lottery/activity/LotMainActivity/aiv_lot20_img Landroid/widget/ImageView;
aload 0
getfield com/nd/android/u/tast/lottery/activity/LotMainActivity/lot20_name Landroid/widget/TextView;
aload 5
aload 7
aload 6
invokevirtual com/nd/android/u/tast/lottery/dataStructure/LotPrise/getCate_name()Ljava/lang/String;
invokespecial com/nd/android/u/tast/lottery/activity/LotMainActivity/setValue(Landroid/widget/ImageView;Landroid/widget/TextView;Ljava/lang/String;Ljava/lang/String;Ljava/lang/String;)V
goto L22
L1:
return
.limit locals 8
.limit stack 6
.end method

.method private setValue(Landroid/widget/ImageView;Landroid/widget/TextView;Ljava/lang/String;Ljava/lang/String;Ljava/lang/String;)V
invokestatic com/nostra13/universalimageloader/core/ImageLoader/getInstance()Lcom/nostra13/universalimageloader/core/ImageLoader;
aload 4
aload 1
getstatic com/nd/android/u/tast/buss/TaskModelManager/INSTANCE Lcom/nd/android/u/tast/buss/TaskModelManager;
getfield com/nd/android/u/tast/buss/TaskModelManager/taskImageOptions Lcom/nostra13/universalimageloader/core/DisplayImageOptions;
invokevirtual com/nostra13/universalimageloader/core/ImageLoader/displayImage(Ljava/lang/String;Landroid/widget/ImageView;Lcom/nostra13/universalimageloader/core/DisplayImageOptions;)V
aload 2
aload 5
invokevirtual android/widget/TextView/setText(Ljava/lang/CharSequence;)V
return
.limit locals 6
.limit stack 4
.end method

.method protected initComponent()V
aload 0
aload 0
getstatic com/nd/android/u/tasklib/R$id/btn_back I
invokevirtual com/nd/android/u/tast/lottery/activity/LotMainActivity/findViewById(I)Landroid/view/View;
checkcast android/widget/ImageButton
putfield com/nd/android/u/tast/lottery/activity/LotMainActivity/btn_back Landroid/widget/ImageButton;
aload 0
getfield com/nd/android/u/tast/lottery/activity/LotMainActivity/btn_back Landroid/widget/ImageButton;
aload 0
invokevirtual android/widget/ImageButton/setOnClickListener(Landroid/view/View$OnClickListener;)V
aload 0
aload 0
getstatic com/nd/android/u/tasklib/R$id/scroll_lot_users1 I
invokevirtual com/nd/android/u/tast/lottery/activity/LotMainActivity/findViewById(I)Landroid/view/View;
checkcast com/product/android/ui/widget/ScrollDoubleLayout
putfield com/nd/android/u/tast/lottery/activity/LotMainActivity/scrollDoubleLayout1 Lcom/product/android/ui/widget/ScrollDoubleLayout;
aload 0
getfield com/nd/android/u/tast/lottery/activity/LotMainActivity/scrollDoubleLayout1 Lcom/product/android/ui/widget/ScrollDoubleLayout;
aload 0
invokevirtual com/product/android/ui/widget/ScrollDoubleLayout/setOnClickListener(Landroid/view/View$OnClickListener;)V
aload 0
aload 0
getstatic com/nd/android/u/tasklib/R$id/lotlay I
invokevirtual com/nd/android/u/tast/lottery/activity/LotMainActivity/findViewById(I)Landroid/view/View;
checkcast android/widget/RelativeLayout
putfield com/nd/android/u/tast/lottery/activity/LotMainActivity/lotlay Landroid/widget/RelativeLayout;
aload 0
aload 0
getstatic com/nd/android/u/tasklib/R$id/tv_no_lot_users I
invokevirtual com/nd/android/u/tast/lottery/activity/LotMainActivity/findViewById(I)Landroid/view/View;
checkcast android/widget/TextView
putfield com/nd/android/u/tast/lottery/activity/LotMainActivity/tv_no_lot_users Landroid/widget/TextView;
aload 0
getfield com/nd/android/u/tast/lottery/activity/LotMainActivity/tv_no_lot_users Landroid/widget/TextView;
aload 0
invokevirtual android/widget/TextView/setOnClickListener(Landroid/view/View$OnClickListener;)V
aload 0
aload 0
getstatic com/nd/android/u/tasklib/R$id/ll_start_lot I
invokevirtual com/nd/android/u/tast/lottery/activity/LotMainActivity/findViewById(I)Landroid/view/View;
checkcast android/widget/LinearLayout
putfield com/nd/android/u/tast/lottery/activity/LotMainActivity/ll_start_lot Landroid/widget/LinearLayout;
aload 0
getfield com/nd/android/u/tast/lottery/activity/LotMainActivity/ll_start_lot Landroid/widget/LinearLayout;
aload 0
invokevirtual android/widget/LinearLayout/setOnClickListener(Landroid/view/View$OnClickListener;)V
aload 0
getfield com/nd/android/u/tast/lottery/activity/LotMainActivity/mItemtype I
sipush 10001
if_icmpne L0
aload 0
getstatic com/nd/android/u/tasklib/R$id/iv_new_year_tip I
invokevirtual com/nd/android/u/tast/lottery/activity/LotMainActivity/findViewById(I)Landroid/view/View;
checkcast android/widget/ImageView
astore 2
aload 2
iconst_0
invokevirtual android/widget/ImageView/setVisibility(I)V
aload 2
getstatic com/nd/android/u/tasklib/R$drawable/lot_new_year_tip I
invokevirtual android/widget/ImageView/setBackgroundResource(I)V
L1:
aload 0
aload 0
getstatic com/nd/android/u/tasklib/R$id/ll_lot1 I
invokevirtual com/nd/android/u/tast/lottery/activity/LotMainActivity/findViewById(I)Landroid/view/View;
checkcast android/widget/LinearLayout
putfield com/nd/android/u/tast/lottery/activity/LotMainActivity/ll_lot1 Landroid/widget/LinearLayout;
aload 0
aload 0
getstatic com/nd/android/u/tasklib/R$id/ll_lot2 I
invokevirtual com/nd/android/u/tast/lottery/activity/LotMainActivity/findViewById(I)Landroid/view/View;
checkcast android/widget/LinearLayout
putfield com/nd/android/u/tast/lottery/activity/LotMainActivity/ll_lot2 Landroid/widget/LinearLayout;
aload 0
aload 0
getstatic com/nd/android/u/tasklib/R$id/ll_lot3 I
invokevirtual com/nd/android/u/tast/lottery/activity/LotMainActivity/findViewById(I)Landroid/view/View;
checkcast android/widget/LinearLayout
putfield com/nd/android/u/tast/lottery/activity/LotMainActivity/ll_lot3 Landroid/widget/LinearLayout;
aload 0
aload 0
getstatic com/nd/android/u/tasklib/R$id/ll_lot4 I
invokevirtual com/nd/android/u/tast/lottery/activity/LotMainActivity/findViewById(I)Landroid/view/View;
checkcast android/widget/LinearLayout
putfield com/nd/android/u/tast/lottery/activity/LotMainActivity/ll_lot4 Landroid/widget/LinearLayout;
aload 0
aload 0
getstatic com/nd/android/u/tasklib/R$id/ll_lot5 I
invokevirtual com/nd/android/u/tast/lottery/activity/LotMainActivity/findViewById(I)Landroid/view/View;
checkcast android/widget/LinearLayout
putfield com/nd/android/u/tast/lottery/activity/LotMainActivity/ll_lot5 Landroid/widget/LinearLayout;
aload 0
aload 0
getstatic com/nd/android/u/tasklib/R$id/ll_lot6 I
invokevirtual com/nd/android/u/tast/lottery/activity/LotMainActivity/findViewById(I)Landroid/view/View;
checkcast android/widget/LinearLayout
putfield com/nd/android/u/tast/lottery/activity/LotMainActivity/ll_lot6 Landroid/widget/LinearLayout;
aload 0
aload 0
getstatic com/nd/android/u/tasklib/R$id/ll_lot7 I
invokevirtual com/nd/android/u/tast/lottery/activity/LotMainActivity/findViewById(I)Landroid/view/View;
checkcast android/widget/LinearLayout
putfield com/nd/android/u/tast/lottery/activity/LotMainActivity/ll_lot7 Landroid/widget/LinearLayout;
aload 0
aload 0
getstatic com/nd/android/u/tasklib/R$id/ll_lot8 I
invokevirtual com/nd/android/u/tast/lottery/activity/LotMainActivity/findViewById(I)Landroid/view/View;
checkcast android/widget/LinearLayout
putfield com/nd/android/u/tast/lottery/activity/LotMainActivity/ll_lot8 Landroid/widget/LinearLayout;
aload 0
aload 0
getstatic com/nd/android/u/tasklib/R$id/ll_lot9 I
invokevirtual com/nd/android/u/tast/lottery/activity/LotMainActivity/findViewById(I)Landroid/view/View;
checkcast android/widget/LinearLayout
putfield com/nd/android/u/tast/lottery/activity/LotMainActivity/ll_lot9 Landroid/widget/LinearLayout;
aload 0
aload 0
getstatic com/nd/android/u/tasklib/R$id/ll_lot10 I
invokevirtual com/nd/android/u/tast/lottery/activity/LotMainActivity/findViewById(I)Landroid/view/View;
checkcast android/widget/LinearLayout
putfield com/nd/android/u/tast/lottery/activity/LotMainActivity/ll_lot10 Landroid/widget/LinearLayout;
aload 0
aload 0
getstatic com/nd/android/u/tasklib/R$id/ll_lot11 I
invokevirtual com/nd/android/u/tast/lottery/activity/LotMainActivity/findViewById(I)Landroid/view/View;
checkcast android/widget/LinearLayout
putfield com/nd/android/u/tast/lottery/activity/LotMainActivity/ll_lot11 Landroid/widget/LinearLayout;
aload 0
aload 0
getstatic com/nd/android/u/tasklib/R$id/ll_lot12 I
invokevirtual com/nd/android/u/tast/lottery/activity/LotMainActivity/findViewById(I)Landroid/view/View;
checkcast android/widget/LinearLayout
putfield com/nd/android/u/tast/lottery/activity/LotMainActivity/ll_lot12 Landroid/widget/LinearLayout;
aload 0
aload 0
getstatic com/nd/android/u/tasklib/R$id/ll_lot13 I
invokevirtual com/nd/android/u/tast/lottery/activity/LotMainActivity/findViewById(I)Landroid/view/View;
checkcast android/widget/LinearLayout
putfield com/nd/android/u/tast/lottery/activity/LotMainActivity/ll_lot13 Landroid/widget/LinearLayout;
aload 0
aload 0
getstatic com/nd/android/u/tasklib/R$id/ll_lot14 I
invokevirtual com/nd/android/u/tast/lottery/activity/LotMainActivity/findViewById(I)Landroid/view/View;
checkcast android/widget/LinearLayout
putfield com/nd/android/u/tast/lottery/activity/LotMainActivity/ll_lot14 Landroid/widget/LinearLayout;
aload 0
aload 0
getstatic com/nd/android/u/tasklib/R$id/ll_lot15 I
invokevirtual com/nd/android/u/tast/lottery/activity/LotMainActivity/findViewById(I)Landroid/view/View;
checkcast android/widget/LinearLayout
putfield com/nd/android/u/tast/lottery/activity/LotMainActivity/ll_lot15 Landroid/widget/LinearLayout;
aload 0
aload 0
getstatic com/nd/android/u/tasklib/R$id/ll_lot16 I
invokevirtual com/nd/android/u/tast/lottery/activity/LotMainActivity/findViewById(I)Landroid/view/View;
checkcast android/widget/LinearLayout
putfield com/nd/android/u/tast/lottery/activity/LotMainActivity/ll_lot16 Landroid/widget/LinearLayout;
aload 0
aload 0
getstatic com/nd/android/u/tasklib/R$id/ll_lot17 I
invokevirtual com/nd/android/u/tast/lottery/activity/LotMainActivity/findViewById(I)Landroid/view/View;
checkcast android/widget/LinearLayout
putfield com/nd/android/u/tast/lottery/activity/LotMainActivity/ll_lot17 Landroid/widget/LinearLayout;
aload 0
aload 0
getstatic com/nd/android/u/tasklib/R$id/ll_lot18 I
invokevirtual com/nd/android/u/tast/lottery/activity/LotMainActivity/findViewById(I)Landroid/view/View;
checkcast android/widget/LinearLayout
putfield com/nd/android/u/tast/lottery/activity/LotMainActivity/ll_lot18 Landroid/widget/LinearLayout;
aload 0
aload 0
getstatic com/nd/android/u/tasklib/R$id/ll_lot19 I
invokevirtual com/nd/android/u/tast/lottery/activity/LotMainActivity/findViewById(I)Landroid/view/View;
checkcast android/widget/LinearLayout
putfield com/nd/android/u/tast/lottery/activity/LotMainActivity/ll_lot19 Landroid/widget/LinearLayout;
aload 0
aload 0
getstatic com/nd/android/u/tasklib/R$id/ll_lot20 I
invokevirtual com/nd/android/u/tast/lottery/activity/LotMainActivity/findViewById(I)Landroid/view/View;
checkcast android/widget/LinearLayout
putfield com/nd/android/u/tast/lottery/activity/LotMainActivity/ll_lot20 Landroid/widget/LinearLayout;
aload 0
aload 0
getstatic com/nd/android/u/tasklib/R$id/aiv_lot1_img I
invokevirtual com/nd/android/u/tast/lottery/activity/LotMainActivity/findViewById(I)Landroid/view/View;
checkcast android/widget/ImageView
putfield com/nd/android/u/tast/lottery/activity/LotMainActivity/aiv_lot1_img Landroid/widget/ImageView;
aload 0
aload 0
getstatic com/nd/android/u/tasklib/R$id/aiv_lot2_img I
invokevirtual com/nd/android/u/tast/lottery/activity/LotMainActivity/findViewById(I)Landroid/view/View;
checkcast android/widget/ImageView
putfield com/nd/android/u/tast/lottery/activity/LotMainActivity/aiv_lot2_img Landroid/widget/ImageView;
aload 0
aload 0
getstatic com/nd/android/u/tasklib/R$id/aiv_lot3_img I
invokevirtual com/nd/android/u/tast/lottery/activity/LotMainActivity/findViewById(I)Landroid/view/View;
checkcast android/widget/ImageView
putfield com/nd/android/u/tast/lottery/activity/LotMainActivity/aiv_lot3_img Landroid/widget/ImageView;
aload 0
aload 0
getstatic com/nd/android/u/tasklib/R$id/aiv_lot4_img I
invokevirtual com/nd/android/u/tast/lottery/activity/LotMainActivity/findViewById(I)Landroid/view/View;
checkcast android/widget/ImageView
putfield com/nd/android/u/tast/lottery/activity/LotMainActivity/aiv_lot4_img Landroid/widget/ImageView;
aload 0
aload 0
getstatic com/nd/android/u/tasklib/R$id/aiv_lot5_img I
invokevirtual com/nd/android/u/tast/lottery/activity/LotMainActivity/findViewById(I)Landroid/view/View;
checkcast android/widget/ImageView
putfield com/nd/android/u/tast/lottery/activity/LotMainActivity/aiv_lot5_img Landroid/widget/ImageView;
aload 0
aload 0
getstatic com/nd/android/u/tasklib/R$id/aiv_lot6_img I
invokevirtual com/nd/android/u/tast/lottery/activity/LotMainActivity/findViewById(I)Landroid/view/View;
checkcast android/widget/ImageView
putfield com/nd/android/u/tast/lottery/activity/LotMainActivity/aiv_lot6_img Landroid/widget/ImageView;
aload 0
aload 0
getstatic com/nd/android/u/tasklib/R$id/aiv_lot7_img I
invokevirtual com/nd/android/u/tast/lottery/activity/LotMainActivity/findViewById(I)Landroid/view/View;
checkcast android/widget/ImageView
putfield com/nd/android/u/tast/lottery/activity/LotMainActivity/aiv_lot7_img Landroid/widget/ImageView;
aload 0
aload 0
getstatic com/nd/android/u/tasklib/R$id/aiv_lot8_img I
invokevirtual com/nd/android/u/tast/lottery/activity/LotMainActivity/findViewById(I)Landroid/view/View;
checkcast android/widget/ImageView
putfield com/nd/android/u/tast/lottery/activity/LotMainActivity/aiv_lot8_img Landroid/widget/ImageView;
aload 0
aload 0
getstatic com/nd/android/u/tasklib/R$id/aiv_lot9_img I
invokevirtual com/nd/android/u/tast/lottery/activity/LotMainActivity/findViewById(I)Landroid/view/View;
checkcast android/widget/ImageView
putfield com/nd/android/u/tast/lottery/activity/LotMainActivity/aiv_lot9_img Landroid/widget/ImageView;
aload 0
aload 0
getstatic com/nd/android/u/tasklib/R$id/aiv_lot10_img I
invokevirtual com/nd/android/u/tast/lottery/activity/LotMainActivity/findViewById(I)Landroid/view/View;
checkcast android/widget/ImageView
putfield com/nd/android/u/tast/lottery/activity/LotMainActivity/aiv_lot10_img Landroid/widget/ImageView;
aload 0
aload 0
getstatic com/nd/android/u/tasklib/R$id/aiv_lot11_img I
invokevirtual com/nd/android/u/tast/lottery/activity/LotMainActivity/findViewById(I)Landroid/view/View;
checkcast android/widget/ImageView
putfield com/nd/android/u/tast/lottery/activity/LotMainActivity/aiv_lot11_img Landroid/widget/ImageView;
aload 0
aload 0
getstatic com/nd/android/u/tasklib/R$id/aiv_lot12_img I
invokevirtual com/nd/android/u/tast/lottery/activity/LotMainActivity/findViewById(I)Landroid/view/View;
checkcast android/widget/ImageView
putfield com/nd/android/u/tast/lottery/activity/LotMainActivity/aiv_lot12_img Landroid/widget/ImageView;
aload 0
aload 0
getstatic com/nd/android/u/tasklib/R$id/aiv_lot13_img I
invokevirtual com/nd/android/u/tast/lottery/activity/LotMainActivity/findViewById(I)Landroid/view/View;
checkcast android/widget/ImageView
putfield com/nd/android/u/tast/lottery/activity/LotMainActivity/aiv_lot13_img Landroid/widget/ImageView;
aload 0
aload 0
getstatic com/nd/android/u/tasklib/R$id/aiv_lot14_img I
invokevirtual com/nd/android/u/tast/lottery/activity/LotMainActivity/findViewById(I)Landroid/view/View;
checkcast android/widget/ImageView
putfield com/nd/android/u/tast/lottery/activity/LotMainActivity/aiv_lot14_img Landroid/widget/ImageView;
aload 0
aload 0
getstatic com/nd/android/u/tasklib/R$id/aiv_lot15_img I
invokevirtual com/nd/android/u/tast/lottery/activity/LotMainActivity/findViewById(I)Landroid/view/View;
checkcast android/widget/ImageView
putfield com/nd/android/u/tast/lottery/activity/LotMainActivity/aiv_lot15_img Landroid/widget/ImageView;
aload 0
aload 0
getstatic com/nd/android/u/tasklib/R$id/aiv_lot16_img I
invokevirtual com/nd/android/u/tast/lottery/activity/LotMainActivity/findViewById(I)Landroid/view/View;
checkcast android/widget/ImageView
putfield com/nd/android/u/tast/lottery/activity/LotMainActivity/aiv_lot16_img Landroid/widget/ImageView;
aload 0
aload 0
getstatic com/nd/android/u/tasklib/R$id/aiv_lot17_img I
invokevirtual com/nd/android/u/tast/lottery/activity/LotMainActivity/findViewById(I)Landroid/view/View;
checkcast android/widget/ImageView
putfield com/nd/android/u/tast/lottery/activity/LotMainActivity/aiv_lot17_img Landroid/widget/ImageView;
aload 0
aload 0
getstatic com/nd/android/u/tasklib/R$id/aiv_lot18_img I
invokevirtual com/nd/android/u/tast/lottery/activity/LotMainActivity/findViewById(I)Landroid/view/View;
checkcast android/widget/ImageView
putfield com/nd/android/u/tast/lottery/activity/LotMainActivity/aiv_lot18_img Landroid/widget/ImageView;
aload 0
aload 0
getstatic com/nd/android/u/tasklib/R$id/aiv_lot19_img I
invokevirtual com/nd/android/u/tast/lottery/activity/LotMainActivity/findViewById(I)Landroid/view/View;
checkcast android/widget/ImageView
putfield com/nd/android/u/tast/lottery/activity/LotMainActivity/aiv_lot19_img Landroid/widget/ImageView;
aload 0
aload 0
getstatic com/nd/android/u/tasklib/R$id/aiv_lot20_img I
invokevirtual com/nd/android/u/tast/lottery/activity/LotMainActivity/findViewById(I)Landroid/view/View;
checkcast android/widget/ImageView
putfield com/nd/android/u/tast/lottery/activity/LotMainActivity/aiv_lot20_img Landroid/widget/ImageView;
aload 0
aload 0
getstatic com/nd/android/u/tasklib/R$id/lot1_name I
invokevirtual com/nd/android/u/tast/lottery/activity/LotMainActivity/findViewById(I)Landroid/view/View;
checkcast android/widget/TextView
putfield com/nd/android/u/tast/lottery/activity/LotMainActivity/lot1_name Landroid/widget/TextView;
aload 0
aload 0
getstatic com/nd/android/u/tasklib/R$id/lot2_name I
invokevirtual com/nd/android/u/tast/lottery/activity/LotMainActivity/findViewById(I)Landroid/view/View;
checkcast android/widget/TextView
putfield com/nd/android/u/tast/lottery/activity/LotMainActivity/lot2_name Landroid/widget/TextView;
aload 0
aload 0
getstatic com/nd/android/u/tasklib/R$id/lot3_name I
invokevirtual com/nd/android/u/tast/lottery/activity/LotMainActivity/findViewById(I)Landroid/view/View;
checkcast android/widget/TextView
putfield com/nd/android/u/tast/lottery/activity/LotMainActivity/lot3_name Landroid/widget/TextView;
aload 0
aload 0
getstatic com/nd/android/u/tasklib/R$id/lot4_name I
invokevirtual com/nd/android/u/tast/lottery/activity/LotMainActivity/findViewById(I)Landroid/view/View;
checkcast android/widget/TextView
putfield com/nd/android/u/tast/lottery/activity/LotMainActivity/lot4_name Landroid/widget/TextView;
aload 0
aload 0
getstatic com/nd/android/u/tasklib/R$id/lot5_name I
invokevirtual com/nd/android/u/tast/lottery/activity/LotMainActivity/findViewById(I)Landroid/view/View;
checkcast android/widget/TextView
putfield com/nd/android/u/tast/lottery/activity/LotMainActivity/lot5_name Landroid/widget/TextView;
aload 0
aload 0
getstatic com/nd/android/u/tasklib/R$id/lot6_name I
invokevirtual com/nd/android/u/tast/lottery/activity/LotMainActivity/findViewById(I)Landroid/view/View;
checkcast android/widget/TextView
putfield com/nd/android/u/tast/lottery/activity/LotMainActivity/lot6_name Landroid/widget/TextView;
aload 0
aload 0
getstatic com/nd/android/u/tasklib/R$id/lot7_name I
invokevirtual com/nd/android/u/tast/lottery/activity/LotMainActivity/findViewById(I)Landroid/view/View;
checkcast android/widget/TextView
putfield com/nd/android/u/tast/lottery/activity/LotMainActivity/lot7_name Landroid/widget/TextView;
aload 0
aload 0
getstatic com/nd/android/u/tasklib/R$id/lot8_name I
invokevirtual com/nd/android/u/tast/lottery/activity/LotMainActivity/findViewById(I)Landroid/view/View;
checkcast android/widget/TextView
putfield com/nd/android/u/tast/lottery/activity/LotMainActivity/lot8_name Landroid/widget/TextView;
aload 0
aload 0
getstatic com/nd/android/u/tasklib/R$id/lot9_name I
invokevirtual com/nd/android/u/tast/lottery/activity/LotMainActivity/findViewById(I)Landroid/view/View;
checkcast android/widget/TextView
putfield com/nd/android/u/tast/lottery/activity/LotMainActivity/lot9_name Landroid/widget/TextView;
aload 0
aload 0
getstatic com/nd/android/u/tasklib/R$id/lot10_name I
invokevirtual com/nd/android/u/tast/lottery/activity/LotMainActivity/findViewById(I)Landroid/view/View;
checkcast android/widget/TextView
putfield com/nd/android/u/tast/lottery/activity/LotMainActivity/lot10_name Landroid/widget/TextView;
aload 0
aload 0
getstatic com/nd/android/u/tasklib/R$id/lot11_name I
invokevirtual com/nd/android/u/tast/lottery/activity/LotMainActivity/findViewById(I)Landroid/view/View;
checkcast android/widget/TextView
putfield com/nd/android/u/tast/lottery/activity/LotMainActivity/lot11_name Landroid/widget/TextView;
aload 0
aload 0
getstatic com/nd/android/u/tasklib/R$id/lot12_name I
invokevirtual com/nd/android/u/tast/lottery/activity/LotMainActivity/findViewById(I)Landroid/view/View;
checkcast android/widget/TextView
putfield com/nd/android/u/tast/lottery/activity/LotMainActivity/lot12_name Landroid/widget/TextView;
aload 0
aload 0
getstatic com/nd/android/u/tasklib/R$id/lot13_name I
invokevirtual com/nd/android/u/tast/lottery/activity/LotMainActivity/findViewById(I)Landroid/view/View;
checkcast android/widget/TextView
putfield com/nd/android/u/tast/lottery/activity/LotMainActivity/lot13_name Landroid/widget/TextView;
aload 0
aload 0
getstatic com/nd/android/u/tasklib/R$id/lot14_name I
invokevirtual com/nd/android/u/tast/lottery/activity/LotMainActivity/findViewById(I)Landroid/view/View;
checkcast android/widget/TextView
putfield com/nd/android/u/tast/lottery/activity/LotMainActivity/lot14_name Landroid/widget/TextView;
aload 0
aload 0
getstatic com/nd/android/u/tasklib/R$id/lot15_name I
invokevirtual com/nd/android/u/tast/lottery/activity/LotMainActivity/findViewById(I)Landroid/view/View;
checkcast android/widget/TextView
putfield com/nd/android/u/tast/lottery/activity/LotMainActivity/lot15_name Landroid/widget/TextView;
aload 0
aload 0
getstatic com/nd/android/u/tasklib/R$id/lot16_name I
invokevirtual com/nd/android/u/tast/lottery/activity/LotMainActivity/findViewById(I)Landroid/view/View;
checkcast android/widget/TextView
putfield com/nd/android/u/tast/lottery/activity/LotMainActivity/lot16_name Landroid/widget/TextView;
aload 0
aload 0
getstatic com/nd/android/u/tasklib/R$id/lot17_name I
invokevirtual com/nd/android/u/tast/lottery/activity/LotMainActivity/findViewById(I)Landroid/view/View;
checkcast android/widget/TextView
putfield com/nd/android/u/tast/lottery/activity/LotMainActivity/lot17_name Landroid/widget/TextView;
aload 0
aload 0
getstatic com/nd/android/u/tasklib/R$id/lot18_name I
invokevirtual com/nd/android/u/tast/lottery/activity/LotMainActivity/findViewById(I)Landroid/view/View;
checkcast android/widget/TextView
putfield com/nd/android/u/tast/lottery/activity/LotMainActivity/lot18_name Landroid/widget/TextView;
aload 0
aload 0
getstatic com/nd/android/u/tasklib/R$id/lot19_name I
invokevirtual com/nd/android/u/tast/lottery/activity/LotMainActivity/findViewById(I)Landroid/view/View;
checkcast android/widget/TextView
putfield com/nd/android/u/tast/lottery/activity/LotMainActivity/lot19_name Landroid/widget/TextView;
aload 0
aload 0
getstatic com/nd/android/u/tasklib/R$id/lot20_name I
invokevirtual com/nd/android/u/tast/lottery/activity/LotMainActivity/findViewById(I)Landroid/view/View;
checkcast android/widget/TextView
putfield com/nd/android/u/tast/lottery/activity/LotMainActivity/lot20_name Landroid/widget/TextView;
aload 0
aload 0
getstatic com/nd/android/u/tasklib/R$id/ll_lot0105 I
invokevirtual com/nd/android/u/tast/lottery/activity/LotMainActivity/findViewById(I)Landroid/view/View;
checkcast android/widget/LinearLayout
putfield com/nd/android/u/tast/lottery/activity/LotMainActivity/ll_lot0105 Landroid/widget/LinearLayout;
aload 0
aload 0
getstatic com/nd/android/u/tasklib/R$id/ll_lot0610 I
invokevirtual com/nd/android/u/tast/lottery/activity/LotMainActivity/findViewById(I)Landroid/view/View;
checkcast android/widget/LinearLayout
putfield com/nd/android/u/tast/lottery/activity/LotMainActivity/ll_lot0610 Landroid/widget/LinearLayout;
aload 0
aload 0
getstatic com/nd/android/u/tasklib/R$id/ll_lot1115 I
invokevirtual com/nd/android/u/tast/lottery/activity/LotMainActivity/findViewById(I)Landroid/view/View;
checkcast android/widget/LinearLayout
putfield com/nd/android/u/tast/lottery/activity/LotMainActivity/ll_lot1115 Landroid/widget/LinearLayout;
aload 0
aload 0
getstatic com/nd/android/u/tasklib/R$id/ll_lot1620 I
invokevirtual com/nd/android/u/tast/lottery/activity/LotMainActivity/findViewById(I)Landroid/view/View;
checkcast android/widget/LinearLayout
putfield com/nd/android/u/tast/lottery/activity/LotMainActivity/ll_lot1620 Landroid/widget/LinearLayout;
aload 0
aload 0
getstatic com/nd/android/u/tasklib/R$id/iv_lot_num_f I
invokevirtual com/nd/android/u/tast/lottery/activity/LotMainActivity/findViewById(I)Landroid/view/View;
checkcast android/widget/ImageView
putfield com/nd/android/u/tast/lottery/activity/LotMainActivity/iv_lot_num_f Landroid/widget/ImageView;
aload 0
aload 0
getstatic com/nd/android/u/tasklib/R$id/iv_lot_num_s I
invokevirtual com/nd/android/u/tast/lottery/activity/LotMainActivity/findViewById(I)Landroid/view/View;
checkcast android/widget/ImageView
putfield com/nd/android/u/tast/lottery/activity/LotMainActivity/iv_lot_num_s Landroid/widget/ImageView;
aload 0
aload 0
getstatic com/nd/android/u/tasklib/R$id/iv_lot_num_t I
invokevirtual com/nd/android/u/tast/lottery/activity/LotMainActivity/findViewById(I)Landroid/view/View;
checkcast android/widget/ImageView
putfield com/nd/android/u/tast/lottery/activity/LotMainActivity/iv_lot_num_t Landroid/widget/ImageView;
new android/util/DisplayMetrics
dup
invokespecial android/util/DisplayMetrics/<init>()V
astore 2
aload 0
invokevirtual com/nd/android/u/tast/lottery/activity/LotMainActivity/getWindowManager()Landroid/view/WindowManager;
invokeinterface android/view/WindowManager/getDefaultDisplay()Landroid/view/Display; 0
aload 2
invokevirtual android/view/Display/getMetrics(Landroid/util/DisplayMetrics;)V
aload 2
getfield android/util/DisplayMetrics/widthPixels I
ifle L2
aload 2
getfield android/util/DisplayMetrics/widthPixels I
iconst_5
idiv
istore 1
iload 1
ifle L2
aload 0
getfield com/nd/android/u/tast/lottery/activity/LotMainActivity/ll_lot0105 Landroid/widget/LinearLayout;
invokevirtual android/widget/LinearLayout/getLayoutParams()Landroid/view/ViewGroup$LayoutParams;
checkcast android/widget/RelativeLayout$LayoutParams
astore 2
aload 2
iload 1
putfield android/widget/RelativeLayout$LayoutParams/height I
aload 0
getfield com/nd/android/u/tast/lottery/activity/LotMainActivity/ll_lot0105 Landroid/widget/LinearLayout;
aload 2
invokevirtual android/widget/LinearLayout/setLayoutParams(Landroid/view/ViewGroup$LayoutParams;)V
aload 0
getfield com/nd/android/u/tast/lottery/activity/LotMainActivity/ll_lot0610 Landroid/widget/LinearLayout;
invokevirtual android/widget/LinearLayout/getLayoutParams()Landroid/view/ViewGroup$LayoutParams;
checkcast android/widget/RelativeLayout$LayoutParams
astore 2
aload 2
iload 1
putfield android/widget/RelativeLayout$LayoutParams/width I
aload 0
getfield com/nd/android/u/tast/lottery/activity/LotMainActivity/ll_lot0610 Landroid/widget/LinearLayout;
aload 2
invokevirtual android/widget/LinearLayout/setLayoutParams(Landroid/view/ViewGroup$LayoutParams;)V
aload 0
getfield com/nd/android/u/tast/lottery/activity/LotMainActivity/ll_lot1115 Landroid/widget/LinearLayout;
invokevirtual android/widget/LinearLayout/getLayoutParams()Landroid/view/ViewGroup$LayoutParams;
checkcast android/widget/RelativeLayout$LayoutParams
astore 2
aload 2
iload 1
putfield android/widget/RelativeLayout$LayoutParams/height I
aload 0
getfield com/nd/android/u/tast/lottery/activity/LotMainActivity/ll_lot1115 Landroid/widget/LinearLayout;
aload 2
invokevirtual android/widget/LinearLayout/setLayoutParams(Landroid/view/ViewGroup$LayoutParams;)V
aload 0
getfield com/nd/android/u/tast/lottery/activity/LotMainActivity/ll_lot1620 Landroid/widget/LinearLayout;
invokevirtual android/widget/LinearLayout/getLayoutParams()Landroid/view/ViewGroup$LayoutParams;
checkcast android/widget/RelativeLayout$LayoutParams
astore 2
aload 2
iload 1
putfield android/widget/RelativeLayout$LayoutParams/width I
aload 0
getfield com/nd/android/u/tast/lottery/activity/LotMainActivity/ll_lot1620 Landroid/widget/LinearLayout;
aload 2
invokevirtual android/widget/LinearLayout/setLayoutParams(Landroid/view/ViewGroup$LayoutParams;)V
L2:
return
L0:
aload 0
getfield com/nd/android/u/tast/lottery/activity/LotMainActivity/mItemtype I
sipush 10002
if_icmpne L1
aload 0
getstatic com/nd/android/u/tasklib/R$id/iv_new_year_tip I
invokevirtual com/nd/android/u/tast/lottery/activity/LotMainActivity/findViewById(I)Landroid/view/View;
checkcast android/widget/ImageView
astore 2
aload 2
iconst_0
invokevirtual android/widget/ImageView/setVisibility(I)V
aload 2
getstatic com/nd/android/u/tasklib/R$drawable/lot_new_year_tip_2 I
invokevirtual android/widget/ImageView/setBackgroundResource(I)V
goto L1
.limit locals 3
.limit stack 3
.end method

.method protected initEvent()V
aload 0
invokespecial com/nd/android/u/tast/lottery/activity/LotMainActivity/getLotteryInfo()V
aload 0
invokespecial com/nd/android/u/tast/lottery/activity/LotMainActivity/initLotTimes()V
aload 0
new com/nd/android/u/tast/lottery/activity/LotMainActivity$1
dup
aload 0
invokespecial com/nd/android/u/tast/lottery/activity/LotMainActivity$1/<init>(Lcom/nd/android/u/tast/lottery/activity/LotMainActivity;)V
putfield com/nd/android/u/tast/lottery/activity/LotMainActivity/timerHandler Landroid/os/Handler;
return
.limit locals 1
.limit stack 4
.end method

.method public onClick(Landroid/view/View;)V
aload 1
invokevirtual android/view/View/getId()I
getstatic com/nd/android/u/tasklib/R$id/ll_start_lot I
if_icmpne L0
aload 0
getfield com/nd/android/u/tast/lottery/activity/LotMainActivity/mCanLot Z
ifeq L1
aload 0
getfield com/nd/android/u/tast/lottery/activity/LotMainActivity/mLotNum I
ifle L1
aload 0
iconst_2
putfield com/nd/android/u/tast/lottery/activity/LotMainActivity/mCurrentCircleNum I
aload 0
iconst_0
putfield com/nd/android/u/tast/lottery/activity/LotMainActivity/mCanLot Z
aload 0
iconst_m1
putfield com/nd/android/u/tast/lottery/activity/LotMainActivity/answer I
aload 0
getfield com/nd/android/u/tast/lottery/activity/LotMainActivity/timerHandler Landroid/os/Handler;
aload 0
getfield com/nd/android/u/tast/lottery/activity/LotMainActivity/timeThread Ljava/lang/Runnable;
ldc2_w 100L
invokevirtual android/os/Handler/postDelayed(Ljava/lang/Runnable;J)Z
pop
new com/nd/android/u/tast/lottery/activity/LotMainActivity$3
dup
aload 0
invokespecial com/nd/android/u/tast/lottery/activity/LotMainActivity$3/<init>(Lcom/nd/android/u/tast/lottery/activity/LotMainActivity;)V
invokevirtual com/nd/android/u/tast/lottery/activity/LotMainActivity$3/start()V
L2:
return
L1:
aload 0
getfield com/nd/android/u/tast/lottery/activity/LotMainActivity/mLotNum I
ifne L2
aload 0
getfield com/nd/android/u/tast/lottery/activity/LotMainActivity/ctx Landroid/content/Context;
getstatic com/nd/android/u/tasklib/R$string/lot_fail_notimes I
invokestatic com/common/android/utils/ToastUtils/display(Landroid/content/Context;I)V
return
L0:
aload 1
invokevirtual android/view/View/getId()I
getstatic com/nd/android/u/tasklib/R$id/scroll_lot_users1 I
if_icmpeq L3
aload 1
invokevirtual android/view/View/getId()I
getstatic com/nd/android/u/tasklib/R$id/tv_no_lot_users I
if_icmpne L4
L3:
aload 0
new android/content/Intent
dup
aload 0
ldc com/nd/android/u/tast/lottery/activity/RafflesListPublicActivity
invokespecial android/content/Intent/<init>(Landroid/content/Context;Ljava/lang/Class;)V
invokevirtual com/nd/android/u/tast/lottery/activity/LotMainActivity/startActivity(Landroid/content/Intent;)V
return
L4:
aload 1
invokevirtual android/view/View/getId()I
getstatic com/nd/android/u/tasklib/R$id/btn_back I
if_icmpne L2
aload 0
invokevirtual com/nd/android/u/tast/lottery/activity/LotMainActivity/finish()V
return
.limit locals 2
.limit stack 5
.end method

.method protected onCreate(Landroid/os/Bundle;)V
aload 0
aload 1
invokespecial android/app/Activity/onCreate(Landroid/os/Bundle;)V
aload 0
getstatic com/nd/android/u/tasklib/R$layout/lot_main I
invokevirtual com/nd/android/u/tast/lottery/activity/LotMainActivity/setContentView(I)V
aload 0
aload 0
putfield com/nd/android/u/tast/lottery/activity/LotMainActivity/ctx Landroid/content/Context;
aload 0
new java/lang/StringBuilder
dup
invokespecial java/lang/StringBuilder/<init>()V
getstatic com/nd/android/u/tast/com/OapLotteryCom/LOT_NEW_SERVER_URL Ljava/lang/String;
invokevirtual java/lang/StringBuilder/append(Ljava/lang/String;)Ljava/lang/StringBuilder;
ldc "jackpot/img?cid=%d&unitid=%d&size=%d"
invokevirtual java/lang/StringBuilder/append(Ljava/lang/String;)Ljava/lang/StringBuilder;
invokevirtual java/lang/StringBuilder/toString()Ljava/lang/String;
putfield com/nd/android/u/tast/lottery/activity/LotMainActivity/JACKPOT_IMG_URL Ljava/lang/String;
aload 0
aload 0
invokevirtual com/nd/android/u/tast/lottery/activity/LotMainActivity/getIntent()Landroid/content/Intent;
ldc "itemtype"
sipush 10000
invokevirtual android/content/Intent/getIntExtra(Ljava/lang/String;I)I
putfield com/nd/android/u/tast/lottery/activity/LotMainActivity/mItemtype I
aload 0
aload 0
invokevirtual com/nd/android/u/tast/lottery/activity/LotMainActivity/getIntent()Landroid/content/Intent;
ldc "lotnum"
iconst_0
invokevirtual android/content/Intent/getIntExtra(Ljava/lang/String;I)I
putfield com/nd/android/u/tast/lottery/activity/LotMainActivity/mLotNum I
aload 0
getfield com/nd/android/u/tast/lottery/activity/LotMainActivity/mLotNum I
ifne L0
aload 0
iconst_0
putfield com/nd/android/u/tast/lottery/activity/LotMainActivity/mLotNumSave Z
L0:
aload 0
getfield com/nd/android/u/tast/lottery/activity/LotMainActivity/mLotOnBgBitmapDrawable Landroid/graphics/drawable/BitmapDrawable;
ifnonnull L1
new android/graphics/BitmapFactory$Options
dup
invokespecial android/graphics/BitmapFactory$Options/<init>()V
astore 1
aload 1
getstatic android/graphics/Bitmap$Config/RGB_565 Landroid/graphics/Bitmap$Config;
putfield android/graphics/BitmapFactory$Options/inPreferredConfig Landroid/graphics/Bitmap$Config;
aload 1
iconst_1
putfield android/graphics/BitmapFactory$Options/inPurgeable Z
aload 1
iconst_1
putfield android/graphics/BitmapFactory$Options/inInputShareable Z
aload 0
new android/graphics/drawable/BitmapDrawable
dup
aload 0
invokevirtual com/nd/android/u/tast/lottery/activity/LotMainActivity/getResources()Landroid/content/res/Resources;
getstatic com/nd/android/u/tasklib/R$drawable/lot_on_bg I
invokestatic android/graphics/BitmapFactory/decodeResource(Landroid/content/res/Resources;I)Landroid/graphics/Bitmap;
invokespecial android/graphics/drawable/BitmapDrawable/<init>(Landroid/graphics/Bitmap;)V
putfield com/nd/android/u/tast/lottery/activity/LotMainActivity/mLotOnBgBitmapDrawable Landroid/graphics/drawable/BitmapDrawable;
L1:
aload 0
invokevirtual com/nd/android/u/tast/lottery/activity/LotMainActivity/initComponent()V
aload 0
invokevirtual com/nd/android/u/tast/lottery/activity/LotMainActivity/initEvent()V
return
.limit locals 2
.limit stack 5
.end method

.method protected onDestroy()V
.catch org/json/JSONException from L0 to L1 using L2
aload 0
invokespecial android/app/Activity/onDestroy()V
aload 0
getfield com/nd/android/u/tast/lottery/activity/LotMainActivity/mLotNumSave Z
ifne L3
aload 0
ldc "GrowUpData"
iconst_2
invokevirtual com/nd/android/u/tast/lottery/activity/LotMainActivity/getSharedPreferences(Ljava/lang/String;I)Landroid/content/SharedPreferences;
invokeinterface android/content/SharedPreferences/edit()Landroid/content/SharedPreferences$Editor; 0
astore 1
aload 1
ldc "lotteryDraw"
aload 0
getfield com/nd/android/u/tast/lottery/activity/LotMainActivity/mLotNum I
invokeinterface android/content/SharedPreferences$Editor/putInt(Ljava/lang/String;I)Landroid/content/SharedPreferences$Editor; 2
pop
aload 1
invokeinterface android/content/SharedPreferences$Editor/commit()Z 0
pop
L3:
aload 0
getfield com/nd/android/u/tast/lottery/activity/LotMainActivity/mHasLoted Z
ifeq L4
new org/json/JSONObject
dup
invokespecial org/json/JSONObject/<init>()V
astore 1
L0:
aload 1
ldc "string_backpack_event_type"
ldc "string_backpack_lotter_return"
invokevirtual org/json/JSONObject/put(Ljava/lang/String;Ljava/lang/Object;)Lorg/json/JSONObject;
pop
aload 1
ldc "string_backpack_event_item_type"
aload 0
getfield com/nd/android/u/tast/lottery/activity/LotMainActivity/mItemtype I
invokevirtual org/json/JSONObject/put(Ljava/lang/String;I)Lorg/json/JSONObject;
pop
aload 1
ldc "string_backpack_event_lotnum"
aload 0
getfield com/nd/android/u/tast/lottery/activity/LotMainActivity/mLotNum I
invokevirtual org/json/JSONObject/put(Ljava/lang/String;I)Lorg/json/JSONObject;
pop
L1:
invokestatic de/greenrobot/event/EventBus/getDefault()Lde/greenrobot/event/EventBus;
aload 1
invokevirtual org/json/JSONObject/toString()Ljava/lang/String;
invokevirtual de/greenrobot/event/EventBus/post(Ljava/lang/Object;)V
L4:
aload 0
getfield com/nd/android/u/tast/lottery/activity/LotMainActivity/timerHandler Landroid/os/Handler;
aload 0
getfield com/nd/android/u/tast/lottery/activity/LotMainActivity/timeThread Ljava/lang/Runnable;
invokevirtual android/os/Handler/removeCallbacks(Ljava/lang/Runnable;)V
aload 0
getfield com/nd/android/u/tast/lottery/activity/LotMainActivity/mGetLotInfoTask Lcom/common/android/utils/task/genericTask/GenericTask;
ifnull L5
aload 0
getfield com/nd/android/u/tast/lottery/activity/LotMainActivity/mGetLotInfoTask Lcom/common/android/utils/task/genericTask/GenericTask;
invokevirtual com/common/android/utils/task/genericTask/GenericTask/getStatus()Landroid/os/AsyncTask$Status;
getstatic android/os/AsyncTask$Status/RUNNING Landroid/os/AsyncTask$Status;
if_acmpne L5
aload 0
getfield com/nd/android/u/tast/lottery/activity/LotMainActivity/mGetLotInfoTask Lcom/common/android/utils/task/genericTask/GenericTask;
iconst_1
invokevirtual com/common/android/utils/task/genericTask/GenericTask/cancel(Z)Z
pop
L5:
aload 0
aload 0
getfield com/nd/android/u/tast/lottery/activity/LotMainActivity/mCurrentPos I
invokespecial com/nd/android/u/tast/lottery/activity/LotMainActivity/chgBackGrountNormal(I)V
aload 0
getfield com/nd/android/u/tast/lottery/activity/LotMainActivity/mLotOnBgBitmapDrawable Landroid/graphics/drawable/BitmapDrawable;
ifnull L6
aload 0
getfield com/nd/android/u/tast/lottery/activity/LotMainActivity/mLotOnBgBitmapDrawable Landroid/graphics/drawable/BitmapDrawable;
invokevirtual android/graphics/drawable/BitmapDrawable/getBitmap()Landroid/graphics/Bitmap;
astore 1
aload 1
ifnull L7
aload 1
invokevirtual android/graphics/Bitmap/isRecycled()Z
ifne L7
aload 1
invokevirtual android/graphics/Bitmap/recycle()V
L7:
aload 0
aconst_null
putfield com/nd/android/u/tast/lottery/activity/LotMainActivity/mLotOnBgBitmapDrawable Landroid/graphics/drawable/BitmapDrawable;
L6:
return
L2:
astore 2
aload 2
invokevirtual org/json/JSONException/printStackTrace()V
goto L1
.limit locals 3
.limit stack 3
.end method

.method protected onPause()V
invokestatic com/nd/android/u/tast/TaskGlobalVariable/getInstance()Lcom/nd/android/u/tast/TaskGlobalVariable;
getfield com/nd/android/u/tast/TaskGlobalVariable/mOapScore Lcom/product/android/commonInterface/task/OapScore;
aload 0
getfield com/nd/android/u/tast/lottery/activity/LotMainActivity/mLotNum I
invokevirtual com/product/android/commonInterface/task/OapScore/setLotterychance(I)V
aload 0
invokespecial android/app/Activity/onPause()V
return
.limit locals 1
.limit stack 2
.end method

.method protected onResume()V
aload 0
invokespecial android/app/Activity/onResume()V
aload 0
getfield com/nd/android/u/tast/lottery/activity/LotMainActivity/mLotNumSave Z
ifne L0
aload 0
invokespecial com/nd/android/u/tast/lottery/activity/LotMainActivity/getLotteryCount()V
L0:
ldc "\u62bd\u5956\u6b21\u6570"
new java/lang/StringBuilder
dup
invokespecial java/lang/StringBuilder/<init>()V
aload 0
getfield com/nd/android/u/tast/lottery/activity/LotMainActivity/mLotNum I
invokevirtual java/lang/StringBuilder/append(I)Ljava/lang/StringBuilder;
ldc ""
invokevirtual java/lang/StringBuilder/append(Ljava/lang/String;)Ljava/lang/StringBuilder;
invokevirtual java/lang/StringBuilder/toString()Ljava/lang/String;
invokestatic android/util/Log/e(Ljava/lang/String;Ljava/lang/String;)I
pop
return
.limit locals 1
.limit stack 3
.end method
