.bytecode 50.0
.class synchronized com/nd/android/u/tast/lottery/activity/RafflesListActivity$3
.super java/lang/Object
.implements com/nd/android/u/tast/lottery/view/LotteryListview$FilpperListener
.enclosing method com/nd/android/u/tast/lottery/activity/RafflesListActivity/setClick()V
.inner class inner com/nd/android/u/tast/lottery/activity/RafflesListActivity$3

.field final synthetic 'this$0' Lcom/nd/android/u/tast/lottery/activity/RafflesListActivity;

.method <init>(Lcom/nd/android/u/tast/lottery/activity/RafflesListActivity;)V
aload 0
aload 1
putfield com/nd/android/u/tast/lottery/activity/RafflesListActivity$3/this$0 Lcom/nd/android/u/tast/lottery/activity/RafflesListActivity;
aload 0
invokespecial java/lang/Object/<init>()V
return
.limit locals 2
.limit stack 2
.end method

.method public filpperLeft(FF)V
aload 0
getfield com/nd/android/u/tast/lottery/activity/RafflesListActivity$3/this$0 Lcom/nd/android/u/tast/lottery/activity/RafflesListActivity;
invokestatic com/nd/android/u/tast/lottery/activity/RafflesListActivity/access$200(Lcom/nd/android/u/tast/lottery/activity/RafflesListActivity;)Lcom/nd/android/u/tast/lottery/view/LotteryListview;
invokevirtual com/nd/android/u/tast/lottery/view/LotteryListview/getChildCount()I
ifne L0
return
L0:
aload 0
getfield com/nd/android/u/tast/lottery/activity/RafflesListActivity$3/this$0 Lcom/nd/android/u/tast/lottery/activity/RafflesListActivity;
invokestatic com/nd/android/u/tast/lottery/activity/RafflesListActivity/access$200(Lcom/nd/android/u/tast/lottery/activity/RafflesListActivity;)Lcom/nd/android/u/tast/lottery/view/LotteryListview;
fload 1
f2i
fload 2
f2i
invokevirtual com/nd/android/u/tast/lottery/view/LotteryListview/pointToPosition(II)I
istore 3
aload 0
getfield com/nd/android/u/tast/lottery/activity/RafflesListActivity$3/this$0 Lcom/nd/android/u/tast/lottery/activity/RafflesListActivity;
invokestatic com/nd/android/u/tast/lottery/activity/RafflesListActivity/access$300(Lcom/nd/android/u/tast/lottery/activity/RafflesListActivity;)Lcom/nd/android/u/tast/lottery/adapter/RafflesListAdapter;
iload 3
invokevirtual com/nd/android/u/tast/lottery/adapter/RafflesListAdapter/disCheck(I)V
aload 0
getfield com/nd/android/u/tast/lottery/activity/RafflesListActivity$3/this$0 Lcom/nd/android/u/tast/lottery/activity/RafflesListActivity;
invokestatic com/nd/android/u/tast/lottery/activity/RafflesListActivity/access$300(Lcom/nd/android/u/tast/lottery/activity/RafflesListActivity;)Lcom/nd/android/u/tast/lottery/adapter/RafflesListAdapter;
invokevirtual com/nd/android/u/tast/lottery/adapter/RafflesListAdapter/notifyDataSetChanged()V
return
.limit locals 4
.limit stack 3
.end method

.method public filpperRight(FF)V
aload 0
getfield com/nd/android/u/tast/lottery/activity/RafflesListActivity$3/this$0 Lcom/nd/android/u/tast/lottery/activity/RafflesListActivity;
invokestatic com/nd/android/u/tast/lottery/activity/RafflesListActivity/access$200(Lcom/nd/android/u/tast/lottery/activity/RafflesListActivity;)Lcom/nd/android/u/tast/lottery/view/LotteryListview;
invokevirtual com/nd/android/u/tast/lottery/view/LotteryListview/getChildCount()I
ifne L0
return
L0:
aload 0
getfield com/nd/android/u/tast/lottery/activity/RafflesListActivity$3/this$0 Lcom/nd/android/u/tast/lottery/activity/RafflesListActivity;
invokestatic com/nd/android/u/tast/lottery/activity/RafflesListActivity/access$200(Lcom/nd/android/u/tast/lottery/activity/RafflesListActivity;)Lcom/nd/android/u/tast/lottery/view/LotteryListview;
fload 1
f2i
fload 2
f2i
invokevirtual com/nd/android/u/tast/lottery/view/LotteryListview/pointToPosition(II)I
istore 3
aload 0
getfield com/nd/android/u/tast/lottery/activity/RafflesListActivity$3/this$0 Lcom/nd/android/u/tast/lottery/activity/RafflesListActivity;
invokestatic com/nd/android/u/tast/lottery/activity/RafflesListActivity/access$300(Lcom/nd/android/u/tast/lottery/activity/RafflesListActivity;)Lcom/nd/android/u/tast/lottery/adapter/RafflesListAdapter;
iload 3
invokevirtual com/nd/android/u/tast/lottery/adapter/RafflesListAdapter/setChecked(I)V
aload 0
getfield com/nd/android/u/tast/lottery/activity/RafflesListActivity$3/this$0 Lcom/nd/android/u/tast/lottery/activity/RafflesListActivity;
invokestatic com/nd/android/u/tast/lottery/activity/RafflesListActivity/access$300(Lcom/nd/android/u/tast/lottery/activity/RafflesListActivity;)Lcom/nd/android/u/tast/lottery/adapter/RafflesListAdapter;
invokevirtual com/nd/android/u/tast/lottery/adapter/RafflesListAdapter/notifyDataSetChanged()V
return
.limit locals 4
.limit stack 3
.end method
