.bytecode 50.0
.class synchronized com/nd/android/u/tast/lottery/activity/RafflesListPublicDetailActivity$1
.super android/os/Handler
.enclosing method com/nd/android/u/tast/lottery/activity/RafflesListPublicDetailActivity
.inner class inner com/nd/android/u/tast/lottery/activity/RafflesListPublicDetailActivity$1

.field final synthetic 'this$0' Lcom/nd/android/u/tast/lottery/activity/RafflesListPublicDetailActivity;

.method <init>(Lcom/nd/android/u/tast/lottery/activity/RafflesListPublicDetailActivity;)V
aload 0
aload 1
putfield com/nd/android/u/tast/lottery/activity/RafflesListPublicDetailActivity$1/this$0 Lcom/nd/android/u/tast/lottery/activity/RafflesListPublicDetailActivity;
aload 0
invokespecial android/os/Handler/<init>()V
return
.limit locals 2
.limit stack 2
.end method

.method public handleMessage(Landroid/os/Message;)V
aload 1
getfield android/os/Message/what I
lookupswitch
10 : L0
11 : L1
20 : L2
21 : L3
default : L4
L4:
aload 0
aload 1
invokespecial android/os/Handler/handleMessage(Landroid/os/Message;)V
return
L0:
aload 0
getfield com/nd/android/u/tast/lottery/activity/RafflesListPublicDetailActivity$1/this$0 Lcom/nd/android/u/tast/lottery/activity/RafflesListPublicDetailActivity;
invokestatic com/nd/android/u/tast/lottery/activity/RafflesListPublicDetailActivity/access$000(Lcom/nd/android/u/tast/lottery/activity/RafflesListPublicDetailActivity;)Landroid/widget/Button;
iconst_4
invokevirtual android/widget/Button/setVisibility(I)V
goto L4
L1:
aload 0
getfield com/nd/android/u/tast/lottery/activity/RafflesListPublicDetailActivity$1/this$0 Lcom/nd/android/u/tast/lottery/activity/RafflesListPublicDetailActivity;
invokestatic com/nd/android/u/tast/lottery/activity/RafflesListPublicDetailActivity/access$000(Lcom/nd/android/u/tast/lottery/activity/RafflesListPublicDetailActivity;)Landroid/widget/Button;
iconst_0
invokevirtual android/widget/Button/setVisibility(I)V
goto L4
L2:
aload 0
getfield com/nd/android/u/tast/lottery/activity/RafflesListPublicDetailActivity$1/this$0 Lcom/nd/android/u/tast/lottery/activity/RafflesListPublicDetailActivity;
invokestatic com/nd/android/u/tast/lottery/activity/RafflesListPublicDetailActivity/access$100(Lcom/nd/android/u/tast/lottery/activity/RafflesListPublicDetailActivity;)Landroid/widget/Button;
iconst_4
invokevirtual android/widget/Button/setVisibility(I)V
goto L4
L3:
aload 0
getfield com/nd/android/u/tast/lottery/activity/RafflesListPublicDetailActivity$1/this$0 Lcom/nd/android/u/tast/lottery/activity/RafflesListPublicDetailActivity;
invokestatic com/nd/android/u/tast/lottery/activity/RafflesListPublicDetailActivity/access$100(Lcom/nd/android/u/tast/lottery/activity/RafflesListPublicDetailActivity;)Landroid/widget/Button;
iconst_0
invokevirtual android/widget/Button/setVisibility(I)V
goto L4
.limit locals 2
.limit stack 2
.end method
