.bytecode 50.0
.class public synchronized com/nd/android/u/tast/lottery/activity/RafflesListPublicDetailActivity
.super android/app/Activity
.inner class inner com/nd/android/u/tast/lottery/activity/RafflesListPublicDetailActivity$1
.inner class inner com/nd/android/u/tast/lottery/activity/RafflesListPublicDetailActivity$2
.inner class inner com/nd/android/u/tast/lottery/activity/RafflesListPublicDetailActivity$3
.inner class inner com/nd/android/u/tast/lottery/activity/RafflesListPublicDetailActivity$4
.inner class private GetLotteryHisTask inner com/nd/android/u/tast/lottery/activity/RafflesListPublicDetailActivity$GetLotteryHisTask outer com/nd/android/u/tast/lottery/activity/RafflesListPublicDetailActivity

.field private 'btn_giftscroll_left' Landroid/widget/Button;

.field private 'btn_giftscroll_right' Landroid/widget/Button;

.field private 'clickListener' Landroid/view/View$OnClickListener;

.field private 'gAdapter' Lcom/nd/android/u/tast/lottery/adapter/RafflesListPublicDetailGiftScrollAdapter;

.field private 'header_btn_lotterydraw' Landroid/widget/Button;

.field private 'header_btn_return' Landroid/widget/Button;

.field 'lv_gift_scroll' Lcom/nd/android/u/tast/birthday/view/HorizontalListView;

.field private 'mAdapter' Lcom/nd/android/u/tast/lottery/adapter/RafflesListPublicDetailAdapter;

.field private 'mGetLotHisTask' Lcom/common/android/utils/task/genericTask/GenericTask;

.field private 'mGetLotHisTaskListener' Lcom/common/android/utils/task/genericTask/TaskListener;

.field 'mHandler' Landroid/os/Handler;

.field private 'mListView' Lcom/nd/android/u/tast/lottery/view/LotteryListview;

.field private 'mRank' I

.field private 'm_dialog' Landroid/app/ProgressDialog;

.field private 'mrlScrollLeft' Landroid/widget/RelativeLayout;

.field private 'mrlScrollRight' Landroid/widget/RelativeLayout;

.field private 'scrollDistance' I

.field 'temMap' Ljava/util/HashMap; signature "Ljava/util/HashMap<Ljava/lang/Integer;Ljava/util/List<Lcom/nd/android/u/tast/lottery/dataStructure/LotUserData;>;>;"

.method public <init>()V
aload 0
invokespecial android/app/Activity/<init>()V
aload 0
bipush 100
putfield com/nd/android/u/tast/lottery/activity/RafflesListPublicDetailActivity/scrollDistance I
aload 0
iconst_4
putfield com/nd/android/u/tast/lottery/activity/RafflesListPublicDetailActivity/mRank I
aload 0
new java/util/HashMap
dup
invokespecial java/util/HashMap/<init>()V
putfield com/nd/android/u/tast/lottery/activity/RafflesListPublicDetailActivity/temMap Ljava/util/HashMap;
aload 0
new com/nd/android/u/tast/lottery/activity/RafflesListPublicDetailActivity$1
dup
aload 0
invokespecial com/nd/android/u/tast/lottery/activity/RafflesListPublicDetailActivity$1/<init>(Lcom/nd/android/u/tast/lottery/activity/RafflesListPublicDetailActivity;)V
putfield com/nd/android/u/tast/lottery/activity/RafflesListPublicDetailActivity/mHandler Landroid/os/Handler;
aload 0
new com/nd/android/u/tast/lottery/activity/RafflesListPublicDetailActivity$3
dup
aload 0
invokespecial com/nd/android/u/tast/lottery/activity/RafflesListPublicDetailActivity$3/<init>(Lcom/nd/android/u/tast/lottery/activity/RafflesListPublicDetailActivity;)V
putfield com/nd/android/u/tast/lottery/activity/RafflesListPublicDetailActivity/clickListener Landroid/view/View$OnClickListener;
aload 0
new com/nd/android/u/tast/lottery/activity/RafflesListPublicDetailActivity$4
dup
aload 0
invokespecial com/nd/android/u/tast/lottery/activity/RafflesListPublicDetailActivity$4/<init>(Lcom/nd/android/u/tast/lottery/activity/RafflesListPublicDetailActivity;)V
putfield com/nd/android/u/tast/lottery/activity/RafflesListPublicDetailActivity/mGetLotHisTaskListener Lcom/common/android/utils/task/genericTask/TaskListener;
return
.limit locals 1
.limit stack 4
.end method

.method static synthetic access$000(Lcom/nd/android/u/tast/lottery/activity/RafflesListPublicDetailActivity;)Landroid/widget/Button;
aload 0
getfield com/nd/android/u/tast/lottery/activity/RafflesListPublicDetailActivity/btn_giftscroll_left Landroid/widget/Button;
areturn
.limit locals 1
.limit stack 1
.end method

.method static synthetic access$100(Lcom/nd/android/u/tast/lottery/activity/RafflesListPublicDetailActivity;)Landroid/widget/Button;
aload 0
getfield com/nd/android/u/tast/lottery/activity/RafflesListPublicDetailActivity/btn_giftscroll_right Landroid/widget/Button;
areturn
.limit locals 1
.limit stack 1
.end method

.method static synthetic access$200(Lcom/nd/android/u/tast/lottery/activity/RafflesListPublicDetailActivity;)Lcom/nd/android/u/tast/lottery/adapter/RafflesListPublicDetailGiftScrollAdapter;
aload 0
getfield com/nd/android/u/tast/lottery/activity/RafflesListPublicDetailActivity/gAdapter Lcom/nd/android/u/tast/lottery/adapter/RafflesListPublicDetailGiftScrollAdapter;
areturn
.limit locals 1
.limit stack 1
.end method

.method static synthetic access$202(Lcom/nd/android/u/tast/lottery/activity/RafflesListPublicDetailActivity;Lcom/nd/android/u/tast/lottery/adapter/RafflesListPublicDetailGiftScrollAdapter;)Lcom/nd/android/u/tast/lottery/adapter/RafflesListPublicDetailGiftScrollAdapter;
aload 0
aload 1
putfield com/nd/android/u/tast/lottery/activity/RafflesListPublicDetailActivity/gAdapter Lcom/nd/android/u/tast/lottery/adapter/RafflesListPublicDetailGiftScrollAdapter;
aload 1
areturn
.limit locals 2
.limit stack 2
.end method

.method static synthetic access$300(Lcom/nd/android/u/tast/lottery/activity/RafflesListPublicDetailActivity;Ljava/util/HashMap;)Ljava/util/List;
aload 0
aload 1
invokespecial com/nd/android/u/tast/lottery/activity/RafflesListPublicDetailActivity/hashMapToPrize(Ljava/util/HashMap;)Ljava/util/List;
areturn
.limit locals 2
.limit stack 2
.end method

.method static synthetic access$400(Lcom/nd/android/u/tast/lottery/activity/RafflesListPublicDetailActivity;)Lcom/nd/android/u/tast/lottery/adapter/RafflesListPublicDetailAdapter;
aload 0
getfield com/nd/android/u/tast/lottery/activity/RafflesListPublicDetailActivity/mAdapter Lcom/nd/android/u/tast/lottery/adapter/RafflesListPublicDetailAdapter;
areturn
.limit locals 1
.limit stack 1
.end method

.method static synthetic access$402(Lcom/nd/android/u/tast/lottery/activity/RafflesListPublicDetailActivity;Lcom/nd/android/u/tast/lottery/adapter/RafflesListPublicDetailAdapter;)Lcom/nd/android/u/tast/lottery/adapter/RafflesListPublicDetailAdapter;
aload 0
aload 1
putfield com/nd/android/u/tast/lottery/activity/RafflesListPublicDetailActivity/mAdapter Lcom/nd/android/u/tast/lottery/adapter/RafflesListPublicDetailAdapter;
aload 1
areturn
.limit locals 2
.limit stack 2
.end method

.method static synthetic access$500(Lcom/nd/android/u/tast/lottery/activity/RafflesListPublicDetailActivity;)I
aload 0
getfield com/nd/android/u/tast/lottery/activity/RafflesListPublicDetailActivity/scrollDistance I
ireturn
.limit locals 1
.limit stack 1
.end method

.method static synthetic access$700(Lcom/nd/android/u/tast/lottery/activity/RafflesListPublicDetailActivity;)I
aload 0
getfield com/nd/android/u/tast/lottery/activity/RafflesListPublicDetailActivity/mRank I
ireturn
.limit locals 1
.limit stack 1
.end method

.method static synthetic access$800(Lcom/nd/android/u/tast/lottery/activity/RafflesListPublicDetailActivity;)Landroid/app/ProgressDialog;
aload 0
getfield com/nd/android/u/tast/lottery/activity/RafflesListPublicDetailActivity/m_dialog Landroid/app/ProgressDialog;
areturn
.limit locals 1
.limit stack 1
.end method

.method static synthetic access$802(Lcom/nd/android/u/tast/lottery/activity/RafflesListPublicDetailActivity;Landroid/app/ProgressDialog;)Landroid/app/ProgressDialog;
aload 0
aload 1
putfield com/nd/android/u/tast/lottery/activity/RafflesListPublicDetailActivity/m_dialog Landroid/app/ProgressDialog;
aload 1
areturn
.limit locals 2
.limit stack 2
.end method

.method static synthetic access$900(Lcom/nd/android/u/tast/lottery/activity/RafflesListPublicDetailActivity;)Lcom/nd/android/u/tast/lottery/view/LotteryListview;
aload 0
getfield com/nd/android/u/tast/lottery/activity/RafflesListPublicDetailActivity/mListView Lcom/nd/android/u/tast/lottery/view/LotteryListview;
areturn
.limit locals 1
.limit stack 1
.end method

.method private findView()V
aload 0
aload 0
getstatic com/nd/android/u/tasklib/R$id/header_btn_lotterydraw I
invokevirtual com/nd/android/u/tast/lottery/activity/RafflesListPublicDetailActivity/findViewById(I)Landroid/view/View;
checkcast android/widget/Button
putfield com/nd/android/u/tast/lottery/activity/RafflesListPublicDetailActivity/header_btn_lotterydraw Landroid/widget/Button;
aload 0
aload 0
getstatic com/nd/android/u/tasklib/R$id/header_btn_return I
invokevirtual com/nd/android/u/tast/lottery/activity/RafflesListPublicDetailActivity/findViewById(I)Landroid/view/View;
checkcast android/widget/Button
putfield com/nd/android/u/tast/lottery/activity/RafflesListPublicDetailActivity/header_btn_return Landroid/widget/Button;
aload 0
aload 0
getstatic com/nd/android/u/tasklib/R$id/record_list_view I
invokevirtual com/nd/android/u/tast/lottery/activity/RafflesListPublicDetailActivity/findViewById(I)Landroid/view/View;
checkcast com/nd/android/u/tast/lottery/view/LotteryListview
putfield com/nd/android/u/tast/lottery/activity/RafflesListPublicDetailActivity/mListView Lcom/nd/android/u/tast/lottery/view/LotteryListview;
aload 0
aload 0
getstatic com/nd/android/u/tasklib/R$id/lv_gift_scroll I
invokevirtual com/nd/android/u/tast/lottery/activity/RafflesListPublicDetailActivity/findViewById(I)Landroid/view/View;
checkcast com/nd/android/u/tast/birthday/view/HorizontalListView
putfield com/nd/android/u/tast/lottery/activity/RafflesListPublicDetailActivity/lv_gift_scroll Lcom/nd/android/u/tast/birthday/view/HorizontalListView;
aload 0
getfield com/nd/android/u/tast/lottery/activity/RafflesListPublicDetailActivity/lv_gift_scroll Lcom/nd/android/u/tast/birthday/view/HorizontalListView;
aload 0
getfield com/nd/android/u/tast/lottery/activity/RafflesListPublicDetailActivity/mHandler Landroid/os/Handler;
invokevirtual com/nd/android/u/tast/birthday/view/HorizontalListView/initHandler(Landroid/os/Handler;)V
aload 0
aload 0
getstatic com/nd/android/u/tasklib/R$id/layout_giftscroll_left I
invokevirtual com/nd/android/u/tast/lottery/activity/RafflesListPublicDetailActivity/findViewById(I)Landroid/view/View;
checkcast android/widget/RelativeLayout
putfield com/nd/android/u/tast/lottery/activity/RafflesListPublicDetailActivity/mrlScrollLeft Landroid/widget/RelativeLayout;
aload 0
aload 0
getstatic com/nd/android/u/tasklib/R$id/btn_giftscroll_left I
invokevirtual com/nd/android/u/tast/lottery/activity/RafflesListPublicDetailActivity/findViewById(I)Landroid/view/View;
checkcast android/widget/Button
putfield com/nd/android/u/tast/lottery/activity/RafflesListPublicDetailActivity/btn_giftscroll_left Landroid/widget/Button;
aload 0
aload 0
getstatic com/nd/android/u/tasklib/R$id/layout_giftscroll_right I
invokevirtual com/nd/android/u/tast/lottery/activity/RafflesListPublicDetailActivity/findViewById(I)Landroid/view/View;
checkcast android/widget/RelativeLayout
putfield com/nd/android/u/tast/lottery/activity/RafflesListPublicDetailActivity/mrlScrollRight Landroid/widget/RelativeLayout;
aload 0
aload 0
getstatic com/nd/android/u/tasklib/R$id/btn_giftscroll_right I
invokevirtual com/nd/android/u/tast/lottery/activity/RafflesListPublicDetailActivity/findViewById(I)Landroid/view/View;
checkcast android/widget/Button
putfield com/nd/android/u/tast/lottery/activity/RafflesListPublicDetailActivity/btn_giftscroll_right Landroid/widget/Button;
return
.limit locals 1
.limit stack 3
.end method

.method private getPrizeName(Lcom/nd/android/u/tast/lottery/dataStructure/LotUserData;)Ljava/lang/String;
aload 1
invokevirtual com/nd/android/u/tast/lottery/dataStructure/LotUserData/getShort_name()Ljava/lang/String;
invokestatic android/text/TextUtils/isEmpty(Ljava/lang/CharSequence;)Z
ifne L0
aload 1
invokevirtual com/nd/android/u/tast/lottery/dataStructure/LotUserData/getShort_name()Ljava/lang/String;
areturn
L0:
aload 1
invokevirtual com/nd/android/u/tast/lottery/dataStructure/LotUserData/getPrize_name()Ljava/lang/String;
areturn
.limit locals 2
.limit stack 1
.end method

.method private hashMapToPrize(Ljava/util/HashMap;)Ljava/util/List;
.signature "(Ljava/util/HashMap<Ljava/lang/Integer;Ljava/util/List<Lcom/nd/android/u/tast/lottery/dataStructure/LotUserData;>;>;)Ljava/util/List<Lcom/nd/android/u/tast/lottery/dataStructure/Prize;>;"
new java/util/ArrayList
dup
invokespecial java/util/ArrayList/<init>()V
astore 4
aload 1
invokevirtual java/util/HashMap/entrySet()Ljava/util/Set;
invokeinterface java/util/Set/iterator()Ljava/util/Iterator; 0
astore 5
iconst_0
istore 2
L0:
aload 5
invokeinterface java/util/Iterator/hasNext()Z 0
ifeq L1
aload 5
invokeinterface java/util/Iterator/next()Ljava/lang/Object; 0
invokevirtual java/lang/Object/toString()Ljava/lang/String;
ldc "="
invokevirtual java/lang/String/split(Ljava/lang/String;)[Ljava/lang/String;
astore 6
aload 6
ifnull L0
aload 6
arraylength
ifle L0
aload 6
iconst_0
aaload
invokestatic java/lang/Integer/parseInt(Ljava/lang/String;)I
istore 3
new com/nd/android/u/tast/lottery/dataStructure/Prize
dup
invokespecial com/nd/android/u/tast/lottery/dataStructure/Prize/<init>()V
astore 6
aload 6
iload 2
putfield com/nd/android/u/tast/lottery/dataStructure/Prize/id I
iload 2
iconst_1
iadd
istore 2
aload 6
iload 3
putfield com/nd/android/u/tast/lottery/dataStructure/Prize/prize_id I
aload 1
iload 3
invokestatic java/lang/Integer/valueOf(I)Ljava/lang/Integer;
invokevirtual java/util/HashMap/get(Ljava/lang/Object;)Ljava/lang/Object;
checkcast java/util/List
invokeinterface java/util/List/size()I 0
ifle L2
aload 6
aload 0
aload 1
iload 3
invokestatic java/lang/Integer/valueOf(I)Ljava/lang/Integer;
invokevirtual java/util/HashMap/get(Ljava/lang/Object;)Ljava/lang/Object;
checkcast java/util/List
iconst_0
invokeinterface java/util/List/get(I)Ljava/lang/Object; 1
checkcast com/nd/android/u/tast/lottery/dataStructure/LotUserData
invokespecial com/nd/android/u/tast/lottery/activity/RafflesListPublicDetailActivity/getPrizeName(Lcom/nd/android/u/tast/lottery/dataStructure/LotUserData;)Ljava/lang/String;
putfield com/nd/android/u/tast/lottery/dataStructure/Prize/prize_name Ljava/lang/String;
L3:
aload 6
aload 1
iload 3
invokestatic java/lang/Integer/valueOf(I)Ljava/lang/Integer;
invokevirtual java/util/HashMap/get(Ljava/lang/Object;)Ljava/lang/Object;
checkcast java/util/List
invokeinterface java/util/List/size()I 0
putfield com/nd/android/u/tast/lottery/dataStructure/Prize/prize_num I
aload 6
aload 1
iload 3
invokestatic java/lang/Integer/valueOf(I)Ljava/lang/Integer;
invokevirtual java/util/HashMap/get(Ljava/lang/Object;)Ljava/lang/Object;
checkcast java/util/List
putfield com/nd/android/u/tast/lottery/dataStructure/Prize/lotUserData Ljava/util/List;
aload 4
aload 6
invokeinterface java/util/List/add(Ljava/lang/Object;)Z 1
pop
goto L0
L2:
aload 6
ldc ""
putfield com/nd/android/u/tast/lottery/dataStructure/Prize/prize_name Ljava/lang/String;
goto L3
L1:
aload 4
areturn
.limit locals 7
.limit stack 4
.end method

.method private init()V
aload 0
invokevirtual com/nd/android/u/tast/lottery/activity/RafflesListPublicDetailActivity/initData()V
return
.limit locals 1
.limit stack 1
.end method

.method private setClick()V
aload 0
getfield com/nd/android/u/tast/lottery/activity/RafflesListPublicDetailActivity/header_btn_lotterydraw Landroid/widget/Button;
aload 0
getfield com/nd/android/u/tast/lottery/activity/RafflesListPublicDetailActivity/clickListener Landroid/view/View$OnClickListener;
invokevirtual android/widget/Button/setOnClickListener(Landroid/view/View$OnClickListener;)V
aload 0
getfield com/nd/android/u/tast/lottery/activity/RafflesListPublicDetailActivity/header_btn_return Landroid/widget/Button;
aload 0
getfield com/nd/android/u/tast/lottery/activity/RafflesListPublicDetailActivity/clickListener Landroid/view/View$OnClickListener;
invokevirtual android/widget/Button/setOnClickListener(Landroid/view/View$OnClickListener;)V
aload 0
getfield com/nd/android/u/tast/lottery/activity/RafflesListPublicDetailActivity/mrlScrollLeft Landroid/widget/RelativeLayout;
aload 0
getfield com/nd/android/u/tast/lottery/activity/RafflesListPublicDetailActivity/clickListener Landroid/view/View$OnClickListener;
invokevirtual android/widget/RelativeLayout/setOnClickListener(Landroid/view/View$OnClickListener;)V
aload 0
getfield com/nd/android/u/tast/lottery/activity/RafflesListPublicDetailActivity/mrlScrollRight Landroid/widget/RelativeLayout;
aload 0
getfield com/nd/android/u/tast/lottery/activity/RafflesListPublicDetailActivity/clickListener Landroid/view/View$OnClickListener;
invokevirtual android/widget/RelativeLayout/setOnClickListener(Landroid/view/View$OnClickListener;)V
aload 0
getfield com/nd/android/u/tast/lottery/activity/RafflesListPublicDetailActivity/btn_giftscroll_left Landroid/widget/Button;
aload 0
getfield com/nd/android/u/tast/lottery/activity/RafflesListPublicDetailActivity/clickListener Landroid/view/View$OnClickListener;
invokevirtual android/widget/Button/setOnClickListener(Landroid/view/View$OnClickListener;)V
aload 0
getfield com/nd/android/u/tast/lottery/activity/RafflesListPublicDetailActivity/btn_giftscroll_right Landroid/widget/Button;
aload 0
getfield com/nd/android/u/tast/lottery/activity/RafflesListPublicDetailActivity/clickListener Landroid/view/View$OnClickListener;
invokevirtual android/widget/Button/setOnClickListener(Landroid/view/View$OnClickListener;)V
aload 0
getfield com/nd/android/u/tast/lottery/activity/RafflesListPublicDetailActivity/lv_gift_scroll Lcom/nd/android/u/tast/birthday/view/HorizontalListView;
new com/nd/android/u/tast/lottery/activity/RafflesListPublicDetailActivity$2
dup
aload 0
invokespecial com/nd/android/u/tast/lottery/activity/RafflesListPublicDetailActivity$2/<init>(Lcom/nd/android/u/tast/lottery/activity/RafflesListPublicDetailActivity;)V
invokevirtual com/nd/android/u/tast/birthday/view/HorizontalListView/setOnItemClickListener(Landroid/widget/AdapterView$OnItemClickListener;)V
return
.limit locals 1
.limit stack 4
.end method

.method public initData()V
aload 0
getfield com/nd/android/u/tast/lottery/activity/RafflesListPublicDetailActivity/mGetLotHisTask Lcom/common/android/utils/task/genericTask/GenericTask;
ifnull L0
aload 0
getfield com/nd/android/u/tast/lottery/activity/RafflesListPublicDetailActivity/mGetLotHisTask Lcom/common/android/utils/task/genericTask/GenericTask;
invokevirtual com/common/android/utils/task/genericTask/GenericTask/getStatus()Landroid/os/AsyncTask$Status;
getstatic android/os/AsyncTask$Status/RUNNING Landroid/os/AsyncTask$Status;
if_acmpne L0
return
L0:
aload 0
new com/nd/android/u/tast/lottery/activity/RafflesListPublicDetailActivity$GetLotteryHisTask
dup
aload 0
aconst_null
invokespecial com/nd/android/u/tast/lottery/activity/RafflesListPublicDetailActivity$GetLotteryHisTask/<init>(Lcom/nd/android/u/tast/lottery/activity/RafflesListPublicDetailActivity;Lcom/nd/android/u/tast/lottery/activity/RafflesListPublicDetailActivity$1;)V
putfield com/nd/android/u/tast/lottery/activity/RafflesListPublicDetailActivity/mGetLotHisTask Lcom/common/android/utils/task/genericTask/GenericTask;
aload 0
getfield com/nd/android/u/tast/lottery/activity/RafflesListPublicDetailActivity/mGetLotHisTask Lcom/common/android/utils/task/genericTask/GenericTask;
aload 0
getfield com/nd/android/u/tast/lottery/activity/RafflesListPublicDetailActivity/mGetLotHisTaskListener Lcom/common/android/utils/task/genericTask/TaskListener;
invokevirtual com/common/android/utils/task/genericTask/GenericTask/setListener(Lcom/common/android/utils/task/genericTask/TaskListener;)V
new com/common/android/utils/task/genericTask/TaskParams
dup
invokespecial com/common/android/utils/task/genericTask/TaskParams/<init>()V
astore 1
aload 0
getfield com/nd/android/u/tast/lottery/activity/RafflesListPublicDetailActivity/mGetLotHisTask Lcom/common/android/utils/task/genericTask/GenericTask;
iconst_1
anewarray com/common/android/utils/task/genericTask/TaskParams
dup
iconst_0
aload 1
aastore
invokevirtual com/common/android/utils/task/genericTask/GenericTask/execute([Ljava/lang/Object;)Landroid/os/AsyncTask;
pop
return
.limit locals 2
.limit stack 5
.end method

.method protected onCreate(Landroid/os/Bundle;)V
aload 0
aload 1
invokespecial android/app/Activity/onCreate(Landroid/os/Bundle;)V
aload 0
getstatic com/nd/android/u/tasklib/R$layout/lottery_public_detail_list I
invokevirtual com/nd/android/u/tast/lottery/activity/RafflesListPublicDetailActivity/setContentView(I)V
aload 0
invokevirtual com/nd/android/u/tast/lottery/activity/RafflesListPublicDetailActivity/getIntent()Landroid/content/Intent;
astore 1
aload 1
ifnull L0
aload 0
aload 1
ldc "lotRank"
iconst_1
invokevirtual android/content/Intent/getIntExtra(Ljava/lang/String;I)I
putfield com/nd/android/u/tast/lottery/activity/RafflesListPublicDetailActivity/mRank I
L0:
aload 0
invokespecial com/nd/android/u/tast/lottery/activity/RafflesListPublicDetailActivity/findView()V
aload 0
invokespecial com/nd/android/u/tast/lottery/activity/RafflesListPublicDetailActivity/setClick()V
aload 0
invokespecial com/nd/android/u/tast/lottery/activity/RafflesListPublicDetailActivity/init()V
return
.limit locals 2
.limit stack 4
.end method

.method protected onDestroy()V
aload 0
invokespecial android/app/Activity/onDestroy()V
return
.limit locals 1
.limit stack 1
.end method
