.bytecode 50.0
.class synchronized com/nd/android/u/cloud/ui/draggrid/DragGridView$1
.super java/lang/Object
.implements android/widget/AdapterView$OnItemLongClickListener
.enclosing method com/nd/android/u/cloud/ui/draggrid/DragGridView/setOnItemLongClickListener(Landroid/view/MotionEvent;)Z
.inner class inner com/nd/android/u/cloud/ui/draggrid/DragGridView$1

.field final synthetic 'this$0' Lcom/nd/android/u/cloud/ui/draggrid/DragGridView;

.field final synthetic 'val$ev' Landroid/view/MotionEvent;

.method <init>(Lcom/nd/android/u/cloud/ui/draggrid/DragGridView;Landroid/view/MotionEvent;)V
aload 0
aload 1
putfield com/nd/android/u/cloud/ui/draggrid/DragGridView$1/this$0 Lcom/nd/android/u/cloud/ui/draggrid/DragGridView;
aload 0
aload 2
putfield com/nd/android/u/cloud/ui/draggrid/DragGridView$1/val$ev Landroid/view/MotionEvent;
aload 0
invokespecial java/lang/Object/<init>()V
return
.limit locals 3
.limit stack 2
.end method

.method public onItemLongClick(Landroid/widget/AdapterView;Landroid/view/View;IJ)Z
.signature "(Landroid/widget/AdapterView<*>;Landroid/view/View;IJ)Z"
aload 0
getfield com/nd/android/u/cloud/ui/draggrid/DragGridView$1/val$ev Landroid/view/MotionEvent;
invokevirtual android/view/MotionEvent/getX()F
f2i
istore 6
aload 0
getfield com/nd/android/u/cloud/ui/draggrid/DragGridView$1/val$ev Landroid/view/MotionEvent;
invokevirtual android/view/MotionEvent/getY()F
f2i
istore 7
aload 0
getfield com/nd/android/u/cloud/ui/draggrid/DragGridView$1/this$0 Lcom/nd/android/u/cloud/ui/draggrid/DragGridView;
iload 6
invokestatic com/nd/android/u/cloud/ui/draggrid/DragGridView/access$002(Lcom/nd/android/u/cloud/ui/draggrid/DragGridView;I)I
pop
aload 0
getfield com/nd/android/u/cloud/ui/draggrid/DragGridView$1/this$0 Lcom/nd/android/u/cloud/ui/draggrid/DragGridView;
iload 7
invokestatic com/nd/android/u/cloud/ui/draggrid/DragGridView/access$102(Lcom/nd/android/u/cloud/ui/draggrid/DragGridView;I)I
pop
aload 0
getfield com/nd/android/u/cloud/ui/draggrid/DragGridView$1/this$0 Lcom/nd/android/u/cloud/ui/draggrid/DragGridView;
aload 0
getfield com/nd/android/u/cloud/ui/draggrid/DragGridView$1/this$0 Lcom/nd/android/u/cloud/ui/draggrid/DragGridView;
aload 0
getfield com/nd/android/u/cloud/ui/draggrid/DragGridView$1/this$0 Lcom/nd/android/u/cloud/ui/draggrid/DragGridView;
iload 3
invokestatic com/nd/android/u/cloud/ui/draggrid/DragGridView/access$402(Lcom/nd/android/u/cloud/ui/draggrid/DragGridView;I)I
invokestatic com/nd/android/u/cloud/ui/draggrid/DragGridView/access$302(Lcom/nd/android/u/cloud/ui/draggrid/DragGridView;I)I
invokestatic com/nd/android/u/cloud/ui/draggrid/DragGridView/access$202(Lcom/nd/android/u/cloud/ui/draggrid/DragGridView;I)I
pop
aload 0
getfield com/nd/android/u/cloud/ui/draggrid/DragGridView$1/this$0 Lcom/nd/android/u/cloud/ui/draggrid/DragGridView;
invokestatic com/nd/android/u/cloud/ui/draggrid/DragGridView/access$300(Lcom/nd/android/u/cloud/ui/draggrid/DragGridView;)I
iconst_m1
if_icmpne L0
iconst_0
ireturn
L0:
aload 0
getfield com/nd/android/u/cloud/ui/draggrid/DragGridView$1/this$0 Lcom/nd/android/u/cloud/ui/draggrid/DragGridView;
aload 0
getfield com/nd/android/u/cloud/ui/draggrid/DragGridView$1/this$0 Lcom/nd/android/u/cloud/ui/draggrid/DragGridView;
invokestatic com/nd/android/u/cloud/ui/draggrid/DragGridView/access$300(Lcom/nd/android/u/cloud/ui/draggrid/DragGridView;)I
aload 0
getfield com/nd/android/u/cloud/ui/draggrid/DragGridView$1/this$0 Lcom/nd/android/u/cloud/ui/draggrid/DragGridView;
invokevirtual com/nd/android/u/cloud/ui/draggrid/DragGridView/getFirstVisiblePosition()I
isub
invokevirtual com/nd/android/u/cloud/ui/draggrid/DragGridView/getChildAt(I)Landroid/view/View;
checkcast android/view/ViewGroup
astore 1
aload 0
getfield com/nd/android/u/cloud/ui/draggrid/DragGridView$1/this$0 Lcom/nd/android/u/cloud/ui/draggrid/DragGridView;
invokestatic com/nd/android/u/cloud/ui/draggrid/DragGridView/access$500(Lcom/nd/android/u/cloud/ui/draggrid/DragGridView;)Z
ifne L1
aload 0
getfield com/nd/android/u/cloud/ui/draggrid/DragGridView$1/this$0 Lcom/nd/android/u/cloud/ui/draggrid/DragGridView;
aload 1
invokevirtual android/view/ViewGroup/getWidth()I
iconst_2
idiv
invokestatic com/nd/android/u/cloud/ui/draggrid/DragGridView/access$602(Lcom/nd/android/u/cloud/ui/draggrid/DragGridView;I)I
pop
aload 0
getfield com/nd/android/u/cloud/ui/draggrid/DragGridView$1/this$0 Lcom/nd/android/u/cloud/ui/draggrid/DragGridView;
aload 0
getfield com/nd/android/u/cloud/ui/draggrid/DragGridView$1/this$0 Lcom/nd/android/u/cloud/ui/draggrid/DragGridView;
invokevirtual com/nd/android/u/cloud/ui/draggrid/DragGridView/getCount()I
invokestatic com/nd/android/u/cloud/ui/draggrid/DragGridView/access$702(Lcom/nd/android/u/cloud/ui/draggrid/DragGridView;I)I
pop
aload 0
getfield com/nd/android/u/cloud/ui/draggrid/DragGridView$1/this$0 Lcom/nd/android/u/cloud/ui/draggrid/DragGridView;
invokestatic com/nd/android/u/cloud/ui/draggrid/DragGridView/access$700(Lcom/nd/android/u/cloud/ui/draggrid/DragGridView;)I
aload 0
getfield com/nd/android/u/cloud/ui/draggrid/DragGridView$1/this$0 Lcom/nd/android/u/cloud/ui/draggrid/DragGridView;
invokestatic com/nd/android/u/cloud/ui/draggrid/DragGridView/access$800(Lcom/nd/android/u/cloud/ui/draggrid/DragGridView;)I
idiv
istore 3
aload 0
getfield com/nd/android/u/cloud/ui/draggrid/DragGridView$1/this$0 Lcom/nd/android/u/cloud/ui/draggrid/DragGridView;
aload 0
getfield com/nd/android/u/cloud/ui/draggrid/DragGridView$1/this$0 Lcom/nd/android/u/cloud/ui/draggrid/DragGridView;
invokestatic com/nd/android/u/cloud/ui/draggrid/DragGridView/access$700(Lcom/nd/android/u/cloud/ui/draggrid/DragGridView;)I
aload 0
getfield com/nd/android/u/cloud/ui/draggrid/DragGridView$1/this$0 Lcom/nd/android/u/cloud/ui/draggrid/DragGridView;
invokestatic com/nd/android/u/cloud/ui/draggrid/DragGridView/access$800(Lcom/nd/android/u/cloud/ui/draggrid/DragGridView;)I
irem
invokestatic com/nd/android/u/cloud/ui/draggrid/DragGridView/access$902(Lcom/nd/android/u/cloud/ui/draggrid/DragGridView;I)I
pop
aload 0
getfield com/nd/android/u/cloud/ui/draggrid/DragGridView$1/this$0 Lcom/nd/android/u/cloud/ui/draggrid/DragGridView;
astore 2
aload 0
getfield com/nd/android/u/cloud/ui/draggrid/DragGridView$1/this$0 Lcom/nd/android/u/cloud/ui/draggrid/DragGridView;
invokestatic com/nd/android/u/cloud/ui/draggrid/DragGridView/access$900(Lcom/nd/android/u/cloud/ui/draggrid/DragGridView;)I
ifne L2
L3:
aload 2
iload 3
invokestatic com/nd/android/u/cloud/ui/draggrid/DragGridView/access$1002(Lcom/nd/android/u/cloud/ui/draggrid/DragGridView;I)I
pop
aload 0
getfield com/nd/android/u/cloud/ui/draggrid/DragGridView$1/this$0 Lcom/nd/android/u/cloud/ui/draggrid/DragGridView;
aload 0
getfield com/nd/android/u/cloud/ui/draggrid/DragGridView$1/this$0 Lcom/nd/android/u/cloud/ui/draggrid/DragGridView;
invokestatic com/nd/android/u/cloud/ui/draggrid/DragGridView/access$700(Lcom/nd/android/u/cloud/ui/draggrid/DragGridView;)I
iconst_1
isub
aload 0
getfield com/nd/android/u/cloud/ui/draggrid/DragGridView$1/this$0 Lcom/nd/android/u/cloud/ui/draggrid/DragGridView;
invokestatic com/nd/android/u/cloud/ui/draggrid/DragGridView/access$900(Lcom/nd/android/u/cloud/ui/draggrid/DragGridView;)I
isub
invokestatic com/nd/android/u/cloud/ui/draggrid/DragGridView/access$1102(Lcom/nd/android/u/cloud/ui/draggrid/DragGridView;I)I
pop
aload 0
getfield com/nd/android/u/cloud/ui/draggrid/DragGridView$1/this$0 Lcom/nd/android/u/cloud/ui/draggrid/DragGridView;
invokestatic com/nd/android/u/cloud/ui/draggrid/DragGridView/access$900(Lcom/nd/android/u/cloud/ui/draggrid/DragGridView;)I
iconst_1
if_icmpeq L4
aload 0
getfield com/nd/android/u/cloud/ui/draggrid/DragGridView$1/this$0 Lcom/nd/android/u/cloud/ui/draggrid/DragGridView;
aload 0
getfield com/nd/android/u/cloud/ui/draggrid/DragGridView$1/this$0 Lcom/nd/android/u/cloud/ui/draggrid/DragGridView;
invokestatic com/nd/android/u/cloud/ui/draggrid/DragGridView/access$800(Lcom/nd/android/u/cloud/ui/draggrid/DragGridView;)I
aload 0
getfield com/nd/android/u/cloud/ui/draggrid/DragGridView$1/this$0 Lcom/nd/android/u/cloud/ui/draggrid/DragGridView;
invokestatic com/nd/android/u/cloud/ui/draggrid/DragGridView/access$1000(Lcom/nd/android/u/cloud/ui/draggrid/DragGridView;)I
iconst_1
isub
imul
invokestatic com/nd/android/u/cloud/ui/draggrid/DragGridView/access$1202(Lcom/nd/android/u/cloud/ui/draggrid/DragGridView;I)I
pop
L4:
aload 0
getfield com/nd/android/u/cloud/ui/draggrid/DragGridView$1/this$0 Lcom/nd/android/u/cloud/ui/draggrid/DragGridView;
invokestatic com/nd/android/u/cloud/ui/draggrid/DragGridView/access$900(Lcom/nd/android/u/cloud/ui/draggrid/DragGridView;)I
ifeq L5
aload 0
getfield com/nd/android/u/cloud/ui/draggrid/DragGridView$1/this$0 Lcom/nd/android/u/cloud/ui/draggrid/DragGridView;
invokestatic com/nd/android/u/cloud/ui/draggrid/DragGridView/access$1000(Lcom/nd/android/u/cloud/ui/draggrid/DragGridView;)I
iconst_1
if_icmpne L6
L5:
aload 0
getfield com/nd/android/u/cloud/ui/draggrid/DragGridView$1/this$0 Lcom/nd/android/u/cloud/ui/draggrid/DragGridView;
iconst_m1
invokestatic com/nd/android/u/cloud/ui/draggrid/DragGridView/access$1102(Lcom/nd/android/u/cloud/ui/draggrid/DragGridView;I)I
pop
L6:
aload 0
getfield com/nd/android/u/cloud/ui/draggrid/DragGridView$1/this$0 Lcom/nd/android/u/cloud/ui/draggrid/DragGridView;
iconst_1
invokestatic com/nd/android/u/cloud/ui/draggrid/DragGridView/access$502(Lcom/nd/android/u/cloud/ui/draggrid/DragGridView;Z)Z
pop
L1:
aload 0
getfield com/nd/android/u/cloud/ui/draggrid/DragGridView$1/this$0 Lcom/nd/android/u/cloud/ui/draggrid/DragGridView;
invokestatic com/nd/android/u/cloud/ui/draggrid/DragGridView/access$1100(Lcom/nd/android/u/cloud/ui/draggrid/DragGridView;)I
aload 0
getfield com/nd/android/u/cloud/ui/draggrid/DragGridView$1/this$0 Lcom/nd/android/u/cloud/ui/draggrid/DragGridView;
invokestatic com/nd/android/u/cloud/ui/draggrid/DragGridView/access$300(Lcom/nd/android/u/cloud/ui/draggrid/DragGridView;)I
if_icmpeq L7
aload 0
getfield com/nd/android/u/cloud/ui/draggrid/DragGridView$1/this$0 Lcom/nd/android/u/cloud/ui/draggrid/DragGridView;
invokestatic com/nd/android/u/cloud/ui/draggrid/DragGridView/access$300(Lcom/nd/android/u/cloud/ui/draggrid/DragGridView;)I
iconst_m1
if_icmpeq L7
aload 0
getfield com/nd/android/u/cloud/ui/draggrid/DragGridView$1/this$0 Lcom/nd/android/u/cloud/ui/draggrid/DragGridView;
invokestatic com/nd/android/u/cloud/ui/draggrid/DragGridView/access$1100(Lcom/nd/android/u/cloud/ui/draggrid/DragGridView;)I
iflt L7
aload 0
getfield com/nd/android/u/cloud/ui/draggrid/DragGridView$1/this$0 Lcom/nd/android/u/cloud/ui/draggrid/DragGridView;
aload 0
getfield com/nd/android/u/cloud/ui/draggrid/DragGridView$1/this$0 Lcom/nd/android/u/cloud/ui/draggrid/DragGridView;
invokestatic com/nd/android/u/cloud/ui/draggrid/DragGridView/access$1100(Lcom/nd/android/u/cloud/ui/draggrid/DragGridView;)I
invokevirtual com/nd/android/u/cloud/ui/draggrid/DragGridView/getChildAt(I)Landroid/view/View;
ifnull L7
aload 0
getfield com/nd/android/u/cloud/ui/draggrid/DragGridView$1/this$0 Lcom/nd/android/u/cloud/ui/draggrid/DragGridView;
aload 0
getfield com/nd/android/u/cloud/ui/draggrid/DragGridView$1/this$0 Lcom/nd/android/u/cloud/ui/draggrid/DragGridView;
invokestatic com/nd/android/u/cloud/ui/draggrid/DragGridView/access$1100(Lcom/nd/android/u/cloud/ui/draggrid/DragGridView;)I
invokevirtual com/nd/android/u/cloud/ui/draggrid/DragGridView/getChildAt(I)Landroid/view/View;
ifnull L7
aload 0
getfield com/nd/android/u/cloud/ui/draggrid/DragGridView$1/this$0 Lcom/nd/android/u/cloud/ui/draggrid/DragGridView;
aload 0
getfield com/nd/android/u/cloud/ui/draggrid/DragGridView$1/this$0 Lcom/nd/android/u/cloud/ui/draggrid/DragGridView;
aload 0
getfield com/nd/android/u/cloud/ui/draggrid/DragGridView$1/this$0 Lcom/nd/android/u/cloud/ui/draggrid/DragGridView;
invokestatic com/nd/android/u/cloud/ui/draggrid/DragGridView/access$1100(Lcom/nd/android/u/cloud/ui/draggrid/DragGridView;)I
invokevirtual com/nd/android/u/cloud/ui/draggrid/DragGridView/getChildAt(I)Landroid/view/View;
invokevirtual android/view/View/getTop()I
invokestatic com/nd/android/u/cloud/ui/draggrid/DragGridView/access$1302(Lcom/nd/android/u/cloud/ui/draggrid/DragGridView;I)I
pop
L8:
aload 0
getfield com/nd/android/u/cloud/ui/draggrid/DragGridView$1/this$0 Lcom/nd/android/u/cloud/ui/draggrid/DragGridView;
invokestatic com/nd/android/u/cloud/ui/draggrid/DragGridView/access$1200(Lcom/nd/android/u/cloud/ui/draggrid/DragGridView;)I
aload 0
getfield com/nd/android/u/cloud/ui/draggrid/DragGridView$1/this$0 Lcom/nd/android/u/cloud/ui/draggrid/DragGridView;
invokestatic com/nd/android/u/cloud/ui/draggrid/DragGridView/access$300(Lcom/nd/android/u/cloud/ui/draggrid/DragGridView;)I
if_icmpeq L9
aload 0
getfield com/nd/android/u/cloud/ui/draggrid/DragGridView$1/this$0 Lcom/nd/android/u/cloud/ui/draggrid/DragGridView;
invokestatic com/nd/android/u/cloud/ui/draggrid/DragGridView/access$300(Lcom/nd/android/u/cloud/ui/draggrid/DragGridView;)I
iconst_m1
if_icmpeq L9
aload 0
getfield com/nd/android/u/cloud/ui/draggrid/DragGridView$1/this$0 Lcom/nd/android/u/cloud/ui/draggrid/DragGridView;
aload 0
getfield com/nd/android/u/cloud/ui/draggrid/DragGridView$1/this$0 Lcom/nd/android/u/cloud/ui/draggrid/DragGridView;
invokestatic com/nd/android/u/cloud/ui/draggrid/DragGridView/access$1200(Lcom/nd/android/u/cloud/ui/draggrid/DragGridView;)I
invokevirtual com/nd/android/u/cloud/ui/draggrid/DragGridView/getChildAt(I)Landroid/view/View;
ifnull L9
aload 0
getfield com/nd/android/u/cloud/ui/draggrid/DragGridView$1/this$0 Lcom/nd/android/u/cloud/ui/draggrid/DragGridView;
aload 0
getfield com/nd/android/u/cloud/ui/draggrid/DragGridView$1/this$0 Lcom/nd/android/u/cloud/ui/draggrid/DragGridView;
invokestatic com/nd/android/u/cloud/ui/draggrid/DragGridView/access$1200(Lcom/nd/android/u/cloud/ui/draggrid/DragGridView;)I
invokevirtual com/nd/android/u/cloud/ui/draggrid/DragGridView/getChildAt(I)Landroid/view/View;
ifnull L9
aload 0
getfield com/nd/android/u/cloud/ui/draggrid/DragGridView$1/this$0 Lcom/nd/android/u/cloud/ui/draggrid/DragGridView;
aload 0
getfield com/nd/android/u/cloud/ui/draggrid/DragGridView$1/this$0 Lcom/nd/android/u/cloud/ui/draggrid/DragGridView;
aload 0
getfield com/nd/android/u/cloud/ui/draggrid/DragGridView$1/this$0 Lcom/nd/android/u/cloud/ui/draggrid/DragGridView;
invokestatic com/nd/android/u/cloud/ui/draggrid/DragGridView/access$1200(Lcom/nd/android/u/cloud/ui/draggrid/DragGridView;)I
invokevirtual com/nd/android/u/cloud/ui/draggrid/DragGridView/getChildAt(I)Landroid/view/View;
invokevirtual android/view/View/getTop()I
invokestatic com/nd/android/u/cloud/ui/draggrid/DragGridView/access$1402(Lcom/nd/android/u/cloud/ui/draggrid/DragGridView;I)I
pop
L10:
aload 0
getfield com/nd/android/u/cloud/ui/draggrid/DragGridView$1/this$0 Lcom/nd/android/u/cloud/ui/draggrid/DragGridView;
aload 1
invokestatic com/nd/android/u/cloud/ui/draggrid/DragGridView/access$1502(Lcom/nd/android/u/cloud/ui/draggrid/DragGridView;Landroid/view/ViewGroup;)Landroid/view/ViewGroup;
pop
aload 1
invokevirtual android/view/ViewGroup/destroyDrawingCache()V
aload 1
iconst_1
invokevirtual android/view/ViewGroup/setDrawingCacheEnabled(Z)V
aload 1
iconst_0
invokevirtual android/view/ViewGroup/setDrawingCacheBackgroundColor(I)V
aload 1
iconst_1
invokevirtual android/view/ViewGroup/getDrawingCache(Z)Landroid/graphics/Bitmap;
invokestatic android/graphics/Bitmap/createBitmap(Landroid/graphics/Bitmap;)Landroid/graphics/Bitmap;
astore 2
aload 2
iconst_0
iconst_0
aload 2
invokevirtual android/graphics/Bitmap/getWidth()I
aload 2
invokevirtual android/graphics/Bitmap/getHeight()I
invokestatic android/graphics/Bitmap/createBitmap(Landroid/graphics/Bitmap;IIII)Landroid/graphics/Bitmap;
astore 2
aload 0
getfield com/nd/android/u/cloud/ui/draggrid/DragGridView$1/this$0 Lcom/nd/android/u/cloud/ui/draggrid/DragGridView;
aload 2
iload 6
iload 7
invokestatic com/nd/android/u/cloud/ui/draggrid/DragGridView/access$1600(Lcom/nd/android/u/cloud/ui/draggrid/DragGridView;Landroid/graphics/Bitmap;II)V
aload 0
getfield com/nd/android/u/cloud/ui/draggrid/DragGridView$1/this$0 Lcom/nd/android/u/cloud/ui/draggrid/DragGridView;
invokestatic com/nd/android/u/cloud/ui/draggrid/DragGridView/access$1700(Lcom/nd/android/u/cloud/ui/draggrid/DragGridView;)V
aload 1
iconst_4
invokevirtual android/view/ViewGroup/setVisibility(I)V
aload 0
getfield com/nd/android/u/cloud/ui/draggrid/DragGridView$1/this$0 Lcom/nd/android/u/cloud/ui/draggrid/DragGridView;
iconst_0
invokestatic com/nd/android/u/cloud/ui/draggrid/DragGridView/access$1802(Lcom/nd/android/u/cloud/ui/draggrid/DragGridView;Z)Z
pop
iconst_0
ireturn
L2:
iload 3
iconst_1
iadd
istore 3
goto L3
L7:
aload 0
getfield com/nd/android/u/cloud/ui/draggrid/DragGridView$1/this$0 Lcom/nd/android/u/cloud/ui/draggrid/DragGridView;
iconst_m1
invokestatic com/nd/android/u/cloud/ui/draggrid/DragGridView/access$1302(Lcom/nd/android/u/cloud/ui/draggrid/DragGridView;I)I
pop
goto L8
L9:
aload 0
getfield com/nd/android/u/cloud/ui/draggrid/DragGridView$1/this$0 Lcom/nd/android/u/cloud/ui/draggrid/DragGridView;
iconst_m1
invokestatic com/nd/android/u/cloud/ui/draggrid/DragGridView/access$1402(Lcom/nd/android/u/cloud/ui/draggrid/DragGridView;I)I
pop
goto L10
.limit locals 8
.limit stack 5
.end method
