.bytecode 50.0
.class public synchronized com/nd/schoollife/controller/operator/impl/tmp/TmpTeamOperatorImpl
.super com/nd/schoollife/controller/operator/impl/BaseOperator
.implements com/nd/schoollife/controller/operator/ITeamOperator

.field private 'resultTeamInfoBean' Lcom/nd/android/forumsdk/business/bean/result/ResultTeamInfoBean;

.field 'teamCom' Lcom/nd/android/forumsdk/business/com/http/ITeamCom;

.method public <init>()V
aload 0
invokespecial com/nd/schoollife/controller/operator/impl/BaseOperator/<init>()V
aload 0
aconst_null
putfield com/nd/schoollife/controller/operator/impl/tmp/TmpTeamOperatorImpl/teamCom Lcom/nd/android/forumsdk/business/com/http/ITeamCom;
aload 0
new com/nd/android/forumsdk/business/bean/result/ResultTeamInfoBean
dup
invokespecial com/nd/android/forumsdk/business/bean/result/ResultTeamInfoBean/<init>()V
putfield com/nd/schoollife/controller/operator/impl/tmp/TmpTeamOperatorImpl/resultTeamInfoBean Lcom/nd/android/forumsdk/business/bean/result/ResultTeamInfoBean;
aload 0
invokestatic com/nd/schoollife/business/com/SchoolLifeHttpFactory/getInstance()Lcom/nd/schoollife/business/com/SchoolLifeHttpFactory;
invokevirtual com/nd/schoollife/business/com/SchoolLifeHttpFactory/getTeamCom()Lcom/nd/android/forumsdk/business/com/http/ITeamCom;
putfield com/nd/schoollife/controller/operator/impl/tmp/TmpTeamOperatorImpl/teamCom Lcom/nd/android/forumsdk/business/com/http/ITeamCom;
return
.limit locals 1
.limit stack 3
.end method

.method public createNewTeam(Ljava/lang/String;Ljava/lang/String;[J[JLjava/lang/String;)Lcom/nd/android/forumsdk/business/bean/result/ResultTeamInfoBean;
.catch java/lang/Exception from L0 to L1 using L2
L0:
aload 0
getfield com/nd/schoollife/controller/operator/impl/tmp/TmpTeamOperatorImpl/resultTeamInfoBean Lcom/nd/android/forumsdk/business/bean/result/ResultTeamInfoBean;
sipush 200
invokevirtual com/nd/android/forumsdk/business/bean/result/ResultTeamInfoBean/setResultCode(I)V
ldc2_w 1000L
invokestatic java/lang/Thread/sleep(J)V
L1:
aload 0
getfield com/nd/schoollife/controller/operator/impl/tmp/TmpTeamOperatorImpl/resultTeamInfoBean Lcom/nd/android/forumsdk/business/bean/result/ResultTeamInfoBean;
areturn
L2:
astore 1
aload 0
getfield com/nd/schoollife/controller/operator/impl/tmp/TmpTeamOperatorImpl/resultTeamInfoBean Lcom/nd/android/forumsdk/business/bean/result/ResultTeamInfoBean;
sipush 999
invokevirtual com/nd/android/forumsdk/business/bean/result/ResultTeamInfoBean/setResultCode(I)V
aload 0
getfield com/nd/schoollife/controller/operator/impl/tmp/TmpTeamOperatorImpl/resultTeamInfoBean Lcom/nd/android/forumsdk/business/bean/result/ResultTeamInfoBean;
aload 1
invokevirtual java/lang/Exception/getMessage()Ljava/lang/String;
invokevirtual com/nd/android/forumsdk/business/bean/result/ResultTeamInfoBean/setResultMsg(Ljava/lang/String;)V
ldc "TeamOperatorImpl"
new java/lang/StringBuilder
dup
invokespecial java/lang/StringBuilder/<init>()V
ldc "createNewTeam  -- resultCode : "
invokevirtual java/lang/StringBuilder/append(Ljava/lang/String;)Ljava/lang/StringBuilder;
aload 0
getfield com/nd/schoollife/controller/operator/impl/tmp/TmpTeamOperatorImpl/resultTeamInfoBean Lcom/nd/android/forumsdk/business/bean/result/ResultTeamInfoBean;
invokevirtual com/nd/android/forumsdk/business/bean/result/ResultTeamInfoBean/getResultCode()I
invokevirtual java/lang/StringBuilder/append(I)Ljava/lang/StringBuilder;
ldc " -- resultMsg : "
invokevirtual java/lang/StringBuilder/append(Ljava/lang/String;)Ljava/lang/StringBuilder;
aload 0
getfield com/nd/schoollife/controller/operator/impl/tmp/TmpTeamOperatorImpl/resultTeamInfoBean Lcom/nd/android/forumsdk/business/bean/result/ResultTeamInfoBean;
invokevirtual com/nd/android/forumsdk/business/bean/result/ResultTeamInfoBean/getResultMsg()Ljava/lang/String;
invokevirtual java/lang/StringBuilder/append(Ljava/lang/String;)Ljava/lang/StringBuilder;
invokevirtual java/lang/StringBuilder/toString()Ljava/lang/String;
invokestatic com/nd/schoollife/common/utils/ui/LogUtil/e(Ljava/lang/String;Ljava/lang/String;)V
goto L1
.limit locals 6
.limit stack 3
.end method

.method public doFocusOrNot(JZ)Lcom/nd/android/forumsdk/business/bean/ForumResultBase;
.catch java/lang/Exception from L0 to L1 using L2
new com/nd/android/forumsdk/business/bean/ForumResultBase
dup
invokespecial com/nd/android/forumsdk/business/bean/ForumResultBase/<init>()V
astore 4
L0:
aload 4
sipush 200
invokevirtual com/nd/android/forumsdk/business/bean/ForumResultBase/setResultCode(I)V
L1:
aload 4
areturn
L2:
astore 5
aload 4
sipush 999
invokevirtual com/nd/android/forumsdk/business/bean/ForumResultBase/setResultCode(I)V
aload 4
aload 5
invokevirtual java/lang/Exception/getMessage()Ljava/lang/String;
invokevirtual com/nd/android/forumsdk/business/bean/ForumResultBase/setResultMsg(Ljava/lang/String;)V
ldc "TeamOperatorImpl"
new java/lang/StringBuilder
dup
invokespecial java/lang/StringBuilder/<init>()V
ldc "doFocusOrNot  -- resultCode : "
invokevirtual java/lang/StringBuilder/append(Ljava/lang/String;)Ljava/lang/StringBuilder;
aload 4
invokevirtual com/nd/android/forumsdk/business/bean/ForumResultBase/getResultCode()I
invokevirtual java/lang/StringBuilder/append(I)Ljava/lang/StringBuilder;
ldc " -- resultMsg : "
invokevirtual java/lang/StringBuilder/append(Ljava/lang/String;)Ljava/lang/StringBuilder;
aload 4
invokevirtual com/nd/android/forumsdk/business/bean/ForumResultBase/getResultMsg()Ljava/lang/String;
invokevirtual java/lang/StringBuilder/append(Ljava/lang/String;)Ljava/lang/StringBuilder;
invokevirtual java/lang/StringBuilder/toString()Ljava/lang/String;
invokestatic com/nd/schoollife/common/utils/ui/LogUtil/e(Ljava/lang/String;Ljava/lang/String;)V
aload 4
areturn
.limit locals 6
.limit stack 3
.end method

.method public editTeamInfo(JLjava/lang/String;Ljava/lang/String;[J[JLjava/lang/String;)Lcom/nd/android/forumsdk/business/bean/result/ResultTeamInfoBean;
.catch java/lang/Exception from L0 to L1 using L2
L0:
aload 0
getfield com/nd/schoollife/controller/operator/impl/tmp/TmpTeamOperatorImpl/resultTeamInfoBean Lcom/nd/android/forumsdk/business/bean/result/ResultTeamInfoBean;
sipush 200
invokevirtual com/nd/android/forumsdk/business/bean/result/ResultTeamInfoBean/setResultCode(I)V
L1:
aload 0
getfield com/nd/schoollife/controller/operator/impl/tmp/TmpTeamOperatorImpl/resultTeamInfoBean Lcom/nd/android/forumsdk/business/bean/result/ResultTeamInfoBean;
areturn
L2:
astore 3
aload 0
getfield com/nd/schoollife/controller/operator/impl/tmp/TmpTeamOperatorImpl/resultTeamInfoBean Lcom/nd/android/forumsdk/business/bean/result/ResultTeamInfoBean;
sipush 999
invokevirtual com/nd/android/forumsdk/business/bean/result/ResultTeamInfoBean/setResultCode(I)V
aload 0
getfield com/nd/schoollife/controller/operator/impl/tmp/TmpTeamOperatorImpl/resultTeamInfoBean Lcom/nd/android/forumsdk/business/bean/result/ResultTeamInfoBean;
aload 3
invokevirtual java/lang/Exception/getMessage()Ljava/lang/String;
invokevirtual com/nd/android/forumsdk/business/bean/result/ResultTeamInfoBean/setResultMsg(Ljava/lang/String;)V
ldc "TeamOperatorImpl"
new java/lang/StringBuilder
dup
invokespecial java/lang/StringBuilder/<init>()V
ldc "editTeamInfo  -- resultCode : "
invokevirtual java/lang/StringBuilder/append(Ljava/lang/String;)Ljava/lang/StringBuilder;
aload 0
getfield com/nd/schoollife/controller/operator/impl/tmp/TmpTeamOperatorImpl/resultTeamInfoBean Lcom/nd/android/forumsdk/business/bean/result/ResultTeamInfoBean;
invokevirtual com/nd/android/forumsdk/business/bean/result/ResultTeamInfoBean/getResultCode()I
invokevirtual java/lang/StringBuilder/append(I)Ljava/lang/StringBuilder;
ldc " -- resultMsg : "
invokevirtual java/lang/StringBuilder/append(Ljava/lang/String;)Ljava/lang/StringBuilder;
aload 0
getfield com/nd/schoollife/controller/operator/impl/tmp/TmpTeamOperatorImpl/resultTeamInfoBean Lcom/nd/android/forumsdk/business/bean/result/ResultTeamInfoBean;
invokevirtual com/nd/android/forumsdk/business/bean/result/ResultTeamInfoBean/getResultMsg()Ljava/lang/String;
invokevirtual java/lang/StringBuilder/append(Ljava/lang/String;)Ljava/lang/StringBuilder;
invokevirtual java/lang/StringBuilder/toString()Ljava/lang/String;
invokestatic com/nd/schoollife/common/utils/ui/LogUtil/e(Ljava/lang/String;Ljava/lang/String;)V
goto L1
.limit locals 8
.limit stack 3
.end method

.method public getAllCategoryForTeam()Lcom/nd/android/forumsdk/business/bean/result/ResultGetTeamCategory;
.catch java/lang/Exception from L0 to L1 using L2
.catch java/lang/Exception from L3 to L4 using L2
.catch java/lang/Exception from L5 to L6 using L2
new com/nd/android/forumsdk/business/bean/result/ResultGetTeamCategory
dup
invokespecial com/nd/android/forumsdk/business/bean/result/ResultGetTeamCategory/<init>()V
astore 2
L0:
aload 2
sipush 200
invokevirtual com/nd/android/forumsdk/business/bean/result/ResultGetTeamCategory/setResultCode(I)V
new java/util/ArrayList
dup
invokespecial java/util/ArrayList/<init>()V
astore 3
L1:
iconst_0
istore 1
L7:
iload 1
iconst_3
if_icmpge L5
L3:
new com/nd/android/forumsdk/business/bean/result/CategoryInfoBean
dup
invokespecial com/nd/android/forumsdk/business/bean/result/CategoryInfoBean/<init>()V
astore 4
aload 4
iload 1
i2l
invokevirtual com/nd/android/forumsdk/business/bean/result/CategoryInfoBean/setId(J)V
aload 4
ldc "http://quc.qhimg.com/dm/180_180_100/t017965e53d0b1cb18f.jpg"
invokevirtual com/nd/android/forumsdk/business/bean/result/CategoryInfoBean/setAvatar(Ljava/lang/String;)V
aload 4
iconst_3
anewarray java/lang/String
dup
iconst_0
ldc "\u5b66\u751f\u793e\u56e2"
aastore
dup
iconst_1
ldc "\u5b66\u751f\u7ec4\u7ec7"
aastore
dup
iconst_2
ldc "\u5176\u5b83"
aastore
iload 1
aaload
invokevirtual com/nd/android/forumsdk/business/bean/result/CategoryInfoBean/setName(Ljava/lang/String;)V
aload 4
ldc "\u6ca1\u6709\u5440\u6ca1\u6709\u5440\u6ca1\u6709\u5440\u6ca1\u6709\u5440\u6ca1\u6709\u5440\u6ca1\u6709\u5440\u6ca1\u6709\u5440"
invokevirtual com/nd/android/forumsdk/business/bean/result/CategoryInfoBean/setIntro(Ljava/lang/String;)V
aload 3
aload 4
invokeinterface java/util/List/add(Ljava/lang/Object;)Z 1
pop
L4:
iload 1
iconst_1
iadd
istore 1
goto L7
L5:
aload 2
aload 3
invokevirtual com/nd/android/forumsdk/business/bean/result/ResultGetTeamCategory/setList(Ljava/util/List;)V
aload 2
iconst_4
invokevirtual com/nd/android/forumsdk/business/bean/result/ResultGetTeamCategory/setTotal(I)V
L6:
aload 2
areturn
L2:
astore 3
aload 2
sipush 999
invokevirtual com/nd/android/forumsdk/business/bean/result/ResultGetTeamCategory/setResultCode(I)V
aload 2
aload 3
invokevirtual java/lang/Exception/getMessage()Ljava/lang/String;
invokevirtual com/nd/android/forumsdk/business/bean/result/ResultGetTeamCategory/setResultMsg(Ljava/lang/String;)V
ldc "TeamOperatorImpl"
new java/lang/StringBuilder
dup
invokespecial java/lang/StringBuilder/<init>()V
ldc "getHotTeam  -- resultCode : "
invokevirtual java/lang/StringBuilder/append(Ljava/lang/String;)Ljava/lang/StringBuilder;
aload 2
invokevirtual com/nd/android/forumsdk/business/bean/result/ResultGetTeamCategory/getResultCode()I
invokevirtual java/lang/StringBuilder/append(I)Ljava/lang/StringBuilder;
ldc " -- resultMsg : "
invokevirtual java/lang/StringBuilder/append(Ljava/lang/String;)Ljava/lang/StringBuilder;
aload 2
invokevirtual com/nd/android/forumsdk/business/bean/result/ResultGetTeamCategory/getResultMsg()Ljava/lang/String;
invokevirtual java/lang/StringBuilder/append(Ljava/lang/String;)Ljava/lang/StringBuilder;
invokevirtual java/lang/StringBuilder/toString()Ljava/lang/String;
invokestatic com/nd/schoollife/common/utils/ui/LogUtil/e(Ljava/lang/String;Ljava/lang/String;)V
aload 2
areturn
.limit locals 5
.limit stack 5
.end method

.method public getHotTeam(JII)Lcom/nd/android/forumsdk/business/bean/result/ResultTeamInfoList;
new com/nd/android/forumsdk/business/bean/result/ResultTeamInfoList
dup
invokespecial com/nd/android/forumsdk/business/bean/result/ResultTeamInfoList/<init>()V
astore 5
new java/util/ArrayList
dup
invokespecial java/util/ArrayList/<init>()V
astore 6
new com/nd/android/forumsdk/business/bean/structure/TeamInfoBean
dup
invokespecial com/nd/android/forumsdk/business/bean/structure/TeamInfoBean/<init>()V
astore 7
aload 7
ldc "\u6b66\u672f\u534f\u4f1a\u5e95\u4e0b\u4eba\u6570\u6700\u591a\uff0c\u6d3b\u52a8\u6700\u591a\u6570\u6700\u591a\uff0c\u6d3b\u52a8\u6570\u6700\u591a\uff0c\u6d3b\u52a8\u6570\u6700\u591a\uff0c\u6d3b\u52a8"
invokevirtual com/nd/android/forumsdk/business/bean/structure/TeamInfoBean/setIntro(Ljava/lang/String;)V
aload 7
ldc "\u6b66\u672f\u5957\u8def\u5c0f\u7ec4"
invokevirtual com/nd/android/forumsdk/business/bean/structure/TeamInfoBean/setName(Ljava/lang/String;)V
aload 7
ldc "http://quc.qhimg.com/dm/180_180_100/t017965e53d0b1cb18f.jpg"
invokevirtual com/nd/android/forumsdk/business/bean/structure/TeamInfoBean/setAvatar(Ljava/lang/String;)V
aload 7
sipush 651
invokevirtual com/nd/android/forumsdk/business/bean/structure/TeamInfoBean/setMembernum(I)V
iconst_0
istore 3
L0:
iload 3
iload 4
if_icmpge L1
aload 6
aload 7
invokeinterface java/util/List/add(Ljava/lang/Object;)Z 1
pop
iload 3
iconst_1
iadd
istore 3
goto L0
L1:
aload 5
aload 6
invokevirtual com/nd/android/forumsdk/business/bean/result/ResultTeamInfoList/setList(Ljava/util/List;)V
aload 5
sipush 200
invokevirtual com/nd/android/forumsdk/business/bean/result/ResultTeamInfoList/setResultCode(I)V
aload 5
areturn
.limit locals 8
.limit stack 2
.end method

.method public getMyFocusTeam(II)Lcom/nd/android/forumsdk/business/bean/result/ResultTeamInfoList;
.catch java/lang/InterruptedException from L0 to L1 using L2
new com/nd/android/forumsdk/business/bean/result/ResultTeamInfoList
dup
invokespecial com/nd/android/forumsdk/business/bean/result/ResultTeamInfoList/<init>()V
astore 3
aload 3
sipush 200
invokevirtual com/nd/android/forumsdk/business/bean/result/ResultTeamInfoList/setResultCode(I)V
new java/util/ArrayList
dup
invokespecial java/util/ArrayList/<init>()V
astore 4
new com/nd/android/forumsdk/business/bean/structure/TeamInfoBean
dup
invokespecial com/nd/android/forumsdk/business/bean/structure/TeamInfoBean/<init>()V
astore 5
aload 5
ldc "\u6444\u5f71\u5c0f\u7ec4"
invokevirtual com/nd/android/forumsdk/business/bean/structure/TeamInfoBean/setName(Ljava/lang/String;)V
aload 5
ldc "\u6444\u5f71\u5c0f\u7ec4\u6d3b\u52a8\u968f\u7740\u793e\u56e2\u6d3b\u52a8\u4e0d\u65ad\u7684\u6269\u5927\u6444\u5f71\u793e\u56e2\u4e5f\u5728\u65e5\u76ca\u58ee\u5927"
invokevirtual com/nd/android/forumsdk/business/bean/structure/TeamInfoBean/setIntro(Ljava/lang/String;)V
aload 5
iconst_1
invokevirtual com/nd/android/forumsdk/business/bean/structure/TeamInfoBean/setGrade(I)V
aload 5
ldc "http://quc.qhimg.com/dm/180_180_100/t017965e53d0b1cb18f.jpg"
invokevirtual com/nd/android/forumsdk/business/bean/structure/TeamInfoBean/setAvatar(Ljava/lang/String;)V
aload 4
aload 5
invokeinterface java/util/List/add(Ljava/lang/Object;)Z 1
pop
aload 4
aload 5
invokeinterface java/util/List/add(Ljava/lang/Object;)Z 1
pop
aload 3
aload 4
invokevirtual com/nd/android/forumsdk/business/bean/result/ResultTeamInfoList/setList(Ljava/util/List;)V
L0:
ldc2_w 3000L
invokestatic java/lang/Thread/sleep(J)V
L1:
aload 3
areturn
L2:
astore 4
aload 4
invokevirtual java/lang/InterruptedException/printStackTrace()V
aload 3
areturn
.limit locals 6
.limit stack 2
.end method

.method public getMyTeam(II)Lcom/nd/android/forumsdk/business/bean/result/ResultTeamInfoList;
.catch java/lang/InterruptedException from L0 to L1 using L2
new com/nd/android/forumsdk/business/bean/result/ResultTeamInfoList
dup
invokespecial com/nd/android/forumsdk/business/bean/result/ResultTeamInfoList/<init>()V
astore 3
aload 3
sipush 200
invokevirtual com/nd/android/forumsdk/business/bean/result/ResultTeamInfoList/setResultCode(I)V
new java/util/ArrayList
dup
invokespecial java/util/ArrayList/<init>()V
astore 4
new com/nd/android/forumsdk/business/bean/structure/TeamInfoBean
dup
invokespecial com/nd/android/forumsdk/business/bean/structure/TeamInfoBean/<init>()V
astore 5
aload 5
ldc "\u6444\u5f71\u5c0f\u7ec4"
invokevirtual com/nd/android/forumsdk/business/bean/structure/TeamInfoBean/setName(Ljava/lang/String;)V
aload 5
ldc "\u6444\u5f71\u5c0f\u7ec4\u6d3b\u52a8\u968f\u7740\u793e\u56e2\u6d3b\u52a8\u4e0d\u65ad\u7684\u6269\u5927\u6444\u5f71\u793e\u56e2\u4e5f\u5728\u65e5\u76ca\u58ee\u5927"
invokevirtual com/nd/android/forumsdk/business/bean/structure/TeamInfoBean/setIntro(Ljava/lang/String;)V
aload 5
iconst_2
invokevirtual com/nd/android/forumsdk/business/bean/structure/TeamInfoBean/setGrade(I)V
aload 5
ldc "http://quc.qhimg.com/dm/180_180_100/t017965e53d0b1cb18f.jpg"
invokevirtual com/nd/android/forumsdk/business/bean/structure/TeamInfoBean/setAvatar(Ljava/lang/String;)V
aload 4
aload 5
invokeinterface java/util/List/add(Ljava/lang/Object;)Z 1
pop
aload 4
aload 5
invokeinterface java/util/List/add(Ljava/lang/Object;)Z 1
pop
aload 3
aload 4
invokevirtual com/nd/android/forumsdk/business/bean/result/ResultTeamInfoList/setList(Ljava/util/List;)V
L0:
ldc2_w 3000L
invokestatic java/lang/Thread/sleep(J)V
L1:
aload 3
areturn
L2:
astore 4
aload 4
invokevirtual java/lang/InterruptedException/printStackTrace()V
aload 3
areturn
.limit locals 6
.limit stack 2
.end method

.method public getTags(II)Lcom/nd/android/forumsdk/business/bean/result/ResultGetTags;
.catch java/lang/Exception from L0 to L1 using L2
.catch java/lang/Exception from L3 to L4 using L2
.catch java/lang/Exception from L5 to L6 using L2
.catch java/lang/Exception from L7 to L8 using L2
.catch java/lang/Exception from L9 to L10 using L2
new com/nd/android/forumsdk/business/bean/result/ResultGetTags
dup
invokespecial com/nd/android/forumsdk/business/bean/result/ResultGetTags/<init>()V
astore 7
L0:
aload 7
sipush 200
invokevirtual com/nd/android/forumsdk/business/bean/result/ResultGetTags/setResultCode(I)V
new java/util/ArrayList
dup
invokespecial java/util/ArrayList/<init>()V
astore 8
aload 7
aload 8
invokevirtual com/nd/android/forumsdk/business/bean/result/ResultGetTags/setList(Ljava/util/List;)V
aload 8
invokeinterface java/util/List/clear()V 0
ldc2_w 1000L
invokestatic java/lang/Thread/sleep(J)V
new java/util/Random
dup
invokespecial java/util/Random/<init>()V
astore 9
aload 7
iload 2
invokevirtual com/nd/android/forumsdk/business/bean/result/ResultGetTags/setTotal(I)V
new java/util/ArrayList
dup
invokespecial java/util/ArrayList/<init>()V
astore 10
aload 10
bipush 20
anewarray java/lang/String
dup
iconst_0
ldc "\u8db3\u7403"
aastore
dup
iconst_1
ldc "\u7bee\u7403"
aastore
dup
iconst_2
ldc "\u4e52\u4e53\u7403"
aastore
dup
iconst_3
ldc "\u7fbd\u6bdb\u7403"
aastore
dup
iconst_4
ldc "\u7f51\u7403 "
aastore
dup
iconst_5
ldc "\u8dd1\u6b65"
aastore
dup
bipush 6
ldc "\u8857\u821e"
aastore
dup
bipush 7
ldc "\u81ea\u884c\u8f66"
aastore
dup
bipush 8
ldc "\u5065\u7f8e\u64cd"
aastore
dup
bipush 9
ldc "\u6b66\u672f "
aastore
dup
bipush 10
ldc "\u8f6e\u6ed1"
aastore
dup
bipush 11
ldc "\u745c\u4f3d"
aastore
dup
bipush 12
ldc "\u6865\u724c"
aastore
dup
bipush 13
ldc "\u68cb\u7c7b"
aastore
dup
bipush 14
ldc "\u684c\u6e38"
aastore
dup
bipush 15
ldc "\u7a7a\u624b\u9053 "
aastore
dup
bipush 16
ldc "\u8dc6\u62f3\u9053"
aastore
dup
bipush 17
ldc "\u6ed1\u677f"
aastore
dup
bipush 18
ldc "\u684c\u7403"
aastore
dup
bipush 19
ldc "\u6392\u7403"
aastore
invokeinterface java/util/List/add(Ljava/lang/Object;)Z 1
pop
aload 10
bipush 19
anewarray java/lang/String
dup
iconst_0
ldc "\u5409\u4ed6"
aastore
dup
iconst_1
ldc "\u94a2\u7434"
aastore
dup
iconst_2
ldc "\u5c0f\u63d0\u7434"
aastore
dup
iconst_3
ldc "\u4e50\u961f"
aastore
dup
iconst_4
ldc "\u56fd\u753b"
aastore
dup
iconst_5
ldc "\u6cb9\u753b"
aastore
dup
bipush 6
ldc "\u6c34\u5f69\u753b"
aastore
dup
bipush 7
ldc "\u6444\u5f71"
aastore
dup
bipush 8
ldc "\u4e66\u6cd5"
aastore
dup
bipush 9
ldc "\u96d5\u523b"
aastore
dup
bipush 10
ldc "\u5408\u5531 "
aastore
dup
bipush 11
ldc "\u6e05\u5531"
aastore
dup
bipush 12
ldc "\u53e3\u7434"
aastore
dup
bipush 13
ldc "\u7235\u58eb"
aastore
dup
bipush 14
ldc "\u62c9\u4e01\u821e"
aastore
dup
bipush 15
ldc "\u4ea4\u8c0a\u821e "
aastore
dup
bipush 16
ldc "\u914d\u97f3"
aastore
dup
bipush 17
ldc "\u8bbe\u8ba1"
aastore
dup
bipush 18
ldc "\u9b54\u672f"
aastore
invokeinterface java/util/List/add(Ljava/lang/Object;)Z 1
pop
aload 10
bipush 11
anewarray java/lang/String
dup
iconst_0
ldc "\u52a8\u6f2b"
aastore
dup
iconst_1
ldc "\u6587\u5b66"
aastore
dup
iconst_2
ldc "\u8bdd\u5267"
aastore
dup
iconst_3
ldc "\u620f\u5267"
aastore
dup
iconst_4
ldc "\u97f3\u4e50\u5267"
aastore
dup
iconst_5
ldc "\u5fc3\u7406\u5267"
aastore
dup
bipush 6
ldc "\u5f71\u8bc4"
aastore
dup
bipush 7
ldc "\u7535\u5f71"
aastore
dup
bipush 8
ldc "\u8bd7\u6b4c"
aastore
dup
bipush 9
ldc "\u519b\u4e8b"
aastore
dup
bipush 10
ldc "\u6c7d\u8f66"
aastore
invokeinterface java/util/List/add(Ljava/lang/Object;)Z 1
pop
aload 10
bipush 7
anewarray java/lang/String
dup
iconst_0
ldc "\u6cd5\u5b66"
aastore
dup
iconst_1
ldc "\u7406\u8bba"
aastore
dup
iconst_2
ldc "\u82f1\u8bed"
aastore
dup
iconst_3
ldc "\u53e4\u5178\u6587\u5b66"
aastore
dup
iconst_4
ldc "\u624b\u8bed "
aastore
dup
iconst_5
ldc "\u5546\u8d38"
aastore
dup
bipush 6
ldc "\u7406\u8d22"
aastore
invokeinterface java/util/List/add(Ljava/lang/Object;)Z 1
pop
aload 10
bipush 6
anewarray java/lang/String
dup
iconst_0
ldc "\u8ba1\u7b97\u673a"
aastore
dup
iconst_1
ldc "\u8f6f\u4ef6"
aastore
dup
iconst_2
ldc "\u786c\u4ef6"
aastore
dup
iconst_3
ldc "ACM"
aastore
dup
iconst_4
ldc "\u673a\u5668\u4eba"
aastore
dup
iconst_5
ldc "\u5929\u6587"
aastore
invokeinterface java/util/List/add(Ljava/lang/Object;)Z 1
pop
aload 10
bipush 14
anewarray java/lang/String
dup
iconst_0
ldc "\u521b\u4e1a"
aastore
dup
iconst_1
ldc "\u8fa9\u8bba"
aastore
dup
iconst_2
ldc "\u5fd7\u613f\u8005"
aastore
dup
iconst_3
ldc "\u73af\u4fdd"
aastore
dup
iconst_4
ldc "\u7231\u5fc3"
aastore
dup
iconst_5
ldc "\u8bb0\u8005"
aastore
dup
bipush 6
ldc "\u6a21\u8054"
aastore
dup
bipush 7
ldc "\u7f8e\u98df"
aastore
dup
bipush 8
ldc "\u65c5\u6e38"
aastore
dup
bipush 9
ldc "\u517b\u751f"
aastore
dup
bipush 10
ldc "\u56ed\u827a"
aastore
dup
bipush 11
ldc "\u624b\u5de5"
aastore
dup
bipush 12
ldc "\u70d8\u7119"
aastore
dup
bipush 13
ldc "\u5341\u5b57\u7ee3"
aastore
invokeinterface java/util/List/add(Ljava/lang/Object;)Z 1
pop
L1:
iconst_0
istore 4
goto L11
L12:
iload 1
istore 4
iload 3
bipush 6
if_icmpge L11
L3:
aload 9
aload 10
iload 3
invokeinterface java/util/List/get(I)Ljava/lang/Object; 1
checkcast [Ljava/lang/String;
arraylength
invokevirtual java/util/Random/nextInt(I)I
istore 6
L4:
iconst_0
istore 5
L5:
new com/nd/android/forumsdk/business/bean/structure/TagInfoBean
dup
invokespecial com/nd/android/forumsdk/business/bean/structure/TagInfoBean/<init>()V
astore 11
aload 11
aload 10
iload 3
invokeinterface java/util/List/get(I)Ljava/lang/Object; 1
checkcast [Ljava/lang/String;
iload 6
aaload
invokevirtual com/nd/android/forumsdk/business/bean/structure/TagInfoBean/setName(Ljava/lang/String;)V
L6:
iconst_0
istore 4
L13:
iload 4
iload 3
if_icmpge L9
L7:
iload 5
aload 10
iload 4
invokeinterface java/util/List/get(I)Ljava/lang/Object; 1
checkcast [Ljava/lang/String;
arraylength
iadd
istore 5
L8:
iload 4
iconst_1
iadd
istore 4
goto L13
L9:
aload 11
iload 5
iload 6
iadd
i2l
invokevirtual com/nd/android/forumsdk/business/bean/structure/TagInfoBean/setId(J)V
aload 8
aload 11
invokeinterface java/util/List/add(Ljava/lang/Object;)Z 1
pop
L10:
iload 1
iconst_1
iadd
istore 1
iload 3
iconst_1
iadd
istore 3
goto L12
L2:
astore 8
aload 7
sipush 999
invokevirtual com/nd/android/forumsdk/business/bean/result/ResultGetTags/setResultCode(I)V
aload 7
aload 8
invokevirtual java/lang/Exception/getMessage()Ljava/lang/String;
invokevirtual com/nd/android/forumsdk/business/bean/result/ResultGetTags/setResultMsg(Ljava/lang/String;)V
ldc "TeamOperatorImpl"
new java/lang/StringBuilder
dup
invokespecial java/lang/StringBuilder/<init>()V
ldc "getTags  -- resultCode : "
invokevirtual java/lang/StringBuilder/append(Ljava/lang/String;)Ljava/lang/StringBuilder;
aload 7
invokevirtual com/nd/android/forumsdk/business/bean/result/ResultGetTags/getResultCode()I
invokevirtual java/lang/StringBuilder/append(I)Ljava/lang/StringBuilder;
ldc " -- resultMsg : "
invokevirtual java/lang/StringBuilder/append(Ljava/lang/String;)Ljava/lang/StringBuilder;
aload 7
invokevirtual com/nd/android/forumsdk/business/bean/result/ResultGetTags/getResultMsg()Ljava/lang/String;
invokevirtual java/lang/StringBuilder/append(Ljava/lang/String;)Ljava/lang/StringBuilder;
invokevirtual java/lang/StringBuilder/toString()Ljava/lang/String;
invokestatic com/nd/schoollife/common/utils/ui/LogUtil/e(Ljava/lang/String;Ljava/lang/String;)V
L14:
aload 7
areturn
L11:
iload 4
iload 2
if_icmpge L14
iconst_0
istore 3
iload 4
istore 1
goto L12
.limit locals 12
.limit stack 5
.end method

.method public getTeamInfo(J)Lcom/nd/android/forumsdk/business/bean/result/ResultGetTeamInfo;
.catch java/lang/Exception from L0 to L1 using L2
.catch java/lang/Exception from L3 to L4 using L2
.catch java/lang/Exception from L5 to L6 using L2
.catch java/lang/Exception from L7 to L8 using L2
.catch java/lang/Exception from L9 to L10 using L2
new com/nd/android/forumsdk/business/bean/result/ResultGetTeamInfo
dup
invokespecial com/nd/android/forumsdk/business/bean/result/ResultGetTeamInfo/<init>()V
astore 4
new com/nd/android/forumsdk/business/bean/structure/GetTeamInfoSuccListBean
dup
invokespecial com/nd/android/forumsdk/business/bean/structure/GetTeamInfoSuccListBean/<init>()V
astore 5
L0:
ldc2_w 1000L
invokestatic java/lang/Thread/sleep(J)V
aload 4
sipush 200
invokevirtual com/nd/android/forumsdk/business/bean/result/ResultGetTeamInfo/setResultCode(I)V
aload 5
getstatic com/nd/schoollife/common/enums/RoleAuthority$TeamRole/CREATOR Lcom/nd/schoollife/common/enums/RoleAuthority$TeamRole;
invokevirtual com/nd/schoollife/common/enums/RoleAuthority$TeamRole/val()I
invokevirtual com/nd/android/forumsdk/business/bean/structure/GetTeamInfoSuccListBean/setGrade(I)V
iconst_1
anewarray com/nd/android/forumsdk/business/bean/result/CategoryInfoBean
astore 6
L1:
iconst_0
istore 3
L11:
iload 3
iconst_1
if_icmpge L5
L3:
aload 6
iload 3
new com/nd/android/forumsdk/business/bean/result/CategoryInfoBean
dup
invokespecial com/nd/android/forumsdk/business/bean/result/CategoryInfoBean/<init>()V
aastore
aload 6
iload 3
aaload
ldc "\u5356\u83ca\u82b1\u7684"
invokevirtual com/nd/android/forumsdk/business/bean/result/CategoryInfoBean/setName(Ljava/lang/String;)V
L4:
iload 3
iconst_1
iadd
istore 3
goto L11
L5:
aload 5
aload 6
invokevirtual com/nd/android/forumsdk/business/bean/structure/GetTeamInfoSuccListBean/setCategory([Lcom/nd/android/forumsdk/business/bean/result/CategoryInfoBean;)V
iconst_5
anewarray com/nd/android/forumsdk/business/bean/structure/TagInfoBean
astore 6
L6:
iconst_0
istore 3
L12:
iload 3
iconst_5
if_icmpge L9
L7:
aload 6
iload 3
new com/nd/android/forumsdk/business/bean/structure/TagInfoBean
dup
invokespecial com/nd/android/forumsdk/business/bean/structure/TagInfoBean/<init>()V
aastore
aload 6
iload 3
aaload
iload 3
i2l
invokevirtual com/nd/android/forumsdk/business/bean/structure/TagInfoBean/setId(J)V
aload 6
iload 3
aaload
iconst_5
anewarray java/lang/String
dup
iconst_0
ldc "\u841d\u8389"
aastore
dup
iconst_1
ldc "\u5fa1\u59d0"
aastore
dup
iconst_2
ldc "\u6e23\u7537"
aastore
dup
iconst_3
ldc "\u6b63\u592a"
aastore
dup
iconst_4
ldc "\u53e4\u5178\u6587\u5b66"
aastore
iload 3
aaload
invokevirtual com/nd/android/forumsdk/business/bean/structure/TagInfoBean/setName(Ljava/lang/String;)V
L8:
iload 3
iconst_1
iadd
istore 3
goto L12
L9:
aload 5
aload 6
invokevirtual com/nd/android/forumsdk/business/bean/structure/GetTeamInfoSuccListBean/setTags([Lcom/nd/android/forumsdk/business/bean/structure/TagInfoBean;)V
aload 5
ldc "\u8282\u64cd\u4e00\u7ec4"
invokevirtual com/nd/android/forumsdk/business/bean/structure/GetTeamInfoSuccListBean/setName(Ljava/lang/String;)V
aload 5
aconst_null
invokevirtual com/nd/android/forumsdk/business/bean/structure/GetTeamInfoSuccListBean/setAvatar(Ljava/lang/String;)V
aload 5
ldc "\u8282\u64cd\u5728\u6211\u4eec\u7684\u773c\u91cc\uff0c\u5c31\u548c\u8336\u53f6\u86cb\u4e00\u6837\u4fbf\u5b9c\u8282\u64cd\u5728\u6211\u4eec\u7684\u773c\u91cc\uff0c\u5c31\u548c\u8336\u53f6\u86cb\u4e00\u6837\u4fbf\u5b9c\u8282\u64cd\u5728\u6211\u4eec\u7684\u773c\u91cc\uff0c\u5c31\u548c\u8336\u53f6\u86cb\u4e00\u6837\u4fbf\u5b9c"
invokevirtual com/nd/android/forumsdk/business/bean/structure/GetTeamInfoSuccListBean/setIntro(Ljava/lang/String;)V
L10:
aload 4
iconst_1
invokevirtual com/nd/android/forumsdk/business/bean/result/ResultGetTeamInfo/setSucc_count(I)V
new java/util/ArrayList
dup
invokespecial java/util/ArrayList/<init>()V
astore 6
aload 6
aload 5
invokevirtual java/util/ArrayList/add(Ljava/lang/Object;)Z
pop
aload 4
aload 6
invokevirtual com/nd/android/forumsdk/business/bean/result/ResultGetTeamInfo/setSucc_list(Ljava/util/ArrayList;)V
aload 4
areturn
L2:
astore 6
aload 4
sipush 999
invokevirtual com/nd/android/forumsdk/business/bean/result/ResultGetTeamInfo/setResultCode(I)V
aload 4
aload 6
invokevirtual java/lang/Exception/getMessage()Ljava/lang/String;
invokevirtual com/nd/android/forumsdk/business/bean/result/ResultGetTeamInfo/setResultMsg(Ljava/lang/String;)V
ldc "TeamOperatorImpl"
new java/lang/StringBuilder
dup
invokespecial java/lang/StringBuilder/<init>()V
ldc "getHotTeam  -- resultCode : "
invokevirtual java/lang/StringBuilder/append(Ljava/lang/String;)Ljava/lang/StringBuilder;
aload 4
invokevirtual com/nd/android/forumsdk/business/bean/result/ResultGetTeamInfo/getResultCode()I
invokevirtual java/lang/StringBuilder/append(I)Ljava/lang/StringBuilder;
ldc " -- resultMsg : "
invokevirtual java/lang/StringBuilder/append(Ljava/lang/String;)Ljava/lang/StringBuilder;
aload 4
invokevirtual com/nd/android/forumsdk/business/bean/result/ResultGetTeamInfo/getResultMsg()Ljava/lang/String;
invokevirtual java/lang/StringBuilder/append(Ljava/lang/String;)Ljava/lang/StringBuilder;
invokevirtual java/lang/StringBuilder/toString()Ljava/lang/String;
invokestatic com/nd/schoollife/common/utils/ui/LogUtil/e(Ljava/lang/String;Ljava/lang/String;)V
goto L10
.limit locals 7
.limit stack 5
.end method

.method public getTeamListByCategory(JII)Lcom/nd/android/forumsdk/business/bean/result/ResultTeamInfoList;
.catch java/lang/InterruptedException from L0 to L1 using L2
new com/nd/android/forumsdk/business/bean/result/ResultTeamInfoList
dup
invokespecial com/nd/android/forumsdk/business/bean/result/ResultTeamInfoList/<init>()V
astore 5
new java/util/ArrayList
dup
invokespecial java/util/ArrayList/<init>()V
astore 6
new com/nd/android/forumsdk/business/bean/structure/TeamInfoBean
dup
invokespecial com/nd/android/forumsdk/business/bean/structure/TeamInfoBean/<init>()V
astore 7
aload 7
ldc "\u6b66\u672f\u534f\u4f1a\u5e95\u4e0b\u4eba\u6570\u6700\u591a\uff0c\u6d3b\u52a8\u6700\u591a\u6700\u591a\uff0c\u6d3b\u52a8\u6700\u6700\u591a\uff0c\u6d3b\u52a8\u6700"
invokevirtual com/nd/android/forumsdk/business/bean/structure/TeamInfoBean/setIntro(Ljava/lang/String;)V
aload 7
ldc "\u6b66\u672f\u5957\u8def\u5c0f\u7ec4"
invokevirtual com/nd/android/forumsdk/business/bean/structure/TeamInfoBean/setName(Ljava/lang/String;)V
aload 7
ldc "http://quc.qhimg.com/dm/180_180_100/t017965e53d0b1cb18f.jpg"
invokevirtual com/nd/android/forumsdk/business/bean/structure/TeamInfoBean/setAvatar(Ljava/lang/String;)V
aload 7
sipush 651
invokevirtual com/nd/android/forumsdk/business/bean/structure/TeamInfoBean/setMembernum(I)V
iconst_0
istore 3
L3:
iload 3
iload 4
if_icmpge L4
aload 6
aload 7
invokeinterface java/util/List/add(Ljava/lang/Object;)Z 1
pop
iload 3
iconst_1
iadd
istore 3
goto L3
L4:
aload 5
aload 6
invokevirtual com/nd/android/forumsdk/business/bean/result/ResultTeamInfoList/setList(Ljava/util/List;)V
aload 5
sipush 200
invokevirtual com/nd/android/forumsdk/business/bean/result/ResultTeamInfoList/setResultCode(I)V
L0:
ldc2_w 5000L
invokestatic java/lang/Thread/sleep(J)V
L1:
aload 5
areturn
L2:
astore 6
aload 6
invokevirtual java/lang/InterruptedException/printStackTrace()V
aload 5
areturn
.limit locals 8
.limit stack 2
.end method

.method public searchTeamByKeyWord(Ljava/lang/String;II)Lcom/nd/android/forumsdk/business/bean/result/ResultTeamInfoList;
aconst_null
areturn
.limit locals 4
.limit stack 1
.end method
