.bytecode 50.0
.class public synchronized com/nd/android/u/tast/main/adapter/TaskAdapter
.super android/widget/BaseAdapter
.inner class static synthetic inner com/nd/android/u/tast/main/adapter/TaskAdapter$1
.inner class private ViewHolder inner com/nd/android/u/tast/main/adapter/TaskAdapter$ViewHolder outer com/nd/android/u/tast/main/adapter/TaskAdapter

.field private 'lastTimeStr' Ljava/lang/String;

.field private 'mContext' Landroid/content/Context;

.field private 'mTaskList' Ljava/util/ArrayList; signature "Ljava/util/ArrayList<Lcom/nd/android/u/tast/experience/bean/MoreExperienceItem;>;"

.method public <init>(Landroid/content/Context;)V
aload 0
invokespecial android/widget/BaseAdapter/<init>()V
aload 0
aload 1
putfield com/nd/android/u/tast/main/adapter/TaskAdapter/mContext Landroid/content/Context;
return
.limit locals 2
.limit stack 2
.end method

.method public getCount()I
aload 0
getfield com/nd/android/u/tast/main/adapter/TaskAdapter/mTaskList Ljava/util/ArrayList;
ifnonnull L0
iconst_0
ireturn
L0:
aload 0
getfield com/nd/android/u/tast/main/adapter/TaskAdapter/mTaskList Ljava/util/ArrayList;
invokevirtual java/util/ArrayList/size()I
ireturn
.limit locals 1
.limit stack 1
.end method

.method public getItem(I)Lcom/nd/android/u/tast/experience/bean/MoreExperienceItem;
aload 0
getfield com/nd/android/u/tast/main/adapter/TaskAdapter/mTaskList Ljava/util/ArrayList;
ifnonnull L0
aconst_null
areturn
L0:
aload 0
getfield com/nd/android/u/tast/main/adapter/TaskAdapter/mTaskList Ljava/util/ArrayList;
iload 1
invokevirtual java/util/ArrayList/get(I)Ljava/lang/Object;
checkcast com/nd/android/u/tast/experience/bean/MoreExperienceItem
areturn
.limit locals 2
.limit stack 2
.end method

.method public volatile synthetic getItem(I)Ljava/lang/Object;
aload 0
iload 1
invokevirtual com/nd/android/u/tast/main/adapter/TaskAdapter/getItem(I)Lcom/nd/android/u/tast/experience/bean/MoreExperienceItem;
areturn
.limit locals 2
.limit stack 2
.end method

.method public getItemId(I)J
iload 1
i2l
lreturn
.limit locals 2
.limit stack 2
.end method

.method public getView(ILandroid/view/View;Landroid/view/ViewGroup;)Landroid/view/View;
aload 2
ifnonnull L0
aload 0
getfield com/nd/android/u/tast/main/adapter/TaskAdapter/mContext Landroid/content/Context;
invokestatic android/view/LayoutInflater/from(Landroid/content/Context;)Landroid/view/LayoutInflater;
getstatic com/nd/android/u/tasklib/R$layout/task_list_item I
aload 3
iconst_0
invokevirtual android/view/LayoutInflater/inflate(ILandroid/view/ViewGroup;Z)Landroid/view/View;
astore 2
new com/nd/android/u/tast/main/adapter/TaskAdapter$ViewHolder
dup
aload 0
aconst_null
invokespecial com/nd/android/u/tast/main/adapter/TaskAdapter$ViewHolder/<init>(Lcom/nd/android/u/tast/main/adapter/TaskAdapter;Lcom/nd/android/u/tast/main/adapter/TaskAdapter$1;)V
astore 3
aload 3
aload 2
getstatic com/nd/android/u/tasklib/R$id/tvTitle I
invokevirtual android/view/View/findViewById(I)Landroid/view/View;
checkcast android/widget/TextView
putfield com/nd/android/u/tast/main/adapter/TaskAdapter$ViewHolder/tvTitle Landroid/widget/TextView;
aload 3
aload 2
getstatic com/nd/android/u/tasklib/R$id/circleView I
invokevirtual android/view/View/findViewById(I)Landroid/view/View;
checkcast com/nd/android/u/tast/main/widget/CircleLiquidProgressView
putfield com/nd/android/u/tast/main/adapter/TaskAdapter$ViewHolder/circleUpView Lcom/nd/android/u/tast/main/widget/CircleLiquidProgressView;
aload 3
aload 2
getstatic com/nd/android/u/tasklib/R$id/ivIcon I
invokevirtual android/view/View/findViewById(I)Landroid/view/View;
checkcast android/widget/ImageView
putfield com/nd/android/u/tast/main/adapter/TaskAdapter$ViewHolder/ivIcon Landroid/widget/ImageView;
aload 3
aload 2
getstatic com/nd/android/u/tasklib/R$id/tvExperience I
invokevirtual android/view/View/findViewById(I)Landroid/view/View;
checkcast android/widget/TextView
putfield com/nd/android/u/tast/main/adapter/TaskAdapter$ViewHolder/tvExperience Landroid/widget/TextView;
aload 3
aload 2
getstatic com/nd/android/u/tasklib/R$id/tvExtend I
invokevirtual android/view/View/findViewById(I)Landroid/view/View;
checkcast android/widget/TextView
putfield com/nd/android/u/tast/main/adapter/TaskAdapter$ViewHolder/tvExtend Landroid/widget/TextView;
aload 2
aload 3
invokevirtual android/view/View/setTag(Ljava/lang/Object;)V
L1:
aload 0
iload 1
invokevirtual com/nd/android/u/tast/main/adapter/TaskAdapter/getItem(I)Lcom/nd/android/u/tast/experience/bean/MoreExperienceItem;
astore 4
aload 4
ifnull L2
aload 3
getfield com/nd/android/u/tast/main/adapter/TaskAdapter$ViewHolder/tvTitle Landroid/widget/TextView;
aload 4
invokevirtual com/nd/android/u/tast/experience/bean/MoreExperienceItem/getItemname()Ljava/lang/String;
invokevirtual android/widget/TextView/setText(Ljava/lang/CharSequence;)V
aload 3
getfield com/nd/android/u/tast/main/adapter/TaskAdapter$ViewHolder/circleUpView Lcom/nd/android/u/tast/main/widget/CircleLiquidProgressView;
aload 4
invokevirtual com/nd/android/u/tast/experience/bean/MoreExperienceItem/getConditionN()I
aload 4
invokevirtual com/nd/android/u/tast/experience/bean/MoreExperienceItem/getConditionM()I
invokevirtual com/nd/android/u/tast/main/widget/CircleLiquidProgressView/setValue(II)V
aload 4
invokevirtual com/nd/android/u/tast/experience/bean/MoreExperienceItem/getIsnew()I
iconst_1
if_icmpne L3
aload 3
getfield com/nd/android/u/tast/main/adapter/TaskAdapter$ViewHolder/ivIcon Landroid/widget/ImageView;
iconst_0
invokevirtual android/widget/ImageView/setVisibility(I)V
aload 3
getfield com/nd/android/u/tast/main/adapter/TaskAdapter$ViewHolder/ivIcon Landroid/widget/ImageView;
getstatic com/nd/android/u/tasklib/R$drawable/new_icon I
invokevirtual android/widget/ImageView/setImageResource(I)V
L4:
aload 4
invokevirtual com/nd/android/u/tast/experience/bean/MoreExperienceItem/getType()I
iconst_1
if_icmpne L5
aload 0
getfield com/nd/android/u/tast/main/adapter/TaskAdapter/lastTimeStr Ljava/lang/String;
ifnonnull L6
aload 0
aload 0
getfield com/nd/android/u/tast/main/adapter/TaskAdapter/mContext Landroid/content/Context;
invokevirtual android/content/Context/getResources()Landroid/content/res/Resources;
getstatic com/nd/android/u/tasklib/R$string/task_last_time I
invokevirtual android/content/res/Resources/getString(I)Ljava/lang/String;
putfield com/nd/android/u/tast/main/adapter/TaskAdapter/lastTimeStr Ljava/lang/String;
L6:
aload 3
getfield com/nd/android/u/tast/main/adapter/TaskAdapter$ViewHolder/tvExtend Landroid/widget/TextView;
aload 0
getfield com/nd/android/u/tast/main/adapter/TaskAdapter/lastTimeStr Ljava/lang/String;
iconst_1
anewarray java/lang/Object
dup
iconst_0
aload 4
invokevirtual com/nd/android/u/tast/experience/bean/MoreExperienceItem/getExpiredate()Ljava/lang/String;
aastore
invokestatic java/lang/String/format(Ljava/lang/String;[Ljava/lang/Object;)Ljava/lang/String;
invokevirtual android/widget/TextView/setText(Ljava/lang/CharSequence;)V
L7:
aload 4
invokevirtual com/nd/android/u/tast/experience/bean/MoreExperienceItem/getTimes()I
iconst_1
if_icmple L8
aload 3
getfield com/nd/android/u/tast/main/adapter/TaskAdapter$ViewHolder/tvExperience Landroid/widget/TextView;
aload 0
getfield com/nd/android/u/tast/main/adapter/TaskAdapter/mContext Landroid/content/Context;
invokevirtual android/content/Context/getResources()Landroid/content/res/Resources;
getstatic com/nd/android/u/tasklib/R$drawable/double_experience_icon I
invokevirtual android/content/res/Resources/getDrawable(I)Landroid/graphics/drawable/Drawable;
aconst_null
aconst_null
aconst_null
invokevirtual android/widget/TextView/setCompoundDrawablesWithIntrinsicBounds(Landroid/graphics/drawable/Drawable;Landroid/graphics/drawable/Drawable;Landroid/graphics/drawable/Drawable;Landroid/graphics/drawable/Drawable;)V
aload 3
getfield com/nd/android/u/tast/main/adapter/TaskAdapter$ViewHolder/tvExperience Landroid/widget/TextView;
new java/lang/StringBuilder
dup
invokespecial java/lang/StringBuilder/<init>()V
ldc "+"
invokevirtual java/lang/StringBuilder/append(Ljava/lang/String;)Ljava/lang/StringBuilder;
aload 4
invokevirtual com/nd/android/u/tast/experience/bean/MoreExperienceItem/getExp()I
invokevirtual java/lang/StringBuilder/append(I)Ljava/lang/StringBuilder;
ldc "X"
invokevirtual java/lang/StringBuilder/append(Ljava/lang/String;)Ljava/lang/StringBuilder;
aload 4
invokevirtual com/nd/android/u/tast/experience/bean/MoreExperienceItem/getTimes()I
invokevirtual java/lang/StringBuilder/append(I)Ljava/lang/StringBuilder;
invokevirtual java/lang/StringBuilder/toString()Ljava/lang/String;
invokevirtual android/widget/TextView/setText(Ljava/lang/CharSequence;)V
aload 3
getfield com/nd/android/u/tast/main/adapter/TaskAdapter$ViewHolder/tvExperience Landroid/widget/TextView;
ldc_w -65536
invokevirtual android/widget/TextView/setTextColor(I)V
L2:
aload 2
areturn
L0:
aload 2
invokevirtual android/view/View/getTag()Ljava/lang/Object;
checkcast com/nd/android/u/tast/main/adapter/TaskAdapter$ViewHolder
astore 3
goto L1
L3:
aload 4
invokevirtual com/nd/android/u/tast/experience/bean/MoreExperienceItem/getTimes()I
iconst_1
if_icmple L9
aload 3
getfield com/nd/android/u/tast/main/adapter/TaskAdapter$ViewHolder/ivIcon Landroid/widget/ImageView;
iconst_0
invokevirtual android/widget/ImageView/setVisibility(I)V
aload 3
getfield com/nd/android/u/tast/main/adapter/TaskAdapter$ViewHolder/ivIcon Landroid/widget/ImageView;
getstatic com/nd/android/u/tasklib/R$drawable/double_icon I
invokevirtual android/widget/ImageView/setImageResource(I)V
goto L4
L9:
aload 4
invokevirtual com/nd/android/u/tast/experience/bean/MoreExperienceItem/getType()I
iconst_1
if_icmpne L10
aload 3
getfield com/nd/android/u/tast/main/adapter/TaskAdapter$ViewHolder/ivIcon Landroid/widget/ImageView;
iconst_0
invokevirtual android/widget/ImageView/setVisibility(I)V
aload 3
getfield com/nd/android/u/tast/main/adapter/TaskAdapter$ViewHolder/ivIcon Landroid/widget/ImageView;
getstatic com/nd/android/u/tasklib/R$drawable/event_icon I
invokevirtual android/widget/ImageView/setImageResource(I)V
goto L4
L10:
aload 3
getfield com/nd/android/u/tast/main/adapter/TaskAdapter$ViewHolder/ivIcon Landroid/widget/ImageView;
bipush 8
invokevirtual android/widget/ImageView/setVisibility(I)V
goto L4
L5:
aload 3
getfield com/nd/android/u/tast/main/adapter/TaskAdapter$ViewHolder/tvExtend Landroid/widget/TextView;
aload 4
invokevirtual com/nd/android/u/tast/experience/bean/MoreExperienceItem/getParttakers()Ljava/lang/String;
invokevirtual android/widget/TextView/setText(Ljava/lang/CharSequence;)V
goto L7
L8:
aload 3
getfield com/nd/android/u/tast/main/adapter/TaskAdapter$ViewHolder/tvExperience Landroid/widget/TextView;
new java/lang/StringBuilder
dup
invokespecial java/lang/StringBuilder/<init>()V
ldc "+"
invokevirtual java/lang/StringBuilder/append(Ljava/lang/String;)Ljava/lang/StringBuilder;
aload 4
invokevirtual com/nd/android/u/tast/experience/bean/MoreExperienceItem/getExp()I
invokevirtual java/lang/StringBuilder/append(I)Ljava/lang/StringBuilder;
invokevirtual java/lang/StringBuilder/toString()Ljava/lang/String;
invokevirtual android/widget/TextView/setText(Ljava/lang/CharSequence;)V
aload 3
getfield com/nd/android/u/tast/main/adapter/TaskAdapter$ViewHolder/tvExperience Landroid/widget/TextView;
aload 0
getfield com/nd/android/u/tast/main/adapter/TaskAdapter/mContext Landroid/content/Context;
invokevirtual android/content/Context/getResources()Landroid/content/res/Resources;
getstatic com/nd/android/u/tasklib/R$drawable/experience_icon I
invokevirtual android/content/res/Resources/getDrawable(I)Landroid/graphics/drawable/Drawable;
aconst_null
aconst_null
aconst_null
invokevirtual android/widget/TextView/setCompoundDrawablesWithIntrinsicBounds(Landroid/graphics/drawable/Drawable;Landroid/graphics/drawable/Drawable;Landroid/graphics/drawable/Drawable;Landroid/graphics/drawable/Drawable;)V
aload 3
getfield com/nd/android/u/tast/main/adapter/TaskAdapter$ViewHolder/tvExperience Landroid/widget/TextView;
ldc_w -7829368
invokevirtual android/widget/TextView/setTextColor(I)V
aload 2
areturn
.limit locals 5
.limit stack 6
.end method

.method public setData(Ljava/util/ArrayList;)V
.signature "(Ljava/util/ArrayList<Lcom/nd/android/u/tast/experience/bean/MoreExperienceItem;>;)V"
aload 0
aload 1
putfield com/nd/android/u/tast/main/adapter/TaskAdapter/mTaskList Ljava/util/ArrayList;
return
.limit locals 2
.limit stack 2
.end method
