.bytecode 50.0
.class public synchronized com/nd/android/util/BroadcastContact
.super java/lang/Object

.field public static final 'GOTO_CONTACT_ACTION' Ljava/lang/String;

.field public static final 'REFRESH_SENIOR_ACTION' Ljava/lang/String;

.method static <clinit>()V
new java/lang/StringBuilder
dup
invokespecial java/lang/StringBuilder/<init>()V
getstatic com/product/android/business/ApplicationVariable/INSTANCE Lcom/product/android/business/ApplicationVariable;
getfield com/product/android/business/ApplicationVariable/applicationContext Landroid/content/Context;
invokevirtual android/content/Context/getPackageName()Ljava/lang/String;
invokevirtual java/lang/StringBuilder/append(Ljava/lang/String;)Ljava/lang/StringBuilder;
ldc ".refresh_senior_action"
invokevirtual java/lang/StringBuilder/append(Ljava/lang/String;)Ljava/lang/StringBuilder;
invokevirtual java/lang/StringBuilder/toString()Ljava/lang/String;
putstatic com/nd/android/util/BroadcastContact/REFRESH_SENIOR_ACTION Ljava/lang/String;
new java/lang/StringBuilder
dup
invokespecial java/lang/StringBuilder/<init>()V
getstatic com/product/android/business/ApplicationVariable/INSTANCE Lcom/product/android/business/ApplicationVariable;
getfield com/product/android/business/ApplicationVariable/applicationContext Landroid/content/Context;
invokevirtual android/content/Context/getPackageName()Ljava/lang/String;
invokevirtual java/lang/StringBuilder/append(Ljava/lang/String;)Ljava/lang/StringBuilder;
ldc ".goto_contact_action"
invokevirtual java/lang/StringBuilder/append(Ljava/lang/String;)Ljava/lang/StringBuilder;
invokevirtual java/lang/StringBuilder/toString()Ljava/lang/String;
putstatic com/nd/android/util/BroadcastContact/GOTO_CONTACT_ACTION Ljava/lang/String;
return
.limit locals 0
.limit stack 2
.end method

.method public <init>()V
aload 0
invokespecial java/lang/Object/<init>()V
return
.limit locals 1
.limit stack 1
.end method
