.bytecode 50.0
.class synchronized com/nd/android/u/publicNumber/ui/widget/PspMenuView$DropUpAdapter
.super android/widget/BaseAdapter
.inner class DropUpAdapter inner com/nd/android/u/publicNumber/ui/widget/PspMenuView$DropUpAdapter outer com/nd/android/u/publicNumber/ui/widget/PspMenuView
.inner class Holder inner com/nd/android/u/publicNumber/ui/widget/PspMenuView$DropUpAdapter$Holder outer com/nd/android/u/publicNumber/ui/widget/PspMenuView$DropUpAdapter

.field private 'msubButtonslist' Ljava/util/ArrayList; signature "Ljava/util/ArrayList<Lcom/nd/android/u/publicNumber/controller/bean/PublicNumberMenuButton;>;"

.field final synthetic 'this$0' Lcom/nd/android/u/publicNumber/ui/widget/PspMenuView;

.method <init>(Lcom/nd/android/u/publicNumber/ui/widget/PspMenuView;)V
aload 0
aload 1
putfield com/nd/android/u/publicNumber/ui/widget/PspMenuView$DropUpAdapter/this$0 Lcom/nd/android/u/publicNumber/ui/widget/PspMenuView;
aload 0
invokespecial android/widget/BaseAdapter/<init>()V
return
.limit locals 2
.limit stack 2
.end method

.method public getCount()I
aload 0
getfield com/nd/android/u/publicNumber/ui/widget/PspMenuView$DropUpAdapter/msubButtonslist Ljava/util/ArrayList;
ifnonnull L0
iconst_0
ireturn
L0:
aload 0
getfield com/nd/android/u/publicNumber/ui/widget/PspMenuView$DropUpAdapter/msubButtonslist Ljava/util/ArrayList;
invokevirtual java/util/ArrayList/size()I
ireturn
.limit locals 1
.limit stack 1
.end method

.method public getItem(I)Ljava/lang/Object;
aload 0
getfield com/nd/android/u/publicNumber/ui/widget/PspMenuView$DropUpAdapter/msubButtonslist Ljava/util/ArrayList;
ifnonnull L0
aconst_null
areturn
L0:
aload 0
getfield com/nd/android/u/publicNumber/ui/widget/PspMenuView$DropUpAdapter/msubButtonslist Ljava/util/ArrayList;
iload 1
invokevirtual java/util/ArrayList/get(I)Ljava/lang/Object;
areturn
.limit locals 2
.limit stack 2
.end method

.method public getItemId(I)J
iload 1
i2l
lreturn
.limit locals 2
.limit stack 2
.end method

.method public getView(ILandroid/view/View;Landroid/view/ViewGroup;)Landroid/view/View;
aload 2
ifnonnull L0
new com/nd/android/u/publicNumber/ui/widget/PspMenuView$DropUpAdapter$Holder
dup
aload 0
invokespecial com/nd/android/u/publicNumber/ui/widget/PspMenuView$DropUpAdapter$Holder/<init>(Lcom/nd/android/u/publicNumber/ui/widget/PspMenuView$DropUpAdapter;)V
astore 3
aload 0
getfield com/nd/android/u/publicNumber/ui/widget/PspMenuView$DropUpAdapter/this$0 Lcom/nd/android/u/publicNumber/ui/widget/PspMenuView;
invokestatic com/nd/android/u/publicNumber/ui/widget/PspMenuView/access$100(Lcom/nd/android/u/publicNumber/ui/widget/PspMenuView;)Landroid/view/View;
invokevirtual android/view/View/getContext()Landroid/content/Context;
invokestatic android/view/LayoutInflater/from(Landroid/content/Context;)Landroid/view/LayoutInflater;
getstatic com/nd/android/u/chat/R$layout/chat_pub_num_popup_item I
aconst_null
invokevirtual android/view/LayoutInflater/inflate(ILandroid/view/ViewGroup;)Landroid/view/View;
astore 2
aload 3
aload 2
getstatic com/nd/android/u/chat/R$id/dropup_list_tx_name I
invokevirtual android/view/View/findViewById(I)Landroid/view/View;
checkcast android/widget/TextView
putfield com/nd/android/u/publicNumber/ui/widget/PspMenuView$DropUpAdapter$Holder/textView Landroid/widget/TextView;
aload 3
aload 2
getstatic com/nd/android/u/chat/R$id/seperator_line I
invokevirtual android/view/View/findViewById(I)Landroid/view/View;
putfield com/nd/android/u/publicNumber/ui/widget/PspMenuView$DropUpAdapter$Holder/seperatorline Landroid/view/View;
aload 2
aload 3
invokevirtual android/view/View/setTag(Ljava/lang/Object;)V
aload 2
aload 0
getfield com/nd/android/u/publicNumber/ui/widget/PspMenuView$DropUpAdapter/this$0 Lcom/nd/android/u/publicNumber/ui/widget/PspMenuView;
invokestatic com/nd/android/u/publicNumber/ui/widget/PspMenuView/access$200(Lcom/nd/android/u/publicNumber/ui/widget/PspMenuView;)Landroid/view/View$OnClickListener;
invokevirtual android/view/View/setOnClickListener(Landroid/view/View$OnClickListener;)V
L1:
aload 0
getfield com/nd/android/u/publicNumber/ui/widget/PspMenuView$DropUpAdapter/msubButtonslist Ljava/util/ArrayList;
iload 1
invokevirtual java/util/ArrayList/get(I)Ljava/lang/Object;
checkcast com/nd/android/u/publicNumber/controller/bean/PublicNumberMenuButton
astore 4
aload 3
getfield com/nd/android/u/publicNumber/ui/widget/PspMenuView$DropUpAdapter$Holder/textView Landroid/widget/TextView;
aload 4
getfield com/nd/android/u/publicNumber/controller/bean/PublicNumberMenuButton/name Ljava/lang/String;
invokevirtual android/widget/TextView/setText(Ljava/lang/CharSequence;)V
iload 1
aload 0
invokevirtual com/nd/android/u/publicNumber/ui/widget/PspMenuView$DropUpAdapter/getCount()I
iconst_1
isub
if_icmpne L2
aload 3
getfield com/nd/android/u/publicNumber/ui/widget/PspMenuView$DropUpAdapter$Holder/seperatorline Landroid/view/View;
bipush 8
invokevirtual android/view/View/setVisibility(I)V
L3:
aload 2
getstatic com/nd/android/u/chat/R$id/dropup_list_tx_name I
iload 1
invokestatic java/lang/Integer/valueOf(I)Ljava/lang/Integer;
invokevirtual android/view/View/setTag(ILjava/lang/Object;)V
aload 2
areturn
L0:
aload 2
invokevirtual android/view/View/getTag()Ljava/lang/Object;
checkcast com/nd/android/u/publicNumber/ui/widget/PspMenuView$DropUpAdapter$Holder
astore 3
goto L1
L2:
aload 3
getfield com/nd/android/u/publicNumber/ui/widget/PspMenuView$DropUpAdapter$Holder/seperatorline Landroid/view/View;
iconst_0
invokevirtual android/view/View/setVisibility(I)V
goto L3
.limit locals 5
.limit stack 3
.end method

.method public setSubButtonsList(Ljava/util/ArrayList;)V
.signature "(Ljava/util/ArrayList<Lcom/nd/android/u/publicNumber/controller/bean/PublicNumberMenuButton;>;)V"
aload 0
aload 1
putfield com/nd/android/u/publicNumber/ui/widget/PspMenuView$DropUpAdapter/msubButtonslist Ljava/util/ArrayList;
return
.limit locals 2
.limit stack 2
.end method
