.bytecode 50.0
.class synchronized com/nd/android/u/publicNumber/ui/widget/PspPopMore$1
.super java/lang/Object
.implements android/widget/AdapterView$OnItemClickListener
.enclosing method com/nd/android/u/publicNumber/ui/widget/PspPopMore
.inner class inner com/nd/android/u/publicNumber/ui/widget/PspPopMore$1
.inner class inner com/nd/android/u/publicNumber/ui/widget/PspPopMore$1$1
.inner class inner com/nd/android/u/publicNumber/ui/widget/PspPopMore$1$2

.field final synthetic 'this$0' Lcom/nd/android/u/publicNumber/ui/widget/PspPopMore;

.method <init>(Lcom/nd/android/u/publicNumber/ui/widget/PspPopMore;)V
aload 0
aload 1
putfield com/nd/android/u/publicNumber/ui/widget/PspPopMore$1/this$0 Lcom/nd/android/u/publicNumber/ui/widget/PspPopMore;
aload 0
invokespecial java/lang/Object/<init>()V
return
.limit locals 2
.limit stack 2
.end method

.method public onItemClick(Landroid/widget/AdapterView;Landroid/view/View;IJ)V
.signature "(Landroid/widget/AdapterView<*>;Landroid/view/View;IJ)V"
iload 3
tableswitch 0
L0
default : L1
L1:
aload 0
getfield com/nd/android/u/publicNumber/ui/widget/PspPopMore$1/this$0 Lcom/nd/android/u/publicNumber/ui/widget/PspPopMore;
invokevirtual com/nd/android/u/publicNumber/ui/widget/PspPopMore/dismiss()V
return
L0:
new android/app/AlertDialog$Builder
dup
aload 0
getfield com/nd/android/u/publicNumber/ui/widget/PspPopMore$1/this$0 Lcom/nd/android/u/publicNumber/ui/widget/PspPopMore;
invokestatic com/nd/android/u/publicNumber/ui/widget/PspPopMore/access$000(Lcom/nd/android/u/publicNumber/ui/widget/PspPopMore;)Landroid/content/Context;
invokespecial android/app/AlertDialog$Builder/<init>(Landroid/content/Context;)V
astore 1
aload 1
aload 0
getfield com/nd/android/u/publicNumber/ui/widget/PspPopMore$1/this$0 Lcom/nd/android/u/publicNumber/ui/widget/PspPopMore;
invokestatic com/nd/android/u/publicNumber/ui/widget/PspPopMore/access$000(Lcom/nd/android/u/publicNumber/ui/widget/PspPopMore;)Landroid/content/Context;
getstatic com/nd/android/u/chat/R$string/public_number_clear_confirm I
invokevirtual android/content/Context/getString(I)Ljava/lang/String;
invokevirtual android/app/AlertDialog$Builder/setTitle(Ljava/lang/CharSequence;)Landroid/app/AlertDialog$Builder;
pop
aload 1
getstatic com/nd/android/u/chat/R$string/ok I
new com/nd/android/u/publicNumber/ui/widget/PspPopMore$1$1
dup
aload 0
invokespecial com/nd/android/u/publicNumber/ui/widget/PspPopMore$1$1/<init>(Lcom/nd/android/u/publicNumber/ui/widget/PspPopMore$1;)V
invokevirtual android/app/AlertDialog$Builder/setPositiveButton(ILandroid/content/DialogInterface$OnClickListener;)Landroid/app/AlertDialog$Builder;
pop
aload 1
getstatic com/nd/android/u/chat/R$string/cancel I
new com/nd/android/u/publicNumber/ui/widget/PspPopMore$1$2
dup
aload 0
invokespecial com/nd/android/u/publicNumber/ui/widget/PspPopMore$1$2/<init>(Lcom/nd/android/u/publicNumber/ui/widget/PspPopMore$1;)V
invokevirtual android/app/AlertDialog$Builder/setNeutralButton(ILandroid/content/DialogInterface$OnClickListener;)Landroid/app/AlertDialog$Builder;
pop
aload 1
invokevirtual android/app/AlertDialog$Builder/create()Landroid/app/AlertDialog;
invokevirtual android/app/AlertDialog/show()V
goto L1
.limit locals 6
.limit stack 5
.end method
