.bytecode 50.0
.class final synchronized com/alipay/android/phone/mrpc/core/t
.super java/util/concurrent/FutureTask
.signature "Ljava/util/concurrent/FutureTask<Lcom/alipay/android/phone/mrpc/core/ab;>;"

.field final synthetic 'a' Lcom/alipay/android/phone/mrpc/core/x;

.field final synthetic 'b' Lcom/alipay/android/phone/mrpc/core/s;

.method <init>(Lcom/alipay/android/phone/mrpc/core/s;Ljava/util/concurrent/Callable;Lcom/alipay/android/phone/mrpc/core/x;)V
aload 0
aload 1
putfield com/alipay/android/phone/mrpc/core/t/b Lcom/alipay/android/phone/mrpc/core/s;
aload 0
aload 3
putfield com/alipay/android/phone/mrpc/core/t/a Lcom/alipay/android/phone/mrpc/core/x;
aload 0
aload 2
invokespecial java/util/concurrent/FutureTask/<init>(Ljava/util/concurrent/Callable;)V
return
.limit locals 4
.limit stack 2
.end method

.method protected final done()V
.catch java/lang/InterruptedException from L0 to L1 using L2
.catch java/util/concurrent/ExecutionException from L0 to L1 using L3
.catch java/util/concurrent/CancellationException from L0 to L1 using L4
.catch java/lang/Throwable from L0 to L1 using L5
.catch java/lang/InterruptedException from L1 to L6 using L2
.catch java/util/concurrent/ExecutionException from L1 to L6 using L3
.catch java/util/concurrent/CancellationException from L1 to L6 using L4
.catch java/lang/Throwable from L1 to L6 using L5
.catch java/lang/InterruptedException from L6 to L7 using L2
.catch java/util/concurrent/ExecutionException from L6 to L7 using L3
.catch java/util/concurrent/CancellationException from L6 to L7 using L4
.catch java/lang/Throwable from L6 to L7 using L5
aload 0
getfield com/alipay/android/phone/mrpc/core/t/a Lcom/alipay/android/phone/mrpc/core/x;
invokevirtual com/alipay/android/phone/mrpc/core/x/a()Lcom/alipay/android/phone/mrpc/core/v;
astore 1
aload 1
invokevirtual com/alipay/android/phone/mrpc/core/aa/a()Lcom/alipay/android/phone/mrpc/core/g;
ifnonnull L0
aload 0
invokespecial java/util/concurrent/FutureTask/done()V
L8:
return
L0:
aload 0
invokevirtual com/alipay/android/phone/mrpc/core/t/get()Ljava/lang/Object;
pop
aload 0
invokevirtual com/alipay/android/phone/mrpc/core/t/isCancelled()Z
ifne L1
aload 1
getfield com/alipay/android/phone/mrpc/core/aa/f Z
ifeq L8
L1:
aload 1
iconst_1
putfield com/alipay/android/phone/mrpc/core/aa/f Z
aload 0
invokevirtual com/alipay/android/phone/mrpc/core/t/isCancelled()Z
ifeq L6
aload 0
invokevirtual com/alipay/android/phone/mrpc/core/t/isDone()Z
ifne L8
L6:
aload 0
iconst_0
invokevirtual com/alipay/android/phone/mrpc/core/t/cancel(Z)Z
pop
L7:
return
L2:
astore 1
new java/lang/StringBuilder
dup
invokespecial java/lang/StringBuilder/<init>()V
aload 1
invokevirtual java/lang/StringBuilder/append(Ljava/lang/Object;)Ljava/lang/StringBuilder;
pop
return
L3:
astore 1
aload 1
invokevirtual java/util/concurrent/ExecutionException/getCause()Ljava/lang/Throwable;
ifnull L9
aload 1
invokevirtual java/util/concurrent/ExecutionException/getCause()Ljava/lang/Throwable;
instanceof com/alipay/android/phone/mrpc/core/a
ifeq L9
aload 1
invokevirtual java/util/concurrent/ExecutionException/getCause()Ljava/lang/Throwable;
checkcast com/alipay/android/phone/mrpc/core/a
astore 1
aload 1
invokevirtual com/alipay/android/phone/mrpc/core/a/a()I
pop
aload 1
invokevirtual com/alipay/android/phone/mrpc/core/a/b()Ljava/lang/String;
pop
return
L9:
new java/lang/StringBuilder
dup
invokespecial java/lang/StringBuilder/<init>()V
aload 1
invokevirtual java/lang/StringBuilder/append(Ljava/lang/Object;)Ljava/lang/StringBuilder;
pop
return
L4:
astore 2
aload 1
iconst_1
putfield com/alipay/android/phone/mrpc/core/aa/f Z
return
L5:
astore 1
new java/lang/RuntimeException
dup
ldc "An error occured while executing http request"
aload 1
invokespecial java/lang/RuntimeException/<init>(Ljava/lang/String;Ljava/lang/Throwable;)V
athrow
.limit locals 3
.limit stack 4
.end method
