.bytecode 50.0
.class public final synchronized com/alipay/android/phone/mrpc/core/x
.super java/lang/Object
.implements java/util/concurrent/Callable
.signature "Ljava/lang/Object;Ljava/util/concurrent/Callable<Lcom/alipay/android/phone/mrpc/core/ab;>;"

.field private static final 'e' Lorg/apache/http/client/HttpRequestRetryHandler;

.field protected 'a' Lcom/alipay/android/phone/mrpc/core/s;

.field protected 'b' Landroid/content/Context;

.field protected 'c' Lcom/alipay/android/phone/mrpc/core/v;

.field 'd' Ljava/lang/String;

.field private 'f' Lorg/apache/http/client/methods/HttpUriRequest;

.field private 'g' Lorg/apache/http/protocol/HttpContext;

.field private 'h' Lorg/apache/http/client/CookieStore;

.field private 'i' Landroid/webkit/CookieManager;

.field private 'j' Lorg/apache/http/entity/AbstractHttpEntity;

.field private 'k' Lorg/apache/http/HttpHost;

.field private 'l' Ljava/net/URL;

.field private 'm' I

.field private 'n' Z

.field private 'o' Z

.field private 'p' Ljava/lang/String;

.field private 'q' Ljava/lang/String;

.method static <clinit>()V
new com/alipay/android/phone/mrpc/core/h
dup
invokespecial com/alipay/android/phone/mrpc/core/h/<init>()V
putstatic com/alipay/android/phone/mrpc/core/x/e Lorg/apache/http/client/HttpRequestRetryHandler;
return
.limit locals 0
.limit stack 2
.end method

.method public <init>(Lcom/alipay/android/phone/mrpc/core/s;Lcom/alipay/android/phone/mrpc/core/v;)V
aload 0
invokespecial java/lang/Object/<init>()V
aload 0
new org/apache/http/protocol/BasicHttpContext
dup
invokespecial org/apache/http/protocol/BasicHttpContext/<init>()V
putfield com/alipay/android/phone/mrpc/core/x/g Lorg/apache/http/protocol/HttpContext;
aload 0
new org/apache/http/impl/client/BasicCookieStore
dup
invokespecial org/apache/http/impl/client/BasicCookieStore/<init>()V
putfield com/alipay/android/phone/mrpc/core/x/h Lorg/apache/http/client/CookieStore;
aload 0
iconst_0
putfield com/alipay/android/phone/mrpc/core/x/m I
aload 0
iconst_0
putfield com/alipay/android/phone/mrpc/core/x/n Z
aload 0
iconst_0
putfield com/alipay/android/phone/mrpc/core/x/o Z
aload 0
aconst_null
putfield com/alipay/android/phone/mrpc/core/x/p Ljava/lang/String;
aload 0
aload 1
putfield com/alipay/android/phone/mrpc/core/x/a Lcom/alipay/android/phone/mrpc/core/s;
aload 0
aload 0
getfield com/alipay/android/phone/mrpc/core/x/a Lcom/alipay/android/phone/mrpc/core/s;
getfield com/alipay/android/phone/mrpc/core/s/a Landroid/content/Context;
putfield com/alipay/android/phone/mrpc/core/x/b Landroid/content/Context;
aload 0
aload 2
putfield com/alipay/android/phone/mrpc/core/x/c Lcom/alipay/android/phone/mrpc/core/v;
return
.limit locals 3
.limit stack 3
.end method

.method private static a([Ljava/lang/String;)J
.catch java/lang/Exception from L0 to L1 using L2
iconst_0
istore 1
L3:
iload 1
aload 0
arraylength
if_icmpge L4
ldc "max-age"
aload 0
iload 1
aaload
invokevirtual java/lang/String/equalsIgnoreCase(Ljava/lang/String;)Z
ifeq L5
aload 0
iload 1
iconst_1
iadd
aaload
ifnull L5
L0:
aload 0
iload 1
iconst_1
iadd
aaload
invokestatic java/lang/Long/parseLong(Ljava/lang/String;)J
lstore 2
L1:
lload 2
lreturn
L2:
astore 4
L5:
iload 1
iconst_1
iadd
istore 1
goto L3
L4:
lconst_0
lreturn
.limit locals 5
.limit stack 3
.end method

.method private a(Lorg/apache/http/HttpResponse;ILjava/lang/String;)Lcom/alipay/android/phone/mrpc/core/ab;
.catch all from L0 to L1 using L2
.catch all from L1 to L3 using L4
.catch all from L5 to L6 using L4
.catch all from L6 to L7 using L4
.catch java/io/IOException from L7 to L8 using L9
.catch java/io/IOException from L10 to L11 using L12
aconst_null
astore 6
aconst_null
astore 8
new java/lang/StringBuilder
dup
ldc "\u5f00\u59cbhandle\uff0chandleResponse-1,"
invokespecial java/lang/StringBuilder/<init>(Ljava/lang/String;)V
invokestatic java/lang/Thread/currentThread()Ljava/lang/Thread;
invokevirtual java/lang/Thread/getId()J
invokevirtual java/lang/StringBuilder/append(J)Ljava/lang/StringBuilder;
pop
aload 1
invokeinterface org/apache/http/HttpResponse/getEntity()Lorg/apache/http/HttpEntity; 0
astore 7
aload 7
ifnull L13
aload 1
invokeinterface org/apache/http/HttpResponse/getStatusLine()Lorg/apache/http/StatusLine; 0
invokeinterface org/apache/http/StatusLine/getStatusCode()I 0
sipush 200
if_icmpne L13
new java/lang/StringBuilder
dup
ldc "200\uff0c\u5f00\u59cb\u5904\u7406\uff0chandleResponse-2,threadid = "
invokespecial java/lang/StringBuilder/<init>(Ljava/lang/String;)V
invokestatic java/lang/Thread/currentThread()Ljava/lang/Thread;
invokevirtual java/lang/Thread/getId()J
invokevirtual java/lang/StringBuilder/append(J)Ljava/lang/StringBuilder;
pop
L0:
new java/io/ByteArrayOutputStream
dup
invokespecial java/io/ByteArrayOutputStream/<init>()V
astore 6
L1:
invokestatic java/lang/System/currentTimeMillis()J
lstore 4
aload 0
aload 7
aload 6
invokespecial com/alipay/android/phone/mrpc/core/x/a(Lorg/apache/http/HttpEntity;Ljava/io/OutputStream;)V
aload 6
invokevirtual java/io/ByteArrayOutputStream/toByteArray()[B
astore 7
aload 0
iconst_0
putfield com/alipay/android/phone/mrpc/core/x/o Z
aload 0
getfield com/alipay/android/phone/mrpc/core/x/a Lcom/alipay/android/phone/mrpc/core/s;
invokestatic java/lang/System/currentTimeMillis()J
lload 4
lsub
invokevirtual com/alipay/android/phone/mrpc/core/s/c(J)V
aload 0
getfield com/alipay/android/phone/mrpc/core/x/a Lcom/alipay/android/phone/mrpc/core/s;
aload 7
arraylength
i2l
invokevirtual com/alipay/android/phone/mrpc/core/s/a(J)V
new java/lang/StringBuilder
dup
ldc "res:"
invokespecial java/lang/StringBuilder/<init>(Ljava/lang/String;)V
aload 7
arraylength
invokevirtual java/lang/StringBuilder/append(I)Ljava/lang/StringBuilder;
pop
new com/alipay/android/phone/mrpc/core/w
dup
aload 1
invokestatic com/alipay/android/phone/mrpc/core/x/a(Lorg/apache/http/HttpResponse;)Lcom/alipay/android/phone/mrpc/core/b;
iload 2
aload 3
aload 7
invokespecial com/alipay/android/phone/mrpc/core/w/<init>(Lcom/alipay/android/phone/mrpc/core/b;ILjava/lang/String;[B)V
astore 7
aload 1
invokestatic com/alipay/android/phone/mrpc/core/x/b(Lorg/apache/http/HttpResponse;)J
lstore 4
aload 1
invokeinterface org/apache/http/HttpResponse/getEntity()Lorg/apache/http/HttpEntity; 0
invokeinterface org/apache/http/HttpEntity/getContentType()Lorg/apache/http/Header; 0
astore 1
L3:
aload 1
ifnull L14
L5:
aload 1
invokeinterface org/apache/http/Header/getValue()Ljava/lang/String; 0
invokestatic com/alipay/android/phone/mrpc/core/x/a(Ljava/lang/String;)Ljava/util/HashMap;
astore 3
aload 3
ldc "charset"
invokevirtual java/util/HashMap/get(Ljava/lang/Object;)Ljava/lang/Object;
checkcast java/lang/String
astore 1
aload 3
ldc "Content-Type"
invokevirtual java/util/HashMap/get(Ljava/lang/Object;)Ljava/lang/Object;
checkcast java/lang/String
astore 3
L6:
aload 7
aload 3
invokevirtual com/alipay/android/phone/mrpc/core/w/a(Ljava/lang/String;)V
aload 7
aload 1
putfield com/alipay/android/phone/mrpc/core/w/c Ljava/lang/String;
aload 7
invokestatic java/lang/System/currentTimeMillis()J
putfield com/alipay/android/phone/mrpc/core/w/a J
aload 7
lload 4
putfield com/alipay/android/phone/mrpc/core/w/b J
L7:
aload 6
invokevirtual java/io/ByteArrayOutputStream/close()V
L8:
aload 7
astore 3
L15:
aload 3
areturn
L9:
astore 1
new java/lang/RuntimeException
dup
ldc "ArrayOutputStream close error!"
aload 1
invokevirtual java/io/IOException/getCause()Ljava/lang/Throwable;
invokespecial java/lang/RuntimeException/<init>(Ljava/lang/String;Ljava/lang/Throwable;)V
athrow
L2:
astore 1
aconst_null
astore 3
L16:
aload 3
ifnull L11
L10:
aload 3
invokevirtual java/io/ByteArrayOutputStream/close()V
L11:
aload 1
athrow
L12:
astore 1
new java/lang/RuntimeException
dup
ldc "ArrayOutputStream close error!"
aload 1
invokevirtual java/io/IOException/getCause()Ljava/lang/Throwable;
invokespecial java/lang/RuntimeException/<init>(Ljava/lang/String;Ljava/lang/Throwable;)V
athrow
L13:
aload 6
astore 3
aload 7
ifnonnull L15
aload 1
invokeinterface org/apache/http/HttpResponse/getStatusLine()Lorg/apache/http/StatusLine; 0
invokeinterface org/apache/http/StatusLine/getStatusCode()I 0
pop
aconst_null
areturn
L4:
astore 1
aload 6
astore 3
goto L16
L14:
aconst_null
astore 3
aload 8
astore 1
goto L6
.limit locals 9
.limit stack 6
.end method

.method private static a(Lorg/apache/http/HttpResponse;)Lcom/alipay/android/phone/mrpc/core/b;
new com/alipay/android/phone/mrpc/core/b
dup
invokespecial com/alipay/android/phone/mrpc/core/b/<init>()V
astore 3
aload 0
invokeinterface org/apache/http/HttpResponse/getAllHeaders()[Lorg/apache/http/Header; 0
astore 0
aload 0
arraylength
istore 2
iconst_0
istore 1
L0:
iload 1
iload 2
if_icmpge L1
aload 0
iload 1
aaload
astore 4
aload 3
aload 4
invokeinterface org/apache/http/Header/getName()Ljava/lang/String; 0
aload 4
invokeinterface org/apache/http/Header/getValue()Ljava/lang/String; 0
invokevirtual com/alipay/android/phone/mrpc/core/b/a(Ljava/lang/String;Ljava/lang/String;)V
iload 1
iconst_1
iadd
istore 1
goto L0
L1:
aload 3
areturn
.limit locals 5
.limit stack 3
.end method

.method private static a(Ljava/lang/String;)Ljava/util/HashMap;
.signature "(Ljava/lang/String;)Ljava/util/HashMap<Ljava/lang/String;Ljava/lang/String;>;"
new java/util/HashMap
dup
invokespecial java/util/HashMap/<init>()V
astore 3
aload 0
ldc ";"
invokevirtual java/lang/String/split(Ljava/lang/String;)[Ljava/lang/String;
astore 4
aload 4
arraylength
istore 2
iconst_0
istore 1
L0:
iload 1
iload 2
if_icmpge L1
aload 4
iload 1
aaload
astore 5
aload 5
bipush 61
invokevirtual java/lang/String/indexOf(I)I
iconst_m1
if_icmpne L2
iconst_2
anewarray java/lang/String
astore 0
aload 0
iconst_0
ldc "Content-Type"
aastore
aload 0
iconst_1
aload 5
aastore
L3:
aload 3
aload 0
iconst_0
aaload
aload 0
iconst_1
aaload
invokevirtual java/util/HashMap/put(Ljava/lang/Object;Ljava/lang/Object;)Ljava/lang/Object;
pop
iload 1
iconst_1
iadd
istore 1
goto L0
L2:
aload 5
ldc "="
invokevirtual java/lang/String/split(Ljava/lang/String;)[Ljava/lang/String;
astore 0
goto L3
L1:
aload 3
areturn
.limit locals 6
.limit stack 4
.end method

.method private a(Lorg/apache/http/HttpEntity;Ljava/io/OutputStream;)V
.catch java/lang/Exception from L0 to L1 using L2
.catch all from L0 to L1 using L3
.catch java/lang/Exception from L1 to L4 using L2
.catch all from L1 to L4 using L3
.catch java/lang/Exception from L5 to L6 using L2
.catch all from L5 to L6 using L3
.catch java/lang/Exception from L7 to L8 using L2
.catch all from L7 to L8 using L3
.catch java/lang/Exception from L9 to L10 using L2
.catch all from L9 to L10 using L3
.catch all from L11 to L3 using L3
aload 1
invokestatic com/alipay/android/phone/mrpc/core/i/a(Lorg/apache/http/HttpEntity;)Ljava/io/InputStream;
astore 6
aload 1
invokeinterface org/apache/http/HttpEntity/getContentLength()J 0
lstore 4
L0:
sipush 2048
newarray byte
astore 1
L1:
aload 6
aload 1
invokevirtual java/io/InputStream/read([B)I
istore 3
L4:
iload 3
iconst_m1
if_icmpeq L9
L5:
aload 0
getfield com/alipay/android/phone/mrpc/core/x/c Lcom/alipay/android/phone/mrpc/core/v;
getfield com/alipay/android/phone/mrpc/core/aa/f Z
ifne L9
aload 2
aload 1
iconst_0
iload 3
invokevirtual java/io/OutputStream/write([BII)V
aload 0
getfield com/alipay/android/phone/mrpc/core/x/c Lcom/alipay/android/phone/mrpc/core/v;
invokevirtual com/alipay/android/phone/mrpc/core/v/a()Lcom/alipay/android/phone/mrpc/core/g;
ifnull L1
L6:
lload 4
lconst_0
lcmp
ifle L1
L7:
aload 0
getfield com/alipay/android/phone/mrpc/core/x/c Lcom/alipay/android/phone/mrpc/core/v;
invokevirtual com/alipay/android/phone/mrpc/core/v/a()Lcom/alipay/android/phone/mrpc/core/g;
pop
aload 0
getfield com/alipay/android/phone/mrpc/core/x/c Lcom/alipay/android/phone/mrpc/core/v;
astore 7
L8:
goto L1
L9:
aload 2
invokevirtual java/io/OutputStream/flush()V
L10:
aload 6
invokestatic com/alipay/android/phone/mrpc/core/y/a(Ljava/io/Closeable;)V
return
L2:
astore 1
L11:
aload 1
invokevirtual java/lang/Exception/getCause()Ljava/lang/Throwable;
pop
new java/io/IOException
dup
new java/lang/StringBuilder
dup
ldc "HttpWorker Request Error!"
invokespecial java/lang/StringBuilder/<init>(Ljava/lang/String;)V
aload 1
invokevirtual java/lang/Exception/getLocalizedMessage()Ljava/lang/String;
invokevirtual java/lang/StringBuilder/append(Ljava/lang/String;)Ljava/lang/StringBuilder;
invokevirtual java/lang/StringBuilder/toString()Ljava/lang/String;
invokespecial java/io/IOException/<init>(Ljava/lang/String;)V
athrow
L3:
astore 1
aload 6
invokestatic com/alipay/android/phone/mrpc/core/y/a(Ljava/io/Closeable;)V
aload 1
athrow
.limit locals 8
.limit stack 5
.end method

.method private static b(Lorg/apache/http/HttpResponse;)J
.catch java/lang/NumberFormatException from L0 to L1 using L2
lconst_0
lstore 1
aload 0
ldc "Cache-Control"
invokeinterface org/apache/http/HttpResponse/getFirstHeader(Ljava/lang/String;)Lorg/apache/http/Header; 1
astore 5
aload 5
ifnull L3
aload 5
invokeinterface org/apache/http/Header/getValue()Ljava/lang/String; 0
ldc "="
invokevirtual java/lang/String/split(Ljava/lang/String;)[Ljava/lang/String;
astore 5
aload 5
arraylength
iconst_2
if_icmplt L3
L0:
aload 5
invokestatic com/alipay/android/phone/mrpc/core/x/a([Ljava/lang/String;)J
lstore 3
L1:
lload 3
lstore 1
L4:
lload 1
lreturn
L2:
astore 5
L3:
aload 0
ldc "Expires"
invokeinterface org/apache/http/HttpResponse/getFirstHeader(Ljava/lang/String;)Lorg/apache/http/Header; 1
astore 0
aload 0
ifnull L4
aload 0
invokeinterface org/apache/http/Header/getValue()Ljava/lang/String; 0
invokestatic com/alipay/android/phone/mrpc/core/i/b(Ljava/lang/String;)J
invokestatic java/lang/System/currentTimeMillis()J
lsub
lreturn
.limit locals 6
.limit stack 4
.end method

.method private b()Ljava/net/URI;
aload 0
getfield com/alipay/android/phone/mrpc/core/x/c Lcom/alipay/android/phone/mrpc/core/v;
getfield com/alipay/android/phone/mrpc/core/v/a Ljava/lang/String;
astore 1
aload 0
getfield com/alipay/android/phone/mrpc/core/x/d Ljava/lang/String;
ifnull L0
aload 0
getfield com/alipay/android/phone/mrpc/core/x/d Ljava/lang/String;
astore 1
L0:
aload 1
ifnonnull L1
new java/lang/RuntimeException
dup
ldc "url should not be null"
invokespecial java/lang/RuntimeException/<init>(Ljava/lang/String;)V
athrow
L1:
new java/net/URI
dup
aload 1
invokespecial java/net/URI/<init>(Ljava/lang/String;)V
areturn
.limit locals 2
.limit stack 3
.end method

.method private c()Lorg/apache/http/client/methods/HttpUriRequest;
aload 0
getfield com/alipay/android/phone/mrpc/core/x/f Lorg/apache/http/client/methods/HttpUriRequest;
ifnull L0
aload 0
getfield com/alipay/android/phone/mrpc/core/x/f Lorg/apache/http/client/methods/HttpUriRequest;
areturn
L0:
aload 0
getfield com/alipay/android/phone/mrpc/core/x/j Lorg/apache/http/entity/AbstractHttpEntity;
ifnonnull L1
aload 0
getfield com/alipay/android/phone/mrpc/core/x/c Lcom/alipay/android/phone/mrpc/core/v;
getfield com/alipay/android/phone/mrpc/core/v/b [B
astore 1
aload 0
getfield com/alipay/android/phone/mrpc/core/x/c Lcom/alipay/android/phone/mrpc/core/v;
ldc "gzip"
invokevirtual com/alipay/android/phone/mrpc/core/v/a(Ljava/lang/String;)Ljava/lang/String;
astore 2
aload 1
ifnull L1
aload 2
ldc "true"
invokestatic android/text/TextUtils/equals(Ljava/lang/CharSequence;Ljava/lang/CharSequence;)Z
ifeq L2
aload 0
aload 1
invokestatic com/alipay/android/phone/mrpc/core/i/a([B)Lorg/apache/http/entity/AbstractHttpEntity;
putfield com/alipay/android/phone/mrpc/core/x/j Lorg/apache/http/entity/AbstractHttpEntity;
L3:
aload 0
getfield com/alipay/android/phone/mrpc/core/x/j Lorg/apache/http/entity/AbstractHttpEntity;
aload 0
getfield com/alipay/android/phone/mrpc/core/x/c Lcom/alipay/android/phone/mrpc/core/v;
getfield com/alipay/android/phone/mrpc/core/v/c Ljava/lang/String;
invokevirtual org/apache/http/entity/AbstractHttpEntity/setContentType(Ljava/lang/String;)V
L1:
aload 0
getfield com/alipay/android/phone/mrpc/core/x/j Lorg/apache/http/entity/AbstractHttpEntity;
astore 1
aload 1
ifnull L4
new org/apache/http/client/methods/HttpPost
dup
aload 0
invokespecial com/alipay/android/phone/mrpc/core/x/b()Ljava/net/URI;
invokespecial org/apache/http/client/methods/HttpPost/<init>(Ljava/net/URI;)V
astore 2
aload 2
aload 1
invokevirtual org/apache/http/client/methods/HttpPost/setEntity(Lorg/apache/http/HttpEntity;)V
aload 0
aload 2
putfield com/alipay/android/phone/mrpc/core/x/f Lorg/apache/http/client/methods/HttpUriRequest;
L5:
aload 0
getfield com/alipay/android/phone/mrpc/core/x/f Lorg/apache/http/client/methods/HttpUriRequest;
areturn
L2:
aload 0
new org/apache/http/entity/ByteArrayEntity
dup
aload 1
invokespecial org/apache/http/entity/ByteArrayEntity/<init>([B)V
putfield com/alipay/android/phone/mrpc/core/x/j Lorg/apache/http/entity/AbstractHttpEntity;
goto L3
L4:
aload 0
new org/apache/http/client/methods/HttpGet
dup
aload 0
invokespecial com/alipay/android/phone/mrpc/core/x/b()Ljava/net/URI;
invokespecial org/apache/http/client/methods/HttpGet/<init>(Ljava/net/URI;)V
putfield com/alipay/android/phone/mrpc/core/x/f Lorg/apache/http/client/methods/HttpUriRequest;
goto L5
.limit locals 3
.limit stack 4
.end method

.method private d()Lcom/alipay/android/phone/mrpc/core/ab;
.catch com/alipay/android/phone/mrpc/core/a from L0 to L1 using L2
.catch java/net/URISyntaxException from L0 to L1 using L3
.catch javax/net/ssl/SSLHandshakeException from L0 to L1 using L4
.catch javax/net/ssl/SSLPeerUnverifiedException from L0 to L1 using L5
.catch javax/net/ssl/SSLException from L0 to L1 using L6
.catch org/apache/http/conn/ConnectionPoolTimeoutException from L0 to L1 using L7
.catch org/apache/http/conn/ConnectTimeoutException from L0 to L1 using L8
.catch java/net/SocketTimeoutException from L0 to L1 using L9
.catch org/apache/http/NoHttpResponseException from L0 to L1 using L10
.catch org/apache/http/conn/HttpHostConnectException from L0 to L1 using L11
.catch java/net/UnknownHostException from L0 to L1 using L12
.catch java/io/IOException from L0 to L1 using L13
.catch java/lang/NullPointerException from L0 to L1 using L14
.catch java/lang/Exception from L0 to L1 using L15
.catch com/alipay/android/phone/mrpc/core/a from L16 to L2 using L2
.catch java/net/URISyntaxException from L16 to L2 using L3
.catch javax/net/ssl/SSLHandshakeException from L16 to L2 using L4
.catch javax/net/ssl/SSLPeerUnverifiedException from L16 to L2 using L5
.catch javax/net/ssl/SSLException from L16 to L2 using L6
.catch org/apache/http/conn/ConnectionPoolTimeoutException from L16 to L2 using L7
.catch org/apache/http/conn/ConnectTimeoutException from L16 to L2 using L8
.catch java/net/SocketTimeoutException from L16 to L2 using L9
.catch org/apache/http/NoHttpResponseException from L16 to L2 using L10
.catch org/apache/http/conn/HttpHostConnectException from L16 to L2 using L11
.catch java/net/UnknownHostException from L16 to L2 using L12
.catch java/io/IOException from L16 to L2 using L13
.catch java/lang/NullPointerException from L16 to L2 using L14
.catch java/lang/Exception from L16 to L2 using L15
.catch com/alipay/android/phone/mrpc/core/a from L17 to L18 using L2
.catch java/net/URISyntaxException from L17 to L18 using L3
.catch javax/net/ssl/SSLHandshakeException from L17 to L18 using L4
.catch javax/net/ssl/SSLPeerUnverifiedException from L17 to L18 using L5
.catch javax/net/ssl/SSLException from L17 to L18 using L6
.catch org/apache/http/conn/ConnectionPoolTimeoutException from L17 to L18 using L7
.catch org/apache/http/conn/ConnectTimeoutException from L17 to L18 using L8
.catch java/net/SocketTimeoutException from L17 to L18 using L9
.catch org/apache/http/NoHttpResponseException from L17 to L18 using L10
.catch org/apache/http/conn/HttpHostConnectException from L17 to L18 using L11
.catch java/net/UnknownHostException from L17 to L18 using L12
.catch java/io/IOException from L17 to L18 using L13
.catch java/lang/NullPointerException from L17 to L18 using L14
.catch java/lang/Exception from L17 to L18 using L15
.catch com/alipay/android/phone/mrpc/core/a from L19 to L20 using L2
.catch java/net/URISyntaxException from L19 to L20 using L3
.catch javax/net/ssl/SSLHandshakeException from L19 to L20 using L4
.catch javax/net/ssl/SSLPeerUnverifiedException from L19 to L20 using L5
.catch javax/net/ssl/SSLException from L19 to L20 using L6
.catch org/apache/http/conn/ConnectionPoolTimeoutException from L19 to L20 using L7
.catch org/apache/http/conn/ConnectTimeoutException from L19 to L20 using L8
.catch java/net/SocketTimeoutException from L19 to L20 using L9
.catch org/apache/http/NoHttpResponseException from L19 to L20 using L10
.catch org/apache/http/conn/HttpHostConnectException from L19 to L20 using L11
.catch java/net/UnknownHostException from L19 to L20 using L12
.catch java/io/IOException from L19 to L20 using L13
.catch java/lang/NullPointerException from L19 to L20 using L14
.catch java/lang/Exception from L19 to L20 using L15
.catch com/alipay/android/phone/mrpc/core/a from L21 to L22 using L2
.catch java/net/URISyntaxException from L21 to L22 using L3
.catch javax/net/ssl/SSLHandshakeException from L21 to L22 using L4
.catch javax/net/ssl/SSLPeerUnverifiedException from L21 to L22 using L5
.catch javax/net/ssl/SSLException from L21 to L22 using L6
.catch org/apache/http/conn/ConnectionPoolTimeoutException from L21 to L22 using L7
.catch org/apache/http/conn/ConnectTimeoutException from L21 to L22 using L8
.catch java/net/SocketTimeoutException from L21 to L22 using L9
.catch org/apache/http/NoHttpResponseException from L21 to L22 using L10
.catch org/apache/http/conn/HttpHostConnectException from L21 to L22 using L11
.catch java/net/UnknownHostException from L21 to L22 using L12
.catch java/io/IOException from L21 to L22 using L13
.catch java/lang/NullPointerException from L21 to L22 using L14
.catch java/lang/Exception from L21 to L22 using L15
.catch com/alipay/android/phone/mrpc/core/a from L22 to L23 using L2
.catch java/net/URISyntaxException from L22 to L23 using L3
.catch javax/net/ssl/SSLHandshakeException from L22 to L23 using L4
.catch javax/net/ssl/SSLPeerUnverifiedException from L22 to L23 using L5
.catch javax/net/ssl/SSLException from L22 to L23 using L6
.catch org/apache/http/conn/ConnectionPoolTimeoutException from L22 to L23 using L7
.catch org/apache/http/conn/ConnectTimeoutException from L22 to L23 using L8
.catch java/net/SocketTimeoutException from L22 to L23 using L9
.catch org/apache/http/NoHttpResponseException from L22 to L23 using L10
.catch org/apache/http/conn/HttpHostConnectException from L22 to L23 using L11
.catch java/net/UnknownHostException from L22 to L23 using L12
.catch java/io/IOException from L22 to L23 using L13
.catch java/lang/NullPointerException from L22 to L23 using L14
.catch java/lang/Exception from L22 to L23 using L15
.catch com/alipay/android/phone/mrpc/core/a from L24 to L25 using L2
.catch java/net/URISyntaxException from L24 to L25 using L3
.catch javax/net/ssl/SSLHandshakeException from L24 to L25 using L4
.catch javax/net/ssl/SSLPeerUnverifiedException from L24 to L25 using L5
.catch javax/net/ssl/SSLException from L24 to L25 using L6
.catch org/apache/http/conn/ConnectionPoolTimeoutException from L24 to L25 using L7
.catch org/apache/http/conn/ConnectTimeoutException from L24 to L25 using L8
.catch java/net/SocketTimeoutException from L24 to L25 using L9
.catch org/apache/http/NoHttpResponseException from L24 to L25 using L10
.catch org/apache/http/conn/HttpHostConnectException from L24 to L25 using L11
.catch java/net/UnknownHostException from L24 to L25 using L12
.catch java/io/IOException from L24 to L25 using L13
.catch java/lang/NullPointerException from L24 to L25 using L14
.catch java/lang/Exception from L24 to L25 using L15
.catch com/alipay/android/phone/mrpc/core/a from L25 to L26 using L2
.catch java/net/URISyntaxException from L25 to L26 using L3
.catch javax/net/ssl/SSLHandshakeException from L25 to L26 using L4
.catch javax/net/ssl/SSLPeerUnverifiedException from L25 to L26 using L5
.catch javax/net/ssl/SSLException from L25 to L26 using L6
.catch org/apache/http/conn/ConnectionPoolTimeoutException from L25 to L26 using L7
.catch org/apache/http/conn/ConnectTimeoutException from L25 to L26 using L8
.catch java/net/SocketTimeoutException from L25 to L26 using L9
.catch org/apache/http/NoHttpResponseException from L25 to L26 using L10
.catch org/apache/http/conn/HttpHostConnectException from L25 to L26 using L11
.catch java/net/UnknownHostException from L25 to L26 using L12
.catch java/io/IOException from L25 to L26 using L13
.catch java/lang/NullPointerException from L25 to L26 using L14
.catch java/lang/Exception from L25 to L26 using L15
.catch com/alipay/android/phone/mrpc/core/a from L27 to L28 using L2
.catch java/net/URISyntaxException from L27 to L28 using L3
.catch javax/net/ssl/SSLHandshakeException from L27 to L28 using L4
.catch javax/net/ssl/SSLPeerUnverifiedException from L27 to L28 using L5
.catch javax/net/ssl/SSLException from L27 to L28 using L6
.catch org/apache/http/conn/ConnectionPoolTimeoutException from L27 to L28 using L7
.catch org/apache/http/conn/ConnectTimeoutException from L27 to L28 using L8
.catch java/net/SocketTimeoutException from L27 to L28 using L9
.catch org/apache/http/NoHttpResponseException from L27 to L28 using L10
.catch org/apache/http/conn/HttpHostConnectException from L27 to L28 using L11
.catch java/net/UnknownHostException from L27 to L28 using L12
.catch java/io/IOException from L27 to L28 using L13
.catch java/lang/NullPointerException from L27 to L28 using L14
.catch java/lang/Exception from L27 to L28 using L15
.catch com/alipay/android/phone/mrpc/core/a from L29 to L30 using L2
.catch java/net/URISyntaxException from L29 to L30 using L3
.catch javax/net/ssl/SSLHandshakeException from L29 to L30 using L4
.catch javax/net/ssl/SSLPeerUnverifiedException from L29 to L30 using L5
.catch javax/net/ssl/SSLException from L29 to L30 using L6
.catch org/apache/http/conn/ConnectionPoolTimeoutException from L29 to L30 using L7
.catch org/apache/http/conn/ConnectTimeoutException from L29 to L30 using L8
.catch java/net/SocketTimeoutException from L29 to L30 using L9
.catch org/apache/http/NoHttpResponseException from L29 to L30 using L10
.catch org/apache/http/conn/HttpHostConnectException from L29 to L30 using L11
.catch java/net/UnknownHostException from L29 to L30 using L12
.catch java/io/IOException from L29 to L30 using L13
.catch java/lang/NullPointerException from L29 to L30 using L14
.catch java/lang/Exception from L29 to L30 using L15
.catch com/alipay/android/phone/mrpc/core/a from L31 to L32 using L2
.catch java/net/URISyntaxException from L31 to L32 using L3
.catch javax/net/ssl/SSLHandshakeException from L31 to L32 using L4
.catch javax/net/ssl/SSLPeerUnverifiedException from L31 to L32 using L5
.catch javax/net/ssl/SSLException from L31 to L32 using L6
.catch org/apache/http/conn/ConnectionPoolTimeoutException from L31 to L32 using L7
.catch org/apache/http/conn/ConnectTimeoutException from L31 to L32 using L8
.catch java/net/SocketTimeoutException from L31 to L32 using L9
.catch org/apache/http/NoHttpResponseException from L31 to L32 using L10
.catch org/apache/http/conn/HttpHostConnectException from L31 to L32 using L11
.catch java/net/UnknownHostException from L31 to L32 using L12
.catch java/io/IOException from L31 to L32 using L13
.catch java/lang/NullPointerException from L31 to L32 using L14
.catch java/lang/Exception from L31 to L32 using L15
.catch com/alipay/android/phone/mrpc/core/a from L33 to L34 using L2
.catch java/net/URISyntaxException from L33 to L34 using L3
.catch javax/net/ssl/SSLHandshakeException from L33 to L34 using L4
.catch javax/net/ssl/SSLPeerUnverifiedException from L33 to L34 using L5
.catch javax/net/ssl/SSLException from L33 to L34 using L6
.catch org/apache/http/conn/ConnectionPoolTimeoutException from L33 to L34 using L7
.catch org/apache/http/conn/ConnectTimeoutException from L33 to L34 using L8
.catch java/net/SocketTimeoutException from L33 to L34 using L9
.catch org/apache/http/NoHttpResponseException from L33 to L34 using L10
.catch org/apache/http/conn/HttpHostConnectException from L33 to L34 using L11
.catch java/net/UnknownHostException from L33 to L34 using L12
.catch java/io/IOException from L33 to L34 using L13
.catch java/lang/NullPointerException from L33 to L34 using L14
.catch java/lang/Exception from L33 to L34 using L15
.catch com/alipay/android/phone/mrpc/core/a from L35 to L36 using L2
.catch java/net/URISyntaxException from L35 to L36 using L3
.catch javax/net/ssl/SSLHandshakeException from L35 to L36 using L4
.catch javax/net/ssl/SSLPeerUnverifiedException from L35 to L36 using L5
.catch javax/net/ssl/SSLException from L35 to L36 using L6
.catch org/apache/http/conn/ConnectionPoolTimeoutException from L35 to L36 using L7
.catch org/apache/http/conn/ConnectTimeoutException from L35 to L36 using L8
.catch java/net/SocketTimeoutException from L35 to L36 using L9
.catch org/apache/http/NoHttpResponseException from L35 to L36 using L10
.catch org/apache/http/conn/HttpHostConnectException from L35 to L36 using L11
.catch java/net/UnknownHostException from L35 to L36 using L12
.catch java/io/IOException from L35 to L36 using L13
.catch java/lang/NullPointerException from L35 to L36 using L14
.catch java/lang/Exception from L35 to L36 using L15
.catch com/alipay/android/phone/mrpc/core/a from L37 to L38 using L2
.catch java/net/URISyntaxException from L37 to L38 using L3
.catch javax/net/ssl/SSLHandshakeException from L37 to L38 using L4
.catch javax/net/ssl/SSLPeerUnverifiedException from L37 to L38 using L5
.catch javax/net/ssl/SSLException from L37 to L38 using L6
.catch org/apache/http/conn/ConnectionPoolTimeoutException from L37 to L38 using L7
.catch org/apache/http/conn/ConnectTimeoutException from L37 to L38 using L8
.catch java/net/SocketTimeoutException from L37 to L38 using L9
.catch org/apache/http/NoHttpResponseException from L37 to L38 using L10
.catch org/apache/http/conn/HttpHostConnectException from L37 to L38 using L11
.catch java/net/UnknownHostException from L37 to L38 using L12
.catch java/io/IOException from L37 to L38 using L13
.catch java/lang/NullPointerException from L37 to L38 using L14
.catch java/lang/Exception from L37 to L38 using L15
.catch com/alipay/android/phone/mrpc/core/a from L38 to L39 using L2
.catch java/net/URISyntaxException from L38 to L39 using L3
.catch javax/net/ssl/SSLHandshakeException from L38 to L39 using L4
.catch javax/net/ssl/SSLPeerUnverifiedException from L38 to L39 using L5
.catch javax/net/ssl/SSLException from L38 to L39 using L6
.catch org/apache/http/conn/ConnectionPoolTimeoutException from L38 to L39 using L7
.catch org/apache/http/conn/ConnectTimeoutException from L38 to L39 using L8
.catch java/net/SocketTimeoutException from L38 to L39 using L9
.catch org/apache/http/NoHttpResponseException from L38 to L39 using L10
.catch org/apache/http/conn/HttpHostConnectException from L38 to L39 using L11
.catch java/net/UnknownHostException from L38 to L39 using L12
.catch java/io/IOException from L38 to L39 using L13
.catch java/lang/NullPointerException from L38 to L39 using L14
.catch java/lang/Exception from L38 to L39 using L15
.catch com/alipay/android/phone/mrpc/core/a from L39 to L40 using L2
.catch java/net/URISyntaxException from L39 to L40 using L3
.catch javax/net/ssl/SSLHandshakeException from L39 to L40 using L4
.catch javax/net/ssl/SSLPeerUnverifiedException from L39 to L40 using L5
.catch javax/net/ssl/SSLException from L39 to L40 using L6
.catch org/apache/http/conn/ConnectionPoolTimeoutException from L39 to L40 using L7
.catch org/apache/http/conn/ConnectTimeoutException from L39 to L40 using L8
.catch java/net/SocketTimeoutException from L39 to L40 using L9
.catch org/apache/http/NoHttpResponseException from L39 to L40 using L10
.catch org/apache/http/conn/HttpHostConnectException from L39 to L40 using L11
.catch java/net/UnknownHostException from L39 to L40 using L12
.catch java/io/IOException from L39 to L40 using L13
.catch java/lang/NullPointerException from L39 to L40 using L14
.catch java/lang/Exception from L39 to L40 using L15
.catch com/alipay/android/phone/mrpc/core/a from L40 to L41 using L2
.catch java/net/URISyntaxException from L40 to L41 using L3
.catch javax/net/ssl/SSLHandshakeException from L40 to L41 using L4
.catch javax/net/ssl/SSLPeerUnverifiedException from L40 to L41 using L5
.catch javax/net/ssl/SSLException from L40 to L41 using L6
.catch org/apache/http/conn/ConnectionPoolTimeoutException from L40 to L41 using L7
.catch org/apache/http/conn/ConnectTimeoutException from L40 to L41 using L8
.catch java/net/SocketTimeoutException from L40 to L41 using L9
.catch org/apache/http/NoHttpResponseException from L40 to L41 using L10
.catch org/apache/http/conn/HttpHostConnectException from L40 to L41 using L11
.catch java/net/UnknownHostException from L40 to L41 using L12
.catch java/io/IOException from L40 to L41 using L13
.catch java/lang/NullPointerException from L40 to L41 using L14
.catch java/lang/Exception from L40 to L41 using L15
.catch com/alipay/android/phone/mrpc/core/a from L41 to L42 using L2
.catch java/net/URISyntaxException from L41 to L42 using L3
.catch javax/net/ssl/SSLHandshakeException from L41 to L42 using L4
.catch javax/net/ssl/SSLPeerUnverifiedException from L41 to L42 using L5
.catch javax/net/ssl/SSLException from L41 to L42 using L6
.catch org/apache/http/conn/ConnectionPoolTimeoutException from L41 to L42 using L7
.catch org/apache/http/conn/ConnectTimeoutException from L41 to L42 using L8
.catch java/net/SocketTimeoutException from L41 to L42 using L9
.catch org/apache/http/NoHttpResponseException from L41 to L42 using L10
.catch org/apache/http/conn/HttpHostConnectException from L41 to L42 using L11
.catch java/net/UnknownHostException from L41 to L42 using L12
.catch java/io/IOException from L41 to L42 using L13
.catch java/lang/NullPointerException from L41 to L42 using L14
.catch java/lang/Exception from L41 to L42 using L15
.catch com/alipay/android/phone/mrpc/core/a from L43 to L44 using L2
.catch java/net/URISyntaxException from L43 to L44 using L3
.catch javax/net/ssl/SSLHandshakeException from L43 to L44 using L4
.catch javax/net/ssl/SSLPeerUnverifiedException from L43 to L44 using L5
.catch javax/net/ssl/SSLException from L43 to L44 using L6
.catch org/apache/http/conn/ConnectionPoolTimeoutException from L43 to L44 using L7
.catch org/apache/http/conn/ConnectTimeoutException from L43 to L44 using L8
.catch java/net/SocketTimeoutException from L43 to L44 using L9
.catch org/apache/http/NoHttpResponseException from L43 to L44 using L10
.catch org/apache/http/conn/HttpHostConnectException from L43 to L44 using L11
.catch java/net/UnknownHostException from L43 to L44 using L12
.catch java/io/IOException from L43 to L44 using L13
.catch java/lang/NullPointerException from L43 to L44 using L14
.catch java/lang/Exception from L43 to L44 using L15
.catch com/alipay/android/phone/mrpc/core/a from L45 to L46 using L2
.catch java/net/URISyntaxException from L45 to L46 using L3
.catch javax/net/ssl/SSLHandshakeException from L45 to L46 using L4
.catch javax/net/ssl/SSLPeerUnverifiedException from L45 to L46 using L5
.catch javax/net/ssl/SSLException from L45 to L46 using L6
.catch org/apache/http/conn/ConnectionPoolTimeoutException from L45 to L46 using L7
.catch org/apache/http/conn/ConnectTimeoutException from L45 to L46 using L8
.catch java/net/SocketTimeoutException from L45 to L46 using L9
.catch org/apache/http/NoHttpResponseException from L45 to L46 using L10
.catch org/apache/http/conn/HttpHostConnectException from L45 to L46 using L11
.catch java/net/UnknownHostException from L45 to L46 using L12
.catch java/io/IOException from L45 to L46 using L13
.catch java/lang/NullPointerException from L45 to L46 using L14
.catch java/lang/Exception from L45 to L46 using L15
.catch com/alipay/android/phone/mrpc/core/a from L47 to L48 using L2
.catch java/net/URISyntaxException from L47 to L48 using L3
.catch javax/net/ssl/SSLHandshakeException from L47 to L48 using L4
.catch javax/net/ssl/SSLPeerUnverifiedException from L47 to L48 using L5
.catch javax/net/ssl/SSLException from L47 to L48 using L6
.catch org/apache/http/conn/ConnectionPoolTimeoutException from L47 to L48 using L7
.catch org/apache/http/conn/ConnectTimeoutException from L47 to L48 using L8
.catch java/net/SocketTimeoutException from L47 to L48 using L9
.catch org/apache/http/NoHttpResponseException from L47 to L48 using L10
.catch org/apache/http/conn/HttpHostConnectException from L47 to L48 using L11
.catch java/net/UnknownHostException from L47 to L48 using L12
.catch java/io/IOException from L47 to L48 using L13
.catch java/lang/NullPointerException from L47 to L48 using L14
.catch java/lang/Exception from L47 to L48 using L15
.catch com/alipay/android/phone/mrpc/core/a from L49 to L5 using L2
.catch java/net/URISyntaxException from L49 to L5 using L3
.catch javax/net/ssl/SSLHandshakeException from L49 to L5 using L4
.catch javax/net/ssl/SSLPeerUnverifiedException from L49 to L5 using L5
.catch javax/net/ssl/SSLException from L49 to L5 using L6
.catch org/apache/http/conn/ConnectionPoolTimeoutException from L49 to L5 using L7
.catch org/apache/http/conn/ConnectTimeoutException from L49 to L5 using L8
.catch java/net/SocketTimeoutException from L49 to L5 using L9
.catch org/apache/http/NoHttpResponseException from L49 to L5 using L10
.catch org/apache/http/conn/HttpHostConnectException from L49 to L5 using L11
.catch java/net/UnknownHostException from L49 to L5 using L12
.catch java/io/IOException from L49 to L5 using L13
.catch java/lang/NullPointerException from L49 to L5 using L14
.catch java/lang/Exception from L49 to L5 using L15
.catch com/alipay/android/phone/mrpc/core/a from L50 to L51 using L2
.catch java/net/URISyntaxException from L50 to L51 using L3
.catch javax/net/ssl/SSLHandshakeException from L50 to L51 using L4
.catch javax/net/ssl/SSLPeerUnverifiedException from L50 to L51 using L5
.catch javax/net/ssl/SSLException from L50 to L51 using L6
.catch org/apache/http/conn/ConnectionPoolTimeoutException from L50 to L51 using L7
.catch org/apache/http/conn/ConnectTimeoutException from L50 to L51 using L8
.catch java/net/SocketTimeoutException from L50 to L51 using L9
.catch org/apache/http/NoHttpResponseException from L50 to L51 using L10
.catch org/apache/http/conn/HttpHostConnectException from L50 to L51 using L11
.catch java/net/UnknownHostException from L50 to L51 using L12
.catch java/io/IOException from L50 to L51 using L13
.catch java/lang/NullPointerException from L50 to L51 using L14
.catch java/lang/Exception from L50 to L51 using L15
.catch com/alipay/android/phone/mrpc/core/a from L52 to L53 using L2
.catch java/net/URISyntaxException from L52 to L53 using L3
.catch javax/net/ssl/SSLHandshakeException from L52 to L53 using L4
.catch javax/net/ssl/SSLPeerUnverifiedException from L52 to L53 using L5
.catch javax/net/ssl/SSLException from L52 to L53 using L6
.catch org/apache/http/conn/ConnectionPoolTimeoutException from L52 to L53 using L7
.catch org/apache/http/conn/ConnectTimeoutException from L52 to L53 using L8
.catch java/net/SocketTimeoutException from L52 to L53 using L9
.catch org/apache/http/NoHttpResponseException from L52 to L53 using L10
.catch org/apache/http/conn/HttpHostConnectException from L52 to L53 using L11
.catch java/net/UnknownHostException from L52 to L53 using L12
.catch java/io/IOException from L52 to L53 using L13
.catch java/lang/NullPointerException from L52 to L53 using L14
.catch java/lang/Exception from L52 to L53 using L15
.catch com/alipay/android/phone/mrpc/core/a from L54 to L55 using L2
.catch java/net/URISyntaxException from L54 to L55 using L3
.catch javax/net/ssl/SSLHandshakeException from L54 to L55 using L4
.catch javax/net/ssl/SSLPeerUnverifiedException from L54 to L55 using L5
.catch javax/net/ssl/SSLException from L54 to L55 using L6
.catch org/apache/http/conn/ConnectionPoolTimeoutException from L54 to L55 using L7
.catch org/apache/http/conn/ConnectTimeoutException from L54 to L55 using L8
.catch java/net/SocketTimeoutException from L54 to L55 using L9
.catch org/apache/http/NoHttpResponseException from L54 to L55 using L10
.catch org/apache/http/conn/HttpHostConnectException from L54 to L55 using L11
.catch java/net/UnknownHostException from L54 to L55 using L12
.catch java/io/IOException from L54 to L55 using L13
.catch java/lang/NullPointerException from L54 to L55 using L14
.catch java/lang/Exception from L54 to L55 using L15
.catch java/lang/Exception from L55 to L56 using L57
.catch com/alipay/android/phone/mrpc/core/a from L55 to L56 using L2
.catch java/net/URISyntaxException from L55 to L56 using L3
.catch javax/net/ssl/SSLHandshakeException from L55 to L56 using L4
.catch javax/net/ssl/SSLPeerUnverifiedException from L55 to L56 using L5
.catch javax/net/ssl/SSLException from L55 to L56 using L6
.catch org/apache/http/conn/ConnectionPoolTimeoutException from L55 to L56 using L7
.catch org/apache/http/conn/ConnectTimeoutException from L55 to L56 using L8
.catch java/net/SocketTimeoutException from L55 to L56 using L9
.catch org/apache/http/NoHttpResponseException from L55 to L56 using L10
.catch org/apache/http/conn/HttpHostConnectException from L55 to L56 using L11
.catch java/net/UnknownHostException from L55 to L56 using L12
.catch java/io/IOException from L55 to L56 using L13
.catch java/lang/NullPointerException from L55 to L56 using L14
.catch com/alipay/android/phone/mrpc/core/a from L56 to L58 using L2
.catch java/net/URISyntaxException from L56 to L58 using L3
.catch javax/net/ssl/SSLHandshakeException from L56 to L58 using L4
.catch javax/net/ssl/SSLPeerUnverifiedException from L56 to L58 using L5
.catch javax/net/ssl/SSLException from L56 to L58 using L6
.catch org/apache/http/conn/ConnectionPoolTimeoutException from L56 to L58 using L7
.catch org/apache/http/conn/ConnectTimeoutException from L56 to L58 using L8
.catch java/net/SocketTimeoutException from L56 to L58 using L9
.catch org/apache/http/NoHttpResponseException from L56 to L58 using L10
.catch org/apache/http/conn/HttpHostConnectException from L56 to L58 using L11
.catch java/net/UnknownHostException from L56 to L58 using L12
.catch java/io/IOException from L56 to L58 using L13
.catch java/lang/NullPointerException from L56 to L58 using L14
.catch java/lang/Exception from L56 to L58 using L15
.catch com/alipay/android/phone/mrpc/core/a from L59 to L60 using L2
.catch java/net/URISyntaxException from L59 to L60 using L3
.catch javax/net/ssl/SSLHandshakeException from L59 to L60 using L4
.catch javax/net/ssl/SSLPeerUnverifiedException from L59 to L60 using L5
.catch javax/net/ssl/SSLException from L59 to L60 using L6
.catch org/apache/http/conn/ConnectionPoolTimeoutException from L59 to L60 using L7
.catch org/apache/http/conn/ConnectTimeoutException from L59 to L60 using L8
.catch java/net/SocketTimeoutException from L59 to L60 using L9
.catch org/apache/http/NoHttpResponseException from L59 to L60 using L10
.catch org/apache/http/conn/HttpHostConnectException from L59 to L60 using L11
.catch java/net/UnknownHostException from L59 to L60 using L12
.catch java/io/IOException from L59 to L60 using L13
.catch java/lang/NullPointerException from L59 to L60 using L14
.catch java/lang/Exception from L59 to L60 using L15
L0:
aload 0
getfield com/alipay/android/phone/mrpc/core/x/b Landroid/content/Context;
ldc "connectivity"
invokevirtual android/content/Context/getSystemService(Ljava/lang/String;)Ljava/lang/Object;
checkcast android/net/ConnectivityManager
invokevirtual android/net/ConnectivityManager/getAllNetworkInfo()[Landroid/net/NetworkInfo;
astore 7
L1:
aload 7
ifnonnull L17
iconst_0
istore 1
L61:
iload 1
ifne L21
L16:
new com/alipay/android/phone/mrpc/core/a
dup
iconst_1
invokestatic java/lang/Integer/valueOf(I)Ljava/lang/Integer;
ldc "The network is not available"
invokespecial com/alipay/android/phone/mrpc/core/a/<init>(Ljava/lang/Integer;Ljava/lang/String;)V
athrow
L2:
astore 7
aload 0
invokespecial com/alipay/android/phone/mrpc/core/x/e()V
aload 0
getfield com/alipay/android/phone/mrpc/core/x/c Lcom/alipay/android/phone/mrpc/core/v;
invokevirtual com/alipay/android/phone/mrpc/core/v/a()Lcom/alipay/android/phone/mrpc/core/g;
ifnull L62
aload 0
getfield com/alipay/android/phone/mrpc/core/x/c Lcom/alipay/android/phone/mrpc/core/v;
invokevirtual com/alipay/android/phone/mrpc/core/v/a()Lcom/alipay/android/phone/mrpc/core/g;
pop
aload 0
getfield com/alipay/android/phone/mrpc/core/x/c Lcom/alipay/android/phone/mrpc/core/v;
astore 8
aload 7
invokevirtual com/alipay/android/phone/mrpc/core/a/a()I
pop
aload 7
invokevirtual com/alipay/android/phone/mrpc/core/a/b()Ljava/lang/String;
pop
L62:
new java/lang/StringBuilder
dup
invokespecial java/lang/StringBuilder/<init>()V
aload 7
invokevirtual java/lang/StringBuilder/append(Ljava/lang/Object;)Ljava/lang/StringBuilder;
pop
aload 7
athrow
L17:
aload 7
arraylength
istore 2
L18:
iconst_0
istore 1
L63:
iload 1
iload 2
if_icmpge L64
aload 7
iload 1
aaload
astore 8
aload 8
ifnull L65
L19:
aload 8
invokevirtual android/net/NetworkInfo/isAvailable()Z
ifeq L65
aload 8
invokevirtual android/net/NetworkInfo/isConnectedOrConnecting()Z
ifeq L65
L20:
iconst_1
istore 1
goto L61
L21:
aload 0
getfield com/alipay/android/phone/mrpc/core/x/c Lcom/alipay/android/phone/mrpc/core/v;
invokevirtual com/alipay/android/phone/mrpc/core/v/a()Lcom/alipay/android/phone/mrpc/core/g;
ifnull L22
aload 0
getfield com/alipay/android/phone/mrpc/core/x/c Lcom/alipay/android/phone/mrpc/core/v;
invokevirtual com/alipay/android/phone/mrpc/core/v/a()Lcom/alipay/android/phone/mrpc/core/g;
pop
aload 0
getfield com/alipay/android/phone/mrpc/core/x/c Lcom/alipay/android/phone/mrpc/core/v;
astore 7
L22:
aload 0
getfield com/alipay/android/phone/mrpc/core/x/c Lcom/alipay/android/phone/mrpc/core/v;
getfield com/alipay/android/phone/mrpc/core/v/d Ljava/util/ArrayList;
astore 7
L23:
aload 7
ifnull L27
L24:
aload 7
invokevirtual java/util/ArrayList/isEmpty()Z
ifne L27
aload 7
invokevirtual java/util/ArrayList/iterator()Ljava/util/Iterator;
astore 7
L25:
aload 7
invokeinterface java/util/Iterator/hasNext()Z 0
ifeq L27
aload 7
invokeinterface java/util/Iterator/next()Ljava/lang/Object; 0
checkcast org/apache/http/Header
astore 8
aload 0
invokespecial com/alipay/android/phone/mrpc/core/x/c()Lorg/apache/http/client/methods/HttpUriRequest;
aload 8
invokeinterface org/apache/http/client/methods/HttpUriRequest/addHeader(Lorg/apache/http/Header;)V 1
L26:
goto L25
L3:
astore 7
new java/lang/RuntimeException
dup
ldc "Url parser error!"
aload 7
invokevirtual java/net/URISyntaxException/getCause()Ljava/lang/Throwable;
invokespecial java/lang/RuntimeException/<init>(Ljava/lang/String;Ljava/lang/Throwable;)V
athrow
L27:
aload 0
invokespecial com/alipay/android/phone/mrpc/core/x/c()Lorg/apache/http/client/methods/HttpUriRequest;
invokestatic com/alipay/android/phone/mrpc/core/i/a(Lorg/apache/http/HttpRequest;)V
aload 0
invokespecial com/alipay/android/phone/mrpc/core/x/c()Lorg/apache/http/client/methods/HttpUriRequest;
invokestatic com/alipay/android/phone/mrpc/core/i/b(Lorg/apache/http/HttpRequest;)V
aload 0
invokespecial com/alipay/android/phone/mrpc/core/x/c()Lorg/apache/http/client/methods/HttpUriRequest;
ldc "cookie"
aload 0
invokespecial com/alipay/android/phone/mrpc/core/x/i()Landroid/webkit/CookieManager;
aload 0
getfield com/alipay/android/phone/mrpc/core/x/c Lcom/alipay/android/phone/mrpc/core/v;
getfield com/alipay/android/phone/mrpc/core/v/a Ljava/lang/String;
invokevirtual android/webkit/CookieManager/getCookie(Ljava/lang/String;)Ljava/lang/String;
invokeinterface org/apache/http/client/methods/HttpUriRequest/addHeader(Ljava/lang/String;Ljava/lang/String;)V 2
aload 0
getfield com/alipay/android/phone/mrpc/core/x/g Lorg/apache/http/protocol/HttpContext;
ldc "http.cookie-store"
aload 0
getfield com/alipay/android/phone/mrpc/core/x/h Lorg/apache/http/client/CookieStore;
invokeinterface org/apache/http/protocol/HttpContext/setAttribute(Ljava/lang/String;Ljava/lang/Object;)V 2
aload 0
getfield com/alipay/android/phone/mrpc/core/x/a Lcom/alipay/android/phone/mrpc/core/s;
invokevirtual com/alipay/android/phone/mrpc/core/s/a()Lcom/alipay/android/phone/mrpc/core/i;
getstatic com/alipay/android/phone/mrpc/core/x/e Lorg/apache/http/client/HttpRequestRetryHandler;
invokevirtual com/alipay/android/phone/mrpc/core/i/a(Lorg/apache/http/client/HttpRequestRetryHandler;)V
invokestatic java/lang/System/currentTimeMillis()J
lstore 3
new java/lang/StringBuilder
dup
ldc "By Http/Https to request. operationType="
invokespecial java/lang/StringBuilder/<init>(Ljava/lang/String;)V
aload 0
invokespecial com/alipay/android/phone/mrpc/core/x/f()Ljava/lang/String;
invokevirtual java/lang/StringBuilder/append(Ljava/lang/String;)Ljava/lang/StringBuilder;
ldc " url="
invokevirtual java/lang/StringBuilder/append(Ljava/lang/String;)Ljava/lang/StringBuilder;
aload 0
getfield com/alipay/android/phone/mrpc/core/x/f Lorg/apache/http/client/methods/HttpUriRequest;
invokeinterface org/apache/http/client/methods/HttpUriRequest/getURI()Ljava/net/URI; 0
invokevirtual java/net/URI/toString()Ljava/lang/String;
invokevirtual java/lang/StringBuilder/append(Ljava/lang/String;)Ljava/lang/StringBuilder;
pop
aload 0
getfield com/alipay/android/phone/mrpc/core/x/a Lcom/alipay/android/phone/mrpc/core/s;
invokevirtual com/alipay/android/phone/mrpc/core/s/a()Lcom/alipay/android/phone/mrpc/core/i;
invokevirtual com/alipay/android/phone/mrpc/core/i/getParams()Lorg/apache/http/params/HttpParams;
astore 9
aload 0
getfield com/alipay/android/phone/mrpc/core/x/b Landroid/content/Context;
ldc "connectivity"
invokevirtual android/content/Context/getSystemService(Ljava/lang/String;)Ljava/lang/Object;
checkcast android/net/ConnectivityManager
invokevirtual android/net/ConnectivityManager/getActiveNetworkInfo()Landroid/net/NetworkInfo;
astore 7
L28:
aload 7
ifnull L66
L29:
aload 7
invokevirtual android/net/NetworkInfo/isAvailable()Z
ifeq L66
invokestatic android/net/Proxy/getDefaultHost()Ljava/lang/String;
astore 7
invokestatic android/net/Proxy/getDefaultPort()I
istore 1
L30:
aload 7
ifnull L66
L31:
new org/apache/http/HttpHost
dup
aload 7
iload 1
invokespecial org/apache/http/HttpHost/<init>(Ljava/lang/String;I)V
astore 7
L32:
aload 7
astore 8
aload 7
ifnull L37
aload 7
astore 8
L33:
aload 7
invokevirtual org/apache/http/HttpHost/getHostName()Ljava/lang/String;
ldc "127.0.0.1"
invokestatic android/text/TextUtils/equals(Ljava/lang/CharSequence;Ljava/lang/CharSequence;)Z
ifeq L37
L34:
aload 7
astore 8
L35:
aload 7
invokevirtual org/apache/http/HttpHost/getPort()I
sipush 8087
if_icmpne L37
L36:
aconst_null
astore 8
L37:
aload 9
ldc "http.route.default-proxy"
aload 8
invokeinterface org/apache/http/params/HttpParams/setParameter(Ljava/lang/String;Ljava/lang/Object;)Lorg/apache/http/params/HttpParams; 2
pop
aload 0
getfield com/alipay/android/phone/mrpc/core/x/k Lorg/apache/http/HttpHost;
ifnull L45
aload 0
getfield com/alipay/android/phone/mrpc/core/x/k Lorg/apache/http/HttpHost;
astore 7
L38:
aload 0
invokespecial com/alipay/android/phone/mrpc/core/x/g()I
bipush 80
if_icmpne L39
new org/apache/http/HttpHost
dup
aload 0
invokespecial com/alipay/android/phone/mrpc/core/x/h()Ljava/net/URL;
invokevirtual java/net/URL/getHost()Ljava/lang/String;
invokespecial org/apache/http/HttpHost/<init>(Ljava/lang/String;)V
astore 7
L39:
aload 0
getfield com/alipay/android/phone/mrpc/core/x/a Lcom/alipay/android/phone/mrpc/core/s;
invokevirtual com/alipay/android/phone/mrpc/core/s/a()Lcom/alipay/android/phone/mrpc/core/i;
aload 7
aload 0
getfield com/alipay/android/phone/mrpc/core/x/f Lorg/apache/http/client/methods/HttpUriRequest;
aload 0
getfield com/alipay/android/phone/mrpc/core/x/g Lorg/apache/http/protocol/HttpContext;
invokevirtual com/alipay/android/phone/mrpc/core/i/execute(Lorg/apache/http/HttpHost;Lorg/apache/http/HttpRequest;Lorg/apache/http/protocol/HttpContext;)Lorg/apache/http/HttpResponse;
astore 8
invokestatic java/lang/System/currentTimeMillis()J
lstore 5
aload 0
getfield com/alipay/android/phone/mrpc/core/x/a Lcom/alipay/android/phone/mrpc/core/s;
lload 5
lload 3
lsub
invokevirtual com/alipay/android/phone/mrpc/core/s/b(J)V
aload 0
getfield com/alipay/android/phone/mrpc/core/x/h Lorg/apache/http/client/CookieStore;
invokeinterface org/apache/http/client/CookieStore/getCookies()Ljava/util/List; 0
astore 7
aload 0
getfield com/alipay/android/phone/mrpc/core/x/c Lcom/alipay/android/phone/mrpc/core/v;
getfield com/alipay/android/phone/mrpc/core/v/e Z
ifeq L40
aload 0
invokespecial com/alipay/android/phone/mrpc/core/x/i()Landroid/webkit/CookieManager;
invokevirtual android/webkit/CookieManager/removeAllCookie()V
L40:
aload 7
invokeinterface java/util/List/isEmpty()Z 0
ifne L47
aload 7
invokeinterface java/util/List/iterator()Ljava/util/Iterator; 0
astore 9
L41:
aload 9
invokeinterface java/util/Iterator/hasNext()Z 0
ifeq L47
aload 9
invokeinterface java/util/Iterator/next()Ljava/lang/Object; 0
checkcast org/apache/http/cookie/Cookie
astore 7
aload 7
invokeinterface org/apache/http/cookie/Cookie/getDomain()Ljava/lang/String; 0
ifnull L41
new java/lang/StringBuilder
dup
invokespecial java/lang/StringBuilder/<init>()V
aload 7
invokeinterface org/apache/http/cookie/Cookie/getName()Ljava/lang/String; 0
invokevirtual java/lang/StringBuilder/append(Ljava/lang/String;)Ljava/lang/StringBuilder;
ldc "="
invokevirtual java/lang/StringBuilder/append(Ljava/lang/String;)Ljava/lang/StringBuilder;
aload 7
invokeinterface org/apache/http/cookie/Cookie/getValue()Ljava/lang/String; 0
invokevirtual java/lang/StringBuilder/append(Ljava/lang/String;)Ljava/lang/StringBuilder;
ldc "; domain="
invokevirtual java/lang/StringBuilder/append(Ljava/lang/String;)Ljava/lang/StringBuilder;
aload 7
invokeinterface org/apache/http/cookie/Cookie/getDomain()Ljava/lang/String; 0
invokevirtual java/lang/StringBuilder/append(Ljava/lang/String;)Ljava/lang/StringBuilder;
astore 10
aload 7
invokeinterface org/apache/http/cookie/Cookie/isSecure()Z 0
ifeq L67
L42:
ldc "; Secure"
astore 7
L43:
aload 10
aload 7
invokevirtual java/lang/StringBuilder/append(Ljava/lang/String;)Ljava/lang/StringBuilder;
invokevirtual java/lang/StringBuilder/toString()Ljava/lang/String;
astore 7
aload 0
invokespecial com/alipay/android/phone/mrpc/core/x/i()Landroid/webkit/CookieManager;
aload 0
getfield com/alipay/android/phone/mrpc/core/x/c Lcom/alipay/android/phone/mrpc/core/v;
getfield com/alipay/android/phone/mrpc/core/v/a Ljava/lang/String;
aload 7
invokevirtual android/webkit/CookieManager/setCookie(Ljava/lang/String;Ljava/lang/String;)V
invokestatic android/webkit/CookieSyncManager/getInstance()Landroid/webkit/CookieSyncManager;
invokevirtual android/webkit/CookieSyncManager/sync()V
L44:
goto L41
L4:
astore 7
aload 0
invokespecial com/alipay/android/phone/mrpc/core/x/e()V
aload 0
getfield com/alipay/android/phone/mrpc/core/x/c Lcom/alipay/android/phone/mrpc/core/v;
invokevirtual com/alipay/android/phone/mrpc/core/v/a()Lcom/alipay/android/phone/mrpc/core/g;
ifnull L68
aload 0
getfield com/alipay/android/phone/mrpc/core/x/c Lcom/alipay/android/phone/mrpc/core/v;
invokevirtual com/alipay/android/phone/mrpc/core/v/a()Lcom/alipay/android/phone/mrpc/core/g;
pop
aload 0
getfield com/alipay/android/phone/mrpc/core/x/c Lcom/alipay/android/phone/mrpc/core/v;
astore 8
new java/lang/StringBuilder
dup
invokespecial java/lang/StringBuilder/<init>()V
aload 7
invokevirtual java/lang/StringBuilder/append(Ljava/lang/Object;)Ljava/lang/StringBuilder;
pop
L68:
new java/lang/StringBuilder
dup
invokespecial java/lang/StringBuilder/<init>()V
aload 7
invokevirtual java/lang/StringBuilder/append(Ljava/lang/Object;)Ljava/lang/StringBuilder;
pop
new com/alipay/android/phone/mrpc/core/a
dup
iconst_2
invokestatic java/lang/Integer/valueOf(I)Ljava/lang/Integer;
aload 7
invokestatic java/lang/String/valueOf(Ljava/lang/Object;)Ljava/lang/String;
invokespecial com/alipay/android/phone/mrpc/core/a/<init>(Ljava/lang/Integer;Ljava/lang/String;)V
athrow
L45:
aload 0
invokespecial com/alipay/android/phone/mrpc/core/x/h()Ljava/net/URL;
astore 7
aload 0
new org/apache/http/HttpHost
dup
aload 7
invokevirtual java/net/URL/getHost()Ljava/lang/String;
aload 0
invokespecial com/alipay/android/phone/mrpc/core/x/g()I
aload 7
invokevirtual java/net/URL/getProtocol()Ljava/lang/String;
invokespecial org/apache/http/HttpHost/<init>(Ljava/lang/String;ILjava/lang/String;)V
putfield com/alipay/android/phone/mrpc/core/x/k Lorg/apache/http/HttpHost;
aload 0
getfield com/alipay/android/phone/mrpc/core/x/k Lorg/apache/http/HttpHost;
astore 7
L46:
goto L38
L47:
aload 0
getfield com/alipay/android/phone/mrpc/core/x/c Lcom/alipay/android/phone/mrpc/core/v;
astore 7
aload 8
invokeinterface org/apache/http/HttpResponse/getStatusLine()Lorg/apache/http/StatusLine; 0
invokeinterface org/apache/http/StatusLine/getStatusCode()I 0
istore 2
aload 8
invokeinterface org/apache/http/HttpResponse/getStatusLine()Lorg/apache/http/StatusLine; 0
invokeinterface org/apache/http/StatusLine/getReasonPhrase()Ljava/lang/String; 0
astore 7
L48:
iload 2
sipush 200
if_icmpeq L50
iload 2
sipush 304
if_icmpne L69
iconst_1
istore 1
L70:
iload 1
ifne L50
L49:
new com/alipay/android/phone/mrpc/core/a
dup
aload 8
invokeinterface org/apache/http/HttpResponse/getStatusLine()Lorg/apache/http/StatusLine; 0
invokeinterface org/apache/http/StatusLine/getStatusCode()I 0
invokestatic java/lang/Integer/valueOf(I)Ljava/lang/Integer;
aload 8
invokeinterface org/apache/http/HttpResponse/getStatusLine()Lorg/apache/http/StatusLine; 0
invokeinterface org/apache/http/StatusLine/getReasonPhrase()Ljava/lang/String; 0
invokespecial com/alipay/android/phone/mrpc/core/a/<init>(Ljava/lang/Integer;Ljava/lang/String;)V
athrow
L5:
astore 7
aload 0
invokespecial com/alipay/android/phone/mrpc/core/x/e()V
aload 0
getfield com/alipay/android/phone/mrpc/core/x/c Lcom/alipay/android/phone/mrpc/core/v;
invokevirtual com/alipay/android/phone/mrpc/core/v/a()Lcom/alipay/android/phone/mrpc/core/g;
ifnull L71
aload 0
getfield com/alipay/android/phone/mrpc/core/x/c Lcom/alipay/android/phone/mrpc/core/v;
invokevirtual com/alipay/android/phone/mrpc/core/v/a()Lcom/alipay/android/phone/mrpc/core/g;
pop
aload 0
getfield com/alipay/android/phone/mrpc/core/x/c Lcom/alipay/android/phone/mrpc/core/v;
astore 8
new java/lang/StringBuilder
dup
invokespecial java/lang/StringBuilder/<init>()V
aload 7
invokevirtual java/lang/StringBuilder/append(Ljava/lang/Object;)Ljava/lang/StringBuilder;
pop
L71:
new java/lang/StringBuilder
dup
invokespecial java/lang/StringBuilder/<init>()V
aload 7
invokevirtual java/lang/StringBuilder/append(Ljava/lang/Object;)Ljava/lang/StringBuilder;
pop
new com/alipay/android/phone/mrpc/core/a
dup
iconst_2
invokestatic java/lang/Integer/valueOf(I)Ljava/lang/Integer;
aload 7
invokestatic java/lang/String/valueOf(Ljava/lang/Object;)Ljava/lang/String;
invokespecial com/alipay/android/phone/mrpc/core/a/<init>(Ljava/lang/Integer;Ljava/lang/String;)V
athrow
L69:
iconst_0
istore 1
goto L70
L50:
aload 0
aload 8
iload 2
aload 7
invokespecial com/alipay/android/phone/mrpc/core/x/a(Lorg/apache/http/HttpResponse;ILjava/lang/String;)Lcom/alipay/android/phone/mrpc/core/ab;
astore 7
L51:
ldc2_w -1L
lstore 5
lload 5
lstore 3
aload 7
ifnull L53
lload 5
lstore 3
L52:
aload 7
invokevirtual com/alipay/android/phone/mrpc/core/ab/a()[B
ifnull L53
aload 7
invokevirtual com/alipay/android/phone/mrpc/core/ab/a()[B
arraylength
i2l
lstore 3
L53:
lload 3
ldc2_w -1L
lcmp
ifne L56
L54:
aload 7
instanceof com/alipay/android/phone/mrpc/core/w
ifeq L56
aload 7
checkcast com/alipay/android/phone/mrpc/core/w
astore 8
L55:
aload 8
getfield com/alipay/android/phone/mrpc/core/w/d Lcom/alipay/android/phone/mrpc/core/b;
ldc "Content-Length"
invokevirtual com/alipay/android/phone/mrpc/core/b/a(Ljava/lang/String;)Ljava/lang/String;
invokestatic java/lang/Long/parseLong(Ljava/lang/String;)J
pop2
L56:
aload 0
getfield com/alipay/android/phone/mrpc/core/x/c Lcom/alipay/android/phone/mrpc/core/v;
getfield com/alipay/android/phone/mrpc/core/v/a Ljava/lang/String;
astore 8
L58:
aload 8
ifnull L60
L59:
aload 0
invokespecial com/alipay/android/phone/mrpc/core/x/f()Ljava/lang/String;
invokestatic android/text/TextUtils/isEmpty(Ljava/lang/CharSequence;)Z
ifne L60
new java/lang/StringBuilder
dup
invokespecial java/lang/StringBuilder/<init>()V
aload 8
invokevirtual java/lang/StringBuilder/append(Ljava/lang/String;)Ljava/lang/StringBuilder;
ldc "#"
invokevirtual java/lang/StringBuilder/append(Ljava/lang/String;)Ljava/lang/StringBuilder;
aload 0
invokespecial com/alipay/android/phone/mrpc/core/x/f()Ljava/lang/String;
invokevirtual java/lang/StringBuilder/append(Ljava/lang/String;)Ljava/lang/StringBuilder;
pop
L60:
aload 7
areturn
L6:
astore 7
aload 0
invokespecial com/alipay/android/phone/mrpc/core/x/e()V
aload 0
getfield com/alipay/android/phone/mrpc/core/x/c Lcom/alipay/android/phone/mrpc/core/v;
invokevirtual com/alipay/android/phone/mrpc/core/v/a()Lcom/alipay/android/phone/mrpc/core/g;
ifnull L72
aload 0
getfield com/alipay/android/phone/mrpc/core/x/c Lcom/alipay/android/phone/mrpc/core/v;
invokevirtual com/alipay/android/phone/mrpc/core/v/a()Lcom/alipay/android/phone/mrpc/core/g;
pop
aload 0
getfield com/alipay/android/phone/mrpc/core/x/c Lcom/alipay/android/phone/mrpc/core/v;
astore 8
new java/lang/StringBuilder
dup
invokespecial java/lang/StringBuilder/<init>()V
aload 7
invokevirtual java/lang/StringBuilder/append(Ljava/lang/Object;)Ljava/lang/StringBuilder;
pop
L72:
new java/lang/StringBuilder
dup
invokespecial java/lang/StringBuilder/<init>()V
aload 7
invokevirtual java/lang/StringBuilder/append(Ljava/lang/Object;)Ljava/lang/StringBuilder;
pop
new com/alipay/android/phone/mrpc/core/a
dup
bipush 6
invokestatic java/lang/Integer/valueOf(I)Ljava/lang/Integer;
aload 7
invokestatic java/lang/String/valueOf(Ljava/lang/Object;)Ljava/lang/String;
invokespecial com/alipay/android/phone/mrpc/core/a/<init>(Ljava/lang/Integer;Ljava/lang/String;)V
athrow
L7:
astore 7
aload 0
invokespecial com/alipay/android/phone/mrpc/core/x/e()V
aload 0
getfield com/alipay/android/phone/mrpc/core/x/c Lcom/alipay/android/phone/mrpc/core/v;
invokevirtual com/alipay/android/phone/mrpc/core/v/a()Lcom/alipay/android/phone/mrpc/core/g;
ifnull L73
aload 0
getfield com/alipay/android/phone/mrpc/core/x/c Lcom/alipay/android/phone/mrpc/core/v;
invokevirtual com/alipay/android/phone/mrpc/core/v/a()Lcom/alipay/android/phone/mrpc/core/g;
pop
aload 0
getfield com/alipay/android/phone/mrpc/core/x/c Lcom/alipay/android/phone/mrpc/core/v;
astore 8
new java/lang/StringBuilder
dup
invokespecial java/lang/StringBuilder/<init>()V
aload 7
invokevirtual java/lang/StringBuilder/append(Ljava/lang/Object;)Ljava/lang/StringBuilder;
pop
L73:
new java/lang/StringBuilder
dup
invokespecial java/lang/StringBuilder/<init>()V
aload 7
invokevirtual java/lang/StringBuilder/append(Ljava/lang/Object;)Ljava/lang/StringBuilder;
pop
new com/alipay/android/phone/mrpc/core/a
dup
iconst_3
invokestatic java/lang/Integer/valueOf(I)Ljava/lang/Integer;
aload 7
invokestatic java/lang/String/valueOf(Ljava/lang/Object;)Ljava/lang/String;
invokespecial com/alipay/android/phone/mrpc/core/a/<init>(Ljava/lang/Integer;Ljava/lang/String;)V
athrow
L8:
astore 7
aload 0
invokespecial com/alipay/android/phone/mrpc/core/x/e()V
aload 0
getfield com/alipay/android/phone/mrpc/core/x/c Lcom/alipay/android/phone/mrpc/core/v;
invokevirtual com/alipay/android/phone/mrpc/core/v/a()Lcom/alipay/android/phone/mrpc/core/g;
ifnull L74
aload 0
getfield com/alipay/android/phone/mrpc/core/x/c Lcom/alipay/android/phone/mrpc/core/v;
invokevirtual com/alipay/android/phone/mrpc/core/v/a()Lcom/alipay/android/phone/mrpc/core/g;
pop
aload 0
getfield com/alipay/android/phone/mrpc/core/x/c Lcom/alipay/android/phone/mrpc/core/v;
astore 8
new java/lang/StringBuilder
dup
invokespecial java/lang/StringBuilder/<init>()V
aload 7
invokevirtual java/lang/StringBuilder/append(Ljava/lang/Object;)Ljava/lang/StringBuilder;
pop
L74:
new java/lang/StringBuilder
dup
invokespecial java/lang/StringBuilder/<init>()V
aload 7
invokevirtual java/lang/StringBuilder/append(Ljava/lang/Object;)Ljava/lang/StringBuilder;
pop
new com/alipay/android/phone/mrpc/core/a
dup
iconst_3
invokestatic java/lang/Integer/valueOf(I)Ljava/lang/Integer;
aload 7
invokestatic java/lang/String/valueOf(Ljava/lang/Object;)Ljava/lang/String;
invokespecial com/alipay/android/phone/mrpc/core/a/<init>(Ljava/lang/Integer;Ljava/lang/String;)V
athrow
L9:
astore 7
aload 0
invokespecial com/alipay/android/phone/mrpc/core/x/e()V
aload 0
getfield com/alipay/android/phone/mrpc/core/x/c Lcom/alipay/android/phone/mrpc/core/v;
invokevirtual com/alipay/android/phone/mrpc/core/v/a()Lcom/alipay/android/phone/mrpc/core/g;
ifnull L75
aload 0
getfield com/alipay/android/phone/mrpc/core/x/c Lcom/alipay/android/phone/mrpc/core/v;
invokevirtual com/alipay/android/phone/mrpc/core/v/a()Lcom/alipay/android/phone/mrpc/core/g;
pop
aload 0
getfield com/alipay/android/phone/mrpc/core/x/c Lcom/alipay/android/phone/mrpc/core/v;
astore 8
new java/lang/StringBuilder
dup
invokespecial java/lang/StringBuilder/<init>()V
aload 7
invokevirtual java/lang/StringBuilder/append(Ljava/lang/Object;)Ljava/lang/StringBuilder;
pop
L75:
new java/lang/StringBuilder
dup
invokespecial java/lang/StringBuilder/<init>()V
aload 7
invokevirtual java/lang/StringBuilder/append(Ljava/lang/Object;)Ljava/lang/StringBuilder;
pop
new com/alipay/android/phone/mrpc/core/a
dup
iconst_4
invokestatic java/lang/Integer/valueOf(I)Ljava/lang/Integer;
aload 7
invokestatic java/lang/String/valueOf(Ljava/lang/Object;)Ljava/lang/String;
invokespecial com/alipay/android/phone/mrpc/core/a/<init>(Ljava/lang/Integer;Ljava/lang/String;)V
athrow
L10:
astore 7
aload 0
invokespecial com/alipay/android/phone/mrpc/core/x/e()V
aload 0
getfield com/alipay/android/phone/mrpc/core/x/c Lcom/alipay/android/phone/mrpc/core/v;
invokevirtual com/alipay/android/phone/mrpc/core/v/a()Lcom/alipay/android/phone/mrpc/core/g;
ifnull L76
aload 0
getfield com/alipay/android/phone/mrpc/core/x/c Lcom/alipay/android/phone/mrpc/core/v;
invokevirtual com/alipay/android/phone/mrpc/core/v/a()Lcom/alipay/android/phone/mrpc/core/g;
pop
aload 0
getfield com/alipay/android/phone/mrpc/core/x/c Lcom/alipay/android/phone/mrpc/core/v;
astore 8
new java/lang/StringBuilder
dup
invokespecial java/lang/StringBuilder/<init>()V
aload 7
invokevirtual java/lang/StringBuilder/append(Ljava/lang/Object;)Ljava/lang/StringBuilder;
pop
L76:
new java/lang/StringBuilder
dup
invokespecial java/lang/StringBuilder/<init>()V
aload 7
invokevirtual java/lang/StringBuilder/append(Ljava/lang/Object;)Ljava/lang/StringBuilder;
pop
new com/alipay/android/phone/mrpc/core/a
dup
iconst_5
invokestatic java/lang/Integer/valueOf(I)Ljava/lang/Integer;
aload 7
invokestatic java/lang/String/valueOf(Ljava/lang/Object;)Ljava/lang/String;
invokespecial com/alipay/android/phone/mrpc/core/a/<init>(Ljava/lang/Integer;Ljava/lang/String;)V
athrow
L11:
astore 7
aload 0
invokespecial com/alipay/android/phone/mrpc/core/x/e()V
aload 0
getfield com/alipay/android/phone/mrpc/core/x/c Lcom/alipay/android/phone/mrpc/core/v;
invokevirtual com/alipay/android/phone/mrpc/core/v/a()Lcom/alipay/android/phone/mrpc/core/g;
ifnull L77
aload 0
getfield com/alipay/android/phone/mrpc/core/x/c Lcom/alipay/android/phone/mrpc/core/v;
invokevirtual com/alipay/android/phone/mrpc/core/v/a()Lcom/alipay/android/phone/mrpc/core/g;
pop
aload 0
getfield com/alipay/android/phone/mrpc/core/x/c Lcom/alipay/android/phone/mrpc/core/v;
astore 8
new java/lang/StringBuilder
dup
invokespecial java/lang/StringBuilder/<init>()V
aload 7
invokevirtual java/lang/StringBuilder/append(Ljava/lang/Object;)Ljava/lang/StringBuilder;
pop
L77:
new com/alipay/android/phone/mrpc/core/a
dup
bipush 8
invokestatic java/lang/Integer/valueOf(I)Ljava/lang/Integer;
aload 7
invokestatic java/lang/String/valueOf(Ljava/lang/Object;)Ljava/lang/String;
invokespecial com/alipay/android/phone/mrpc/core/a/<init>(Ljava/lang/Integer;Ljava/lang/String;)V
athrow
L12:
astore 7
aload 0
invokespecial com/alipay/android/phone/mrpc/core/x/e()V
aload 0
getfield com/alipay/android/phone/mrpc/core/x/c Lcom/alipay/android/phone/mrpc/core/v;
invokevirtual com/alipay/android/phone/mrpc/core/v/a()Lcom/alipay/android/phone/mrpc/core/g;
ifnull L78
aload 0
getfield com/alipay/android/phone/mrpc/core/x/c Lcom/alipay/android/phone/mrpc/core/v;
invokevirtual com/alipay/android/phone/mrpc/core/v/a()Lcom/alipay/android/phone/mrpc/core/g;
pop
aload 0
getfield com/alipay/android/phone/mrpc/core/x/c Lcom/alipay/android/phone/mrpc/core/v;
astore 8
new java/lang/StringBuilder
dup
invokespecial java/lang/StringBuilder/<init>()V
aload 7
invokevirtual java/lang/StringBuilder/append(Ljava/lang/Object;)Ljava/lang/StringBuilder;
pop
L78:
new java/lang/StringBuilder
dup
invokespecial java/lang/StringBuilder/<init>()V
aload 7
invokevirtual java/lang/StringBuilder/append(Ljava/lang/Object;)Ljava/lang/StringBuilder;
pop
new com/alipay/android/phone/mrpc/core/a
dup
bipush 9
invokestatic java/lang/Integer/valueOf(I)Ljava/lang/Integer;
aload 7
invokestatic java/lang/String/valueOf(Ljava/lang/Object;)Ljava/lang/String;
invokespecial com/alipay/android/phone/mrpc/core/a/<init>(Ljava/lang/Integer;Ljava/lang/String;)V
athrow
L13:
astore 7
aload 0
invokespecial com/alipay/android/phone/mrpc/core/x/e()V
aload 0
getfield com/alipay/android/phone/mrpc/core/x/c Lcom/alipay/android/phone/mrpc/core/v;
invokevirtual com/alipay/android/phone/mrpc/core/v/a()Lcom/alipay/android/phone/mrpc/core/g;
ifnull L79
aload 0
getfield com/alipay/android/phone/mrpc/core/x/c Lcom/alipay/android/phone/mrpc/core/v;
invokevirtual com/alipay/android/phone/mrpc/core/v/a()Lcom/alipay/android/phone/mrpc/core/g;
pop
aload 0
getfield com/alipay/android/phone/mrpc/core/x/c Lcom/alipay/android/phone/mrpc/core/v;
astore 8
new java/lang/StringBuilder
dup
invokespecial java/lang/StringBuilder/<init>()V
aload 7
invokevirtual java/lang/StringBuilder/append(Ljava/lang/Object;)Ljava/lang/StringBuilder;
pop
L79:
new java/lang/StringBuilder
dup
invokespecial java/lang/StringBuilder/<init>()V
aload 7
invokevirtual java/lang/StringBuilder/append(Ljava/lang/Object;)Ljava/lang/StringBuilder;
pop
new com/alipay/android/phone/mrpc/core/a
dup
bipush 6
invokestatic java/lang/Integer/valueOf(I)Ljava/lang/Integer;
aload 7
invokestatic java/lang/String/valueOf(Ljava/lang/Object;)Ljava/lang/String;
invokespecial com/alipay/android/phone/mrpc/core/a/<init>(Ljava/lang/Integer;Ljava/lang/String;)V
athrow
L14:
astore 7
aload 0
invokespecial com/alipay/android/phone/mrpc/core/x/e()V
aload 0
getfield com/alipay/android/phone/mrpc/core/x/m I
ifgt L80
aload 0
aload 0
getfield com/alipay/android/phone/mrpc/core/x/m I
iconst_1
iadd
putfield com/alipay/android/phone/mrpc/core/x/m I
goto L0
L80:
new java/lang/StringBuilder
dup
invokespecial java/lang/StringBuilder/<init>()V
aload 7
invokevirtual java/lang/StringBuilder/append(Ljava/lang/Object;)Ljava/lang/StringBuilder;
pop
new com/alipay/android/phone/mrpc/core/a
dup
iconst_0
invokestatic java/lang/Integer/valueOf(I)Ljava/lang/Integer;
aload 7
invokestatic java/lang/String/valueOf(Ljava/lang/Object;)Ljava/lang/String;
invokespecial com/alipay/android/phone/mrpc/core/a/<init>(Ljava/lang/Integer;Ljava/lang/String;)V
athrow
L15:
astore 7
aload 0
invokespecial com/alipay/android/phone/mrpc/core/x/e()V
aload 0
getfield com/alipay/android/phone/mrpc/core/x/c Lcom/alipay/android/phone/mrpc/core/v;
invokevirtual com/alipay/android/phone/mrpc/core/v/a()Lcom/alipay/android/phone/mrpc/core/g;
ifnull L81
aload 0
getfield com/alipay/android/phone/mrpc/core/x/c Lcom/alipay/android/phone/mrpc/core/v;
invokevirtual com/alipay/android/phone/mrpc/core/v/a()Lcom/alipay/android/phone/mrpc/core/g;
pop
aload 0
getfield com/alipay/android/phone/mrpc/core/x/c Lcom/alipay/android/phone/mrpc/core/v;
astore 8
new java/lang/StringBuilder
dup
invokespecial java/lang/StringBuilder/<init>()V
aload 7
invokevirtual java/lang/StringBuilder/append(Ljava/lang/Object;)Ljava/lang/StringBuilder;
pop
L81:
new com/alipay/android/phone/mrpc/core/a
dup
iconst_0
invokestatic java/lang/Integer/valueOf(I)Ljava/lang/Integer;
aload 7
invokestatic java/lang/String/valueOf(Ljava/lang/Object;)Ljava/lang/String;
invokespecial com/alipay/android/phone/mrpc/core/a/<init>(Ljava/lang/Integer;Ljava/lang/String;)V
athrow
L57:
astore 8
goto L56
L66:
aconst_null
astore 7
goto L32
L64:
iconst_0
istore 1
goto L61
L65:
iload 1
iconst_1
iadd
istore 1
goto L63
L67:
ldc ""
astore 7
goto L43
.limit locals 11
.limit stack 6
.end method

.method private e()V
aload 0
getfield com/alipay/android/phone/mrpc/core/x/f Lorg/apache/http/client/methods/HttpUriRequest;
ifnull L0
aload 0
getfield com/alipay/android/phone/mrpc/core/x/f Lorg/apache/http/client/methods/HttpUriRequest;
invokeinterface org/apache/http/client/methods/HttpUriRequest/abort()V 0
L0:
return
.limit locals 1
.limit stack 1
.end method

.method private f()Ljava/lang/String;
aload 0
getfield com/alipay/android/phone/mrpc/core/x/q Ljava/lang/String;
invokestatic android/text/TextUtils/isEmpty(Ljava/lang/CharSequence;)Z
ifne L0
aload 0
getfield com/alipay/android/phone/mrpc/core/x/q Ljava/lang/String;
areturn
L0:
aload 0
aload 0
getfield com/alipay/android/phone/mrpc/core/x/c Lcom/alipay/android/phone/mrpc/core/v;
ldc "operationType"
invokevirtual com/alipay/android/phone/mrpc/core/v/a(Ljava/lang/String;)Ljava/lang/String;
putfield com/alipay/android/phone/mrpc/core/x/q Ljava/lang/String;
aload 0
getfield com/alipay/android/phone/mrpc/core/x/q Ljava/lang/String;
areturn
.limit locals 1
.limit stack 3
.end method

.method private g()I
aload 0
invokespecial com/alipay/android/phone/mrpc/core/x/h()Ljava/net/URL;
astore 1
aload 1
invokevirtual java/net/URL/getPort()I
iconst_m1
if_icmpne L0
aload 1
invokevirtual java/net/URL/getDefaultPort()I
ireturn
L0:
aload 1
invokevirtual java/net/URL/getPort()I
ireturn
.limit locals 2
.limit stack 2
.end method

.method private h()Ljava/net/URL;
aload 0
getfield com/alipay/android/phone/mrpc/core/x/l Ljava/net/URL;
ifnull L0
aload 0
getfield com/alipay/android/phone/mrpc/core/x/l Ljava/net/URL;
areturn
L0:
aload 0
new java/net/URL
dup
aload 0
getfield com/alipay/android/phone/mrpc/core/x/c Lcom/alipay/android/phone/mrpc/core/v;
getfield com/alipay/android/phone/mrpc/core/v/a Ljava/lang/String;
invokespecial java/net/URL/<init>(Ljava/lang/String;)V
putfield com/alipay/android/phone/mrpc/core/x/l Ljava/net/URL;
aload 0
getfield com/alipay/android/phone/mrpc/core/x/l Ljava/net/URL;
areturn
.limit locals 1
.limit stack 4
.end method

.method private i()Landroid/webkit/CookieManager;
aload 0
getfield com/alipay/android/phone/mrpc/core/x/i Landroid/webkit/CookieManager;
ifnull L0
aload 0
getfield com/alipay/android/phone/mrpc/core/x/i Landroid/webkit/CookieManager;
areturn
L0:
aload 0
invokestatic android/webkit/CookieManager/getInstance()Landroid/webkit/CookieManager;
putfield com/alipay/android/phone/mrpc/core/x/i Landroid/webkit/CookieManager;
aload 0
getfield com/alipay/android/phone/mrpc/core/x/i Landroid/webkit/CookieManager;
areturn
.limit locals 1
.limit stack 2
.end method

.method public final a()Lcom/alipay/android/phone/mrpc/core/v;
aload 0
getfield com/alipay/android/phone/mrpc/core/x/c Lcom/alipay/android/phone/mrpc/core/v;
areturn
.limit locals 1
.limit stack 1
.end method

.method public final synthetic call()Ljava/lang/Object;
aload 0
invokespecial com/alipay/android/phone/mrpc/core/x/d()Lcom/alipay/android/phone/mrpc/core/ab;
areturn
.limit locals 1
.limit stack 1
.end method
